Workbook

Sheet Assumptions
A1: Series F Analysis — Assumptions
A2: Knob | B2: Value | C2: Notes
A3: series_f_pre_money_usd | B3: 1400000000 | C3: Series F pre-money valuation
A4: series_f_primary_raise_usd | B4: 30000000 | C4: New Series F primary capital
A5: series_f_secondary_raise_usd | B5: 15000000 | C5: Secondary tender from founders
A6: series_f_tender_pps_multiplier | B6: 0.85 | C6: Tender PPS = mult x F_PPS
A7: esop_refresh_target_post_f | B7: 0.13 | C7: Post-F ESOP as fraction of post-F FD
A8: our_fund_check_usd | B8: 10000000 | C8: Our fund check (1/3 of primary)
A9: f_lead_primary_check_usd | B9: 20000000 | C9: F_LEAD primary check (2/3 of primary)
A10: option_strike_usd | B10: 1 | C10: Strike for issued options
A11: exit_value_1_usd | B11: 700000000 | C11: Exit 1
A12: exit_value_2_usd | B12: 1200000000 | C12: Exit 2
A13: exit_value_3_usd | B13: 2000000000 | C13: Exit 3 (sensitivity)
A14: exit_value_4_usd | B14: 4000000000 | C14: Exit 4
... A57: return_multiple_4x | B57: 4 | C57: Return target 4x

Sheet Solver
A1: Solver — Round Fixed-Point Iteration Ladder
A3: Step | B3: F_PPS | C3: D_NCP | D3: E_NCP | E3: ΔD | F3: ΔE | G3: ESOP | H3: N_A | I3: N_B | J3: pre_money_FD | K3: T_F_post | L3: F_PPS check
A4: Base seed | B4: =Assumptions!$B$3/Assumptions!$B$29 | C4: =Assumptions!$B$20 | D4: =Assumptions!$B$21 | E4: 0 | F4: 0 | G4: 0 | H4: 0 | I4: 0 | J4: =Assumptions!$B$29 | K4: =J4+Assumptions!$B$4/B4 | L4: =B4
A5: Base iter 1 | B5: =Assumptions!$B$3/J4 | C5: =IF(B5<Assumptions!$B$20,Assumptions!$B$20*(Assumptions!$B$29+Assumptions!$B$4/Assumptions!$B$20)/(Assumptions!$B$29+Assumptions!$B$4/B5),Assumptions!$B$20) | D5: =IF(B5<Assumptions!$B$21,Assumptions!$B$21*(Assumptions!$B$29+Assumptions!$B$4/Assumptions!$B$21)/(Assumptions!$B$29+Assumptions!$B$4/B5),Assumptions!$B$21) | E5: =Assumptions!$B$37*Assumptions!$B$22/C5-Assumptions!$B$38 | F5: =Assumptions!$B$39*Assumptions!$B$21/D5-Assumptions!$B$39 | G5: =MAX(0,Assumptions!$B$7*(Assumptions!$B$29+E5+F5+G4+H4+I4+Assumptions!$B$4/B5)-Assumptions!$B$30) | H5: =Assumptions!$B$23/MIN(Assumptions!$B$24/(Assumptions!$B$29+E5+F5+G5+I4),B5*(1-Assumptions!$B$25)) | I5: =Assumptions!$B$26/MIN(Assumptions!$B$27/(Assumptions!$B$29+E5+F5+G5+H5),B5*(1-Assumptions!$B$28)) | J5: =Assumptions!$B$29+E5+F5+G5+H5+I5 | K5: =J5+Assumptions!$B$4/B5 | L5: =B5
A6: Base iter 2 | B6: =Assumptions!$B$3/J5 | C6: =IF(B6<Assumptions!$B$20,Assumptions!$B$20*(Assumptions!$B$29+Assumptions!$B$4/Assumptions!$B$20)/(Assumptions!$B$29+Assumptions!$B$4/B6),Assumptions!$B$20) | D6: =IF(B6<Assumptions!$B$21,Assumptions!$B$21*(Assumptions!$B$29+Assumptions!$B$4/Assumptions!$B$21)/(Assumptions!$B$29+Assumptions!$B$4/B6),Assumptions!$B$21) | E6: =Assumptions!$B$37*Assumptions!$B$22/C6-Assumptions!$B$38 | F6: =Assumptions!$B$39*Assumptions!$B$21/D6-Assumptions!$B$39 | G6: =MAX(0,Assumptions!$B$7*(Assumptions!$B$29+E6+F6+G5+H5+I5+Assumptions!$B$4/B6)-Assumptions!$B$30) | H6: =Assumptions!$B$23/MIN(Assumptions!$B$24/(Assumptions!$B$29+E6+F6+G6+I5),B6*(1-Assumptions!$B$25)) | I6: =Assumptions!$B$26/MIN(Assumptions!$B$27/(Assumptions!$B$29+E6+F6+G6+H6),B6*(1-Assumptions!$B$28)) | J6: =Assumptions!$B$29+E6+F6+G6+H6+I6 | K6: =J6+Assumptions!$B$4/B6 | L6: =B6
A7: Base iter 3 | B7: =Assumptions!$B$3/J6 | C7: =IF(B7<Assumptions!$B$20,Assumptions!$B$20*(Assumptions!$B$29+Assumptions!$B$4/Assumptions!$B$20)/(Assumptions!$B$29+Assumptions!$B$4/B7),Assumptions!$B$20) | D7: =IF(B7<Assumptions!$B$21,Assumptions!$B$21*(Assumptions!$B$29+Assumptions!$B$4/Assumptions!$B$21)/(Assumptions!$B$29+Assumptions!$B$4/B7),Assumptions!$B$21) | E7: =Assumptions!$B$37*Assumptions!$B$22/C7-Assumptions!$B$38 | F7: =Assumptions!$B$39*Assumptions!$B$21/D7-Assumptions!$B$39 | G7: =MAX(0,Assumptions!$B$7*(Assumptions!$B$29+E7+F7+G6+H6+I6+Assumptions!$B$4/B7)-Assumptions!$B$30) | H7: =Assumptions!$B$23/MIN(Assumptions!$B$24/(Assumptions!$B$29+E7+F7+G7+I6),B7*(1-Assumptions!$B$25)) | I7: =Assumptions!$B$26/MIN(Assumptions!$B$27/(Assumptions!$B$29+E7+F7+G7+H7),B7*(1-Assumptions!$B$28)) | J7: =Assumptions!$B$29+E7+F7+G7+H7+I7 | K7: =J7+Assumptions!$B$4/B7 | L7: =B7
A8: Base iter 4 | B8: =Assumptions!$B$3/J7 | C8: =IF(B8<Assumptions!$B$20,Assumptions!$B$20*(Assumptions!$B$29+Assumptions!$B$4/Assumptions!$B$20)/(Assumptions!$B$29+Assumptions!$B$4/B8),Assumptions!$B$20) | D8: =IF(B8<Assumptions!$B$21,Assumptions!$B$21*(Assumptions!$B$29+Assumptions!$B$4/Assumptions!$B$21)/(Assumptions!$B$29+Assumptions!$B$4/B8),Assumptions!$B$21) | E8: =Assumptions!$B$37*Assumptions!$B$22/C8-Assumptions!$B$38 | F8: =Assumptions!$B$39*Assumptions!$B$21/D8-Assumptions!$B$39 | G8: =MAX(0,Assumptions!$B$7*(Assumptions!$B$29+E8+F8+G7+H7+I7+Assumptions!$B$4/B8)-Assumptions!$B$30) | H8: =Assumptions!$B$23/MIN(Assumptions!$B$24/(Assumptions!$B$29+E8+F8+G8+I7),B8*(1-Assumptions!$B$25)) | I8: =Assumptions!$B$26/MIN(Assumptions!$B$27/(Assumptions!$B$29+E8+F8+G8+H8),B8*(1-Assumptions!$B$28)) | J8: =Assumptions!$B$29+E8+F8+G8+H8+I8 | K8: =J8+Assumptions!$B$4/B8 | L8: =B8
A9: Base iter 5 | B9: =Assumptions!$B$3/J8 | C9: =IF(B9<Assumptions!$B$20,Assumptions!$B$20*(Assumptions!$B$29+Assumptions!$B$4/Assumptions!$B$20)/(Assumptions!$B$29+Assumptions!$B$4/B9),Assumptions!$B$20) | D9: =IF(B9<Assumptions!$B$21,Assumptions!$B$21*(Assumptions!$B$29+Assumptions!$B$4/Assumptions!$B$21)/(Assumptions!$B$29+Assumptions!$B$4/B9),Assumptions!$B$21) | E9: =Assumptions!$B$37*Assumptions!$B$22/C9-Assumptions!$B$38 | F9: =Assumptions!$B$39*Assumptions!$B$21/D9-Assumptions!$B$39 | G9: =MAX(0,Assumptions!$B$7*(Assumptions!$B$29+E9+F9+G8+H8+I8+Assumptions!$B$4/B9)-Assumptions!$B$30) | H9: =Assumptions!$B$23/MIN(Assumptions!$B$24/(Assumptions!$B$29+E9+F9+G9+I8),B9*(1-Assumptions!$B$25)) | I9: =Assumptions!$B$26/MIN(Assumptions!$B$27/(Assumptions!$B$29+E9+F9+G9+H9),B9*(1-Assumptions!$B$28)) | J9: =Assumptions!$B$29+E9+F9+G9+H9+I9 | K9: =J9+Assumptions!$B$4/B9 | L9: =B9
A10: Base iter 6 | B10: =Assumptions!$B$3/J9 | C10: =IF(B10<Assumptions!$B$20,Assumptions!$B$20*(Assumptions!$B$29+Assumptions!$B$4/Assumptions!$B$20)/(Assumptions!$B$29+Assumptions!$B$4/B10),Assumptions!$B$20) | D10: =IF(B10<Assumptions!$B$21,Assumptions!$B$21*(Assumptions!$B$29+Assumptions!$B$4/Assumptions!$B$21)/(Assumptions!$B$29+Assumptions!$B$4/B10),Assumptions!$B$21) | E10: =Assumptions!$B$37*Assumptions!$B$22/C10-Assumptions!$B$38 | F10: =Assumptions!$B$39*Assumptions!$B$21/D10-Assumptions!$B$39 | G10: =MAX(0,Assumptions!$B$7*(Assumptions!$B$29+E10+F10+G9+H9+I9+Assumptions!$B$4/B10)-Assumptions!$B$30) | H10: =Assumptions!$B$23/MIN(Assumptions!$B$24/(Assumptions!$B$29+E10+F10+G10+I9),B10*(1-Assumptions!$B$25)) | I10: =Assumptions!$B$26/MIN(Assumptions!$B$27/(Assumptions!$B$29+E10+F10+G10+H10),B10*(1-Assumptions!$B$28)) | J10: =Assumptions!$B$29+E10+F10+G10+H10+I10 | K10: =J10+Assumptions!$B$4/B10 | L10: =B10
A11: Base iter 7 | B11: =Assumptions!$B$3/J10 | C11: =IF(B11<Assumptions!$B$20,Assumptions!$B$20*(Assumptions!$B$29+Assumptions!$B$4/Assumptions!$B$20)/(Assumptions!$B$29+Assumptions!$B$4/B11),Assumptions!$B$20) | D11: =IF(B11<Assumptions!$B$21,Assumptions!$B$21*(Assumptions!$B$29+Assumptions!$B$4/Assumptions!$B$21)/(Assumptions!$B$29+Assumptions!$B$4/B11),Assumptions!$B$21) | E11: =Assumptions!$B$37*Assumptions!$B$22/C11-Assumptions!$B$38 | F11: =Assumptions!$B$39*Assumptions!$B$21/D11-Assumptions!$B$39 | G11: =MAX(0,Assumptions!$B$7*(Assumptions!$B$29+E11+F11+G10+H10+I10+Assumptions!$B$4/B11)-Assumptions!$B$30) | H11: =Assumptions!$B$23/MIN(Assumptions!$B$24/(Assumptions!$B$29+E11+F11+G11+I10),B11*(1-Assumptions!$B$25)) | I11: =Assumptions!$B$26/MIN(Assumptions!$B$27/(Assumptions!$B$29+E11+F11+G11+H11),B11*(1-Assumptions!$B$28)) | J11: =Assumptions!$B$29+E11+F11+G11+H11+I11 | K11: =J11+Assumptions!$B$4/B11 | L11: =B11
A12: Base iter 8 | B12: =Assumptions!$B$3/J11 | C12: =IF(B12<Assumptions!$B$20,Assumptions!$B$20*(Assumptions!$B$29+Assumptions!$B$4/Assumptions!$B$20)/(Assumptions!$B$29+Assumptions!$B$4/B12),Assumptions!$B$20) | D12: =IF(B12<Assumptions!$B$21,Assumptions!$B$21*(Assumptions!$B$29+Assumptions!$B$4/Assumptions!$B$21)/(Assumptions!$B$29+Assumptions!$B$4/B12),Assumptions!$B$21) | E12: =Assumptions!$B$37*Assumptions!$B$22/C12-Assumptions!$B$38 | F12: =Assumptions!$B$39*Assumptions!$B$21/D12-Assumptions!$B$39 | G12: =MAX(0,Assumptions!$B$7*(Assumptions!$B$29+E12+F12+G11+H11+I11+Assumptions!$B$4/B12)-Assumptions!$B$30) | H12: =Assumptions!$B$23/MIN(Assumptions!$B$24/(Assumptions!$B$29+E12+F12+G12+I11),B12*(1-Assumptions!$B$25)) | I12: =Assumptions!$B$26/MIN(Assumptions!$B$27/(Assumptions!$B$29+E12+F12+G12+H12),B12*(1-Assumptions!$B$28)) | J12: =Assumptions!$B$29+E12+F12+G12+H12+I12 | K12: =J12+Assumptions!$B$4/B12 | L12: =B12
A13: Base iter 9 | B13: =Assumptions!$B$3/J12 | C13: =IF(B13<Assumptions!$B$20,Assumptions!$B$20*(Assumptions!$B$29+Assumptions!$B$4/Assumptions!$B$20)/(Assumptions!$B$29+Assumptions!$B$4/B13),Assumptions!$B$20) | D13: =IF(B13<Assumptions!$B$21,Assumptions!$B$21*(Assumptions!$B$29+Assumptions!$B$4/Assumptions!$B$21)/(Assumptions!$B$29+Assumptions!$B$4/B13),Assumptions!$B$21) | E13: =Assumptions!$B$37*Assumptions!$B$22/C13-Assumptions!$B$38 | F13: =Assumptions!$B$39*Assumptions!$B$21/D13-Assumptions!$B$39 | G13: =MAX(0,Assumptions!$B$7*(Assumptions!$B$29+E13+F13+G12+H12+I12+Assumptions!$B$4/B13)-Assumptions!$B$30) | H13: =Assumptions!$B$23/MIN(Assumptions!$B$24/(Assumptions!$B$29+E13+F13+G13+I12),B13*(1-Assumptions!$B$25)) | I13: =Assumptions!$B$26/MIN(Assumptions!$B$27/(Assumptions!$B$29+E13+F13+G13+H13),B13*(1-Assumptions!$B$28)) | J13: =Assumptions!$B$29+E13+F13+G13+H13+I13 | K13: =J13+Assumptions!$B$4/B13 | L13: =B13
A14: Base iter 10 | B14: =Assumptions!$B$3/J13 | C14: =IF(B14<Assumptions!$B$20,Assumptions!$B$20*(Assumptions!$B$29+Assumptions!$B$4/Assumptions!$B$20)/(Assumptions!$B$29+Assumptions!$B$4/B14),Assumptions!$B$20) | D14: =IF(B14<Assumptions!$B$21,Assumptions!$B$21*(Assumptions!$B$29+Assumptions!$B$4/Assumptions!$B$21)/(Assumptions!$B$29+Assumptions!$B$4/B14),Assumptions!$B$21) | E14: =Assumptions!$B$37*Assumptions!$B$22/C14-Assumptions!$B$38 | F14: =Assumptions!$B$39*Assumptions!$B$21/D14-Assumptions!$B$39 | G14: =MAX(0,Assumptions!$B$7*(Assumptions!$B$29+E14+F14+G13+H13+I13+Assumptions!$B$4/B14)-Assumptions!$B$30) | H14: =Assumptions!$B$23/MIN(Assumptions!$B$24/(Assumptions!$B$29+E14+F14+G14+I13),B14*(1-Assumptions!$B$25)) | I14: =Assumptions!$B$26/MIN(Assumptions!$B$27/(Assumptions!$B$29+E14+F14+G14+H14),B14*(1-Assumptions!$B$28)) | J14: =Assumptions!$B$29+E14+F14+G14+H14+I14 | K14: =J14+Assumptions!$B$4/B14 | L14: =B14
A15: Base iter 11 | B15: =Assumptions!$B$3/J14 | C15: =IF(B15<Assumptions!$B$20,Assumptions!$B$20*(Assumptions!$B$29+Assumptions!$B$4/Assumptions!$B$20)/(Assumptions!$B$29+Assumptions!$B$4/B15),Assumptions!$B$20) | D15: =IF(B15<Assumptions!$B$21,Assumptions!$B$21*(Assumptions!$B$29+Assumptions!$B$4/Assumptions!$B$21)/(Assumptions!$B$29+Assumptions!$B$4/B15),Assumptions!$B$21) | E15: =Assumptions!$B$37*Assumptions!$B$22/C15-Assumptions!$B$38 | F15: =Assumptions!$B$39*Assumptions!$B$21/D15-Assumptions!$B$39 | G15: =MAX(0,Assumptions!$B$7*(Assumptions!$B$29+E15+F15+G14+H14+I14+Assumptions!$B$4/B15)-Assumptions!$B$30) | H15: =Assumptions!$B$23/MIN(Assumptions!$B$24/(Assumptions!$B$29+E15+F15+G15+I14),B15*(1-Assumptions!$B$25)) | I15: =Assumptions!$B$26/MIN(Assumptions!$B$27/(Assumptions!$B$29+E15+F15+G15+H15),B15*(1-Assumptions!$B$28)) | J15: =Assumptions!$B$29+E15+F15+G15+H15+I15 | K15: =J15+Assumptions!$B$4/B15 | L15: =B15
A16: Base iter 12 | B16: =Assumptions!$B$3/J15 | C16: =IF(B16<Assumptions!$B$20,Assumptions!$B$20*(Assumptions!$B$29+Assumptions!$B$4/Assumptions!$B$20)/(Assumptions!$B$29+Assumptions!$B$4/B16),Assumptions!$B$20) | D16: =IF(B16<Assumptions!$B$21,Assumptions!$B$21*(Assumptions!$B$29+Assumptions!$B$4/Assumptions!$B$21)/(Assumptions!$B$29+Assumptions!$B$4/B16),Assumptions!$B$21) | E16: =Assumptions!$B$37*Assumptions!$B$22/C16-Assumptions!$B$38 | F16: =Assumptions!$B$39*Assumptions!$B$21/D16-Assumptions!$B$39 | G16: =MAX(0,Assumptions!$B$7*(Assumptions!$B$29+E16+F16+G15+H15+I15+Assumptions!$B$4/B16)-Assumptions!$B$30) | H16: =Assumptions!$B$23/MIN(Assumptions!$B$24/(Assumptions!$B$29+E16+F16+G16+I15),B16*(1-Assumptions!$B$25)) | I16: =Assumptions!$B$26/MIN(Assumptions!$B$27/(Assumptions!$B$29+E16+F16+G16+H16),B16*(1-Assumptions!$B$28)) | J16: =Assumptions!$B$29+E16+F16+G16+H16+I16 | K16: =J16+Assumptions!$B$4/B16 | L16: =B16
... A84: Base iter 80 | B84: =Assumptions!$B$3/J83 | C84: =IF(B84<Assumptions!$B$20,Assumptions!$B$20*(Assumptions!$B$29+Assumptions!$B$4/Assumptions!$B$20)/(Assumptions!$B$29+Assumptions!$B$4/B84),Assumptions!$B$20) | D84: =IF(B84<Assumptions!$B$21,Assumptions!$B$21*(Assumptions!$B$29+Assumptions!$B$4/Assumptions!$B$21)/(Assumptions!$B$29+Assumptions!$B$4/B84),Assumptions!$B$21) | E84: =Assumptions!$B$37*Assumptions!$B$22/C84-Assumptions!$B$38 | F84: =Assumptions!$B$39*Assumptions!$B$21/D84-Assumptions!$B$39 | G84: =MAX(0,Assumptions!$B$7*(Assumptions!$B$29+E84+F84+G83+H83+I83+Assumptions!$B$4/B84)-Assumptions!$B$30) | H84: =Assumptions!$B$23/MIN(Assumptions!$B$24/(Assumptions!$B$29+E84+F84+G84+I83),B84*(1-Assumptions!$B$25)) | I84: =Assumptions!$B$26/MIN(Assumptions!$B$27/(Assumptions!$B$29+E84+F84+G84+H84),B84*(1-Assumptions!$B$28)) | J84: =Assumptions!$B$29+E84+F84+G84+H84+I84 | K84: =J84+Assumptions!$B$4/B84 | L84: =B84

Sheet Pro-Forma
A1: Pro-Forma Post-F Cap Table
A3: Round Mechanics (from Solver)
A4: F PPS (USD) | B4: =Solver!B84
A5: D new conversion price (NCP) | B5: =Solver!C84
A6: E new conversion price (NCP) | B6: =Solver!D84
A7: ΔD shares (AD bump) | B7: =Solver!E84
A8: ΔE shares (AD bump) | B8: =Solver!F84
A9: ESOP top-up shares | B9: =Solver!G84
A10: Note A converted shares | B10: =M21
A11: Note B converted shares | B11: =M22
A12: New F primary shares ($30M / F_PPS) | B12: =Assumptions!$B$4/B4
A13: Pre-money FD | B13: =Solver!J84
A14: Post-F FD (T_F) | B14: =Solver!K84
A15: Tender shares | B15: =Assumptions!$B$5/(Assumptions!$B$6*B4)
A17: Anti-Dilution Block (Broad-Based WA) | H17: Convertible Notes Block
A18: Class | B18: OCP | C18: F_PPS<OCP? | D18: New CP | E18: New ratio (compound) | F18: As-converted shares | H18: Note | I18: Cap-implied PPS | J18: Discount-implied PPS | K18: Conversion PPS (min) | L18: Branch | M18: Shares
A19: Seed | B19: =Assumptions!$B$16 | C19: =IF(B4<B19,"trigger","dormant") | D19: =B19 | E19: =B19/D19 | F19: =Assumptions!$B$33*E19
A20: Series A | B20: =Assumptions!$B$17 | C20: =IF(B4<B20,"trigger","dormant") | D20: =B20 | E20: =B20/D20 | F20: =Assumptions!$B$34*E20
A21: Series B | B21: =Assumptions!$B$18 | C21: =IF(B4<B21,"trigger","dormant") | D21: =B21 | E21: =B21/D21 | F21: =Assumptions!$B$35*E21 | H21: Note A | I21: =Assumptions!$B$24/(Assumptions!$B$29+B7+B8+B9+Solver!I84) | J21: =B4*(1-Assumptions!$B$25) | K21: =MIN(I21,J21) | L21: =IF(I21<J21,"cap","discount") | M21: =Assumptions!$B$23/K21
A22: Series C | B22: =Assumptions!$B$19 | C22: =IF(B4<B22,"trigger","dormant") | D22: =B22 | E22: =B22/D22 | F22: =Assumptions!$B$36*E22 | H22: Note B | I22: =Assumptions!$B$27/(Assumptions!$B$29+B7+B8+B9+Solver!H84) | J22: =B4*(1-Assumptions!$B$28) | K22: =MIN(I22,J22) | L22: =IF(I22<J22,"cap","discount") | M22: =Assumptions!$B$26/K22
A23: Series D | B23: =Assumptions!$B$20 | C23: =IF(B4<B23,"trigger","dormant") | D23: =B5 | E23: =Assumptions!$B$22/D23 | F23: =Assumptions!$B$37*E23
A24: Series E | B24: =Assumptions!$B$21 | C24: =IF(B4<B24,"trigger","dormant") | D24: =B6 | E24: =Assumptions!$B$21/D24 | F24: =Assumptions!$B$39*E24
A27: Tender Block (Secondary)
A28: Tender shares | B28: =B15
A29: F1 share-out (50%) | B29: =B28*0.5
A30: F2 share-out (31.25%) | B30: =B28*0.3125
A31: F3 share-out (18.75%) | B31: =B28*0.1875
A32: F_LEAD secondary common | B32: =B28
A35: Stakeholder Breakdown (Post-F)
A36: Stakeholder | B36: Common | C36: Pref Class | D36: Pref Shares | E36: Total FD Shares | F36: Ownership %
A37: F1 | B37: =Assumptions!$B$46-B29 | D37: =0 | E37: =B37+D37 | F37: =E37/$B$14
A38: F2 | B38: =Assumptions!$B$47-B30 | D38: =0 | E38: =B38+D38 | F38: =E38/$B$14
A39: F3 | B39: =Assumptions!$B$48-B31 | D39: =0 | E39: =B39+D39 | F39: =E39/$B$14
A40: RSA holders (E1-E10) | B40: =Assumptions!$B$49 | D40: =0 | E40: =B40+D40 | F40: =E40/$B$14
A41: SEED1 | B41: =0 | C41: Seed | D41: =Assumptions!$B$33 | E41: =B41+D41 | F41: =E41/$B$14
A42: A1 | B42: =0 | C42: Series A | D42: =Assumptions!$B$34 | E42: =B42+D42 | F42: =E42/$B$14
A43: B1 | B43: =0 | C43: Series B | D43: =Assumptions!$B$35 | E43: =B43+D43 | F43: =E43/$B$14
A44: C1 | B44: =0 | C44: Series C | D44: =Assumptions!$B$36 | E44: =B44+D44 | F44: =E44/$B$14
A45: D1 | B45: =0 | C45: Series D | D45: =F23 | E45: =B45+D45 | F45: =E45/$B$14
A46: Series E LPs (10) | B46: =0 | C46: Series E | D46: =F24 | E46: =B46+D46 | F46: =E46/$B$14
A47: NA1 (Note A) | B47: =M21 | C47: Common (note conv) | D47: =0 | E47: =B47+D47 | F47: =E47/$B$14
A48: NB1 (Note B) | B48: =M22 | C48: Common (note conv) | D48: =0 | E48: =B48+D48 | F48: =E48/$B$14
A49: F_LEAD (primary) | B49: =0 | C49: Series F | D49: =Assumptions!$B$9/B4 | E49: =B49+D49 | F49: =E49/$B$14
A50: F_LEAD (secondary common) | B50: =B32 | D50: =0 | E50: =B50+D50 | F50: =E50/$B$14
A51: F_FUND (our fund) | B51: =0 | C51: Series F | D51: =Assumptions!$B$8/B4 | E51: =B51+D51 | F51: =E51/$B$14
A52: Issued options | B52: =0 | C52: Options (issued) | D52: =Assumptions!$B$31 | E52: =B52+D52 | F52: =E52/$B$14
A53: Unissued options (ESOP) | B53: =0 | C53: Options (unissued) | D53: =Assumptions!$B$32+B9 | E53: =B53+D53 | F53: =E53/$B$14
A55: TOTAL | B55: =SUM(B37:B54) | D55: =SUM(D37:D54) | E55: =SUM(E37:E54) | F55: =SUM(F37:F54)

Sheet Waterfall
A1: Waterfall by Exit Value
A3: Class | B3: LP ($) | C3: Post-F shares
A4: F | B4: =Assumptions!$B$4 | C4: =Assumptions!$B$4/'Pro-Forma'!$B$4
A5: E | B5: =Assumptions!$B$45 | C5: ='Pro-Forma'!$F$24
A6: D | B6: =Assumptions!$B$44 | C6: ='Pro-Forma'!$F$23
A7: C | B7: =Assumptions!$B$43 | C7: =Assumptions!$B$36
A8: B | B8: =Assumptions!$B$42 | C8: =Assumptions!$B$35
A9: A | B9: =Assumptions!$B$41 | C9: =Assumptions!$B$34
A10: Seed | B10: =Assumptions!$B$40 | C10: =Assumptions!$B$33
A12: Exit Value (USD) | B12: =Assumptions!$B$11 | C12: =Assumptions!$B$12 | D12: =Assumptions!$B$13 | E12: =Assumptions!$B$14 | F12: =Assumptions!$B$15
A14: 35 Election Cells (formula-driven IF)
A16: Exit 1 iteration ladder
A17: Step | B17: F_el | C17: E_el | D17: D_el | E17: C_el | F17: B_el | G17: A_el | H17: Seed_el | I17: prefs | J17: conv_sh | K17: cpool | L17: ITM_PPS | M17: ITM? | N17: common_PPS | O17: opt_proc
A18: seed (all convert) | B18: ="convert" | C18: ="convert" | D18: ="convert" | E18: ="convert" | F18: ="convert" | G18: ="convert" | H18: ="convert" | I18: =IF(B18="preference",$B$4,0)+IF(C18="preference",$B$5,0)+IF(D18="preference",$B$6,0)+IF(E18="preference",$B$7,0)+IF(F18="preference",$B$8,0)+IF(G18="preference",$B$9,0)+IF(H18="preference",$B$10,0) | J18: =IF(B18="convert",$C$4,0)+IF(C18="convert",$C$5,0)+IF(D18="convert",$C$6,0)+IF(E18="convert",$C$7,0)+IF(F18="convert",$C$8,0)+IF(G18="convert",$C$9,0)+IF(H18="convert",$C$10,0) | K18: =(Assumptions!$B$46+Assumptions!$B$47+Assumptions!$B$48)+Assumptions!$B$49+('Pro-Forma'!$M$21+'Pro-Forma'!$M$22)+J18 | L18: =(B12-I18+Assumptions!$B$31*Assumptions!$B$10)/(K18+Assumptions!$B$31) | M18: =IF(L18>Assumptions!$B$10,"yes","no") | N18: =IF(M18="yes",L18,MAX(0,(B12-I18)/K18)) | O18: =IF(M18="yes",Assumptions!$B$31*(N18-Assumptions!$B$10),0)
A19: iter 1 | B19: =IF($B$4>$C$4*N18,"preference","convert") | C19: =IF($B$5>$C$5*N18,"preference","convert") | D19: =IF($B$6>$C$6*N18,"preference","convert") | E19: =IF($B$7>$C$7*N18,"preference","convert") | F19: =IF($B$8>$C$8*N18,"preference","convert") | G19: =IF($B$9>$C$9*N18,"preference","convert") | H19: =IF($B$10>$C$10*N18,"preference","convert") | I19: =IF(B19="preference",$B$4,0)+IF(C19="preference",$B$5,0)+IF(D19="preference",$B$6,0)+IF(E19="preference",$B$7,0)+IF(F19="preference",$B$8,0)+IF(G19="preference",$B$9,0)+IF(H19="preference",$B$10,0) | J19: =IF(B19="convert",$C$4,0)+IF(C19="convert",$C$5,0)+IF(D19="convert",$C$6,0)+IF(E19="convert",$C$7,0)+IF(F19="convert",$C$8,0)+IF(G19="convert",$C$9,0)+IF(H19="convert",$C$10,0) | K19: =(Assumptions!$B$46+Assumptions!$B$47+Assumptions!$B$48)+Assumptions!$B$49+('Pro-Forma'!$M$21+'Pro-Forma'!$M$22)+J19 | L19: =(B12-I19+Assumptions!$B$31*Assumptions!$B$10)/(K19+Assumptions!$B$31) | M19: =IF(L19>Assumptions!$B$10,"yes","no") | N19: =IF(M19="yes",L19,MAX(0,(B12-I19)/K19)) | O19: =IF(M19="yes",Assumptions!$B$31*(N19-Assumptions!$B$10),0)
A20: iter 2 | B20: =IF($B$4>$C$4*N19,"preference","convert") | C20: =IF($B$5>$C$5*N19,"preference","convert") | D20: =IF($B$6>$C$6*N19,"preference","convert") | E20: =IF($B$7>$C$7*N19,"preference","convert") | F20: =IF($B$8>$C$8*N19,"preference","convert") | G20: =IF($B$9>$C$9*N19,"preference","convert") | H20: =IF($B$10>$C$10*N19,"preference","convert") | I20: =IF(B20="preference",$B$4,0)+IF(C20="preference",$B$5,0)+IF(D20="preference",$B$6,0)+IF(E20="preference",$B$7,0)+IF(F20="preference",$B$8,0)+IF(G20="preference",$B$9,0)+IF(H20="preference",$B$10,0) | J20: =IF(B20="convert",$C$4,0)+IF(C20="convert",$C$5,0)+IF(D20="convert",$C$6,0)+IF(E20="convert",$C$7,0)+IF(F20="convert",$C$8,0)+IF(G20="convert",$C$9,0)+IF(H20="convert",$C$10,0) | K20: =(Assumptions!$B$46+Assumptions!$B$47+Assumptions!$B$48)+Assumptions!$B$49+('Pro-Forma'!$M$21+'Pro-Forma'!$M$22)+J20 | L20: =(B12-I20+Assumptions!$B$31*Assumptions!$B$10)/(K20+Assumptions!$B$31) | M20: =IF(L20>Assumptions!$B$10,"yes","no") | N20: =IF(M20="yes",L20,MAX(0,(B12-I20)/K20)) | O20: =IF(M20="yes",Assumptions!$B$31*(N20-Assumptions!$B$10),0)
A21: iter 3 | B21: =IF($B$4>$C$4*N20,"preference","convert") | C21: =IF($B$5>$C$5*N20,"preference","convert") | D21: =IF($B$6>$C$6*N20,"preference","convert") | E21: =IF($B$7>$C$7*N20,"preference","convert") | F21: =IF($B$8>$C$8*N20,"preference","convert") | G21: =IF($B$9>$C$9*N20,"preference","convert") | H21: =IF($B$10>$C$10*N20,"preference","convert") | I21: =IF(B21="preference",$B$4,0)+IF(C21="preference",$B$5,0)+IF(D21="preference",$B$6,0)+IF(E21="preference",$B$7,0)+IF(F21="preference",$B$8,0)+IF(G21="preference",$B$9,0)+IF(H21="preference",$B$10,0) | J21: =IF(B21="convert",$C$4,0)+IF(C21="convert",$C$5,0)+IF(D21="convert",$C$6,0)+IF(E21="convert",$C$7,0)+IF(F21="convert",$C$8,0)+IF(G21="convert",$C$9,0)+IF(H21="convert",$C$10,0) | K21: =(Assumptions!$B$46+Assumptions!$B$47+Assumptions!$B$48)+Assumptions!$B$49+('Pro-Forma'!$M$21+'Pro-Forma'!$M$22)+J21 | L21: =(B12-I21+Assumptions!$B$31*Assumptions!$B$10)/(K21+Assumptions!$B$31) | M21: =IF(L21>Assumptions!$B$10,"yes","no") | N21: =IF(M21="yes",L21,MAX(0,(B12-I21)/K21)) | O21: =IF(M21="yes",Assumptions!$B$31*(N21-Assumptions!$B$10),0)
A22: iter 4 | B22: =IF($B$4>$C$4*N21,"preference","convert") | C22: =IF($B$5>$C$5*N21,"preference","convert") | D22: =IF($B$6>$C$6*N21,"preference","convert") | E22: =IF($B$7>$C$7*N21,"preference","convert") | F22: =IF($B$8>$C$8*N21,"preference","convert") | G22: =IF($B$9>$C$9*N21,"preference","convert") | H22: =IF($B$10>$C$10*N21,"preference","convert") | I22: =IF(B22="preference",$B$4,0)+IF(C22="preference",$B$5,0)+IF(D22="preference",$B$6,0)+IF(E22="preference",$B$7,0)+IF(F22="preference",$B$8,0)+IF(G22="preference",$B$9,0)+IF(H22="preference",$B$10,0) | J22: =IF(B22="convert",$C$4,0)+IF(C22="convert",$C$5,0)+IF(D22="convert",$C$6,0)+IF(E22="convert",$C$7,0)+IF(F22="convert",$C$8,0)+IF(G22="convert",$C$9,0)+IF(H22="convert",$C$10,0) | K22: =(Assumptions!$B$46+Assumptions!$B$47+Assumptions!$B$48)+Assumptions!$B$49+('Pro-Forma'!$M$21+'Pro-Forma'!$M$22)+J22 | L22: =(B12-I22+Assumptions!$B$31*Assumptions!$B$10)/(K22+Assumptions!$B$31) | M22: =IF(L22>Assumptions!$B$10,"yes","no") | N22: =IF(M22="yes",L22,MAX(0,(B12-I22)/K22)) | O22: =IF(M22="yes",Assumptions!$B$31*(N22-Assumptions!$B$10),0)
A23: iter 5 | B23: =IF($B$4>$C$4*N22,"preference","convert") | C23: =IF($B$5>$C$5*N22,"preference","convert") | D23: =IF($B$6>$C$6*N22,"preference","convert") | E23: =IF($B$7>$C$7*N22,"preference","convert") | F23: =IF($B$8>$C$8*N22,"preference","convert") | G23: =IF($B$9>$C$9*N22,"preference","convert") | H23: =IF($B$10>$C$10*N22,"preference","convert") | I23: =IF(B23="preference",$B$4,0)+IF(C23="preference",$B$5,0)+IF(D23="preference",$B$6,0)+IF(E23="preference",$B$7,0)+IF(F23="preference",$B$8,0)+IF(G23="preference",$B$9,0)+IF(H23="preference",$B$10,0) | J23: =IF(B23="convert",$C$4,0)+IF(C23="convert",$C$5,0)+IF(D23="convert",$C$6,0)+IF(E23="convert",$C$7,0)+IF(F23="convert",$C$8,0)+IF(G23="convert",$C$9,0)+IF(H23="convert",$C$10,0) | K23: =(Assumptions!$B$46+Assumptions!$B$47+Assumptions!$B$48)+Assumptions!$B$49+('Pro-Forma'!$M$21+'Pro-Forma'!$M$22)+J23 | L23: =(B12-I23+Assumptions!$B$31*Assumptions!$B$10)/(K23+Assumptions!$B$31) | M23: =IF(L23>Assumptions!$B$10,"yes","no") | N23: =IF(M23="yes",L23,MAX(0,(B12-I23)/K23)) | O23: =IF(M23="yes",Assumptions!$B$31*(N23-Assumptions!$B$10),0)
A24: iter 6 | B24: =IF($B$4>$C$4*N23,"preference","convert") | C24: =IF($B$5>$C$5*N23,"preference","convert") | D24: =IF($B$6>$C$6*N23,"preference","convert") | E24: =IF($B$7>$C$7*N23,"preference","convert") | F24: =IF($B$8>$C$8*N23,"preference","convert") | G24: =IF($B$9>$C$9*N23,"preference","convert") | H24: =IF($B$10>$C$10*N23,"preference","convert") | I24: =IF(B24="preference",$B$4,0)+IF(C24="preference",$B$5,0)+IF(D24="preference",$B$6,0)+IF(E24="preference",$B$7,0)+IF(F24="preference",$B$8,0)+IF(G24="preference",$B$9,0)+IF(H24="preference",$B$10,0) | J24: =IF(B24="convert",$C$4,0)+IF(C24="convert",$C$5,0)+IF(D24="convert",$C$6,0)+IF(E24="convert",$C$7,0)+IF(F24="convert",$C$8,0)+IF(G24="convert",$C$9,0)+IF(H24="convert",$C$10,0) | K24: =(Assumptions!$B$46+Assumptions!$B$47+Assumptions!$B$48)+Assumptions!$B$49+('Pro-Forma'!$M$21+'Pro-Forma'!$M$22)+J24 | L24: =(B12-I24+Assumptions!$B$31*Assumptions!$B$10)/(K24+Assumptions!$B$31) | M24: =IF(L24>Assumptions!$B$10,"yes","no") | N24: =IF(M24="yes",L24,MAX(0,(B12-I24)/K24)) | O24: =IF(M24="yes",Assumptions!$B$31*(N24-Assumptions!$B$10),0)
A25: iter 7 | B25: =IF($B$4>$C$4*N24,"preference","convert") | C25: =IF($B$5>$C$5*N24,"preference","convert") | D25: =IF($B$6>$C$6*N24,"preference","convert") | E25: =IF($B$7>$C$7*N24,"preference","convert") | F25: =IF($B$8>$C$8*N24,"preference","convert") | G25: =IF($B$9>$C$9*N24,"preference","convert") | H25: =IF($B$10>$C$10*N24,"preference","convert") | I25: =IF(B25="preference",$B$4,0)+IF(C25="preference",$B$5,0)+IF(D25="preference",$B$6,0)+IF(E25="preference",$B$7,0)+IF(F25="preference",$B$8,0)+IF(G25="preference",$B$9,0)+IF(H25="preference",$B$10,0) | J25: =IF(B25="convert",$C$4,0)+IF(C25="convert",$C$5,0)+IF(D25="convert",$C$6,0)+IF(E25="convert",$C$7,0)+IF(F25="convert",$C$8,0)+IF(G25="convert",$C$9,0)+IF(H25="convert",$C$10,0) | K25: =(Assumptions!$B$46+Assumptions!$B$47+Assumptions!$B$48)+Assumptions!$B$49+('Pro-Forma'!$M$21+'Pro-Forma'!$M$22)+J25 | L25: =(B12-I25+Assumptions!$B$31*Assumptions!$B$10)/(K25+Assumptions!$B$31) | M25: =IF(L25>Assumptions!$B$10,"yes","no") | N25: =IF(M25="yes",L25,MAX(0,(B12-I25)/K25)) | O25: =IF(M25="yes",Assumptions!$B$31*(N25-Assumptions!$B$10),0)
A26: iter 8 | B26: =IF($B$4>$C$4*N25,"preference","convert") | C26: =IF($B$5>$C$5*N25,"preference","convert") | D26: =IF($B$6>$C$6*N25,"preference","convert") | E26: =IF($B$7>$C$7*N25,"preference","convert") | F26: =IF($B$8>$C$8*N25,"preference","convert") | G26: =IF($B$9>$C$9*N25,"preference","convert") | H26: =IF($B$10>$C$10*N25,"preference","convert") | I26: =IF(B26="preference",$B$4,0)+IF(C26="preference",$B$5,0)+IF(D26="preference",$B$6,0)+IF(E26="preference",$B$7,0)+IF(F26="preference",$B$8,0)+IF(G26="preference",$B$9,0)+IF(H26="preference",$B$10,0) | J26: =IF(B26="convert",$C$4,0)+IF(C26="convert",$C$5,0)+IF(D26="convert",$C$6,0)+IF(E26="convert",$C$7,0)+IF(F26="convert",$C$8,0)+IF(G26="convert",$C$9,0)+IF(H26="convert",$C$10,0) | K26: =(Assumptions!$B$46+Assumptions!$B$47+Assumptions!$B$48)+Assumptions!$B$49+('Pro-Forma'!$M$21+'Pro-Forma'!$M$22)+J26 | L26: =(B12-I26+Assumptions!$B$31*Assumptions!$B$10)/(K26+Assumptions!$B$31) | M26: =IF(L26>Assumptions!$B$10,"yes","no") | N26: =IF(M26="yes",L26,MAX(0,(B12-I26)/K26)) | O26: =IF(M26="yes",Assumptions!$B$31*(N26-Assumptions!$B$10),0)
A27: iter 9 | B27: =IF($B$4>$C$4*N26,"preference","convert") | C27: =IF($B$5>$C$5*N26,"preference","convert") | D27: =IF($B$6>$C$6*N26,"preference","convert") | E27: =IF($B$7>$C$7*N26,"preference","convert") | F27: =IF($B$8>$C$8*N26,"preference","convert") | G27: =IF($B$9>$C$9*N26,"preference","convert") | H27: =IF($B$10>$C$10*N26,"preference","convert") | I27: =IF(B27="preference",$B$4,0)+IF(C27="preference",$B$5,0)+IF(D27="preference",$B$6,0)+IF(E27="preference",$B$7,0)+IF(F27="preference",$B$8,0)+IF(G27="preference",$B$9,0)+IF(H27="preference",$B$10,0) | J27: =IF(B27="convert",$C$4,0)+IF(C27="convert",$C$5,0)+IF(D27="convert",$C$6,0)+IF(E27="convert",$C$7,0)+IF(F27="convert",$C$8,0)+IF(G27="convert",$C$9,0)+IF(H27="convert",$C$10,0) | K27: =(Assumptions!$B$46+Assumptions!$B$47+Assumptions!$B$48)+Assumptions!$B$49+('Pro-Forma'!$M$21+'Pro-Forma'!$M$22)+J27 | L27: =(B12-I27+Assumptions!$B$31*Assumptions!$B$10)/(K27+Assumptions!$B$31) | M27: =IF(L27>Assumptions!$B$10,"yes","no") | N27: =IF(M27="yes",L27,MAX(0,(B12-I27)/K27)) | O27: =IF(M27="yes",Assumptions!$B$31*(N27-Assumptions!$B$10),0)
A28: iter 10 | B28: =IF($B$4>$C$4*N27,"preference","convert") | C28: =IF($B$5>$C$5*N27,"preference","convert") | D28: =IF($B$6>$C$6*N27,"preference","convert") | E28: =IF($B$7>$C$7*N27,"preference","convert") | F28: =IF($B$8>$C$8*N27,"preference","convert") | G28: =IF($B$9>$C$9*N27,"preference","convert") | H28: =IF($B$10>$C$10*N27,"preference","convert") | I28: =IF(B28="preference",$B$4,0)+IF(C28="preference",$B$5,0)+IF(D28="preference",$B$6,0)+IF(E28="preference",$B$7,0)+IF(F28="preference",$B$8,0)+IF(G28="preference",$B$9,0)+IF(H28="preference",$B$10,0) | J28: =IF(B28="convert",$C$4,0)+IF(C28="convert",$C$5,0)+IF(D28="convert",$C$6,0)+IF(E28="convert",$C$7,0)+IF(F28="convert",$C$8,0)+IF(G28="convert",$C$9,0)+IF(H28="convert",$C$10,0) | K28: =(Assumptions!$B$46+Assumptions!$B$47+Assumptions!$B$48)+Assumptions!$B$49+('Pro-Forma'!$M$21+'Pro-Forma'!$M$22)+J28 | L28: =(B12-I28+Assumptions!$B$31*Assumptions!$B$10)/(K28+Assumptions!$B$31) | M28: =IF(L28>Assumptions!$B$10,"yes","no") | N28: =IF(M28="yes",L28,MAX(0,(B12-I28)/K28)) | O28: =IF(M28="yes",Assumptions!$B$31*(N28-Assumptions!$B$10),0)
A29: iter 11 | B29: =IF($B$4>$C$4*N28,"preference","convert") | C29: =IF($B$5>$C$5*N28,"preference","convert") | D29: =IF($B$6>$C$6*N28,"preference","convert") | E29: =IF($B$7>$C$7*N28,"preference","convert") | F29: =IF($B$8>$C$8*N28,"preference","convert") | G29: =IF($B$9>$C$9*N28,"preference","convert") | H29: =IF($B$10>$C$10*N28,"preference","convert") | I29: =IF(B29="preference",$B$4,0)+IF(C29="preference",$B$5,0)+IF(D29="preference",$B$6,0)+IF(E29="preference",$B$7,0)+IF(F29="preference",$B$8,0)+IF(G29="preference",$B$9,0)+IF(H29="preference",$B$10,0) | J29: =IF(B29="convert",$C$4,0)+IF(C29="convert",$C$5,0)+IF(D29="convert",$C$6,0)+IF(E29="convert",$C$7,0)+IF(F29="convert",$C$8,0)+IF(G29="convert",$C$9,0)+IF(H29="convert",$C$10,0) | K29: =(Assumptions!$B$46+Assumptions!$B$47+Assumptions!$B$48)+Assumptions!$B$49+('Pro-Forma'!$M$21+'Pro-Forma'!$M$22)+J29 | L29: =(B12-I29+Assumptions!$B$31*Assumptions!$B$10)/(K29+Assumptions!$B$31) | M29: =IF(L29>Assumptions!$B$10,"yes","no") | N29: =IF(M29="yes",L29,MAX(0,(B12-I29)/K29)) | O29: =IF(M29="yes",Assumptions!$B$31*(N29-Assumptions!$B$10),0)
A30: iter 12 | B30: =IF($B$4>$C$4*N29,"preference","convert") | C30: =IF($B$5>$C$5*N29,"preference","convert") | D30: =IF($B$6>$C$6*N29,"preference","convert") | E30: =IF($B$7>$C$7*N29,"preference","convert") | F30: =IF($B$8>$C$8*N29,"preference","convert") | G30: =IF($B$9>$C$9*N29,"preference","convert") | H30: =IF($B$10>$C$10*N29,"preference","convert") | I30: =IF(B30="preference",$B$4,0)+IF(C30="preference",$B$5,0)+IF(D30="preference",$B$6,0)+IF(E30="preference",$B$7,0)+IF(F30="preference",$B$8,0)+IF(G30="preference",$B$9,0)+IF(H30="preference",$B$10,0) | J30: =IF(B30="convert",$C$4,0)+IF(C30="convert",$C$5,0)+IF(D30="convert",$C$6,0)+IF(E30="convert",$C$7,0)+IF(F30="convert",$C$8,0)+IF(G30="convert",$C$9,0)+IF(H30="convert",$C$10,0) | K30: =(Assumptions!$B$46+Assumptions!$B$47+Assumptions!$B$48)+Assumptions!$B$49+('Pro-Forma'!$M$21+'Pro-Forma'!$M$22)+J30 | L30: =(B12-I30+Assumptions!$B$31*Assumptions!$B$10)/(K30+Assumptions!$B$31) | M30: =IF(L30>Assumptions!$B$10,"yes","no") | N30: =IF(M30="yes",L30,MAX(0,(B12-I30)/K30)) | O30: =IF(M30="yes",Assumptions!$B$31*(N30-Assumptions!$B$10),0)
A31: iter 13 | B31: =IF($B$4>$C$4*N30,"preference","convert") | C31: =IF($B$5>$C$5*N30,"preference","convert") | D31: =IF($B$6>$C$6*N30,"preference","convert") | E31: =IF($B$7>$C$7*N30,"preference","convert") | F31: =IF($B$8>$C$8*N30,"preference","convert") | G31: =IF($B$9>$C$9*N30,"preference","convert") | H31: =IF($B$10>$C$10*N30,"preference","convert") | I31: =IF(B31="preference",$B$4,0)+IF(C31="preference",$B$5,0)+IF(D31="preference",$B$6,0)+IF(E31="preference",$B$7,0)+IF(F31="preference",$B$8,0)+IF(G31="preference",$B$9,0)+IF(H31="preference",$B$10,0) | J31: =IF(B31="convert",$C$4,0)+IF(C31="convert",$C$5,0)+IF(D31="convert",$C$6,0)+IF(E31="convert",$C$7,0)+IF(F31="convert",$C$8,0)+IF(G31="convert",$C$9,0)+IF(H31="convert",$C$10,0) | K31: =(Assumptions!$B$46+Assumptions!$B$47+Assumptions!$B$48)+Assumptions!$B$49+('Pro-Forma'!$M$21+'Pro-Forma'!$M$22)+J31 | L31: =(B12-I31+Assumptions!$B$31*Assumptions!$B$10)/(K31+Assumptions!$B$31) | M31: =IF(L31>Assumptions!$B$10,"yes","no") | N31: =IF(M31="yes",L31,MAX(0,(B12-I31)/K31)) | O31: =IF(M31="yes",Assumptions!$B$31*(N31-Assumptions!$B$10),0)
A32: iter 14 | B32: =IF($B$4>$C$4*N31,"preference","convert") | C32: =IF($B$5>$C$5*N31,"preference","convert") | D32: =IF($B$6>$C$6*N31,"preference","convert") | E32: =IF($B$7>$C$7*N31,"preference","convert") | F32: =IF($B$8>$C$8*N31,"preference","convert") | G32: =IF($B$9>$C$9*N31,"preference","convert") | H32: =IF($B$10>$C$10*N31,"preference","convert") | I32: =IF(B32="preference",$B$4,0)+IF(C32="preference",$B$5,0)+IF(D32="preference",$B$6,0)+IF(E32="preference",$B$7,0)+IF(F32="preference",$B$8,0)+IF(G32="preference",$B$9,0)+IF(H32="preference",$B$10,0) | J32: =IF(B32="convert",$C$4,0)+IF(C32="convert",$C$5,0)+IF(D32="convert",$C$6,0)+IF(E32="convert",$C$7,0)+IF(F32="convert",$C$8,0)+IF(G32="convert",$C$9,0)+IF(H32="convert",$C$10,0) | K32: =(Assumptions!$B$46+Assumptions!$B$47+Assumptions!$B$48)+Assumptions!$B$49+('Pro-Forma'!$M$21+'Pro-Forma'!$M$22)+J32 | L32: =(B12-I32+Assumptions!$B$31*Assumptions!$B$10)/(K32+Assumptions!$B$31) | M32: =IF(L32>Assumptions!$B$10,"yes","no") | N32: =IF(M32="yes",L32,MAX(0,(B12-I32)/K32)) | O32: =IF(M32="yes",Assumptions!$B$31*(N32-Assumptions!$B$10),0)
A33: iter 15 | B33: =IF($B$4>$C$4*N32,"preference","convert") | C33: =IF($B$5>$C$5*N32,"preference","convert") | D33: =IF($B$6>$C$6*N32,"preference","convert") | E33: =IF($B$7>$C$7*N32,"preference","convert") | F33: =IF($B$8>$C$8*N32,"preference","convert") | G33: =IF($B$9>$C$9*N32,"preference","convert") | H33: =IF($B$10>$C$10*N32,"preference","convert") | I33: =IF(B33="preference",$B$4,0)+IF(C33="preference",$B$5,0)+IF(D33="preference",$B$6,0)+IF(E33="preference",$B$7,0)+IF(F33="preference",$B$8,0)+IF(G33="preference",$B$9,0)+IF(H33="preference",$B$10,0) | J33: =IF(B33="convert",$C$4,0)+IF(C33="convert",$C$5,0)+IF(D33="convert",$C$6,0)+IF(E33="convert",$C$7,0)+IF(F33="convert",$C$8,0)+IF(G33="convert",$C$9,0)+IF(H33="convert",$C$10,0) | K33: =(Assumptions!$B$46+Assumptions!$B$47+Assumptions!$B$48)+Assumptions!$B$49+('Pro-Forma'!$M$21+'Pro-Forma'!$M$22)+J33 | L33: =(B12-I33+Assumptions!$B$31*Assumptions!$B$10)/(K33+Assumptions!$B$31) | M33: =IF(L33>Assumptions!$B$10,"yes","no") | N33: =IF(M33="yes",L33,MAX(0,(B12-I33)/K33)) | O33: =IF(M33="yes",Assumptions!$B$31*(N33-Assumptions!$B$10),0)
A34: iter 16 | B34: =IF($B$4>$C$4*N33,"preference","convert") | C34: =IF($B$5>$C$5*N33,"preference","convert") | D34: =IF($B$6>$C$6*N33,"preference","convert") | E34: =IF($B$7>$C$7*N33,"preference","convert") | F34: =IF($B$8>$C$8*N33,"preference","convert") | G34: =IF($B$9>$C$9*N33,"preference","convert") | H34: =IF($B$10>$C$10*N33,"preference","convert") | I34: =IF(B34="preference",$B$4,0)+IF(C34="preference",$B$5,0)+IF(D34="preference",$B$6,0)+IF(E34="preference",$B$7,0)+IF(F34="preference",$B$8,0)+IF(G34="preference",$B$9,0)+IF(H34="preference",$B$10,0) | J34: =IF(B34="convert",$C$4,0)+IF(C34="convert",$C$5,0)+IF(D34="convert",$C$6,0)+IF(E34="convert",$C$7,0)+IF(F34="convert",$C$8,0)+IF(G34="convert",$C$9,0)+IF(H34="convert",$C$10,0) | K34: =(Assumptions!$B$46+Assumptions!$B$47+Assumptions!$B$48)+Assumptions!$B$49+('Pro-Forma'!$M$21+'Pro-Forma'!$M$22)+J34 | L34: =(B12-I34+Assumptions!$B$31*Assumptions!$B$10)/(K34+Assumptions!$B$31) | M34: =IF(L34>Assumptions!$B$10,"yes","no") | N34: =IF(M34="yes",L34,MAX(0,(B12-I34)/K34)) | O34: =IF(M34="yes",Assumptions!$B$31*(N34-Assumptions!$B$10),0)
A35: iter 17 | B35: =IF($B$4>$C$4*N34,"preference","convert") | C35: =IF($B$5>$C$5*N34,"preference","convert") | D35: =IF($B$6>$C$6*N34,"preference","convert") | E35: =IF($B$7>$C$7*N34,"preference","convert") | F35: =IF($B$8>$C$8*N34,"preference","convert") | G35: =IF($B$9>$C$9*N34,"preference","convert") | H35: =IF($B$10>$C$10*N34,"preference","convert") | I35: =IF(B35="preference",$B$4,0)+IF(C35="preference",$B$5,0)+IF(D35="preference",$B$6,0)+IF(E35="preference",$B$7,0)+IF(F35="preference",$B$8,0)+IF(G35="preference",$B$9,0)+IF(H35="preference",$B$10,0) | J35: =IF(B35="convert",$C$4,0)+IF(C35="convert",$C$5,0)+IF(D35="convert",$C$6,0)+IF(E35="convert",$C$7,0)+IF(F35="convert",$C$8,0)+IF(G35="convert",$C$9,0)+IF(H35="convert",$C$10,0) | K35: =(Assumptions!$B$46+Assumptions!$B$47+Assumptions!$B$48)+Assumptions!$B$49+('Pro-Forma'!$M$21+'Pro-Forma'!$M$22)+J35 | L35: =(B12-I35+Assumptions!$B$31*Assumptions!$B$10)/(K35+Assumptions!$B$31) | M35: =IF(L35>Assumptions!$B$10,"yes","no") | N35: =IF(M35="yes",L35,MAX(0,(B12-I35)/K35)) | O35: =IF(M35="yes",Assumptions!$B$31*(N35-Assumptions!$B$10),0)
A36: iter 18 | B36: =IF($B$4>$C$4*N35,"preference","convert") | C36: =IF($B$5>$C$5*N35,"preference","convert") | D36: =IF($B$6>$C$6*N35,"preference","convert") | E36: =IF($B$7>$C$7*N35,"preference","convert") | F36: =IF($B$8>$C$8*N35,"preference","convert") | G36: =IF($B$9>$C$9*N35,"preference","convert") | H36: =IF($B$10>$C$10*N35,"preference","convert") | I36: =IF(B36="preference",$B$4,0)+IF(C36="preference",$B$5,0)+IF(D36="preference",$B$6,0)+IF(E36="preference",$B$7,0)+IF(F36="preference",$B$8,0)+IF(G36="preference",$B$9,0)+IF(H36="preference",$B$10,0) | J36: =IF(B36="convert",$C$4,0)+IF(C36="convert",$C$5,0)+IF(D36="convert",$C$6,0)+IF(E36="convert",$C$7,0)+IF(F36="convert",$C$8,0)+IF(G36="convert",$C$9,0)+IF(H36="convert",$C$10,0) | K36: =(Assumptions!$B$46+Assumptions!$B$47+Assumptions!$B$48)+Assumptions!$B$49+('Pro-Forma'!$M$21+'Pro-Forma'!$M$22)+J36 | L36: =(B12-I36+Assumptions!$B$31*Assumptions!$B$10)/(K36+Assumptions!$B$31) | M36: =IF(L36>Assumptions!$B$10,"yes","no") | N36: =IF(M36="yes",L36,MAX(0,(B12-I36)/K36)) | O36: =IF(M36="yes",Assumptions!$B$31*(N36-Assumptions!$B$10),0)
A37: iter 19 | B37: =IF($B$4>$C$4*N36,"preference","convert") | C37: =IF($B$5>$C$5*N36,"preference","convert") | D37: =IF($B$6>$C$6*N36,"preference","convert") | E37: =IF($B$7>$C$7*N36,"preference","convert") | F37: =IF($B$8>$C$8*N36,"preference","convert") | G37: =IF($B$9>$C$9*N36,"preference","convert") | H37: =IF($B$10>$C$10*N36,"preference","convert") | I37: =IF(B37="preference",$B$4,0)+IF(C37="preference",$B$5,0)+IF(D37="preference",$B$6,0)+IF(E37="preference",$B$7,0)+IF(F37="preference",$B$8,0)+IF(G37="preference",$B$9,0)+IF(H37="preference",$B$10,0) | J37: =IF(B37="convert",$C$4,0)+IF(C37="convert",$C$5,0)+IF(D37="convert",$C$6,0)+IF(E37="convert",$C$7,0)+IF(F37="convert",$C$8,0)+IF(G37="convert",$C$9,0)+IF(H37="convert",$C$10,0) | K37: =(Assumptions!$B$46+Assumptions!$B$47+Assumptions!$B$48)+Assumptions!$B$49+('Pro-Forma'!$M$21+'Pro-Forma'!$M$22)+J37 | L37: =(B12-I37+Assumptions!$B$31*Assumptions!$B$10)/(K37+Assumptions!$B$31) | M37: =IF(L37>Assumptions!$B$10,"yes","no") | N37: =IF(M37="yes",L37,MAX(0,(B12-I37)/K37)) | O37: =IF(M37="yes",Assumptions!$B$31*(N37-Assumptions!$B$10),0)
A38: iter 20 | B38: =IF($B$4>$C$4*N37,"preference","convert") | C38: =IF($B$5>$C$5*N37,"preference","convert") | D38: =IF($B$6>$C$6*N37,"preference","convert") | E38: =IF($B$7>$C$7*N37,"preference","convert") | F38: =IF($B$8>$C$8*N37,"preference","convert") | G38: =IF($B$9>$C$9*N37,"preference","convert") | H38: =IF($B$10>$C$10*N37,"preference","convert") | I38: =IF(B38="preference",$B$4,0)+IF(C38="preference",$B$5,0)+IF(D38="preference",$B$6,0)+IF(E38="preference",$B$7,0)+IF(F38="preference",$B$8,0)+IF(G38="preference",$B$9,0)+IF(H38="preference",$B$10,0) | J38: =IF(B38="convert",$C$4,0)+IF(C38="convert",$C$5,0)+IF(D38="convert",$C$6,0)+IF(E38="convert",$C$7,0)+IF(F38="convert",$C$8,0)+IF(G38="convert",$C$9,0)+IF(H38="convert",$C$10,0) | K38: =(Assumptions!$B$46+Assumptions!$B$47+Assumptions!$B$48)+Assumptions!$B$49+('Pro-Forma'!$M$21+'Pro-Forma'!$M$22)+J38 | L38: =(B12-I38+Assumptions!$B$31*Assumptions!$B$10)/(K38+Assumptions!$B$31) | M38: =IF(L38>Assumptions!$B$10,"yes","no") | N38: =IF(M38="yes",L38,MAX(0,(B12-I38)/K38)) | O38: =IF(M38="yes",Assumptions!$B$31*(N38-Assumptions!$B$10),0)
A39: iter 21 | B39: =IF($B$4>$C$4*N38,"preference","convert") | C39: =IF($B$5>$C$5*N38,"preference","convert") | D39: =IF($B$6>$C$6*N38,"preference","convert") | E39: =IF($B$7>$C$7*N38,"preference","convert") | F39: =IF($B$8>$C$8*N38,"preference","convert") | G39: =IF($B$9>$C$9*N38,"preference","convert") | H39: =IF($B$10>$C$10*N38,"preference","convert") | I39: =IF(B39="preference",$B$4,0)+IF(C39="preference",$B$5,0)+IF(D39="preference",$B$6,0)+IF(E39="preference",$B$7,0)+IF(F39="preference",$B$8,0)+IF(G39="preference",$B$9,0)+IF(H39="preference",$B$10,0) | J39: =IF(B39="convert",$C$4,0)+IF(C39="convert",$C$5,0)+IF(D39="convert",$C$6,0)+IF(E39="convert",$C$7,0)+IF(F39="convert",$C$8,0)+IF(G39="convert",$C$9,0)+IF(H39="convert",$C$10,0) | K39: =(Assumptions!$B$46+Assumptions!$B$47+Assumptions!$B$48)+Assumptions!$B$49+('Pro-Forma'!$M$21+'Pro-Forma'!$M$22)+J39 | L39: =(B12-I39+Assumptions!$B$31*Assumptions!$B$10)/(K39+Assumptions!$B$31) | M39: =IF(L39>Assumptions!$B$10,"yes","no") | N39: =IF(M39="yes",L39,MAX(0,(B12-I39)/K39)) | O39: =IF(M39="yes",Assumptions!$B$31*(N39-Assumptions!$B$10),0)
A40: iter 22 | B40: =IF($B$4>$C$4*N39,"preference","convert") | C40: =IF($B$5>$C$5*N39,"preference","convert") | D40: =IF($B$6>$C$6*N39,"preference","convert") | E40: =IF($B$7>$C$7*N39,"preference","convert") | F40: =IF($B$8>$C$8*N39,"preference","convert") | G40: =IF($B$9>$C$9*N39,"preference","convert") | H40: =IF($B$10>$C$10*N39,"preference","convert") | I40: =IF(B40="preference",$B$4,0)+IF(C40="preference",$B$5,0)+IF(D40="preference",$B$6,0)+IF(E40="preference",$B$7,0)+IF(F40="preference",$B$8,0)+IF(G40="preference",$B$9,0)+IF(H40="preference",$B$10,0) | J40: =IF(B40="convert",$C$4,0)+IF(C40="convert",$C$5,0)+IF(D40="convert",$C$6,0)+IF(E40="convert",$C$7,0)+IF(F40="convert",$C$8,0)+IF(G40="convert",$C$9,0)+IF(H40="convert",$C$10,0) | K40: =(Assumptions!$B$46+Assumptions!$B$47+Assumptions!$B$48)+Assumptions!$B$49+('Pro-Forma'!$M$21+'Pro-Forma'!$M$22)+J40 | L40: =(B12-I40+Assumptions!$B$31*Assumptions!$B$10)/(K40+Assumptions!$B$31) | M40: =IF(L40>Assumptions!$B$10,"yes","no") | N40: =IF(M40="yes",L40,MAX(0,(B12-I40)/K40)) | O40: =IF(M40="yes",Assumptions!$B$31*(N40-Assumptions!$B$10),0)
A41: iter 23 | B41: =IF($B$4>$C$4*N40,"preference","convert") | C41: =IF($B$5>$C$5*N40,"preference","convert") | D41: =IF($B$6>$C$6*N40,"preference","convert") | E41: =IF($B$7>$C$7*N40,"preference","convert") | F41: =IF($B$8>$C$8*N40,"preference","convert") | G41: =IF($B$9>$C$9*N40,"preference","convert") | H41: =IF($B$10>$C$10*N40,"preference","convert") | I41: =IF(B41="preference",$B$4,0)+IF(C41="preference",$B$5,0)+IF(D41="preference",$B$6,0)+IF(E41="preference",$B$7,0)+IF(F41="preference",$B$8,0)+IF(G41="preference",$B$9,0)+IF(H41="preference",$B$10,0) | J41: =IF(B41="convert",$C$4,0)+IF(C41="convert",$C$5,0)+IF(D41="convert",$C$6,0)+IF(E41="convert",$C$7,0)+IF(F41="convert",$C$8,0)+IF(G41="convert",$C$9,0)+IF(H41="convert",$C$10,0) | K41: =(Assumptions!$B$46+Assumptions!$B$47+Assumptions!$B$48)+Assumptions!$B$49+('Pro-Forma'!$M$21+'Pro-Forma'!$M$22)+J41 | L41: =(B12-I41+Assumptions!$B$31*Assumptions!$B$10)/(K41+Assumptions!$B$31) | M41: =IF(L41>Assumptions!$B$10,"yes","no") | N41: =IF(M41="yes",L41,MAX(0,(B12-I41)/K41)) | O41: =IF(M41="yes",Assumptions!$B$31*(N41-Assumptions!$B$10),0)
A42: iter 24 | B42: =IF($B$4>$C$4*N41,"preference","convert") | C42: =IF($B$5>$C$5*N41,"preference","convert") | D42: =IF($B$6>$C$6*N41,"preference","convert") | E42: =IF($B$7>$C$7*N41,"preference","convert") | F42: =IF($B$8>$C$8*N41,"preference","convert") | G42: =IF($B$9>$C$9*N41,"preference","convert") | H42: =IF($B$10>$C$10*N41,"preference","convert") | I42: =IF(B42="preference",$B$4,0)+IF(C42="preference",$B$5,0)+IF(D42="preference",$B$6,0)+IF(E42="preference",$B$7,0)+IF(F42="preference",$B$8,0)+IF(G42="preference",$B$9,0)+IF(H42="preference",$B$10,0) | J42: =IF(B42="convert",$C$4,0)+IF(C42="convert",$C$5,0)+IF(D42="convert",$C$6,0)+IF(E42="convert",$C$7,0)+IF(F42="convert",$C$8,0)+IF(G42="convert",$C$9,0)+IF(H42="convert",$C$10,0) | K42: =(Assumptions!$B$46+Assumptions!$B$47+Assumptions!$B$48)+Assumptions!$B$49+('Pro-Forma'!$M$21+'Pro-Forma'!$M$22)+J42 | L42: =(B12-I42+Assumptions!$B$31*Assumptions!$B$10)/(K42+Assumptions!$B$31) | M42: =IF(L42>Assumptions!$B$10,"yes","no") | N42: =IF(M42="yes",L42,MAX(0,(B12-I42)/K42)) | O42: =IF(M42="yes",Assumptions!$B$31*(N42-Assumptions!$B$10),0)
A43: iter 25 | B43: =IF($B$4>$C$4*N42,"preference","convert") | C43: =IF($B$5>$C$5*N42,"preference","convert") | D43: =IF($B$6>$C$6*N42,"preference","convert") | E43: =IF($B$7>$C$7*N42,"preference","convert") | F43: =IF($B$8>$C$8*N42,"preference","convert") | G43: =IF($B$9>$C$9*N42,"preference","convert") | H43: =IF($B$10>$C$10*N42,"preference","convert") | I43: =IF(B43="preference",$B$4,0)+IF(C43="preference",$B$5,0)+IF(D43="preference",$B$6,0)+IF(E43="preference",$B$7,0)+IF(F43="preference",$B$8,0)+IF(G43="preference",$B$9,0)+IF(H43="preference",$B$10,0) | J43: =IF(B43="convert",$C$4,0)+IF(C43="convert",$C$5,0)+IF(D43="convert",$C$6,0)+IF(E43="convert",$C$7,0)+IF(F43="convert",$C$8,0)+IF(G43="convert",$C$9,0)+IF(H43="convert",$C$10,0) | K43: =(Assumptions!$B$46+Assumptions!$B$47+Assumptions!$B$48)+Assumptions!$B$49+('Pro-Forma'!$M$21+'Pro-Forma'!$M$22)+J43 | L43: =(B12-I43+Assumptions!$B$31*Assumptions!$B$10)/(K43+Assumptions!$B$31) | M43: =IF(L43>Assumptions!$B$10,"yes","no") | N43: =IF(M43="yes",L43,MAX(0,(B12-I43)/K43)) | O43: =IF(M43="yes",Assumptions!$B$31*(N43-Assumptions!$B$10),0)
A44: iter 26 | B44: =IF($B$4>$C$4*N43,"preference","convert") | C44: =IF($B$5>$C$5*N43,"preference","convert") | D44: =IF($B$6>$C$6*N43,"preference","convert") | E44: =IF($B$7>$C$7*N43,"preference","convert") | F44: =IF($B$8>$C$8*N43,"preference","convert") | G44: =IF($B$9>$C$9*N43,"preference","convert") | H44: =IF($B$10>$C$10*N43,"preference","convert") | I44: =IF(B44="preference",$B$4,0)+IF(C44="preference",$B$5,0)+IF(D44="preference",$B$6,0)+IF(E44="preference",$B$7,0)+IF(F44="preference",$B$8,0)+IF(G44="preference",$B$9,0)+IF(H44="preference",$B$10,0) | J44: =IF(B44="convert",$C$4,0)+IF(C44="convert",$C$5,0)+IF(D44="convert",$C$6,0)+IF(E44="convert",$C$7,0)+IF(F44="convert",$C$8,0)+IF(G44="convert",$C$9,0)+IF(H44="convert",$C$10,0) | K44: =(Assumptions!$B$46+Assumptions!$B$47+Assumptions!$B$48)+Assumptions!$B$49+('Pro-Forma'!$M$21+'Pro-Forma'!$M$22)+J44 | L44: =(B12-I44+Assumptions!$B$31*Assumptions!$B$10)/(K44+Assumptions!$B$31) | M44: =IF(L44>Assumptions!$B$10,"yes","no") | N44: =IF(M44="yes",L44,MAX(0,(B12-I44)/K44)) | O44: =IF(M44="yes",Assumptions!$B$31*(N44-Assumptions!$B$10),0)
A45: iter 27 | B45: =IF($B$4>$C$4*N44,"preference","convert") | C45: =IF($B$5>$C$5*N44,"preference","convert") | D45: =IF($B$6>$C$6*N44,"preference","convert") | E45: =IF($B$7>$C$7*N44,"preference","convert") | F45: =IF($B$8>$C$8*N44,"preference","convert") | G45: =IF($B$9>$C$9*N44,"preference","convert") | H45: =IF($B$10>$C$10*N44,"preference","convert") | I45: =IF(B45="preference",$B$4,0)+IF(C45="preference",$B$5,0)+IF(D45="preference",$B$6,0)+IF(E45="preference",$B$7,0)+IF(F45="preference",$B$8,0)+IF(G45="preference",$B$9,0)+IF(H45="preference",$B$10,0) | J45: =IF(B45="convert",$C$4,0)+IF(C45="convert",$C$5,0)+IF(D45="convert",$C$6,0)+IF(E45="convert",$C$7,0)+IF(F45="convert",$C$8,0)+IF(G45="convert",$C$9,0)+IF(H45="convert",$C$10,0) | K45: =(Assumptions!$B$46+Assumptions!$B$47+Assumptions!$B$48)+Assumptions!$B$49+('Pro-Forma'!$M$21+'Pro-Forma'!$M$22)+J45 | L45: =(B12-I45+Assumptions!$B$31*Assumptions!$B$10)/(K45+Assumptions!$B$31) | M45: =IF(L45>Assumptions!$B$10,"yes","no") | N45: =IF(M45="yes",L45,MAX(0,(B12-I45)/K45)) | O45: =IF(M45="yes",Assumptions!$B$31*(N45-Assumptions!$B$10),0)
A46: iter 28 | B46: =IF($B$4>$C$4*N45,"preference","convert") | C46: =IF($B$5>$C$5*N45,"preference","convert") | D46: =IF($B$6>$C$6*N45,"preference","convert") | E46: =IF($B$7>$C$7*N45,"preference","convert") | F46: =IF($B$8>$C$8*N45,"preference","convert") | G46: =IF($B$9>$C$9*N45,"preference","convert") | H46: =IF($B$10>$C$10*N45,"preference","convert") | I46: =IF(B46="preference",$B$4,0)+IF(C46="preference",$B$5,0)+IF(D46="preference",$B$6,0)+IF(E46="preference",$B$7,0)+IF(F46="preference",$B$8,0)+IF(G46="preference",$B$9,0)+IF(H46="preference",$B$10,0) | J46: =IF(B46="convert",$C$4,0)+IF(C46="convert",$C$5,0)+IF(D46="convert",$C$6,0)+IF(E46="convert",$C$7,0)+IF(F46="convert",$C$8,0)+IF(G46="convert",$C$9,0)+IF(H46="convert",$C$10,0) | K46: =(Assumptions!$B$46+Assumptions!$B$47+Assumptions!$B$48)+Assumptions!$B$49+('Pro-Forma'!$M$21+'Pro-Forma'!$M$22)+J46 | L46: =(B12-I46+Assumptions!$B$31*Assumptions!$B$10)/(K46+Assumptions!$B$31) | M46: =IF(L46>Assumptions!$B$10,"yes","no") | N46: =IF(M46="yes",L46,MAX(0,(B12-I46)/K46)) | O46: =IF(M46="yes",Assumptions!$B$31*(N46-Assumptions!$B$10),0)
A47: iter 29 | B47: =IF($B$4>$C$4*N46,"preference","convert") | C47: =IF($B$5>$C$5*N46,"preference","convert") | D47: =IF($B$6>$C$6*N46,"preference","convert") | E47: =IF($B$7>$C$7*N46,"preference","convert") | F47: =IF($B$8>$C$8*N46,"preference","convert") | G47: =IF($B$9>$C$9*N46,"preference","convert") | H47: =IF($B$10>$C$10*N46,"preference","convert") | I47: =IF(B47="preference",$B$4,0)+IF(C47="preference",$B$5,0)+IF(D47="preference",$B$6,0)+IF(E47="preference",$B$7,0)+IF(F47="preference",$B$8,0)+IF(G47="preference",$B$9,0)+IF(H47="preference",$B$10,0) | J47: =IF(B47="convert",$C$4,0)+IF(C47="convert",$C$5,0)+IF(D47="convert",$C$6,0)+IF(E47="convert",$C$7,0)+IF(F47="convert",$C$8,0)+IF(G47="convert",$C$9,0)+IF(H47="convert",$C$10,0) | K47: =(Assumptions!$B$46+Assumptions!$B$47+Assumptions!$B$48)+Assumptions!$B$49+('Pro-Forma'!$M$21+'Pro-Forma'!$M$22)+J47 | L47: =(B12-I47+Assumptions!$B$31*Assumptions!$B$10)/(K47+Assumptions!$B$31) | M47: =IF(L47>Assumptions!$B$10,"yes","no") | N47: =IF(M47="yes",L47,MAX(0,(B12-I47)/K47)) | O47: =IF(M47="yes",Assumptions!$B$31*(N47-Assumptions!$B$10),0)
A48: iter 30 | B48: =IF($B$4>$C$4*N47,"preference","convert") | C48: =IF($B$5>$C$5*N47,"preference","convert") | D48: =IF($B$6>$C$6*N47,"preference","convert") | E48: =IF($B$7>$C$7*N47,"preference","convert") | F48: =IF($B$8>$C$8*N47,"preference","convert") | G48: =IF($B$9>$C$9*N47,"preference","convert") | H48: =IF($B$10>$C$10*N47,"preference","convert") | I48: =IF(B48="preference",$B$4,0)+IF(C48="preference",$B$5,0)+IF(D48="preference",$B$6,0)+IF(E48="preference",$B$7,0)+IF(F48="preference",$B$8,0)+IF(G48="preference",$B$9,0)+IF(H48="preference",$B$10,0) | J48: =IF(B48="convert",$C$4,0)+IF(C48="convert",$C$5,0)+IF(D48="convert",$C$6,0)+IF(E48="convert",$C$7,0)+IF(F48="convert",$C$8,0)+IF(G48="convert",$C$9,0)+IF(H48="convert",$C$10,0) | K48: =(Assumptions!$B$46+Assumptions!$B$47+Assumptions!$B$48)+Assumptions!$B$49+('Pro-Forma'!$M$21+'Pro-Forma'!$M$22)+J48 | L48: =(B12-I48+Assumptions!$B$31*Assumptions!$B$10)/(K48+Assumptions!$B$31) | M48: =IF(L48>Assumptions!$B$10,"yes","no") | N48: =IF(M48="yes",L48,MAX(0,(B12-I48)/K48)) | O48: =IF(M48="yes",Assumptions!$B$31*(N48-Assumptions!$B$10),0)
A51: Exit 2 iteration ladder
A52: Step | B52: F_el | C52: E_el | D52: D_el | E52: C_el | F52: B_el | G52: A_el | H52: Seed_el | I52: prefs | J52: conv_sh | K52: cpool | L52: ITM_PPS | M52: ITM? | N52: common_PPS | O52: opt_proc
A53: seed (all convert) | B53: ="convert" | C53: ="convert" | D53: ="convert" | E53: ="convert" | F53: ="convert" | G53: ="convert" | H53: ="convert" | I53: =IF(B53="preference",$B$4,0)+IF(C53="preference",$B$5,0)+IF(D53="preference",$B$6,0)+IF(E53="preference",$B$7,0)+IF(F53="preference",$B$8,0)+IF(G53="preference",$B$9,0)+IF(H53="preference",$B$10,0) | J53: =IF(B53="convert",$C$4,0)+IF(C53="convert",$C$5,0)+IF(D53="convert",$C$6,0)+IF(E53="convert",$C$7,0)+IF(F53="convert",$C$8,0)+IF(G53="convert",$C$9,0)+IF(H53="convert",$C$10,0) | K53: =(Assumptions!$B$46+Assumptions!$B$47+Assumptions!$B$48)+Assumptions!$B$49+('Pro-Forma'!$M$21+'Pro-Forma'!$M$22)+J53 | L53: =(C12-I53+Assumptions!$B$31*Assumptions!$B$10)/(K53+Assumptions!$B$31) | M53: =IF(L53>Assumptions!$B$10,"yes","no") | N53: =IF(M53="yes",L53,MAX(0,(C12-I53)/K53)) | O53: =IF(M53="yes",Assumptions!$B$31*(N53-Assumptions!$B$10),0)
A54: iter 1 | B54: =IF($B$4>$C$4*N53,"preference","convert") | C54: =IF($B$5>$C$5*N53,"preference","convert") | D54: =IF($B$6>$C$6*N53,"preference","convert") | E54: =IF($B$7>$C$7*N53,"preference","convert") | F54: =IF($B$8>$C$8*N53,"preference","convert") | G54: =IF($B$9>$C$9*N53,"preference","convert") | H54: =IF($B$10>$C$10*N53,"preference","convert") | I54: =IF(B54="preference",$B$4,0)+IF(C54="preference",$B$5,0)+IF(D54="preference",$B$6,0)+IF(E54="preference",$B$7,0)+IF(F54="preference",$B$8,0)+IF(G54="preference",$B$9,0)+IF(H54="preference",$B$10,0) | J54: =IF(B54="convert",$C$4,0)+IF(C54="convert",$C$5,0)+IF(D54="convert",$C$6,0)+IF(E54="convert",$C$7,0)+IF(F54="convert",$C$8,0)+IF(G54="convert",$C$9,0)+IF(H54="convert",$C$10,0) | K54: =(Assumptions!$B$46+Assumptions!$B$47+Assumptions!$B$48)+Assumptions!$B$49+('Pro-Forma'!$M$21+'Pro-Forma'!$M$22)+J54 | L54: =(C12-I54+Assumptions!$B$31*Assumptions!$B$10)/(K54+Assumptions!$B$31) | M54: =IF(L54>Assumptions!$B$10,"yes","no") | N54: =IF(M54="yes",L54,MAX(0,(C12-I54)/K54)) | O54: =IF(M54="yes",Assumptions!$B$31*(N54-Assumptions!$B$10),0)
A55: iter 2 | B55: =IF($B$4>$C$4*N54,"preference","convert") | C55: =IF($B$5>$C$5*N54,"preference","convert") | D55: =IF($B$6>$C$6*N54,"preference","convert") | E55: =IF($B$7>$C$7*N54,"preference","convert") | F55: =IF($B$8>$C$8*N54,"preference","convert") | G55: =IF($B$9>$C$9*N54,"preference","convert") | H55: =IF($B$10>$C$10*N54,"preference","convert") | I55: =IF(B55="preference",$B$4,0)+IF(C55="preference",$B$5,0)+IF(D55="preference",$B$6,0)+IF(E55="preference",$B$7,0)+IF(F55="preference",$B$8,0)+IF(G55="preference",$B$9,0)+IF(H55="preference",$B$10,0) | J55: =IF(B55="convert",$C$4,0)+IF(C55="convert",$C$5,0)+IF(D55="convert",$C$6,0)+IF(E55="convert",$C$7,0)+IF(F55="convert",$C$8,0)+IF(G55="convert",$C$9,0)+IF(H55="convert",$C$10,0) | K55: =(Assumptions!$B$46+Assumptions!$B$47+Assumptions!$B$48)+Assumptions!$B$49+('Pro-Forma'!$M$21+'Pro-Forma'!$M$22)+J55 | L55: =(C12-I55+Assumptions!$B$31*Assumptions!$B$10)/(K55+Assumptions!$B$31) | M55: =IF(L55>Assumptions!$B$10,"yes","no") | N55: =IF(M55="yes",L55,MAX(0,(C12-I55)/K55)) | O55: =IF(M55="yes",Assumptions!$B$31*(N55-Assumptions!$B$10),0)
A56: iter 3 | B56: =IF($B$4>$C$4*N55,"preference","convert") | C56: =IF($B$5>$C$5*N55,"preference","convert") | D56: =IF($B$6>$C$6*N55,"preference","convert") | E56: =IF($B$7>$C$7*N55,"preference","convert") | F56: =IF($B$8>$C$8*N55,"preference","convert") | G56: =IF($B$9>$C$9*N55,"preference","convert") | H56: =IF($B$10>$C$10*N55,"preference","convert") | I56: =IF(B56="preference",$B$4,0)+IF(C56="preference",$B$5,0)+IF(D56="preference",$B$6,0)+IF(E56="preference",$B$7,0)+IF(F56="preference",$B$8,0)+IF(G56="preference",$B$9,0)+IF(H56="preference",$B$10,0) | J56: =IF(B56="convert",$C$4,0)+IF(C56="convert",$C$5,0)+IF(D56="convert",$C$6,0)+IF(E56="convert",$C$7,0)+IF(F56="convert",$C$8,0)+IF(G56="convert",$C$9,0)+IF(H56="convert",$C$10,0) | K56: =(Assumptions!$B$46+Assumptions!$B$47+Assumptions!$B$48)+Assumptions!$B$49+('Pro-Forma'!$M$21+'Pro-Forma'!$M$22)+J56 | L56: =(C12-I56+Assumptions!$B$31*Assumptions!$B$10)/(K56+Assumptions!$B$31) | M56: =IF(L56>Assumptions!$B$10,"yes","no") | N56: =IF(M56="yes",L56,MAX(0,(C12-I56)/K56)) | O56: =IF(M56="yes",Assumptions!$B$31*(N56-Assumptions!$B$10),0)
A57: iter 4 | B57: =IF($B$4>$C$4*N56,"preference","convert") | C57: =IF($B$5>$C$5*N56,"preference","convert") | D57: =IF($B$6>$C$6*N56,"preference","convert") | E57: =IF($B$7>$C$7*N56,"preference","convert") | F57: =IF($B$8>$C$8*N56,"preference","convert") | G57: =IF($B$9>$C$9*N56,"preference","convert") | H57: =IF($B$10>$C$10*N56,"preference","convert") | I57: =IF(B57="preference",$B$4,0)+IF(C57="preference",$B$5,0)+IF(D57="preference",$B$6,0)+IF(E57="preference",$B$7,0)+IF(F57="preference",$B$8,0)+IF(G57="preference",$B$9,0)+IF(H57="preference",$B$10,0) | J57: =IF(B57="convert",$C$4,0)+IF(C57="convert",$C$5,0)+IF(D57="convert",$C$6,0)+IF(E57="convert",$C$7,0)+IF(F57="convert",$C$8,0)+IF(G57="convert",$C$9,0)+IF(H57="convert",$C$10,0) | K57: =(Assumptions!$B$46+Assumptions!$B$47+Assumptions!$B$48)+Assumptions!$B$49+('Pro-Forma'!$M$21+'Pro-Forma'!$M$22)+J57 | L57: =(C12-I57+Assumptions!$B$31*Assumptions!$B$10)/(K57+Assumptions!$B$31) | M57: =IF(L57>Assumptions!$B$10,"yes","no") | N57: =IF(M57="yes",L57,MAX(0,(C12-I57)/K57)) | O57: =IF(M57="yes",Assumptions!$B$31*(N57-Assumptions!$B$10),0)
A58: iter 5 | B58: =IF($B$4>$C$4*N57,"preference","convert") | C58: =IF($B$5>$C$5*N57,"preference","convert") | D58: =IF($B$6>$C$6*N57,"preference","convert") | E58: =IF($B$7>$C$7*N57,"preference","convert") | F58: =IF($B$8>$C$8*N57,"preference","convert") | G58: =IF($B$9>$C$9*N57,"preference","convert") | H58: =IF($B$10>$C$10*N57,"preference","convert") | I58: =IF(B58="preference",$B$4,0)+IF(C58="preference",$B$5,0)+IF(D58="preference",$B$6,0)+IF(E58="preference",$B$7,0)+IF(F58="preference",$B$8,0)+IF(G58="preference",$B$9,0)+IF(H58="preference",$B$10,0) | J58: =IF(B58="convert",$C$4,0)+IF(C58="convert",$C$5,0)+IF(D58="convert",$C$6,0)+IF(E58="convert",$C$7,0)+IF(F58="convert",$C$8,0)+IF(G58="convert",$C$9,0)+IF(H58="convert",$C$10,0) | K58: =(Assumptions!$B$46+Assumptions!$B$47+Assumptions!$B$48)+Assumptions!$B$49+('Pro-Forma'!$M$21+'Pro-Forma'!$M$22)+J58 | L58: =(C12-I58+Assumptions!$B$31*Assumptions!$B$10)/(K58+Assumptions!$B$31) | M58: =IF(L58>Assumptions!$B$10,"yes","no") | N58: =IF(M58="yes",L58,MAX(0,(C12-I58)/K58)) | O58: =IF(M58="yes",Assumptions!$B$31*(N58-Assumptions!$B$10),0)
A59: iter 6 | B59: =IF($B$4>$C$4*N58,"preference","convert") | C59: =IF($B$5>$C$5*N58,"preference","convert") | D59: =IF($B$6>$C$6*N58,"preference","convert") | E59: =IF($B$7>$C$7*N58,"preference","convert") | F59: =IF($B$8>$C$8*N58,"preference","convert") | G59: =IF($B$9>$C$9*N58,"preference","convert") | H59: =IF($B$10>$C$10*N58,"preference","convert") | I59: =IF(B59="preference",$B$4,0)+IF(C59="preference",$B$5,0)+IF(D59="preference",$B$6,0)+IF(E59="preference",$B$7,0)+IF(F59="preference",$B$8,0)+IF(G59="preference",$B$9,0)+IF(H59="preference",$B$10,0) | J59: =IF(B59="convert",$C$4,0)+IF(C59="convert",$C$5,0)+IF(D59="convert",$C$6,0)+IF(E59="convert",$C$7,0)+IF(F59="convert",$C$8,0)+IF(G59="convert",$C$9,0)+IF(H59="convert",$C$10,0) | K59: =(Assumptions!$B$46+Assumptions!$B$47+Assumptions!$B$48)+Assumptions!$B$49+('Pro-Forma'!$M$21+'Pro-Forma'!$M$22)+J59 | L59: =(C12-I59+Assumptions!$B$31*Assumptions!$B$10)/(K59+Assumptions!$B$31) | M59: =IF(L59>Assumptions!$B$10,"yes","no") | N59: =IF(M59="yes",L59,MAX(0,(C12-I59)/K59)) | O59: =IF(M59="yes",Assumptions!$B$31*(N59-Assumptions!$B$10),0)
A60: iter 7 | B60: =IF($B$4>$C$4*N59,"preference","convert") | C60: =IF($B$5>$C$5*N59,"preference","convert") | D60: =IF($B$6>$C$6*N59,"preference","convert") | E60: =IF($B$7>$C$7*N59,"preference","convert") | F60: =IF($B$8>$C$8*N59,"preference","convert") | G60: =IF($B$9>$C$9*N59,"preference","convert") | H60: =IF($B$10>$C$10*N59,"preference","convert") | I60: =IF(B60="preference",$B$4,0)+IF(C60="preference",$B$5,0)+IF(D60="preference",$B$6,0)+IF(E60="preference",$B$7,0)+IF(F60="preference",$B$8,0)+IF(G60="preference",$B$9,0)+IF(H60="preference",$B$10,0) | J60: =IF(B60="convert",$C$4,0)+IF(C60="convert",$C$5,0)+IF(D60="convert",$C$6,0)+IF(E60="convert",$C$7,0)+IF(F60="convert",$C$8,0)+IF(G60="convert",$C$9,0)+IF(H60="convert",$C$10,0) | K60: =(Assumptions!$B$46+Assumptions!$B$47+Assumptions!$B$48)+Assumptions!$B$49+('Pro-Forma'!$M$21+'Pro-Forma'!$M$22)+J60 | L60: =(C12-I60+Assumptions!$B$31*Assumptions!$B$10)/(K60+Assumptions!$B$31) | M60: =IF(L60>Assumptions!$B$10,"yes","no") | N60: =IF(M60="yes",L60,MAX(0,(C12-I60)/K60)) | O60: =IF(M60="yes",Assumptions!$B$31*(N60-Assumptions!$B$10),0)
A61: iter 8 | B61: =IF($B$4>$C$4*N60,"preference","convert") | C61: =IF($B$5>$C$5*N60,"preference","convert") | D61: =IF($B$6>$C$6*N60,"preference","convert") | E61: =IF($B$7>$C$7*N60,"preference","convert") | F61: =IF($B$8>$C$8*N60,"preference","convert") | G61: =IF($B$9>$C$9*N60,"preference","convert") | H61: =IF($B$10>$C$10*N60,"preference","convert") | I61: =IF(B61="preference",$B$4,0)+IF(C61="preference",$B$5,0)+IF(D61="preference",$B$6,0)+IF(E61="preference",$B$7,0)+IF(F61="preference",$B$8,0)+IF(G61="preference",$B$9,0)+IF(H61="preference",$B$10,0) | J61: =IF(B61="convert",$C$4,0)+IF(C61="convert",$C$5,0)+IF(D61="convert",$C$6,0)+IF(E61="convert",$C$7,0)+IF(F61="convert",$C$8,0)+IF(G61="convert",$C$9,0)+IF(H61="convert",$C$10,0) | K61: =(Assumptions!$B$46+Assumptions!$B$47+Assumptions!$B$48)+Assumptions!$B$49+('Pro-Forma'!$M$21+'Pro-Forma'!$M$22)+J61 | L61: =(C12-I61+Assumptions!$B$31*Assumptions!$B$10)/(K61+Assumptions!$B$31) | M61: =IF(L61>Assumptions!$B$10,"yes","no") | N61: =IF(M61="yes",L61,MAX(0,(C12-I61)/K61)) | O61: =IF(M61="yes",Assumptions!$B$31*(N61-Assumptions!$B$10),0)
A62: iter 9 | B62: =IF($B$4>$C$4*N61,"preference","convert") | C62: =IF($B$5>$C$5*N61,"preference","convert") | D62: =IF($B$6>$C$6*N61,"preference","convert") | E62: =IF($B$7>$C$7*N61,"preference","convert") | F62: =IF($B$8>$C$8*N61,"preference","convert") | G62: =IF($B$9>$C$9*N61,"preference","convert") | H62: =IF($B$10>$C$10*N61,"preference","convert") | I62: =IF(B62="preference",$B$4,0)+IF(C62="preference",$B$5,0)+IF(D62="preference",$B$6,0)+IF(E62="preference",$B$7,0)+IF(F62="preference",$B$8,0)+IF(G62="preference",$B$9,0)+IF(H62="preference",$B$10,0) | J62: =IF(B62="convert",$C$4,0)+IF(C62="convert",$C$5,0)+IF(D62="convert",$C$6,0)+IF(E62="convert",$C$7,0)+IF(F62="convert",$C$8,0)+IF(G62="convert",$C$9,0)+IF(H62="convert",$C$10,0) | K62: =(Assumptions!$B$46+Assumptions!$B$47+Assumptions!$B$48)+Assumptions!$B$49+('Pro-Forma'!$M$21+'Pro-Forma'!$M$22)+J62 | L62: =(C12-I62+Assumptions!$B$31*Assumptions!$B$10)/(K62+Assumptions!$B$31) | M62: =IF(L62>Assumptions!$B$10,"yes","no") | N62: =IF(M62="yes",L62,MAX(0,(C12-I62)/K62)) | O62: =IF(M62="yes",Assumptions!$B$31*(N62-Assumptions!$B$10),0)
A63: iter 10 | B63: =IF($B$4>$C$4*N62,"preference","convert") | C63: =IF($B$5>$C$5*N62,"preference","convert") | D63: =IF($B$6>$C$6*N62,"preference","convert") | E63: =IF($B$7>$C$7*N62,"preference","convert") | F63: =IF($B$8>$C$8*N62,"preference","convert") | G63: =IF($B$9>$C$9*N62,"preference","convert") | H63: =IF($B$10>$C$10*N62,"preference","convert") | I63: =IF(B63="preference",$B$4,0)+IF(C63="preference",$B$5,0)+IF(D63="preference",$B$6,0)+IF(E63="preference",$B$7,0)+IF(F63="preference",$B$8,0)+IF(G63="preference",$B$9,0)+IF(H63="preference",$B$10,0) | J63: =IF(B63="convert",$C$4,0)+IF(C63="convert",$C$5,0)+IF(D63="convert",$C$6,0)+IF(E63="convert",$C$7,0)+IF(F63="convert",$C$8,0)+IF(G63="convert",$C$9,0)+IF(H63="convert",$C$10,0) | K63: =(Assumptions!$B$46+Assumptions!$B$47+Assumptions!$B$48)+Assumptions!$B$49+('Pro-Forma'!$M$21+'Pro-Forma'!$M$22)+J63 | L63: =(C12-I63+Assumptions!$B$31*Assumptions!$B$10)/(K63+Assumptions!$B$31) | M63: =IF(L63>Assumptions!$B$10,"yes","no") | N63: =IF(M63="yes",L63,MAX(0,(C12-I63)/K63)) | O63: =IF(M63="yes",Assumptions!$B$31*(N63-Assumptions!$B$10),0)
A64: iter 11 | B64: =IF($B$4>$C$4*N63,"preference","convert") | C64: =IF($B$5>$C$5*N63,"preference","convert") | D64: =IF($B$6>$C$6*N63,"preference","convert") | E64: =IF($B$7>$C$7*N63,"preference","convert") | F64: =IF($B$8>$C$8*N63,"preference","convert") | G64: =IF($B$9>$C$9*N63,"preference","convert") | H64: =IF($B$10>$C$10*N63,"preference","convert") | I64: =IF(B64="preference",$B$4,0)+IF(C64="preference",$B$5,0)+IF(D64="preference",$B$6,0)+IF(E64="preference",$B$7,0)+IF(F64="preference",$B$8,0)+IF(G64="preference",$B$9,0)+IF(H64="preference",$B$10,0) | J64: =IF(B64="convert",$C$4,0)+IF(C64="convert",$C$5,0)+IF(D64="convert",$C$6,0)+IF(E64="convert",$C$7,0)+IF(F64="convert",$C$8,0)+IF(G64="convert",$C$9,0)+IF(H64="convert",$C$10,0) | K64: =(Assumptions!$B$46+Assumptions!$B$47+Assumptions!$B$48)+Assumptions!$B$49+('Pro-Forma'!$M$21+'Pro-Forma'!$M$22)+J64 | L64: =(C12-I64+Assumptions!$B$31*Assumptions!$B$10)/(K64+Assumptions!$B$31) | M64: =IF(L64>Assumptions!$B$10,"yes","no") | N64: =IF(M64="yes",L64,MAX(0,(C12-I64)/K64)) | O64: =IF(M64="yes",Assumptions!$B$31*(N64-Assumptions!$B$10),0)
A65: iter 12 | B65: =IF($B$4>$C$4*N64,"preference","convert") | C65: =IF($B$5>$C$5*N64,"preference","convert") | D65: =IF($B$6>$C$6*N64,"preference","convert") | E65: =IF($B$7>$C$7*N64,"preference","convert") | F65: =IF($B$8>$C$8*N64,"preference","convert") | G65: =IF($B$9>$C$9*N64,"preference","convert") | H65: =IF($B$10>$C$10*N64,"preference","convert") | I65: =IF(B65="preference",$B$4,0)+IF(C65="preference",$B$5,0)+IF(D65="preference",$B$6,0)+IF(E65="preference",$B$7,0)+IF(F65="preference",$B$8,0)+IF(G65="preference",$B$9,0)+IF(H65="preference",$B$10,0) | J65: =IF(B65="convert",$C$4,0)+IF(C65="convert",$C$5,0)+IF(D65="convert",$C$6,0)+IF(E65="convert",$C$7,0)+IF(F65="convert",$C$8,0)+IF(G65="convert",$C$9,0)+IF(H65="convert",$C$10,0) | K65: =(Assumptions!$B$46+Assumptions!$B$47+Assumptions!$B$48)+Assumptions!$B$49+('Pro-Forma'!$M$21+'Pro-Forma'!$M$22)+J65 | L65: =(C12-I65+Assumptions!$B$31*Assumptions!$B$10)/(K65+Assumptions!$B$31) | M65: =IF(L65>Assumptions!$B$10,"yes","no") | N65: =IF(M65="yes",L65,MAX(0,(C12-I65)/K65)) | O65: =IF(M65="yes",Assumptions!$B$31*(N65-Assumptions!$B$10),0)
A66: iter 13 | B66: =IF($B$4>$C$4*N65,"preference","convert") | C66: =IF($B$5>$C$5*N65,"preference","convert") | D66: =IF($B$6>$C$6*N65,"preference","convert") | E66: =IF($B$7>$C$7*N65,"preference","convert") | F66: =IF($B$8>$C$8*N65,"preference","convert") | G66: =IF($B$9>$C$9*N65,"preference","convert") | H66: =IF($B$10>$C$10*N65,"preference","convert") | I66: =IF(B66="preference",$B$4,0)+IF(C66="preference",$B$5,0)+IF(D66="preference",$B$6,0)+IF(E66="preference",$B$7,0)+IF(F66="preference",$B$8,0)+IF(G66="preference",$B$9,0)+IF(H66="preference",$B$10,0) | J66: =IF(B66="convert",$C$4,0)+IF(C66="convert",$C$5,0)+IF(D66="convert",$C$6,0)+IF(E66="convert",$C$7,0)+IF(F66="convert",$C$8,0)+IF(G66="convert",$C$9,0)+IF(H66="convert",$C$10,0) | K66: =(Assumptions!$B$46+Assumptions!$B$47+Assumptions!$B$48)+Assumptions!$B$49+('Pro-Forma'!$M$21+'Pro-Forma'!$M$22)+J66 | L66: =(C12-I66+Assumptions!$B$31*Assumptions!$B$10)/(K66+Assumptions!$B$31) | M66: =IF(L66>Assumptions!$B$10,"yes","no") | N66: =IF(M66="yes",L66,MAX(0,(C12-I66)/K66)) | O66: =IF(M66="yes",Assumptions!$B$31*(N66-Assumptions!$B$10),0)
A67: iter 14 | B67: =IF($B$4>$C$4*N66,"preference","convert") | C67: =IF($B$5>$C$5*N66,"preference","convert") | D67: =IF($B$6>$C$6*N66,"preference","convert") | E67: =IF($B$7>$C$7*N66,"preference","convert") | F67: =IF($B$8>$C$8*N66,"preference","convert") | G67: =IF($B$9>$C$9*N66,"preference","convert") | H67: =IF($B$10>$C$10*N66,"preference","convert") | I67: =IF(B67="preference",$B$4,0)+IF(C67="preference",$B$5,0)+IF(D67="preference",$B$6,0)+IF(E67="preference",$B$7,0)+IF(F67="preference",$B$8,0)+IF(G67="preference",$B$9,0)+IF(H67="preference",$B$10,0) | J67: =IF(B67="convert",$C$4,0)+IF(C67="convert",$C$5,0)+IF(D67="convert",$C$6,0)+IF(E67="convert",$C$7,0)+IF(F67="convert",$C$8,0)+IF(G67="convert",$C$9,0)+IF(H67="convert",$C$10,0) | K67: =(Assumptions!$B$46+Assumptions!$B$47+Assumptions!$B$48)+Assumptions!$B$49+('Pro-Forma'!$M$21+'Pro-Forma'!$M$22)+J67 | L67: =(C12-I67+Assumptions!$B$31*Assumptions!$B$10)/(K67+Assumptions!$B$31) | M67: =IF(L67>Assumptions!$B$10,"yes","no") | N67: =IF(M67="yes",L67,MAX(0,(C12-I67)/K67)) | O67: =IF(M67="yes",Assumptions!$B$31*(N67-Assumptions!$B$10),0)
A68: iter 15 | B68: =IF($B$4>$C$4*N67,"preference","convert") | C68: =IF($B$5>$C$5*N67,"preference","convert") | D68: =IF($B$6>$C$6*N67,"preference","convert") | E68: =IF($B$7>$C$7*N67,"preference","convert") | F68: =IF($B$8>$C$8*N67,"preference","convert") | G68: =IF($B$9>$C$9*N67,"preference","convert") | H68: =IF($B$10>$C$10*N67,"preference","convert") | I68: =IF(B68="preference",$B$4,0)+IF(C68="preference",$B$5,0)+IF(D68="preference",$B$6,0)+IF(E68="preference",$B$7,0)+IF(F68="preference",$B$8,0)+IF(G68="preference",$B$9,0)+IF(H68="preference",$B$10,0) | J68: =IF(B68="convert",$C$4,0)+IF(C68="convert",$C$5,0)+IF(D68="convert",$C$6,0)+IF(E68="convert",$C$7,0)+IF(F68="convert",$C$8,0)+IF(G68="convert",$C$9,0)+IF(H68="convert",$C$10,0) | K68: =(Assumptions!$B$46+Assumptions!$B$47+Assumptions!$B$48)+Assumptions!$B$49+('Pro-Forma'!$M$21+'Pro-Forma'!$M$22)+J68 | L68: =(C12-I68+Assumptions!$B$31*Assumptions!$B$10)/(K68+Assumptions!$B$31) | M68: =IF(L68>Assumptions!$B$10,"yes","no") | N68: =IF(M68="yes",L68,MAX(0,(C12-I68)/K68)) | O68: =IF(M68="yes",Assumptions!$B$31*(N68-Assumptions!$B$10),0)
A69: iter 16 | B69: =IF($B$4>$C$4*N68,"preference","convert") | C69: =IF($B$5>$C$5*N68,"preference","convert") | D69: =IF($B$6>$C$6*N68,"preference","convert") | E69: =IF($B$7>$C$7*N68,"preference","convert") | F69: =IF($B$8>$C$8*N68,"preference","convert") | G69: =IF($B$9>$C$9*N68,"preference","convert") | H69: =IF($B$10>$C$10*N68,"preference","convert") | I69: =IF(B69="preference",$B$4,0)+IF(C69="preference",$B$5,0)+IF(D69="preference",$B$6,0)+IF(E69="preference",$B$7,0)+IF(F69="preference",$B$8,0)+IF(G69="preference",$B$9,0)+IF(H69="preference",$B$10,0) | J69: =IF(B69="convert",$C$4,0)+IF(C69="convert",$C$5,0)+IF(D69="convert",$C$6,0)+IF(E69="convert",$C$7,0)+IF(F69="convert",$C$8,0)+IF(G69="convert",$C$9,0)+IF(H69="convert",$C$10,0) | K69: =(Assumptions!$B$46+Assumptions!$B$47+Assumptions!$B$48)+Assumptions!$B$49+('Pro-Forma'!$M$21+'Pro-Forma'!$M$22)+J69 | L69: =(C12-I69+Assumptions!$B$31*Assumptions!$B$10)/(K69+Assumptions!$B$31) | M69: =IF(L69>Assumptions!$B$10,"yes","no") | N69: =IF(M69="yes",L69,MAX(0,(C12-I69)/K69)) | O69: =IF(M69="yes",Assumptions!$B$31*(N69-Assumptions!$B$10),0)
A70: iter 17 | B70: =IF($B$4>$C$4*N69,"preference","convert") | C70: =IF($B$5>$C$5*N69,"preference","convert") | D70: =IF($B$6>$C$6*N69,"preference","convert") | E70: =IF($B$7>$C$7*N69,"preference","convert") | F70: =IF($B$8>$C$8*N69,"preference","convert") | G70: =IF($B$9>$C$9*N69,"preference","convert") | H70: =IF($B$10>$C$10*N69,"preference","convert") | I70: =IF(B70="preference",$B$4,0)+IF(C70="preference",$B$5,0)+IF(D70="preference",$B$6,0)+IF(E70="preference",$B$7,0)+IF(F70="preference",$B$8,0)+IF(G70="preference",$B$9,0)+IF(H70="preference",$B$10,0) | J70: =IF(B70="convert",$C$4,0)+IF(C70="convert",$C$5,0)+IF(D70="convert",$C$6,0)+IF(E70="convert",$C$7,0)+IF(F70="convert",$C$8,0)+IF(G70="convert",$C$9,0)+IF(H70="convert",$C$10,0) | K70: =(Assumptions!$B$46+Assumptions!$B$47+Assumptions!$B$48)+Assumptions!$B$49+('Pro-Forma'!$M$21+'Pro-Forma'!$M$22)+J70 | L70: =(C12-I70+Assumptions!$B$31*Assumptions!$B$10)/(K70+Assumptions!$B$31) | M70: =IF(L70>Assumptions!$B$10,"yes","no") | N70: =IF(M70="yes",L70,MAX(0,(C12-I70)/K70)) | O70: =IF(M70="yes",Assumptions!$B$31*(N70-Assumptions!$B$10),0)
A71: iter 18 | B71: =IF($B$4>$C$4*N70,"preference","convert") | C71: =IF($B$5>$C$5*N70,"preference","convert") | D71: =IF($B$6>$C$6*N70,"preference","convert") | E71: =IF($B$7>$C$7*N70,"preference","convert") | F71: =IF($B$8>$C$8*N70,"preference","convert") | G71: =IF($B$9>$C$9*N70,"preference","convert") | H71: =IF($B$10>$C$10*N70,"preference","convert") | I71: =IF(B71="preference",$B$4,0)+IF(C71="preference",$B$5,0)+IF(D71="preference",$B$6,0)+IF(E71="preference",$B$7,0)+IF(F71="preference",$B$8,0)+IF(G71="preference",$B$9,0)+IF(H71="preference",$B$10,0) | J71: =IF(B71="convert",$C$4,0)+IF(C71="convert",$C$5,0)+IF(D71="convert",$C$6,0)+IF(E71="convert",$C$7,0)+IF(F71="convert",$C$8,0)+IF(G71="convert",$C$9,0)+IF(H71="convert",$C$10,0) | K71: =(Assumptions!$B$46+Assumptions!$B$47+Assumptions!$B$48)+Assumptions!$B$49+('Pro-Forma'!$M$21+'Pro-Forma'!$M$22)+J71 | L71: =(C12-I71+Assumptions!$B$31*Assumptions!$B$10)/(K71+Assumptions!$B$31) | M71: =IF(L71>Assumptions!$B$10,"yes","no") | N71: =IF(M71="yes",L71,MAX(0,(C12-I71)/K71)) | O71: =IF(M71="yes",Assumptions!$B$31*(N71-Assumptions!$B$10),0)
A72: iter 19 | B72: =IF($B$4>$C$4*N71,"preference","convert") | C72: =IF($B$5>$C$5*N71,"preference","convert") | D72: =IF($B$6>$C$6*N71,"preference","convert") | E72: =IF($B$7>$C$7*N71,"preference","convert") | F72: =IF($B$8>$C$8*N71,"preference","convert") | G72: =IF($B$9>$C$9*N71,"preference","convert") | H72: =IF($B$10>$C$10*N71,"preference","convert") | I72: =IF(B72="preference",$B$4,0)+IF(C72="preference",$B$5,0)+IF(D72="preference",$B$6,0)+IF(E72="preference",$B$7,0)+IF(F72="preference",$B$8,0)+IF(G72="preference",$B$9,0)+IF(H72="preference",$B$10,0) | J72: =IF(B72="convert",$C$4,0)+IF(C72="convert",$C$5,0)+IF(D72="convert",$C$6,0)+IF(E72="convert",$C$7,0)+IF(F72="convert",$C$8,0)+IF(G72="convert",$C$9,0)+IF(H72="convert",$C$10,0) | K72: =(Assumptions!$B$46+Assumptions!$B$47+Assumptions!$B$48)+Assumptions!$B$49+('Pro-Forma'!$M$21+'Pro-Forma'!$M$22)+J72 | L72: =(C12-I72+Assumptions!$B$31*Assumptions!$B$10)/(K72+Assumptions!$B$31) | M72: =IF(L72>Assumptions!$B$10,"yes","no") | N72: =IF(M72="yes",L72,MAX(0,(C12-I72)/K72)) | O72: =IF(M72="yes",Assumptions!$B$31*(N72-Assumptions!$B$10),0)
A73: iter 20 | B73: =IF($B$4>$C$4*N72,"preference","convert") | C73: =IF($B$5>$C$5*N72,"preference","convert") | D73: =IF($B$6>$C$6*N72,"preference","convert") | E73: =IF($B$7>$C$7*N72,"preference","convert") | F73: =IF($B$8>$C$8*N72,"preference","convert") | G73: =IF($B$9>$C$9*N72,"preference","convert") | H73: =IF($B$10>$C$10*N72,"preference","convert") | I73: =IF(B73="preference",$B$4,0)+IF(C73="preference",$B$5,0)+IF(D73="preference",$B$6,0)+IF(E73="preference",$B$7,0)+IF(F73="preference",$B$8,0)+IF(G73="preference",$B$9,0)+IF(H73="preference",$B$10,0) | J73: =IF(B73="convert",$C$4,0)+IF(C73="convert",$C$5,0)+IF(D73="convert",$C$6,0)+IF(E73="convert",$C$7,0)+IF(F73="convert",$C$8,0)+IF(G73="convert",$C$9,0)+IF(H73="convert",$C$10,0) | K73: =(Assumptions!$B$46+Assumptions!$B$47+Assumptions!$B$48)+Assumptions!$B$49+('Pro-Forma'!$M$21+'Pro-Forma'!$M$22)+J73 | L73: =(C12-I73+Assumptions!$B$31*Assumptions!$B$10)/(K73+Assumptions!$B$31) | M73: =IF(L73>Assumptions!$B$10,"yes","no") | N73: =IF(M73="yes",L73,MAX(0,(C12-I73)/K73)) | O73: =IF(M73="yes",Assumptions!$B$31*(N73-Assumptions!$B$10),0)
A74: iter 21 | B74: =IF($B$4>$C$4*N73,"preference","convert") | C74: =IF($B$5>$C$5*N73,"preference","convert") | D74: =IF($B$6>$C$6*N73,"preference","convert") | E74: =IF($B$7>$C$7*N73,"preference","convert") | F74: =IF($B$8>$C$8*N73,"preference","convert") | G74: =IF($B$9>$C$9*N73,"preference","convert") | H74: =IF($B$10>$C$10*N73,"preference","convert") | I74: =IF(B74="preference",$B$4,0)+IF(C74="preference",$B$5,0)+IF(D74="preference",$B$6,0)+IF(E74="preference",$B$7,0)+IF(F74="preference",$B$8,0)+IF(G74="preference",$B$9,0)+IF(H74="preference",$B$10,0) | J74: =IF(B74="convert",$C$4,0)+IF(C74="convert",$C$5,0)+IF(D74="convert",$C$6,0)+IF(E74="convert",$C$7,0)+IF(F74="convert",$C$8,0)+IF(G74="convert",$C$9,0)+IF(H74="convert",$C$10,0) | K74: =(Assumptions!$B$46+Assumptions!$B$47+Assumptions!$B$48)+Assumptions!$B$49+('Pro-Forma'!$M$21+'Pro-Forma'!$M$22)+J74 | L74: =(C12-I74+Assumptions!$B$31*Assumptions!$B$10)/(K74+Assumptions!$B$31) | M74: =IF(L74>Assumptions!$B$10,"yes","no") | N74: =IF(M74="yes",L74,MAX(0,(C12-I74)/K74)) | O74: =IF(M74="yes",Assumptions!$B$31*(N74-Assumptions!$B$10),0)
A75: iter 22 | B75: =IF($B$4>$C$4*N74,"preference","convert") | C75: =IF($B$5>$C$5*N74,"preference","convert") | D75: =IF($B$6>$C$6*N74,"preference","convert") | E75: =IF($B$7>$C$7*N74,"preference","convert") | F75: =IF($B$8>$C$8*N74,"preference","convert") | G75: =IF($B$9>$C$9*N74,"preference","convert") | H75: =IF($B$10>$C$10*N74,"preference","convert") | I75: =IF(B75="preference",$B$4,0)+IF(C75="preference",$B$5,0)+IF(D75="preference",$B$6,0)+IF(E75="preference",$B$7,0)+IF(F75="preference",$B$8,0)+IF(G75="preference",$B$9,0)+IF(H75="preference",$B$10,0) | J75: =IF(B75="convert",$C$4,0)+IF(C75="convert",$C$5,0)+IF(D75="convert",$C$6,0)+IF(E75="convert",$C$7,0)+IF(F75="convert",$C$8,0)+IF(G75="convert",$C$9,0)+IF(H75="convert",$C$10,0) | K75: =(Assumptions!$B$46+Assumptions!$B$47+Assumptions!$B$48)+Assumptions!$B$49+('Pro-Forma'!$M$21+'Pro-Forma'!$M$22)+J75 | L75: =(C12-I75+Assumptions!$B$31*Assumptions!$B$10)/(K75+Assumptions!$B$31) | M75: =IF(L75>Assumptions!$B$10,"yes","no") | N75: =IF(M75="yes",L75,MAX(0,(C12-I75)/K75)) | O75: =IF(M75="yes",Assumptions!$B$31*(N75-Assumptions!$B$10),0)
A76: iter 23 | B76: =IF($B$4>$C$4*N75,"preference","convert") | C76: =IF($B$5>$C$5*N75,"preference","convert") | D76: =IF($B$6>$C$6*N75,"preference","convert") | E76: =IF($B$7>$C$7*N75,"preference","convert") | F76: =IF($B$8>$C$8*N75,"preference","convert") | G76: =IF($B$9>$C$9*N75,"preference","convert") | H76: =IF($B$10>$C$10*N75,"preference","convert") | I76: =IF(B76="preference",$B$4,0)+IF(C76="preference",$B$5,0)+IF(D76="preference",$B$6,0)+IF(E76="preference",$B$7,0)+IF(F76="preference",$B$8,0)+IF(G76="preference",$B$9,0)+IF(H76="preference",$B$10,0) | J76: =IF(B76="convert",$C$4,0)+IF(C76="convert",$C$5,0)+IF(D76="convert",$C$6,0)+IF(E76="convert",$C$7,0)+IF(F76="convert",$C$8,0)+IF(G76="convert",$C$9,0)+IF(H76="convert",$C$10,0) | K76: =(Assumptions!$B$46+Assumptions!$B$47+Assumptions!$B$48)+Assumptions!$B$49+('Pro-Forma'!$M$21+'Pro-Forma'!$M$22)+J76 | L76: =(C12-I76+Assumptions!$B$31*Assumptions!$B$10)/(K76+Assumptions!$B$31) | M76: =IF(L76>Assumptions!$B$10,"yes","no") | N76: =IF(M76="yes",L76,MAX(0,(C12-I76)/K76)) | O76: =IF(M76="yes",Assumptions!$B$31*(N76-Assumptions!$B$10),0)
A77: iter 24 | B77: =IF($B$4>$C$4*N76,"preference","convert") | C77: =IF($B$5>$C$5*N76,"preference","convert") | D77: =IF($B$6>$C$6*N76,"preference","convert") | E77: =IF($B$7>$C$7*N76,"preference","convert") | F77: =IF($B$8>$C$8*N76,"preference","convert") | G77: =IF($B$9>$C$9*N76,"preference","convert") | H77: =IF($B$10>$C$10*N76,"preference","convert") | I77: =IF(B77="preference",$B$4,0)+IF(C77="preference",$B$5,0)+IF(D77="preference",$B$6,0)+IF(E77="preference",$B$7,0)+IF(F77="preference",$B$8,0)+IF(G77="preference",$B$9,0)+IF(H77="preference",$B$10,0) | J77: =IF(B77="convert",$C$4,0)+IF(C77="convert",$C$5,0)+IF(D77="convert",$C$6,0)+IF(E77="convert",$C$7,0)+IF(F77="convert",$C$8,0)+IF(G77="convert",$C$9,0)+IF(H77="convert",$C$10,0) | K77: =(Assumptions!$B$46+Assumptions!$B$47+Assumptions!$B$48)+Assumptions!$B$49+('Pro-Forma'!$M$21+'Pro-Forma'!$M$22)+J77 | L77: =(C12-I77+Assumptions!$B$31*Assumptions!$B$10)/(K77+Assumptions!$B$31) | M77: =IF(L77>Assumptions!$B$10,"yes","no") | N77: =IF(M77="yes",L77,MAX(0,(C12-I77)/K77)) | O77: =IF(M77="yes",Assumptions!$B$31*(N77-Assumptions!$B$10),0)
A78: iter 25 | B78: =IF($B$4>$C$4*N77,"preference","convert") | C78: =IF($B$5>$C$5*N77,"preference","convert") | D78: =IF($B$6>$C$6*N77,"preference","convert") | E78: =IF($B$7>$C$7*N77,"preference","convert") | F78: =IF($B$8>$C$8*N77,"preference","convert") | G78: =IF($B$9>$C$9*N77,"preference","convert") | H78: =IF($B$10>$C$10*N77,"preference","convert") | I78: =IF(B78="preference",$B$4,0)+IF(C78="preference",$B$5,0)+IF(D78="preference",$B$6,0)+IF(E78="preference",$B$7,0)+IF(F78="preference",$B$8,0)+IF(G78="preference",$B$9,0)+IF(H78="preference",$B$10,0) | J78: =IF(B78="convert",$C$4,0)+IF(C78="convert",$C$5,0)+IF(D78="convert",$C$6,0)+IF(E78="convert",$C$7,0)+IF(F78="convert",$C$8,0)+IF(G78="convert",$C$9,0)+IF(H78="convert",$C$10,0) | K78: =(Assumptions!$B$46+Assumptions!$B$47+Assumptions!$B$48)+Assumptions!$B$49+('Pro-Forma'!$M$21+'Pro-Forma'!$M$22)+J78 | L78: =(C12-I78+Assumptions!$B$31*Assumptions!$B$10)/(K78+Assumptions!$B$31) | M78: =IF(L78>Assumptions!$B$10,"yes","no") | N78: =IF(M78="yes",L78,MAX(0,(C12-I78)/K78)) | O78: =IF(M78="yes",Assumptions!$B$31*(N78-Assumptions!$B$10),0)
A79: iter 26 | B79: =IF($B$4>$C$4*N78,"preference","convert") | C79: =IF($B$5>$C$5*N78,"preference","convert") | D79: =IF($B$6>$C$6*N78,"preference","convert") | E79: =IF($B$7>$C$7*N78,"preference","convert") | F79: =IF($B$8>$C$8*N78,"preference","convert") | G79: =IF($B$9>$C$9*N78,"preference","convert") | H79: =IF($B$10>$C$10*N78,"preference","convert") | I79: =IF(B79="preference",$B$4,0)+IF(C79="preference",$B$5,0)+IF(D79="preference",$B$6,0)+IF(E79="preference",$B$7,0)+IF(F79="preference",$B$8,0)+IF(G79="preference",$B$9,0)+IF(H79="preference",$B$10,0) | J79: =IF(B79="convert",$C$4,0)+IF(C79="convert",$C$5,0)+IF(D79="convert",$C$6,0)+IF(E79="convert",$C$7,0)+IF(F79="convert",$C$8,0)+IF(G79="convert",$C$9,0)+IF(H79="convert",$C$10,0) | K79: =(Assumptions!$B$46+Assumptions!$B$47+Assumptions!$B$48)+Assumptions!$B$49+('Pro-Forma'!$M$21+'Pro-Forma'!$M$22)+J79 | L79: =(C12-I79+Assumptions!$B$31*Assumptions!$B$10)/(K79+Assumptions!$B$31) | M79: =IF(L79>Assumptions!$B$10,"yes","no") | N79: =IF(M79="yes",L79,MAX(0,(C12-I79)/K79)) | O79: =IF(M79="yes",Assumptions!$B$31*(N79-Assumptions!$B$10),0)
A80: iter 27 | B80: =IF($B$4>$C$4*N79,"preference","convert") | C80: =IF($B$5>$C$5*N79,"preference","convert") | D80: =IF($B$6>$C$6*N79,"preference","convert") | E80: =IF($B$7>$C$7*N79,"preference","convert") | F80: =IF($B$8>$C$8*N79,"preference","convert") | G80: =IF($B$9>$C$9*N79,"preference","convert") | H80: =IF($B$10>$C$10*N79,"preference","convert") | I80: =IF(B80="preference",$B$4,0)+IF(C80="preference",$B$5,0)+IF(D80="preference",$B$6,0)+IF(E80="preference",$B$7,0)+IF(F80="preference",$B$8,0)+IF(G80="preference",$B$9,0)+IF(H80="preference",$B$10,0) | J80: =IF(B80="convert",$C$4,0)+IF(C80="convert",$C$5,0)+IF(D80="convert",$C$6,0)+IF(E80="convert",$C$7,0)+IF(F80="convert",$C$8,0)+IF(G80="convert",$C$9,0)+IF(H80="convert",$C$10,0) | K80: =(Assumptions!$B$46+Assumptions!$B$47+Assumptions!$B$48)+Assumptions!$B$49+('Pro-Forma'!$M$21+'Pro-Forma'!$M$22)+J80 | L80: =(C12-I80+Assumptions!$B$31*Assumptions!$B$10)/(K80+Assumptions!$B$31) | M80: =IF(L80>Assumptions!$B$10,"yes","no") | N80: =IF(M80="yes",L80,MAX(0,(C12-I80)/K80)) | O80: =IF(M80="yes",Assumptions!$B$31*(N80-Assumptions!$B$10),0)
A81: iter 28 | B81: =IF($B$4>$C$4*N80,"preference","convert") | C81: =IF($B$5>$C$5*N80,"preference","convert") | D81: =IF($B$6>$C$6*N80,"preference","convert") | E81: =IF($B$7>$C$7*N80,"preference","convert") | F81: =IF($B$8>$C$8*N80,"preference","convert") | G81: =IF($B$9>$C$9*N80,"preference","convert") | H81: =IF($B$10>$C$10*N80,"preference","convert") | I81: =IF(B81="preference",$B$4,0)+IF(C81="preference",$B$5,0)+IF(D81="preference",$B$6,0)+IF(E81="preference",$B$7,0)+IF(F81="preference",$B$8,0)+IF(G81="preference",$B$9,0)+IF(H81="preference",$B$10,0) | J81: =IF(B81="convert",$C$4,0)+IF(C81="convert",$C$5,0)+IF(D81="convert",$C$6,0)+IF(E81="convert",$C$7,0)+IF(F81="convert",$C$8,0)+IF(G81="convert",$C$9,0)+IF(H81="convert",$C$10,0) | K81: =(Assumptions!$B$46+Assumptions!$B$47+Assumptions!$B$48)+Assumptions!$B$49+('Pro-Forma'!$M$21+'Pro-Forma'!$M$22)+J81 | L81: =(C12-I81+Assumptions!$B$31*Assumptions!$B$10)/(K81+Assumptions!$B$31) | M81: =IF(L81>Assumptions!$B$10,"yes","no") | N81: =IF(M81="yes",L81,MAX(0,(C12-I81)/K81)) | O81: =IF(M81="yes",Assumptions!$B$31*(N81-Assumptions!$B$10),0)
A82: iter 29 | B82: =IF($B$4>$C$4*N81,"preference","convert") | C82: =IF($B$5>$C$5*N81,"preference","convert") | D82: =IF($B$6>$C$6*N81,"preference","convert") | E82: =IF($B$7>$C$7*N81,"preference","convert") | F82: =IF($B$8>$C$8*N81,"preference","convert") | G82: =IF($B$9>$C$9*N81,"preference","convert") | H82: =IF($B$10>$C$10*N81,"preference","convert") | I82: =IF(B82="preference",$B$4,0)+IF(C82="preference",$B$5,0)+IF(D82="preference",$B$6,0)+IF(E82="preference",$B$7,0)+IF(F82="preference",$B$8,0)+IF(G82="preference",$B$9,0)+IF(H82="preference",$B$10,0) | J82: =IF(B82="convert",$C$4,0)+IF(C82="convert",$C$5,0)+IF(D82="convert",$C$6,0)+IF(E82="convert",$C$7,0)+IF(F82="convert",$C$8,0)+IF(G82="convert",$C$9,0)+IF(H82="convert",$C$10,0) | K82: =(Assumptions!$B$46+Assumptions!$B$47+Assumptions!$B$48)+Assumptions!$B$49+('Pro-Forma'!$M$21+'Pro-Forma'!$M$22)+J82 | L82: =(C12-I82+Assumptions!$B$31*Assumptions!$B$10)/(K82+Assumptions!$B$31) | M82: =IF(L82>Assumptions!$B$10,"yes","no") | N82: =IF(M82="yes",L82,MAX(0,(C12-I82)/K82)) | O82: =IF(M82="yes",Assumptions!$B$31*(N82-Assumptions!$B$10),0)
A83: iter 30 | B83: =IF($B$4>$C$4*N82,"preference","convert") | C83: =IF($B$5>$C$5*N82,"preference","convert") | D83: =IF($B$6>$C$6*N82,"preference","convert") | E83: =IF($B$7>$C$7*N82,"preference","convert") | F83: =IF($B$8>$C$8*N82,"preference","convert") | G83: =IF($B$9>$C$9*N82,"preference","convert") | H83: =IF($B$10>$C$10*N82,"preference","convert") | I83: =IF(B83="preference",$B$4,0)+IF(C83="preference",$B$5,0)+IF(D83="preference",$B$6,0)+IF(E83="preference",$B$7,0)+IF(F83="preference",$B$8,0)+IF(G83="preference",$B$9,0)+IF(H83="preference",$B$10,0) | J83: =IF(B83="convert",$C$4,0)+IF(C83="convert",$C$5,0)+IF(D83="convert",$C$6,0)+IF(E83="convert",$C$7,0)+IF(F83="convert",$C$8,0)+IF(G83="convert",$C$9,0)+IF(H83="convert",$C$10,0) | K83: =(Assumptions!$B$46+Assumptions!$B$47+Assumptions!$B$48)+Assumptions!$B$49+('Pro-Forma'!$M$21+'Pro-Forma'!$M$22)+J83 | L83: =(C12-I83+Assumptions!$B$31*Assumptions!$B$10)/(K83+Assumptions!$B$31) | M83: =IF(L83>Assumptions!$B$10,"yes","no") | N83: =IF(M83="yes",L83,MAX(0,(C12-I83)/K83)) | O83: =IF(M83="yes",Assumptions!$B$31*(N83-Assumptions!$B$10),0)
A86: Exit 3 iteration ladder
A87: Step | B87: F_el | C87: E_el | D87: D_el | E87: C_el | F87: B_el | G87: A_el | H87: Seed_el | I87: prefs | J87: conv_sh | K87: cpool | L87: ITM_PPS | M87: ITM? | N87: common_PPS | O87: opt_proc
A88: seed (all convert) | B88: ="convert" | C88: ="convert" | D88: ="convert" | E88: ="convert" | F88: ="convert" | G88: ="convert" | H88: ="convert" | I88: =IF(B88="preference",$B$4,0)+IF(C88="preference",$B$5,0)+IF(D88="preference",$B$6,0)+IF(E88="preference",$B$7,0)+IF(F88="preference",$B$8,0)+IF(G88="preference",$B$9,0)+IF(H88="preference",$B$10,0) | J88: =IF(B88="convert",$C$4,0)+IF(C88="convert",$C$5,0)+IF(D88="convert",$C$6,0)+IF(E88="convert",$C$7,0)+IF(F88="convert",$C$8,0)+IF(G88="convert",$C$9,0)+IF(H88="convert",$C$10,0) | K88: =(Assumptions!$B$46+Assumptions!$B$47+Assumptions!$B$48)+Assumptions!$B$49+('Pro-Forma'!$M$21+'Pro-Forma'!$M$22)+J88 | L88: =(D12-I88+Assumptions!$B$31*Assumptions!$B$10)/(K88+Assumptions!$B$31) | M88: =IF(L88>Assumptions!$B$10,"yes","no") | N88: =IF(M88="yes",L88,MAX(0,(D12-I88)/K88)) | O88: =IF(M88="yes",Assumptions!$B$31*(N88-Assumptions!$B$10),0)
A89: iter 1 | B89: =IF($B$4>$C$4*N88,"preference","convert") | C89: =IF($B$5>$C$5*N88,"preference","convert") | D89: =IF($B$6>$C$6*N88,"preference","convert") | E89: =IF($B$7>$C$7*N88,"preference","convert") | F89: =IF($B$8>$C$8*N88,"preference","convert") | G89: =IF($B$9>$C$9*N88,"preference","convert") | H89: =IF($B$10>$C$10*N88,"preference","convert") | I89: =IF(B89="preference",$B$4,0)+IF(C89="preference",$B$5,0)+IF(D89="preference",$B$6,0)+IF(E89="preference",$B$7,0)+IF(F89="preference",$B$8,0)+IF(G89="preference",$B$9,0)+IF(H89="preference",$B$10,0) | J89: =IF(B89="convert",$C$4,0)+IF(C89="convert",$C$5,0)+IF(D89="convert",$C$6,0)+IF(E89="convert",$C$7,0)+IF(F89="convert",$C$8,0)+IF(G89="convert",$C$9,0)+IF(H89="convert",$C$10,0) | K89: =(Assumptions!$B$46+Assumptions!$B$47+Assumptions!$B$48)+Assumptions!$B$49+('Pro-Forma'!$M$21+'Pro-Forma'!$M$22)+J89 | L89: =(D12-I89+Assumptions!$B$31*Assumptions!$B$10)/(K89+Assumptions!$B$31) | M89: =IF(L89>Assumptions!$B$10,"yes","no") | N89: =IF(M89="yes",L89,MAX(0,(D12-I89)/K89)) | O89: =IF(M89="yes",Assumptions!$B$31*(N89-Assumptions!$B$10),0)
A90: iter 2 | B90: =IF($B$4>$C$4*N89,"preference","convert") | C90: =IF($B$5>$C$5*N89,"preference","convert") | D90: =IF($B$6>$C$6*N89,"preference","convert") | E90: =IF($B$7>$C$7*N89,"preference","convert") | F90: =IF($B$8>$C$8*N89,"preference","convert") | G90: =IF($B$9>$C$9*N89,"preference","convert") | H90: =IF($B$10>$C$10*N89,"preference","convert") | I90: =IF(B90="preference",$B$4,0)+IF(C90="preference",$B$5,0)+IF(D90="preference",$B$6,0)+IF(E90="preference",$B$7,0)+IF(F90="preference",$B$8,0)+IF(G90="preference",$B$9,0)+IF(H90="preference",$B$10,0) | J90: =IF(B90="convert",$C$4,0)+IF(C90="convert",$C$5,0)+IF(D90="convert",$C$6,0)+IF(E90="convert",$C$7,0)+IF(F90="convert",$C$8,0)+IF(G90="convert",$C$9,0)+IF(H90="convert",$C$10,0) | K90: =(Assumptions!$B$46+Assumptions!$B$47+Assumptions!$B$48)+Assumptions!$B$49+('Pro-Forma'!$M$21+'Pro-Forma'!$M$22)+J90 | L90: =(D12-I90+Assumptions!$B$31*Assumptions!$B$10)/(K90+Assumptions!$B$31) | M90: =IF(L90>Assumptions!$B$10,"yes","no") | N90: =IF(M90="yes",L90,MAX(0,(D12-I90)/K90)) | O90: =IF(M90="yes",Assumptions!$B$31*(N90-Assumptions!$B$10),0)
A91: iter 3 | B91: =IF($B$4>$C$4*N90,"preference","convert") | C91: =IF($B$5>$C$5*N90,"preference","convert") | D91: =IF($B$6>$C$6*N90,"preference","convert") | E91: =IF($B$7>$C$7*N90,"preference","convert") | F91: =IF($B$8>$C$8*N90,"preference","convert") | G91: =IF($B$9>$C$9*N90,"preference","convert") | H91: =IF($B$10>$C$10*N90,"preference","convert") | I91: =IF(B91="preference",$B$4,0)+IF(C91="preference",$B$5,0)+IF(D91="preference",$B$6,0)+IF(E91="preference",$B$7,0)+IF(F91="preference",$B$8,0)+IF(G91="preference",$B$9,0)+IF(H91="preference",$B$10,0) | J91: =IF(B91="convert",$C$4,0)+IF(C91="convert",$C$5,0)+IF(D91="convert",$C$6,0)+IF(E91="convert",$C$7,0)+IF(F91="convert",$C$8,0)+IF(G91="convert",$C$9,0)+IF(H91="convert",$C$10,0) | K91: =(Assumptions!$B$46+Assumptions!$B$47+Assumptions!$B$48)+Assumptions!$B$49+('Pro-Forma'!$M$21+'Pro-Forma'!$M$22)+J91 | L91: =(D12-I91+Assumptions!$B$31*Assumptions!$B$10)/(K91+Assumptions!$B$31) | M91: =IF(L91>Assumptions!$B$10,"yes","no") | N91: =IF(M91="yes",L91,MAX(0,(D12-I91)/K91)) | O91: =IF(M91="yes",Assumptions!$B$31*(N91-Assumptions!$B$10),0)
A92: iter 4 | B92: =IF($B$4>$C$4*N91,"preference","convert") | C92: =IF($B$5>$C$5*N91,"preference","convert") | D92: =IF($B$6>$C$6*N91,"preference","convert") | E92: =IF($B$7>$C$7*N91,"preference","convert") | F92: =IF($B$8>$C$8*N91,"preference","convert") | G92: =IF($B$9>$C$9*N91,"preference","convert") | H92: =IF($B$10>$C$10*N91,"preference","convert") | I92: =IF(B92="preference",$B$4,0)+IF(C92="preference",$B$5,0)+IF(D92="preference",$B$6,0)+IF(E92="preference",$B$7,0)+IF(F92="preference",$B$8,0)+IF(G92="preference",$B$9,0)+IF(H92="preference",$B$10,0) | J92: =IF(B92="convert",$C$4,0)+IF(C92="convert",$C$5,0)+IF(D92="convert",$C$6,0)+IF(E92="convert",$C$7,0)+IF(F92="convert",$C$8,0)+IF(G92="convert",$C$9,0)+IF(H92="convert",$C$10,0) | K92: =(Assumptions!$B$46+Assumptions!$B$47+Assumptions!$B$48)+Assumptions!$B$49+('Pro-Forma'!$M$21+'Pro-Forma'!$M$22)+J92 | L92: =(D12-I92+Assumptions!$B$31*Assumptions!$B$10)/(K92+Assumptions!$B$31) | M92: =IF(L92>Assumptions!$B$10,"yes","no") | N92: =IF(M92="yes",L92,MAX(0,(D12-I92)/K92)) | O92: =IF(M92="yes",Assumptions!$B$31*(N92-Assumptions!$B$10),0)
A93: iter 5 | B93: =IF($B$4>$C$4*N92,"preference","convert") | C93: =IF($B$5>$C$5*N92,"preference","convert") | D93: =IF($B$6>$C$6*N92,"preference","convert") | E93: =IF($B$7>$C$7*N92,"preference","convert") | F93: =IF($B$8>$C$8*N92,"preference","convert") | G93: =IF($B$9>$C$9*N92,"preference","convert") | H93: =IF($B$10>$C$10*N92,"preference","convert") | I93: =IF(B93="preference",$B$4,0)+IF(C93="preference",$B$5,0)+IF(D93="preference",$B$6,0)+IF(E93="preference",$B$7,0)+IF(F93="preference",$B$8,0)+IF(G93="preference",$B$9,0)+IF(H93="preference",$B$10,0) | J93: =IF(B93="convert",$C$4,0)+IF(C93="convert",$C$5,0)+IF(D93="convert",$C$6,0)+IF(E93="convert",$C$7,0)+IF(F93="convert",$C$8,0)+IF(G93="convert",$C$9,0)+IF(H93="convert",$C$10,0) | K93: =(Assumptions!$B$46+Assumptions!$B$47+Assumptions!$B$48)+Assumptions!$B$49+('Pro-Forma'!$M$21+'Pro-Forma'!$M$22)+J93 | L93: =(D12-I93+Assumptions!$B$31*Assumptions!$B$10)/(K93+Assumptions!$B$31) | M93: =IF(L93>Assumptions!$B$10,"yes","no") | N93: =IF(M93="yes",L93,MAX(0,(D12-I93)/K93)) | O93: =IF(M93="yes",Assumptions!$B$31*(N93-Assumptions!$B$10),0)
A94: iter 6 | B94: =IF($B$4>$C$4*N93,"preference","convert") | C94: =IF($B$5>$C$5*N93,"preference","convert") | D94: =IF($B$6>$C$6*N93,"preference","convert") | E94: =IF($B$7>$C$7*N93,"preference","convert") | F94: =IF($B$8>$C$8*N93,"preference","convert") | G94: =IF($B$9>$C$9*N93,"preference","convert") | H94: =IF($B$10>$C$10*N93,"preference","convert") | I94: =IF(B94="preference",$B$4,0)+IF(C94="preference",$B$5,0)+IF(D94="preference",$B$6,0)+IF(E94="preference",$B$7,0)+IF(F94="preference",$B$8,0)+IF(G94="preference",$B$9,0)+IF(H94="preference",$B$10,0) | J94: =IF(B94="convert",$C$4,0)+IF(C94="convert",$C$5,0)+IF(D94="convert",$C$6,0)+IF(E94="convert",$C$7,0)+IF(F94="convert",$C$8,0)+IF(G94="convert",$C$9,0)+IF(H94="convert",$C$10,0) | K94: =(Assumptions!$B$46+Assumptions!$B$47+Assumptions!$B$48)+Assumptions!$B$49+('Pro-Forma'!$M$21+'Pro-Forma'!$M$22)+J94 | L94: =(D12-I94+Assumptions!$B$31*Assumptions!$B$10)/(K94+Assumptions!$B$31) | M94: =IF(L94>Assumptions!$B$10,"yes","no") | N94: =IF(M94="yes",L94,MAX(0,(D12-I94)/K94)) | O94: =IF(M94="yes",Assumptions!$B$31*(N94-Assumptions!$B$10),0)
A95: iter 7 | B95: =IF($B$4>$C$4*N94,"preference","convert") | C95: =IF($B$5>$C$5*N94,"preference","convert") | D95: =IF($B$6>$C$6*N94,"preference","convert") | E95: =IF($B$7>$C$7*N94,"preference","convert") | F95: =IF($B$8>$C$8*N94,"preference","convert") | G95: =IF($B$9>$C$9*N94,"preference","convert") | H95: =IF($B$10>$C$10*N94,"preference","convert") | I95: =IF(B95="preference",$B$4,0)+IF(C95="preference",$B$5,0)+IF(D95="preference",$B$6,0)+IF(E95="preference",$B$7,0)+IF(F95="preference",$B$8,0)+IF(G95="preference",$B$9,0)+IF(H95="preference",$B$10,0) | J95: =IF(B95="convert",$C$4,0)+IF(C95="convert",$C$5,0)+IF(D95="convert",$C$6,0)+IF(E95="convert",$C$7,0)+IF(F95="convert",$C$8,0)+IF(G95="convert",$C$9,0)+IF(H95="convert",$C$10,0) | K95: =(Assumptions!$B$46+Assumptions!$B$47+Assumptions!$B$48)+Assumptions!$B$49+('Pro-Forma'!$M$21+'Pro-Forma'!$M$22)+J95 | L95: =(D12-I95+Assumptions!$B$31*Assumptions!$B$10)/(K95+Assumptions!$B$31) | M95: =IF(L95>Assumptions!$B$10,"yes","no") | N95: =IF(M95="yes",L95,MAX(0,(D12-I95)/K95)) | O95: =IF(M95="yes",Assumptions!$B$31*(N95-Assumptions!$B$10),0)
A96: iter 8 | B96: =IF($B$4>$C$4*N95,"preference","convert") | C96: =IF($B$5>$C$5*N95,"preference","convert") | D96: =IF($B$6>$C$6*N95,"preference","convert") | E96: =IF($B$7>$C$7*N95,"preference","convert") | F96: =IF($B$8>$C$8*N95,"preference","convert") | G96: =IF($B$9>$C$9*N95,"preference","convert") | H96: =IF($B$10>$C$10*N95,"preference","convert") | I96: =IF(B96="preference",$B$4,0)+IF(C96="preference",$B$5,0)+IF(D96="preference",$B$6,0)+IF(E96="preference",$B$7,0)+IF(F96="preference",$B$8,0)+IF(G96="preference",$B$9,0)+IF(H96="preference",$B$10,0) | J96: =IF(B96="convert",$C$4,0)+IF(C96="convert",$C$5,0)+IF(D96="convert",$C$6,0)+IF(E96="convert",$C$7,0)+IF(F96="convert",$C$8,0)+IF(G96="convert",$C$9,0)+IF(H96="convert",$C$10,0) | K96: =(Assumptions!$B$46+Assumptions!$B$47+Assumptions!$B$48)+Assumptions!$B$49+('Pro-Forma'!$M$21+'Pro-Forma'!$M$22)+J96 | L96: =(D12-I96+Assumptions!$B$31*Assumptions!$B$10)/(K96+Assumptions!$B$31) | M96: =IF(L96>Assumptions!$B$10,"yes","no") | N96: =IF(M96="yes",L96,MAX(0,(D12-I96)/K96)) | O96: =IF(M96="yes",Assumptions!$B$31*(N96-Assumptions!$B$10),0)
A97: iter 9 | B97: =IF($B$4>$C$4*N96,"preference","convert") | C97: =IF($B$5>$C$5*N96,"preference","convert") | D97: =IF($B$6>$C$6*N96,"preference","convert") | E97: =IF($B$7>$C$7*N96,"preference","convert") | F97: =IF($B$8>$C$8*N96,"preference","convert") | G97: =IF($B$9>$C$9*N96,"preference","convert") | H97: =IF($B$10>$C$10*N96,"preference","convert") | I97: =IF(B97="preference",$B$4,0)+IF(C97="preference",$B$5,0)+IF(D97="preference",$B$6,0)+IF(E97="preference",$B$7,0)+IF(F97="preference",$B$8,0)+IF(G97="preference",$B$9,0)+IF(H97="preference",$B$10,0) | J97: =IF(B97="convert",$C$4,0)+IF(C97="convert",$C$5,0)+IF(D97="convert",$C$6,0)+IF(E97="convert",$C$7,0)+IF(F97="convert",$C$8,0)+IF(G97="convert",$C$9,0)+IF(H97="convert",$C$10,0) | K97: =(Assumptions!$B$46+Assumptions!$B$47+Assumptions!$B$48)+Assumptions!$B$49+('Pro-Forma'!$M$21+'Pro-Forma'!$M$22)+J97 | L97: =(D12-I97+Assumptions!$B$31*Assumptions!$B$10)/(K97+Assumptions!$B$31) | M97: =IF(L97>Assumptions!$B$10,"yes","no") | N97: =IF(M97="yes",L97,MAX(0,(D12-I97)/K97)) | O97: =IF(M97="yes",Assumptions!$B$31*(N97-Assumptions!$B$10),0)
A98: iter 10 | B98: =IF($B$4>$C$4*N97,"preference","convert") | C98: =IF($B$5>$C$5*N97,"preference","convert") | D98: =IF($B$6>$C$6*N97,"preference","convert") | E98: =IF($B$7>$C$7*N97,"preference","convert") | F98: =IF($B$8>$C$8*N97,"preference","convert") | G98: =IF($B$9>$C$9*N97,"preference","convert") | H98: =IF($B$10>$C$10*N97,"preference","convert") | I98: =IF(B98="preference",$B$4,0)+IF(C98="preference",$B$5,0)+IF(D98="preference",$B$6,0)+IF(E98="preference",$B$7,0)+IF(F98="preference",$B$8,0)+IF(G98="preference",$B$9,0)+IF(H98="preference",$B$10,0) | J98: =IF(B98="convert",$C$4,0)+IF(C98="convert",$C$5,0)+IF(D98="convert",$C$6,0)+IF(E98="convert",$C$7,0)+IF(F98="convert",$C$8,0)+IF(G98="convert",$C$9,0)+IF(H98="convert",$C$10,0) | K98: =(Assumptions!$B$46+Assumptions!$B$47+Assumptions!$B$48)+Assumptions!$B$49+('Pro-Forma'!$M$21+'Pro-Forma'!$M$22)+J98 | L98: =(D12-I98+Assumptions!$B$31*Assumptions!$B$10)/(K98+Assumptions!$B$31) | M98: =IF(L98>Assumptions!$B$10,"yes","no") | N98: =IF(M98="yes",L98,MAX(0,(D12-I98)/K98)) | O98: =IF(M98="yes",Assumptions!$B$31*(N98-Assumptions!$B$10),0)
A99: iter 11 | B99: =IF($B$4>$C$4*N98,"preference","convert") | C99: =IF($B$5>$C$5*N98,"preference","convert") | D99: =IF($B$6>$C$6*N98,"preference","convert") | E99: =IF($B$7>$C$7*N98,"preference","convert") | F99: =IF($B$8>$C$8*N98,"preference","convert") | G99: =IF($B$9>$C$9*N98,"preference","convert") | H99: =IF($B$10>$C$10*N98,"preference","convert") | I99: =IF(B99="preference",$B$4,0)+IF(C99="preference",$B$5,0)+IF(D99="preference",$B$6,0)+IF(E99="preference",$B$7,0)+IF(F99="preference",$B$8,0)+IF(G99="preference",$B$9,0)+IF(H99="preference",$B$10,0) | J99: =IF(B99="convert",$C$4,0)+IF(C99="convert",$C$5,0)+IF(D99="convert",$C$6,0)+IF(E99="convert",$C$7,0)+IF(F99="convert",$C$8,0)+IF(G99="convert",$C$9,0)+IF(H99="convert",$C$10,0) | K99: =(Assumptions!$B$46+Assumptions!$B$47+Assumptions!$B$48)+Assumptions!$B$49+('Pro-Forma'!$M$21+'Pro-Forma'!$M$22)+J99 | L99: =(D12-I99+Assumptions!$B$31*Assumptions!$B$10)/(K99+Assumptions!$B$31) | M99: =IF(L99>Assumptions!$B$10,"yes","no") | N99: =IF(M99="yes",L99,MAX(0,(D12-I99)/K99)) | O99: =IF(M99="yes",Assumptions!$B$31*(N99-Assumptions!$B$10),0)
A100: iter 12 | B100: =IF($B$4>$C$4*N99,"preference","convert") | C100: =IF($B$5>$C$5*N99,"preference","convert") | D100: =IF($B$6>$C$6*N99,"preference","convert") | E100: =IF($B$7>$C$7*N99,"preference","convert") | F100: =IF($B$8>$C$8*N99,"preference","convert") | G100: =IF($B$9>$C$9*N99,"preference","convert") | H100: =IF($B$10>$C$10*N99,"preference","convert") | I100: =IF(B100="preference",$B$4,0)+IF(C100="preference",$B$5,0)+IF(D100="preference",$B$6,0)+IF(E100="preference",$B$7,0)+IF(F100="preference",$B$8,0)+IF(G100="preference",$B$9,0)+IF(H100="preference",$B$10,0) | J100: =IF(B100="convert",$C$4,0)+IF(C100="convert",$C$5,0)+IF(D100="convert",$C$6,0)+IF(E100="convert",$C$7,0)+IF(F100="convert",$C$8,0)+IF(G100="convert",$C$9,0)+IF(H100="convert",$C$10,0) | K100: =(Assumptions!$B$46+Assumptions!$B$47+Assumptions!$B$48)+Assumptions!$B$49+('Pro-Forma'!$M$21+'Pro-Forma'!$M$22)+J100 | L100: =(D12-I100+Assumptions!$B$31*Assumptions!$B$10)/(K100+Assumptions!$B$31) | M100: =IF(L100>Assumptions!$B$10,"yes","no") | N100: =IF(M100="yes",L100,MAX(0,(D12-I100)/K100)) | O100: =IF(M100="yes",Assumptions!$B$31*(N100-Assumptions!$B$10),0)
A101: iter 13 | B101: =IF($B$4>$C$4*N100,"preference","convert") | C101: =IF($B$5>$C$5*N100,"preference","convert") | D101: =IF($B$6>$C$6*N100,"preference","convert") | E101: =IF($B$7>$C$7*N100,"preference","convert") | F101: =IF($B$8>$C$8*N100,"preference","convert") | G101: =IF($B$9>$C$9*N100,"preference","convert") | H101: =IF($B$10>$C$10*N100,"preference","convert") | I101: =IF(B101="preference",$B$4,0)+IF(C101="preference",$B$5,0)+IF(D101="preference",$B$6,0)+IF(E101="preference",$B$7,0)+IF(F101="preference",$B$8,0)+IF(G101="preference",$B$9,0)+IF(H101="preference",$B$10,0) | J101: =IF(B101="convert",$C$4,0)+IF(C101="convert",$C$5,0)+IF(D101="convert",$C$6,0)+IF(E101="convert",$C$7,0)+IF(F101="convert",$C$8,0)+IF(G101="convert",$C$9,0)+IF(H101="convert",$C$10,0) | K101: =(Assumptions!$B$46+Assumptions!$B$47+Assumptions!$B$48)+Assumptions!$B$49+('Pro-Forma'!$M$21+'Pro-Forma'!$M$22)+J101 | L101: =(D12-I101+Assumptions!$B$31*Assumptions!$B$10)/(K101+Assumptions!$B$31) | M101: =IF(L101>Assumptions!$B$10,"yes","no") | N101: =IF(M101="yes",L101,MAX(0,(D12-I101)/K101)) | O101: =IF(M101="yes",Assumptions!$B$31*(N101-Assumptions!$B$10),0)
A102: iter 14 | B102: =IF($B$4>$C$4*N101,"preference","convert") | C102: =IF($B$5>$C$5*N101,"preference","convert") | D102: =IF($B$6>$C$6*N101,"preference","convert") | E102: =IF($B$7>$C$7*N101,"preference","convert") | F102: =IF($B$8>$C$8*N101,"preference","convert") | G102: =IF($B$9>$C$9*N101,"preference","convert") | H102: =IF($B$10>$C$10*N101,"preference","convert") | I102: =IF(B102="preference",$B$4,0)+IF(C102="preference",$B$5,0)+IF(D102="preference",$B$6,0)+IF(E102="preference",$B$7,0)+IF(F102="preference",$B$8,0)+IF(G102="preference",$B$9,0)+IF(H102="preference",$B$10,0) | J102: =IF(B102="convert",$C$4,0)+IF(C102="convert",$C$5,0)+IF(D102="convert",$C$6,0)+IF(E102="convert",$C$7,0)+IF(F102="convert",$C$8,0)+IF(G102="convert",$C$9,0)+IF(H102="convert",$C$10,0) | K102: =(Assumptions!$B$46+Assumptions!$B$47+Assumptions!$B$48)+Assumptions!$B$49+('Pro-Forma'!$M$21+'Pro-Forma'!$M$22)+J102 | L102: =(D12-I102+Assumptions!$B$31*Assumptions!$B$10)/(K102+Assumptions!$B$31) | M102: =IF(L102>Assumptions!$B$10,"yes","no") | N102: =IF(M102="yes",L102,MAX(0,(D12-I102)/K102)) | O102: =IF(M102="yes",Assumptions!$B$31*(N102-Assumptions!$B$10),0)
A103: iter 15 | B103: =IF($B$4>$C$4*N102,"preference","convert") | C103: =IF($B$5>$C$5*N102,"preference","convert") | D103: =IF($B$6>$C$6*N102,"preference","convert") | E103: =IF($B$7>$C$7*N102,"preference","convert") | F103: =IF($B$8>$C$8*N102,"preference","convert") | G103: =IF($B$9>$C$9*N102,"preference","convert") | H103: =IF($B$10>$C$10*N102,"preference","convert") | I103: =IF(B103="preference",$B$4,0)+IF(C103="preference",$B$5,0)+IF(D103="preference",$B$6,0)+IF(E103="preference",$B$7,0)+IF(F103="preference",$B$8,0)+IF(G103="preference",$B$9,0)+IF(H103="preference",$B$10,0) | J103: =IF(B103="convert",$C$4,0)+IF(C103="convert",$C$5,0)+IF(D103="convert",$C$6,0)+IF(E103="convert",$C$7,0)+IF(F103="convert",$C$8,0)+IF(G103="convert",$C$9,0)+IF(H103="convert",$C$10,0) | K103: =(Assumptions!$B$46+Assumptions!$B$47+Assumptions!$B$48)+Assumptions!$B$49+('Pro-Forma'!$M$21+'Pro-Forma'!$M$22)+J103 | L103: =(D12-I103+Assumptions!$B$31*Assumptions!$B$10)/(K103+Assumptions!$B$31) | M103: =IF(L103>Assumptions!$B$10,"yes","no") | N103: =IF(M103="yes",L103,MAX(0,(D12-I103)/K103)) | O103: =IF(M103="yes",Assumptions!$B$31*(N103-Assumptions!$B$10),0)
A104: iter 16 | B104: =IF($B$4>$C$4*N103,"preference","convert") | C104: =IF($B$5>$C$5*N103,"preference","convert") | D104: =IF($B$6>$C$6*N103,"preference","convert") | E104: =IF($B$7>$C$7*N103,"preference","convert") | F104: =IF($B$8>$C$8*N103,"preference","convert") | G104: =IF($B$9>$C$9*N103,"preference","convert") | H104: =IF($B$10>$C$10*N103,"preference","convert") | I104: =IF(B104="preference",$B$4,0)+IF(C104="preference",$B$5,0)+IF(D104="preference",$B$6,0)+IF(E104="preference",$B$7,0)+IF(F104="preference",$B$8,0)+IF(G104="preference",$B$9,0)+IF(H104="preference",$B$10,0) | J104: =IF(B104="convert",$C$4,0)+IF(C104="convert",$C$5,0)+IF(D104="convert",$C$6,0)+IF(E104="convert",$C$7,0)+IF(F104="convert",$C$8,0)+IF(G104="convert",$C$9,0)+IF(H104="convert",$C$10,0) | K104: =(Assumptions!$B$46+Assumptions!$B$47+Assumptions!$B$48)+Assumptions!$B$49+('Pro-Forma'!$M$21+'Pro-Forma'!$M$22)+J104 | L104: =(D12-I104+Assumptions!$B$31*Assumptions!$B$10)/(K104+Assumptions!$B$31) | M104: =IF(L104>Assumptions!$B$10,"yes","no") | N104: =IF(M104="yes",L104,MAX(0,(D12-I104)/K104)) | O104: =IF(M104="yes",Assumptions!$B$31*(N104-Assumptions!$B$10),0)
A105: iter 17 | B105: =IF($B$4>$C$4*N104,"preference","convert") | C105: =IF($B$5>$C$5*N104,"preference","convert") | D105: =IF($B$6>$C$6*N104,"preference","convert") | E105: =IF($B$7>$C$7*N104,"preference","convert") | F105: =IF($B$8>$C$8*N104,"preference","convert") | G105: =IF($B$9>$C$9*N104,"preference","convert") | H105: =IF($B$10>$C$10*N104,"preference","convert") | I105: =IF(B105="preference",$B$4,0)+IF(C105="preference",$B$5,0)+IF(D105="preference",$B$6,0)+IF(E105="preference",$B$7,0)+IF(F105="preference",$B$8,0)+IF(G105="preference",$B$9,0)+IF(H105="preference",$B$10,0) | J105: =IF(B105="convert",$C$4,0)+IF(C105="convert",$C$5,0)+IF(D105="convert",$C$6,0)+IF(E105="convert",$C$7,0)+IF(F105="convert",$C$8,0)+IF(G105="convert",$C$9,0)+IF(H105="convert",$C$10,0) | K105: =(Assumptions!$B$46+Assumptions!$B$47+Assumptions!$B$48)+Assumptions!$B$49+('Pro-Forma'!$M$21+'Pro-Forma'!$M$22)+J105 | L105: =(D12-I105+Assumptions!$B$31*Assumptions!$B$10)/(K105+Assumptions!$B$31) | M105: =IF(L105>Assumptions!$B$10,"yes","no") | N105: =IF(M105="yes",L105,MAX(0,(D12-I105)/K105)) | O105: =IF(M105="yes",Assumptions!$B$31*(N105-Assumptions!$B$10),0)
A106: iter 18 | B106: =IF($B$4>$C$4*N105,"preference","convert") | C106: =IF($B$5>$C$5*N105,"preference","convert") | D106: =IF($B$6>$C$6*N105,"preference","convert") | E106: =IF($B$7>$C$7*N105,"preference","convert") | F106: =IF($B$8>$C$8*N105,"preference","convert") | G106: =IF($B$9>$C$9*N105,"preference","convert") | H106: =IF($B$10>$C$10*N105,"preference","convert") | I106: =IF(B106="preference",$B$4,0)+IF(C106="preference",$B$5,0)+IF(D106="preference",$B$6,0)+IF(E106="preference",$B$7,0)+IF(F106="preference",$B$8,0)+IF(G106="preference",$B$9,0)+IF(H106="preference",$B$10,0) | J106: =IF(B106="convert",$C$4,0)+IF(C106="convert",$C$5,0)+IF(D106="convert",$C$6,0)+IF(E106="convert",$C$7,0)+IF(F106="convert",$C$8,0)+IF(G106="convert",$C$9,0)+IF(H106="convert",$C$10,0) | K106: =(Assumptions!$B$46+Assumptions!$B$47+Assumptions!$B$48)+Assumptions!$B$49+('Pro-Forma'!$M$21+'Pro-Forma'!$M$22)+J106 | L106: =(D12-I106+Assumptions!$B$31*Assumptions!$B$10)/(K106+Assumptions!$B$31) | M106: =IF(L106>Assumptions!$B$10,"yes","no") | N106: =IF(M106="yes",L106,MAX(0,(D12-I106)/K106)) | O106: =IF(M106="yes",Assumptions!$B$31*(N106-Assumptions!$B$10),0)
A107: iter 19 | B107: =IF($B$4>$C$4*N106,"preference","convert") | C107: =IF($B$5>$C$5*N106,"preference","convert") | D107: =IF($B$6>$C$6*N106,"preference","convert") | E107: =IF($B$7>$C$7*N106,"preference","convert") | F107: =IF($B$8>$C$8*N106,"preference","convert") | G107: =IF($B$9>$C$9*N106,"preference","convert") | H107: =IF($B$10>$C$10*N106,"preference","convert") | I107: =IF(B107="preference",$B$4,0)+IF(C107="preference",$B$5,0)+IF(D107="preference",$B$6,0)+IF(E107="preference",$B$7,0)+IF(F107="preference",$B$8,0)+IF(G107="preference",$B$9,0)+IF(H107="preference",$B$10,0) | J107: =IF(B107="convert",$C$4,0)+IF(C107="convert",$C$5,0)+IF(D107="convert",$C$6,0)+IF(E107="convert",$C$7,0)+IF(F107="convert",$C$8,0)+IF(G107="convert",$C$9,0)+IF(H107="convert",$C$10,0) | K107: =(Assumptions!$B$46+Assumptions!$B$47+Assumptions!$B$48)+Assumptions!$B$49+('Pro-Forma'!$M$21+'Pro-Forma'!$M$22)+J107 | L107: =(D12-I107+Assumptions!$B$31*Assumptions!$B$10)/(K107+Assumptions!$B$31) | M107: =IF(L107>Assumptions!$B$10,"yes","no") | N107: =IF(M107="yes",L107,MAX(0,(D12-I107)/K107)) | O107: =IF(M107="yes",Assumptions!$B$31*(N107-Assumptions!$B$10),0)
A108: iter 20 | B108: =IF($B$4>$C$4*N107,"preference","convert") | C108: =IF($B$5>$C$5*N107,"preference","convert") | D108: =IF($B$6>$C$6*N107,"preference","convert") | E108: =IF($B$7>$C$7*N107,"preference","convert") | F108: =IF($B$8>$C$8*N107,"preference","convert") | G108: =IF($B$9>$C$9*N107,"preference","convert") | H108: =IF($B$10>$C$10*N107,"preference","convert") | I108: =IF(B108="preference",$B$4,0)+IF(C108="preference",$B$5,0)+IF(D108="preference",$B$6,0)+IF(E108="preference",$B$7,0)+IF(F108="preference",$B$8,0)+IF(G108="preference",$B$9,0)+IF(H108="preference",$B$10,0) | J108: =IF(B108="convert",$C$4,0)+IF(C108="convert",$C$5,0)+IF(D108="convert",$C$6,0)+IF(E108="convert",$C$7,0)+IF(F108="convert",$C$8,0)+IF(G108="convert",$C$9,0)+IF(H108="convert",$C$10,0) | K108: =(Assumptions!$B$46+Assumptions!$B$47+Assumptions!$B$48)+Assumptions!$B$49+('Pro-Forma'!$M$21+'Pro-Forma'!$M$22)+J108 | L108: =(D12-I108+Assumptions!$B$31*Assumptions!$B$10)/(K108+Assumptions!$B$31) | M108: =IF(L108>Assumptions!$B$10,"yes","no") | N108: =IF(M108="yes",L108,MAX(0,(D12-I108)/K108)) | O108: =IF(M108="yes",Assumptions!$B$31*(N108-Assumptions!$B$10),0)
...

Sheet Sensitivity
A1: Sensitivity Grid — Our $10M check, post-F ownership % and $ proceeds at $2B exit
A3: Each cell re-solves full round + waterfall fixed point at the cell's (ESOP, pre-money).
A6: ESOP \ Pre-money | B6: =Assumptions!$B$53 | C6: =Assumptions!$B$54 | D6: =Assumptions!$B$55
A7: =Assumptions!$B$50 | B7: =TEXT(B133*100,"0.0000")&"% / $"&TEXT(B134,"#,##0") | C7: =TEXT(B257*100,"0.0000")&"% / $"&TEXT(B258,"#,##0") | D7: =TEXT(B381*100,"0.0000")&"% / $"&TEXT(B382,"#,##0")
A8: =Assumptions!$B$51 | B8: =TEXT(B505*100,"0.0000")&"% / $"&TEXT(B506,"#,##0") | C8: =TEXT(B629*100,"0.0000")&"% / $"&TEXT(B630,"#,##0") | D8: =TEXT(B753*100,"0.0000")&"% / $"&TEXT(B754,"#,##0")
A9: =Assumptions!$B$52 | B9: =TEXT(B877*100,"0.0000")&"% / $"&TEXT(B878,"#,##0") | C9: =TEXT(B1001*100,"0.0000")&"% / $"&TEXT(B1002,"#,##0") | D9: =TEXT(B1125*100,"0.0000")&"% / $"&TEXT(B1126,"#,##0")
A13: Cell (0,0) — ESOP=low, Pre=low
A14: Step | B14: F_PPS | C14: D_NCP | D14: E_NCP | E14: ΔD | F14: ΔE | G14: ESOP | H14: N_A | I14: N_B | J14: preFD | K14: T_F | L14: F_PPS chk
A15: cell(0,0) seed | B15: =Assumptions!$B$53/Assumptions!$B$29 | C15: =Assumptions!$B$20 | D15: =Assumptions!$B$21 | E15: 0 | F15: 0 | G15: 0 | H15: 0 | I15: 0 | J15: =Assumptions!$B$29 | K15: =J15+Assumptions!$B$4/B15 | L15: =B15
A16: cell(0,0) iter 1 | B16: =Assumptions!$B$53/J15 | C16: =IF(B16<Assumptions!$B$20,Assumptions!$B$20*(Assumptions!$B$29+Assumptions!$B$4/Assumptions!$B$20)/(Assumptions!$B$29+Assumptions!$B$4/B16),Assumptions!$B$20) | D16: =IF(B16<Assumptions!$B$21,Assumptions!$B$21*(Assumptions!$B$29+Assumptions!$B$4/Assumptions!$B$21)/(Assumptions!$B$29+Assumptions!$B$4/B16),Assumptions!$B$21) | E16: =Assumptions!$B$37*Assumptions!$B$22/C16-Assumptions!$B$38 | F16: =Assumptions!$B$39*Assumptions!$B$21/D16-Assumptions!$B$39 | G16: =MAX(0,Assumptions!$B$50*(Assumptions!$B$29+E16+F16+G15+H15+I15+Assumptions!$B$4/B16)-Assumptions!$B$30) | H16: =Assumptions!$B$23/MIN(Assumptions!$B$24/(Assumptions!$B$29+E16+F16+G16+I15),B16*(1-Assumptions!$B$25)) | I16: =Assumptions!$B$26/MIN(Assumptions!$B$27/(Assumptions!$B$29+E16+F16+G16+H16),B16*(1-Assumptions!$B$28)) | J16: =Assumptions!$B$29+E16+F16+G16+H16+I16 | K16: =J16+Assumptions!$B$4/B16 | L16: =B16
A17: cell(0,0) iter 2 | B17: =Assumptions!$B$53/J16 | C17: =IF(B17<Assumptions!$B$20,Assumptions!$B$20*(Assumptions!$B$29+Assumptions!$B$4/Assumptions!$B$20)/(Assumptions!$B$29+Assumptions!$B$4/B17),Assumptions!$B$20) | D17: =IF(B17<Assumptions!$B$21,Assumptions!$B$21*(Assumptions!$B$29+Assumptions!$B$4/Assumptions!$B$21)/(Assumptions!$B$29+Assumptions!$B$4/B17),Assumptions!$B$21) | E17: =Assumptions!$B$37*Assumptions!$B$22/C17-Assumptions!$B$38 | F17: =Assumptions!$B$39*Assumptions!$B$21/D17-Assumptions!$B$39 | G17: =MAX(0,Assumptions!$B$50*(Assumptions!$B$29+E17+F17+G16+H16+I16+Assumptions!$B$4/B17)-Assumptions!$B$30) | H17: =Assumptions!$B$23/MIN(Assumptions!$B$24/(Assumptions!$B$29+E17+F17+G17+I16),B17*(1-Assumptions!$B$25)) | I17: =Assumptions!$B$26/MIN(Assumptions!$B$27/(Assumptions!$B$29+E17+F17+G17+H17),B17*(1-Assumptions!$B$28)) | J17: =Assumptions!$B$29+E17+F17+G17+H17+I17 | K17: =J17+Assumptions!$B$4/B17 | L17: =B17
A18: cell(0,0) iter 3 | B18: =Assumptions!$B$53/J17 | C18: =IF(B18<Assumptions!$B$20,Assumptions!$B$20*(Assumptions!$B$29+Assumptions!$B$4/Assumptions!$B$20)/(Assumptions!$B$29+Assumptions!$B$4/B18),Assumptions!$B$20) | D18: =IF(B18<Assumptions!$B$21,Assumptions!$B$21*(Assumptions!$B$29+Assumptions!$B$4/Assumptions!$B$21)/(Assumptions!$B$29+Assumptions!$B$4/B18),Assumptions!$B$21) | E18: =Assumptions!$B$37*Assumptions!$B$22/C18-Assumptions!$B$38 | F18: =Assumptions!$B$39*Assumptions!$B$21/D18-Assumptions!$B$39 | G18: =MAX(0,Assumptions!$B$50*(Assumptions!$B$29+E18+F18+G17+H17+I17+Assumptions!$B$4/B18)-Assumptions!$B$30) | H18: =Assumptions!$B$23/MIN(Assumptions!$B$24/(Assumptions!$B$29+E18+F18+G18+I17),B18*(1-Assumptions!$B$25)) | I18: =Assumptions!$B$26/MIN(Assumptions!$B$27/(Assumptions!$B$29+E18+F18+G18+H18),B18*(1-Assumptions!$B$28)) | J18: =Assumptions!$B$29+E18+F18+G18+H18+I18 | K18: =J18+Assumptions!$B$4/B18 | L18: =B18
A19: cell(0,0) iter 4 | B19: =Assumptions!$B$53/J18 | C19: =IF(B19<Assumptions!$B$20,Assumptions!$B$20*(Assumptions!$B$29+Assumptions!$B$4/Assumptions!$B$20)/(Assumptions!$B$29+Assumptions!$B$4/B19),Assumptions!$B$20) | D19: =IF(B19<Assumptions!$B$21,Assumptions!$B$21*(Assumptions!$B$29+Assumptions!$B$4/Assumptions!$B$21)/(Assumptions!$B$29+Assumptions!$B$4/B19),Assumptions!$B$21) | E19: =Assumptions!$B$37*Assumptions!$B$22/C19-Assumptions!$B$38 | F19: =Assumptions!$B$39*Assumptions!$B$21/D19-Assumptions!$B$39 | G19: =MAX(0,Assumptions!$B$50*(Assumptions!$B$29+E19+F19+G18+H18+I18+Assumptions!$B$4/B19)-Assumptions!$B$30) | H19: =Assumptions!$B$23/MIN(Assumptions!$B$24/(Assumptions!$B$29+E19+F19+G19+I18),B19*(1-Assumptions!$B$25)) | I19: =Assumptions!$B$26/MIN(Assumptions!$B$27/(Assumptions!$B$29+E19+F19+G19+H19),B19*(1-Assumptions!$B$28)) | J19: =Assumptions!$B$29+E19+F19+G19+H19+I19 | K19: =J19+Assumptions!$B$4/B19 | L19: =B19
A20: cell(0,0) iter 5 | B20: =Assumptions!$B$53/J19 | C20: =IF(B20<Assumptions!$B$20,Assumptions!$B$20*(Assumptions!$B$29+Assumptions!$B$4/Assumptions!$B$20)/(Assumptions!$B$29+Assumptions!$B$4/B20),Assumptions!$B$20) | D20: =IF(B20<Assumptions!$B$21,Assumptions!$B$21*(Assumptions!$B$29+Assumptions!$B$4/Assumptions!$B$21)/(Assumptions!$B$29+Assumptions!$B$4/B20),Assumptions!$B$21) | E20: =Assumptions!$B$37*Assumptions!$B$22/C20-Assumptions!$B$38 | F20: =Assumptions!$B$39*Assumptions!$B$21/D20-Assumptions!$B$39 | G20: =MAX(0,Assumptions!$B$50*(Assumptions!$B$29+E20+F20+G19+H19+I19+Assumptions!$B$4/B20)-Assumptions!$B$30) | H20: =Assumptions!$B$23/MIN(Assumptions!$B$24/(Assumptions!$B$29+E20+F20+G20+I19),B20*(1-Assumptions!$B$25)) | I20: =Assumptions!$B$26/MIN(Assumptions!$B$27/(Assumptions!$B$29+E20+F20+G20+H20),B20*(1-Assumptions!$B$28)) | J20: =Assumptions!$B$29+E20+F20+G20+H20+I20 | K20: =J20+Assumptions!$B$4/B20 | L20: =B20
A21: cell(0,0) iter 6 | B21: =Assumptions!$B$53/J20 | C21: =IF(B21<Assumptions!$B$20,Assumptions!$B$20*(Assumptions!$B$29+Assumptions!$B$4/Assumptions!$B$20)/(Assumptions!$B$29+Assumptions!$B$4/B21),Assumptions!$B$20) | D21: =IF(B21<Assumptions!$B$21,Assumptions!$B$21*(Assumptions!$B$29+Assumptions!$B$4/Assumptions!$B$21)/(Assumptions!$B$29+Assumptions!$B$4/B21),Assumptions!$B$21) | E21: =Assumptions!$B$37*Assumptions!$B$22/C21-Assumptions!$B$38 | F21: =Assumptions!$B$39*Assumptions!$B$21/D21-Assumptions!$B$39 | G21: =MAX(0,Assumptions!$B$50*(Assumptions!$B$29+E21+F21+G20+H20+I20+Assumptions!$B$4/B21)-Assumptions!$B$30) | H21: =Assumptions!$B$23/MIN(Assumptions!$B$24/(Assumptions!$B$29+E21+F21+G21+I20),B21*(1-Assumptions!$B$25)) | I21: =Assumptions!$B$26/MIN(Assumptions!$B$27/(Assumptions!$B$29+E21+F21+G21+H21),B21*(1-Assumptions!$B$28)) | J21: =Assumptions!$B$29+E21+F21+G21+H21+I21 | K21: =J21+Assumptions!$B$4/B21 | L21: =B21
A22: cell(0,0) iter 7 | B22: =Assumptions!$B$53/J21 | C22: =IF(B22<Assumptions!$B$20,Assumptions!$B$20*(Assumptions!$B$29+Assumptions!$B$4/Assumptions!$B$20)/(Assumptions!$B$29+Assumptions!$B$4/B22),Assumptions!$B$20) | D22: =IF(B22<Assumptions!$B$21,Assumptions!$B$21*(Assumptions!$B$29+Assumptions!$B$4/Assumptions!$B$21)/(Assumptions!$B$29+Assumptions!$B$4/B22),Assumptions!$B$21) | E22: =Assumptions!$B$37*Assumptions!$B$22/C22-Assumptions!$B$38 | F22: =Assumptions!$B$39*Assumptions!$B$21/D22-Assumptions!$B$39 | G22: =MAX(0,Assumptions!$B$50*(Assumptions!$B$29+E22+F22+G21+H21+I21+Assumptions!$B$4/B22)-Assumptions!$B$30) | H22: =Assumptions!$B$23/MIN(Assumptions!$B$24/(Assumptions!$B$29+E22+F22+G22+I21),B22*(1-Assumptions!$B$25)) | I22: =Assumptions!$B$26/MIN(Assumptions!$B$27/(Assumptions!$B$29+E22+F22+G22+H22),B22*(1-Assumptions!$B$28)) | J22: =Assumptions!$B$29+E22+F22+G22+H22+I22 | K22: =J22+Assumptions!$B$4/B22 | L22: =B22
A23: cell(0,0) iter 8 | B23: =Assumptions!$B$53/J22 | C23: =IF(B23<Assumptions!$B$20,Assumptions!$B$20*(Assumptions!$B$29+Assumptions!$B$4/Assumptions!$B$20)/(Assumptions!$B$29+Assumptions!$B$4/B23),Assumptions!$B$20) | D23: =IF(B23<Assumptions!$B$21,Assumptions!$B$21*(Assumptions!$B$29+Assumptions!$B$4/Assumptions!$B$21)/(Assumptions!$B$29+Assumptions!$B$4/B23),Assumptions!$B$21) | E23: =Assumptions!$B$37*Assumptions!$B$22/C23-Assumptions!$B$38 | F23: =Assumptions!$B$39*Assumptions!$B$21/D23-Assumptions!$B$39 | G23: =MAX(0,Assumptions!$B$50*(Assumptions!$B$29+E23+F23+G22+H22+I22+Assumptions!$B$4/B23)-Assumptions!$B$30) | H23: =Assumptions!$B$23/MIN(Assumptions!$B$24/(Assumptions!$B$29+E23+F23+G23+I22),B23*(1-Assumptions!$B$25)) | I23: =Assumptions!$B$26/MIN(Assumptions!$B$27/(Assumptions!$B$29+E23+F23+G23+H23),B23*(1-Assumptions!$B$28)) | J23: =Assumptions!$B$29+E23+F23+G23+H23+I23 | K23: =J23+Assumptions!$B$4/B23 | L23: =B23
A24: cell(0,0) iter 9 | B24: =Assumptions!$B$53/J23 | C24: =IF(B24<Assumptions!$B$20,Assumptions!$B$20*(Assumptions!$B$29+Assumptions!$B$4/Assumptions!$B$20)/(Assumptions!$B$29+Assumptions!$B$4/B24),Assumptions!$B$20) | D24: =IF(B24<Assumptions!$B$21,Assumptions!$B$21*(Assumptions!$B$29+Assumptions!$B$4/Assumptions!$B$21)/(Assumptions!$B$29+Assumptions!$B$4/B24),Assumptions!$B$21) | E24: =Assumptions!$B$37*Assumptions!$B$22/C24-Assumptions!$B$38 | F24: =Assumptions!$B$39*Assumptions!$B$21/D24-Assumptions!$B$39 | G24: =MAX(0,Assumptions!$B$50*(Assumptions!$B$29+E24+F24+G23+H23+I23+Assumptions!$B$4/B24)-Assumptions!$B$30) | H24: =Assumptions!$B$23/MIN(Assumptions!$B$24/(Assumptions!$B$29+E24+F24+G24+I23),B24*(1-Assumptions!$B$25)) | I24: =Assumptions!$B$26/MIN(Assumptions!$B$27/(Assumptions!$B$29+E24+F24+G24+H24),B24*(1-Assumptions!$B$28)) | J24: =Assumptions!$B$29+E24+F24+G24+H24+I24 | K24: =J24+Assumptions!$B$4/B24 | L24: =B24
A25: cell(0,0) iter 10 | B25: =Assumptions!$B$53/J24 | C25: =IF(B25<Assumptions!$B$20,Assumptions!$B$20*(Assumptions!$B$29+Assumptions!$B$4/Assumptions!$B$20)/(Assumptions!$B$29+Assumptions!$B$4/B25),Assumptions!$B$20) | D25: =IF(B25<Assumptions!$B$21,Assumptions!$B$21*(Assumptions!$B$29+Assumptions!$B$4/Assumptions!$B$21)/(Assumptions!$B$29+Assumptions!$B$4/B25),Assumptions!$B$21) | E25: =Assumptions!$B$37*Assumptions!$B$22/C25-Assumptions!$B$38 | F25: =Assumptions!$B$39*Assumptions!$B$21/D25-Assumptions!$B$39 | G25: =MAX(0,Assumptions!$B$50*(Assumptions!$B$29+E25+F25+G24+H24+I24+Assumptions!$B$4/B25)-Assumptions!$B$30) | H25: =Assumptions!$B$23/MIN(Assumptions!$B$24/(Assumptions!$B$29+E25+F25+G25+I24),B25*(1-Assumptions!$B$25)) | I25: =Assumptions!$B$26/MIN(Assumptions!$B$27/(Assumptions!$B$29+E25+F25+G25+H25),B25*(1-Assumptions!$B$28)) | J25: =Assumptions!$B$29+E25+F25+G25+H25+I25 | K25: =J25+Assumptions!$B$4/B25 | L25: =B25
A26: cell(0,0) iter 11 | B26: =Assumptions!$B$53/J25 | C26: =IF(B26<Assumptions!$B$20,Assumptions!$B$20*(Assumptions!$B$29+Assumptions!$B$4/Assumptions!$B$20)/(Assumptions!$B$29+Assumptions!$B$4/B26),Assumptions!$B$20) | D26: =IF(B26<Assumptions!$B$21,Assumptions!$B$21*(Assumptions!$B$29+Assumptions!$B$4/Assumptions!$B$21)/(Assumptions!$B$29+Assumptions!$B$4/B26),Assumptions!$B$21) | E26: =Assumptions!$B$37*Assumptions!$B$22/C26-Assumptions!$B$38 | F26: =Assumptions!$B$39*Assumptions!$B$21/D26-Assumptions!$B$39 | G26: =MAX(0,Assumptions!$B$50*(Assumptions!$B$29+E26+F26+G25+H25+I25+Assumptions!$B$4/B26)-Assumptions!$B$30) | H26: =Assumptions!$B$23/MIN(Assumptions!$B$24/(Assumptions!$B$29+E26+F26+G26+I25),B26*(1-Assumptions!$B$25)) | I26: =Assumptions!$B$26/MIN(Assumptions!$B$27/(Assumptions!$B$29+E26+F26+G26+H26),B26*(1-Assumptions!$B$28)) | J26: =Assumptions!$B$29+E26+F26+G26+H26+I26 | K26: =J26+Assumptions!$B$4/B26 | L26: =B26
A27: cell(0,0) iter 12 | B27: =Assumptions!$B$53/J26 | C27: =IF(B27<Assumptions!$B$20,Assumptions!$B$20*(Assumptions!$B$29+Assumptions!$B$4/Assumptions!$B$20)/(Assumptions!$B$29+Assumptions!$B$4/B27),Assumptions!$B$20) | D27: =IF(B27<Assumptions!$B$21,Assumptions!$B$21*(Assumptions!$B$29+Assumptions!$B$4/Assumptions!$B$21)/(Assumptions!$B$29+Assumptions!$B$4/B27),Assumptions!$B$21) | E27: =Assumptions!$B$37*Assumptions!$B$22/C27-Assumptions!$B$38 | F27: =Assumptions!$B$39*Assumptions!$B$21/D27-Assumptions!$B$39 | G27: =MAX(0,Assumptions!$B$50*(Assumptions!$B$29+E27+F27+G26+H26+I26+Assumptions!$B$4/B27)-Assumptions!$B$30) | H27: =Assumptions!$B$23/MIN(Assumptions!$B$24/(Assumptions!$B$29+E27+F27+G27+I26),B27*(1-Assumptions!$B$25)) | I27: =Assumptions!$B$26/MIN(Assumptions!$B$27/(Assumptions!$B$29+E27+F27+G27+H27),B27*(1-Assumptions!$B$28)) | J27: =Assumptions!$B$29+E27+F27+G27+H27+I27 | K27: =J27+Assumptions!$B$4/B27 | L27: =B27
... A95: cell(0,0) iter 80 | B95: =Assumptions!$B$53/J94 | C95: =IF(B95<Assumptions!$B$20,Assumptions!$B$20*(Assumptions!$B$29+Assumptions!$B$4/Assumptions!$B$20)/(Assumptions!$B$29+Assumptions!$B$4/B95),Assumptions!$B$20) | D95: =IF(B95<Assumptions!$B$21,Assumptions!$B$21*(Assumptions!$B$29+Assumptions!$B$4/Assumptions!$B$21)/(Assumptions!$B$29+Assumptions!$B$4/B95),Assumptions!$B$21) | E95: =Assumptions!$B$37*Assumptions!$B$22/C95-Assumptions!$B$38 | F95: =Assumptions!$B$39*Assumptions!$B$21/D95-Assumptions!$B$39 | G95: =MAX(0,Assumptions!$B$50*(Assumptions!$B$29+E95+F95+G94+H94+I94+Assumptions!$B$4/B95)-Assumptions!$B$30) | H95: =Assumptions!$B$23/MIN(Assumptions!$B$24/(Assumptions!$B$29+E95+F95+G95+I94),B95*(1-Assumptions!$B$25)) | I95: =Assumptions!$B$26/MIN(Assumptions!$B$27/(Assumptions!$B$29+E95+F95+G95+H95),B95*(1-Assumptions!$B$28)) | J95: =Assumptions!$B$29+E95+F95+G95+H95+I95 | K95: =J95+Assumptions!$B$4/B95 | L95: =B95
A98: Waterfall ladder ($2B exit)
A99: Step | B99: F_el | C99: E_el | D99: D_el | E99: C_el | F99: B_el | G99: A_el | H99: Seed_el | I99: prefs | J99: conv_sh | K99: cpool | L99: ITM_PPS | M99: ITM? | N99: common_PPS | O99: opt_proc
A100: seed (all convert) | B100: ="convert" | C100: ="convert" | D100: ="convert" | E100: ="convert" | F100: ="convert" | G100: ="convert" | H100: ="convert" | I100: =IF(B100="preference",Assumptions!$B$4,0)+IF(C100="preference",Assumptions!$B$45,0)+IF(D100="preference",Assumptions!$B$44,0)+IF(E100="preference",Assumptions!$B$43,0)+IF(F100="preference",Assumptions!$B$42,0)+IF(G100="preference",Assumptions!$B$41,0)+IF(H100="preference",Assumptions!$B$40,0) | J100: =IF(B100="convert",(Assumptions!$B$4/B95),0)+IF(C100="convert",(Assumptions!$B$39+F95),0)+IF(D100="convert",(Assumptions!$B$38+E95),0)+IF(E100="convert",Assumptions!$B$36,0)+IF(F100="convert",Assumptions!$B$35,0)+IF(G100="convert",Assumptions!$B$34,0)+IF(H100="convert",Assumptions!$B$33,0) | K100: =(Assumptions!$B$46+Assumptions!$B$47+Assumptions!$B$48)+Assumptions!$B$49+(H95+I95)+J100 | L100: =(Assumptions!$B$13-I100+Assumptions!$B$31*Assumptions!$B$10)/(K100+Assumptions!$B$31) | M100: =IF(L100>Assumptions!$B$10,"yes","no") | N100: =IF(M100="yes",L100,MAX(0,(Assumptions!$B$13-I100)/K100)) | O100: =IF(M100="yes",Assumptions!$B$31*(N100-Assumptions!$B$10),0)
A101: iter 1 | B101: =IF(Assumptions!$B$4>(Assumptions!$B$4/B95)*N100,"preference","convert") | C101: =IF(Assumptions!$B$45>(Assumptions!$B$39+F95)*N100,"preference","convert") | D101: =IF(Assumptions!$B$44>(Assumptions!$B$38+E95)*N100,"preference","convert") | E101: =IF(Assumptions!$B$43>Assumptions!$B$36*N100,"preference","convert") | F101: =IF(Assumptions!$B$42>Assumptions!$B$35*N100,"preference","convert") | G101: =IF(Assumptions!$B$41>Assumptions!$B$34*N100,"preference","convert") | H101: =IF(Assumptions!$B$40>Assumptions!$B$33*N100,"preference","convert") | I101: =IF(B101="preference",Assumptions!$B$4,0)+IF(C101="preference",Assumptions!$B$45,0)+IF(D101="preference",Assumptions!$B$44,0)+IF(E101="preference",Assumptions!$B$43,0)+IF(F101="preference",Assumptions!$B$42,0)+IF(G101="preference",Assumptions!$B$41,0)+IF(H101="preference",Assumptions!$B$40,0) | J101: =IF(B101="convert",(Assumptions!$B$4/B95),0)+IF(C101="convert",(Assumptions!$B$39+F95),0)+IF(D101="convert",(Assumptions!$B$38+E95),0)+IF(E101="convert",Assumptions!$B$36,0)+IF(F101="convert",Assumptions!$B$35,0)+IF(G101="convert",Assumptions!$B$34,0)+IF(H101="convert",Assumptions!$B$33,0) | K101: =(Assumptions!$B$46+Assumptions!$B$47+Assumptions!$B$48)+Assumptions!$B$49+(H95+I95)+J101 | L101: =(Assumptions!$B$13-I101+Assumptions!$B$31*Assumptions!$B$10)/(K101+Assumptions!$B$31) | M101: =IF(L101>Assumptions!$B$10,"yes","no") | N101: =IF(M101="yes",L101,MAX(0,(Assumptions!$B$13-I101)/K101)) | O101: =IF(M101="yes",Assumptions!$B$31*(N101-Assumptions!$B$10),0)
A102: iter 2 | B102: =IF(Assumptions!$B$4>(Assumptions!$B$4/B95)*N101,"preference","convert") | C102: =IF(Assumptions!$B$45>(Assumptions!$B$39+F95)*N101,"preference","convert") | D102: =IF(Assumptions!$B$44>(Assumptions!$B$38+E95)*N101,"preference","convert") | E102: =IF(Assumptions!$B$43>Assumptions!$B$36*N101,"preference","convert") | F102: =IF(Assumptions!$B$42>Assumptions!$B$35*N101,"preference","convert") | G102: =IF(Assumptions!$B$41>Assumptions!$B$34*N101,"preference","convert") | H102: =IF(Assumptions!$B$40>Assumptions!$B$33*N101,"preference","convert") | I102: =IF(B102="preference",Assumptions!$B$4,0)+IF(C102="preference",Assumptions!$B$45,0)+IF(D102="preference",Assumptions!$B$44,0)+IF(E102="preference",Assumptions!$B$43,0)+IF(F102="preference",Assumptions!$B$42,0)+IF(G102="preference",Assumptions!$B$41,0)+IF(H102="preference",Assumptions!$B$40,0) | J102: =IF(B102="convert",(Assumptions!$B$4/B95),0)+IF(C102="convert",(Assumptions!$B$39+F95),0)+IF(D102="convert",(Assumptions!$B$38+E95),0)+IF(E102="convert",Assumptions!$B$36,0)+IF(F102="convert",Assumptions!$B$35,0)+IF(G102="convert",Assumptions!$B$34,0)+IF(H102="convert",Assumptions!$B$33,0) | K102: =(Assumptions!$B$46+Assumptions!$B$47+Assumptions!$B$48)+Assumptions!$B$49+(H95+I95)+J102 | L102: =(Assumptions!$B$13-I102+Assumptions!$B$31*Assumptions!$B$10)/(K102+Assumptions!$B$31) | M102: =IF(L102>Assumptions!$B$10,"yes","no") | N102: =IF(M102="yes",L102,MAX(0,(Assumptions!$B$13-I102)/K102)) | O102: =IF(M102="yes",Assumptions!$B$31*(N102-Assumptions!$B$10),0)
A103: iter 3 | B103: =IF(Assumptions!$B$4>(Assumptions!$B$4/B95)*N102,"preference","convert") | C103: =IF(Assumptions!$B$45>(Assumptions!$B$39+F95)*N102,"preference","convert") | D103: =IF(Assumptions!$B$44>(Assumptions!$B$38+E95)*N102,"preference","convert") | E103: =IF(Assumptions!$B$43>Assumptions!$B$36*N102,"preference","convert") | F103: =IF(Assumptions!$B$42>Assumptions!$B$35*N102,"preference","convert") | G103: =IF(Assumptions!$B$41>Assumptions!$B$34*N102,"preference","convert") | H103: =IF(Assumptions!$B$40>Assumptions!$B$33*N102,"preference","convert") | I103: =IF(B103="preference",Assumptions!$B$4,0)+IF(C103="preference",Assumptions!$B$45,0)+IF(D103="preference",Assumptions!$B$44,0)+IF(E103="preference",Assumptions!$B$43,0)+IF(F103="preference",Assumptions!$B$42,0)+IF(G103="preference",Assumptions!$B$41,0)+IF(H103="preference",Assumptions!$B$40,0) | J103: =IF(B103="convert",(Assumptions!$B$4/B95),0)+IF(C103="convert",(Assumptions!$B$39+F95),0)+IF(D103="convert",(Assumptions!$B$38+E95),0)+IF(E103="convert",Assumptions!$B$36,0)+IF(F103="convert",Assumptions!$B$35,0)+IF(G103="convert",Assumptions!$B$34,0)+IF(H103="convert",Assumptions!$B$33,0) | K103: =(Assumptions!$B$46+Assumptions!$B$47+Assumptions!$B$48)+Assumptions!$B$49+(H95+I95)+J103 | L103: =(Assumptions!$B$13-I103+Assumptions!$B$31*Assumptions!$B$10)/(K103+Assumptions!$B$31) | M103: =IF(L103>Assumptions!$B$10,"yes","no") | N103: =IF(M103="yes",L103,MAX(0,(Assumptions!$B$13-I103)/K103)) | O103: =IF(M103="yes",Assumptions!$B$31*(N103-Assumptions!$B$10),0)
A104: iter 4 | B104: =IF(Assumptions!$B$4>(Assumptions!$B$4/B95)*N103,"preference","convert") | C104: =IF(Assumptions!$B$45>(Assumptions!$B$39+F95)*N103,"preference","convert") | D104: =IF(Assumptions!$B$44>(Assumptions!$B$38+E95)*N103,"preference","convert") | E104: =IF(Assumptions!$B$43>Assumptions!$B$36*N103,"preference","convert") | F104: =IF(Assumptions!$B$42>Assumptions!$B$35*N103,"preference","convert") | G104: =IF(Assumptions!$B$41>Assumptions!$B$34*N103,"preference","convert") | H104: =IF(Assumptions!$B$40>Assumptions!$B$33*N103,"preference","convert") | I104: =IF(B104="preference",Assumptions!$B$4,0)+IF(C104="preference",Assumptions!$B$45,0)+IF(D104="preference",Assumptions!$B$44,0)+IF(E104="preference",Assumptions!$B$43,0)+IF(F104="preference",Assumptions!$B$42,0)+IF(G104="preference",Assumptions!$B$41,0)+IF(H104="preference",Assumptions!$B$40,0) | J104: =IF(B104="convert",(Assumptions!$B$4/B95),0)+IF(C104="convert",(Assumptions!$B$39+F95),0)+IF(D104="convert",(Assumptions!$B$38+E95),0)+IF(E104="convert",Assumptions!$B$36,0)+IF(F104="convert",Assumptions!$B$35,0)+IF(G104="convert",Assumptions!$B$34,0)+IF(H104="convert",Assumptions!$B$33,0) | K104: =(Assumptions!$B$46+Assumptions!$B$47+Assumptions!$B$48)+Assumptions!$B$49+(H95+I95)+J104 | L104: =(Assumptions!$B$13-I104+Assumptions!$B$31*Assumptions!$B$10)/(K104+Assumptions!$B$31) | M104: =IF(L104>Assumptions!$B$10,"yes","no") | N104: =IF(M104="yes",L104,MAX(0,(Assumptions!$B$13-I104)/K104)) | O104: =IF(M104="yes",Assumptions!$B$31*(N104-Assumptions!$B$10),0)
A105: iter 5 | B105: =IF(Assumptions!$B$4>(Assumptions!$B$4/B95)*N104,"preference","convert") | C105: =IF(Assumptions!$B$45>(Assumptions!$B$39+F95)*N104,"preference","convert") | D105: =IF(Assumptions!$B$44>(Assumptions!$B$38+E95)*N104,"preference","convert") | E105: =IF(Assumptions!$B$43>Assumptions!$B$36*N104,"preference","convert") | F105: =IF(Assumptions!$B$42>Assumptions!$B$35*N104,"preference","convert") | G105: =IF(Assumptions!$B$41>Assumptions!$B$34*N104,"preference","convert") | H105: =IF(Assumptions!$B$40>Assumptions!$B$33*N104,"preference","convert") | I105: =IF(B105="preference",Assumptions!$B$4,0)+IF(C105="preference",Assumptions!$B$45,0)+IF(D105="preference",Assumptions!$B$44,0)+IF(E105="preference",Assumptions!$B$43,0)+IF(F105="preference",Assumptions!$B$42,0)+IF(G105="preference",Assumptions!$B$41,0)+IF(H105="preference",Assumptions!$B$40,0) | J105: =IF(B105="convert",(Assumptions!$B$4/B95),0)+IF(C105="convert",(Assumptions!$B$39+F95),0)+IF(D105="convert",(Assumptions!$B$38+E95),0)+IF(E105="convert",Assumptions!$B$36,0)+IF(F105="convert",Assumptions!$B$35,0)+IF(G105="convert",Assumptions!$B$34,0)+IF(H105="convert",Assumptions!$B$33,0) | K105: =(Assumptions!$B$46+Assumptions!$B$47+Assumptions!$B$48)+Assumptions!$B$49+(H95+I95)+J105 | L105: =(Assumptions!$B$13-I105+Assumptions!$B$31*Assumptions!$B$10)/(K105+Assumptions!$B$31) | M105: =IF(L105>Assumptions!$B$10,"yes","no") | N105: =IF(M105="yes",L105,MAX(0,(Assumptions!$B$13-I105)/K105)) | O105: =IF(M105="yes",Assumptions!$B$31*(N105-Assumptions!$B$10),0)
A106: iter 6 | B106: =IF(Assumptions!$B$4>(Assumptions!$B$4/B95)*N105,"preference","convert") | C106: =IF(Assumptions!$B$45>(Assumptions!$B$39+F95)*N105,"preference","convert") | D106: =IF(Assumptions!$B$44>(Assumptions!$B$38+E95)*N105,"preference","convert") | E106: =IF(Assumptions!$B$43>Assumptions!$B$36*N105,"preference","convert") | F106: =IF(Assumptions!$B$42>Assumptions!$B$35*N105,"preference","convert") | G106: =IF(Assumptions!$B$41>Assumptions!$B$34*N105,"preference","convert") | H106: =IF(Assumptions!$B$40>Assumptions!$B$33*N105,"preference","convert") | I106: =IF(B106="preference",Assumptions!$B$4,0)+IF(C106="preference",Assumptions!$B$45,0)+IF(D106="preference",Assumptions!$B$44,0)+IF(E106="preference",Assumptions!$B$43,0)+IF(F106="preference",Assumptions!$B$42,0)+IF(G106="preference",Assumptions!$B$41,0)+IF(H106="preference",Assumptions!$B$40,0) | J106: =IF(B106="convert",(Assumptions!$B$4/B95),0)+IF(C106="convert",(Assumptions!$B$39+F95),0)+IF(D106="convert",(Assumptions!$B$38+E95),0)+IF(E106="convert",Assumptions!$B$36,0)+IF(F106="convert",Assumptions!$B$35,0)+IF(G106="convert",Assumptions!$B$34,0)+IF(H106="convert",Assumptions!$B$33,0) | K106: =(Assumptions!$B$46+Assumptions!$B$47+Assumptions!$B$48)+Assumptions!$B$49+(H95+I95)+J106 | L106: =(Assumptions!$B$13-I106+Assumptions!$B$31*Assumptions!$B$10)/(K106+Assumptions!$B$31) | M106: =IF(L106>Assumptions!$B$10,"yes","no") | N106: =IF(M106="yes",L106,MAX(0,(Assumptions!$B$13-I106)/K106)) | O106: =IF(M106="yes",Assumptions!$B$31*(N106-Assumptions!$B$10),0)
A107: iter 7 | B107: =IF(Assumptions!$B$4>(Assumptions!$B$4/B95)*N106,"preference","convert") | C107: =IF(Assumptions!$B$45>(Assumptions!$B$39+F95)*N106,"preference","convert") | D107: =IF(Assumptions!$B$44>(Assumptions!$B$38+E95)*N106,"preference","convert") | E107: =IF(Assumptions!$B$43>Assumptions!$B$36*N106,"preference","convert") | F107: =IF(Assumptions!$B$42>Assumptions!$B$35*N106,"preference","convert") | G107: =IF(Assumptions!$B$41>Assumptions!$B$34*N106,"preference","convert") | H107: =IF(Assumptions!$B$40>Assumptions!$B$33*N106,"preference","convert") | I107: =IF(B107="preference",Assumptions!$B$4,0)+IF(C107="preference",Assumptions!$B$45,0)+IF(D107="preference",Assumptions!$B$44,0)+IF(E107="preference",Assumptions!$B$43,0)+IF(F107="preference",Assumptions!$B$42,0)+IF(G107="preference",Assumptions!$B$41,0)+IF(H107="preference",Assumptions!$B$40,0) | J107: =IF(B107="convert",(Assumptions!$B$4/B95),0)+IF(C107="convert",(Assumptions!$B$39+F95),0)+IF(D107="convert",(Assumptions!$B$38+E95),0)+IF(E107="convert",Assumptions!$B$36,0)+IF(F107="convert",Assumptions!$B$35,0)+IF(G107="convert",Assumptions!$B$34,0)+IF(H107="convert",Assumptions!$B$33,0) | K107: =(Assumptions!$B$46+Assumptions!$B$47+Assumptions!$B$48)+Assumptions!$B$49+(H95+I95)+J107 | L107: =(Assumptions!$B$13-I107+Assumptions!$B$31*Assumptions!$B$10)/(K107+Assumptions!$B$31) | M107: =IF(L107>Assumptions!$B$10,"yes","no") | N107: =IF(M107="yes",L107,MAX(0,(Assumptions!$B$13-I107)/K107)) | O107: =IF(M107="yes",Assumptions!$B$31*(N107-Assumptions!$B$10),0)
A108: iter 8 | B108: =IF(Assumptions!$B$4>(Assumptions!$B$4/B95)*N107,"preference","convert") | C108: =IF(Assumptions!$B$45>(Assumptions!$B$39+F95)*N107,"preference","convert") | D108: =IF(Assumptions!$B$44>(Assumptions!$B$38+E95)*N107,"preference","convert") | E108: =IF(Assumptions!$B$43>Assumptions!$B$36*N107,"preference","convert") | F108: =IF(Assumptions!$B$42>Assumptions!$B$35*N107,"preference","convert") | G108: =IF(Assumptions!$B$41>Assumptions!$B$34*N107,"preference","convert") | H108: =IF(Assumptions!$B$40>Assumptions!$B$33*N107,"preference","convert") | I108: =IF(B108="preference",Assumptions!$B$4,0)+IF(C108="preference",Assumptions!$B$45,0)+IF(D108="preference",Assumptions!$B$44,0)+IF(E108="preference",Assumptions!$B$43,0)+IF(F108="preference",Assumptions!$B$42,0)+IF(G108="preference",Assumptions!$B$41,0)+IF(H108="preference",Assumptions!$B$40,0) | J108: =IF(B108="convert",(Assumptions!$B$4/B95),0)+IF(C108="convert",(Assumptions!$B$39+F95),0)+IF(D108="convert",(Assumptions!$B$38+E95),0)+IF(E108="convert",Assumptions!$B$36,0)+IF(F108="convert",Assumptions!$B$35,0)+IF(G108="convert",Assumptions!$B$34,0)+IF(H108="convert",Assumptions!$B$33,0) | K108: =(Assumptions!$B$46+Assumptions!$B$47+Assumptions!$B$48)+Assumptions!$B$49+(H95+I95)+J108 | L108: =(Assumptions!$B$13-I108+Assumptions!$B$31*Assumptions!$B$10)/(K108+Assumptions!$B$31) | M108: =IF(L108>Assumptions!$B$10,"yes","no") | N108: =IF(M108="yes",L108,MAX(0,(Assumptions!$B$13-I108)/K108)) | O108: =IF(M108="yes",Assumptions!$B$31*(N108-Assumptions!$B$10),0)
A109: iter 9 | B109: =IF(Assumptions!$B$4>(Assumptions!$B$4/B95)*N108,"preference","convert") | C109: =IF(Assumptions!$B$45>(Assumptions!$B$39+F95)*N108,"preference","convert") | D109: =IF(Assumptions!$B$44>(Assumptions!$B$38+E95)*N108,"preference","convert") | E109: =IF(Assumptions!$B$43>Assumptions!$B$36*N108,"preference","convert") | F109: =IF(Assumptions!$B$42>Assumptions!$B$35*N108,"preference","convert") | G109: =IF(Assumptions!$B$41>Assumptions!$B$34*N108,"preference","convert") | H109: =IF(Assumptions!$B$40>Assumptions!$B$33*N108,"preference","convert") | I109: =IF(B109="preference",Assumptions!$B$4,0)+IF(C109="preference",Assumptions!$B$45,0)+IF(D109="preference",Assumptions!$B$44,0)+IF(E109="preference",Assumptions!$B$43,0)+IF(F109="preference",Assumptions!$B$42,0)+IF(G109="preference",Assumptions!$B$41,0)+IF(H109="preference",Assumptions!$B$40,0) | J109: =IF(B109="convert",(Assumptions!$B$4/B95),0)+IF(C109="convert",(Assumptions!$B$39+F95),0)+IF(D109="convert",(Assumptions!$B$38+E95),0)+IF(E109="convert",Assumptions!$B$36,0)+IF(F109="convert",Assumptions!$B$35,0)+IF(G109="convert",Assumptions!$B$34,0)+IF(H109="convert",Assumptions!$B$33,0) | K109: =(Assumptions!$B$46+Assumptions!$B$47+Assumptions!$B$48)+Assumptions!$B$49+(H95+I95)+J109 | L109: =(Assumptions!$B$13-I109+Assumptions!$B$31*Assumptions!$B$10)/(K109+Assumptions!$B$31) | M109: =IF(L109>Assumptions!$B$10,"yes","no") | N109: =IF(M109="yes",L109,MAX(0,(Assumptions!$B$13-I109)/K109)) | O109: =IF(M109="yes",Assumptions!$B$31*(N109-Assumptions!$B$10),0)
A110: iter 10 | B110: =IF(Assumptions!$B$4>(Assumptions!$B$4/B95)*N109,"preference","convert") | C110: =IF(Assumptions!$B$45>(Assumptions!$B$39+F95)*N109,"preference","convert") | D110: =IF(Assumptions!$B$44>(Assumptions!$B$38+E95)*N109,"preference","convert") | E110: =IF(Assumptions!$B$43>Assumptions!$B$36*N109,"preference","convert") | F110: =IF(Assumptions!$B$42>Assumptions!$B$35*N109,"preference","convert") | G110: =IF(Assumptions!$B$41>Assumptions!$B$34*N109,"preference","convert") | H110: =IF(Assumptions!$B$40>Assumptions!$B$33*N109,"preference","convert") | I110: =IF(B110="preference",Assumptions!$B$4,0)+IF(C110="preference",Assumptions!$B$45,0)+IF(D110="preference",Assumptions!$B$44,0)+IF(E110="preference",Assumptions!$B$43,0)+IF(F110="preference",Assumptions!$B$42,0)+IF(G110="preference",Assumptions!$B$41,0)+IF(H110="preference",Assumptions!$B$40,0) | J110: =IF(B110="convert",(Assumptions!$B$4/B95),0)+IF(C110="convert",(Assumptions!$B$39+F95),0)+IF(D110="convert",(Assumptions!$B$38+E95),0)+IF(E110="convert",Assumptions!$B$36,0)+IF(F110="convert",Assumptions!$B$35,0)+IF(G110="convert",Assumptions!$B$34,0)+IF(H110="convert",Assumptions!$B$33,0) | K110: =(Assumptions!$B$46+Assumptions!$B$47+Assumptions!$B$48)+Assumptions!$B$49+(H95+I95)+J110 | L110: =(Assumptions!$B$13-I110+Assumptions!$B$31*Assumptions!$B$10)/(K110+Assumptions!$B$31) | M110: =IF(L110>Assumptions!$B$10,"yes","no") | N110: =IF(M110="yes",L110,MAX(0,(Assumptions!$B$13-I110)/K110)) | O110: =IF(M110="yes",Assumptions!$B$31*(N110-Assumptions!$B$10),0)
A111: iter 11 | B111: =IF(Assumptions!$B$4>(Assumptions!$B$4/B95)*N110,"preference","convert") | C111: =IF(Assumptions!$B$45>(Assumptions!$B$39+F95)*N110,"preference","convert") | D111: =IF(Assumptions!$B$44>(Assumptions!$B$38+E95)*N110,"preference","convert") | E111: =IF(Assumptions!$B$43>Assumptions!$B$36*N110,"preference","convert") | F111: =IF(Assumptions!$B$42>Assumptions!$B$35*N110,"preference","convert") | G111: =IF(Assumptions!$B$41>Assumptions!$B$34*N110,"preference","convert") | H111: =IF(Assumptions!$B$40>Assumptions!$B$33*N110,"preference","convert") | I111: =IF(B111="preference",Assumptions!$B$4,0)+IF(C111="preference",Assumptions!$B$45,0)+IF(D111="preference",Assumptions!$B$44,0)+IF(E111="preference",Assumptions!$B$43,0)+IF(F111="preference",Assumptions!$B$42,0)+IF(G111="preference",Assumptions!$B$41,0)+IF(H111="preference",Assumptions!$B$40,0) | J111: =IF(B111="convert",(Assumptions!$B$4/B95),0)+IF(C111="convert",(Assumptions!$B$39+F95),0)+IF(D111="convert",(Assumptions!$B$38+E95),0)+IF(E111="convert",Assumptions!$B$36,0)+IF(F111="convert",Assumptions!$B$35,0)+IF(G111="convert",Assumptions!$B$34,0)+IF(H111="convert",Assumptions!$B$33,0) | K111: =(Assumptions!$B$46+Assumptions!$B$47+Assumptions!$B$48)+Assumptions!$B$49+(H95+I95)+J111 | L111: =(Assumptions!$B$13-I111+Assumptions!$B$31*Assumptions!$B$10)/(K111+Assumptions!$B$31) | M111: =IF(L111>Assumptions!$B$10,"yes","no") | N111: =IF(M111="yes",L111,MAX(0,(Assumptions!$B$13-I111)/K111)) | O111: =IF(M111="yes",Assumptions!$B$31*(N111-Assumptions!$B$10),0)
A112: iter 12 | B112: =IF(Assumptions!$B$4>(Assumptions!$B$4/B95)*N111,"preference","convert") | C112: =IF(Assumptions!$B$45>(Assumptions!$B$39+F95)*N111,"preference","convert") | D112: =IF(Assumptions!$B$44>(Assumptions!$B$38+E95)*N111,"preference","convert") | E112: =IF(Assumptions!$B$43>Assumptions!$B$36*N111,"preference","convert") | F112: =IF(Assumptions!$B$42>Assumptions!$B$35*N111,"preference","convert") | G112: =IF(Assumptions!$B$41>Assumptions!$B$34*N111,"preference","convert") | H112: =IF(Assumptions!$B$40>Assumptions!$B$33*N111,"preference","convert") | I112: =IF(B112="preference",Assumptions!$B$4,0)+IF(C112="preference",Assumptions!$B$45,0)+IF(D112="preference",Assumptions!$B$44,0)+IF(E112="preference",Assumptions!$B$43,0)+IF(F112="preference",Assumptions!$B$42,0)+IF(G112="preference",Assumptions!$B$41,0)+IF(H112="preference",Assumptions!$B$40,0) | J112: =IF(B112="convert",(Assumptions!$B$4/B95),0)+IF(C112="convert",(Assumptions!$B$39+F95),0)+IF(D112="convert",(Assumptions!$B$38+E95),0)+IF(E112="convert",Assumptions!$B$36,0)+IF(F112="convert",Assumptions!$B$35,0)+IF(G112="convert",Assumptions!$B$34,0)+IF(H112="convert",Assumptions!$B$33,0) | K112: =(Assumptions!$B$46+Assumptions!$B$47+Assumptions!$B$48)+Assumptions!$B$49+(H95+I95)+J112 | L112: =(Assumptions!$B$13-I112+Assumptions!$B$31*Assumptions!$B$10)/(K112+Assumptions!$B$31) | M112: =IF(L112>Assumptions!$B$10,"yes","no") | N112: =IF(M112="yes",L112,MAX(0,(Assumptions!$B$13-I112)/K112)) | O112: =IF(M112="yes",Assumptions!$B$31*(N112-Assumptions!$B$10),0)
A113: iter 13 | B113: =IF(Assumptions!$B$4>(Assumptions!$B$4/B95)*N112,"preference","convert") | C113: =IF(Assumptions!$B$45>(Assumptions!$B$39+F95)*N112,"preference","convert") | D113: =IF(Assumptions!$B$44>(Assumptions!$B$38+E95)*N112,"preference","convert") | E113: =IF(Assumptions!$B$43>Assumptions!$B$36*N112,"preference","convert") | F113: =IF(Assumptions!$B$42>Assumptions!$B$35*N112,"preference","convert") | G113: =IF(Assumptions!$B$41>Assumptions!$B$34*N112,"preference","convert") | H113: =IF(Assumptions!$B$40>Assumptions!$B$33*N112,"preference","convert") | I113: =IF(B113="preference",Assumptions!$B$4,0)+IF(C113="preference",Assumptions!$B$45,0)+IF(D113="preference",Assumptions!$B$44,0)+IF(E113="preference",Assumptions!$B$43,0)+IF(F113="preference",Assumptions!$B$42,0)+IF(G113="preference",Assumptions!$B$41,0)+IF(H113="preference",Assumptions!$B$40,0) | J113: =IF(B113="convert",(Assumptions!$B$4/B95),0)+IF(C113="convert",(Assumptions!$B$39+F95),0)+IF(D113="convert",(Assumptions!$B$38+E95),0)+IF(E113="convert",Assumptions!$B$36,0)+IF(F113="convert",Assumptions!$B$35,0)+IF(G113="convert",Assumptions!$B$34,0)+IF(H113="convert",Assumptions!$B$33,0) | K113: =(Assumptions!$B$46+Assumptions!$B$47+Assumptions!$B$48)+Assumptions!$B$49+(H95+I95)+J113 | L113: =(Assumptions!$B$13-I113+Assumptions!$B$31*Assumptions!$B$10)/(K113+Assumptions!$B$31) | M113: =IF(L113>Assumptions!$B$10,"yes","no") | N113: =IF(M113="yes",L113,MAX(0,(Assumptions!$B$13-I113)/K113)) | O113: =IF(M113="yes",Assumptions!$B$31*(N113-Assumptions!$B$10),0)
A114: iter 14 | B114: =IF(Assumptions!$B$4>(Assumptions!$B$4/B95)*N113,"preference","convert") | C114: =IF(Assumptions!$B$45>(Assumptions!$B$39+F95)*N113,"preference","convert") | D114: =IF(Assumptions!$B$44>(Assumptions!$B$38+E95)*N113,"preference","convert") | E114: =IF(Assumptions!$B$43>Assumptions!$B$36*N113,"preference","convert") | F114: =IF(Assumptions!$B$42>Assumptions!$B$35*N113,"preference","convert") | G114: =IF(Assumptions!$B$41>Assumptions!$B$34*N113,"preference","convert") | H114: =IF(Assumptions!$B$40>Assumptions!$B$33*N113,"preference","convert") | I114: =IF(B114="preference",Assumptions!$B$4,0)+IF(C114="preference",Assumptions!$B$45,0)+IF(D114="preference",Assumptions!$B$44,0)+IF(E114="preference",Assumptions!$B$43,0)+IF(F114="preference",Assumptions!$B$42,0)+IF(G114="preference",Assumptions!$B$41,0)+IF(H114="preference",Assumptions!$B$40,0) | J114: =IF(B114="convert",(Assumptions!$B$4/B95),0)+IF(C114="convert",(Assumptions!$B$39+F95),0)+IF(D114="convert",(Assumptions!$B$38+E95),0)+IF(E114="convert",Assumptions!$B$36,0)+IF(F114="convert",Assumptions!$B$35,0)+IF(G114="convert",Assumptions!$B$34,0)+IF(H114="convert",Assumptions!$B$33,0) | K114: =(Assumptions!$B$46+Assumptions!$B$47+Assumptions!$B$48)+Assumptions!$B$49+(H95+I95)+J114 | L114: =(Assumptions!$B$13-I114+Assumptions!$B$31*Assumptions!$B$10)/(K114+Assumptions!$B$31) | M114: =IF(L114>Assumptions!$B$10,"yes","no") | N114: =IF(M114="yes",L114,MAX(0,(Assumptions!$B$13-I114)/K114)) | O114: =IF(M114="yes",Assumptions!$B$31*(N114-Assumptions!$B$10),0)
A115: iter 15 | B115: =IF(Assumptions!$B$4>(Assumptions!$B$4/B95)*N114,"preference","convert") | C115: =IF(Assumptions!$B$45>(Assumptions!$B$39+F95)*N114,"preference","convert") | D115: =IF(Assumptions!$B$44>(Assumptions!$B$38+E95)*N114,"preference","convert") | E115: =IF(Assumptions!$B$43>Assumptions!$B$36*N114,"preference","convert") | F115: =IF(Assumptions!$B$42>Assumptions!$B$35*N114,"preference","convert") | G115: =IF(Assumptions!$B$41>Assumptions!$B$34*N114,"preference","convert") | H115: =IF(Assumptions!$B$40>Assumptions!$B$33*N114,"preference","convert") | I115: =IF(B115="preference",Assumptions!$B$4,0)+IF(C115="preference",Assumptions!$B$45,0)+IF(D115="preference",Assumptions!$B$44,0)+IF(E115="preference",Assumptions!$B$43,0)+IF(F115="preference",Assumptions!$B$42,0)+IF(G115="preference",Assumptions!$B$41,0)+IF(H115="preference",Assumptions!$B$40,0) | J115: =IF(B115="convert",(Assumptions!$B$4/B95),0)+IF(C115="convert",(Assumptions!$B$39+F95),0)+IF(D115="convert",(Assumptions!$B$38+E95),0)+IF(E115="convert",Assumptions!$B$36,0)+IF(F115="convert",Assumptions!$B$35,0)+IF(G115="convert",Assumptions!$B$34,0)+IF(H115="convert",Assumptions!$B$33,0) | K115: =(Assumptions!$B$46+Assumptions!$B$47+Assumptions!$B$48)+Assumptions!$B$49+(H95+I95)+J115 | L115: =(Assumptions!$B$13-I115+Assumptions!$B$31*Assumptions!$B$10)/(K115+Assumptions!$B$31) | M115: =IF(L115>Assumptions!$B$10,"yes","no") | N115: =IF(M115="yes",L115,MAX(0,(Assumptions!$B$13-I115)/K115)) | O115: =IF(M115="yes",Assumptions!$B$31*(N115-Assumptions!$B$10),0)
A116: iter 16 | B116: =IF(Assumptions!$B$4>(Assumptions!$B$4/B95)*N115,"preference","convert") | C116: =IF(Assumptions!$B$45>(Assumptions!$B$39+F95)*N115,"preference","convert") | D116: =IF(Assumptions!$B$44>(Assumptions!$B$38+E95)*N115,"preference","convert") | E116: =IF(Assumptions!$B$43>Assumptions!$B$36*N115,"preference","convert") | F116: =IF(Assumptions!$B$42>Assumptions!$B$35*N115,"preference","convert") | G116: =IF(Assumptions!$B$41>Assumptions!$B$34*N115,"preference","convert") | H116: =IF(Assumptions!$B$40>Assumptions!$B$33*N115,"preference","convert") | I116: =IF(B116="preference",Assumptions!$B$4,0)+IF(C116="preference",Assumptions!$B$45,0)+IF(D116="preference",Assumptions!$B$44,0)+IF(E116="preference",Assumptions!$B$43,0)+IF(F116="preference",Assumptions!$B$42,0)+IF(G116="preference",Assumptions!$B$41,0)+IF(H116="preference",Assumptions!$B$40,0) | J116: =IF(B116="convert",(Assumptions!$B$4/B95),0)+IF(C116="convert",(Assumptions!$B$39+F95),0)+IF(D116="convert",(Assumptions!$B$38+E95),0)+IF(E116="convert",Assumptions!$B$36,0)+IF(F116="convert",Assumptions!$B$35,0)+IF(G116="convert",Assumptions!$B$34,0)+IF(H116="convert",Assumptions!$B$33,0) | K116: =(Assumptions!$B$46+Assumptions!$B$47+Assumptions!$B$48)+Assumptions!$B$49+(H95+I95)+J116 | L116: =(Assumptions!$B$13-I116+Assumptions!$B$31*Assumptions!$B$10)/(K116+Assumptions!$B$31) | M116: =IF(L116>Assumptions!$B$10,"yes","no") | N116: =IF(M116="yes",L116,MAX(0,(Assumptions!$B$13-I116)/K116)) | O116: =IF(M116="yes",Assumptions!$B$31*(N116-Assumptions!$B$10),0)
A117: iter 17 | B117: =IF(Assumptions!$B$4>(Assumptions!$B$4/B95)*N116,"preference","convert") | C117: =IF(Assumptions!$B$45>(Assumptions!$B$39+F95)*N116,"preference","convert") | D117: =IF(Assumptions!$B$44>(Assumptions!$B$38+E95)*N116,"preference","convert") | E117: =IF(Assumptions!$B$43>Assumptions!$B$36*N116,"preference","convert") | F117: =IF(Assumptions!$B$42>Assumptions!$B$35*N116,"preference","convert") | G117: =IF(Assumptions!$B$41>Assumptions!$B$34*N116,"preference","convert") | H117: =IF(Assumptions!$B$40>Assumptions!$B$33*N116,"preference","convert") | I117: =IF(B117="preference",Assumptions!$B$4,0)+IF(C117="preference",Assumptions!$B$45,0)+IF(D117="preference",Assumptions!$B$44,0)+IF(E117="preference",Assumptions!$B$43,0)+IF(F117="preference",Assumptions!$B$42,0)+IF(G117="preference",Assumptions!$B$41,0)+IF(H117="preference",Assumptions!$B$40,0) | J117: =IF(B117="convert",(Assumptions!$B$4/B95),0)+IF(C117="convert",(Assumptions!$B$39+F95),0)+IF(D117="convert",(Assumptions!$B$38+E95),0)+IF(E117="convert",Assumptions!$B$36,0)+IF(F117="convert",Assumptions!$B$35,0)+IF(G117="convert",Assumptions!$B$34,0)+IF(H117="convert",Assumptions!$B$33,0) | K117: =(Assumptions!$B$46+Assumptions!$B$47+Assumptions!$B$48)+Assumptions!$B$49+(H95+I95)+J117 | L117: =(Assumptions!$B$13-I117+Assumptions!$B$31*Assumptions!$B$10)/(K117+Assumptions!$B$31) | M117: =IF(L117>Assumptions!$B$10,"yes","no") | N117: =IF(M117="yes",L117,MAX(0,(Assumptions!$B$13-I117)/K117)) | O117: =IF(M117="yes",Assumptions!$B$31*(N117-Assumptions!$B$10),0)
A118: iter 18 | B118: =IF(Assumptions!$B$4>(Assumptions!$B$4/B95)*N117,"preference","convert") | C118: =IF(Assumptions!$B$45>(Assumptions!$B$39+F95)*N117,"preference","convert") | D118: =IF(Assumptions!$B$44>(Assumptions!$B$38+E95)*N117,"preference","convert") | E118: =IF(Assumptions!$B$43>Assumptions!$B$36*N117,"preference","convert") | F118: =IF(Assumptions!$B$42>Assumptions!$B$35*N117,"preference","convert") | G118: =IF(Assumptions!$B$41>Assumptions!$B$34*N117,"preference","convert") | H118: =IF(Assumptions!$B$40>Assumptions!$B$33*N117,"preference","convert") | I118: =IF(B118="preference",Assumptions!$B$4,0)+IF(C118="preference",Assumptions!$B$45,0)+IF(D118="preference",Assumptions!$B$44,0)+IF(E118="preference",Assumptions!$B$43,0)+IF(F118="preference",Assumptions!$B$42,0)+IF(G118="preference",Assumptions!$B$41,0)+IF(H118="preference",Assumptions!$B$40,0) | J118: =IF(B118="convert",(Assumptions!$B$4/B95),0)+IF(C118="convert",(Assumptions!$B$39+F95),0)+IF(D118="convert",(Assumptions!$B$38+E95),0)+IF(E118="convert",Assumptions!$B$36,0)+IF(F118="convert",Assumptions!$B$35,0)+IF(G118="convert",Assumptions!$B$34,0)+IF(H118="convert",Assumptions!$B$33,0) | K118: =(Assumptions!$B$46+Assumptions!$B$47+Assumptions!$B$48)+Assumptions!$B$49+(H95+I95)+J118 | L118: =(Assumptions!$B$13-I118+Assumptions!$B$31*Assumptions!$B$10)/(K118+Assumptions!$B$31) | M118: =IF(L118>Assumptions!$B$10,"yes","no") | N118: =IF(M118="yes",L118,MAX(0,(Assumptions!$B$13-I118)/K118)) | O118: =IF(M118="yes",Assumptions!$B$31*(N118-Assumptions!$B$10),0)
A119: iter 19 | B119: =IF(Assumptions!$B$4>(Assumptions!$B$4/B95)*N118,"preference","convert") | C119: =IF(Assumptions!$B$45>(Assumptions!$B$39+F95)*N118,"preference","convert") | D119: =IF(Assumptions!$B$44>(Assumptions!$B$38+E95)*N118,"preference","convert") | E119: =IF(Assumptions!$B$43>Assumptions!$B$36*N118,"preference","convert") | F119: =IF(Assumptions!$B$42>Assumptions!$B$35*N118,"preference","convert") | G119: =IF(Assumptions!$B$41>Assumptions!$B$34*N118,"preference","convert") | H119: =IF(Assumptions!$B$40>Assumptions!$B$33*N118,"preference","convert") | I119: =IF(B119="preference",Assumptions!$B$4,0)+IF(C119="preference",Assumptions!$B$45,0)+IF(D119="preference",Assumptions!$B$44,0)+IF(E119="preference",Assumptions!$B$43,0)+IF(F119="preference",Assumptions!$B$42,0)+IF(G119="preference",Assumptions!$B$41,0)+IF(H119="preference",Assumptions!$B$40,0) | J119: =IF(B119="convert",(Assumptions!$B$4/B95),0)+IF(C119="convert",(Assumptions!$B$39+F95),0)+IF(D119="convert",(Assumptions!$B$38+E95),0)+IF(E119="convert",Assumptions!$B$36,0)+IF(F119="convert",Assumptions!$B$35,0)+IF(G119="convert",Assumptions!$B$34,0)+IF(H119="convert",Assumptions!$B$33,0) | K119: =(Assumptions!$B$46+Assumptions!$B$47+Assumptions!$B$48)+Assumptions!$B$49+(H95+I95)+J119 | L119: =(Assumptions!$B$13-I119+Assumptions!$B$31*Assumptions!$B$10)/(K119+Assumptions!$B$31) | M119: =IF(L119>Assumptions!$B$10,"yes","no") | N119: =IF(M119="yes",L119,MAX(0,(Assumptions!$B$13-I119)/K119)) | O119: =IF(M119="yes",Assumptions!$B$31*(N119-Assumptions!$B$10),0)
A120: iter 20 | B120: =IF(Assumptions!$B$4>(Assumptions!$B$4/B95)*N119,"preference","convert") | C120: =IF(Assumptions!$B$45>(Assumptions!$B$39+F95)*N119,"preference","convert") | D120: =IF(Assumptions!$B$44>(Assumptions!$B$38+E95)*N119,"preference","convert") | E120: =IF(Assumptions!$B$43>Assumptions!$B$36*N119,"preference","convert") | F120: =IF(Assumptions!$B$42>Assumptions!$B$35*N119,"preference","convert") | G120: =IF(Assumptions!$B$41>Assumptions!$B$34*N119,"preference","convert") | H120: =IF(Assumptions!$B$40>Assumptions!$B$33*N119,"preference","convert") | I120: =IF(B120="preference",Assumptions!$B$4,0)+IF(C120="preference",Assumptions!$B$45,0)+IF(D120="preference",Assumptions!$B$44,0)+IF(E120="preference",Assumptions!$B$43,0)+IF(F120="preference",Assumptions!$B$42,0)+IF(G120="preference",Assumptions!$B$41,0)+IF(H120="preference",Assumptions!$B$40,0) | J120: =IF(B120="convert",(Assumptions!$B$4/B95),0)+IF(C120="convert",(Assumptions!$B$39+F95),0)+IF(D120="convert",(Assumptions!$B$38+E95),0)+IF(E120="convert",Assumptions!$B$36,0)+IF(F120="convert",Assumptions!$B$35,0)+IF(G120="convert",Assumptions!$B$34,0)+IF(H120="convert",Assumptions!$B$33,0) | K120: =(Assumptions!$B$46+Assumptions!$B$47+Assumptions!$B$48)+Assumptions!$B$49+(H95+I95)+J120 | L120: =(Assumptions!$B$13-I120+Assumptions!$B$31*Assumptions!$B$10)/(K120+Assumptions!$B$31) | M120: =IF(L120>Assumptions!$B$10,"yes","no") | N120: =IF(M120="yes",L120,MAX(0,(Assumptions!$B$13-I120)/K120)) | O120: =IF(M120="yes",Assumptions!$B$31*(N120-Assumptions!$B$10),0)
A121: iter 21 | B121: =IF(Assumptions!$B$4>(Assumptions!$B$4/B95)*N120,"preference","convert") | C121: =IF(Assumptions!$B$45>(Assumptions!$B$39+F95)*N120,"preference","convert") | D121: =IF(Assumptions!$B$44>(Assumptions!$B$38+E95)*N120,"preference","convert") | E121: =IF(Assumptions!$B$43>Assumptions!$B$36*N120,"preference","convert") | F121: =IF(Assumptions!$B$42>Assumptions!$B$35*N120,"preference","convert") | G121: =IF(Assumptions!$B$41>Assumptions!$B$34*N120,"preference","convert") | H121: =IF(Assumptions!$B$40>Assumptions!$B$33*N120,"preference","convert") | I121: =IF(B121="preference",Assumptions!$B$4,0)+IF(C121="preference",Assumptions!$B$45,0)+IF(D121="preference",Assumptions!$B$44,0)+IF(E121="preference",Assumptions!$B$43,0)+IF(F121="preference",Assumptions!$B$42,0)+IF(G121="preference",Assumptions!$B$41,0)+IF(H121="preference",Assumptions!$B$40,0) | J121: =IF(B121="convert",(Assumptions!$B$4/B95),0)+IF(C121="convert",(Assumptions!$B$39+F95),0)+IF(D121="convert",(Assumptions!$B$38+E95),0)+IF(E121="convert",Assumptions!$B$36,0)+IF(F121="convert",Assumptions!$B$35,0)+IF(G121="convert",Assumptions!$B$34,0)+IF(H121="convert",Assumptions!$B$33,0) | K121: =(Assumptions!$B$46+Assumptions!$B$47+Assumptions!$B$48)+Assumptions!$B$49+(H95+I95)+J121 | L121: =(Assumptions!$B$13-I121+Assumptions!$B$31*Assumptions!$B$10)/(K121+Assumptions!$B$31) | M121: =IF(L121>Assumptions!$B$10,"yes","no") | N121: =IF(M121="yes",L121,MAX(0,(Assumptions!$B$13-I121)/K121)) | O121: =IF(M121="yes",Assumptions!$B$31*(N121-Assumptions!$B$10),0)
A122: iter 22 | B122: =IF(Assumptions!$B$4>(Assumptions!$B$4/B95)*N121,"preference","convert") | C122: =IF(Assumptions!$B$45>(Assumptions!$B$39+F95)*N121,"preference","convert") | D122: =IF(Assumptions!$B$44>(Assumptions!$B$38+E95)*N121,"preference","convert") | E122: =IF(Assumptions!$B$43>Assumptions!$B$36*N121,"preference","convert") | F122: =IF(Assumptions!$B$42>Assumptions!$B$35*N121,"preference","convert") | G122: =IF(Assumptions!$B$41>Assumptions!$B$34*N121,"preference","convert") | H122: =IF(Assumptions!$B$40>Assumptions!$B$33*N121,"preference","convert") | I122: =IF(B122="preference",Assumptions!$B$4,0)+IF(C122="preference",Assumptions!$B$45,0)+IF(D122="preference",Assumptions!$B$44,0)+IF(E122="preference",Assumptions!$B$43,0)+IF(F122="preference",Assumptions!$B$42,0)+IF(G122="preference",Assumptions!$B$41,0)+IF(H122="preference",Assumptions!$B$40,0) | J122: =IF(B122="convert",(Assumptions!$B$4/B95),0)+IF(C122="convert",(Assumptions!$B$39+F95),0)+IF(D122="convert",(Assumptions!$B$38+E95),0)+IF(E122="convert",Assumptions!$B$36,0)+IF(F122="convert",Assumptions!$B$35,0)+IF(G122="convert",Assumptions!$B$34,0)+IF(H122="convert",Assumptions!$B$33,0) | K122: =(Assumptions!$B$46+Assumptions!$B$47+Assumptions!$B$48)+Assumptions!$B$49+(H95+I95)+J122 | L122: =(Assumptions!$B$13-I122+Assumptions!$B$31*Assumptions!$B$10)/(K122+Assumptions!$B$31) | M122: =IF(L122>Assumptions!$B$10,"yes","no") | N122: =IF(M122="yes",L122,MAX(0,(Assumptions!$B$13-I122)/K122)) | O122: =IF(M122="yes",Assumptions!$B$31*(N122-Assumptions!$B$10),0)
A123: iter 23 | B123: =IF(Assumptions!$B$4>(Assumptions!$B$4/B95)*N122,"preference","convert") | C123: =IF(Assumptions!$B$45>(Assumptions!$B$39+F95)*N122,"preference","convert") | D123: =IF(Assumptions!$B$44>(Assumptions!$B$38+E95)*N122,"preference","convert") | E123: =IF(Assumptions!$B$43>Assumptions!$B$36*N122,"preference","convert") | F123: =IF(Assumptions!$B$42>Assumptions!$B$35*N122,"preference","convert") | G123: =IF(Assumptions!$B$41>Assumptions!$B$34*N122,"preference","convert") | H123: =IF(Assumptions!$B$40>Assumptions!$B$33*N122,"preference","convert") | I123: =IF(B123="preference",Assumptions!$B$4,0)+IF(C123="preference",Assumptions!$B$45,0)+IF(D123="preference",Assumptions!$B$44,0)+IF(E123="preference",Assumptions!$B$43,0)+IF(F123="preference",Assumptions!$B$42,0)+IF(G123="preference",Assumptions!$B$41,0)+IF(H123="preference",Assumptions!$B$40,0) | J123: =IF(B123="convert",(Assumptions!$B$4/B95),0)+IF(C123="convert",(Assumptions!$B$39+F95),0)+IF(D123="convert",(Assumptions!$B$38+E95),0)+IF(E123="convert",Assumptions!$B$36,0)+IF(F123="convert",Assumptions!$B$35,0)+IF(G123="convert",Assumptions!$B$34,0)+IF(H123="convert",Assumptions!$B$33,0) | K123: =(Assumptions!$B$46+Assumptions!$B$47+Assumptions!$B$48)+Assumptions!$B$49+(H95+I95)+J123 | L123: =(Assumptions!$B$13-I123+Assumptions!$B$31*Assumptions!$B$10)/(K123+Assumptions!$B$31) | M123: =IF(L123>Assumptions!$B$10,"yes","no") | N123: =IF(M123="yes",L123,MAX(0,(Assumptions!$B$13-I123)/K123)) | O123: =IF(M123="yes",Assumptions!$B$31*(N123-Assumptions!$B$10),0)
A124: iter 24 | B124: =IF(Assumptions!$B$4>(Assumptions!$B$4/B95)*N123,"preference","convert") | C124: =IF(Assumptions!$B$45>(Assumptions!$B$39+F95)*N123,"preference","convert") | D124: =IF(Assumptions!$B$44>(Assumptions!$B$38+E95)*N123,"preference","convert") | E124: =IF(Assumptions!$B$43>Assumptions!$B$36*N123,"preference","convert") | F124: =IF(Assumptions!$B$42>Assumptions!$B$35*N123,"preference","convert") | G124: =IF(Assumptions!$B$41>Assumptions!$B$34*N123,"preference","convert") | H124: =IF(Assumptions!$B$40>Assumptions!$B$33*N123,"preference","convert") | I124: =IF(B124="preference",Assumptions!$B$4,0)+IF(C124="preference",Assumptions!$B$45,0)+IF(D124="preference",Assumptions!$B$44,0)+IF(E124="preference",Assumptions!$B$43,0)+IF(F124="preference",Assumptions!$B$42,0)+IF(G124="preference",Assumptions!$B$41,0)+IF(H124="preference",Assumptions!$B$40,0) | J124: =IF(B124="convert",(Assumptions!$B$4/B95),0)+IF(C124="convert",(Assumptions!$B$39+F95),0)+IF(D124="convert",(Assumptions!$B$38+E95),0)+IF(E124="convert",Assumptions!$B$36,0)+IF(F124="convert",Assumptions!$B$35,0)+IF(G124="convert",Assumptions!$B$34,0)+IF(H124="convert",Assumptions!$B$33,0) | K124: =(Assumptions!$B$46+Assumptions!$B$47+Assumptions!$B$48)+Assumptions!$B$49+(H95+I95)+J124 | L124: =(Assumptions!$B$13-I124+Assumptions!$B$31*Assumptions!$B$10)/(K124+Assumptions!$B$31) | M124: =IF(L124>Assumptions!$B$10,"yes","no") | N124: =IF(M124="yes",L124,MAX(0,(Assumptions!$B$13-I124)/K124)) | O124: =IF(M124="yes",Assumptions!$B$31*(N124-Assumptions!$B$10),0)
A125: iter 25 | B125: =IF(Assumptions!$B$4>(Assumptions!$B$4/B95)*N124,"preference","convert") | C125: =IF(Assumptions!$B$45>(Assumptions!$B$39+F95)*N124,"preference","convert") | D125: =IF(Assumptions!$B$44>(Assumptions!$B$38+E95)*N124,"preference","convert") | E125: =IF(Assumptions!$B$43>Assumptions!$B$36*N124,"preference","convert") | F125: =IF(Assumptions!$B$42>Assumptions!$B$35*N124,"preference","convert") | G125: =IF(Assumptions!$B$41>Assumptions!$B$34*N124,"preference","convert") | H125: =IF(Assumptions!$B$40>Assumptions!$B$33*N124,"preference","convert") | I125: =IF(B125="preference",Assumptions!$B$4,0)+IF(C125="preference",Assumptions!$B$45,0)+IF(D125="preference",Assumptions!$B$44,0)+IF(E125="preference",Assumptions!$B$43,0)+IF(F125="preference",Assumptions!$B$42,0)+IF(G125="preference",Assumptions!$B$41,0)+IF(H125="preference",Assumptions!$B$40,0) | J125: =IF(B125="convert",(Assumptions!$B$4/B95),0)+IF(C125="convert",(Assumptions!$B$39+F95),0)+IF(D125="convert",(Assumptions!$B$38+E95),0)+IF(E125="convert",Assumptions!$B$36,0)+IF(F125="convert",Assumptions!$B$35,0)+IF(G125="convert",Assumptions!$B$34,0)+IF(H125="convert",Assumptions!$B$33,0) | K125: =(Assumptions!$B$46+Assumptions!$B$47+Assumptions!$B$48)+Assumptions!$B$49+(H95+I95)+J125 | L125: =(Assumptions!$B$13-I125+Assumptions!$B$31*Assumptions!$B$10)/(K125+Assumptions!$B$31) | M125: =IF(L125>Assumptions!$B$10,"yes","no") | N125: =IF(M125="yes",L125,MAX(0,(Assumptions!$B$13-I125)/K125)) | O125: =IF(M125="yes",Assumptions!$B$31*(N125-Assumptions!$B$10),0)
A126: iter 26 | B126: =IF(Assumptions!$B$4>(Assumptions!$B$4/B95)*N125,"preference","convert") | C126: =IF(Assumptions!$B$45>(Assumptions!$B$39+F95)*N125,"preference","convert") | D126: =IF(Assumptions!$B$44>(Assumptions!$B$38+E95)*N125,"preference","convert") | E126: =IF(Assumptions!$B$43>Assumptions!$B$36*N125,"preference","convert") | F126: =IF(Assumptions!$B$42>Assumptions!$B$35*N125,"preference","convert") | G126: =IF(Assumptions!$B$41>Assumptions!$B$34*N125,"preference","convert") | H126: =IF(Assumptions!$B$40>Assumptions!$B$33*N125,"preference","convert") | I126: =IF(B126="preference",Assumptions!$B$4,0)+IF(C126="preference",Assumptions!$B$45,0)+IF(D126="preference",Assumptions!$B$44,0)+IF(E126="preference",Assumptions!$B$43,0)+IF(F126="preference",Assumptions!$B$42,0)+IF(G126="preference",Assumptions!$B$41,0)+IF(H126="preference",Assumptions!$B$40,0) | J126: =IF(B126="convert",(Assumptions!$B$4/B95),0)+IF(C126="convert",(Assumptions!$B$39+F95),0)+IF(D126="convert",(Assumptions!$B$38+E95),0)+IF(E126="convert",Assumptions!$B$36,0)+IF(F126="convert",Assumptions!$B$35,0)+IF(G126="convert",Assumptions!$B$34,0)+IF(H126="convert",Assumptions!$B$33,0) | K126: =(Assumptions!$B$46+Assumptions!$B$47+Assumptions!$B$48)+Assumptions!$B$49+(H95+I95)+J126 | L126: =(Assumptions!$B$13-I126+Assumptions!$B$31*Assumptions!$B$10)/(K126+Assumptions!$B$31) | M126: =IF(L126>Assumptions!$B$10,"yes","no") | N126: =IF(M126="yes",L126,MAX(0,(Assumptions!$B$13-I126)/K126)) | O126: =IF(M126="yes",Assumptions!$B$31*(N126-Assumptions!$B$10),0)
A127: iter 27 | B127: =IF(Assumptions!$B$4>(Assumptions!$B$4/B95)*N126,"preference","convert") | C127: =IF(Assumptions!$B$45>(Assumptions!$B$39+F95)*N126,"preference","convert") | D127: =IF(Assumptions!$B$44>(Assumptions!$B$38+E95)*N126,"preference","convert") | E127: =IF(Assumptions!$B$43>Assumptions!$B$36*N126,"preference","convert") | F127: =IF(Assumptions!$B$42>Assumptions!$B$35*N126,"preference","convert") | G127: =IF(Assumptions!$B$41>Assumptions!$B$34*N126,"preference","convert") | H127: =IF(Assumptions!$B$40>Assumptions!$B$33*N126,"preference","convert") | I127: =IF(B127="preference",Assumptions!$B$4,0)+IF(C127="preference",Assumptions!$B$45,0)+IF(D127="preference",Assumptions!$B$44,0)+IF(E127="preference",Assumptions!$B$43,0)+IF(F127="preference",Assumptions!$B$42,0)+IF(G127="preference",Assumptions!$B$41,0)+IF(H127="preference",Assumptions!$B$40,0) | J127: =IF(B127="convert",(Assumptions!$B$4/B95),0)+IF(C127="convert",(Assumptions!$B$39+F95),0)+IF(D127="convert",(Assumptions!$B$38+E95),0)+IF(E127="convert",Assumptions!$B$36,0)+IF(F127="convert",Assumptions!$B$35,0)+IF(G127="convert",Assumptions!$B$34,0)+IF(H127="convert",Assumptions!$B$33,0) | K127: =(Assumptions!$B$46+Assumptions!$B$47+Assumptions!$B$48)+Assumptions!$B$49+(H95+I95)+J127 | L127: =(Assumptions!$B$13-I127+Assumptions!$B$31*Assumptions!$B$10)/(K127+Assumptions!$B$31) | M127: =IF(L127>Assumptions!$B$10,"yes","no") | N127: =IF(M127="yes",L127,MAX(0,(Assumptions!$B$13-I127)/K127)) | O127: =IF(M127="yes",Assumptions!$B$31*(N127-Assumptions!$B$10),0)
A128: iter 28 | B128: =IF(Assumptions!$B$4>(Assumptions!$B$4/B95)*N127,"preference","convert") | C128: =IF(Assumptions!$B$45>(Assumptions!$B$39+F95)*N127,"preference","convert") | D128: =IF(Assumptions!$B$44>(Assumptions!$B$38+E95)*N127,"preference","convert") | E128: =IF(Assumptions!$B$43>Assumptions!$B$36*N127,"preference","convert") | F128: =IF(Assumptions!$B$42>Assumptions!$B$35*N127,"preference","convert") | G128: =IF(Assumptions!$B$41>Assumptions!$B$34*N127,"preference","convert") | H128: =IF(Assumptions!$B$40>Assumptions!$B$33*N127,"preference","convert") | I128: =IF(B128="preference",Assumptions!$B$4,0)+IF(C128="preference",Assumptions!$B$45,0)+IF(D128="preference",Assumptions!$B$44,0)+IF(E128="preference",Assumptions!$B$43,0)+IF(F128="preference",Assumptions!$B$42,0)+IF(G128="preference",Assumptions!$B$41,0)+IF(H128="preference",Assumptions!$B$40,0) | J128: =IF(B128="convert",(Assumptions!$B$4/B95),0)+IF(C128="convert",(Assumptions!$B$39+F95),0)+IF(D128="convert",(Assumptions!$B$38+E95),0)+IF(E128="convert",Assumptions!$B$36,0)+IF(F128="convert",Assumptions!$B$35,0)+IF(G128="convert",Assumptions!$B$34,0)+IF(H128="convert",Assumptions!$B$33,0) | K128: =(Assumptions!$B$46+Assumptions!$B$47+Assumptions!$B$48)+Assumptions!$B$49+(H95+I95)+J128 | L128: =(Assumptions!$B$13-I128+Assumptions!$B$31*Assumptions!$B$10)/(K128+Assumptions!$B$31) | M128: =IF(L128>Assumptions!$B$10,"yes","no") | N128: =IF(M128="yes",L128,MAX(0,(Assumptions!$B$13-I128)/K128)) | O128: =IF(M128="yes",Assumptions!$B$31*(N128-Assumptions!$B$10),0)
A129: iter 29 | B129: =IF(Assumptions!$B$4>(Assumptions!$B$4/B95)*N128,"preference","convert") | C129: =IF(Assumptions!$B$45>(Assumptions!$B$39+F95)*N128,"preference","convert") | D129: =IF(Assumptions!$B$44>(Assumptions!$B$38+E95)*N128,"preference","convert") | E129: =IF(Assumptions!$B$43>Assumptions!$B$36*N128,"preference","convert") | F129: =IF(Assumptions!$B$42>Assumptions!$B$35*N128,"preference","convert") | G129: =IF(Assumptions!$B$41>Assumptions!$B$34*N128,"preference","convert") | H129: =IF(Assumptions!$B$40>Assumptions!$B$33*N128,"preference","convert") | I129: =IF(B129="preference",Assumptions!$B$4,0)+IF(C129="preference",Assumptions!$B$45,0)+IF(D129="preference",Assumptions!$B$44,0)+IF(E129="preference",Assumptions!$B$43,0)+IF(F129="preference",Assumptions!$B$42,0)+IF(G129="preference",Assumptions!$B$41,0)+IF(H129="preference",Assumptions!$B$40,0) | J129: =IF(B129="convert",(Assumptions!$B$4/B95),0)+IF(C129="convert",(Assumptions!$B$39+F95),0)+IF(D129="convert",(Assumptions!$B$38+E95),0)+IF(E129="convert",Assumptions!$B$36,0)+IF(F129="convert",Assumptions!$B$35,0)+IF(G129="convert",Assumptions!$B$34,0)+IF(H129="convert",Assumptions!$B$33,0) | K129: =(Assumptions!$B$46+Assumptions!$B$47+Assumptions!$B$48)+Assumptions!$B$49+(H95+I95)+J129 | L129: =(Assumptions!$B$13-I129+Assumptions!$B$31*Assumptions!$B$10)/(K129+Assumptions!$B$31) | M129: =IF(L129>Assumptions!$B$10,"yes","no") | N129: =IF(M129="yes",L129,MAX(0,(Assumptions!$B$13-I129)/K129)) | O129: =IF(M129="yes",Assumptions!$B$31*(N129-Assumptions!$B$10),0)
A130: iter 30 | B130: =IF(Assumptions!$B$4>(Assumptions!$B$4/B95)*N129,"preference","convert") | C130: =IF(Assumptions!$B$45>(Assumptions!$B$39+F95)*N129,"preference","convert") | D130: =IF(Assumptions!$B$44>(Assumptions!$B$38+E95)*N129,"preference","convert") | E130: =IF(Assumptions!$B$43>Assumptions!$B$36*N129,"preference","convert") | F130: =IF(Assumptions!$B$42>Assumptions!$B$35*N129,"preference","convert") | G130: =IF(Assumptions!$B$41>Assumptions!$B$34*N129,"preference","convert") | H130: =IF(Assumptions!$B$40>Assumptions!$B$33*N129,"preference","convert") | I130: =IF(B130="preference",Assumptions!$B$4,0)+IF(C130="preference",Assumptions!$B$45,0)+IF(D130="preference",Assumptions!$B$44,0)+IF(E130="preference",Assumptions!$B$43,0)+IF(F130="preference",Assumptions!$B$42,0)+IF(G130="preference",Assumptions!$B$41,0)+IF(H130="preference",Assumptions!$B$40,0) | J130: =IF(B130="convert",(Assumptions!$B$4/B95),0)+IF(C130="convert",(Assumptions!$B$39+F95),0)+IF(D130="convert",(Assumptions!$B$38+E95),0)+IF(E130="convert",Assumptions!$B$36,0)+IF(F130="convert",Assumptions!$B$35,0)+IF(G130="convert",Assumptions!$B$34,0)+IF(H130="convert",Assumptions!$B$33,0) | K130: =(Assumptions!$B$46+Assumptions!$B$47+Assumptions!$B$48)+Assumptions!$B$49+(H95+I95)+J130 | L130: =(Assumptions!$B$13-I130+Assumptions!$B$31*Assumptions!$B$10)/(K130+Assumptions!$B$31) | M130: =IF(L130>Assumptions!$B$10,"yes","no") | N130: =IF(M130="yes",L130,MAX(0,(Assumptions!$B$13-I130)/K130)) | O130: =IF(M130="yes",Assumptions!$B$31*(N130-Assumptions!$B$10),0)
A132: Our shares (post-F) | B132: =(Assumptions!$B$8/B95)
A133: Our ownership % (of T_F) | B133: =(Assumptions!$B$8/B95)/K95
A134: Our $ proceeds at $2B | B134: =IF(B130="convert",(Assumptions!$B$8/B95)*N130,(Assumptions!$B$8/B95)*B95)
A137: Cell (0,1) — ESOP=low, Pre=base
A138: Step | B138: F_PPS | C138: D_NCP | D138: E_NCP | E138: ΔD | F138: ΔE | G138: ESOP | H138: N_A | I138: N_B | J138: preFD | K138: T_F | L138: F_PPS chk
A139: cell(0,1) seed | B139: =Assumptions!$B$54/Assumptions!$B$29 | C139: =Assumptions!$B$20 | D139: =Assumptions!$B$21 | E139: 0 | F139: 0 | G139: 0 | H139: 0 | I139: 0 | J139: =Assumptions!$B$29 | K139: =J139+Assumptions!$B$4/B139 | L139: =B139
A140: cell(0,1) iter 1 | B140: =Assumptions!$B$54/J139 | C140: =IF(B140<Assumptions!$B$20,Assumptions!$B$20*(Assumptions!$B$29+Assumptions!$B$4/Assumptions!$B$20)/(Assumptions!$B$29+Assumptions!$B$4/B140),Assumptions!$B$20) | D140: =IF(B140<Assumptions!$B$21,Assumptions!$B$21*(Assumptions!$B$29+Assumptions!$B$4/Assumptions!$B$21)/(Assumptions!$B$29+Assumptions!$B$4/B140),Assumptions!$B$21) | E140: =Assumptions!$B$37*Assumptions!$B$22/C140-Assumptions!$B$38 | F140: =Assumptions!$B$39*Assumptions!$B$21/D140-Assumptions!$B$39 | G140: =MAX(0,Assumptions!$B$50*(Assumptions!$B$29+E140+F140+G139+H139+I139+Assumptions!$B$4/B140)-Assumptions!$B$30) | H140: =Assumptions!$B$23/MIN(Assumptions!$B$24/(Assumptions!$B$29+E140+F140+G140+I139),B140*(1-Assumptions!$B$25)) | I140: =Assumptions!$B$26/MIN(Assumptions!$B$27/(Assumptions!$B$29+E140+F140+G140+H140),B140*(1-Assumptions!$B$28)) | J140: =Assumptions!$B$29+E140+F140+G140+H140+I140 | K140: =J140+Assumptions!$B$4/B140 | L140: =B140
A141: cell(0,1) iter 2 | B141: =Assumptions!$B$54/J140 | C141: =IF(B141<Assumptions!$B$20,Assumptions!$B$20*(Assumptions!$B$29+Assumptions!$B$4/Assumptions!$B$20)/(Assumptions!$B$29+Assumptions!$B$4/B141),Assumptions!$B$20) | D141: =IF(B141<Assumptions!$B$21,Assumptions!$B$21*(Assumptions!$B$29+Assumptions!$B$4/Assumptions!$B$21)/(Assumptions!$B$29+Assumptions!$B$4/B141),Assumptions!$B$21) | E141: =Assumptions!$B$37*Assumptions!$B$22/C141-Assumptions!$B$38 | F141: =Assumptions!$B$39*Assumptions!$B$21/D141-Assumptions!$B$39 | G141: =MAX(0,Assumptions!$B$50*(Assumptions!$B$29+E141+F141+G140+H140+I140+Assumptions!$B$4/B141)-Assumptions!$B$30) | H141: =Assumptions!$B$23/MIN(Assumptions!$B$24/(Assumptions!$B$29+E141+F141+G141+I140),B141*(1-Assumptions!$B$25)) | I141: =Assumptions!$B$26/MIN(Assumptions!$B$27/(Assumptions!$B$29+E141+F141+G141+H141),B141*(1-Assumptions!$B$28)) | J141: =Assumptions!$B$29+E141+F141+G141+H141+I141 | K141: =J141+Assumptions!$B$4/B141 | L141: =B141
A142: cell(0,1) iter 3 | B142: =Assumptions!$B$54/J141 | C142: =IF(B142<Assumptions!$B$20,Assumptions!$B$20*(Assumptions!$B$29+Assumptions!$B$4/Assumptions!$B$20)/(Assumptions!$B$29+Assumptions!$B$4/B142),Assumptions!$B$20) | D142: =IF(B142<Assumptions!$B$21,Assumptions!$B$21*(Assumptions!$B$29+Assumptions!$B$4/Assumptions!$B$21)/(Assumptions!$B$29+Assumptions!$B$4/B142),Assumptions!$B$21) | E142: =Assumptions!$B$37*Assumptions!$B$22/C142-Assumptions!$B$38 | F142: =Assumptions!$B$39*Assumptions!$B$21/D142-Assumptions!$B$39 | G142: =MAX(0,Assumptions!$B$50*(Assumptions!$B$29+E142+F142+G141+H141+I141+Assumptions!$B$4/B142)-Assumptions!$B$30) | H142: =Assumptions!$B$23/MIN(Assumptions!$B$24/(Assumptions!$B$29+E142+F142+G142+I141),B142*(1-Assumptions!$B$25)) | I142: =Assumptions!$B$26/MIN(Assumptions!$B$27/(Assumptions!$B$29+E142+F142+G142+H142),B142*(1-Assumptions!$B$28)) | J142: =Assumptions!$B$29+E142+F142+G142+H142+I142 | K142: =J142+Assumptions!$B$4/B142 | L142: =B142
A143: cell(0,1) iter 4 | B143: =Assumptions!$B$54/J142 | C143: =IF(B143<Assumptions!$B$20,Assumptions!$B$20*(Assumptions!$B$29+Assumptions!$B$4/Assumptions!$B$20)/(Assumptions!$B$29+Assumptions!$B$4/B143),Assumptions!$B$20) | D143: =IF(B143<Assumptions!$B$21,Assumptions!$B$21*(Assumptions!$B$29+Assumptions!$B$4/Assumptions!$B$21)/(Assumptions!$B$29+Assumptions!$B$4/B143),Assumptions!$B$21) | E143: =Assumptions!$B$37*Assumptions!$B$22/C143-Assumptions!$B$38 | F143: =Assumptions!$B$39*Assumptions!$B$21/D143-Assumptions!$B$39 | G143: =MAX(0,Assumptions!$B$50*(Assumptions!$B$29+E143+F143+G142+H142+I142+Assumptions!$B$4/B143)-Assumptions!$B$30) | H143: =Assumptions!$B$23/MIN(Assumptions!$B$24/(Assumptions!$B$29+E143+F143+G143+I142),B143*(1-Assumptions!$B$25)) | I143: =Assumptions!$B$26/MIN(Assumptions!$B$27/(Assumptions!$B$29+E143+F143+G143+H143),B143*(1-Assumptions!$B$28)) | J143: =Assumptions!$B$29+E143+F143+G143+H143+I143 | K143: =J143+Assumptions!$B$4/B143 | L143: =B143
A144: cell(0,1) iter 5 | B144: =Assumptions!$B$54/J143 | C144: =IF(B144<Assumptions!$B$20,Assumptions!$B$20*(Assumptions!$B$29+Assumptions!$B$4/Assumptions!$B$20)/(Assumptions!$B$29+Assumptions!$B$4/B144),Assumptions!$B$20) | D144: =IF(B144<Assumptions!$B$21,Assumptions!$B$21*(Assumptions!$B$29+Assumptions!$B$4/Assumptions!$B$21)/(Assumptions!$B$29+Assumptions!$B$4/B144),Assumptions!$B$21) | E144: =Assumptions!$B$37*Assumptions!$B$22/C144-Assumptions!$B$38 | F144: =Assumptions!$B$39*Assumptions!$B$21/D144-Assumptions!$B$39 | G144: =MAX(0,Assumptions!$B$50*(Assumptions!$B$29+E144+F144+G143+H143+I143+Assumptions!$B$4/B144)-Assumptions!$B$30) | H144: =Assumptions!$B$23/MIN(Assumptions!$B$24/(Assumptions!$B$29+E144+F144+G144+I143),B144*(1-Assumptions!$B$25)) | I144: =Assumptions!$B$26/MIN(Assumptions!$B$27/(Assumptions!$B$29+E144+F144+G144+H144),B144*(1-Assumptions!$B$28)) | J144: =Assumptions!$B$29+E144+F144+G144+H144+I144 | K144: =J144+Assumptions!$B$4/B144 | L144: =B144
A145: cell(0,1) iter 6 | B145: =Assumptions!$B$54/J144 | C145: =IF(B145<Assumptions!$B$20,Assumptions!$B$20*(Assumptions!$B$29+Assumptions!$B$4/Assumptions!$B$20)/(Assumptions!$B$29+Assumptions!$B$4/B145),Assumptions!$B$20) | D145: =IF(B145<Assumptions!$B$21,Assumptions!$B$21*(Assumptions!$B$29+Assumptions!$B$4/Assumptions!$B$21)/(Assumptions!$B$29+Assumptions!$B$4/B145),Assumptions!$B$21) | E145: =Assumptions!$B$37*Assumptions!$B$22/C145-Assumptions!$B$38 | F145: =Assumptions!$B$39*Assumptions!$B$21/D145-Assumptions!$B$39 | G145: =MAX(0,Assumptions!$B$50*(Assumptions!$B$29+E145+F145+G144+H144+I144+Assumptions!$B$4/B145)-Assumptions!$B$30) | H145: =Assumptions!$B$23/MIN(Assumptions!$B$24/(Assumptions!$B$29+E145+F145+G145+I144),B145*(1-Assumptions!$B$25)) | I145: =Assumptions!$B$26/MIN(Assumptions!$B$27/(Assumptions!$B$29+E145+F145+G145+H145),B145*(1-Assumptions!$B$28)) | J145: =Assumptions!$B$29+E145+F145+G145+H145+I145 | K145: =J145+Assumptions!$B$4/B145 | L145: =B145
A146: cell(0,1) iter 7 | B146: =Assumptions!$B$54/J145 | C146: =IF(B146<Assumptions!$B$20,Assumptions!$B$20*(Assumptions!$B$29+Assumptions!$B$4/Assumptions!$B$20)/(Assumptions!$B$29+Assumptions!$B$4/B146),Assumptions!$B$20) | D146: =IF(B146<Assumptions!$B$21,Assumptions!$B$21*(Assumptions!$B$29+Assumptions!$B$4/Assumptions!$B$21)/(Assumptions!$B$29+Assumptions!$B$4/B146),Assumptions!$B$21) | E146: =Assumptions!$B$37*Assumptions!$B$22/C146-Assumptions!$B$38 | F146: =Assumptions!$B$39*Assumptions!$B$21/D146-Assumptions!$B$39 | G146: =MAX(0,Assumptions!$B$50*(Assumptions!$B$29+E146+F146+G145+H145+I145+Assumptions!$B$4/B146)-Assumptions!$B$30) | H146: =Assumptions!$B$23/MIN(Assumptions!$B$24/(Assumptions!$B$29+E146+F146+G146+I145),B146*(1-Assumptions!$B$25)) | I146: =Assumptions!$B$26/MIN(Assumptions!$B$27/(Assumptions!$B$29+E146+F146+G146+H146),B146*(1-Assumptions!$B$28)) | J146: =Assumptions!$B$29+E146+F146+G146+H146+I146 | K146: =J146+Assumptions!$B$4/B146 | L146: =B146
A147: cell(0,1) iter 8 | B147: =Assumptions!$B$54/J146 | C147: =IF(B147<Assumptions!$B$20,Assumptions!$B$20*(Assumptions!$B$29+Assumptions!$B$4/Assumptions!$B$20)/(Assumptions!$B$29+Assumptions!$B$4/B147),Assumptions!$B$20) | D147: =IF(B147<Assumptions!$B$21,Assumptions!$B$21*(Assumptions!$B$29+Assumptions!$B$4/Assumptions!$B$21)/(Assumptions!$B$29+Assumptions!$B$4/B147),Assumptions!$B$21) | E147: =Assumptions!$B$37*Assumptions!$B$22/C147-Assumptions!$B$38 | F147: =Assumptions!$B$39*Assumptions!$B$21/D147-Assumptions!$B$39 | G147: =MAX(0,Assumptions!$B$50*(Assumptions!$B$29+E147+F147+G146+H146+I146+Assumptions!$B$4/B147)-Assumptions!$B$30) | H147: =Assumptions!$B$23/MIN(Assumptions!$B$24/(Assumptions!$B$29+E147+F147+G147+I146),B147*(1-Assumptions!$B$25)) | I147: =Assumptions!$B$26/MIN(Assumptions!$B$27/(Assumptions!$B$29+E147+F147+G147+H147),B147*(1-Assumptions!$B$28)) | J147: =Assumptions!$B$29+E147+F147+G147+H147+I147 | K147: =J147+Assumptions!$B$4/B147 | L147: =B147
A148: cell(0,1) iter 9 | B148: =Assumptions!$B$54/J147 | C148: =IF(B148<Assumptions!$B$20,Assumptions!$B$20*(Assumptions!$B$29+Assumptions!$B$4/Assumptions!$B$20)/(Assumptions!$B$29+Assumptions!$B$4/B148),Assumptions!$B$20) | D148: =IF(B148<Assumptions!$B$21,Assumptions!$B$21*(Assumptions!$B$29+Assumptions!$B$4/Assumptions!$B$21)/(Assumptions!$B$29+Assumptions!$B$4/B148),Assumptions!$B$21) | E148: =Assumptions!$B$37*Assumptions!$B$22/C148-Assumptions!$B$38 | F148: =Assumptions!$B$39*Assumptions!$B$21/D148-Assumptions!$B$39 | G148: =MAX(0,Assumptions!$B$50*(Assumptions!$B$29+E148+F148+G147+H147+I147+Assumptions!$B$4/B148)-Assumptions!$B$30) | H148: =Assumptions!$B$23/MIN(Assumptions!$B$24/(Assumptions!$B$29+E148+F148+G148+I147),B148*(1-Assumptions!$B$25)) | I148: =Assumptions!$B$26/MIN(Assumptions!$B$27/(Assumptions!$B$29+E148+F148+G148+H148),B148*(1-Assumptions!$B$28)) | J148: =Assumptions!$B$29+E148+F148+G148+H148+I148 | K148: =J148+Assumptions!$B$4/B148 | L148: =B148
A149: cell(0,1) iter 10 | B149: =Assumptions!$B$54/J148 | C149: =IF(B149<Assumptions!$B$20,Assumptions!$B$20*(Assumptions!$B$29+Assumptions!$B$4/Assumptions!$B$20)/(Assumptions!$B$29+Assumptions!$B$4/B149),Assumptions!$B$20) | D149: =IF(B149<Assumptions!$B$21,Assumptions!$B$21*(Assumptions!$B$29+Assumptions!$B$4/Assumptions!$B$21)/(Assumptions!$B$29+Assumptions!$B$4/B149),Assumptions!$B$21) | E149: =Assumptions!$B$37*Assumptions!$B$22/C149-Assumptions!$B$38 | F149: =Assumptions!$B$39*Assumptions!$B$21/D149-Assumptions!$B$39 | G149: =MAX(0,Assumptions!$B$50*(Assumptions!$B$29+E149+F149+G148+H148+I148+Assumptions!$B$4/B149)-Assumptions!$B$30) | H149: =Assumptions!$B$23/MIN(Assumptions!$B$24/(Assumptions!$B$29+E149+F149+G149+I148),B149*(1-Assumptions!$B$25)) | I149: =Assumptions!$B$26/MIN(Assumptions!$B$27/(Assumptions!$B$29+E149+F149+G149+H149),B149*(1-Assumptions!$B$28)) | J149: =Assumptions!$B$29+E149+F149+G149+H149+I149 | K149: =J149+Assumptions!$B$4/B149 | L149: =B149
A150: cell(0,1) iter 11 | B150: =Assumptions!$B$54/J149 | C150: =IF(B150<Assumptions!$B$20,Assumptions!$B$20*(Assumptions!$B$29+Assumptions!$B$4/Assumptions!$B$20)/(Assumptions!$B$29+Assumptions!$B$4/B150),Assumptions!$B$20) | D150: =IF(B150<Assumptions!$B$21,Assumptions!$B$21*(Assumptions!$B$29+Assumptions!$B$4/Assumptions!$B$21)/(Assumptions!$B$29+Assumptions!$B$4/B150),Assumptions!$B$21) | E150: =Assumptions!$B$37*Assumptions!$B$22/C150-Assumptions!$B$38 | F150: =Assumptions!$B$39*Assumptions!$B$21/D150-Assumptions!$B$39 | G150: =MAX(0,Assumptions!$B$50*(Assumptions!$B$29+E150+F150+G149+H149+I149+Assumptions!$B$4/B150)-Assumptions!$B$30) | H150: =Assumptions!$B$23/MIN(Assumptions!$B$24/(Assumptions!$B$29+E150+F150+G150+I149),B150*(1-Assumptions!$B$25)) | I150: =Assumptions!$B$26/MIN(Assumptions!$B$27/(Assumptions!$B$29+E150+F150+G150+H150),B150*(1-Assumptions!$B$28)) | J150: =Assumptions!$B$29+E150+F150+G150+H150+I150 | K150: =J150+Assumptions!$B$4/B150 | L150: =B150
A151: cell(0,1) iter 12 | B151: =Assumptions!$B$54/J150 | C151: =IF(B151<Assumptions!$B$20,Assumptions!$B$20*(Assumptions!$B$29+Assumptions!$B$4/Assumptions!$B$20)/(Assumptions!$B$29+Assumptions!$B$4/B151),Assumptions!$B$20) | D151: =IF(B151<Assumptions!$B$21,Assumptions!$B$21*(Assumptions!$B$29+Assumptions!$B$4/Assumptions!$B$21)/(Assumptions!$B$29+Assumptions!$B$4/B151),Assumptions!$B$21) | E151: =Assumptions!$B$37*Assumptions!$B$22/C151-Assumptions!$B$38 | F151: =Assumptions!$B$39*Assumptions!$B$21/D151-Assumptions!$B$39 | G151: =MAX(0,Assumptions!$B$50*(Assumptions!$B$29+E151+F151+G150+H150+I150+Assumptions!$B$4/B151)-Assumptions!$B$30) | H151: =Assumptions!$B$23/MIN(Assumptions!$B$24/(Assumptions!$B$29+E151+F151+G151+I150),B151*(1-Assumptions!$B$25)) | I151: =Assumptions!$B$26/MIN(Assumptions!$B$27/(Assumptions!$B$29+E151+F151+G151+H151),B151*(1-Assumptions!$B$28)) | J151: =Assumptions!$B$29+E151+F151+G151+H151+I151 | K151: =J151+Assumptions!$B$4/B151 | L151: =B151
... A219: cell(0,1) iter 80 | B219: =Assumptions!$B$54/J218 | C219: =IF(B219<Assumptions!$B$20,Assumptions!$B$20*(Assumptions!$B$29+Assumptions!$B$4/Assumptions!$B$20)/(Assumptions!$B$29+Assumptions!$B$4/B219),Assumptions!$B$20) | D219: =IF(B219<Assumptions!$B$21,Assumptions!$B$21*(Assumptions!$B$29+Assumptions!$B$4/Assumptions!$B$21)/(Assumptions!$B$29+Assumptions!$B$4/B219),Assumptions!$B$21) | E219: =Assumptions!$B$37*Assumptions!$B$22/C219-Assumptions!$B$38 | F219: =Assumptions!$B$39*Assumptions!$B$21/D219-Assumptions!$B$39 | G219: =MAX(0,Assumptions!$B$50*(Assumptions!$B$29+E219+F219+G218+H218+I218+Assumptions!$B$4/B219)-Assumptions!$B$30) | H219: =Assumptions!$B$23/MIN(Assumptions!$B$24/(Assumptions!$B$29+E219+F219+G219+I218),B219*(1-Assumptions!$B$25)) | I219: =Assumptions!$B$26/MIN(Assumptions!$B$27/(Assumptions!$B$29+E219+F219+G219+H219),B219*(1-Assumptions!$B$28)) | J219: =Assumptions!$B$29+E219+F219+G219+H219+I219 | K219: =J219+Assumptions!$B$4/B219 | L219: =B219
A222: Waterfall ladder ($2B exit)
A223: Step | B223: F_el | C223: E_el | D223: D_el | E223: C_el | F223: B_el | G223: A_el | H223: Seed_el | I223: prefs | J223: conv_sh | K223: cpool | L223: ITM_PPS | M223: ITM? | N223: common_PPS | O223: opt_proc
A224: seed (all convert) | B224: ="convert" | C224: ="convert" | D224: ="convert" | E224: ="convert" | F224: ="convert" | G224: ="convert" | H224: ="convert" | I224: =IF(B224="preference",Assumptions!$B$4,0)+IF(C224="preference",Assumptions!$B$45,0)+IF(D224="preference",Assumptions!$B$44,0)+IF(E224="preference",Assumptions!$B$43,0)+IF(F224="preference",Assumptions!$B$42,0)+IF(G224="preference",Assumptions!$B$41,0)+IF(H224="preference",Assumptions!$B$40,0) | J224: =IF(B224="convert",(Assumptions!$B$4/B219),0)+IF(C224="convert",(Assumptions!$B$39+F219),0)+IF(D224="convert",(Assumptions!$B$38+E219),0)+IF(E224="convert",Assumptions!$B$36,0)+IF(F224="convert",Assumptions!$B$35,0)+IF(G224="convert",Assumptions!$B$34,0)+IF(H224="convert",Assumptions!$B$33,0) | K224: =(Assumptions!$B$46+Assumptions!$B$47+Assumptions!$B$48)+Assumptions!$B$49+(H219+I219)+J224 | L224: =(Assumptions!$B$13-I224+Assumptions!$B$31*Assumptions!$B$10)/(K224+Assumptions!$B$31) | M224: =IF(L224>Assumptions!$B$10,"yes","no") | N224: =IF(M224="yes",L224,MAX(0,(Assumptions!$B$13-I224)/K224)) | O224: =IF(M224="yes",Assumptions!$B$31*(N224-Assumptions!$B$10),0)
A225: iter 1 | B225: =IF(Assumptions!$B$4>(Assumptions!$B$4/B219)*N224,"preference","convert") | C225: =IF(Assumptions!$B$45>(Assumptions!$B$39+F219)*N224,"preference","convert") | D225: =IF(Assumptions!$B$44>(Assumptions!$B$38+E219)*N224,"preference","convert") | E225: =IF(Assumptions!$B$43>Assumptions!$B$36*N224,"preference","convert") | F225: =IF(Assumptions!$B$42>Assumptions!$B$35*N224,"preference","convert") | G225: =IF(Assumptions!$B$41>Assumptions!$B$34*N224,"preference","convert") | H225: =IF(Assumptions!$B$40>Assumptions!$B$33*N224,"preference","convert") | I225: =IF(B225="preference",Assumptions!$B$4,0)+IF(C225="preference",Assumptions!$B$45,0)+IF(D225="preference",Assumptions!$B$44,0)+IF(E225="preference",Assumptions!$B$43,0)+IF(F225="preference",Assumptions!$B$42,0)+IF(G225="preference",Assumptions!$B$41,0)+IF(H225="preference",Assumptions!$B$40,0) | J225: =IF(B225="convert",(Assumptions!$B$4/B219),0)+IF(C225="convert",(Assumptions!$B$39+F219),0)+IF(D225="convert",(Assumptions!$B$38+E219),0)+IF(E225="convert",Assumptions!$B$36,0)+IF(F225="convert",Assumptions!$B$35,0)+IF(G225="convert",Assumptions!$B$34,0)+IF(H225="convert",Assumptions!$B$33,0) | K225: =(Assumptions!$B$46+Assumptions!$B$47+Assumptions!$B$48)+Assumptions!$B$49+(H219+I219)+J225 | L225: =(Assumptions!$B$13-I225+Assumptions!$B$31*Assumptions!$B$10)/(K225+Assumptions!$B$31) | M225: =IF(L225>Assumptions!$B$10,"yes","no") | N225: =IF(M225="yes",L225,MAX(0,(Assumptions!$B$13-I225)/K225)) | O225: =IF(M225="yes",Assumptions!$B$31*(N225-Assumptions!$B$10),0)
A226: iter 2 | B226: =IF(Assumptions!$B$4>(Assumptions!$B$4/B219)*N225,"preference","convert") | C226: =IF(Assumptions!$B$45>(Assumptions!$B$39+F219)*N225,"preference","convert") | D226: =IF(Assumptions!$B$44>(Assumptions!$B$38+E219)*N225,"preference","convert") | E226: =IF(Assumptions!$B$43>Assumptions!$B$36*N225,"preference","convert") | F226: =IF(Assumptions!$B$42>Assumptions!$B$35*N225,"preference","convert") | G226: =IF(Assumptions!$B$41>Assumptions!$B$34*N225,"preference","convert") | H226: =IF(Assumptions!$B$40>Assumptions!$B$33*N225,"preference","convert") | I226: =IF(B226="preference",Assumptions!$B$4,0)+IF(C226="preference",Assumptions!$B$45,0)+IF(D226="preference",Assumptions!$B$44,0)+IF(E226="preference",Assumptions!$B$43,0)+IF(F226="preference",Assumptions!$B$42,0)+IF(G226="preference",Assumptions!$B$41,0)+IF(H226="preference",Assumptions!$B$40,0) | J226: =IF(B226="convert",(Assumptions!$B$4/B219),0)+IF(C226="convert",(Assumptions!$B$39+F219),0)+IF(D226="convert",(Assumptions!$B$38+E219),0)+IF(E226="convert",Assumptions!$B$36,0)+IF(F226="convert",Assumptions!$B$35,0)+IF(G226="convert",Assumptions!$B$34,0)+IF(H226="convert",Assumptions!$B$33,0) | K226: =(Assumptions!$B$46+Assumptions!$B$47+Assumptions!$B$48)+Assumptions!$B$49+(H219+I219)+J226 | L226: =(Assumptions!$B$13-I226+Assumptions!$B$31*Assumptions!$B$10)/(K226+Assumptions!$B$31) | M226: =IF(L226>Assumptions!$B$10,"yes","no") | N226: =IF(M226="yes",L226,MAX(0,(Assumptions!$B$13-I226)/K226)) | O226: =IF(M226="yes",Assumptions!$B$31*(N226-Assumptions!$B$10),0)
A227: iter 3 | B227: =IF(Assumptions!$B$4>(Assumptions!$B$4/B219)*N226,"preference","convert") | C227: =IF(Assumptions!$B$45>(Assumptions!$B$39+F219)*N226,"preference","convert") | D227: =IF(Assumptions!$B$44>(Assumptions!$B$38+E219)*N226,"preference","convert") | E227: =IF(Assumptions!$B$43>Assumptions!$B$36*N226,"preference","convert") | F227: =IF(Assumptions!$B$42>Assumptions!$B$35*N226,"preference","convert") | G227: =IF(Assumptions!$B$41>Assumptions!$B$34*N226,"preference","convert") | H227: =IF(Assumptions!$B$40>Assumptions!$B$33*N226,"preference","convert") | I227: =IF(B227="preference",Assumptions!$B$4,0)+IF(C227="preference",Assumptions!$B$45,0)+IF(D227="preference",Assumptions!$B$44,0)+IF(E227="preference",Assumptions!$B$43,0)+IF(F227="preference",Assumptions!$B$42,0)+IF(G227="preference",Assumptions!$B$41,0)+IF(H227="preference",Assumptions!$B$40,0) | J227: =IF(B227="convert",(Assumptions!$B$4/B219),0)+IF(C227="convert",(Assumptions!$B$39+F219),0)+IF(D227="convert",(Assumptions!$B$38+E219),0)+IF(E227="convert",Assumptions!$B$36,0)+IF(F227="convert",Assumptions!$B$35,0)+IF(G227="convert",Assumptions!$B$34,0)+IF(H227="convert",Assumptions!$B$33,0) | K227: =(Assumptions!$B$46+Assumptions!$B$47+Assumptions!$B$48)+Assumptions!$B$49+(H219+I219)+J227 | L227: =(Assumptions!$B$13-I227+Assumptions!$B$31*Assumptions!$B$10)/(K227+Assumptions!$B$31) | M227: =IF(L227>Assumptions!$B$10,"yes","no") | N227: =IF(M227="yes",L227,MAX(0,(Assumptions!$B$13-I227)/K227)) | O227: =IF(M227="yes",Assumptions!$B$31*(N227-Assumptions!$B$10),0)
A228: iter 4 | B228: =IF(Assumptions!$B$4>(Assumptions!$B$4/B219)*N227,"preference","convert") | C228: =IF(Assumptions!$B$45>(Assumptions!$B$39+F219)*N227,"preference","convert") | D228: =IF(Assumptions!$B$44>(Assumptions!$B$38+E219)*N227,"preference","convert") | E228: =IF(Assumptions!$B$43>Assumptions!$B$36*N227,"preference","convert") | F228: =IF(Assumptions!$B$42>Assumptions!$B$35*N227,"preference","convert") | G228: =IF(Assumptions!$B$41>Assumptions!$B$34*N227,"preference","convert") | H228: =IF(Assumptions!$B$40>Assumptions!$B$33*N227,"preference","convert") | I228: =IF(B228="preference",Assumptions!$B$4,0)+IF(C228="preference",Assumptions!$B$45,0)+IF(D228="preference",Assumptions!$B$44,0)+IF(E228="preference",Assumptions!$B$43,0)+IF(F228="preference",Assumptions!$B$42,0)+IF(G228="preference",Assumptions!$B$41,0)+IF(H228="preference",Assumptions!$B$40,0) | J228: =IF(B228="convert",(Assumptions!$B$4/B219),0)+IF(C228="convert",(Assumptions!$B$39+F219),0)+IF(D228="convert",(Assumptions!$B$38+E219),0)+IF(E228="convert",Assumptions!$B$36,0)+IF(F228="convert",Assumptions!$B$35,0)+IF(G228="convert",Assumptions!$B$34,0)+IF(H228="convert",Assumptions!$B$33,0) | K228: =(Assumptions!$B$46+Assumptions!$B$47+Assumptions!$B$48)+Assumptions!$B$49+(H219+I219)+J228 | L228: =(Assumptions!$B$13-I228+Assumptions!$B$31*Assumptions!$B$10)/(K228+Assumptions!$B$31) | M228: =IF(L228>Assumptions!$B$10,"yes","no") | N228: =IF(M228="yes",L228,MAX(0,(Assumptions!$B$13-I228)/K228)) | O228: =IF(M228="yes",Assumptions!$B$31*(N228-Assumptions!$B$10),0)
A229: iter 5 | B229: =IF(Assumptions!$B$4>(Assumptions!$B$4/B219)*N228,"preference","convert") | C229: =IF(Assumptions!$B$45>(Assumptions!$B$39+F219)*N228,"preference","convert") | D229: =IF(Assumptions!$B$44>(Assumptions!$B$38+E219)*N228,"preference","convert") | E229: =IF(Assumptions!$B$43>Assumptions!$B$36*N228,"preference","convert") | F229: =IF(Assumptions!$B$42>Assumptions!$B$35*N228,"preference","convert") | G229: =IF(Assumptions!$B$41>Assumptions!$B$34*N228,"preference","convert") | H229: =IF(Assumptions!$B$40>Assumptions!$B$33*N228,"preference","convert") | I229: =IF(B229="preference",Assumptions!$B$4,0)+IF(C229="preference",Assumptions!$B$45,0)+IF(D229="preference",Assumptions!$B$44,0)+IF(E229="preference",Assumptions!$B$43,0)+IF(F229="preference",Assumptions!$B$42,0)+IF(G229="preference",Assumptions!$B$41,0)+IF(H229="preference",Assumptions!$B$40,0) | J229: =IF(B229="convert",(Assumptions!$B$4/B219),0)+IF(C229="convert",(Assumptions!$B$39+F219),0)+IF(D229="convert",(Assumptions!$B$38+E219),0)+IF(E229="convert",Assumptions!$B$36,0)+IF(F229="convert",Assumptions!$B$35,0)+IF(G229="convert",Assumptions!$B$34,0)+IF(H229="convert",Assumptions!$B$33,0) | K229: =(Assumptions!$B$46+Assumptions!$B$47+Assumptions!$B$48)+Assumptions!$B$49+(H219+I219)+J229 | L229: =(Assumptions!$B$13-I229+Assumptions!$B$31*Assumptions!$B$10)/(K229+Assumptions!$B$31) | M229: =IF(L229>Assumptions!$B$10,"yes","no") | N229: =IF(M229="yes",L229,MAX(0,(Assumptions!$B$13-I229)/K229)) | O229: =IF(M229="yes",Assumptions!$B$31*(N229-Assumptions!$B$10),0)
A230: iter 6 | B230: =IF(Assumptions!$B$4>(Assumptions!$B$4/B219)*N229,"preference","convert") | C230: =IF(Assumptions!$B$45>(Assumptions!$B$39+F219)*N229,"preference","convert") | D230: =IF(Assumptions!$B$44>(Assumptions!$B$38+E219)*N229,"preference","convert") | E230: =IF(Assumptions!$B$43>Assumptions!$B$36*N229,"preference","convert") | F230: =IF(Assumptions!$B$42>Assumptions!$B$35*N229,"preference","convert") | G230: =IF(Assumptions!$B$41>Assumptions!$B$34*N229,"preference","convert") | H230: =IF(Assumptions!$B$40>Assumptions!$B$33*N229,"preference","convert") | I230: =IF(B230="preference",Assumptions!$B$4,0)+IF(C230="preference",Assumptions!$B$45,0)+IF(D230="preference",Assumptions!$B$44,0)+IF(E230="preference",Assumptions!$B$43,0)+IF(F230="preference",Assumptions!$B$42,0)+IF(G230="preference",Assumptions!$B$41,0)+IF(H230="preference",Assumptions!$B$40,0) | J230: =IF(B230="convert",(Assumptions!$B$4/B219),0)+IF(C230="convert",(Assumptions!$B$39+F219),0)+IF(D230="convert",(Assumptions!$B$38+E219),0)+IF(E230="convert",Assumptions!$B$36,0)+IF(F230="convert",Assumptions!$B$35,0)+IF(G230="convert",Assumptions!$B$34,0)+IF(H230="convert",Assumptions!$B$33,0) | K230: =(Assumptions!$B$46+Assumptions!$B$47+Assumptions!$B$48)+Assumptions!$B$49+(H219+I219)+J230 | L230: =(Assumptions!$B$13-I230+Assumptions!$B$31*Assumptions!$B$10)/(K230+Assumptions!$B$31) | M230: =IF(L230>Assumptions!$B$10,"yes","no") | N230: =IF(M230="yes",L230,MAX(0,(Assumptions!$B$13-I230)/K230)) | O230: =IF(M230="yes",Assumptions!$B$31*(N230-Assumptions!$B$10),0)
A231: iter 7 | B231: =IF(Assumptions!$B$4>(Assumptions!$B$4/B219)*N230,"preference","convert") | C231: =IF(Assumptions!$B$45>(Assumptions!$B$39+F219)*N230,"preference","convert") | D231: =IF(Assumptions!$B$44>(Assumptions!$B$38+E219)*N230,"preference","convert") | E231: =IF(Assumptions!$B$43>Assumptions!$B$36*N230,"preference","convert") | F231: =IF(Assumptions!$B$42>Assumptions!$B$35*N230,"preference","convert") | G231: =IF(Assumptions!$B$41>Assumptions!$B$34*N230,"preference","convert") | H231: =IF(Assumptions!$B$40>Assumptions!$B$33*N230,"preference","convert") | I231: =IF(B231="preference",Assumptions!$B$4,0)+IF(C231="preference",Assumptions!$B$45,0)+IF(D231="preference",Assumptions!$B$44,0)+IF(E231="preference",Assumptions!$B$43,0)+IF(F231="preference",Assumptions!$B$42,0)+IF(G231="preference",Assumptions!$B$41,0)+IF(H231="preference",Assumptions!$B$40,0) | J231: =IF(B231="convert",(Assumptions!$B$4/B219),0)+IF(C231="convert",(Assumptions!$B$39+F219),0)+IF(D231="convert",(Assumptions!$B$38+E219),0)+IF(E231="convert",Assumptions!$B$36,0)+IF(F231="convert",Assumptions!$B$35,0)+IF(G231="convert",Assumptions!$B$34,0)+IF(H231="convert",Assumptions!$B$33,0) | K231: =(Assumptions!$B$46+Assumptions!$B$47+Assumptions!$B$48)+Assumptions!$B$49+(H219+I219)+J231 | L231: =(Assumptions!$B$13-I231+Assumptions!$B$31*Assumptions!$B$10)/(K231+Assumptions!$B$31) | M231: =IF(L231>Assumptions!$B$10,"yes","no") | N231: =IF(M231="yes",L231,MAX(0,(Assumptions!$B$13-I231)/K231)) | O231: =IF(M231="yes",Assumptions!$B$31*(N231-Assumptions!$B$10),0)
A232: iter 8 | B232: =IF(Assumptions!$B$4>(Assumptions!$B$4/B219)*N231,"preference","convert") | C232: =IF(Assumptions!$B$45>(Assumptions!$B$39+F219)*N231,"preference","convert") | D232: =IF(Assumptions!$B$44>(Assumptions!$B$38+E219)*N231,"preference","convert") | E232: =IF(Assumptions!$B$43>Assumptions!$B$36*N231,"preference","convert") | F232: =IF(Assumptions!$B$42>Assumptions!$B$35*N231,"preference","convert") | G232: =IF(Assumptions!$B$41>Assumptions!$B$34*N231,"preference","convert") | H232: =IF(Assumptions!$B$40>Assumptions!$B$33*N231,"preference","convert") | I232: =IF(B232="preference",Assumptions!$B$4,0)+IF(C232="preference",Assumptions!$B$45,0)+IF(D232="preference",Assumptions!$B$44,0)+IF(E232="preference",Assumptions!$B$43,0)+IF(F232="preference",Assumptions!$B$42,0)+IF(G232="preference",Assumptions!$B$41,0)+IF(H232="preference",Assumptions!$B$40,0) | J232: =IF(B232="convert",(Assumptions!$B$4/B219),0)+IF(C232="convert",(Assumptions!$B$39+F219),0)+IF(D232="convert",(Assumptions!$B$38+E219),0)+IF(E232="convert",Assumptions!$B$36,0)+IF(F232="convert",Assumptions!$B$35,0)+IF(G232="convert",Assumptions!$B$34,0)+IF(H232="convert",Assumptions!$B$33,0) | K232: =(Assumptions!$B$46+Assumptions!$B$47+Assumptions!$B$48)+Assumptions!$B$49+(H219+I219)+J232 | L232: =(Assumptions!$B$13-I232+Assumptions!$B$31*Assumptions!$B$10)/(K232+Assumptions!$B$31) | M232: =IF(L232>Assumptions!$B$10,"yes","no") | N232: =IF(M232="yes",L232,MAX(0,(Assumptions!$B$13-I232)/K232)) | O232: =IF(M232="yes",Assumptions!$B$31*(N232-Assumptions!$B$10),0)
