Workbook

Sheet Assumptions
B2: Kelvin Dynamics Series F — Assumptions
B3: All values in USD unless noted
B5: Round Terms
B6: Series F pre-money | C6: 1400000000 | D6: USD
B7: Series F primary raise | C7: 30000000 | D7: USD
B8: Series F secondary raise | C8: 15000000 | D8: USD
B9: Tender PPS multiplier | C9: 0.85 | D9: fraction
B10: ESOP refresh target (post-F FD) | C10: 0.13 | D10: fraction
B11: Our fund check | C11: 10000000 | D11: USD
B12: F_LEAD primary check | C12: 20000000 | D12: USD
B13: Option strike | C13: 1 | D13: USD
B15: Pre-F Share Counts
B16: Founder F1 (CEO) common | C16: 4000000 | D16: shares
B17: Founder F2 (CTO) common | C17: 2500000 | D17: shares
B18: Founder F3 (Chief Sci) common | C18: 1500000 | D18: shares
B19: Employee RSAs (10 holders) | C19: 1000000 | D19: shares
B20: Seed preferred shares | C20: 5000000 | D20: shares
B21: Series A preferred shares | C21: 5000000 | D21: shares
B22: Series B preferred shares | C22: 3000000 | D22: shares
B23: Series C preferred shares | C23: 2400000 | D23: shares
B24: Series D preferred shares (post-E AD) | C24: 1720627 | D24: shares
B25: Series E preferred shares | C25: 6102667 | D25: shares
B26: Pre-F options issued | C26: 2500000 | D26: shares
B27: Pre-F options unissued | C27: 1894667 | D27: shares
B28: Pre-F broad-based FD total | C28: =SUM(C16:C27) -> 36617961 | D28: shares
B30: Original Conversion Prices (OCP-for-AD)
B31: Seed OCP | C31: 1 | D31: USD/share
B32: Series A OCP | C32: 3 | D32: USD/share
B33: Series B OCP | C33: 10 | D33: USD/share
B34: Series C OCP | C34: 25 | D34: USD/share
B35: Series D OCP (compound, post-E AD) | C35: 58.118347 | D35: USD/share
B36: Series E OCP | C36: 49.158311 | D36: USD/share
B38: Invested Capital (= 1x liq pref)
B39: Seed invested | C39: 5000000 | D39: USD
B40: Series A invested | C40: 15000000 | D40: USD
B41: Series B invested | C41: 30000000 | D41: USD
B42: Series C invested | C42: 60000000 | D42: USD
B43: Series D invested | C43: 100000000 | D43: USD
B44: Series E invested | C44: 300000000 | D44: USD
B46: Convertible Notes
B47: Note A principal | C47: 5000000 | D47: USD
B48: Note A cap | C48: 1000000000 | D48: USD
B49: Note A discount | C49: 0.2 | D49: fraction
B50: Note B principal | C50: 3000000 | D50: USD
B51: Note B cap | C51: 1600000000 | D51: USD
B52: Note B discount | C52: 0.15 | D52: fraction
B54: Exit Scenarios
B55: Exit value 1 | C55: 700000000 | D55: USD
B56: Exit value 2 | C56: 1200000000 | D56: USD
B57: Exit value 3 | C57: 2000000000 | D57: USD
B58: Exit value 4 | C58: 4000000000 | D58: USD
B59: Exit value 5 | C59: 8000000000 | D59: USD
B61: Sensitivity Axes
B62: ESOP low | C62: 0.11 | D62: fraction
B63: ESOP base | C63: 0.13 | D63: fraction
B64: ESOP high | C64: 0.15 | D64: fraction
B65: Pre-money low | C65: 1200000000 | D65: USD
B66: Pre-money base | C66: 1400000000 | D66: USD
B67: Pre-money high | C67: 1800000000 | D67: USD
B69: Return Targets
B70: 3x return multiple | C70: 3 | D70: multiple
B71: 4x return multiple | C71: 4 | D71: multiple
B72: Founder F1 share of common | C72: 0.5 | D72: 4M / 8M
B73: Founder F2 share of common | C73: 0.3125 | D73: 2.5M / 8M
B74: Founder F3 share of common | C74: 0.1875 | D74: 1.5M / 8M

Sheet Pro-Forma
B2: Series F Pro-Forma Cap Table
B3: $ in actual; shares in actual
B5: Round Outputs (Solved)
B6: F PPS | C6: =Solver!$N$26 -> 37.299685
B7: Tender PPS | C7: =Assumptions!$C$9*$C$6 -> 31.704732
B8: Pre-money FD shares | C8: =Solver!$M$26 -> 37533829
B9: Series F primary shares | C9: =Assumptions!$C$7/$C$6 -> 804296.34
B10: Post-F FD total (T_F) | C10: =$C$8+$C$9 -> 38338126
B11: ESOP top-up shares | C11: =Solver!$J$26 -> 589289.34
B12: Tender shares | C12: =Assumptions!$C$8/(Assumptions!$C$9*$C$6) -> 473115.5
B14: Anti-Dilution Block (Broad-Based Weighted Average)
B15: Class | C15: OCP | D15: Trigger | E15: NCP | F15: New ratio | G15: As-conv shares
B16: Seed | C16: =Assumptions!$C$31 -> 1 | D16: =IF($C$6<Assumptions!$C$31,"trigger","dormant") -> dormant | E16: =IF($C$6<Assumptions!$C$31,(Assumptions!$C$31*Assumptions!$C$28+Assumptions!$C$7)/(Assumptions!$C$28+Assumptions!$C$7/$C$6),Assumptions!$C$31) -> 1 | F16: =Assumptions!$C$31/E16 -> 1 | G16: =Assumptions!$C$20 -> 5000000
B17: Series A | C17: =Assumptions!$C$32 -> 3 | D17: =IF($C$6<Assumptions!$C$32,"trigger","dormant") -> dormant | E17: =IF($C$6<Assumptions!$C$32,(Assumptions!$C$32*Assumptions!$C$28+Assumptions!$C$7)/(Assumptions!$C$28+Assumptions!$C$7/$C$6),Assumptions!$C$32) -> 3 | F17: =Assumptions!$C$32/E17 -> 1 | G17: =Assumptions!$C$21 -> 5000000
B18: Series B | C18: =Assumptions!$C$33 -> 10 | D18: =IF($C$6<Assumptions!$C$33,"trigger","dormant") -> dormant | E18: =IF($C$6<Assumptions!$C$33,(Assumptions!$C$33*Assumptions!$C$28+Assumptions!$C$7)/(Assumptions!$C$28+Assumptions!$C$7/$C$6),Assumptions!$C$33) -> 10 | F18: =Assumptions!$C$33/E18 -> 1 | G18: =Assumptions!$C$22 -> 3000000
B19: Series C | C19: =Assumptions!$C$34 -> 25 | D19: =IF($C$6<Assumptions!$C$34,"trigger","dormant") -> dormant | E19: =IF($C$6<Assumptions!$C$34,(Assumptions!$C$34*Assumptions!$C$28+Assumptions!$C$7)/(Assumptions!$C$28+Assumptions!$C$7/$C$6),Assumptions!$C$34) -> 25 | F19: =Assumptions!$C$34/E19 -> 1 | G19: =Assumptions!$C$23 -> 2400000
B20: Series D | C20: =Assumptions!$C$35 -> 58.118347 | D20: =IF($C$6<Assumptions!$C$35,"trigger","dormant") -> trigger | E20: =IF($C$6<Assumptions!$C$35,(Assumptions!$C$35*Assumptions!$C$28+Assumptions!$C$7)/(Assumptions!$C$28+Assumptions!$C$7/$C$6),Assumptions!$C$35) -> 57.670903 | F20: =60/E20 -> 1.040386 | G20: =IF($C$6<Assumptions!$C$35,Assumptions!$C$43/E20,Assumptions!$C$24) -> 1733976.7
B21: Series E | C21: =Assumptions!$C$36 -> 49.158311 | D21: =IF($C$6<Assumptions!$C$36,"trigger","dormant") -> trigger | E21: =IF($C$6<Assumptions!$C$36,(Assumptions!$C$36*Assumptions!$C$28+Assumptions!$C$7)/(Assumptions!$C$28+Assumptions!$C$7/$C$6),Assumptions!$C$36) -> 48.90344 | F21: =Assumptions!$C$36/E21 -> 1.0052117 | G21: =IF($C$6<Assumptions!$C$36,Assumptions!$C$44/E21,Assumptions!$C$25) -> 6134537.8
B23: Convertible Notes Block
B24: Note | C24: Cap PPS | D24: Discount PPS | E24: Conv PPS | F24: Branch | G24: Shares
B25: Note A | C25: =Assumptions!$C$48/(Solver!$M$26-Solver!$K$26) -> 26.775845 | D25: =$C$6*(1-Assumptions!$C$49) -> 29.839748 | E25: =MIN(C25,D25) -> 26.775845 | F25: =IF(C25<D25,"cap","discount") -> cap | G25: =Assumptions!$C$47/E25 -> 186735.47
B26: Note B | C26: =Assumptions!$C$51/(Solver!$M$26-Solver!$L$26) -> 42.735949 | D26: =$C$6*(1-Assumptions!$C$52) -> 31.704732 | E26: =MIN(C26,D26) -> 31.704732 | F26: =IF(C26<D26,"cap","discount") -> discount | G26: =Assumptions!$C$50/E26 -> 94623.099
B28: Secondary Tender Block
B29: Tender shares total | C29: =Assumptions!$C$8/(Assumptions!$C$9*$C$6) -> 473115.5
B30: F1 founder tender (50%) | C30: =Assumptions!$C$72*$C$12 -> 236557.75
B31: F2 founder tender (31.25%) | C31: =Assumptions!$C$73*$C$12 -> 147848.59
B32: F3 founder tender (18.75%) | C32: =Assumptions!$C$74*$C$12 -> 88709.156
B33: F_LEAD secondary holding | C33: =$C$12 -> 473115.5
B35: Post-F Cap Table by Stakeholder
B36: Stakeholder | C36: Class | D36: Shares | E36: % of T_F
B37: F1 (CEO) | C37: Common | D37: =Assumptions!$C$16-Assumptions!$C$72*$C$12 -> 3763442.3 | E37: =D37/$C$10 -> 0.098164482
B38: F2 (CTO) | C38: Common | D38: =Assumptions!$C$17-Assumptions!$C$73*$C$12 -> 2352151.4 | E38: =D38/$C$10 -> 0.061352801
B39: F3 (Chief Sci) | C39: Common | D39: =Assumptions!$C$18-Assumptions!$C$74*$C$12 -> 1411290.8 | E39: =D39/$C$10 -> 0.036811681
B40: Employee RSAs (10) | C40: Common | D40: =Assumptions!$C$19 -> 1000000 | E40: =D40/$C$10 -> 0.026083696
B41: Seed LP | C41: Seed pref | D41: =Assumptions!$C$20 -> 5000000 | E41: =D41/$C$10 -> 0.13041848
B42: Series A LP | C42: A pref | D42: =Assumptions!$C$21 -> 5000000 | E42: =D42/$C$10 -> 0.13041848
B43: Series B LP | C43: B pref | D43: =Assumptions!$C$22 -> 3000000 | E43: =D43/$C$10 -> 0.078251087
B44: Series C LP | C44: C pref | D44: =Assumptions!$C$23 -> 2400000 | E44: =D44/$C$10 -> 0.062600869
B45: Series D LP | C45: D pref (post-AD) | D45: =$G$20 -> 1733976.7 | E45: =D45/$C$10 -> 0.04522852
B46: Series E LPs (10) | C46: E pref (post-AD) | D46: =$G$21 -> 6134537.8 | E46: =D46/$C$10 -> 0.16001142
B47: Note A holder | C47: Common (conv) | D47: =$G$25 -> 186735.47 | E47: =D47/$C$10 -> 0.0048707511
B48: Note B holder | C48: Common (conv) | D48: =$G$26 -> 94623.099 | E48: =D48/$C$10 -> 0.0024681201
B49: Options issued | C49: Options | D49: =Assumptions!$C$26 -> 2500000 | E49: =D49/$C$10 -> 0.065209239
B50: Options unissued (refresh) | C50: Options | D50: =Assumptions!$C$27+$C$11 -> 2483956.3 | E50: =D50/$C$10 -> 0.064790761
B51: F_LEAD primary | C51: F pref | D51: =Assumptions!$C$12/$C$6 -> 536197.56 | E51: =D51/$C$10 -> 0.013986014
B52: F_LEAD secondary | C52: Common | D52: =$C$12 -> 473115.5 | E52: =D52/$C$10 -> 0.012340601
B53: Our fund | C53: F pref | D53: =Assumptions!$C$11/$C$6 -> 268098.78 | E53: =D53/$C$10 -> 0.006993007
B54: Total | D54: =SUM(D37:D53) -> 38338126 | E54: =SUM(E37:E53) -> 1
B55: Check | D55: =ROUND(D54-$C$10,0) -> 0 | E55: =ROUND(E54-1,6) -> 0

Sheet Return-Solver
B2: Return Solver — Required Series F Ownership for 3x and 4x
B3: Solves required post-F ownership %; flags infeasible (≤ 0% or > 100%)
B5: Inputs (Base Case)
B6: Our check | C6: =Assumptions!$C$11 -> 10000000
B7: Series F post-money | C7: =Assumptions!$C$6+Assumptions!$C$7 -> 1430000000
B8: Post-F FD total (T_F) | C8: ='Pro-Forma'!$C$10 -> 38338126
B9: Actual ownership of $10M check | C9: =(Assumptions!$C$11/'Pro-Forma'!$C$6)/$C$8 -> 0.006993007
B11: Per-Exit Waterfall Data (Base Case)
B12: Exit | D12: =Assumptions!$C$55 -> 700000000 | E12: =Assumptions!$C$56 -> 1200000000 | F12: =Assumptions!$C$57 -> 2000000000 | G12: =Assumptions!$C$58 -> 4000000000 | H12: =Assumptions!$C$59 -> 8000000000
B13: F class election | D13: =Waterfall!$D$74 -> preference | E13: =Waterfall!$E$74 -> preference | F13: =Waterfall!$F$74 -> convert | G13: =Waterfall!$G$74 -> convert | H13: =Waterfall!$H$74 -> convert
B14: Per-share value (final) | D14: =Waterfall!$D$72 -> 8.3787244 | E14: =Waterfall!$E$72 -> 28.420213 | F14: =Waterfall!$F$72 -> 55.758771 | G14: =Waterfall!$G$72 -> 111.63276 | H14: =Waterfall!$H$72 -> 223.1958
B15: Pool $ per 1% ownership | D15: =IF(D13="preference",0.01*$C$7,0.01*$C$8*D14) -> 14300000 | E15: =IF(E13="preference",0.01*$C$7,0.01*$C$8*E14) -> 14300000 | F15: =IF(F13="preference",0.01*$C$7,0.01*$C$8*F14) -> 21376868 | G15: =IF(G13="preference",0.01*$C$7,0.01*$C$8*G14) -> 42797909 | H15: =IF(H13="preference",0.01*$C$7,0.01*$C$8*H14) -> 85569086
B17: Required Post-F Ownership for Target Returns
B18: Exit | D18: =Assumptions!$C$55 -> 700000000 | E18: =Assumptions!$C$56 -> 1200000000 | F18: =Assumptions!$C$57 -> 2000000000 | G18: =Assumptions!$C$58 -> 4000000000 | H18: =Assumptions!$C$59 -> 8000000000
B19: Target proceeds (3x) | D19: =Assumptions!$C$70*Assumptions!$C$11 -> 30000000 | E19: =Assumptions!$C$70*Assumptions!$C$11 -> 30000000 | F19: =Assumptions!$C$70*Assumptions!$C$11 -> 30000000 | G19: =Assumptions!$C$70*Assumptions!$C$11 -> 30000000 | H19: =Assumptions!$C$70*Assumptions!$C$11 -> 30000000
B20: Required ownership % (3x) | D20: =IF(D13="preference",D19/$C$7,D19/($C$8*D14)) -> 0.020979021 | E20: =IF(E13="preference",E19/$C$7,E19/($C$8*E14)) -> 0.020979021 | F20: =IF(F13="preference",F19/$C$7,F19/($C$8*F14)) -> 0.014033862 | G20: =IF(G13="preference",G19/$C$7,G19/($C$8*G14)) -> 0.0070096882 | H20: =IF(H13="preference",H19/$C$7,H19/($C$8*H14)) -> 0.003505939
B21: Feasibility (3x) | D21: =IF(OR(D20<=0,D20>1),"infeasible","feasible") -> feasible | E21: =IF(OR(E20<=0,E20>1),"infeasible","feasible") -> feasible | F21: =IF(OR(F20<=0,F20>1),"infeasible","feasible") -> feasible | G21: =IF(OR(G20<=0,G20>1),"infeasible","feasible") -> feasible | H21: =IF(OR(H20<=0,H20>1),"infeasible","feasible") -> feasible
B23: Target proceeds (4x) | D23: =Assumptions!$C$71*Assumptions!$C$11 -> 40000000 | E23: =Assumptions!$C$71*Assumptions!$C$11 -> 40000000 | F23: =Assumptions!$C$71*Assumptions!$C$11 -> 40000000 | G23: =Assumptions!$C$71*Assumptions!$C$11 -> 40000000 | H23: =Assumptions!$C$71*Assumptions!$C$11 -> 40000000
B24: Required ownership % (4x) | D24: =IF(D13="preference",D23/$C$7,D23/($C$8*D14)) -> 0.027972028 | E24: =IF(E13="preference",E23/$C$7,E23/($C$8*E14)) -> 0.027972028 | F24: =IF(F13="preference",F23/$C$7,F23/($C$8*F14)) -> 0.018711815 | G24: =IF(G13="preference",G23/$C$7,G23/($C$8*G14)) -> 0.009346251 | H24: =IF(H13="preference",H23/$C$7,H23/($C$8*H14)) -> 0.0046745854
B25: Feasibility (4x) | D25: =IF(OR(D24<=0,D24>1),"infeasible","feasible") -> feasible | E25: =IF(OR(E24<=0,E24>1),"infeasible","feasible") -> feasible | F25: =IF(OR(F24<=0,F24>1),"infeasible","feasible") -> feasible | G25: =IF(OR(G24<=0,G24>1),"infeasible","feasible") -> feasible | H25: =IF(OR(H24<=0,H24>1),"infeasible","feasible") -> feasible
B27: Actual vs Required (Base Case)
B28: Actual ownership % | D28: =$C$9 -> 0.006993007 | E28: =$C$9 -> 0.006993007 | F28: =$C$9 -> 0.006993007 | G28: =$C$9 -> 0.006993007 | H28: =$C$9 -> 0.006993007
B29: Implied multiple at actual % (per exit) | D29: =(IF(D13="preference",$C$9*$C$7,$C$9*$C$8*D14))/Assumptions!$C$11 -> 1 | E29: =(IF(E13="preference",$C$9*$C$7,$C$9*$C$8*E14))/Assumptions!$C$11 -> 1 | F29: =(IF(F13="preference",$C$9*$C$7,$C$9*$C$8*F14))/Assumptions!$C$11 -> 1.4948858 | G29: =(IF(G13="preference",$C$9*$C$7,$C$9*$C$8*G14))/Assumptions!$C$11 -> 2.9928608 | H29: =(IF(H13="preference",$C$9*$C$7,$C$9*$C$8*H14))/Assumptions!$C$11 -> 5.9838522

Sheet Sens-Engine
B2: Sensitivity Engine — 9 Per-Cell Fixed-Point Solvers
B3: Each block re-solves F PPS for a (pre-money, ESOP) pair, then runs $2B waterfall
B5: Block 1: pre=$1.2B, ESOP=11%
B6: Pre / ESOP / Post | C6: =Assumptions!$C$65 -> 1200000000 | D6: =Assumptions!$C$62 -> 0.11 | E6: =C6+Assumptions!$C$7 -> 1230000000
B7: Iter | D7: p | E7: q | F7: NCP_D | G7: NCP_E | H7: D sh | I7: E sh | J7: topup | K7: NA sh | L7: NB sh | M7: pre-FD | N7: p_new
B8: 1 | D8: =($C$6+Assumptions!$C$7)/Assumptions!$C$28 -> 33.590073 | E8: =Assumptions!$C$28+Assumptions!$C$7/D8 -> 37511082 | F8: =IF(D8<Assumptions!$C$35,(Assumptions!$C$35*Assumptions!$C$28+Assumptions!$C$7)/E8,Assumptions!$C$35) -> 57.53434 | G8: =IF(D8<Assumptions!$C$36,(Assumptions!$C$36*Assumptions!$C$28+Assumptions!$C$7)/E8,Assumptions!$C$36) -> 48.787639 | H8: =IF(D8<Assumptions!$C$35,Assumptions!$C$43/F8,Assumptions!$C$24) -> 1738092.4 | I8: =IF(D8<Assumptions!$C$36,Assumptions!$C$44/G8,Assumptions!$C$25) -> 6149098.6 | J8: =MAX(0,$D$6*($C$6+Assumptions!$C$7)/D8-Assumptions!$C$26-Assumptions!$C$27) -> 0 | K8: 0 | L8: 0 | M8: =Assumptions!$C$28+(H8-Assumptions!$C$24)+(I8-Assumptions!$C$25)+J8+K8+L8 -> 36681858 | N8: =$C$6/M8 -> 32.713719
B9: 2 | D9: =N8 -> 32.713719 | E9: =Assumptions!$C$28+Assumptions!$C$7/D9 -> 37535007 | F9: =IF(D9<Assumptions!$C$35,(Assumptions!$C$35*Assumptions!$C$28+Assumptions!$C$7)/E9,Assumptions!$C$35) -> 57.497667 | G9: =IF(D9<Assumptions!$C$36,(Assumptions!$C$36*Assumptions!$C$28+Assumptions!$C$7)/E9,Assumptions!$C$36) -> 48.756541 | H9: =IF(D9<Assumptions!$C$35,Assumptions!$C$43/F9,Assumptions!$C$24) -> 1739201 | I9: =IF(D9<Assumptions!$C$36,Assumptions!$C$44/G9,Assumptions!$C$25) -> 6153020.6 | J9: =MAX(0,$D$6*($C$6+Assumptions!$C$7)/D9-Assumptions!$C$26-Assumptions!$C$27) -> 0 | K9: =IF((M8-K8)<=0,0,Assumptions!$C$47/MIN(Assumptions!$C$48/(M8-K8),D9*(1-Assumptions!$C$49))) -> 191051.34 | L9: =IF((M8-L8)<=0,0,Assumptions!$C$50/MIN(Assumptions!$C$51/(M8-L8),D9*(1-Assumptions!$C$52))) -> 107887.82 | M9: =Assumptions!$C$28+(H9-Assumptions!$C$24)+(I9-Assumptions!$C$25)+J9+K9+L9 -> 36985828 | N9: =$C$6/M9 -> 32.44486
B10: 3 | D10: =N9 -> 32.44486 | E10: =Assumptions!$C$28+Assumptions!$C$7/D10 -> 37542607 | F10: =IF(D10<Assumptions!$C$35,(Assumptions!$C$35*Assumptions!$C$28+Assumptions!$C$7)/E10,Assumptions!$C$35) -> 57.486029 | G10: =IF(D10<Assumptions!$C$36,(Assumptions!$C$36*Assumptions!$C$28+Assumptions!$C$7)/E10,Assumptions!$C$36) -> 48.746671 | H10: =IF(D10<Assumptions!$C$35,Assumptions!$C$43/F10,Assumptions!$C$24) -> 1739553.1 | I10: =IF(D10<Assumptions!$C$36,Assumptions!$C$44/G10,Assumptions!$C$25) -> 6154266.4 | J10: =MAX(0,$D$6*($C$6+Assumptions!$C$7)/D10-Assumptions!$C$26-Assumptions!$C$27) -> 0 | K10: =IF((M9-K9)<=0,0,Assumptions!$C$47/MIN(Assumptions!$C$48/(M9-K9),D10*(1-Assumptions!$C$49))) -> 192634.52 | L10: =IF((M9-L9)<=0,0,Assumptions!$C$50/MIN(Assumptions!$C$51/(M9-L9),D10*(1-Assumptions!$C$52))) -> 108781.85 | M10: =Assumptions!$C$28+(H10-Assumptions!$C$24)+(I10-Assumptions!$C$25)+J10+K10+L10 -> 36989903 | N10: =$C$6/M10 -> 32.441286
B11: 4 | D11: =N10 -> 32.441286 | E11: =Assumptions!$C$28+Assumptions!$C$7/D11 -> 37542709 | F11: =IF(D11<Assumptions!$C$35,(Assumptions!$C$35*Assumptions!$C$28+Assumptions!$C$7)/E11,Assumptions!$C$35) -> 57.485873 | G11: =IF(D11<Assumptions!$C$36,(Assumptions!$C$36*Assumptions!$C$28+Assumptions!$C$7)/E11,Assumptions!$C$36) -> 48.746539 | H11: =IF(D11<Assumptions!$C$35,Assumptions!$C$43/F11,Assumptions!$C$24) -> 1739557.8 | I11: =IF(D11<Assumptions!$C$36,Assumptions!$C$44/G11,Assumptions!$C$25) -> 6154283.1 | J11: =MAX(0,$D$6*($C$6+Assumptions!$C$7)/D11-Assumptions!$C$26-Assumptions!$C$27) -> 0 | K11: =IF((M10-K10)<=0,0,Assumptions!$C$47/MIN(Assumptions!$C$48/(M10-K10),D11*(1-Assumptions!$C$49))) -> 192655.74 | L11: =IF((M10-L10)<=0,0,Assumptions!$C$50/MIN(Assumptions!$C$51/(M10-L10),D11*(1-Assumptions!$C$52))) -> 108793.83 | M11: =Assumptions!$C$28+(H11-Assumptions!$C$24)+(I11-Assumptions!$C$25)+J11+K11+L11 -> 36989957 | N11: =$C$6/M11 -> 32.441238
B12: 5 | D12: =N11 -> 32.441238 | E12: =Assumptions!$C$28+Assumptions!$C$7/D12 -> 37542710 | F12: =IF(D12<Assumptions!$C$35,(Assumptions!$C$35*Assumptions!$C$28+Assumptions!$C$7)/E12,Assumptions!$C$35) -> 57.485871 | G12: =IF(D12<Assumptions!$C$36,(Assumptions!$C$36*Assumptions!$C$28+Assumptions!$C$7)/E12,Assumptions!$C$36) -> 48.746537 | H12: =IF(D12<Assumptions!$C$35,Assumptions!$C$43/F12,Assumptions!$C$24) -> 1739557.9 | I12: =IF(D12<Assumptions!$C$36,Assumptions!$C$44/G12,Assumptions!$C$25) -> 6154283.3 | J12: =MAX(0,$D$6*($C$6+Assumptions!$C$7)/D12-Assumptions!$C$26-Assumptions!$C$27) -> 0 | K12: =IF((M11-K11)<=0,0,Assumptions!$C$47/MIN(Assumptions!$C$48/(M11-K11),D12*(1-Assumptions!$C$49))) -> 192656.03 | L12: =IF((M11-L11)<=0,0,Assumptions!$C$50/MIN(Assumptions!$C$51/(M11-L11),D12*(1-Assumptions!$C$52))) -> 108793.99 | M12: =Assumptions!$C$28+(H12-Assumptions!$C$24)+(I12-Assumptions!$C$25)+J12+K12+L12 -> 36989958 | N12: =$C$6/M12 -> 32.441237
B13: 6 | D13: =N12 -> 32.441237 | E13: =Assumptions!$C$28+Assumptions!$C$7/D13 -> 37542710 | F13: =IF(D13<Assumptions!$C$35,(Assumptions!$C$35*Assumptions!$C$28+Assumptions!$C$7)/E13,Assumptions!$C$35) -> 57.485871 | G13: =IF(D13<Assumptions!$C$36,(Assumptions!$C$36*Assumptions!$C$28+Assumptions!$C$7)/E13,Assumptions!$C$36) -> 48.746537 | H13: =IF(D13<Assumptions!$C$35,Assumptions!$C$43/F13,Assumptions!$C$24) -> 1739557.9 | I13: =IF(D13<Assumptions!$C$36,Assumptions!$C$44/G13,Assumptions!$C$25) -> 6154283.3 | J13: =MAX(0,$D$6*($C$6+Assumptions!$C$7)/D13-Assumptions!$C$26-Assumptions!$C$27) -> 0 | K13: =IF((M12-K12)<=0,0,Assumptions!$C$47/MIN(Assumptions!$C$48/(M12-K12),D13*(1-Assumptions!$C$49))) -> 192656.03 | L13: =IF((M12-L12)<=0,0,Assumptions!$C$50/MIN(Assumptions!$C$51/(M12-L12),D13*(1-Assumptions!$C$52))) -> 108793.99 | M13: =Assumptions!$C$28+(H13-Assumptions!$C$24)+(I13-Assumptions!$C$25)+J13+K13+L13 -> 36989958 | N13: =$C$6/M13 -> 32.441237
B14: 7 | D14: =N13 -> 32.441237 | E14: =Assumptions!$C$28+Assumptions!$C$7/D14 -> 37542710 | F14: =IF(D14<Assumptions!$C$35,(Assumptions!$C$35*Assumptions!$C$28+Assumptions!$C$7)/E14,Assumptions!$C$35) -> 57.485871 | G14: =IF(D14<Assumptions!$C$36,(Assumptions!$C$36*Assumptions!$C$28+Assumptions!$C$7)/E14,Assumptions!$C$36) -> 48.746537 | H14: =IF(D14<Assumptions!$C$35,Assumptions!$C$43/F14,Assumptions!$C$24) -> 1739557.9 | I14: =IF(D14<Assumptions!$C$36,Assumptions!$C$44/G14,Assumptions!$C$25) -> 6154283.3 | J14: =MAX(0,$D$6*($C$6+Assumptions!$C$7)/D14-Assumptions!$C$26-Assumptions!$C$27) -> 0 | K14: =IF((M13-K13)<=0,0,Assumptions!$C$47/MIN(Assumptions!$C$48/(M13-K13),D14*(1-Assumptions!$C$49))) -> 192656.03 | L14: =IF((M13-L13)<=0,0,Assumptions!$C$50/MIN(Assumptions!$C$51/(M13-L13),D14*(1-Assumptions!$C$52))) -> 108793.99 | M14: =Assumptions!$C$28+(H14-Assumptions!$C$24)+(I14-Assumptions!$C$25)+J14+K14+L14 -> 36989958 | N14: =$C$6/M14 -> 32.441237
B15: 8 | D15: =N14 -> 32.441237 | E15: =Assumptions!$C$28+Assumptions!$C$7/D15 -> 37542710 | F15: =IF(D15<Assumptions!$C$35,(Assumptions!$C$35*Assumptions!$C$28+Assumptions!$C$7)/E15,Assumptions!$C$35) -> 57.485871 | G15: =IF(D15<Assumptions!$C$36,(Assumptions!$C$36*Assumptions!$C$28+Assumptions!$C$7)/E15,Assumptions!$C$36) -> 48.746537 | H15: =IF(D15<Assumptions!$C$35,Assumptions!$C$43/F15,Assumptions!$C$24) -> 1739557.9 | I15: =IF(D15<Assumptions!$C$36,Assumptions!$C$44/G15,Assumptions!$C$25) -> 6154283.3 | J15: =MAX(0,$D$6*($C$6+Assumptions!$C$7)/D15-Assumptions!$C$26-Assumptions!$C$27) -> 0 | K15: =IF((M14-K14)<=0,0,Assumptions!$C$47/MIN(Assumptions!$C$48/(M14-K14),D15*(1-Assumptions!$C$49))) -> 192656.03 | L15: =IF((M14-L14)<=0,0,Assumptions!$C$50/MIN(Assumptions!$C$51/(M14-L14),D15*(1-Assumptions!$C$52))) -> 108793.99 | M15: =Assumptions!$C$28+(H15-Assumptions!$C$24)+(I15-Assumptions!$C$25)+J15+K15+L15 -> 36989958 | N15: =$C$6/M15 -> 32.441237
B16: 9 | D16: =N15 -> 32.441237 | E16: =Assumptions!$C$28+Assumptions!$C$7/D16 -> 37542710 | F16: =IF(D16<Assumptions!$C$35,(Assumptions!$C$35*Assumptions!$C$28+Assumptions!$C$7)/E16,Assumptions!$C$35) -> 57.485871 | G16: =IF(D16<Assumptions!$C$36,(Assumptions!$C$36*Assumptions!$C$28+Assumptions!$C$7)/E16,Assumptions!$C$36) -> 48.746537 | H16: =IF(D16<Assumptions!$C$35,Assumptions!$C$43/F16,Assumptions!$C$24) -> 1739557.9 | I16: =IF(D16<Assumptions!$C$36,Assumptions!$C$44/G16,Assumptions!$C$25) -> 6154283.3 | J16: =MAX(0,$D$6*($C$6+Assumptions!$C$7)/D16-Assumptions!$C$26-Assumptions!$C$27) -> 0 | K16: =IF((M15-K15)<=0,0,Assumptions!$C$47/MIN(Assumptions!$C$48/(M15-K15),D16*(1-Assumptions!$C$49))) -> 192656.03 | L16: =IF((M15-L15)<=0,0,Assumptions!$C$50/MIN(Assumptions!$C$51/(M15-L15),D16*(1-Assumptions!$C$52))) -> 108793.99 | M16: =Assumptions!$C$28+(H16-Assumptions!$C$24)+(I16-Assumptions!$C$25)+J16+K16+L16 -> 36989958 | N16: =$C$6/M16 -> 32.441237
B17: 10 | D17: =N16 -> 32.441237 | E17: =Assumptions!$C$28+Assumptions!$C$7/D17 -> 37542710 | F17: =IF(D17<Assumptions!$C$35,(Assumptions!$C$35*Assumptions!$C$28+Assumptions!$C$7)/E17,Assumptions!$C$35) -> 57.485871 | G17: =IF(D17<Assumptions!$C$36,(Assumptions!$C$36*Assumptions!$C$28+Assumptions!$C$7)/E17,Assumptions!$C$36) -> 48.746537 | H17: =IF(D17<Assumptions!$C$35,Assumptions!$C$43/F17,Assumptions!$C$24) -> 1739557.9 | I17: =IF(D17<Assumptions!$C$36,Assumptions!$C$44/G17,Assumptions!$C$25) -> 6154283.3 | J17: =MAX(0,$D$6*($C$6+Assumptions!$C$7)/D17-Assumptions!$C$26-Assumptions!$C$27) -> 0 | K17: =IF((M16-K16)<=0,0,Assumptions!$C$47/MIN(Assumptions!$C$48/(M16-K16),D17*(1-Assumptions!$C$49))) -> 192656.03 | L17: =IF((M16-L16)<=0,0,Assumptions!$C$50/MIN(Assumptions!$C$51/(M16-L16),D17*(1-Assumptions!$C$52))) -> 108793.99 | M17: =Assumptions!$C$28+(H17-Assumptions!$C$24)+(I17-Assumptions!$C$25)+J17+K17+L17 -> 36989958 | N17: =$C$6/M17 -> 32.441237
B18: 11 | D18: =N17 -> 32.441237 | E18: =Assumptions!$C$28+Assumptions!$C$7/D18 -> 37542710 | F18: =IF(D18<Assumptions!$C$35,(Assumptions!$C$35*Assumptions!$C$28+Assumptions!$C$7)/E18,Assumptions!$C$35) -> 57.485871 | G18: =IF(D18<Assumptions!$C$36,(Assumptions!$C$36*Assumptions!$C$28+Assumptions!$C$7)/E18,Assumptions!$C$36) -> 48.746537 | H18: =IF(D18<Assumptions!$C$35,Assumptions!$C$43/F18,Assumptions!$C$24) -> 1739557.9 | I18: =IF(D18<Assumptions!$C$36,Assumptions!$C$44/G18,Assumptions!$C$25) -> 6154283.3 | J18: =MAX(0,$D$6*($C$6+Assumptions!$C$7)/D18-Assumptions!$C$26-Assumptions!$C$27) -> 0 | K18: =IF((M17-K17)<=0,0,Assumptions!$C$47/MIN(Assumptions!$C$48/(M17-K17),D18*(1-Assumptions!$C$49))) -> 192656.03 | L18: =IF((M17-L17)<=0,0,Assumptions!$C$50/MIN(Assumptions!$C$51/(M17-L17),D18*(1-Assumptions!$C$52))) -> 108793.99 | M18: =Assumptions!$C$28+(H18-Assumptions!$C$24)+(I18-Assumptions!$C$25)+J18+K18+L18 -> 36989958 | N18: =$C$6/M18 -> 32.441237
B19: 12 | D19: =N18 -> 32.441237 | E19: =Assumptions!$C$28+Assumptions!$C$7/D19 -> 37542710 | F19: =IF(D19<Assumptions!$C$35,(Assumptions!$C$35*Assumptions!$C$28+Assumptions!$C$7)/E19,Assumptions!$C$35) -> 57.485871 | G19: =IF(D19<Assumptions!$C$36,(Assumptions!$C$36*Assumptions!$C$28+Assumptions!$C$7)/E19,Assumptions!$C$36) -> 48.746537 | H19: =IF(D19<Assumptions!$C$35,Assumptions!$C$43/F19,Assumptions!$C$24) -> 1739557.9 | I19: =IF(D19<Assumptions!$C$36,Assumptions!$C$44/G19,Assumptions!$C$25) -> 6154283.3 | J19: =MAX(0,$D$6*($C$6+Assumptions!$C$7)/D19-Assumptions!$C$26-Assumptions!$C$27) -> 0 | K19: =IF((M18-K18)<=0,0,Assumptions!$C$47/MIN(Assumptions!$C$48/(M18-K18),D19*(1-Assumptions!$C$49))) -> 192656.03 | L19: =IF((M18-L18)<=0,0,Assumptions!$C$50/MIN(Assumptions!$C$51/(M18-L18),D19*(1-Assumptions!$C$52))) -> 108793.99 | M19: =Assumptions!$C$28+(H19-Assumptions!$C$24)+(I19-Assumptions!$C$25)+J19+K19+L19 -> 36989958 | N19: =$C$6/M19 -> 32.441237
B20: 13 | D20: =N19 -> 32.441237 | E20: =Assumptions!$C$28+Assumptions!$C$7/D20 -> 37542710 | F20: =IF(D20<Assumptions!$C$35,(Assumptions!$C$35*Assumptions!$C$28+Assumptions!$C$7)/E20,Assumptions!$C$35) -> 57.485871 | G20: =IF(D20<Assumptions!$C$36,(Assumptions!$C$36*Assumptions!$C$28+Assumptions!$C$7)/E20,Assumptions!$C$36) -> 48.746537 | H20: =IF(D20<Assumptions!$C$35,Assumptions!$C$43/F20,Assumptions!$C$24) -> 1739557.9 | I20: =IF(D20<Assumptions!$C$36,Assumptions!$C$44/G20,Assumptions!$C$25) -> 6154283.3 | J20: =MAX(0,$D$6*($C$6+Assumptions!$C$7)/D20-Assumptions!$C$26-Assumptions!$C$27) -> 0 | K20: =IF((M19-K19)<=0,0,Assumptions!$C$47/MIN(Assumptions!$C$48/(M19-K19),D20*(1-Assumptions!$C$49))) -> 192656.03 | L20: =IF((M19-L19)<=0,0,Assumptions!$C$50/MIN(Assumptions!$C$51/(M19-L19),D20*(1-Assumptions!$C$52))) -> 108793.99 | M20: =Assumptions!$C$28+(H20-Assumptions!$C$24)+(I20-Assumptions!$C$25)+J20+K20+L20 -> 36989958 | N20: =$C$6/M20 -> 32.441237
... B27: 20 | D27: =N26 -> 32.441237 | E27: =Assumptions!$C$28+Assumptions!$C$7/D27 -> 37542710 | F27: =IF(D27<Assumptions!$C$35,(Assumptions!$C$35*Assumptions!$C$28+Assumptions!$C$7)/E27,Assumptions!$C$35) -> 57.485871 | G27: =IF(D27<Assumptions!$C$36,(Assumptions!$C$36*Assumptions!$C$28+Assumptions!$C$7)/E27,Assumptions!$C$36) -> 48.746537 | H27: =IF(D27<Assumptions!$C$35,Assumptions!$C$43/F27,Assumptions!$C$24) -> 1739557.9 | I27: =IF(D27<Assumptions!$C$36,Assumptions!$C$44/G27,Assumptions!$C$25) -> 6154283.3 | J27: =MAX(0,$D$6*($C$6+Assumptions!$C$7)/D27-Assumptions!$C$26-Assumptions!$C$27) -> 0 | K27: =IF((M26-K26)<=0,0,Assumptions!$C$47/MIN(Assumptions!$C$48/(M26-K26),D27*(1-Assumptions!$C$49))) -> 192656.03 | L27: =IF((M26-L26)<=0,0,Assumptions!$C$50/MIN(Assumptions!$C$51/(M26-L26),D27*(1-Assumptions!$C$52))) -> 108793.99 | M27: =Assumptions!$C$28+(H27-Assumptions!$C$24)+(I27-Assumptions!$C$25)+J27+K27+L27 -> 36989958 | N27: =$C$6/M27 -> 32.441237
B28: Outputs | D28: =N27 -> 32.441237 | E28: =$E$6/D28 -> 37914707 | H28: =H27 -> 1739557.9 | I28: =I27 -> 6154283.3 | J28: =J27 -> 0 | K28: =K27 -> 192656.03 | L28: =L27 -> 108793.99
B29: Total pool (all convert) | C29: =Assumptions!$C$16+Assumptions!$C$17+Assumptions!$C$18+Assumptions!$C$19+Assumptions!$C$20+Assumptions!$C$21+Assumptions!$C$22+Assumptions!$C$23+$H$28+$I$28+(Assumptions!$C$7/$D$28)+$K$28+$L$28+Assumptions!$C$26 -> 36020040
B30: Adj exit ($2B + opt strike) | C30: =Assumptions!$C$57+Assumptions!$C$26*Assumptions!$C$13 -> 2002500000
B31: Iter1 per_share | C31: =$C$30/$C$29 -> 55.594052
B32: Iter1 elections (F E D C B A Seed) | D32: =IF(Assumptions!$C$7>(Assumptions!$C$7/$D$28)*$C$31,"preference","convert") -> convert | E32: =IF(Assumptions!$C$44>$I$28*$C$31,"preference","convert") -> convert | F32: =IF(Assumptions!$C$43>$H$28*$C$31,"preference","convert") -> preference | G32: =IF(Assumptions!$C$42>Assumptions!$C$23*$C$31,"preference","convert") -> convert | H32: =IF(Assumptions!$C$41>Assumptions!$C$22*$C$31,"preference","convert") -> convert | I32: =IF(Assumptions!$C$40>Assumptions!$C$21*$C$31,"preference","convert") -> convert | J32: =IF(Assumptions!$C$39>Assumptions!$C$20*$C$31,"preference","convert") -> convert
B33: Iter2 per_share | C33: =($C$30-(IF($D$32="preference",Assumptions!$C$7,0)+IF($E$32="preference",Assumptions!$C$44,0)+IF($F$32="preference",Assumptions!$C$43,0)+IF($G$32="preference",Assumptions!$C$42,0)+IF($H$32="preference",Assumptions!$C$41,0)+IF($I$32="preference",Assumptions!$C$40,0)+IF($J$32="preference",Assumptions!$C$39,0)))/($C$29-(IF($D$32="preference",Assumptions!$C$7/$D$28,0)+IF($E$32="preference",$I$28,0)+IF($F$32="preference",$H$28,0)+IF($G$32="preference",Assumptions!$C$23,0)+IF($H$32="preference",Assumptions!$C$22,0)+IF($I$32="preference",Assumptions!$C$21,0)+IF($J$32="preference",Assumptions!$C$20,0))) -> 55.498052
B34: Iter2 elections | D34: =IF(Assumptions!$C$7>(Assumptions!$C$7/$D$28)*$C$33,"preference","convert") -> convert | E34: =IF(Assumptions!$C$44>$I$28*$C$33,"preference","convert") -> convert | F34: =IF(Assumptions!$C$43>$H$28*$C$33,"preference","convert") -> preference | G34: =IF(Assumptions!$C$42>Assumptions!$C$23*$C$33,"preference","convert") -> convert | H34: =IF(Assumptions!$C$41>Assumptions!$C$22*$C$33,"preference","convert") -> convert | I34: =IF(Assumptions!$C$40>Assumptions!$C$21*$C$33,"preference","convert") -> convert | J34: =IF(Assumptions!$C$39>Assumptions!$C$20*$C$33,"preference","convert") -> convert
B35: Final per_share | C35: =($C$30-(IF($D$34="preference",Assumptions!$C$7,0)+IF($E$34="preference",Assumptions!$C$44,0)+IF($F$34="preference",Assumptions!$C$43,0)+IF($G$34="preference",Assumptions!$C$42,0)+IF($H$34="preference",Assumptions!$C$41,0)+IF($I$34="preference",Assumptions!$C$40,0)+IF($J$34="preference",Assumptions!$C$39,0)))/($C$29-(IF($D$34="preference",Assumptions!$C$7/$D$28,0)+IF($E$34="preference",$I$28,0)+IF($F$34="preference",$H$28,0)+IF($G$34="preference",Assumptions!$C$23,0)+IF($H$34="preference",Assumptions!$C$22,0)+IF($I$34="preference",Assumptions!$C$21,0)+IF($J$34="preference",Assumptions!$C$20,0))) -> 55.498052
B36: Our $10M proceeds at $2B | C36: =IF($D$34="preference",Assumptions!$C$11,(Assumptions!$C$11/$D$28)*$C$35) -> 17107255
B37: Our $10M ownership % | C37: =(Assumptions!$C$11/$D$28)/$E$28 -> 0.0081300813
B39: Block 2: pre=$1.4B, ESOP=11%
B40: Pre / ESOP / Post | C40: =Assumptions!$C$66 -> 1400000000 | D40: =Assumptions!$C$62 -> 0.11 | E40: =C40+Assumptions!$C$7 -> 1430000000
B41: Iter | D41: p | E41: q | F41: NCP_D | G41: NCP_E | H41: D sh | I41: E sh | J41: topup | K41: NA sh | L41: NB sh | M41: pre-FD | N41: p_new
B42: 1 | D42: =($C$40+Assumptions!$C$7)/Assumptions!$C$28 -> 39.051874 | E42: =Assumptions!$C$28+Assumptions!$C$7/D42 -> 37386170 | F42: =IF(D42<Assumptions!$C$35,(Assumptions!$C$35*Assumptions!$C$28+Assumptions!$C$7)/E42,Assumptions!$C$35) -> 57.72657 | G42: =IF(D42<Assumptions!$C$36,(Assumptions!$C$36*Assumptions!$C$28+Assumptions!$C$7)/E42,Assumptions!$C$36) -> 48.950644 | H42: =IF(D42<Assumptions!$C$35,Assumptions!$C$43/F42,Assumptions!$C$24) -> 1732304.5 | I42: =IF(D42<Assumptions!$C$36,Assumptions!$C$44/G42,Assumptions!$C$25) -> 6128622.1 | J42: =MAX(0,$D$40*($C$40+Assumptions!$C$7)/D42-Assumptions!$C$26-Assumptions!$C$27) -> 0 | K42: 0 | L42: 0 | M42: =Assumptions!$C$28+(H42-Assumptions!$C$24)+(I42-Assumptions!$C$25)+J42+K42+L42 -> 36655594 | N42: =$C$40/M42 -> 38.193352
B43: 2 | D43: =N42 -> 38.193352 | E43: =Assumptions!$C$28+Assumptions!$C$7/D43 -> 37403438 | F43: =IF(D43<Assumptions!$C$35,(Assumptions!$C$35*Assumptions!$C$28+Assumptions!$C$7)/E43,Assumptions!$C$35) -> 57.69992 | G43: =IF(D43<Assumptions!$C$36,(Assumptions!$C$36*Assumptions!$C$28+Assumptions!$C$7)/E43,Assumptions!$C$36) -> 48.928045 | H43: =IF(D43<Assumptions!$C$35,Assumptions!$C$43/F43,Assumptions!$C$24) -> 1733104.7 | I43: =IF(D43<Assumptions!$C$36,Assumptions!$C$44/G43,Assumptions!$C$25) -> 6131452.8 | J43: =MAX(0,$D$40*($C$40+Assumptions!$C$7)/D43-Assumptions!$C$26-Assumptions!$C$27) -> 0 | K43: =IF((M42-K42)<=0,0,Assumptions!$C$47/MIN(Assumptions!$C$48/(M42-K42),D43*(1-Assumptions!$C$49))) -> 183277.97 | L43: =IF((M42-L42)<=0,0,Assumptions!$C$50/MIN(Assumptions!$C$51/(M42-L42),D43*(1-Assumptions!$C$52))) -> 92409.06 | M43: =Assumptions!$C$28+(H43-Assumptions!$C$24)+(I43-Assumptions!$C$25)+J43+K43+L43 -> 36934911 | N43: =$C$40/M43 -> 37.904518
B44: 3 | D44: =N43 -> 37.904518 | E44: =Assumptions!$C$28+Assumptions!$C$7/D44 -> 37409423 | F44: =IF(D44<Assumptions!$C$35,(Assumptions!$C$35*Assumptions!$C$28+Assumptions!$C$7)/E44,Assumptions!$C$35) -> 57.690688 | G44: =IF(D44<Assumptions!$C$36,(Assumptions!$C$36*Assumptions!$C$28+Assumptions!$C$7)/E44,Assumptions!$C$36) -> 48.920217 | H44: =IF(D44<Assumptions!$C$35,Assumptions!$C$43/F44,Assumptions!$C$24) -> 1733382 | I44: =IF(D44<Assumptions!$C$36,Assumptions!$C$44/G44,Assumptions!$C$25) -> 6132433.9 | J44: =MAX(0,$D$40*($C$40+Assumptions!$C$7)/D44-Assumptions!$C$26-Assumptions!$C$27) -> 0 | K44: =IF((M43-K43)<=0,0,Assumptions!$C$47/MIN(Assumptions!$C$48/(M43-K43),D44*(1-Assumptions!$C$49))) -> 183758.17 | L44: =IF((M43-L43)<=0,0,Assumptions!$C$50/MIN(Assumptions!$C$51/(M43-L43),D44*(1-Assumptions!$C$52))) -> 93113.222 | M44: =Assumptions!$C$28+(H44-Assumptions!$C$24)+(I44-Assumptions!$C$25)+J44+K44+L44 -> 36937354 | N44: =$C$40/M44 -> 37.902011
B45: 4 | D45: =N44 -> 37.902011 | E45: =Assumptions!$C$28+Assumptions!$C$7/D45 -> 37409476 | F45: =IF(D45<Assumptions!$C$35,(Assumptions!$C$35*Assumptions!$C$28+Assumptions!$C$7)/E45,Assumptions!$C$35) -> 57.690607 | G45: =IF(D45<Assumptions!$C$36,(Assumptions!$C$36*Assumptions!$C$28+Assumptions!$C$7)/E45,Assumptions!$C$36) -> 48.920149 | H45: =IF(D45<Assumptions!$C$35,Assumptions!$C$43/F45,Assumptions!$C$24) -> 1733384.4 | I45: =IF(D45<Assumptions!$C$36,Assumptions!$C$44/G45,Assumptions!$C$25) -> 6132442.5 | J45: =MAX(0,$D$40*($C$40+Assumptions!$C$7)/D45-Assumptions!$C$26-Assumptions!$C$27) -> 0 | K45: =IF((M44-K44)<=0,0,Assumptions!$C$47/MIN(Assumptions!$C$48/(M44-K44),D45*(1-Assumptions!$C$49))) -> 183767.98 | L45: =IF((M44-L44)<=0,0,Assumptions!$C$50/MIN(Assumptions!$C$51/(M44-L44),D45*(1-Assumptions!$C$52))) -> 93119.381 | M45: =Assumptions!$C$28+(H45-Assumptions!$C$24)+(I45-Assumptions!$C$25)+J45+K45+L45 -> 36937381 | N45: =$C$40/M45 -> 37.901983
B46: 5 | D46: =N45 -> 37.901983 | E46: =Assumptions!$C$28+Assumptions!$C$7/D46 -> 37409476 | F46: =IF(D46<Assumptions!$C$35,(Assumptions!$C$35*Assumptions!$C$28+Assumptions!$C$7)/E46,Assumptions!$C$35) -> 57.690606 | G46: =IF(D46<Assumptions!$C$36,(Assumptions!$C$36*Assumptions!$C$28+Assumptions!$C$7)/E46,Assumptions!$C$36) -> 48.920148 | H46: =IF(D46<Assumptions!$C$35,Assumptions!$C$43/F46,Assumptions!$C$24) -> 1733384.5 | I46: =IF(D46<Assumptions!$C$36,Assumptions!$C$44/G46,Assumptions!$C$25) -> 6132442.6 | J46: =MAX(0,$D$40*($C$40+Assumptions!$C$7)/D46-Assumptions!$C$26-Assumptions!$C$27) -> 0 | K46: =IF((M45-K45)<=0,0,Assumptions!$C$47/MIN(Assumptions!$C$48/(M45-K45),D46*(1-Assumptions!$C$49))) -> 183768.07 | L46: =IF((M45-L45)<=0,0,Assumptions!$C$50/MIN(Assumptions!$C$51/(M45-L45),D46*(1-Assumptions!$C$52))) -> 93119.449 | M46: =Assumptions!$C$28+(H46-Assumptions!$C$24)+(I46-Assumptions!$C$25)+J46+K46+L46 -> 36937382 | N46: =$C$40/M46 -> 37.901983
B47: 6 | D47: =N46 -> 37.901983 | E47: =Assumptions!$C$28+Assumptions!$C$7/D47 -> 37409476 | F47: =IF(D47<Assumptions!$C$35,(Assumptions!$C$35*Assumptions!$C$28+Assumptions!$C$7)/E47,Assumptions!$C$35) -> 57.690606 | G47: =IF(D47<Assumptions!$C$36,(Assumptions!$C$36*Assumptions!$C$28+Assumptions!$C$7)/E47,Assumptions!$C$36) -> 48.920148 | H47: =IF(D47<Assumptions!$C$35,Assumptions!$C$43/F47,Assumptions!$C$24) -> 1733384.5 | I47: =IF(D47<Assumptions!$C$36,Assumptions!$C$44/G47,Assumptions!$C$25) -> 6132442.6 | J47: =MAX(0,$D$40*($C$40+Assumptions!$C$7)/D47-Assumptions!$C$26-Assumptions!$C$27) -> 0 | K47: =IF((M46-K46)<=0,0,Assumptions!$C$47/MIN(Assumptions!$C$48/(M46-K46),D47*(1-Assumptions!$C$49))) -> 183768.07 | L47: =IF((M46-L46)<=0,0,Assumptions!$C$50/MIN(Assumptions!$C$51/(M46-L46),D47*(1-Assumptions!$C$52))) -> 93119.449 | M47: =Assumptions!$C$28+(H47-Assumptions!$C$24)+(I47-Assumptions!$C$25)+J47+K47+L47 -> 36937382 | N47: =$C$40/M47 -> 37.901983
B48: 7 | D48: =N47 -> 37.901983 | E48: =Assumptions!$C$28+Assumptions!$C$7/D48 -> 37409476 | F48: =IF(D48<Assumptions!$C$35,(Assumptions!$C$35*Assumptions!$C$28+Assumptions!$C$7)/E48,Assumptions!$C$35) -> 57.690606 | G48: =IF(D48<Assumptions!$C$36,(Assumptions!$C$36*Assumptions!$C$28+Assumptions!$C$7)/E48,Assumptions!$C$36) -> 48.920148 | H48: =IF(D48<Assumptions!$C$35,Assumptions!$C$43/F48,Assumptions!$C$24) -> 1733384.5 | I48: =IF(D48<Assumptions!$C$36,Assumptions!$C$44/G48,Assumptions!$C$25) -> 6132442.6 | J48: =MAX(0,$D$40*($C$40+Assumptions!$C$7)/D48-Assumptions!$C$26-Assumptions!$C$27) -> 0 | K48: =IF((M47-K47)<=0,0,Assumptions!$C$47/MIN(Assumptions!$C$48/(M47-K47),D48*(1-Assumptions!$C$49))) -> 183768.07 | L48: =IF((M47-L47)<=0,0,Assumptions!$C$50/MIN(Assumptions!$C$51/(M47-L47),D48*(1-Assumptions!$C$52))) -> 93119.449 | M48: =Assumptions!$C$28+(H48-Assumptions!$C$24)+(I48-Assumptions!$C$25)+J48+K48+L48 -> 36937382 | N48: =$C$40/M48 -> 37.901983
B49: 8 | D49: =N48 -> 37.901983 | E49: =Assumptions!$C$28+Assumptions!$C$7/D49 -> 37409476 | F49: =IF(D49<Assumptions!$C$35,(Assumptions!$C$35*Assumptions!$C$28+Assumptions!$C$7)/E49,Assumptions!$C$35) -> 57.690606 | G49: =IF(D49<Assumptions!$C$36,(Assumptions!$C$36*Assumptions!$C$28+Assumptions!$C$7)/E49,Assumptions!$C$36) -> 48.920148 | H49: =IF(D49<Assumptions!$C$35,Assumptions!$C$43/F49,Assumptions!$C$24) -> 1733384.5 | I49: =IF(D49<Assumptions!$C$36,Assumptions!$C$44/G49,Assumptions!$C$25) -> 6132442.6 | J49: =MAX(0,$D$40*($C$40+Assumptions!$C$7)/D49-Assumptions!$C$26-Assumptions!$C$27) -> 0 | K49: =IF((M48-K48)<=0,0,Assumptions!$C$47/MIN(Assumptions!$C$48/(M48-K48),D49*(1-Assumptions!$C$49))) -> 183768.07 | L49: =IF((M48-L48)<=0,0,Assumptions!$C$50/MIN(Assumptions!$C$51/(M48-L48),D49*(1-Assumptions!$C$52))) -> 93119.449 | M49: =Assumptions!$C$28+(H49-Assumptions!$C$24)+(I49-Assumptions!$C$25)+J49+K49+L49 -> 36937382 | N49: =$C$40/M49 -> 37.901983
B50: 9 | D50: =N49 -> 37.901983 | E50: =Assumptions!$C$28+Assumptions!$C$7/D50 -> 37409476 | F50: =IF(D50<Assumptions!$C$35,(Assumptions!$C$35*Assumptions!$C$28+Assumptions!$C$7)/E50,Assumptions!$C$35) -> 57.690606 | G50: =IF(D50<Assumptions!$C$36,(Assumptions!$C$36*Assumptions!$C$28+Assumptions!$C$7)/E50,Assumptions!$C$36) -> 48.920148 | H50: =IF(D50<Assumptions!$C$35,Assumptions!$C$43/F50,Assumptions!$C$24) -> 1733384.5 | I50: =IF(D50<Assumptions!$C$36,Assumptions!$C$44/G50,Assumptions!$C$25) -> 6132442.6 | J50: =MAX(0,$D$40*($C$40+Assumptions!$C$7)/D50-Assumptions!$C$26-Assumptions!$C$27) -> 0 | K50: =IF((M49-K49)<=0,0,Assumptions!$C$47/MIN(Assumptions!$C$48/(M49-K49),D50*(1-Assumptions!$C$49))) -> 183768.07 | L50: =IF((M49-L49)<=0,0,Assumptions!$C$50/MIN(Assumptions!$C$51/(M49-L49),D50*(1-Assumptions!$C$52))) -> 93119.449 | M50: =Assumptions!$C$28+(H50-Assumptions!$C$24)+(I50-Assumptions!$C$25)+J50+K50+L50 -> 36937382 | N50: =$C$40/M50 -> 37.901983
B51: 10 | D51: =N50 -> 37.901983 | E51: =Assumptions!$C$28+Assumptions!$C$7/D51 -> 37409476 | F51: =IF(D51<Assumptions!$C$35,(Assumptions!$C$35*Assumptions!$C$28+Assumptions!$C$7)/E51,Assumptions!$C$35) -> 57.690606 | G51: =IF(D51<Assumptions!$C$36,(Assumptions!$C$36*Assumptions!$C$28+Assumptions!$C$7)/E51,Assumptions!$C$36) -> 48.920148 | H51: =IF(D51<Assumptions!$C$35,Assumptions!$C$43/F51,Assumptions!$C$24) -> 1733384.5 | I51: =IF(D51<Assumptions!$C$36,Assumptions!$C$44/G51,Assumptions!$C$25) -> 6132442.6 | J51: =MAX(0,$D$40*($C$40+Assumptions!$C$7)/D51-Assumptions!$C$26-Assumptions!$C$27) -> 0 | K51: =IF((M50-K50)<=0,0,Assumptions!$C$47/MIN(Assumptions!$C$48/(M50-K50),D51*(1-Assumptions!$C$49))) -> 183768.07 | L51: =IF((M50-L50)<=0,0,Assumptions!$C$50/MIN(Assumptions!$C$51/(M50-L50),D51*(1-Assumptions!$C$52))) -> 93119.449 | M51: =Assumptions!$C$28+(H51-Assumptions!$C$24)+(I51-Assumptions!$C$25)+J51+K51+L51 -> 36937382 | N51: =$C$40/M51 -> 37.901983
B52: 11 | D52: =N51 -> 37.901983 | E52: =Assumptions!$C$28+Assumptions!$C$7/D52 -> 37409476 | F52: =IF(D52<Assumptions!$C$35,(Assumptions!$C$35*Assumptions!$C$28+Assumptions!$C$7)/E52,Assumptions!$C$35) -> 57.690606 | G52: =IF(D52<Assumptions!$C$36,(Assumptions!$C$36*Assumptions!$C$28+Assumptions!$C$7)/E52,Assumptions!$C$36) -> 48.920148 | H52: =IF(D52<Assumptions!$C$35,Assumptions!$C$43/F52,Assumptions!$C$24) -> 1733384.5 | I52: =IF(D52<Assumptions!$C$36,Assumptions!$C$44/G52,Assumptions!$C$25) -> 6132442.6 | J52: =MAX(0,$D$40*($C$40+Assumptions!$C$7)/D52-Assumptions!$C$26-Assumptions!$C$27) -> 0 | K52: =IF((M51-K51)<=0,0,Assumptions!$C$47/MIN(Assumptions!$C$48/(M51-K51),D52*(1-Assumptions!$C$49))) -> 183768.07 | L52: =IF((M51-L51)<=0,0,Assumptions!$C$50/MIN(Assumptions!$C$51/(M51-L51),D52*(1-Assumptions!$C$52))) -> 93119.449 | M52: =Assumptions!$C$28+(H52-Assumptions!$C$24)+(I52-Assumptions!$C$25)+J52+K52+L52 -> 36937382 | N52: =$C$40/M52 -> 37.901983
B53: 12 | D53: =N52 -> 37.901983 | E53: =Assumptions!$C$28+Assumptions!$C$7/D53 -> 37409476 | F53: =IF(D53<Assumptions!$C$35,(Assumptions!$C$35*Assumptions!$C$28+Assumptions!$C$7)/E53,Assumptions!$C$35) -> 57.690606 | G53: =IF(D53<Assumptions!$C$36,(Assumptions!$C$36*Assumptions!$C$28+Assumptions!$C$7)/E53,Assumptions!$C$36) -> 48.920148 | H53: =IF(D53<Assumptions!$C$35,Assumptions!$C$43/F53,Assumptions!$C$24) -> 1733384.5 | I53: =IF(D53<Assumptions!$C$36,Assumptions!$C$44/G53,Assumptions!$C$25) -> 6132442.6 | J53: =MAX(0,$D$40*($C$40+Assumptions!$C$7)/D53-Assumptions!$C$26-Assumptions!$C$27) -> 0 | K53: =IF((M52-K52)<=0,0,Assumptions!$C$47/MIN(Assumptions!$C$48/(M52-K52),D53*(1-Assumptions!$C$49))) -> 183768.07 | L53: =IF((M52-L52)<=0,0,Assumptions!$C$50/MIN(Assumptions!$C$51/(M52-L52),D53*(1-Assumptions!$C$52))) -> 93119.449 | M53: =Assumptions!$C$28+(H53-Assumptions!$C$24)+(I53-Assumptions!$C$25)+J53+K53+L53 -> 36937382 | N53: =$C$40/M53 -> 37.901983
B54: 13 | D54: =N53 -> 37.901983 | E54: =Assumptions!$C$28+Assumptions!$C$7/D54 -> 37409476 | F54: =IF(D54<Assumptions!$C$35,(Assumptions!$C$35*Assumptions!$C$28+Assumptions!$C$7)/E54,Assumptions!$C$35) -> 57.690606 | G54: =IF(D54<Assumptions!$C$36,(Assumptions!$C$36*Assumptions!$C$28+Assumptions!$C$7)/E54,Assumptions!$C$36) -> 48.920148 | H54: =IF(D54<Assumptions!$C$35,Assumptions!$C$43/F54,Assumptions!$C$24) -> 1733384.5 | I54: =IF(D54<Assumptions!$C$36,Assumptions!$C$44/G54,Assumptions!$C$25) -> 6132442.6 | J54: =MAX(0,$D$40*($C$40+Assumptions!$C$7)/D54-Assumptions!$C$26-Assumptions!$C$27) -> 0 | K54: =IF((M53-K53)<=0,0,Assumptions!$C$47/MIN(Assumptions!$C$48/(M53-K53),D54*(1-Assumptions!$C$49))) -> 183768.07 | L54: =IF((M53-L53)<=0,0,Assumptions!$C$50/MIN(Assumptions!$C$51/(M53-L53),D54*(1-Assumptions!$C$52))) -> 93119.449 | M54: =Assumptions!$C$28+(H54-Assumptions!$C$24)+(I54-Assumptions!$C$25)+J54+K54+L54 -> 36937382 | N54: =$C$40/M54 -> 37.901983
... B61: 20 | D61: =N60 -> 37.901983 | E61: =Assumptions!$C$28+Assumptions!$C$7/D61 -> 37409476 | F61: =IF(D61<Assumptions!$C$35,(Assumptions!$C$35*Assumptions!$C$28+Assumptions!$C$7)/E61,Assumptions!$C$35) -> 57.690606 | G61: =IF(D61<Assumptions!$C$36,(Assumptions!$C$36*Assumptions!$C$28+Assumptions!$C$7)/E61,Assumptions!$C$36) -> 48.920148 | H61: =IF(D61<Assumptions!$C$35,Assumptions!$C$43/F61,Assumptions!$C$24) -> 1733384.5 | I61: =IF(D61<Assumptions!$C$36,Assumptions!$C$44/G61,Assumptions!$C$25) -> 6132442.6 | J61: =MAX(0,$D$40*($C$40+Assumptions!$C$7)/D61-Assumptions!$C$26-Assumptions!$C$27) -> 0 | K61: =IF((M60-K60)<=0,0,Assumptions!$C$47/MIN(Assumptions!$C$48/(M60-K60),D61*(1-Assumptions!$C$49))) -> 183768.07 | L61: =IF((M60-L60)<=0,0,Assumptions!$C$50/MIN(Assumptions!$C$51/(M60-L60),D61*(1-Assumptions!$C$52))) -> 93119.449 | M61: =Assumptions!$C$28+(H61-Assumptions!$C$24)+(I61-Assumptions!$C$25)+J61+K61+L61 -> 36937382 | N61: =$C$40/M61 -> 37.901983
B62: Outputs | D62: =N61 -> 37.901983 | E62: =$E$40/D62 -> 37728897 | H62: =H61 -> 1733384.5 | I62: =I61 -> 6132442.6 | J62: =J61 -> 0 | K62: =K61 -> 183768.07 | L62: =L61 -> 93119.449
B63: Total pool (all convert) | C63: =Assumptions!$C$16+Assumptions!$C$17+Assumptions!$C$18+Assumptions!$C$19+Assumptions!$C$20+Assumptions!$C$21+Assumptions!$C$22+Assumptions!$C$23+$H$62+$I$62+(Assumptions!$C$7/$D$62)+$K$62+$L$62+Assumptions!$C$26 -> 35834230
B64: Adj exit ($2B + opt strike) | C64: =Assumptions!$C$57+Assumptions!$C$26*Assumptions!$C$13 -> 2002500000
B65: Iter1 per_share | C65: =$C$64/$C$63 -> 55.882323
B66: Iter1 elections (F E D C B A Seed) | D66: =IF(Assumptions!$C$7>(Assumptions!$C$7/$D$62)*$C$65,"preference","convert") -> convert | E66: =IF(Assumptions!$C$44>$I$62*$C$65,"preference","convert") -> convert | F66: =IF(Assumptions!$C$43>$H$62*$C$65,"preference","convert") -> preference | G66: =IF(Assumptions!$C$42>Assumptions!$C$23*$C$65,"preference","convert") -> convert | H66: =IF(Assumptions!$C$41>Assumptions!$C$22*$C$65,"preference","convert") -> convert | I66: =IF(Assumptions!$C$40>Assumptions!$C$21*$C$65,"preference","convert") -> convert | J66: =IF(Assumptions!$C$39>Assumptions!$C$20*$C$65,"preference","convert") -> convert
B67: Iter2 per_share | C67: =($C$64-(IF($D$66="preference",Assumptions!$C$7,0)+IF($E$66="preference",Assumptions!$C$44,0)+IF($F$66="preference",Assumptions!$C$43,0)+IF($G$66="preference",Assumptions!$C$42,0)+IF($H$66="preference",Assumptions!$C$41,0)+IF($I$66="preference",Assumptions!$C$40,0)+IF($J$66="preference",Assumptions!$C$39,0)))/($C$63-(IF($D$66="preference",Assumptions!$C$7/$D$62,0)+IF($E$66="preference",$I$62,0)+IF($F$66="preference",$H$62,0)+IF($G$66="preference",Assumptions!$C$23,0)+IF($H$66="preference",Assumptions!$C$22,0)+IF($I$66="preference",Assumptions!$C$21,0)+IF($J$66="preference",Assumptions!$C$20,0))) -> 55.790406
B68: Iter2 elections | D68: =IF(Assumptions!$C$7>(Assumptions!$C$7/$D$62)*$C$67,"preference","convert") -> convert | E68: =IF(Assumptions!$C$44>$I$62*$C$67,"preference","convert") -> convert | F68: =IF(Assumptions!$C$43>$H$62*$C$67,"preference","convert") -> preference | G68: =IF(Assumptions!$C$42>Assumptions!$C$23*$C$67,"preference","convert") -> convert | H68: =IF(Assumptions!$C$41>Assumptions!$C$22*$C$67,"preference","convert") -> convert | I68: =IF(Assumptions!$C$40>Assumptions!$C$21*$C$67,"preference","convert") -> convert | J68: =IF(Assumptions!$C$39>Assumptions!$C$20*$C$67,"preference","convert") -> convert
B69: Final per_share | C69: =($C$64-(IF($D$68="preference",Assumptions!$C$7,0)+IF($E$68="preference",Assumptions!$C$44,0)+IF($F$68="preference",Assumptions!$C$43,0)+IF($G$68="preference",Assumptions!$C$42,0)+IF($H$68="preference",Assumptions!$C$41,0)+IF($I$68="preference",Assumptions!$C$40,0)+IF($J$68="preference",Assumptions!$C$39,0)))/($C$63-(IF($D$68="preference",Assumptions!$C$7/$D$62,0)+IF($E$68="preference",$I$62,0)+IF($F$68="preference",$H$62,0)+IF($G$68="preference",Assumptions!$C$23,0)+IF($H$68="preference",Assumptions!$C$22,0)+IF($I$68="preference",Assumptions!$C$21,0)+IF($J$68="preference",Assumptions!$C$20,0))) -> 55.790406
B70: Our $10M proceeds at $2B | C70: =IF($D$68="preference",Assumptions!$C$11,(Assumptions!$C$11/$D$62)*$C$69) -> 14719654
B71: Our $10M ownership % | C71: =(Assumptions!$C$11/$D$62)/$E$62 -> 0.006993007
B73: Block 3: pre=$1.8B, ESOP=11%
B74: Pre / ESOP / Post | C74: =Assumptions!$C$67 -> 1800000000 | D74: =Assumptions!$C$62 -> 0.11 | E74: =C74+Assumptions!$C$7 -> 1830000000
B75: Iter | D75: p | E75: q | F75: NCP_D | G75: NCP_E | H75: D sh | I75: E sh | J75: topup | K75: NA sh | L75: NB sh | M75: pre-FD | N75: p_new
B76: 1 | D76: =($C$74+Assumptions!$C$7)/Assumptions!$C$28 -> 49.975475 | E76: =Assumptions!$C$28+Assumptions!$C$7/D76 -> 37218255 | F76: =IF(D76<Assumptions!$C$35,(Assumptions!$C$35*Assumptions!$C$28+Assumptions!$C$7)/E76,Assumptions!$C$35) -> 57.98701 | G76: =IF(D76<Assumptions!$C$36,(Assumptions!$C$36*Assumptions!$C$28+Assumptions!$C$7)/E76,Assumptions!$C$36) -> 49.158311 | H76: =IF(D76<Assumptions!$C$35,Assumptions!$C$43/F76,Assumptions!$C$24) -> 1724524.2 | I76: =IF(D76<Assumptions!$C$36,Assumptions!$C$44/G76,Assumptions!$C$25) -> 6102667 | J76: =MAX(0,$D$74*($C$74+Assumptions!$C$7)/D76-Assumptions!$C$26-Assumptions!$C$27) -> 0 | K76: 0 | L76: 0 | M76: =Assumptions!$C$28+(H76-Assumptions!$C$24)+(I76-Assumptions!$C$25)+J76+K76+L76 -> 36621858 | N76: =$C$74/M76 -> 49.150974
B77: 2 | D77: =N76 -> 49.150974 | E77: =Assumptions!$C$28+Assumptions!$C$7/D77 -> 37228325 | F77: =IF(D77<Assumptions!$C$35,(Assumptions!$C$35*Assumptions!$C$28+Assumptions!$C$7)/E77,Assumptions!$C$35) -> 57.971325 | G77: =IF(D77<Assumptions!$C$36,(Assumptions!$C$36*Assumptions!$C$28+Assumptions!$C$7)/E77,Assumptions!$C$36) -> 49.158191 | H77: =IF(D77<Assumptions!$C$35,Assumptions!$C$43/F77,Assumptions!$C$24) -> 1724990.7 | I77: =IF(D77<Assumptions!$C$36,Assumptions!$C$44/G77,Assumptions!$C$25) -> 6102747 | J77: =MAX(0,$D$74*($C$74+Assumptions!$C$7)/D77-Assumptions!$C$26-Assumptions!$C$27) -> 0 | K77: =IF((M76-K76)<=0,0,Assumptions!$C$47/MIN(Assumptions!$C$48/(M76-K76),D77*(1-Assumptions!$C$49))) -> 183109.29 | L77: =IF((M76-L76)<=0,0,Assumptions!$C$50/MIN(Assumptions!$C$51/(M76-L76),D77*(1-Assumptions!$C$52))) -> 71807.565 | M77: =Assumptions!$C$28+(H77-Assumptions!$C$24)+(I77-Assumptions!$C$25)+J77+K77+L77 -> 36877322 | N77: =$C$74/M77 -> 48.810486
B78: 3 | D78: =N77 -> 48.810486 | E78: =Assumptions!$C$28+Assumptions!$C$7/D78 -> 37232583 | F78: =IF(D78<Assumptions!$C$35,(Assumptions!$C$35*Assumptions!$C$28+Assumptions!$C$7)/E78,Assumptions!$C$35) -> 57.964696 | G78: =IF(D78<Assumptions!$C$36,(Assumptions!$C$36*Assumptions!$C$28+Assumptions!$C$7)/E78,Assumptions!$C$36) -> 49.152569 | H78: =IF(D78<Assumptions!$C$35,Assumptions!$C$43/F78,Assumptions!$C$24) -> 1725188 | I78: =IF(D78<Assumptions!$C$36,Assumptions!$C$44/G78,Assumptions!$C$25) -> 6103444.9 | J78: =MAX(0,$D$74*($C$74+Assumptions!$C$7)/D78-Assumptions!$C$26-Assumptions!$C$27) -> 0 | K78: =IF((M77-K77)<=0,0,Assumptions!$C$47/MIN(Assumptions!$C$48/(M77-K77),D78*(1-Assumptions!$C$49))) -> 183471.06 | L78: =IF((M77-L77)<=0,0,Assumptions!$C$50/MIN(Assumptions!$C$51/(M77-L77),D78*(1-Assumptions!$C$52))) -> 72308.474 | M78: =Assumptions!$C$28+(H78-Assumptions!$C$24)+(I78-Assumptions!$C$25)+J78+K78+L78 -> 36879080 | N78: =$C$74/M78 -> 48.80816
B79: 4 | D79: =N78 -> 48.80816 | E79: =Assumptions!$C$28+Assumptions!$C$7/D79 -> 37232612 | F79: =IF(D79<Assumptions!$C$35,(Assumptions!$C$35*Assumptions!$C$28+Assumptions!$C$7)/E79,Assumptions!$C$35) -> 57.964651 | G79: =IF(D79<Assumptions!$C$36,(Assumptions!$C$36*Assumptions!$C$28+Assumptions!$C$7)/E79,Assumptions!$C$36) -> 49.152531 | H79: =IF(D79<Assumptions!$C$35,Assumptions!$C$43/F79,Assumptions!$C$24) -> 1725189.4 | I79: =IF(D79<Assumptions!$C$36,Assumptions!$C$44/G79,Assumptions!$C$25) -> 6103449.7 | J79: =MAX(0,$D$74*($C$74+Assumptions!$C$7)/D79-Assumptions!$C$26-Assumptions!$C$27) -> 0 | K79: =IF((M78-K78)<=0,0,Assumptions!$C$47/MIN(Assumptions!$C$48/(M78-K78),D79*(1-Assumptions!$C$49))) -> 183478.04 | L79: =IF((M78-L78)<=0,0,Assumptions!$C$50/MIN(Assumptions!$C$51/(M78-L78),D79*(1-Assumptions!$C$52))) -> 72311.921 | M79: =Assumptions!$C$28+(H79-Assumptions!$C$24)+(I79-Assumptions!$C$25)+J79+K79+L79 -> 36879096 | N79: =$C$74/M79 -> 48.808138
B80: 5 | D80: =N79 -> 48.808138 | E80: =Assumptions!$C$28+Assumptions!$C$7/D80 -> 37232613 | F80: =IF(D80<Assumptions!$C$35,(Assumptions!$C$35*Assumptions!$C$28+Assumptions!$C$7)/E80,Assumptions!$C$35) -> 57.96465 | G80: =IF(D80<Assumptions!$C$36,(Assumptions!$C$36*Assumptions!$C$28+Assumptions!$C$7)/E80,Assumptions!$C$36) -> 49.15253 | H80: =IF(D80<Assumptions!$C$35,Assumptions!$C$43/F80,Assumptions!$C$24) -> 1725189.4 | I80: =IF(D80<Assumptions!$C$36,Assumptions!$C$44/G80,Assumptions!$C$25) -> 6103449.8 | J80: =MAX(0,$D$74*($C$74+Assumptions!$C$7)/D80-Assumptions!$C$26-Assumptions!$C$27) -> 0 | K80: =IF((M79-K79)<=0,0,Assumptions!$C$47/MIN(Assumptions!$C$48/(M79-K79),D80*(1-Assumptions!$C$49))) -> 183478.09 | L80: =IF((M79-L79)<=0,0,Assumptions!$C$50/MIN(Assumptions!$C$51/(M79-L79),D80*(1-Assumptions!$C$52))) -> 72311.953 | M80: =Assumptions!$C$28+(H80-Assumptions!$C$24)+(I80-Assumptions!$C$25)+J80+K80+L80 -> 36879096 | N80: =$C$74/M80 -> 48.808138
B81: 6 | D81: =N80 -> 48.808138 | E81: =Assumptions!$C$28+Assumptions!$C$7/D81 -> 37232613 | F81: =IF(D81<Assumptions!$C$35,(Assumptions!$C$35*Assumptions!$C$28+Assumptions!$C$7)/E81,Assumptions!$C$35) -> 57.96465 | G81: =IF(D81<Assumptions!$C$36,(Assumptions!$C$36*Assumptions!$C$28+Assumptions!$C$7)/E81,Assumptions!$C$36) -> 49.15253 | H81: =IF(D81<Assumptions!$C$35,Assumptions!$C$43/F81,Assumptions!$C$24) -> 1725189.4 | I81: =IF(D81<Assumptions!$C$36,Assumptions!$C$44/G81,Assumptions!$C$25) -> 6103449.8 | J81: =MAX(0,$D$74*($C$74+Assumptions!$C$7)/D81-Assumptions!$C$26-Assumptions!$C$27) -> 0 | K81: =IF((M80-K80)<=0,0,Assumptions!$C$47/MIN(Assumptions!$C$48/(M80-K80),D81*(1-Assumptions!$C$49))) -> 183478.09 | L81: =IF((M80-L80)<=0,0,Assumptions!$C$50/MIN(Assumptions!$C$51/(M80-L80),D81*(1-Assumptions!$C$52))) -> 72311.953 | M81: =Assumptions!$C$28+(H81-Assumptions!$C$24)+(I81-Assumptions!$C$25)+J81+K81+L81 -> 36879096 | N81: =$C$74/M81 -> 48.808138
B82: 7 | D82: =N81 -> 48.808138 | E82: =Assumptions!$C$28+Assumptions!$C$7/D82 -> 37232613 | F82: =IF(D82<Assumptions!$C$35,(Assumptions!$C$35*Assumptions!$C$28+Assumptions!$C$7)/E82,Assumptions!$C$35) -> 57.96465 | G82: =IF(D82<Assumptions!$C$36,(Assumptions!$C$36*Assumptions!$C$28+Assumptions!$C$7)/E82,Assumptions!$C$36) -> 49.15253 | H82: =IF(D82<Assumptions!$C$35,Assumptions!$C$43/F82,Assumptions!$C$24) -> 1725189.4 | I82: =IF(D82<Assumptions!$C$36,Assumptions!$C$44/G82,Assumptions!$C$25) -> 6103449.8 | J82: =MAX(0,$D$74*($C$74+Assumptions!$C$7)/D82-Assumptions!$C$26-Assumptions!$C$27) -> 0 | K82: =IF((M81-K81)<=0,0,Assumptions!$C$47/MIN(Assumptions!$C$48/(M81-K81),D82*(1-Assumptions!$C$49))) -> 183478.09 | L82: =IF((M81-L81)<=0,0,Assumptions!$C$50/MIN(Assumptions!$C$51/(M81-L81),D82*(1-Assumptions!$C$52))) -> 72311.953 | M82: =Assumptions!$C$28+(H82-Assumptions!$C$24)+(I82-Assumptions!$C$25)+J82+K82+L82 -> 36879096 | N82: =$C$74/M82 -> 48.808138
B83: 8 | D83: =N82 -> 48.808138 | E83: =Assumptions!$C$28+Assumptions!$C$7/D83 -> 37232613 | F83: =IF(D83<Assumptions!$C$35,(Assumptions!$C$35*Assumptions!$C$28+Assumptions!$C$7)/E83,Assumptions!$C$35) -> 57.96465 | G83: =IF(D83<Assumptions!$C$36,(Assumptions!$C$36*Assumptions!$C$28+Assumptions!$C$7)/E83,Assumptions!$C$36) -> 49.15253 | H83: =IF(D83<Assumptions!$C$35,Assumptions!$C$43/F83,Assumptions!$C$24) -> 1725189.4 | I83: =IF(D83<Assumptions!$C$36,Assumptions!$C$44/G83,Assumptions!$C$25) -> 6103449.8 | J83: =MAX(0,$D$74*($C$74+Assumptions!$C$7)/D83-Assumptions!$C$26-Assumptions!$C$27) -> 0 | K83: =IF((M82-K82)<=0,0,Assumptions!$C$47/MIN(Assumptions!$C$48/(M82-K82),D83*(1-Assumptions!$C$49))) -> 183478.09 | L83: =IF((M82-L82)<=0,0,Assumptions!$C$50/MIN(Assumptions!$C$51/(M82-L82),D83*(1-Assumptions!$C$52))) -> 72311.953 | M83: =Assumptions!$C$28+(H83-Assumptions!$C$24)+(I83-Assumptions!$C$25)+J83+K83+L83 -> 36879096 | N83: =$C$74/M83 -> 48.808138
B84: 9 | D84: =N83 -> 48.808138 | E84: =Assumptions!$C$28+Assumptions!$C$7/D84 -> 37232613 | F84: =IF(D84<Assumptions!$C$35,(Assumptions!$C$35*Assumptions!$C$28+Assumptions!$C$7)/E84,Assumptions!$C$35) -> 57.96465 | G84: =IF(D84<Assumptions!$C$36,(Assumptions!$C$36*Assumptions!$C$28+Assumptions!$C$7)/E84,Assumptions!$C$36) -> 49.15253 | H84: =IF(D84<Assumptions!$C$35,Assumptions!$C$43/F84,Assumptions!$C$24) -> 1725189.4 | I84: =IF(D84<Assumptions!$C$36,Assumptions!$C$44/G84,Assumptions!$C$25) -> 6103449.8 | J84: =MAX(0,$D$74*($C$74+Assumptions!$C$7)/D84-Assumptions!$C$26-Assumptions!$C$27) -> 0 | K84: =IF((M83-K83)<=0,0,Assumptions!$C$47/MIN(Assumptions!$C$48/(M83-K83),D84*(1-Assumptions!$C$49))) -> 183478.09 | L84: =IF((M83-L83)<=0,0,Assumptions!$C$50/MIN(Assumptions!$C$51/(M83-L83),D84*(1-Assumptions!$C$52))) -> 72311.953 | M84: =Assumptions!$C$28+(H84-Assumptions!$C$24)+(I84-Assumptions!$C$25)+J84+K84+L84 -> 36879096 | N84: =$C$74/M84 -> 48.808138
B85: 10 | D85: =N84 -> 48.808138 | E85: =Assumptions!$C$28+Assumptions!$C$7/D85 -> 37232613 | F85: =IF(D85<Assumptions!$C$35,(Assumptions!$C$35*Assumptions!$C$28+Assumptions!$C$7)/E85,Assumptions!$C$35) -> 57.96465 | G85: =IF(D85<Assumptions!$C$36,(Assumptions!$C$36*Assumptions!$C$28+Assumptions!$C$7)/E85,Assumptions!$C$36) -> 49.15253 | H85: =IF(D85<Assumptions!$C$35,Assumptions!$C$43/F85,Assumptions!$C$24) -> 1725189.4 | I85: =IF(D85<Assumptions!$C$36,Assumptions!$C$44/G85,Assumptions!$C$25) -> 6103449.8 | J85: =MAX(0,$D$74*($C$74+Assumptions!$C$7)/D85-Assumptions!$C$26-Assumptions!$C$27) -> 0 | K85: =IF((M84-K84)<=0,0,Assumptions!$C$47/MIN(Assumptions!$C$48/(M84-K84),D85*(1-Assumptions!$C$49))) -> 183478.09 | L85: =IF((M84-L84)<=0,0,Assumptions!$C$50/MIN(Assumptions!$C$51/(M84-L84),D85*(1-Assumptions!$C$52))) -> 72311.953 | M85: =Assumptions!$C$28+(H85-Assumptions!$C$24)+(I85-Assumptions!$C$25)+J85+K85+L85 -> 36879096 | N85: =$C$74/M85 -> 48.808138
B86: 11 | D86: =N85 -> 48.808138 | E86: =Assumptions!$C$28+Assumptions!$C$7/D86 -> 37232613 | F86: =IF(D86<Assumptions!$C$35,(Assumptions!$C$35*Assumptions!$C$28+Assumptions!$C$7)/E86,Assumptions!$C$35) -> 57.96465 | G86: =IF(D86<Assumptions!$C$36,(Assumptions!$C$36*Assumptions!$C$28+Assumptions!$C$7)/E86,Assumptions!$C$36) -> 49.15253 | H86: =IF(D86<Assumptions!$C$35,Assumptions!$C$43/F86,Assumptions!$C$24) -> 1725189.4 | I86: =IF(D86<Assumptions!$C$36,Assumptions!$C$44/G86,Assumptions!$C$25) -> 6103449.8 | J86: =MAX(0,$D$74*($C$74+Assumptions!$C$7)/D86-Assumptions!$C$26-Assumptions!$C$27) -> 0 | K86: =IF((M85-K85)<=0,0,Assumptions!$C$47/MIN(Assumptions!$C$48/(M85-K85),D86*(1-Assumptions!$C$49))) -> 183478.09 | L86: =IF((M85-L85)<=0,0,Assumptions!$C$50/MIN(Assumptions!$C$51/(M85-L85),D86*(1-Assumptions!$C$52))) -> 72311.953 | M86: =Assumptions!$C$28+(H86-Assumptions!$C$24)+(I86-Assumptions!$C$25)+J86+K86+L86 -> 36879096 | N86: =$C$74/M86 -> 48.808138
B87: 12 | D87: =N86 -> 48.808138 | E87: =Assumptions!$C$28+Assumptions!$C$7/D87 -> 37232613 | F87: =IF(D87<Assumptions!$C$35,(Assumptions!$C$35*Assumptions!$C$28+Assumptions!$C$7)/E87,Assumptions!$C$35) -> 57.96465 | G87: =IF(D87<Assumptions!$C$36,(Assumptions!$C$36*Assumptions!$C$28+Assumptions!$C$7)/E87,Assumptions!$C$36) -> 49.15253 | H87: =IF(D87<Assumptions!$C$35,Assumptions!$C$43/F87,Assumptions!$C$24) -> 1725189.4 | I87: =IF(D87<Assumptions!$C$36,Assumptions!$C$44/G87,Assumptions!$C$25) -> 6103449.8 | J87: =MAX(0,$D$74*($C$74+Assumptions!$C$7)/D87-Assumptions!$C$26-Assumptions!$C$27) -> 0 | K87: =IF((M86-K86)<=0,0,Assumptions!$C$47/MIN(Assumptions!$C$48/(M86-K86),D87*(1-Assumptions!$C$49))) -> 183478.09 | L87: =IF((M86-L86)<=0,0,Assumptions!$C$50/MIN(Assumptions!$C$51/(M86-L86),D87*(1-Assumptions!$C$52))) -> 72311.953 | M87: =Assumptions!$C$28+(H87-Assumptions!$C$24)+(I87-Assumptions!$C$25)+J87+K87+L87 -> 36879096 | N87: =$C$74/M87 -> 48.808138
B88: 13 | D88: =N87 -> 48.808138 | E88: =Assumptions!$C$28+Assumptions!$C$7/D88 -> 37232613 | F88: =IF(D88<Assumptions!$C$35,(Assumptions!$C$35*Assumptions!$C$28+Assumptions!$C$7)/E88,Assumptions!$C$35) -> 57.96465 | G88: =IF(D88<Assumptions!$C$36,(Assumptions!$C$36*Assumptions!$C$28+Assumptions!$C$7)/E88,Assumptions!$C$36) -> 49.15253 | H88: =IF(D88<Assumptions!$C$35,Assumptions!$C$43/F88,Assumptions!$C$24) -> 1725189.4 | I88: =IF(D88<Assumptions!$C$36,Assumptions!$C$44/G88,Assumptions!$C$25) -> 6103449.8 | J88: =MAX(0,$D$74*($C$74+Assumptions!$C$7)/D88-Assumptions!$C$26-Assumptions!$C$27) -> 0 | K88: =IF((M87-K87)<=0,0,Assumptions!$C$47/MIN(Assumptions!$C$48/(M87-K87),D88*(1-Assumptions!$C$49))) -> 183478.09 | L88: =IF((M87-L87)<=0,0,Assumptions!$C$50/MIN(Assumptions!$C$51/(M87-L87),D88*(1-Assumptions!$C$52))) -> 72311.953 | M88: =Assumptions!$C$28+(H88-Assumptions!$C$24)+(I88-Assumptions!$C$25)+J88+K88+L88 -> 36879096 | N88: =$C$74/M88 -> 48.808138
... B95: 20 | D95: =N94 -> 48.808138 | E95: =Assumptions!$C$28+Assumptions!$C$7/D95 -> 37232613 | F95: =IF(D95<Assumptions!$C$35,(Assumptions!$C$35*Assumptions!$C$28+Assumptions!$C$7)/E95,Assumptions!$C$35) -> 57.96465 | G95: =IF(D95<Assumptions!$C$36,(Assumptions!$C$36*Assumptions!$C$28+Assumptions!$C$7)/E95,Assumptions!$C$36) -> 49.15253 | H95: =IF(D95<Assumptions!$C$35,Assumptions!$C$43/F95,Assumptions!$C$24) -> 1725189.4 | I95: =IF(D95<Assumptions!$C$36,Assumptions!$C$44/G95,Assumptions!$C$25) -> 6103449.8 | J95: =MAX(0,$D$74*($C$74+Assumptions!$C$7)/D95-Assumptions!$C$26-Assumptions!$C$27) -> 0 | K95: =IF((M94-K94)<=0,0,Assumptions!$C$47/MIN(Assumptions!$C$48/(M94-K94),D95*(1-Assumptions!$C$49))) -> 183478.09 | L95: =IF((M94-L94)<=0,0,Assumptions!$C$50/MIN(Assumptions!$C$51/(M94-L94),D95*(1-Assumptions!$C$52))) -> 72311.953 | M95: =Assumptions!$C$28+(H95-Assumptions!$C$24)+(I95-Assumptions!$C$25)+J95+K95+L95 -> 36879096 | N95: =$C$74/M95 -> 48.808138
B96: Outputs | D96: =N95 -> 48.808138 | E96: =$E$74/D96 -> 37493748 | H96: =H95 -> 1725189.4 | I96: =I95 -> 6103449.8 | J96: =J95 -> 0 | K96: =K95 -> 183478.09 | L96: =L95 -> 72311.953
B97: Total pool (all convert) | C97: =Assumptions!$C$16+Assumptions!$C$17+Assumptions!$C$18+Assumptions!$C$19+Assumptions!$C$20+Assumptions!$C$21+Assumptions!$C$22+Assumptions!$C$23+$H$96+$I$96+(Assumptions!$C$7/$D$96)+$K$96+$L$96+Assumptions!$C$26 -> 35599081
B98: Adj exit ($2B + opt strike) | C98: =Assumptions!$C$57+Assumptions!$C$26*Assumptions!$C$13 -> 2002500000
B99: Iter1 per_share | C99: =$C$98/$C$97 -> 56.251452
B100: Iter1 elections (F E D C B A Seed) | D100: =IF(Assumptions!$C$7>(Assumptions!$C$7/$D$96)*$C$99,"preference","convert") -> convert | E100: =IF(Assumptions!$C$44>$I$96*$C$99,"preference","convert") -> convert | F100: =IF(Assumptions!$C$43>$H$96*$C$99,"preference","convert") -> preference | G100: =IF(Assumptions!$C$42>Assumptions!$C$23*$C$99,"preference","convert") -> convert | H100: =IF(Assumptions!$C$41>Assumptions!$C$22*$C$99,"preference","convert") -> convert | I100: =IF(Assumptions!$C$40>Assumptions!$C$21*$C$99,"preference","convert") -> convert | J100: =IF(Assumptions!$C$39>Assumptions!$C$20*$C$99,"preference","convert") -> convert
B101: Iter2 per_share | C101: =($C$98-(IF($D$100="preference",Assumptions!$C$7,0)+IF($E$100="preference",Assumptions!$C$44,0)+IF($F$100="preference",Assumptions!$C$43,0)+IF($G$100="preference",Assumptions!$C$42,0)+IF($H$100="preference",Assumptions!$C$41,0)+IF($I$100="preference",Assumptions!$C$40,0)+IF($J$100="preference",Assumptions!$C$39,0)))/($C$97-(IF($D$100="preference",Assumptions!$C$7/$D$96,0)+IF($E$100="preference",$I$96,0)+IF($F$100="preference",$H$96,0)+IF($G$100="preference",Assumptions!$C$23,0)+IF($H$100="preference",Assumptions!$C$22,0)+IF($I$100="preference",Assumptions!$C$21,0)+IF($J$100="preference",Assumptions!$C$20,0))) -> 56.1642
B102: Iter2 elections | D102: =IF(Assumptions!$C$7>(Assumptions!$C$7/$D$96)*$C$101,"preference","convert") -> convert | E102: =IF(Assumptions!$C$44>$I$96*$C$101,"preference","convert") -> convert | F102: =IF(Assumptions!$C$43>$H$96*$C$101,"preference","convert") -> preference | G102: =IF(Assumptions!$C$42>Assumptions!$C$23*$C$101,"preference","convert") -> convert | H102: =IF(Assumptions!$C$41>Assumptions!$C$22*$C$101,"preference","convert") -> convert | I102: =IF(Assumptions!$C$40>Assumptions!$C$21*$C$101,"preference","convert") -> convert | J102: =IF(Assumptions!$C$39>Assumptions!$C$20*$C$101,"preference","convert") -> convert
B103: Final per_share | C103: =($C$98-(IF($D$102="preference",Assumptions!$C$7,0)+IF($E$102="preference",Assumptions!$C$44,0)+IF($F$102="preference",Assumptions!$C$43,0)+IF($G$102="preference",Assumptions!$C$42,0)+IF($H$102="preference",Assumptions!$C$41,0)+IF($I$102="preference",Assumptions!$C$40,0)+IF($J$102="preference",Assumptions!$C$39,0)))/($C$97-(IF($D$102="preference",Assumptions!$C$7/$D$96,0)+IF($E$102="preference",$I$96,0)+IF($F$102="preference",$H$96,0)+IF($G$102="preference",Assumptions!$C$23,0)+IF($H$102="preference",Assumptions!$C$22,0)+IF($I$102="preference",Assumptions!$C$21,0)+IF($J$102="preference",Assumptions!$C$20,0))) -> 56.1642
B104: Our $10M proceeds at $2B | C104: =IF($D$102="preference",Assumptions!$C$11,(Assumptions!$C$11/$D$96)*$C$103) -> 11507138
B105: Our $10M ownership % | C105: =(Assumptions!$C$11/$D$96)/$E$96 -> 0.0054644809
B107: Block 4: pre=$1.2B, ESOP=13%
B108: Pre / ESOP / Post | C108: =Assumptions!$C$65 -> 1200000000 | D108: =Assumptions!$C$63 -> 0.13 | E108: =C108+Assumptions!$C$7 -> 1230000000
B109: Iter | D109: p | E109: q | F109: NCP_D | G109: NCP_E | H109: D sh | I109: E sh | J109: topup | K109: NA sh | L109: NB sh | M109: pre-FD | N109: p_new
B110: 1 | D110: =($C$108+Assumptions!$C$7)/Assumptions!$C$28 -> 33.590073 | E110: =Assumptions!$C$28+Assumptions!$C$7/D110 -> 37511082 | F110: =IF(D110<Assumptions!$C$35,(Assumptions!$C$35*Assumptions!$C$28+Assumptions!$C$7)/E110,Assumptions!$C$35) -> 57.53434 | G110: =IF(D110<Assumptions!$C$36,(Assumptions!$C$36*Assumptions!$C$28+Assumptions!$C$7)/E110,Assumptions!$C$36) -> 48.787639 | H110: =IF(D110<Assumptions!$C$35,Assumptions!$C$43/F110,Assumptions!$C$24) -> 1738092.4 | I110: =IF(D110<Assumptions!$C$36,Assumptions!$C$44/G110,Assumptions!$C$25) -> 6149098.6 | J110: =MAX(0,$D$108*($C$108+Assumptions!$C$7)/D110-Assumptions!$C$26-Assumptions!$C$27) -> 365667.93 | K110: 0 | L110: 0 | M110: =Assumptions!$C$28+(H110-Assumptions!$C$24)+(I110-Assumptions!$C$25)+J110+K110+L110 -> 37047526 | N110: =$C$108/M110 -> 32.390827
B111: 2 | D111: =N110 -> 32.390827 | E111: =Assumptions!$C$28+Assumptions!$C$7/D111 -> 37544149 | F111: =IF(D111<Assumptions!$C$35,(Assumptions!$C$35*Assumptions!$C$28+Assumptions!$C$7)/E111,Assumptions!$C$35) -> 57.483667 | G111: =IF(D111<Assumptions!$C$36,(Assumptions!$C$36*Assumptions!$C$28+Assumptions!$C$7)/E111,Assumptions!$C$36) -> 48.744669 | H111: =IF(D111<Assumptions!$C$35,Assumptions!$C$43/F111,Assumptions!$C$24) -> 1739624.6 | I111: =IF(D111<Assumptions!$C$36,Assumptions!$C$44/G111,Assumptions!$C$25) -> 6154519.2 | J111: =MAX(0,$D$108*($C$108+Assumptions!$C$7)/D111-Assumptions!$C$26-Assumptions!$C$27) -> 541915.83 | K111: =IF((M110-K110)<=0,0,Assumptions!$C$47/MIN(Assumptions!$C$48/(M110-K110),D111*(1-Assumptions!$C$49))) -> 192955.86 | L111: =IF((M110-L110)<=0,0,Assumptions!$C$50/MIN(Assumptions!$C$51/(M110-L110),D111*(1-Assumptions!$C$52))) -> 108963.31 | M111: =Assumptions!$C$28+(H111-Assumptions!$C$24)+(I111-Assumptions!$C$25)+J111+K111+L111 -> 37532646 | N111: =$C$108/M111 -> 31.972166
B112: 3 | D112: =N111 -> 31.972166 | E112: =Assumptions!$C$28+Assumptions!$C$7/D112 -> 37556277 | F112: =IF(D112<Assumptions!$C$35,(Assumptions!$C$35*Assumptions!$C$28+Assumptions!$C$7)/E112,Assumptions!$C$35) -> 57.465104 | G112: =IF(D112<Assumptions!$C$36,(Assumptions!$C$36*Assumptions!$C$28+Assumptions!$C$7)/E112,Assumptions!$C$36) -> 48.728928 | H112: =IF(D112<Assumptions!$C$35,Assumptions!$C$43/F112,Assumptions!$C$24) -> 1740186.5 | I112: =IF(D112<Assumptions!$C$36,Assumptions!$C$44/G112,Assumptions!$C$25) -> 6156507.3 | J112: =MAX(0,$D$108*($C$108+Assumptions!$C$7)/D112-Assumptions!$C$26-Assumptions!$C$27) -> 606558.05 | K112: =IF((M111-K111)<=0,0,Assumptions!$C$47/MIN(Assumptions!$C$48/(M111-K111),D112*(1-Assumptions!$C$49))) -> 195482.53 | L112: =IF((M111-L111)<=0,0,Assumptions!$C$50/MIN(Assumptions!$C$51/(M111-L111),D112*(1-Assumptions!$C$52))) -> 110390.13 | M112: =Assumptions!$C$28+(H112-Assumptions!$C$24)+(I112-Assumptions!$C$25)+J112+K112+L112 -> 37603792 | N112: =$C$108/M112 -> 31.911676
B113: 4 | D113: =N112 -> 31.911676 | E113: =Assumptions!$C$28+Assumptions!$C$7/D113 -> 37558056 | F113: =IF(D113<Assumptions!$C$35,(Assumptions!$C$35*Assumptions!$C$28+Assumptions!$C$7)/E113,Assumptions!$C$35) -> 57.462382 | G113: =IF(D113<Assumptions!$C$36,(Assumptions!$C$36*Assumptions!$C$28+Assumptions!$C$7)/E113,Assumptions!$C$36) -> 48.72662 | H113: =IF(D113<Assumptions!$C$35,Assumptions!$C$43/F113,Assumptions!$C$24) -> 1740269 | I113: =IF(D113<Assumptions!$C$36,Assumptions!$C$44/G113,Assumptions!$C$25) -> 6156798.9 | J113: =MAX(0,$D$108*($C$108+Assumptions!$C$7)/D113-Assumptions!$C$26-Assumptions!$C$27) -> 616038.23 | K113: =IF((M112-K112)<=0,0,Assumptions!$C$47/MIN(Assumptions!$C$48/(M112-K112),D113*(1-Assumptions!$C$49))) -> 195853.08 | L113: =IF((M112-L112)<=0,0,Assumptions!$C$50/MIN(Assumptions!$C$51/(M112-L112),D113*(1-Assumptions!$C$52))) -> 110599.39 | M113: =Assumptions!$C$28+(H113-Assumptions!$C$24)+(I113-Assumptions!$C$25)+J113+K113+L113 -> 37614226 | N113: =$C$108/M113 -> 31.902824
B114: 5 | D114: =N113 -> 31.902824 | E114: =Assumptions!$C$28+Assumptions!$C$7/D114 -> 37558317 | F114: =IF(D114<Assumptions!$C$35,(Assumptions!$C$35*Assumptions!$C$28+Assumptions!$C$7)/E114,Assumptions!$C$35) -> 57.461983 | G114: =IF(D114<Assumptions!$C$36,(Assumptions!$C$36*Assumptions!$C$28+Assumptions!$C$7)/E114,Assumptions!$C$36) -> 48.726282 | H114: =IF(D114<Assumptions!$C$35,Assumptions!$C$43/F114,Assumptions!$C$24) -> 1740281 | I114: =IF(D114<Assumptions!$C$36,Assumptions!$C$44/G114,Assumptions!$C$25) -> 6156841.6 | J114: =MAX(0,$D$108*($C$108+Assumptions!$C$7)/D114-Assumptions!$C$26-Assumptions!$C$27) -> 617428.55 | K114: =IF((M113-K113)<=0,0,Assumptions!$C$47/MIN(Assumptions!$C$48/(M113-K113),D114*(1-Assumptions!$C$49))) -> 195907.42 | L114: =IF((M113-L113)<=0,0,Assumptions!$C$50/MIN(Assumptions!$C$51/(M113-L113),D114*(1-Assumptions!$C$52))) -> 110630.08 | M114: =Assumptions!$C$28+(H114-Assumptions!$C$24)+(I114-Assumptions!$C$25)+J114+K114+L114 -> 37615756 | N114: =$C$108/M114 -> 31.901526
B115: 6 | D115: =N114 -> 31.901526 | E115: =Assumptions!$C$28+Assumptions!$C$7/D115 -> 37558355 | F115: =IF(D115<Assumptions!$C$35,(Assumptions!$C$35*Assumptions!$C$28+Assumptions!$C$7)/E115,Assumptions!$C$35) -> 57.461925 | G115: =IF(D115<Assumptions!$C$36,(Assumptions!$C$36*Assumptions!$C$28+Assumptions!$C$7)/E115,Assumptions!$C$36) -> 48.726232 | H115: =IF(D115<Assumptions!$C$35,Assumptions!$C$43/F115,Assumptions!$C$24) -> 1740282.8 | I115: =IF(D115<Assumptions!$C$36,Assumptions!$C$44/G115,Assumptions!$C$25) -> 6156847.9 | J115: =MAX(0,$D$108*($C$108+Assumptions!$C$7)/D115-Assumptions!$C$26-Assumptions!$C$27) -> 617632.45 | K115: =IF((M114-K114)<=0,0,Assumptions!$C$47/MIN(Assumptions!$C$48/(M114-K114),D115*(1-Assumptions!$C$49))) -> 195915.39 | L115: =IF((M114-L114)<=0,0,Assumptions!$C$50/MIN(Assumptions!$C$51/(M114-L114),D115*(1-Assumptions!$C$52))) -> 110634.58 | M115: =Assumptions!$C$28+(H115-Assumptions!$C$24)+(I115-Assumptions!$C$25)+J115+K115+L115 -> 37615980 | N115: =$C$108/M115 -> 31.901335
B116: 7 | D116: =N115 -> 31.901335 | E116: =Assumptions!$C$28+Assumptions!$C$7/D116 -> 37558361 | F116: =IF(D116<Assumptions!$C$35,(Assumptions!$C$35*Assumptions!$C$28+Assumptions!$C$7)/E116,Assumptions!$C$35) -> 57.461916 | G116: =IF(D116<Assumptions!$C$36,(Assumptions!$C$36*Assumptions!$C$28+Assumptions!$C$7)/E116,Assumptions!$C$36) -> 48.726225 | H116: =IF(D116<Assumptions!$C$35,Assumptions!$C$43/F116,Assumptions!$C$24) -> 1740283.1 | I116: =IF(D116<Assumptions!$C$36,Assumptions!$C$44/G116,Assumptions!$C$25) -> 6156848.8 | J116: =MAX(0,$D$108*($C$108+Assumptions!$C$7)/D116-Assumptions!$C$26-Assumptions!$C$27) -> 617662.35 | K116: =IF((M115-K115)<=0,0,Assumptions!$C$47/MIN(Assumptions!$C$48/(M115-K115),D116*(1-Assumptions!$C$49))) -> 195916.56 | L116: =IF((M115-L115)<=0,0,Assumptions!$C$50/MIN(Assumptions!$C$51/(M115-L115),D116*(1-Assumptions!$C$52))) -> 110635.24 | M116: =Assumptions!$C$28+(H116-Assumptions!$C$24)+(I116-Assumptions!$C$25)+J116+K116+L116 -> 37616013 | N116: =$C$108/M116 -> 31.901308
B117: 8 | D117: =N116 -> 31.901308 | E117: =Assumptions!$C$28+Assumptions!$C$7/D117 -> 37558361 | F117: =IF(D117<Assumptions!$C$35,(Assumptions!$C$35*Assumptions!$C$28+Assumptions!$C$7)/E117,Assumptions!$C$35) -> 57.461915 | G117: =IF(D117<Assumptions!$C$36,(Assumptions!$C$36*Assumptions!$C$28+Assumptions!$C$7)/E117,Assumptions!$C$36) -> 48.726224 | H117: =IF(D117<Assumptions!$C$35,Assumptions!$C$43/F117,Assumptions!$C$24) -> 1740283.1 | I117: =IF(D117<Assumptions!$C$36,Assumptions!$C$44/G117,Assumptions!$C$25) -> 6156849 | J117: =MAX(0,$D$108*($C$108+Assumptions!$C$7)/D117-Assumptions!$C$26-Assumptions!$C$27) -> 617666.74 | K117: =IF((M116-K116)<=0,0,Assumptions!$C$47/MIN(Assumptions!$C$48/(M116-K116),D117*(1-Assumptions!$C$49))) -> 195916.73 | L117: =IF((M116-L116)<=0,0,Assumptions!$C$50/MIN(Assumptions!$C$51/(M116-L116),D117*(1-Assumptions!$C$52))) -> 110635.33 | M117: =Assumptions!$C$28+(H117-Assumptions!$C$24)+(I117-Assumptions!$C$25)+J117+K117+L117 -> 37616018 | N117: =$C$108/M117 -> 31.901303
B118: 9 | D118: =N117 -> 31.901303 | E118: =Assumptions!$C$28+Assumptions!$C$7/D118 -> 37558361 | F118: =IF(D118<Assumptions!$C$35,(Assumptions!$C$35*Assumptions!$C$28+Assumptions!$C$7)/E118,Assumptions!$C$35) -> 57.461915 | G118: =IF(D118<Assumptions!$C$36,(Assumptions!$C$36*Assumptions!$C$28+Assumptions!$C$7)/E118,Assumptions!$C$36) -> 48.726224 | H118: =IF(D118<Assumptions!$C$35,Assumptions!$C$43/F118,Assumptions!$C$24) -> 1740283.1 | I118: =IF(D118<Assumptions!$C$36,Assumptions!$C$44/G118,Assumptions!$C$25) -> 6156849 | J118: =MAX(0,$D$108*($C$108+Assumptions!$C$7)/D118-Assumptions!$C$26-Assumptions!$C$27) -> 617667.38 | K118: =IF((M117-K117)<=0,0,Assumptions!$C$47/MIN(Assumptions!$C$48/(M117-K117),D118*(1-Assumptions!$C$49))) -> 195916.76 | L118: =IF((M117-L117)<=0,0,Assumptions!$C$50/MIN(Assumptions!$C$51/(M117-L117),D118*(1-Assumptions!$C$52))) -> 110635.35 | M118: =Assumptions!$C$28+(H118-Assumptions!$C$24)+(I118-Assumptions!$C$25)+J118+K118+L118 -> 37616019 | N118: =$C$108/M118 -> 31.901303
B119: 10 | D119: =N118 -> 31.901303 | E119: =Assumptions!$C$28+Assumptions!$C$7/D119 -> 37558361 | F119: =IF(D119<Assumptions!$C$35,(Assumptions!$C$35*Assumptions!$C$28+Assumptions!$C$7)/E119,Assumptions!$C$35) -> 57.461915 | G119: =IF(D119<Assumptions!$C$36,(Assumptions!$C$36*Assumptions!$C$28+Assumptions!$C$7)/E119,Assumptions!$C$36) -> 48.726223 | H119: =IF(D119<Assumptions!$C$35,Assumptions!$C$43/F119,Assumptions!$C$24) -> 1740283.1 | I119: =IF(D119<Assumptions!$C$36,Assumptions!$C$44/G119,Assumptions!$C$25) -> 6156849 | J119: =MAX(0,$D$108*($C$108+Assumptions!$C$7)/D119-Assumptions!$C$26-Assumptions!$C$27) -> 617667.48 | K119: =IF((M118-K118)<=0,0,Assumptions!$C$47/MIN(Assumptions!$C$48/(M118-K118),D119*(1-Assumptions!$C$49))) -> 195916.76 | L119: =IF((M118-L118)<=0,0,Assumptions!$C$50/MIN(Assumptions!$C$51/(M118-L118),D119*(1-Assumptions!$C$52))) -> 110635.35 | M119: =Assumptions!$C$28+(H119-Assumptions!$C$24)+(I119-Assumptions!$C$25)+J119+K119+L119 -> 37616019 | N119: =$C$108/M119 -> 31.901303
B120: 11 | D120: =N119 -> 31.901303 | E120: =Assumptions!$C$28+Assumptions!$C$7/D120 -> 37558361 | F120: =IF(D120<Assumptions!$C$35,(Assumptions!$C$35*Assumptions!$C$28+Assumptions!$C$7)/E120,Assumptions!$C$35) -> 57.461915 | G120: =IF(D120<Assumptions!$C$36,(Assumptions!$C$36*Assumptions!$C$28+Assumptions!$C$7)/E120,Assumptions!$C$36) -> 48.726223 | H120: =IF(D120<Assumptions!$C$35,Assumptions!$C$43/F120,Assumptions!$C$24) -> 1740283.1 | I120: =IF(D120<Assumptions!$C$36,Assumptions!$C$44/G120,Assumptions!$C$25) -> 6156849 | J120: =MAX(0,$D$108*($C$108+Assumptions!$C$7)/D120-Assumptions!$C$26-Assumptions!$C$27) -> 617667.49 | K120: =IF((M119-K119)<=0,0,Assumptions!$C$47/MIN(Assumptions!$C$48/(M119-K119),D120*(1-Assumptions!$C$49))) -> 195916.76 | L120: =IF((M119-L119)<=0,0,Assumptions!$C$50/MIN(Assumptions!$C$51/(M119-L119),D120*(1-Assumptions!$C$52))) -> 110635.35 | M120: =Assumptions!$C$28+(H120-Assumptions!$C$24)+(I120-Assumptions!$C$25)+J120+K120+L120 -> 37616019 | N120: =$C$108/M120 -> 31.901303
B121: 12 | D121: =N120 -> 31.901303 | E121: =Assumptions!$C$28+Assumptions!$C$7/D121 -> 37558361 | F121: =IF(D121<Assumptions!$C$35,(Assumptions!$C$35*Assumptions!$C$28+Assumptions!$C$7)/E121,Assumptions!$C$35) -> 57.461915 | G121: =IF(D121<Assumptions!$C$36,(Assumptions!$C$36*Assumptions!$C$28+Assumptions!$C$7)/E121,Assumptions!$C$36) -> 48.726223 | H121: =IF(D121<Assumptions!$C$35,Assumptions!$C$43/F121,Assumptions!$C$24) -> 1740283.1 | I121: =IF(D121<Assumptions!$C$36,Assumptions!$C$44/G121,Assumptions!$C$25) -> 6156849 | J121: =MAX(0,$D$108*($C$108+Assumptions!$C$7)/D121-Assumptions!$C$26-Assumptions!$C$27) -> 617667.49 | K121: =IF((M120-K120)<=0,0,Assumptions!$C$47/MIN(Assumptions!$C$48/(M120-K120),D121*(1-Assumptions!$C$49))) -> 195916.76 | L121: =IF((M120-L120)<=0,0,Assumptions!$C$50/MIN(Assumptions!$C$51/(M120-L120),D121*(1-Assumptions!$C$52))) -> 110635.35 | M121: =Assumptions!$C$28+(H121-Assumptions!$C$24)+(I121-Assumptions!$C$25)+J121+K121+L121 -> 37616019 | N121: =$C$108/M121 -> 31.901303
B122: 13 | D122: =N121 -> 31.901303 | E122: =Assumptions!$C$28+Assumptions!$C$7/D122 -> 37558361 | F122: =IF(D122<Assumptions!$C$35,(Assumptions!$C$35*Assumptions!$C$28+Assumptions!$C$7)/E122,Assumptions!$C$35) -> 57.461915 | G122: =IF(D122<Assumptions!$C$36,(Assumptions!$C$36*Assumptions!$C$28+Assumptions!$C$7)/E122,Assumptions!$C$36) -> 48.726223 | H122: =IF(D122<Assumptions!$C$35,Assumptions!$C$43/F122,Assumptions!$C$24) -> 1740283.1 | I122: =IF(D122<Assumptions!$C$36,Assumptions!$C$44/G122,Assumptions!$C$25) -> 6156849 | J122: =MAX(0,$D$108*($C$108+Assumptions!$C$7)/D122-Assumptions!$C$26-Assumptions!$C$27) -> 617667.49 | K122: =IF((M121-K121)<=0,0,Assumptions!$C$47/MIN(Assumptions!$C$48/(M121-K121),D122*(1-Assumptions!$C$49))) -> 195916.76 | L122: =IF((M121-L121)<=0,0,Assumptions!$C$50/MIN(Assumptions!$C$51/(M121-L121),D122*(1-Assumptions!$C$52))) -> 110635.35 | M122: =Assumptions!$C$28+(H122-Assumptions!$C$24)+(I122-Assumptions!$C$25)+J122+K122+L122 -> 37616019 | N122: =$C$108/M122 -> 31.901303
... B129: 20 | D129: =N128 -> 31.901303 | E129: =Assumptions!$C$28+Assumptions!$C$7/D129 -> 37558361 | F129: =IF(D129<Assumptions!$C$35,(Assumptions!$C$35*Assumptions!$C$28+Assumptions!$C$7)/E129,Assumptions!$C$35) -> 57.461915 | G129: =IF(D129<Assumptions!$C$36,(Assumptions!$C$36*Assumptions!$C$28+Assumptions!$C$7)/E129,Assumptions!$C$36) -> 48.726223 | H129: =IF(D129<Assumptions!$C$35,Assumptions!$C$43/F129,Assumptions!$C$24) -> 1740283.1 | I129: =IF(D129<Assumptions!$C$36,Assumptions!$C$44/G129,Assumptions!$C$25) -> 6156849 | J129: =MAX(0,$D$108*($C$108+Assumptions!$C$7)/D129-Assumptions!$C$26-Assumptions!$C$27) -> 617667.49 | K129: =IF((M128-K128)<=0,0,Assumptions!$C$47/MIN(Assumptions!$C$48/(M128-K128),D129*(1-Assumptions!$C$49))) -> 195916.76 | L129: =IF((M128-L128)<=0,0,Assumptions!$C$50/MIN(Assumptions!$C$51/(M128-L128),D129*(1-Assumptions!$C$52))) -> 110635.35 | M129: =Assumptions!$C$28+(H129-Assumptions!$C$24)+(I129-Assumptions!$C$25)+J129+K129+L129 -> 37616019 | N129: =$C$108/M129 -> 31.901303
...

Sheet Sensitivity
B2: Sensitivity Grid — Our $10M @ $2B Exit
B3: ESOP refresh × Series F pre-money | post-F ownership and $ proceeds
B5: Post-F Ownership of Our $10M Check
C6: Pre-money → | D6: Pre $1.2B | E6: Pre $1.4B | F6: Pre $1.8B
B7: ESOP refresh ↓
B8: ESOP 11% | D8: ='Sens-Engine'!$C$37 -> 0.0081300813 | E8: ='Sens-Engine'!$C$71 -> 0.006993007 | F8: ='Sens-Engine'!$C$105 -> 0.0054644809
B9: ESOP 13% | D9: ='Sens-Engine'!$C$139 -> 0.0081300813 | E9: ='Sens-Engine'!$C$173 -> 0.006993007 | F9: ='Sens-Engine'!$C$207 -> 0.0054644809
B10: ESOP 15% | D10: ='Sens-Engine'!$C$241 -> 0.0081300813 | E10: ='Sens-Engine'!$C$275 -> 0.006993007 | F10: ='Sens-Engine'!$C$309 -> 0.0054644809
B12: Our $10M Proceeds at $2B Exit
C13: Pre-money → | D13: Pre $1.2B | E13: Pre $1.4B | F13: Pre $1.8B
B14: ESOP refresh ↓
B15: ESOP 11% | D15: ='Sens-Engine'!$C$36 -> 17107255 | E15: ='Sens-Engine'!$C$70 -> 14719654 | F15: ='Sens-Engine'!$C$104 -> 11507138
B16: ESOP 13% | D16: ='Sens-Engine'!$C$138 -> 17384972 | E16: ='Sens-Engine'!$C$172 -> 14948858 | F16: ='Sens-Engine'!$C$206 -> 11676569
B17: ESOP 15% | D17: ='Sens-Engine'!$C$240 -> 17795003 | E17: ='Sens-Engine'!$C$274 -> 15301321 | F17: ='Sens-Engine'!$C$308 -> 11951762
B19: Notes:
B20: Each cell re-solves the full round fixed point (F PPS, ESOP top-up, AD on D & E, both note conversion branches) per (pre-money, ESOP) pair.
B21: Engine runs 20 fixed-point iterations and 2 election rounds per cell. Note A flips cap → discount at $1.2B pre-money; both cap at $1.4B and $1.8B.
B22: Ownership % is invariant in ESOP because: pct = our_check / post-money. Proceeds vary with both axes via F PPS and waterfall pool.

Sheet Solver
B2: Series F Round Solver
B3: Fixed-point iteration: F PPS, AD, ESOP top-up, note conversion
B5: Iteration Block (Base Case)
B6: Iter | D6: p (F PPS) | E6: q | F6: NCP_D | G6: NCP_E | H6: D shares | I6: E shares | J6: ESOP top-up | K6: Note A sh | L6: Note B sh | M6: pre-FD | N6: p_new
B7: 1 | D7: =(Assumptions!$C$6+Assumptions!$C$7)/Assumptions!$C$28 -> 39.051874 | E7: =Assumptions!$C$28+Assumptions!$C$7/D7 -> 37386170 | F7: =IF(D7<Assumptions!$C$35,(Assumptions!$C$35*Assumptions!$C$28+Assumptions!$C$7)/E7,Assumptions!$C$35) -> 57.72657 | G7: =IF(D7<Assumptions!$C$36,(Assumptions!$C$36*Assumptions!$C$28+Assumptions!$C$7)/E7,Assumptions!$C$36) -> 48.950644 | H7: =IF(D7<Assumptions!$C$35,Assumptions!$C$43/F7,Assumptions!$C$24) -> 1732304.5 | I7: =IF(D7<Assumptions!$C$36,Assumptions!$C$44/G7,Assumptions!$C$25) -> 6128622.1 | J7: =MAX(0,Assumptions!$C$10*(Assumptions!$C$6+Assumptions!$C$7)/D7-Assumptions!$C$26-Assumptions!$C$27) -> 365667.93 | K7: 0 | L7: 0 | M7: =Assumptions!$C$28+(H7-Assumptions!$C$24)+(I7-Assumptions!$C$25)+J7+K7+L7 -> 37021262 | N7: =Assumptions!$C$6/M7 -> 37.816107
B8: 2 | D8: =N7 -> 37.816107 | E8: =Assumptions!$C$28+Assumptions!$C$7/D8 -> 37411274 | F8: =IF(D8<Assumptions!$C$35,(Assumptions!$C$35*Assumptions!$C$28+Assumptions!$C$7)/E8,Assumptions!$C$35) -> 57.687834 | G8: =IF(D8<Assumptions!$C$36,(Assumptions!$C$36*Assumptions!$C$28+Assumptions!$C$7)/E8,Assumptions!$C$36) -> 48.917798 | H8: =IF(D8<Assumptions!$C$35,Assumptions!$C$43/F8,Assumptions!$C$24) -> 1733467.7 | I8: =IF(D8<Assumptions!$C$36,Assumptions!$C$44/G8,Assumptions!$C$25) -> 6132737.3 | J8: =MAX(0,Assumptions!$C$10*(Assumptions!$C$6+Assumptions!$C$7)/D8-Assumptions!$C$26-Assumptions!$C$27) -> 521227.66 | K8: =IF((M7-K7)<=0,0,Assumptions!$C$47/MIN(Assumptions!$C$48/(M7-K7),D8*(1-Assumptions!$C$49))) -> 185106.31 | L8: =IF((M7-L7)<=0,0,Assumptions!$C$50/MIN(Assumptions!$C$51/(M7-L7),D8*(1-Assumptions!$C$52))) -> 93330.911 | M8: =Assumptions!$C$28+(H8-Assumptions!$C$24)+(I8-Assumptions!$C$25)+J8+K8+L8 -> 37460537 | N8: =Assumptions!$C$6/M8 -> 37.372662
B9: 3 | D9: =N8 -> 37.372662 | E9: =Assumptions!$C$28+Assumptions!$C$7/D9 -> 37420687 | F9: =IF(D9<Assumptions!$C$35,(Assumptions!$C$35*Assumptions!$C$28+Assumptions!$C$7)/E9,Assumptions!$C$35) -> 57.673323 | G9: =IF(D9<Assumptions!$C$36,(Assumptions!$C$36*Assumptions!$C$28+Assumptions!$C$7)/E9,Assumptions!$C$36) -> 48.905492 | H9: =IF(D9<Assumptions!$C$35,Assumptions!$C$43/F9,Assumptions!$C$24) -> 1733903.9 | I9: =IF(D9<Assumptions!$C$36,Assumptions!$C$44/G9,Assumptions!$C$25) -> 6134280.3 | J9: =MAX(0,Assumptions!$C$10*(Assumptions!$C$6+Assumptions!$C$7)/D9-Assumptions!$C$26-Assumptions!$C$27) -> 579557.15 | K9: =IF((M8-K8)<=0,0,Assumptions!$C$47/MIN(Assumptions!$C$48/(M8-K8),D9*(1-Assumptions!$C$49))) -> 186377.15 | L9: =IF((M8-L8)<=0,0,Assumptions!$C$50/MIN(Assumptions!$C$51/(M8-L8),D9*(1-Assumptions!$C$52))) -> 94438.328 | M9: =Assumptions!$C$28+(H9-Assumptions!$C$24)+(I9-Assumptions!$C$25)+J9+K9+L9 -> 37523224 | N9: =Assumptions!$C$6/M9 -> 37.310227
B10: 4 | D10: =N9 -> 37.310227 | E10: =Assumptions!$C$28+Assumptions!$C$7/D10 -> 37422030 | F10: =IF(D10<Assumptions!$C$35,(Assumptions!$C$35*Assumptions!$C$28+Assumptions!$C$7)/E10,Assumptions!$C$35) -> 57.671253 | G10: =IF(D10<Assumptions!$C$36,(Assumptions!$C$36*Assumptions!$C$28+Assumptions!$C$7)/E10,Assumptions!$C$36) -> 48.903737 | H10: =IF(D10<Assumptions!$C$35,Assumptions!$C$43/F10,Assumptions!$C$24) -> 1733966.1 | I10: =IF(D10<Assumptions!$C$36,Assumptions!$C$44/G10,Assumptions!$C$25) -> 6134500.5 | J10: =MAX(0,Assumptions!$C$10*(Assumptions!$C$6+Assumptions!$C$7)/D10-Assumptions!$C$26-Assumptions!$C$27) -> 587881.08 | K10: =IF((M9-K9)<=0,0,Assumptions!$C$47/MIN(Assumptions!$C$48/(M9-K9),D10*(1-Assumptions!$C$49))) -> 186684.23 | L10: =IF((M9-L9)<=0,0,Assumptions!$C$50/MIN(Assumptions!$C$51/(M9-L9),D10*(1-Assumptions!$C$52))) -> 94596.363 | M10: =Assumptions!$C$28+(H10-Assumptions!$C$24)+(I10-Assumptions!$C$25)+J10+K10+L10 -> 37532295 | N10: =Assumptions!$C$6/M10 -> 37.301209
B11: 5 | D11: =N10 -> 37.301209 | E11: =Assumptions!$C$28+Assumptions!$C$7/D11 -> 37422224 | F11: =IF(D11<Assumptions!$C$35,(Assumptions!$C$35*Assumptions!$C$28+Assumptions!$C$7)/E11,Assumptions!$C$35) -> 57.670953 | G11: =IF(D11<Assumptions!$C$36,(Assumptions!$C$36*Assumptions!$C$28+Assumptions!$C$7)/E11,Assumptions!$C$36) -> 48.903483 | H11: =IF(D11<Assumptions!$C$35,Assumptions!$C$43/F11,Assumptions!$C$24) -> 1733975.1 | I11: =IF(D11<Assumptions!$C$36,Assumptions!$C$44/G11,Assumptions!$C$25) -> 6134532.4 | J11: =MAX(0,Assumptions!$C$10*(Assumptions!$C$6+Assumptions!$C$7)/D11-Assumptions!$C$26-Assumptions!$C$27) -> 589085.65 | K11: =IF((M10-K10)<=0,0,Assumptions!$C$47/MIN(Assumptions!$C$48/(M10-K10),D11*(1-Assumptions!$C$49))) -> 186728.06 | L11: =IF((M10-L10)<=0,0,Assumptions!$C$50/MIN(Assumptions!$C$51/(M10-L10),D11*(1-Assumptions!$C$52))) -> 94619.232 | M11: =Assumptions!$C$28+(H11-Assumptions!$C$24)+(I11-Assumptions!$C$25)+J11+K11+L11 -> 37533607 | N11: =Assumptions!$C$6/M11 -> 37.299905
B12: 6 | D12: =N11 -> 37.299905 | E12: =Assumptions!$C$28+Assumptions!$C$7/D12 -> 37422253 | F12: =IF(D12<Assumptions!$C$35,(Assumptions!$C$35*Assumptions!$C$28+Assumptions!$C$7)/E12,Assumptions!$C$35) -> 57.67091 | G12: =IF(D12<Assumptions!$C$36,(Assumptions!$C$36*Assumptions!$C$28+Assumptions!$C$7)/E12,Assumptions!$C$36) -> 48.903446 | H12: =IF(D12<Assumptions!$C$35,Assumptions!$C$43/F12,Assumptions!$C$24) -> 1733976.5 | I12: =IF(D12<Assumptions!$C$36,Assumptions!$C$44/G12,Assumptions!$C$25) -> 6134537 | J12: =MAX(0,Assumptions!$C$10*(Assumptions!$C$6+Assumptions!$C$7)/D12-Assumptions!$C$26-Assumptions!$C$27) -> 589259.88 | K12: =IF((M11-K11)<=0,0,Assumptions!$C$47/MIN(Assumptions!$C$48/(M11-K11),D12*(1-Assumptions!$C$49))) -> 186734.4 | L12: =IF((M11-L11)<=0,0,Assumptions!$C$50/MIN(Assumptions!$C$51/(M11-L11),D12*(1-Assumptions!$C$52))) -> 94622.54 | M12: =Assumptions!$C$28+(H12-Assumptions!$C$24)+(I12-Assumptions!$C$25)+J12+K12+L12 -> 37533797 | N12: =Assumptions!$C$6/M12 -> 37.299717
B13: 7 | D13: =N12 -> 37.299717 | E13: =Assumptions!$C$28+Assumptions!$C$7/D13 -> 37422257 | F13: =IF(D13<Assumptions!$C$35,(Assumptions!$C$35*Assumptions!$C$28+Assumptions!$C$7)/E13,Assumptions!$C$35) -> 57.670904 | G13: =IF(D13<Assumptions!$C$36,(Assumptions!$C$36*Assumptions!$C$28+Assumptions!$C$7)/E13,Assumptions!$C$36) -> 48.903441 | H13: =IF(D13<Assumptions!$C$35,Assumptions!$C$43/F13,Assumptions!$C$24) -> 1733976.6 | I13: =IF(D13<Assumptions!$C$36,Assumptions!$C$44/G13,Assumptions!$C$25) -> 6134537.7 | J13: =MAX(0,Assumptions!$C$10*(Assumptions!$C$6+Assumptions!$C$7)/D13-Assumptions!$C$26-Assumptions!$C$27) -> 589285.08 | K13: =IF((M12-K12)<=0,0,Assumptions!$C$47/MIN(Assumptions!$C$48/(M12-K12),D13*(1-Assumptions!$C$49))) -> 186735.31 | L13: =IF((M12-L12)<=0,0,Assumptions!$C$50/MIN(Assumptions!$C$51/(M12-L12),D13*(1-Assumptions!$C$52))) -> 94623.018 | M13: =Assumptions!$C$28+(H13-Assumptions!$C$24)+(I13-Assumptions!$C$25)+J13+K13+L13 -> 37533825 | N13: =Assumptions!$C$6/M13 -> 37.299689
B14: 8 | D14: =N13 -> 37.299689 | E14: =Assumptions!$C$28+Assumptions!$C$7/D14 -> 37422257 | F14: =IF(D14<Assumptions!$C$35,(Assumptions!$C$35*Assumptions!$C$28+Assumptions!$C$7)/E14,Assumptions!$C$35) -> 57.670903 | G14: =IF(D14<Assumptions!$C$36,(Assumptions!$C$36*Assumptions!$C$28+Assumptions!$C$7)/E14,Assumptions!$C$36) -> 48.90344 | H14: =IF(D14<Assumptions!$C$35,Assumptions!$C$43/F14,Assumptions!$C$24) -> 1733976.7 | I14: =IF(D14<Assumptions!$C$36,Assumptions!$C$44/G14,Assumptions!$C$25) -> 6134537.8 | J14: =MAX(0,Assumptions!$C$10*(Assumptions!$C$6+Assumptions!$C$7)/D14-Assumptions!$C$26-Assumptions!$C$27) -> 589288.73 | K14: =IF((M13-K13)<=0,0,Assumptions!$C$47/MIN(Assumptions!$C$48/(M13-K13),D14*(1-Assumptions!$C$49))) -> 186735.45 | L14: =IF((M13-L13)<=0,0,Assumptions!$C$50/MIN(Assumptions!$C$51/(M13-L13),D14*(1-Assumptions!$C$52))) -> 94623.088 | M14: =Assumptions!$C$28+(H14-Assumptions!$C$24)+(I14-Assumptions!$C$25)+J14+K14+L14 -> 37533829 | N14: =Assumptions!$C$6/M14 -> 37.299685
B15: 9 | D15: =N14 -> 37.299685 | E15: =Assumptions!$C$28+Assumptions!$C$7/D15 -> 37422257 | F15: =IF(D15<Assumptions!$C$35,(Assumptions!$C$35*Assumptions!$C$28+Assumptions!$C$7)/E15,Assumptions!$C$35) -> 57.670903 | G15: =IF(D15<Assumptions!$C$36,(Assumptions!$C$36*Assumptions!$C$28+Assumptions!$C$7)/E15,Assumptions!$C$36) -> 48.90344 | H15: =IF(D15<Assumptions!$C$35,Assumptions!$C$43/F15,Assumptions!$C$24) -> 1733976.7 | I15: =IF(D15<Assumptions!$C$36,Assumptions!$C$44/G15,Assumptions!$C$25) -> 6134537.8 | J15: =MAX(0,Assumptions!$C$10*(Assumptions!$C$6+Assumptions!$C$7)/D15-Assumptions!$C$26-Assumptions!$C$27) -> 589289.25 | K15: =IF((M14-K14)<=0,0,Assumptions!$C$47/MIN(Assumptions!$C$48/(M14-K14),D15*(1-Assumptions!$C$49))) -> 186735.47 | L15: =IF((M14-L14)<=0,0,Assumptions!$C$50/MIN(Assumptions!$C$51/(M14-L14),D15*(1-Assumptions!$C$52))) -> 94623.098 | M15: =Assumptions!$C$28+(H15-Assumptions!$C$24)+(I15-Assumptions!$C$25)+J15+K15+L15 -> 37533829 | N15: =Assumptions!$C$6/M15 -> 37.299685
B16: 10 | D16: =N15 -> 37.299685 | E16: =Assumptions!$C$28+Assumptions!$C$7/D16 -> 37422257 | F16: =IF(D16<Assumptions!$C$35,(Assumptions!$C$35*Assumptions!$C$28+Assumptions!$C$7)/E16,Assumptions!$C$35) -> 57.670903 | G16: =IF(D16<Assumptions!$C$36,(Assumptions!$C$36*Assumptions!$C$28+Assumptions!$C$7)/E16,Assumptions!$C$36) -> 48.90344 | H16: =IF(D16<Assumptions!$C$35,Assumptions!$C$43/F16,Assumptions!$C$24) -> 1733976.7 | I16: =IF(D16<Assumptions!$C$36,Assumptions!$C$44/G16,Assumptions!$C$25) -> 6134537.8 | J16: =MAX(0,Assumptions!$C$10*(Assumptions!$C$6+Assumptions!$C$7)/D16-Assumptions!$C$26-Assumptions!$C$27) -> 589289.33 | K16: =IF((M15-K15)<=0,0,Assumptions!$C$47/MIN(Assumptions!$C$48/(M15-K15),D16*(1-Assumptions!$C$49))) -> 186735.47 | L16: =IF((M15-L15)<=0,0,Assumptions!$C$50/MIN(Assumptions!$C$51/(M15-L15),D16*(1-Assumptions!$C$52))) -> 94623.099 | M16: =Assumptions!$C$28+(H16-Assumptions!$C$24)+(I16-Assumptions!$C$25)+J16+K16+L16 -> 37533829 | N16: =Assumptions!$C$6/M16 -> 37.299685
B17: 11 | D17: =N16 -> 37.299685 | E17: =Assumptions!$C$28+Assumptions!$C$7/D17 -> 37422257 | F17: =IF(D17<Assumptions!$C$35,(Assumptions!$C$35*Assumptions!$C$28+Assumptions!$C$7)/E17,Assumptions!$C$35) -> 57.670903 | G17: =IF(D17<Assumptions!$C$36,(Assumptions!$C$36*Assumptions!$C$28+Assumptions!$C$7)/E17,Assumptions!$C$36) -> 48.90344 | H17: =IF(D17<Assumptions!$C$35,Assumptions!$C$43/F17,Assumptions!$C$24) -> 1733976.7 | I17: =IF(D17<Assumptions!$C$36,Assumptions!$C$44/G17,Assumptions!$C$25) -> 6134537.8 | J17: =MAX(0,Assumptions!$C$10*(Assumptions!$C$6+Assumptions!$C$7)/D17-Assumptions!$C$26-Assumptions!$C$27) -> 589289.34 | K17: =IF((M16-K16)<=0,0,Assumptions!$C$47/MIN(Assumptions!$C$48/(M16-K16),D17*(1-Assumptions!$C$49))) -> 186735.47 | L17: =IF((M16-L16)<=0,0,Assumptions!$C$50/MIN(Assumptions!$C$51/(M16-L16),D17*(1-Assumptions!$C$52))) -> 94623.099 | M17: =Assumptions!$C$28+(H17-Assumptions!$C$24)+(I17-Assumptions!$C$25)+J17+K17+L17 -> 37533829 | N17: =Assumptions!$C$6/M17 -> 37.299685
B18: 12 | D18: =N17 -> 37.299685 | E18: =Assumptions!$C$28+Assumptions!$C$7/D18 -> 37422257 | F18: =IF(D18<Assumptions!$C$35,(Assumptions!$C$35*Assumptions!$C$28+Assumptions!$C$7)/E18,Assumptions!$C$35) -> 57.670903 | G18: =IF(D18<Assumptions!$C$36,(Assumptions!$C$36*Assumptions!$C$28+Assumptions!$C$7)/E18,Assumptions!$C$36) -> 48.90344 | H18: =IF(D18<Assumptions!$C$35,Assumptions!$C$43/F18,Assumptions!$C$24) -> 1733976.7 | I18: =IF(D18<Assumptions!$C$36,Assumptions!$C$44/G18,Assumptions!$C$25) -> 6134537.8 | J18: =MAX(0,Assumptions!$C$10*(Assumptions!$C$6+Assumptions!$C$7)/D18-Assumptions!$C$26-Assumptions!$C$27) -> 589289.34 | K18: =IF((M17-K17)<=0,0,Assumptions!$C$47/MIN(Assumptions!$C$48/(M17-K17),D18*(1-Assumptions!$C$49))) -> 186735.47 | L18: =IF((M17-L17)<=0,0,Assumptions!$C$50/MIN(Assumptions!$C$51/(M17-L17),D18*(1-Assumptions!$C$52))) -> 94623.099 | M18: =Assumptions!$C$28+(H18-Assumptions!$C$24)+(I18-Assumptions!$C$25)+J18+K18+L18 -> 37533829 | N18: =Assumptions!$C$6/M18 -> 37.299685
B19: 13 | D19: =N18 -> 37.299685 | E19: =Assumptions!$C$28+Assumptions!$C$7/D19 -> 37422257 | F19: =IF(D19<Assumptions!$C$35,(Assumptions!$C$35*Assumptions!$C$28+Assumptions!$C$7)/E19,Assumptions!$C$35) -> 57.670903 | G19: =IF(D19<Assumptions!$C$36,(Assumptions!$C$36*Assumptions!$C$28+Assumptions!$C$7)/E19,Assumptions!$C$36) -> 48.90344 | H19: =IF(D19<Assumptions!$C$35,Assumptions!$C$43/F19,Assumptions!$C$24) -> 1733976.7 | I19: =IF(D19<Assumptions!$C$36,Assumptions!$C$44/G19,Assumptions!$C$25) -> 6134537.8 | J19: =MAX(0,Assumptions!$C$10*(Assumptions!$C$6+Assumptions!$C$7)/D19-Assumptions!$C$26-Assumptions!$C$27) -> 589289.34 | K19: =IF((M18-K18)<=0,0,Assumptions!$C$47/MIN(Assumptions!$C$48/(M18-K18),D19*(1-Assumptions!$C$49))) -> 186735.47 | L19: =IF((M18-L18)<=0,0,Assumptions!$C$50/MIN(Assumptions!$C$51/(M18-L18),D19*(1-Assumptions!$C$52))) -> 94623.099 | M19: =Assumptions!$C$28+(H19-Assumptions!$C$24)+(I19-Assumptions!$C$25)+J19+K19+L19 -> 37533829 | N19: =Assumptions!$C$6/M19 -> 37.299685
... B26: 20 | D26: =N25 -> 37.299685 | E26: =Assumptions!$C$28+Assumptions!$C$7/D26 -> 37422257 | F26: =IF(D26<Assumptions!$C$35,(Assumptions!$C$35*Assumptions!$C$28+Assumptions!$C$7)/E26,Assumptions!$C$35) -> 57.670903 | G26: =IF(D26<Assumptions!$C$36,(Assumptions!$C$36*Assumptions!$C$28+Assumptions!$C$7)/E26,Assumptions!$C$36) -> 48.90344 | H26: =IF(D26<Assumptions!$C$35,Assumptions!$C$43/F26,Assumptions!$C$24) -> 1733976.7 | I26: =IF(D26<Assumptions!$C$36,Assumptions!$C$44/G26,Assumptions!$C$25) -> 6134537.8 | J26: =MAX(0,Assumptions!$C$10*(Assumptions!$C$6+Assumptions!$C$7)/D26-Assumptions!$C$26-Assumptions!$C$27) -> 589289.34 | K26: =IF((M25-K25)<=0,0,Assumptions!$C$47/MIN(Assumptions!$C$48/(M25-K25),D26*(1-Assumptions!$C$49))) -> 186735.47 | L26: =IF((M25-L25)<=0,0,Assumptions!$C$50/MIN(Assumptions!$C$51/(M25-L25),D26*(1-Assumptions!$C$52))) -> 94623.099 | M26: =Assumptions!$C$28+(H26-Assumptions!$C$24)+(I26-Assumptions!$C$25)+J26+K26+L26 -> 37533829 | N26: =Assumptions!$C$6/M26 -> 37.299685
B28: Converged | D28: =D26 -> 37.299685 | E28: =E26 -> 37422257 | F28: =F26 -> 57.670903 | G28: =G26 -> 48.90344 | H28: =H26 -> 1733976.7 | I28: =I26 -> 6134537.8 | J28: =J26 -> 589289.34 | K28: =K26 -> 186735.47 | ... N28: =N26 -> 37.299685

Sheet Waterfall
B2: Waterfall — Exit Outcomes by Class
B3: $ in actual; 5 exit scenarios; conversion election per class
B5: Per-Class Inputs
B6: Class | C6: Shares (as-conv) | D6: 1x liq pref ($) | E6: Pref / share ($)
B7: Series F | C7: ='Pro-Forma'!$C$9 -> 804296.34 | D7: =Assumptions!$C$7 -> 30000000 | E7: =D7/C7 -> 37.299685
B8: Series E | C8: ='Pro-Forma'!$G$21 -> 6134537.8 | D8: =Assumptions!$C$44 -> 300000000 | E8: =D8/C8 -> 48.90344
B9: Series D | C9: ='Pro-Forma'!$G$20 -> 1733976.7 | D9: =Assumptions!$C$43 -> 100000000 | E9: =D9/C9 -> 57.670903
B10: Series C | C10: =Assumptions!$C$23 -> 2400000 | D10: =Assumptions!$C$42 -> 60000000 | E10: =D10/C10 -> 25
B11: Series B | C11: =Assumptions!$C$22 -> 3000000 | D11: =Assumptions!$C$41 -> 30000000 | E11: =D11/C11 -> 10
B12: Series A | C12: =Assumptions!$C$21 -> 5000000 | D12: =Assumptions!$C$40 -> 15000000 | E12: =D12/C12 -> 3
B13: Seed | C13: =Assumptions!$C$20 -> 5000000 | D13: =Assumptions!$C$39 -> 5000000 | E13: =D13/C13 -> 1
B15: Common Pool (no election)
B16: Founders + RSAs common | C16: =Assumptions!$C$16+Assumptions!$C$17+Assumptions!$C$18+Assumptions!$C$19 -> 9000000
B17: Notes (combined NA+NB) | C17: ='Pro-Forma'!$G$25+'Pro-Forma'!$G$26 -> 281358.57
B18: Issued options | C18: =Assumptions!$C$26 -> 2500000
B19: Common pool total | C19: =$C$16+$C$17+$C$18 -> 11781359
B20: Total pool if all classes convert | C20: =$C$19+SUM(C7:C13) -> 35854169
B22: Election Engine (5 Iterations)
B23: Metric | D23: =Assumptions!$C$55 -> 700000000 | E23: =Assumptions!$C$56 -> 1200000000 | F23: =Assumptions!$C$57 -> 2000000000 | G23: =Assumptions!$C$58 -> 4000000000 | H23: =Assumptions!$C$59 -> 8000000000
B24: Adj exit (+ option strike proceeds) | D24: =Assumptions!$C$55+$C$18*Assumptions!$C$13 -> 702500000 | E24: =Assumptions!$C$56+$C$18*Assumptions!$C$13 -> 1202500000 | F24: =Assumptions!$C$57+$C$18*Assumptions!$C$13 -> 2002500000 | G24: =Assumptions!$C$58+$C$18*Assumptions!$C$13 -> 4002500000 | H24: =Assumptions!$C$59+$C$18*Assumptions!$C$13 -> 8002500000
B25: Iteration 1
B26: per-share (residual / pool) | D26: =D24/$C$20 -> 19.593258 | E26: =E24/$C$20 -> 33.538638 | F26: =F24/$C$20 -> 55.851245 | G26: =G24/$C$20 -> 111.63276 | H26: =H24/$C$20 -> 223.1958
B27: F election | D27: =IF(D7>C7*D26,"preference","convert") -> preference | E27: =IF(D7>C7*E26,"preference","convert") -> preference | F27: =IF(D7>C7*F26,"preference","convert") -> convert | G27: =IF(D7>C7*G26,"preference","convert") -> convert | H27: =IF(D7>C7*H26,"preference","convert") -> convert
B28: E election | D28: =IF(D8>C8*D26,"preference","convert") -> preference | E28: =IF(D8>C8*E26,"preference","convert") -> preference | F28: =IF(D8>C8*F26,"preference","convert") -> convert | G28: =IF(D8>C8*G26,"preference","convert") -> convert | H28: =IF(D8>C8*H26,"preference","convert") -> convert
B29: D election | D29: =IF(D9>C9*D26,"preference","convert") -> preference | E29: =IF(D9>C9*E26,"preference","convert") -> preference | F29: =IF(D9>C9*F26,"preference","convert") -> preference | G29: =IF(D9>C9*G26,"preference","convert") -> convert | H29: =IF(D9>C9*H26,"preference","convert") -> convert
B30: C election | D30: =IF(D10>C10*D26,"preference","convert") -> preference | E30: =IF(D10>C10*E26,"preference","convert") -> convert | F30: =IF(D10>C10*F26,"preference","convert") -> convert | G30: =IF(D10>C10*G26,"preference","convert") -> convert | H30: =IF(D10>C10*H26,"preference","convert") -> convert
B31: B election | D31: =IF(D11>C11*D26,"preference","convert") -> convert | E31: =IF(D11>C11*E26,"preference","convert") -> convert | F31: =IF(D11>C11*F26,"preference","convert") -> convert | G31: =IF(D11>C11*G26,"preference","convert") -> convert | H31: =IF(D11>C11*H26,"preference","convert") -> convert
B32: A election | D32: =IF(D12>C12*D26,"preference","convert") -> convert | E32: =IF(D12>C12*E26,"preference","convert") -> convert | F32: =IF(D12>C12*F26,"preference","convert") -> convert | G32: =IF(D12>C12*G26,"preference","convert") -> convert | H32: =IF(D12>C12*H26,"preference","convert") -> convert
B33: Seed election | D33: =IF(D13>C13*D26,"preference","convert") -> convert | E33: =IF(D13>C13*E26,"preference","convert") -> convert | F33: =IF(D13>C13*F26,"preference","convert") -> convert | G33: =IF(D13>C13*G26,"preference","convert") -> convert | H33: =IF(D13>C13*H26,"preference","convert") -> convert
B34: Iteration 2
B35: per-share (residual / pool) | D35: =(D24-(IF(D27="preference",D7,0)+IF(D28="preference",D8,0)+IF(D29="preference",D9,0)+IF(D30="preference",D10,0)+IF(D31="preference",D11,0)+IF(D32="preference",D12,0)+IF(D33="preference",D13,0)))/($C$20-(IF(D27="preference",C7,0)+IF(D28="preference",C8,0)+IF(D29="preference",C9,0)+IF(D30="preference",C10,0)+IF(D31="preference",C11,0)+IF(D32="preference",C12,0)+IF(D33="preference",C13,0))) -> 8.574994 | E35: =(E24-(IF(E27="preference",D7,0)+IF(E28="preference",D8,0)+IF(E29="preference",D9,0)+IF(E30="preference",D10,0)+IF(E31="preference",D11,0)+IF(E32="preference",D12,0)+IF(E33="preference",D13,0)))/($C$20-(IF(E27="preference",C7,0)+IF(E28="preference",C8,0)+IF(E29="preference",C9,0)+IF(E30="preference",C10,0)+IF(E31="preference",C11,0)+IF(E32="preference",C12,0)+IF(E33="preference",C13,0))) -> 28.420213 | F35: =(F24-(IF(F27="preference",D7,0)+IF(F28="preference",D8,0)+IF(F29="preference",D9,0)+IF(F30="preference",D10,0)+IF(F31="preference",D11,0)+IF(F32="preference",D12,0)+IF(F33="preference",D13,0)))/($C$20-(IF(F27="preference",C7,0)+IF(F28="preference",C8,0)+IF(F29="preference",C9,0)+IF(F30="preference",C10,0)+IF(F31="preference",C11,0)+IF(F32="preference",C12,0)+IF(F33="preference",C13,0))) -> 55.758771 | G35: =(G24-(IF(G27="preference",D7,0)+IF(G28="preference",D8,0)+IF(G29="preference",D9,0)+IF(G30="preference",D10,0)+IF(G31="preference",D11,0)+IF(G32="preference",D12,0)+IF(G33="preference",D13,0)))/($C$20-(IF(G27="preference",C7,0)+IF(G28="preference",C8,0)+IF(G29="preference",C9,0)+IF(G30="preference",C10,0)+IF(G31="preference",C11,0)+IF(G32="preference",C12,0)+IF(G33="preference",C13,0))) -> 111.63276 | H35: =(H24-(IF(H27="preference",D7,0)+IF(H28="preference",D8,0)+IF(H29="preference",D9,0)+IF(H30="preference",D10,0)+IF(H31="preference",D11,0)+IF(H32="preference",D12,0)+IF(H33="preference",D13,0)))/($C$20-(IF(H27="preference",C7,0)+IF(H28="preference",C8,0)+IF(H29="preference",C9,0)+IF(H30="preference",C10,0)+IF(H31="preference",C11,0)+IF(H32="preference",C12,0)+IF(H33="preference",C13,0))) -> 223.1958
B36: F election | D36: =IF(D7>C7*D35,"preference","convert") -> preference | E36: =IF(D7>C7*E35,"preference","convert") -> preference | F36: =IF(D7>C7*F35,"preference","convert") -> convert | G36: =IF(D7>C7*G35,"preference","convert") -> convert | H36: =IF(D7>C7*H35,"preference","convert") -> convert
B37: E election | D37: =IF(D8>C8*D35,"preference","convert") -> preference | E37: =IF(D8>C8*E35,"preference","convert") -> preference | F37: =IF(D8>C8*F35,"preference","convert") -> convert | G37: =IF(D8>C8*G35,"preference","convert") -> convert | H37: =IF(D8>C8*H35,"preference","convert") -> convert
B38: D election | D38: =IF(D9>C9*D35,"preference","convert") -> preference | E38: =IF(D9>C9*E35,"preference","convert") -> preference | F38: =IF(D9>C9*F35,"preference","convert") -> preference | G38: =IF(D9>C9*G35,"preference","convert") -> convert | H38: =IF(D9>C9*H35,"preference","convert") -> convert
B39: C election | D39: =IF(D10>C10*D35,"preference","convert") -> preference | E39: =IF(D10>C10*E35,"preference","convert") -> convert | F39: =IF(D10>C10*F35,"preference","convert") -> convert | G39: =IF(D10>C10*G35,"preference","convert") -> convert | H39: =IF(D10>C10*H35,"preference","convert") -> convert
B40: B election | D40: =IF(D11>C11*D35,"preference","convert") -> preference | E40: =IF(D11>C11*E35,"preference","convert") -> convert | F40: =IF(D11>C11*F35,"preference","convert") -> convert | G40: =IF(D11>C11*G35,"preference","convert") -> convert | H40: =IF(D11>C11*H35,"preference","convert") -> convert
B41: A election | D41: =IF(D12>C12*D35,"preference","convert") -> convert | E41: =IF(D12>C12*E35,"preference","convert") -> convert | F41: =IF(D12>C12*F35,"preference","convert") -> convert | G41: =IF(D12>C12*G35,"preference","convert") -> convert | H41: =IF(D12>C12*H35,"preference","convert") -> convert
B42: Seed election | D42: =IF(D13>C13*D35,"preference","convert") -> convert | E42: =IF(D13>C13*E35,"preference","convert") -> convert | F42: =IF(D13>C13*F35,"preference","convert") -> convert | G42: =IF(D13>C13*G35,"preference","convert") -> convert | H42: =IF(D13>C13*H35,"preference","convert") -> convert
B43: Iteration 3
B44: per-share (residual / pool) | D44: =(D24-(IF(D36="preference",D7,0)+IF(D37="preference",D8,0)+IF(D38="preference",D9,0)+IF(D39="preference",D10,0)+IF(D40="preference",D11,0)+IF(D41="preference",D12,0)+IF(D42="preference",D13,0)))/($C$20-(IF(D36="preference",C7,0)+IF(D37="preference",C8,0)+IF(D38="preference",C9,0)+IF(D39="preference",C10,0)+IF(D40="preference",C11,0)+IF(D41="preference",C12,0)+IF(D42="preference",C13,0))) -> 8.3787244 | E44: =(E24-(IF(E36="preference",D7,0)+IF(E37="preference",D8,0)+IF(E38="preference",D9,0)+IF(E39="preference",D10,0)+IF(E40="preference",D11,0)+IF(E41="preference",D12,0)+IF(E42="preference",D13,0)))/($C$20-(IF(E36="preference",C7,0)+IF(E37="preference",C8,0)+IF(E38="preference",C9,0)+IF(E39="preference",C10,0)+IF(E40="preference",C11,0)+IF(E41="preference",C12,0)+IF(E42="preference",C13,0))) -> 28.420213 | F44: =(F24-(IF(F36="preference",D7,0)+IF(F37="preference",D8,0)+IF(F38="preference",D9,0)+IF(F39="preference",D10,0)+IF(F40="preference",D11,0)+IF(F41="preference",D12,0)+IF(F42="preference",D13,0)))/($C$20-(IF(F36="preference",C7,0)+IF(F37="preference",C8,0)+IF(F38="preference",C9,0)+IF(F39="preference",C10,0)+IF(F40="preference",C11,0)+IF(F41="preference",C12,0)+IF(F42="preference",C13,0))) -> 55.758771 | G44: =(G24-(IF(G36="preference",D7,0)+IF(G37="preference",D8,0)+IF(G38="preference",D9,0)+IF(G39="preference",D10,0)+IF(G40="preference",D11,0)+IF(G41="preference",D12,0)+IF(G42="preference",D13,0)))/($C$20-(IF(G36="preference",C7,0)+IF(G37="preference",C8,0)+IF(G38="preference",C9,0)+IF(G39="preference",C10,0)+IF(G40="preference",C11,0)+IF(G41="preference",C12,0)+IF(G42="preference",C13,0))) -> 111.63276 | H44: =(H24-(IF(H36="preference",D7,0)+IF(H37="preference",D8,0)+IF(H38="preference",D9,0)+IF(H39="preference",D10,0)+IF(H40="preference",D11,0)+IF(H41="preference",D12,0)+IF(H42="preference",D13,0)))/($C$20-(IF(H36="preference",C7,0)+IF(H37="preference",C8,0)+IF(H38="preference",C9,0)+IF(H39="preference",C10,0)+IF(H40="preference",C11,0)+IF(H41="preference",C12,0)+IF(H42="preference",C13,0))) -> 223.1958
B45: F election | D45: =IF(D7>C7*D44,"preference","convert") -> preference | E45: =IF(D7>C7*E44,"preference","convert") -> preference | F45: =IF(D7>C7*F44,"preference","convert") -> convert | G45: =IF(D7>C7*G44,"preference","convert") -> convert | H45: =IF(D7>C7*H44,"preference","convert") -> convert
B46: E election | D46: =IF(D8>C8*D44,"preference","convert") -> preference | E46: =IF(D8>C8*E44,"preference","convert") -> preference | F46: =IF(D8>C8*F44,"preference","convert") -> convert | G46: =IF(D8>C8*G44,"preference","convert") -> convert | H46: =IF(D8>C8*H44,"preference","convert") -> convert
B47: D election | D47: =IF(D9>C9*D44,"preference","convert") -> preference | E47: =IF(D9>C9*E44,"preference","convert") -> preference | F47: =IF(D9>C9*F44,"preference","convert") -> preference | G47: =IF(D9>C9*G44,"preference","convert") -> convert | H47: =IF(D9>C9*H44,"preference","convert") -> convert
B48: C election | D48: =IF(D10>C10*D44,"preference","convert") -> preference | E48: =IF(D10>C10*E44,"preference","convert") -> convert | F48: =IF(D10>C10*F44,"preference","convert") -> convert | G48: =IF(D10>C10*G44,"preference","convert") -> convert | H48: =IF(D10>C10*H44,"preference","convert") -> convert
B49: B election | D49: =IF(D11>C11*D44,"preference","convert") -> preference | E49: =IF(D11>C11*E44,"preference","convert") -> convert | F49: =IF(D11>C11*F44,"preference","convert") -> convert | G49: =IF(D11>C11*G44,"preference","convert") -> convert | H49: =IF(D11>C11*H44,"preference","convert") -> convert
B50: A election | D50: =IF(D12>C12*D44,"preference","convert") -> convert | E50: =IF(D12>C12*E44,"preference","convert") -> convert | F50: =IF(D12>C12*F44,"preference","convert") -> convert | G50: =IF(D12>C12*G44,"preference","convert") -> convert | H50: =IF(D12>C12*H44,"preference","convert") -> convert
B51: Seed election | D51: =IF(D13>C13*D44,"preference","convert") -> convert | E51: =IF(D13>C13*E44,"preference","convert") -> convert | F51: =IF(D13>C13*F44,"preference","convert") -> convert | G51: =IF(D13>C13*G44,"preference","convert") -> convert | H51: =IF(D13>C13*H44,"preference","convert") -> convert
B52: Iteration 4
B53: per-share (residual / pool) | D53: =(D24-(IF(D45="preference",D7,0)+IF(D46="preference",D8,0)+IF(D47="preference",D9,0)+IF(D48="preference",D10,0)+IF(D49="preference",D11,0)+IF(D50="preference",D12,0)+IF(D51="preference",D13,0)))/($C$20-(IF(D45="preference",C7,0)+IF(D46="preference",C8,0)+IF(D47="preference",C9,0)+IF(D48="preference",C10,0)+IF(D49="preference",C11,0)+IF(D50="preference",C12,0)+IF(D51="preference",C13,0))) -> 8.3787244 | E53: =(E24-(IF(E45="preference",D7,0)+IF(E46="preference",D8,0)+IF(E47="preference",D9,0)+IF(E48="preference",D10,0)+IF(E49="preference",D11,0)+IF(E50="preference",D12,0)+IF(E51="preference",D13,0)))/($C$20-(IF(E45="preference",C7,0)+IF(E46="preference",C8,0)+IF(E47="preference",C9,0)+IF(E48="preference",C10,0)+IF(E49="preference",C11,0)+IF(E50="preference",C12,0)+IF(E51="preference",C13,0))) -> 28.420213 | F53: =(F24-(IF(F45="preference",D7,0)+IF(F46="preference",D8,0)+IF(F47="preference",D9,0)+IF(F48="preference",D10,0)+IF(F49="preference",D11,0)+IF(F50="preference",D12,0)+IF(F51="preference",D13,0)))/($C$20-(IF(F45="preference",C7,0)+IF(F46="preference",C8,0)+IF(F47="preference",C9,0)+IF(F48="preference",C10,0)+IF(F49="preference",C11,0)+IF(F50="preference",C12,0)+IF(F51="preference",C13,0))) -> 55.758771 | G53: =(G24-(IF(G45="preference",D7,0)+IF(G46="preference",D8,0)+IF(G47="preference",D9,0)+IF(G48="preference",D10,0)+IF(G49="preference",D11,0)+IF(G50="preference",D12,0)+IF(G51="preference",D13,0)))/($C$20-(IF(G45="preference",C7,0)+IF(G46="preference",C8,0)+IF(G47="preference",C9,0)+IF(G48="preference",C10,0)+IF(G49="preference",C11,0)+IF(G50="preference",C12,0)+IF(G51="preference",C13,0))) -> 111.63276 | H53: =(H24-(IF(H45="preference",D7,0)+IF(H46="preference",D8,0)+IF(H47="preference",D9,0)+IF(H48="preference",D10,0)+IF(H49="preference",D11,0)+IF(H50="preference",D12,0)+IF(H51="preference",D13,0)))/($C$20-(IF(H45="preference",C7,0)+IF(H46="preference",C8,0)+IF(H47="preference",C9,0)+IF(H48="preference",C10,0)+IF(H49="preference",C11,0)+IF(H50="preference",C12,0)+IF(H51="preference",C13,0))) -> 223.1958
B54: F election | D54: =IF(D7>C7*D53,"preference","convert") -> preference | E54: =IF(D7>C7*E53,"preference","convert") -> preference | F54: =IF(D7>C7*F53,"preference","convert") -> convert | G54: =IF(D7>C7*G53,"preference","convert") -> convert | H54: =IF(D7>C7*H53,"preference","convert") -> convert
B55: E election | D55: =IF(D8>C8*D53,"preference","convert") -> preference | E55: =IF(D8>C8*E53,"preference","convert") -> preference | F55: =IF(D8>C8*F53,"preference","convert") -> convert | G55: =IF(D8>C8*G53,"preference","convert") -> convert | H55: =IF(D8>C8*H53,"preference","convert") -> convert
B56: D election | D56: =IF(D9>C9*D53,"preference","convert") -> preference | E56: =IF(D9>C9*E53,"preference","convert") -> preference | F56: =IF(D9>C9*F53,"preference","convert") -> preference | G56: =IF(D9>C9*G53,"preference","convert") -> convert | H56: =IF(D9>C9*H53,"preference","convert") -> convert
B57: C election | D57: =IF(D10>C10*D53,"preference","convert") -> preference | E57: =IF(D10>C10*E53,"preference","convert") -> convert | F57: =IF(D10>C10*F53,"preference","convert") -> convert | G57: =IF(D10>C10*G53,"preference","convert") -> convert | H57: =IF(D10>C10*H53,"preference","convert") -> convert
B58: B election | D58: =IF(D11>C11*D53,"preference","convert") -> preference | E58: =IF(D11>C11*E53,"preference","convert") -> convert | F58: =IF(D11>C11*F53,"preference","convert") -> convert | G58: =IF(D11>C11*G53,"preference","convert") -> convert | H58: =IF(D11>C11*H53,"preference","convert") -> convert
B59: A election | D59: =IF(D12>C12*D53,"preference","convert") -> convert | E59: =IF(D12>C12*E53,"preference","convert") -> convert | F59: =IF(D12>C12*F53,"preference","convert") -> convert | G59: =IF(D12>C12*G53,"preference","convert") -> convert | H59: =IF(D12>C12*H53,"preference","convert") -> convert
B60: Seed election | D60: =IF(D13>C13*D53,"preference","convert") -> convert | E60: =IF(D13>C13*E53,"preference","convert") -> convert | F60: =IF(D13>C13*F53,"preference","convert") -> convert | G60: =IF(D13>C13*G53,"preference","convert") -> convert | H60: =IF(D13>C13*H53,"preference","convert") -> convert
B61: Iteration 5
B62: per-share (residual / pool) | D62: =(D24-(IF(D54="preference",D7,0)+IF(D55="preference",D8,0)+IF(D56="preference",D9,0)+IF(D57="preference",D10,0)+IF(D58="preference",D11,0)+IF(D59="preference",D12,0)+IF(D60="preference",D13,0)))/($C$20-(IF(D54="preference",C7,0)+IF(D55="preference",C8,0)+IF(D56="preference",C9,0)+IF(D57="preference",C10,0)+IF(D58="preference",C11,0)+IF(D59="preference",C12,0)+IF(D60="preference",C13,0))) -> 8.3787244 | E62: =(E24-(IF(E54="preference",D7,0)+IF(E55="preference",D8,0)+IF(E56="preference",D9,0)+IF(E57="preference",D10,0)+IF(E58="preference",D11,0)+IF(E59="preference",D12,0)+IF(E60="preference",D13,0)))/($C$20-(IF(E54="preference",C7,0)+IF(E55="preference",C8,0)+IF(E56="preference",C9,0)+IF(E57="preference",C10,0)+IF(E58="preference",C11,0)+IF(E59="preference",C12,0)+IF(E60="preference",C13,0))) -> 28.420213 | F62: =(F24-(IF(F54="preference",D7,0)+IF(F55="preference",D8,0)+IF(F56="preference",D9,0)+IF(F57="preference",D10,0)+IF(F58="preference",D11,0)+IF(F59="preference",D12,0)+IF(F60="preference",D13,0)))/($C$20-(IF(F54="preference",C7,0)+IF(F55="preference",C8,0)+IF(F56="preference",C9,0)+IF(F57="preference",C10,0)+IF(F58="preference",C11,0)+IF(F59="preference",C12,0)+IF(F60="preference",C13,0))) -> 55.758771 | G62: =(G24-(IF(G54="preference",D7,0)+IF(G55="preference",D8,0)+IF(G56="preference",D9,0)+IF(G57="preference",D10,0)+IF(G58="preference",D11,0)+IF(G59="preference",D12,0)+IF(G60="preference",D13,0)))/($C$20-(IF(G54="preference",C7,0)+IF(G55="preference",C8,0)+IF(G56="preference",C9,0)+IF(G57="preference",C10,0)+IF(G58="preference",C11,0)+IF(G59="preference",C12,0)+IF(G60="preference",C13,0))) -> 111.63276 | H62: =(H24-(IF(H54="preference",D7,0)+IF(H55="preference",D8,0)+IF(H56="preference",D9,0)+IF(H57="preference",D10,0)+IF(H58="preference",D11,0)+IF(H59="preference",D12,0)+IF(H60="preference",D13,0)))/($C$20-(IF(H54="preference",C7,0)+IF(H55="preference",C8,0)+IF(H56="preference",C9,0)+IF(H57="preference",C10,0)+IF(H58="preference",C11,0)+IF(H59="preference",C12,0)+IF(H60="preference",C13,0))) -> 223.1958
B63: F election | D63: =IF(D7>C7*D62,"preference","convert") -> preference | E63: =IF(D7>C7*E62,"preference","convert") -> preference | F63: =IF(D7>C7*F62,"preference","convert") -> convert | G63: =IF(D7>C7*G62,"preference","convert") -> convert | H63: =IF(D7>C7*H62,"preference","convert") -> convert
B64: E election | D64: =IF(D8>C8*D62,"preference","convert") -> preference | E64: =IF(D8>C8*E62,"preference","convert") -> preference | F64: =IF(D8>C8*F62,"preference","convert") -> convert | G64: =IF(D8>C8*G62,"preference","convert") -> convert | H64: =IF(D8>C8*H62,"preference","convert") -> convert
B65: D election | D65: =IF(D9>C9*D62,"preference","convert") -> preference | E65: =IF(D9>C9*E62,"preference","convert") -> preference | F65: =IF(D9>C9*F62,"preference","convert") -> preference | G65: =IF(D9>C9*G62,"preference","convert") -> convert | H65: =IF(D9>C9*H62,"preference","convert") -> convert
B66: C election | D66: =IF(D10>C10*D62,"preference","convert") -> preference | E66: =IF(D10>C10*E62,"preference","convert") -> convert | F66: =IF(D10>C10*F62,"preference","convert") -> convert | G66: =IF(D10>C10*G62,"preference","convert") -> convert | H66: =IF(D10>C10*H62,"preference","convert") -> convert
B67: B election | D67: =IF(D11>C11*D62,"preference","convert") -> preference | E67: =IF(D11>C11*E62,"preference","convert") -> convert | F67: =IF(D11>C11*F62,"preference","convert") -> convert | G67: =IF(D11>C11*G62,"preference","convert") -> convert | H67: =IF(D11>C11*H62,"preference","convert") -> convert
B68: A election | D68: =IF(D12>C12*D62,"preference","convert") -> convert | E68: =IF(D12>C12*E62,"preference","convert") -> convert | F68: =IF(D12>C12*F62,"preference","convert") -> convert | G68: =IF(D12>C12*G62,"preference","convert") -> convert | H68: =IF(D12>C12*H62,"preference","convert") -> convert
B69: Seed election | D69: =IF(D13>C13*D62,"preference","convert") -> convert | E69: =IF(D13>C13*E62,"preference","convert") -> convert | F69: =IF(D13>C13*F62,"preference","convert") -> convert | G69: =IF(D13>C13*G62,"preference","convert") -> convert | H69: =IF(D13>C13*H62,"preference","convert") -> convert
B71: Final Calculations
B72: Final per-share value | D72: =(D24-(IF(D63="preference",D7,0)+IF(D64="preference",D8,0)+IF(D65="preference",D9,0)+IF(D66="preference",D10,0)+IF(D67="preference",D11,0)+IF(D68="preference",D12,0)+IF(D69="preference",D13,0)))/($C$20-(IF(D63="preference",C7,0)+IF(D64="preference",C8,0)+IF(D65="preference",C9,0)+IF(D66="preference",C10,0)+IF(D67="preference",C11,0)+IF(D68="preference",C12,0)+IF(D69="preference",C13,0))) -> 8.3787244 | E72: =(E24-(IF(E63="preference",D7,0)+IF(E64="preference",D8,0)+IF(E65="preference",D9,0)+IF(E66="preference",D10,0)+IF(E67="preference",D11,0)+IF(E68="preference",D12,0)+IF(E69="preference",D13,0)))/($C$20-(IF(E63="preference",C7,0)+IF(E64="preference",C8,0)+IF(E65="preference",C9,0)+IF(E66="preference",C10,0)+IF(E67="preference",C11,0)+IF(E68="preference",C12,0)+IF(E69="preference",C13,0))) -> 28.420213 | F72: =(F24-(IF(F63="preference",D7,0)+IF(F64="preference",D8,0)+IF(F65="preference",D9,0)+IF(F66="preference",D10,0)+IF(F67="preference",D11,0)+IF(F68="preference",D12,0)+IF(F69="preference",D13,0)))/($C$20-(IF(F63="preference",C7,0)+IF(F64="preference",C8,0)+IF(F65="preference",C9,0)+IF(F66="preference",C10,0)+IF(F67="preference",C11,0)+IF(F68="preference",C12,0)+IF(F69="preference",C13,0))) -> 55.758771 | G72: =(G24-(IF(G63="preference",D7,0)+IF(G64="preference",D8,0)+IF(G65="preference",D9,0)+IF(G66="preference",D10,0)+IF(G67="preference",D11,0)+IF(G68="preference",D12,0)+IF(G69="preference",D13,0)))/($C$20-(IF(G63="preference",C7,0)+IF(G64="preference",C8,0)+IF(G65="preference",C9,0)+IF(G66="preference",C10,0)+IF(G67="preference",C11,0)+IF(G68="preference",C12,0)+IF(G69="preference",C13,0))) -> 111.63276 | H72: =(H24-(IF(H63="preference",D7,0)+IF(H64="preference",D8,0)+IF(H65="preference",D9,0)+IF(H66="preference",D10,0)+IF(H67="preference",D11,0)+IF(H68="preference",D12,0)+IF(H69="preference",D13,0)))/($C$20-(IF(H63="preference",C7,0)+IF(H64="preference",C8,0)+IF(H65="preference",C9,0)+IF(H66="preference",C10,0)+IF(H67="preference",C11,0)+IF(H68="preference",C12,0)+IF(H69="preference",C13,0))) -> 223.1958
B73: Final Elections
B74: F election (final) | D74: =IF(D7>C7*D72,"preference","convert") -> preference | E74: =IF(D7>C7*E72,"preference","convert") -> preference | F74: =IF(D7>C7*F72,"preference","convert") -> convert | G74: =IF(D7>C7*G72,"preference","convert") -> convert | H74: =IF(D7>C7*H72,"preference","convert") -> convert
B75: E election (final) | D75: =IF(D8>C8*D72,"preference","convert") -> preference | E75: =IF(D8>C8*E72,"preference","convert") -> preference | F75: =IF(D8>C8*F72,"preference","convert") -> convert | G75: =IF(D8>C8*G72,"preference","convert") -> convert | H75: =IF(D8>C8*H72,"preference","convert") -> convert
B76: D election (final) | D76: =IF(D9>C9*D72,"preference","convert") -> preference | E76: =IF(D9>C9*E72,"preference","convert") -> preference | F76: =IF(D9>C9*F72,"preference","convert") -> preference | G76: =IF(D9>C9*G72,"preference","convert") -> convert | H76: =IF(D9>C9*H72,"preference","convert") -> convert
B77: C election (final) | D77: =IF(D10>C10*D72,"preference","convert") -> preference | E77: =IF(D10>C10*E72,"preference","convert") -> convert | F77: =IF(D10>C10*F72,"preference","convert") -> convert | G77: =IF(D10>C10*G72,"preference","convert") -> convert | H77: =IF(D10>C10*H72,"preference","convert") -> convert
B78: B election (final) | D78: =IF(D11>C11*D72,"preference","convert") -> preference | E78: =IF(D11>C11*E72,"preference","convert") -> convert | F78: =IF(D11>C11*F72,"preference","convert") -> convert | G78: =IF(D11>C11*G72,"preference","convert") -> convert | H78: =IF(D11>C11*H72,"preference","convert") -> convert
B79: A election (final) | D79: =IF(D12>C12*D72,"preference","convert") -> convert | E79: =IF(D12>C12*E72,"preference","convert") -> convert | F79: =IF(D12>C12*F72,"preference","convert") -> convert | G79: =IF(D12>C12*G72,"preference","convert") -> convert | H79: =IF(D12>C12*H72,"preference","convert") -> convert
B80: Seed election (final) | D80: =IF(D13>C13*D72,"preference","convert") -> convert | E80: =IF(D13>C13*E72,"preference","convert") -> convert | F80: =IF(D13>C13*F72,"preference","convert") -> convert | G80: =IF(D13>C13*G72,"preference","convert") -> convert | H80: =IF(D13>C13*H72,"preference","convert") -> convert
B82: Waterfall — Proceeds by Class
B83: Class / Stake | D83: =Assumptions!$C$55 -> 700000000 | E83: =Assumptions!$C$56 -> 1200000000 | F83: =Assumptions!$C$57 -> 2000000000 | G83: =Assumptions!$C$58 -> 4000000000 | H83: =Assumptions!$C$59 -> 8000000000
B84: Series F | D84: =IF(D74="preference",D7,C7*D72) -> 30000000 | E84: =IF(E74="preference",D7,C7*E72) -> 30000000 | F84: =IF(F74="preference",D7,C7*F72) -> 44846575 | G84: =IF(G74="preference",D7,C7*G72) -> 89785823 | H84: =IF(H74="preference",D7,C7*H72) -> 1.7951557e+08
B85: Series E | D85: =IF(D75="preference",D8,C8*D72) -> 300000000 | E85: =IF(E75="preference",D8,C8*E72) -> 300000000 | F85: =IF(F75="preference",D8,C8*F72) -> 3.4205429e+08 | G85: =IF(G75="preference",D8,C8*G72) -> 6.848154e+08 | H85: =IF(H75="preference",D8,C8*H72) -> 1.3692031e+09
B86: Series D | D86: =IF(D76="preference",D9,C9*D72) -> 100000000 | E86: =IF(E76="preference",D9,C9*E72) -> 100000000 | F86: =IF(F76="preference",D9,C9*F72) -> 100000000 | G86: =IF(G76="preference",D9,C9*G72) -> 1.9356861e+08 | H86: =IF(H76="preference",D9,C9*H72) -> 3.8701631e+08
B87: Series C | D87: =IF(D77="preference",D10,C10*D72) -> 60000000 | E87: =IF(E77="preference",D10,C10*E72) -> 68208511 | F87: =IF(F77="preference",D10,C10*F72) -> 1.3382105e+08 | G87: =IF(G77="preference",D10,C10*G72) -> 2.6791863e+08 | H87: =IF(H77="preference",D10,C10*H72) -> 5.3566992e+08
B88: Series B | D88: =IF(D78="preference",D11,C11*D72) -> 30000000 | E88: =IF(E78="preference",D11,C11*E72) -> 85260639 | F88: =IF(F78="preference",D11,C11*F72) -> 1.6727631e+08 | G88: =IF(G78="preference",D11,C11*G72) -> 3.3489829e+08 | H88: =IF(H78="preference",D11,C11*H72) -> 6.695874e+08
B89: Series A | D89: =IF(D79="preference",D12,C12*D72) -> 41893622 | E89: =IF(E79="preference",D12,C12*E72) -> 1.4210106e+08 | F89: =IF(F79="preference",D12,C12*F72) -> 2.7879385e+08 | G89: =IF(G79="preference",D12,C12*G72) -> 5.5816382e+08 | H89: =IF(H79="preference",D12,C12*H72) -> 1.115979e+09
B90: Seed | D90: =IF(D80="preference",D13,C13*D72) -> 41893622 | E90: =IF(E80="preference",D13,C13*E72) -> 1.4210106e+08 | F90: =IF(F80="preference",D13,C13*F72) -> 2.7879385e+08 | G90: =IF(G80="preference",D13,C13*G72) -> 5.5816382e+08 | H90: =IF(H80="preference",D13,C13*H72) -> 1.115979e+09
B91: Notes (NA + NB) | D91: =$C$17*D72 -> 2357425.9 | E91: =$C$17*E72 -> 7996270.5 | F91: =$C$17*F72 -> 15688208 | G91: =$C$17*G72 -> 31408834 | H91: =$C$17*H72 -> 62798051
B92: Common + RSAs | D92: =$C$16*D72 -> 75408519 | E92: =$C$16*E72 -> 2.5578192e+08 | F92: =$C$16*F72 -> 5.0182894e+08 | G92: =$C$16*G72 -> 1.0046949e+09 | H92: =$C$16*H72 -> 2.0087622e+09
B93: Issued options (net of strike) | D93: =MAX(0,$C$18*D72-$C$18*Assumptions!$C$13) -> 18446811 | E93: =MAX(0,$C$18*E72-$C$18*Assumptions!$C$13) -> 68550532 | F93: =MAX(0,$C$18*F72-$C$18*Assumptions!$C$13) -> 1.3689693e+08 | G93: =MAX(0,$C$18*G72-$C$18*Assumptions!$C$13) -> 2.7658191e+08 | H93: =MAX(0,$C$18*H72-$C$18*Assumptions!$C$13) -> 5.554895e+08
B94: Total proceeds | D94: =SUM(D84,D85,D86,D87,D88,D89,D90)+D91+D92+D93 -> 700000000 | E94: =SUM(E84,E85,E86,E87,E88,E89,E90)+E91+E92+E93 -> 1.2e+09 | F94: =SUM(F84,F85,F86,F87,F88,F89,F90)+F91+F92+F93 -> 2e+09 | G94: =SUM(G84,G85,G86,G87,G88,G89,G90)+G91+G92+G93 -> 4e+09 | H94: =SUM(H84,H85,H86,H87,H88,H89,H90)+H91+H92+H93 -> 8000000000
B95: Reconciliation (Total − Exit) | D95: =ROUND(D94-Assumptions!$C$55,0) -> 0 | E95: =ROUND(E94-Assumptions!$C$56,0) -> 0 | F95: =ROUND(F94-Assumptions!$C$57,0) -> 0 | G95: =ROUND(G94-Assumptions!$C$58,0) -> 0 | H95: =ROUND(H94-Assumptions!$C$59,0) -> 0
B96: Check | D96: =ROUND(D94-Assumptions!$C$55,0) -> 0 | E96: =ROUND(E94-Assumptions!$C$56,0) -> 0 | F96: =ROUND(F94-Assumptions!$C$57,0) -> 0 | G96: =ROUND(G94-Assumptions!$C$58,0) -> 0 | H96: =ROUND(H94-Assumptions!$C$59,0) -> 0
