Workbook

Sheet Assumptions
B2: Kelvin Dynamics — Series F Assumptions
B3: USD; share counts in actuals; PPS in dollars
B5: Series F Round Terms
B6: Series F pre-money (USD) | C6: 1400000000
B7: Series F primary raise (USD) | C7: 30000000
B8: Series F secondary raise (USD) | C8: 15000000
B9: Tender PPS multiplier (x F PPS) | C9: 0.85
B10: ESOP refresh target (% of post-F FD) | C10: 0.13
B11: Our fund check (USD) | C11: 10000000
B12: F_LEAD primary check (USD) | C12: 20000000
B14: Prior Round OCPs (for AD)
B15: Seed OCP | C15: 1
B16: Series A OCP | C16: 3
B17: Series B OCP | C17: 10
B18: Series C OCP | C18: 25
B19: Series D effective OCP (compound v3·v4) | C19: 58.118347
B20: Series E OCP | C20: 49.158311
B22: Pre-F Capitalization (broad-based WA inputs)
B23: Pre-F broad-based FD (A in WA formula) | C23: 36617961
B24: Pre-F options issued (vested/exercisable) | C24: 2500000
B25: Pre-F options unissued (pool) | C25: 1894667
B26: Option strike (USD) | C26: 1
B28: Convertible Notes
B29: Note A principal (USD) | C29: 5000000
B30: Note A valuation cap (USD) | C30: 1000000000
B31: Note A discount | C31: 0.2
B32: Note B principal (USD) | C32: 3000000
B33: Note B valuation cap (USD) | C33: 1600000000
B34: Note B discount | C34: 0.15
B36: Pre-F Holders (shares outstanding)
B37: F1 (CEO) common | C37: 4000000
B38: F2 (CTO) common | C38: 2500000
B39: F3 (Chief Scientist) common | C39: 1500000
B40: Employee RSAs (10 holders × 100k) | C40: 1000000
B41: Seed shares | C41: 5000000
B42: Series A shares | C42: 5000000
B43: Series B shares | C43: 3000000
B44: Series C shares | C44: 2400000
B45: Series D shares (post-E AD adjustment) | C45: 1720627
B46: Series E shares | C46: 6102667
B47: Series D invested capital (USD) | C47: 100000000
B48: Series E invested capital (USD) | C48: 300000000
... B52: Seed invested capital (USD) | C52: 5000000
B54: Founder Tender Pro-Rata Split
B55: F1 share of tender | C55: =C37/(C37+C38+C39) -> 0.5
B56: F2 share of tender | C56: =C38/(C37+C38+C39) -> 0.3125
B57: F3 share of tender | C57: =C39/(C37+C38+C39) -> 0.1875
B59: Exit Scenarios
B60: Exit 1 | C60: 700000000
B61: Exit 2 | C61: 1200000000
B62: Exit 3 (sensitivity reference) | C62: 2000000000
B63: Exit 4 | C63: 4000000000
B64: Exit 5 | C64: 8000000000
B66: Sensitivity Axes
B67: ESOP refresh — low | C67: 0.11
B68: ESOP refresh — base | C68: 0.13
B69: ESOP refresh — high | C69: 0.15
B70: Series F pre-money — low | C70: 1200000000
B71: Series F pre-money — base | C71: 1400000000
B72: Series F pre-money — high | C72: 1800000000
B74: Return-Solver Targets
B75: 3x net target ($) | C75: =C11*3 -> 30000000
B76: 4x net target ($) | C76: =C11*4 -> 40000000

Sheet Pro-Forma
B2: Kelvin Dynamics — Series F Pro-Forma
B3: Post-F cap table; share counts in actuals; PPS in dollars
B5: Round Closing Fixed Point (iterative)
B6: Variable | C6: Source | D6: Iter 0 | E6: Iter 1 | F6: Iter 2 | G6: Iter 3 | H6: Iter 4 | I6: Iter 5 | J6: Iter 6 | K6: Final
B7: Pre-F FD (A in WA) | C7: =Assumptions!C23 -> 36617961
B8: F primary raise ($) | C8: =Assumptions!C7 -> 30000000
B9: F pre-money ($) | C9: =Assumptions!C6 -> 1400000000
B10: ESOP target (% post-F FD) | C10: =Assumptions!C10 -> 0.13
B11: Pre-F option pool | C11: =Assumptions!C24+Assumptions!C25 -> 4394667
B13: ESOP top-up shares | D13: 0 | E13: =MAX(0,C10*D30-C11) -> 473017.31 | F13: =MAX(0,C10*E30-C11) -> 572369.32 | G13: =MAX(0,C10*F30-C11) -> 586809.89 | H13: =MAX(0,C10*G30-C11) -> 588757.68 | I13: =MAX(0,C10*H30-C11) -> 589019.83 | J13: =MAX(0,C10*I30-C11) -> 589055.11 | K13: =J13 -> 589055.11
B14: Note A shares | D14: 0 | E14: =Assumptions!C29/E19 -> 185454.89 | F14: =Assumptions!C29/F19 -> 186419.18 | G14: =Assumptions!C29/G19 -> 186496.16 | H14: =Assumptions!C29/H19 -> 186506.1 | I14: =Assumptions!C29/I19 -> 186507.44 | J14: =Assumptions!C29/J19 -> 186507.62 | K14: =J14 -> 186507.62
B15: Note B shares | D15: 0 | E15: =Assumptions!C32/E22 -> 93506.668 | F15: =Assumptions!C32/F22 -> 94460.4 | G15: =Assumptions!C32/G22 -> 94501.64 | H15: =Assumptions!C32/H22 -> 94506.848 | I15: =Assumptions!C32/I22 -> 94507.547 | J15: =Assumptions!C32/J22 -> 94507.641 | K15: =J15 -> 94507.641
B16: F PPS ($) | D16: =C9/C7 -> 38.232604 | E16: =C9/(C7+E13+D14+D15) -> 37.745028 | F16: =C9/(C7+F13+E14+E15) -> 37.36393 | G16: =C9/(C7+G13+F14+F15) -> 37.347625 | H16: =C9/(C7+H13+G14+G15) -> 37.345566 | I16: =C9/(C7+I13+H14+H15) -> 37.34529 | J16: =C9/(C7+J13+I14+I15) -> 37.345253 | K16: =J16 -> 37.345253
B17: Note A cap-implied PPS ($) | D17: =Assumptions!C30/(C7+D13+D15) -> 27.309003 | E17: =Assumptions!C30/(C7+E13+D15) -> 26.960734 | F17: =Assumptions!C30/(C7+F13+E15) -> 26.821274 | G17: =Assumptions!C30/(C7+G13+F15) -> 26.810204 | H17: =Assumptions!C30/(C7+H13+G15) -> 26.808774 | I17: =Assumptions!C30/(C7+I13+H15) -> 26.808582 | J17: =Assumptions!C30/(C7+J13+I15) -> 26.808556 | K17: =J17 -> 26.808556
B18: Note A discount-implied PPS ($) | D18: =D16*(1-Assumptions!C31) -> 30.586083 | E18: =E16*(1-Assumptions!C31) -> 30.196022 | F18: =F16*(1-Assumptions!C31) -> 29.891144 | G18: =G16*(1-Assumptions!C31) -> 29.8781 | H18: =H16*(1-Assumptions!C31) -> 29.876453 | I18: =I16*(1-Assumptions!C31) -> 29.876232 | J18: =J16*(1-Assumptions!C31) -> 29.876202 | K18: =J18 -> 29.876202
B19: Note A conversion PPS ($) | D19: =MIN(D17,D18) -> 27.309003 | E19: =MIN(E17,E18) -> 26.960734 | F19: =MIN(F17,F18) -> 26.821274 | G19: =MIN(G17,G18) -> 26.810204 | H19: =MIN(H17,H18) -> 26.808774 | I19: =MIN(I17,I18) -> 26.808582 | J19: =MIN(J17,J18) -> 26.808556 | K19: =J19 -> 26.808556
B20: Note B cap-implied PPS ($) | D20: =Assumptions!C33/(C7+D13+D14) -> 43.694405 | E20: =Assumptions!C33/(C7+E13+E14) -> 42.922562 | F20: =Assumptions!C33/(C7+F13+F14) -> 42.807361 | G20: =Assumptions!C33/(C7+G13+G14) -> 42.79074 | H20: =Assumptions!C33/(C7+H13+H14) -> 42.7885 | I20: =Assumptions!C33/(C7+I13+I14) -> 42.788199 | J20: =Assumptions!C33/(C7+J13+J14) -> 42.788158 | K20: =J20 -> 42.788158
B21: Note B discount-implied PPS ($) | D21: =D16*(1-Assumptions!C34) -> 32.497713 | E21: =E16*(1-Assumptions!C34) -> 32.083273 | F21: =F16*(1-Assumptions!C34) -> 31.759341 | G21: =G16*(1-Assumptions!C34) -> 31.745481 | H21: =H16*(1-Assumptions!C34) -> 31.743731 | I21: =I16*(1-Assumptions!C34) -> 31.743497 | J21: =J16*(1-Assumptions!C34) -> 31.743465 | K21: =J21 -> 31.743465
B22: Note B conversion PPS ($) | D22: =MIN(D20,D21) -> 32.497713 | E22: =MIN(E20,E21) -> 32.083273 | F22: =MIN(F20,F21) -> 31.759341 | G22: =MIN(G20,G21) -> 31.745481 | H22: =MIN(H20,H21) -> 31.743731 | I22: =MIN(I20,I21) -> 31.743497 | J22: =MIN(J20,J21) -> 31.743465 | K22: =J22 -> 31.743465
B23: F primary new shares | D23: =C8/D16 -> 784670.59 | E23: =C8/E16 -> 794806.68 | F23: =C8/F16 -> 802913.4 | G23: =C8/G16 -> 803263.94 | H23: =C8/H16 -> 803308.21 | I23: =C8/I16 -> 803314.15 | J23: =C8/J16 -> 803314.95 | K23: =J23 -> 803314.95
B24: Series E new conversion price ($) | D24: =Assumptions!C20*(C7+C8/Assumptions!C20)/(C7+C8/D16) -> 48.9291 | E24: =Assumptions!C20*(C7+C8/Assumptions!C20)/(C7+C8/E16) -> 48.915844 | F24: =Assumptions!C20*(C7+C8/Assumptions!C20)/(C7+C8/F16) -> 48.905247 | G24: =Assumptions!C20*(C7+C8/Assumptions!C20)/(C7+C8/G16) -> 48.904789 | H24: =Assumptions!C20*(C7+C8/Assumptions!C20)/(C7+C8/H16) -> 48.904731 | I24: =Assumptions!C20*(C7+C8/Assumptions!C20)/(C7+C8/I16) -> 48.904724 | J24: =Assumptions!C20*(C7+C8/Assumptions!C20)/(C7+C8/J16) -> 48.904722 | K24: =J24 -> 48.904722
B25: Series E shares post-AD | D25: =Assumptions!C48/D24 -> 6131320.6 | E25: =Assumptions!C48/E24 -> 6132982.2 | F25: =Assumptions!C48/F24 -> 6134311.1 | G25: =Assumptions!C48/G24 -> 6134368.5 | H25: =Assumptions!C48/H24 -> 6134375.8 | I25: =Assumptions!C48/I24 -> 6134376.8 | J25: =Assumptions!C48/J24 -> 6134376.9 | K25: =J25 -> 6134376.9
B26: Series E AD extra shares | D26: =D25-Assumptions!C46 -> 28653.58 | E26: =E25-Assumptions!C46 -> 30315.163 | F26: =F25-Assumptions!C46 -> 31644.077 | G26: =G25-Assumptions!C46 -> 31701.541 | H26: =H25-Assumptions!C46 -> 31708.798 | I26: =I25-Assumptions!C46 -> 31709.772 | J26: =J25-Assumptions!C46 -> 31709.903 | K26: =J26 -> 31709.903
B27: Series D new conversion price ($) | D27: =Assumptions!C19*(C7+C8/Assumptions!C19)/(C7+C8/D16) -> 57.701164 | E27: =Assumptions!C19*(C7+C8/Assumptions!C19)/(C7+C8/E16) -> 57.685531 | F27: =Assumptions!C19*(C7+C8/Assumptions!C19)/(C7+C8/F16) -> 57.673034 | G27: =Assumptions!C19*(C7+C8/Assumptions!C19)/(C7+C8/G16) -> 57.672494 | H27: =Assumptions!C19*(C7+C8/Assumptions!C19)/(C7+C8/H16) -> 57.672426 | I27: =Assumptions!C19*(C7+C8/Assumptions!C19)/(C7+C8/I16) -> 57.672416 | J27: =Assumptions!C19*(C7+C8/Assumptions!C19)/(C7+C8/J16) -> 57.672415 | K27: =J27 -> 57.672415
B28: Series D shares post-AD | D28: =Assumptions!C47/D27 -> 1733067.3 | E28: =Assumptions!C47/E27 -> 1733537 | F28: =Assumptions!C47/F27 -> 1733912.6 | G28: =Assumptions!C47/G27 -> 1733928.8 | H28: =Assumptions!C47/H27 -> 1733930.9 | I28: =Assumptions!C47/I27 -> 1733931.2 | J28: =Assumptions!C47/J27 -> 1733931.2 | K28: =J28 -> 1733931.2
B29: Series D AD extra shares | D29: =D28-Assumptions!C45 -> 12440.304 | E29: =E28-Assumptions!C45 -> 12909.964 | F29: =F28-Assumptions!C45 -> 13285.592 | G29: =G28-Assumptions!C45 -> 13301.835 | H29: =H28-Assumptions!C45 -> 13303.886 | I29: =I28-Assumptions!C45 -> 13304.161 | J29: =J28-Assumptions!C45 -> 13304.199 | K29: =J29 -> 13304.199
B30: T_F (post-F fully diluted) | D30: =C7+D13+D23+D14+D15+D26+D29 -> 37443725 | E30: =C7+E13+E23+E14+E15+E26+E29 -> 38207972 | F30: =C7+F13+F23+F14+F15+F26+F29 -> 38319053 | G30: =C7+G13+G23+G14+G15+G26+G29 -> 38334036 | H30: =C7+H13+H23+H14+H15+H26+H29 -> 38336053 | I30: =C7+I13+I23+I14+I15+I26+I29 -> 38336324 | J30: =C7+J13+J23+J14+J15+J26+J29 -> 38336360 | K30: =J30 -> 38336360
B32: Anti-Dilution (Broad-Based WA) Block
B33: Class | C33: OCP for AD | D33: F PPS | E33: Trigger? | F33: New OCP | G33: New Ratio | H33: Orig Shares | I33: As-Converted | J33: Extra Shares
B34: Seed | C34: =Assumptions!C15 -> 1 | D34: =K16 -> 37.345253 | E34: =IF(D34<C34,"Trigger","Dormant") -> Dormant | F34: =IF(D34<C34,C34*(C7+C8/C34)/(C7+C8/D34),C34) -> 1 | G34: =C34/F34 -> 1 | H34: =Assumptions!C41 -> 5000000 | I34: =IF(D34<C34,Assumptions!C52/F34,H34) -> 5000000 | J34: =I34-H34 -> 0
B35: Series A | C35: =Assumptions!C16 -> 3 | D35: =K16 -> 37.345253 | E35: =IF(D35<C35,"Trigger","Dormant") -> Dormant | F35: =IF(D35<C35,C35*(C7+C8/C35)/(C7+C8/D35),C35) -> 3 | G35: =C35/F35 -> 1 | H35: =Assumptions!C42 -> 5000000 | I35: =IF(D35<C35,Assumptions!C51/F35,H35) -> 5000000 | J35: =I35-H35 -> 0
B36: Series B | C36: =Assumptions!C17 -> 10 | D36: =K16 -> 37.345253 | E36: =IF(D36<C36,"Trigger","Dormant") -> Dormant | F36: =IF(D36<C36,C36*(C7+C8/C36)/(C7+C8/D36),C36) -> 10 | G36: =C36/F36 -> 1 | H36: =Assumptions!C43 -> 3000000 | I36: =IF(D36<C36,Assumptions!C50/F36,H36) -> 3000000 | J36: =I36-H36 -> 0
B37: Series C | C37: =Assumptions!C18 -> 25 | D37: =K16 -> 37.345253 | E37: =IF(D37<C37,"Trigger","Dormant") -> Dormant | F37: =IF(D37<C37,C37*(C7+C8/C37)/(C7+C8/D37),C37) -> 25 | G37: =C37/F37 -> 1 | H37: =Assumptions!C44 -> 2400000 | I37: =IF(D37<C37,Assumptions!C49/F37,H37) -> 2400000 | J37: =I37-H37 -> 0
B38: Series D | C38: =Assumptions!C19 -> 58.118347 | D38: =K16 -> 37.345253 | E38: =IF(D38<C38,"Trigger","Dormant") -> Trigger | F38: =IF(D38<C38,C38*(C7+C8/C38)/(C7+C8/D38),C38) -> 57.672415 | G38: =60/F38 -> 1.0403587 | H38: =Assumptions!C45 -> 1720627 | I38: =IF(D38<C38,Assumptions!C47/F38,H38) -> 1733931.2 | J38: =I38-H38 -> 13304.199
B39: Series E | C39: =Assumptions!C20 -> 49.158311 | D39: =K16 -> 37.345253 | E39: =IF(D39<C39,"Trigger","Dormant") -> Trigger | F39: =IF(D39<C39,C39*(C7+C8/C39)/(C7+C8/D39),C39) -> 48.904722 | G39: =C39/F39 -> 1.0051854 | H39: =Assumptions!C46 -> 6102667 | I39: =IF(D39<C39,Assumptions!C48/F39,H39) -> 6134376.9 | J39: =I39-H39 -> 31709.903
B41: Convertible Notes Conversion Block
B42: Note | C42: Principal | D42: Cap | E42: Discount | F42: Cap PPS | G42: Disc PPS | H42: Branch | I42: Conv PPS | J42: Shares
B43: Note A | C43: =Assumptions!C29 -> 5000000 | D43: =Assumptions!C30 -> 1000000000 | E43: =Assumptions!C31 -> 0.2 | F43: =K17 -> 26.808556 | G43: =K18 -> 29.876202 | H43: =IF(F43<G43,"cap","discount") -> cap | I43: =K19 -> 26.808556 | J43: =K14 -> 186507.62
B44: Note B | C44: =Assumptions!C32 -> 3000000 | D44: =Assumptions!C33 -> 1600000000 | E44: =Assumptions!C34 -> 0.15 | F44: =K20 -> 42.788158 | G44: =K21 -> 31.743465 | H44: =IF(F44<G44,"cap","discount") -> discount | I44: =K22 -> 31.743465 | J44: =K15 -> 94507.641
B46: Secondary Tender Block (founders → F_LEAD)
B47: Tender PPS = 0.85 × F_PPS | C47: =Assumptions!C9*K16 -> 31.743465
B48: Total tender shares | C48: =Assumptions!C8/C47 -> 472538.21
B49: F1 tender shares (50.0%) | C49: =C48*Assumptions!C55 -> 236269.1
B50: F2 tender shares (31.25%) | C50: =C48*Assumptions!C56 -> 147668.19
B51: F3 tender shares (18.75%) | C51: =C48*Assumptions!C57 -> 88600.914
B52: F_LEAD secondary common (= total tender) | C52: =C48 -> 472538.21
B54: Post-F Capitalization by Stakeholder
B55: Stakeholder | C55: Class | D55: Common/RSA | E55: Preferred | F55: Notes | G55: Options | H55: Total Shares | I55: Ownership %
B56: F1 (CEO) | C56: Common | D56: =Assumptions!C37-C49 -> 3763730.9 | H56: =SUM(D56:G56) -> 3763730.9 | I56: =H56/K30 -> 0.098176532
B57: F2 (CTO) | C57: Common | D57: =Assumptions!C38-C50 -> 2352331.8 | H57: =SUM(D57:G57) -> 2352331.8 | I57: =H57/K30 -> 0.061360332
B58: F3 (Chief Sci) | C58: Common | D58: =Assumptions!C39-C51 -> 1411399.1 | H58: =SUM(D58:G58) -> 1411399.1 | I58: =H58/K30 -> 0.036816199
B59: Employee RSAs | C59: RSA | D59: =Assumptions!C40 -> 1000000 | H59: =SUM(D59:G59) -> 1000000 | I59: =H59/K30 -> 0.026084897
B60: Seed LP | C60: Seed | E60: =Assumptions!C41 -> 5000000 | H60: =SUM(D60:G60) -> 5000000 | I60: =H60/K30 -> 0.13042448
B61: Series A LP | C61: Series A | E61: =Assumptions!C42 -> 5000000 | H61: =SUM(D61:G61) -> 5000000 | I61: =H61/K30 -> 0.13042448
B62: Series B LP | C62: Series B | E62: =Assumptions!C43 -> 3000000 | H62: =SUM(D62:G62) -> 3000000 | I62: =H62/K30 -> 0.07825469
B63: Series C LP | C63: Series C | E63: =Assumptions!C44 -> 2400000 | H63: =SUM(D63:G63) -> 2400000 | I63: =H63/K30 -> 0.062603752
B64: Series D LP | C64: Series D | E64: =I38 -> 1733931.2 | H64: =SUM(D64:G64) -> 1733931.2 | I64: =H64/K30 -> 0.045229416
B65: Series E LP | C65: Series E | E65: =I39 -> 6134376.9 | H65: =SUM(D65:G65) -> 6134376.9 | I65: =H65/K30 -> 0.16001459
B66: Note A holder | C66: Common-equiv | F66: =K14 -> 186507.62 | H66: =SUM(D66:G66) -> 186507.62 | I66: =H66/K30 -> 0.0048650319
B67: Note B holder | C67: Common-equiv | F67: =K15 -> 94507.641 | H67: =SUM(D67:G67) -> 94507.641 | I67: =H67/K30 -> 0.0024652221
B68: F_LEAD primary | C68: Series F | E68: =Assumptions!C12/K16 -> 535543.3 | H68: =SUM(D68:G68) -> 535543.3 | I68: =H68/K30 -> 0.013969592
B69: F_LEAD secondary | C69: Common (tender) | D69: =C52 -> 472538.21 | H69: =SUM(D69:G69) -> 472538.21 | I69: =H69/K30 -> 0.01232611
B70: Our fund (F primary) | C70: Series F | E70: =Assumptions!C11/K16 -> 267771.65 | H70: =SUM(D70:G70) -> 267771.65 | I70: =H70/K30 -> 0.0069847958
B71: Issued options | C71: Options | G71: =Assumptions!C24 -> 2500000 | H71: =SUM(D71:G71) -> 2500000 | I71: =H71/K30 -> 0.065212242
B72: Unissued option pool | C72: Options | G72: =Assumptions!C25+K13 -> 2483722.1 | H72: =SUM(D72:G72) -> 2483722.1 | I72: =H72/K30 -> 0.064787635
B73: Total | D73: =SUM(D56:D72) -> 9000000 | E73: =SUM(E56:E72) -> 24071623 | F73: =SUM(F56:F72) -> 281015.26 | G73: =SUM(G56:G72) -> 4983722.1 | H73: =SUM(H56:H72) -> 38336360 | I73: =SUM(I56:I72) -> 1
B74: Check | H74: =ROUND(H73-K30,2) -> 0

Sheet Waterfall
B2: Kelvin Dynamics — Exit Waterfall
B3: Five exits; per-class election (preference/convert); reverse-chronological Nash
B5: Always-In Pool (no election)
B6: Founders + RSAs common (post-tender) | C6: ='Pro-Forma'!D56+'Pro-Forma'!D57+'Pro-Forma'!D58+'Pro-Forma'!D59 -> 8527461.8
B7: F_LEAD secondary common | C7: ='Pro-Forma'!D69 -> 472538.21
B8: Note A shares (common-equiv) | C8: ='Pro-Forma'!K14 -> 186507.62
B9: Note B shares (common-equiv) | C9: ='Pro-Forma'!K15 -> 94507.641
B10: Issued options (ITM) | C10: =Assumptions!C24 -> 2500000
B11: Always-in pool subtotal | C11: =SUM(C6:C10) -> 11781015
B13: Priced Classes (election-eligible)
B14: Class | C14: Shares (post-AD) | D14: Pref ($) | E14: Pref/Share (OCP eff)
B15: Series F | C15: ='Pro-Forma'!K23 -> 803314.95 | D15: =Assumptions!C7 -> 30000000 | E15: =D15/C15 -> 37.345253
B16: Series E | C16: ='Pro-Forma'!I39 -> 6134376.9 | D16: =Assumptions!C48 -> 300000000 | E16: =D16/C16 -> 48.904722
B17: Series D | C17: ='Pro-Forma'!I38 -> 1733931.2 | D17: =Assumptions!C47 -> 100000000 | E17: =D17/C17 -> 57.672415
B18: Series C | C18: =Assumptions!C44 -> 2400000 | D18: =Assumptions!C49 -> 60000000 | E18: =D18/C18 -> 25
B19: Series B | C19: =Assumptions!C43 -> 3000000 | D19: =Assumptions!C50 -> 30000000 | E19: =D19/C19 -> 10
B20: Series A | C20: =Assumptions!C42 -> 5000000 | D20: =Assumptions!C51 -> 15000000 | E20: =D20/C20 -> 3
B21: Seed | C21: =Assumptions!C41 -> 5000000 | D21: =Assumptions!C52 -> 5000000 | E21: =D21/C21 -> 1
B23: Exit Scenarios & Equilibrium PPS
B24: Exit Scenario | I24: =Assumptions!C60 -> 700000000 | J24: =Assumptions!C61 -> 1200000000 | K24: =Assumptions!C62 -> 2000000000 | L24: =Assumptions!C63 -> 4000000000 | M24: =Assumptions!C64 -> 8000000000
B25: Exit value ($) | I25: =I24 -> 700000000 | J25: =J24 -> 1200000000 | K25: =K24 -> 2000000000 | L25: =L24 -> 4000000000 | M25: =M24 -> 8000000000
B26: ITM options strike paid in | I26: =$C$10*Assumptions!C26 -> 2500000 | J26: =$C$10*Assumptions!C26 -> 2500000 | K26: =$C$10*Assumptions!C26 -> 2500000 | L26: =$C$10*Assumptions!C26 -> 2500000 | M26: =$C$10*Assumptions!C26 -> 2500000
B27: Total preferences (all classes) | I27: =SUM($D$15:$D$21) -> 540000000 | J27: =SUM($D$15:$D$21) -> 540000000 | K27: =SUM($D$15:$D$21) -> 540000000 | L27: =SUM($D$15:$D$21) -> 540000000 | M27: =SUM($D$15:$D$21) -> 540000000
B28: Iter 0: p (all elect preference) | I28: =(I25+I26-I27)/$C$11 -> 13.793378 | J28: =(J25+J26-J27)/$C$11 -> 56.234542 | K28: =(K25+K26-K27)/$C$11 -> 124.1404 | L28: =(L25+L26-L27)/$C$11 -> 293.90506 | M28: =(M25+M26-M27)/$C$11 -> 633.43437
B29: Iter 1: p | I29: =(I25+I26-SUMPRODUCT(($E$15:$E$21>I28)*$D$15:$D$21))/($C$11+SUMPRODUCT(($E$15:$E$21<=I28)*$C$15:$C$21)) -> 8.5751128 | J29: =(J25+J26-SUMPRODUCT(($E$15:$E$21>J28)*$D$15:$D$21))/($C$11+SUMPRODUCT(($E$15:$E$21<=J28)*$C$15:$C$21)) -> 32.313651 | K29: =(K25+K26-SUMPRODUCT(($E$15:$E$21>K28)*$D$15:$D$21))/($C$11+SUMPRODUCT(($E$15:$E$21<=K28)*$C$15:$C$21)) -> 55.85363 | L29: =(L25+L26-SUMPRODUCT(($E$15:$E$21>L28)*$D$15:$D$21))/($C$11+SUMPRODUCT(($E$15:$E$21<=L28)*$C$15:$C$21)) -> 111.63753 | M29: =(M25+M26-SUMPRODUCT(($E$15:$E$21>M28)*$D$15:$D$21))/($C$11+SUMPRODUCT(($E$15:$E$21<=M28)*$C$15:$C$21)) -> 223.20533
B30: Iter 2: p | I30: =(I25+I26-SUMPRODUCT(($E$15:$E$21>I29)*$D$15:$D$21))/($C$11+SUMPRODUCT(($E$15:$E$21<=I29)*$C$15:$C$21)) -> 8.3788564 | J30: =(J25+J26-SUMPRODUCT(($E$15:$E$21>J29)*$D$15:$D$21))/($C$11+SUMPRODUCT(($E$15:$E$21<=J29)*$C$15:$C$21)) -> 28.420572 | K30: =(K25+K26-SUMPRODUCT(($E$15:$E$21>K29)*$D$15:$D$21))/($C$11+SUMPRODUCT(($E$15:$E$21<=K29)*$C$15:$C$21)) -> 55.761199 | L30: =(L25+L26-SUMPRODUCT(($E$15:$E$21>L29)*$D$15:$D$21))/($C$11+SUMPRODUCT(($E$15:$E$21<=L29)*$C$15:$C$21)) -> 111.63753 | M30: =(M25+M26-SUMPRODUCT(($E$15:$E$21>M29)*$D$15:$D$21))/($C$11+SUMPRODUCT(($E$15:$E$21<=M29)*$C$15:$C$21)) -> 223.20533
B31: Iter 3: p | I31: =(I25+I26-SUMPRODUCT(($E$15:$E$21>I30)*$D$15:$D$21))/($C$11+SUMPRODUCT(($E$15:$E$21<=I30)*$C$15:$C$21)) -> 8.3788564 | J31: =(J25+J26-SUMPRODUCT(($E$15:$E$21>J30)*$D$15:$D$21))/($C$11+SUMPRODUCT(($E$15:$E$21<=J30)*$C$15:$C$21)) -> 28.420572 | K31: =(K25+K26-SUMPRODUCT(($E$15:$E$21>K30)*$D$15:$D$21))/($C$11+SUMPRODUCT(($E$15:$E$21<=K30)*$C$15:$C$21)) -> 55.761199 | L31: =(L25+L26-SUMPRODUCT(($E$15:$E$21>L30)*$D$15:$D$21))/($C$11+SUMPRODUCT(($E$15:$E$21<=L30)*$C$15:$C$21)) -> 111.63753 | M31: =(M25+M26-SUMPRODUCT(($E$15:$E$21>M30)*$D$15:$D$21))/($C$11+SUMPRODUCT(($E$15:$E$21<=M30)*$C$15:$C$21)) -> 223.20533
B32: Iter 4: p | I32: =(I25+I26-SUMPRODUCT(($E$15:$E$21>I31)*$D$15:$D$21))/($C$11+SUMPRODUCT(($E$15:$E$21<=I31)*$C$15:$C$21)) -> 8.3788564 | J32: =(J25+J26-SUMPRODUCT(($E$15:$E$21>J31)*$D$15:$D$21))/($C$11+SUMPRODUCT(($E$15:$E$21<=J31)*$C$15:$C$21)) -> 28.420572 | K32: =(K25+K26-SUMPRODUCT(($E$15:$E$21>K31)*$D$15:$D$21))/($C$11+SUMPRODUCT(($E$15:$E$21<=K31)*$C$15:$C$21)) -> 55.761199 | L32: =(L25+L26-SUMPRODUCT(($E$15:$E$21>L31)*$D$15:$D$21))/($C$11+SUMPRODUCT(($E$15:$E$21<=L31)*$C$15:$C$21)) -> 111.63753 | M32: =(M25+M26-SUMPRODUCT(($E$15:$E$21>M31)*$D$15:$D$21))/($C$11+SUMPRODUCT(($E$15:$E$21<=M31)*$C$15:$C$21)) -> 223.20533
B33: Iter 5: p (final) | I33: =(I25+I26-SUMPRODUCT(($E$15:$E$21>I32)*$D$15:$D$21))/($C$11+SUMPRODUCT(($E$15:$E$21<=I32)*$C$15:$C$21)) -> 8.3788564 | J33: =(J25+J26-SUMPRODUCT(($E$15:$E$21>J32)*$D$15:$D$21))/($C$11+SUMPRODUCT(($E$15:$E$21<=J32)*$C$15:$C$21)) -> 28.420572 | K33: =(K25+K26-SUMPRODUCT(($E$15:$E$21>K32)*$D$15:$D$21))/($C$11+SUMPRODUCT(($E$15:$E$21<=K32)*$C$15:$C$21)) -> 55.761199 | L33: =(L25+L26-SUMPRODUCT(($E$15:$E$21>L32)*$D$15:$D$21))/($C$11+SUMPRODUCT(($E$15:$E$21<=L32)*$C$15:$C$21)) -> 111.63753 | M33: =(M25+M26-SUMPRODUCT(($E$15:$E$21>M32)*$D$15:$D$21))/($C$11+SUMPRODUCT(($E$15:$E$21<=M32)*$C$15:$C$21)) -> 223.20533
B35: Elections (per class × exit, formula-driven)
B36: Class | I36: =I24 -> 700000000 | J36: =J24 -> 1200000000 | K36: =K24 -> 2000000000 | L36: =L24 -> 4000000000 | M36: =M24 -> 8000000000
B37: Series F | I37: =IF($E$15<=I$33,"convert","preference") -> preference | J37: =IF($E$15<=J$33,"convert","preference") -> preference | K37: =IF($E$15<=K$33,"convert","preference") -> convert | L37: =IF($E$15<=L$33,"convert","preference") -> convert | M37: =IF($E$15<=M$33,"convert","preference") -> convert
B38: Series E | I38: =IF($E$16<=I$33,"convert","preference") -> preference | J38: =IF($E$16<=J$33,"convert","preference") -> preference | K38: =IF($E$16<=K$33,"convert","preference") -> convert | L38: =IF($E$16<=L$33,"convert","preference") -> convert | M38: =IF($E$16<=M$33,"convert","preference") -> convert
B39: Series D | I39: =IF($E$17<=I$33,"convert","preference") -> preference | J39: =IF($E$17<=J$33,"convert","preference") -> preference | K39: =IF($E$17<=K$33,"convert","preference") -> preference | L39: =IF($E$17<=L$33,"convert","preference") -> convert | M39: =IF($E$17<=M$33,"convert","preference") -> convert
B40: Series C | I40: =IF($E$18<=I$33,"convert","preference") -> preference | J40: =IF($E$18<=J$33,"convert","preference") -> convert | K40: =IF($E$18<=K$33,"convert","preference") -> convert | L40: =IF($E$18<=L$33,"convert","preference") -> convert | M40: =IF($E$18<=M$33,"convert","preference") -> convert
B41: Series B | I41: =IF($E$19<=I$33,"convert","preference") -> preference | J41: =IF($E$19<=J$33,"convert","preference") -> convert | K41: =IF($E$19<=K$33,"convert","preference") -> convert | L41: =IF($E$19<=L$33,"convert","preference") -> convert | M41: =IF($E$19<=M$33,"convert","preference") -> convert
B42: Series A | I42: =IF($E$20<=I$33,"convert","preference") -> convert | J42: =IF($E$20<=J$33,"convert","preference") -> convert | K42: =IF($E$20<=K$33,"convert","preference") -> convert | L42: =IF($E$20<=L$33,"convert","preference") -> convert | M42: =IF($E$20<=M$33,"convert","preference") -> convert
B43: Seed | I43: =IF($E$21<=I$33,"convert","preference") -> convert | J43: =IF($E$21<=J$33,"convert","preference") -> convert | K43: =IF($E$21<=K$33,"convert","preference") -> convert | L43: =IF($E$21<=L$33,"convert","preference") -> convert | M43: =IF($E$21<=M$33,"convert","preference") -> convert
B45: Proceeds Distribution by Class
B46: Holder/Class | I46: =I24 -> 700000000 | J46: =J24 -> 1200000000 | K46: =K24 -> 2000000000 | L46: =L24 -> 4000000000 | M46: =M24 -> 8000000000
B47: Series F | I47: =IF(I37="convert",$C$15*I$33,$D$15) -> 30000000 | J47: =IF(J37="convert",$C$15*J$33,$D$15) -> 30000000 | K47: =IF(K37="convert",$C$15*K$33,$D$15) -> 44793804 | L47: =IF(L37="convert",$C$15*L$33,$D$15) -> 89680097 | M47: =IF(M37="convert",$C$15*M$33,$D$15) -> 1.7930418e+08
B48: Series E | I48: =IF(I38="convert",$C$16*I$33,$D$16) -> 300000000 | J48: =IF(J38="convert",$C$16*J$33,$D$16) -> 300000000 | K48: =IF(K38="convert",$C$16*K$33,$D$16) -> 3.4206021e+08 | L48: =IF(L38="convert",$C$16*L$33,$D$16) -> 6.8482669e+08 | M48: =IF(M38="convert",$C$16*M$33,$D$16) -> 1.3692256e+09
B49: Series D | I49: =IF(I39="convert",$C$17*I$33,$D$17) -> 100000000 | J49: =IF(J39="convert",$C$17*J$33,$D$17) -> 100000000 | K49: =IF(K39="convert",$C$17*K$33,$D$17) -> 100000000 | L49: =IF(L39="convert",$C$17*L$33,$D$17) -> 1.935718e+08 | M49: =IF(M39="convert",$C$17*M$33,$D$17) -> 3.8702269e+08
B50: Series C | I50: =IF(I40="convert",$C$18*I$33,$D$18) -> 60000000 | J50: =IF(J40="convert",$C$18*J$33,$D$18) -> 68209373 | K50: =IF(K40="convert",$C$18*K$33,$D$18) -> 1.3382688e+08 | L50: =IF(L40="convert",$C$18*L$33,$D$18) -> 2.6793007e+08 | M50: =IF(M40="convert",$C$18*M$33,$D$18) -> 5.3569279e+08
B51: Series B | I51: =IF(I41="convert",$C$19*I$33,$D$19) -> 30000000 | J51: =IF(J41="convert",$C$19*J$33,$D$19) -> 85261716 | K51: =IF(K41="convert",$C$19*K$33,$D$19) -> 1.672836e+08 | L51: =IF(L41="convert",$C$19*L$33,$D$19) -> 3.3491259e+08 | M51: =IF(M41="convert",$C$19*M$33,$D$19) -> 6.6961599e+08
B52: Series A | I52: =IF(I42="convert",$C$20*I$33,$D$20) -> 41894282 | J52: =IF(J42="convert",$C$20*J$33,$D$20) -> 1.4210286e+08 | K52: =IF(K42="convert",$C$20*K$33,$D$20) -> 2.7880599e+08 | L52: =IF(L42="convert",$C$20*L$33,$D$20) -> 5.5818765e+08 | M52: =IF(M42="convert",$C$20*M$33,$D$20) -> 1.1160267e+09
B53: Seed | I53: =IF(I43="convert",$C$21*I$33,$D$21) -> 41894282 | J53: =IF(J43="convert",$C$21*J$33,$D$21) -> 1.4210286e+08 | K53: =IF(K43="convert",$C$21*K$33,$D$21) -> 2.7880599e+08 | L53: =IF(L43="convert",$C$21*L$33,$D$21) -> 5.5818765e+08 | M53: =IF(M43="convert",$C$21*M$33,$D$21) -> 1.1160267e+09
B54: Notes A + B (common-equiv) | I54: =($C$8+$C$9)*I$33 -> 2354586.5 | J54: =($C$8+$C$9)*J$33 -> 7986614.4 | K54: =($C$8+$C$9)*K$33 -> 15669748 | L54: =($C$8+$C$9)*L$33 -> 31371850 | M54: =($C$8+$C$9)*M$33 -> 62724104
B55: Common + RSAs (founders+F_LEAD secondary) | I55: =($C$6+$C$7)*I$33 -> 75409708 | J55: =($C$6+$C$7)*J$33 -> 2.5578515e+08 | K55: =($C$6+$C$7)*K$33 -> 5.0185079e+08 | L55: =($C$6+$C$7)*L$33 -> 1.0047378e+09 | M55: =($C$6+$C$7)*M$33 -> 2.008848e+09
B56: Issued options (net of strike) | I56: =$C$10*MAX(0,I$33-Assumptions!C26) -> 18447141 | J56: =$C$10*MAX(0,J$33-Assumptions!C26) -> 68551430 | K56: =$C$10*MAX(0,K$33-Assumptions!C26) -> 1.36903e+08 | L56: =$C$10*MAX(0,L$33-Assumptions!C26) -> 2.7659383e+08 | M56: =$C$10*MAX(0,M$33-Assumptions!C26) -> 5.5551333e+08
B57: Total proceeds | I57: =SUM(I47:I56) -> 7e+08 | J57: =SUM(J47:J56) -> 1.2e+09 | K57: =SUM(K47:K56) -> 2e+09 | L57: =SUM(L47:L56) -> 4e+09 | M57: =SUM(M47:M56) -> 8000000000
B58: Check | I58: =ROUND(I57-I25,2) -> 0 | J58: =ROUND(J57-J25,2) -> 0 | K58: =ROUND(K57-K25,2) -> 0 | L58: =ROUND(L57-L25,2) -> 0 | M58: =ROUND(M57-M25,2) -> 0

Sheet Sensitivity
B2: Kelvin Dynamics — Sensitivity (3×3)
B3: $10M check ownership % and proceeds at $2B exit; per-cell fixed-point solve
B5: Our $10M Check — Post-F Ownership %
B6: ESOP \ Pre-money | C6: =Assumptions!C70 -> 1200000000 | D6: =Assumptions!C71 -> 1400000000 | E6: =Assumptions!C72 -> 1800000000
B7: =Assumptions!C67 -> 0.11 | C7: =D68 -> 0.0081150287 | D7: =E68 -> 0.0069851578 | E7: =F68 -> 0.005463704
B8: =Assumptions!C68 -> 0.13 | C8: =G68 -> 0.0081145625 | D8: =H68 -> 0.0069847758 | E8: =I68 -> 0.0054634228
B9: =Assumptions!C69 -> 0.15 | C9: =J68 -> 0.0081139014 | D9: =K68 -> 0.0069842106 | E9: =L68 -> 0.005462983
B11: Our $10M Check — Proceeds at $2B Exit
B12: ESOP \ Pre-money | C12: =Assumptions!C70 -> 1200000000 | D12: =Assumptions!C71 -> 1400000000 | E12: =Assumptions!C72 -> 1800000000
B13: =Assumptions!C67 -> 0.11 | C13: =D69 -> 17075671 | D13: =E69 -> 14703173 | E13: =F69 -> 11505506
B14: =Assumptions!C68 -> 0.13 | C14: =G69 -> 17350600 | D14: =H69 -> 14930354 | E14: =I69 -> 11673682
B15: =Assumptions!C69 -> 0.15 | C15: =J69 -> 17756273 | D15: =K69 -> 15279393 | E15: =L69 -> 11946526
B18: Per-Scenario Fixed-Point Detail
B19: Scenario # | D19: 1 | E19: 2 | F19: 3 | G19: 4 | H19: 5 | I19: 6 | J19: 7 | K19: 8 | L19: 9
B20: ESOP target | D20: =Assumptions!C67 -> 0.11 | E20: =Assumptions!C67 -> 0.11 | F20: =Assumptions!C67 -> 0.11 | G20: =Assumptions!C68 -> 0.13 | H20: =Assumptions!C68 -> 0.13 | I20: =Assumptions!C68 -> 0.13 | J20: =Assumptions!C69 -> 0.15 | K20: =Assumptions!C69 -> 0.15 | L20: =Assumptions!C69 -> 0.15
B21: Pre-money ($) | D21: =Assumptions!C70 -> 1200000000 | E21: =Assumptions!C71 -> 1400000000 | F21: =Assumptions!C72 -> 1800000000 | G21: =Assumptions!C70 -> 1200000000 | H21: =Assumptions!C71 -> 1400000000 | I21: =Assumptions!C72 -> 1800000000 | J21: =Assumptions!C70 -> 1200000000 | K21: =Assumptions!C71 -> 1400000000 | L21: =Assumptions!C72 -> 1800000000
B22: Pre-F FD | D22: =Assumptions!C23 -> 36617961 | E22: =Assumptions!C23 -> 36617961 | F22: =Assumptions!C23 -> 36617961 | G22: =Assumptions!C23 -> 36617961 | H22: =Assumptions!C23 -> 36617961 | I22: =Assumptions!C23 -> 36617961 | J22: =Assumptions!C23 -> 36617961 | K22: =Assumptions!C23 -> 36617961 | L22: =Assumptions!C23 -> 36617961
B23: F primary $ | D23: =Assumptions!C7 -> 30000000 | E23: =Assumptions!C7 -> 30000000 | F23: =Assumptions!C7 -> 30000000 | G23: =Assumptions!C7 -> 30000000 | H23: =Assumptions!C7 -> 30000000 | I23: =Assumptions!C7 -> 30000000 | J23: =Assumptions!C7 -> 30000000 | K23: =Assumptions!C7 -> 30000000 | L23: =Assumptions!C7 -> 30000000
B24: Pre-F option pool | D24: =Assumptions!C24+Assumptions!C25 -> 4394667 | E24: =Assumptions!C24+Assumptions!C25 -> 4394667 | F24: =Assumptions!C24+Assumptions!C25 -> 4394667 | G24: =Assumptions!C24+Assumptions!C25 -> 4394667 | H24: =Assumptions!C24+Assumptions!C25 -> 4394667 | I24: =Assumptions!C24+Assumptions!C25 -> 4394667 | J24: =Assumptions!C24+Assumptions!C25 -> 4394667 | K24: =Assumptions!C24+Assumptions!C25 -> 4394667 | L24: =Assumptions!C24+Assumptions!C25 -> 4394667
B26: Iter 0: ESOP top-up | D26: =0*D21 -> 0 | E26: =0*E21 -> 0 | F26: =0*F21 -> 0 | G26: =0*G21 -> 0 | H26: =0*H21 -> 0 | I26: =0*I21 -> 0 | J26: =0*J21 -> 0 | K26: =0*K21 -> 0 | L26: =0*L21 -> 0
B27: Iter 0: F PPS ($) | D27: =D21/D22 -> 32.770803 | E27: =E21/E22 -> 38.232604 | F27: =F21/F22 -> 49.156205 | G27: =G21/G22 -> 32.770803 | H27: =H21/H22 -> 38.232604 | I27: =I21/I22 -> 49.156205 | J27: =J21/J22 -> 32.770803 | K27: =K21/K22 -> 38.232604 | L27: =L21/L22 -> 49.156205
B28: Iter 0: Note A shares | D28: =0*D21 -> 0 | E28: =0*E21 -> 0 | F28: =0*F21 -> 0 | G28: =0*G21 -> 0 | H28: =0*H21 -> 0 | I28: =0*I21 -> 0 | J28: =0*J21 -> 0 | K28: =0*K21 -> 0 | L28: =0*L21 -> 0
B29: Iter 0: Note B shares | D29: =0*D21 -> 0 | E29: =0*E21 -> 0 | F29: =0*F21 -> 0 | G29: =0*G21 -> 0 | H29: =0*H21 -> 0 | I29: =0*I21 -> 0 | J29: =0*J21 -> 0 | K29: =0*K21 -> 0 | L29: =0*L21 -> 0
B30: Iter 0: F primary shares | D30: =D23/D27 -> 915449.03 | E30: =E23/E27 -> 784670.59 | F30: =F23/F27 -> 610299.35 | G30: =G23/G27 -> 915449.03 | H30: =H23/H27 -> 784670.59 | I30: =I23/I27 -> 610299.35 | J30: =J23/J27 -> 915449.03 | K30: =K23/K27 -> 784670.59 | L30: =L23/L27 -> 610299.35
B31: Iter 0: AD-E extra shares | D31: =Assumptions!C48/(Assumptions!C20*(D22+D23/Assumptions!C20)/(D22+D23/D27))-Assumptions!C46 -> 50091.764 | E31: =Assumptions!C48/(Assumptions!C20*(E22+E23/Assumptions!C20)/(E22+E23/E27))-Assumptions!C46 -> 28653.58 | F31: =Assumptions!C48/(Assumptions!C20*(F22+F23/Assumptions!C20)/(F22+F23/F27))-Assumptions!C46 -> 69.334613 | G31: =Assumptions!C48/(Assumptions!C20*(G22+G23/Assumptions!C20)/(G22+G23/G27))-Assumptions!C46 -> 50091.764 | H31: =Assumptions!C48/(Assumptions!C20*(H22+H23/Assumptions!C20)/(H22+H23/H27))-Assumptions!C46 -> 28653.58 | I31: =Assumptions!C48/(Assumptions!C20*(I22+I23/Assumptions!C20)/(I22+I23/I27))-Assumptions!C46 -> 69.334613 | J31: =Assumptions!C48/(Assumptions!C20*(J22+J23/Assumptions!C20)/(J22+J23/J27))-Assumptions!C46 -> 50091.764 | K31: =Assumptions!C48/(Assumptions!C20*(K22+K23/Assumptions!C20)/(K22+K23/K27))-Assumptions!C46 -> 28653.58 | L31: =Assumptions!C48/(Assumptions!C20*(L22+L23/Assumptions!C20)/(L22+L23/L27))-Assumptions!C46 -> 69.334613
B32: Iter 0: AD-D extra shares | D32: =Assumptions!C47/(Assumptions!C19*(D22+D23/Assumptions!C19)/(D22+D23/D27))-Assumptions!C45 -> 18499.98 | E32: =Assumptions!C47/(Assumptions!C19*(E22+E23/Assumptions!C19)/(E22+E23/E27))-Assumptions!C45 -> 12440.304 | F32: =Assumptions!C47/(Assumptions!C19*(F22+F23/Assumptions!C19)/(F22+F23/F27))-Assumptions!C45 -> 4360.7361 | G32: =Assumptions!C47/(Assumptions!C19*(G22+G23/Assumptions!C19)/(G22+G23/G27))-Assumptions!C45 -> 18499.98 | H32: =Assumptions!C47/(Assumptions!C19*(H22+H23/Assumptions!C19)/(H22+H23/H27))-Assumptions!C45 -> 12440.304 | I32: =Assumptions!C47/(Assumptions!C19*(I22+I23/Assumptions!C19)/(I22+I23/I27))-Assumptions!C45 -> 4360.7361 | J32: =Assumptions!C47/(Assumptions!C19*(J22+J23/Assumptions!C19)/(J22+J23/J27))-Assumptions!C45 -> 18499.98 | K32: =Assumptions!C47/(Assumptions!C19*(K22+K23/Assumptions!C19)/(K22+K23/K27))-Assumptions!C45 -> 12440.304 | L32: =Assumptions!C47/(Assumptions!C19*(L22+L23/Assumptions!C19)/(L22+L23/L27))-Assumptions!C45 -> 4360.7361
B33: Iter 0: T_F (post-F FD) | D33: =D22+D26+D30+D28+D29+D31+D32 -> 37602002 | E33: =E22+E26+E30+E28+E29+E31+E32 -> 37443725 | F33: =F22+F26+F30+F28+F29+F31+F32 -> 37232690 | G33: =G22+G26+G30+G28+G29+G31+G32 -> 37602002 | H33: =H22+H26+H30+H28+H29+H31+H32 -> 37443725 | I33: =I22+I26+I30+I28+I29+I31+I32 -> 37232690 | J33: =J22+J26+J30+J28+J29+J31+J32 -> 37602002 | K33: =K22+K26+K30+K28+K29+K31+K32 -> 37443725 | L33: =L22+L26+L30+L28+L29+L31+L32 -> 37232690
B34: Iter 1: ESOP top-up | D34: =MAX(0,D20*D33-D24) -> 0 | E34: =MAX(0,E20*E33-E24) -> 0 | F34: =MAX(0,F20*F33-F24) -> 0 | G34: =MAX(0,G20*G33-G24) -> 493593.23 | H34: =MAX(0,H20*H33-H24) -> 473017.31 | I34: =MAX(0,I20*I33-I24) -> 445582.75 | J34: =MAX(0,J20*J33-J24) -> 1245633.3 | K34: =MAX(0,K20*K33-K24) -> 1221891.8 | L34: =MAX(0,L20*L33-L24) -> 1190236.6
B35: Iter 1: F PPS ($) | D35: =D21/(D22+D34+D28+D29) -> 32.770803 | E35: =E21/(E22+E34+E28+E29) -> 38.232604 | F35: =F21/(F22+F34+F28+F29) -> 49.156205 | G35: =G21/(G22+G34+G28+G29) -> 32.334943 | H35: =H21/(H22+H34+H28+H29) -> 37.745028 | I35: =I21/(I22+I34+I28+I29) -> 48.565243 | J35: =J21/(J22+J34+J28+J29) -> 31.692712 | K35: =K21/(K22+K34+K28+K29) -> 36.99803 | L35: =L21/(L22+L34+L28+L29) -> 47.608723
B36: Iter 1: Note A shares | D36: =Assumptions!C29/MIN(Assumptions!C30/(D22+D34+D29),D35*(1-Assumptions!C31)) -> 190718.55 | E36: =Assumptions!C29/MIN(Assumptions!C30/(E22+E34+E29),E35*(1-Assumptions!C31)) -> 183089.81 | F36: =Assumptions!C29/MIN(Assumptions!C30/(F22+F34+F29),F35*(1-Assumptions!C31)) -> 183089.81 | G36: =Assumptions!C29/MIN(Assumptions!C30/(G22+G34+G29),G35*(1-Assumptions!C31)) -> 193289.34 | H36: =Assumptions!C29/MIN(Assumptions!C30/(H22+H34+H29),H35*(1-Assumptions!C31)) -> 185454.89 | I36: =Assumptions!C29/MIN(Assumptions!C30/(I22+I34+I29),I35*(1-Assumptions!C31)) -> 185317.72 | J36: =Assumptions!C29/MIN(Assumptions!C30/(J22+J34+J29),J35*(1-Assumptions!C31)) -> 197206.22 | K36: =Assumptions!C29/MIN(Assumptions!C30/(K22+K34+K29),K35*(1-Assumptions!C31)) -> 189199.26 | L36: =Assumptions!C29/MIN(Assumptions!C30/(L22+L34+L29),L35*(1-Assumptions!C31)) -> 189040.99
B37: Iter 1: Note B shares | D37: =Assumptions!C32/MIN(Assumptions!C33/(D22+D34+D36),D35*(1-Assumptions!C34)) -> 107699.89 | E37: =Assumptions!C32/MIN(Assumptions!C33/(E22+E34+E36),E35*(1-Assumptions!C34)) -> 92314.187 | F37: =Assumptions!C32/MIN(Assumptions!C33/(F22+F34+F36),F35*(1-Assumptions!C34)) -> 71799.924 | G37: =Assumptions!C32/MIN(Assumptions!C33/(G22+G34+G36),G35*(1-Assumptions!C34)) -> 109151.63 | H37: =Assumptions!C32/MIN(Assumptions!C33/(H22+H34+H36),H35*(1-Assumptions!C34)) -> 93506.668 | I37: =Assumptions!C32/MIN(Assumptions!C33/(I22+I34+I36),I35*(1-Assumptions!C34)) -> 72673.615 | J37: =Assumptions!C32/MIN(Assumptions!C33/(J22+J34+J36),J35*(1-Assumptions!C34)) -> 111363.51 | K37: =Assumptions!C32/MIN(Assumptions!C33/(K22+K34+K36),K35*(1-Assumptions!C34)) -> 95394.587 | L37: =Assumptions!C32/MIN(Assumptions!C33/(L22+L34+L36),L35*(1-Assumptions!C34)) -> 74133.721
B38: Iter 1: F primary shares | D38: =D23/D35 -> 915449.03 | E38: =E23/E35 -> 784670.59 | F38: =F23/F35 -> 610299.35 | G38: =G23/G35 -> 927788.86 | H38: =H23/H35 -> 794806.68 | I38: =I23/I35 -> 617725.73 | J38: =J23/J35 -> 946589.86 | K38: =K23/K35 -> 810853.99 | L38: =L23/L35 -> 630136.63
B39: Iter 1: AD-E extra shares | D39: =Assumptions!C48/(Assumptions!C20*(D22+D23/Assumptions!C20)/(D22+D23/D35))-Assumptions!C46 -> 50091.764 | E39: =Assumptions!C48/(Assumptions!C20*(E22+E23/Assumptions!C20)/(E22+E23/E35))-Assumptions!C46 -> 28653.58 | F39: =Assumptions!C48/(Assumptions!C20*(F22+F23/Assumptions!C20)/(F22+F23/F35))-Assumptions!C46 -> 69.334613 | G39: =Assumptions!C48/(Assumptions!C20*(G22+G23/Assumptions!C20)/(G22+G23/G35))-Assumptions!C46 -> 52114.601 | H39: =Assumptions!C48/(Assumptions!C20*(H22+H23/Assumptions!C20)/(H22+H23/H35))-Assumptions!C46 -> 30315.163 | I39: =Assumptions!C48/(Assumptions!C20*(I22+I23/Assumptions!C20)/(I22+I23/I35))-Assumptions!C46 -> 1286.7225 | J39: =Assumptions!C48/(Assumptions!C20*(J22+J23/Assumptions!C20)/(J22+J23/J35))-Assumptions!C46 -> 55196.603 | K39: =Assumptions!C48/(Assumptions!C20*(K22+K23/Assumptions!C20)/(K22+K23/K35))-Assumptions!C46 -> 32945.759 | L39: =Assumptions!C48/(Assumptions!C20*(L22+L23/Assumptions!C20)/(L22+L23/L35))-Assumptions!C46 -> 3321.21
B40: Iter 1: AD-D extra shares | D40: =Assumptions!C47/(Assumptions!C19*(D22+D23/Assumptions!C19)/(D22+D23/D35))-Assumptions!C45 -> 18499.98 | E40: =Assumptions!C47/(Assumptions!C19*(E22+E23/Assumptions!C19)/(E22+E23/E35))-Assumptions!C45 -> 12440.304 | F40: =Assumptions!C47/(Assumptions!C19*(F22+F23/Assumptions!C19)/(F22+F23/F35))-Assumptions!C45 -> 4360.7361 | G40: =Assumptions!C47/(Assumptions!C19*(G22+G23/Assumptions!C19)/(G22+G23/G35))-Assumptions!C45 -> 19071.751 | H40: =Assumptions!C47/(Assumptions!C19*(H22+H23/Assumptions!C19)/(H22+H23/H35))-Assumptions!C45 -> 12909.964 | I40: =Assumptions!C47/(Assumptions!C19*(I22+I23/Assumptions!C19)/(I22+I23/I35))-Assumptions!C45 -> 4704.8407 | J40: =Assumptions!C47/(Assumptions!C19*(J22+J23/Assumptions!C19)/(J22+J23/J35))-Assumptions!C45 -> 19942.904 | K40: =Assumptions!C47/(Assumptions!C19*(K22+K23/Assumptions!C19)/(K22+K23/K35))-Assumptions!C45 -> 13653.523 | L40: =Assumptions!C47/(Assumptions!C19*(L22+L23/Assumptions!C19)/(L22+L23/L35))-Assumptions!C45 -> 5279.905
B41: Iter 1: T_F (post-F FD) | D41: =D22+D34+D38+D36+D37+D39+D40 -> 37900420 | E41: =E22+E34+E38+E36+E37+E39+E40 -> 37719129 | F41: =F22+F34+F38+F36+F37+F39+F40 -> 37487580 | G41: =G22+G34+G38+G36+G37+G39+G40 -> 38412970 | H41: =H22+H34+H38+H36+H37+H39+H40 -> 38207972 | I41: =I22+I34+I38+I36+I37+I39+I40 -> 37945252 | J41: =J22+J34+J38+J36+J37+J39+J40 -> 39193893 | K41: =K22+K34+K38+K36+K37+K39+K40 -> 38981900 | L41: =L22+L34+L38+L36+L37+L39+L40 -> 38710110
B42: Iter 2: ESOP top-up | D42: =MAX(0,D20*D41-D24) -> 0 | E42: =MAX(0,E20*E41-E24) -> 0 | F42: =MAX(0,F20*F41-F24) -> 0 | G42: =MAX(0,G20*G41-G24) -> 599019.15 | H42: =MAX(0,H20*H41-H24) -> 572369.32 | I42: =MAX(0,I20*I41-I24) -> 538215.81 | J42: =MAX(0,J20*J41-J24) -> 1484417 | K42: =MAX(0,K20*K41-K24) -> 1452618 | L42: =MAX(0,L20*L41-L24) -> 1411849.5
B43: Iter 2: F PPS ($) | D43: =D21/(D22+D42+D36+D37) -> 32.505896 | E43: =E21/(E22+E42+E36+E37) -> 37.947203 | F43: =F21/(F22+F42+F36+F37) -> 48.816405 | G43: =G21/(G22+G42+G36+G37) -> 31.983436 | H43: =H21/(H22+H42+H36+H37) -> 37.36393 | I43: =I21/(I22+I42+I36+I37) -> 48.110117 | J43: =J21/(J22+J42+J36+J37) -> 31.241093 | K43: =K21/(K22+K42+K36+K37) -> 36.500944 | L43: =L21/(L22+L42+L36+L37) -> 47.005998
B44: Iter 2: Note A shares | D44: =Assumptions!C29/MIN(Assumptions!C30/(D22+D42+D37),D43*(1-Assumptions!C31)) -> 192272.81 | E44: =Assumptions!C29/MIN(Assumptions!C30/(E22+E42+E37),E43*(1-Assumptions!C31)) -> 183551.38 | F44: =Assumptions!C29/MIN(Assumptions!C30/(F22+F42+F37),F43*(1-Assumptions!C31)) -> 183448.8 | G44: =Assumptions!C29/MIN(Assumptions!C30/(G22+G42+G37),G43*(1-Assumptions!C31)) -> 195413.65 | H44: =Assumptions!C29/MIN(Assumptions!C30/(H22+H42+H37),H43*(1-Assumptions!C31)) -> 186419.18 | I44: =Assumptions!C29/MIN(Assumptions!C30/(I22+I42+I37),I43*(1-Assumptions!C31)) -> 186144.25 | J44: =Assumptions!C29/MIN(Assumptions!C30/(J22+J42+J37),J43*(1-Assumptions!C31)) -> 200057.02 | K44: =Assumptions!C29/MIN(Assumptions!C30/(K22+K42+K37),K43*(1-Assumptions!C31)) -> 190829.87 | L44: =Assumptions!C29/MIN(Assumptions!C30/(L22+L42+L37),L43*(1-Assumptions!C31)) -> 190519.72
B45: Iter 2: Note B shares | D45: =Assumptions!C32/MIN(Assumptions!C33/(D22+D42+D44),D43*(1-Assumptions!C34)) -> 108577.59 | E45: =Assumptions!C32/MIN(Assumptions!C33/(E22+E42+E44),E43*(1-Assumptions!C34)) -> 93008.483 | F45: =Assumptions!C32/MIN(Assumptions!C33/(F22+F42+F44),F43*(1-Assumptions!C34)) -> 72299.707 | G45: =Assumptions!C32/MIN(Assumptions!C33/(G22+G42+G44),G43*(1-Assumptions!C34)) -> 110351.24 | H45: =Assumptions!C32/MIN(Assumptions!C33/(H22+H42+H44),H43*(1-Assumptions!C34)) -> 94460.4 | I45: =Assumptions!C32/MIN(Assumptions!C33/(I22+I42+I44),I43*(1-Assumptions!C34)) -> 73361.114 | J45: =Assumptions!C32/MIN(Assumptions!C33/(J22+J42+J44),J43*(1-Assumptions!C34)) -> 112973.38 | K45: =Assumptions!C32/MIN(Assumptions!C33/(K22+K42+K44),K43*(1-Assumptions!C34)) -> 96693.713 | L45: =Assumptions!C32/MIN(Assumptions!C33/(L22+L42+L44),L43*(1-Assumptions!C34)) -> 75084.285
B46: Iter 2: F primary shares | D46: =D23/D43 -> 922909.49 | E46: =E23/E43 -> 790572.11 | F46: =F23/F43 -> 614547.51 | G46: =G23/G43 -> 937985.53 | H46: =H23/H43 -> 802913.4 | I46: =I23/I43 -> 623569.47 | J46: =J23/J43 -> 960273.69 | K46: =K23/K43 -> 821896.56 | L46: =L23/L43 -> 638216.42
B47: Iter 2: AD-E extra shares | D47: =Assumptions!C48/(Assumptions!C20*(D22+D23/Assumptions!C20)/(D22+D23/D43))-Assumptions!C46 -> 51314.738 | E47: =Assumptions!C48/(Assumptions!C20*(E22+E23/Assumptions!C20)/(E22+E23/E43))-Assumptions!C46 -> 29621 | F47: =Assumptions!C48/(Assumptions!C20*(F22+F23/Assumptions!C20)/(F22+F23/F43))-Assumptions!C46 -> 765.72529 | G47: =Assumptions!C48/(Assumptions!C20*(G22+G23/Assumptions!C20)/(G22+G23/G43))-Assumptions!C46 -> 53786.117 | H47: =Assumptions!C48/(Assumptions!C20*(H22+H23/Assumptions!C20)/(H22+H23/H43))-Assumptions!C46 -> 31644.077 | I47: =Assumptions!C48/(Assumptions!C20*(I22+I23/Assumptions!C20)/(I22+I23/I43))-Assumptions!C46 -> 2244.6723 | J47: =Assumptions!C48/(Assumptions!C20*(J22+J23/Assumptions!C20)/(J22+J23/J43))-Assumptions!C46 -> 57439.76 | K47: =Assumptions!C48/(Assumptions!C20*(K22+K23/Assumptions!C20)/(K22+K23/K43))-Assumptions!C46 -> 34755.94 | L47: =Assumptions!C48/(Assumptions!C20*(L22+L23/Assumptions!C20)/(L22+L23/L43))-Assumptions!C46 -> 4645.7106
B48: Iter 2: AD-D extra shares | D48: =Assumptions!C47/(Assumptions!C19*(D22+D23/Assumptions!C19)/(D22+D23/D43))-Assumptions!C45 -> 18845.664 | E48: =Assumptions!C47/(Assumptions!C19*(E22+E23/Assumptions!C19)/(E22+E23/E43))-Assumptions!C45 -> 12713.753 | F48: =Assumptions!C47/(Assumptions!C19*(F22+F23/Assumptions!C19)/(F22+F23/F43))-Assumptions!C45 -> 4557.5766 | G48: =Assumptions!C47/(Assumptions!C19*(G22+G23/Assumptions!C19)/(G22+G23/G43))-Assumptions!C45 -> 19544.219 | H48: =Assumptions!C47/(Assumptions!C19*(H22+H23/Assumptions!C19)/(H22+H23/H43))-Assumptions!C45 -> 13285.592 | I48: =Assumptions!C47/(Assumptions!C19*(I22+I23/Assumptions!C19)/(I22+I23/I43))-Assumptions!C45 -> 4975.6129 | J48: =Assumptions!C47/(Assumptions!C19*(J22+J23/Assumptions!C19)/(J22+J23/J43))-Assumptions!C45 -> 20576.95 | K48: =Assumptions!C47/(Assumptions!C19*(K22+K23/Assumptions!C19)/(K22+K23/K43))-Assumptions!C45 -> 14165.185 | L48: =Assumptions!C47/(Assumptions!C19*(L22+L23/Assumptions!C19)/(L22+L23/L43))-Assumptions!C45 -> 5654.2858
B49: Iter 2: T_F (post-F FD) | D49: =D22+D42+D46+D44+D45+D47+D48 -> 37911881 | E49: =E22+E42+E46+E44+E45+E47+E48 -> 37727428 | F49: =F22+F42+F46+F44+F45+F47+F48 -> 37493580 | G49: =G22+G42+G46+G44+G45+G47+G48 -> 38534061 | H49: =H22+H42+H46+H44+H45+H47+H48 -> 38319053 | I49: =I22+I42+I46+I44+I45+I47+I48 -> 38046472 | J49: =J22+J42+J46+J44+J45+J47+J48 -> 39453699 | K49: =K22+K42+K46+K44+K45+K47+K48 -> 39228920 | L49: =L22+L42+L46+L44+L45+L47+L48 -> 38943931
B50: Iter 3: ESOP top-up | D50: =MAX(0,D20*D49-D24) -> 0 | E50: =MAX(0,E20*E49-E24) -> 0 | F50: =MAX(0,F20*F49-F24) -> 0 | G50: =MAX(0,G20*G49-G24) -> 614760.92 | H50: =MAX(0,H20*H49-H24) -> 586809.89 | I50: =MAX(0,I20*I49-I24) -> 551374.35 | J50: =MAX(0,J20*J49-J24) -> 1523387.8 | K50: =MAX(0,K20*K49-K24) -> 1489671 | L50: =MAX(0,L20*L49-L24) -> 1446922.6
B51: Iter 3: F PPS ($) | D51: =D21/(D22+D50+D44+D45) -> 32.503755 | E51: =E21/(E22+E50+E44+E45) -> 37.946014 | F51: =F21/(F22+F50+F44+F45) -> 48.815268 | G51: =G21/(G22+G50+G44+G45) -> 31.967192 | H51: =H21/(H22+H50+H44+H45) -> 37.347625 | I51: =I21/(I22+I50+I44+I45) -> 48.091257 | J51: =J21/(J22+J50+J44+J45) -> 31.205809 | K51: =K21/(K22+K50+K44+K45) -> 36.462933 | L51: =L21/(L22+L50+L44+L45) -> 46.960008
B52: Iter 3: Note A shares | D52: =Assumptions!C29/MIN(Assumptions!C30/(D22+D50+D45),D51*(1-Assumptions!C31)) -> 192285.48 | E52: =Assumptions!C29/MIN(Assumptions!C30/(E22+E50+E45),E51*(1-Assumptions!C31)) -> 183554.85 | F52: =Assumptions!C29/MIN(Assumptions!C30/(F22+F50+F45),F51*(1-Assumptions!C31)) -> 183451.3 | G52: =Assumptions!C29/MIN(Assumptions!C30/(G22+G50+G45),G51*(1-Assumptions!C31)) -> 195512.95 | H52: =Assumptions!C29/MIN(Assumptions!C30/(H22+H50+H45),H51*(1-Assumptions!C31)) -> 186496.16 | I52: =Assumptions!C29/MIN(Assumptions!C30/(I22+I50+I45),I51*(1-Assumptions!C31)) -> 186213.48 | J52: =Assumptions!C29/MIN(Assumptions!C30/(J22+J50+J45),J51*(1-Assumptions!C31)) -> 200283.23 | K52: =Assumptions!C29/MIN(Assumptions!C30/(K22+K50+K45),K51*(1-Assumptions!C31)) -> 191021.63 | L52: =Assumptions!C29/MIN(Assumptions!C30/(L22+L50+L45),L51*(1-Assumptions!C31)) -> 190699.84
B53: Iter 3: Note B shares | D53: =Assumptions!C32/MIN(Assumptions!C33/(D22+D50+D52),D51*(1-Assumptions!C34)) -> 108584.74 | E53: =Assumptions!C32/MIN(Assumptions!C33/(E22+E50+E52),E51*(1-Assumptions!C34)) -> 93011.397 | F53: =Assumptions!C32/MIN(Assumptions!C33/(F22+F50+F52),F51*(1-Assumptions!C34)) -> 72301.391 | G53: =Assumptions!C32/MIN(Assumptions!C33/(G22+G50+G52),G51*(1-Assumptions!C34)) -> 110407.31 | H53: =Assumptions!C32/MIN(Assumptions!C33/(H22+H50+H52),H51*(1-Assumptions!C34)) -> 94501.64 | I53: =Assumptions!C32/MIN(Assumptions!C33/(I22+I50+I52),I51*(1-Assumptions!C34)) -> 73389.884 | J53: =Assumptions!C32/MIN(Assumptions!C33/(J22+J50+J52),J51*(1-Assumptions!C34)) -> 113101.12 | K53: =Assumptions!C32/MIN(Assumptions!C33/(K22+K50+K52),K51*(1-Assumptions!C34)) -> 96794.51 | L53: =Assumptions!C32/MIN(Assumptions!C33/(L22+L50+L52),L51*(1-Assumptions!C34)) -> 75157.819
B54: Iter 3: F primary shares | D54: =D23/D51 -> 922970.28 | E54: =E23/E51 -> 790596.88 | F54: =F23/F51 -> 614561.83 | G54: =G23/G51 -> 938462.17 | H54: =H23/H51 -> 803263.94 | I54: =I23/I51 -> 623814.01 | J54: =J23/J51 -> 961359.48 | K54: =K23/K51 -> 822753.33 | L54: =L23/L51 -> 638841.46
B55: Iter 3: AD-E extra shares | D55: =Assumptions!C48/(Assumptions!C20*(D22+D23/Assumptions!C20)/(D22+D23/D51))-Assumptions!C46 -> 51324.705 | E55: =Assumptions!C48/(Assumptions!C20*(E22+E23/Assumptions!C20)/(E22+E23/E51))-Assumptions!C46 -> 29625.061 | F55: =Assumptions!C48/(Assumptions!C20*(F22+F23/Assumptions!C20)/(F22+F23/F51))-Assumptions!C46 -> 768.07159 | G55: =Assumptions!C48/(Assumptions!C20*(G22+G23/Assumptions!C20)/(G22+G23/G51))-Assumptions!C46 -> 53864.251 | H55: =Assumptions!C48/(Assumptions!C20*(H22+H23/Assumptions!C20)/(H22+H23/H51))-Assumptions!C46 -> 31701.541 | I55: =Assumptions!C48/(Assumptions!C20*(I22+I23/Assumptions!C20)/(I22+I23/I51))-Assumptions!C46 -> 2284.7596 | J55: =Assumptions!C48/(Assumptions!C20*(J22+J23/Assumptions!C20)/(J22+J23/J51))-Assumptions!C46 -> 57617.751 | K55: =Assumptions!C48/(Assumptions!C20*(K22+K23/Assumptions!C20)/(K22+K23/K51))-Assumptions!C46 -> 34896.389 | L55: =Assumptions!C48/(Assumptions!C20*(L22+L23/Assumptions!C20)/(L22+L23/L51))-Assumptions!C46 -> 4748.172
B56: Iter 3: AD-D extra shares | D56: =Assumptions!C47/(Assumptions!C19*(D22+D23/Assumptions!C19)/(D22+D23/D51))-Assumptions!C45 -> 18848.481 | E56: =Assumptions!C47/(Assumptions!C19*(E22+E23/Assumptions!C19)/(E22+E23/E51))-Assumptions!C45 -> 12714.901 | F56: =Assumptions!C47/(Assumptions!C19*(F22+F23/Assumptions!C19)/(F22+F23/F51))-Assumptions!C45 -> 4558.2398 | G56: =Assumptions!C47/(Assumptions!C19*(G22+G23/Assumptions!C19)/(G22+G23/G51))-Assumptions!C45 -> 19566.304 | H56: =Assumptions!C47/(Assumptions!C19*(H22+H23/Assumptions!C19)/(H22+H23/H51))-Assumptions!C45 -> 13301.835 | I56: =Assumptions!C47/(Assumptions!C19*(I22+I23/Assumptions!C19)/(I22+I23/I51))-Assumptions!C45 -> 4986.9439 | J56: =Assumptions!C47/(Assumptions!C19*(J22+J23/Assumptions!C19)/(J22+J23/J51))-Assumptions!C45 -> 20627.261 | K56: =Assumptions!C47/(Assumptions!C19*(K22+K23/Assumptions!C19)/(K22+K23/K51))-Assumptions!C45 -> 14204.884 | L56: =Assumptions!C47/(Assumptions!C19*(L22+L23/Assumptions!C19)/(L22+L23/L51))-Assumptions!C45 -> 5683.2473
B57: Iter 3: T_F (post-F FD) | D57: =D22+D50+D54+D52+D53+D55+D56 -> 37911975 | E57: =E22+E50+E54+E52+E53+E55+E56 -> 37727464 | F57: =F22+F50+F54+F52+F53+F55+F56 -> 37493602 | G57: =G22+G50+G54+G52+G53+G55+G56 -> 38550535 | H57: =H22+H50+H54+H52+H53+H55+H56 -> 38334036 | I57: =I22+I50+I54+I52+I53+I55+I56 -> 38060024 | J57: =J22+J50+J54+J52+J53+J55+J56 -> 39494338 | K57: =K22+K50+K54+K52+K53+K55+K56 -> 39267303 | L57: =L22+L50+L54+L52+L53+L55+L56 -> 38980014
B60: Final Values & $2B Exit Outcome
B61: F PPS final ($) | D61: =D51 -> 32.503755 | E61: =E51 -> 37.946014 | F61: =F51 -> 48.815268 | G61: =G51 -> 31.967192 | H61: =H51 -> 37.347625 | I61: =I51 -> 48.091257 | J61: =J51 -> 31.205809 | K61: =K51 -> 36.462933 | L61: =L51 -> 46.960008
B62: T_F (post-F FD) | D62: =D57 -> 37911975 | E62: =E57 -> 37727464 | F62: =F57 -> 37493602 | G62: =G57 -> 38550535 | H62: =H57 -> 38334036 | I62: =I57 -> 38060024 | J62: =J57 -> 39494338 | K62: =K57 -> 39267303 | L62: =L57 -> 38980014
B63: Note A branch | D63: =IF(Assumptions!C30/(D22+D50+D53)<D51*(1-Assumptions!C31),"cap","discount") -> discount | E63: =IF(Assumptions!C30/(E22+E50+E53)<E51*(1-Assumptions!C31),"cap","discount") -> cap | F63: =IF(Assumptions!C30/(F22+F50+F53)<F51*(1-Assumptions!C31),"cap","discount") -> cap | G63: =IF(Assumptions!C30/(G22+G50+G53)<G51*(1-Assumptions!C31),"cap","discount") -> discount | H63: =IF(Assumptions!C30/(H22+H50+H53)<H51*(1-Assumptions!C31),"cap","discount") -> cap | I63: =IF(Assumptions!C30/(I22+I50+I53)<I51*(1-Assumptions!C31),"cap","discount") -> cap | J63: =IF(Assumptions!C30/(J22+J50+J53)<J51*(1-Assumptions!C31),"cap","discount") -> discount | K63: =IF(Assumptions!C30/(K22+K50+K53)<K51*(1-Assumptions!C31),"cap","discount") -> cap | L63: =IF(Assumptions!C30/(L22+L50+L53)<L51*(1-Assumptions!C31),"cap","discount") -> cap
B64: Note B branch | D64: =IF(Assumptions!C33/(D22+D50+D52)<D51*(1-Assumptions!C34),"cap","discount") -> discount | E64: =IF(Assumptions!C33/(E22+E50+E52)<E51*(1-Assumptions!C34),"cap","discount") -> discount | F64: =IF(Assumptions!C33/(F22+F50+F52)<F51*(1-Assumptions!C34),"cap","discount") -> discount | G64: =IF(Assumptions!C33/(G22+G50+G52)<G51*(1-Assumptions!C34),"cap","discount") -> discount | H64: =IF(Assumptions!C33/(H22+H50+H52)<H51*(1-Assumptions!C34),"cap","discount") -> discount | I64: =IF(Assumptions!C33/(I22+I50+I52)<I51*(1-Assumptions!C34),"cap","discount") -> discount | J64: =IF(Assumptions!C33/(J22+J50+J52)<J51*(1-Assumptions!C34),"cap","discount") -> discount | K64: =IF(Assumptions!C33/(K22+K50+K52)<K51*(1-Assumptions!C34),"cap","discount") -> discount | L64: =IF(Assumptions!C33/(L22+L50+L52)<L51*(1-Assumptions!C34),"cap","discount") -> discount
B65: Our shares (=$10M / F_PPS) | D65: =Assumptions!C11/D51 -> 307656.76 | E65: =Assumptions!C11/E51 -> 263532.29 | F65: =Assumptions!C11/F51 -> 204853.94 | G65: =Assumptions!C11/G51 -> 312820.72 | H65: =Assumptions!C11/H51 -> 267754.65 | I65: =Assumptions!C11/I51 -> 207938 | J65: =Assumptions!C11/J51 -> 320453.16 | K65: =Assumptions!C11/K51 -> 274251.11 | L65: =Assumptions!C11/L51 -> 212947.15
B66: Always-in pool shares | D66: =Assumptions!C37+Assumptions!C38+Assumptions!C39+Assumptions!C40+D52+D53+Assumptions!C24 -> 11800870 | E66: =Assumptions!C37+Assumptions!C38+Assumptions!C39+Assumptions!C40+E52+E53+Assumptions!C24 -> 11776566 | F66: =Assumptions!C37+Assumptions!C38+Assumptions!C39+Assumptions!C40+F52+F53+Assumptions!C24 -> 11755753 | G66: =Assumptions!C37+Assumptions!C38+Assumptions!C39+Assumptions!C40+G52+G53+Assumptions!C24 -> 11805920 | H66: =Assumptions!C37+Assumptions!C38+Assumptions!C39+Assumptions!C40+H52+H53+Assumptions!C24 -> 11780998 | I66: =Assumptions!C37+Assumptions!C38+Assumptions!C39+Assumptions!C40+I52+I53+Assumptions!C24 -> 11759603 | J66: =Assumptions!C37+Assumptions!C38+Assumptions!C39+Assumptions!C40+J52+J53+Assumptions!C24 -> 11813384 | K66: =Assumptions!C37+Assumptions!C38+Assumptions!C39+Assumptions!C40+K52+K53+Assumptions!C24 -> 11787816 | L66: =Assumptions!C37+Assumptions!C38+Assumptions!C39+Assumptions!C40+L52+L53+Assumptions!C24 -> 11765858
B67: (see scenario detail for $2B waterfall)
B68: Our ownership % | D68: =D65/D62 -> 0.0081150287 | E68: =E65/E62 -> 0.0069851578 | F68: =F65/F62 -> 0.005463704 | G68: =G65/G62 -> 0.0081145625 | H68: =H65/H62 -> 0.0069847758 | I68: =I65/I62 -> 0.0054634228 | J68: =J65/J62 -> 0.0081139014 | K68: =K65/K62 -> 0.0069842106 | L68: =L65/L62 -> 0.005462983
B69: Our $ proceeds @ $2B | D69: =IF(D76="convert",D65*D75,Assumptions!C11) -> 17075671 | E69: =IF(E76="convert",E65*E75,Assumptions!C11) -> 14703173 | F69: =IF(F76="convert",F65*F75,Assumptions!C11) -> 11505506 | G69: =IF(G76="convert",G65*G75,Assumptions!C11) -> 17350600 | H69: =IF(H76="convert",H65*H75,Assumptions!C11) -> 14930354 | I69: =IF(I76="convert",I65*I75,Assumptions!C11) -> 11673682 | J69: =IF(J76="convert",J65*J75,Assumptions!C11) -> 17756273 | K69: =IF(K76="convert",K65*K75,Assumptions!C11) -> 15279393 | L69: =IF(L76="convert",L65*L75,Assumptions!C11) -> 11946526
B70: $2B Exit Waterfall (per-scenario)
B71: Iter 0 p (all preference) | D71: =(Assumptions!C62+Assumptions!C24*Assumptions!C26-(Assumptions!C7+Assumptions!C48+Assumptions!C47+Assumptions!C49+Assumptions!C50+Assumptions!C51+Assumptions!C52))/D66 -> 123.93154 | E71: =(Assumptions!C62+Assumptions!C24*Assumptions!C26-(Assumptions!C7+Assumptions!C48+Assumptions!C47+Assumptions!C49+Assumptions!C50+Assumptions!C51+Assumptions!C52))/E66 -> 124.1873 | F71: =(Assumptions!C62+Assumptions!C24*Assumptions!C26-(Assumptions!C7+Assumptions!C48+Assumptions!C47+Assumptions!C49+Assumptions!C50+Assumptions!C51+Assumptions!C52))/F66 -> 124.40718 | G71: =(Assumptions!C62+Assumptions!C24*Assumptions!C26-(Assumptions!C7+Assumptions!C48+Assumptions!C47+Assumptions!C49+Assumptions!C50+Assumptions!C51+Assumptions!C52))/G66 -> 123.87853 | H71: =(Assumptions!C62+Assumptions!C24*Assumptions!C26-(Assumptions!C7+Assumptions!C48+Assumptions!C47+Assumptions!C49+Assumptions!C50+Assumptions!C51+Assumptions!C52))/H66 -> 124.14059 | I71: =(Assumptions!C62+Assumptions!C24*Assumptions!C26-(Assumptions!C7+Assumptions!C48+Assumptions!C47+Assumptions!C49+Assumptions!C50+Assumptions!C51+Assumptions!C52))/I66 -> 124.36644 | J71: =(Assumptions!C62+Assumptions!C24*Assumptions!C26-(Assumptions!C7+Assumptions!C48+Assumptions!C47+Assumptions!C49+Assumptions!C50+Assumptions!C51+Assumptions!C52))/J66 -> 123.80026 | K71: =(Assumptions!C62+Assumptions!C24*Assumptions!C26-(Assumptions!C7+Assumptions!C48+Assumptions!C47+Assumptions!C49+Assumptions!C50+Assumptions!C51+Assumptions!C52))/K66 -> 124.06878 | L71: =(Assumptions!C62+Assumptions!C24*Assumptions!C26-(Assumptions!C7+Assumptions!C48+Assumptions!C47+Assumptions!C49+Assumptions!C50+Assumptions!C51+Assumptions!C52))/L66 -> 124.30033
B72: Iter 1 p | D72: =(Assumptions!C62+Assumptions!C24*Assumptions!C26-(IF((Assumptions!C7/D54)>D71,Assumptions!C7,0)+IF((Assumptions!C48/(Assumptions!C46+D55))>D71,Assumptions!C48,0)+IF((Assumptions!C47/(Assumptions!C45+D56))>D71,Assumptions!C47,0)+IF((Assumptions!C49/Assumptions!C44)>D71,Assumptions!C49,0)+IF((Assumptions!C50/Assumptions!C43)>D71,Assumptions!C50,0)+IF((Assumptions!C51/Assumptions!C42)>D71,Assumptions!C51,0)+IF((Assumptions!C52/Assumptions!C41)>D71,Assumptions!C52,0)))/(D66+(IF((Assumptions!C7/D54)<=D71,D54,0)+IF((Assumptions!C48/(Assumptions!C46+D55))<=D71,(Assumptions!C46+D55),0)+IF((Assumptions!C47/(Assumptions!C45+D56))<=D71,(Assumptions!C45+D56),0)+IF((Assumptions!C49/Assumptions!C44)<=D71,Assumptions!C44,0)+IF((Assumptions!C50/Assumptions!C43)<=D71,Assumptions!C43,0)+IF((Assumptions!C51/Assumptions!C42)<=D71,Assumptions!C42,0)+IF((Assumptions!C52/Assumptions!C41)<=D71,Assumptions!C41,0))) -> 55.59827 | E72: =(Assumptions!C62+Assumptions!C24*Assumptions!C26-(IF((Assumptions!C7/E54)>E71,Assumptions!C7,0)+IF((Assumptions!C48/(Assumptions!C46+E55))>E71,Assumptions!C48,0)+IF((Assumptions!C47/(Assumptions!C45+E56))>E71,Assumptions!C47,0)+IF((Assumptions!C49/Assumptions!C44)>E71,Assumptions!C49,0)+IF((Assumptions!C50/Assumptions!C43)>E71,Assumptions!C50,0)+IF((Assumptions!C51/Assumptions!C42)>E71,Assumptions!C51,0)+IF((Assumptions!C52/Assumptions!C41)>E71,Assumptions!C52,0)))/(E66+(IF((Assumptions!C7/E54)<=E71,E54,0)+IF((Assumptions!C48/(Assumptions!C46+E55))<=E71,(Assumptions!C46+E55),0)+IF((Assumptions!C47/(Assumptions!C45+E56))<=E71,(Assumptions!C45+E56),0)+IF((Assumptions!C49/Assumptions!C44)<=E71,Assumptions!C44,0)+IF((Assumptions!C50/Assumptions!C43)<=E71,Assumptions!C43,0)+IF((Assumptions!C51/Assumptions!C42)<=E71,Assumptions!C42,0)+IF((Assumptions!C52/Assumptions!C41)<=E71,Assumptions!C41,0))) -> 55.884557 | F72: =(Assumptions!C62+Assumptions!C24*Assumptions!C26-(IF((Assumptions!C7/F54)>F71,Assumptions!C7,0)+IF((Assumptions!C48/(Assumptions!C46+F55))>F71,Assumptions!C48,0)+IF((Assumptions!C47/(Assumptions!C45+F56))>F71,Assumptions!C47,0)+IF((Assumptions!C49/Assumptions!C44)>F71,Assumptions!C49,0)+IF((Assumptions!C50/Assumptions!C43)>F71,Assumptions!C50,0)+IF((Assumptions!C51/Assumptions!C42)>F71,Assumptions!C51,0)+IF((Assumptions!C52/Assumptions!C41)>F71,Assumptions!C52,0)))/(F66+(IF((Assumptions!C7/F54)<=F71,F54,0)+IF((Assumptions!C48/(Assumptions!C46+F55))<=F71,(Assumptions!C46+F55),0)+IF((Assumptions!C47/(Assumptions!C45+F56))<=F71,(Assumptions!C45+F56),0)+IF((Assumptions!C49/Assumptions!C44)<=F71,Assumptions!C44,0)+IF((Assumptions!C50/Assumptions!C43)<=F71,Assumptions!C43,0)+IF((Assumptions!C51/Assumptions!C42)<=F71,Assumptions!C42,0)+IF((Assumptions!C52/Assumptions!C41)<=F71,Assumptions!C41,0))) -> 56.251683 | G72: =(Assumptions!C62+Assumptions!C24*Assumptions!C26-(IF((Assumptions!C7/G54)>G71,Assumptions!C7,0)+IF((Assumptions!C48/(Assumptions!C46+G55))>G71,Assumptions!C48,0)+IF((Assumptions!C47/(Assumptions!C45+G56))>G71,Assumptions!C47,0)+IF((Assumptions!C49/Assumptions!C44)>G71,Assumptions!C49,0)+IF((Assumptions!C50/Assumptions!C43)>G71,Assumptions!C50,0)+IF((Assumptions!C51/Assumptions!C42)>G71,Assumptions!C51,0)+IF((Assumptions!C52/Assumptions!C41)>G71,Assumptions!C52,0)))/(G66+(IF((Assumptions!C7/G54)<=G71,G54,0)+IF((Assumptions!C48/(Assumptions!C46+G55))<=G71,(Assumptions!C46+G55),0)+IF((Assumptions!C47/(Assumptions!C45+G56))<=G71,(Assumptions!C45+G56),0)+IF((Assumptions!C49/Assumptions!C44)<=G71,Assumptions!C44,0)+IF((Assumptions!C50/Assumptions!C43)<=G71,Assumptions!C43,0)+IF((Assumptions!C51/Assumptions!C42)<=G71,Assumptions!C42,0)+IF((Assumptions!C52/Assumptions!C41)<=G71,Assumptions!C41,0))) -> 55.561556 | H72: =(Assumptions!C62+Assumptions!C24*Assumptions!C26-(IF((Assumptions!C7/H54)>H71,Assumptions!C7,0)+IF((Assumptions!C48/(Assumptions!C46+H55))>H71,Assumptions!C48,0)+IF((Assumptions!C47/(Assumptions!C45+H56))>H71,Assumptions!C47,0)+IF((Assumptions!C49/Assumptions!C44)>H71,Assumptions!C49,0)+IF((Assumptions!C50/Assumptions!C43)>H71,Assumptions!C50,0)+IF((Assumptions!C51/Assumptions!C42)>H71,Assumptions!C51,0)+IF((Assumptions!C52/Assumptions!C41)>H71,Assumptions!C52,0)))/(H66+(IF((Assumptions!C7/H54)<=H71,H54,0)+IF((Assumptions!C48/(Assumptions!C46+H55))<=H71,(Assumptions!C46+H55),0)+IF((Assumptions!C47/(Assumptions!C45+H56))<=H71,(Assumptions!C45+H56),0)+IF((Assumptions!C49/Assumptions!C44)<=H71,Assumptions!C44,0)+IF((Assumptions!C50/Assumptions!C43)<=H71,Assumptions!C43,0)+IF((Assumptions!C51/Assumptions!C42)<=H71,Assumptions!C42,0)+IF((Assumptions!C52/Assumptions!C41)<=H71,Assumptions!C41,0))) -> 55.853754 | I72: =(Assumptions!C62+Assumptions!C24*Assumptions!C26-(IF((Assumptions!C7/I54)>I71,Assumptions!C7,0)+IF((Assumptions!C48/(Assumptions!C46+I55))>I71,Assumptions!C48,0)+IF((Assumptions!C47/(Assumptions!C45+I56))>I71,Assumptions!C47,0)+IF((Assumptions!C49/Assumptions!C44)>I71,Assumptions!C49,0)+IF((Assumptions!C50/Assumptions!C43)>I71,Assumptions!C50,0)+IF((Assumptions!C51/Assumptions!C42)>I71,Assumptions!C51,0)+IF((Assumptions!C52/Assumptions!C41)>I71,Assumptions!C52,0)))/(I66+(IF((Assumptions!C7/I54)<=I71,I54,0)+IF((Assumptions!C48/(Assumptions!C46+I55))<=I71,(Assumptions!C46+I55),0)+IF((Assumptions!C47/(Assumptions!C45+I56))<=I71,(Assumptions!C45+I56),0)+IF((Assumptions!C49/Assumptions!C44)<=I71,Assumptions!C44,0)+IF((Assumptions!C50/Assumptions!C43)<=I71,Assumptions!C43,0)+IF((Assumptions!C51/Assumptions!C42)<=I71,Assumptions!C42,0)+IF((Assumptions!C52/Assumptions!C41)<=I71,Assumptions!C41,0))) -> 56.227915 | J72: =(Assumptions!C62+Assumptions!C24*Assumptions!C26-(IF((Assumptions!C7/J54)>J71,Assumptions!C7,0)+IF((Assumptions!C48/(Assumptions!C46+J55))>J71,Assumptions!C48,0)+IF((Assumptions!C47/(Assumptions!C45+J56))>J71,Assumptions!C47,0)+IF((Assumptions!C49/Assumptions!C44)>J71,Assumptions!C49,0)+IF((Assumptions!C50/Assumptions!C43)>J71,Assumptions!C50,0)+IF((Assumptions!C51/Assumptions!C42)>J71,Assumptions!C51,0)+IF((Assumptions!C52/Assumptions!C41)>J71,Assumptions!C52,0)))/(J66+(IF((Assumptions!C7/J54)<=J71,J54,0)+IF((Assumptions!C48/(Assumptions!C46+J55))<=J71,(Assumptions!C46+J55),0)+IF((Assumptions!C47/(Assumptions!C45+J56))<=J71,(Assumptions!C45+J56),0)+IF((Assumptions!C49/Assumptions!C44)<=J71,Assumptions!C44,0)+IF((Assumptions!C50/Assumptions!C43)<=J71,Assumptions!C43,0)+IF((Assumptions!C51/Assumptions!C42)<=J71,Assumptions!C42,0)+IF((Assumptions!C52/Assumptions!C41)<=J71,Assumptions!C41,0))) -> 55.507382 | K72: =(Assumptions!C62+Assumptions!C24*Assumptions!C26-(IF((Assumptions!C7/K54)>K71,Assumptions!C7,0)+IF((Assumptions!C48/(Assumptions!C46+K55))>K71,Assumptions!C48,0)+IF((Assumptions!C47/(Assumptions!C45+K56))>K71,Assumptions!C47,0)+IF((Assumptions!C49/Assumptions!C44)>K71,Assumptions!C49,0)+IF((Assumptions!C50/Assumptions!C43)>K71,Assumptions!C50,0)+IF((Assumptions!C51/Assumptions!C42)>K71,Assumptions!C51,0)+IF((Assumptions!C52/Assumptions!C41)>K71,Assumptions!C52,0)))/(K66+(IF((Assumptions!C7/K54)<=K71,K54,0)+IF((Assumptions!C48/(Assumptions!C46+K55))<=K71,(Assumptions!C46+K55),0)+IF((Assumptions!C47/(Assumptions!C45+K56))<=K71,(Assumptions!C45+K56),0)+IF((Assumptions!C49/Assumptions!C44)<=K71,Assumptions!C44,0)+IF((Assumptions!C50/Assumptions!C43)<=K71,Assumptions!C43,0)+IF((Assumptions!C51/Assumptions!C42)<=K71,Assumptions!C42,0)+IF((Assumptions!C52/Assumptions!C41)<=K71,Assumptions!C41,0))) -> 55.806426 | L72: =(Assumptions!C62+Assumptions!C24*Assumptions!C26-(IF((Assumptions!C7/L54)>L71,Assumptions!C7,0)+IF((Assumptions!C48/(Assumptions!C46+L55))>L71,Assumptions!C48,0)+IF((Assumptions!C47/(Assumptions!C45+L56))>L71,Assumptions!C47,0)+IF((Assumptions!C49/Assumptions!C44)>L71,Assumptions!C49,0)+IF((Assumptions!C50/Assumptions!C43)>L71,Assumptions!C50,0)+IF((Assumptions!C51/Assumptions!C42)>L71,Assumptions!C51,0)+IF((Assumptions!C52/Assumptions!C41)>L71,Assumptions!C52,0)))/(L66+(IF((Assumptions!C7/L54)<=L71,L54,0)+IF((Assumptions!C48/(Assumptions!C46+L55))<=L71,(Assumptions!C46+L55),0)+IF((Assumptions!C47/(Assumptions!C45+L56))<=L71,(Assumptions!C45+L56),0)+IF((Assumptions!C49/Assumptions!C44)<=L71,Assumptions!C44,0)+IF((Assumptions!C50/Assumptions!C43)<=L71,Assumptions!C43,0)+IF((Assumptions!C51/Assumptions!C42)<=L71,Assumptions!C42,0)+IF((Assumptions!C52/Assumptions!C41)<=L71,Assumptions!C41,0))) -> 56.189353
B73: Iter 2 p | D73: =(Assumptions!C62+Assumptions!C24*Assumptions!C26-(IF((Assumptions!C7/D54)>D72,Assumptions!C7,0)+IF((Assumptions!C48/(Assumptions!C46+D55))>D72,Assumptions!C48,0)+IF((Assumptions!C47/(Assumptions!C45+D56))>D72,Assumptions!C47,0)+IF((Assumptions!C49/Assumptions!C44)>D72,Assumptions!C49,0)+IF((Assumptions!C50/Assumptions!C43)>D72,Assumptions!C50,0)+IF((Assumptions!C51/Assumptions!C42)>D72,Assumptions!C51,0)+IF((Assumptions!C52/Assumptions!C41)>D72,Assumptions!C52,0)))/(D66+(IF((Assumptions!C7/D54)<=D72,D54,0)+IF((Assumptions!C48/(Assumptions!C46+D55))<=D72,(Assumptions!C46+D55),0)+IF((Assumptions!C47/(Assumptions!C45+D56))<=D72,(Assumptions!C45+D56),0)+IF((Assumptions!C49/Assumptions!C44)<=D72,Assumptions!C44,0)+IF((Assumptions!C50/Assumptions!C43)<=D72,Assumptions!C43,0)+IF((Assumptions!C51/Assumptions!C42)<=D72,Assumptions!C42,0)+IF((Assumptions!C52/Assumptions!C41)<=D72,Assumptions!C41,0))) -> 55.502343 | E73: =(Assumptions!C62+Assumptions!C24*Assumptions!C26-(IF((Assumptions!C7/E54)>E72,Assumptions!C7,0)+IF((Assumptions!C48/(Assumptions!C46+E55))>E72,Assumptions!C48,0)+IF((Assumptions!C47/(Assumptions!C45+E56))>E72,Assumptions!C47,0)+IF((Assumptions!C49/Assumptions!C44)>E72,Assumptions!C49,0)+IF((Assumptions!C50/Assumptions!C43)>E72,Assumptions!C50,0)+IF((Assumptions!C51/Assumptions!C42)>E72,Assumptions!C51,0)+IF((Assumptions!C52/Assumptions!C41)>E72,Assumptions!C52,0)))/(E66+(IF((Assumptions!C7/E54)<=E72,E54,0)+IF((Assumptions!C48/(Assumptions!C46+E55))<=E72,(Assumptions!C46+E55),0)+IF((Assumptions!C47/(Assumptions!C45+E56))<=E72,(Assumptions!C45+E56),0)+IF((Assumptions!C49/Assumptions!C44)<=E72,Assumptions!C44,0)+IF((Assumptions!C50/Assumptions!C43)<=E72,Assumptions!C43,0)+IF((Assumptions!C51/Assumptions!C42)<=E72,Assumptions!C42,0)+IF((Assumptions!C52/Assumptions!C41)<=E72,Assumptions!C41,0))) -> 55.79268 | F73: =(Assumptions!C62+Assumptions!C24*Assumptions!C26-(IF((Assumptions!C7/F54)>F72,Assumptions!C7,0)+IF((Assumptions!C48/(Assumptions!C46+F55))>F72,Assumptions!C48,0)+IF((Assumptions!C47/(Assumptions!C45+F56))>F72,Assumptions!C47,0)+IF((Assumptions!C49/Assumptions!C44)>F72,Assumptions!C49,0)+IF((Assumptions!C50/Assumptions!C43)>F72,Assumptions!C50,0)+IF((Assumptions!C51/Assumptions!C42)>F72,Assumptions!C51,0)+IF((Assumptions!C52/Assumptions!C41)>F72,Assumptions!C52,0)))/(F66+(IF((Assumptions!C7/F54)<=F72,F54,0)+IF((Assumptions!C48/(Assumptions!C46+F55))<=F72,(Assumptions!C46+F55),0)+IF((Assumptions!C47/(Assumptions!C45+F56))<=F72,(Assumptions!C45+F56),0)+IF((Assumptions!C49/Assumptions!C44)<=F72,Assumptions!C44,0)+IF((Assumptions!C50/Assumptions!C43)<=F72,Assumptions!C43,0)+IF((Assumptions!C51/Assumptions!C42)<=F72,Assumptions!C42,0)+IF((Assumptions!C52/Assumptions!C41)<=F72,Assumptions!C41,0))) -> 56.164435 | G73: =(Assumptions!C62+Assumptions!C24*Assumptions!C26-(IF((Assumptions!C7/G54)>G72,Assumptions!C7,0)+IF((Assumptions!C48/(Assumptions!C46+G55))>G72,Assumptions!C48,0)+IF((Assumptions!C47/(Assumptions!C45+G56))>G72,Assumptions!C47,0)+IF((Assumptions!C49/Assumptions!C44)>G72,Assumptions!C49,0)+IF((Assumptions!C50/Assumptions!C43)>G72,Assumptions!C50,0)+IF((Assumptions!C51/Assumptions!C42)>G72,Assumptions!C51,0)+IF((Assumptions!C52/Assumptions!C41)>G72,Assumptions!C52,0)))/(G66+(IF((Assumptions!C7/G54)<=G72,G54,0)+IF((Assumptions!C48/(Assumptions!C46+G55))<=G72,(Assumptions!C46+G55),0)+IF((Assumptions!C47/(Assumptions!C45+G56))<=G72,(Assumptions!C45+G56),0)+IF((Assumptions!C49/Assumptions!C44)<=G72,Assumptions!C44,0)+IF((Assumptions!C50/Assumptions!C43)<=G72,Assumptions!C43,0)+IF((Assumptions!C51/Assumptions!C42)<=G72,Assumptions!C42,0)+IF((Assumptions!C52/Assumptions!C41)<=G72,Assumptions!C41,0))) -> 55.464995 | H73: =(Assumptions!C62+Assumptions!C24*Assumptions!C26-(IF((Assumptions!C7/H54)>H72,Assumptions!C7,0)+IF((Assumptions!C48/(Assumptions!C46+H55))>H72,Assumptions!C48,0)+IF((Assumptions!C47/(Assumptions!C45+H56))>H72,Assumptions!C47,0)+IF((Assumptions!C49/Assumptions!C44)>H72,Assumptions!C49,0)+IF((Assumptions!C50/Assumptions!C43)>H72,Assumptions!C50,0)+IF((Assumptions!C51/Assumptions!C42)>H72,Assumptions!C51,0)+IF((Assumptions!C52/Assumptions!C41)>H72,Assumptions!C52,0)))/(H66+(IF((Assumptions!C7/H54)<=H72,H54,0)+IF((Assumptions!C48/(Assumptions!C46+H55))<=H72,(Assumptions!C46+H55),0)+IF((Assumptions!C47/(Assumptions!C45+H56))<=H72,(Assumptions!C45+H56),0)+IF((Assumptions!C49/Assumptions!C44)<=H72,Assumptions!C44,0)+IF((Assumptions!C50/Assumptions!C43)<=H72,Assumptions!C43,0)+IF((Assumptions!C51/Assumptions!C42)<=H72,Assumptions!C42,0)+IF((Assumptions!C52/Assumptions!C41)<=H72,Assumptions!C41,0))) -> 55.761324 | I73: =(Assumptions!C62+Assumptions!C24*Assumptions!C26-(IF((Assumptions!C7/I54)>I72,Assumptions!C7,0)+IF((Assumptions!C48/(Assumptions!C46+I55))>I72,Assumptions!C48,0)+IF((Assumptions!C47/(Assumptions!C45+I56))>I72,Assumptions!C47,0)+IF((Assumptions!C49/Assumptions!C44)>I72,Assumptions!C49,0)+IF((Assumptions!C50/Assumptions!C43)>I72,Assumptions!C50,0)+IF((Assumptions!C51/Assumptions!C42)>I72,Assumptions!C51,0)+IF((Assumptions!C52/Assumptions!C41)>I72,Assumptions!C52,0)))/(I66+(IF((Assumptions!C7/I54)<=I72,I54,0)+IF((Assumptions!C48/(Assumptions!C46+I55))<=I72,(Assumptions!C46+I55),0)+IF((Assumptions!C47/(Assumptions!C45+I56))<=I72,(Assumptions!C45+I56),0)+IF((Assumptions!C49/Assumptions!C44)<=I72,Assumptions!C44,0)+IF((Assumptions!C50/Assumptions!C43)<=I72,Assumptions!C43,0)+IF((Assumptions!C51/Assumptions!C42)<=I72,Assumptions!C42,0)+IF((Assumptions!C52/Assumptions!C41)<=I72,Assumptions!C41,0))) -> 56.140205 | J73: =(Assumptions!C62+Assumptions!C24*Assumptions!C26-(IF((Assumptions!C7/J54)>J72,Assumptions!C7,0)+IF((Assumptions!C48/(Assumptions!C46+J55))>J72,Assumptions!C48,0)+IF((Assumptions!C47/(Assumptions!C45+J56))>J72,Assumptions!C47,0)+IF((Assumptions!C49/Assumptions!C44)>J72,Assumptions!C49,0)+IF((Assumptions!C50/Assumptions!C43)>J72,Assumptions!C50,0)+IF((Assumptions!C51/Assumptions!C42)>J72,Assumptions!C51,0)+IF((Assumptions!C52/Assumptions!C41)>J72,Assumptions!C52,0)))/(J66+(IF((Assumptions!C7/J54)<=J72,J54,0)+IF((Assumptions!C48/(Assumptions!C46+J55))<=J72,(Assumptions!C46+J55),0)+IF((Assumptions!C47/(Assumptions!C45+J56))<=J72,(Assumptions!C45+J56),0)+IF((Assumptions!C49/Assumptions!C44)<=J72,Assumptions!C44,0)+IF((Assumptions!C50/Assumptions!C43)<=J72,Assumptions!C43,0)+IF((Assumptions!C51/Assumptions!C42)<=J72,Assumptions!C42,0)+IF((Assumptions!C52/Assumptions!C41)<=J72,Assumptions!C41,0))) -> 55.409885 | K73: =(Assumptions!C62+Assumptions!C24*Assumptions!C26-(IF((Assumptions!C7/K54)>K72,Assumptions!C7,0)+IF((Assumptions!C48/(Assumptions!C46+K55))>K72,Assumptions!C48,0)+IF((Assumptions!C47/(Assumptions!C45+K56))>K72,Assumptions!C47,0)+IF((Assumptions!C49/Assumptions!C44)>K72,Assumptions!C49,0)+IF((Assumptions!C50/Assumptions!C43)>K72,Assumptions!C50,0)+IF((Assumptions!C51/Assumptions!C42)>K72,Assumptions!C51,0)+IF((Assumptions!C52/Assumptions!C41)>K72,Assumptions!C52,0)))/(K66+(IF((Assumptions!C7/K54)<=K72,K54,0)+IF((Assumptions!C48/(Assumptions!C46+K55))<=K72,(Assumptions!C46+K55),0)+IF((Assumptions!C47/(Assumptions!C45+K56))<=K72,(Assumptions!C45+K56),0)+IF((Assumptions!C49/Assumptions!C44)<=K72,Assumptions!C44,0)+IF((Assumptions!C50/Assumptions!C43)<=K72,Assumptions!C43,0)+IF((Assumptions!C51/Assumptions!C42)<=K72,Assumptions!C42,0)+IF((Assumptions!C52/Assumptions!C41)<=K72,Assumptions!C41,0))) -> 55.713149 | L73: =(Assumptions!C62+Assumptions!C24*Assumptions!C26-(IF((Assumptions!C7/L54)>L72,Assumptions!C7,0)+IF((Assumptions!C48/(Assumptions!C46+L55))>L72,Assumptions!C48,0)+IF((Assumptions!C47/(Assumptions!C45+L56))>L72,Assumptions!C47,0)+IF((Assumptions!C49/Assumptions!C44)>L72,Assumptions!C49,0)+IF((Assumptions!C50/Assumptions!C43)>L72,Assumptions!C50,0)+IF((Assumptions!C51/Assumptions!C42)>L72,Assumptions!C51,0)+IF((Assumptions!C52/Assumptions!C41)>L72,Assumptions!C52,0)))/(L66+(IF((Assumptions!C7/L54)<=L72,L54,0)+IF((Assumptions!C48/(Assumptions!C46+L55))<=L72,(Assumptions!C46+L55),0)+IF((Assumptions!C47/(Assumptions!C45+L56))<=L72,(Assumptions!C45+L56),0)+IF((Assumptions!C49/Assumptions!C44)<=L72,Assumptions!C44,0)+IF((Assumptions!C50/Assumptions!C43)<=L72,Assumptions!C43,0)+IF((Assumptions!C51/Assumptions!C42)<=L72,Assumptions!C42,0)+IF((Assumptions!C52/Assumptions!C41)<=L72,Assumptions!C41,0))) -> 56.100896
B74: Iter 3 p | D74: =(Assumptions!C62+Assumptions!C24*Assumptions!C26-(IF((Assumptions!C7/D54)>D73,Assumptions!C7,0)+IF((Assumptions!C48/(Assumptions!C46+D55))>D73,Assumptions!C48,0)+IF((Assumptions!C47/(Assumptions!C45+D56))>D73,Assumptions!C47,0)+IF((Assumptions!C49/Assumptions!C44)>D73,Assumptions!C49,0)+IF((Assumptions!C50/Assumptions!C43)>D73,Assumptions!C50,0)+IF((Assumptions!C51/Assumptions!C42)>D73,Assumptions!C51,0)+IF((Assumptions!C52/Assumptions!C41)>D73,Assumptions!C52,0)))/(D66+(IF((Assumptions!C7/D54)<=D73,D54,0)+IF((Assumptions!C48/(Assumptions!C46+D55))<=D73,(Assumptions!C46+D55),0)+IF((Assumptions!C47/(Assumptions!C45+D56))<=D73,(Assumptions!C45+D56),0)+IF((Assumptions!C49/Assumptions!C44)<=D73,Assumptions!C44,0)+IF((Assumptions!C50/Assumptions!C43)<=D73,Assumptions!C43,0)+IF((Assumptions!C51/Assumptions!C42)<=D73,Assumptions!C42,0)+IF((Assumptions!C52/Assumptions!C41)<=D73,Assumptions!C41,0))) -> 55.502343 | E74: =(Assumptions!C62+Assumptions!C24*Assumptions!C26-(IF((Assumptions!C7/E54)>E73,Assumptions!C7,0)+IF((Assumptions!C48/(Assumptions!C46+E55))>E73,Assumptions!C48,0)+IF((Assumptions!C47/(Assumptions!C45+E56))>E73,Assumptions!C47,0)+IF((Assumptions!C49/Assumptions!C44)>E73,Assumptions!C49,0)+IF((Assumptions!C50/Assumptions!C43)>E73,Assumptions!C50,0)+IF((Assumptions!C51/Assumptions!C42)>E73,Assumptions!C51,0)+IF((Assumptions!C52/Assumptions!C41)>E73,Assumptions!C52,0)))/(E66+(IF((Assumptions!C7/E54)<=E73,E54,0)+IF((Assumptions!C48/(Assumptions!C46+E55))<=E73,(Assumptions!C46+E55),0)+IF((Assumptions!C47/(Assumptions!C45+E56))<=E73,(Assumptions!C45+E56),0)+IF((Assumptions!C49/Assumptions!C44)<=E73,Assumptions!C44,0)+IF((Assumptions!C50/Assumptions!C43)<=E73,Assumptions!C43,0)+IF((Assumptions!C51/Assumptions!C42)<=E73,Assumptions!C42,0)+IF((Assumptions!C52/Assumptions!C41)<=E73,Assumptions!C41,0))) -> 55.79268 | F74: =(Assumptions!C62+Assumptions!C24*Assumptions!C26-(IF((Assumptions!C7/F54)>F73,Assumptions!C7,0)+IF((Assumptions!C48/(Assumptions!C46+F55))>F73,Assumptions!C48,0)+IF((Assumptions!C47/(Assumptions!C45+F56))>F73,Assumptions!C47,0)+IF((Assumptions!C49/Assumptions!C44)>F73,Assumptions!C49,0)+IF((Assumptions!C50/Assumptions!C43)>F73,Assumptions!C50,0)+IF((Assumptions!C51/Assumptions!C42)>F73,Assumptions!C51,0)+IF((Assumptions!C52/Assumptions!C41)>F73,Assumptions!C52,0)))/(F66+(IF((Assumptions!C7/F54)<=F73,F54,0)+IF((Assumptions!C48/(Assumptions!C46+F55))<=F73,(Assumptions!C46+F55),0)+IF((Assumptions!C47/(Assumptions!C45+F56))<=F73,(Assumptions!C45+F56),0)+IF((Assumptions!C49/Assumptions!C44)<=F73,Assumptions!C44,0)+IF((Assumptions!C50/Assumptions!C43)<=F73,Assumptions!C43,0)+IF((Assumptions!C51/Assumptions!C42)<=F73,Assumptions!C42,0)+IF((Assumptions!C52/Assumptions!C41)<=F73,Assumptions!C41,0))) -> 56.164435 | G74: =(Assumptions!C62+Assumptions!C24*Assumptions!C26-(IF((Assumptions!C7/G54)>G73,Assumptions!C7,0)+IF((Assumptions!C48/(Assumptions!C46+G55))>G73,Assumptions!C48,0)+IF((Assumptions!C47/(Assumptions!C45+G56))>G73,Assumptions!C47,0)+IF((Assumptions!C49/Assumptions!C44)>G73,Assumptions!C49,0)+IF((Assumptions!C50/Assumptions!C43)>G73,Assumptions!C50,0)+IF((Assumptions!C51/Assumptions!C42)>G73,Assumptions!C51,0)+IF((Assumptions!C52/Assumptions!C41)>G73,Assumptions!C52,0)))/(G66+(IF((Assumptions!C7/G54)<=G73,G54,0)+IF((Assumptions!C48/(Assumptions!C46+G55))<=G73,(Assumptions!C46+G55),0)+IF((Assumptions!C47/(Assumptions!C45+G56))<=G73,(Assumptions!C45+G56),0)+IF((Assumptions!C49/Assumptions!C44)<=G73,Assumptions!C44,0)+IF((Assumptions!C50/Assumptions!C43)<=G73,Assumptions!C43,0)+IF((Assumptions!C51/Assumptions!C42)<=G73,Assumptions!C42,0)+IF((Assumptions!C52/Assumptions!C41)<=G73,Assumptions!C41,0))) -> 55.464995 | H74: =(Assumptions!C62+Assumptions!C24*Assumptions!C26-(IF((Assumptions!C7/H54)>H73,Assumptions!C7,0)+IF((Assumptions!C48/(Assumptions!C46+H55))>H73,Assumptions!C48,0)+IF((Assumptions!C47/(Assumptions!C45+H56))>H73,Assumptions!C47,0)+IF((Assumptions!C49/Assumptions!C44)>H73,Assumptions!C49,0)+IF((Assumptions!C50/Assumptions!C43)>H73,Assumptions!C50,0)+IF((Assumptions!C51/Assumptions!C42)>H73,Assumptions!C51,0)+IF((Assumptions!C52/Assumptions!C41)>H73,Assumptions!C52,0)))/(H66+(IF((Assumptions!C7/H54)<=H73,H54,0)+IF((Assumptions!C48/(Assumptions!C46+H55))<=H73,(Assumptions!C46+H55),0)+IF((Assumptions!C47/(Assumptions!C45+H56))<=H73,(Assumptions!C45+H56),0)+IF((Assumptions!C49/Assumptions!C44)<=H73,Assumptions!C44,0)+IF((Assumptions!C50/Assumptions!C43)<=H73,Assumptions!C43,0)+IF((Assumptions!C51/Assumptions!C42)<=H73,Assumptions!C42,0)+IF((Assumptions!C52/Assumptions!C41)<=H73,Assumptions!C41,0))) -> 55.761324 | I74: =(Assumptions!C62+Assumptions!C24*Assumptions!C26-(IF((Assumptions!C7/I54)>I73,Assumptions!C7,0)+IF((Assumptions!C48/(Assumptions!C46+I55))>I73,Assumptions!C48,0)+IF((Assumptions!C47/(Assumptions!C45+I56))>I73,Assumptions!C47,0)+IF((Assumptions!C49/Assumptions!C44)>I73,Assumptions!C49,0)+IF((Assumptions!C50/Assumptions!C43)>I73,Assumptions!C50,0)+IF((Assumptions!C51/Assumptions!C42)>I73,Assumptions!C51,0)+IF((Assumptions!C52/Assumptions!C41)>I73,Assumptions!C52,0)))/(I66+(IF((Assumptions!C7/I54)<=I73,I54,0)+IF((Assumptions!C48/(Assumptions!C46+I55))<=I73,(Assumptions!C46+I55),0)+IF((Assumptions!C47/(Assumptions!C45+I56))<=I73,(Assumptions!C45+I56),0)+IF((Assumptions!C49/Assumptions!C44)<=I73,Assumptions!C44,0)+IF((Assumptions!C50/Assumptions!C43)<=I73,Assumptions!C43,0)+IF((Assumptions!C51/Assumptions!C42)<=I73,Assumptions!C42,0)+IF((Assumptions!C52/Assumptions!C41)<=I73,Assumptions!C41,0))) -> 56.140205 | J74: =(Assumptions!C62+Assumptions!C24*Assumptions!C26-(IF((Assumptions!C7/J54)>J73,Assumptions!C7,0)+IF((Assumptions!C48/(Assumptions!C46+J55))>J73,Assumptions!C48,0)+IF((Assumptions!C47/(Assumptions!C45+J56))>J73,Assumptions!C47,0)+IF((Assumptions!C49/Assumptions!C44)>J73,Assumptions!C49,0)+IF((Assumptions!C50/Assumptions!C43)>J73,Assumptions!C50,0)+IF((Assumptions!C51/Assumptions!C42)>J73,Assumptions!C51,0)+IF((Assumptions!C52/Assumptions!C41)>J73,Assumptions!C52,0)))/(J66+(IF((Assumptions!C7/J54)<=J73,J54,0)+IF((Assumptions!C48/(Assumptions!C46+J55))<=J73,(Assumptions!C46+J55),0)+IF((Assumptions!C47/(Assumptions!C45+J56))<=J73,(Assumptions!C45+J56),0)+IF((Assumptions!C49/Assumptions!C44)<=J73,Assumptions!C44,0)+IF((Assumptions!C50/Assumptions!C43)<=J73,Assumptions!C43,0)+IF((Assumptions!C51/Assumptions!C42)<=J73,Assumptions!C42,0)+IF((Assumptions!C52/Assumptions!C41)<=J73,Assumptions!C41,0))) -> 55.409885 | K74: =(Assumptions!C62+Assumptions!C24*Assumptions!C26-(IF((Assumptions!C7/K54)>K73,Assumptions!C7,0)+IF((Assumptions!C48/(Assumptions!C46+K55))>K73,Assumptions!C48,0)+IF((Assumptions!C47/(Assumptions!C45+K56))>K73,Assumptions!C47,0)+IF((Assumptions!C49/Assumptions!C44)>K73,Assumptions!C49,0)+IF((Assumptions!C50/Assumptions!C43)>K73,Assumptions!C50,0)+IF((Assumptions!C51/Assumptions!C42)>K73,Assumptions!C51,0)+IF((Assumptions!C52/Assumptions!C41)>K73,Assumptions!C52,0)))/(K66+(IF((Assumptions!C7/K54)<=K73,K54,0)+IF((Assumptions!C48/(Assumptions!C46+K55))<=K73,(Assumptions!C46+K55),0)+IF((Assumptions!C47/(Assumptions!C45+K56))<=K73,(Assumptions!C45+K56),0)+IF((Assumptions!C49/Assumptions!C44)<=K73,Assumptions!C44,0)+IF((Assumptions!C50/Assumptions!C43)<=K73,Assumptions!C43,0)+IF((Assumptions!C51/Assumptions!C42)<=K73,Assumptions!C42,0)+IF((Assumptions!C52/Assumptions!C41)<=K73,Assumptions!C41,0))) -> 55.713149 | L74: =(Assumptions!C62+Assumptions!C24*Assumptions!C26-(IF((Assumptions!C7/L54)>L73,Assumptions!C7,0)+IF((Assumptions!C48/(Assumptions!C46+L55))>L73,Assumptions!C48,0)+IF((Assumptions!C47/(Assumptions!C45+L56))>L73,Assumptions!C47,0)+IF((Assumptions!C49/Assumptions!C44)>L73,Assumptions!C49,0)+IF((Assumptions!C50/Assumptions!C43)>L73,Assumptions!C50,0)+IF((Assumptions!C51/Assumptions!C42)>L73,Assumptions!C51,0)+IF((Assumptions!C52/Assumptions!C41)>L73,Assumptions!C52,0)))/(L66+(IF((Assumptions!C7/L54)<=L73,L54,0)+IF((Assumptions!C48/(Assumptions!C46+L55))<=L73,(Assumptions!C46+L55),0)+IF((Assumptions!C47/(Assumptions!C45+L56))<=L73,(Assumptions!C45+L56),0)+IF((Assumptions!C49/Assumptions!C44)<=L73,Assumptions!C44,0)+IF((Assumptions!C50/Assumptions!C43)<=L73,Assumptions!C43,0)+IF((Assumptions!C51/Assumptions!C42)<=L73,Assumptions!C42,0)+IF((Assumptions!C52/Assumptions!C41)<=L73,Assumptions!C41,0))) -> 56.100896
B75: Iter 4 p (final) | D75: =(Assumptions!C62+Assumptions!C24*Assumptions!C26-(IF((Assumptions!C7/D54)>D74,Assumptions!C7,0)+IF((Assumptions!C48/(Assumptions!C46+D55))>D74,Assumptions!C48,0)+IF((Assumptions!C47/(Assumptions!C45+D56))>D74,Assumptions!C47,0)+IF((Assumptions!C49/Assumptions!C44)>D74,Assumptions!C49,0)+IF((Assumptions!C50/Assumptions!C43)>D74,Assumptions!C50,0)+IF((Assumptions!C51/Assumptions!C42)>D74,Assumptions!C51,0)+IF((Assumptions!C52/Assumptions!C41)>D74,Assumptions!C52,0)))/(D66+(IF((Assumptions!C7/D54)<=D74,D54,0)+IF((Assumptions!C48/(Assumptions!C46+D55))<=D74,(Assumptions!C46+D55),0)+IF((Assumptions!C47/(Assumptions!C45+D56))<=D74,(Assumptions!C45+D56),0)+IF((Assumptions!C49/Assumptions!C44)<=D74,Assumptions!C44,0)+IF((Assumptions!C50/Assumptions!C43)<=D74,Assumptions!C43,0)+IF((Assumptions!C51/Assumptions!C42)<=D74,Assumptions!C42,0)+IF((Assumptions!C52/Assumptions!C41)<=D74,Assumptions!C41,0))) -> 55.502343 | E75: =(Assumptions!C62+Assumptions!C24*Assumptions!C26-(IF((Assumptions!C7/E54)>E74,Assumptions!C7,0)+IF((Assumptions!C48/(Assumptions!C46+E55))>E74,Assumptions!C48,0)+IF((Assumptions!C47/(Assumptions!C45+E56))>E74,Assumptions!C47,0)+IF((Assumptions!C49/Assumptions!C44)>E74,Assumptions!C49,0)+IF((Assumptions!C50/Assumptions!C43)>E74,Assumptions!C50,0)+IF((Assumptions!C51/Assumptions!C42)>E74,Assumptions!C51,0)+IF((Assumptions!C52/Assumptions!C41)>E74,Assumptions!C52,0)))/(E66+(IF((Assumptions!C7/E54)<=E74,E54,0)+IF((Assumptions!C48/(Assumptions!C46+E55))<=E74,(Assumptions!C46+E55),0)+IF((Assumptions!C47/(Assumptions!C45+E56))<=E74,(Assumptions!C45+E56),0)+IF((Assumptions!C49/Assumptions!C44)<=E74,Assumptions!C44,0)+IF((Assumptions!C50/Assumptions!C43)<=E74,Assumptions!C43,0)+IF((Assumptions!C51/Assumptions!C42)<=E74,Assumptions!C42,0)+IF((Assumptions!C52/Assumptions!C41)<=E74,Assumptions!C41,0))) -> 55.79268 | F75: =(Assumptions!C62+Assumptions!C24*Assumptions!C26-(IF((Assumptions!C7/F54)>F74,Assumptions!C7,0)+IF((Assumptions!C48/(Assumptions!C46+F55))>F74,Assumptions!C48,0)+IF((Assumptions!C47/(Assumptions!C45+F56))>F74,Assumptions!C47,0)+IF((Assumptions!C49/Assumptions!C44)>F74,Assumptions!C49,0)+IF((Assumptions!C50/Assumptions!C43)>F74,Assumptions!C50,0)+IF((Assumptions!C51/Assumptions!C42)>F74,Assumptions!C51,0)+IF((Assumptions!C52/Assumptions!C41)>F74,Assumptions!C52,0)))/(F66+(IF((Assumptions!C7/F54)<=F74,F54,0)+IF((Assumptions!C48/(Assumptions!C46+F55))<=F74,(Assumptions!C46+F55),0)+IF((Assumptions!C47/(Assumptions!C45+F56))<=F74,(Assumptions!C45+F56),0)+IF((Assumptions!C49/Assumptions!C44)<=F74,Assumptions!C44,0)+IF((Assumptions!C50/Assumptions!C43)<=F74,Assumptions!C43,0)+IF((Assumptions!C51/Assumptions!C42)<=F74,Assumptions!C42,0)+IF((Assumptions!C52/Assumptions!C41)<=F74,Assumptions!C41,0))) -> 56.164435 | G75: =(Assumptions!C62+Assumptions!C24*Assumptions!C26-(IF((Assumptions!C7/G54)>G74,Assumptions!C7,0)+IF((Assumptions!C48/(Assumptions!C46+G55))>G74,Assumptions!C48,0)+IF((Assumptions!C47/(Assumptions!C45+G56))>G74,Assumptions!C47,0)+IF((Assumptions!C49/Assumptions!C44)>G74,Assumptions!C49,0)+IF((Assumptions!C50/Assumptions!C43)>G74,Assumptions!C50,0)+IF((Assumptions!C51/Assumptions!C42)>G74,Assumptions!C51,0)+IF((Assumptions!C52/Assumptions!C41)>G74,Assumptions!C52,0)))/(G66+(IF((Assumptions!C7/G54)<=G74,G54,0)+IF((Assumptions!C48/(Assumptions!C46+G55))<=G74,(Assumptions!C46+G55),0)+IF((Assumptions!C47/(Assumptions!C45+G56))<=G74,(Assumptions!C45+G56),0)+IF((Assumptions!C49/Assumptions!C44)<=G74,Assumptions!C44,0)+IF((Assumptions!C50/Assumptions!C43)<=G74,Assumptions!C43,0)+IF((Assumptions!C51/Assumptions!C42)<=G74,Assumptions!C42,0)+IF((Assumptions!C52/Assumptions!C41)<=G74,Assumptions!C41,0))) -> 55.464995 | H75: =(Assumptions!C62+Assumptions!C24*Assumptions!C26-(IF((Assumptions!C7/H54)>H74,Assumptions!C7,0)+IF((Assumptions!C48/(Assumptions!C46+H55))>H74,Assumptions!C48,0)+IF((Assumptions!C47/(Assumptions!C45+H56))>H74,Assumptions!C47,0)+IF((Assumptions!C49/Assumptions!C44)>H74,Assumptions!C49,0)+IF((Assumptions!C50/Assumptions!C43)>H74,Assumptions!C50,0)+IF((Assumptions!C51/Assumptions!C42)>H74,Assumptions!C51,0)+IF((Assumptions!C52/Assumptions!C41)>H74,Assumptions!C52,0)))/(H66+(IF((Assumptions!C7/H54)<=H74,H54,0)+IF((Assumptions!C48/(Assumptions!C46+H55))<=H74,(Assumptions!C46+H55),0)+IF((Assumptions!C47/(Assumptions!C45+H56))<=H74,(Assumptions!C45+H56),0)+IF((Assumptions!C49/Assumptions!C44)<=H74,Assumptions!C44,0)+IF((Assumptions!C50/Assumptions!C43)<=H74,Assumptions!C43,0)+IF((Assumptions!C51/Assumptions!C42)<=H74,Assumptions!C42,0)+IF((Assumptions!C52/Assumptions!C41)<=H74,Assumptions!C41,0))) -> 55.761324 | I75: =(Assumptions!C62+Assumptions!C24*Assumptions!C26-(IF((Assumptions!C7/I54)>I74,Assumptions!C7,0)+IF((Assumptions!C48/(Assumptions!C46+I55))>I74,Assumptions!C48,0)+IF((Assumptions!C47/(Assumptions!C45+I56))>I74,Assumptions!C47,0)+IF((Assumptions!C49/Assumptions!C44)>I74,Assumptions!C49,0)+IF((Assumptions!C50/Assumptions!C43)>I74,Assumptions!C50,0)+IF((Assumptions!C51/Assumptions!C42)>I74,Assumptions!C51,0)+IF((Assumptions!C52/Assumptions!C41)>I74,Assumptions!C52,0)))/(I66+(IF((Assumptions!C7/I54)<=I74,I54,0)+IF((Assumptions!C48/(Assumptions!C46+I55))<=I74,(Assumptions!C46+I55),0)+IF((Assumptions!C47/(Assumptions!C45+I56))<=I74,(Assumptions!C45+I56),0)+IF((Assumptions!C49/Assumptions!C44)<=I74,Assumptions!C44,0)+IF((Assumptions!C50/Assumptions!C43)<=I74,Assumptions!C43,0)+IF((Assumptions!C51/Assumptions!C42)<=I74,Assumptions!C42,0)+IF((Assumptions!C52/Assumptions!C41)<=I74,Assumptions!C41,0))) -> 56.140205 | J75: =(Assumptions!C62+Assumptions!C24*Assumptions!C26-(IF((Assumptions!C7/J54)>J74,Assumptions!C7,0)+IF((Assumptions!C48/(Assumptions!C46+J55))>J74,Assumptions!C48,0)+IF((Assumptions!C47/(Assumptions!C45+J56))>J74,Assumptions!C47,0)+IF((Assumptions!C49/Assumptions!C44)>J74,Assumptions!C49,0)+IF((Assumptions!C50/Assumptions!C43)>J74,Assumptions!C50,0)+IF((Assumptions!C51/Assumptions!C42)>J74,Assumptions!C51,0)+IF((Assumptions!C52/Assumptions!C41)>J74,Assumptions!C52,0)))/(J66+(IF((Assumptions!C7/J54)<=J74,J54,0)+IF((Assumptions!C48/(Assumptions!C46+J55))<=J74,(Assumptions!C46+J55),0)+IF((Assumptions!C47/(Assumptions!C45+J56))<=J74,(Assumptions!C45+J56),0)+IF((Assumptions!C49/Assumptions!C44)<=J74,Assumptions!C44,0)+IF((Assumptions!C50/Assumptions!C43)<=J74,Assumptions!C43,0)+IF((Assumptions!C51/Assumptions!C42)<=J74,Assumptions!C42,0)+IF((Assumptions!C52/Assumptions!C41)<=J74,Assumptions!C41,0))) -> 55.409885 | K75: =(Assumptions!C62+Assumptions!C24*Assumptions!C26-(IF((Assumptions!C7/K54)>K74,Assumptions!C7,0)+IF((Assumptions!C48/(Assumptions!C46+K55))>K74,Assumptions!C48,0)+IF((Assumptions!C47/(Assumptions!C45+K56))>K74,Assumptions!C47,0)+IF((Assumptions!C49/Assumptions!C44)>K74,Assumptions!C49,0)+IF((Assumptions!C50/Assumptions!C43)>K74,Assumptions!C50,0)+IF((Assumptions!C51/Assumptions!C42)>K74,Assumptions!C51,0)+IF((Assumptions!C52/Assumptions!C41)>K74,Assumptions!C52,0)))/(K66+(IF((Assumptions!C7/K54)<=K74,K54,0)+IF((Assumptions!C48/(Assumptions!C46+K55))<=K74,(Assumptions!C46+K55),0)+IF((Assumptions!C47/(Assumptions!C45+K56))<=K74,(Assumptions!C45+K56),0)+IF((Assumptions!C49/Assumptions!C44)<=K74,Assumptions!C44,0)+IF((Assumptions!C50/Assumptions!C43)<=K74,Assumptions!C43,0)+IF((Assumptions!C51/Assumptions!C42)<=K74,Assumptions!C42,0)+IF((Assumptions!C52/Assumptions!C41)<=K74,Assumptions!C41,0))) -> 55.713149 | L75: =(Assumptions!C62+Assumptions!C24*Assumptions!C26-(IF((Assumptions!C7/L54)>L74,Assumptions!C7,0)+IF((Assumptions!C48/(Assumptions!C46+L55))>L74,Assumptions!C48,0)+IF((Assumptions!C47/(Assumptions!C45+L56))>L74,Assumptions!C47,0)+IF((Assumptions!C49/Assumptions!C44)>L74,Assumptions!C49,0)+IF((Assumptions!C50/Assumptions!C43)>L74,Assumptions!C50,0)+IF((Assumptions!C51/Assumptions!C42)>L74,Assumptions!C51,0)+IF((Assumptions!C52/Assumptions!C41)>L74,Assumptions!C52,0)))/(L66+(IF((Assumptions!C7/L54)<=L74,L54,0)+IF((Assumptions!C48/(Assumptions!C46+L55))<=L74,(Assumptions!C46+L55),0)+IF((Assumptions!C47/(Assumptions!C45+L56))<=L74,(Assumptions!C45+L56),0)+IF((Assumptions!C49/Assumptions!C44)<=L74,Assumptions!C44,0)+IF((Assumptions!C50/Assumptions!C43)<=L74,Assumptions!C43,0)+IF((Assumptions!C51/Assumptions!C42)<=L74,Assumptions!C42,0)+IF((Assumptions!C52/Assumptions!C41)<=L74,Assumptions!C41,0))) -> 56.100896
B76: Series F election @ $2B | D76: =IF(D51<=D75,"convert","preference") -> convert | E76: =IF(E51<=E75,"convert","preference") -> convert | F76: =IF(F51<=F75,"convert","preference") -> convert | G76: =IF(G51<=G75,"convert","preference") -> convert | H76: =IF(H51<=H75,"convert","preference") -> convert | I76: =IF(I51<=I75,"convert","preference") -> convert | J76: =IF(J51<=J75,"convert","preference") -> convert | K76: =IF(K51<=K75,"convert","preference") -> convert | L76: =IF(L51<=L75,"convert","preference") -> convert

Sheet Return-Solver
B2: Kelvin Dynamics — Return Solver
B3: Required Series F ownership % for $10M check to hit 3x / 4x at each exit
B5: Inputs (from Pro-Forma & Waterfall)
B6: Item | C6: =Assumptions!C60 -> 700000000 | D6: =Assumptions!C61 -> 1200000000 | E6: =Assumptions!C62 -> 2000000000 | F6: =Assumptions!C63 -> 4000000000 | G6: =Assumptions!C64 -> 8000000000
B7: Exit value | C7: =Assumptions!C60 -> 700000000 | D7: =Assumptions!C61 -> 1200000000 | E7: =Assumptions!C62 -> 2000000000 | F7: =Assumptions!C63 -> 4000000000 | G7: =Assumptions!C64 -> 8000000000
B8: Equilibrium per-share p ($) | C8: =Waterfall!I33 -> 8.3788564 | D8: =Waterfall!J33 -> 28.420572 | E8: =Waterfall!K33 -> 55.761199 | F8: =Waterfall!L33 -> 111.63753 | G8: =Waterfall!M33 -> 223.20533
B9: F election (from Waterfall) | C9: =Waterfall!I37 -> preference | D9: =Waterfall!J37 -> preference | E9: =Waterfall!K37 -> convert | F9: =Waterfall!L37 -> convert | G9: =Waterfall!M37 -> convert
B10: F class shares (post-F) | C10: =Waterfall!C15 -> 803314.95 | D10: =Waterfall!C15 -> 803314.95 | E10: =Waterfall!C15 -> 803314.95 | F10: =Waterfall!C15 -> 803314.95 | G10: =Waterfall!C15 -> 803314.95
B11: F class preference ($) | C11: =Assumptions!C7 -> 30000000 | D11: =Assumptions!C7 -> 30000000 | E11: =Assumptions!C7 -> 30000000 | F11: =Assumptions!C7 -> 30000000 | G11: =Assumptions!C7 -> 30000000
B12: T_F (post-F FD) | C12: ='Pro-Forma'!K30 -> 38336360 | D12: ='Pro-Forma'!K30 -> 38336360 | E12: ='Pro-Forma'!K30 -> 38336360 | F12: ='Pro-Forma'!K30 -> 38336360 | G12: ='Pro-Forma'!K30 -> 38336360
B14: 3x Target — $30M Net Return
B15: 3x target ($) | C15: =Assumptions!C75 -> 30000000 | D15: =Assumptions!C75 -> 30000000 | E15: =Assumptions!C75 -> 30000000 | F15: =Assumptions!C75 -> 30000000 | G15: =Assumptions!C75 -> 30000000
B16: Required ownership % | C16: =IF(C9="convert",C15/(C8*C12),C15*C10/(C11*C12)) -> 0.020954388 | D16: =IF(D9="convert",D15/(D8*D12),D15*D10/(D11*D12)) -> 0.020954388 | E16: =IF(E9="convert",E15/(E8*E12),E15*E10/(E11*E12)) -> 0.014033897 | F16: =IF(F9="convert",F15/(F8*F12),F15*F10/(F11*F12)) -> 0.0070097117 | G16: =IF(G9="convert",G15/(G8*G12),G15*G10/(G11*G12)) -> 0.0035059508
B17: Feasibility | C17: =IF(OR(C16<=0,C16>1,AND(C9="preference",C15>C11)),"Infeasible","Feasible") -> Feasible | D17: =IF(OR(D16<=0,D16>1,AND(D9="preference",D15>D11)),"Infeasible","Feasible") -> Feasible | E17: =IF(OR(E16<=0,E16>1,AND(E9="preference",E15>E11)),"Infeasible","Feasible") -> Feasible | F17: =IF(OR(F16<=0,F16>1,AND(F9="preference",F15>F11)),"Infeasible","Feasible") -> Feasible | G17: =IF(OR(G16<=0,G16>1,AND(G9="preference",G15>G11)),"Infeasible","Feasible") -> Feasible
B18: Comparison: our actual ownership % | C18: ='Pro-Forma'!I70 -> 0.0069847958 | D18: ='Pro-Forma'!I70 -> 0.0069847958 | E18: ='Pro-Forma'!I70 -> 0.0069847958 | F18: ='Pro-Forma'!I70 -> 0.0069847958 | G18: ='Pro-Forma'!I70 -> 0.0069847958
B20: 4x Target — $40M Net Return
B21: 4x target ($) | C21: =Assumptions!C76 -> 40000000 | D21: =Assumptions!C76 -> 40000000 | E21: =Assumptions!C76 -> 40000000 | F21: =Assumptions!C76 -> 40000000 | G21: =Assumptions!C76 -> 40000000
B22: Required ownership % | C22: =IF(C9="convert",C21/(C8*C12),C21*C10/(C11*C12)) -> 0.027939183 | D22: =IF(D9="convert",D21/(D8*D12),D21*D10/(D11*D12)) -> 0.027939183 | E22: =IF(E9="convert",E21/(E8*E12),E21*E10/(E11*E12)) -> 0.018711862 | F22: =IF(F9="convert",F21/(F8*F12),F21*F10/(F11*F12)) -> 0.0093462822 | G22: =IF(G9="convert",G21/(G8*G12),G21*G10/(G11*G12)) -> 0.004674601
B23: Feasibility | C23: =IF(OR(C22<=0,C22>1,AND(C9="preference",C21>C11)),"Infeasible","Feasible") -> Infeasible | D23: =IF(OR(D22<=0,D22>1,AND(D9="preference",D21>D11)),"Infeasible","Feasible") -> Infeasible | E23: =IF(OR(E22<=0,E22>1,AND(E9="preference",E21>E11)),"Infeasible","Feasible") -> Feasible | F23: =IF(OR(F22<=0,F22>1,AND(F9="preference",F21>F11)),"Infeasible","Feasible") -> Feasible | G23: =IF(OR(G22<=0,G22>1,AND(G9="preference",G21>G11)),"Infeasible","Feasible") -> Feasible
B24: Comparison: our actual ownership % | C24: ='Pro-Forma'!I70 -> 0.0069847958 | D24: ='Pro-Forma'!I70 -> 0.0069847958 | E24: ='Pro-Forma'!I70 -> 0.0069847958 | F24: ='Pro-Forma'!I70 -> 0.0069847958 | G24: ='Pro-Forma'!I70 -> 0.0069847958
B26: Actual $10M Check Proceeds (base case)
B27: Our shares ($10M / F_PPS) | C27: ='Pro-Forma'!H70 -> 267771.65 | D27: ='Pro-Forma'!H70 -> 267771.65 | E27: ='Pro-Forma'!H70 -> 267771.65 | F27: ='Pro-Forma'!H70 -> 267771.65 | G27: ='Pro-Forma'!H70 -> 267771.65
B28: Our $ proceeds at this exit | C28: =IF(C9="convert",C27*C8,Assumptions!C11) -> 10000000 | D28: =IF(D9="convert",D27*D8,Assumptions!C11) -> 10000000 | E28: =IF(E9="convert",E27*E8,Assumptions!C11) -> 14931268 | F28: =IF(F9="convert",F27*F8,Assumptions!C11) -> 29893366 | G28: =IF(G9="convert",G27*G8,Assumptions!C11) -> 59768060
B29: Our MOIC | C29: =C28/Assumptions!C11 -> 1 | D29: =D28/Assumptions!C11 -> 1 | E29: =E28/Assumptions!C11 -> 1.4931268 | F29: =F28/Assumptions!C11 -> 2.9893366 | G29: =G28/Assumptions!C11 -> 5.976806
