Workbook

Sheet Assumptions
B2: Kelvin Dynamics — Series F Assumptions
B3: $ in actual dollars; shares in actual count
B5: Round Terms
B6: Series F pre-money valuation ($) | C6: 1400000000
B7: Series F primary raise ($) | C7: 30000000
B8: Series F secondary raise ($) | C8: 15000000
B9: Tender PPS multiplier (× F PPS) | C9: 0.85
B10: ESOP refresh target (% of post-F FD) | C10: 0.13
B11: Our fund check ($) | C11: 10000000
B12: F_LEAD primary check ($) | C12: 20000000
B13: Option strike ($/share) | C13: 1
B15: Pre-F Cap Table Inputs
B16: Founder F1 (CEO) common shares | C16: 4000000
B17: Founder F2 (CTO) common shares | C17: 2500000
B18: Founder F3 (Chief Scientist) common shares | C18: 1500000
B19: Employee RSAs (10× 100k) | C19: 1000000
B20: Pre-F issued options | C20: 2500000
B21: Pre-F unissued options | C21: 1894667
B22: Pre-F option pool (issued + unissued) | C22: =C20+C21 -> 4394667
B23: Pre-F broad-based FD total | C23: 36617961
B25: Prior-Round OCPs / PPS / Investments
C26: OCP-for-AD ($) | D26: PPS-issued ($) | E26: Issued shares | F26: Invested ($)
B27: Seed | C27: 1 | D27: 1 | E27: 5000000 | F27: 5000000
B28: Series A | C28: 3 | D28: 3 | E28: 5000000 | F28: 15000000
B29: Series B | C29: 10 | D29: 10 | E29: 3000000 | F29: 30000000
B30: Series C | C30: 25 | D30: 25 | E30: 2400000 | F30: 60000000
B31: Series D (post-E v3·v4 compound) | C31: 58.118347 | D31: 60 | E31: 1720627 | F31: 100000000
B32: Series E | C32: 49.158311 | D32: 49.158311 | E32: 6102667 | F32: 300000000
B34: Convertible Notes
C35: Principal ($) | D35: Cap ($) | E35: Discount
B36: Note A | C36: 5000000 | D36: 1000000000 | E36: 0.2
B37: Note B | C37: 3000000 | D37: 1600000000 | E37: 0.15
B39: Exit Scenarios
B40: Exit 1 ($) | C40: 700000000
B41: Exit 2 ($) | C41: 1200000000
B42: Exit 3 ($) — sensitivity reference | C42: 2000000000
B43: Exit 4 ($) | C43: 4000000000
B44: Exit 5 ($) | C44: 8000000000
B46: Sensitivity Axes
B47: ESOP refresh — low | C47: 0.11
B48: ESOP refresh — base | C48: 0.13
B49: ESOP refresh — high | C49: 0.15
B50: Series F pre-money — low ($) | C50: 1200000000
B51: Series F pre-money — base ($) | C51: 1400000000
B52: Series F pre-money — high ($) | C52: 1800000000
B54: Return Multiples
B55: Target multiple — 3× | C55: 3
B56: Target multiple — 4× | C56: 4
B58: Tender ($15M @ 0.85·F_PPS) transfers founder common to F_LEAD; no new shares issued.
B59: AD: broad-based weighted-average. NCP = OCP × (A+B) / (A+C); A=pre-F FD, B=$30M/OCP, C=$30M/F_PPS.
B60: Notes convert at F closing. Cap-implied PPS computed against pre-money FD excluding own note's shares.

Sheet Pro-Forma
B2: Kelvin Dynamics — Pro-Forma Series F Cap Table
B3: Round mechanics, anti-dilution, note conversions, secondary tender, post-F cap table
B5: Round Mechanics
B6: Series F pre-money ($) | C6: =Assumptions!C6 -> 1400000000
B7: Primary raise ($) | C7: =Assumptions!C7 -> 30000000
B8: ESOP refresh target (% of post-F FD) | C8: =Assumptions!C10 -> 0.13
B9: Pre-F broad-based FD | C9: =Assumptions!C23 -> 36617961
B10: Pre-F option pool | C10: =Assumptions!C22 -> 4394667
B11: Pre-F shares ex-options | C11: =C9-C10 -> 32223294
B12: α_D coefficient (D AD constant) | C12: =Assumptions!F31/(Assumptions!C31*(C9+C7/Assumptions!C31)) -> 0.046335438
B13: α_E coefficient (E AD constant) | C13: =Assumptions!F32/(Assumptions!C32*(C9+C7/Assumptions!C32)) -> 0.16392752
B14: Note A — cap-branch test (cap+prin < pre·(1−disc)) | C14: =IF(Assumptions!D36+Assumptions!C36<C6*(1-Assumptions!E36),1,0) -> 1
B15: Note A — share coefficient (c_A) | C15: =IF(C14=1,Assumptions!C36/(Assumptions!D36+Assumptions!C36),Assumptions!C36/(C6*(1-Assumptions!E36))) -> 0.0049751244
B16: Note B — cap-branch test | C16: =IF(Assumptions!D37+Assumptions!C37<C6*(1-Assumptions!E37),1,0) -> 0
B17: Note B — share coefficient (c_B) | C17: =IF(C16=1,Assumptions!C37/(Assumptions!D37+Assumptions!C37),Assumptions!C37/(C6*(1-Assumptions!E37))) -> 0.0025210084
B18: K_const numerator | C18: =C11-Assumptions!E31-Assumptions!E32+(C12+C13)*C9 -> 32099401
B19: Solver denominator | C19: =(1-C8)-(C12+C13+C8)*C7/C6-C15-C17 -> 0.85521252
B20: Pre-money FD (P) | C20: =C18/C19 -> 37533829
B21: Series F PPS ($) | C21: =C6/C20 -> 37.299685
B22: New F primary shares | C22: =C7/C21 -> 804296.34
B23: Post-F FD (T) | C23: =C20+C22 -> 38338126
B24: ESOP pool total post-F | C24: =C8*C23 -> 4983956.3
B25: ESOP top-up shares (new) | C25: =C24-C10 -> 589289.34
B26: Post-F unissued options | C26: =C24-Assumptions!C20 -> 2483956.3
B28: Anti-Dilution Block (broad-based WA)
C29: OCP-for-AD ($) | D29: Trigger? | E29: New Conv Price ($) | F29: New Ratio | G29: Issued Shares | H29: As-Converted Shares
B30: Seed | C30: =Assumptions!C27 -> 1 | D30: =IF($C$21<C30,"YES","no") -> no | E30: =IF($C$21<C30,C30*($C$9+$C$7/C30)/($C$9+$C$7/$C$21),C30) -> 1 | F30: =Assumptions!D27/E30 -> 1 | G30: =Assumptions!E27 -> 5000000 | H30: =IF($C$21<C30,Assumptions!F27/E30,G30) -> 5000000
B31: Series A | C31: =Assumptions!C28 -> 3 | D31: =IF($C$21<C31,"YES","no") -> no | E31: =IF($C$21<C31,C31*($C$9+$C$7/C31)/($C$9+$C$7/$C$21),C31) -> 3 | F31: =Assumptions!D28/E31 -> 1 | G31: =Assumptions!E28 -> 5000000 | H31: =IF($C$21<C31,Assumptions!F28/E31,G31) -> 5000000
B32: Series B | C32: =Assumptions!C29 -> 10 | D32: =IF($C$21<C32,"YES","no") -> no | E32: =IF($C$21<C32,C32*($C$9+$C$7/C32)/($C$9+$C$7/$C$21),C32) -> 10 | F32: =Assumptions!D29/E32 -> 1 | G32: =Assumptions!E29 -> 3000000 | H32: =IF($C$21<C32,Assumptions!F29/E32,G32) -> 3000000
B33: Series C | C33: =Assumptions!C30 -> 25 | D33: =IF($C$21<C33,"YES","no") -> no | E33: =IF($C$21<C33,C33*($C$9+$C$7/C33)/($C$9+$C$7/$C$21),C33) -> 25 | F33: =Assumptions!D30/E33 -> 1 | G33: =Assumptions!E30 -> 2400000 | H33: =IF($C$21<C33,Assumptions!F30/E33,G33) -> 2400000
B34: Series D | C34: =Assumptions!C31 -> 58.118347 | D34: =IF($C$21<C34,"YES","no") -> YES | E34: =IF($C$21<C34,C34*($C$9+$C$7/C34)/($C$9+$C$7/$C$21),C34) -> 57.670903 | F34: =Assumptions!D31/E34 -> 1.040386 | G34: =Assumptions!E31 -> 1720627 | H34: =IF($C$21<C34,Assumptions!F31/E34,G34) -> 1733976.7
B35: Series E | C35: =Assumptions!C32 -> 49.158311 | D35: =IF($C$21<C35,"YES","no") -> YES | E35: =IF($C$21<C35,C35*($C$9+$C$7/C35)/($C$9+$C$7/$C$21),C35) -> 48.90344 | F35: =Assumptions!D32/E35 -> 1.0052117 | G35: =Assumptions!E32 -> 6102667 | H35: =IF($C$21<C35,Assumptions!F32/E35,G35) -> 6134537.8
B37: Convertible Note Conversions
C38: Cap-Implied PPS ($) | D38: Disc-Implied PPS ($) | E38: Conv PPS ($) | F38: Branch | G38: Principal ($) | H38: Shares Issued
B39: Note A | C39: =Assumptions!D36/($C$20-$C$15*$C$20) -> 26.775845 | D39: =$C$21*(1-Assumptions!E36) -> 29.839748 | E39: =MIN(C39,D39) -> 26.775845 | F39: =IF(C39<D39,"cap","discount") -> cap | G39: =Assumptions!C36 -> 5000000 | H39: =G39/E39 -> 186735.47
B40: Note B | C40: =Assumptions!D37/($C$20-$C$17*$C$20) -> 42.735949 | D40: =$C$21*(1-Assumptions!E37) -> 31.704732 | E40: =MIN(C40,D40) -> 31.704732 | F40: =IF(C40<D40,"cap","discount") -> discount | G40: =Assumptions!C37 -> 3000000 | H40: =G40/E40 -> 94623.099
B42: Secondary Tender ($15M @ 0.85·F_PPS)
B43: Tender PPS ($) | C43: =Assumptions!C9*$C$21 -> 31.704732
B44: Tender shares (transferred to F_LEAD) | C44: =Assumptions!C8/C43 -> 473115.5
B45: Founder F1 share-out (50.00%) | C45: =C44*Assumptions!C16/(Assumptions!C16+Assumptions!C17+Assumptions!C18) -> 236557.75
B46: Founder F2 share-out (31.25%) | C46: =C44*Assumptions!C17/(Assumptions!C16+Assumptions!C17+Assumptions!C18) -> 147848.59
B47: Founder F3 share-out (18.75%) | C47: =C44*Assumptions!C18/(Assumptions!C16+Assumptions!C17+Assumptions!C18) -> 88709.156
B48: F_LEAD secondary common holding | C48: =C44 -> 473115.5
B50: Post-F Cap Table by Stakeholder
B51: Stakeholder | C51: Security Class | D51: Shares | E51: % FD
B52: Founder F1 (CEO) | C52: Common | D52: =Assumptions!C16-C45 -> 3763442.3 | E52: =D52/$C$23 -> 0.098164482
B53: Founder F2 (CTO) | C53: Common | D53: =Assumptions!C17-C46 -> 2352151.4 | E53: =D53/$C$23 -> 0.061352801
B54: Founder F3 (Chief Scientist) | C54: Common | D54: =Assumptions!C18-C47 -> 1411290.8 | E54: =D54/$C$23 -> 0.036811681
B55: Employee RSAs (10×100k) | C55: Common (RSA) | D55: =Assumptions!C19 -> 1000000 | E55: =D55/$C$23 -> 0.026083696
B56: F_LEAD — secondary common | C56: Common (tender) | D56: =C44 -> 473115.5 | E56: =D56/$C$23 -> 0.012340601
B57: Series Seed LP | C57: Series Seed | D57: =H30 -> 5000000 | E57: =D57/$C$23 -> 0.13041848
B58: Series A LP | C58: Series A | D58: =H31 -> 5000000 | E58: =D58/$C$23 -> 0.13041848
B59: Series B LP | C59: Series B | D59: =H32 -> 3000000 | E59: =D59/$C$23 -> 0.078251087
B60: Series C LP | C60: Series C | D60: =H33 -> 2400000 | E60: =D60/$C$23 -> 0.062600869
B61: Series D LP | C61: Series D (post-AD) | D61: =H34 -> 1733976.7 | E61: =D61/$C$23 -> 0.04522852
B62: Series E LPs (10 investors) | C62: Series E (post-AD) | D62: =H35 -> 6134537.8 | E62: =D62/$C$23 -> 0.16001142
B63: Note A holder | C63: Notes (F-equiv) | D63: =H39 -> 186735.47 | E63: =D63/$C$23 -> 0.0048707511
B64: Note B holder | C64: Notes (F-equiv) | D64: =H40 -> 94623.099 | E64: =D64/$C$23 -> 0.0024681201
B65: F_LEAD — Series F primary | C65: Series F | D65: =Assumptions!C12/$C$21 -> 536197.56 | E65: =D65/$C$23 -> 0.013986014
B66: Our Fund — Series F primary | C66: Series F | D66: =Assumptions!C11/$C$21 -> 268098.78 | E66: =D66/$C$23 -> 0.006993007
B67: Issued options (vested) | C67: Options | D67: =Assumptions!C20 -> 2500000 | E67: =D67/$C$23 -> 0.065209239
B68: Unissued options | C68: Options pool | D68: =$C$26 -> 2483956.3 | E68: =D68/$C$23 -> 0.064790761
B69: TOTAL post-F FD | D69: =SUM(D52:D68) -> 38338126 | E69: =SUM(E52:E68) -> 1
B70: Check | D70: =ROUND(D69-$C$23,2) -> 0

Sheet Return-Solver
B2: Kelvin Dynamics — Return Solver
B3: Required Series F ownership % for our $10M to return 3× ($30M) and 4× ($40M), per exit
B5: Base Case Inputs (from Pro-Forma)
B6: Series F PPS ($) | C6: ='Pro-Forma'!C21 -> 37.299685
B7: F primary total shares | C7: ='Pro-Forma'!C22 -> 804296.34
B8: F primary aggregate liquidation pref ($) | C8: =Assumptions!C7 -> 30000000
B9: Post-F FD (T) | C9: ='Pro-Forma'!C23 -> 38338126
B10: Our $10M check | C10: =Assumptions!C11 -> 10000000
B11: Our F primary shares | C11: =C10/C6 -> 268098.78
B12: Target multiple — 3× | C12: =Assumptions!C55 -> 3
B13: Target multiple — 4× | C13: =Assumptions!C56 -> 4
B14: Target proceeds — 3× ($) | C14: =C10*C12 -> 30000000
B15: Target proceeds — 4× ($) | C15: =C10*C13 -> 40000000
B17: Required Series F Ownership % per Exit
B18: Exit value ($) | D18: =Assumptions!C40 -> 700000000 | E18: =Assumptions!C41 -> 1200000000 | F18: =Assumptions!C42 -> 2000000000 | G18: =Assumptions!C43 -> 4000000000 | H18: =Assumptions!C44 -> 8000000000
B19: Equilibrium per-share ($) | D19: ='Waterfall'!I33 -> 8.3787244 | E19: ='Waterfall'!J33 -> 28.420213 | F19: ='Waterfall'!K33 -> 55.758771 | G19: ='Waterfall'!L33 -> 111.63276 | H19: ='Waterfall'!M33 -> 223.1958
B20: F election | D20: ='Waterfall'!I37 -> preference | E20: ='Waterfall'!J37 -> preference | F20: ='Waterfall'!K37 -> convert | G20: ='Waterfall'!L37 -> convert | H20: ='Waterfall'!M37 -> convert
B22: — 3× return target ($30M) —
B23: Required F ownership % (3×) | D23: =IF(D$20="preference",$C$14/$C$8,$C$14/($C$7*D$19)) -> 1 | E23: =IF(E$20="preference",$C$14/$C$8,$C$14/($C$7*E$19)) -> 1 | F23: =IF(F$20="preference",$C$14/$C$8,$C$14/($C$7*F$19)) -> 0.6689474 | G23: =IF(G$20="preference",$C$14/$C$8,$C$14/($C$7*G$19)) -> 0.33412847 | H23: =IF(H$20="preference",$C$14/$C$8,$C$14/($C$7*H$19)) -> 0.16711643
B24: Feasibility (3×) | D24: =IF(OR(D$23<=0,D$23>1),"INFEASIBLE","OK") -> OK | E24: =IF(OR(E$23<=0,E$23>1),"INFEASIBLE","OK") -> OK | F24: =IF(OR(F$23<=0,F$23>1),"INFEASIBLE","OK") -> OK | G24: =IF(OR(G$23<=0,G$23>1),"INFEASIBLE","OK") -> OK | H24: =IF(OR(H$23<=0,H$23>1),"INFEASIBLE","OK") -> OK
B25: Implied $ check (sanity recon) | D25: =IF(D$20="preference",D$23*$C$8,D$23*$C$7*D$19) -> 30000000 | E25: =IF(E$20="preference",E$23*$C$8,E$23*$C$7*E$19) -> 30000000 | F25: =IF(F$20="preference",F$23*$C$8,F$23*$C$7*F$19) -> 30000000 | G25: =IF(G$20="preference",G$23*$C$8,G$23*$C$7*G$19) -> 30000000 | H25: =IF(H$20="preference",H$23*$C$8,H$23*$C$7*H$19) -> 30000000
B27: — 4× return target ($40M) —
B28: Required F ownership % (4×) | D28: =IF(D$20="preference",$C$15/$C$8,$C$15/($C$7*D$19)) -> 1.3333333 | E28: =IF(E$20="preference",$C$15/$C$8,$C$15/($C$7*E$19)) -> 1.3333333 | F28: =IF(F$20="preference",$C$15/$C$8,$C$15/($C$7*F$19)) -> 0.89192987 | G28: =IF(G$20="preference",$C$15/$C$8,$C$15/($C$7*G$19)) -> 0.44550463 | H28: =IF(H$20="preference",$C$15/$C$8,$C$15/($C$7*H$19)) -> 0.2228219
B29: Feasibility (4×) | D29: =IF(OR(D$28<=0,D$28>1),"INFEASIBLE","OK") -> INFEASIBLE | E29: =IF(OR(E$28<=0,E$28>1),"INFEASIBLE","OK") -> INFEASIBLE | F29: =IF(OR(F$28<=0,F$28>1),"INFEASIBLE","OK") -> OK | G29: =IF(OR(G$28<=0,G$28>1),"INFEASIBLE","OK") -> OK | H29: =IF(OR(H$28<=0,H$28>1),"INFEASIBLE","OK") -> OK
B30: Implied $ check (sanity recon) | D30: =IF(D$20="preference",D$28*$C$8,D$28*$C$7*D$19) -> 40000000 | E30: =IF(E$20="preference",E$28*$C$8,E$28*$C$7*E$19) -> 40000000 | F30: =IF(F$20="preference",F$28*$C$8,F$28*$C$7*F$19) -> 40000000 | G30: =IF(G$20="preference",G$28*$C$8,G$28*$C$7*G$19) -> 40000000 | H30: =IF(H$20="preference",H$28*$C$8,H$28*$C$7*H$19) -> 40000000
B32: Reference: actual base-case position (our $10M = 1/3 of F)
B33: Our actual F ownership % | D33: =$C$11/$C$7 -> 0.33333333 | E33: =$C$11/$C$7 -> 0.33333333 | F33: =$C$11/$C$7 -> 0.33333333 | G33: =$C$11/$C$7 -> 0.33333333 | H33: =$C$11/$C$7 -> 0.33333333
B34: Our proceeds (base case, $) | D34: =IF(D$20="preference",($C$11/$C$7)*$C$8,$C$11*D$19) -> 10000000 | E34: =IF(E$20="preference",($C$11/$C$7)*$C$8,$C$11*E$19) -> 10000000 | F34: =IF(F$20="preference",($C$11/$C$7)*$C$8,$C$11*F$19) -> 14948858 | G34: =IF(G$20="preference",($C$11/$C$7)*$C$8,$C$11*G$19) -> 29928608 | H34: =IF(H$20="preference",($C$11/$C$7)*$C$8,$C$11*H$19) -> 59838522
B35: Our actual return multiple | D35: =D$34/$C$10 -> 1 | E35: =E$34/$C$10 -> 1 | F35: =F$34/$C$10 -> 1.4948858 | G35: =G$34/$C$10 -> 2.9928608 | H35: =H$34/$C$10 -> 5.9838522
B37: Note: 3× / 4× pcts > 100% are infeasible (our $10M cannot own >100% of Series F primary).
B38: At low exits (where F elects preference), required pct = target / F_pref ($30M); 4× target requires $40M / $30M = 133% which is infeasible.

Sheet Sensitivity
B2: Kelvin Dynamics — Sensitivity Analysis
B3: 3×3: ESOP refresh × Series F pre-money. Each cell re-solves round + waterfall at $2B exit.
B5: Scenario Engine — Round Fixed Point + Waterfall at $2B
B6: Scenario | C6: ="$"&TEXT(Assumptions!C50/1000000000,"0.0")&"B / "&TEXT(Assumptions!C47,"0%") -> $1.2B / 11% | D6: ="$"&TEXT(Assumptions!C50/1000000000,"0.0")&"B / "&TEXT(Assumptions!C48,"0%") -> $1.2B / 13% | E6: ="$"&TEXT(Assumptions!C50/1000000000,"0.0")&"B / "&TEXT(Assumptions!C49,"0%") -> $1.2B / 15% | F6: ="$"&TEXT(Assumptions!C51/1000000000,"0.0")&"B / "&TEXT(Assumptions!C47,"0%") -> $1.4B / 11% | G6: ="$"&TEXT(Assumptions!C51/1000000000,"0.0")&"B / "&TEXT(Assumptions!C48,"0%") -> $1.4B / 13% | H6: ="$"&TEXT(Assumptions!C51/1000000000,"0.0")&"B / "&TEXT(Assumptions!C49,"0%") -> $1.4B / 15% | I6: ="$"&TEXT(Assumptions!C52/1000000000,"0.0")&"B / "&TEXT(Assumptions!C47,"0%") -> $1.8B / 11% | J6: ="$"&TEXT(Assumptions!C52/1000000000,"0.0")&"B / "&TEXT(Assumptions!C48,"0%") -> $1.8B / 13% | K6: ="$"&TEXT(Assumptions!C52/1000000000,"0.0")&"B / "&TEXT(Assumptions!C49,"0%") -> $1.8B / 15%
B7: Pre-money ($) | C7: =Assumptions!C50 -> 1200000000 | D7: =Assumptions!C50 -> 1200000000 | E7: =Assumptions!C50 -> 1200000000 | F7: =Assumptions!C51 -> 1400000000 | G7: =Assumptions!C51 -> 1400000000 | H7: =Assumptions!C51 -> 1400000000 | I7: =Assumptions!C52 -> 1800000000 | J7: =Assumptions!C52 -> 1800000000 | K7: =Assumptions!C52 -> 1800000000
B8: ESOP target | C8: =Assumptions!C47 -> 0.11 | D8: =Assumptions!C48 -> 0.13 | E8: =Assumptions!C49 -> 0.15 | F8: =Assumptions!C47 -> 0.11 | G8: =Assumptions!C48 -> 0.13 | H8: =Assumptions!C49 -> 0.15 | I8: =Assumptions!C47 -> 0.11 | J8: =Assumptions!C48 -> 0.13 | K8: =Assumptions!C49 -> 0.15
B10: c_A (Note A coef given pre) | C10: =IF(Assumptions!$D$36+Assumptions!$C$36<C$7*(1-Assumptions!$E$36),Assumptions!$C$36/(Assumptions!$D$36+Assumptions!$C$36),Assumptions!$C$36/(C$7*(1-Assumptions!$E$36))) -> 0.0052083333 | D10: =IF(Assumptions!$D$36+Assumptions!$C$36<D$7*(1-Assumptions!$E$36),Assumptions!$C$36/(Assumptions!$D$36+Assumptions!$C$36),Assumptions!$C$36/(D$7*(1-Assumptions!$E$36))) -> 0.0052083333 | E10: =IF(Assumptions!$D$36+Assumptions!$C$36<E$7*(1-Assumptions!$E$36),Assumptions!$C$36/(Assumptions!$D$36+Assumptions!$C$36),Assumptions!$C$36/(E$7*(1-Assumptions!$E$36))) -> 0.0052083333 | F10: =IF(Assumptions!$D$36+Assumptions!$C$36<F$7*(1-Assumptions!$E$36),Assumptions!$C$36/(Assumptions!$D$36+Assumptions!$C$36),Assumptions!$C$36/(F$7*(1-Assumptions!$E$36))) -> 0.0049751244 | G10: =IF(Assumptions!$D$36+Assumptions!$C$36<G$7*(1-Assumptions!$E$36),Assumptions!$C$36/(Assumptions!$D$36+Assumptions!$C$36),Assumptions!$C$36/(G$7*(1-Assumptions!$E$36))) -> 0.0049751244 | H10: =IF(Assumptions!$D$36+Assumptions!$C$36<H$7*(1-Assumptions!$E$36),Assumptions!$C$36/(Assumptions!$D$36+Assumptions!$C$36),Assumptions!$C$36/(H$7*(1-Assumptions!$E$36))) -> 0.0049751244 | I10: =IF(Assumptions!$D$36+Assumptions!$C$36<I$7*(1-Assumptions!$E$36),Assumptions!$C$36/(Assumptions!$D$36+Assumptions!$C$36),Assumptions!$C$36/(I$7*(1-Assumptions!$E$36))) -> 0.0049751244 | J10: =IF(Assumptions!$D$36+Assumptions!$C$36<J$7*(1-Assumptions!$E$36),Assumptions!$C$36/(Assumptions!$D$36+Assumptions!$C$36),Assumptions!$C$36/(J$7*(1-Assumptions!$E$36))) -> 0.0049751244 | K10: =IF(Assumptions!$D$36+Assumptions!$C$36<K$7*(1-Assumptions!$E$36),Assumptions!$C$36/(Assumptions!$D$36+Assumptions!$C$36),Assumptions!$C$36/(K$7*(1-Assumptions!$E$36))) -> 0.0049751244
B11: c_B (Note B coef given pre) | C11: =IF(Assumptions!$D$37+Assumptions!$C$37<C$7*(1-Assumptions!$E$37),Assumptions!$C$37/(Assumptions!$D$37+Assumptions!$C$37),Assumptions!$C$37/(C$7*(1-Assumptions!$E$37))) -> 0.0029411765 | D11: =IF(Assumptions!$D$37+Assumptions!$C$37<D$7*(1-Assumptions!$E$37),Assumptions!$C$37/(Assumptions!$D$37+Assumptions!$C$37),Assumptions!$C$37/(D$7*(1-Assumptions!$E$37))) -> 0.0029411765 | E11: =IF(Assumptions!$D$37+Assumptions!$C$37<E$7*(1-Assumptions!$E$37),Assumptions!$C$37/(Assumptions!$D$37+Assumptions!$C$37),Assumptions!$C$37/(E$7*(1-Assumptions!$E$37))) -> 0.0029411765 | F11: =IF(Assumptions!$D$37+Assumptions!$C$37<F$7*(1-Assumptions!$E$37),Assumptions!$C$37/(Assumptions!$D$37+Assumptions!$C$37),Assumptions!$C$37/(F$7*(1-Assumptions!$E$37))) -> 0.0025210084 | G11: =IF(Assumptions!$D$37+Assumptions!$C$37<G$7*(1-Assumptions!$E$37),Assumptions!$C$37/(Assumptions!$D$37+Assumptions!$C$37),Assumptions!$C$37/(G$7*(1-Assumptions!$E$37))) -> 0.0025210084 | H11: =IF(Assumptions!$D$37+Assumptions!$C$37<H$7*(1-Assumptions!$E$37),Assumptions!$C$37/(Assumptions!$D$37+Assumptions!$C$37),Assumptions!$C$37/(H$7*(1-Assumptions!$E$37))) -> 0.0025210084 | I11: =IF(Assumptions!$D$37+Assumptions!$C$37<I$7*(1-Assumptions!$E$37),Assumptions!$C$37/(Assumptions!$D$37+Assumptions!$C$37),Assumptions!$C$37/(I$7*(1-Assumptions!$E$37))) -> 0.0019607843 | J11: =IF(Assumptions!$D$37+Assumptions!$C$37<J$7*(1-Assumptions!$E$37),Assumptions!$C$37/(Assumptions!$D$37+Assumptions!$C$37),Assumptions!$C$37/(J$7*(1-Assumptions!$E$37))) -> 0.0019607843 | K11: =IF(Assumptions!$D$37+Assumptions!$C$37<K$7*(1-Assumptions!$E$37),Assumptions!$C$37/(Assumptions!$D$37+Assumptions!$C$37),Assumptions!$C$37/(K$7*(1-Assumptions!$E$37))) -> 0.0019607843
B12: α_D coefficient | C12: =Assumptions!F31/(Assumptions!C31*(Assumptions!C23+Assumptions!C7/Assumptions!C31)) -> 0.046335438 | D12: =Assumptions!F31/(Assumptions!C31*(Assumptions!C23+Assumptions!C7/Assumptions!C31)) -> 0.046335438 | E12: =Assumptions!F31/(Assumptions!C31*(Assumptions!C23+Assumptions!C7/Assumptions!C31)) -> 0.046335438 | F12: =Assumptions!F31/(Assumptions!C31*(Assumptions!C23+Assumptions!C7/Assumptions!C31)) -> 0.046335438 | G12: =Assumptions!F31/(Assumptions!C31*(Assumptions!C23+Assumptions!C7/Assumptions!C31)) -> 0.046335438 | H12: =Assumptions!F31/(Assumptions!C31*(Assumptions!C23+Assumptions!C7/Assumptions!C31)) -> 0.046335438 | I12: =Assumptions!F31/(Assumptions!C31*(Assumptions!C23+Assumptions!C7/Assumptions!C31)) -> 0.046335438 | J12: =Assumptions!F31/(Assumptions!C31*(Assumptions!C23+Assumptions!C7/Assumptions!C31)) -> 0.046335438 | K12: =Assumptions!F31/(Assumptions!C31*(Assumptions!C23+Assumptions!C7/Assumptions!C31)) -> 0.046335438
B13: α_E coefficient | C13: =Assumptions!F32/(Assumptions!C32*(Assumptions!C23+Assumptions!C7/Assumptions!C32)) -> 0.16392752 | D13: =Assumptions!F32/(Assumptions!C32*(Assumptions!C23+Assumptions!C7/Assumptions!C32)) -> 0.16392752 | E13: =Assumptions!F32/(Assumptions!C32*(Assumptions!C23+Assumptions!C7/Assumptions!C32)) -> 0.16392752 | F13: =Assumptions!F32/(Assumptions!C32*(Assumptions!C23+Assumptions!C7/Assumptions!C32)) -> 0.16392752 | G13: =Assumptions!F32/(Assumptions!C32*(Assumptions!C23+Assumptions!C7/Assumptions!C32)) -> 0.16392752 | H13: =Assumptions!F32/(Assumptions!C32*(Assumptions!C23+Assumptions!C7/Assumptions!C32)) -> 0.16392752 | I13: =Assumptions!F32/(Assumptions!C32*(Assumptions!C23+Assumptions!C7/Assumptions!C32)) -> 0.16392752 | J13: =Assumptions!F32/(Assumptions!C32*(Assumptions!C23+Assumptions!C7/Assumptions!C32)) -> 0.16392752 | K13: =Assumptions!F32/(Assumptions!C32*(Assumptions!C23+Assumptions!C7/Assumptions!C32)) -> 0.16392752
B14: K_const numerator | C14: =(Assumptions!$C$23-Assumptions!$C$22)-Assumptions!$E$31-Assumptions!$E$32+(C$12+C$13)*Assumptions!$C$23 -> 32099401 | D14: =(Assumptions!$C$23-Assumptions!$C$22)-Assumptions!$E$31-Assumptions!$E$32+(D$12+D$13)*Assumptions!$C$23 -> 32099401 | E14: =(Assumptions!$C$23-Assumptions!$C$22)-Assumptions!$E$31-Assumptions!$E$32+(E$12+E$13)*Assumptions!$C$23 -> 32099401 | F14: =(Assumptions!$C$23-Assumptions!$C$22)-Assumptions!$E$31-Assumptions!$E$32+(F$12+F$13)*Assumptions!$C$23 -> 32099401 | G14: =(Assumptions!$C$23-Assumptions!$C$22)-Assumptions!$E$31-Assumptions!$E$32+(G$12+G$13)*Assumptions!$C$23 -> 32099401 | H14: =(Assumptions!$C$23-Assumptions!$C$22)-Assumptions!$E$31-Assumptions!$E$32+(H$12+H$13)*Assumptions!$C$23 -> 32099401 | I14: =(Assumptions!$C$23-Assumptions!$C$22)-Assumptions!$E$31-Assumptions!$E$32+(I$12+I$13)*Assumptions!$C$23 -> 32099401 | J14: =(Assumptions!$C$23-Assumptions!$C$22)-Assumptions!$E$31-Assumptions!$E$32+(J$12+J$13)*Assumptions!$C$23 -> 32099401 | K14: =(Assumptions!$C$23-Assumptions!$C$22)-Assumptions!$E$31-Assumptions!$E$32+(K$12+K$13)*Assumptions!$C$23 -> 32099401
B15: Denom (form 1, top-up positive) | C15: =(1-C$8)-(C$12+C$13+C$8)*Assumptions!$C$7/C$7-C$10-C$11 -> 0.87384392 | D15: =(1-D$8)-(D$12+D$13+D$8)*Assumptions!$C$7/D$7-D$10-D$11 -> 0.85334392 | E15: =(1-E$8)-(E$12+E$13+E$8)*Assumptions!$C$7/E$7-E$10-E$11 -> 0.83284392 | F15: =(1-F$8)-(F$12+F$13+F$8)*Assumptions!$C$7/F$7-F$10-F$11 -> 0.87564109 | G15: =(1-G$8)-(G$12+G$13+G$8)*Assumptions!$C$7/G$7-G$10-G$11 -> 0.85521252 | H15: =(1-H$8)-(H$12+H$13+H$8)*Assumptions!$C$7/H$7-H$10-H$11 -> 0.83478395 | I15: =(1-I$8)-(I$12+I$13+I$8)*Assumptions!$C$7/I$7-I$10-I$11 -> 0.87772638 | J15: =(1-J$8)-(J$12+J$13+J$8)*Assumptions!$C$7/J$7-J$10-J$11 -> 0.85739304 | K15: =(1-K$8)-(K$12+K$13+K$8)*Assumptions!$C$7/K$7-K$10-K$11 -> 0.83705971
B16: P1 (form 1) | C16: =C$14/C$15 -> 36733563 | D16: =D$14/D$15 -> 37616019 | E16: =E$14/E$15 -> 38541917 | F16: =F$14/F$15 -> 36658171 | G16: =G$14/G$15 -> 37533829 | H16: =H$14/H$15 -> 38452345 | I16: =I$14/I$15 -> 36571079 | J16: =J$14/J$15 -> 37438373 | K16: =K$14/K$15 -> 38347803
B17: T1 (form 1) | C17: =C$16*(C$7+Assumptions!$C$7)/C$7 -> 37651902 | D17: =D$16*(D$7+Assumptions!$C$7)/D$7 -> 38556419 | E17: =E$16*(E$7+Assumptions!$C$7)/E$7 -> 39505464 | F17: =F$16*(F$7+Assumptions!$C$7)/F$7 -> 37443703 | G17: =G$16*(G$7+Assumptions!$C$7)/G$7 -> 38338126 | H17: =H$16*(H$7+Assumptions!$C$7)/H$7 -> 39276324 | I17: =I$16*(I$7+Assumptions!$C$7)/I$7 -> 37180597 | J17: =J$16*(J$7+Assumptions!$C$7)/J$7 -> 38062346 | K17: =K$16*(K$7+Assumptions!$C$7)/K$7 -> 38986933
B18: Form 1 ESOP target $T1 | C18: =C$8*C$17 -> 4141709.3 | D18: =D$8*D$17 -> 5012334.5 | E18: =E$8*E$17 -> 5925819.7 | F18: =F$8*F$17 -> 4118807.3 | G18: =G$8*G$17 -> 4983956.3 | H18: =H$8*H$17 -> 5891448.6 | I18: =I$8*I$17 -> 4089865.7 | J18: =J$8*J$17 -> 4948105 | K18: =K$8*K$17 -> 5848039.9
B19: Form 1 valid? (target > pre-F pool) | C19: =IF(C$18>Assumptions!$C$22,1,0) -> 0 | D19: =IF(D$18>Assumptions!$C$22,1,0) -> 1 | E19: =IF(E$18>Assumptions!$C$22,1,0) -> 1 | F19: =IF(F$18>Assumptions!$C$22,1,0) -> 0 | G19: =IF(G$18>Assumptions!$C$22,1,0) -> 1 | H19: =IF(H$18>Assumptions!$C$22,1,0) -> 1 | I19: =IF(I$18>Assumptions!$C$22,1,0) -> 0 | J19: =IF(J$18>Assumptions!$C$22,1,0) -> 1 | K19: =IF(K$18>Assumptions!$C$22,1,0) -> 1
B20: Denom (form 2, pool stays at pre-F) | C20: =(1-C$10-C$11)-(C$12+C$13)*Assumptions!$C$7/C$7 -> 0.98659392 | D20: =(1-D$10-D$11)-(D$12+D$13)*Assumptions!$C$7/D$7 -> 0.98659392 | E20: =(1-E$10-E$11)-(E$12+E$13)*Assumptions!$C$7/E$7 -> 0.98659392 | F20: =(1-F$10-F$11)-(F$12+F$13)*Assumptions!$C$7/F$7 -> 0.98799823 | G20: =(1-G$10-G$11)-(G$12+G$13)*Assumptions!$C$7/G$7 -> 0.98799823 | H20: =(1-H$10-H$11)-(H$12+H$13)*Assumptions!$C$7/H$7 -> 0.98799823 | I20: =(1-I$10-I$11)-(I$12+I$13)*Assumptions!$C$7/I$7 -> 0.98955971 | J20: =(1-J$10-J$11)-(J$12+J$13)*Assumptions!$C$7/J$7 -> 0.98955971 | K20: =(1-K$10-K$11)-(K$12+K$13)*Assumptions!$C$7/K$7 -> 0.98955971
B21: P2 (form 2) | C21: =(C$14+Assumptions!$C$22)/C$20 -> 36989958 | D21: =(D$14+Assumptions!$C$22)/D$20 -> 36989958 | E21: =(E$14+Assumptions!$C$22)/E$20 -> 36989958 | F21: =(F$14+Assumptions!$C$22)/F$20 -> 36937382 | G21: =(G$14+Assumptions!$C$22)/G$20 -> 36937382 | H21: =(H$14+Assumptions!$C$22)/H$20 -> 36937382 | I21: =(I$14+Assumptions!$C$22)/I$20 -> 36879096 | J21: =(J$14+Assumptions!$C$22)/J$20 -> 36879096 | K21: =(K$14+Assumptions!$C$22)/K$20 -> 36879096
B22: Pre-money FD (P, chosen) | C22: =IF(C$19=1,C$16,C$21) -> 36989958 | D22: =IF(D$19=1,D$16,D$21) -> 37616019 | E22: =IF(E$19=1,E$16,E$21) -> 38541917 | F22: =IF(F$19=1,F$16,F$21) -> 36937382 | G22: =IF(G$19=1,G$16,G$21) -> 37533829 | H22: =IF(H$19=1,H$16,H$21) -> 38452345 | I22: =IF(I$19=1,I$16,I$21) -> 36879096 | J22: =IF(J$19=1,J$16,J$21) -> 37438373 | K22: =IF(K$19=1,K$16,K$21) -> 38347803
B23: Series F PPS ($) | C23: =C$7/C$22 -> 32.441237 | D23: =D$7/D$22 -> 31.901303 | E23: =E$7/E$22 -> 31.134933 | F23: =F$7/F$22 -> 37.901983 | G23: =G$7/G$22 -> 37.299685 | H23: =H$7/H$22 -> 36.408702 | I23: =I$7/I$22 -> 48.808138 | J23: =J$7/J$22 -> 48.079012 | K23: =K$7/K$22 -> 46.938804
B24: New F primary shares | C24: =Assumptions!$C$7/C$23 -> 924748.96 | D24: =Assumptions!$C$7/D$23 -> 940400.47 | E24: =Assumptions!$C$7/E$23 -> 963547.91 | F24: =Assumptions!$C$7/F$23 -> 791515.32 | G24: =Assumptions!$C$7/G$23 -> 804296.34 | H24: =Assumptions!$C$7/H$23 -> 823978.83 | I24: =Assumptions!$C$7/I$23 -> 614651.6 | J24: =Assumptions!$C$7/J$23 -> 623972.89 | K24: =Assumptions!$C$7/K$23 -> 639130.05
B25: Post-F FD (T) | C25: =C$22+C$24 -> 37914707 | D25: =D$22+D$24 -> 38556419 | E25: =E$22+E$24 -> 39505464 | F25: =F$22+F$24 -> 37728897 | G25: =G$22+G$24 -> 38338126 | H25: =H$22+H$24 -> 39276324 | I25: =I$22+I$24 -> 37493748 | J25: =J$22+J$24 -> 38062346 | K25: =K$22+K$24 -> 38986933
B26: ESOP pool (post-F) | C26: =MAX(C$8*C$25,Assumptions!$C$22) -> 4394667 | D26: =MAX(D$8*D$25,Assumptions!$C$22) -> 5012334.5 | E26: =MAX(E$8*E$25,Assumptions!$C$22) -> 5925819.7 | F26: =MAX(F$8*F$25,Assumptions!$C$22) -> 4394667 | G26: =MAX(G$8*G$25,Assumptions!$C$22) -> 4983956.3 | H26: =MAX(H$8*H$25,Assumptions!$C$22) -> 5891448.6 | I26: =MAX(I$8*I$25,Assumptions!$C$22) -> 4394667 | J26: =MAX(J$8*J$25,Assumptions!$C$22) -> 4948105 | K26: =MAX(K$8*K$25,Assumptions!$C$22) -> 5848039.9
B27: AD_D as-converted shares | C27: =Assumptions!$F$31*(Assumptions!$C$23+C$24)/(Assumptions!$C$31*(Assumptions!$C$23+Assumptions!$C$7/Assumptions!$C$31)) -> 1739557.9 | D27: =Assumptions!$F$31*(Assumptions!$C$23+D$24)/(Assumptions!$C$31*(Assumptions!$C$23+Assumptions!$C$7/Assumptions!$C$31)) -> 1740283.1 | E27: =Assumptions!$F$31*(Assumptions!$C$23+E$24)/(Assumptions!$C$31*(Assumptions!$C$23+Assumptions!$C$7/Assumptions!$C$31)) -> 1741355.7 | F27: =Assumptions!$F$31*(Assumptions!$C$23+F$24)/(Assumptions!$C$31*(Assumptions!$C$23+Assumptions!$C$7/Assumptions!$C$31)) -> 1733384.5 | G27: =Assumptions!$F$31*(Assumptions!$C$23+G$24)/(Assumptions!$C$31*(Assumptions!$C$23+Assumptions!$C$7/Assumptions!$C$31)) -> 1733976.7 | H27: =Assumptions!$F$31*(Assumptions!$C$23+H$24)/(Assumptions!$C$31*(Assumptions!$C$23+Assumptions!$C$7/Assumptions!$C$31)) -> 1734888.7 | I27: =Assumptions!$F$31*(Assumptions!$C$23+I$24)/(Assumptions!$C$31*(Assumptions!$C$23+Assumptions!$C$7/Assumptions!$C$31)) -> 1725189.4 | J27: =Assumptions!$F$31*(Assumptions!$C$23+J$24)/(Assumptions!$C$31*(Assumptions!$C$23+Assumptions!$C$7/Assumptions!$C$31)) -> 1725621.3 | K27: =Assumptions!$F$31*(Assumptions!$C$23+K$24)/(Assumptions!$C$31*(Assumptions!$C$23+Assumptions!$C$7/Assumptions!$C$31)) -> 1726323.6
B28: AD_E as-converted shares | C28: =Assumptions!$F$32*(Assumptions!$C$23+C$24)/(Assumptions!$C$32*(Assumptions!$C$23+Assumptions!$C$7/Assumptions!$C$32)) -> 6154283.3 | D28: =Assumptions!$F$32*(Assumptions!$C$23+D$24)/(Assumptions!$C$32*(Assumptions!$C$23+Assumptions!$C$7/Assumptions!$C$32)) -> 6156849 | E28: =Assumptions!$F$32*(Assumptions!$C$23+E$24)/(Assumptions!$C$32*(Assumptions!$C$23+Assumptions!$C$7/Assumptions!$C$32)) -> 6160643.5 | F28: =Assumptions!$F$32*(Assumptions!$C$23+F$24)/(Assumptions!$C$32*(Assumptions!$C$23+Assumptions!$C$7/Assumptions!$C$32)) -> 6132442.6 | G28: =Assumptions!$F$32*(Assumptions!$C$23+G$24)/(Assumptions!$C$32*(Assumptions!$C$23+Assumptions!$C$7/Assumptions!$C$32)) -> 6134537.8 | H28: =Assumptions!$F$32*(Assumptions!$C$23+H$24)/(Assumptions!$C$32*(Assumptions!$C$23+Assumptions!$C$7/Assumptions!$C$32)) -> 6137764.3 | I28: =Assumptions!$F$32*(Assumptions!$C$23+I$24)/(Assumptions!$C$32*(Assumptions!$C$23+Assumptions!$C$7/Assumptions!$C$32)) -> 6103449.8 | J28: =Assumptions!$F$32*(Assumptions!$C$23+J$24)/(Assumptions!$C$32*(Assumptions!$C$23+Assumptions!$C$7/Assumptions!$C$32)) -> 6104977.8 | K28: =Assumptions!$F$32*(Assumptions!$C$23+K$24)/(Assumptions!$C$32*(Assumptions!$C$23+Assumptions!$C$7/Assumptions!$C$32)) -> 6107462.5
B29: Note A shares (= c_A × P) | C29: =C$10*C$22 -> 192656.03 | D29: =D$10*D$22 -> 195916.76 | E29: =E$10*E$22 -> 200739.15 | F29: =F$10*F$22 -> 183768.07 | G29: =G$10*G$22 -> 186735.47 | H29: =H$10*H$22 -> 191305.2 | I29: =I$10*I$22 -> 183478.09 | J29: =J$10*J$22 -> 186260.56 | K29: =K$10*K$22 -> 190785.09
B30: Note B shares (= c_B × P) | C30: =C$11*C$22 -> 108793.99 | D30: =D$11*D$22 -> 110635.35 | E30: =E$11*E$22 -> 113358.58 | F30: =F$11*F$22 -> 93119.449 | G30: =G$11*G$22 -> 94623.099 | H30: =H$11*H$22 -> 96938.686 | I30: =I$11*I$22 -> 72311.953 | J30: =J$11*J$22 -> 73408.575 | K30: =K$11*K$22 -> 75191.77
B31: Note A branch | C31: =IF(Assumptions!$D$36+Assumptions!$C$36<C$7*(1-Assumptions!$E$36),"cap","discount") -> discount | D31: =IF(Assumptions!$D$36+Assumptions!$C$36<D$7*(1-Assumptions!$E$36),"cap","discount") -> discount | E31: =IF(Assumptions!$D$36+Assumptions!$C$36<E$7*(1-Assumptions!$E$36),"cap","discount") -> discount | F31: =IF(Assumptions!$D$36+Assumptions!$C$36<F$7*(1-Assumptions!$E$36),"cap","discount") -> cap | G31: =IF(Assumptions!$D$36+Assumptions!$C$36<G$7*(1-Assumptions!$E$36),"cap","discount") -> cap | H31: =IF(Assumptions!$D$36+Assumptions!$C$36<H$7*(1-Assumptions!$E$36),"cap","discount") -> cap | I31: =IF(Assumptions!$D$36+Assumptions!$C$36<I$7*(1-Assumptions!$E$36),"cap","discount") -> cap | J31: =IF(Assumptions!$D$36+Assumptions!$C$36<J$7*(1-Assumptions!$E$36),"cap","discount") -> cap | K31: =IF(Assumptions!$D$36+Assumptions!$C$36<K$7*(1-Assumptions!$E$36),"cap","discount") -> cap
B32: Note B branch | C32: =IF(Assumptions!$D$37+Assumptions!$C$37<C$7*(1-Assumptions!$E$37),"cap","discount") -> discount | D32: =IF(Assumptions!$D$37+Assumptions!$C$37<D$7*(1-Assumptions!$E$37),"cap","discount") -> discount | E32: =IF(Assumptions!$D$37+Assumptions!$C$37<E$7*(1-Assumptions!$E$37),"cap","discount") -> discount | F32: =IF(Assumptions!$D$37+Assumptions!$C$37<F$7*(1-Assumptions!$E$37),"cap","discount") -> discount | G32: =IF(Assumptions!$D$37+Assumptions!$C$37<G$7*(1-Assumptions!$E$37),"cap","discount") -> discount | H32: =IF(Assumptions!$D$37+Assumptions!$C$37<H$7*(1-Assumptions!$E$37),"cap","discount") -> discount | I32: =IF(Assumptions!$D$37+Assumptions!$C$37<I$7*(1-Assumptions!$E$37),"cap","discount") -> discount | J32: =IF(Assumptions!$D$37+Assumptions!$C$37<J$7*(1-Assumptions!$E$37),"cap","discount") -> discount | K32: =IF(Assumptions!$D$37+Assumptions!$C$37<K$7*(1-Assumptions!$E$37),"cap","discount") -> discount
B34: ψ_Seed | C34: =Assumptions!$F$27/Assumptions!$E$27 -> 1 | D34: =Assumptions!$F$27/Assumptions!$E$27 -> 1 | E34: =Assumptions!$F$27/Assumptions!$E$27 -> 1 | F34: =Assumptions!$F$27/Assumptions!$E$27 -> 1 | G34: =Assumptions!$F$27/Assumptions!$E$27 -> 1 | H34: =Assumptions!$F$27/Assumptions!$E$27 -> 1 | I34: =Assumptions!$F$27/Assumptions!$E$27 -> 1 | J34: =Assumptions!$F$27/Assumptions!$E$27 -> 1 | K34: =Assumptions!$F$27/Assumptions!$E$27 -> 1
B35: ψ_A | C35: =Assumptions!$F$28/Assumptions!$E$28 -> 3 | D35: =Assumptions!$F$28/Assumptions!$E$28 -> 3 | E35: =Assumptions!$F$28/Assumptions!$E$28 -> 3 | F35: =Assumptions!$F$28/Assumptions!$E$28 -> 3 | G35: =Assumptions!$F$28/Assumptions!$E$28 -> 3 | H35: =Assumptions!$F$28/Assumptions!$E$28 -> 3 | I35: =Assumptions!$F$28/Assumptions!$E$28 -> 3 | J35: =Assumptions!$F$28/Assumptions!$E$28 -> 3 | K35: =Assumptions!$F$28/Assumptions!$E$28 -> 3
B36: ψ_B | C36: =Assumptions!$F$29/Assumptions!$E$29 -> 10 | D36: =Assumptions!$F$29/Assumptions!$E$29 -> 10 | E36: =Assumptions!$F$29/Assumptions!$E$29 -> 10 | F36: =Assumptions!$F$29/Assumptions!$E$29 -> 10 | G36: =Assumptions!$F$29/Assumptions!$E$29 -> 10 | H36: =Assumptions!$F$29/Assumptions!$E$29 -> 10 | I36: =Assumptions!$F$29/Assumptions!$E$29 -> 10 | J36: =Assumptions!$F$29/Assumptions!$E$29 -> 10 | K36: =Assumptions!$F$29/Assumptions!$E$29 -> 10
B37: ψ_C | C37: =Assumptions!$F$30/Assumptions!$E$30 -> 25 | D37: =Assumptions!$F$30/Assumptions!$E$30 -> 25 | E37: =Assumptions!$F$30/Assumptions!$E$30 -> 25 | F37: =Assumptions!$F$30/Assumptions!$E$30 -> 25 | G37: =Assumptions!$F$30/Assumptions!$E$30 -> 25 | H37: =Assumptions!$F$30/Assumptions!$E$30 -> 25 | I37: =Assumptions!$F$30/Assumptions!$E$30 -> 25 | J37: =Assumptions!$F$30/Assumptions!$E$30 -> 25 | K37: =Assumptions!$F$30/Assumptions!$E$30 -> 25
B38: ψ_F (= F_PPS) | C38: =C$23 -> 32.441237 | D38: =D$23 -> 31.901303 | E38: =E$23 -> 31.134933 | F38: =F$23 -> 37.901983 | G38: =G$23 -> 37.299685 | H38: =H$23 -> 36.408702 | I38: =I$23 -> 48.808138 | J38: =J$23 -> 48.079012 | K38: =K$23 -> 46.938804
B39: ψ_E (= 300M / AD_E shares) | C39: =Assumptions!$F$32/C$28 -> 48.746537 | D39: =Assumptions!$F$32/D$28 -> 48.726223 | E39: =Assumptions!$F$32/E$28 -> 48.696212 | F39: =Assumptions!$F$32/F$28 -> 48.920148 | G39: =Assumptions!$F$32/G$28 -> 48.90344 | H39: =Assumptions!$F$32/H$28 -> 48.877732 | I39: =Assumptions!$F$32/I$28 -> 49.15253 | J39: =Assumptions!$F$32/J$28 -> 49.140228 | K39: =Assumptions!$F$32/K$28 -> 49.120236
B40: ψ_D (= 100M / AD_D shares) | C40: =Assumptions!$F$31/C$27 -> 57.485871 | D40: =Assumptions!$F$31/D$27 -> 57.461915 | E40: =Assumptions!$F$31/E$27 -> 57.426522 | F40: =Assumptions!$F$31/F$27 -> 57.690606 | G40: =Assumptions!$F$31/G$27 -> 57.670903 | H40: =Assumptions!$F$31/H$27 -> 57.640586 | I40: =Assumptions!$F$31/I$27 -> 57.96465 | J40: =Assumptions!$F$31/J$27 -> 57.950142 | K40: =Assumptions!$F$31/K$27 -> 57.926567
B42: PS_{k=0} candidate | C42: =IF((Assumptions!$C$42-(Assumptions!$F$27+Assumptions!$F$28+Assumptions!$F$29+Assumptions!$F$30+Assumptions!$F$31+Assumptions!$F$32+Assumptions!$C$7)+0)>Assumptions!$C$13*((Assumptions!$C$16+Assumptions!$C$17+Assumptions!$C$18+Assumptions!$C$19)+(C$29+C$30)+0),((Assumptions!$C$42-(Assumptions!$F$27+Assumptions!$F$28+Assumptions!$F$29+Assumptions!$F$30+Assumptions!$F$31+Assumptions!$F$32+Assumptions!$C$7)+0)+Assumptions!$C$13*Assumptions!$C$20)/(((Assumptions!$C$16+Assumptions!$C$17+Assumptions!$C$18+Assumptions!$C$19)+(C$29+C$30)+0)+Assumptions!$C$20),(Assumptions!$C$42-(Assumptions!$F$27+Assumptions!$F$28+Assumptions!$F$29+Assumptions!$F$30+Assumptions!$F$31+Assumptions!$F$32+Assumptions!$C$7)+0)/((Assumptions!$C$16+Assumptions!$C$17+Assumptions!$C$18+Assumptions!$C$19)+(C$29+C$30)+0)) -> 123.92545 | D42: =IF((Assumptions!$C$42-(Assumptions!$F$27+Assumptions!$F$28+Assumptions!$F$29+Assumptions!$F$30+Assumptions!$F$31+Assumptions!$F$32+Assumptions!$C$7)+0)>Assumptions!$C$13*((Assumptions!$C$16+Assumptions!$C$17+Assumptions!$C$18+Assumptions!$C$19)+(D$29+D$30)+0),((Assumptions!$C$42-(Assumptions!$F$27+Assumptions!$F$28+Assumptions!$F$29+Assumptions!$F$30+Assumptions!$F$31+Assumptions!$F$32+Assumptions!$C$7)+0)+Assumptions!$C$13*Assumptions!$C$20)/(((Assumptions!$C$16+Assumptions!$C$17+Assumptions!$C$18+Assumptions!$C$19)+(D$29+D$30)+0)+Assumptions!$C$20),(Assumptions!$C$42-(Assumptions!$F$27+Assumptions!$F$28+Assumptions!$F$29+Assumptions!$F$30+Assumptions!$F$31+Assumptions!$F$32+Assumptions!$C$7)+0)/((Assumptions!$C$16+Assumptions!$C$17+Assumptions!$C$18+Assumptions!$C$19)+(D$29+D$30)+0)) -> 123.8719 | E42: =IF((Assumptions!$C$42-(Assumptions!$F$27+Assumptions!$F$28+Assumptions!$F$29+Assumptions!$F$30+Assumptions!$F$31+Assumptions!$F$32+Assumptions!$C$7)+0)>Assumptions!$C$13*((Assumptions!$C$16+Assumptions!$C$17+Assumptions!$C$18+Assumptions!$C$19)+(E$29+E$30)+0),((Assumptions!$C$42-(Assumptions!$F$27+Assumptions!$F$28+Assumptions!$F$29+Assumptions!$F$30+Assumptions!$F$31+Assumptions!$F$32+Assumptions!$C$7)+0)+Assumptions!$C$13*Assumptions!$C$20)/(((Assumptions!$C$16+Assumptions!$C$17+Assumptions!$C$18+Assumptions!$C$19)+(E$29+E$30)+0)+Assumptions!$C$20),(Assumptions!$C$42-(Assumptions!$F$27+Assumptions!$F$28+Assumptions!$F$29+Assumptions!$F$30+Assumptions!$F$31+Assumptions!$F$32+Assumptions!$C$7)+0)/((Assumptions!$C$16+Assumptions!$C$17+Assumptions!$C$18+Assumptions!$C$19)+(E$29+E$30)+0)) -> 123.79278 | F42: =IF((Assumptions!$C$42-(Assumptions!$F$27+Assumptions!$F$28+Assumptions!$F$29+Assumptions!$F$30+Assumptions!$F$31+Assumptions!$F$32+Assumptions!$C$7)+0)>Assumptions!$C$13*((Assumptions!$C$16+Assumptions!$C$17+Assumptions!$C$18+Assumptions!$C$19)+(F$29+F$30)+0),((Assumptions!$C$42-(Assumptions!$F$27+Assumptions!$F$28+Assumptions!$F$29+Assumptions!$F$30+Assumptions!$F$31+Assumptions!$F$32+Assumptions!$C$7)+0)+Assumptions!$C$13*Assumptions!$C$20)/(((Assumptions!$C$16+Assumptions!$C$17+Assumptions!$C$18+Assumptions!$C$19)+(F$29+F$30)+0)+Assumptions!$C$20),(Assumptions!$C$42-(Assumptions!$F$27+Assumptions!$F$28+Assumptions!$F$29+Assumptions!$F$30+Assumptions!$F$31+Assumptions!$F$32+Assumptions!$C$7)+0)/((Assumptions!$C$16+Assumptions!$C$17+Assumptions!$C$18+Assumptions!$C$19)+(F$29+F$30)+0)) -> 124.18392 | G42: =IF((Assumptions!$C$42-(Assumptions!$F$27+Assumptions!$F$28+Assumptions!$F$29+Assumptions!$F$30+Assumptions!$F$31+Assumptions!$F$32+Assumptions!$C$7)+0)>Assumptions!$C$13*((Assumptions!$C$16+Assumptions!$C$17+Assumptions!$C$18+Assumptions!$C$19)+(G$29+G$30)+0),((Assumptions!$C$42-(Assumptions!$F$27+Assumptions!$F$28+Assumptions!$F$29+Assumptions!$F$30+Assumptions!$F$31+Assumptions!$F$32+Assumptions!$C$7)+0)+Assumptions!$C$13*Assumptions!$C$20)/(((Assumptions!$C$16+Assumptions!$C$17+Assumptions!$C$18+Assumptions!$C$19)+(G$29+G$30)+0)+Assumptions!$C$20),(Assumptions!$C$42-(Assumptions!$F$27+Assumptions!$F$28+Assumptions!$F$29+Assumptions!$F$30+Assumptions!$F$31+Assumptions!$F$32+Assumptions!$C$7)+0)/((Assumptions!$C$16+Assumptions!$C$17+Assumptions!$C$18+Assumptions!$C$19)+(G$29+G$30)+0)) -> 124.13679 | H42: =IF((Assumptions!$C$42-(Assumptions!$F$27+Assumptions!$F$28+Assumptions!$F$29+Assumptions!$F$30+Assumptions!$F$31+Assumptions!$F$32+Assumptions!$C$7)+0)>Assumptions!$C$13*((Assumptions!$C$16+Assumptions!$C$17+Assumptions!$C$18+Assumptions!$C$19)+(H$29+H$30)+0),((Assumptions!$C$42-(Assumptions!$F$27+Assumptions!$F$28+Assumptions!$F$29+Assumptions!$F$30+Assumptions!$F$31+Assumptions!$F$32+Assumptions!$C$7)+0)+Assumptions!$C$13*Assumptions!$C$20)/(((Assumptions!$C$16+Assumptions!$C$17+Assumptions!$C$18+Assumptions!$C$19)+(H$29+H$30)+0)+Assumptions!$C$20),(Assumptions!$C$42-(Assumptions!$F$27+Assumptions!$F$28+Assumptions!$F$29+Assumptions!$F$30+Assumptions!$F$31+Assumptions!$F$32+Assumptions!$C$7)+0)/((Assumptions!$C$16+Assumptions!$C$17+Assumptions!$C$18+Assumptions!$C$19)+(H$29+H$30)+0)) -> 124.06428 | I42: =IF((Assumptions!$C$42-(Assumptions!$F$27+Assumptions!$F$28+Assumptions!$F$29+Assumptions!$F$30+Assumptions!$F$31+Assumptions!$F$32+Assumptions!$C$7)+0)>Assumptions!$C$13*((Assumptions!$C$16+Assumptions!$C$17+Assumptions!$C$18+Assumptions!$C$19)+(I$29+I$30)+0),((Assumptions!$C$42-(Assumptions!$F$27+Assumptions!$F$28+Assumptions!$F$29+Assumptions!$F$30+Assumptions!$F$31+Assumptions!$F$32+Assumptions!$C$7)+0)+Assumptions!$C$13*Assumptions!$C$20)/(((Assumptions!$C$16+Assumptions!$C$17+Assumptions!$C$18+Assumptions!$C$19)+(I$29+I$30)+0)+Assumptions!$C$20),(Assumptions!$C$42-(Assumptions!$F$27+Assumptions!$F$28+Assumptions!$F$29+Assumptions!$F$30+Assumptions!$F$31+Assumptions!$F$32+Assumptions!$C$7)+0)/((Assumptions!$C$16+Assumptions!$C$17+Assumptions!$C$18+Assumptions!$C$19)+(I$29+I$30)+0)) -> 124.40678 | J42: =IF((Assumptions!$C$42-(Assumptions!$F$27+Assumptions!$F$28+Assumptions!$F$29+Assumptions!$F$30+Assumptions!$F$31+Assumptions!$F$32+Assumptions!$C$7)+0)>Assumptions!$C$13*((Assumptions!$C$16+Assumptions!$C$17+Assumptions!$C$18+Assumptions!$C$19)+(J$29+J$30)+0),((Assumptions!$C$42-(Assumptions!$F$27+Assumptions!$F$28+Assumptions!$F$29+Assumptions!$F$30+Assumptions!$F$31+Assumptions!$F$32+Assumptions!$C$7)+0)+Assumptions!$C$13*Assumptions!$C$20)/(((Assumptions!$C$16+Assumptions!$C$17+Assumptions!$C$18+Assumptions!$C$19)+(J$29+J$30)+0)+Assumptions!$C$20),(Assumptions!$C$42-(Assumptions!$F$27+Assumptions!$F$28+Assumptions!$F$29+Assumptions!$F$30+Assumptions!$F$31+Assumptions!$F$32+Assumptions!$C$7)+0)/((Assumptions!$C$16+Assumptions!$C$17+Assumptions!$C$18+Assumptions!$C$19)+(J$29+J$30)+0)) -> 124.36574 | K42: =IF((Assumptions!$C$42-(Assumptions!$F$27+Assumptions!$F$28+Assumptions!$F$29+Assumptions!$F$30+Assumptions!$F$31+Assumptions!$F$32+Assumptions!$C$7)+0)>Assumptions!$C$13*((Assumptions!$C$16+Assumptions!$C$17+Assumptions!$C$18+Assumptions!$C$19)+(K$29+K$30)+0),((Assumptions!$C$42-(Assumptions!$F$27+Assumptions!$F$28+Assumptions!$F$29+Assumptions!$F$30+Assumptions!$F$31+Assumptions!$F$32+Assumptions!$C$7)+0)+Assumptions!$C$13*Assumptions!$C$20)/(((Assumptions!$C$16+Assumptions!$C$17+Assumptions!$C$18+Assumptions!$C$19)+(K$29+K$30)+0)+Assumptions!$C$20),(Assumptions!$C$42-(Assumptions!$F$27+Assumptions!$F$28+Assumptions!$F$29+Assumptions!$F$30+Assumptions!$F$31+Assumptions!$F$32+Assumptions!$C$7)+0)/((Assumptions!$C$16+Assumptions!$C$17+Assumptions!$C$18+Assumptions!$C$19)+(K$29+K$30)+0)) -> 124.29907
B43: PS_{k=1} candidate | C43: =IF((Assumptions!$C$42-(Assumptions!$F$27+Assumptions!$F$28+Assumptions!$F$29+Assumptions!$F$30+Assumptions!$F$31+Assumptions!$F$32+Assumptions!$C$7)+Assumptions!$F$27)>Assumptions!$C$13*((Assumptions!$C$16+Assumptions!$C$17+Assumptions!$C$18+Assumptions!$C$19)+(C$29+C$30)+Assumptions!$E$27),((Assumptions!$C$42-(Assumptions!$F$27+Assumptions!$F$28+Assumptions!$F$29+Assumptions!$F$30+Assumptions!$F$31+Assumptions!$F$32+Assumptions!$C$7)+Assumptions!$F$27)+Assumptions!$C$13*Assumptions!$C$20)/(((Assumptions!$C$16+Assumptions!$C$17+Assumptions!$C$18+Assumptions!$C$19)+(C$29+C$30)+Assumptions!$E$27)+Assumptions!$C$20),(Assumptions!$C$42-(Assumptions!$F$27+Assumptions!$F$28+Assumptions!$F$29+Assumptions!$F$30+Assumptions!$F$31+Assumptions!$F$32+Assumptions!$C$7)+Assumptions!$F$27)/((Assumptions!$C$16+Assumptions!$C$17+Assumptions!$C$18+Assumptions!$C$19)+(C$29+C$30)+Assumptions!$E$27)) -> 87.343652 | D43: =IF((Assumptions!$C$42-(Assumptions!$F$27+Assumptions!$F$28+Assumptions!$F$29+Assumptions!$F$30+Assumptions!$F$31+Assumptions!$F$32+Assumptions!$C$7)+Assumptions!$F$27)>Assumptions!$C$13*((Assumptions!$C$16+Assumptions!$C$17+Assumptions!$C$18+Assumptions!$C$19)+(D$29+D$30)+Assumptions!$E$27),((Assumptions!$C$42-(Assumptions!$F$27+Assumptions!$F$28+Assumptions!$F$29+Assumptions!$F$30+Assumptions!$F$31+Assumptions!$F$32+Assumptions!$C$7)+Assumptions!$F$27)+Assumptions!$C$13*Assumptions!$C$20)/(((Assumptions!$C$16+Assumptions!$C$17+Assumptions!$C$18+Assumptions!$C$19)+(D$29+D$30)+Assumptions!$E$27)+Assumptions!$C$20),(Assumptions!$C$42-(Assumptions!$F$27+Assumptions!$F$28+Assumptions!$F$29+Assumptions!$F$30+Assumptions!$F$31+Assumptions!$F$32+Assumptions!$C$7)+Assumptions!$F$27)/((Assumptions!$C$16+Assumptions!$C$17+Assumptions!$C$18+Assumptions!$C$19)+(D$29+D$30)+Assumptions!$E$27)) -> 87.317136 | E43: =IF((Assumptions!$C$42-(Assumptions!$F$27+Assumptions!$F$28+Assumptions!$F$29+Assumptions!$F$30+Assumptions!$F$31+Assumptions!$F$32+Assumptions!$C$7)+Assumptions!$F$27)>Assumptions!$C$13*((Assumptions!$C$16+Assumptions!$C$17+Assumptions!$C$18+Assumptions!$C$19)+(E$29+E$30)+Assumptions!$E$27),((Assumptions!$C$42-(Assumptions!$F$27+Assumptions!$F$28+Assumptions!$F$29+Assumptions!$F$30+Assumptions!$F$31+Assumptions!$F$32+Assumptions!$C$7)+Assumptions!$F$27)+Assumptions!$C$13*Assumptions!$C$20)/(((Assumptions!$C$16+Assumptions!$C$17+Assumptions!$C$18+Assumptions!$C$19)+(E$29+E$30)+Assumptions!$E$27)+Assumptions!$C$20),(Assumptions!$C$42-(Assumptions!$F$27+Assumptions!$F$28+Assumptions!$F$29+Assumptions!$F$30+Assumptions!$F$31+Assumptions!$F$32+Assumptions!$C$7)+Assumptions!$F$27)/((Assumptions!$C$16+Assumptions!$C$17+Assumptions!$C$18+Assumptions!$C$19)+(E$29+E$30)+Assumptions!$E$27)) -> 87.277951 | F43: =IF((Assumptions!$C$42-(Assumptions!$F$27+Assumptions!$F$28+Assumptions!$F$29+Assumptions!$F$30+Assumptions!$F$31+Assumptions!$F$32+Assumptions!$C$7)+Assumptions!$F$27)>Assumptions!$C$13*((Assumptions!$C$16+Assumptions!$C$17+Assumptions!$C$18+Assumptions!$C$19)+(F$29+F$30)+Assumptions!$E$27),((Assumptions!$C$42-(Assumptions!$F$27+Assumptions!$F$28+Assumptions!$F$29+Assumptions!$F$30+Assumptions!$F$31+Assumptions!$F$32+Assumptions!$C$7)+Assumptions!$F$27)+Assumptions!$C$13*Assumptions!$C$20)/(((Assumptions!$C$16+Assumptions!$C$17+Assumptions!$C$18+Assumptions!$C$19)+(F$29+F$30)+Assumptions!$E$27)+Assumptions!$C$20),(Assumptions!$C$42-(Assumptions!$F$27+Assumptions!$F$28+Assumptions!$F$29+Assumptions!$F$30+Assumptions!$F$31+Assumptions!$F$32+Assumptions!$C$7)+Assumptions!$F$27)/((Assumptions!$C$16+Assumptions!$C$17+Assumptions!$C$18+Assumptions!$C$19)+(F$29+F$30)+Assumptions!$E$27)) -> 87.471529 | G43: =IF((Assumptions!$C$42-(Assumptions!$F$27+Assumptions!$F$28+Assumptions!$F$29+Assumptions!$F$30+Assumptions!$F$31+Assumptions!$F$32+Assumptions!$C$7)+Assumptions!$F$27)>Assumptions!$C$13*((Assumptions!$C$16+Assumptions!$C$17+Assumptions!$C$18+Assumptions!$C$19)+(G$29+G$30)+Assumptions!$E$27),((Assumptions!$C$42-(Assumptions!$F$27+Assumptions!$F$28+Assumptions!$F$29+Assumptions!$F$30+Assumptions!$F$31+Assumptions!$F$32+Assumptions!$C$7)+Assumptions!$F$27)+Assumptions!$C$13*Assumptions!$C$20)/(((Assumptions!$C$16+Assumptions!$C$17+Assumptions!$C$18+Assumptions!$C$19)+(G$29+G$30)+Assumptions!$E$27)+Assumptions!$C$20),(Assumptions!$C$42-(Assumptions!$F$27+Assumptions!$F$28+Assumptions!$F$29+Assumptions!$F$30+Assumptions!$F$31+Assumptions!$F$32+Assumptions!$C$7)+Assumptions!$F$27)/((Assumptions!$C$16+Assumptions!$C$17+Assumptions!$C$18+Assumptions!$C$19)+(G$29+G$30)+Assumptions!$E$27)) -> 87.448224 | H43: =IF((Assumptions!$C$42-(Assumptions!$F$27+Assumptions!$F$28+Assumptions!$F$29+Assumptions!$F$30+Assumptions!$F$31+Assumptions!$F$32+Assumptions!$C$7)+Assumptions!$F$27)>Assumptions!$C$13*((Assumptions!$C$16+Assumptions!$C$17+Assumptions!$C$18+Assumptions!$C$19)+(H$29+H$30)+Assumptions!$E$27),((Assumptions!$C$42-(Assumptions!$F$27+Assumptions!$F$28+Assumptions!$F$29+Assumptions!$F$30+Assumptions!$F$31+Assumptions!$F$32+Assumptions!$C$7)+Assumptions!$F$27)+Assumptions!$C$13*Assumptions!$C$20)/(((Assumptions!$C$16+Assumptions!$C$17+Assumptions!$C$18+Assumptions!$C$19)+(H$29+H$30)+Assumptions!$E$27)+Assumptions!$C$20),(Assumptions!$C$42-(Assumptions!$F$27+Assumptions!$F$28+Assumptions!$F$29+Assumptions!$F$30+Assumptions!$F$31+Assumptions!$F$32+Assumptions!$C$7)+Assumptions!$F$27)/((Assumptions!$C$16+Assumptions!$C$17+Assumptions!$C$18+Assumptions!$C$19)+(H$29+H$30)+Assumptions!$E$27)) -> 87.412359 | I43: =IF((Assumptions!$C$42-(Assumptions!$F$27+Assumptions!$F$28+Assumptions!$F$29+Assumptions!$F$30+Assumptions!$F$31+Assumptions!$F$32+Assumptions!$C$7)+Assumptions!$F$27)>Assumptions!$C$13*((Assumptions!$C$16+Assumptions!$C$17+Assumptions!$C$18+Assumptions!$C$19)+(I$29+I$30)+Assumptions!$E$27),((Assumptions!$C$42-(Assumptions!$F$27+Assumptions!$F$28+Assumptions!$F$29+Assumptions!$F$30+Assumptions!$F$31+Assumptions!$F$32+Assumptions!$C$7)+Assumptions!$F$27)+Assumptions!$C$13*Assumptions!$C$20)/(((Assumptions!$C$16+Assumptions!$C$17+Assumptions!$C$18+Assumptions!$C$19)+(I$29+I$30)+Assumptions!$E$27)+Assumptions!$C$20),(Assumptions!$C$42-(Assumptions!$F$27+Assumptions!$F$28+Assumptions!$F$29+Assumptions!$F$30+Assumptions!$F$31+Assumptions!$F$32+Assumptions!$C$7)+Assumptions!$F$27)/((Assumptions!$C$16+Assumptions!$C$17+Assumptions!$C$18+Assumptions!$C$19)+(I$29+I$30)+Assumptions!$E$27)) -> 87.581666 | J43: =IF((Assumptions!$C$42-(Assumptions!$F$27+Assumptions!$F$28+Assumptions!$F$29+Assumptions!$F$30+Assumptions!$F$31+Assumptions!$F$32+Assumptions!$C$7)+Assumptions!$F$27)>Assumptions!$C$13*((Assumptions!$C$16+Assumptions!$C$17+Assumptions!$C$18+Assumptions!$C$19)+(J$29+J$30)+Assumptions!$E$27),((Assumptions!$C$42-(Assumptions!$F$27+Assumptions!$F$28+Assumptions!$F$29+Assumptions!$F$30+Assumptions!$F$31+Assumptions!$F$32+Assumptions!$C$7)+Assumptions!$F$27)+Assumptions!$C$13*Assumptions!$C$20)/(((Assumptions!$C$16+Assumptions!$C$17+Assumptions!$C$18+Assumptions!$C$19)+(J$29+J$30)+Assumptions!$E$27)+Assumptions!$C$20),(Assumptions!$C$42-(Assumptions!$F$27+Assumptions!$F$28+Assumptions!$F$29+Assumptions!$F$30+Assumptions!$F$31+Assumptions!$F$32+Assumptions!$C$7)+Assumptions!$F$27)/((Assumptions!$C$16+Assumptions!$C$17+Assumptions!$C$18+Assumptions!$C$19)+(J$29+J$30)+Assumptions!$E$27)) -> 87.561394 | K43: =IF((Assumptions!$C$42-(Assumptions!$F$27+Assumptions!$F$28+Assumptions!$F$29+Assumptions!$F$30+Assumptions!$F$31+Assumptions!$F$32+Assumptions!$C$7)+Assumptions!$F$27)>Assumptions!$C$13*((Assumptions!$C$16+Assumptions!$C$17+Assumptions!$C$18+Assumptions!$C$19)+(K$29+K$30)+Assumptions!$E$27),((Assumptions!$C$42-(Assumptions!$F$27+Assumptions!$F$28+Assumptions!$F$29+Assumptions!$F$30+Assumptions!$F$31+Assumptions!$F$32+Assumptions!$C$7)+Assumptions!$F$27)+Assumptions!$C$13*Assumptions!$C$20)/(((Assumptions!$C$16+Assumptions!$C$17+Assumptions!$C$18+Assumptions!$C$19)+(K$29+K$30)+Assumptions!$E$27)+Assumptions!$C$20),(Assumptions!$C$42-(Assumptions!$F$27+Assumptions!$F$28+Assumptions!$F$29+Assumptions!$F$30+Assumptions!$F$31+Assumptions!$F$32+Assumptions!$C$7)+Assumptions!$F$27)/((Assumptions!$C$16+Assumptions!$C$17+Assumptions!$C$18+Assumptions!$C$19)+(K$29+K$30)+Assumptions!$E$27)) -> 87.528452
B44: PS_{k=2} candidate | C44: =IF((Assumptions!$C$42-(Assumptions!$F$27+Assumptions!$F$28+Assumptions!$F$29+Assumptions!$F$30+Assumptions!$F$31+Assumptions!$F$32+Assumptions!$C$7)+Assumptions!$F$27+Assumptions!$F$28)>Assumptions!$C$13*((Assumptions!$C$16+Assumptions!$C$17+Assumptions!$C$18+Assumptions!$C$19)+(C$29+C$30)+Assumptions!$E$27+Assumptions!$E$28),((Assumptions!$C$42-(Assumptions!$F$27+Assumptions!$F$28+Assumptions!$F$29+Assumptions!$F$30+Assumptions!$F$31+Assumptions!$F$32+Assumptions!$C$7)+Assumptions!$F$27+Assumptions!$F$28)+Assumptions!$C$13*Assumptions!$C$20)/(((Assumptions!$C$16+Assumptions!$C$17+Assumptions!$C$18+Assumptions!$C$19)+(C$29+C$30)+Assumptions!$E$27+Assumptions!$E$28)+Assumptions!$C$20),(Assumptions!$C$42-(Assumptions!$F$27+Assumptions!$F$28+Assumptions!$F$29+Assumptions!$F$30+Assumptions!$F$31+Assumptions!$F$32+Assumptions!$C$7)+Assumptions!$F$27+Assumptions!$F$28)/((Assumptions!$C$16+Assumptions!$C$17+Assumptions!$C$18+Assumptions!$C$19)+(C$29+C$30)+Assumptions!$E$27+Assumptions!$E$28)) -> 68.000064 | D44: =IF((Assumptions!$C$42-(Assumptions!$F$27+Assumptions!$F$28+Assumptions!$F$29+Assumptions!$F$30+Assumptions!$F$31+Assumptions!$F$32+Assumptions!$C$7)+Assumptions!$F$27+Assumptions!$F$28)>Assumptions!$C$13*((Assumptions!$C$16+Assumptions!$C$17+Assumptions!$C$18+Assumptions!$C$19)+(D$29+D$30)+Assumptions!$E$27+Assumptions!$E$28),((Assumptions!$C$42-(Assumptions!$F$27+Assumptions!$F$28+Assumptions!$F$29+Assumptions!$F$30+Assumptions!$F$31+Assumptions!$F$32+Assumptions!$C$7)+Assumptions!$F$27+Assumptions!$F$28)+Assumptions!$C$13*Assumptions!$C$20)/(((Assumptions!$C$16+Assumptions!$C$17+Assumptions!$C$18+Assumptions!$C$19)+(D$29+D$30)+Assumptions!$E$27+Assumptions!$E$28)+Assumptions!$C$20),(Assumptions!$C$42-(Assumptions!$F$27+Assumptions!$F$28+Assumptions!$F$29+Assumptions!$F$30+Assumptions!$F$31+Assumptions!$F$32+Assumptions!$C$7)+Assumptions!$F$27+Assumptions!$F$28)/((Assumptions!$C$16+Assumptions!$C$17+Assumptions!$C$18+Assumptions!$C$19)+(D$29+D$30)+Assumptions!$E$27+Assumptions!$E$28)) -> 67.984154 | E44: =IF((Assumptions!$C$42-(Assumptions!$F$27+Assumptions!$F$28+Assumptions!$F$29+Assumptions!$F$30+Assumptions!$F$31+Assumptions!$F$32+Assumptions!$C$7)+Assumptions!$F$27+Assumptions!$F$28)>Assumptions!$C$13*((Assumptions!$C$16+Assumptions!$C$17+Assumptions!$C$18+Assumptions!$C$19)+(E$29+E$30)+Assumptions!$E$27+Assumptions!$E$28),((Assumptions!$C$42-(Assumptions!$F$27+Assumptions!$F$28+Assumptions!$F$29+Assumptions!$F$30+Assumptions!$F$31+Assumptions!$F$32+Assumptions!$C$7)+Assumptions!$F$27+Assumptions!$F$28)+Assumptions!$C$13*Assumptions!$C$20)/(((Assumptions!$C$16+Assumptions!$C$17+Assumptions!$C$18+Assumptions!$C$19)+(E$29+E$30)+Assumptions!$E$27+Assumptions!$E$28)+Assumptions!$C$20),(Assumptions!$C$42-(Assumptions!$F$27+Assumptions!$F$28+Assumptions!$F$29+Assumptions!$F$30+Assumptions!$F$31+Assumptions!$F$32+Assumptions!$C$7)+Assumptions!$F$27+Assumptions!$F$28)/((Assumptions!$C$16+Assumptions!$C$17+Assumptions!$C$18+Assumptions!$C$19)+(E$29+E$30)+Assumptions!$E$27+Assumptions!$E$28)) -> 67.960638 | F44: =IF((Assumptions!$C$42-(Assumptions!$F$27+Assumptions!$F$28+Assumptions!$F$29+Assumptions!$F$30+Assumptions!$F$31+Assumptions!$F$32+Assumptions!$C$7)+Assumptions!$F$27+Assumptions!$F$28)>Assumptions!$C$13*((Assumptions!$C$16+Assumptions!$C$17+Assumptions!$C$18+Assumptions!$C$19)+(F$29+F$30)+Assumptions!$E$27+Assumptions!$E$28),((Assumptions!$C$42-(Assumptions!$F$27+Assumptions!$F$28+Assumptions!$F$29+Assumptions!$F$30+Assumptions!$F$31+Assumptions!$F$32+Assumptions!$C$7)+Assumptions!$F$27+Assumptions!$F$28)+Assumptions!$C$13*Assumptions!$C$20)/(((Assumptions!$C$16+Assumptions!$C$17+Assumptions!$C$18+Assumptions!$C$19)+(F$29+F$30)+Assumptions!$E$27+Assumptions!$E$28)+Assumptions!$C$20),(Assumptions!$C$42-(Assumptions!$F$27+Assumptions!$F$28+Assumptions!$F$29+Assumptions!$F$30+Assumptions!$F$31+Assumptions!$F$32+Assumptions!$C$7)+Assumptions!$F$27+Assumptions!$F$28)/((Assumptions!$C$16+Assumptions!$C$17+Assumptions!$C$18+Assumptions!$C$19)+(F$29+F$30)+Assumptions!$E$27+Assumptions!$E$28)) -> 68.076763 | G44: =IF((Assumptions!$C$42-(Assumptions!$F$27+Assumptions!$F$28+Assumptions!$F$29+Assumptions!$F$30+Assumptions!$F$31+Assumptions!$F$32+Assumptions!$C$7)+Assumptions!$F$27+Assumptions!$F$28)>Assumptions!$C$13*((Assumptions!$C$16+Assumptions!$C$17+Assumptions!$C$18+Assumptions!$C$19)+(G$29+G$30)+Assumptions!$E$27+Assumptions!$E$28),((Assumptions!$C$42-(Assumptions!$F$27+Assumptions!$F$28+Assumptions!$F$29+Assumptions!$F$30+Assumptions!$F$31+Assumptions!$F$32+Assumptions!$C$7)+Assumptions!$F$27+Assumptions!$F$28)+Assumptions!$C$13*Assumptions!$C$20)/(((Assumptions!$C$16+Assumptions!$C$17+Assumptions!$C$18+Assumptions!$C$19)+(G$29+G$30)+Assumptions!$E$27+Assumptions!$E$28)+Assumptions!$C$20),(Assumptions!$C$42-(Assumptions!$F$27+Assumptions!$F$28+Assumptions!$F$29+Assumptions!$F$30+Assumptions!$F$31+Assumptions!$F$32+Assumptions!$C$7)+Assumptions!$F$27+Assumptions!$F$28)/((Assumptions!$C$16+Assumptions!$C$17+Assumptions!$C$18+Assumptions!$C$19)+(G$29+G$30)+Assumptions!$E$27+Assumptions!$E$28)) -> 68.062788 | H44: =IF((Assumptions!$C$42-(Assumptions!$F$27+Assumptions!$F$28+Assumptions!$F$29+Assumptions!$F$30+Assumptions!$F$31+Assumptions!$F$32+Assumptions!$C$7)+Assumptions!$F$27+Assumptions!$F$28)>Assumptions!$C$13*((Assumptions!$C$16+Assumptions!$C$17+Assumptions!$C$18+Assumptions!$C$19)+(H$29+H$30)+Assumptions!$E$27+Assumptions!$E$28),((Assumptions!$C$42-(Assumptions!$F$27+Assumptions!$F$28+Assumptions!$F$29+Assumptions!$F$30+Assumptions!$F$31+Assumptions!$F$32+Assumptions!$C$7)+Assumptions!$F$27+Assumptions!$F$28)+Assumptions!$C$13*Assumptions!$C$20)/(((Assumptions!$C$16+Assumptions!$C$17+Assumptions!$C$18+Assumptions!$C$19)+(H$29+H$30)+Assumptions!$E$27+Assumptions!$E$28)+Assumptions!$C$20),(Assumptions!$C$42-(Assumptions!$F$27+Assumptions!$F$28+Assumptions!$F$29+Assumptions!$F$30+Assumptions!$F$31+Assumptions!$F$32+Assumptions!$C$7)+Assumptions!$F$27+Assumptions!$F$28)/((Assumptions!$C$16+Assumptions!$C$17+Assumptions!$C$18+Assumptions!$C$19)+(H$29+H$30)+Assumptions!$E$27+Assumptions!$E$28)) -> 68.04128 | I44: =IF((Assumptions!$C$42-(Assumptions!$F$27+Assumptions!$F$28+Assumptions!$F$29+Assumptions!$F$30+Assumptions!$F$31+Assumptions!$F$32+Assumptions!$C$7)+Assumptions!$F$27+Assumptions!$F$28)>Assumptions!$C$13*((Assumptions!$C$16+Assumptions!$C$17+Assumptions!$C$18+Assumptions!$C$19)+(I$29+I$30)+Assumptions!$E$27+Assumptions!$E$28),((Assumptions!$C$42-(Assumptions!$F$27+Assumptions!$F$28+Assumptions!$F$29+Assumptions!$F$30+Assumptions!$F$31+Assumptions!$F$32+Assumptions!$C$7)+Assumptions!$F$27+Assumptions!$F$28)+Assumptions!$C$13*Assumptions!$C$20)/(((Assumptions!$C$16+Assumptions!$C$17+Assumptions!$C$18+Assumptions!$C$19)+(I$29+I$30)+Assumptions!$E$27+Assumptions!$E$28)+Assumptions!$C$20),(Assumptions!$C$42-(Assumptions!$F$27+Assumptions!$F$28+Assumptions!$F$29+Assumptions!$F$30+Assumptions!$F$31+Assumptions!$F$32+Assumptions!$C$7)+Assumptions!$F$27+Assumptions!$F$28)/((Assumptions!$C$16+Assumptions!$C$17+Assumptions!$C$18+Assumptions!$C$19)+(I$29+I$30)+Assumptions!$E$27+Assumptions!$E$28)) -> 68.142779 | J44: =IF((Assumptions!$C$42-(Assumptions!$F$27+Assumptions!$F$28+Assumptions!$F$29+Assumptions!$F$30+Assumptions!$F$31+Assumptions!$F$32+Assumptions!$C$7)+Assumptions!$F$27+Assumptions!$F$28)>Assumptions!$C$13*((Assumptions!$C$16+Assumptions!$C$17+Assumptions!$C$18+Assumptions!$C$19)+(J$29+J$30)+Assumptions!$E$27+Assumptions!$E$28),((Assumptions!$C$42-(Assumptions!$F$27+Assumptions!$F$28+Assumptions!$F$29+Assumptions!$F$30+Assumptions!$F$31+Assumptions!$F$32+Assumptions!$C$7)+Assumptions!$F$27+Assumptions!$F$28)+Assumptions!$C$13*Assumptions!$C$20)/(((Assumptions!$C$16+Assumptions!$C$17+Assumptions!$C$18+Assumptions!$C$19)+(J$29+J$30)+Assumptions!$E$27+Assumptions!$E$28)+Assumptions!$C$20),(Assumptions!$C$42-(Assumptions!$F$27+Assumptions!$F$28+Assumptions!$F$29+Assumptions!$F$30+Assumptions!$F$31+Assumptions!$F$32+Assumptions!$C$7)+Assumptions!$F$27+Assumptions!$F$28)/((Assumptions!$C$16+Assumptions!$C$17+Assumptions!$C$18+Assumptions!$C$19)+(J$29+J$30)+Assumptions!$E$27+Assumptions!$E$28)) -> 68.130632 | K44: =IF((Assumptions!$C$42-(Assumptions!$F$27+Assumptions!$F$28+Assumptions!$F$29+Assumptions!$F$30+Assumptions!$F$31+Assumptions!$F$32+Assumptions!$C$7)+Assumptions!$F$27+Assumptions!$F$28)>Assumptions!$C$13*((Assumptions!$C$16+Assumptions!$C$17+Assumptions!$C$18+Assumptions!$C$19)+(K$29+K$30)+Assumptions!$E$27+Assumptions!$E$28),((Assumptions!$C$42-(Assumptions!$F$27+Assumptions!$F$28+Assumptions!$F$29+Assumptions!$F$30+Assumptions!$F$31+Assumptions!$F$32+Assumptions!$C$7)+Assumptions!$F$27+Assumptions!$F$28)+Assumptions!$C$13*Assumptions!$C$20)/(((Assumptions!$C$16+Assumptions!$C$17+Assumptions!$C$18+Assumptions!$C$19)+(K$29+K$30)+Assumptions!$E$27+Assumptions!$E$28)+Assumptions!$C$20),(Assumptions!$C$42-(Assumptions!$F$27+Assumptions!$F$28+Assumptions!$F$29+Assumptions!$F$30+Assumptions!$F$31+Assumptions!$F$32+Assumptions!$C$7)+Assumptions!$F$27+Assumptions!$F$28)/((Assumptions!$C$16+Assumptions!$C$17+Assumptions!$C$18+Assumptions!$C$19)+(K$29+K$30)+Assumptions!$E$27+Assumptions!$E$28)) -> 68.110887
B45: PS_{k=3} candidate | C45: =IF((Assumptions!$C$42-(Assumptions!$F$27+Assumptions!$F$28+Assumptions!$F$29+Assumptions!$F$30+Assumptions!$F$31+Assumptions!$F$32+Assumptions!$C$7)+Assumptions!$F$27+Assumptions!$F$28+Assumptions!$F$29)>Assumptions!$C$13*((Assumptions!$C$16+Assumptions!$C$17+Assumptions!$C$18+Assumptions!$C$19)+(C$29+C$30)+Assumptions!$E$27+Assumptions!$E$28+Assumptions!$E$29),((Assumptions!$C$42-(Assumptions!$F$27+Assumptions!$F$28+Assumptions!$F$29+Assumptions!$F$30+Assumptions!$F$31+Assumptions!$F$32+Assumptions!$C$7)+Assumptions!$F$27+Assumptions!$F$28+Assumptions!$F$29)+Assumptions!$C$13*Assumptions!$C$20)/(((Assumptions!$C$16+Assumptions!$C$17+Assumptions!$C$18+Assumptions!$C$19)+(C$29+C$30)+Assumptions!$E$27+Assumptions!$E$28+Assumptions!$E$29)+Assumptions!$C$20),(Assumptions!$C$42-(Assumptions!$F$27+Assumptions!$F$28+Assumptions!$F$29+Assumptions!$F$30+Assumptions!$F$31+Assumptions!$F$32+Assumptions!$C$7)+Assumptions!$F$27+Assumptions!$F$28+Assumptions!$F$29)/((Assumptions!$C$16+Assumptions!$C$17+Assumptions!$C$18+Assumptions!$C$19)+(C$29+C$30)+Assumptions!$E$27+Assumptions!$E$28+Assumptions!$E$29)) -> 60.984338 | D45: =IF((Assumptions!$C$42-(Assumptions!$F$27+Assumptions!$F$28+Assumptions!$F$29+Assumptions!$F$30+Assumptions!$F$31+Assumptions!$F$32+Assumptions!$C$7)+Assumptions!$F$27+Assumptions!$F$28+Assumptions!$F$29)>Assumptions!$C$13*((Assumptions!$C$16+Assumptions!$C$17+Assumptions!$C$18+Assumptions!$C$19)+(D$29+D$30)+Assumptions!$E$27+Assumptions!$E$28+Assumptions!$E$29),((Assumptions!$C$42-(Assumptions!$F$27+Assumptions!$F$28+Assumptions!$F$29+Assumptions!$F$30+Assumptions!$F$31+Assumptions!$F$32+Assumptions!$C$7)+Assumptions!$F$27+Assumptions!$F$28+Assumptions!$F$29)+Assumptions!$C$13*Assumptions!$C$20)/(((Assumptions!$C$16+Assumptions!$C$17+Assumptions!$C$18+Assumptions!$C$19)+(D$29+D$30)+Assumptions!$E$27+Assumptions!$E$28+Assumptions!$E$29)+Assumptions!$C$20),(Assumptions!$C$42-(Assumptions!$F$27+Assumptions!$F$28+Assumptions!$F$29+Assumptions!$F$30+Assumptions!$F$31+Assumptions!$F$32+Assumptions!$C$7)+Assumptions!$F$27+Assumptions!$F$28+Assumptions!$F$29)/((Assumptions!$C$16+Assumptions!$C$17+Assumptions!$C$18+Assumptions!$C$19)+(D$29+D$30)+Assumptions!$E$27+Assumptions!$E$28+Assumptions!$E$29)) -> 60.971795 | E45: =IF((Assumptions!$C$42-(Assumptions!$F$27+Assumptions!$F$28+Assumptions!$F$29+Assumptions!$F$30+Assumptions!$F$31+Assumptions!$F$32+Assumptions!$C$7)+Assumptions!$F$27+Assumptions!$F$28+Assumptions!$F$29)>Assumptions!$C$13*((Assumptions!$C$16+Assumptions!$C$17+Assumptions!$C$18+Assumptions!$C$19)+(E$29+E$30)+Assumptions!$E$27+Assumptions!$E$28+Assumptions!$E$29),((Assumptions!$C$42-(Assumptions!$F$27+Assumptions!$F$28+Assumptions!$F$29+Assumptions!$F$30+Assumptions!$F$31+Assumptions!$F$32+Assumptions!$C$7)+Assumptions!$F$27+Assumptions!$F$28+Assumptions!$F$29)+Assumptions!$C$13*Assumptions!$C$20)/(((Assumptions!$C$16+Assumptions!$C$17+Assumptions!$C$18+Assumptions!$C$19)+(E$29+E$30)+Assumptions!$E$27+Assumptions!$E$28+Assumptions!$E$29)+Assumptions!$C$20),(Assumptions!$C$42-(Assumptions!$F$27+Assumptions!$F$28+Assumptions!$F$29+Assumptions!$F$30+Assumptions!$F$31+Assumptions!$F$32+Assumptions!$C$7)+Assumptions!$F$27+Assumptions!$F$28+Assumptions!$F$29)/((Assumptions!$C$16+Assumptions!$C$17+Assumptions!$C$18+Assumptions!$C$19)+(E$29+E$30)+Assumptions!$E$27+Assumptions!$E$28+Assumptions!$E$29)) -> 60.953254 | F45: =IF((Assumptions!$C$42-(Assumptions!$F$27+Assumptions!$F$28+Assumptions!$F$29+Assumptions!$F$30+Assumptions!$F$31+Assumptions!$F$32+Assumptions!$C$7)+Assumptions!$F$27+Assumptions!$F$28+Assumptions!$F$29)>Assumptions!$C$13*((Assumptions!$C$16+Assumptions!$C$17+Assumptions!$C$18+Assumptions!$C$19)+(F$29+F$30)+Assumptions!$E$27+Assumptions!$E$28+Assumptions!$E$29),((Assumptions!$C$42-(Assumptions!$F$27+Assumptions!$F$28+Assumptions!$F$29+Assumptions!$F$30+Assumptions!$F$31+Assumptions!$F$32+Assumptions!$C$7)+Assumptions!$F$27+Assumptions!$F$28+Assumptions!$F$29)+Assumptions!$C$13*Assumptions!$C$20)/(((Assumptions!$C$16+Assumptions!$C$17+Assumptions!$C$18+Assumptions!$C$19)+(F$29+F$30)+Assumptions!$E$27+Assumptions!$E$28+Assumptions!$E$29)+Assumptions!$C$20),(Assumptions!$C$42-(Assumptions!$F$27+Assumptions!$F$28+Assumptions!$F$29+Assumptions!$F$30+Assumptions!$F$31+Assumptions!$F$32+Assumptions!$C$7)+Assumptions!$F$27+Assumptions!$F$28+Assumptions!$F$29)/((Assumptions!$C$16+Assumptions!$C$17+Assumptions!$C$18+Assumptions!$C$19)+(F$29+F$30)+Assumptions!$E$27+Assumptions!$E$28+Assumptions!$E$29)) -> 61.044794 | G45: =IF((Assumptions!$C$42-(Assumptions!$F$27+Assumptions!$F$28+Assumptions!$F$29+Assumptions!$F$30+Assumptions!$F$31+Assumptions!$F$32+Assumptions!$C$7)+Assumptions!$F$27+Assumptions!$F$28+Assumptions!$F$29)>Assumptions!$C$13*((Assumptions!$C$16+Assumptions!$C$17+Assumptions!$C$18+Assumptions!$C$19)+(G$29+G$30)+Assumptions!$E$27+Assumptions!$E$28+Assumptions!$E$29),((Assumptions!$C$42-(Assumptions!$F$27+Assumptions!$F$28+Assumptions!$F$29+Assumptions!$F$30+Assumptions!$F$31+Assumptions!$F$32+Assumptions!$C$7)+Assumptions!$F$27+Assumptions!$F$28+Assumptions!$F$29)+Assumptions!$C$13*Assumptions!$C$20)/(((Assumptions!$C$16+Assumptions!$C$17+Assumptions!$C$18+Assumptions!$C$19)+(G$29+G$30)+Assumptions!$E$27+Assumptions!$E$28+Assumptions!$E$29)+Assumptions!$C$20),(Assumptions!$C$42-(Assumptions!$F$27+Assumptions!$F$28+Assumptions!$F$29+Assumptions!$F$30+Assumptions!$F$31+Assumptions!$F$32+Assumptions!$C$7)+Assumptions!$F$27+Assumptions!$F$28+Assumptions!$F$29)/((Assumptions!$C$16+Assumptions!$C$17+Assumptions!$C$18+Assumptions!$C$19)+(G$29+G$30)+Assumptions!$E$27+Assumptions!$E$28+Assumptions!$E$29)) -> 61.033781 | H45: =IF((Assumptions!$C$42-(Assumptions!$F$27+Assumptions!$F$28+Assumptions!$F$29+Assumptions!$F$30+Assumptions!$F$31+Assumptions!$F$32+Assumptions!$C$7)+Assumptions!$F$27+Assumptions!$F$28+Assumptions!$F$29)>Assumptions!$C$13*((Assumptions!$C$16+Assumptions!$C$17+Assumptions!$C$18+Assumptions!$C$19)+(H$29+H$30)+Assumptions!$E$27+Assumptions!$E$28+Assumptions!$E$29),((Assumptions!$C$42-(Assumptions!$F$27+Assumptions!$F$28+Assumptions!$F$29+Assumptions!$F$30+Assumptions!$F$31+Assumptions!$F$32+Assumptions!$C$7)+Assumptions!$F$27+Assumptions!$F$28+Assumptions!$F$29)+Assumptions!$C$13*Assumptions!$C$20)/(((Assumptions!$C$16+Assumptions!$C$17+Assumptions!$C$18+Assumptions!$C$19)+(H$29+H$30)+Assumptions!$E$27+Assumptions!$E$28+Assumptions!$E$29)+Assumptions!$C$20),(Assumptions!$C$42-(Assumptions!$F$27+Assumptions!$F$28+Assumptions!$F$29+Assumptions!$F$30+Assumptions!$F$31+Assumptions!$F$32+Assumptions!$C$7)+Assumptions!$F$27+Assumptions!$F$28+Assumptions!$F$29)/((Assumptions!$C$16+Assumptions!$C$17+Assumptions!$C$18+Assumptions!$C$19)+(H$29+H$30)+Assumptions!$E$27+Assumptions!$E$28+Assumptions!$E$29)) -> 61.016827 | I45: =IF((Assumptions!$C$42-(Assumptions!$F$27+Assumptions!$F$28+Assumptions!$F$29+Assumptions!$F$30+Assumptions!$F$31+Assumptions!$F$32+Assumptions!$C$7)+Assumptions!$F$27+Assumptions!$F$28+Assumptions!$F$29)>Assumptions!$C$13*((Assumptions!$C$16+Assumptions!$C$17+Assumptions!$C$18+Assumptions!$C$19)+(I$29+I$30)+Assumptions!$E$27+Assumptions!$E$28+Assumptions!$E$29),((Assumptions!$C$42-(Assumptions!$F$27+Assumptions!$F$28+Assumptions!$F$29+Assumptions!$F$30+Assumptions!$F$31+Assumptions!$F$32+Assumptions!$C$7)+Assumptions!$F$27+Assumptions!$F$28+Assumptions!$F$29)+Assumptions!$C$13*Assumptions!$C$20)/(((Assumptions!$C$16+Assumptions!$C$17+Assumptions!$C$18+Assumptions!$C$19)+(I$29+I$30)+Assumptions!$E$27+Assumptions!$E$28+Assumptions!$E$29)+Assumptions!$C$20),(Assumptions!$C$42-(Assumptions!$F$27+Assumptions!$F$28+Assumptions!$F$29+Assumptions!$F$30+Assumptions!$F$31+Assumptions!$F$32+Assumptions!$C$7)+Assumptions!$F$27+Assumptions!$F$28+Assumptions!$F$29)/((Assumptions!$C$16+Assumptions!$C$17+Assumptions!$C$18+Assumptions!$C$19)+(I$29+I$30)+Assumptions!$E$27+Assumptions!$E$28+Assumptions!$E$29)) -> 61.096818 | J45: =IF((Assumptions!$C$42-(Assumptions!$F$27+Assumptions!$F$28+Assumptions!$F$29+Assumptions!$F$30+Assumptions!$F$31+Assumptions!$F$32+Assumptions!$C$7)+Assumptions!$F$27+Assumptions!$F$28+Assumptions!$F$29)>Assumptions!$C$13*((Assumptions!$C$16+Assumptions!$C$17+Assumptions!$C$18+Assumptions!$C$19)+(J$29+J$30)+Assumptions!$E$27+Assumptions!$E$28+Assumptions!$E$29),((Assumptions!$C$42-(Assumptions!$F$27+Assumptions!$F$28+Assumptions!$F$29+Assumptions!$F$30+Assumptions!$F$31+Assumptions!$F$32+Assumptions!$C$7)+Assumptions!$F$27+Assumptions!$F$28+Assumptions!$F$29)+Assumptions!$C$13*Assumptions!$C$20)/(((Assumptions!$C$16+Assumptions!$C$17+Assumptions!$C$18+Assumptions!$C$19)+(J$29+J$30)+Assumptions!$E$27+Assumptions!$E$28+Assumptions!$E$29)+Assumptions!$C$20),(Assumptions!$C$42-(Assumptions!$F$27+Assumptions!$F$28+Assumptions!$F$29+Assumptions!$F$30+Assumptions!$F$31+Assumptions!$F$32+Assumptions!$C$7)+Assumptions!$F$27+Assumptions!$F$28+Assumptions!$F$29)/((Assumptions!$C$16+Assumptions!$C$17+Assumptions!$C$18+Assumptions!$C$19)+(J$29+J$30)+Assumptions!$E$27+Assumptions!$E$28+Assumptions!$E$29)) -> 61.087246 | K45: =IF((Assumptions!$C$42-(Assumptions!$F$27+Assumptions!$F$28+Assumptions!$F$29+Assumptions!$F$30+Assumptions!$F$31+Assumptions!$F$32+Assumptions!$C$7)+Assumptions!$F$27+Assumptions!$F$28+Assumptions!$F$29)>Assumptions!$C$13*((Assumptions!$C$16+Assumptions!$C$17+Assumptions!$C$18+Assumptions!$C$19)+(K$29+K$30)+Assumptions!$E$27+Assumptions!$E$28+Assumptions!$E$29),((Assumptions!$C$42-(Assumptions!$F$27+Assumptions!$F$28+Assumptions!$F$29+Assumptions!$F$30+Assumptions!$F$31+Assumptions!$F$32+Assumptions!$C$7)+Assumptions!$F$27+Assumptions!$F$28+Assumptions!$F$29)+Assumptions!$C$13*Assumptions!$C$20)/(((Assumptions!$C$16+Assumptions!$C$17+Assumptions!$C$18+Assumptions!$C$19)+(K$29+K$30)+Assumptions!$E$27+Assumptions!$E$28+Assumptions!$E$29)+Assumptions!$C$20),(Assumptions!$C$42-(Assumptions!$F$27+Assumptions!$F$28+Assumptions!$F$29+Assumptions!$F$30+Assumptions!$F$31+Assumptions!$F$32+Assumptions!$C$7)+Assumptions!$F$27+Assumptions!$F$28+Assumptions!$F$29)/((Assumptions!$C$16+Assumptions!$C$17+Assumptions!$C$18+Assumptions!$C$19)+(K$29+K$30)+Assumptions!$E$27+Assumptions!$E$28+Assumptions!$E$29)) -> 61.071688
B46: PS_{k=4} candidate | C46: =IF((Assumptions!$C$42-(Assumptions!$F$27+Assumptions!$F$28+Assumptions!$F$29+Assumptions!$F$30+Assumptions!$F$31+Assumptions!$F$32+Assumptions!$C$7)+Assumptions!$F$27+Assumptions!$F$28+Assumptions!$F$29+Assumptions!$F$30)>Assumptions!$C$13*((Assumptions!$C$16+Assumptions!$C$17+Assumptions!$C$18+Assumptions!$C$19)+(C$29+C$30)+Assumptions!$E$27+Assumptions!$E$28+Assumptions!$E$29+Assumptions!$E$30),((Assumptions!$C$42-(Assumptions!$F$27+Assumptions!$F$28+Assumptions!$F$29+Assumptions!$F$30+Assumptions!$F$31+Assumptions!$F$32+Assumptions!$C$7)+Assumptions!$F$27+Assumptions!$F$28+Assumptions!$F$29+Assumptions!$F$30)+Assumptions!$C$13*Assumptions!$C$20)/(((Assumptions!$C$16+Assumptions!$C$17+Assumptions!$C$18+Assumptions!$C$19)+(C$29+C$30)+Assumptions!$E$27+Assumptions!$E$28+Assumptions!$E$29+Assumptions!$E$30)+Assumptions!$C$20),(Assumptions!$C$42-(Assumptions!$F$27+Assumptions!$F$28+Assumptions!$F$29+Assumptions!$F$30+Assumptions!$F$31+Assumptions!$F$32+Assumptions!$C$7)+Assumptions!$F$27+Assumptions!$F$28+Assumptions!$F$29+Assumptions!$F$30)/((Assumptions!$C$16+Assumptions!$C$17+Assumptions!$C$18+Assumptions!$C$19)+(C$29+C$30)+Assumptions!$E$27+Assumptions!$E$28+Assumptions!$E$29+Assumptions!$E$30)) -> 57.809418 | D46: =IF((Assumptions!$C$42-(Assumptions!$F$27+Assumptions!$F$28+Assumptions!$F$29+Assumptions!$F$30+Assumptions!$F$31+Assumptions!$F$32+Assumptions!$C$7)+Assumptions!$F$27+Assumptions!$F$28+Assumptions!$F$29+Assumptions!$F$30)>Assumptions!$C$13*((Assumptions!$C$16+Assumptions!$C$17+Assumptions!$C$18+Assumptions!$C$19)+(D$29+D$30)+Assumptions!$E$27+Assumptions!$E$28+Assumptions!$E$29+Assumptions!$E$30),((Assumptions!$C$42-(Assumptions!$F$27+Assumptions!$F$28+Assumptions!$F$29+Assumptions!$F$30+Assumptions!$F$31+Assumptions!$F$32+Assumptions!$C$7)+Assumptions!$F$27+Assumptions!$F$28+Assumptions!$F$29+Assumptions!$F$30)+Assumptions!$C$13*Assumptions!$C$20)/(((Assumptions!$C$16+Assumptions!$C$17+Assumptions!$C$18+Assumptions!$C$19)+(D$29+D$30)+Assumptions!$E$27+Assumptions!$E$28+Assumptions!$E$29+Assumptions!$E$30)+Assumptions!$C$20),(Assumptions!$C$42-(Assumptions!$F$27+Assumptions!$F$28+Assumptions!$F$29+Assumptions!$F$30+Assumptions!$F$31+Assumptions!$F$32+Assumptions!$C$7)+Assumptions!$F$27+Assumptions!$F$28+Assumptions!$F$29+Assumptions!$F$30)/((Assumptions!$C$16+Assumptions!$C$17+Assumptions!$C$18+Assumptions!$C$19)+(D$29+D$30)+Assumptions!$E$27+Assumptions!$E$28+Assumptions!$E$29+Assumptions!$E$30)) -> 57.798577 | E46: =IF((Assumptions!$C$42-(Assumptions!$F$27+Assumptions!$F$28+Assumptions!$F$29+Assumptions!$F$30+Assumptions!$F$31+Assumptions!$F$32+Assumptions!$C$7)+Assumptions!$F$27+Assumptions!$F$28+Assumptions!$F$29+Assumptions!$F$30)>Assumptions!$C$13*((Assumptions!$C$16+Assumptions!$C$17+Assumptions!$C$18+Assumptions!$C$19)+(E$29+E$30)+Assumptions!$E$27+Assumptions!$E$28+Assumptions!$E$29+Assumptions!$E$30),((Assumptions!$C$42-(Assumptions!$F$27+Assumptions!$F$28+Assumptions!$F$29+Assumptions!$F$30+Assumptions!$F$31+Assumptions!$F$32+Assumptions!$C$7)+Assumptions!$F$27+Assumptions!$F$28+Assumptions!$F$29+Assumptions!$F$30)+Assumptions!$C$13*Assumptions!$C$20)/(((Assumptions!$C$16+Assumptions!$C$17+Assumptions!$C$18+Assumptions!$C$19)+(E$29+E$30)+Assumptions!$E$27+Assumptions!$E$28+Assumptions!$E$29+Assumptions!$E$30)+Assumptions!$C$20),(Assumptions!$C$42-(Assumptions!$F$27+Assumptions!$F$28+Assumptions!$F$29+Assumptions!$F$30+Assumptions!$F$31+Assumptions!$F$32+Assumptions!$C$7)+Assumptions!$F$27+Assumptions!$F$28+Assumptions!$F$29+Assumptions!$F$30)/((Assumptions!$C$16+Assumptions!$C$17+Assumptions!$C$18+Assumptions!$C$19)+(E$29+E$30)+Assumptions!$E$27+Assumptions!$E$28+Assumptions!$E$29+Assumptions!$E$30)) -> 57.782551 | F46: =IF((Assumptions!$C$42-(Assumptions!$F$27+Assumptions!$F$28+Assumptions!$F$29+Assumptions!$F$30+Assumptions!$F$31+Assumptions!$F$32+Assumptions!$C$7)+Assumptions!$F$27+Assumptions!$F$28+Assumptions!$F$29+Assumptions!$F$30)>Assumptions!$C$13*((Assumptions!$C$16+Assumptions!$C$17+Assumptions!$C$18+Assumptions!$C$19)+(F$29+F$30)+Assumptions!$E$27+Assumptions!$E$28+Assumptions!$E$29+Assumptions!$E$30),((Assumptions!$C$42-(Assumptions!$F$27+Assumptions!$F$28+Assumptions!$F$29+Assumptions!$F$30+Assumptions!$F$31+Assumptions!$F$32+Assumptions!$C$7)+Assumptions!$F$27+Assumptions!$F$28+Assumptions!$F$29+Assumptions!$F$30)+Assumptions!$C$13*Assumptions!$C$20)/(((Assumptions!$C$16+Assumptions!$C$17+Assumptions!$C$18+Assumptions!$C$19)+(F$29+F$30)+Assumptions!$E$27+Assumptions!$E$28+Assumptions!$E$29+Assumptions!$E$30)+Assumptions!$C$20),(Assumptions!$C$42-(Assumptions!$F$27+Assumptions!$F$28+Assumptions!$F$29+Assumptions!$F$30+Assumptions!$F$31+Assumptions!$F$32+Assumptions!$C$7)+Assumptions!$F$27+Assumptions!$F$28+Assumptions!$F$29+Assumptions!$F$30)/((Assumptions!$C$16+Assumptions!$C$17+Assumptions!$C$18+Assumptions!$C$19)+(F$29+F$30)+Assumptions!$E$27+Assumptions!$E$28+Assumptions!$E$29+Assumptions!$E$30)) -> 57.861666 | G46: =IF((Assumptions!$C$42-(Assumptions!$F$27+Assumptions!$F$28+Assumptions!$F$29+Assumptions!$F$30+Assumptions!$F$31+Assumptions!$F$32+Assumptions!$C$7)+Assumptions!$F$27+Assumptions!$F$28+Assumptions!$F$29+Assumptions!$F$30)>Assumptions!$C$13*((Assumptions!$C$16+Assumptions!$C$17+Assumptions!$C$18+Assumptions!$C$19)+(G$29+G$30)+Assumptions!$E$27+Assumptions!$E$28+Assumptions!$E$29+Assumptions!$E$30),((Assumptions!$C$42-(Assumptions!$F$27+Assumptions!$F$28+Assumptions!$F$29+Assumptions!$F$30+Assumptions!$F$31+Assumptions!$F$32+Assumptions!$C$7)+Assumptions!$F$27+Assumptions!$F$28+Assumptions!$F$29+Assumptions!$F$30)+Assumptions!$C$13*Assumptions!$C$20)/(((Assumptions!$C$16+Assumptions!$C$17+Assumptions!$C$18+Assumptions!$C$19)+(G$29+G$30)+Assumptions!$E$27+Assumptions!$E$28+Assumptions!$E$29+Assumptions!$E$30)+Assumptions!$C$20),(Assumptions!$C$42-(Assumptions!$F$27+Assumptions!$F$28+Assumptions!$F$29+Assumptions!$F$30+Assumptions!$F$31+Assumptions!$F$32+Assumptions!$C$7)+Assumptions!$F$27+Assumptions!$F$28+Assumptions!$F$29+Assumptions!$F$30)/((Assumptions!$C$16+Assumptions!$C$17+Assumptions!$C$18+Assumptions!$C$19)+(G$29+G$30)+Assumptions!$E$27+Assumptions!$E$28+Assumptions!$E$29+Assumptions!$E$30)) -> 57.852149 | H46: =IF((Assumptions!$C$42-(Assumptions!$F$27+Assumptions!$F$28+Assumptions!$F$29+Assumptions!$F$30+Assumptions!$F$31+Assumptions!$F$32+Assumptions!$C$7)+Assumptions!$F$27+Assumptions!$F$28+Assumptions!$F$29+Assumptions!$F$30)>Assumptions!$C$13*((Assumptions!$C$16+Assumptions!$C$17+Assumptions!$C$18+Assumptions!$C$19)+(H$29+H$30)+Assumptions!$E$27+Assumptions!$E$28+Assumptions!$E$29+Assumptions!$E$30),((Assumptions!$C$42-(Assumptions!$F$27+Assumptions!$F$28+Assumptions!$F$29+Assumptions!$F$30+Assumptions!$F$31+Assumptions!$F$32+Assumptions!$C$7)+Assumptions!$F$27+Assumptions!$F$28+Assumptions!$F$29+Assumptions!$F$30)+Assumptions!$C$13*Assumptions!$C$20)/(((Assumptions!$C$16+Assumptions!$C$17+Assumptions!$C$18+Assumptions!$C$19)+(H$29+H$30)+Assumptions!$E$27+Assumptions!$E$28+Assumptions!$E$29+Assumptions!$E$30)+Assumptions!$C$20),(Assumptions!$C$42-(Assumptions!$F$27+Assumptions!$F$28+Assumptions!$F$29+Assumptions!$F$30+Assumptions!$F$31+Assumptions!$F$32+Assumptions!$C$7)+Assumptions!$F$27+Assumptions!$F$28+Assumptions!$F$29+Assumptions!$F$30)/((Assumptions!$C$16+Assumptions!$C$17+Assumptions!$C$18+Assumptions!$C$19)+(H$29+H$30)+Assumptions!$E$27+Assumptions!$E$28+Assumptions!$E$29+Assumptions!$E$30)) -> 57.837498 | I46: =IF((Assumptions!$C$42-(Assumptions!$F$27+Assumptions!$F$28+Assumptions!$F$29+Assumptions!$F$30+Assumptions!$F$31+Assumptions!$F$32+Assumptions!$C$7)+Assumptions!$F$27+Assumptions!$F$28+Assumptions!$F$29+Assumptions!$F$30)>Assumptions!$C$13*((Assumptions!$C$16+Assumptions!$C$17+Assumptions!$C$18+Assumptions!$C$19)+(I$29+I$30)+Assumptions!$E$27+Assumptions!$E$28+Assumptions!$E$29+Assumptions!$E$30),((Assumptions!$C$42-(Assumptions!$F$27+Assumptions!$F$28+Assumptions!$F$29+Assumptions!$F$30+Assumptions!$F$31+Assumptions!$F$32+Assumptions!$C$7)+Assumptions!$F$27+Assumptions!$F$28+Assumptions!$F$29+Assumptions!$F$30)+Assumptions!$C$13*Assumptions!$C$20)/(((Assumptions!$C$16+Assumptions!$C$17+Assumptions!$C$18+Assumptions!$C$19)+(I$29+I$30)+Assumptions!$E$27+Assumptions!$E$28+Assumptions!$E$29+Assumptions!$E$30)+Assumptions!$C$20),(Assumptions!$C$42-(Assumptions!$F$27+Assumptions!$F$28+Assumptions!$F$29+Assumptions!$F$30+Assumptions!$F$31+Assumptions!$F$32+Assumptions!$C$7)+Assumptions!$F$27+Assumptions!$F$28+Assumptions!$F$29+Assumptions!$F$30)/((Assumptions!$C$16+Assumptions!$C$17+Assumptions!$C$18+Assumptions!$C$19)+(I$29+I$30)+Assumptions!$E$27+Assumptions!$E$28+Assumptions!$E$29+Assumptions!$E$30)) -> 57.906619 | J46: =IF((Assumptions!$C$42-(Assumptions!$F$27+Assumptions!$F$28+Assumptions!$F$29+Assumptions!$F$30+Assumptions!$F$31+Assumptions!$F$32+Assumptions!$C$7)+Assumptions!$F$27+Assumptions!$F$28+Assumptions!$F$29+Assumptions!$F$30)>Assumptions!$C$13*((Assumptions!$C$16+Assumptions!$C$17+Assumptions!$C$18+Assumptions!$C$19)+(J$29+J$30)+Assumptions!$E$27+Assumptions!$E$28+Assumptions!$E$29+Assumptions!$E$30),((Assumptions!$C$42-(Assumptions!$F$27+Assumptions!$F$28+Assumptions!$F$29+Assumptions!$F$30+Assumptions!$F$31+Assumptions!$F$32+Assumptions!$C$7)+Assumptions!$F$27+Assumptions!$F$28+Assumptions!$F$29+Assumptions!$F$30)+Assumptions!$C$13*Assumptions!$C$20)/(((Assumptions!$C$16+Assumptions!$C$17+Assumptions!$C$18+Assumptions!$C$19)+(J$29+J$30)+Assumptions!$E$27+Assumptions!$E$28+Assumptions!$E$29+Assumptions!$E$30)+Assumptions!$C$20),(Assumptions!$C$42-(Assumptions!$F$27+Assumptions!$F$28+Assumptions!$F$29+Assumptions!$F$30+Assumptions!$F$31+Assumptions!$F$32+Assumptions!$C$7)+Assumptions!$F$27+Assumptions!$F$28+Assumptions!$F$29+Assumptions!$F$30)/((Assumptions!$C$16+Assumptions!$C$17+Assumptions!$C$18+Assumptions!$C$19)+(J$29+J$30)+Assumptions!$E$27+Assumptions!$E$28+Assumptions!$E$29+Assumptions!$E$30)) -> 57.898349 | K46: =IF((Assumptions!$C$42-(Assumptions!$F$27+Assumptions!$F$28+Assumptions!$F$29+Assumptions!$F$30+Assumptions!$F$31+Assumptions!$F$32+Assumptions!$C$7)+Assumptions!$F$27+Assumptions!$F$28+Assumptions!$F$29+Assumptions!$F$30)>Assumptions!$C$13*((Assumptions!$C$16+Assumptions!$C$17+Assumptions!$C$18+Assumptions!$C$19)+(K$29+K$30)+Assumptions!$E$27+Assumptions!$E$28+Assumptions!$E$29+Assumptions!$E$30),((Assumptions!$C$42-(Assumptions!$F$27+Assumptions!$F$28+Assumptions!$F$29+Assumptions!$F$30+Assumptions!$F$31+Assumptions!$F$32+Assumptions!$C$7)+Assumptions!$F$27+Assumptions!$F$28+Assumptions!$F$29+Assumptions!$F$30)+Assumptions!$C$13*Assumptions!$C$20)/(((Assumptions!$C$16+Assumptions!$C$17+Assumptions!$C$18+Assumptions!$C$19)+(K$29+K$30)+Assumptions!$E$27+Assumptions!$E$28+Assumptions!$E$29+Assumptions!$E$30)+Assumptions!$C$20),(Assumptions!$C$42-(Assumptions!$F$27+Assumptions!$F$28+Assumptions!$F$29+Assumptions!$F$30+Assumptions!$F$31+Assumptions!$F$32+Assumptions!$C$7)+Assumptions!$F$27+Assumptions!$F$28+Assumptions!$F$29+Assumptions!$F$30)/((Assumptions!$C$16+Assumptions!$C$17+Assumptions!$C$18+Assumptions!$C$19)+(K$29+K$30)+Assumptions!$E$27+Assumptions!$E$28+Assumptions!$E$29+Assumptions!$E$30)) -> 57.884905
B47: PS_{k=5} candidate | C47: =IF((Assumptions!$C$42-(Assumptions!$F$27+Assumptions!$F$28+Assumptions!$F$29+Assumptions!$F$30+Assumptions!$F$31+Assumptions!$F$32+Assumptions!$C$7)+Assumptions!$F$27+Assumptions!$F$28+Assumptions!$F$29+Assumptions!$F$30+Assumptions!$C$7)>Assumptions!$C$13*((Assumptions!$C$16+Assumptions!$C$17+Assumptions!$C$18+Assumptions!$C$19)+(C$29+C$30)+Assumptions!$E$27+Assumptions!$E$28+Assumptions!$E$29+Assumptions!$E$30+C$24),((Assumptions!$C$42-(Assumptions!$F$27+Assumptions!$F$28+Assumptions!$F$29+Assumptions!$F$30+Assumptions!$F$31+Assumptions!$F$32+Assumptions!$C$7)+Assumptions!$F$27+Assumptions!$F$28+Assumptions!$F$29+Assumptions!$F$30+Assumptions!$C$7)+Assumptions!$C$13*Assumptions!$C$20)/(((Assumptions!$C$16+Assumptions!$C$17+Assumptions!$C$18+Assumptions!$C$19)+(C$29+C$30)+Assumptions!$E$27+Assumptions!$E$28+Assumptions!$E$29+Assumptions!$E$30+C$24)+Assumptions!$C$20),(Assumptions!$C$42-(Assumptions!$F$27+Assumptions!$F$28+Assumptions!$F$29+Assumptions!$F$30+Assumptions!$F$31+Assumptions!$F$32+Assumptions!$C$7)+Assumptions!$F$27+Assumptions!$F$28+Assumptions!$F$29+Assumptions!$F$30+Assumptions!$C$7)/((Assumptions!$C$16+Assumptions!$C$17+Assumptions!$C$18+Assumptions!$C$19)+(C$29+C$30)+Assumptions!$E$27+Assumptions!$E$28+Assumptions!$E$29+Assumptions!$E$30+C$24)) -> 56.975349 | D47: =IF((Assumptions!$C$42-(Assumptions!$F$27+Assumptions!$F$28+Assumptions!$F$29+Assumptions!$F$30+Assumptions!$F$31+Assumptions!$F$32+Assumptions!$C$7)+Assumptions!$F$27+Assumptions!$F$28+Assumptions!$F$29+Assumptions!$F$30+Assumptions!$C$7)>Assumptions!$C$13*((Assumptions!$C$16+Assumptions!$C$17+Assumptions!$C$18+Assumptions!$C$19)+(D$29+D$30)+Assumptions!$E$27+Assumptions!$E$28+Assumptions!$E$29+Assumptions!$E$30+D$24),((Assumptions!$C$42-(Assumptions!$F$27+Assumptions!$F$28+Assumptions!$F$29+Assumptions!$F$30+Assumptions!$F$31+Assumptions!$F$32+Assumptions!$C$7)+Assumptions!$F$27+Assumptions!$F$28+Assumptions!$F$29+Assumptions!$F$30+Assumptions!$C$7)+Assumptions!$C$13*Assumptions!$C$20)/(((Assumptions!$C$16+Assumptions!$C$17+Assumptions!$C$18+Assumptions!$C$19)+(D$29+D$30)+Assumptions!$E$27+Assumptions!$E$28+Assumptions!$E$29+Assumptions!$E$30+D$24)+Assumptions!$C$20),(Assumptions!$C$42-(Assumptions!$F$27+Assumptions!$F$28+Assumptions!$F$29+Assumptions!$F$30+Assumptions!$F$31+Assumptions!$F$32+Assumptions!$C$7)+Assumptions!$F$27+Assumptions!$F$28+Assumptions!$F$29+Assumptions!$F$30+Assumptions!$C$7)/((Assumptions!$C$16+Assumptions!$C$17+Assumptions!$C$18+Assumptions!$C$19)+(D$29+D$30)+Assumptions!$E$27+Assumptions!$E$28+Assumptions!$E$29+Assumptions!$E$30+D$24)) -> 56.933339 | E47: =IF((Assumptions!$C$42-(Assumptions!$F$27+Assumptions!$F$28+Assumptions!$F$29+Assumptions!$F$30+Assumptions!$F$31+Assumptions!$F$32+Assumptions!$C$7)+Assumptions!$F$27+Assumptions!$F$28+Assumptions!$F$29+Assumptions!$F$30+Assumptions!$C$7)>Assumptions!$C$13*((Assumptions!$C$16+Assumptions!$C$17+Assumptions!$C$18+Assumptions!$C$19)+(E$29+E$30)+Assumptions!$E$27+Assumptions!$E$28+Assumptions!$E$29+Assumptions!$E$30+E$24),((Assumptions!$C$42-(Assumptions!$F$27+Assumptions!$F$28+Assumptions!$F$29+Assumptions!$F$30+Assumptions!$F$31+Assumptions!$F$32+Assumptions!$C$7)+Assumptions!$F$27+Assumptions!$F$28+Assumptions!$F$29+Assumptions!$F$30+Assumptions!$C$7)+Assumptions!$C$13*Assumptions!$C$20)/(((Assumptions!$C$16+Assumptions!$C$17+Assumptions!$C$18+Assumptions!$C$19)+(E$29+E$30)+Assumptions!$E$27+Assumptions!$E$28+Assumptions!$E$29+Assumptions!$E$30+E$24)+Assumptions!$C$20),(Assumptions!$C$42-(Assumptions!$F$27+Assumptions!$F$28+Assumptions!$F$29+Assumptions!$F$30+Assumptions!$F$31+Assumptions!$F$32+Assumptions!$C$7)+Assumptions!$F$27+Assumptions!$F$28+Assumptions!$F$29+Assumptions!$F$30+Assumptions!$C$7)/((Assumptions!$C$16+Assumptions!$C$17+Assumptions!$C$18+Assumptions!$C$19)+(E$29+E$30)+Assumptions!$E$27+Assumptions!$E$28+Assumptions!$E$29+Assumptions!$E$30+E$24)) -> 56.871323 | F47: =IF((Assumptions!$C$42-(Assumptions!$F$27+Assumptions!$F$28+Assumptions!$F$29+Assumptions!$F$30+Assumptions!$F$31+Assumptions!$F$32+Assumptions!$C$7)+Assumptions!$F$27+Assumptions!$F$28+Assumptions!$F$29+Assumptions!$F$30+Assumptions!$C$7)>Assumptions!$C$13*((Assumptions!$C$16+Assumptions!$C$17+Assumptions!$C$18+Assumptions!$C$19)+(F$29+F$30)+Assumptions!$E$27+Assumptions!$E$28+Assumptions!$E$29+Assumptions!$E$30+F$24),((Assumptions!$C$42-(Assumptions!$F$27+Assumptions!$F$28+Assumptions!$F$29+Assumptions!$F$30+Assumptions!$F$31+Assumptions!$F$32+Assumptions!$C$7)+Assumptions!$F$27+Assumptions!$F$28+Assumptions!$F$29+Assumptions!$F$30+Assumptions!$C$7)+Assumptions!$C$13*Assumptions!$C$20)/(((Assumptions!$C$16+Assumptions!$C$17+Assumptions!$C$18+Assumptions!$C$19)+(F$29+F$30)+Assumptions!$E$27+Assumptions!$E$28+Assumptions!$E$29+Assumptions!$E$30+F$24)+Assumptions!$C$20),(Assumptions!$C$42-(Assumptions!$F$27+Assumptions!$F$28+Assumptions!$F$29+Assumptions!$F$30+Assumptions!$F$31+Assumptions!$F$32+Assumptions!$C$7)+Assumptions!$F$27+Assumptions!$F$28+Assumptions!$F$29+Assumptions!$F$30+Assumptions!$C$7)/((Assumptions!$C$16+Assumptions!$C$17+Assumptions!$C$18+Assumptions!$C$19)+(F$29+F$30)+Assumptions!$E$27+Assumptions!$E$28+Assumptions!$E$29+Assumptions!$E$30+F$24)) -> 57.296801 | G47: =IF((Assumptions!$C$42-(Assumptions!$F$27+Assumptions!$F$28+Assumptions!$F$29+Assumptions!$F$30+Assumptions!$F$31+Assumptions!$F$32+Assumptions!$C$7)+Assumptions!$F$27+Assumptions!$F$28+Assumptions!$F$29+Assumptions!$F$30+Assumptions!$C$7)>Assumptions!$C$13*((Assumptions!$C$16+Assumptions!$C$17+Assumptions!$C$18+Assumptions!$C$19)+(G$29+G$30)+Assumptions!$E$27+Assumptions!$E$28+Assumptions!$E$29+Assumptions!$E$30+G$24),((Assumptions!$C$42-(Assumptions!$F$27+Assumptions!$F$28+Assumptions!$F$29+Assumptions!$F$30+Assumptions!$F$31+Assumptions!$F$32+Assumptions!$C$7)+Assumptions!$F$27+Assumptions!$F$28+Assumptions!$F$29+Assumptions!$F$30+Assumptions!$C$7)+Assumptions!$C$13*Assumptions!$C$20)/(((Assumptions!$C$16+Assumptions!$C$17+Assumptions!$C$18+Assumptions!$C$19)+(G$29+G$30)+Assumptions!$E$27+Assumptions!$E$28+Assumptions!$E$29+Assumptions!$E$30+G$24)+Assumptions!$C$20),(Assumptions!$C$42-(Assumptions!$F$27+Assumptions!$F$28+Assumptions!$F$29+Assumptions!$F$30+Assumptions!$F$31+Assumptions!$F$32+Assumptions!$C$7)+Assumptions!$F$27+Assumptions!$F$28+Assumptions!$F$29+Assumptions!$F$30+Assumptions!$C$7)/((Assumptions!$C$16+Assumptions!$C$17+Assumptions!$C$18+Assumptions!$C$19)+(G$29+G$30)+Assumptions!$E$27+Assumptions!$E$28+Assumptions!$E$29+Assumptions!$E$30+G$24)) -> 57.261479 | H47: =IF((Assumptions!$C$42-(Assumptions!$F$27+Assumptions!$F$28+Assumptions!$F$29+Assumptions!$F$30+Assumptions!$F$31+Assumptions!$F$32+Assumptions!$C$7)+Assumptions!$F$27+Assumptions!$F$28+Assumptions!$F$29+Assumptions!$F$30+Assumptions!$C$7)>Assumptions!$C$13*((Assumptions!$C$16+Assumptions!$C$17+Assumptions!$C$18+Assumptions!$C$19)+(H$29+H$30)+Assumptions!$E$27+Assumptions!$E$28+Assumptions!$E$29+Assumptions!$E$30+H$24),((Assumptions!$C$42-(Assumptions!$F$27+Assumptions!$F$28+Assumptions!$F$29+Assumptions!$F$30+Assumptions!$F$31+Assumptions!$F$32+Assumptions!$C$7)+Assumptions!$F$27+Assumptions!$F$28+Assumptions!$F$29+Assumptions!$F$30+Assumptions!$C$7)+Assumptions!$C$13*Assumptions!$C$20)/(((Assumptions!$C$16+Assumptions!$C$17+Assumptions!$C$18+Assumptions!$C$19)+(H$29+H$30)+Assumptions!$E$27+Assumptions!$E$28+Assumptions!$E$29+Assumptions!$E$30+H$24)+Assumptions!$C$20),(Assumptions!$C$42-(Assumptions!$F$27+Assumptions!$F$28+Assumptions!$F$29+Assumptions!$F$30+Assumptions!$F$31+Assumptions!$F$32+Assumptions!$C$7)+Assumptions!$F$27+Assumptions!$F$28+Assumptions!$F$29+Assumptions!$F$30+Assumptions!$C$7)/((Assumptions!$C$16+Assumptions!$C$17+Assumptions!$C$18+Assumptions!$C$19)+(H$29+H$30)+Assumptions!$E$27+Assumptions!$E$28+Assumptions!$E$29+Assumptions!$E$30+H$24)) -> 57.20717 | I47: =IF((Assumptions!$C$42-(Assumptions!$F$27+Assumptions!$F$28+Assumptions!$F$29+Assumptions!$F$30+Assumptions!$F$31+Assumptions!$F$32+Assumptions!$C$7)+Assumptions!$F$27+Assumptions!$F$28+Assumptions!$F$29+Assumptions!$F$30+Assumptions!$C$7)>Assumptions!$C$13*((Assumptions!$C$16+Assumptions!$C$17+Assumptions!$C$18+Assumptions!$C$19)+(I$29+I$30)+Assumptions!$E$27+Assumptions!$E$28+Assumptions!$E$29+Assumptions!$E$30+I$24),((Assumptions!$C$42-(Assumptions!$F$27+Assumptions!$F$28+Assumptions!$F$29+Assumptions!$F$30+Assumptions!$F$31+Assumptions!$F$32+Assumptions!$C$7)+Assumptions!$F$27+Assumptions!$F$28+Assumptions!$F$29+Assumptions!$F$30+Assumptions!$C$7)+Assumptions!$C$13*Assumptions!$C$20)/(((Assumptions!$C$16+Assumptions!$C$17+Assumptions!$C$18+Assumptions!$C$19)+(I$29+I$30)+Assumptions!$E$27+Assumptions!$E$28+Assumptions!$E$29+Assumptions!$E$30+I$24)+Assumptions!$C$20),(Assumptions!$C$42-(Assumptions!$F$27+Assumptions!$F$28+Assumptions!$F$29+Assumptions!$F$30+Assumptions!$F$31+Assumptions!$F$32+Assumptions!$C$7)+Assumptions!$F$27+Assumptions!$F$28+Assumptions!$F$29+Assumptions!$F$30+Assumptions!$C$7)/((Assumptions!$C$16+Assumptions!$C$17+Assumptions!$C$18+Assumptions!$C$19)+(I$29+I$30)+Assumptions!$E$27+Assumptions!$E$28+Assumptions!$E$29+Assumptions!$E$30+I$24)) -> 57.70524 | J47: =IF((Assumptions!$C$42-(Assumptions!$F$27+Assumptions!$F$28+Assumptions!$F$29+Assumptions!$F$30+Assumptions!$F$31+Assumptions!$F$32+Assumptions!$C$7)+Assumptions!$F$27+Assumptions!$F$28+Assumptions!$F$29+Assumptions!$F$30+Assumptions!$C$7)>Assumptions!$C$13*((Assumptions!$C$16+Assumptions!$C$17+Assumptions!$C$18+Assumptions!$C$19)+(J$29+J$30)+Assumptions!$E$27+Assumptions!$E$28+Assumptions!$E$29+Assumptions!$E$30+J$24),((Assumptions!$C$42-(Assumptions!$F$27+Assumptions!$F$28+Assumptions!$F$29+Assumptions!$F$30+Assumptions!$F$31+Assumptions!$F$32+Assumptions!$C$7)+Assumptions!$F$27+Assumptions!$F$28+Assumptions!$F$29+Assumptions!$F$30+Assumptions!$C$7)+Assumptions!$C$13*Assumptions!$C$20)/(((Assumptions!$C$16+Assumptions!$C$17+Assumptions!$C$18+Assumptions!$C$19)+(J$29+J$30)+Assumptions!$E$27+Assumptions!$E$28+Assumptions!$E$29+Assumptions!$E$30+J$24)+Assumptions!$C$20),(Assumptions!$C$42-(Assumptions!$F$27+Assumptions!$F$28+Assumptions!$F$29+Assumptions!$F$30+Assumptions!$F$31+Assumptions!$F$32+Assumptions!$C$7)+Assumptions!$F$27+Assumptions!$F$28+Assumptions!$F$29+Assumptions!$F$30+Assumptions!$C$7)/((Assumptions!$C$16+Assumptions!$C$17+Assumptions!$C$18+Assumptions!$C$19)+(J$29+J$30)+Assumptions!$E$27+Assumptions!$E$28+Assumptions!$E$29+Assumptions!$E$30+J$24)) -> 57.677823 | K47: =IF((Assumptions!$C$42-(Assumptions!$F$27+Assumptions!$F$28+Assumptions!$F$29+Assumptions!$F$30+Assumptions!$F$31+Assumptions!$F$32+Assumptions!$C$7)+Assumptions!$F$27+Assumptions!$F$28+Assumptions!$F$29+Assumptions!$F$30+Assumptions!$C$7)>Assumptions!$C$13*((Assumptions!$C$16+Assumptions!$C$17+Assumptions!$C$18+Assumptions!$C$19)+(K$29+K$30)+Assumptions!$E$27+Assumptions!$E$28+Assumptions!$E$29+Assumptions!$E$30+K$24),((Assumptions!$C$42-(Assumptions!$F$27+Assumptions!$F$28+Assumptions!$F$29+Assumptions!$F$30+Assumptions!$F$31+Assumptions!$F$32+Assumptions!$C$7)+Assumptions!$F$27+Assumptions!$F$28+Assumptions!$F$29+Assumptions!$F$30+Assumptions!$C$7)+Assumptions!$C$13*Assumptions!$C$20)/(((Assumptions!$C$16+Assumptions!$C$17+Assumptions!$C$18+Assumptions!$C$19)+(K$29+K$30)+Assumptions!$E$27+Assumptions!$E$28+Assumptions!$E$29+Assumptions!$E$30+K$24)+Assumptions!$C$20),(Assumptions!$C$42-(Assumptions!$F$27+Assumptions!$F$28+Assumptions!$F$29+Assumptions!$F$30+Assumptions!$F$31+Assumptions!$F$32+Assumptions!$C$7)+Assumptions!$F$27+Assumptions!$F$28+Assumptions!$F$29+Assumptions!$F$30+Assumptions!$C$7)/((Assumptions!$C$16+Assumptions!$C$17+Assumptions!$C$18+Assumptions!$C$19)+(K$29+K$30)+Assumptions!$E$27+Assumptions!$E$28+Assumptions!$E$29+Assumptions!$E$30+K$24)) -> 57.633298
B48: PS_{k=6} candidate | C48: =IF((Assumptions!$C$42-(Assumptions!$F$27+Assumptions!$F$28+Assumptions!$F$29+Assumptions!$F$30+Assumptions!$F$31+Assumptions!$F$32+Assumptions!$C$7)+Assumptions!$F$27+Assumptions!$F$28+Assumptions!$F$29+Assumptions!$F$30+Assumptions!$C$7+Assumptions!$F$32)>Assumptions!$C$13*((Assumptions!$C$16+Assumptions!$C$17+Assumptions!$C$18+Assumptions!$C$19)+(C$29+C$30)+Assumptions!$E$27+Assumptions!$E$28+Assumptions!$E$29+Assumptions!$E$30+C$24+C$28),((Assumptions!$C$42-(Assumptions!$F$27+Assumptions!$F$28+Assumptions!$F$29+Assumptions!$F$30+Assumptions!$F$31+Assumptions!$F$32+Assumptions!$C$7)+Assumptions!$F$27+Assumptions!$F$28+Assumptions!$F$29+Assumptions!$F$30+Assumptions!$C$7+Assumptions!$F$32)+Assumptions!$C$13*Assumptions!$C$20)/(((Assumptions!$C$16+Assumptions!$C$17+Assumptions!$C$18+Assumptions!$C$19)+(C$29+C$30)+Assumptions!$E$27+Assumptions!$E$28+Assumptions!$E$29+Assumptions!$E$30+C$24+C$28)+Assumptions!$C$20),(Assumptions!$C$42-(Assumptions!$F$27+Assumptions!$F$28+Assumptions!$F$29+Assumptions!$F$30+Assumptions!$F$31+Assumptions!$F$32+Assumptions!$C$7)+Assumptions!$F$27+Assumptions!$F$28+Assumptions!$F$29+Assumptions!$F$30+Assumptions!$C$7+Assumptions!$F$32)/((Assumptions!$C$16+Assumptions!$C$17+Assumptions!$C$18+Assumptions!$C$19)+(C$29+C$30)+Assumptions!$E$27+Assumptions!$E$28+Assumptions!$E$29+Assumptions!$E$30+C$24+C$28)) -> 55.498052 | D48: =IF((Assumptions!$C$42-(Assumptions!$F$27+Assumptions!$F$28+Assumptions!$F$29+Assumptions!$F$30+Assumptions!$F$31+Assumptions!$F$32+Assumptions!$C$7)+Assumptions!$F$27+Assumptions!$F$28+Assumptions!$F$29+Assumptions!$F$30+Assumptions!$C$7+Assumptions!$F$32)>Assumptions!$C$13*((Assumptions!$C$16+Assumptions!$C$17+Assumptions!$C$18+Assumptions!$C$19)+(D$29+D$30)+Assumptions!$E$27+Assumptions!$E$28+Assumptions!$E$29+Assumptions!$E$30+D$24+D$28),((Assumptions!$C$42-(Assumptions!$F$27+Assumptions!$F$28+Assumptions!$F$29+Assumptions!$F$30+Assumptions!$F$31+Assumptions!$F$32+Assumptions!$C$7)+Assumptions!$F$27+Assumptions!$F$28+Assumptions!$F$29+Assumptions!$F$30+Assumptions!$C$7+Assumptions!$F$32)+Assumptions!$C$13*Assumptions!$C$20)/(((Assumptions!$C$16+Assumptions!$C$17+Assumptions!$C$18+Assumptions!$C$19)+(D$29+D$30)+Assumptions!$E$27+Assumptions!$E$28+Assumptions!$E$29+Assumptions!$E$30+D$24+D$28)+Assumptions!$C$20),(Assumptions!$C$42-(Assumptions!$F$27+Assumptions!$F$28+Assumptions!$F$29+Assumptions!$F$30+Assumptions!$F$31+Assumptions!$F$32+Assumptions!$C$7)+Assumptions!$F$27+Assumptions!$F$28+Assumptions!$F$29+Assumptions!$F$30+Assumptions!$C$7+Assumptions!$F$32)/((Assumptions!$C$16+Assumptions!$C$17+Assumptions!$C$18+Assumptions!$C$19)+(D$29+D$30)+Assumptions!$E$27+Assumptions!$E$28+Assumptions!$E$29+Assumptions!$E$30+D$24+D$28)) -> 55.460325 | E48: =IF((Assumptions!$C$42-(Assumptions!$F$27+Assumptions!$F$28+Assumptions!$F$29+Assumptions!$F$30+Assumptions!$F$31+Assumptions!$F$32+Assumptions!$C$7)+Assumptions!$F$27+Assumptions!$F$28+Assumptions!$F$29+Assumptions!$F$30+Assumptions!$C$7+Assumptions!$F$32)>Assumptions!$C$13*((Assumptions!$C$16+Assumptions!$C$17+Assumptions!$C$18+Assumptions!$C$19)+(E$29+E$30)+Assumptions!$E$27+Assumptions!$E$28+Assumptions!$E$29+Assumptions!$E$30+E$24+E$28),((Assumptions!$C$42-(Assumptions!$F$27+Assumptions!$F$28+Assumptions!$F$29+Assumptions!$F$30+Assumptions!$F$31+Assumptions!$F$32+Assumptions!$C$7)+Assumptions!$F$27+Assumptions!$F$28+Assumptions!$F$29+Assumptions!$F$30+Assumptions!$C$7+Assumptions!$F$32)+Assumptions!$C$13*Assumptions!$C$20)/(((Assumptions!$C$16+Assumptions!$C$17+Assumptions!$C$18+Assumptions!$C$19)+(E$29+E$30)+Assumptions!$E$27+Assumptions!$E$28+Assumptions!$E$29+Assumptions!$E$30+E$24+E$28)+Assumptions!$C$20),(Assumptions!$C$42-(Assumptions!$F$27+Assumptions!$F$28+Assumptions!$F$29+Assumptions!$F$30+Assumptions!$F$31+Assumptions!$F$32+Assumptions!$C$7)+Assumptions!$F$27+Assumptions!$F$28+Assumptions!$F$29+Assumptions!$F$30+Assumptions!$C$7+Assumptions!$F$32)/((Assumptions!$C$16+Assumptions!$C$17+Assumptions!$C$18+Assumptions!$C$19)+(E$29+E$30)+Assumptions!$E$27+Assumptions!$E$28+Assumptions!$E$29+Assumptions!$E$30+E$24+E$28)) -> 55.404624 | F48: =IF((Assumptions!$C$42-(Assumptions!$F$27+Assumptions!$F$28+Assumptions!$F$29+Assumptions!$F$30+Assumptions!$F$31+Assumptions!$F$32+Assumptions!$C$7)+Assumptions!$F$27+Assumptions!$F$28+Assumptions!$F$29+Assumptions!$F$30+Assumptions!$C$7+Assumptions!$F$32)>Assumptions!$C$13*((Assumptions!$C$16+Assumptions!$C$17+Assumptions!$C$18+Assumptions!$C$19)+(F$29+F$30)+Assumptions!$E$27+Assumptions!$E$28+Assumptions!$E$29+Assumptions!$E$30+F$24+F$28),((Assumptions!$C$42-(Assumptions!$F$27+Assumptions!$F$28+Assumptions!$F$29+Assumptions!$F$30+Assumptions!$F$31+Assumptions!$F$32+Assumptions!$C$7)+Assumptions!$F$27+Assumptions!$F$28+Assumptions!$F$29+Assumptions!$F$30+Assumptions!$C$7+Assumptions!$F$32)+Assumptions!$C$13*Assumptions!$C$20)/(((Assumptions!$C$16+Assumptions!$C$17+Assumptions!$C$18+Assumptions!$C$19)+(F$29+F$30)+Assumptions!$E$27+Assumptions!$E$28+Assumptions!$E$29+Assumptions!$E$30+F$24+F$28)+Assumptions!$C$20),(Assumptions!$C$42-(Assumptions!$F$27+Assumptions!$F$28+Assumptions!$F$29+Assumptions!$F$30+Assumptions!$F$31+Assumptions!$F$32+Assumptions!$C$7)+Assumptions!$F$27+Assumptions!$F$28+Assumptions!$F$29+Assumptions!$F$30+Assumptions!$C$7+Assumptions!$F$32)/((Assumptions!$C$16+Assumptions!$C$17+Assumptions!$C$18+Assumptions!$C$19)+(F$29+F$30)+Assumptions!$E$27+Assumptions!$E$28+Assumptions!$E$29+Assumptions!$E$30+F$24+F$28)) -> 55.790406 | G48: =IF((Assumptions!$C$42-(Assumptions!$F$27+Assumptions!$F$28+Assumptions!$F$29+Assumptions!$F$30+Assumptions!$F$31+Assumptions!$F$32+Assumptions!$C$7)+Assumptions!$F$27+Assumptions!$F$28+Assumptions!$F$29+Assumptions!$F$30+Assumptions!$C$7+Assumptions!$F$32)>Assumptions!$C$13*((Assumptions!$C$16+Assumptions!$C$17+Assumptions!$C$18+Assumptions!$C$19)+(G$29+G$30)+Assumptions!$E$27+Assumptions!$E$28+Assumptions!$E$29+Assumptions!$E$30+G$24+G$28),((Assumptions!$C$42-(Assumptions!$F$27+Assumptions!$F$28+Assumptions!$F$29+Assumptions!$F$30+Assumptions!$F$31+Assumptions!$F$32+Assumptions!$C$7)+Assumptions!$F$27+Assumptions!$F$28+Assumptions!$F$29+Assumptions!$F$30+Assumptions!$C$7+Assumptions!$F$32)+Assumptions!$C$13*Assumptions!$C$20)/(((Assumptions!$C$16+Assumptions!$C$17+Assumptions!$C$18+Assumptions!$C$19)+(G$29+G$30)+Assumptions!$E$27+Assumptions!$E$28+Assumptions!$E$29+Assumptions!$E$30+G$24+G$28)+Assumptions!$C$20),(Assumptions!$C$42-(Assumptions!$F$27+Assumptions!$F$28+Assumptions!$F$29+Assumptions!$F$30+Assumptions!$F$31+Assumptions!$F$32+Assumptions!$C$7)+Assumptions!$F$27+Assumptions!$F$28+Assumptions!$F$29+Assumptions!$F$30+Assumptions!$C$7+Assumptions!$F$32)/((Assumptions!$C$16+Assumptions!$C$17+Assumptions!$C$18+Assumptions!$C$19)+(G$29+G$30)+Assumptions!$E$27+Assumptions!$E$28+Assumptions!$E$29+Assumptions!$E$30+G$24+G$28)) -> 55.758771 | H48: =IF((Assumptions!$C$42-(Assumptions!$F$27+Assumptions!$F$28+Assumptions!$F$29+Assumptions!$F$30+Assumptions!$F$31+Assumptions!$F$32+Assumptions!$C$7)+Assumptions!$F$27+Assumptions!$F$28+Assumptions!$F$29+Assumptions!$F$30+Assumptions!$C$7+Assumptions!$F$32)>Assumptions!$C$13*((Assumptions!$C$16+Assumptions!$C$17+Assumptions!$C$18+Assumptions!$C$19)+(H$29+H$30)+Assumptions!$E$27+Assumptions!$E$28+Assumptions!$E$29+Assumptions!$E$30+H$24+H$28),((Assumptions!$C$42-(Assumptions!$F$27+Assumptions!$F$28+Assumptions!$F$29+Assumptions!$F$30+Assumptions!$F$31+Assumptions!$F$32+Assumptions!$C$7)+Assumptions!$F$27+Assumptions!$F$28+Assumptions!$F$29+Assumptions!$F$30+Assumptions!$C$7+Assumptions!$F$32)+Assumptions!$C$13*Assumptions!$C$20)/(((Assumptions!$C$16+Assumptions!$C$17+Assumptions!$C$18+Assumptions!$C$19)+(H$29+H$30)+Assumptions!$E$27+Assumptions!$E$28+Assumptions!$E$29+Assumptions!$E$30+H$24+H$28)+Assumptions!$C$20),(Assumptions!$C$42-(Assumptions!$F$27+Assumptions!$F$28+Assumptions!$F$29+Assumptions!$F$30+Assumptions!$F$31+Assumptions!$F$32+Assumptions!$C$7)+Assumptions!$F$27+Assumptions!$F$28+Assumptions!$F$29+Assumptions!$F$30+Assumptions!$C$7+Assumptions!$F$32)/((Assumptions!$C$16+Assumptions!$C$17+Assumptions!$C$18+Assumptions!$C$19)+(H$29+H$30)+Assumptions!$E$27+Assumptions!$E$28+Assumptions!$E$29+Assumptions!$E$30+H$24+H$28)) -> 55.710124 | I48: =IF((Assumptions!$C$42-(Assumptions!$F$27+Assumptions!$F$28+Assumptions!$F$29+Assumptions!$F$30+Assumptions!$F$31+Assumptions!$F$32+Assumptions!$C$7)+Assumptions!$F$27+Assumptions!$F$28+Assumptions!$F$29+Assumptions!$F$30+Assumptions!$C$7+Assumptions!$F$32)>Assumptions!$C$13*((Assumptions!$C$16+Assumptions!$C$17+Assumptions!$C$18+Assumptions!$C$19)+(I$29+I$30)+Assumptions!$E$27+Assumptions!$E$28+Assumptions!$E$29+Assumptions!$E$30+I$24+I$28),((Assumptions!$C$42-(Assumptions!$F$27+Assumptions!$F$28+Assumptions!$F$29+Assumptions!$F$30+Assumptions!$F$31+Assumptions!$F$32+Assumptions!$C$7)+Assumptions!$F$27+Assumptions!$F$28+Assumptions!$F$29+Assumptions!$F$30+Assumptions!$C$7+Assumptions!$F$32)+Assumptions!$C$13*Assumptions!$C$20)/(((Assumptions!$C$16+Assumptions!$C$17+Assumptions!$C$18+Assumptions!$C$19)+(I$29+I$30)+Assumptions!$E$27+Assumptions!$E$28+Assumptions!$E$29+Assumptions!$E$30+I$24+I$28)+Assumptions!$C$20),(Assumptions!$C$42-(Assumptions!$F$27+Assumptions!$F$28+Assumptions!$F$29+Assumptions!$F$30+Assumptions!$F$31+Assumptions!$F$32+Assumptions!$C$7)+Assumptions!$F$27+Assumptions!$F$28+Assumptions!$F$29+Assumptions!$F$30+Assumptions!$C$7+Assumptions!$F$32)/((Assumptions!$C$16+Assumptions!$C$17+Assumptions!$C$18+Assumptions!$C$19)+(I$29+I$30)+Assumptions!$E$27+Assumptions!$E$28+Assumptions!$E$29+Assumptions!$E$30+I$24+I$28)) -> 56.1642 | J48: =IF((Assumptions!$C$42-(Assumptions!$F$27+Assumptions!$F$28+Assumptions!$F$29+Assumptions!$F$30+Assumptions!$F$31+Assumptions!$F$32+Assumptions!$C$7)+Assumptions!$F$27+Assumptions!$F$28+Assumptions!$F$29+Assumptions!$F$30+Assumptions!$C$7+Assumptions!$F$32)>Assumptions!$C$13*((Assumptions!$C$16+Assumptions!$C$17+Assumptions!$C$18+Assumptions!$C$19)+(J$29+J$30)+Assumptions!$E$27+Assumptions!$E$28+Assumptions!$E$29+Assumptions!$E$30+J$24+J$28),((Assumptions!$C$42-(Assumptions!$F$27+Assumptions!$F$28+Assumptions!$F$29+Assumptions!$F$30+Assumptions!$F$31+Assumptions!$F$32+Assumptions!$C$7)+Assumptions!$F$27+Assumptions!$F$28+Assumptions!$F$29+Assumptions!$F$30+Assumptions!$C$7+Assumptions!$F$32)+Assumptions!$C$13*Assumptions!$C$20)/(((Assumptions!$C$16+Assumptions!$C$17+Assumptions!$C$18+Assumptions!$C$19)+(J$29+J$30)+Assumptions!$E$27+Assumptions!$E$28+Assumptions!$E$29+Assumptions!$E$30+J$24+J$28)+Assumptions!$C$20),(Assumptions!$C$42-(Assumptions!$F$27+Assumptions!$F$28+Assumptions!$F$29+Assumptions!$F$30+Assumptions!$F$31+Assumptions!$F$32+Assumptions!$C$7)+Assumptions!$F$27+Assumptions!$F$28+Assumptions!$F$29+Assumptions!$F$30+Assumptions!$C$7+Assumptions!$F$32)/((Assumptions!$C$16+Assumptions!$C$17+Assumptions!$C$18+Assumptions!$C$19)+(J$29+J$30)+Assumptions!$E$27+Assumptions!$E$28+Assumptions!$E$29+Assumptions!$E$30+J$24+J$28)) -> 56.13979 | K48: =IF((Assumptions!$C$42-(Assumptions!$F$27+Assumptions!$F$28+Assumptions!$F$29+Assumptions!$F$30+Assumptions!$F$31+Assumptions!$F$32+Assumptions!$C$7)+Assumptions!$F$27+Assumptions!$F$28+Assumptions!$F$29+Assumptions!$F$30+Assumptions!$C$7+Assumptions!$F$32)>Assumptions!$C$13*((Assumptions!$C$16+Assumptions!$C$17+Assumptions!$C$18+Assumptions!$C$19)+(K$29+K$30)+Assumptions!$E$27+Assumptions!$E$28+Assumptions!$E$29+Assumptions!$E$30+K$24+K$28),((Assumptions!$C$42-(Assumptions!$F$27+Assumptions!$F$28+Assumptions!$F$29+Assumptions!$F$30+Assumptions!$F$31+Assumptions!$F$32+Assumptions!$C$7)+Assumptions!$F$27+Assumptions!$F$28+Assumptions!$F$29+Assumptions!$F$30+Assumptions!$C$7+Assumptions!$F$32)+Assumptions!$C$13*Assumptions!$C$20)/(((Assumptions!$C$16+Assumptions!$C$17+Assumptions!$C$18+Assumptions!$C$19)+(K$29+K$30)+Assumptions!$E$27+Assumptions!$E$28+Assumptions!$E$29+Assumptions!$E$30+K$24+K$28)+Assumptions!$C$20),(Assumptions!$C$42-(Assumptions!$F$27+Assumptions!$F$28+Assumptions!$F$29+Assumptions!$F$30+Assumptions!$F$31+Assumptions!$F$32+Assumptions!$C$7)+Assumptions!$F$27+Assumptions!$F$28+Assumptions!$F$29+Assumptions!$F$30+Assumptions!$C$7+Assumptions!$F$32)/((Assumptions!$C$16+Assumptions!$C$17+Assumptions!$C$18+Assumptions!$C$19)+(K$29+K$30)+Assumptions!$E$27+Assumptions!$E$28+Assumptions!$E$29+Assumptions!$E$30+K$24+K$28)) -> 56.100143
B49: PS_{k=7} candidate | C49: =IF((Assumptions!$C$42-(Assumptions!$F$27+Assumptions!$F$28+Assumptions!$F$29+Assumptions!$F$30+Assumptions!$F$31+Assumptions!$F$32+Assumptions!$C$7)+Assumptions!$F$27+Assumptions!$F$28+Assumptions!$F$29+Assumptions!$F$30+Assumptions!$C$7+Assumptions!$F$32+Assumptions!$F$31)>Assumptions!$C$13*((Assumptions!$C$16+Assumptions!$C$17+Assumptions!$C$18+Assumptions!$C$19)+(C$29+C$30)+Assumptions!$E$27+Assumptions!$E$28+Assumptions!$E$29+Assumptions!$E$30+C$24+C$28+C$27),((Assumptions!$C$42-(Assumptions!$F$27+Assumptions!$F$28+Assumptions!$F$29+Assumptions!$F$30+Assumptions!$F$31+Assumptions!$F$32+Assumptions!$C$7)+Assumptions!$F$27+Assumptions!$F$28+Assumptions!$F$29+Assumptions!$F$30+Assumptions!$C$7+Assumptions!$F$32+Assumptions!$F$31)+Assumptions!$C$13*Assumptions!$C$20)/(((Assumptions!$C$16+Assumptions!$C$17+Assumptions!$C$18+Assumptions!$C$19)+(C$29+C$30)+Assumptions!$E$27+Assumptions!$E$28+Assumptions!$E$29+Assumptions!$E$30+C$24+C$28+C$27)+Assumptions!$C$20),(Assumptions!$C$42-(Assumptions!$F$27+Assumptions!$F$28+Assumptions!$F$29+Assumptions!$F$30+Assumptions!$F$31+Assumptions!$F$32+Assumptions!$C$7)+Assumptions!$F$27+Assumptions!$F$28+Assumptions!$F$29+Assumptions!$F$30+Assumptions!$C$7+Assumptions!$F$32+Assumptions!$F$31)/((Assumptions!$C$16+Assumptions!$C$17+Assumptions!$C$18+Assumptions!$C$19)+(C$29+C$30)+Assumptions!$E$27+Assumptions!$E$28+Assumptions!$E$29+Assumptions!$E$30+C$24+C$28+C$27)) -> 55.594052 | D49: =IF((Assumptions!$C$42-(Assumptions!$F$27+Assumptions!$F$28+Assumptions!$F$29+Assumptions!$F$30+Assumptions!$F$31+Assumptions!$F$32+Assumptions!$C$7)+Assumptions!$F$27+Assumptions!$F$28+Assumptions!$F$29+Assumptions!$F$30+Assumptions!$C$7+Assumptions!$F$32+Assumptions!$F$31)>Assumptions!$C$13*((Assumptions!$C$16+Assumptions!$C$17+Assumptions!$C$18+Assumptions!$C$19)+(D$29+D$30)+Assumptions!$E$27+Assumptions!$E$28+Assumptions!$E$29+Assumptions!$E$30+D$24+D$28+D$27),((Assumptions!$C$42-(Assumptions!$F$27+Assumptions!$F$28+Assumptions!$F$29+Assumptions!$F$30+Assumptions!$F$31+Assumptions!$F$32+Assumptions!$C$7)+Assumptions!$F$27+Assumptions!$F$28+Assumptions!$F$29+Assumptions!$F$30+Assumptions!$C$7+Assumptions!$F$32+Assumptions!$F$31)+Assumptions!$C$13*Assumptions!$C$20)/(((Assumptions!$C$16+Assumptions!$C$17+Assumptions!$C$18+Assumptions!$C$19)+(D$29+D$30)+Assumptions!$E$27+Assumptions!$E$28+Assumptions!$E$29+Assumptions!$E$30+D$24+D$28+D$27)+Assumptions!$C$20),(Assumptions!$C$42-(Assumptions!$F$27+Assumptions!$F$28+Assumptions!$F$29+Assumptions!$F$30+Assumptions!$F$31+Assumptions!$F$32+Assumptions!$C$7)+Assumptions!$F$27+Assumptions!$F$28+Assumptions!$F$29+Assumptions!$F$30+Assumptions!$C$7+Assumptions!$F$32+Assumptions!$F$31)/((Assumptions!$C$16+Assumptions!$C$17+Assumptions!$C$18+Assumptions!$C$19)+(D$29+D$30)+Assumptions!$E$27+Assumptions!$E$28+Assumptions!$E$29+Assumptions!$E$30+D$24+D$28+D$27)) -> 55.556966 | E49: =IF((Assumptions!$C$42-(Assumptions!$F$27+Assumptions!$F$28+Assumptions!$F$29+Assumptions!$F$30+Assumptions!$F$31+Assumptions!$F$32+Assumptions!$C$7)+Assumptions!$F$27+Assumptions!$F$28+Assumptions!$F$29+Assumptions!$F$30+Assumptions!$C$7+Assumptions!$F$32+Assumptions!$F$31)>Assumptions!$C$13*((Assumptions!$C$16+Assumptions!$C$17+Assumptions!$C$18+Assumptions!$C$19)+(E$29+E$30)+Assumptions!$E$27+Assumptions!$E$28+Assumptions!$E$29+Assumptions!$E$30+E$24+E$28+E$27),((Assumptions!$C$42-(Assumptions!$F$27+Assumptions!$F$28+Assumptions!$F$29+Assumptions!$F$30+Assumptions!$F$31+Assumptions!$F$32+Assumptions!$C$7)+Assumptions!$F$27+Assumptions!$F$28+Assumptions!$F$29+Assumptions!$F$30+Assumptions!$C$7+Assumptions!$F$32+Assumptions!$F$31)+Assumptions!$C$13*Assumptions!$C$20)/(((Assumptions!$C$16+Assumptions!$C$17+Assumptions!$C$18+Assumptions!$C$19)+(E$29+E$30)+Assumptions!$E$27+Assumptions!$E$28+Assumptions!$E$29+Assumptions!$E$30+E$24+E$28+E$27)+Assumptions!$C$20),(Assumptions!$C$42-(Assumptions!$F$27+Assumptions!$F$28+Assumptions!$F$29+Assumptions!$F$30+Assumptions!$F$31+Assumptions!$F$32+Assumptions!$C$7)+Assumptions!$F$27+Assumptions!$F$28+Assumptions!$F$29+Assumptions!$F$30+Assumptions!$C$7+Assumptions!$F$32+Assumptions!$F$31)/((Assumptions!$C$16+Assumptions!$C$17+Assumptions!$C$18+Assumptions!$C$19)+(E$29+E$30)+Assumptions!$E$27+Assumptions!$E$28+Assumptions!$E$29+Assumptions!$E$30+E$24+E$28+E$27)) -> 55.502209 | F49: =IF((Assumptions!$C$42-(Assumptions!$F$27+Assumptions!$F$28+Assumptions!$F$29+Assumptions!$F$30+Assumptions!$F$31+Assumptions!$F$32+Assumptions!$C$7)+Assumptions!$F$27+Assumptions!$F$28+Assumptions!$F$29+Assumptions!$F$30+Assumptions!$C$7+Assumptions!$F$32+Assumptions!$F$31)>Assumptions!$C$13*((Assumptions!$C$16+Assumptions!$C$17+Assumptions!$C$18+Assumptions!$C$19)+(F$29+F$30)+Assumptions!$E$27+Assumptions!$E$28+Assumptions!$E$29+Assumptions!$E$30+F$24+F$28+F$27),((Assumptions!$C$42-(Assumptions!$F$27+Assumptions!$F$28+Assumptions!$F$29+Assumptions!$F$30+Assumptions!$F$31+Assumptions!$F$32+Assumptions!$C$7)+Assumptions!$F$27+Assumptions!$F$28+Assumptions!$F$29+Assumptions!$F$30+Assumptions!$C$7+Assumptions!$F$32+Assumptions!$F$31)+Assumptions!$C$13*Assumptions!$C$20)/(((Assumptions!$C$16+Assumptions!$C$17+Assumptions!$C$18+Assumptions!$C$19)+(F$29+F$30)+Assumptions!$E$27+Assumptions!$E$28+Assumptions!$E$29+Assumptions!$E$30+F$24+F$28+F$27)+Assumptions!$C$20),(Assumptions!$C$42-(Assumptions!$F$27+Assumptions!$F$28+Assumptions!$F$29+Assumptions!$F$30+Assumptions!$F$31+Assumptions!$F$32+Assumptions!$C$7)+Assumptions!$F$27+Assumptions!$F$28+Assumptions!$F$29+Assumptions!$F$30+Assumptions!$C$7+Assumptions!$F$32+Assumptions!$F$31)/((Assumptions!$C$16+Assumptions!$C$17+Assumptions!$C$18+Assumptions!$C$19)+(F$29+F$30)+Assumptions!$E$27+Assumptions!$E$28+Assumptions!$E$29+Assumptions!$E$30+F$24+F$28+F$27)) -> 55.882323 | G49: =IF((Assumptions!$C$42-(Assumptions!$F$27+Assumptions!$F$28+Assumptions!$F$29+Assumptions!$F$30+Assumptions!$F$31+Assumptions!$F$32+Assumptions!$C$7)+Assumptions!$F$27+Assumptions!$F$28+Assumptions!$F$29+Assumptions!$F$30+Assumptions!$C$7+Assumptions!$F$32+Assumptions!$F$31)>Assumptions!$C$13*((Assumptions!$C$16+Assumptions!$C$17+Assumptions!$C$18+Assumptions!$C$19)+(G$29+G$30)+Assumptions!$E$27+Assumptions!$E$28+Assumptions!$E$29+Assumptions!$E$30+G$24+G$28+G$27),((Assumptions!$C$42-(Assumptions!$F$27+Assumptions!$F$28+Assumptions!$F$29+Assumptions!$F$30+Assumptions!$F$31+Assumptions!$F$32+Assumptions!$C$7)+Assumptions!$F$27+Assumptions!$F$28+Assumptions!$F$29+Assumptions!$F$30+Assumptions!$C$7+Assumptions!$F$32+Assumptions!$F$31)+Assumptions!$C$13*Assumptions!$C$20)/(((Assumptions!$C$16+Assumptions!$C$17+Assumptions!$C$18+Assumptions!$C$19)+(G$29+G$30)+Assumptions!$E$27+Assumptions!$E$28+Assumptions!$E$29+Assumptions!$E$30+G$24+G$28+G$27)+Assumptions!$C$20),(Assumptions!$C$42-(Assumptions!$F$27+Assumptions!$F$28+Assumptions!$F$29+Assumptions!$F$30+Assumptions!$F$31+Assumptions!$F$32+Assumptions!$C$7)+Assumptions!$F$27+Assumptions!$F$28+Assumptions!$F$29+Assumptions!$F$30+Assumptions!$C$7+Assumptions!$F$32+Assumptions!$F$31)/((Assumptions!$C$16+Assumptions!$C$17+Assumptions!$C$18+Assumptions!$C$19)+(G$29+G$30)+Assumptions!$E$27+Assumptions!$E$28+Assumptions!$E$29+Assumptions!$E$30+G$24+G$28+G$27)) -> 55.851245 | H49: =IF((Assumptions!$C$42-(Assumptions!$F$27+Assumptions!$F$28+Assumptions!$F$29+Assumptions!$F$30+Assumptions!$F$31+Assumptions!$F$32+Assumptions!$C$7)+Assumptions!$F$27+Assumptions!$F$28+Assumptions!$F$29+Assumptions!$F$30+Assumptions!$C$7+Assumptions!$F$32+Assumptions!$F$31)>Assumptions!$C$13*((Assumptions!$C$16+Assumptions!$C$17+Assumptions!$C$18+Assumptions!$C$19)+(H$29+H$30)+Assumptions!$E$27+Assumptions!$E$28+Assumptions!$E$29+Assumptions!$E$30+H$24+H$28+H$27),((Assumptions!$C$42-(Assumptions!$F$27+Assumptions!$F$28+Assumptions!$F$29+Assumptions!$F$30+Assumptions!$F$31+Assumptions!$F$32+Assumptions!$C$7)+Assumptions!$F$27+Assumptions!$F$28+Assumptions!$F$29+Assumptions!$F$30+Assumptions!$C$7+Assumptions!$F$32+Assumptions!$F$31)+Assumptions!$C$13*Assumptions!$C$20)/(((Assumptions!$C$16+Assumptions!$C$17+Assumptions!$C$18+Assumptions!$C$19)+(H$29+H$30)+Assumptions!$E$27+Assumptions!$E$28+Assumptions!$E$29+Assumptions!$E$30+H$24+H$28+H$27)+Assumptions!$C$20),(Assumptions!$C$42-(Assumptions!$F$27+Assumptions!$F$28+Assumptions!$F$29+Assumptions!$F$30+Assumptions!$F$31+Assumptions!$F$32+Assumptions!$C$7)+Assumptions!$F$27+Assumptions!$F$28+Assumptions!$F$29+Assumptions!$F$30+Assumptions!$C$7+Assumptions!$F$32+Assumptions!$F$31)/((Assumptions!$C$16+Assumptions!$C$17+Assumptions!$C$18+Assumptions!$C$19)+(H$29+H$30)+Assumptions!$E$27+Assumptions!$E$28+Assumptions!$E$29+Assumptions!$E$30+H$24+H$28+H$27)) -> 55.803454 | I49: =IF((Assumptions!$C$42-(Assumptions!$F$27+Assumptions!$F$28+Assumptions!$F$29+Assumptions!$F$30+Assumptions!$F$31+Assumptions!$F$32+Assumptions!$C$7)+Assumptions!$F$27+Assumptions!$F$28+Assumptions!$F$29+Assumptions!$F$30+Assumptions!$C$7+Assumptions!$F$32+Assumptions!$F$31)>Assumptions!$C$13*((Assumptions!$C$16+Assumptions!$C$17+Assumptions!$C$18+Assumptions!$C$19)+(I$29+I$30)+Assumptions!$E$27+Assumptions!$E$28+Assumptions!$E$29+Assumptions!$E$30+I$24+I$28+I$27),((Assumptions!$C$42-(Assumptions!$F$27+Assumptions!$F$28+Assumptions!$F$29+Assumptions!$F$30+Assumptions!$F$31+Assumptions!$F$32+Assumptions!$C$7)+Assumptions!$F$27+Assumptions!$F$28+Assumptions!$F$29+Assumptions!$F$30+Assumptions!$C$7+Assumptions!$F$32+Assumptions!$F$31)+Assumptions!$C$13*Assumptions!$C$20)/(((Assumptions!$C$16+Assumptions!$C$17+Assumptions!$C$18+Assumptions!$C$19)+(I$29+I$30)+Assumptions!$E$27+Assumptions!$E$28+Assumptions!$E$29+Assumptions!$E$30+I$24+I$28+I$27)+Assumptions!$C$20),(Assumptions!$C$42-(Assumptions!$F$27+Assumptions!$F$28+Assumptions!$F$29+Assumptions!$F$30+Assumptions!$F$31+Assumptions!$F$32+Assumptions!$C$7)+Assumptions!$F$27+Assumptions!$F$28+Assumptions!$F$29+Assumptions!$F$30+Assumptions!$C$7+Assumptions!$F$32+Assumptions!$F$31)/((Assumptions!$C$16+Assumptions!$C$17+Assumptions!$C$18+Assumptions!$C$19)+(I$29+I$30)+Assumptions!$E$27+Assumptions!$E$28+Assumptions!$E$29+Assumptions!$E$30+I$24+I$28+I$27)) -> 56.251452 | J49: =IF((Assumptions!$C$42-(Assumptions!$F$27+Assumptions!$F$28+Assumptions!$F$29+Assumptions!$F$30+Assumptions!$F$31+Assumptions!$F$32+Assumptions!$C$7)+Assumptions!$F$27+Assumptions!$F$28+Assumptions!$F$29+Assumptions!$F$30+Assumptions!$C$7+Assumptions!$F$32+Assumptions!$F$31)>Assumptions!$C$13*((Assumptions!$C$16+Assumptions!$C$17+Assumptions!$C$18+Assumptions!$C$19)+(J$29+J$30)+Assumptions!$E$27+Assumptions!$E$28+Assumptions!$E$29+Assumptions!$E$30+J$24+J$28+J$27),((Assumptions!$C$42-(Assumptions!$F$27+Assumptions!$F$28+Assumptions!$F$29+Assumptions!$F$30+Assumptions!$F$31+Assumptions!$F$32+Assumptions!$C$7)+Assumptions!$F$27+Assumptions!$F$28+Assumptions!$F$29+Assumptions!$F$30+Assumptions!$C$7+Assumptions!$F$32+Assumptions!$F$31)+Assumptions!$C$13*Assumptions!$C$20)/(((Assumptions!$C$16+Assumptions!$C$17+Assumptions!$C$18+Assumptions!$C$19)+(J$29+J$30)+Assumptions!$E$27+Assumptions!$E$28+Assumptions!$E$29+Assumptions!$E$30+J$24+J$28+J$27)+Assumptions!$C$20),(Assumptions!$C$42-(Assumptions!$F$27+Assumptions!$F$28+Assumptions!$F$29+Assumptions!$F$30+Assumptions!$F$31+Assumptions!$F$32+Assumptions!$C$7)+Assumptions!$F$27+Assumptions!$F$28+Assumptions!$F$29+Assumptions!$F$30+Assumptions!$C$7+Assumptions!$F$32+Assumptions!$F$31)/((Assumptions!$C$16+Assumptions!$C$17+Assumptions!$C$18+Assumptions!$C$19)+(J$29+J$30)+Assumptions!$E$27+Assumptions!$E$28+Assumptions!$E$29+Assumptions!$E$30+J$24+J$28+J$27)) -> 56.227507 | K49: =IF((Assumptions!$C$42-(Assumptions!$F$27+Assumptions!$F$28+Assumptions!$F$29+Assumptions!$F$30+Assumptions!$F$31+Assumptions!$F$32+Assumptions!$C$7)+Assumptions!$F$27+Assumptions!$F$28+Assumptions!$F$29+Assumptions!$F$30+Assumptions!$C$7+Assumptions!$F$32+Assumptions!$F$31)>Assumptions!$C$13*((Assumptions!$C$16+Assumptions!$C$17+Assumptions!$C$18+Assumptions!$C$19)+(K$29+K$30)+Assumptions!$E$27+Assumptions!$E$28+Assumptions!$E$29+Assumptions!$E$30+K$24+K$28+K$27),((Assumptions!$C$42-(Assumptions!$F$27+Assumptions!$F$28+Assumptions!$F$29+Assumptions!$F$30+Assumptions!$F$31+Assumptions!$F$32+Assumptions!$C$7)+Assumptions!$F$27+Assumptions!$F$28+Assumptions!$F$29+Assumptions!$F$30+Assumptions!$C$7+Assumptions!$F$32+Assumptions!$F$31)+Assumptions!$C$13*Assumptions!$C$20)/(((Assumptions!$C$16+Assumptions!$C$17+Assumptions!$C$18+Assumptions!$C$19)+(K$29+K$30)+Assumptions!$E$27+Assumptions!$E$28+Assumptions!$E$29+Assumptions!$E$30+K$24+K$28+K$27)+Assumptions!$C$20),(Assumptions!$C$42-(Assumptions!$F$27+Assumptions!$F$28+Assumptions!$F$29+Assumptions!$F$30+Assumptions!$F$31+Assumptions!$F$32+Assumptions!$C$7)+Assumptions!$F$27+Assumptions!$F$28+Assumptions!$F$29+Assumptions!$F$30+Assumptions!$C$7+Assumptions!$F$32+Assumptions!$F$31)/((Assumptions!$C$16+Assumptions!$C$17+Assumptions!$C$18+Assumptions!$C$19)+(K$29+K$30)+Assumptions!$E$27+Assumptions!$E$28+Assumptions!$E$29+Assumptions!$E$30+K$24+K$28+K$27)) -> 56.188614
B50: Equilibrium per-share at $2B ($) | C50: =IF(AND(0<=C42,C42<C$34),C42,0)+IF(AND(C$34<=C43,C43<C$35),C43,0)+IF(AND(C$35<=C44,C44<C$36),C44,0)+IF(AND(C$36<=C45,C45<C$37),C45,0)+IF(AND(C$37<=C46,C46<C$38),C46,0)+IF(AND(C$38<=C47,C47<C$39),C47,0)+IF(AND(C$39<=C48,C48<C$40),C48,0)+IF(AND(C$40<=C49,C49<1E18),C49,0) -> 55.498052 | D50: =IF(AND(0<=D42,D42<D$34),D42,0)+IF(AND(D$34<=D43,D43<D$35),D43,0)+IF(AND(D$35<=D44,D44<D$36),D44,0)+IF(AND(D$36<=D45,D45<D$37),D45,0)+IF(AND(D$37<=D46,D46<D$38),D46,0)+IF(AND(D$38<=D47,D47<D$39),D47,0)+IF(AND(D$39<=D48,D48<D$40),D48,0)+IF(AND(D$40<=D49,D49<1E18),D49,0) -> 55.460325 | E50: =IF(AND(0<=E42,E42<E$34),E42,0)+IF(AND(E$34<=E43,E43<E$35),E43,0)+IF(AND(E$35<=E44,E44<E$36),E44,0)+IF(AND(E$36<=E45,E45<E$37),E45,0)+IF(AND(E$37<=E46,E46<E$38),E46,0)+IF(AND(E$38<=E47,E47<E$39),E47,0)+IF(AND(E$39<=E48,E48<E$40),E48,0)+IF(AND(E$40<=E49,E49<1E18),E49,0) -> 55.404624 | F50: =IF(AND(0<=F42,F42<F$34),F42,0)+IF(AND(F$34<=F43,F43<F$35),F43,0)+IF(AND(F$35<=F44,F44<F$36),F44,0)+IF(AND(F$36<=F45,F45<F$37),F45,0)+IF(AND(F$37<=F46,F46<F$38),F46,0)+IF(AND(F$38<=F47,F47<F$39),F47,0)+IF(AND(F$39<=F48,F48<F$40),F48,0)+IF(AND(F$40<=F49,F49<1E18),F49,0) -> 55.790406 | G50: =IF(AND(0<=G42,G42<G$34),G42,0)+IF(AND(G$34<=G43,G43<G$35),G43,0)+IF(AND(G$35<=G44,G44<G$36),G44,0)+IF(AND(G$36<=G45,G45<G$37),G45,0)+IF(AND(G$37<=G46,G46<G$38),G46,0)+IF(AND(G$38<=G47,G47<G$39),G47,0)+IF(AND(G$39<=G48,G48<G$40),G48,0)+IF(AND(G$40<=G49,G49<1E18),G49,0) -> 55.758771 | H50: =IF(AND(0<=H42,H42<H$34),H42,0)+IF(AND(H$34<=H43,H43<H$35),H43,0)+IF(AND(H$35<=H44,H44<H$36),H44,0)+IF(AND(H$36<=H45,H45<H$37),H45,0)+IF(AND(H$37<=H46,H46<H$38),H46,0)+IF(AND(H$38<=H47,H47<H$39),H47,0)+IF(AND(H$39<=H48,H48<H$40),H48,0)+IF(AND(H$40<=H49,H49<1E18),H49,0) -> 55.710124 | I50: =IF(AND(0<=I42,I42<I$34),I42,0)+IF(AND(I$34<=I43,I43<I$35),I43,0)+IF(AND(I$35<=I44,I44<I$36),I44,0)+IF(AND(I$36<=I45,I45<I$37),I45,0)+IF(AND(I$37<=I46,I46<I$38),I46,0)+IF(AND(I$38<=I47,I47<I$39),I47,0)+IF(AND(I$39<=I48,I48<I$40),I48,0)+IF(AND(I$40<=I49,I49<1E18),I49,0) -> 56.1642 | J50: =IF(AND(0<=J42,J42<J$34),J42,0)+IF(AND(J$34<=J43,J43<J$35),J43,0)+IF(AND(J$35<=J44,J44<J$36),J44,0)+IF(AND(J$36<=J45,J45<J$37),J45,0)+IF(AND(J$37<=J46,J46<J$38),J46,0)+IF(AND(J$38<=J47,J47<J$39),J47,0)+IF(AND(J$39<=J48,J48<J$40),J48,0)+IF(AND(J$40<=J49,J49<1E18),J49,0) -> 56.13979 | K50: =IF(AND(0<=K42,K42<K$34),K42,0)+IF(AND(K$34<=K43,K43<K$35),K43,0)+IF(AND(K$35<=K44,K44<K$36),K44,0)+IF(AND(K$36<=K45,K45<K$37),K45,0)+IF(AND(K$37<=K46,K46<K$38),K46,0)+IF(AND(K$38<=K47,K47<K$39),K47,0)+IF(AND(K$39<=K48,K48<K$40),K48,0)+IF(AND(K$40<=K49,K49<1E18),K49,0) -> 56.100143
B52: F election at $2B | C52: =IF(Assumptions!$C$7>C$24*C$50,"preference","convert") -> convert | D52: =IF(Assumptions!$C$7>D$24*D$50,"preference","convert") -> convert | E52: =IF(Assumptions!$C$7>E$24*E$50,"preference","convert") -> convert | F52: =IF(Assumptions!$C$7>F$24*F$50,"preference","convert") -> convert | G52: =IF(Assumptions!$C$7>G$24*G$50,"preference","convert") -> convert | H52: =IF(Assumptions!$C$7>H$24*H$50,"preference","convert") -> convert | I52: =IF(Assumptions!$C$7>I$24*I$50,"preference","convert") -> convert | J52: =IF(Assumptions!$C$7>J$24*J$50,"preference","convert") -> convert | K52: =IF(Assumptions!$C$7>K$24*K$50,"preference","convert") -> convert
B53: Our F primary shares | C53: =Assumptions!$C$11/C$23 -> 308249.65 | D53: =Assumptions!$C$11/D$23 -> 313466.82 | E53: =Assumptions!$C$11/E$23 -> 321182.64 | F53: =Assumptions!$C$11/F$23 -> 263838.44 | G53: =Assumptions!$C$11/G$23 -> 268098.78 | H53: =Assumptions!$C$11/H$23 -> 274659.61 | I53: =Assumptions!$C$11/I$23 -> 204883.87 | J53: =Assumptions!$C$11/J$23 -> 207990.96 | K53: =Assumptions!$C$11/K$23 -> 213043.35
B54: Our post-F ownership % | C54: =C$53/C$25 -> 0.0081300813 | D54: =D$53/D$25 -> 0.0081300813 | E54: =E$53/E$25 -> 0.0081300813 | F54: =F$53/F$25 -> 0.006993007 | G54: =G$53/G$25 -> 0.006993007 | H54: =H$53/H$25 -> 0.006993007 | I54: =I$53/I$25 -> 0.0054644809 | J54: =J$53/J$25 -> 0.0054644809 | K54: =K$53/K$25 -> 0.0054644809
B55: Our proceeds at $2B exit ($) | C55: =IF(C$52="preference",Assumptions!$C$11,C$53*C$50) -> 17107255 | D55: =IF(D$52="preference",Assumptions!$C$11,D$53*D$50) -> 17384972 | E55: =IF(E$52="preference",Assumptions!$C$11,E$53*E$50) -> 17795003 | F55: =IF(F$52="preference",Assumptions!$C$11,F$53*F$50) -> 14719654 | G55: =IF(G$52="preference",Assumptions!$C$11,G$53*G$50) -> 14948858 | H55: =IF(H$52="preference",Assumptions!$C$11,H$53*H$50) -> 15301321 | I55: =IF(I$52="preference",Assumptions!$C$11,I$53*I$50) -> 11507138 | J55: =IF(J$52="preference",Assumptions!$C$11,J$53*J$50) -> 11676569 | K55: =IF(K$52="preference",Assumptions!$C$11,K$53*K$50) -> 11951762
B58: Sensitivity Grid — Our Post-F Ownership %
B59: ESOP \ Pre-money | C59: =Assumptions!C50 -> 1200000000 | D59: =Assumptions!C51 -> 1400000000 | E59: =Assumptions!C52 -> 1800000000
B60: =Assumptions!C47 -> 0.11 | C60: =C54 -> 0.0081300813 | D60: =F54 -> 0.006993007 | E60: =I54 -> 0.0054644809
B61: =Assumptions!C48 -> 0.13 | C61: =D54 -> 0.0081300813 | D61: =G54 -> 0.006993007 | E61: =J54 -> 0.0054644809
B62: =Assumptions!C49 -> 0.15 | C62: =E54 -> 0.0081300813 | D62: =H54 -> 0.006993007 | E62: =K54 -> 0.0054644809
B64: Sensitivity Grid — Our Proceeds at $2B Exit
B65: ESOP \ Pre-money | C65: =Assumptions!C50 -> 1200000000 | D65: =Assumptions!C51 -> 1400000000 | E65: =Assumptions!C52 -> 1800000000
B66: =Assumptions!C47 -> 0.11 | C66: =C55 -> 17107255 | D66: =F55 -> 14719654 | E66: =I55 -> 11507138
B67: =Assumptions!C48 -> 0.13 | C67: =D55 -> 17384972 | D67: =G55 -> 14948858 | E67: =J55 -> 11676569
B68: =Assumptions!C49 -> 0.15 | C68: =E55 -> 17795003 | D68: =H55 -> 15301321 | E68: =K55 -> 11951762
B70: Note: yellow cell = base case ($1.4B pre, 13% ESOP). Form 2 (pool stays at pre-F) used when target × T < pre-F pool.
B71: At pre=$1.2B, Note A's branch flips from cap to discount (cap+prin > pre·(1−disc)).

Sheet Waterfall
B2: Kelvin Dynamics — Exit Waterfall
B3: 1× non-participating with conversion election; 5 exit scenarios; 7 priced classes
B5: Inputs (from Pro-Forma)
C6: Liquidation Pref ($) | D6: As-Converted Shares | E6: ψ = Pref / Shares
B7: Series Seed | C7: =Assumptions!F27 -> 5000000 | D7: ='Pro-Forma'!H30 -> 5000000 | E7: =C7/D7 -> 1
B8: Series A | C8: =Assumptions!F28 -> 15000000 | D8: ='Pro-Forma'!H31 -> 5000000 | E8: =C8/D8 -> 3
B9: Series B | C9: =Assumptions!F29 -> 30000000 | D9: ='Pro-Forma'!H32 -> 3000000 | E9: =C9/D9 -> 10
B10: Series C | C10: =Assumptions!F30 -> 60000000 | D10: ='Pro-Forma'!H33 -> 2400000 | E10: =C10/D10 -> 25
B11: Series D | C11: =Assumptions!F31 -> 100000000 | D11: ='Pro-Forma'!H34 -> 1733976.7 | E11: =C11/D11 -> 57.670903
B12: Series E | C12: =Assumptions!F32 -> 300000000 | D12: ='Pro-Forma'!H35 -> 6134537.8 | E12: =C12/D12 -> 48.90344
B13: Series F | C13: =Assumptions!C7 -> 30000000 | D13: ='Pro-Forma'!C22 -> 804296.34 | E13: =C13/D13 -> 37.299685
B14: Common + RSAs (founders + employees, post-tender total unchanged) | D14: =Assumptions!C16+Assumptions!C17+Assumptions!C18+Assumptions!C19 -> 9000000
B15: Notes (Note A + Note B converted, common-equivalent) | D15: ='Pro-Forma'!H39+'Pro-Forma'!H40 -> 281358.57
B16: Issued options | D16: =Assumptions!C20 -> 2500000
B17: Option strike ($) | D17: =Assumptions!C13 -> 1
B18: Total preferred prefs (all 7) | C18: =SUM(C7:C13) -> 540000000
B20: Exit Scenarios
B21: Exit value ($) | I21: =Assumptions!C40 -> 700000000 | J21: =Assumptions!C41 -> 1200000000 | K21: =Assumptions!C42 -> 2000000000 | L21: =Assumptions!C43 -> 4000000000 | M21: =Assumptions!C44 -> 8000000000
B23: Per-Share Equilibrium (k = # of converting classes, sorted by ψ asc)
B24: k (# converting) | C24: ψ_k | D24: Cum Conv Shares | E24: Cum Conv Prefs ($) | F24: ψ_{k+1} | I24: PS_k Exit 1 | J24: PS_k Exit 2 | K24: PS_k Exit 3 | L24: PS_k Exit 4 | M24: PS_k Exit 5
B25: k=0 (no converters) | C25: 0 | D25: 0 | E25: 0 | F25: =E7 -> 1 | I25: =IF((I$21-$C$18+$E25)>$D$17*($D$14+$D$15+$D25),((I$21-$C$18+$E25)+$D$17*$D$16)/($D$14+$D$15+$D25+$D$16),(I$21-$C$18+$E25)/($D$14+$D$15+$D25)) -> 13.792976 | J25: =IF((J$21-$C$18+$E25)>$D$17*($D$14+$D$15+$D25),((J$21-$C$18+$E25)+$D$17*$D$16)/($D$14+$D$15+$D25+$D$16),(J$21-$C$18+$E25)/($D$14+$D$15+$D25)) -> 56.232904 | K25: =IF((K$21-$C$18+$E25)>$D$17*($D$14+$D$15+$D25),((K$21-$C$18+$E25)+$D$17*$D$16)/($D$14+$D$15+$D25+$D$16),(K$21-$C$18+$E25)/($D$14+$D$15+$D25)) -> 124.13679 | L25: =IF((L$21-$C$18+$E25)>$D$17*($D$14+$D$15+$D25),((L$21-$C$18+$E25)+$D$17*$D$16)/($D$14+$D$15+$D25+$D$16),(L$21-$C$18+$E25)/($D$14+$D$15+$D25)) -> 293.8965 | M25: =IF((M$21-$C$18+$E25)>$D$17*($D$14+$D$15+$D25),((M$21-$C$18+$E25)+$D$17*$D$16)/($D$14+$D$15+$D25+$D$16),(M$21-$C$18+$E25)/($D$14+$D$15+$D25)) -> 633.41591
B26: k=1 (1 converter) | C26: =E7 -> 1 | D26: =D25+D7 -> 5000000 | E26: =C7 -> 5000000 | F26: =E8 -> 3 | I26: =IF((I$21-$C$18+$E26)>$D$17*($D$14+$D$15+$D26),((I$21-$C$18+$E26)+$D$17*$D$16)/($D$14+$D$15+$D26+$D$16),(I$21-$C$18+$E26)/($D$14+$D$15+$D26)) -> 9.9813135 | J26: =IF((J$21-$C$18+$E26)>$D$17*($D$14+$D$15+$D26),((J$21-$C$18+$E26)+$D$17*$D$16)/($D$14+$D$15+$D26+$D$16),(J$21-$C$18+$E26)/($D$14+$D$15+$D26)) -> 39.776279 | K26: =IF((K$21-$C$18+$E26)>$D$17*($D$14+$D$15+$D26),((K$21-$C$18+$E26)+$D$17*$D$16)/($D$14+$D$15+$D26+$D$16),(K$21-$C$18+$E26)/($D$14+$D$15+$D26)) -> 87.448224 | L26: =IF((L$21-$C$18+$E26)>$D$17*($D$14+$D$15+$D26),((L$21-$C$18+$E26)+$D$17*$D$16)/($D$14+$D$15+$D26+$D$16),(L$21-$C$18+$E26)/($D$14+$D$15+$D26)) -> 206.62809 | M26: =IF((M$21-$C$18+$E26)>$D$17*($D$14+$D$15+$D26),((M$21-$C$18+$E26)+$D$17*$D$16)/($D$14+$D$15+$D26+$D$16),(M$21-$C$18+$E26)/($D$14+$D$15+$D26)) -> 444.98781
B27: k=2 (2 converters) | C27: =E8 -> 3 | D27: =D26+D8 -> 10000000 | E27: =C7+C8 -> 20000000 | F27: =E9 -> 10 | I27: =IF((I$21-$C$18+$E27)>$D$17*($D$14+$D$15+$D27),((I$21-$C$18+$E27)+$D$17*$D$16)/($D$14+$D$15+$D27+$D$16),(I$21-$C$18+$E27)/($D$14+$D$15+$D27)) -> 8.3787244 | J27: =IF((J$21-$C$18+$E27)>$D$17*($D$14+$D$15+$D27),((J$21-$C$18+$E27)+$D$17*$D$16)/($D$14+$D$15+$D27+$D$16),(J$21-$C$18+$E27)/($D$14+$D$15+$D27)) -> 31.334134 | K27: =IF((K$21-$C$18+$E27)>$D$17*($D$14+$D$15+$D27),((K$21-$C$18+$E27)+$D$17*$D$16)/($D$14+$D$15+$D27+$D$16),(K$21-$C$18+$E27)/($D$14+$D$15+$D27)) -> 68.062788 | L27: =IF((L$21-$C$18+$E27)>$D$17*($D$14+$D$15+$D27),((L$21-$C$18+$E27)+$D$17*$D$16)/($D$14+$D$15+$D27+$D$16),(L$21-$C$18+$E27)/($D$14+$D$15+$D27)) -> 159.88443 | M27: =IF((M$21-$C$18+$E27)>$D$17*($D$14+$D$15+$D27),((M$21-$C$18+$E27)+$D$17*$D$16)/($D$14+$D$15+$D27+$D$16),(M$21-$C$18+$E27)/($D$14+$D$15+$D27)) -> 343.5277
B28: k=3 (3 converters) | C28: =E9 -> 10 | D28: =D27+D9 -> 13000000 | E28: =C7+C8+C9 -> 50000000 | F28: =E10 -> 25 | I28: =IF((I$21-$C$18+$E28)>$D$17*($D$14+$D$15+$D28),((I$21-$C$18+$E28)+$D$17*$D$16)/($D$14+$D$15+$D28+$D$16),(I$21-$C$18+$E28)/($D$14+$D$15+$D28)) -> 8.574994 | J28: =IF((J$21-$C$18+$E28)>$D$17*($D$14+$D$15+$D28),((J$21-$C$18+$E28)+$D$17*$D$16)/($D$14+$D$15+$D28+$D$16),(J$21-$C$18+$E28)/($D$14+$D$15+$D28)) -> 28.75145 | K28: =IF((K$21-$C$18+$E28)>$D$17*($D$14+$D$15+$D28),((K$21-$C$18+$E28)+$D$17*$D$16)/($D$14+$D$15+$D28+$D$16),(K$21-$C$18+$E28)/($D$14+$D$15+$D28)) -> 61.033781 | L28: =IF((L$21-$C$18+$E28)>$D$17*($D$14+$D$15+$D28),((L$21-$C$18+$E28)+$D$17*$D$16)/($D$14+$D$15+$D28+$D$16),(L$21-$C$18+$E28)/($D$14+$D$15+$D28)) -> 141.73961 | M28: =IF((M$21-$C$18+$E28)>$D$17*($D$14+$D$15+$D28),((M$21-$C$18+$E28)+$D$17*$D$16)/($D$14+$D$15+$D28+$D$16),(M$21-$C$18+$E28)/($D$14+$D$15+$D28)) -> 303.15126
B29: k=4 (4 converters) | C29: =E10 -> 25 | D29: =D28+D10 -> 15400000 | E29: =C7+C8+C9+C10 -> 110000000 | F29: =E13 -> 37.299685 | I29: =IF((I$21-$C$18+$E29)>$D$17*($D$14+$D$15+$D29),((I$21-$C$18+$E29)+$D$17*$D$16)/($D$14+$D$15+$D29+$D$16),(I$21-$C$18+$E29)/($D$14+$D$15+$D29)) -> 10.025253 | J29: =IF((J$21-$C$18+$E29)>$D$17*($D$14+$D$15+$D29),((J$21-$C$18+$E29)+$D$17*$D$16)/($D$14+$D$15+$D29+$D$16),(J$21-$C$18+$E29)/($D$14+$D$15+$D29)) -> 28.420213 | K29: =IF((K$21-$C$18+$E29)>$D$17*($D$14+$D$15+$D29),((K$21-$C$18+$E29)+$D$17*$D$16)/($D$14+$D$15+$D29+$D$16),(K$21-$C$18+$E29)/($D$14+$D$15+$D29)) -> 57.852149 | L29: =IF((L$21-$C$18+$E29)>$D$17*($D$14+$D$15+$D29),((L$21-$C$18+$E29)+$D$17*$D$16)/($D$14+$D$15+$D29+$D$16),(L$21-$C$18+$E29)/($D$14+$D$15+$D29)) -> 131.43199 | M29: =IF((M$21-$C$18+$E29)>$D$17*($D$14+$D$15+$D29),((M$21-$C$18+$E29)+$D$17*$D$16)/($D$14+$D$15+$D29+$D$16),(M$21-$C$18+$E29)/($D$14+$D$15+$D29)) -> 278.59167
B30: k=5 (5 converters) | C30: =E13 -> 37.299685 | D30: =D29+D13 -> 16204296 | E30: =C7+C8+C9+C10+C13 -> 140000000 | F30: =E12 -> 48.90344 | I30: =IF((I$21-$C$18+$E30)>$D$17*($D$14+$D$15+$D30),((I$21-$C$18+$E30)+$D$17*$D$16)/($D$14+$D$15+$D30+$D$16),(I$21-$C$18+$E30)/($D$14+$D$15+$D30)) -> 10.809109 | J30: =IF((J$21-$C$18+$E30)>$D$17*($D$14+$D$15+$D30),((J$21-$C$18+$E30)+$D$17*$D$16)/($D$14+$D$15+$D30+$D$16),(J$21-$C$18+$E30)/($D$14+$D$15+$D30)) -> 28.675405 | K30: =IF((K$21-$C$18+$E30)>$D$17*($D$14+$D$15+$D30),((K$21-$C$18+$E30)+$D$17*$D$16)/($D$14+$D$15+$D30+$D$16),(K$21-$C$18+$E30)/($D$14+$D$15+$D30)) -> 57.261479 | L30: =IF((L$21-$C$18+$E30)>$D$17*($D$14+$D$15+$D30),((L$21-$C$18+$E30)+$D$17*$D$16)/($D$14+$D$15+$D30+$D$16),(L$21-$C$18+$E30)/($D$14+$D$15+$D30)) -> 128.72666 | M30: =IF((M$21-$C$18+$E30)>$D$17*($D$14+$D$15+$D30),((M$21-$C$18+$E30)+$D$17*$D$16)/($D$14+$D$15+$D30+$D$16),(M$21-$C$18+$E30)/($D$14+$D$15+$D30)) -> 271.65703
B31: k=6 (6 converters) | C31: =E12 -> 48.90344 | D31: =D30+D12 -> 22338834 | E31: =C7+C8+C9+C10+C13+C12 -> 440000000 | F31: =E11 -> 57.670903 | I31: =IF((I$21-$C$18+$E31)>$D$17*($D$14+$D$15+$D31),((I$21-$C$18+$E31)+$D$17*$D$16)/($D$14+$D$15+$D31+$D$16),(I$21-$C$18+$E31)/($D$14+$D$15+$D31)) -> 17.658165 | J31: =IF((J$21-$C$18+$E31)>$D$17*($D$14+$D$15+$D31),((J$21-$C$18+$E31)+$D$17*$D$16)/($D$14+$D$15+$D31+$D$16),(J$21-$C$18+$E31)/($D$14+$D$15+$D31)) -> 32.312244 | K31: =IF((K$21-$C$18+$E31)>$D$17*($D$14+$D$15+$D31),((K$21-$C$18+$E31)+$D$17*$D$16)/($D$14+$D$15+$D31+$D$16),(K$21-$C$18+$E31)/($D$14+$D$15+$D31)) -> 55.758771 | L31: =IF((L$21-$C$18+$E31)>$D$17*($D$14+$D$15+$D31),((L$21-$C$18+$E31)+$D$17*$D$16)/($D$14+$D$15+$D31+$D$16),(L$21-$C$18+$E31)/($D$14+$D$15+$D31)) -> 114.37509 | M31: =IF((M$21-$C$18+$E31)>$D$17*($D$14+$D$15+$D31),((M$21-$C$18+$E31)+$D$17*$D$16)/($D$14+$D$15+$D31+$D$16),(M$21-$C$18+$E31)/($D$14+$D$15+$D31)) -> 231.60772
B32: k=7 (all converters) | C32: =E11 -> 57.670903 | D32: =D7+D8+D9+D10+D13+D12+D11 -> 24072811 | E32: =C7+C8+C9+C10+C13+C12+C11 -> 540000000 | F32: 1e+18 | I32: =IF((I$21-$C$18+$E32)>$D$17*($D$14+$D$15+$D32),((I$21-$C$18+$E32)+$D$17*$D$16)/($D$14+$D$15+$D32+$D$16),(I$21-$C$18+$E32)/($D$14+$D$15+$D32)) -> 19.593258 | J32: =IF((J$21-$C$18+$E32)>$D$17*($D$14+$D$15+$D32),((J$21-$C$18+$E32)+$D$17*$D$16)/($D$14+$D$15+$D32+$D$16),(J$21-$C$18+$E32)/($D$14+$D$15+$D32)) -> 33.538638 | K32: =IF((K$21-$C$18+$E32)>$D$17*($D$14+$D$15+$D32),((K$21-$C$18+$E32)+$D$17*$D$16)/($D$14+$D$15+$D32+$D$16),(K$21-$C$18+$E32)/($D$14+$D$15+$D32)) -> 55.851245 | L32: =IF((L$21-$C$18+$E32)>$D$17*($D$14+$D$15+$D32),((L$21-$C$18+$E32)+$D$17*$D$16)/($D$14+$D$15+$D32+$D$16),(L$21-$C$18+$E32)/($D$14+$D$15+$D32)) -> 111.63276 | M32: =IF((M$21-$C$18+$E32)>$D$17*($D$14+$D$15+$D32),((M$21-$C$18+$E32)+$D$17*$D$16)/($D$14+$D$15+$D32+$D$16),(M$21-$C$18+$E32)/($D$14+$D$15+$D32)) -> 223.1958
B33: Equilibrium per-share ($) | I33: =SUMPRODUCT(($C$25:$C$32<=I$25:I$32)*(I$25:I$32<$F$25:$F$32)*I$25:I$32) -> 8.3787244 | J33: =SUMPRODUCT(($C$25:$C$32<=J$25:J$32)*(J$25:J$32<$F$25:$F$32)*J$25:J$32) -> 28.420213 | K33: =SUMPRODUCT(($C$25:$C$32<=K$25:K$32)*(K$25:K$32<$F$25:$F$32)*K$25:K$32) -> 55.758771 | L33: =SUMPRODUCT(($C$25:$C$32<=L$25:L$32)*(L$25:L$32<$F$25:$F$32)*L$25:L$32) -> 111.63276 | M33: =SUMPRODUCT(($C$25:$C$32<=M$25:M$32)*(M$25:M$32<$F$25:$F$32)*M$25:M$32) -> 223.1958
B34: Options ITM at equilibrium? | I34: =IF(I$33>$D$17,"YES","no") -> YES | J34: =IF(J$33>$D$17,"YES","no") -> YES | K34: =IF(K$33>$D$17,"YES","no") -> YES | L34: =IF(L$33>$D$17,"YES","no") -> YES | M34: =IF(M$33>$D$17,"YES","no") -> YES
B36: Class Elections (preference vs convert, given Nash equilibrium)
B37: Series F — election | I37: =IF(C13>D13*I$33,"preference","convert") -> preference | J37: =IF(C13>D13*J$33,"preference","convert") -> preference | K37: =IF(C13>D13*K$33,"preference","convert") -> convert | L37: =IF(C13>D13*L$33,"preference","convert") -> convert | M37: =IF(C13>D13*M$33,"preference","convert") -> convert
B38: Series E — election | I38: =IF(C12>D12*I$33,"preference","convert") -> preference | J38: =IF(C12>D12*J$33,"preference","convert") -> preference | K38: =IF(C12>D12*K$33,"preference","convert") -> convert | L38: =IF(C12>D12*L$33,"preference","convert") -> convert | M38: =IF(C12>D12*M$33,"preference","convert") -> convert
B39: Series D — election | I39: =IF(C11>D11*I$33,"preference","convert") -> preference | J39: =IF(C11>D11*J$33,"preference","convert") -> preference | K39: =IF(C11>D11*K$33,"preference","convert") -> preference | L39: =IF(C11>D11*L$33,"preference","convert") -> convert | M39: =IF(C11>D11*M$33,"preference","convert") -> convert
B40: Series C — election | I40: =IF(C10>D10*I$33,"preference","convert") -> preference | J40: =IF(C10>D10*J$33,"preference","convert") -> convert | K40: =IF(C10>D10*K$33,"preference","convert") -> convert | L40: =IF(C10>D10*L$33,"preference","convert") -> convert | M40: =IF(C10>D10*M$33,"preference","convert") -> convert
B41: Series B — election | I41: =IF(C9>D9*I$33,"preference","convert") -> preference | J41: =IF(C9>D9*J$33,"preference","convert") -> convert | K41: =IF(C9>D9*K$33,"preference","convert") -> convert | L41: =IF(C9>D9*L$33,"preference","convert") -> convert | M41: =IF(C9>D9*M$33,"preference","convert") -> convert
B42: Series A — election | I42: =IF(C8>D8*I$33,"preference","convert") -> convert | J42: =IF(C8>D8*J$33,"preference","convert") -> convert | K42: =IF(C8>D8*K$33,"preference","convert") -> convert | L42: =IF(C8>D8*L$33,"preference","convert") -> convert | M42: =IF(C8>D8*M$33,"preference","convert") -> convert
B43: Series Seed — election | I43: =IF(C7>D7*I$33,"preference","convert") -> convert | J43: =IF(C7>D7*J$33,"preference","convert") -> convert | K43: =IF(C7>D7*K$33,"preference","convert") -> convert | L43: =IF(C7>D7*L$33,"preference","convert") -> convert | M43: =IF(C7>D7*M$33,"preference","convert") -> convert
B45: Proceeds by Class ($)
B46: Series F | I46: =IF(I37="preference",C13,D13*I$33) -> 30000000 | J46: =IF(J37="preference",C13,D13*J$33) -> 30000000 | K46: =IF(K37="preference",C13,D13*K$33) -> 44846575 | L46: =IF(L37="preference",C13,D13*L$33) -> 89785823 | M46: =IF(M37="preference",C13,D13*M$33) -> 1.7951557e+08
B47: Series E | I47: =IF(I38="preference",C12,D12*I$33) -> 300000000 | J47: =IF(J38="preference",C12,D12*J$33) -> 300000000 | K47: =IF(K38="preference",C12,D12*K$33) -> 3.4205429e+08 | L47: =IF(L38="preference",C12,D12*L$33) -> 6.848154e+08 | M47: =IF(M38="preference",C12,D12*M$33) -> 1.3692031e+09
B48: Series D | I48: =IF(I39="preference",C11,D11*I$33) -> 100000000 | J48: =IF(J39="preference",C11,D11*J$33) -> 100000000 | K48: =IF(K39="preference",C11,D11*K$33) -> 100000000 | L48: =IF(L39="preference",C11,D11*L$33) -> 1.9356861e+08 | M48: =IF(M39="preference",C11,D11*M$33) -> 3.8701631e+08
B49: Series C | I49: =IF(I40="preference",C10,D10*I$33) -> 60000000 | J49: =IF(J40="preference",C10,D10*J$33) -> 68208511 | K49: =IF(K40="preference",C10,D10*K$33) -> 1.3382105e+08 | L49: =IF(L40="preference",C10,D10*L$33) -> 2.6791863e+08 | M49: =IF(M40="preference",C10,D10*M$33) -> 5.3566992e+08
B50: Series B | I50: =IF(I41="preference",C9,D9*I$33) -> 30000000 | J50: =IF(J41="preference",C9,D9*J$33) -> 85260639 | K50: =IF(K41="preference",C9,D9*K$33) -> 1.6727631e+08 | L50: =IF(L41="preference",C9,D9*L$33) -> 3.3489829e+08 | M50: =IF(M41="preference",C9,D9*M$33) -> 6.695874e+08
B51: Series A | I51: =IF(I42="preference",C8,D8*I$33) -> 41893622 | J51: =IF(J42="preference",C8,D8*J$33) -> 1.4210106e+08 | K51: =IF(K42="preference",C8,D8*K$33) -> 2.7879385e+08 | L51: =IF(L42="preference",C8,D8*L$33) -> 5.5816382e+08 | M51: =IF(M42="preference",C8,D8*M$33) -> 1.115979e+09
B52: Series Seed | I52: =IF(I43="preference",C7,D7*I$33) -> 41893622 | J52: =IF(J43="preference",C7,D7*J$33) -> 1.4210106e+08 | K52: =IF(K43="preference",C7,D7*K$33) -> 2.7879385e+08 | L52: =IF(L43="preference",C7,D7*L$33) -> 5.5816382e+08 | M52: =IF(M43="preference",C7,D7*M$33) -> 1.115979e+09
B53: Notes (Note A + Note B, common-equiv) | I53: =$D$15*I$33 -> 2357425.9 | J53: =$D$15*J$33 -> 7996270.5 | K53: =$D$15*K$33 -> 15688208 | L53: =$D$15*L$33 -> 31408834 | M53: =$D$15*M$33 -> 62798051
B54: Common + RSAs | I54: =$D$14*I$33 -> 75408519 | J54: =$D$14*J$33 -> 2.5578192e+08 | K54: =$D$14*K$33 -> 5.0182894e+08 | L54: =$D$14*L$33 -> 1.0046949e+09 | M54: =$D$14*M$33 -> 2.0087622e+09
B55: Issued options (net of strike if ITM) | I55: =IF(I$33>$D$17,$D$16*(I$33-$D$17),0) -> 18446811 | J55: =IF(J$33>$D$17,$D$16*(J$33-$D$17),0) -> 68550532 | K55: =IF(K$33>$D$17,$D$16*(K$33-$D$17),0) -> 1.3689693e+08 | L55: =IF(L$33>$D$17,$D$16*(L$33-$D$17),0) -> 2.7658191e+08 | M55: =IF(M$33>$D$17,$D$16*(M$33-$D$17),0) -> 5.554895e+08
B56: TOTAL proceeds | I56: =SUM(I46:I55) -> 700000000 | J56: =SUM(J46:J55) -> 1200000000 | K56: =SUM(K46:K55) -> 2e+09 | L56: =SUM(L46:L55) -> 4e+09 | M56: =SUM(M46:M55) -> 8e+09
B57: Reconciliation diff vs exit ($) | I57: =ROUND(I56-I$21,2) -> 0 | J57: =ROUND(J56-J$21,2) -> 0 | K57: =ROUND(K56-K$21,2) -> 0 | L57: =ROUND(L56-L$21,2) -> 0 | M57: =ROUND(M56-M$21,2) -> 0
B58: Check | I58: =ROUND(I56-I$21,2) -> 0 | J58: =ROUND(J56-J$21,2) -> 0 | K58: =ROUND(K56-K$21,2) -> 0 | L58: =ROUND(L56-L$21,2) -> 0 | M58: =ROUND(M56-M$21,2) -> 0
