Workbook

Sheet Assumptions
B2: Assumptions
B3: Kelvin Dynamics — Series F Round Inputs
B5: Round Terms
B6: Series F pre-money valuation | C6: 1400000000 | D6: USD
B7: Series F primary raise | C7: 30000000 | D7: USD
B8: Series F post-money | C8: =C6+C7 -> 1430000000 | D8: USD
B9: Series F secondary raise (tender) | C9: 15000000 | D9: USD
B10: Tender PPS multiplier | C10: 0.85 | D10: × F PPS
B11: ESOP refresh target (post-F FD) | C11: 0.13 | D11: of T_F
B12: Our fund check size | C12: 10000000 | D12: USD
B13: F_LEAD primary check | C13: 20000000 | D13: USD
B14: Option strike (issued options) | C14: 1 | D14: USD/share
B16: Pre-F Capitalization (carryover from Series E)
B17: Pre-F broad-based FD (A in WA AD formula) | C17: 36617961 | D17: shares
B18: Pre-F options issued | C18: 2500000 | D18: shares
B19: Pre-F options unissued (existing pool) | C19: 1894667 | D19: shares
B20: Pre-F existing option pool (issued + unissued) | C20: =C18+C19 -> 4394667 | D20: shares
B22: Common Stock Holdings
B23: Founder F1 (CEO) common | C23: 4000000 | D23: shares
B24: Founder F2 (CTO) common | C24: 2500000 | D24: shares
B25: Founder F3 (Chief Sci) common | C25: 1500000 | D25: shares
B26: Founders subtotal | C26: =SUM(C23:C25) -> 8000000 | D26: shares
B27: Employee RSAs (E1-E10, 100k each) | C27: 1000000 | D27: shares
B28: Total common + RSAs | C28: =C26+C27 -> 9000000 | D28: shares
B30: Prior Round OCPs (for Anti-Dilution)
B31: Seed OCP | C31: 1 | D31: USD/sh
B32: Series A OCP | C32: 3 | D32: USD/sh
B33: Series B OCP | C33: 10 | D33: USD/sh
B34: Series C OCP | C34: 25 | D34: USD/sh
B35: Series D OCP (compound v3·v4 = post-E NCP) | C35: 58.118347 | D35: USD/sh
B36: Series D original PPS (issued at) | C36: 60 | D36: USD/sh
B37: Series E OCP / PPS | C37: 49.158311 | D37: USD/sh
B39: Prior Round Shares Outstanding
B40: Seed shares | C40: 5000000 | D40: shares
B41: Series A shares | C41: 5000000 | D41: shares
B42: Series B shares | C42: 3000000 | D42: shares
B43: Series C shares | C43: 2400000 | D43: shares
B44: Series D shares (originally issued at $60) | C44: 1666667 | D44: shares
B45: Series E shares | C45: 6102667 | D45: shares
B47: Invested USD per Class
B48: Seed invested | C48: 5000000
B49: Series A invested | C49: 15000000
B50: Series B invested | C50: 30000000
B51: Series C invested | C51: 60000000
B52: Series D invested | C52: 100000000
B53: Series E invested | C53: 300000000
B55: Convertible Notes
B56: Note A principal | C56: 5000000
B57: Note A valuation cap | C57: 1000000000
B58: Note A discount | C58: 0.2
B59: Note B principal | C59: 3000000
B60: Note B valuation cap | C60: 1600000000
B61: Note B discount | C61: 0.15
B63: Exit Scenarios
B64: Exit 1 | C64: 700000000
B65: Exit 2 | C65: 1200000000
B66: Exit 3 (sensitivity ref) | C66: 2000000000
B67: Exit 4 | C67: 4000000000
B68: Exit 5 | C68: 8000000000
B70: Sensitivity Axes
B71: ESOP low / base / high | C71: 0.11 | D71: 0.13 | E71: 0.15
B72: Pre-money low / base / high | C72: 1200000000 | D72: 1400000000 | E72: 1800000000
B74: Return Multiples
B75: Target multiple (3×) | C75: 3
B76: Target multiple (4×) | C76: 4

Sheet Pro-Forma
B2: Pro-Forma Cap Table
B3: Series F closing — fully-diluted ownership
B5: Round Solve (Fixed Point)
B6: Series F pre-money | C6: =Assumptions!C6 -> 1400000000
B7: Series F primary raise | C7: =Assumptions!C7 -> 30000000
B8: Series F post-money | C8: =C6+C7 -> 1430000000
B9: ESOP target % of post-F FD | C9: =Assumptions!C11 -> 0.13
B10: Pre-F broad-based FD (A in WA AD) | C10: =Assumptions!C17 -> 36617961
B11: Existing option pool (issued + unissued) | C11: =Assumptions!C20 -> 4394667
B12: Common + RSAs | C12: =Assumptions!C28 -> 9000000
B14: Series E AD Coefficients
B15: OCP_E | C15: =Assumptions!C37 -> 49.158311
B16: α_E (E shares constant) | C16: =Assumptions!C45*C15*C10/(C15*C10+C7) -> 6002627.5
B17: β_E (E shares × p) | C17: =Assumptions!C45*C15*C7/(C15*C10+C7) -> 4917773.1
B19: Series D AD Coefficients
B20: OCP_D (compound v3·v4 = post-E NCP) | C20: =Assumptions!C35 -> 58.118347
B21: Original D PPS | C21: =Assumptions!C36 -> 60
B22: α_D | C22: =Assumptions!C44*C21*C10/(C20*C10+C7) -> 1696709.6
B23: β_D | C23: =Assumptions!C44*C21*C7/(C20*C10+C7) -> 1390063.4
B25: Note A Branch Determination
B26: Note A principal | C26: =Assumptions!C56 -> 5000000
B27: Note A cap | C27: =Assumptions!C57 -> 1000000000
B28: Note A discount | C28: =Assumptions!C58 -> 0.2
B29: Cap branch wins iff pre > threshold | C29: =(C27+C26)/(1-C28) -> 1256250000
B30: Note A branch | C30: =IF(C6>C29,"cap","discount") -> cap
B31: β_NA (NA shares × p) | C31: =IF(C30="cap",C26*C6/(C27+C26),C26/(1-C28)) -> 6965174.1
B33: Note B Branch Determination
B34: Note B principal | C34: =Assumptions!C59 -> 3000000
B35: Note B cap | C35: =Assumptions!C60 -> 1600000000
B36: Note B discount | C36: =Assumptions!C61 -> 0.15
B37: Cap branch wins iff pre > threshold | C37: =(C35+C34)/(1-C36) -> 1.8858824e+09
B38: Note B branch | C38: =IF(C6>C37,"cap","discount") -> discount
B39: β_NB | C39: =IF(C38="cap",C34*C6/(C35+C34),C34/(1-C36)) -> 3529411.8
B41: Closed-Form Solve
B42: Pre-F constant shares (Common+Seed+A+B+C) | C42: =C12+Assumptions!C40+Assumptions!C41+Assumptions!C42+Assumptions!C43 -> 24400000
B43: M = constants + α_E + α_D | C43: =C42+C16+C22 -> 32099337
B44: K = (1-esop)·post − raise − β_E − β_D − β_NA − β_NB | C44: =(1-C9)*C8-C7-C17-C23-C31-C39 -> 1.1972976e+09
B45: F_PPS = K / M (top-up triggered branch) | C45: =C44/C43 -> 37.29976
B46: T_F = post / F_PPS | C46: =C8/C45 -> 38338048
B47: ESOP top-up triggered? (0.13·T_F > 4.39M) | C47: =IF(C9*C46>C11,"Yes","No") -> Yes
B49: F_PPS (final) | C49: =C45 -> 37.29976
B50: T_F (final) | C50: =C46 -> 38338048
B52: Anti-Dilution Block (Broad-Based WA)
B53: Class | C53: OCP | D53: Trigger? | E53: New Conv. Price | F53: New Ratio | G53: As-Conv Shares | H53: Original Shares
B54: Seed | C54: =Assumptions!C31 -> 1 | D54: =IF(C49<C54,"Yes","No") -> No | E54: =IF(D54="Yes",C54*(C10+C7/C54)/(C10+C7/C49),C54) -> 1 | F54: =C54/E54 -> 1 | G54: =Assumptions!C40*F54 -> 5000000 | H54: =Assumptions!C40 -> 5000000
B55: Series A | C55: =Assumptions!C32 -> 3 | D55: =IF(C49<C55,"Yes","No") -> No | E55: =IF(D55="Yes",C55*(C10+C7/C55)/(C10+C7/C49),C55) -> 3 | F55: =C55/E55 -> 1 | G55: =Assumptions!C41*F55 -> 5000000 | H55: =Assumptions!C41 -> 5000000
B56: Series B | C56: =Assumptions!C33 -> 10 | D56: =IF(C49<C56,"Yes","No") -> No | E56: =IF(D56="Yes",C56*(C10+C7/C56)/(C10+C7/C49),C56) -> 10 | F56: =C56/E56 -> 1 | G56: =Assumptions!C42*F56 -> 3000000 | H56: =Assumptions!C42 -> 3000000
B57: Series C | C57: =Assumptions!C34 -> 25 | D57: =IF(C49<C57,"Yes","No") -> No | E57: =IF(D57="Yes",C57*(C10+C7/C57)/(C10+C7/C49),C57) -> 25 | F57: =C57/E57 -> 1 | G57: =Assumptions!C43*F57 -> 2400000 | H57: =Assumptions!C43 -> 2400000
B58: Series D | C58: =C20 -> 58.118347 | D58: =IF(C49<C58,"Yes","No") -> Yes | E58: =IF(D58="Yes",C58*(C10+C7/C58)/(C10+C7/C49),C58) -> 57.670905 | F58: =C21/E58 -> 1.040386 | G58: =Assumptions!C44*F58 -> 1733976.9 | H58: =Assumptions!C44 -> 1666667
B59: Series E | C59: =C15 -> 49.158311 | D59: =IF(C49<C59,"Yes","No") -> Yes | E59: =IF(D59="Yes",C59*(C10+C7/C59)/(C10+C7/C49),C59) -> 48.903442 | F59: =C59/E59 -> 1.0052117 | G59: =Assumptions!C45*F59 -> 6134472.1 | H59: =Assumptions!C45 -> 6102667
B61: Convertible Notes Block
B62: Note | C62: Cap-Implied PPS | D62: Discount-Implied PPS | E62: Conversion PPS | F62: Branch | G62: Shares Issued | H62: Principal
B63: Note A | C63: =C27*C49/(C6-C31) -> 26.775899 | D63: =C49*(1-C28) -> 29.839808 | E63: =MIN(C63,D63) -> 26.775899 | F63: =IF(C63<D63,"cap","discount") -> cap | G63: =C26/E63 -> 186735.09 | H63: =C26 -> 5000000
B64: Note B | C64: =C35*C49/(C6-C39) -> 42.736035 | D64: =C49*(1-C36) -> 31.704796 | E64: =MIN(C64,D64) -> 31.704796 | F64: =IF(C64<D64,"cap","discount") -> discount | G64: =C34/E64 -> 94622.908 | H64: =C34 -> 3000000
B66: Secondary Tender Block
B67: Tender raise ($) | C67: =Assumptions!C9 -> 15000000
B68: Tender PPS multiplier | C68: =Assumptions!C10 -> 0.85
B69: Tender PPS | C69: =C68*C49 -> 31.704796
B70: Tender shares (transferred from founders) | C70: =C67/C69 -> 473114.54
B71: Founders' total common (pre-tender) | C71: =Assumptions!C26 -> 8000000
B72: F1 tender give-up (50.00% of founders) | C72: =C70*Assumptions!C23/C71 -> 236557.27
B73: F2 tender give-up (31.25%) | C73: =C70*Assumptions!C24/C71 -> 147848.29
B74: F3 tender give-up (18.75%) | C74: =C70*Assumptions!C25/C71 -> 88708.976
B75: F_LEAD secondary common holding | C75: =C70 -> 473114.54
B77: Post-F Capitalization Table
B78: Stakeholder | C78: Class | D78: Shares | E78: % of Post-F FD | F78: Notes
B79: F1 (CEO) | C79: Common | D79: =Assumptions!C23-C72 -> 3763442.7 | E79: =D79/C50 -> 0.098164693
B80: F2 (CTO) | C80: Common | D80: =Assumptions!C24-C73 -> 2352151.7 | E80: =D80/C50 -> 0.061352933
B81: F3 (Chief Sci) | C81: Common | D81: =Assumptions!C25-C74 -> 1411291 | E81: =D81/C50 -> 0.03681176
B82: Employee RSAs (E1-E10) | C82: Common | D82: =Assumptions!C27 -> 1000000 | E82: =D82/C50 -> 0.026083748
B83: Seed holder | C83: Seed Pref (AS-CONV) | D83: =G54 -> 5000000 | E83: =D83/C50 -> 0.13041874
B84: Series A holder | C84: Series A Pref (AS-CONV) | D84: =G55 -> 5000000 | E84: =D84/C50 -> 0.13041874
B85: Series B holder | C85: Series B Pref (AS-CONV) | D85: =G56 -> 3000000 | E85: =D85/C50 -> 0.078251245
B86: Series C holder | C86: Series C Pref (AS-CONV) | D86: =G57 -> 2400000 | E86: =D86/C50 -> 0.062600996
B87: Series D holder | C87: Series D Pref (AS-CONV) | D87: =G58 -> 1733976.9 | E87: =D87/C50 -> 0.045228618
B88: Series E holders (10) | C88: Series E Pref (AS-CONV) | D88: =G59 -> 6134472.1 | E88: =D88/C50 -> 0.16001003
B89: Note A holder | C89: Common (post-conv) | D89: =G63 -> 186735.09 | E89: =D89/C50 -> 0.0048707511
B90: Note B holder | C90: Common (post-conv) | D90: =G64 -> 94622.908 | E90: =D90/C50 -> 0.0024681201
B91: F_LEAD (primary) | C91: Series F Pref | D91: =Assumptions!C13/C49 -> 536196.48 | E91: =D91/C50 -> 0.013986014
B92: F_LEAD (secondary) | C92: Common (from founders) | D92: =C70 -> 473114.54 | E92: =D92/C50 -> 0.012340601
B93: Our fund (F_FUND) | C93: Series F Pref | D93: =Assumptions!C12/C49 -> 268098.24 | E93: =D93/C50 -> 0.006993007
B94: ESOP issued options | C94: Options | D94: =Assumptions!C18 -> 2500000 | E94: =D94/C50 -> 0.065209371
B95: ESOP unissued (post-F top-up) | C95: Options Pool | D95: =C9*C50-Assumptions!C18 -> 2483946.2 | E95: =D95/C50 -> 0.064790629
B96: Total | D96: =SUM(D79:D95) -> 38338048 | E96: =SUM(E79:E95) -> 1
B97: Check | D97: =ROUND(D96-C50,2) -> 0 | E97: =ROUND(E96-1,8) -> 0

Sheet Return-Solver
B2: Return Solver
B3: Required Series F ownership for 3× / 4× return on our $10M check
B5: Inputs (Base Case)
B6: Our fund check | C6: =Assumptions!C12 -> 10000000
B7: Series F primary raise (total) | C7: =Assumptions!C7 -> 30000000
B8: Target multiple 3× | C8: =Assumptions!C75 -> 3
B9: Target multiple 4× | C9: =Assumptions!C76 -> 4
B10: 3× target proceeds | C10: =C6*C8 -> 30000000
B11: 4× target proceeds | C11: =C6*C9 -> 40000000
B12: Post-F T_F (base case) | C12: ='Pro-Forma'!C50 -> 38338048
B13: Post-money (base) | C13: ='Pro-Forma'!C8 -> 1430000000
B14: Per-Exit Required Ownership
B15: Exit Scenario | C15: Exit Value | D15: F Election (base) | E15: PPS at Exit | F15: Req % for 3× ($30M) | G15: Req % for 4× ($40M) | H15: Feasibility Flag
B16: Exit 1 | C16: =Assumptions!C64 -> 700000000 | D16: ='Waterfall'!D43 -> preference | E16: ='Waterfall'!C44 -> 8.3787246 | F16: =IF(D16="convert",$C$10/(E16*$C$12),$C$10/$C$13) -> 0.020979021 | G16: =IF(D16="convert",$C$11/(E16*$C$12),$C$11/$C$13) -> 0.027972028 | H16: =IF(OR(F16<=0,F16>1,G16<=0,G16>1),"INFEASIBLE","feasible") -> feasible
B17: Exit 2 | C17: =Assumptions!C65 -> 1200000000 | D17: ='Waterfall'!D58 -> preference | E17: ='Waterfall'!C59 -> 28.420214 | F17: =IF(D17="convert",$C$10/(E17*$C$12),$C$10/$C$13) -> 0.020979021 | G17: =IF(D17="convert",$C$11/(E17*$C$12),$C$11/$C$13) -> 0.027972028 | H17: =IF(OR(F17<=0,F17>1,G17<=0,G17>1),"INFEASIBLE","feasible") -> feasible
B18: Exit 3 | C18: =Assumptions!C66 -> 2000000000 | D18: ='Waterfall'!D73 -> convert | E18: ='Waterfall'!C74 -> 55.758882 | F18: =IF(D18="convert",$C$10/(E18*$C$12),$C$10/$C$13) -> 0.014033862 | G18: =IF(D18="convert",$C$11/(E18*$C$12),$C$11/$C$13) -> 0.018711816 | H18: =IF(OR(F18<=0,F18>1,G18<=0,G18>1),"INFEASIBLE","feasible") -> feasible
B19: Exit 4 | C19: =Assumptions!C67 -> 4000000000 | D19: ='Waterfall'!D88 -> convert | E19: ='Waterfall'!C89 -> 111.63297 | F19: =IF(D19="convert",$C$10/(E19*$C$12),$C$10/$C$13) -> 0.0070096892 | G19: =IF(D19="convert",$C$11/(E19*$C$12),$C$11/$C$13) -> 0.0093462523 | H19: =IF(OR(F19<=0,F19>1,G19<=0,G19>1),"INFEASIBLE","feasible") -> feasible
B20: Exit 5 | C20: =Assumptions!C68 -> 8000000000 | D20: ='Waterfall'!D103 -> convert | E20: ='Waterfall'!C104 -> 223.19622 | F20: =IF(D20="convert",$C$10/(E20*$C$12),$C$10/$C$13) -> 0.0035059395 | G20: =IF(D20="convert",$C$11/(E20*$C$12),$C$11/$C$13) -> 0.004674586 | H20: =IF(OR(F20<=0,F20>1,G20<=0,G20>1),"INFEASIBLE","feasible") -> feasible
B22: Notes
B23: If F takes preference at an exit, max F-class proceeds = $30M total
B24: regardless of ownership %; 4× target requires $40M, infeasible by definition
B25: When F converts, required ownership scales as target / (PPS × T_F)

Sheet Sensitivity
B2: Sensitivity Analysis
B3: Our $10M check — ownership % and $ proceeds at $2B exit
B5: Global Constants (independent of cell)
B6: Pre-F broad-based FD (A in WA AD) | C6: =Assumptions!C17 -> 36617961
B7: Series F primary raise | C7: =Assumptions!C7 -> 30000000
B8: OCP_E | C8: =Assumptions!C37 -> 49.158311
B9: OCP_D | C9: =Assumptions!C35 -> 58.118347
B10: Original D PPS | C10: =Assumptions!C36 -> 60
B11: α_E (constant) | C11: =Assumptions!C45*C8*C6/(C8*C6+C7) -> 6002627.5
B12: β_E (constant) | C12: =Assumptions!C45*C8*C7/(C8*C6+C7) -> 4917773.1
B13: α_D (constant) | C13: =Assumptions!C44*C10*C6/(C9*C6+C7) -> 1696709.6
B14: β_D (constant) | C14: =Assumptions!C44*C10*C7/(C9*C6+C7) -> 1390063.4
B15: M (constant pre-F shares) | C15: =Assumptions!C28+Assumptions!C40+Assumptions!C41+Assumptions!C42+Assumptions!C43+C11+C13 -> 32099337
B16: Common (9M + RSAs) | C16: =Assumptions!C28 -> 9000000
B17: Options issued | C17: =Assumptions!C18 -> 2500000
B18: Option strike | C18: =Assumptions!C14 -> 1
B19: Existing option pool | C19: =Assumptions!C20 -> 4394667
B20: Note A principal / cap / disc | C20: =Assumptions!C56 -> 5000000 | D20: =Assumptions!C57 -> 1000000000 | E20: =Assumptions!C58 -> 0.2
B21: Note B principal / cap / disc | C21: =Assumptions!C59 -> 3000000 | D21: =Assumptions!C60 -> 1600000000 | E21: =Assumptions!C61 -> 0.15
B22: Cap branch threshold (NA, NB) | C22: =(D20+C20)/(1-E20) -> 1256250000 | D22: =(D21+C21)/(1-E21) -> 1.8858824e+09
B23: $2B exit target | C23: =Assumptions!C66 -> 2000000000
B24: Our fund check | C24: =Assumptions!C12 -> 10000000
B28: Cell (11%, $1.2B)
B29: Pre-money | C29: =Assumptions!C72 -> 1200000000
B30: ESOP refresh | C30: =Assumptions!C71 -> 0.11
B31: Post-money | C31: =C29+$C$7 -> 1230000000
B32: Note A branch / β_NA | C32: =IF(C29>$C$22,"cap","discount") -> discount | D32: =IF(C32="cap",$C$20*C29/($D$20+$C$20),$C$20/(1-$E$20)) -> 6250000
B33: Note B branch / β_NB | C33: =IF(C29>$D$22,"cap","discount") -> discount | D33: =IF(C33="cap",$C$21*C29/($D$21+$C$21),$C$21/(1-$E$21)) -> 3529411.8
B34: K | C34: =(1-C30)*C31-$C$7-$C$12-$C$14-D32-D33 -> 1.0486128e+09
B35: F_PPS | C35: =C34/$C$15 -> 32.667739
B36: T_F | C36: =C31/C35 -> 37651826
B37: F_pri shares | C37: =$C$7/C35 -> 918337.21
B38: E_sh (with AD) | C38: =$C$11+$C$12/C35 -> 6153166.6
B39: D_sh (with AD) | C39: =$C$13+$C$14/C35 -> 1739261.2
B40: NA_sh / NB_sh | C40: =D32/C35 -> 191320.25 | D40: =D33/C35 -> 108039.67
B41: Opts (max) | C41: =MAX($C$19,C30*C36) -> 4394667
B42: Common-eq base (common+opts+notes) | C42: =$C$16+$C$17+C40+D40 -> 11799360
B43: $2B Waterfall — Iteration
B44: Class → | D44: F | E44: E | F44: D | G44: C | H44: B | I44: A | J44: Seed | K44: ΣPref | L44: ΣConvN
B45: S (pref $) | D45: =$C$7 | E45: =Assumptions!C53 -> 300000000 | F45: =Assumptions!C52 -> 100000000 | G45: =Assumptions!C51 -> 60000000 | H45: =Assumptions!C50 -> 30000000 | I45: =Assumptions!C49 -> 15000000 | J45: =Assumptions!C48 -> 5000000
B46: n (as-conv shares) | D46: =C37 -> 918337.21 | E46: =C38 -> 6153166.6 | F46: =C39 -> 1739261.2 | G46: =Assumptions!C43 -> 2400000 | H46: =Assumptions!C42 -> 3000000 | I46: =Assumptions!C41 -> 5000000 | J46: =Assumptions!C40 -> 5000000
B47: Iter 0 | D47: convert | E47: convert | F47: convert | G47: convert | H47: convert | I47: convert | J47: convert | K47: =IF(D47="preference",D45,0)+IF(E47="preference",E45,0)+IF(F47="preference",F45,0)+IF(G47="preference",G45,0)+IF(H47="preference",H45,0)+IF(I47="preference",I45,0)+IF(J47="preference",J45,0) -> 0 | L47: =IF(D47="convert",D46,0)+IF(E47="convert",E46,0)+IF(F47="convert",F46,0)+IF(G47="convert",G46,0)+IF(H47="convert",H46,0)+IF(I47="convert",I46,0)+IF(J47="convert",J46,0) -> 24210765
B48: Iter 1 | D48: =IF(D$45>((($C$23+$C$17*$C$18)-(K47-IF(D47="preference",D$45,0)))/(C$42+(L47-IF(D47="convert",D$46,0))+D$46)*D$46),"preference","convert") -> convert | E48: =IF(E$45>((($C$23+$C$17*$C$18)-(K47-IF(E47="preference",E$45,0)))/(C$42+(L47-IF(E47="convert",E$46,0))+E$46)*E$46),"preference","convert") -> convert | F48: =IF(F$45>((($C$23+$C$17*$C$18)-(K47-IF(F47="preference",F$45,0)))/(C$42+(L47-IF(F47="convert",F$46,0))+F$46)*F$46),"preference","convert") -> preference | G48: =IF(G$45>((($C$23+$C$17*$C$18)-(K47-IF(G47="preference",G$45,0)))/(C$42+(L47-IF(G47="convert",G$46,0))+G$46)*G$46),"preference","convert") -> convert | H48: =IF(H$45>((($C$23+$C$17*$C$18)-(K47-IF(H47="preference",H$45,0)))/(C$42+(L47-IF(H47="convert",H$46,0))+H$46)*H$46),"preference","convert") -> convert | I48: =IF(I$45>((($C$23+$C$17*$C$18)-(K47-IF(I47="preference",I$45,0)))/(C$42+(L47-IF(I47="convert",I$46,0))+I$46)*I$46),"preference","convert") -> convert | J48: =IF(J$45>((($C$23+$C$17*$C$18)-(K47-IF(J47="preference",J$45,0)))/(C$42+(L47-IF(J47="convert",J$46,0))+J$46)*J$46),"preference","convert") -> convert | K48: =IF(D48="preference",D45,0)+IF(E48="preference",E45,0)+IF(F48="preference",F45,0)+IF(G48="preference",G45,0)+IF(H48="preference",H45,0)+IF(I48="preference",I45,0)+IF(J48="preference",J45,0) -> 100000000 | L48: =IF(D48="convert",D46,0)+IF(E48="convert",E46,0)+IF(F48="convert",F46,0)+IF(G48="convert",G46,0)+IF(H48="convert",H46,0)+IF(I48="convert",I46,0)+IF(J48="convert",J46,0) -> 22471504
B49: Iter 2 | D49: =IF(D$45>((($C$23+$C$17*$C$18)-(K48-IF(D48="preference",D$45,0)))/(C$42+(L48-IF(D48="convert",D$46,0))+D$46)*D$46),"preference","convert") -> convert | E49: =IF(E$45>((($C$23+$C$17*$C$18)-(K48-IF(E48="preference",E$45,0)))/(C$42+(L48-IF(E48="convert",E$46,0))+E$46)*E$46),"preference","convert") -> convert | F49: =IF(F$45>((($C$23+$C$17*$C$18)-(K48-IF(F48="preference",F$45,0)))/(C$42+(L48-IF(F48="convert",F$46,0))+F$46)*F$46),"preference","convert") -> preference | G49: =IF(G$45>((($C$23+$C$17*$C$18)-(K48-IF(G48="preference",G$45,0)))/(C$42+(L48-IF(G48="convert",G$46,0))+G$46)*G$46),"preference","convert") -> convert | H49: =IF(H$45>((($C$23+$C$17*$C$18)-(K48-IF(H48="preference",H$45,0)))/(C$42+(L48-IF(H48="convert",H$46,0))+H$46)*H$46),"preference","convert") -> convert | I49: =IF(I$45>((($C$23+$C$17*$C$18)-(K48-IF(I48="preference",I$45,0)))/(C$42+(L48-IF(I48="convert",I$46,0))+I$46)*I$46),"preference","convert") -> convert | J49: =IF(J$45>((($C$23+$C$17*$C$18)-(K48-IF(J48="preference",J$45,0)))/(C$42+(L48-IF(J48="convert",J$46,0))+J$46)*J$46),"preference","convert") -> convert | K49: =IF(D49="preference",D45,0)+IF(E49="preference",E45,0)+IF(F49="preference",F45,0)+IF(G49="preference",G45,0)+IF(H49="preference",H45,0)+IF(I49="preference",I45,0)+IF(J49="preference",J45,0) -> 100000000 | L49: =IF(D49="convert",D46,0)+IF(E49="convert",E46,0)+IF(F49="convert",F46,0)+IF(G49="convert",G46,0)+IF(H49="convert",H46,0)+IF(I49="convert",I46,0)+IF(J49="convert",J46,0) -> 22471504
B50: Iter 3 | D50: =IF(D$45>((($C$23+$C$17*$C$18)-(K49-IF(D49="preference",D$45,0)))/(C$42+(L49-IF(D49="convert",D$46,0))+D$46)*D$46),"preference","convert") -> convert | E50: =IF(E$45>((($C$23+$C$17*$C$18)-(K49-IF(E49="preference",E$45,0)))/(C$42+(L49-IF(E49="convert",E$46,0))+E$46)*E$46),"preference","convert") -> convert | F50: =IF(F$45>((($C$23+$C$17*$C$18)-(K49-IF(F49="preference",F$45,0)))/(C$42+(L49-IF(F49="convert",F$46,0))+F$46)*F$46),"preference","convert") -> preference | G50: =IF(G$45>((($C$23+$C$17*$C$18)-(K49-IF(G49="preference",G$45,0)))/(C$42+(L49-IF(G49="convert",G$46,0))+G$46)*G$46),"preference","convert") -> convert | H50: =IF(H$45>((($C$23+$C$17*$C$18)-(K49-IF(H49="preference",H$45,0)))/(C$42+(L49-IF(H49="convert",H$46,0))+H$46)*H$46),"preference","convert") -> convert | I50: =IF(I$45>((($C$23+$C$17*$C$18)-(K49-IF(I49="preference",I$45,0)))/(C$42+(L49-IF(I49="convert",I$46,0))+I$46)*I$46),"preference","convert") -> convert | J50: =IF(J$45>((($C$23+$C$17*$C$18)-(K49-IF(J49="preference",J$45,0)))/(C$42+(L49-IF(J49="convert",J$46,0))+J$46)*J$46),"preference","convert") -> convert | K50: =IF(D50="preference",D45,0)+IF(E50="preference",E45,0)+IF(F50="preference",F45,0)+IF(G50="preference",G45,0)+IF(H50="preference",H45,0)+IF(I50="preference",I45,0)+IF(J50="preference",J45,0) -> 100000000 | L50: =IF(D50="convert",D46,0)+IF(E50="convert",E46,0)+IF(F50="convert",F46,0)+IF(G50="convert",G46,0)+IF(H50="convert",H46,0)+IF(I50="convert",I46,0)+IF(J50="convert",J46,0) -> 22471504
B51: Iter 4 | D51: =IF(D$45>((($C$23+$C$17*$C$18)-(K50-IF(D50="preference",D$45,0)))/(C$42+(L50-IF(D50="convert",D$46,0))+D$46)*D$46),"preference","convert") -> convert | E51: =IF(E$45>((($C$23+$C$17*$C$18)-(K50-IF(E50="preference",E$45,0)))/(C$42+(L50-IF(E50="convert",E$46,0))+E$46)*E$46),"preference","convert") -> convert | F51: =IF(F$45>((($C$23+$C$17*$C$18)-(K50-IF(F50="preference",F$45,0)))/(C$42+(L50-IF(F50="convert",F$46,0))+F$46)*F$46),"preference","convert") -> preference | G51: =IF(G$45>((($C$23+$C$17*$C$18)-(K50-IF(G50="preference",G$45,0)))/(C$42+(L50-IF(G50="convert",G$46,0))+G$46)*G$46),"preference","convert") -> convert | H51: =IF(H$45>((($C$23+$C$17*$C$18)-(K50-IF(H50="preference",H$45,0)))/(C$42+(L50-IF(H50="convert",H$46,0))+H$46)*H$46),"preference","convert") -> convert | I51: =IF(I$45>((($C$23+$C$17*$C$18)-(K50-IF(I50="preference",I$45,0)))/(C$42+(L50-IF(I50="convert",I$46,0))+I$46)*I$46),"preference","convert") -> convert | J51: =IF(J$45>((($C$23+$C$17*$C$18)-(K50-IF(J50="preference",J$45,0)))/(C$42+(L50-IF(J50="convert",J$46,0))+J$46)*J$46),"preference","convert") -> convert | K51: =IF(D51="preference",D45,0)+IF(E51="preference",E45,0)+IF(F51="preference",F45,0)+IF(G51="preference",G45,0)+IF(H51="preference",H45,0)+IF(I51="preference",I45,0)+IF(J51="preference",J45,0) -> 100000000 | L51: =IF(D51="convert",D46,0)+IF(E51="convert",E46,0)+IF(F51="convert",F46,0)+IF(G51="convert",G46,0)+IF(H51="convert",H46,0)+IF(I51="convert",I46,0)+IF(J51="convert",J46,0) -> 22471504
B52: Iter 5 | D52: =IF(D$45>((($C$23+$C$17*$C$18)-(K51-IF(D51="preference",D$45,0)))/(C$42+(L51-IF(D51="convert",D$46,0))+D$46)*D$46),"preference","convert") -> convert | E52: =IF(E$45>((($C$23+$C$17*$C$18)-(K51-IF(E51="preference",E$45,0)))/(C$42+(L51-IF(E51="convert",E$46,0))+E$46)*E$46),"preference","convert") -> convert | F52: =IF(F$45>((($C$23+$C$17*$C$18)-(K51-IF(F51="preference",F$45,0)))/(C$42+(L51-IF(F51="convert",F$46,0))+F$46)*F$46),"preference","convert") -> preference | G52: =IF(G$45>((($C$23+$C$17*$C$18)-(K51-IF(G51="preference",G$45,0)))/(C$42+(L51-IF(G51="convert",G$46,0))+G$46)*G$46),"preference","convert") -> convert | H52: =IF(H$45>((($C$23+$C$17*$C$18)-(K51-IF(H51="preference",H$45,0)))/(C$42+(L51-IF(H51="convert",H$46,0))+H$46)*H$46),"preference","convert") -> convert | I52: =IF(I$45>((($C$23+$C$17*$C$18)-(K51-IF(I51="preference",I$45,0)))/(C$42+(L51-IF(I51="convert",I$46,0))+I$46)*I$46),"preference","convert") -> convert | J52: =IF(J$45>((($C$23+$C$17*$C$18)-(K51-IF(J51="preference",J$45,0)))/(C$42+(L51-IF(J51="convert",J$46,0))+J$46)*J$46),"preference","convert") -> convert | K52: =IF(D52="preference",D45,0)+IF(E52="preference",E45,0)+IF(F52="preference",F45,0)+IF(G52="preference",G45,0)+IF(H52="preference",H45,0)+IF(I52="preference",I45,0)+IF(J52="preference",J45,0) -> 100000000 | L52: =IF(D52="convert",D46,0)+IF(E52="convert",E46,0)+IF(F52="convert",F46,0)+IF(G52="convert",G46,0)+IF(H52="convert",H46,0)+IF(I52="convert",I46,0)+IF(J52="convert",J46,0) -> 22471504
B53: PPS at $2B | C53: =(($C$23+$C$17*$C$18)-K52)/(C42+L52) -> 55.513629
B54: F election / our proceeds | C54: =D52 -> convert | D54: =IF(D52="preference",$C$24,C53*$C$24/C35) -> 16993410
B55: Our ownership % | C55: =($C$24/C35)/C36 -> 0.0081300813
B56: Cell (11%, $1.4B)
B57: Pre-money | C57: =Assumptions!D72 -> 1400000000
B58: ESOP refresh | C58: =Assumptions!C71 -> 0.11
B59: Post-money | C59: =C57+$C$7 -> 1430000000
B60: Note A branch / β_NA | C60: =IF(C57>$C$22,"cap","discount") -> cap | D60: =IF(C60="cap",$C$20*C57/($D$20+$C$20),$C$20/(1-$E$20)) -> 6965174.1
B61: Note B branch / β_NB | C61: =IF(C57>$D$22,"cap","discount") -> discount | D61: =IF(C61="cap",$C$21*C57/($D$21+$C$21),$C$21/(1-$E$21)) -> 3529411.8
B62: K | C62: =(1-C58)*C59-$C$7-$C$12-$C$14-D60-D61 -> 1.2258976e+09
B63: F_PPS | C63: =C62/$C$15 -> 38.190744
B64: T_F | C64: =C59/C63 -> 37443627
B65: F_pri shares | C65: =$C$7/C63 -> 785530.64
B66: E_sh (with AD) | C66: =$C$11+$C$12/C63 -> 6131396.2
B67: D_sh (with AD) | C67: =$C$13+$C$14/C63 -> 1733107.5
B68: NA_sh / NB_sh | C68: =D60/C63 -> 182378.59 | D68: =D61/C63 -> 92415.37
B69: Opts (max) | C69: =MAX($C$19,C58*C64) -> 4394667
B70: Common-eq base (common+opts+notes) | C70: =$C$16+$C$17+C68+D68 -> 11774794
B71: $2B Waterfall — Iteration
B72: Class → | D72: F | E72: E | F72: D | G72: C | H72: B | I72: A | J72: Seed | K72: ΣPref | L72: ΣConvN
B73: S (pref $) | D73: =$C$7 | E73: =Assumptions!C53 -> 300000000 | F73: =Assumptions!C52 -> 100000000 | G73: =Assumptions!C51 -> 60000000 | H73: =Assumptions!C50 -> 30000000 | I73: =Assumptions!C49 -> 15000000 | J73: =Assumptions!C48 -> 5000000
B74: n (as-conv shares) | D74: =C65 -> 785530.64 | E74: =C66 -> 6131396.2 | F74: =C67 -> 1733107.5 | G74: =Assumptions!C43 -> 2400000 | H74: =Assumptions!C42 -> 3000000 | I74: =Assumptions!C41 -> 5000000 | J74: =Assumptions!C40 -> 5000000
B75: Iter 0 | D75: convert | E75: convert | F75: convert | G75: convert | H75: convert | I75: convert | J75: convert | K75: =IF(D75="preference",D73,0)+IF(E75="preference",E73,0)+IF(F75="preference",F73,0)+IF(G75="preference",G73,0)+IF(H75="preference",H73,0)+IF(I75="preference",I73,0)+IF(J75="preference",J73,0) -> 0 | L75: =IF(D75="convert",D74,0)+IF(E75="convert",E74,0)+IF(F75="convert",F74,0)+IF(G75="convert",G74,0)+IF(H75="convert",H74,0)+IF(I75="convert",I74,0)+IF(J75="convert",J74,0) -> 24050034
B76: Iter 1 | D76: =IF(D$73>((($C$23+$C$17*$C$18)-(K75-IF(D75="preference",D$73,0)))/(C$70+(L75-IF(D75="convert",D$74,0))+D$74)*D$74),"preference","convert") -> convert | E76: =IF(E$73>((($C$23+$C$17*$C$18)-(K75-IF(E75="preference",E$73,0)))/(C$70+(L75-IF(E75="convert",E$74,0))+E$74)*E$74),"preference","convert") -> convert | F76: =IF(F$73>((($C$23+$C$17*$C$18)-(K75-IF(F75="preference",F$73,0)))/(C$70+(L75-IF(F75="convert",F$74,0))+F$74)*F$74),"preference","convert") -> preference | G76: =IF(G$73>((($C$23+$C$17*$C$18)-(K75-IF(G75="preference",G$73,0)))/(C$70+(L75-IF(G75="convert",G$74,0))+G$74)*G$74),"preference","convert") -> convert | H76: =IF(H$73>((($C$23+$C$17*$C$18)-(K75-IF(H75="preference",H$73,0)))/(C$70+(L75-IF(H75="convert",H$74,0))+H$74)*H$74),"preference","convert") -> convert | I76: =IF(I$73>((($C$23+$C$17*$C$18)-(K75-IF(I75="preference",I$73,0)))/(C$70+(L75-IF(I75="convert",I$74,0))+I$74)*I$74),"preference","convert") -> convert | J76: =IF(J$73>((($C$23+$C$17*$C$18)-(K75-IF(J75="preference",J$73,0)))/(C$70+(L75-IF(J75="convert",J$74,0))+J$74)*J$74),"preference","convert") -> convert | K76: =IF(D76="preference",D73,0)+IF(E76="preference",E73,0)+IF(F76="preference",F73,0)+IF(G76="preference",G73,0)+IF(H76="preference",H73,0)+IF(I76="preference",I73,0)+IF(J76="preference",J73,0) -> 100000000 | L76: =IF(D76="convert",D74,0)+IF(E76="convert",E74,0)+IF(F76="convert",F74,0)+IF(G76="convert",G74,0)+IF(H76="convert",H74,0)+IF(I76="convert",I74,0)+IF(J76="convert",J74,0) -> 22316927
B77: Iter 2 | D77: =IF(D$73>((($C$23+$C$17*$C$18)-(K76-IF(D76="preference",D$73,0)))/(C$70+(L76-IF(D76="convert",D$74,0))+D$74)*D$74),"preference","convert") -> convert | E77: =IF(E$73>((($C$23+$C$17*$C$18)-(K76-IF(E76="preference",E$73,0)))/(C$70+(L76-IF(E76="convert",E$74,0))+E$74)*E$74),"preference","convert") -> convert | F77: =IF(F$73>((($C$23+$C$17*$C$18)-(K76-IF(F76="preference",F$73,0)))/(C$70+(L76-IF(F76="convert",F$74,0))+F$74)*F$74),"preference","convert") -> preference | G77: =IF(G$73>((($C$23+$C$17*$C$18)-(K76-IF(G76="preference",G$73,0)))/(C$70+(L76-IF(G76="convert",G$74,0))+G$74)*G$74),"preference","convert") -> convert | H77: =IF(H$73>((($C$23+$C$17*$C$18)-(K76-IF(H76="preference",H$73,0)))/(C$70+(L76-IF(H76="convert",H$74,0))+H$74)*H$74),"preference","convert") -> convert | I77: =IF(I$73>((($C$23+$C$17*$C$18)-(K76-IF(I76="preference",I$73,0)))/(C$70+(L76-IF(I76="convert",I$74,0))+I$74)*I$74),"preference","convert") -> convert | J77: =IF(J$73>((($C$23+$C$17*$C$18)-(K76-IF(J76="preference",J$73,0)))/(C$70+(L76-IF(J76="convert",J$74,0))+J$74)*J$74),"preference","convert") -> convert | K77: =IF(D77="preference",D73,0)+IF(E77="preference",E73,0)+IF(F77="preference",F73,0)+IF(G77="preference",G73,0)+IF(H77="preference",H73,0)+IF(I77="preference",I73,0)+IF(J77="preference",J73,0) -> 100000000 | L77: =IF(D77="convert",D74,0)+IF(E77="convert",E74,0)+IF(F77="convert",F74,0)+IF(G77="convert",G74,0)+IF(H77="convert",H74,0)+IF(I77="convert",I74,0)+IF(J77="convert",J74,0) -> 22316927
B78: Iter 3 | D78: =IF(D$73>((($C$23+$C$17*$C$18)-(K77-IF(D77="preference",D$73,0)))/(C$70+(L77-IF(D77="convert",D$74,0))+D$74)*D$74),"preference","convert") -> convert | E78: =IF(E$73>((($C$23+$C$17*$C$18)-(K77-IF(E77="preference",E$73,0)))/(C$70+(L77-IF(E77="convert",E$74,0))+E$74)*E$74),"preference","convert") -> convert | F78: =IF(F$73>((($C$23+$C$17*$C$18)-(K77-IF(F77="preference",F$73,0)))/(C$70+(L77-IF(F77="convert",F$74,0))+F$74)*F$74),"preference","convert") -> preference | G78: =IF(G$73>((($C$23+$C$17*$C$18)-(K77-IF(G77="preference",G$73,0)))/(C$70+(L77-IF(G77="convert",G$74,0))+G$74)*G$74),"preference","convert") -> convert | H78: =IF(H$73>((($C$23+$C$17*$C$18)-(K77-IF(H77="preference",H$73,0)))/(C$70+(L77-IF(H77="convert",H$74,0))+H$74)*H$74),"preference","convert") -> convert | I78: =IF(I$73>((($C$23+$C$17*$C$18)-(K77-IF(I77="preference",I$73,0)))/(C$70+(L77-IF(I77="convert",I$74,0))+I$74)*I$74),"preference","convert") -> convert | J78: =IF(J$73>((($C$23+$C$17*$C$18)-(K77-IF(J77="preference",J$73,0)))/(C$70+(L77-IF(J77="convert",J$74,0))+J$74)*J$74),"preference","convert") -> convert | K78: =IF(D78="preference",D73,0)+IF(E78="preference",E73,0)+IF(F78="preference",F73,0)+IF(G78="preference",G73,0)+IF(H78="preference",H73,0)+IF(I78="preference",I73,0)+IF(J78="preference",J73,0) -> 100000000 | L78: =IF(D78="convert",D74,0)+IF(E78="convert",E74,0)+IF(F78="convert",F74,0)+IF(G78="convert",G74,0)+IF(H78="convert",H74,0)+IF(I78="convert",I74,0)+IF(J78="convert",J74,0) -> 22316927
B79: Iter 4 | D79: =IF(D$73>((($C$23+$C$17*$C$18)-(K78-IF(D78="preference",D$73,0)))/(C$70+(L78-IF(D78="convert",D$74,0))+D$74)*D$74),"preference","convert") -> convert | E79: =IF(E$73>((($C$23+$C$17*$C$18)-(K78-IF(E78="preference",E$73,0)))/(C$70+(L78-IF(E78="convert",E$74,0))+E$74)*E$74),"preference","convert") -> convert | F79: =IF(F$73>((($C$23+$C$17*$C$18)-(K78-IF(F78="preference",F$73,0)))/(C$70+(L78-IF(F78="convert",F$74,0))+F$74)*F$74),"preference","convert") -> preference | G79: =IF(G$73>((($C$23+$C$17*$C$18)-(K78-IF(G78="preference",G$73,0)))/(C$70+(L78-IF(G78="convert",G$74,0))+G$74)*G$74),"preference","convert") -> convert | H79: =IF(H$73>((($C$23+$C$17*$C$18)-(K78-IF(H78="preference",H$73,0)))/(C$70+(L78-IF(H78="convert",H$74,0))+H$74)*H$74),"preference","convert") -> convert | I79: =IF(I$73>((($C$23+$C$17*$C$18)-(K78-IF(I78="preference",I$73,0)))/(C$70+(L78-IF(I78="convert",I$74,0))+I$74)*I$74),"preference","convert") -> convert | J79: =IF(J$73>((($C$23+$C$17*$C$18)-(K78-IF(J78="preference",J$73,0)))/(C$70+(L78-IF(J78="convert",J$74,0))+J$74)*J$74),"preference","convert") -> convert | K79: =IF(D79="preference",D73,0)+IF(E79="preference",E73,0)+IF(F79="preference",F73,0)+IF(G79="preference",G73,0)+IF(H79="preference",H73,0)+IF(I79="preference",I73,0)+IF(J79="preference",J73,0) -> 100000000 | L79: =IF(D79="convert",D74,0)+IF(E79="convert",E74,0)+IF(F79="convert",F74,0)+IF(G79="convert",G74,0)+IF(H79="convert",H74,0)+IF(I79="convert",I74,0)+IF(J79="convert",J74,0) -> 22316927
B80: Iter 5 | D80: =IF(D$73>((($C$23+$C$17*$C$18)-(K79-IF(D79="preference",D$73,0)))/(C$70+(L79-IF(D79="convert",D$74,0))+D$74)*D$74),"preference","convert") -> convert | E80: =IF(E$73>((($C$23+$C$17*$C$18)-(K79-IF(E79="preference",E$73,0)))/(C$70+(L79-IF(E79="convert",E$74,0))+E$74)*E$74),"preference","convert") -> convert | F80: =IF(F$73>((($C$23+$C$17*$C$18)-(K79-IF(F79="preference",F$73,0)))/(C$70+(L79-IF(F79="convert",F$74,0))+F$74)*F$74),"preference","convert") -> preference | G80: =IF(G$73>((($C$23+$C$17*$C$18)-(K79-IF(G79="preference",G$73,0)))/(C$70+(L79-IF(G79="convert",G$74,0))+G$74)*G$74),"preference","convert") -> convert | H80: =IF(H$73>((($C$23+$C$17*$C$18)-(K79-IF(H79="preference",H$73,0)))/(C$70+(L79-IF(H79="convert",H$74,0))+H$74)*H$74),"preference","convert") -> convert | I80: =IF(I$73>((($C$23+$C$17*$C$18)-(K79-IF(I79="preference",I$73,0)))/(C$70+(L79-IF(I79="convert",I$74,0))+I$74)*I$74),"preference","convert") -> convert | J80: =IF(J$73>((($C$23+$C$17*$C$18)-(K79-IF(J79="preference",J$73,0)))/(C$70+(L79-IF(J79="convert",J$74,0))+J$74)*J$74),"preference","convert") -> convert | K80: =IF(D80="preference",D73,0)+IF(E80="preference",E73,0)+IF(F80="preference",F73,0)+IF(G80="preference",G73,0)+IF(H80="preference",H73,0)+IF(I80="preference",I73,0)+IF(J80="preference",J73,0) -> 100000000 | L80: =IF(D80="convert",D74,0)+IF(E80="convert",E74,0)+IF(F80="convert",F74,0)+IF(G80="convert",G74,0)+IF(H80="convert",H74,0)+IF(I80="convert",I74,0)+IF(J80="convert",J74,0) -> 22316927
B81: PPS at $2B | C81: =(($C$23+$C$17*$C$18)-K80)/(C70+L80) -> 55.805338
B82: F election / our proceeds | C82: =D80 -> convert | D82: =IF(D80="preference",$C$24,C81*$C$24/C63) -> 14612268
B83: Our ownership % | C83: =($C$24/C63)/C64 -> 0.006993007
B84: Cell (11%, $1.8B)
B85: Pre-money | C85: =Assumptions!E72 -> 1800000000
B86: ESOP refresh | C86: =Assumptions!C71 -> 0.11
B87: Post-money | C87: =C85+$C$7 -> 1830000000
B88: Note A branch / β_NA | C88: =IF(C85>$C$22,"cap","discount") -> cap | D88: =IF(C88="cap",$C$20*C85/($D$20+$C$20),$C$20/(1-$E$20)) -> 8955223.9
B89: Note B branch / β_NB | C89: =IF(C85>$D$22,"cap","discount") -> discount | D89: =IF(C89="cap",$C$21*C85/($D$21+$C$21),$C$21/(1-$E$21)) -> 3529411.8
B90: K | C90: =(1-C86)*C87-$C$7-$C$12-$C$14-D88-D89 -> 1.5799075e+09
B91: F_PPS | C91: =C90/$C$15 -> 49.21932
B92: T_F | C92: =C87/C91 -> 37180522
B93: F_pri shares | C93: =$C$7/C91 -> 609516.76
B94: E_sh (with AD) | C94: =$C$11+$C$12/C91 -> 6102543
B95: D_sh (with AD) | C95: =$C$13+$C$14/C91 -> 1724951.8
B96: NA_sh / NB_sh | C96: =D88/C91 -> 181945.3 | D96: =D89/C91 -> 71707.854
B97: Opts (max) | C97: =MAX($C$19,C86*C92) -> 4394667
B98: Common-eq base (common+opts+notes) | C98: =$C$16+$C$17+C96+D96 -> 11753653
B99: $2B Waterfall — Iteration
B100: Class → | D100: F | E100: E | F100: D | G100: C | H100: B | I100: A | J100: Seed | K100: ΣPref | L100: ΣConvN
B101: S (pref $) | D101: =$C$7 | E101: =Assumptions!C53 -> 300000000 | F101: =Assumptions!C52 -> 100000000 | G101: =Assumptions!C51 -> 60000000 | H101: =Assumptions!C50 -> 30000000 | I101: =Assumptions!C49 -> 15000000 | J101: =Assumptions!C48 -> 5000000
B102: n (as-conv shares) | D102: =C93 -> 609516.76 | E102: =C94 -> 6102543 | F102: =C95 -> 1724951.8 | G102: =Assumptions!C43 -> 2400000 | H102: =Assumptions!C42 -> 3000000 | I102: =Assumptions!C41 -> 5000000 | J102: =Assumptions!C40 -> 5000000
B103: Iter 0 | D103: convert | E103: convert | F103: convert | G103: convert | H103: convert | I103: convert | J103: convert | K103: =IF(D103="preference",D101,0)+IF(E103="preference",E101,0)+IF(F103="preference",F101,0)+IF(G103="preference",G101,0)+IF(H103="preference",H101,0)+IF(I103="preference",I101,0)+IF(J103="preference",J101,0) -> 0 | L103: =IF(D103="convert",D102,0)+IF(E103="convert",E102,0)+IF(F103="convert",F102,0)+IF(G103="convert",G102,0)+IF(H103="convert",H102,0)+IF(I103="convert",I102,0)+IF(J103="convert",J102,0) -> 23837012
B104: Iter 1 | D104: =IF(D$101>((($C$23+$C$17*$C$18)-(K103-IF(D103="preference",D$101,0)))/(C$98+(L103-IF(D103="convert",D$102,0))+D$102)*D$102),"preference","convert") -> convert | E104: =IF(E$101>((($C$23+$C$17*$C$18)-(K103-IF(E103="preference",E$101,0)))/(C$98+(L103-IF(E103="convert",E$102,0))+E$102)*E$102),"preference","convert") -> convert | F104: =IF(F$101>((($C$23+$C$17*$C$18)-(K103-IF(F103="preference",F$101,0)))/(C$98+(L103-IF(F103="convert",F$102,0))+F$102)*F$102),"preference","convert") -> preference | G104: =IF(G$101>((($C$23+$C$17*$C$18)-(K103-IF(G103="preference",G$101,0)))/(C$98+(L103-IF(G103="convert",G$102,0))+G$102)*G$102),"preference","convert") -> convert | H104: =IF(H$101>((($C$23+$C$17*$C$18)-(K103-IF(H103="preference",H$101,0)))/(C$98+(L103-IF(H103="convert",H$102,0))+H$102)*H$102),"preference","convert") -> convert | I104: =IF(I$101>((($C$23+$C$17*$C$18)-(K103-IF(I103="preference",I$101,0)))/(C$98+(L103-IF(I103="convert",I$102,0))+I$102)*I$102),"preference","convert") -> convert | J104: =IF(J$101>((($C$23+$C$17*$C$18)-(K103-IF(J103="preference",J$101,0)))/(C$98+(L103-IF(J103="convert",J$102,0))+J$102)*J$102),"preference","convert") -> convert | K104: =IF(D104="preference",D101,0)+IF(E104="preference",E101,0)+IF(F104="preference",F101,0)+IF(G104="preference",G101,0)+IF(H104="preference",H101,0)+IF(I104="preference",I101,0)+IF(J104="preference",J101,0) -> 100000000 | L104: =IF(D104="convert",D102,0)+IF(E104="convert",E102,0)+IF(F104="convert",F102,0)+IF(G104="convert",G102,0)+IF(H104="convert",H102,0)+IF(I104="convert",I102,0)+IF(J104="convert",J102,0) -> 22112060
B105: Iter 2 | D105: =IF(D$101>((($C$23+$C$17*$C$18)-(K104-IF(D104="preference",D$101,0)))/(C$98+(L104-IF(D104="convert",D$102,0))+D$102)*D$102),"preference","convert") -> convert | E105: =IF(E$101>((($C$23+$C$17*$C$18)-(K104-IF(E104="preference",E$101,0)))/(C$98+(L104-IF(E104="convert",E$102,0))+E$102)*E$102),"preference","convert") -> convert | F105: =IF(F$101>((($C$23+$C$17*$C$18)-(K104-IF(F104="preference",F$101,0)))/(C$98+(L104-IF(F104="convert",F$102,0))+F$102)*F$102),"preference","convert") -> preference | G105: =IF(G$101>((($C$23+$C$17*$C$18)-(K104-IF(G104="preference",G$101,0)))/(C$98+(L104-IF(G104="convert",G$102,0))+G$102)*G$102),"preference","convert") -> convert | H105: =IF(H$101>((($C$23+$C$17*$C$18)-(K104-IF(H104="preference",H$101,0)))/(C$98+(L104-IF(H104="convert",H$102,0))+H$102)*H$102),"preference","convert") -> convert | I105: =IF(I$101>((($C$23+$C$17*$C$18)-(K104-IF(I104="preference",I$101,0)))/(C$98+(L104-IF(I104="convert",I$102,0))+I$102)*I$102),"preference","convert") -> convert | J105: =IF(J$101>((($C$23+$C$17*$C$18)-(K104-IF(J104="preference",J$101,0)))/(C$98+(L104-IF(J104="convert",J$102,0))+J$102)*J$102),"preference","convert") -> convert | K105: =IF(D105="preference",D101,0)+IF(E105="preference",E101,0)+IF(F105="preference",F101,0)+IF(G105="preference",G101,0)+IF(H105="preference",H101,0)+IF(I105="preference",I101,0)+IF(J105="preference",J101,0) -> 100000000 | L105: =IF(D105="convert",D102,0)+IF(E105="convert",E102,0)+IF(F105="convert",F102,0)+IF(G105="convert",G102,0)+IF(H105="convert",H102,0)+IF(I105="convert",I102,0)+IF(J105="convert",J102,0) -> 22112060
...

Sheet Waterfall
B2: Waterfall Analysis
B3: Per-class elections (Nash equilibrium) and payoffs at five exits
B5: Class Constants
B6: Class | C6: Pref ($) | D6: As-Conv Shares
B7: Series F | C7: ='Pro-Forma'!C7 -> 30000000 | D7: ='Pro-Forma'!C7/'Pro-Forma'!C49 -> 804294.71
B8: Series E | C8: =Assumptions!C53 -> 300000000 | D8: ='Pro-Forma'!G59 -> 6134472.1
B9: Series D | C9: =Assumptions!C52 -> 100000000 | D9: ='Pro-Forma'!G58 -> 1733976.9
B10: Series C | C10: =Assumptions!C51 -> 60000000 | D10: ='Pro-Forma'!G57 -> 2400000
B11: Series B | C11: =Assumptions!C50 -> 30000000 | D11: ='Pro-Forma'!G56 -> 3000000
B12: Series A | C12: =Assumptions!C49 -> 15000000 | D12: ='Pro-Forma'!G55 -> 5000000
B13: Seed | C13: =Assumptions!C48 -> 5000000 | D13: ='Pro-Forma'!G54 -> 5000000
B15: Common + RSAs | D15: =Assumptions!C28 -> 9000000
B16: Notes (A + B common-eq post-conv) | D16: ='Pro-Forma'!G63+'Pro-Forma'!G64 -> 281358
B17: Options issued (ITM at exit) | D17: =Assumptions!C18 -> 2500000
B18: Option strike | C18: =Assumptions!C14 -> 1
B19: Common-equivalent base (always in pool) | D19: =D15+D16+D17 -> 11781358
B21: Exit Scenarios ($)
B22: Exit value | D22: =Assumptions!C64 -> 700000000 | E22: =Assumptions!C65 -> 1200000000 | F22: =Assumptions!C66 -> 2000000000 | G22: =Assumptions!C67 -> 4000000000 | H22: =Assumptions!C68 -> 8000000000
B23: Effective exit (+ options strike cash) | D23: =D22+$D$17*$C$18 -> 702500000 | E23: =E22+$D$17*$C$18 -> 1202500000 | F23: =F22+$D$17*$C$18 -> 2002500000 | G23: =G22+$D$17*$C$18 -> 4002500000 | H23: =H22+$D$17*$C$18 -> 8002500000
B25: Election Decisions (Nash Equilibrium) — 35 cells
B26: Class | D26: $700M | E26: $1.2B | F26: $2.0B | G26: $4.0B | H26: $8.0B
B27: Series F | D27: =D43 -> preference | E27: =D58 -> preference | F27: =D73 -> convert | G27: =D88 -> convert | H27: =D103 -> convert
B28: Series E | D28: =E43 -> preference | E28: =E58 -> preference | F28: =E73 -> convert | G28: =E88 -> convert | H28: =E103 -> convert
B29: Series D | D29: =F43 -> preference | E29: =F58 -> preference | F29: =F73 -> preference | G29: =F88 -> convert | H29: =F103 -> convert
B30: Series C | D30: =G43 -> preference | E30: =G58 -> convert | F30: =G73 -> convert | G30: =G88 -> convert | H30: =G103 -> convert
B31: Series B | D31: =H43 -> preference | E31: =H58 -> convert | F31: =H73 -> convert | G31: =H88 -> convert | H31: =H103 -> convert
B32: Series A | D32: =I43 -> convert | E32: =I58 -> convert | F32: =I73 -> convert | G32: =I88 -> convert | H32: =I103 -> convert
B33: Seed | D33: =J43 -> convert | E33: =J58 -> convert | F33: =J73 -> convert | G33: =J88 -> convert | H33: =J103 -> convert
B36: Exit 1: $700M — Iteration & Payoffs
B37: Iter / Class | D37: F | E37: E | F37: D | G37: C | H37: B | I37: A | J37: Seed | K37: ΣPref | L37: ΣConvN
B38: Iter 0 (init) | D38: convert | E38: convert | F38: convert | G38: convert | H38: convert | I38: convert | J38: convert | K38: =IF(D38="preference",$C$7,0)+IF(E38="preference",$C$8,0)+IF(F38="preference",$C$9,0)+IF(G38="preference",$C$10,0)+IF(H38="preference",$C$11,0)+IF(I38="preference",$C$12,0)+IF(J38="preference",$C$13,0) -> 0 | L38: =IF(D38="convert",$D$7,0)+IF(E38="convert",$D$8,0)+IF(F38="convert",$D$9,0)+IF(G38="convert",$D$10,0)+IF(H38="convert",$D$11,0)+IF(I38="convert",$D$12,0)+IF(J38="convert",$D$13,0) -> 24072744
B39: Iter 1 | D39: =IF($C$7>((D$23-(K38-IF(D38="preference",$C$7,0)))/($D$19+(L38-IF(D38="convert",$D$7,0))+$D$7)*$D$7),"preference","convert") -> preference | E39: =IF($C$8>((D$23-(K38-IF(E38="preference",$C$8,0)))/($D$19+(L38-IF(E38="convert",$D$8,0))+$D$8)*$D$8),"preference","convert") -> preference | F39: =IF($C$9>((D$23-(K38-IF(F38="preference",$C$9,0)))/($D$19+(L38-IF(F38="convert",$D$9,0))+$D$9)*$D$9),"preference","convert") -> preference | G39: =IF($C$10>((D$23-(K38-IF(G38="preference",$C$10,0)))/($D$19+(L38-IF(G38="convert",$D$10,0))+$D$10)*$D$10),"preference","convert") -> preference | H39: =IF($C$11>((D$23-(K38-IF(H38="preference",$C$11,0)))/($D$19+(L38-IF(H38="convert",$D$11,0))+$D$11)*$D$11),"preference","convert") -> convert | I39: =IF($C$12>((D$23-(K38-IF(I38="preference",$C$12,0)))/($D$19+(L38-IF(I38="convert",$D$12,0))+$D$12)*$D$12),"preference","convert") -> convert | J39: =IF($C$13>((D$23-(K38-IF(J38="preference",$C$13,0)))/($D$19+(L38-IF(J38="convert",$D$13,0))+$D$13)*$D$13),"preference","convert") -> convert | K39: =IF(D39="preference",$C$7,0)+IF(E39="preference",$C$8,0)+IF(F39="preference",$C$9,0)+IF(G39="preference",$C$10,0)+IF(H39="preference",$C$11,0)+IF(I39="preference",$C$12,0)+IF(J39="preference",$C$13,0) -> 490000000 | L39: =IF(D39="convert",$D$7,0)+IF(E39="convert",$D$8,0)+IF(F39="convert",$D$9,0)+IF(G39="convert",$D$10,0)+IF(H39="convert",$D$11,0)+IF(I39="convert",$D$12,0)+IF(J39="convert",$D$13,0) -> 13000000
B40: Iter 2 | D40: =IF($C$7>((D$23-(K39-IF(D39="preference",$C$7,0)))/($D$19+(L39-IF(D39="convert",$D$7,0))+$D$7)*$D$7),"preference","convert") -> preference | E40: =IF($C$8>((D$23-(K39-IF(E39="preference",$C$8,0)))/($D$19+(L39-IF(E39="convert",$D$8,0))+$D$8)*$D$8),"preference","convert") -> preference | F40: =IF($C$9>((D$23-(K39-IF(F39="preference",$C$9,0)))/($D$19+(L39-IF(F39="convert",$D$9,0))+$D$9)*$D$9),"preference","convert") -> preference | G40: =IF($C$10>((D$23-(K39-IF(G39="preference",$C$10,0)))/($D$19+(L39-IF(G39="convert",$D$10,0))+$D$10)*$D$10),"preference","convert") -> preference | H40: =IF($C$11>((D$23-(K39-IF(H39="preference",$C$11,0)))/($D$19+(L39-IF(H39="convert",$D$11,0))+$D$11)*$D$11),"preference","convert") -> preference | I40: =IF($C$12>((D$23-(K39-IF(I39="preference",$C$12,0)))/($D$19+(L39-IF(I39="convert",$D$12,0))+$D$12)*$D$12),"preference","convert") -> convert | J40: =IF($C$13>((D$23-(K39-IF(J39="preference",$C$13,0)))/($D$19+(L39-IF(J39="convert",$D$13,0))+$D$13)*$D$13),"preference","convert") -> convert | K40: =IF(D40="preference",$C$7,0)+IF(E40="preference",$C$8,0)+IF(F40="preference",$C$9,0)+IF(G40="preference",$C$10,0)+IF(H40="preference",$C$11,0)+IF(I40="preference",$C$12,0)+IF(J40="preference",$C$13,0) -> 520000000 | L40: =IF(D40="convert",$D$7,0)+IF(E40="convert",$D$8,0)+IF(F40="convert",$D$9,0)+IF(G40="convert",$D$10,0)+IF(H40="convert",$D$11,0)+IF(I40="convert",$D$12,0)+IF(J40="convert",$D$13,0) -> 10000000
B41: Iter 3 | D41: =IF($C$7>((D$23-(K40-IF(D40="preference",$C$7,0)))/($D$19+(L40-IF(D40="convert",$D$7,0))+$D$7)*$D$7),"preference","convert") -> preference | E41: =IF($C$8>((D$23-(K40-IF(E40="preference",$C$8,0)))/($D$19+(L40-IF(E40="convert",$D$8,0))+$D$8)*$D$8),"preference","convert") -> preference | F41: =IF($C$9>((D$23-(K40-IF(F40="preference",$C$9,0)))/($D$19+(L40-IF(F40="convert",$D$9,0))+$D$9)*$D$9),"preference","convert") -> preference | G41: =IF($C$10>((D$23-(K40-IF(G40="preference",$C$10,0)))/($D$19+(L40-IF(G40="convert",$D$10,0))+$D$10)*$D$10),"preference","convert") -> preference | H41: =IF($C$11>((D$23-(K40-IF(H40="preference",$C$11,0)))/($D$19+(L40-IF(H40="convert",$D$11,0))+$D$11)*$D$11),"preference","convert") -> preference | I41: =IF($C$12>((D$23-(K40-IF(I40="preference",$C$12,0)))/($D$19+(L40-IF(I40="convert",$D$12,0))+$D$12)*$D$12),"preference","convert") -> convert | J41: =IF($C$13>((D$23-(K40-IF(J40="preference",$C$13,0)))/($D$19+(L40-IF(J40="convert",$D$13,0))+$D$13)*$D$13),"preference","convert") -> convert | K41: =IF(D41="preference",$C$7,0)+IF(E41="preference",$C$8,0)+IF(F41="preference",$C$9,0)+IF(G41="preference",$C$10,0)+IF(H41="preference",$C$11,0)+IF(I41="preference",$C$12,0)+IF(J41="preference",$C$13,0) -> 520000000 | L41: =IF(D41="convert",$D$7,0)+IF(E41="convert",$D$8,0)+IF(F41="convert",$D$9,0)+IF(G41="convert",$D$10,0)+IF(H41="convert",$D$11,0)+IF(I41="convert",$D$12,0)+IF(J41="convert",$D$13,0) -> 10000000
B42: Iter 4 | D42: =IF($C$7>((D$23-(K41-IF(D41="preference",$C$7,0)))/($D$19+(L41-IF(D41="convert",$D$7,0))+$D$7)*$D$7),"preference","convert") -> preference | E42: =IF($C$8>((D$23-(K41-IF(E41="preference",$C$8,0)))/($D$19+(L41-IF(E41="convert",$D$8,0))+$D$8)*$D$8),"preference","convert") -> preference | F42: =IF($C$9>((D$23-(K41-IF(F41="preference",$C$9,0)))/($D$19+(L41-IF(F41="convert",$D$9,0))+$D$9)*$D$9),"preference","convert") -> preference | G42: =IF($C$10>((D$23-(K41-IF(G41="preference",$C$10,0)))/($D$19+(L41-IF(G41="convert",$D$10,0))+$D$10)*$D$10),"preference","convert") -> preference | H42: =IF($C$11>((D$23-(K41-IF(H41="preference",$C$11,0)))/($D$19+(L41-IF(H41="convert",$D$11,0))+$D$11)*$D$11),"preference","convert") -> preference | I42: =IF($C$12>((D$23-(K41-IF(I41="preference",$C$12,0)))/($D$19+(L41-IF(I41="convert",$D$12,0))+$D$12)*$D$12),"preference","convert") -> convert | J42: =IF($C$13>((D$23-(K41-IF(J41="preference",$C$13,0)))/($D$19+(L41-IF(J41="convert",$D$13,0))+$D$13)*$D$13),"preference","convert") -> convert | K42: =IF(D42="preference",$C$7,0)+IF(E42="preference",$C$8,0)+IF(F42="preference",$C$9,0)+IF(G42="preference",$C$10,0)+IF(H42="preference",$C$11,0)+IF(I42="preference",$C$12,0)+IF(J42="preference",$C$13,0) -> 520000000 | L42: =IF(D42="convert",$D$7,0)+IF(E42="convert",$D$8,0)+IF(F42="convert",$D$9,0)+IF(G42="convert",$D$10,0)+IF(H42="convert",$D$11,0)+IF(I42="convert",$D$12,0)+IF(J42="convert",$D$13,0) -> 10000000
B43: Iter 5 | D43: =IF($C$7>((D$23-(K42-IF(D42="preference",$C$7,0)))/($D$19+(L42-IF(D42="convert",$D$7,0))+$D$7)*$D$7),"preference","convert") -> preference | E43: =IF($C$8>((D$23-(K42-IF(E42="preference",$C$8,0)))/($D$19+(L42-IF(E42="convert",$D$8,0))+$D$8)*$D$8),"preference","convert") -> preference | F43: =IF($C$9>((D$23-(K42-IF(F42="preference",$C$9,0)))/($D$19+(L42-IF(F42="convert",$D$9,0))+$D$9)*$D$9),"preference","convert") -> preference | G43: =IF($C$10>((D$23-(K42-IF(G42="preference",$C$10,0)))/($D$19+(L42-IF(G42="convert",$D$10,0))+$D$10)*$D$10),"preference","convert") -> preference | H43: =IF($C$11>((D$23-(K42-IF(H42="preference",$C$11,0)))/($D$19+(L42-IF(H42="convert",$D$11,0))+$D$11)*$D$11),"preference","convert") -> preference | I43: =IF($C$12>((D$23-(K42-IF(I42="preference",$C$12,0)))/($D$19+(L42-IF(I42="convert",$D$12,0))+$D$12)*$D$12),"preference","convert") -> convert | J43: =IF($C$13>((D$23-(K42-IF(J42="preference",$C$13,0)))/($D$19+(L42-IF(J42="convert",$D$13,0))+$D$13)*$D$13),"preference","convert") -> convert | K43: =IF(D43="preference",$C$7,0)+IF(E43="preference",$C$8,0)+IF(F43="preference",$C$9,0)+IF(G43="preference",$C$10,0)+IF(H43="preference",$C$11,0)+IF(I43="preference",$C$12,0)+IF(J43="preference",$C$13,0) -> 520000000 | L43: =IF(D43="convert",$D$7,0)+IF(E43="convert",$D$8,0)+IF(F43="convert",$D$9,0)+IF(G43="convert",$D$10,0)+IF(H43="convert",$D$11,0)+IF(I43="convert",$D$12,0)+IF(J43="convert",$D$13,0) -> 10000000
B44: PPS (post conversions) | C44: =(D$23-K43)/($D$19+L43) -> 8.3787246
B45: Class payoff ($) | D45: =IF(D43="preference",$C$7,$C$44*$D$7) -> 30000000 | E45: =IF(E43="preference",$C$8,$C$44*$D$8) -> 300000000 | F45: =IF(F43="preference",$C$9,$C$44*$D$9) -> 100000000 | G45: =IF(G43="preference",$C$10,$C$44*$D$10) -> 60000000 | H45: =IF(H43="preference",$C$11,$C$44*$D$11) -> 30000000 | I45: =IF(I43="preference",$C$12,$C$44*$D$12) -> 41893623 | J45: =IF(J43="preference",$C$13,$C$44*$D$13) -> 41893623
B46: Common + RSA payoff | C46: =$C$44*$D$15 -> 75408521
B47: Notes (A+B common-eq) payoff | C47: =$C$44*$D$16 -> 2357421.2
B48: Options issued (net of strike) | C48: =MAX(0,($C$44-$C$18)*$D$17) -> 18446811
B49: Total proceeds | C49: =C46+C47+C48+D45+E45+F45+G45+H45+I45+J45 -> 700000000
B50: Check | C50: =ROUND(C49-D$22,0) -> 0
B51: Exit 2: $1.2B — Iteration & Payoffs
B52: Iter / Class | D52: F | E52: E | F52: D | G52: C | H52: B | I52: A | J52: Seed | K52: ΣPref | L52: ΣConvN
B53: Iter 0 (init) | D53: convert | E53: convert | F53: convert | G53: convert | H53: convert | I53: convert | J53: convert | K53: =IF(D53="preference",$C$7,0)+IF(E53="preference",$C$8,0)+IF(F53="preference",$C$9,0)+IF(G53="preference",$C$10,0)+IF(H53="preference",$C$11,0)+IF(I53="preference",$C$12,0)+IF(J53="preference",$C$13,0) -> 0 | L53: =IF(D53="convert",$D$7,0)+IF(E53="convert",$D$8,0)+IF(F53="convert",$D$9,0)+IF(G53="convert",$D$10,0)+IF(H53="convert",$D$11,0)+IF(I53="convert",$D$12,0)+IF(J53="convert",$D$13,0) -> 24072744
B54: Iter 1 | D54: =IF($C$7>((E$23-(K53-IF(D53="preference",$C$7,0)))/($D$19+(L53-IF(D53="convert",$D$7,0))+$D$7)*$D$7),"preference","convert") -> preference | E54: =IF($C$8>((E$23-(K53-IF(E53="preference",$C$8,0)))/($D$19+(L53-IF(E53="convert",$D$8,0))+$D$8)*$D$8),"preference","convert") -> preference | F54: =IF($C$9>((E$23-(K53-IF(F53="preference",$C$9,0)))/($D$19+(L53-IF(F53="convert",$D$9,0))+$D$9)*$D$9),"preference","convert") -> preference | G54: =IF($C$10>((E$23-(K53-IF(G53="preference",$C$10,0)))/($D$19+(L53-IF(G53="convert",$D$10,0))+$D$10)*$D$10),"preference","convert") -> convert | H54: =IF($C$11>((E$23-(K53-IF(H53="preference",$C$11,0)))/($D$19+(L53-IF(H53="convert",$D$11,0))+$D$11)*$D$11),"preference","convert") -> convert | I54: =IF($C$12>((E$23-(K53-IF(I53="preference",$C$12,0)))/($D$19+(L53-IF(I53="convert",$D$12,0))+$D$12)*$D$12),"preference","convert") -> convert | J54: =IF($C$13>((E$23-(K53-IF(J53="preference",$C$13,0)))/($D$19+(L53-IF(J53="convert",$D$13,0))+$D$13)*$D$13),"preference","convert") -> convert | K54: =IF(D54="preference",$C$7,0)+IF(E54="preference",$C$8,0)+IF(F54="preference",$C$9,0)+IF(G54="preference",$C$10,0)+IF(H54="preference",$C$11,0)+IF(I54="preference",$C$12,0)+IF(J54="preference",$C$13,0) -> 430000000 | L54: =IF(D54="convert",$D$7,0)+IF(E54="convert",$D$8,0)+IF(F54="convert",$D$9,0)+IF(G54="convert",$D$10,0)+IF(H54="convert",$D$11,0)+IF(I54="convert",$D$12,0)+IF(J54="convert",$D$13,0) -> 15400000
B55: Iter 2 | D55: =IF($C$7>((E$23-(K54-IF(D54="preference",$C$7,0)))/($D$19+(L54-IF(D54="convert",$D$7,0))+$D$7)*$D$7),"preference","convert") -> preference | E55: =IF($C$8>((E$23-(K54-IF(E54="preference",$C$8,0)))/($D$19+(L54-IF(E54="convert",$D$8,0))+$D$8)*$D$8),"preference","convert") -> preference | F55: =IF($C$9>((E$23-(K54-IF(F54="preference",$C$9,0)))/($D$19+(L54-IF(F54="convert",$D$9,0))+$D$9)*$D$9),"preference","convert") -> preference | G55: =IF($C$10>((E$23-(K54-IF(G54="preference",$C$10,0)))/($D$19+(L54-IF(G54="convert",$D$10,0))+$D$10)*$D$10),"preference","convert") -> convert | H55: =IF($C$11>((E$23-(K54-IF(H54="preference",$C$11,0)))/($D$19+(L54-IF(H54="convert",$D$11,0))+$D$11)*$D$11),"preference","convert") -> convert | I55: =IF($C$12>((E$23-(K54-IF(I54="preference",$C$12,0)))/($D$19+(L54-IF(I54="convert",$D$12,0))+$D$12)*$D$12),"preference","convert") -> convert | J55: =IF($C$13>((E$23-(K54-IF(J54="preference",$C$13,0)))/($D$19+(L54-IF(J54="convert",$D$13,0))+$D$13)*$D$13),"preference","convert") -> convert | K55: =IF(D55="preference",$C$7,0)+IF(E55="preference",$C$8,0)+IF(F55="preference",$C$9,0)+IF(G55="preference",$C$10,0)+IF(H55="preference",$C$11,0)+IF(I55="preference",$C$12,0)+IF(J55="preference",$C$13,0) -> 430000000 | L55: =IF(D55="convert",$D$7,0)+IF(E55="convert",$D$8,0)+IF(F55="convert",$D$9,0)+IF(G55="convert",$D$10,0)+IF(H55="convert",$D$11,0)+IF(I55="convert",$D$12,0)+IF(J55="convert",$D$13,0) -> 15400000
B56: Iter 3 | D56: =IF($C$7>((E$23-(K55-IF(D55="preference",$C$7,0)))/($D$19+(L55-IF(D55="convert",$D$7,0))+$D$7)*$D$7),"preference","convert") -> preference | E56: =IF($C$8>((E$23-(K55-IF(E55="preference",$C$8,0)))/($D$19+(L55-IF(E55="convert",$D$8,0))+$D$8)*$D$8),"preference","convert") -> preference | F56: =IF($C$9>((E$23-(K55-IF(F55="preference",$C$9,0)))/($D$19+(L55-IF(F55="convert",$D$9,0))+$D$9)*$D$9),"preference","convert") -> preference | G56: =IF($C$10>((E$23-(K55-IF(G55="preference",$C$10,0)))/($D$19+(L55-IF(G55="convert",$D$10,0))+$D$10)*$D$10),"preference","convert") -> convert | H56: =IF($C$11>((E$23-(K55-IF(H55="preference",$C$11,0)))/($D$19+(L55-IF(H55="convert",$D$11,0))+$D$11)*$D$11),"preference","convert") -> convert | I56: =IF($C$12>((E$23-(K55-IF(I55="preference",$C$12,0)))/($D$19+(L55-IF(I55="convert",$D$12,0))+$D$12)*$D$12),"preference","convert") -> convert | J56: =IF($C$13>((E$23-(K55-IF(J55="preference",$C$13,0)))/($D$19+(L55-IF(J55="convert",$D$13,0))+$D$13)*$D$13),"preference","convert") -> convert | K56: =IF(D56="preference",$C$7,0)+IF(E56="preference",$C$8,0)+IF(F56="preference",$C$9,0)+IF(G56="preference",$C$10,0)+IF(H56="preference",$C$11,0)+IF(I56="preference",$C$12,0)+IF(J56="preference",$C$13,0) -> 430000000 | L56: =IF(D56="convert",$D$7,0)+IF(E56="convert",$D$8,0)+IF(F56="convert",$D$9,0)+IF(G56="convert",$D$10,0)+IF(H56="convert",$D$11,0)+IF(I56="convert",$D$12,0)+IF(J56="convert",$D$13,0) -> 15400000
B57: Iter 4 | D57: =IF($C$7>((E$23-(K56-IF(D56="preference",$C$7,0)))/($D$19+(L56-IF(D56="convert",$D$7,0))+$D$7)*$D$7),"preference","convert") -> preference | E57: =IF($C$8>((E$23-(K56-IF(E56="preference",$C$8,0)))/($D$19+(L56-IF(E56="convert",$D$8,0))+$D$8)*$D$8),"preference","convert") -> preference | F57: =IF($C$9>((E$23-(K56-IF(F56="preference",$C$9,0)))/($D$19+(L56-IF(F56="convert",$D$9,0))+$D$9)*$D$9),"preference","convert") -> preference | G57: =IF($C$10>((E$23-(K56-IF(G56="preference",$C$10,0)))/($D$19+(L56-IF(G56="convert",$D$10,0))+$D$10)*$D$10),"preference","convert") -> convert | H57: =IF($C$11>((E$23-(K56-IF(H56="preference",$C$11,0)))/($D$19+(L56-IF(H56="convert",$D$11,0))+$D$11)*$D$11),"preference","convert") -> convert | I57: =IF($C$12>((E$23-(K56-IF(I56="preference",$C$12,0)))/($D$19+(L56-IF(I56="convert",$D$12,0))+$D$12)*$D$12),"preference","convert") -> convert | J57: =IF($C$13>((E$23-(K56-IF(J56="preference",$C$13,0)))/($D$19+(L56-IF(J56="convert",$D$13,0))+$D$13)*$D$13),"preference","convert") -> convert | K57: =IF(D57="preference",$C$7,0)+IF(E57="preference",$C$8,0)+IF(F57="preference",$C$9,0)+IF(G57="preference",$C$10,0)+IF(H57="preference",$C$11,0)+IF(I57="preference",$C$12,0)+IF(J57="preference",$C$13,0) -> 430000000 | L57: =IF(D57="convert",$D$7,0)+IF(E57="convert",$D$8,0)+IF(F57="convert",$D$9,0)+IF(G57="convert",$D$10,0)+IF(H57="convert",$D$11,0)+IF(I57="convert",$D$12,0)+IF(J57="convert",$D$13,0) -> 15400000
B58: Iter 5 | D58: =IF($C$7>((E$23-(K57-IF(D57="preference",$C$7,0)))/($D$19+(L57-IF(D57="convert",$D$7,0))+$D$7)*$D$7),"preference","convert") -> preference | E58: =IF($C$8>((E$23-(K57-IF(E57="preference",$C$8,0)))/($D$19+(L57-IF(E57="convert",$D$8,0))+$D$8)*$D$8),"preference","convert") -> preference | F58: =IF($C$9>((E$23-(K57-IF(F57="preference",$C$9,0)))/($D$19+(L57-IF(F57="convert",$D$9,0))+$D$9)*$D$9),"preference","convert") -> preference | G58: =IF($C$10>((E$23-(K57-IF(G57="preference",$C$10,0)))/($D$19+(L57-IF(G57="convert",$D$10,0))+$D$10)*$D$10),"preference","convert") -> convert | H58: =IF($C$11>((E$23-(K57-IF(H57="preference",$C$11,0)))/($D$19+(L57-IF(H57="convert",$D$11,0))+$D$11)*$D$11),"preference","convert") -> convert | I58: =IF($C$12>((E$23-(K57-IF(I57="preference",$C$12,0)))/($D$19+(L57-IF(I57="convert",$D$12,0))+$D$12)*$D$12),"preference","convert") -> convert | J58: =IF($C$13>((E$23-(K57-IF(J57="preference",$C$13,0)))/($D$19+(L57-IF(J57="convert",$D$13,0))+$D$13)*$D$13),"preference","convert") -> convert | K58: =IF(D58="preference",$C$7,0)+IF(E58="preference",$C$8,0)+IF(F58="preference",$C$9,0)+IF(G58="preference",$C$10,0)+IF(H58="preference",$C$11,0)+IF(I58="preference",$C$12,0)+IF(J58="preference",$C$13,0) -> 430000000 | L58: =IF(D58="convert",$D$7,0)+IF(E58="convert",$D$8,0)+IF(F58="convert",$D$9,0)+IF(G58="convert",$D$10,0)+IF(H58="convert",$D$11,0)+IF(I58="convert",$D$12,0)+IF(J58="convert",$D$13,0) -> 15400000
B59: PPS (post conversions) | C59: =(E$23-K58)/($D$19+L58) -> 28.420214
B60: Class payoff ($) | D60: =IF(D58="preference",$C$7,$C$59*$D$7) -> 30000000 | E60: =IF(E58="preference",$C$8,$C$59*$D$8) -> 300000000 | F60: =IF(F58="preference",$C$9,$C$59*$D$9) -> 100000000 | G60: =IF(G58="preference",$C$10,$C$59*$D$10) -> 68208513 | H60: =IF(H58="preference",$C$11,$C$59*$D$11) -> 85260641 | I60: =IF(I58="preference",$C$12,$C$59*$D$12) -> 1.4210107e+08 | J60: =IF(J58="preference",$C$13,$C$59*$D$13) -> 1.4210107e+08
B61: Common + RSA payoff | C61: =$C$59*$D$15 -> 2.5578192e+08
B62: Notes (A+B common-eq) payoff | C62: =$C$59*$D$16 -> 7996254.4
B63: Options issued (net of strike) | C63: =MAX(0,($C$59-$C$18)*$D$17) -> 68550534
B64: Total proceeds | C64: =C61+C62+C63+D60+E60+F60+G60+H60+I60+J60 -> 1200000000
B65: Check | C65: =ROUND(C64-E$22,0) -> 0
B66: Exit 3: $2.0B — Iteration & Payoffs
B67: Iter / Class | D67: F | E67: E | F67: D | G67: C | H67: B | I67: A | J67: Seed | K67: ΣPref | L67: ΣConvN
B68: Iter 0 (init) | D68: convert | E68: convert | F68: convert | G68: convert | H68: convert | I68: convert | J68: convert | K68: =IF(D68="preference",$C$7,0)+IF(E68="preference",$C$8,0)+IF(F68="preference",$C$9,0)+IF(G68="preference",$C$10,0)+IF(H68="preference",$C$11,0)+IF(I68="preference",$C$12,0)+IF(J68="preference",$C$13,0) -> 0 | L68: =IF(D68="convert",$D$7,0)+IF(E68="convert",$D$8,0)+IF(F68="convert",$D$9,0)+IF(G68="convert",$D$10,0)+IF(H68="convert",$D$11,0)+IF(I68="convert",$D$12,0)+IF(J68="convert",$D$13,0) -> 24072744
B69: Iter 1 | D69: =IF($C$7>((F$23-(K68-IF(D68="preference",$C$7,0)))/($D$19+(L68-IF(D68="convert",$D$7,0))+$D$7)*$D$7),"preference","convert") -> convert | E69: =IF($C$8>((F$23-(K68-IF(E68="preference",$C$8,0)))/($D$19+(L68-IF(E68="convert",$D$8,0))+$D$8)*$D$8),"preference","convert") -> convert | F69: =IF($C$9>((F$23-(K68-IF(F68="preference",$C$9,0)))/($D$19+(L68-IF(F68="convert",$D$9,0))+$D$9)*$D$9),"preference","convert") -> preference | G69: =IF($C$10>((F$23-(K68-IF(G68="preference",$C$10,0)))/($D$19+(L68-IF(G68="convert",$D$10,0))+$D$10)*$D$10),"preference","convert") -> convert | H69: =IF($C$11>((F$23-(K68-IF(H68="preference",$C$11,0)))/($D$19+(L68-IF(H68="convert",$D$11,0))+$D$11)*$D$11),"preference","convert") -> convert | I69: =IF($C$12>((F$23-(K68-IF(I68="preference",$C$12,0)))/($D$19+(L68-IF(I68="convert",$D$12,0))+$D$12)*$D$12),"preference","convert") -> convert | J69: =IF($C$13>((F$23-(K68-IF(J68="preference",$C$13,0)))/($D$19+(L68-IF(J68="convert",$D$13,0))+$D$13)*$D$13),"preference","convert") -> convert | K69: =IF(D69="preference",$C$7,0)+IF(E69="preference",$C$8,0)+IF(F69="preference",$C$9,0)+IF(G69="preference",$C$10,0)+IF(H69="preference",$C$11,0)+IF(I69="preference",$C$12,0)+IF(J69="preference",$C$13,0) -> 100000000 | L69: =IF(D69="convert",$D$7,0)+IF(E69="convert",$D$8,0)+IF(F69="convert",$D$9,0)+IF(G69="convert",$D$10,0)+IF(H69="convert",$D$11,0)+IF(I69="convert",$D$12,0)+IF(J69="convert",$D$13,0) -> 22338767
B70: Iter 2 | D70: =IF($C$7>((F$23-(K69-IF(D69="preference",$C$7,0)))/($D$19+(L69-IF(D69="convert",$D$7,0))+$D$7)*$D$7),"preference","convert") -> convert | E70: =IF($C$8>((F$23-(K69-IF(E69="preference",$C$8,0)))/($D$19+(L69-IF(E69="convert",$D$8,0))+$D$8)*$D$8),"preference","convert") -> convert | F70: =IF($C$9>((F$23-(K69-IF(F69="preference",$C$9,0)))/($D$19+(L69-IF(F69="convert",$D$9,0))+$D$9)*$D$9),"preference","convert") -> preference | G70: =IF($C$10>((F$23-(K69-IF(G69="preference",$C$10,0)))/($D$19+(L69-IF(G69="convert",$D$10,0))+$D$10)*$D$10),"preference","convert") -> convert | H70: =IF($C$11>((F$23-(K69-IF(H69="preference",$C$11,0)))/($D$19+(L69-IF(H69="convert",$D$11,0))+$D$11)*$D$11),"preference","convert") -> convert | I70: =IF($C$12>((F$23-(K69-IF(I69="preference",$C$12,0)))/($D$19+(L69-IF(I69="convert",$D$12,0))+$D$12)*$D$12),"preference","convert") -> convert | J70: =IF($C$13>((F$23-(K69-IF(J69="preference",$C$13,0)))/($D$19+(L69-IF(J69="convert",$D$13,0))+$D$13)*$D$13),"preference","convert") -> convert | K70: =IF(D70="preference",$C$7,0)+IF(E70="preference",$C$8,0)+IF(F70="preference",$C$9,0)+IF(G70="preference",$C$10,0)+IF(H70="preference",$C$11,0)+IF(I70="preference",$C$12,0)+IF(J70="preference",$C$13,0) -> 100000000 | L70: =IF(D70="convert",$D$7,0)+IF(E70="convert",$D$8,0)+IF(F70="convert",$D$9,0)+IF(G70="convert",$D$10,0)+IF(H70="convert",$D$11,0)+IF(I70="convert",$D$12,0)+IF(J70="convert",$D$13,0) -> 22338767
B71: Iter 3 | D71: =IF($C$7>((F$23-(K70-IF(D70="preference",$C$7,0)))/($D$19+(L70-IF(D70="convert",$D$7,0))+$D$7)*$D$7),"preference","convert") -> convert | E71: =IF($C$8>((F$23-(K70-IF(E70="preference",$C$8,0)))/($D$19+(L70-IF(E70="convert",$D$8,0))+$D$8)*$D$8),"preference","convert") -> convert | F71: =IF($C$9>((F$23-(K70-IF(F70="preference",$C$9,0)))/($D$19+(L70-IF(F70="convert",$D$9,0))+$D$9)*$D$9),"preference","convert") -> preference | G71: =IF($C$10>((F$23-(K70-IF(G70="preference",$C$10,0)))/($D$19+(L70-IF(G70="convert",$D$10,0))+$D$10)*$D$10),"preference","convert") -> convert | H71: =IF($C$11>((F$23-(K70-IF(H70="preference",$C$11,0)))/($D$19+(L70-IF(H70="convert",$D$11,0))+$D$11)*$D$11),"preference","convert") -> convert | I71: =IF($C$12>((F$23-(K70-IF(I70="preference",$C$12,0)))/($D$19+(L70-IF(I70="convert",$D$12,0))+$D$12)*$D$12),"preference","convert") -> convert | J71: =IF($C$13>((F$23-(K70-IF(J70="preference",$C$13,0)))/($D$19+(L70-IF(J70="convert",$D$13,0))+$D$13)*$D$13),"preference","convert") -> convert | K71: =IF(D71="preference",$C$7,0)+IF(E71="preference",$C$8,0)+IF(F71="preference",$C$9,0)+IF(G71="preference",$C$10,0)+IF(H71="preference",$C$11,0)+IF(I71="preference",$C$12,0)+IF(J71="preference",$C$13,0) -> 100000000 | L71: =IF(D71="convert",$D$7,0)+IF(E71="convert",$D$8,0)+IF(F71="convert",$D$9,0)+IF(G71="convert",$D$10,0)+IF(H71="convert",$D$11,0)+IF(I71="convert",$D$12,0)+IF(J71="convert",$D$13,0) -> 22338767
B72: Iter 4 | D72: =IF($C$7>((F$23-(K71-IF(D71="preference",$C$7,0)))/($D$19+(L71-IF(D71="convert",$D$7,0))+$D$7)*$D$7),"preference","convert") -> convert | E72: =IF($C$8>((F$23-(K71-IF(E71="preference",$C$8,0)))/($D$19+(L71-IF(E71="convert",$D$8,0))+$D$8)*$D$8),"preference","convert") -> convert | F72: =IF($C$9>((F$23-(K71-IF(F71="preference",$C$9,0)))/($D$19+(L71-IF(F71="convert",$D$9,0))+$D$9)*$D$9),"preference","convert") -> preference | G72: =IF($C$10>((F$23-(K71-IF(G71="preference",$C$10,0)))/($D$19+(L71-IF(G71="convert",$D$10,0))+$D$10)*$D$10),"preference","convert") -> convert | H72: =IF($C$11>((F$23-(K71-IF(H71="preference",$C$11,0)))/($D$19+(L71-IF(H71="convert",$D$11,0))+$D$11)*$D$11),"preference","convert") -> convert | I72: =IF($C$12>((F$23-(K71-IF(I71="preference",$C$12,0)))/($D$19+(L71-IF(I71="convert",$D$12,0))+$D$12)*$D$12),"preference","convert") -> convert | J72: =IF($C$13>((F$23-(K71-IF(J71="preference",$C$13,0)))/($D$19+(L71-IF(J71="convert",$D$13,0))+$D$13)*$D$13),"preference","convert") -> convert | K72: =IF(D72="preference",$C$7,0)+IF(E72="preference",$C$8,0)+IF(F72="preference",$C$9,0)+IF(G72="preference",$C$10,0)+IF(H72="preference",$C$11,0)+IF(I72="preference",$C$12,0)+IF(J72="preference",$C$13,0) -> 100000000 | L72: =IF(D72="convert",$D$7,0)+IF(E72="convert",$D$8,0)+IF(F72="convert",$D$9,0)+IF(G72="convert",$D$10,0)+IF(H72="convert",$D$11,0)+IF(I72="convert",$D$12,0)+IF(J72="convert",$D$13,0) -> 22338767
B73: Iter 5 | D73: =IF($C$7>((F$23-(K72-IF(D72="preference",$C$7,0)))/($D$19+(L72-IF(D72="convert",$D$7,0))+$D$7)*$D$7),"preference","convert") -> convert | E73: =IF($C$8>((F$23-(K72-IF(E72="preference",$C$8,0)))/($D$19+(L72-IF(E72="convert",$D$8,0))+$D$8)*$D$8),"preference","convert") -> convert | F73: =IF($C$9>((F$23-(K72-IF(F72="preference",$C$9,0)))/($D$19+(L72-IF(F72="convert",$D$9,0))+$D$9)*$D$9),"preference","convert") -> preference | G73: =IF($C$10>((F$23-(K72-IF(G72="preference",$C$10,0)))/($D$19+(L72-IF(G72="convert",$D$10,0))+$D$10)*$D$10),"preference","convert") -> convert | H73: =IF($C$11>((F$23-(K72-IF(H72="preference",$C$11,0)))/($D$19+(L72-IF(H72="convert",$D$11,0))+$D$11)*$D$11),"preference","convert") -> convert | I73: =IF($C$12>((F$23-(K72-IF(I72="preference",$C$12,0)))/($D$19+(L72-IF(I72="convert",$D$12,0))+$D$12)*$D$12),"preference","convert") -> convert | J73: =IF($C$13>((F$23-(K72-IF(J72="preference",$C$13,0)))/($D$19+(L72-IF(J72="convert",$D$13,0))+$D$13)*$D$13),"preference","convert") -> convert | K73: =IF(D73="preference",$C$7,0)+IF(E73="preference",$C$8,0)+IF(F73="preference",$C$9,0)+IF(G73="preference",$C$10,0)+IF(H73="preference",$C$11,0)+IF(I73="preference",$C$12,0)+IF(J73="preference",$C$13,0) -> 100000000 | L73: =IF(D73="convert",$D$7,0)+IF(E73="convert",$D$8,0)+IF(F73="convert",$D$9,0)+IF(G73="convert",$D$10,0)+IF(H73="convert",$D$11,0)+IF(I73="convert",$D$12,0)+IF(J73="convert",$D$13,0) -> 22338767
B74: PPS (post conversions) | C74: =(F$23-K73)/($D$19+L73) -> 55.758882
B75: Class payoff ($) | D75: =IF(D73="preference",$C$7,$C$74*$D$7) -> 44846574 | E75: =IF(E73="preference",$C$8,$C$74*$D$8) -> 3.420513e+08 | F75: =IF(F73="preference",$C$9,$C$74*$D$9) -> 100000000 | G75: =IF(G73="preference",$C$10,$C$74*$D$10) -> 1.3382132e+08 | H75: =IF(H73="preference",$C$11,$C$74*$D$11) -> 1.6727664e+08 | I75: =IF(I73="preference",$C$12,$C$74*$D$12) -> 2.7879441e+08 | J75: =IF(J73="preference",$C$13,$C$74*$D$13) -> 2.7879441e+08
B76: Common + RSA payoff | C76: =$C$74*$D$15 -> 5.0182993e+08
B77: Notes (A+B common-eq) payoff | C77: =$C$74*$D$16 -> 15688207
B78: Options issued (net of strike) | C78: =MAX(0,($C$74-$C$18)*$D$17) -> 1.368972e+08
B79: Total proceeds | C79: =C76+C77+C78+D75+E75+F75+G75+H75+I75+J75 -> 2000000000
B80: Check | C80: =ROUND(C79-F$22,0) -> 0
B81: Exit 4: $4.0B — Iteration & Payoffs
B82: Iter / Class | D82: F | E82: E | F82: D | G82: C | H82: B | I82: A | J82: Seed | K82: ΣPref | L82: ΣConvN
B83: Iter 0 (init) | D83: convert | E83: convert | F83: convert | G83: convert | H83: convert | I83: convert | J83: convert | K83: =IF(D83="preference",$C$7,0)+IF(E83="preference",$C$8,0)+IF(F83="preference",$C$9,0)+IF(G83="preference",$C$10,0)+IF(H83="preference",$C$11,0)+IF(I83="preference",$C$12,0)+IF(J83="preference",$C$13,0) -> 0 | L83: =IF(D83="convert",$D$7,0)+IF(E83="convert",$D$8,0)+IF(F83="convert",$D$9,0)+IF(G83="convert",$D$10,0)+IF(H83="convert",$D$11,0)+IF(I83="convert",$D$12,0)+IF(J83="convert",$D$13,0) -> 24072744
B84: Iter 1 | D84: =IF($C$7>((G$23-(K83-IF(D83="preference",$C$7,0)))/($D$19+(L83-IF(D83="convert",$D$7,0))+$D$7)*$D$7),"preference","convert") -> convert | E84: =IF($C$8>((G$23-(K83-IF(E83="preference",$C$8,0)))/($D$19+(L83-IF(E83="convert",$D$8,0))+$D$8)*$D$8),"preference","convert") -> convert | F84: =IF($C$9>((G$23-(K83-IF(F83="preference",$C$9,0)))/($D$19+(L83-IF(F83="convert",$D$9,0))+$D$9)*$D$9),"preference","convert") -> convert | G84: =IF($C$10>((G$23-(K83-IF(G83="preference",$C$10,0)))/($D$19+(L83-IF(G83="convert",$D$10,0))+$D$10)*$D$10),"preference","convert") -> convert | H84: =IF($C$11>((G$23-(K83-IF(H83="preference",$C$11,0)))/($D$19+(L83-IF(H83="convert",$D$11,0))+$D$11)*$D$11),"preference","convert") -> convert | I84: =IF($C$12>((G$23-(K83-IF(I83="preference",$C$12,0)))/($D$19+(L83-IF(I83="convert",$D$12,0))+$D$12)*$D$12),"preference","convert") -> convert | J84: =IF($C$13>((G$23-(K83-IF(J83="preference",$C$13,0)))/($D$19+(L83-IF(J83="convert",$D$13,0))+$D$13)*$D$13),"preference","convert") -> convert | K84: =IF(D84="preference",$C$7,0)+IF(E84="preference",$C$8,0)+IF(F84="preference",$C$9,0)+IF(G84="preference",$C$10,0)+IF(H84="preference",$C$11,0)+IF(I84="preference",$C$12,0)+IF(J84="preference",$C$13,0) -> 0 | L84: =IF(D84="convert",$D$7,0)+IF(E84="convert",$D$8,0)+IF(F84="convert",$D$9,0)+IF(G84="convert",$D$10,0)+IF(H84="convert",$D$11,0)+IF(I84="convert",$D$12,0)+IF(J84="convert",$D$13,0) -> 24072744
B85: Iter 2 | D85: =IF($C$7>((G$23-(K84-IF(D84="preference",$C$7,0)))/($D$19+(L84-IF(D84="convert",$D$7,0))+$D$7)*$D$7),"preference","convert") -> convert | E85: =IF($C$8>((G$23-(K84-IF(E84="preference",$C$8,0)))/($D$19+(L84-IF(E84="convert",$D$8,0))+$D$8)*$D$8),"preference","convert") -> convert | F85: =IF($C$9>((G$23-(K84-IF(F84="preference",$C$9,0)))/($D$19+(L84-IF(F84="convert",$D$9,0))+$D$9)*$D$9),"preference","convert") -> convert | G85: =IF($C$10>((G$23-(K84-IF(G84="preference",$C$10,0)))/($D$19+(L84-IF(G84="convert",$D$10,0))+$D$10)*$D$10),"preference","convert") -> convert | H85: =IF($C$11>((G$23-(K84-IF(H84="preference",$C$11,0)))/($D$19+(L84-IF(H84="convert",$D$11,0))+$D$11)*$D$11),"preference","convert") -> convert | I85: =IF($C$12>((G$23-(K84-IF(I84="preference",$C$12,0)))/($D$19+(L84-IF(I84="convert",$D$12,0))+$D$12)*$D$12),"preference","convert") -> convert | J85: =IF($C$13>((G$23-(K84-IF(J84="preference",$C$13,0)))/($D$19+(L84-IF(J84="convert",$D$13,0))+$D$13)*$D$13),"preference","convert") -> convert | K85: =IF(D85="preference",$C$7,0)+IF(E85="preference",$C$8,0)+IF(F85="preference",$C$9,0)+IF(G85="preference",$C$10,0)+IF(H85="preference",$C$11,0)+IF(I85="preference",$C$12,0)+IF(J85="preference",$C$13,0) -> 0 | L85: =IF(D85="convert",$D$7,0)+IF(E85="convert",$D$8,0)+IF(F85="convert",$D$9,0)+IF(G85="convert",$D$10,0)+IF(H85="convert",$D$11,0)+IF(I85="convert",$D$12,0)+IF(J85="convert",$D$13,0) -> 24072744
B86: Iter 3 | D86: =IF($C$7>((G$23-(K85-IF(D85="preference",$C$7,0)))/($D$19+(L85-IF(D85="convert",$D$7,0))+$D$7)*$D$7),"preference","convert") -> convert | E86: =IF($C$8>((G$23-(K85-IF(E85="preference",$C$8,0)))/($D$19+(L85-IF(E85="convert",$D$8,0))+$D$8)*$D$8),"preference","convert") -> convert | F86: =IF($C$9>((G$23-(K85-IF(F85="preference",$C$9,0)))/($D$19+(L85-IF(F85="convert",$D$9,0))+$D$9)*$D$9),"preference","convert") -> convert | G86: =IF($C$10>((G$23-(K85-IF(G85="preference",$C$10,0)))/($D$19+(L85-IF(G85="convert",$D$10,0))+$D$10)*$D$10),"preference","convert") -> convert | H86: =IF($C$11>((G$23-(K85-IF(H85="preference",$C$11,0)))/($D$19+(L85-IF(H85="convert",$D$11,0))+$D$11)*$D$11),"preference","convert") -> convert | I86: =IF($C$12>((G$23-(K85-IF(I85="preference",$C$12,0)))/($D$19+(L85-IF(I85="convert",$D$12,0))+$D$12)*$D$12),"preference","convert") -> convert | J86: =IF($C$13>((G$23-(K85-IF(J85="preference",$C$13,0)))/($D$19+(L85-IF(J85="convert",$D$13,0))+$D$13)*$D$13),"preference","convert") -> convert | K86: =IF(D86="preference",$C$7,0)+IF(E86="preference",$C$8,0)+IF(F86="preference",$C$9,0)+IF(G86="preference",$C$10,0)+IF(H86="preference",$C$11,0)+IF(I86="preference",$C$12,0)+IF(J86="preference",$C$13,0) -> 0 | L86: =IF(D86="convert",$D$7,0)+IF(E86="convert",$D$8,0)+IF(F86="convert",$D$9,0)+IF(G86="convert",$D$10,0)+IF(H86="convert",$D$11,0)+IF(I86="convert",$D$12,0)+IF(J86="convert",$D$13,0) -> 24072744
B87: Iter 4 | D87: =IF($C$7>((G$23-(K86-IF(D86="preference",$C$7,0)))/($D$19+(L86-IF(D86="convert",$D$7,0))+$D$7)*$D$7),"preference","convert") -> convert | E87: =IF($C$8>((G$23-(K86-IF(E86="preference",$C$8,0)))/($D$19+(L86-IF(E86="convert",$D$8,0))+$D$8)*$D$8),"preference","convert") -> convert | F87: =IF($C$9>((G$23-(K86-IF(F86="preference",$C$9,0)))/($D$19+(L86-IF(F86="convert",$D$9,0))+$D$9)*$D$9),"preference","convert") -> convert | G87: =IF($C$10>((G$23-(K86-IF(G86="preference",$C$10,0)))/($D$19+(L86-IF(G86="convert",$D$10,0))+$D$10)*$D$10),"preference","convert") -> convert | H87: =IF($C$11>((G$23-(K86-IF(H86="preference",$C$11,0)))/($D$19+(L86-IF(H86="convert",$D$11,0))+$D$11)*$D$11),"preference","convert") -> convert | I87: =IF($C$12>((G$23-(K86-IF(I86="preference",$C$12,0)))/($D$19+(L86-IF(I86="convert",$D$12,0))+$D$12)*$D$12),"preference","convert") -> convert | J87: =IF($C$13>((G$23-(K86-IF(J86="preference",$C$13,0)))/($D$19+(L86-IF(J86="convert",$D$13,0))+$D$13)*$D$13),"preference","convert") -> convert | K87: =IF(D87="preference",$C$7,0)+IF(E87="preference",$C$8,0)+IF(F87="preference",$C$9,0)+IF(G87="preference",$C$10,0)+IF(H87="preference",$C$11,0)+IF(I87="preference",$C$12,0)+IF(J87="preference",$C$13,0) -> 0 | L87: =IF(D87="convert",$D$7,0)+IF(E87="convert",$D$8,0)+IF(F87="convert",$D$9,0)+IF(G87="convert",$D$10,0)+IF(H87="convert",$D$11,0)+IF(I87="convert",$D$12,0)+IF(J87="convert",$D$13,0) -> 24072744
B88: Iter 5 | D88: =IF($C$7>((G$23-(K87-IF(D87="preference",$C$7,0)))/($D$19+(L87-IF(D87="convert",$D$7,0))+$D$7)*$D$7),"preference","convert") -> convert | E88: =IF($C$8>((G$23-(K87-IF(E87="preference",$C$8,0)))/($D$19+(L87-IF(E87="convert",$D$8,0))+$D$8)*$D$8),"preference","convert") -> convert | F88: =IF($C$9>((G$23-(K87-IF(F87="preference",$C$9,0)))/($D$19+(L87-IF(F87="convert",$D$9,0))+$D$9)*$D$9),"preference","convert") -> convert | G88: =IF($C$10>((G$23-(K87-IF(G87="preference",$C$10,0)))/($D$19+(L87-IF(G87="convert",$D$10,0))+$D$10)*$D$10),"preference","convert") -> convert | H88: =IF($C$11>((G$23-(K87-IF(H87="preference",$C$11,0)))/($D$19+(L87-IF(H87="convert",$D$11,0))+$D$11)*$D$11),"preference","convert") -> convert | I88: =IF($C$12>((G$23-(K87-IF(I87="preference",$C$12,0)))/($D$19+(L87-IF(I87="convert",$D$12,0))+$D$12)*$D$12),"preference","convert") -> convert | J88: =IF($C$13>((G$23-(K87-IF(J87="preference",$C$13,0)))/($D$19+(L87-IF(J87="convert",$D$13,0))+$D$13)*$D$13),"preference","convert") -> convert | K88: =IF(D88="preference",$C$7,0)+IF(E88="preference",$C$8,0)+IF(F88="preference",$C$9,0)+IF(G88="preference",$C$10,0)+IF(H88="preference",$C$11,0)+IF(I88="preference",$C$12,0)+IF(J88="preference",$C$13,0) -> 0 | L88: =IF(D88="convert",$D$7,0)+IF(E88="convert",$D$8,0)+IF(F88="convert",$D$9,0)+IF(G88="convert",$D$10,0)+IF(H88="convert",$D$11,0)+IF(I88="convert",$D$12,0)+IF(J88="convert",$D$13,0) -> 24072744
B89: PPS (post conversions) | C89: =(G$23-K88)/($D$19+L88) -> 111.63297
B90: Class payoff ($) | D90: =IF(D88="preference",$C$7,$C$89*$D$7) -> 89785811 | E90: =IF(E88="preference",$C$8,$C$89*$D$8) -> 6.8480937e+08 | F90: =IF(F88="preference",$C$9,$C$89*$D$9) -> 1.93569e+08 | G90: =IF(G88="preference",$C$10,$C$89*$D$10) -> 2.6791914e+08 | H90: =IF(H88="preference",$C$11,$C$89*$D$11) -> 3.3489892e+08 | I90: =IF(I88="preference",$C$12,$C$89*$D$12) -> 5.5816487e+08 | J90: =IF(J88="preference",$C$13,$C$89*$D$13) -> 5.5816487e+08
B91: Common + RSA payoff | C91: =$C$89*$D$15 -> 1.0046968e+09
B92: Notes (A+B common-eq) payoff | C92: =$C$89*$D$16 -> 31408830
B93: Options issued (net of strike) | C93: =MAX(0,($C$89-$C$18)*$D$17) -> 2.7658243e+08
B94: Total proceeds | C94: =C91+C92+C93+D90+E90+F90+G90+H90+I90+J90 -> 4e+09
B95: Check | C95: =ROUND(C94-G$22,0) -> 0
B96: Exit 5: $8.0B — Iteration & Payoffs
B97: Iter / Class | D97: F | E97: E | F97: D | G97: C | H97: B | I97: A | J97: Seed | K97: ΣPref | L97: ΣConvN
B98: Iter 0 (init) | D98: convert | E98: convert | F98: convert | G98: convert | H98: convert | I98: convert | J98: convert | K98: =IF(D98="preference",$C$7,0)+IF(E98="preference",$C$8,0)+IF(F98="preference",$C$9,0)+IF(G98="preference",$C$10,0)+IF(H98="preference",$C$11,0)+IF(I98="preference",$C$12,0)+IF(J98="preference",$C$13,0) -> 0 | L98: =IF(D98="convert",$D$7,0)+IF(E98="convert",$D$8,0)+IF(F98="convert",$D$9,0)+IF(G98="convert",$D$10,0)+IF(H98="convert",$D$11,0)+IF(I98="convert",$D$12,0)+IF(J98="convert",$D$13,0) -> 24072744
B99: Iter 1 | D99: =IF($C$7>((H$23-(K98-IF(D98="preference",$C$7,0)))/($D$19+(L98-IF(D98="convert",$D$7,0))+$D$7)*$D$7),"preference","convert") -> convert | E99: =IF($C$8>((H$23-(K98-IF(E98="preference",$C$8,0)))/($D$19+(L98-IF(E98="convert",$D$8,0))+$D$8)*$D$8),"preference","convert") -> convert | F99: =IF($C$9>((H$23-(K98-IF(F98="preference",$C$9,0)))/($D$19+(L98-IF(F98="convert",$D$9,0))+$D$9)*$D$9),"preference","convert") -> convert | G99: =IF($C$10>((H$23-(K98-IF(G98="preference",$C$10,0)))/($D$19+(L98-IF(G98="convert",$D$10,0))+$D$10)*$D$10),"preference","convert") -> convert | H99: =IF($C$11>((H$23-(K98-IF(H98="preference",$C$11,0)))/($D$19+(L98-IF(H98="convert",$D$11,0))+$D$11)*$D$11),"preference","convert") -> convert | I99: =IF($C$12>((H$23-(K98-IF(I98="preference",$C$12,0)))/($D$19+(L98-IF(I98="convert",$D$12,0))+$D$12)*$D$12),"preference","convert") -> convert | J99: =IF($C$13>((H$23-(K98-IF(J98="preference",$C$13,0)))/($D$19+(L98-IF(J98="convert",$D$13,0))+$D$13)*$D$13),"preference","convert") -> convert | K99: =IF(D99="preference",$C$7,0)+IF(E99="preference",$C$8,0)+IF(F99="preference",$C$9,0)+IF(G99="preference",$C$10,0)+IF(H99="preference",$C$11,0)+IF(I99="preference",$C$12,0)+IF(J99="preference",$C$13,0) -> 0 | L99: =IF(D99="convert",$D$7,0)+IF(E99="convert",$D$8,0)+IF(F99="convert",$D$9,0)+IF(G99="convert",$D$10,0)+IF(H99="convert",$D$11,0)+IF(I99="convert",$D$12,0)+IF(J99="convert",$D$13,0) -> 24072744
B100: Iter 2 | D100: =IF($C$7>((H$23-(K99-IF(D99="preference",$C$7,0)))/($D$19+(L99-IF(D99="convert",$D$7,0))+$D$7)*$D$7),"preference","convert") -> convert | E100: =IF($C$8>((H$23-(K99-IF(E99="preference",$C$8,0)))/($D$19+(L99-IF(E99="convert",$D$8,0))+$D$8)*$D$8),"preference","convert") -> convert | F100: =IF($C$9>((H$23-(K99-IF(F99="preference",$C$9,0)))/($D$19+(L99-IF(F99="convert",$D$9,0))+$D$9)*$D$9),"preference","convert") -> convert | G100: =IF($C$10>((H$23-(K99-IF(G99="preference",$C$10,0)))/($D$19+(L99-IF(G99="convert",$D$10,0))+$D$10)*$D$10),"preference","convert") -> convert | H100: =IF($C$11>((H$23-(K99-IF(H99="preference",$C$11,0)))/($D$19+(L99-IF(H99="convert",$D$11,0))+$D$11)*$D$11),"preference","convert") -> convert | I100: =IF($C$12>((H$23-(K99-IF(I99="preference",$C$12,0)))/($D$19+(L99-IF(I99="convert",$D$12,0))+$D$12)*$D$12),"preference","convert") -> convert | J100: =IF($C$13>((H$23-(K99-IF(J99="preference",$C$13,0)))/($D$19+(L99-IF(J99="convert",$D$13,0))+$D$13)*$D$13),"preference","convert") -> convert | K100: =IF(D100="preference",$C$7,0)+IF(E100="preference",$C$8,0)+IF(F100="preference",$C$9,0)+IF(G100="preference",$C$10,0)+IF(H100="preference",$C$11,0)+IF(I100="preference",$C$12,0)+IF(J100="preference",$C$13,0) -> 0 | L100: =IF(D100="convert",$D$7,0)+IF(E100="convert",$D$8,0)+IF(F100="convert",$D$9,0)+IF(G100="convert",$D$10,0)+IF(H100="convert",$D$11,0)+IF(I100="convert",$D$12,0)+IF(J100="convert",$D$13,0) -> 24072744
B101: Iter 3 | D101: =IF($C$7>((H$23-(K100-IF(D100="preference",$C$7,0)))/($D$19+(L100-IF(D100="convert",$D$7,0))+$D$7)*$D$7),"preference","convert") -> convert | E101: =IF($C$8>((H$23-(K100-IF(E100="preference",$C$8,0)))/($D$19+(L100-IF(E100="convert",$D$8,0))+$D$8)*$D$8),"preference","convert") -> convert | F101: =IF($C$9>((H$23-(K100-IF(F100="preference",$C$9,0)))/($D$19+(L100-IF(F100="convert",$D$9,0))+$D$9)*$D$9),"preference","convert") -> convert | G101: =IF($C$10>((H$23-(K100-IF(G100="preference",$C$10,0)))/($D$19+(L100-IF(G100="convert",$D$10,0))+$D$10)*$D$10),"preference","convert") -> convert | H101: =IF($C$11>((H$23-(K100-IF(H100="preference",$C$11,0)))/($D$19+(L100-IF(H100="convert",$D$11,0))+$D$11)*$D$11),"preference","convert") -> convert | I101: =IF($C$12>((H$23-(K100-IF(I100="preference",$C$12,0)))/($D$19+(L100-IF(I100="convert",$D$12,0))+$D$12)*$D$12),"preference","convert") -> convert | J101: =IF($C$13>((H$23-(K100-IF(J100="preference",$C$13,0)))/($D$19+(L100-IF(J100="convert",$D$13,0))+$D$13)*$D$13),"preference","convert") -> convert | K101: =IF(D101="preference",$C$7,0)+IF(E101="preference",$C$8,0)+IF(F101="preference",$C$9,0)+IF(G101="preference",$C$10,0)+IF(H101="preference",$C$11,0)+IF(I101="preference",$C$12,0)+IF(J101="preference",$C$13,0) -> 0 | L101: =IF(D101="convert",$D$7,0)+IF(E101="convert",$D$8,0)+IF(F101="convert",$D$9,0)+IF(G101="convert",$D$10,0)+IF(H101="convert",$D$11,0)+IF(I101="convert",$D$12,0)+IF(J101="convert",$D$13,0) -> 24072744
B102: Iter 4 | D102: =IF($C$7>((H$23-(K101-IF(D101="preference",$C$7,0)))/($D$19+(L101-IF(D101="convert",$D$7,0))+$D$7)*$D$7),"preference","convert") -> convert | E102: =IF($C$8>((H$23-(K101-IF(E101="preference",$C$8,0)))/($D$19+(L101-IF(E101="convert",$D$8,0))+$D$8)*$D$8),"preference","convert") -> convert | F102: =IF($C$9>((H$23-(K101-IF(F101="preference",$C$9,0)))/($D$19+(L101-IF(F101="convert",$D$9,0))+$D$9)*$D$9),"preference","convert") -> convert | G102: =IF($C$10>((H$23-(K101-IF(G101="preference",$C$10,0)))/($D$19+(L101-IF(G101="convert",$D$10,0))+$D$10)*$D$10),"preference","convert") -> convert | H102: =IF($C$11>((H$23-(K101-IF(H101="preference",$C$11,0)))/($D$19+(L101-IF(H101="convert",$D$11,0))+$D$11)*$D$11),"preference","convert") -> convert | I102: =IF($C$12>((H$23-(K101-IF(I101="preference",$C$12,0)))/($D$19+(L101-IF(I101="convert",$D$12,0))+$D$12)*$D$12),"preference","convert") -> convert | J102: =IF($C$13>((H$23-(K101-IF(J101="preference",$C$13,0)))/($D$19+(L101-IF(J101="convert",$D$13,0))+$D$13)*$D$13),"preference","convert") -> convert | K102: =IF(D102="preference",$C$7,0)+IF(E102="preference",$C$8,0)+IF(F102="preference",$C$9,0)+IF(G102="preference",$C$10,0)+IF(H102="preference",$C$11,0)+IF(I102="preference",$C$12,0)+IF(J102="preference",$C$13,0) -> 0 | L102: =IF(D102="convert",$D$7,0)+IF(E102="convert",$D$8,0)+IF(F102="convert",$D$9,0)+IF(G102="convert",$D$10,0)+IF(H102="convert",$D$11,0)+IF(I102="convert",$D$12,0)+IF(J102="convert",$D$13,0) -> 24072744
B103: Iter 5 | D103: =IF($C$7>((H$23-(K102-IF(D102="preference",$C$7,0)))/($D$19+(L102-IF(D102="convert",$D$7,0))+$D$7)*$D$7),"preference","convert") -> convert | E103: =IF($C$8>((H$23-(K102-IF(E102="preference",$C$8,0)))/($D$19+(L102-IF(E102="convert",$D$8,0))+$D$8)*$D$8),"preference","convert") -> convert | F103: =IF($C$9>((H$23-(K102-IF(F102="preference",$C$9,0)))/($D$19+(L102-IF(F102="convert",$D$9,0))+$D$9)*$D$9),"preference","convert") -> convert | G103: =IF($C$10>((H$23-(K102-IF(G102="preference",$C$10,0)))/($D$19+(L102-IF(G102="convert",$D$10,0))+$D$10)*$D$10),"preference","convert") -> convert | H103: =IF($C$11>((H$23-(K102-IF(H102="preference",$C$11,0)))/($D$19+(L102-IF(H102="convert",$D$11,0))+$D$11)*$D$11),"preference","convert") -> convert | I103: =IF($C$12>((H$23-(K102-IF(I102="preference",$C$12,0)))/($D$19+(L102-IF(I102="convert",$D$12,0))+$D$12)*$D$12),"preference","convert") -> convert | J103: =IF($C$13>((H$23-(K102-IF(J102="preference",$C$13,0)))/($D$19+(L102-IF(J102="convert",$D$13,0))+$D$13)*$D$13),"preference","convert") -> convert | K103: =IF(D103="preference",$C$7,0)+IF(E103="preference",$C$8,0)+IF(F103="preference",$C$9,0)+IF(G103="preference",$C$10,0)+IF(H103="preference",$C$11,0)+IF(I103="preference",$C$12,0)+IF(J103="preference",$C$13,0) -> 0 | L103: =IF(D103="convert",$D$7,0)+IF(E103="convert",$D$8,0)+IF(F103="convert",$D$9,0)+IF(G103="convert",$D$10,0)+IF(H103="convert",$D$11,0)+IF(I103="convert",$D$12,0)+IF(J103="convert",$D$13,0) -> 24072744
B104: PPS (post conversions) | C104: =(H$23-K103)/($D$19+L103) -> 223.19622
B105: Class payoff ($) | D105: =IF(D103="preference",$C$7,$C$104*$D$7) -> 1.7951554e+08 | E105: =IF(E103="preference",$C$8,$C$104*$D$8) -> 1.369191e+09 | F105: =IF(F103="preference",$C$9,$C$104*$D$9) -> 3.870171e+08 | G105: =IF(G103="preference",$C$10,$C$104*$D$10) -> 5.3567093e+08 | H105: =IF(H103="preference",$C$11,$C$104*$D$11) -> 6.6958866e+08 | I105: =IF(I103="preference",$C$12,$C$104*$D$12) -> 1.1159811e+09 | J105: =IF(J103="preference",$C$13,$C$104*$D$13) -> 1.1159811e+09
B106: Common + RSA payoff | C106: =$C$104*$D$15 -> 2.008766e+09
B107: Notes (A+B common-eq) payoff | C107: =$C$104*$D$16 -> 62798042
...
