Workbook

Sheet Assumptions
B2: Kelvin Dynamics — Series F Assumptions & Solver
B3: All inputs in USD or shares unless noted
B5: Series F Round Terms
B6: Series F pre-money valuation ($) | C6: 1400000000
B7: Series F primary raise ($) | C7: 30000000
B8: Series F secondary raise ($) | C8: 15000000
B9: Tender PPS multiplier (× F PPS) | C9: 0.85
B10: ESOP refresh target (% of post-F FD) | C10: 0.13
B11: Our fund check ($) | C11: 10000000
B12: F_LEAD primary check ($) | C12: 20000000
B13: Option strike ($) | C13: 1
B15: Prior Round OCPs (for AD)
B16: Seed OCP | C16: 1
B17: Series A OCP | C17: 3
B18: Series B OCP | C18: 10
B19: Series C OCP | C19: 25
B20: Series D OCP (post-E NCP, compound base) | C20: 58.118347
B21: Series D original OCP (issued at) | C21: 60
B22: Series E OCP | C22: 49.158311
B24: Invested Capital by Series
B25: Seed invested ($) | C25: 5000000
B26: Series A invested ($) | C26: 15000000
B27: Series B invested ($) | C27: 30000000
B28: Series C invested ($) | C28: 60000000
B29: Series D invested ($) | C29: 100000000
B30: Series E invested ($) | C30: 300000000
B32: Convertible Notes
B33: Note A principal ($) | C33: 5000000
B34: Note A valuation cap ($) | C34: 1000000000
B35: Note A discount | C35: 0.2
B36: Note B principal ($) | C36: 3000000
B37: Note B valuation cap ($) | C37: 1600000000
B38: Note B discount | C38: 0.15
B40: Pre-F Share Counts (broad-based AD inputs)
B41: Founders common (F1+F2+F3) | C41: =E41+F41+G41 -> 8000000 | D41: (F1 / F2 / F3 →) | E41: 4000000 | F41: 2500000 | G41: 1500000
B42: Employee RSAs (10 × 100,000) | C42: 1000000
B43: Seed preferred shares | C43: 5000000
B44: Series A preferred shares | C44: 5000000
B45: Series B preferred shares | C45: 3000000
B46: Series C preferred shares | C46: 2400000
B47: Series D preferred shares (post v3 AD) | C47: 1720627
B48: Series E preferred shares | C48: 6102667
B49: Pre-F issued options | C49: 2500000
B50: Pre-F unissued options | C50: 1894667
B51: Pre-F existing pool (issued + unissued) | C51: =C49+C50 -> 4394667
B52: Pre-F fully-diluted total (broad-based A) | C52: =C41+C42+C43+C44+C45+C46+C47+C48+C49+C50 -> 36617961
B54: Exit Scenarios
B55: Exit 1 ($) | C55: 700000000
B56: Exit 2 ($) | C56: 1200000000
B57: Exit 3 ($) — sensitivity ref | C57: 2000000000
B58: Exit 4 ($) | C58: 4000000000
B59: Exit 5 ($) | C59: 8000000000
B61: Sensitivity Axes & Return Targets
B62: ESOP low / base / high | C62: 0.11 | D62: 0.13 | E62: 0.15
B63: Pre-money low / base / high ($) | C63: 1200000000 | D63: 1400000000 | E63: 1800000000
B64: Return targets (3× / 4×) | C64: 3 | D64: 4
B66: Fixed-Point Solver (6 iterations)
B67: Iteration | C67: 0 | D67: 1 | E67: 2 | F67: 3 | G67: 4 | H67: 5 | I67: 6
B68: F PPS ($) | C68: =C6/C52 -> 38.232604 | D68: =C6/(C52+C77+C84+C85) -> 37.673237 | E68: =C6/(C52+D77+D84+D85) -> 37.34825 | F68: =C6/(C52+E77+E84+E85) -> 37.345281 | G68: =C6/(C52+F77+F84+F85) -> 37.345247 | H68: =C6/(C52+G77+G84+G85) -> 37.345247 | I68: =C6/(C52+H77+H84+H85) -> 37.345247
B69: F primary new shares | C69: =C7/C68 -> 784670.59 | D69: =C7/D68 -> 796321.27 | E69: =C7/E68 -> 803250.48 | F69: =C7/F68 -> 803314.35 | G69: =C7/G68 -> 803315.07 | H69: =C7/H68 -> 803315.08 | I69: =C7/I68 -> 803315.08
B70: AD D denom (A + 30M/F_PPS) | C70: =C52+C7/C68 -> 37402632 | D70: =C52+C7/D68 -> 37414282 | E70: =C52+C7/E68 -> 37421211 | F70: =C52+C7/F68 -> 37421275 | G70: =C52+C7/G68 -> 37421276 | H70: =C52+C7/H68 -> 37421276 | I70: =C52+C7/I68 -> 37421276
B71: AD D numer (A + 30M/D_OCP) | C71: =C52+C7/C20 -> 37134149 | D71: =C52+C7/C20 -> 37134149 | E71: =C52+C7/C20 -> 37134149 | F71: =C52+C7/C20 -> 37134149 | G71: =C52+C7/C20 -> 37134149 | H71: =C52+C7/C20 -> 37134149 | I71: =C52+C7/C20 -> 37134149
B72: NCP_D (post-F) | C72: =C20*C71/C70 -> 57.701164 | D72: =C20*D71/D70 -> 57.683196 | E72: =C20*E71/E70 -> 57.672515 | F72: =C20*F71/F70 -> 57.672416 | G72: =C20*G71/G70 -> 57.672415 | H72: =C20*H71/H70 -> 57.672415 | I72: =C20*I71/I70 -> 57.672415
B73: AD_D top-up shares | C73: =MAX(0,IF(C68<C20,C29/C72-C47,0)) -> 12440.304 | D73: =MAX(0,IF(D68<C20,C29/D72-C47,0)) -> 12980.143 | E73: =MAX(0,IF(E68<C20,C29/E72-C47,0)) -> 13301.211 | F73: =MAX(0,IF(F68<C20,C29/F72-C47,0)) -> 13304.171 | G73: =MAX(0,IF(G68<C20,C29/G72-C47,0)) -> 13304.204 | H73: =MAX(0,IF(H68<C20,C29/H72-C47,0)) -> 13304.204 | I73: =MAX(0,IF(I68<C20,C29/I72-C47,0)) -> 13304.204
B74: NCP_E (post-F) | C74: =C22*(C52+C7/C22)/(C52+C7/C68) -> 48.9291 | D74: =C22*(C52+C7/C22)/(C52+C7/D68) -> 48.913864 | E74: =C22*(C52+C7/C22)/(C52+C7/E68) -> 48.904807 | F74: =C22*(C52+C7/C22)/(C52+C7/F68) -> 48.904723 | G74: =C22*(C52+C7/C22)/(C52+C7/G68) -> 48.904722 | H74: =C22*(C52+C7/C22)/(C52+C7/H68) -> 48.904722 | I74: =C22*(C52+C7/C22)/(C52+C7/I68) -> 48.904722
B75: AD_E top-up shares | C75: =MAX(0,IF(C68<C22,C30/C74-C48,0)) -> 28653.58 | D75: =MAX(0,IF(D68<C22,C30/D74-C48,0)) -> 30563.446 | E75: =MAX(0,IF(E68<C22,C30/E74-C48,0)) -> 31699.335 | F75: =MAX(0,IF(F68<C22,C30/F74-C48,0)) -> 31709.805 | G75: =MAX(0,IF(G68<C22,C30/G74-C48,0)) -> 31709.922 | H75: =MAX(0,IF(H68<C22,C30/H74-C48,0)) -> 31709.924 | I75: =MAX(0,IF(I68<C22,C30/I74-C48,0)) -> 31709.924
B76: Other shares (for ESOP base) | C76: =C52+C73+C75+C69+C84+C85 -> 37443725 | D76: =C52+D73+D75+D69+D84+D85 -> 37737319 | E76: =C52+E73+E75+E69+E84+E85 -> 37747208 | F76: =C52+F73+F75+F69+F84+F85 -> 37747304 | G76: =C52+G73+G75+G69+G84+G85 -> 37747305 | H76: =C52+H73+H75+H69+H84+H85 -> 37747306 | I76: =C52+I73+I75+I69+I84+I85 -> 37747306
B77: ESOP top-up shares | C77: =MAX(0,(C10*C76-C51)/(1-C10)) -> 543698.06 | D77: =MAX(0,(C10*D76-C51)/(1-C10)) -> 587568.36 | E77: =MAX(0,(C10*E76-C51)/(1-C10)) -> 589046.05 | F77: =MAX(0,(C10*F76-C51)/(1-C10)) -> 589060.43 | G77: =MAX(0,(C10*G76-C51)/(1-C10)) -> 589060.59 | H77: =MAX(0,(C10*H76-C51)/(1-C10)) -> 589060.59 | I77: =MAX(0,(C10*I76-C51)/(1-C10)) -> 589060.59
B78: Note A cap PPS | C78: =C34/(C52+C77+C85) -> 26.909455 | D78: =C34/(C52+C77+C85) -> 26.909455 | E78: =C34/(C52+D77+D85) -> 26.810216 | F78: =C34/(C52+E77+E85) -> 26.808568 | G78: =C34/(C52+F77+F85) -> 26.808553 | H78: =C34/(C52+G77+G85) -> 26.808552 | I78: =C34/(C52+H77+H85) -> 26.808552
B79: Note A discount PPS | C79: =C68*(1-C35) -> 30.586083 | D79: =D68*(1-C35) -> 30.13859 | E79: =E68*(1-C35) -> 29.8786 | F79: =F68*(1-C35) -> 29.876225 | G79: =G68*(1-C35) -> 29.876198 | H79: =H68*(1-C35) -> 29.876198 | I79: =I68*(1-C35) -> 29.876198
B80: Note A conversion PPS | C80: =MIN(C78,C79) -> 26.909455 | D80: =MIN(D78,D79) -> 26.909455 | E80: =MIN(E78,E79) -> 26.810216 | F80: =MIN(F78,F79) -> 26.808568 | G80: =MIN(G78,G79) -> 26.808553 | H80: =MIN(H78,H79) -> 26.808552 | I80: =MIN(I78,I79) -> 26.808552
B81: Note B cap PPS | C81: =C37/(C52+C77+C84) -> 43.055128 | D81: =C37/(C52+C77+C84) -> 43.055128 | E81: =C37/(C52+D77+D84) -> 42.79066 | F81: =C37/(C52+E77+E84) -> 42.788182 | G81: =C37/(C52+F77+F84) -> 42.788152 | H81: =C37/(C52+G77+G84) -> 42.788152 | I81: =C37/(C52+H77+H84) -> 42.788152
B82: Note B discount PPS | C82: =C68*(1-C38) -> 32.497713 | D82: =D68*(1-C38) -> 32.022252 | E82: =E68*(1-C38) -> 31.746013 | F82: =F68*(1-C38) -> 31.743489 | G82: =G68*(1-C38) -> 31.74346 | H82: =H68*(1-C38) -> 31.74346 | I82: =I68*(1-C38) -> 31.74346
B83: Note B conversion PPS | C83: =MIN(C81,C82) -> 32.497713 | D83: =MIN(D81,D82) -> 32.022252 | E83: =MIN(E81,E82) -> 31.746013 | F83: =MIN(F81,F82) -> 31.743489 | G83: =MIN(G81,G82) -> 31.74346 | H83: =MIN(H81,H82) -> 31.74346 | I83: =MIN(I81,I82) -> 31.74346
B84: Note A shares (current) | C84: 0 | D84: =C33/D80 -> 185808.3 | E84: =C33/E80 -> 186496.07 | F84: =C33/F80 -> 186507.54 | G84: =C33/G80 -> 186507.65 | H84: =C33/H80 -> 186507.65 | I84: =C33/I80 -> 186507.65
B85: Note B shares (current) | C85: 0 | D85: =C36/D83 -> 93684.855 | E85: =C36/E83 -> 94500.057 | F85: =C36/F83 -> 94507.571 | G85: =C36/G83 -> 94507.655 | H85: =C36/H83 -> 94507.656 | I85: =C36/I83 -> 94507.656
B87: Solved Values (from final iteration)
B88: F PPS ($) — solved | C88: =I68 -> 37.345247
B89: F primary new shares — solved | C89: =I69 -> 803315.08
B90: ESOP top-up shares — solved | C90: =I77 -> 589060.59
B91: AD D top-up shares — solved | C91: =I73 -> 13304.204
B92: AD E top-up shares — solved | C92: =I75 -> 31709.924
B93: Note A conversion PPS — solved | C93: =I80 -> 26.808552
B94: Note A shares — solved | C94: =I84 -> 186507.65
B95: Note B conversion PPS — solved | C95: =I83 -> 31.74346
B96: Note B shares — solved | C96: =I85 -> 94507.656
B97: Tender PPS ($) | C97: =C88*C9 -> 31.74346
B98: Tender shares (transferred from founders) | C98: =C8/C97 -> 472538.28
B99: Post-F NCP for D (effective) | C99: =I72 -> 57.672415
B100: Post-F NCP for E (effective) | C100: =I74 -> 48.904722
B101: Post-F FD total (T_F) | C101: =C52+C90+C91+C92+C94+C96+C89 -> 38336366
B102: Our fund F primary shares | C102: =C11/C88 -> 267771.69
B103: F_LEAD F primary shares | C103: =C12/C88 -> 535543.38

Sheet Pro-Forma
B2: Kelvin Dynamics — Pro-Forma Cap Table (Post-Series F)
B3: Shares and ownership % after F closing, AD adjustments, note conversions, and tender
B5: Anti-Dilution Block (Broad-Based WA)
B6: Class | C6: OCP-for-AD | D6: F PPS | E6: Trigger? | F6: NCP (post-F) | G6: New Ratio | H6: As-Converted Shares
B7: Seed | C7: =Assumptions!C16 -> 1 | D7: =Assumptions!C88 -> 37.345247 | E7: =IF(D7<C7,"Yes","No") -> No | F7: =IF(E7="Yes",C7*(Assumptions!C52+Assumptions!C7/C7)/(Assumptions!C52+Assumptions!C7/D7),C7) -> 1 | G7: =C7/F7 -> 1 | H7: =Assumptions!C25/F7 -> 5000000
B8: Series A | C8: =Assumptions!C17 -> 3 | D8: =Assumptions!C88 -> 37.345247 | E8: =IF(D8<C8,"Yes","No") -> No | F8: =IF(E8="Yes",C8*(Assumptions!C52+Assumptions!C7/C8)/(Assumptions!C52+Assumptions!C7/D8),C8) -> 3 | G8: =C8/F8 -> 1 | H8: =Assumptions!C26/F8 -> 5000000
B9: Series B | C9: =Assumptions!C18 -> 10 | D9: =Assumptions!C88 -> 37.345247 | E9: =IF(D9<C9,"Yes","No") -> No | F9: =IF(E9="Yes",C9*(Assumptions!C52+Assumptions!C7/C9)/(Assumptions!C52+Assumptions!C7/D9),C9) -> 10 | G9: =C9/F9 -> 1 | H9: =Assumptions!C27/F9 -> 3000000
B10: Series C | C10: =Assumptions!C19 -> 25 | D10: =Assumptions!C88 -> 37.345247 | E10: =IF(D10<C10,"Yes","No") -> No | F10: =IF(E10="Yes",C10*(Assumptions!C52+Assumptions!C7/C10)/(Assumptions!C52+Assumptions!C7/D10),C10) -> 25 | G10: =C10/F10 -> 1 | H10: =Assumptions!C28/F10 -> 2400000
B11: Series D | C11: =Assumptions!C20 -> 58.118347 | D11: =Assumptions!C88 -> 37.345247 | E11: =IF(D11<C11,"Yes","No") -> Yes | F11: =IF(E11="Yes",C11*(Assumptions!C52+Assumptions!C7/C11)/(Assumptions!C52+Assumptions!C7/D11),C11) -> 57.672415 | G11: =Assumptions!C21/F11 -> 1.0403587 | H11: =Assumptions!C29/F11 -> 1733931.2
B12: Series E | C12: =Assumptions!C22 -> 49.158311 | D12: =Assumptions!C88 -> 37.345247 | E12: =IF(D12<C12,"Yes","No") -> Yes | F12: =IF(E12="Yes",C12*(Assumptions!C52+Assumptions!C7/C12)/(Assumptions!C52+Assumptions!C7/D12),C12) -> 48.904722 | G12: =C12/F12 -> 1.0051854 | H12: =Assumptions!C30/F12 -> 6134376.9
B13: Total AD top-up shares | H13: =SUM(H7:H12)-({A}C43+{A}C44+{A}C45+{A}C46+{A}C47+{A}C48) -> #VALUE!
B15: Convertible Notes Conversion
B16: Note | C16: Principal | D16: Cap-Implied PPS | E16: Discount-Implied PPS | F16: Conversion PPS | G16: Branch | H16: Shares Issued
B17: Note A | C17: =Assumptions!C33 -> 5000000 | D17: =Assumptions!C34/(Assumptions!C52+Assumptions!C90+Assumptions!C96) -> 26.808552 | E17: =Assumptions!C88*(1-Assumptions!C35) -> 29.876198 | F17: =MIN(D17,E17) -> 26.808552 | G17: =IF(D17<=E17,"cap","discount") -> cap | H17: =C17/F17 -> 186507.65
B18: Note B | C18: =Assumptions!C36 -> 3000000 | D18: =Assumptions!C37/(Assumptions!C52+Assumptions!C90+Assumptions!C94) -> 42.788152 | E18: =Assumptions!C88*(1-Assumptions!C38) -> 31.74346 | F18: =MIN(D18,E18) -> 31.74346 | G18: =IF(D18<=E18,"cap","discount") -> discount | H18: =C18/F18 -> 94507.656
B19: Total notes shares | H19: =SUM(H17:H18) -> 281015.3
B21: Secondary Tender (founder share-out → F_LEAD)
B22: Tender PPS (= 0.85 × F_PPS) | C22: =Assumptions!C97 -> 31.74346
B23: Tender size ($) | C23: =Assumptions!C8 -> 15000000
B24: Total tender shares (transferred) | C24: =C23/C22 -> 472538.28
B26: Founder | C26: Pre-F Common | D26: Pro-Rata Share | E26: Tendered to F_LEAD | F26: Post-F Common
B27: F1 (CEO) | C27: =Assumptions!E41 -> 4000000 | D27: =C27/Assumptions!C41 -> 0.5 | E27: =$C$24*D27 -> 236269.14 | F27: =C27-E27 -> 3763730.9
B28: F2 (CTO) | C28: =Assumptions!F41 -> 2500000 | D28: =C28/Assumptions!C41 -> 0.3125 | E28: =$C$24*D28 -> 147668.21 | F28: =C28-E28 -> 2352331.8
B29: F3 (Chief Sci.) | C29: =Assumptions!G41 -> 1500000 | D29: =C29/Assumptions!C41 -> 0.1875 | E29: =$C$24*D29 -> 88600.928 | F29: =C29-E29 -> 1411399.1
B30: Total founders | C30: =SUM(C27:C29) -> 8000000 | D30: =SUM(D27:D29) -> 1 | E30: =SUM(E27:E29) -> 472538.28 | F30: =SUM(F27:F29) -> 7527461.7
B32: F_LEAD secondary common (from tender) | C32: =C24 -> 472538.28
B34: Post-F Cap Table by Stakeholder
B35: Stakeholder | C35: Role / Class | D35: Common (incl. RSAs) | E35: Preferred (as-conv.) | F35: Note-Conv. | G35: F Primary | H35: F Secondary | I35: Total Shares | J35: Ownership %
B36: F1 | C36: Founder (CEO) | D36: =F27 -> 3763730.9 | E36: 0 | F36: 0 | G36: 0 | H36: 0 | I36: =D36+E36+F36+G36+H36 -> 3763730.9 | J36: =I36/I$70 -> 0.098176516
B37: F2 | C37: Founder (CTO) | D37: =F28 -> 2352331.8 | E37: 0 | F37: 0 | G37: 0 | H37: 0 | I37: =D37+E37+F37+G37+H37 -> 2352331.8 | J37: =I37/I$70 -> 0.061360323
B38: F3 | C38: Founder (Chief Sci.) | D38: =F29 -> 1411399.1 | E38: 0 | F38: 0 | G38: 0 | H38: 0 | I38: =D38+E38+F38+G38+H38 -> 1411399.1 | J38: =I38/I$70 -> 0.036816194
B39: E1 | C39: Employee RSA | D39: =Assumptions!C42/10 -> 100000 | E39: 0 | F39: 0 | G39: 0 | H39: 0 | I39: =D39+E39+F39+G39+H39 -> 100000 | J39: =I39/I$70 -> 0.0026084893
B40: E2 | C40: Employee RSA | D40: =Assumptions!C42/10 -> 100000 | E40: 0 | F40: 0 | G40: 0 | H40: 0 | I40: =D40+E40+F40+G40+H40 -> 100000 | J40: =I40/I$70 -> 0.0026084893
B41: E3 | C41: Employee RSA | D41: =Assumptions!C42/10 -> 100000 | E41: 0 | F41: 0 | G41: 0 | H41: 0 | I41: =D41+E41+F41+G41+H41 -> 100000 | J41: =I41/I$70 -> 0.0026084893
B42: E4 | C42: Employee RSA | D42: =Assumptions!C42/10 -> 100000 | E42: 0 | F42: 0 | G42: 0 | H42: 0 | I42: =D42+E42+F42+G42+H42 -> 100000 | J42: =I42/I$70 -> 0.0026084893
B43: E5 | C43: Employee RSA | D43: =Assumptions!C42/10 -> 100000 | E43: 0 | F43: 0 | G43: 0 | H43: 0 | I43: =D43+E43+F43+G43+H43 -> 100000 | J43: =I43/I$70 -> 0.0026084893
B44: E6 | C44: Employee RSA | D44: =Assumptions!C42/10 -> 100000 | E44: 0 | F44: 0 | G44: 0 | H44: 0 | I44: =D44+E44+F44+G44+H44 -> 100000 | J44: =I44/I$70 -> 0.0026084893
B45: E7 | C45: Employee RSA | D45: =Assumptions!C42/10 -> 100000 | E45: 0 | F45: 0 | G45: 0 | H45: 0 | I45: =D45+E45+F45+G45+H45 -> 100000 | J45: =I45/I$70 -> 0.0026084893
B46: E8 | C46: Employee RSA | D46: =Assumptions!C42/10 -> 100000 | E46: 0 | F46: 0 | G46: 0 | H46: 0 | I46: =D46+E46+F46+G46+H46 -> 100000 | J46: =I46/I$70 -> 0.0026084893
B47: E9 | C47: Employee RSA | D47: =Assumptions!C42/10 -> 100000 | E47: 0 | F47: 0 | G47: 0 | H47: 0 | I47: =D47+E47+F47+G47+H47 -> 100000 | J47: =I47/I$70 -> 0.0026084893
B48: E10 | C48: Employee RSA | D48: =Assumptions!C42/10 -> 100000 | E48: 0 | F48: 0 | G48: 0 | H48: 0 | I48: =D48+E48+F48+G48+H48 -> 100000 | J48: =I48/I$70 -> 0.0026084893
B49: SEED1 | C49: Seed pref LP | D49: 0 | E49: =H7 -> 5000000 | F49: 0 | G49: 0 | H49: 0 | I49: =D49+E49+F49+G49+H49 -> 5000000 | J49: =I49/I$70 -> 0.13042446
B50: A1 | C50: Series A pref LP | D50: 0 | E50: =H8 -> 5000000 | F50: 0 | G50: 0 | H50: 0 | I50: =D50+E50+F50+G50+H50 -> 5000000 | J50: =I50/I$70 -> 0.13042446
B51: B1 | C51: Series B pref LP | D51: 0 | E51: =H9 -> 3000000 | F51: 0 | G51: 0 | H51: 0 | I51: =D51+E51+F51+G51+H51 -> 3000000 | J51: =I51/I$70 -> 0.078254678
B52: C1 | C52: Series C pref LP | D52: 0 | E52: =H10 -> 2400000 | F52: 0 | G52: 0 | H52: 0 | I52: =D52+E52+F52+G52+H52 -> 2400000 | J52: =I52/I$70 -> 0.062603743
B53: D1 | C53: Series D pref LP | D53: 0 | E53: =H11 -> 1733931.2 | F53: 0 | G53: 0 | H53: 0 | I53: =D53+E53+F53+G53+H53 -> 1733931.2 | J53: =I53/I$70 -> 0.04522941
B54: E1_INV | C54: Series E pref LP | D54: 0 | E54: =H12*Assumptions!C48/Assumptions!C48*(610267/6102667) -> 613437.99 | F54: 0 | G54: 0 | H54: 0 | I54: =D54+E54+F54+G54+H54 -> 613437.99 | J54: =I54/I$70 -> 0.016001464
B55: E2_INV | C55: Series E pref LP | D55: 0 | E55: =H12*Assumptions!C48/Assumptions!C48*(610267/6102667) -> 613437.99 | F55: 0 | G55: 0 | H55: 0 | I55: =D55+E55+F55+G55+H55 -> 613437.99 | J55: =I55/I$70 -> 0.016001464
B56: E3_INV | C56: Series E pref LP | D56: 0 | E56: =H12*Assumptions!C48/Assumptions!C48*(610267/6102667) -> 613437.99 | F56: 0 | G56: 0 | H56: 0 | I56: =D56+E56+F56+G56+H56 -> 613437.99 | J56: =I56/I$70 -> 0.016001464
B57: E4_INV | C57: Series E pref LP | D57: 0 | E57: =H12*Assumptions!C48/Assumptions!C48*(610267/6102667) -> 613437.99 | F57: 0 | G57: 0 | H57: 0 | I57: =D57+E57+F57+G57+H57 -> 613437.99 | J57: =I57/I$70 -> 0.016001464
B58: E5_INV | C58: Series E pref LP | D58: 0 | E58: =H12*Assumptions!C48/Assumptions!C48*(610267/6102667) -> 613437.99 | F58: 0 | G58: 0 | H58: 0 | I58: =D58+E58+F58+G58+H58 -> 613437.99 | J58: =I58/I$70 -> 0.016001464
B59: E6_INV | C59: Series E pref LP | D59: 0 | E59: =H12*Assumptions!C48/Assumptions!C48*(610267/6102667) -> 613437.99 | F59: 0 | G59: 0 | H59: 0 | I59: =D59+E59+F59+G59+H59 -> 613437.99 | J59: =I59/I$70 -> 0.016001464
B60: E7_INV | C60: Series E pref LP | D60: 0 | E60: =H12*Assumptions!C48/Assumptions!C48*(610267/6102667) -> 613437.99 | F60: 0 | G60: 0 | H60: 0 | I60: =D60+E60+F60+G60+H60 -> 613437.99 | J60: =I60/I$70 -> 0.016001464
B61: E8_INV | C61: Series E pref LP | D61: 0 | E61: =H12*Assumptions!C48/Assumptions!C48*(610267/6102667) -> 613437.99 | F61: 0 | G61: 0 | H61: 0 | I61: =D61+E61+F61+G61+H61 -> 613437.99 | J61: =I61/I$70 -> 0.016001464
B62: E9_INV | C62: Series E pref LP | D62: 0 | E62: =H12*Assumptions!C48/Assumptions!C48*(610267/6102667) -> 613437.99 | F62: 0 | G62: 0 | H62: 0 | I62: =D62+E62+F62+G62+H62 -> 613437.99 | J62: =I62/I$70 -> 0.016001464
B63: E10_INV | C63: Series E pref LP | D63: 0 | E63: =H12*(610264/6102667) -> 613434.98 | F63: 0 | G63: 0 | H63: 0 | I63: =D63+E63+F63+G63+H63 -> 613434.98 | J63: =I63/I$70 -> 0.016001386
B64: NA1 | C64: Note A holder | D64: 0 | E64: 0 | F64: =H17 -> 186507.65 | G64: 0 | H64: 0 | I64: =D64+E64+F64+G64+H64 -> 186507.65 | J64: =I64/I$70 -> 0.004865032
B65: NB1 | C65: Note B holder | D65: 0 | E65: 0 | F65: =H18 -> 94507.656 | G65: 0 | H65: 0 | I65: =D65+E65+F65+G65+H65 -> 94507.656 | J65: =I65/I$70 -> 0.0024652221
B66: F_LEAD | C66: F lead investor | D66: 0 | E66: 0 | F66: 0 | G66: =Assumptions!C103 -> 535543.38 | H66: =C32 -> 472538.28 | I66: =D66+E66+F66+G66+H66 -> 1008081.7 | J66: =I66/I$70 -> 0.026295702
B67: F_FUND | C67: Our fund (F primary) | D67: 0 | E67: 0 | F67: 0 | G67: =Assumptions!C102 -> 267771.69 | H67: 0 | I67: =D67+E67+F67+G67+H67 -> 267771.69 | J67: =I67/I$70 -> 0.0069847959
B68: Pool | C68: Unallocated option pool | D68: =Assumptions!C50+Assumptions!C90 -> 2483727.6 | E68: 0 | F68: 0 | G68: 0 | H68: 0 | I68: =D68+E68+F68+G68+H68 -> 2483727.6 | J68: =I68/I$70 -> 0.064787768
B69: Issued Options | C69: Vested ESOP (employees) | D69: =Assumptions!C49 -> 2500000 | E69: 0 | F69: 0 | G69: 0 | H69: 0 | I69: =D69+E69+F69+G69+H69 -> 2500000 | J69: =I69/I$70 -> 0.065212232
B70: Total post-F FD | D70: =SUM(D36:D69) -> 13511189 | E70: =SUM(E36:E69) -> 23268308 | F70: =SUM(F36:F69) -> 281015.3 | G70: =SUM(G36:G69) -> 803315.08 | H70: =SUM(H36:H69) -> 472538.28 | I70: =SUM(I36:I69) -> 38336366 | J70: =SUM(J36:J69) -> 1
B71: Check | I71: =ROUND(I70-Assumptions!C101,2) -> 0

Sheet Return-Solver
B2: Kelvin Dynamics — Return Solver
B3: Required Series F class ownership % to return 3× / 4× our $10M check, by exit
B5: Inputs (base case)
B6: Our check ($) | C6: =Assumptions!C11 -> 10000000
B7: 3× target ($) | C7: =Assumptions!C64*C6 -> 30000000
B8: 4× target ($) | C8: =Assumptions!D64*C6 -> 40000000
B9: F primary new shares (base) | C9: =Assumptions!C89 -> 803315.08
B10: Post-F FD T_F (base) | C10: =Assumptions!C101 -> 38336366
B12: Required F-Class Ownership % per Exit (incl. F's equilibrium election)
B13: Exit Value | C13: F Class Total $ (waterfall) | D13: F Election (waterfall) | E13: Req. F-Class % for 3× | F13: Req. F-Class % for 4× | G13: Req. Company % for 3× | H13: Req. Company % for 4× | I13: Feasibility
B14: Exit 1: $700M | C14: =Waterfall!C34 -> 30000000 | D14: =Waterfall!C24 -> preference | E14: =$C$7/C14 -> 1 | F14: =$C$8/C14 -> 1.3333333 | G14: =E14*$C$9/$C$10 -> 0.020954388 | H14: =F14*$C$9/$C$10 -> 0.027939184 | I14: =IF(F14>1,"4× infeasible",IF(E14>1,"3× infeasible","Both feasible")) -> 4× infeasible
B15: Exit 2: $1.2B | C15: =Waterfall!D34 -> 30000000 | D15: =Waterfall!D24 -> preference | E15: =$C$7/C15 -> 1 | F15: =$C$8/C15 -> 1.3333333 | G15: =E15*$C$9/$C$10 -> 0.020954388 | H15: =F15*$C$9/$C$10 -> 0.027939184 | I15: =IF(F15>1,"4× infeasible",IF(E15>1,"3× infeasible","Both feasible")) -> 4× infeasible
B16: Exit 3: $2B | C16: =Waterfall!E34 -> 44793811 | D16: =Waterfall!E24 -> convert | E16: =$C$7/C16 -> 0.66973538 | F16: =$C$8/C16 -> 0.8929805 | G16: =E16*$C$9/$C$10 -> 0.014033895 | H16: =F16*$C$9/$C$10 -> 0.01871186 | I16: =IF(F16>1,"4× infeasible",IF(E16>1,"3× infeasible","Both feasible")) -> Both feasible
B17: Exit 4: $4B | C17: =Waterfall!F34 -> 89680111 | D17: =Waterfall!F24 -> convert | E17: =$C$7/C17 -> 0.33452233 | F17: =$C$8/C17 -> 0.44602978 | G17: =E17*$C$9/$C$10 -> 0.0070097107 | H17: =F17*$C$9/$C$10 -> 0.0093462809 | I17: =IF(F17>1,"4× infeasible",IF(E17>1,"3× infeasible","Both feasible")) -> Both feasible
B18: Exit 5: $8B | C18: =Waterfall!G34 -> 1.7930421e+08 | D18: =Waterfall!G24 -> convert | E18: =$C$7/C18 -> 0.16731342 | F18: =$C$8/C18 -> 0.22308456 | G18: =E18*$C$9/$C$10 -> 0.0035059503 | H18: =F18*$C$9/$C$10 -> 0.0046746003 | I18: =IF(F18>1,"4× infeasible",IF(E18>1,"3× infeasible","Both feasible")) -> Both feasible
B20: Reference: at base-case (1/3 of F class) our return = | C20: =Waterfall!C22 -> 700000000 | D20: =Waterfall!D22 -> 1200000000 | E20: =Waterfall!E22 -> 2000000000 | F20: =Waterfall!F22 -> 4000000000 | G20: =Waterfall!G22 -> 8000000000
B21: Our $ proceeds at base-case ownership | C21: =Waterfall!C34*(Assumptions!C11/Assumptions!C7) -> 10000000 | D21: =Waterfall!D34*(Assumptions!C11/Assumptions!C7) -> 10000000 | E21: =Waterfall!E34*(Assumptions!C11/Assumptions!C7) -> 14931270 | F21: =Waterfall!F34*(Assumptions!C11/Assumptions!C7) -> 29893370 | G21: =Waterfall!G34*(Assumptions!C11/Assumptions!C7) -> 59768069
B22: Our MOIC at base-case ownership | C22: =C21/Assumptions!C11 -> 1 | D22: =D21/Assumptions!C11 -> 1 | E22: =E21/Assumptions!C11 -> 1.493127 | F22: =F21/Assumptions!C11 -> 2.989337 | G22: =G21/Assumptions!C11 -> 5.9768069
B24: Notes
B25: F-Class % is share of Series F class (vs F_LEAD's 2/3 + our 1/3 = 100%).
B26: Company % = Required F-Class % × F_class_shares / T_F (post-F FD).
B27: Infeasibility triggered when target exceeds the entire F-class proceeds at that exit.

Sheet Sensitivity
B2: Kelvin Dynamics — Sensitivity (ESOP × Pre-Money @ $2B Exit)
B3: Per-cell fixed-point solve (F PPS, ESOP top-up, AD on D and E, both notes branches)
B5: Our $10M Check — Post-F Ownership %
B6: ESOP refresh ↓ / Pre-money → | C6: =Assumptions!C63 -> 1200000000 | D6: =Assumptions!D63 -> 1400000000 | E6: =Assumptions!E63 -> 1800000000
B7: =Assumptions!C62 -> 0.11 | C7: =M61 -> 0.0081150329 | D7: =M111 -> 0.006985159 | E7: =M161 -> 0.0054637046
B8: =Assumptions!D62 -> 0.13 | C8: =M211 -> 0.0081145933 | D8: =M261 -> 0.0069847959 | E8: =M311 -> 0.0054634358
B9: =Assumptions!E62 -> 0.15 | C9: =M361 -> 0.008113969 | D9: =M411 -> 0.0069842585 | E9: =M461 -> 0.0054630155
B11: Our $10M Check — $ Proceeds at $2B Exit
B12: ESOP refresh ↓ / Pre-money → | C12: =Assumptions!C63 -> 1200000000 | D12: =Assumptions!D63 -> 1400000000 | E12: =Assumptions!E63 -> 1800000000
B13: =Assumptions!C62 -> 0.11 | C13: =M62 -> 17075680 | D13: =M112 -> 14703175 | E13: =M162 -> 11505507
B14: =Assumptions!D62 -> 0.13 | C14: =M212 -> 17351776 | D14: =M262 -> 14931270 | E14: =M312 -> 11674332
B15: =Assumptions!E62 -> 0.15 | C15: =M362 -> 17759653 | D15: =M412 -> 15282139 | E15: =M462 -> 11948552
B17: Our $10M Check — Multiple of Invested Capital (MOIC)
B18: ESOP refresh ↓ / Pre-money → | C18: =Assumptions!C63 -> 1200000000 | D18: =Assumptions!D63 -> 1400000000 | E18: =Assumptions!E63 -> 1800000000
B19: =Assumptions!C62 -> 0.11 | C19: =M62/Assumptions!C11 -> 1.707568 | D19: =M112/Assumptions!C11 -> 1.4703175 | E19: =M162/Assumptions!C11 -> 1.1505507
B20: =Assumptions!D62 -> 0.13 | C20: =M212/Assumptions!C11 -> 1.7351776 | D20: =M262/Assumptions!C11 -> 1.493127 | E20: =M312/Assumptions!C11 -> 1.1674332
B21: =Assumptions!E62 -> 0.15 | C21: =M362/Assumptions!C11 -> 1.7759653 | D21: =M412/Assumptions!C11 -> 1.5282139 | E21: =M462/Assumptions!C11 -> 1.1948552
B30: Scenario 1: ESOP=11%, Pre=$1.2B
B31: Iter → | C31: 0 | D31: 1 | E31: 2 | F31: 3 | G31: 4 | H31: 5
B32: F PPS | C32: =Assumptions!C63/Assumptions!C52 -> 32.770803 | D32: =Assumptions!C63/(Assumptions!C52+C38+C42+C46) -> 32.770803 | E32: =Assumptions!C63/(Assumptions!C52+D38+D42+D46) -> 32.505896 | F32: =Assumptions!C63/(Assumptions!C52+E38+E42+E46) -> 32.503755 | G32: =Assumptions!C63/(Assumptions!C52+F38+F42+F46) -> 32.503738 | H32: =Assumptions!C63/(Assumptions!C52+G38+G42+G46) -> 32.503737
B33: F primary shares | C33: =Assumptions!C7/C32 -> 915449.03 | D33: =Assumptions!C7/D32 -> 915449.03 | E33: =Assumptions!C7/E32 -> 922909.49 | F33: =Assumptions!C7/F32 -> 922970.28 | G33: =Assumptions!C7/G32 -> 922970.78 | H33: =Assumptions!C7/H32 -> 922970.78
B34: NCP_D | C34: =Assumptions!C20*(Assumptions!C52+Assumptions!C7/Assumptions!C20)/(Assumptions!C52+Assumptions!C7/C32) -> 57.500114 | D34: =Assumptions!C20*(Assumptions!C52+Assumptions!C7/Assumptions!C20)/(Assumptions!C52+Assumptions!C7/D32) -> 57.500114 | E34: =Assumptions!C20*(Assumptions!C52+Assumptions!C7/Assumptions!C20)/(Assumptions!C52+Assumptions!C7/E32) -> 57.488687 | F34: =Assumptions!C20*(Assumptions!C52+Assumptions!C7/Assumptions!C20)/(Assumptions!C52+Assumptions!C7/F32) -> 57.488594 | G34: =Assumptions!C20*(Assumptions!C52+Assumptions!C7/Assumptions!C20)/(Assumptions!C52+Assumptions!C7/G32) -> 57.488593 | H34: =Assumptions!C20*(Assumptions!C52+Assumptions!C7/Assumptions!C20)/(Assumptions!C52+Assumptions!C7/H32) -> 57.488593
B35: AD_D shares | C35: =MAX(0,IF(C32<Assumptions!C20,Assumptions!C29/C34-Assumptions!C47,0)) -> 18499.98 | D35: =MAX(0,IF(D32<Assumptions!C20,Assumptions!C29/D34-Assumptions!C47,0)) -> 18499.98 | E35: =MAX(0,IF(E32<Assumptions!C20,Assumptions!C29/E34-Assumptions!C47,0)) -> 18845.664 | F35: =MAX(0,IF(F32<Assumptions!C20,Assumptions!C29/F34-Assumptions!C47,0)) -> 18848.481 | G35: =MAX(0,IF(G32<Assumptions!C20,Assumptions!C29/G34-Assumptions!C47,0)) -> 18848.504 | H35: =MAX(0,IF(H32<Assumptions!C20,Assumptions!C29/H34-Assumptions!C47,0)) -> 18848.504
B36: NCP_E | C36: =Assumptions!C22*(Assumptions!C52+Assumptions!C7/Assumptions!C22)/(Assumptions!C52+Assumptions!C7/C32) -> 48.758616 | D36: =Assumptions!C22*(Assumptions!C52+Assumptions!C7/Assumptions!C22)/(Assumptions!C52+Assumptions!C7/D32) -> 48.758616 | E36: =Assumptions!C22*(Assumptions!C52+Assumptions!C7/Assumptions!C22)/(Assumptions!C52+Assumptions!C7/E32) -> 48.748926 | F36: =Assumptions!C22*(Assumptions!C52+Assumptions!C7/Assumptions!C22)/(Assumptions!C52+Assumptions!C7/F32) -> 48.748847 | G36: =Assumptions!C22*(Assumptions!C52+Assumptions!C7/Assumptions!C22)/(Assumptions!C52+Assumptions!C7/G32) -> 48.748846 | H36: =Assumptions!C22*(Assumptions!C52+Assumptions!C7/Assumptions!C22)/(Assumptions!C52+Assumptions!C7/H32) -> 48.748846
B37: AD_E shares | C37: =MAX(0,IF(C32<Assumptions!C22,Assumptions!C30/C36-Assumptions!C48,0)) -> 50091.764 | D37: =MAX(0,IF(D32<Assumptions!C22,Assumptions!C30/D36-Assumptions!C48,0)) -> 50091.764 | E37: =MAX(0,IF(E32<Assumptions!C22,Assumptions!C30/E36-Assumptions!C48,0)) -> 51314.738 | F37: =MAX(0,IF(F32<Assumptions!C22,Assumptions!C30/F36-Assumptions!C48,0)) -> 51324.705 | G37: =MAX(0,IF(G32<Assumptions!C22,Assumptions!C30/G36-Assumptions!C48,0)) -> 51324.786 | H37: =MAX(0,IF(H32<Assumptions!C22,Assumptions!C30/H36-Assumptions!C48,0)) -> 51324.787
B38: ESOP top-up | C38: =MAX(0,(Assumptions!C62*(Assumptions!C52+C35+C37+C33+C42+C46)-Assumptions!C51)/(1-Assumptions!C62)) -> 0 | D38: =MAX(0,(Assumptions!C62*(Assumptions!C52+D35+D37+D33+D42+D46)-Assumptions!C51)/(1-Assumptions!C62)) -> 0 | E38: =MAX(0,(Assumptions!C62*(Assumptions!C52+E35+E37+E33+E42+E46)-Assumptions!C51)/(1-Assumptions!C62)) -> 0 | F38: =MAX(0,(Assumptions!C62*(Assumptions!C52+F35+F37+F33+F42+F46)-Assumptions!C51)/(1-Assumptions!C62)) -> 0 | G38: =MAX(0,(Assumptions!C62*(Assumptions!C52+G35+G37+G33+G42+G46)-Assumptions!C51)/(1-Assumptions!C62)) -> 0 | H38: =MAX(0,(Assumptions!C62*(Assumptions!C52+H35+H37+H33+H42+H46)-Assumptions!C51)/(1-Assumptions!C62)) -> 0
B39: N_A cap PPS | C39: =Assumptions!C34/(Assumptions!C52+C38+C46) -> 27.309003 | D39: =Assumptions!C34/(Assumptions!C52+C38+C46) -> 27.309003 | E39: =Assumptions!C34/(Assumptions!C52+D38+D46) -> 27.228918 | F39: =Assumptions!C34/(Assumptions!C52+E38+E46) -> 27.228267 | G39: =Assumptions!C34/(Assumptions!C52+F38+F46) -> 27.228262 | H39: =Assumptions!C34/(Assumptions!C52+G38+G46) -> 27.228262
B40: N_A disc PPS | C40: =C32*(1-Assumptions!C35) -> 26.216643 | D40: =D32*(1-Assumptions!C35) -> 26.216643 | E40: =E32*(1-Assumptions!C35) -> 26.004717 | F40: =F32*(1-Assumptions!C35) -> 26.003004 | G40: =G32*(1-Assumptions!C35) -> 26.00299 | H40: =H32*(1-Assumptions!C35) -> 26.00299
B41: N_A conv PPS | C41: =MIN(C39,C40) -> 26.216643 | D41: =MIN(D39,D40) -> 26.216643 | E41: =MIN(E39,E40) -> 26.004717 | F41: =MIN(F39,F40) -> 26.003004 | G41: =MIN(G39,G40) -> 26.00299 | H41: =MIN(H39,H40) -> 26.00299
B42: N_A shares | C42: 0 | D42: =Assumptions!C33/D41 -> 190718.55 | E42: =Assumptions!C33/E41 -> 192272.81 | F42: =Assumptions!C33/F41 -> 192285.48 | G42: =Assumptions!C33/G41 -> 192285.58 | H42: =Assumptions!C33/H41 -> 192285.58
B43: N_B cap PPS | C43: =Assumptions!C37/(Assumptions!C52+C38+C42) -> 43.694405 | D43: =Assumptions!C37/(Assumptions!C52+C38+C42) -> 43.694405 | E43: =Assumptions!C37/(Assumptions!C52+D38+D42) -> 43.468009 | F43: =Assumptions!C37/(Assumptions!C52+E38+E42) -> 43.466173 | G43: =Assumptions!C37/(Assumptions!C52+F38+F42) -> 43.466158 | H43: =Assumptions!C37/(Assumptions!C52+G38+G42) -> 43.466158
B44: N_B disc PPS | C44: =C32*(1-Assumptions!C38) -> 27.855183 | D44: =D32*(1-Assumptions!C38) -> 27.855183 | E44: =E32*(1-Assumptions!C38) -> 27.630012 | F44: =F32*(1-Assumptions!C38) -> 27.628192 | G44: =G32*(1-Assumptions!C38) -> 27.628177 | H44: =H32*(1-Assumptions!C38) -> 27.628177
B45: N_B conv PPS | C45: =MIN(C43,C44) -> 27.855183 | D45: =MIN(D43,D44) -> 27.855183 | E45: =MIN(E43,E44) -> 27.630012 | F45: =MIN(F43,F44) -> 27.628192 | G45: =MIN(G43,G44) -> 27.628177 | H45: =MIN(H43,H44) -> 27.628177
B46: N_B shares | C46: 0 | D46: =Assumptions!C36/D45 -> 107699.89 | E46: =Assumptions!C36/E45 -> 108577.59 | F46: =Assumptions!C36/F45 -> 108584.74 | G46: =Assumptions!C36/G45 -> 108584.8 | H46: =Assumptions!C36/H45 -> 108584.8
B47: Post-F FD (T_F) | H47: =Assumptions!C52+H38+H35+H37+H42+H46+H33 -> 37911975
B49: Mini-waterfall @ $2B exit
B50: Class | C50: Shares | D50: Pref ($) | E50: Iter1 | F50: Iter2 | G50: Iter3 | H50: Iter4 | I50: Convert@final | J50: Final $
B51: Series F | C51: =H33 -> 922970.78 | D51: =Assumptions!C7 -> 30000000 | E51: =IF(D51>((Assumptions!C57+IF(D62=1,C61*C60,0))*C51/(SUM($C$51:$C$57)+C58+C59+IF(D62=1,C60,0))),1,0) -> 0 | F51: =IF(D51>((Assumptions!C57+IF(D62=1,C61*C60,0)-(SUMPRODUCT($D$51:$D$57,$E$51:$E$57)-D51*E51))*C51/((((SUM($C$51:$C$57)-SUMPRODUCT($C$51:$C$57,$E$51:$E$57))-C51*(1-E51))+C58+C59+IF(D62=1,C60,0))+C51)),1,0) -> 0 | G51: =IF(D51>((Assumptions!C57+IF(D62=1,C61*C60,0)-(SUMPRODUCT($D$51:$D$57,$F$51:$F$57)-D51*F51))*C51/((((SUM($C$51:$C$57)-SUMPRODUCT($C$51:$C$57,$F$51:$F$57))-C51*(1-F51))+C58+C59+IF(D62=1,C60,0))+C51)),1,0) -> 0 | H51: =IF(D51>((Assumptions!C57+IF(D62=1,C61*C60,0)-(SUMPRODUCT($D$51:$D$57,$G$51:$G$57)-D51*G51))*C51/((((SUM($C$51:$C$57)-SUMPRODUCT($C$51:$C$57,$G$51:$G$57))-C51*(1-G51))+C58+C59+IF(D62=1,C60,0))+C51)),1,0) -> 0 | I51: =((Assumptions!C57+IF(D62=1,C61*C60,0)-(SUMPRODUCT($D$51:$D$57,$H$51:$H$57)-D51*H51))*C51/((((SUM($C$51:$C$57)-SUMPRODUCT($C$51:$C$57,$H$51:$H$57))-C51*(1-H51))+C58+C59+IF(D62=1,C60,0))+C51)) -> 51227040 | J51: =IF(H51=1,D51,I51) -> 51227040
B52: Series E | C52: =Assumptions!C48+H37 -> 6153991.8 | D52: =Assumptions!C30 -> 300000000 | E52: =IF(D52>((Assumptions!C57+IF(D62=1,C61*C60,0))*C52/(SUM($C$51:$C$57)+C58+C59+IF(D62=1,C60,0))),1,0) -> 0 | F52: =IF(D52>((Assumptions!C57+IF(D62=1,C61*C60,0)-(SUMPRODUCT($D$51:$D$57,$E$51:$E$57)-D52*E52))*C52/((((SUM($C$51:$C$57)-SUMPRODUCT($C$51:$C$57,$E$51:$E$57))-C52*(1-E52))+C58+C59+IF(D62=1,C60,0))+C52)),1,0) -> 0 | G52: =IF(D52>((Assumptions!C57+IF(D62=1,C61*C60,0)-(SUMPRODUCT($D$51:$D$57,$F$51:$F$57)-D52*F52))*C52/((((SUM($C$51:$C$57)-SUMPRODUCT($C$51:$C$57,$F$51:$F$57))-C52*(1-F52))+C58+C59+IF(D62=1,C60,0))+C52)),1,0) -> 0 | H52: =IF(D52>((Assumptions!C57+IF(D62=1,C61*C60,0)-(SUMPRODUCT($D$51:$D$57,$G$51:$G$57)-D52*G52))*C52/((((SUM($C$51:$C$57)-SUMPRODUCT($C$51:$C$57,$G$51:$G$57))-C52*(1-G52))+C58+C59+IF(D62=1,C60,0))+C52)),1,0) -> 0 | I52: =((Assumptions!C57+IF(D62=1,C61*C60,0)-(SUMPRODUCT($D$51:$D$57,$H$51:$H$57)-D52*H52))*C52/((((SUM($C$51:$C$57)-SUMPRODUCT($C$51:$C$57,$H$51:$H$57))-C52*(1-H52))+C58+C59+IF(D62=1,C60,0))+C52)) -> 3.4156096e+08 | J52: =IF(H52=1,D52,I52) -> 3.4156096e+08
B53: Series D | C53: =Assumptions!C47+H35 -> 1739475.5 | D53: =Assumptions!C29 -> 100000000 | E53: =IF(D53>((Assumptions!C57+IF(D62=1,C61*C60,0))*C53/(SUM($C$51:$C$57)+C58+C59+IF(D62=1,C60,0))),1,0) -> 1 | F53: =IF(D53>((Assumptions!C57+IF(D62=1,C61*C60,0)-(SUMPRODUCT($D$51:$D$57,$E$51:$E$57)-D53*E53))*C53/((((SUM($C$51:$C$57)-SUMPRODUCT($C$51:$C$57,$E$51:$E$57))-C53*(1-E53))+C58+C59+IF(D62=1,C60,0))+C53)),1,0) -> 1 | G53: =IF(D53>((Assumptions!C57+IF(D62=1,C61*C60,0)-(SUMPRODUCT($D$51:$D$57,$F$51:$F$57)-D53*F53))*C53/((((SUM($C$51:$C$57)-SUMPRODUCT($C$51:$C$57,$F$51:$F$57))-C53*(1-F53))+C58+C59+IF(D62=1,C60,0))+C53)),1,0) -> 1 | H53: =IF(D53>((Assumptions!C57+IF(D62=1,C61*C60,0)-(SUMPRODUCT($D$51:$D$57,$G$51:$G$57)-D53*G53))*C53/((((SUM($C$51:$C$57)-SUMPRODUCT($C$51:$C$57,$G$51:$G$57))-C53*(1-G53))+C58+C59+IF(D62=1,C60,0))+C53)),1,0) -> 1 | I53: =((Assumptions!C57+IF(D62=1,C61*C60,0)-(SUMPRODUCT($D$51:$D$57,$H$51:$H$57)-D53*H53))*C53/((((SUM($C$51:$C$57)-SUMPRODUCT($C$51:$C$57,$H$51:$H$57))-C53*(1-H53))+C58+C59+IF(D62=1,C60,0))+C53)) -> 96711827 | J53: =IF(H53=1,D53,I53) -> 100000000
B54: Series C | C54: =Assumptions!C46 -> 2400000 | D54: =Assumptions!C28 -> 60000000 | E54: =IF(D54>((Assumptions!C57+IF(D62=1,C61*C60,0))*C54/(SUM($C$51:$C$57)+C58+C59+IF(D62=1,C60,0))),1,0) -> 0 | F54: =IF(D54>((Assumptions!C57+IF(D62=1,C61*C60,0)-(SUMPRODUCT($D$51:$D$57,$E$51:$E$57)-D54*E54))*C54/((((SUM($C$51:$C$57)-SUMPRODUCT($C$51:$C$57,$E$51:$E$57))-C54*(1-E54))+C58+C59+IF(D62=1,C60,0))+C54)),1,0) -> 0 | G54: =IF(D54>((Assumptions!C57+IF(D62=1,C61*C60,0)-(SUMPRODUCT($D$51:$D$57,$F$51:$F$57)-D54*F54))*C54/((((SUM($C$51:$C$57)-SUMPRODUCT($C$51:$C$57,$F$51:$F$57))-C54*(1-F54))+C58+C59+IF(D62=1,C60,0))+C54)),1,0) -> 0 | H54: =IF(D54>((Assumptions!C57+IF(D62=1,C61*C60,0)-(SUMPRODUCT($D$51:$D$57,$G$51:$G$57)-D54*G54))*C54/((((SUM($C$51:$C$57)-SUMPRODUCT($C$51:$C$57,$G$51:$G$57))-C54*(1-G54))+C58+C59+IF(D62=1,C60,0))+C54)),1,0) -> 0 | I54: =((Assumptions!C57+IF(D62=1,C61*C60,0)-(SUMPRODUCT($D$51:$D$57,$H$51:$H$57)-D54*H54))*C54/((((SUM($C$51:$C$57)-SUMPRODUCT($C$51:$C$57,$H$51:$H$57))-C54*(1-H54))+C58+C59+IF(D62=1,C60,0))+C54)) -> 1.3320562e+08 | J54: =IF(H54=1,D54,I54) -> 1.3320562e+08
B55: Series B | C55: =Assumptions!C45 -> 3000000 | D55: =Assumptions!C27 -> 30000000 | E55: =IF(D55>((Assumptions!C57+IF(D62=1,C61*C60,0))*C55/(SUM($C$51:$C$57)+C58+C59+IF(D62=1,C60,0))),1,0) -> 0 | F55: =IF(D55>((Assumptions!C57+IF(D62=1,C61*C60,0)-(SUMPRODUCT($D$51:$D$57,$E$51:$E$57)-D55*E55))*C55/((((SUM($C$51:$C$57)-SUMPRODUCT($C$51:$C$57,$E$51:$E$57))-C55*(1-E55))+C58+C59+IF(D62=1,C60,0))+C55)),1,0) -> 0 | G55: =IF(D55>((Assumptions!C57+IF(D62=1,C61*C60,0)-(SUMPRODUCT($D$51:$D$57,$F$51:$F$57)-D55*F55))*C55/((((SUM($C$51:$C$57)-SUMPRODUCT($C$51:$C$57,$F$51:$F$57))-C55*(1-F55))+C58+C59+IF(D62=1,C60,0))+C55)),1,0) -> 0 | H55: =IF(D55>((Assumptions!C57+IF(D62=1,C61*C60,0)-(SUMPRODUCT($D$51:$D$57,$G$51:$G$57)-D55*G55))*C55/((((SUM($C$51:$C$57)-SUMPRODUCT($C$51:$C$57,$G$51:$G$57))-C55*(1-G55))+C58+C59+IF(D62=1,C60,0))+C55)),1,0) -> 0 | I55: =((Assumptions!C57+IF(D62=1,C61*C60,0)-(SUMPRODUCT($D$51:$D$57,$H$51:$H$57)-D55*H55))*C55/((((SUM($C$51:$C$57)-SUMPRODUCT($C$51:$C$57,$H$51:$H$57))-C55*(1-H55))+C58+C59+IF(D62=1,C60,0))+C55)) -> 1.6650703e+08 | J55: =IF(H55=1,D55,I55) -> 1.6650703e+08
B56: Series A | C56: =Assumptions!C44 -> 5000000 | D56: =Assumptions!C26 -> 15000000 | E56: =IF(D56>((Assumptions!C57+IF(D62=1,C61*C60,0))*C56/(SUM($C$51:$C$57)+C58+C59+IF(D62=1,C60,0))),1,0) -> 0 | F56: =IF(D56>((Assumptions!C57+IF(D62=1,C61*C60,0)-(SUMPRODUCT($D$51:$D$57,$E$51:$E$57)-D56*E56))*C56/((((SUM($C$51:$C$57)-SUMPRODUCT($C$51:$C$57,$E$51:$E$57))-C56*(1-E56))+C58+C59+IF(D62=1,C60,0))+C56)),1,0) -> 0 | G56: =IF(D56>((Assumptions!C57+IF(D62=1,C61*C60,0)-(SUMPRODUCT($D$51:$D$57,$F$51:$F$57)-D56*F56))*C56/((((SUM($C$51:$C$57)-SUMPRODUCT($C$51:$C$57,$F$51:$F$57))-C56*(1-F56))+C58+C59+IF(D62=1,C60,0))+C56)),1,0) -> 0 | H56: =IF(D56>((Assumptions!C57+IF(D62=1,C61*C60,0)-(SUMPRODUCT($D$51:$D$57,$G$51:$G$57)-D56*G56))*C56/((((SUM($C$51:$C$57)-SUMPRODUCT($C$51:$C$57,$G$51:$G$57))-C56*(1-G56))+C58+C59+IF(D62=1,C60,0))+C56)),1,0) -> 0 | I56: =((Assumptions!C57+IF(D62=1,C61*C60,0)-(SUMPRODUCT($D$51:$D$57,$H$51:$H$57)-D56*H56))*C56/((((SUM($C$51:$C$57)-SUMPRODUCT($C$51:$C$57,$H$51:$H$57))-C56*(1-H56))+C58+C59+IF(D62=1,C60,0))+C56)) -> 2.7751171e+08 | J56: =IF(H56=1,D56,I56) -> 2.7751171e+08
B57: Seed | C57: =Assumptions!C43 -> 5000000 | D57: =Assumptions!C25 -> 5000000 | E57: =IF(D57>((Assumptions!C57+IF(D62=1,C61*C60,0))*C57/(SUM($C$51:$C$57)+C58+C59+IF(D62=1,C60,0))),1,0) -> 0 | F57: =IF(D57>((Assumptions!C57+IF(D62=1,C61*C60,0)-(SUMPRODUCT($D$51:$D$57,$E$51:$E$57)-D57*E57))*C57/((((SUM($C$51:$C$57)-SUMPRODUCT($C$51:$C$57,$E$51:$E$57))-C57*(1-E57))+C58+C59+IF(D62=1,C60,0))+C57)),1,0) -> 0 | G57: =IF(D57>((Assumptions!C57+IF(D62=1,C61*C60,0)-(SUMPRODUCT($D$51:$D$57,$F$51:$F$57)-D57*F57))*C57/((((SUM($C$51:$C$57)-SUMPRODUCT($C$51:$C$57,$F$51:$F$57))-C57*(1-F57))+C58+C59+IF(D62=1,C60,0))+C57)),1,0) -> 0 | H57: =IF(D57>((Assumptions!C57+IF(D62=1,C61*C60,0)-(SUMPRODUCT($D$51:$D$57,$G$51:$G$57)-D57*G57))*C57/((((SUM($C$51:$C$57)-SUMPRODUCT($C$51:$C$57,$G$51:$G$57))-C57*(1-G57))+C58+C59+IF(D62=1,C60,0))+C57)),1,0) -> 0 | I57: =((Assumptions!C57+IF(D62=1,C61*C60,0)-(SUMPRODUCT($D$51:$D$57,$H$51:$H$57)-D57*H57))*C57/((((SUM($C$51:$C$57)-SUMPRODUCT($C$51:$C$57,$H$51:$H$57))-C57*(1-H57))+C58+C59+IF(D62=1,C60,0))+C57)) -> 2.7751171e+08 | J57: =IF(H57=1,D57,I57) -> 2.7751171e+08
B58: Notes (combined) | C58: =H42+H46 -> 300870.38 | J58: =(Assumptions!C57+IF(D62=1,C61*C60,0)-SUMPRODUCT($D$51:$D$57,$H$51:$H$57))*C58/((SUM($C$51:$C$57)-SUMPRODUCT($C$51:$C$57,$H$51:$H$57))+C58+C59+IF(D62=1,C60,0)) -> 16699011
B59: Common+RSAs | C59: =Assumptions!C41+Assumptions!C42 -> 9000000 | J59: =(Assumptions!C57+IF(D62=1,C61*C60,0)-SUMPRODUCT($D$51:$D$57,$H$51:$H$57))*C59/((SUM($C$51:$C$57)-SUMPRODUCT($C$51:$C$57,$H$51:$H$57))+C58+C59+IF(D62=1,C60,0)) -> 4.9952108e+08
B60: Our shares (10M / F_PPS) | C60: =Assumptions!C49 -> 2500000 | J60: =IF(D62=1,(Assumptions!C57+IF(D62=1,C61*C60,0)-SUMPRODUCT($D$51:$D$57,$H$51:$H$57))*C60/((SUM($C$51:$C$57)-SUMPRODUCT($C$51:$C$57,$H$51:$H$57))+C58+C59+IF(D62=1,C60,0))-C61*C60,0) -> 1.3625585e+08 | M60: =Assumptions!C11/H32 -> 307656.93
B61: Our ownership % | C61: =Assumptions!C13 -> 1 | M61: =M60/H47 -> 0.0081150329
B62: Our $ proceeds @ $2B | C62: =(Assumptions!C57+C61*C60)/(SUM(C51:C57)+C58+C59+C60) -> 55.598269 | D62: =IF(C62>C61,1,0) -> 1 | M62: =J51*(Assumptions!C11/Assumptions!C7) -> 17075680
B63: Total proceeds (waterfall) | J63: =SUM(J51:J60) -> 2e+09
B64: Check | J64: =ROUND(J63-Assumptions!C57,2) -> 0
B80: Scenario 2: ESOP=11%, Pre=$1.4B
B81: Iter → | C81: 0 | D81: 1 | E81: 2 | F81: 3 | G81: 4 | H81: 5
B82: F PPS | C82: =Assumptions!D63/Assumptions!C52 -> 38.232604 | D82: =Assumptions!D63/(Assumptions!C52+C88+C92+C96) -> 38.232604 | E82: =Assumptions!D63/(Assumptions!C52+D88+D92+D96) -> 37.947203 | F82: =Assumptions!D63/(Assumptions!C52+E88+E92+E96) -> 37.946014 | G82: =Assumptions!D63/(Assumptions!C52+F88+F92+F96) -> 37.946007 | H82: =Assumptions!D63/(Assumptions!C52+G88+G92+G96) -> 37.946007
B83: F primary shares | C83: =Assumptions!C7/C82 -> 784670.59 | D83: =Assumptions!C7/D82 -> 784670.59 | E83: =Assumptions!C7/E82 -> 790572.11 | F83: =Assumptions!C7/F82 -> 790596.88 | G83: =Assumptions!C7/G82 -> 790597.01 | H83: =Assumptions!C7/H82 -> 790597.01
B84: NCP_D | C84: =Assumptions!C20*(Assumptions!C52+Assumptions!C7/Assumptions!C20)/(Assumptions!C52+Assumptions!C7/C82) -> 57.701164 | D84: =Assumptions!C20*(Assumptions!C52+Assumptions!C7/Assumptions!C20)/(Assumptions!C52+Assumptions!C7/D82) -> 57.701164 | E84: =Assumptions!C20*(Assumptions!C52+Assumptions!C7/Assumptions!C20)/(Assumptions!C52+Assumptions!C7/E82) -> 57.692061 | F84: =Assumptions!C20*(Assumptions!C52+Assumptions!C7/Assumptions!C20)/(Assumptions!C52+Assumptions!C7/F82) -> 57.692023 | G84: =Assumptions!C20*(Assumptions!C52+Assumptions!C7/Assumptions!C20)/(Assumptions!C52+Assumptions!C7/G82) -> 57.692022 | H84: =Assumptions!C20*(Assumptions!C52+Assumptions!C7/Assumptions!C20)/(Assumptions!C52+Assumptions!C7/H82) -> 57.692022
B85: AD_D shares | C85: =MAX(0,IF(C82<Assumptions!C20,Assumptions!C29/C84-Assumptions!C47,0)) -> 12440.304 | D85: =MAX(0,IF(D82<Assumptions!C20,Assumptions!C29/D84-Assumptions!C47,0)) -> 12440.304 | E85: =MAX(0,IF(E82<Assumptions!C20,Assumptions!C29/E84-Assumptions!C47,0)) -> 12713.753 | F85: =MAX(0,IF(F82<Assumptions!C20,Assumptions!C29/F84-Assumptions!C47,0)) -> 12714.901 | G85: =MAX(0,IF(G82<Assumptions!C20,Assumptions!C29/G84-Assumptions!C47,0)) -> 12714.907 | H85: =MAX(0,IF(H82<Assumptions!C20,Assumptions!C29/H84-Assumptions!C47,0)) -> 12714.907
B86: NCP_E | C86: =Assumptions!C22*(Assumptions!C52+Assumptions!C7/Assumptions!C22)/(Assumptions!C52+Assumptions!C7/C82) -> 48.9291 | D86: =Assumptions!C22*(Assumptions!C52+Assumptions!C7/Assumptions!C22)/(Assumptions!C52+Assumptions!C7/D82) -> 48.9291 | E86: =Assumptions!C22*(Assumptions!C52+Assumptions!C7/Assumptions!C22)/(Assumptions!C52+Assumptions!C7/E82) -> 48.921381 | F86: =Assumptions!C22*(Assumptions!C52+Assumptions!C7/Assumptions!C22)/(Assumptions!C52+Assumptions!C7/F82) -> 48.921349 | G86: =Assumptions!C22*(Assumptions!C52+Assumptions!C7/Assumptions!C22)/(Assumptions!C52+Assumptions!C7/G82) -> 48.921349 | H86: =Assumptions!C22*(Assumptions!C52+Assumptions!C7/Assumptions!C22)/(Assumptions!C52+Assumptions!C7/H82) -> 48.921349
B87: AD_E shares | C87: =MAX(0,IF(C82<Assumptions!C22,Assumptions!C30/C86-Assumptions!C48,0)) -> 28653.58 | D87: =MAX(0,IF(D82<Assumptions!C22,Assumptions!C30/D86-Assumptions!C48,0)) -> 28653.58 | E87: =MAX(0,IF(E82<Assumptions!C22,Assumptions!C30/E86-Assumptions!C48,0)) -> 29621 | F87: =MAX(0,IF(F82<Assumptions!C22,Assumptions!C30/F86-Assumptions!C48,0)) -> 29625.061 | G87: =MAX(0,IF(G82<Assumptions!C22,Assumptions!C30/G86-Assumptions!C48,0)) -> 29625.083 | H87: =MAX(0,IF(H82<Assumptions!C22,Assumptions!C30/H86-Assumptions!C48,0)) -> 29625.083
B88: ESOP top-up | C88: =MAX(0,(Assumptions!C62*(Assumptions!C52+C85+C87+C83+C92+C96)-Assumptions!C51)/(1-Assumptions!C62)) -> 0 | D88: =MAX(0,(Assumptions!C62*(Assumptions!C52+D85+D87+D83+D92+D96)-Assumptions!C51)/(1-Assumptions!C62)) -> 0 | E88: =MAX(0,(Assumptions!C62*(Assumptions!C52+E85+E87+E83+E92+E96)-Assumptions!C51)/(1-Assumptions!C62)) -> 0 | F88: =MAX(0,(Assumptions!C62*(Assumptions!C52+F85+F87+F83+F92+F96)-Assumptions!C51)/(1-Assumptions!C62)) -> 0 | G88: =MAX(0,(Assumptions!C62*(Assumptions!C52+G85+G87+G83+G92+G96)-Assumptions!C51)/(1-Assumptions!C62)) -> 0 | H88: =MAX(0,(Assumptions!C62*(Assumptions!C52+H85+H87+H83+H92+H96)-Assumptions!C51)/(1-Assumptions!C62)) -> 0
B89: N_A cap PPS | C89: =Assumptions!C34/(Assumptions!C52+C88+C96) -> 27.309003 | D89: =Assumptions!C34/(Assumptions!C52+C88+C96) -> 27.309003 | E89: =Assumptions!C34/(Assumptions!C52+D88+D96) -> 27.24033 | F89: =Assumptions!C34/(Assumptions!C52+E88+E96) -> 27.239815 | G89: =Assumptions!C34/(Assumptions!C52+F88+F96) -> 27.239812 | H89: =Assumptions!C34/(Assumptions!C52+G88+G96) -> 27.239812
B90: N_A disc PPS | C90: =C82*(1-Assumptions!C35) -> 30.586083 | D90: =D82*(1-Assumptions!C35) -> 30.586083 | E90: =E82*(1-Assumptions!C35) -> 30.357762 | F90: =F82*(1-Assumptions!C35) -> 30.356811 | G90: =G82*(1-Assumptions!C35) -> 30.356806 | H90: =H82*(1-Assumptions!C35) -> 30.356806
B91: N_A conv PPS | C91: =MIN(C89,C90) -> 27.309003 | D91: =MIN(D89,D90) -> 27.309003 | E91: =MIN(E89,E90) -> 27.24033 | F91: =MIN(F89,F90) -> 27.239815 | G91: =MIN(G89,G90) -> 27.239812 | H91: =MIN(H89,H90) -> 27.239812
B92: N_A shares | C92: 0 | D92: =Assumptions!C33/D91 -> 183089.81 | E92: =Assumptions!C33/E91 -> 183551.38 | F92: =Assumptions!C33/F91 -> 183554.85 | G92: =Assumptions!C33/G91 -> 183554.86 | H92: =Assumptions!C33/H91 -> 183554.86
B93: N_B cap PPS | C93: =Assumptions!C37/(Assumptions!C52+C88+C92) -> 43.694405 | D93: =Assumptions!C37/(Assumptions!C52+C88+C92) -> 43.694405 | E93: =Assumptions!C37/(Assumptions!C52+D88+D92) -> 43.477019 | F93: =Assumptions!C37/(Assumptions!C52+E88+E92) -> 43.476474 | G93: =Assumptions!C37/(Assumptions!C52+F88+F92) -> 43.47647 | H93: =Assumptions!C37/(Assumptions!C52+G88+G92) -> 43.47647
B94: N_B disc PPS | C94: =C82*(1-Assumptions!C38) -> 32.497713 | D94: =D82*(1-Assumptions!C38) -> 32.497713 | E94: =E82*(1-Assumptions!C38) -> 32.255122 | F94: =F82*(1-Assumptions!C38) -> 32.254112 | G94: =G82*(1-Assumptions!C38) -> 32.254106 | H94: =H82*(1-Assumptions!C38) -> 32.254106
B95: N_B conv PPS | C95: =MIN(C93,C94) -> 32.497713 | D95: =MIN(D93,D94) -> 32.497713 | E95: =MIN(E93,E94) -> 32.255122 | F95: =MIN(F93,F94) -> 32.254112 | G95: =MIN(G93,G94) -> 32.254106 | H95: =MIN(H93,H94) -> 32.254106
B96: N_B shares | C96: 0 | D96: =Assumptions!C36/D95 -> 92314.187 | E96: =Assumptions!C36/E95 -> 93008.483 | F96: =Assumptions!C36/F95 -> 93011.397 | G96: =Assumptions!C36/G95 -> 93011.413 | H96: =Assumptions!C36/H95 -> 93011.413
B97: Post-F FD (T_F) | H97: =Assumptions!C52+H88+H85+H87+H92+H96+H83 -> 37727464
B99: Mini-waterfall @ $2B exit
B100: Class | C100: Shares | D100: Pref ($) | E100: Iter1 | F100: Iter2 | G100: Iter3 | H100: Iter4 | I100: Convert@final | J100: Final $
B101: Series F | C101: =H83 -> 790597.01 | D101: =Assumptions!C7 -> 30000000 | E101: =IF(D101>((Assumptions!C57+IF(D112=1,C111*C110,0))*C101/(SUM($C$101:$C$107)+C108+C109+IF(D112=1,C110,0))),1,0) -> 0 | F101: =IF(D101>((Assumptions!C57+IF(D112=1,C111*C110,0)-(SUMPRODUCT($D$101:$D$107,$E$101:$E$107)-D101*E101))*C101/((((SUM($C$101:$C$107)-SUMPRODUCT($C$101:$C$107,$E$101:$E$107))-C101*(1-E101))+C108+C109+IF(D112=1,C110,0))+C101)),1,0) -> 0 | G101: =IF(D101>((Assumptions!C57+IF(D112=1,C111*C110,0)-(SUMPRODUCT($D$101:$D$107,$F$101:$F$107)-D101*F101))*C101/((((SUM($C$101:$C$107)-SUMPRODUCT($C$101:$C$107,$F$101:$F$107))-C101*(1-F101))+C108+C109+IF(D112=1,C110,0))+C101)),1,0) -> 0 | H101: =IF(D101>((Assumptions!C57+IF(D112=1,C111*C110,0)-(SUMPRODUCT($D$101:$D$107,$G$101:$G$107)-D101*G101))*C101/((((SUM($C$101:$C$107)-SUMPRODUCT($C$101:$C$107,$G$101:$G$107))-C101*(1-G101))+C108+C109+IF(D112=1,C110,0))+C101)),1,0) -> 0 | I101: =((Assumptions!C57+IF(D112=1,C111*C110,0)-(SUMPRODUCT($D$101:$D$107,$H$101:$H$107)-D101*H101))*C101/((((SUM($C$101:$C$107)-SUMPRODUCT($C$101:$C$107,$H$101:$H$107))-C101*(1-H101))+C108+C109+IF(D112=1,C110,0))+C101)) -> 44109526 | J101: =IF(H101=1,D101,I101) -> 44109526
B102: Series E | C102: =Assumptions!C48+H87 -> 6132292.1 | D102: =Assumptions!C30 -> 300000000 | E102: =IF(D102>((Assumptions!C57+IF(D112=1,C111*C110,0))*C102/(SUM($C$101:$C$107)+C108+C109+IF(D112=1,C110,0))),1,0) -> 0 | F102: =IF(D102>((Assumptions!C57+IF(D112=1,C111*C110,0)-(SUMPRODUCT($D$101:$D$107,$E$101:$E$107)-D102*E102))*C102/((((SUM($C$101:$C$107)-SUMPRODUCT($C$101:$C$107,$E$101:$E$107))-C102*(1-E102))+C108+C109+IF(D112=1,C110,0))+C102)),1,0) -> 0 | G102: =IF(D102>((Assumptions!C57+IF(D112=1,C111*C110,0)-(SUMPRODUCT($D$101:$D$107,$F$101:$F$107)-D102*F102))*C102/((((SUM($C$101:$C$107)-SUMPRODUCT($C$101:$C$107,$F$101:$F$107))-C102*(1-F102))+C108+C109+IF(D112=1,C110,0))+C102)),1,0) -> 0 | H102: =IF(D102>((Assumptions!C57+IF(D112=1,C111*C110,0)-(SUMPRODUCT($D$101:$D$107,$G$101:$G$107)-D102*G102))*C102/((((SUM($C$101:$C$107)-SUMPRODUCT($C$101:$C$107,$G$101:$G$107))-C102*(1-G102))+C108+C109+IF(D112=1,C110,0))+C102)),1,0) -> 0 | I102: =((Assumptions!C57+IF(D112=1,C111*C110,0)-(SUMPRODUCT($D$101:$D$107,$H$101:$H$107)-D102*H102))*C102/((((SUM($C$101:$C$107)-SUMPRODUCT($C$101:$C$107,$H$101:$H$107))-C102*(1-H102))+C108+C109+IF(D112=1,C110,0))+C102)) -> 3.4213701e+08 | J102: =IF(H102=1,D102,I102) -> 3.4213701e+08
B103: Series D | C103: =Assumptions!C47+H85 -> 1733341.9 | D103: =Assumptions!C29 -> 100000000 | E103: =IF(D103>((Assumptions!C57+IF(D112=1,C111*C110,0))*C103/(SUM($C$101:$C$107)+C108+C109+IF(D112=1,C110,0))),1,0) -> 1 | F103: =IF(D103>((Assumptions!C57+IF(D112=1,C111*C110,0)-(SUMPRODUCT($D$101:$D$107,$E$101:$E$107)-D103*E103))*C103/((((SUM($C$101:$C$107)-SUMPRODUCT($C$101:$C$107,$E$101:$E$107))-C103*(1-E103))+C108+C109+IF(D112=1,C110,0))+C103)),1,0) -> 1 | G103: =IF(D103>((Assumptions!C57+IF(D112=1,C111*C110,0)-(SUMPRODUCT($D$101:$D$107,$F$101:$F$107)-D103*F103))*C103/((((SUM($C$101:$C$107)-SUMPRODUCT($C$101:$C$107,$F$101:$F$107))-C103*(1-F103))+C108+C109+IF(D112=1,C110,0))+C103)),1,0) -> 1 | H103: =IF(D103>((Assumptions!C57+IF(D112=1,C111*C110,0)-(SUMPRODUCT($D$101:$D$107,$G$101:$G$107)-D103*G103))*C103/((((SUM($C$101:$C$107)-SUMPRODUCT($C$101:$C$107,$G$101:$G$107))-C103*(1-G103))+C108+C109+IF(D112=1,C110,0))+C103)),1,0) -> 1 | I103: =((Assumptions!C57+IF(D112=1,C111*C110,0)-(SUMPRODUCT($D$101:$D$107,$H$101:$H$107)-D103*H103))*C103/((((SUM($C$101:$C$107)-SUMPRODUCT($C$101:$C$107,$H$101:$H$107))-C103*(1-H103))+C108+C109+IF(D112=1,C110,0))+C103)) -> 96867045 | J103: =IF(H103=1,D103,I103) -> 100000000
B104: Series C | C104: =Assumptions!C46 -> 2400000 | D104: =Assumptions!C28 -> 60000000 | E104: =IF(D104>((Assumptions!C57+IF(D112=1,C111*C110,0))*C104/(SUM($C$101:$C$107)+C108+C109+IF(D112=1,C110,0))),1,0) -> 0 | F104: =IF(D104>((Assumptions!C57+IF(D112=1,C111*C110,0)-(SUMPRODUCT($D$101:$D$107,$E$101:$E$107)-D104*E104))*C104/((((SUM($C$101:$C$107)-SUMPRODUCT($C$101:$C$107,$E$101:$E$107))-C104*(1-E104))+C108+C109+IF(D112=1,C110,0))+C104)),1,0) -> 0 | G104: =IF(D104>((Assumptions!C57+IF(D112=1,C111*C110,0)-(SUMPRODUCT($D$101:$D$107,$F$101:$F$107)-D104*F104))*C104/((((SUM($C$101:$C$107)-SUMPRODUCT($C$101:$C$107,$F$101:$F$107))-C104*(1-F104))+C108+C109+IF(D112=1,C110,0))+C104)),1,0) -> 0 | H104: =IF(D104>((Assumptions!C57+IF(D112=1,C111*C110,0)-(SUMPRODUCT($D$101:$D$107,$G$101:$G$107)-D104*G104))*C104/((((SUM($C$101:$C$107)-SUMPRODUCT($C$101:$C$107,$G$101:$G$107))-C104*(1-G104))+C108+C109+IF(D112=1,C110,0))+C104)),1,0) -> 0 | I104: =((Assumptions!C57+IF(D112=1,C111*C110,0)-(SUMPRODUCT($D$101:$D$107,$H$101:$H$107)-D104*H104))*C104/((((SUM($C$101:$C$107)-SUMPRODUCT($C$101:$C$107,$H$101:$H$107))-C104*(1-H104))+C108+C109+IF(D112=1,C110,0))+C104)) -> 1.3390243e+08 | J104: =IF(H104=1,D104,I104) -> 1.3390243e+08
B105: Series B | C105: =Assumptions!C45 -> 3000000 | D105: =Assumptions!C27 -> 30000000 | E105: =IF(D105>((Assumptions!C57+IF(D112=1,C111*C110,0))*C105/(SUM($C$101:$C$107)+C108+C109+IF(D112=1,C110,0))),1,0) -> 0 | F105: =IF(D105>((Assumptions!C57+IF(D112=1,C111*C110,0)-(SUMPRODUCT($D$101:$D$107,$E$101:$E$107)-D105*E105))*C105/((((SUM($C$101:$C$107)-SUMPRODUCT($C$101:$C$107,$E$101:$E$107))-C105*(1-E105))+C108+C109+IF(D112=1,C110,0))+C105)),1,0) -> 0 | G105: =IF(D105>((Assumptions!C57+IF(D112=1,C111*C110,0)-(SUMPRODUCT($D$101:$D$107,$F$101:$F$107)-D105*F105))*C105/((((SUM($C$101:$C$107)-SUMPRODUCT($C$101:$C$107,$F$101:$F$107))-C105*(1-F105))+C108+C109+IF(D112=1,C110,0))+C105)),1,0) -> 0 | H105: =IF(D105>((Assumptions!C57+IF(D112=1,C111*C110,0)-(SUMPRODUCT($D$101:$D$107,$G$101:$G$107)-D105*G105))*C105/((((SUM($C$101:$C$107)-SUMPRODUCT($C$101:$C$107,$G$101:$G$107))-C105*(1-G105))+C108+C109+IF(D112=1,C110,0))+C105)),1,0) -> 0 | I105: =((Assumptions!C57+IF(D112=1,C111*C110,0)-(SUMPRODUCT($D$101:$D$107,$H$101:$H$107)-D105*H105))*C105/((((SUM($C$101:$C$107)-SUMPRODUCT($C$101:$C$107,$H$101:$H$107))-C105*(1-H105))+C108+C109+IF(D112=1,C110,0))+C105)) -> 1.6737804e+08 | J105: =IF(H105=1,D105,I105) -> 1.6737804e+08
B106: Series A | C106: =Assumptions!C44 -> 5000000 | D106: =Assumptions!C26 -> 15000000 | E106: =IF(D106>((Assumptions!C57+IF(D112=1,C111*C110,0))*C106/(SUM($C$101:$C$107)+C108+C109+IF(D112=1,C110,0))),1,0) -> 0 | F106: =IF(D106>((Assumptions!C57+IF(D112=1,C111*C110,0)-(SUMPRODUCT($D$101:$D$107,$E$101:$E$107)-D106*E106))*C106/((((SUM($C$101:$C$107)-SUMPRODUCT($C$101:$C$107,$E$101:$E$107))-C106*(1-E106))+C108+C109+IF(D112=1,C110,0))+C106)),1,0) -> 0 | G106: =IF(D106>((Assumptions!C57+IF(D112=1,C111*C110,0)-(SUMPRODUCT($D$101:$D$107,$F$101:$F$107)-D106*F106))*C106/((((SUM($C$101:$C$107)-SUMPRODUCT($C$101:$C$107,$F$101:$F$107))-C106*(1-F106))+C108+C109+IF(D112=1,C110,0))+C106)),1,0) -> 0 | H106: =IF(D106>((Assumptions!C57+IF(D112=1,C111*C110,0)-(SUMPRODUCT($D$101:$D$107,$G$101:$G$107)-D106*G106))*C106/((((SUM($C$101:$C$107)-SUMPRODUCT($C$101:$C$107,$G$101:$G$107))-C106*(1-G106))+C108+C109+IF(D112=1,C110,0))+C106)),1,0) -> 0 | I106: =((Assumptions!C57+IF(D112=1,C111*C110,0)-(SUMPRODUCT($D$101:$D$107,$H$101:$H$107)-D106*H106))*C106/((((SUM($C$101:$C$107)-SUMPRODUCT($C$101:$C$107,$H$101:$H$107))-C106*(1-H106))+C108+C109+IF(D112=1,C110,0))+C106)) -> 2.789634e+08 | J106: =IF(H106=1,D106,I106) -> 2.789634e+08
B107: Seed | C107: =Assumptions!C43 -> 5000000 | D107: =Assumptions!C25 -> 5000000 | E107: =IF(D107>((Assumptions!C57+IF(D112=1,C111*C110,0))*C107/(SUM($C$101:$C$107)+C108+C109+IF(D112=1,C110,0))),1,0) -> 0 | F107: =IF(D107>((Assumptions!C57+IF(D112=1,C111*C110,0)-(SUMPRODUCT($D$101:$D$107,$E$101:$E$107)-D107*E107))*C107/((((SUM($C$101:$C$107)-SUMPRODUCT($C$101:$C$107,$E$101:$E$107))-C107*(1-E107))+C108+C109+IF(D112=1,C110,0))+C107)),1,0) -> 0 | G107: =IF(D107>((Assumptions!C57+IF(D112=1,C111*C110,0)-(SUMPRODUCT($D$101:$D$107,$F$101:$F$107)-D107*F107))*C107/((((SUM($C$101:$C$107)-SUMPRODUCT($C$101:$C$107,$F$101:$F$107))-C107*(1-F107))+C108+C109+IF(D112=1,C110,0))+C107)),1,0) -> 0 | H107: =IF(D107>((Assumptions!C57+IF(D112=1,C111*C110,0)-(SUMPRODUCT($D$101:$D$107,$G$101:$G$107)-D107*G107))*C107/((((SUM($C$101:$C$107)-SUMPRODUCT($C$101:$C$107,$G$101:$G$107))-C107*(1-G107))+C108+C109+IF(D112=1,C110,0))+C107)),1,0) -> 0 | I107: =((Assumptions!C57+IF(D112=1,C111*C110,0)-(SUMPRODUCT($D$101:$D$107,$H$101:$H$107)-D107*H107))*C107/((((SUM($C$101:$C$107)-SUMPRODUCT($C$101:$C$107,$H$101:$H$107))-C107*(1-H107))+C108+C109+IF(D112=1,C110,0))+C107)) -> 2.789634e+08 | J107: =IF(H107=1,D107,I107) -> 2.789634e+08
B108: Notes (combined) | C108: =H92+H96 -> 276566.28 | J108: =(Assumptions!C57+IF(D112=1,C111*C110,0)-SUMPRODUCT($D$101:$D$107,$H$101:$H$107))*C108/((SUM($C$101:$C$107)-SUMPRODUCT($C$101:$C$107,$H$101:$H$107))+C108+C109+IF(D112=1,C110,0)) -> 15430374
B109: Common+RSAs | C109: =Assumptions!C41+Assumptions!C42 -> 9000000 | J109: =(Assumptions!C57+IF(D112=1,C111*C110,0)-SUMPRODUCT($D$101:$D$107,$H$101:$H$107))*C109/((SUM($C$101:$C$107)-SUMPRODUCT($C$101:$C$107,$H$101:$H$107))+C108+C109+IF(D112=1,C110,0)) -> 5.0213412e+08
B110: Our shares (10M / F_PPS) | C110: =Assumptions!C49 -> 2500000 | J110: =IF(D112=1,(Assumptions!C57+IF(D112=1,C111*C110,0)-SUMPRODUCT($D$101:$D$107,$H$101:$H$107))*C110/((SUM($C$101:$C$107)-SUMPRODUCT($C$101:$C$107,$H$101:$H$107))+C108+C109+IF(D112=1,C110,0))-C111*C110,0) -> 1.369817e+08 | M110: =Assumptions!C11/H82 -> 263532.34
B111: Our ownership % | C111: =Assumptions!C13 -> 1 | M111: =M110/H97 -> 0.006985159
B112: Our $ proceeds @ $2B | C112: =(Assumptions!C57+C111*C110)/(SUM(C101:C107)+C108+C109+C110) -> 55.884557 | D112: =IF(C112>C111,1,0) -> 1 | M112: =J101*(Assumptions!C11/Assumptions!C7) -> 14703175
B113: Total proceeds (waterfall) | J113: =SUM(J101:J110) -> 2000000000
B114: Check | J114: =ROUND(J113-Assumptions!C57,2) -> 0
B130: Scenario 3: ESOP=11%, Pre=$1.8B
B131: Iter → | C131: 0 | D131: 1 | E131: 2 | F131: 3 | G131: 4 | H131: 5
B132: F PPS | C132: =Assumptions!E63/Assumptions!C52 -> 49.156205 | D132: =Assumptions!E63/(Assumptions!C52+C138+C142+C146) -> 49.156205 | E132: =Assumptions!E63/(Assumptions!C52+D138+D142+D146) -> 48.816405 | F132: =Assumptions!E63/(Assumptions!C52+E138+E142+E146) -> 48.815268 | G132: =Assumptions!E63/(Assumptions!C52+F138+F142+F146) -> 48.815262 | H132: =Assumptions!E63/(Assumptions!C52+G138+G142+G146) -> 48.815262
B133: F primary shares | C133: =Assumptions!C7/C132 -> 610299.35 | D133: =Assumptions!C7/D132 -> 610299.35 | E133: =Assumptions!C7/E132 -> 614547.51 | F133: =Assumptions!C7/F132 -> 614561.83 | G133: =Assumptions!C7/G132 -> 614561.89 | H133: =Assumptions!C7/H132 -> 614561.9
B134: NCP_D | C134: =Assumptions!C20*(Assumptions!C52+Assumptions!C7/Assumptions!C20)/(Assumptions!C52+Assumptions!C7/C132) -> 57.971427 | D134: =Assumptions!C20*(Assumptions!C52+Assumptions!C7/Assumptions!C20)/(Assumptions!C52+Assumptions!C7/D132) -> 57.971427 | E134: =Assumptions!C20*(Assumptions!C52+Assumptions!C7/Assumptions!C20)/(Assumptions!C52+Assumptions!C7/E132) -> 57.964812 | F134: =Assumptions!C20*(Assumptions!C52+Assumptions!C7/Assumptions!C20)/(Assumptions!C52+Assumptions!C7/F132) -> 57.96479 | G134: =Assumptions!C20*(Assumptions!C52+Assumptions!C7/Assumptions!C20)/(Assumptions!C52+Assumptions!C7/G132) -> 57.96479 | H134: =Assumptions!C20*(Assumptions!C52+Assumptions!C7/Assumptions!C20)/(Assumptions!C52+Assumptions!C7/H132) -> 57.96479
B135: AD_D shares | C135: =MAX(0,IF(C132<Assumptions!C20,Assumptions!C29/C134-Assumptions!C47,0)) -> 4360.7361 | D135: =MAX(0,IF(D132<Assumptions!C20,Assumptions!C29/D134-Assumptions!C47,0)) -> 4360.7361 | E135: =MAX(0,IF(E132<Assumptions!C20,Assumptions!C29/E134-Assumptions!C47,0)) -> 4557.5766 | F135: =MAX(0,IF(F132<Assumptions!C20,Assumptions!C29/F134-Assumptions!C47,0)) -> 4558.2398 | G135: =MAX(0,IF(G132<Assumptions!C20,Assumptions!C29/G134-Assumptions!C47,0)) -> 4558.243 | H135: =MAX(0,IF(H132<Assumptions!C20,Assumptions!C29/H134-Assumptions!C47,0)) -> 4558.243
B136: NCP_E | C136: =Assumptions!C22*(Assumptions!C52+Assumptions!C7/Assumptions!C22)/(Assumptions!C52+Assumptions!C7/C132) -> 49.158276 | D136: =Assumptions!C22*(Assumptions!C52+Assumptions!C7/Assumptions!C22)/(Assumptions!C52+Assumptions!C7/D132) -> 49.158276 | E136: =Assumptions!C22*(Assumptions!C52+Assumptions!C7/Assumptions!C22)/(Assumptions!C52+Assumptions!C7/E132) -> 49.152668 | F136: =Assumptions!C22*(Assumptions!C52+Assumptions!C7/Assumptions!C22)/(Assumptions!C52+Assumptions!C7/F132) -> 49.152649 | G136: =Assumptions!C22*(Assumptions!C52+Assumptions!C7/Assumptions!C22)/(Assumptions!C52+Assumptions!C7/G132) -> 49.152649 | H136: =Assumptions!C22*(Assumptions!C52+Assumptions!C7/Assumptions!C22)/(Assumptions!C52+Assumptions!C7/H132) -> 49.152649
B137: AD_E shares | C137: =MAX(0,IF(C132<Assumptions!C22,Assumptions!C30/C136-Assumptions!C48,0)) -> 69.334613 | D137: =MAX(0,IF(D132<Assumptions!C22,Assumptions!C30/D136-Assumptions!C48,0)) -> 69.334613 | E137: =MAX(0,IF(E132<Assumptions!C22,Assumptions!C30/E136-Assumptions!C48,0)) -> 765.72529 | F137: =MAX(0,IF(F132<Assumptions!C22,Assumptions!C30/F136-Assumptions!C48,0)) -> 768.07159 | G137: =MAX(0,IF(G132<Assumptions!C22,Assumptions!C30/G136-Assumptions!C48,0)) -> 768.08302 | H137: =MAX(0,IF(H132<Assumptions!C22,Assumptions!C30/H136-Assumptions!C48,0)) -> 768.08307
B138: ESOP top-up | C138: =MAX(0,(Assumptions!C62*(Assumptions!C52+C135+C137+C133+C142+C146)-Assumptions!C51)/(1-Assumptions!C62)) -> 0 | D138: =MAX(0,(Assumptions!C62*(Assumptions!C52+D135+D137+D133+D142+D146)-Assumptions!C51)/(1-Assumptions!C62)) -> 0 | E138: =MAX(0,(Assumptions!C62*(Assumptions!C52+E135+E137+E133+E142+E146)-Assumptions!C51)/(1-Assumptions!C62)) -> 0 | F138: =MAX(0,(Assumptions!C62*(Assumptions!C52+F135+F137+F133+F142+F146)-Assumptions!C51)/(1-Assumptions!C62)) -> 0 | G138: =MAX(0,(Assumptions!C62*(Assumptions!C52+G135+G137+G133+G142+G146)-Assumptions!C51)/(1-Assumptions!C62)) -> 0 | H138: =MAX(0,(Assumptions!C62*(Assumptions!C52+H135+H137+H133+H142+H146)-Assumptions!C51)/(1-Assumptions!C62)) -> 0
B139: N_A cap PPS | C139: =Assumptions!C34/(Assumptions!C52+C138+C146) -> 27.309003 | D139: =Assumptions!C34/(Assumptions!C52+C138+C146) -> 27.309003 | E139: =Assumptions!C34/(Assumptions!C52+D138+D146) -> 27.255561 | F139: =Assumptions!C34/(Assumptions!C52+E138+E146) -> 27.255189 | G139: =Assumptions!C34/(Assumptions!C52+F138+F146) -> 27.255188 | H139: =Assumptions!C34/(Assumptions!C52+G138+G146) -> 27.255188
B140: N_A disc PPS | C140: =C132*(1-Assumptions!C35) -> 39.324964 | D140: =D132*(1-Assumptions!C35) -> 39.324964 | E140: =E132*(1-Assumptions!C35) -> 39.053124 | F140: =F132*(1-Assumptions!C35) -> 39.052214 | G140: =G132*(1-Assumptions!C35) -> 39.05221 | H140: =H132*(1-Assumptions!C35) -> 39.05221
B141: N_A conv PPS | C141: =MIN(C139,C140) -> 27.309003 | D141: =MIN(D139,D140) -> 27.309003 | E141: =MIN(E139,E140) -> 27.255561 | F141: =MIN(F139,F140) -> 27.255189 | G141: =MIN(G139,G140) -> 27.255188 | H141: =MIN(H139,H140) -> 27.255188
B142: N_A shares | C142: 0 | D142: =Assumptions!C33/D141 -> 183089.81 | E142: =Assumptions!C33/E141 -> 183448.8 | F142: =Assumptions!C33/F141 -> 183451.3 | G142: =Assumptions!C33/G141 -> 183451.31 | H142: =Assumptions!C33/H141 -> 183451.31
B143: N_B cap PPS | C143: =Assumptions!C37/(Assumptions!C52+C138+C142) -> 43.694405 | D143: =Assumptions!C37/(Assumptions!C52+C138+C142) -> 43.694405 | E143: =Assumptions!C37/(Assumptions!C52+D138+D142) -> 43.477019 | F143: =Assumptions!C37/(Assumptions!C52+E138+E142) -> 43.476595 | G143: =Assumptions!C37/(Assumptions!C52+F138+F142) -> 43.476592 | H143: =Assumptions!C37/(Assumptions!C52+G138+G142) -> 43.476592
B144: N_B disc PPS | C144: =C132*(1-Assumptions!C38) -> 41.782774 | D144: =D132*(1-Assumptions!C38) -> 41.782774 | E144: =E132*(1-Assumptions!C38) -> 41.493944 | F144: =F132*(1-Assumptions!C38) -> 41.492978 | G144: =G132*(1-Assumptions!C38) -> 41.492973 | H144: =H132*(1-Assumptions!C38) -> 41.492973
...

Sheet Waterfall
B2: Kelvin Dynamics — Exit Waterfall (5 Scenarios × 7 Election Cells)
B3: 1× non-participating preferred with conversion election; notes ride convert pool
B5: Class Reference Schedule
B6: Class | C6: Shares (post-F) | D6: Liquidation Pref ($)
B7: Series F | C7: =Assumptions!C89 -> 803315.08 | D7: =Assumptions!C7 -> 30000000
B8: Series E | C8: ='Pro-Forma'!H12 -> 6134376.9 | D8: =Assumptions!C30 -> 300000000
B9: Series D | C9: ='Pro-Forma'!H11 -> 1733931.2 | D9: =Assumptions!C29 -> 100000000
B10: Series C | C10: ='Pro-Forma'!H10 -> 2400000 | D10: =Assumptions!C28 -> 60000000
B11: Series B | C11: ='Pro-Forma'!H9 -> 3000000 | D11: =Assumptions!C27 -> 30000000
B12: Series A | C12: ='Pro-Forma'!H8 -> 5000000 | D12: =Assumptions!C26 -> 15000000
B13: Seed | C13: ='Pro-Forma'!H7 -> 5000000 | D13: =Assumptions!C25 -> 5000000
B14: Notes A+B (combined) | C14: ='Pro-Forma'!H17+'Pro-Forma'!H18 -> 281015.3 | D14: 0
B15: Common + RSAs + F_LEAD secondary | C15: =Assumptions!C41+Assumptions!C42 -> 9000000 | D15: 0
B16: Issued options (vested, ITM only) | C16: =Assumptions!C49 -> 2500000 | D16: 0
B17: Option strike ($) | C17: =Assumptions!C13 -> 1
B18: Total pref ($, max if all take pref) | D18: =SUM(D7:D13) -> 540000000
B19: Total convert pool (priced + common + notes + ITM opts) | C19: =SUM(C7:C16) -> 35852639
B21: Exit Scenarios — Final Elections and Proceeds
B22: Exit Value ($) | C22: =Assumptions!C55 -> 700000000 | D22: =Assumptions!C56 -> 1200000000 | E22: =Assumptions!C57 -> 2000000000 | F22: =Assumptions!C58 -> 4000000000 | G22: =Assumptions!C59 -> 8000000000
B23: Class
B24: Series F | C24: =IF(H52=1,"preference","convert") -> preference | D24: =IF(H67=1,"preference","convert") -> preference | E24: =IF(H82=1,"preference","convert") -> convert | F24: =IF(H97=1,"preference","convert") -> convert | G24: =IF(H112=1,"preference","convert") -> convert
B25: Series E | C25: =IF(H53=1,"preference","convert") -> preference | D25: =IF(H68=1,"preference","convert") -> preference | E25: =IF(H83=1,"preference","convert") -> convert | F25: =IF(H98=1,"preference","convert") -> convert | G25: =IF(H113=1,"preference","convert") -> convert
B26: Series D | C26: =IF(H54=1,"preference","convert") -> preference | D26: =IF(H69=1,"preference","convert") -> preference | E26: =IF(H84=1,"preference","convert") -> preference | F26: =IF(H99=1,"preference","convert") -> convert | G26: =IF(H114=1,"preference","convert") -> convert
B27: Series C | C27: =IF(H55=1,"preference","convert") -> preference | D27: =IF(H70=1,"preference","convert") -> convert | E27: =IF(H85=1,"preference","convert") -> convert | F27: =IF(H100=1,"preference","convert") -> convert | G27: =IF(H115=1,"preference","convert") -> convert
B28: Series B | C28: =IF(H56=1,"preference","convert") -> preference | D28: =IF(H71=1,"preference","convert") -> convert | E28: =IF(H86=1,"preference","convert") -> convert | F28: =IF(H101=1,"preference","convert") -> convert | G28: =IF(H116=1,"preference","convert") -> convert
B29: Series A | C29: =IF(H57=1,"preference","convert") -> convert | D29: =IF(H72=1,"preference","convert") -> convert | E29: =IF(H87=1,"preference","convert") -> convert | F29: =IF(H102=1,"preference","convert") -> convert | G29: =IF(H117=1,"preference","convert") -> convert
B30: Seed | C30: =IF(H58=1,"preference","convert") -> convert | D30: =IF(H73=1,"preference","convert") -> convert | E30: =IF(H88=1,"preference","convert") -> convert | F30: =IF(H103=1,"preference","convert") -> convert | G30: =IF(H118=1,"preference","convert") -> convert
B32: Proceeds Matrix ($)
B33: Class | C33: $700M | D33: $1.2B | E33: $2B | F33: $4B | G33: $8B
B34: Series F | C34: =J52 -> 30000000 | D34: =J67 -> 30000000 | E34: =J82 -> 44793811 | F34: =J97 -> 89680111 | G34: =J112 -> 1.7930421e+08
B35: Series E | C35: =J53 -> 300000000 | D35: =J68 -> 300000000 | E35: =J83 -> 3.4206021e+08 | F35: =J98 -> 6.8482669e+08 | G35: =J113 -> 1.3692256e+09
B36: Series D | C36: =J54 -> 100000000 | D36: =J69 -> 100000000 | E36: =J84 -> 100000000 | F36: =J99 -> 1.935718e+08 | G36: =J114 -> 3.8702269e+08
B37: Series C | C37: =J55 -> 60000000 | D37: =J70 -> 68209373 | E37: =J85 -> 1.3382688e+08 | F37: =J100 -> 2.6793007e+08 | G37: =J115 -> 5.3569279e+08
B38: Series B | C38: =J56 -> 30000000 | D38: =J71 -> 85261716 | E38: =J86 -> 1.6728359e+08 | F38: =J101 -> 3.3491259e+08 | G38: =J116 -> 6.6961599e+08
B39: Series A | C39: =J57 -> 41894282 | D39: =J72 -> 1.4210286e+08 | E39: =J87 -> 2.7880599e+08 | F39: =J102 -> 5.5818765e+08 | G39: =J117 -> 1.1160266e+09
B40: Seed | C40: =J58 -> 41894282 | D40: =J73 -> 1.4210286e+08 | E40: =J88 -> 2.7880599e+08 | F40: =J103 -> 5.5818765e+08 | G40: =J118 -> 1.1160266e+09
B41: Notes A+B | C41: =J60 -> 2354586.9 | D41: =J75 -> 7986615.6 | E41: =J90 -> 15669750 | F41: =J105 -> 31371854 | G41: =J120 -> 62724113
B42: Common + RSAs + F_LEAD sec. | C42: =J61 -> 75409708 | D42: =J76 -> 2.5578515e+08 | E42: =J91 -> 5.0185078e+08 | F42: =J106 -> 1.0047378e+09 | G42: =J121 -> 2.008848e+09
B43: Issued options (net of strike) | C43: =J62 -> 18447141 | D43: =J77 -> 68551430 | E43: =J92 -> 1.36903e+08 | F43: =J107 -> 2.7659382e+08 | G43: =J122 -> 5.5551332e+08
B44: Total | C44: =SUM(C34:C43) -> 700000000 | D44: =SUM(D34:D43) -> 1200000000 | E44: =SUM(E34:E43) -> 2e+09 | F44: =SUM(F34:F43) -> 4e+09 | G44: =SUM(G34:G43) -> 8e+09
B45: Check | C45: =ROUND(C44-C22,2) -> 0 | D45: =ROUND(D44-D22,2) -> 0 | E45: =ROUND(E44-E22,2) -> 0 | F45: =ROUND(F44-F22,2) -> 0 | G45: =ROUND(G44-G22,2) -> 0
B50: Iteration block: $700M
B51: Class | C51: Shares | D51: Pref ($) | E51: Ind iter1 | F51: Ind iter2 | G51: Ind iter3 | H51: Ind iter4 | I51: Convert@iter4 | J51: Final $ proceeds
B52: =B7 -> Series F | C52: =C7 -> 803315.08 | D52: =D7 -> 30000000 | E52: =IF(D52>(($C$22+IF($D$59=1,$C$17*$C$16,0))*C52/(SUM($C$7:$C$13)+$C$14+$C$15+IF($D$59=1,$C$16,0))),1,0) -> 1 | F52: =IF(D52>(($C$22+IF($D$59=1,$C$17*$C$16,0)-(SUMPRODUCT($D$52:$D$58,$E$52:$E$58)-D52*E52))*C52/((((SUM($C$52:$C$58)-SUMPRODUCT($C$52:$C$58,$E$52:$E$58))-C52*(1-E52))+$C$14+$C$15+IF($D$59=1,$C$16,0))+C52)),1,0) -> 1 | G52: =IF(D52>(($C$22+IF($D$59=1,$C$17*$C$16,0)-(SUMPRODUCT($D$52:$D$58,$F$52:$F$58)-D52*F52))*C52/((((SUM($C$52:$C$58)-SUMPRODUCT($C$52:$C$58,$F$52:$F$58))-C52*(1-F52))+$C$14+$C$15+IF($D$59=1,$C$16,0))+C52)),1,0) -> 1 | H52: =IF(D52>(($C$22+IF($D$59=1,$C$17*$C$16,0)-(SUMPRODUCT($D$52:$D$58,$G$52:$G$58)-D52*G52))*C52/((((SUM($C$52:$C$58)-SUMPRODUCT($C$52:$C$58,$G$52:$G$58))-C52*(1-G52))+$C$14+$C$15+IF($D$59=1,$C$16,0))+C52)),1,0) -> 1 | I52: =(($C$22+IF($D$59=1,$C$17*$C$16,0)-(SUMPRODUCT($D$52:$D$58,$H$52:$H$58)-D52*H52))*C52/((((SUM($C$52:$C$58)-SUMPRODUCT($C$52:$C$58,$H$52:$H$58))-C52*(1-H52))+$C$14+$C$15+IF($D$59=1,$C$16,0))+C52)) -> 7558535.1 | J52: =IF(H52=1,D52,I52) -> 30000000
B53: =B8 -> Series E | C53: =C8 -> 6134376.9 | D53: =D8 -> 300000000 | E53: =IF(D53>(($C$22+IF($D$59=1,$C$17*$C$16,0))*C53/(SUM($C$7:$C$13)+$C$14+$C$15+IF($D$59=1,$C$16,0))),1,0) -> 1 | F53: =IF(D53>(($C$22+IF($D$59=1,$C$17*$C$16,0)-(SUMPRODUCT($D$52:$D$58,$E$52:$E$58)-D53*E53))*C53/((((SUM($C$52:$C$58)-SUMPRODUCT($C$52:$C$58,$E$52:$E$58))-C53*(1-E53))+$C$14+$C$15+IF($D$59=1,$C$16,0))+C53)),1,0) -> 1 | G53: =IF(D53>(($C$22+IF($D$59=1,$C$17*$C$16,0)-(SUMPRODUCT($D$52:$D$58,$F$52:$F$58)-D53*F53))*C53/((((SUM($C$52:$C$58)-SUMPRODUCT($C$52:$C$58,$F$52:$F$58))-C53*(1-F53))+$C$14+$C$15+IF($D$59=1,$C$16,0))+C53)),1,0) -> 1 | H53: =IF(D53>(($C$22+IF($D$59=1,$C$17*$C$16,0)-(SUMPRODUCT($D$52:$D$58,$G$52:$G$58)-D53*G53))*C53/((((SUM($C$52:$C$58)-SUMPRODUCT($C$52:$C$58,$G$52:$G$58))-C53*(1-G53))+$C$14+$C$15+IF($D$59=1,$C$16,0))+C53)),1,0) -> 1 | I53: =(($C$22+IF($D$59=1,$C$17*$C$16,0)-(SUMPRODUCT($D$52:$D$58,$H$52:$H$58)-D53*H53))*C53/((((SUM($C$52:$C$58)-SUMPRODUCT($C$52:$C$58,$H$52:$H$58))-C53*(1-H53))+$C$14+$C$15+IF($D$59=1,$C$16,0))+C53)) -> 1.0602885e+08 | J53: =IF(H53=1,D53,I53) -> 300000000
B54: =B9 -> Series D | C54: =C9 -> 1733931.2 | D54: =D9 -> 100000000 | E54: =IF(D54>(($C$22+IF($D$59=1,$C$17*$C$16,0))*C54/(SUM($C$7:$C$13)+$C$14+$C$15+IF($D$59=1,$C$16,0))),1,0) -> 1 | F54: =IF(D54>(($C$22+IF($D$59=1,$C$17*$C$16,0)-(SUMPRODUCT($D$52:$D$58,$E$52:$E$58)-D54*E54))*C54/((((SUM($C$52:$C$58)-SUMPRODUCT($C$52:$C$58,$E$52:$E$58))-C54*(1-E54))+$C$14+$C$15+IF($D$59=1,$C$16,0))+C54)),1,0) -> 1 | G54: =IF(D54>(($C$22+IF($D$59=1,$C$17*$C$16,0)-(SUMPRODUCT($D$52:$D$58,$F$52:$F$58)-D54*F54))*C54/((((SUM($C$52:$C$58)-SUMPRODUCT($C$52:$C$58,$F$52:$F$58))-C54*(1-F54))+$C$14+$C$15+IF($D$59=1,$C$16,0))+C54)),1,0) -> 1 | H54: =IF(D54>(($C$22+IF($D$59=1,$C$17*$C$16,0)-(SUMPRODUCT($D$52:$D$58,$G$52:$G$58)-D54*G54))*C54/((((SUM($C$52:$C$58)-SUMPRODUCT($C$52:$C$58,$G$52:$G$58))-C54*(1-G54))+$C$14+$C$15+IF($D$59=1,$C$16,0))+C54)),1,0) -> 1 | I54: =(($C$22+IF($D$59=1,$C$17*$C$16,0)-(SUMPRODUCT($D$52:$D$58,$H$52:$H$58)-D54*H54))*C54/((((SUM($C$52:$C$58)-SUMPRODUCT($C$52:$C$58,$H$52:$H$58))-C54*(1-H54))+$C$14+$C$15+IF($D$59=1,$C$16,0))+C54)) -> 20830818 | J54: =IF(H54=1,D54,I54) -> 100000000
B55: =B10 -> Series C | C55: =C10 -> 2400000 | D55: =D10 -> 60000000 | E55: =IF(D55>(($C$22+IF($D$59=1,$C$17*$C$16,0))*C55/(SUM($C$7:$C$13)+$C$14+$C$15+IF($D$59=1,$C$16,0))),1,0) -> 1 | F55: =IF(D55>(($C$22+IF($D$59=1,$C$17*$C$16,0)-(SUMPRODUCT($D$52:$D$58,$E$52:$E$58)-D55*E55))*C55/((((SUM($C$52:$C$58)-SUMPRODUCT($C$52:$C$58,$E$52:$E$58))-C55*(1-E55))+$C$14+$C$15+IF($D$59=1,$C$16,0))+C55)),1,0) -> 1 | G55: =IF(D55>(($C$22+IF($D$59=1,$C$17*$C$16,0)-(SUMPRODUCT($D$52:$D$58,$F$52:$F$58)-D55*F55))*C55/((((SUM($C$52:$C$58)-SUMPRODUCT($C$52:$C$58,$F$52:$F$58))-C55*(1-F55))+$C$14+$C$15+IF($D$59=1,$C$16,0))+C55)),1,0) -> 1 | H55: =IF(D55>(($C$22+IF($D$59=1,$C$17*$C$16,0)-(SUMPRODUCT($D$52:$D$58,$G$52:$G$58)-D55*G55))*C55/((((SUM($C$52:$C$58)-SUMPRODUCT($C$52:$C$58,$G$52:$G$58))-C55*(1-G55))+$C$14+$C$15+IF($D$59=1,$C$16,0))+C55)),1,0) -> 1 | I55: =(($C$22+IF($D$59=1,$C$17*$C$16,0)-(SUMPRODUCT($D$52:$D$58,$H$52:$H$58)-D55*H55))*C55/((((SUM($C$52:$C$58)-SUMPRODUCT($C$52:$C$58,$H$52:$H$58))-C55*(1-H55))+$C$14+$C$15+IF($D$59=1,$C$16,0))+C55)) -> 24068468 | J55: =IF(H55=1,D55,I55) -> 60000000
B56: =B11 -> Series B | C56: =C11 -> 3000000 | D56: =D11 -> 30000000 | E56: =IF(D56>(($C$22+IF($D$59=1,$C$17*$C$16,0))*C56/(SUM($C$7:$C$13)+$C$14+$C$15+IF($D$59=1,$C$16,0))),1,0) -> 0 | F56: =IF(D56>(($C$22+IF($D$59=1,$C$17*$C$16,0)-(SUMPRODUCT($D$52:$D$58,$E$52:$E$58)-D56*E56))*C56/((((SUM($C$52:$C$58)-SUMPRODUCT($C$52:$C$58,$E$52:$E$58))-C56*(1-E56))+$C$14+$C$15+IF($D$59=1,$C$16,0))+C56)),1,0) -> 1 | G56: =IF(D56>(($C$22+IF($D$59=1,$C$17*$C$16,0)-(SUMPRODUCT($D$52:$D$58,$F$52:$F$58)-D56*F56))*C56/((((SUM($C$52:$C$58)-SUMPRODUCT($C$52:$C$58,$F$52:$F$58))-C56*(1-F56))+$C$14+$C$15+IF($D$59=1,$C$16,0))+C56)),1,0) -> 1 | H56: =IF(D56>(($C$22+IF($D$59=1,$C$17*$C$16,0)-(SUMPRODUCT($D$52:$D$58,$G$52:$G$58)-D56*G56))*C56/((((SUM($C$52:$C$58)-SUMPRODUCT($C$52:$C$58,$G$52:$G$58))-C56*(1-G56))+$C$14+$C$15+IF($D$59=1,$C$16,0))+C56)),1,0) -> 1 | I56: =(($C$22+IF($D$59=1,$C$17*$C$16,0)-(SUMPRODUCT($D$52:$D$58,$H$52:$H$58)-D56*H56))*C56/((((SUM($C$52:$C$58)-SUMPRODUCT($C$52:$C$58,$H$52:$H$58))-C56*(1-H56))+$C$14+$C$15+IF($D$59=1,$C$16,0))+C56)) -> 25725338 | J56: =IF(H56=1,D56,I56) -> 30000000
B57: =B12 -> Series A | C57: =C12 -> 5000000 | D57: =D12 -> 15000000 | E57: =IF(D57>(($C$22+IF($D$59=1,$C$17*$C$16,0))*C57/(SUM($C$7:$C$13)+$C$14+$C$15+IF($D$59=1,$C$16,0))),1,0) -> 0 | F57: =IF(D57>(($C$22+IF($D$59=1,$C$17*$C$16,0)-(SUMPRODUCT($D$52:$D$58,$E$52:$E$58)-D57*E57))*C57/((((SUM($C$52:$C$58)-SUMPRODUCT($C$52:$C$58,$E$52:$E$58))-C57*(1-E57))+$C$14+$C$15+IF($D$59=1,$C$16,0))+C57)),1,0) -> 0 | G57: =IF(D57>(($C$22+IF($D$59=1,$C$17*$C$16,0)-(SUMPRODUCT($D$52:$D$58,$F$52:$F$58)-D57*F57))*C57/((((SUM($C$52:$C$58)-SUMPRODUCT($C$52:$C$58,$F$52:$F$58))-C57*(1-F57))+$C$14+$C$15+IF($D$59=1,$C$16,0))+C57)),1,0) -> 0 | H57: =IF(D57>(($C$22+IF($D$59=1,$C$17*$C$16,0)-(SUMPRODUCT($D$52:$D$58,$G$52:$G$58)-D57*G57))*C57/((((SUM($C$52:$C$58)-SUMPRODUCT($C$52:$C$58,$G$52:$G$58))-C57*(1-G57))+$C$14+$C$15+IF($D$59=1,$C$16,0))+C57)),1,0) -> 0 | I57: =(($C$22+IF($D$59=1,$C$17*$C$16,0)-(SUMPRODUCT($D$52:$D$58,$H$52:$H$58)-D57*H57))*C57/((((SUM($C$52:$C$58)-SUMPRODUCT($C$52:$C$58,$H$52:$H$58))-C57*(1-H57))+$C$14+$C$15+IF($D$59=1,$C$16,0))+C57)) -> 41894282 | J57: =IF(H57=1,D57,I57) -> 41894282
B58: =B13 -> Seed | C58: =C13 -> 5000000 | D58: =D13 -> 5000000 | E58: =IF(D58>(($C$22+IF($D$59=1,$C$17*$C$16,0))*C58/(SUM($C$7:$C$13)+$C$14+$C$15+IF($D$59=1,$C$16,0))),1,0) -> 0 | F58: =IF(D58>(($C$22+IF($D$59=1,$C$17*$C$16,0)-(SUMPRODUCT($D$52:$D$58,$E$52:$E$58)-D58*E58))*C58/((((SUM($C$52:$C$58)-SUMPRODUCT($C$52:$C$58,$E$52:$E$58))-C58*(1-E58))+$C$14+$C$15+IF($D$59=1,$C$16,0))+C58)),1,0) -> 0 | G58: =IF(D58>(($C$22+IF($D$59=1,$C$17*$C$16,0)-(SUMPRODUCT($D$52:$D$58,$F$52:$F$58)-D58*F58))*C58/((((SUM($C$52:$C$58)-SUMPRODUCT($C$52:$C$58,$F$52:$F$58))-C58*(1-F58))+$C$14+$C$15+IF($D$59=1,$C$16,0))+C58)),1,0) -> 0 | H58: =IF(D58>(($C$22+IF($D$59=1,$C$17*$C$16,0)-(SUMPRODUCT($D$52:$D$58,$G$52:$G$58)-D58*G58))*C58/((((SUM($C$52:$C$58)-SUMPRODUCT($C$52:$C$58,$G$52:$G$58))-C58*(1-G58))+$C$14+$C$15+IF($D$59=1,$C$16,0))+C58)),1,0) -> 0 | I58: =(($C$22+IF($D$59=1,$C$17*$C$16,0)-(SUMPRODUCT($D$52:$D$58,$H$52:$H$58)-D58*H58))*C58/((((SUM($C$52:$C$58)-SUMPRODUCT($C$52:$C$58,$H$52:$H$58))-C58*(1-H58))+$C$14+$C$15+IF($D$59=1,$C$16,0))+C58)) -> 41894282 | J58: =IF(H58=1,D58,I58) -> 41894282
B59: Aggregates | C59: =($C$22+$C$17*$C$16)/(SUM($C$7:$C$13)+$C$14+$C$15+$C$16) -> 19.594095 | D59: =IF(C59>$C$17,1,0) -> 1
B60: Notes (combined) | C60: =$C$14 -> 281015.3 | J60: =($C$22+IF($D$59=1,$C$17*$C$16,0)-SUMPRODUCT($D$52:$D$58,$H$52:$H$58))*$C$14/((SUM($C$52:$C$58)-SUMPRODUCT($C$52:$C$58,$H$52:$H$58))+$C$14+$C$15+IF($D$59=1,$C$16,0)) -> 2354586.9
B61: Common+RSAs+F_LEAD sec | C61: =$C$15 -> 9000000 | J61: =($C$22+IF($D$59=1,$C$17*$C$16,0)-SUMPRODUCT($D$52:$D$58,$H$52:$H$58))*$C$15/((SUM($C$52:$C$58)-SUMPRODUCT($C$52:$C$58,$H$52:$H$58))+$C$14+$C$15+IF($D$59=1,$C$16,0)) -> 75409708
B62: Issued options (net) | C62: =$C$16 -> 2500000 | J62: =IF($D$59=1,($C$22+IF($D$59=1,$C$17*$C$16,0)-SUMPRODUCT($D$52:$D$58,$H$52:$H$58))*$C$16/((SUM($C$52:$C$58)-SUMPRODUCT($C$52:$C$58,$H$52:$H$58))+$C$14+$C$15+IF($D$59=1,$C$16,0))-$C$17*$C$16,0) -> 18447141
B63: Total proceeds | J63: =SUM(J52:J62) -> 700000000
B64: Check | J64: =ROUND(J63-$C$22,2) -> 0
B65: Iteration block: $1.2B
B66: Class | C66: Shares | D66: Pref ($) | E66: Ind iter1 | F66: Ind iter2 | G66: Ind iter3 | H66: Ind iter4 | I66: Convert@iter4 | J66: Final $ proceeds
B67: =B7 -> Series F | C67: =C7 -> 803315.08 | D67: =D7 -> 30000000 | E67: =IF(D67>(($D$22+IF($D$74=1,$C$17*$C$16,0))*C67/(SUM($C$7:$C$13)+$C$14+$C$15+IF($D$74=1,$C$16,0))),1,0) -> 1 | F67: =IF(D67>(($D$22+IF($D$74=1,$C$17*$C$16,0)-(SUMPRODUCT($D$67:$D$73,$E$67:$E$73)-D67*E67))*C67/((((SUM($C$67:$C$73)-SUMPRODUCT($C$67:$C$73,$E$67:$E$73))-C67*(1-E67))+$C$14+$C$15+IF($D$74=1,$C$16,0))+C67)),1,0) -> 1 | G67: =IF(D67>(($D$22+IF($D$74=1,$C$17*$C$16,0)-(SUMPRODUCT($D$67:$D$73,$F$67:$F$73)-D67*F67))*C67/((((SUM($C$67:$C$73)-SUMPRODUCT($C$67:$C$73,$F$67:$F$73))-C67*(1-F67))+$C$14+$C$15+IF($D$74=1,$C$16,0))+C67)),1,0) -> 1 | H67: =IF(D67>(($D$22+IF($D$74=1,$C$17*$C$16,0)-(SUMPRODUCT($D$67:$D$73,$G$67:$G$73)-D67*G67))*C67/((((SUM($C$67:$C$73)-SUMPRODUCT($C$67:$C$73,$G$67:$G$73))-C67*(1-G67))+$C$14+$C$15+IF($D$74=1,$C$16,0))+C67)),1,0) -> 1 | I67: =(($D$22+IF($D$74=1,$C$17*$C$16,0)-(SUMPRODUCT($D$67:$D$73,$H$67:$H$73)-D67*H67))*C67/((((SUM($C$67:$C$73)-SUMPRODUCT($C$67:$C$73,$H$67:$H$73))-C67*(1-H67))+$C$14+$C$15+IF($D$74=1,$C$16,0))+C67)) -> 23036476 | J67: =IF(H67=1,D67,I67) -> 30000000
B68: =B8 -> Series E | C68: =C8 -> 6134376.9 | D68: =D8 -> 300000000 | E68: =IF(D68>(($D$22+IF($D$74=1,$C$17*$C$16,0))*C68/(SUM($C$7:$C$13)+$C$14+$C$15+IF($D$74=1,$C$16,0))),1,0) -> 1 | F68: =IF(D68>(($D$22+IF($D$74=1,$C$17*$C$16,0)-(SUMPRODUCT($D$67:$D$73,$E$67:$E$73)-D68*E68))*C68/((((SUM($C$67:$C$73)-SUMPRODUCT($C$67:$C$73,$E$67:$E$73))-C68*(1-E68))+$C$14+$C$15+IF($D$74=1,$C$16,0))+C68)),1,0) -> 1 | G68: =IF(D68>(($D$22+IF($D$74=1,$C$17*$C$16,0)-(SUMPRODUCT($D$67:$D$73,$F$67:$F$73)-D68*F68))*C68/((((SUM($C$67:$C$73)-SUMPRODUCT($C$67:$C$73,$F$67:$F$73))-C68*(1-F68))+$C$14+$C$15+IF($D$74=1,$C$16,0))+C68)),1,0) -> 1 | H68: =IF(D68>(($D$22+IF($D$74=1,$C$17*$C$16,0)-(SUMPRODUCT($D$67:$D$73,$G$67:$G$73)-D68*G68))*C68/((((SUM($C$67:$C$73)-SUMPRODUCT($C$67:$C$73,$G$67:$G$73))-C68*(1-G68))+$C$14+$C$15+IF($D$74=1,$C$16,0))+C68)),1,0) -> 1 | I68: =(($D$22+IF($D$74=1,$C$17*$C$16,0)-(SUMPRODUCT($D$67:$D$73,$H$67:$H$73)-D68*H68))*C68/((((SUM($C$67:$C$73)-SUMPRODUCT($C$67:$C$73,$H$67:$H$73))-C68*(1-H68))+$C$14+$C$15+IF($D$74=1,$C$16,0))+C68)) -> 1.9747987e+08 | J68: =IF(H68=1,D68,I68) -> 300000000
B69: =B9 -> Series D | C69: =C9 -> 1733931.2 | D69: =D9 -> 100000000 | E69: =IF(D69>(($D$22+IF($D$74=1,$C$17*$C$16,0))*C69/(SUM($C$7:$C$13)+$C$14+$C$15+IF($D$74=1,$C$16,0))),1,0) -> 1 | F69: =IF(D69>(($D$22+IF($D$74=1,$C$17*$C$16,0)-(SUMPRODUCT($D$67:$D$73,$E$67:$E$73)-D69*E69))*C69/((((SUM($C$67:$C$73)-SUMPRODUCT($C$67:$C$73,$E$67:$E$73))-C69*(1-E69))+$C$14+$C$15+IF($D$74=1,$C$16,0))+C69)),1,0) -> 1 | G69: =IF(D69>(($D$22+IF($D$74=1,$C$17*$C$16,0)-(SUMPRODUCT($D$67:$D$73,$F$67:$F$73)-D69*F69))*C69/((((SUM($C$67:$C$73)-SUMPRODUCT($C$67:$C$73,$F$67:$F$73))-C69*(1-F69))+$C$14+$C$15+IF($D$74=1,$C$16,0))+C69)),1,0) -> 1 | H69: =IF(D69>(($D$22+IF($D$74=1,$C$17*$C$16,0)-(SUMPRODUCT($D$67:$D$73,$G$67:$G$73)-D69*G69))*C69/((((SUM($C$67:$C$73)-SUMPRODUCT($C$67:$C$73,$G$67:$G$73))-C69*(1-G69))+$C$14+$C$15+IF($D$74=1,$C$16,0))+C69)),1,0) -> 1 | I69: =(($D$22+IF($D$74=1,$C$17*$C$16,0)-(SUMPRODUCT($D$67:$D$73,$H$67:$H$73)-D69*H69))*C69/((((SUM($C$67:$C$73)-SUMPRODUCT($C$67:$C$73,$H$67:$H$73))-C69*(1-H69))+$C$14+$C$15+IF($D$74=1,$C$16,0))+C69)) -> 52320864 | J69: =IF(H69=1,D69,I69) -> 100000000
B70: =B10 -> Series C | C70: =C10 -> 2400000 | D70: =D10 -> 60000000 | E70: =IF(D70>(($D$22+IF($D$74=1,$C$17*$C$16,0))*C70/(SUM($C$7:$C$13)+$C$14+$C$15+IF($D$74=1,$C$16,0))),1,0) -> 0 | F70: =IF(D70>(($D$22+IF($D$74=1,$C$17*$C$16,0)-(SUMPRODUCT($D$67:$D$73,$E$67:$E$73)-D70*E70))*C70/((((SUM($C$67:$C$73)-SUMPRODUCT($C$67:$C$73,$E$67:$E$73))-C70*(1-E70))+$C$14+$C$15+IF($D$74=1,$C$16,0))+C70)),1,0) -> 0 | G70: =IF(D70>(($D$22+IF($D$74=1,$C$17*$C$16,0)-(SUMPRODUCT($D$67:$D$73,$F$67:$F$73)-D70*F70))*C70/((((SUM($C$67:$C$73)-SUMPRODUCT($C$67:$C$73,$F$67:$F$73))-C70*(1-F70))+$C$14+$C$15+IF($D$74=1,$C$16,0))+C70)),1,0) -> 0 | H70: =IF(D70>(($D$22+IF($D$74=1,$C$17*$C$16,0)-(SUMPRODUCT($D$67:$D$73,$G$67:$G$73)-D70*G70))*C70/((((SUM($C$67:$C$73)-SUMPRODUCT($C$67:$C$73,$G$67:$G$73))-C70*(1-G70))+$C$14+$C$15+IF($D$74=1,$C$16,0))+C70)),1,0) -> 0 | I70: =(($D$22+IF($D$74=1,$C$17*$C$16,0)-(SUMPRODUCT($D$67:$D$73,$H$67:$H$73)-D70*H70))*C70/((((SUM($C$67:$C$73)-SUMPRODUCT($C$67:$C$73,$H$67:$H$73))-C70*(1-H70))+$C$14+$C$15+IF($D$74=1,$C$16,0))+C70)) -> 68209373 | J70: =IF(H70=1,D70,I70) -> 68209373
B71: =B11 -> Series B | C71: =C11 -> 3000000 | D71: =D11 -> 30000000 | E71: =IF(D71>(($D$22+IF($D$74=1,$C$17*$C$16,0))*C71/(SUM($C$7:$C$13)+$C$14+$C$15+IF($D$74=1,$C$16,0))),1,0) -> 0 | F71: =IF(D71>(($D$22+IF($D$74=1,$C$17*$C$16,0)-(SUMPRODUCT($D$67:$D$73,$E$67:$E$73)-D71*E71))*C71/((((SUM($C$67:$C$73)-SUMPRODUCT($C$67:$C$73,$E$67:$E$73))-C71*(1-E71))+$C$14+$C$15+IF($D$74=1,$C$16,0))+C71)),1,0) -> 0 | G71: =IF(D71>(($D$22+IF($D$74=1,$C$17*$C$16,0)-(SUMPRODUCT($D$67:$D$73,$F$67:$F$73)-D71*F71))*C71/((((SUM($C$67:$C$73)-SUMPRODUCT($C$67:$C$73,$F$67:$F$73))-C71*(1-F71))+$C$14+$C$15+IF($D$74=1,$C$16,0))+C71)),1,0) -> 0 | H71: =IF(D71>(($D$22+IF($D$74=1,$C$17*$C$16,0)-(SUMPRODUCT($D$67:$D$73,$G$67:$G$73)-D71*G71))*C71/((((SUM($C$67:$C$73)-SUMPRODUCT($C$67:$C$73,$G$67:$G$73))-C71*(1-G71))+$C$14+$C$15+IF($D$74=1,$C$16,0))+C71)),1,0) -> 0 | I71: =(($D$22+IF($D$74=1,$C$17*$C$16,0)-(SUMPRODUCT($D$67:$D$73,$H$67:$H$73)-D71*H71))*C71/((((SUM($C$67:$C$73)-SUMPRODUCT($C$67:$C$73,$H$67:$H$73))-C71*(1-H71))+$C$14+$C$15+IF($D$74=1,$C$16,0))+C71)) -> 85261716 | J71: =IF(H71=1,D71,I71) -> 85261716
B72: =B12 -> Series A | C72: =C12 -> 5000000 | D72: =D12 -> 15000000 | E72: =IF(D72>(($D$22+IF($D$74=1,$C$17*$C$16,0))*C72/(SUM($C$7:$C$13)+$C$14+$C$15+IF($D$74=1,$C$16,0))),1,0) -> 0 | F72: =IF(D72>(($D$22+IF($D$74=1,$C$17*$C$16,0)-(SUMPRODUCT($D$67:$D$73,$E$67:$E$73)-D72*E72))*C72/((((SUM($C$67:$C$73)-SUMPRODUCT($C$67:$C$73,$E$67:$E$73))-C72*(1-E72))+$C$14+$C$15+IF($D$74=1,$C$16,0))+C72)),1,0) -> 0 | G72: =IF(D72>(($D$22+IF($D$74=1,$C$17*$C$16,0)-(SUMPRODUCT($D$67:$D$73,$F$67:$F$73)-D72*F72))*C72/((((SUM($C$67:$C$73)-SUMPRODUCT($C$67:$C$73,$F$67:$F$73))-C72*(1-F72))+$C$14+$C$15+IF($D$74=1,$C$16,0))+C72)),1,0) -> 0 | H72: =IF(D72>(($D$22+IF($D$74=1,$C$17*$C$16,0)-(SUMPRODUCT($D$67:$D$73,$G$67:$G$73)-D72*G72))*C72/((((SUM($C$67:$C$73)-SUMPRODUCT($C$67:$C$73,$G$67:$G$73))-C72*(1-G72))+$C$14+$C$15+IF($D$74=1,$C$16,0))+C72)),1,0) -> 0 | I72: =(($D$22+IF($D$74=1,$C$17*$C$16,0)-(SUMPRODUCT($D$67:$D$73,$H$67:$H$73)-D72*H72))*C72/((((SUM($C$67:$C$73)-SUMPRODUCT($C$67:$C$73,$H$67:$H$73))-C72*(1-H72))+$C$14+$C$15+IF($D$74=1,$C$16,0))+C72)) -> 1.4210286e+08 | J72: =IF(H72=1,D72,I72) -> 1.4210286e+08
B73: =B13 -> Seed | C73: =C13 -> 5000000 | D73: =D13 -> 5000000 | E73: =IF(D73>(($D$22+IF($D$74=1,$C$17*$C$16,0))*C73/(SUM($C$7:$C$13)+$C$14+$C$15+IF($D$74=1,$C$16,0))),1,0) -> 0 | F73: =IF(D73>(($D$22+IF($D$74=1,$C$17*$C$16,0)-(SUMPRODUCT($D$67:$D$73,$E$67:$E$73)-D73*E73))*C73/((((SUM($C$67:$C$73)-SUMPRODUCT($C$67:$C$73,$E$67:$E$73))-C73*(1-E73))+$C$14+$C$15+IF($D$74=1,$C$16,0))+C73)),1,0) -> 0 | G73: =IF(D73>(($D$22+IF($D$74=1,$C$17*$C$16,0)-(SUMPRODUCT($D$67:$D$73,$F$67:$F$73)-D73*F73))*C73/((((SUM($C$67:$C$73)-SUMPRODUCT($C$67:$C$73,$F$67:$F$73))-C73*(1-F73))+$C$14+$C$15+IF($D$74=1,$C$16,0))+C73)),1,0) -> 0 | H73: =IF(D73>(($D$22+IF($D$74=1,$C$17*$C$16,0)-(SUMPRODUCT($D$67:$D$73,$G$67:$G$73)-D73*G73))*C73/((((SUM($C$67:$C$73)-SUMPRODUCT($C$67:$C$73,$G$67:$G$73))-C73*(1-G73))+$C$14+$C$15+IF($D$74=1,$C$16,0))+C73)),1,0) -> 0 | I73: =(($D$22+IF($D$74=1,$C$17*$C$16,0)-(SUMPRODUCT($D$67:$D$73,$H$67:$H$73)-D73*H73))*C73/((((SUM($C$67:$C$73)-SUMPRODUCT($C$67:$C$73,$H$67:$H$73))-C73*(1-H73))+$C$14+$C$15+IF($D$74=1,$C$16,0))+C73)) -> 1.4210286e+08 | J73: =IF(H73=1,D73,I73) -> 1.4210286e+08
B74: Aggregates | C74: =($D$22+$C$17*$C$16)/(SUM($C$7:$C$13)+$C$14+$C$15+$C$16) -> 33.54007 | D74: =IF(C74>$C$17,1,0) -> 1
B75: Notes (combined) | C75: =$C$14 -> 281015.3 | J75: =($D$22+IF($D$74=1,$C$17*$C$16,0)-SUMPRODUCT($D$67:$D$73,$H$67:$H$73))*$C$14/((SUM($C$67:$C$73)-SUMPRODUCT($C$67:$C$73,$H$67:$H$73))+$C$14+$C$15+IF($D$74=1,$C$16,0)) -> 7986615.6
B76: Common+RSAs+F_LEAD sec | C76: =$C$15 -> 9000000 | J76: =($D$22+IF($D$74=1,$C$17*$C$16,0)-SUMPRODUCT($D$67:$D$73,$H$67:$H$73))*$C$15/((SUM($C$67:$C$73)-SUMPRODUCT($C$67:$C$73,$H$67:$H$73))+$C$14+$C$15+IF($D$74=1,$C$16,0)) -> 2.5578515e+08
B77: Issued options (net) | C77: =$C$16 -> 2500000 | J77: =IF($D$74=1,($D$22+IF($D$74=1,$C$17*$C$16,0)-SUMPRODUCT($D$67:$D$73,$H$67:$H$73))*$C$16/((SUM($C$67:$C$73)-SUMPRODUCT($C$67:$C$73,$H$67:$H$73))+$C$14+$C$15+IF($D$74=1,$C$16,0))-$C$17*$C$16,0) -> 68551430
B78: Total proceeds | J78: =SUM(J67:J77) -> 1200000000
B79: Check | J79: =ROUND(J78-$D$22,2) -> 0
B80: Iteration block: $2B
B81: Class | C81: Shares | D81: Pref ($) | E81: Ind iter1 | F81: Ind iter2 | G81: Ind iter3 | H81: Ind iter4 | I81: Convert@iter4 | J81: Final $ proceeds
B82: =B7 -> Series F | C82: =C7 -> 803315.08 | D82: =D7 -> 30000000 | E82: =IF(D82>(($E$22+IF($D$89=1,$C$17*$C$16,0))*C82/(SUM($C$7:$C$13)+$C$14+$C$15+IF($D$89=1,$C$16,0))),1,0) -> 0 | F82: =IF(D82>(($E$22+IF($D$89=1,$C$17*$C$16,0)-(SUMPRODUCT($D$82:$D$88,$E$82:$E$88)-D82*E82))*C82/((((SUM($C$82:$C$88)-SUMPRODUCT($C$82:$C$88,$E$82:$E$88))-C82*(1-E82))+$C$14+$C$15+IF($D$89=1,$C$16,0))+C82)),1,0) -> 0 | G82: =IF(D82>(($E$22+IF($D$89=1,$C$17*$C$16,0)-(SUMPRODUCT($D$82:$D$88,$F$82:$F$88)-D82*F82))*C82/((((SUM($C$82:$C$88)-SUMPRODUCT($C$82:$C$88,$F$82:$F$88))-C82*(1-F82))+$C$14+$C$15+IF($D$89=1,$C$16,0))+C82)),1,0) -> 0 | H82: =IF(D82>(($E$22+IF($D$89=1,$C$17*$C$16,0)-(SUMPRODUCT($D$82:$D$88,$G$82:$G$88)-D82*G82))*C82/((((SUM($C$82:$C$88)-SUMPRODUCT($C$82:$C$88,$G$82:$G$88))-C82*(1-G82))+$C$14+$C$15+IF($D$89=1,$C$16,0))+C82)),1,0) -> 0 | I82: =(($E$22+IF($D$89=1,$C$17*$C$16,0)-(SUMPRODUCT($D$82:$D$88,$H$82:$H$88)-D82*H82))*C82/((((SUM($C$82:$C$88)-SUMPRODUCT($C$82:$C$88,$H$82:$H$88))-C82*(1-H82))+$C$14+$C$15+IF($D$89=1,$C$16,0))+C82)) -> 44793811 | J82: =IF(H82=1,D82,I82) -> 44793811
B83: =B8 -> Series E | C83: =C8 -> 6134376.9 | D83: =D8 -> 300000000 | E83: =IF(D83>(($E$22+IF($D$89=1,$C$17*$C$16,0))*C83/(SUM($C$7:$C$13)+$C$14+$C$15+IF($D$89=1,$C$16,0))),1,0) -> 0 | F83: =IF(D83>(($E$22+IF($D$89=1,$C$17*$C$16,0)-(SUMPRODUCT($D$82:$D$88,$E$82:$E$88)-D83*E83))*C83/((((SUM($C$82:$C$88)-SUMPRODUCT($C$82:$C$88,$E$82:$E$88))-C83*(1-E83))+$C$14+$C$15+IF($D$89=1,$C$16,0))+C83)),1,0) -> 0 | G83: =IF(D83>(($E$22+IF($D$89=1,$C$17*$C$16,0)-(SUMPRODUCT($D$82:$D$88,$F$82:$F$88)-D83*F83))*C83/((((SUM($C$82:$C$88)-SUMPRODUCT($C$82:$C$88,$F$82:$F$88))-C83*(1-F83))+$C$14+$C$15+IF($D$89=1,$C$16,0))+C83)),1,0) -> 0 | H83: =IF(D83>(($E$22+IF($D$89=1,$C$17*$C$16,0)-(SUMPRODUCT($D$82:$D$88,$G$82:$G$88)-D83*G83))*C83/((((SUM($C$82:$C$88)-SUMPRODUCT($C$82:$C$88,$G$82:$G$88))-C83*(1-G83))+$C$14+$C$15+IF($D$89=1,$C$16,0))+C83)),1,0) -> 0 | I83: =(($E$22+IF($D$89=1,$C$17*$C$16,0)-(SUMPRODUCT($D$82:$D$88,$H$82:$H$88)-D83*H83))*C83/((((SUM($C$82:$C$88)-SUMPRODUCT($C$82:$C$88,$H$82:$H$88))-C83*(1-H83))+$C$14+$C$15+IF($D$89=1,$C$16,0))+C83)) -> 3.4206021e+08 | J83: =IF(H83=1,D83,I83) -> 3.4206021e+08
B84: =B9 -> Series D | C84: =C9 -> 1733931.2 | D84: =D9 -> 100000000 | E84: =IF(D84>(($E$22+IF($D$89=1,$C$17*$C$16,0))*C84/(SUM($C$7:$C$13)+$C$14+$C$15+IF($D$89=1,$C$16,0))),1,0) -> 1 | F84: =IF(D84>(($E$22+IF($D$89=1,$C$17*$C$16,0)-(SUMPRODUCT($D$82:$D$88,$E$82:$E$88)-D84*E84))*C84/((((SUM($C$82:$C$88)-SUMPRODUCT($C$82:$C$88,$E$82:$E$88))-C84*(1-E84))+$C$14+$C$15+IF($D$89=1,$C$16,0))+C84)),1,0) -> 1 | G84: =IF(D84>(($E$22+IF($D$89=1,$C$17*$C$16,0)-(SUMPRODUCT($D$82:$D$88,$F$82:$F$88)-D84*F84))*C84/((((SUM($C$82:$C$88)-SUMPRODUCT($C$82:$C$88,$F$82:$F$88))-C84*(1-F84))+$C$14+$C$15+IF($D$89=1,$C$16,0))+C84)),1,0) -> 1 | H84: =IF(D84>(($E$22+IF($D$89=1,$C$17*$C$16,0)-(SUMPRODUCT($D$82:$D$88,$G$82:$G$88)-D84*G84))*C84/((((SUM($C$82:$C$88)-SUMPRODUCT($C$82:$C$88,$G$82:$G$88))-C84*(1-G84))+$C$14+$C$15+IF($D$89=1,$C$16,0))+C84)),1,0) -> 1 | I84: =(($E$22+IF($D$89=1,$C$17*$C$16,0)-(SUMPRODUCT($D$82:$D$88,$H$82:$H$88)-D84*H84))*C84/((((SUM($C$82:$C$88)-SUMPRODUCT($C$82:$C$88,$H$82:$H$88))-C84*(1-H84))+$C$14+$C$15+IF($D$89=1,$C$16,0))+C84)) -> 96846352 | J84: =IF(H84=1,D84,I84) -> 100000000
B85: =B10 -> Series C | C85: =C10 -> 2400000 | D85: =D10 -> 60000000 | E85: =IF(D85>(($E$22+IF($D$89=1,$C$17*$C$16,0))*C85/(SUM($C$7:$C$13)+$C$14+$C$15+IF($D$89=1,$C$16,0))),1,0) -> 0 | F85: =IF(D85>(($E$22+IF($D$89=1,$C$17*$C$16,0)-(SUMPRODUCT($D$82:$D$88,$E$82:$E$88)-D85*E85))*C85/((((SUM($C$82:$C$88)-SUMPRODUCT($C$82:$C$88,$E$82:$E$88))-C85*(1-E85))+$C$14+$C$15+IF($D$89=1,$C$16,0))+C85)),1,0) -> 0 | G85: =IF(D85>(($E$22+IF($D$89=1,$C$17*$C$16,0)-(SUMPRODUCT($D$82:$D$88,$F$82:$F$88)-D85*F85))*C85/((((SUM($C$82:$C$88)-SUMPRODUCT($C$82:$C$88,$F$82:$F$88))-C85*(1-F85))+$C$14+$C$15+IF($D$89=1,$C$16,0))+C85)),1,0) -> 0 | H85: =IF(D85>(($E$22+IF($D$89=1,$C$17*$C$16,0)-(SUMPRODUCT($D$82:$D$88,$G$82:$G$88)-D85*G85))*C85/((((SUM($C$82:$C$88)-SUMPRODUCT($C$82:$C$88,$G$82:$G$88))-C85*(1-G85))+$C$14+$C$15+IF($D$89=1,$C$16,0))+C85)),1,0) -> 0 | I85: =(($E$22+IF($D$89=1,$C$17*$C$16,0)-(SUMPRODUCT($D$82:$D$88,$H$82:$H$88)-D85*H85))*C85/((((SUM($C$82:$C$88)-SUMPRODUCT($C$82:$C$88,$H$82:$H$88))-C85*(1-H85))+$C$14+$C$15+IF($D$89=1,$C$16,0))+C85)) -> 1.3382688e+08 | J85: =IF(H85=1,D85,I85) -> 1.3382688e+08
B86: =B11 -> Series B | C86: =C11 -> 3000000 | D86: =D11 -> 30000000 | E86: =IF(D86>(($E$22+IF($D$89=1,$C$17*$C$16,0))*C86/(SUM($C$7:$C$13)+$C$14+$C$15+IF($D$89=1,$C$16,0))),1,0) -> 0 | F86: =IF(D86>(($E$22+IF($D$89=1,$C$17*$C$16,0)-(SUMPRODUCT($D$82:$D$88,$E$82:$E$88)-D86*E86))*C86/((((SUM($C$82:$C$88)-SUMPRODUCT($C$82:$C$88,$E$82:$E$88))-C86*(1-E86))+$C$14+$C$15+IF($D$89=1,$C$16,0))+C86)),1,0) -> 0 | G86: =IF(D86>(($E$22+IF($D$89=1,$C$17*$C$16,0)-(SUMPRODUCT($D$82:$D$88,$F$82:$F$88)-D86*F86))*C86/((((SUM($C$82:$C$88)-SUMPRODUCT($C$82:$C$88,$F$82:$F$88))-C86*(1-F86))+$C$14+$C$15+IF($D$89=1,$C$16,0))+C86)),1,0) -> 0 | H86: =IF(D86>(($E$22+IF($D$89=1,$C$17*$C$16,0)-(SUMPRODUCT($D$82:$D$88,$G$82:$G$88)-D86*G86))*C86/((((SUM($C$82:$C$88)-SUMPRODUCT($C$82:$C$88,$G$82:$G$88))-C86*(1-G86))+$C$14+$C$15+IF($D$89=1,$C$16,0))+C86)),1,0) -> 0 | I86: =(($E$22+IF($D$89=1,$C$17*$C$16,0)-(SUMPRODUCT($D$82:$D$88,$H$82:$H$88)-D86*H86))*C86/((((SUM($C$82:$C$88)-SUMPRODUCT($C$82:$C$88,$H$82:$H$88))-C86*(1-H86))+$C$14+$C$15+IF($D$89=1,$C$16,0))+C86)) -> 1.6728359e+08 | J86: =IF(H86=1,D86,I86) -> 1.6728359e+08
B87: =B12 -> Series A | C87: =C12 -> 5000000 | D87: =D12 -> 15000000 | E87: =IF(D87>(($E$22+IF($D$89=1,$C$17*$C$16,0))*C87/(SUM($C$7:$C$13)+$C$14+$C$15+IF($D$89=1,$C$16,0))),1,0) -> 0 | F87: =IF(D87>(($E$22+IF($D$89=1,$C$17*$C$16,0)-(SUMPRODUCT($D$82:$D$88,$E$82:$E$88)-D87*E87))*C87/((((SUM($C$82:$C$88)-SUMPRODUCT($C$82:$C$88,$E$82:$E$88))-C87*(1-E87))+$C$14+$C$15+IF($D$89=1,$C$16,0))+C87)),1,0) -> 0 | G87: =IF(D87>(($E$22+IF($D$89=1,$C$17*$C$16,0)-(SUMPRODUCT($D$82:$D$88,$F$82:$F$88)-D87*F87))*C87/((((SUM($C$82:$C$88)-SUMPRODUCT($C$82:$C$88,$F$82:$F$88))-C87*(1-F87))+$C$14+$C$15+IF($D$89=1,$C$16,0))+C87)),1,0) -> 0 | H87: =IF(D87>(($E$22+IF($D$89=1,$C$17*$C$16,0)-(SUMPRODUCT($D$82:$D$88,$G$82:$G$88)-D87*G87))*C87/((((SUM($C$82:$C$88)-SUMPRODUCT($C$82:$C$88,$G$82:$G$88))-C87*(1-G87))+$C$14+$C$15+IF($D$89=1,$C$16,0))+C87)),1,0) -> 0 | I87: =(($E$22+IF($D$89=1,$C$17*$C$16,0)-(SUMPRODUCT($D$82:$D$88,$H$82:$H$88)-D87*H87))*C87/((((SUM($C$82:$C$88)-SUMPRODUCT($C$82:$C$88,$H$82:$H$88))-C87*(1-H87))+$C$14+$C$15+IF($D$89=1,$C$16,0))+C87)) -> 2.7880599e+08 | J87: =IF(H87=1,D87,I87) -> 2.7880599e+08
B88: =B13 -> Seed | C88: =C13 -> 5000000 | D88: =D13 -> 5000000 | E88: =IF(D88>(($E$22+IF($D$89=1,$C$17*$C$16,0))*C88/(SUM($C$7:$C$13)+$C$14+$C$15+IF($D$89=1,$C$16,0))),1,0) -> 0 | F88: =IF(D88>(($E$22+IF($D$89=1,$C$17*$C$16,0)-(SUMPRODUCT($D$82:$D$88,$E$82:$E$88)-D88*E88))*C88/((((SUM($C$82:$C$88)-SUMPRODUCT($C$82:$C$88,$E$82:$E$88))-C88*(1-E88))+$C$14+$C$15+IF($D$89=1,$C$16,0))+C88)),1,0) -> 0 | G88: =IF(D88>(($E$22+IF($D$89=1,$C$17*$C$16,0)-(SUMPRODUCT($D$82:$D$88,$F$82:$F$88)-D88*F88))*C88/((((SUM($C$82:$C$88)-SUMPRODUCT($C$82:$C$88,$F$82:$F$88))-C88*(1-F88))+$C$14+$C$15+IF($D$89=1,$C$16,0))+C88)),1,0) -> 0 | H88: =IF(D88>(($E$22+IF($D$89=1,$C$17*$C$16,0)-(SUMPRODUCT($D$82:$D$88,$G$82:$G$88)-D88*G88))*C88/((((SUM($C$82:$C$88)-SUMPRODUCT($C$82:$C$88,$G$82:$G$88))-C88*(1-G88))+$C$14+$C$15+IF($D$89=1,$C$16,0))+C88)),1,0) -> 0 | I88: =(($E$22+IF($D$89=1,$C$17*$C$16,0)-(SUMPRODUCT($D$82:$D$88,$H$82:$H$88)-D88*H88))*C88/((((SUM($C$82:$C$88)-SUMPRODUCT($C$82:$C$88,$H$82:$H$88))-C88*(1-H88))+$C$14+$C$15+IF($D$89=1,$C$16,0))+C88)) -> 2.7880599e+08 | J88: =IF(H88=1,D88,I88) -> 2.7880599e+08
B89: Aggregates | C89: =($E$22+$C$17*$C$16)/(SUM($C$7:$C$13)+$C$14+$C$15+$C$16) -> 55.85363 | D89: =IF(C89>$C$17,1,0) -> 1
B90: Notes (combined) | C90: =$C$14 -> 281015.3 | J90: =($E$22+IF($D$89=1,$C$17*$C$16,0)-SUMPRODUCT($D$82:$D$88,$H$82:$H$88))*$C$14/((SUM($C$82:$C$88)-SUMPRODUCT($C$82:$C$88,$H$82:$H$88))+$C$14+$C$15+IF($D$89=1,$C$16,0)) -> 15669750
B91: Common+RSAs+F_LEAD sec | C91: =$C$15 -> 9000000 | J91: =($E$22+IF($D$89=1,$C$17*$C$16,0)-SUMPRODUCT($D$82:$D$88,$H$82:$H$88))*$C$15/((SUM($C$82:$C$88)-SUMPRODUCT($C$82:$C$88,$H$82:$H$88))+$C$14+$C$15+IF($D$89=1,$C$16,0)) -> 5.0185078e+08
B92: Issued options (net) | C92: =$C$16 -> 2500000 | J92: =IF($D$89=1,($E$22+IF($D$89=1,$C$17*$C$16,0)-SUMPRODUCT($D$82:$D$88,$H$82:$H$88))*$C$16/((SUM($C$82:$C$88)-SUMPRODUCT($C$82:$C$88,$H$82:$H$88))+$C$14+$C$15+IF($D$89=1,$C$16,0))-$C$17*$C$16,0) -> 1.36903e+08
B93: Total proceeds | J93: =SUM(J82:J92) -> 2e+09
B94: Check | J94: =ROUND(J93-$E$22,2) -> 0
B95: Iteration block: $4B
B96: Class | C96: Shares | D96: Pref ($) | E96: Ind iter1 | F96: Ind iter2 | G96: Ind iter3 | H96: Ind iter4 | I96: Convert@iter4 | J96: Final $ proceeds
B97: =B7 -> Series F | C97: =C7 -> 803315.08 | D97: =D7 -> 30000000 | E97: =IF(D97>(($F$22+IF($D$104=1,$C$17*$C$16,0))*C97/(SUM($C$7:$C$13)+$C$14+$C$15+IF($D$104=1,$C$16,0))),1,0) -> 0 | F97: =IF(D97>(($F$22+IF($D$104=1,$C$17*$C$16,0)-(SUMPRODUCT($D$97:$D$103,$E$97:$E$103)-D97*E97))*C97/((((SUM($C$97:$C$103)-SUMPRODUCT($C$97:$C$103,$E$97:$E$103))-C97*(1-E97))+$C$14+$C$15+IF($D$104=1,$C$16,0))+C97)),1,0) -> 0 | G97: =IF(D97>(($F$22+IF($D$104=1,$C$17*$C$16,0)-(SUMPRODUCT($D$97:$D$103,$F$97:$F$103)-D97*F97))*C97/((((SUM($C$97:$C$103)-SUMPRODUCT($C$97:$C$103,$F$97:$F$103))-C97*(1-F97))+$C$14+$C$15+IF($D$104=1,$C$16,0))+C97)),1,0) -> 0 | H97: =IF(D97>(($F$22+IF($D$104=1,$C$17*$C$16,0)-(SUMPRODUCT($D$97:$D$103,$G$97:$G$103)-D97*G97))*C97/((((SUM($C$97:$C$103)-SUMPRODUCT($C$97:$C$103,$G$97:$G$103))-C97*(1-G97))+$C$14+$C$15+IF($D$104=1,$C$16,0))+C97)),1,0) -> 0 | I97: =(($F$22+IF($D$104=1,$C$17*$C$16,0)-(SUMPRODUCT($D$97:$D$103,$H$97:$H$103)-D97*H97))*C97/((((SUM($C$97:$C$103)-SUMPRODUCT($C$97:$C$103,$H$97:$H$103))-C97*(1-H97))+$C$14+$C$15+IF($D$104=1,$C$16,0))+C97)) -> 89680111 | J97: =IF(H97=1,D97,I97) -> 89680111
B98: =B8 -> Series E | C98: =C8 -> 6134376.9 | D98: =D8 -> 300000000 | E98: =IF(D98>(($F$22+IF($D$104=1,$C$17*$C$16,0))*C98/(SUM($C$7:$C$13)+$C$14+$C$15+IF($D$104=1,$C$16,0))),1,0) -> 0 | F98: =IF(D98>(($F$22+IF($D$104=1,$C$17*$C$16,0)-(SUMPRODUCT($D$97:$D$103,$E$97:$E$103)-D98*E98))*C98/((((SUM($C$97:$C$103)-SUMPRODUCT($C$97:$C$103,$E$97:$E$103))-C98*(1-E98))+$C$14+$C$15+IF($D$104=1,$C$16,0))+C98)),1,0) -> 0 | G98: =IF(D98>(($F$22+IF($D$104=1,$C$17*$C$16,0)-(SUMPRODUCT($D$97:$D$103,$F$97:$F$103)-D98*F98))*C98/((((SUM($C$97:$C$103)-SUMPRODUCT($C$97:$C$103,$F$97:$F$103))-C98*(1-F98))+$C$14+$C$15+IF($D$104=1,$C$16,0))+C98)),1,0) -> 0 | H98: =IF(D98>(($F$22+IF($D$104=1,$C$17*$C$16,0)-(SUMPRODUCT($D$97:$D$103,$G$97:$G$103)-D98*G98))*C98/((((SUM($C$97:$C$103)-SUMPRODUCT($C$97:$C$103,$G$97:$G$103))-C98*(1-G98))+$C$14+$C$15+IF($D$104=1,$C$16,0))+C98)),1,0) -> 0 | I98: =(($F$22+IF($D$104=1,$C$17*$C$16,0)-(SUMPRODUCT($D$97:$D$103,$H$97:$H$103)-D98*H98))*C98/((((SUM($C$97:$C$103)-SUMPRODUCT($C$97:$C$103,$H$97:$H$103))-C98*(1-H98))+$C$14+$C$15+IF($D$104=1,$C$16,0))+C98)) -> 6.8482669e+08 | J98: =IF(H98=1,D98,I98) -> 6.8482669e+08
B99: =B9 -> Series D | C99: =C9 -> 1733931.2 | D99: =D9 -> 100000000 | E99: =IF(D99>(($F$22+IF($D$104=1,$C$17*$C$16,0))*C99/(SUM($C$7:$C$13)+$C$14+$C$15+IF($D$104=1,$C$16,0))),1,0) -> 0 | F99: =IF(D99>(($F$22+IF($D$104=1,$C$17*$C$16,0)-(SUMPRODUCT($D$97:$D$103,$E$97:$E$103)-D99*E99))*C99/((((SUM($C$97:$C$103)-SUMPRODUCT($C$97:$C$103,$E$97:$E$103))-C99*(1-E99))+$C$14+$C$15+IF($D$104=1,$C$16,0))+C99)),1,0) -> 0 | G99: =IF(D99>(($F$22+IF($D$104=1,$C$17*$C$16,0)-(SUMPRODUCT($D$97:$D$103,$F$97:$F$103)-D99*F99))*C99/((((SUM($C$97:$C$103)-SUMPRODUCT($C$97:$C$103,$F$97:$F$103))-C99*(1-F99))+$C$14+$C$15+IF($D$104=1,$C$16,0))+C99)),1,0) -> 0 | H99: =IF(D99>(($F$22+IF($D$104=1,$C$17*$C$16,0)-(SUMPRODUCT($D$97:$D$103,$G$97:$G$103)-D99*G99))*C99/((((SUM($C$97:$C$103)-SUMPRODUCT($C$97:$C$103,$G$97:$G$103))-C99*(1-G99))+$C$14+$C$15+IF($D$104=1,$C$16,0))+C99)),1,0) -> 0 | I99: =(($F$22+IF($D$104=1,$C$17*$C$16,0)-(SUMPRODUCT($D$97:$D$103,$H$97:$H$103)-D99*H99))*C99/((((SUM($C$97:$C$103)-SUMPRODUCT($C$97:$C$103,$H$97:$H$103))-C99*(1-H99))+$C$14+$C$15+IF($D$104=1,$C$16,0))+C99)) -> 1.935718e+08 | J99: =IF(H99=1,D99,I99) -> 1.935718e+08
B100: =B10 -> Series C | C100: =C10 -> 2400000 | D100: =D10 -> 60000000 | E100: =IF(D100>(($F$22+IF($D$104=1,$C$17*$C$16,0))*C100/(SUM($C$7:$C$13)+$C$14+$C$15+IF($D$104=1,$C$16,0))),1,0) -> 0 | F100: =IF(D100>(($F$22+IF($D$104=1,$C$17*$C$16,0)-(SUMPRODUCT($D$97:$D$103,$E$97:$E$103)-D100*E100))*C100/((((SUM($C$97:$C$103)-SUMPRODUCT($C$97:$C$103,$E$97:$E$103))-C100*(1-E100))+$C$14+$C$15+IF($D$104=1,$C$16,0))+C100)),1,0) -> 0 | G100: =IF(D100>(($F$22+IF($D$104=1,$C$17*$C$16,0)-(SUMPRODUCT($D$97:$D$103,$F$97:$F$103)-D100*F100))*C100/((((SUM($C$97:$C$103)-SUMPRODUCT($C$97:$C$103,$F$97:$F$103))-C100*(1-F100))+$C$14+$C$15+IF($D$104=1,$C$16,0))+C100)),1,0) -> 0 | H100: =IF(D100>(($F$22+IF($D$104=1,$C$17*$C$16,0)-(SUMPRODUCT($D$97:$D$103,$G$97:$G$103)-D100*G100))*C100/((((SUM($C$97:$C$103)-SUMPRODUCT($C$97:$C$103,$G$97:$G$103))-C100*(1-G100))+$C$14+$C$15+IF($D$104=1,$C$16,0))+C100)),1,0) -> 0 | I100: =(($F$22+IF($D$104=1,$C$17*$C$16,0)-(SUMPRODUCT($D$97:$D$103,$H$97:$H$103)-D100*H100))*C100/((((SUM($C$97:$C$103)-SUMPRODUCT($C$97:$C$103,$H$97:$H$103))-C100*(1-H100))+$C$14+$C$15+IF($D$104=1,$C$16,0))+C100)) -> 2.6793007e+08 | J100: =IF(H100=1,D100,I100) -> 2.6793007e+08
B101: =B11 -> Series B | C101: =C11 -> 3000000 | D101: =D11 -> 30000000 | E101: =IF(D101>(($F$22+IF($D$104=1,$C$17*$C$16,0))*C101/(SUM($C$7:$C$13)+$C$14+$C$15+IF($D$104=1,$C$16,0))),1,0) -> 0 | F101: =IF(D101>(($F$22+IF($D$104=1,$C$17*$C$16,0)-(SUMPRODUCT($D$97:$D$103,$E$97:$E$103)-D101*E101))*C101/((((SUM($C$97:$C$103)-SUMPRODUCT($C$97:$C$103,$E$97:$E$103))-C101*(1-E101))+$C$14+$C$15+IF($D$104=1,$C$16,0))+C101)),1,0) -> 0 | G101: =IF(D101>(($F$22+IF($D$104=1,$C$17*$C$16,0)-(SUMPRODUCT($D$97:$D$103,$F$97:$F$103)-D101*F101))*C101/((((SUM($C$97:$C$103)-SUMPRODUCT($C$97:$C$103,$F$97:$F$103))-C101*(1-F101))+$C$14+$C$15+IF($D$104=1,$C$16,0))+C101)),1,0) -> 0 | H101: =IF(D101>(($F$22+IF($D$104=1,$C$17*$C$16,0)-(SUMPRODUCT($D$97:$D$103,$G$97:$G$103)-D101*G101))*C101/((((SUM($C$97:$C$103)-SUMPRODUCT($C$97:$C$103,$G$97:$G$103))-C101*(1-G101))+$C$14+$C$15+IF($D$104=1,$C$16,0))+C101)),1,0) -> 0 | I101: =(($F$22+IF($D$104=1,$C$17*$C$16,0)-(SUMPRODUCT($D$97:$D$103,$H$97:$H$103)-D101*H101))*C101/((((SUM($C$97:$C$103)-SUMPRODUCT($C$97:$C$103,$H$97:$H$103))-C101*(1-H101))+$C$14+$C$15+IF($D$104=1,$C$16,0))+C101)) -> 3.3491259e+08 | J101: =IF(H101=1,D101,I101) -> 3.3491259e+08
B102: =B12 -> Series A | C102: =C12 -> 5000000 | D102: =D12 -> 15000000 | E102: =IF(D102>(($F$22+IF($D$104=1,$C$17*$C$16,0))*C102/(SUM($C$7:$C$13)+$C$14+$C$15+IF($D$104=1,$C$16,0))),1,0) -> 0 | F102: =IF(D102>(($F$22+IF($D$104=1,$C$17*$C$16,0)-(SUMPRODUCT($D$97:$D$103,$E$97:$E$103)-D102*E102))*C102/((((SUM($C$97:$C$103)-SUMPRODUCT($C$97:$C$103,$E$97:$E$103))-C102*(1-E102))+$C$14+$C$15+IF($D$104=1,$C$16,0))+C102)),1,0) -> 0 | G102: =IF(D102>(($F$22+IF($D$104=1,$C$17*$C$16,0)-(SUMPRODUCT($D$97:$D$103,$F$97:$F$103)-D102*F102))*C102/((((SUM($C$97:$C$103)-SUMPRODUCT($C$97:$C$103,$F$97:$F$103))-C102*(1-F102))+$C$14+$C$15+IF($D$104=1,$C$16,0))+C102)),1,0) -> 0 | H102: =IF(D102>(($F$22+IF($D$104=1,$C$17*$C$16,0)-(SUMPRODUCT($D$97:$D$103,$G$97:$G$103)-D102*G102))*C102/((((SUM($C$97:$C$103)-SUMPRODUCT($C$97:$C$103,$G$97:$G$103))-C102*(1-G102))+$C$14+$C$15+IF($D$104=1,$C$16,0))+C102)),1,0) -> 0 | I102: =(($F$22+IF($D$104=1,$C$17*$C$16,0)-(SUMPRODUCT($D$97:$D$103,$H$97:$H$103)-D102*H102))*C102/((((SUM($C$97:$C$103)-SUMPRODUCT($C$97:$C$103,$H$97:$H$103))-C102*(1-H102))+$C$14+$C$15+IF($D$104=1,$C$16,0))+C102)) -> 5.5818765e+08 | J102: =IF(H102=1,D102,I102) -> 5.5818765e+08
B103: =B13 -> Seed | C103: =C13 -> 5000000 | D103: =D13 -> 5000000 | E103: =IF(D103>(($F$22+IF($D$104=1,$C$17*$C$16,0))*C103/(SUM($C$7:$C$13)+$C$14+$C$15+IF($D$104=1,$C$16,0))),1,0) -> 0 | F103: =IF(D103>(($F$22+IF($D$104=1,$C$17*$C$16,0)-(SUMPRODUCT($D$97:$D$103,$E$97:$E$103)-D103*E103))*C103/((((SUM($C$97:$C$103)-SUMPRODUCT($C$97:$C$103,$E$97:$E$103))-C103*(1-E103))+$C$14+$C$15+IF($D$104=1,$C$16,0))+C103)),1,0) -> 0 | G103: =IF(D103>(($F$22+IF($D$104=1,$C$17*$C$16,0)-(SUMPRODUCT($D$97:$D$103,$F$97:$F$103)-D103*F103))*C103/((((SUM($C$97:$C$103)-SUMPRODUCT($C$97:$C$103,$F$97:$F$103))-C103*(1-F103))+$C$14+$C$15+IF($D$104=1,$C$16,0))+C103)),1,0) -> 0 | H103: =IF(D103>(($F$22+IF($D$104=1,$C$17*$C$16,0)-(SUMPRODUCT($D$97:$D$103,$G$97:$G$103)-D103*G103))*C103/((((SUM($C$97:$C$103)-SUMPRODUCT($C$97:$C$103,$G$97:$G$103))-C103*(1-G103))+$C$14+$C$15+IF($D$104=1,$C$16,0))+C103)),1,0) -> 0 | I103: =(($F$22+IF($D$104=1,$C$17*$C$16,0)-(SUMPRODUCT($D$97:$D$103,$H$97:$H$103)-D103*H103))*C103/((((SUM($C$97:$C$103)-SUMPRODUCT($C$97:$C$103,$H$97:$H$103))-C103*(1-H103))+$C$14+$C$15+IF($D$104=1,$C$16,0))+C103)) -> 5.5818765e+08 | J103: =IF(H103=1,D103,I103) -> 5.5818765e+08
B104: Aggregates | C104: =($F$22+$C$17*$C$16)/(SUM($C$7:$C$13)+$C$14+$C$15+$C$16) -> 111.63753 | D104: =IF(C104>$C$17,1,0) -> 1
B105: Notes (combined) | C105: =$C$14 -> 281015.3 | J105: =($F$22+IF($D$104=1,$C$17*$C$16,0)-SUMPRODUCT($D$97:$D$103,$H$97:$H$103))*$C$14/((SUM($C$97:$C$103)-SUMPRODUCT($C$97:$C$103,$H$97:$H$103))+$C$14+$C$15+IF($D$104=1,$C$16,0)) -> 31371854
B106: Common+RSAs+F_LEAD sec | C106: =$C$15 -> 9000000 | J106: =($F$22+IF($D$104=1,$C$17*$C$16,0)-SUMPRODUCT($D$97:$D$103,$H$97:$H$103))*$C$15/((SUM($C$97:$C$103)-SUMPRODUCT($C$97:$C$103,$H$97:$H$103))+$C$14+$C$15+IF($D$104=1,$C$16,0)) -> 1.0047378e+09
B107: Issued options (net) | C107: =$C$16 -> 2500000 | J107: =IF($D$104=1,($F$22+IF($D$104=1,$C$17*$C$16,0)-SUMPRODUCT($D$97:$D$103,$H$97:$H$103))*$C$16/((SUM($C$97:$C$103)-SUMPRODUCT($C$97:$C$103,$H$97:$H$103))+$C$14+$C$15+IF($D$104=1,$C$16,0))-$C$17*$C$16,0) -> 2.7659382e+08
B108: Total proceeds | J108: =SUM(J97:J107) -> 4e+09
...
