Workbook

Sheet Assumptions
B2: Series F Round Assumptions
B3: Source: cap_table.xlsx (Stakeholders, Securities, Notes, RoundTerms); $ values in USD; share counts in units
B4: Round Terms
B5: Series F pre-money | C5: 1400000000 | D5: USD
B6: Series F primary raise | C6: 30000000 | D6: USD
B7: Series F secondary raise (tender) | C7: 15000000 | D7: USD
B8: Tender PPS multiplier (vs F PPS) | C8: 0.85 | D8: %
B9: ESOP refresh target (% post-F FD) | C9: 0.13 | D9: %
B10: Our fund Series F check | C10: 10000000 | D10: USD
B11: F_LEAD Series F primary check | C11: 20000000 | D11: USD
B12: Option strike price (issued options) | C12: 1 | D12: USD
B14: Pre-F Capital Structure
B15: Founder F1 (CEO) common | C15: 4000000 | D15: shares
B16: Founder F2 (CTO) common | C16: 2500000 | D16: shares
B17: Founder F3 (Chief Scientist) common | C17: 1500000 | D17: shares
B18: Employee RSAs (E1..E10, 100k each) | C18: 1000000 | D18: shares
B19: Issued options outstanding (pre-F) | C19: 2500000 | D19: shares
B20: Unissued option pool (pre-F) | C20: 1894667 | D20: shares
B21: Pre-F broad-based FD total | C21: 36617961 | D21: shares
B23: Prior-Round Preferred (Seed thru E)
B24: Seed shares | C24: 5000000 | D24: shares
B25: Seed OCP | C25: 1 | D25: USD/sh
B26: Series A shares | C26: 5000000 | D26: shares
B27: Series A OCP | C27: 3 | D27: USD/sh
B28: Series B shares | C28: 3000000 | D28: shares
B29: Series B OCP | C29: 10 | D29: USD/sh
B30: Series C shares | C30: 2400000 | D30: shares
B31: Series C OCP | C31: 25 | D31: USD/sh
B32: Series D shares (issued) | C32: 1666667 | D32: shares
B33: Series D OCP-for-AD (post-E compound NCP) | C33: 58.118347 | D33: USD/sh
B34: Series D PPS issued at (original $60) | C34: 60 | D34: USD/sh
B35: Series D as-converted post-E | C35: 1720627 | D35: shares
... B37: Series E OCP | C37: 49.158311 | D37: USD/sh
B39: Convertible Notes (zero accrued interest)
B40: Note A principal | C40: 5000000 | D40: USD
B41: Note A valuation cap | C41: 1000000000 | D41: USD
B42: Note A discount | C42: 0.2 | D42: %
B43: Note B principal | C43: 3000000 | D43: USD
B44: Note B valuation cap | C44: 1600000000 | D44: USD
B45: Note B discount | C45: 0.15 | D45: %
B47: Broad-Based WA Anti-Dilution Inputs
B48: A: Pre-F broad-based FD (excl. notes & new F primary) | C48: 36617961 | D48: shares
B50: Exit Scenarios
B51: Exit 1 | C51: 700000000 | D51: USD
B52: Exit 2 | C52: 1200000000 | D52: USD
B53: Exit 3 (sensitivity reference) | C53: 2000000000 | D53: USD
B54: Exit 4 | C54: 4000000000 | D54: USD
B55: Exit 5 | C55: 8000000000 | D55: USD
B57: Sensitivity Axes
B58: ESOP low | C58: 0.11 | D58: %
B59: ESOP base | C59: 0.13 | D59: %
B60: ESOP high | C60: 0.15 | D60: %
B61: Pre-money low | C61: 1200000000 | D61: USD
B62: Pre-money base | C62: 1400000000 | D62: USD
B63: Pre-money high | C63: 1800000000 | D63: USD
B65: Return Targets
B66: 3x return on $10M check | C66: 3 | D66: multiple
B67: 4x return on $10M check | C67: 4 | D67: multiple

Sheet Pro-Forma
B2: Series F Pro-Forma Cap Table
B3: Post-F ownership by stakeholder and security class; values traced from Assumptions
B5: Fixed-Point Solve: F PPS, ESOP Top-Up, Note Conversions
B6: Iteration | C6: 0 | D6: 1 | E6: 2 | F6: 3 | G6: 4 | H6: 5 | I6: 6
B7: F PPS = pre-money / pre-money FD | C7: =Assumptions!C5/Assumptions!C21 -> 38.232604 | D7: =Assumptions!C5/(Assumptions!C21+C8+C11+C14) -> 37.469845 | E7: =Assumptions!C5/(Assumptions!C21+D8+D11+D14) -> 37.368016 | F7: =Assumptions!C5/(Assumptions!C21+E8+E11+E14) -> 37.354203 | G7: =Assumptions!C5/(Assumptions!C21+F8+F11+F14) -> 37.352325 | H7: =Assumptions!C5/(Assumptions!C21+G8+G11+G14) -> 37.352069 | I7: =Assumptions!C5/(Assumptions!C21+H8+H11+H14) -> 37.352035
B8: ESOP top-up (post-F target less prior pool) | C8: =MAX(0,Assumptions!C9*(Assumptions!C5+Assumptions!C6)/C7-(Assumptions!C19+Assumptions!C20)) -> 467675.11 | D8: =MAX(0,Assumptions!C9*(Assumptions!C5+Assumptions!C6)/D7-(Assumptions!C19+Assumptions!C20)) -> 566655.9 | E8: =MAX(0,Assumptions!C9*(Assumptions!C5+Assumptions!C6)/E7-(Assumptions!C19+Assumptions!C20)) -> 580175.67 | F8: =MAX(0,Assumptions!C9*(Assumptions!C5+Assumptions!C6)/F7-(Assumptions!C19+Assumptions!C20)) -> 582015.21 | G8: =MAX(0,Assumptions!C9*(Assumptions!C5+Assumptions!C6)/G7-(Assumptions!C19+Assumptions!C20)) -> 582265.51 | H8: =MAX(0,Assumptions!C9*(Assumptions!C5+Assumptions!C6)/H7-(Assumptions!C19+Assumptions!C20)) -> 582299.56 | I8: =MAX(0,Assumptions!C9*(Assumptions!C5+Assumptions!C6)/I7-(Assumptions!C19+Assumptions!C20)) -> 582304.2
B9: Note A cap-branch shares | C9: =Assumptions!C40*(Assumptions!C21+C8+0)/Assumptions!C41 -> 185428.18 | D9: =Assumptions!C40*(Assumptions!C21+D8+C14)/Assumptions!C41 -> 186384.66 | E9: =Assumptions!C40*(Assumptions!C21+E8+D14)/Assumptions!C41 -> 186461.65 | F9: =Assumptions!C40*(Assumptions!C21+F8+E14)/Assumptions!C41 -> 186472.13 | G9: =Assumptions!C40*(Assumptions!C21+G8+F14)/Assumptions!C41 -> 186473.56 | H9: =Assumptions!C40*(Assumptions!C21+H8+G14)/Assumptions!C41 -> 186473.75 | I9: =Assumptions!C40*(Assumptions!C21+I8+H14)/Assumptions!C41 -> 186473.78
B10: Note A discount-branch shares | C10: =Assumptions!C40/((1-Assumptions!C42)*C7) -> 163473.04 | D10: =Assumptions!C40/((1-Assumptions!C42)*D7) -> 166800.8 | E10: =Assumptions!C40/((1-Assumptions!C42)*E7) -> 167255.33 | F10: =Assumptions!C40/((1-Assumptions!C42)*F7) -> 167317.18 | G10: =Assumptions!C40/((1-Assumptions!C42)*G7) -> 167325.6 | H10: =Assumptions!C40/((1-Assumptions!C42)*H7) -> 167326.74 | I10: =Assumptions!C40/((1-Assumptions!C42)*I7) -> 167326.9
B11: Note A shares (= MAX of two branches) | C11: =MAX(C9,C10) -> 185428.18 | D11: =MAX(D9,D10) -> 186384.66 | E11: =MAX(E9,E10) -> 186461.65 | F11: =MAX(F9,F10) -> 186472.13 | G11: =MAX(G9,G10) -> 186473.56 | H11: =MAX(H9,H10) -> 186473.75 | I11: =MAX(I9,I10) -> 186473.78
B12: Note B cap-branch shares | C12: =Assumptions!C43*(Assumptions!C21+C8+C11)/Assumptions!C44 -> 69883.246 | D12: =Assumptions!C43*(Assumptions!C21+D8+D11)/Assumptions!C44 -> 70070.628 | E12: =Assumptions!C43*(Assumptions!C21+E8+E11)/Assumptions!C44 -> 70096.122 | F12: =Assumptions!C43*(Assumptions!C21+F8+F11)/Assumptions!C44 -> 70099.591 | G12: =Assumptions!C43*(Assumptions!C21+G8+G11)/Assumptions!C44 -> 70100.063 | H12: =Assumptions!C43*(Assumptions!C21+H8+H11)/Assumptions!C44 -> 70100.127 | I12: =Assumptions!C43*(Assumptions!C21+I8+I11)/Assumptions!C44 -> 70100.136
B13: Note B discount-branch shares | C13: =Assumptions!C43/((1-Assumptions!C45)*C7) -> 92314.187 | D13: =Assumptions!C43/((1-Assumptions!C45)*D7) -> 94193.391 | E13: =Assumptions!C43/((1-Assumptions!C45)*E7) -> 94450.071 | F13: =Assumptions!C43/((1-Assumptions!C45)*F7) -> 94484.996 | G13: =Assumptions!C43/((1-Assumptions!C45)*G7) -> 94489.748 | H13: =Assumptions!C43/((1-Assumptions!C45)*H7) -> 94490.394 | I13: =Assumptions!C43/((1-Assumptions!C45)*I7) -> 94490.482
B14: Note B shares (= MAX of two branches) | C14: =MAX(C12,C13) -> 92314.187 | D14: =MAX(D12,D13) -> 94193.391 | E14: =MAX(E12,E13) -> 94450.071 | F14: =MAX(F12,F13) -> 94484.996 | G14: =MAX(G12,G13) -> 94489.748 | H14: =MAX(H12,H13) -> 94490.394 | I14: =MAX(I12,I13) -> 94490.482
B15: Residual: F_PPS change vs prior iter | D15: =ABS(D7-C7) -> 0.76275894 | E15: =ABS(E7-D7) -> 0.10182911 | F15: =ABS(F7-E7) -> 0.013812407 | G15: =ABS(G7-F7) -> 0.0018785724 | H15: =ABS(H7-G7) -> 0.00025559014 | I15: =ABS(I7-H7) -> 3.4776165e-05
B17: Final Fixed-Point Values (from iter 6)
B18: F PPS | C18: =I7 -> 37.352035
B19: ESOP top-up shares | C19: =I8 -> 582304.2
B20: Note A converted shares | C20: =I11 -> 186473.78
B21: Note B converted shares | C21: =I14 -> 94490.482
B22: F primary new shares (= primary / F PPS) | C22: =Assumptions!C6/C18 -> 803169.1
B23: Pre-money FD basis (pre + ESOP + notes), headcount | C23: =Assumptions!C21+C19+C20+C21 -> 37481229
B24: AD uplift on D & E (as-converted excess vs headcount) | C24: =(G33-Assumptions!C35)+(G34-Assumptions!C36) -> 44917.998
B25: Total post-F FD (as-converted basis) | C25: =C23+C22+C24 -> 38329317
B26: ESOP % of post-F FD (target = 13.0%) | C26: =(Assumptions!C19+Assumptions!C20+C19)/C25 -> 0.12984764
B27: Broad-Based Weighted-Average Anti-Dilution
B28: Class | C28: OCP (used for AD) | D28: Trigger? (F PPS < OCP) | E28: New Conversion Price (NCP) | F28: New Ratio (OCP / NCP) | G28: As-converted shares
B29: Seed | C29: =Assumptions!C25 -> 1 | D29: =IF($C$18<Assumptions!C25,"trigger","dormant") -> dormant | E29: =IF($C$18<Assumptions!C25,Assumptions!C25*(Assumptions!C48+Assumptions!C6/Assumptions!C25)/(Assumptions!C48+Assumptions!C6/$C$18),Assumptions!C25) -> 1 | F29: =Assumptions!C25/E29 -> 1 | G29: =Assumptions!C24*Assumptions!C25/E29 -> 5000000
B30: Series A | C30: =Assumptions!C27 -> 3 | D30: =IF($C$18<Assumptions!C27,"trigger","dormant") -> dormant | E30: =IF($C$18<Assumptions!C27,Assumptions!C27*(Assumptions!C48+Assumptions!C6/Assumptions!C27)/(Assumptions!C48+Assumptions!C6/$C$18),Assumptions!C27) -> 3 | F30: =Assumptions!C27/E30 -> 1 | G30: =Assumptions!C26*Assumptions!C27/E30 -> 5000000
B31: Series B | C31: =Assumptions!C29 -> 10 | D31: =IF($C$18<Assumptions!C29,"trigger","dormant") -> dormant | E31: =IF($C$18<Assumptions!C29,Assumptions!C29*(Assumptions!C48+Assumptions!C6/Assumptions!C29)/(Assumptions!C48+Assumptions!C6/$C$18),Assumptions!C29) -> 10 | F31: =Assumptions!C29/E31 -> 1 | G31: =Assumptions!C28*Assumptions!C29/E31 -> 3000000
B32: Series C | C32: =Assumptions!C31 -> 25 | D32: =IF($C$18<Assumptions!C31,"trigger","dormant") -> dormant | E32: =IF($C$18<Assumptions!C31,Assumptions!C31*(Assumptions!C48+Assumptions!C6/Assumptions!C31)/(Assumptions!C48+Assumptions!C6/$C$18),Assumptions!C31) -> 25 | F32: =Assumptions!C31/E32 -> 1 | G32: =Assumptions!C30*Assumptions!C31/E32 -> 2400000
B33: Series D | C33: =Assumptions!C33 -> 58.118347 | D33: =IF($C$18<Assumptions!C33,"trigger","dormant") -> trigger | E33: =IF($C$18<Assumptions!C33,Assumptions!C33*(Assumptions!C48+Assumptions!C6/Assumptions!C33)/(Assumptions!C48+Assumptions!C6/$C$18),Assumptions!C33) -> 57.67264 | F33: =Assumptions!C33/E33 -> 1.0077282 | G33: =Assumptions!C35*Assumptions!C33/E33 -> 1733924.4
B34: Series E | C34: =Assumptions!C37 -> 49.158311 | D34: =IF($C$18<Assumptions!C37,"trigger","dormant") -> trigger | E34: =IF($C$18<Assumptions!C37,Assumptions!C37*(Assumptions!C48+Assumptions!C6/Assumptions!C37)/(Assumptions!C48+Assumptions!C6/$C$18),Assumptions!C37) -> 48.904913 | F34: =Assumptions!C37/E34 -> 1.0051814 | G34: =Assumptions!C36*Assumptions!C37/E34 -> 6134287.6
B36: Total preferred as-converted (post-F AD) | G36: =SUM(G29:G34) -> 23268212
B38: Convertible Notes Block
B39: Note | C39: Cap-implied PPS | D39: Discount-implied PPS | E39: Conversion PPS (MIN) | F39: Branch elected | G39: Shares issued
B40: Note A | C40: =Assumptions!C41/(Assumptions!C21+C19+C21) -> 26.813421 | D40: =$C$18*(1-Assumptions!C42) -> 29.881628 | E40: =MIN(C40,D40) -> 26.813421 | F40: =IF(C40<D40,"cap","discount") -> cap | G40: =Assumptions!C40/E40 -> 186473.78
B41: Note B | C41: =Assumptions!C44/(Assumptions!C21+C19+C20) -> 42.795923 | D41: =$C$18*(1-Assumptions!C45) -> 31.749229 | E41: =MIN(C41,D41) -> 31.749229 | F41: =IF(C41<D41,"cap","discount") -> discount | G41: =Assumptions!C43/E41 -> 94490.482
B42: Total notes shares | G42: =G40+G41 -> 280964.26
B43: Check vs fixed-point block (row 20-21) | G43: =ROUND((G40+G41)-(C20+C21),2) -> 0
B45: Secondary Tender (founders -> F_LEAD)
B46: Tender PPS (F PPS x multiplier) | C46: =$C$18*Assumptions!C8 -> 31.749229
B47: Tender shares ($15M / tender PPS) | C47: =Assumptions!C7/C46 -> 472452.41
B48: Founder F1 contribution (50%) | C48: =C47*(Assumptions!C15/(Assumptions!C15+Assumptions!C16+Assumptions!C17)) -> 236226.21
B49: Founder F2 contribution (31.25%) | C49: =C47*(Assumptions!C16/(Assumptions!C15+Assumptions!C16+Assumptions!C17)) -> 147641.38
B50: Founder F3 contribution (18.75%) | C50: =C47*(Assumptions!C17/(Assumptions!C15+Assumptions!C16+Assumptions!C17)) -> 88584.827
B51: Tender check (sum = total tender) | C51: =ROUND((C48+C49+C50)-C47,2) -> 0
B52: F_LEAD primary preferred shares ($20M / F PPS) | C52: =Assumptions!C11/$C$18 -> 535446.07
B53: F_LEAD secondary common shares (= tender shares) | C53: =C47 -> 472452.41
B54: Our fund primary shares ($10M / F PPS) | C54: =Assumptions!C10/$C$18 -> 267723.03
B56: Post-F Cap Table by Stakeholder & Security
B57: Stakeholder | C57: Security | D57: Common / RSA | E57: Preferred (as-conv.) | F57: Options | G57: Total FD | H57: Ownership %
B58: F1 (CEO) | C58: Common | D58: =Assumptions!C15-C48 -> 3763773.8 | E58: =0 -> 0 | F58: =0 -> 0 | G58: =D58+E58+F58 -> 3763773.8 | H58: =G58/$G$75 -> 0.098195693
B59: F2 (CTO) | C59: Common | D59: =Assumptions!C16-C49 -> 2352358.6 | E59: =0 -> 0 | F59: =0 -> 0 | G59: =D59+E59+F59 -> 2352358.6 | H59: =G59/$G$75 -> 0.061372308
B60: F3 (Chief Sci.) | C60: Common | D60: =Assumptions!C17-C50 -> 1411415.2 | E60: =0 -> 0 | F60: =0 -> 0 | G60: =D60+E60+F60 -> 1411415.2 | H60: =G60/$G$75 -> 0.036823385
B61: Employees E1..E10 (RSAs) | C61: RSA | D61: =Assumptions!C18 -> 1000000 | E61: =0 -> 0 | F61: =0 -> 0 | G61: =D61+E61+F61 -> 1000000 | H61: =G61/$G$75 -> 0.02608969
B62: Option holders (issued options) | C62: Options | D62: =0 -> 0 | E62: =0 -> 0 | F62: =Assumptions!C19 -> 2500000 | G62: =D62+E62+F62 -> 2500000 | H62: =G62/$G$75 -> 0.065224226
B63: Option pool (unissued, post-F) | C63: Pool (unissued) | D63: =0 -> 0 | E63: =0 -> 0 | F63: =Assumptions!C20+C19 -> 2476971.2 | G63: =D63+E63+F63 -> 2476971.2 | H63: =G63/$G$75 -> 0.064623411
B64: SEED1 (Seed LP) | C64: Seed Pref. | D64: =0 -> 0 | E64: =G29 -> 5000000 | F64: =0 -> 0 | G64: =D64+E64+F64 -> 5000000 | H64: =G64/$G$75 -> 0.13044845
B65: A1 (Series A LP) | C65: Series A Pref. | D65: =0 -> 0 | E65: =G30 -> 5000000 | F65: =0 -> 0 | G65: =D65+E65+F65 -> 5000000 | H65: =G65/$G$75 -> 0.13044845
B66: B1 (Series B LP) | C66: Series B Pref. | D66: =0 -> 0 | E66: =G31 -> 3000000 | F66: =0 -> 0 | G66: =D66+E66+F66 -> 3000000 | H66: =G66/$G$75 -> 0.078269071
B67: C1 (Series C LP) | C67: Series C Pref. | D67: =0 -> 0 | E67: =G32 -> 2400000 | F67: =0 -> 0 | G67: =D67+E67+F67 -> 2400000 | H67: =G67/$G$75 -> 0.062615257
B68: D1 (Series D LP) | C68: Series D Pref. | D68: =0 -> 0 | E68: =G33 -> 1733924.4 | F68: =0 -> 0 | G68: =D68+E68+F68 -> 1733924.4 | H68: =G68/$G$75 -> 0.04523755
B69: E1..E10 (Series E LPs) | C69: Series E Pref. | D69: =0 -> 0 | E69: =G34 -> 6134287.6 | F69: =0 -> 0 | G69: =D69+E69+F69 -> 6134287.6 | H69: =G69/$G$75 -> 0.16004166
B70: NA1 (Note A holder) | C70: Note A -> common-equiv. | D70: =G40 -> 186473.78 | E70: =0 -> 0 | F70: =0 -> 0 | G70: =D70+E70+F70 -> 186473.78 | H70: =G70/$G$75 -> 0.0048650431
B71: NB1 (Note B holder) | C71: Note B -> common-equiv. | D71: =G41 -> 94490.482 | E71: =0 -> 0 | F71: =0 -> 0 | G71: =D71+E71+F71 -> 94490.482 | H71: =G71/$G$75 -> 0.0024652274
B72: F_LEAD (Series F primary) | C72: Series F Pref. | D72: =0 -> 0 | E72: =C52 -> 535446.07 | F72: =0 -> 0 | G72: =D72+E72+F72 -> 535446.07 | H72: =G72/$G$75 -> 0.013969622
B73: F_LEAD (secondary common) | C73: Common (tender) | D73: =C53 -> 472452.41 | E73: =0 -> 0 | F73: =0 -> 0 | G73: =D73+E73+F73 -> 472452.41 | H73: =G73/$G$75 -> 0.012326137
B74: Our Fund (Series F primary) | C74: Series F Pref. | D74: =0 -> 0 | E74: =C54 -> 267723.03 | F74: =0 -> 0 | G74: =D74+E74+F74 -> 267723.03 | H74: =G74/$G$75 -> 0.006984811
B75: Total post-F FD | D75: =SUM(D58:D74) -> 9280964.3 | E75: =SUM(E58:E74) -> 24071381 | F75: =SUM(F58:F74) -> 4976971.2 | G75: =SUM(G58:G74) -> 38329317 | H75: =SUM(H58:H74) -> 1
B76: Check | G76: =ROUND(G75-C25,2) -> 0
B78: Our $10M check post-F ownership | C78: =C54/G75 -> 0.006984811

Sheet Waterfall
B2: Series F Waterfall — 1x NP with Conversion Election
B3: Nash equilibrium under reverse-chronological seniority; F most senior, Seed most junior
B5: Class Inputs
B6: Class | C6: As-conv Shares | D6: Aggregate Pref ($) | E6: Exit 1 | F6: Exit 2 | G6: Exit 3 | H6: Exit 4 | I6: Exit 5 | J6: Proc. Ex.1 | K6: Proc. Ex.2 | L6: Proc. Ex.3 | M6: Proc. Ex.4 | N6: Proc. Ex.5
B7: Series F | C7: ='Pro-Forma'!C22 -> 803169.1 | D7: =Assumptions!C6 -> 30000000 | E7: =IF(D7>(C7*(Assumptions!C51-(E$49-IF(E38="preference",D7,0))+$C$20)/($C$19+(E$50-IF(E38="convert",C7,0))+C7)),"preference","convert") -> preference | F7: =IF(D7>(C7*(Assumptions!C52-(F$49-IF(F38="preference",D7,0))+$C$20)/($C$19+(F$50-IF(F38="convert",C7,0))+C7)),"preference","convert") -> preference | G7: =IF(D7>(C7*(Assumptions!C53-(G$49-IF(G38="preference",D7,0))+$C$20)/($C$19+(G$50-IF(G38="convert",C7,0))+C7)),"preference","convert") -> convert | H7: =IF(D7>(C7*(Assumptions!C54-(H$49-IF(H38="preference",D7,0))+$C$20)/($C$19+(H$50-IF(H38="convert",C7,0))+C7)),"preference","convert") -> convert | I7: =IF(D7>(C7*(Assumptions!C55-(I$49-IF(I38="preference",D7,0))+$C$20)/($C$19+(I$50-IF(I38="convert",C7,0))+C7)),"preference","convert") -> convert | J7: =IF(E7="preference",D7,C7*E60) -> 30000000 | K7: =IF(F7="preference",D7,C7*F60) -> 30000000 | L7: =IF(G7="preference",D7,C7*G60) -> 44786047 | M7: =IF(H7="preference",D7,C7*H60) -> 89664548 | N7: =IF(I7="preference",D7,C7*I60) -> 1.7927309e+08
B8: Series E | C8: ='Pro-Forma'!G34 -> 6134287.6 | D8: =Assumptions!C36*Assumptions!C37 -> 2.999968e+08 | E8: =IF(D8>(C8*(Assumptions!C51-(E$49-IF(E39="preference",D8,0))+$C$20)/($C$19+(E$50-IF(E39="convert",C8,0))+C8)),"preference","convert") -> preference | F8: =IF(D8>(C8*(Assumptions!C52-(F$49-IF(F39="preference",D8,0))+$C$20)/($C$19+(F$50-IF(F39="convert",C8,0))+C8)),"preference","convert") -> preference | G8: =IF(D8>(C8*(Assumptions!C53-(G$49-IF(G39="preference",D8,0))+$C$20)/($C$19+(G$50-IF(G39="convert",C8,0))+C8)),"preference","convert") -> convert | H8: =IF(D8>(C8*(Assumptions!C54-(H$49-IF(H39="preference",D8,0))+$C$20)/($C$19+(H$50-IF(H39="convert",C8,0))+C8)),"preference","convert") -> convert | I8: =IF(D8>(C8*(Assumptions!C55-(I$49-IF(I39="preference",D8,0))+$C$20)/($C$19+(I$50-IF(I39="convert",C8,0))+C8)),"preference","convert") -> convert | J8: =IF(E8="preference",D8,C8*E60) -> 2.999968e+08 | K8: =IF(F8="preference",D8,C8*F60) -> 2.999968e+08 | L8: =IF(G8="preference",D8,C8*G60) -> 3.4205809e+08 | M8: =IF(H8="preference",D8,C8*H60) -> 6.8482232e+08 | N8: =IF(I8="preference",D8,C8*I60) -> 1.3692169e+09
B9: Series D | C9: ='Pro-Forma'!G33 -> 1733924.4 | D9: =Assumptions!C32*Assumptions!C34 -> 100000020 | E9: =IF(D9>(C9*(Assumptions!C51-(E$49-IF(E40="preference",D9,0))+$C$20)/($C$19+(E$50-IF(E40="convert",C9,0))+C9)),"preference","convert") -> preference | F9: =IF(D9>(C9*(Assumptions!C52-(F$49-IF(F40="preference",D9,0))+$C$20)/($C$19+(F$50-IF(F40="convert",C9,0))+C9)),"preference","convert") -> preference | G9: =IF(D9>(C9*(Assumptions!C53-(G$49-IF(G40="preference",D9,0))+$C$20)/($C$19+(G$50-IF(G40="convert",C9,0))+C9)),"preference","convert") -> preference | H9: =IF(D9>(C9*(Assumptions!C54-(H$49-IF(H40="preference",D9,0))+$C$20)/($C$19+(H$50-IF(H40="convert",C9,0))+C9)),"preference","convert") -> convert | I9: =IF(D9>(C9*(Assumptions!C55-(I$49-IF(I40="preference",D9,0))+$C$20)/($C$19+(I$50-IF(I40="convert",C9,0))+C9)),"preference","convert") -> convert | J9: =IF(E9="preference",D9,C9*E60) -> 100000020 | K9: =IF(F9="preference",D9,C9*F60) -> 100000020 | L9: =IF(G9="preference",D9,C9*G60) -> 100000020 | M9: =IF(H9="preference",D9,C9*H60) -> 1.9357262e+08 | N9: =IF(I9="preference",D9,C9*I60) -> 3.8702433e+08
B10: Series C | C10: ='Pro-Forma'!G32 -> 2400000 | D10: =Assumptions!C30*Assumptions!C31 -> 60000000 | E10: =IF(D10>(C10*(Assumptions!C51-(E$49-IF(E41="preference",D10,0))+$C$20)/($C$19+(E$50-IF(E41="convert",C10,0))+C10)),"preference","convert") -> preference | F10: =IF(D10>(C10*(Assumptions!C52-(F$49-IF(F41="preference",D10,0))+$C$20)/($C$19+(F$50-IF(F41="convert",C10,0))+C10)),"preference","convert") -> convert | G10: =IF(D10>(C10*(Assumptions!C53-(G$49-IF(G41="preference",D10,0))+$C$20)/($C$19+(G$50-IF(G41="convert",C10,0))+C10)),"preference","convert") -> convert | H10: =IF(D10>(C10*(Assumptions!C54-(H$49-IF(H41="preference",D10,0))+$C$20)/($C$19+(H$50-IF(H41="convert",C10,0))+C10)),"preference","convert") -> convert | I10: =IF(D10>(C10*(Assumptions!C55-(I$49-IF(I41="preference",D10,0))+$C$20)/($C$19+(I$50-IF(I41="convert",C10,0))+C10)),"preference","convert") -> convert | J10: =IF(E10="preference",D10,C10*E60) -> 60000000 | K10: =IF(F10="preference",D10,C10*F60) -> 68209781 | L10: =IF(G10="preference",D10,C10*G60) -> 1.33828e+08 | M10: =IF(H10="preference",D10,C10*H60) -> 2.6793226e+08 | N10: =IF(I10="preference",D10,C10*I60) -> 5.3569717e+08
B11: Series B | C11: ='Pro-Forma'!G31 -> 3000000 | D11: =Assumptions!C28*Assumptions!C29 -> 30000000 | E11: =IF(D11>(C11*(Assumptions!C51-(E$49-IF(E42="preference",D11,0))+$C$20)/($C$19+(E$50-IF(E42="convert",C11,0))+C11)),"preference","convert") -> preference | F11: =IF(D11>(C11*(Assumptions!C52-(F$49-IF(F42="preference",D11,0))+$C$20)/($C$19+(F$50-IF(F42="convert",C11,0))+C11)),"preference","convert") -> convert | G11: =IF(D11>(C11*(Assumptions!C53-(G$49-IF(G42="preference",D11,0))+$C$20)/($C$19+(G$50-IF(G42="convert",C11,0))+C11)),"preference","convert") -> convert | H11: =IF(D11>(C11*(Assumptions!C54-(H$49-IF(H42="preference",D11,0))+$C$20)/($C$19+(H$50-IF(H42="convert",C11,0))+C11)),"preference","convert") -> convert | I11: =IF(D11>(C11*(Assumptions!C55-(I$49-IF(I42="preference",D11,0))+$C$20)/($C$19+(I$50-IF(I42="convert",C11,0))+C11)),"preference","convert") -> convert | J11: =IF(E11="preference",D11,C11*E60) -> 30000000 | K11: =IF(F11="preference",D11,C11*F60) -> 85262227 | L11: =IF(G11="preference",D11,C11*G60) -> 1.67285e+08 | M11: =IF(H11="preference",D11,C11*H60) -> 3.3491533e+08 | N11: =IF(I11="preference",D11,C11*I60) -> 6.6962146e+08
B12: Series A | C12: ='Pro-Forma'!G30 -> 5000000 | D12: =Assumptions!C26*Assumptions!C27 -> 15000000 | E12: =IF(D12>(C12*(Assumptions!C51-(E$49-IF(E43="preference",D12,0))+$C$20)/($C$19+(E$50-IF(E43="convert",C12,0))+C12)),"preference","convert") -> convert | F12: =IF(D12>(C12*(Assumptions!C52-(F$49-IF(F43="preference",D12,0))+$C$20)/($C$19+(F$50-IF(F43="convert",C12,0))+C12)),"preference","convert") -> convert | G12: =IF(D12>(C12*(Assumptions!C53-(G$49-IF(G43="preference",D12,0))+$C$20)/($C$19+(G$50-IF(G43="convert",C12,0))+C12)),"preference","convert") -> convert | H12: =IF(D12>(C12*(Assumptions!C54-(H$49-IF(H43="preference",D12,0))+$C$20)/($C$19+(H$50-IF(H43="convert",C12,0))+C12)),"preference","convert") -> convert | I12: =IF(D12>(C12*(Assumptions!C55-(I$49-IF(I43="preference",D12,0))+$C$20)/($C$19+(I$50-IF(I43="convert",C12,0))+C12)),"preference","convert") -> convert | J12: =IF(E12="preference",D12,C12*E60) -> 41895110 | K12: =IF(F12="preference",D12,C12*F60) -> 1.4210371e+08 | L12: =IF(G12="preference",D12,C12*G60) -> 2.7880833e+08 | M12: =IF(H12="preference",D12,C12*H60) -> 5.5819221e+08 | N12: =IF(I12="preference",D12,C12*I60) -> 1.1160358e+09
B13: Seed | C13: ='Pro-Forma'!G29 -> 5000000 | D13: =Assumptions!C24*Assumptions!C25 -> 5000000 | E13: =IF(D13>(C13*(Assumptions!C51-(E$49-IF(E44="preference",D13,0))+$C$20)/($C$19+(E$50-IF(E44="convert",C13,0))+C13)),"preference","convert") -> convert | F13: =IF(D13>(C13*(Assumptions!C52-(F$49-IF(F44="preference",D13,0))+$C$20)/($C$19+(F$50-IF(F44="convert",C13,0))+C13)),"preference","convert") -> convert | G13: =IF(D13>(C13*(Assumptions!C53-(G$49-IF(G44="preference",D13,0))+$C$20)/($C$19+(G$50-IF(G44="convert",C13,0))+C13)),"preference","convert") -> convert | H13: =IF(D13>(C13*(Assumptions!C54-(H$49-IF(H44="preference",D13,0))+$C$20)/($C$19+(H$50-IF(H44="convert",C13,0))+C13)),"preference","convert") -> convert | I13: =IF(D13>(C13*(Assumptions!C55-(I$49-IF(I44="preference",D13,0))+$C$20)/($C$19+(I$50-IF(I44="convert",C13,0))+C13)),"preference","convert") -> convert | J13: =IF(E13="preference",D13,C13*E60) -> 41895110 | K13: =IF(F13="preference",D13,C13*F60) -> 1.4210371e+08 | L13: =IF(G13="preference",D13,C13*G60) -> 2.7880833e+08 | M13: =IF(H13="preference",D13,C13*H60) -> 5.5819221e+08 | N13: =IF(I13="preference",D13,C13*I60) -> 1.1160358e+09
B14: Common+RSA / Notes / Options (non-class, always convert)
B15: Non-Class Pool Constants
B16: Common + RSAs (founders + F_LEAD tender + employees) | C16: =Assumptions!C15+Assumptions!C16+Assumptions!C17+Assumptions!C18 -> 9000000
B17: Issued options (assumed ITM at all 5 exits) | C17: =Assumptions!C19 -> 2500000
B18: Notes shares (Note A + Note B, common-equiv post-conv.) | C18: ='Pro-Forma'!G40+'Pro-Forma'!G41 -> 280964.26
B19: Non-class pool subtotal (rides convert pool always) | C19: =C16+C17+C18 -> 11780964
B20: Issued options strike value (added to residual on ITM) | C20: =Assumptions!C19*Assumptions!C12 -> 2500000
B22: Iteration 1 (bootstrap: assume all others convert)
B23: Class | C23: Pool if all convert | D23: Residual | E23: Exit 1 elec | F23: Exit 2 elec | G23: Exit 3 elec | H23: Exit 4 elec | I23: Exit 5 elec
B24: Series F | C24: =C19+SUM(C7:C13) -> 35852345 | E24: =IF(D7>C7*(Assumptions!C51+C20)/C24,"preference","convert") -> preference | F24: =IF(D7>C7*(Assumptions!C52+C20)/C24,"preference","convert") -> preference | G24: =IF(D7>C7*(Assumptions!C53+C20)/C24,"preference","convert") -> convert | H24: =IF(D7>C7*(Assumptions!C54+C20)/C24,"preference","convert") -> convert | I24: =IF(D7>C7*(Assumptions!C55+C20)/C24,"preference","convert") -> convert
B25: Series E | E25: =IF(D8>C8*(Assumptions!C51+C20)/C24,"preference","convert") -> preference | F25: =IF(D8>C8*(Assumptions!C52+C20)/C24,"preference","convert") -> preference | G25: =IF(D8>C8*(Assumptions!C53+C20)/C24,"preference","convert") -> convert | H25: =IF(D8>C8*(Assumptions!C54+C20)/C24,"preference","convert") -> convert | I25: =IF(D8>C8*(Assumptions!C55+C20)/C24,"preference","convert") -> convert
B26: Series D | E26: =IF(D9>C9*(Assumptions!C51+C20)/C24,"preference","convert") -> preference | F26: =IF(D9>C9*(Assumptions!C52+C20)/C24,"preference","convert") -> preference | G26: =IF(D9>C9*(Assumptions!C53+C20)/C24,"preference","convert") -> preference | H26: =IF(D9>C9*(Assumptions!C54+C20)/C24,"preference","convert") -> convert | I26: =IF(D9>C9*(Assumptions!C55+C20)/C24,"preference","convert") -> convert
B27: Series C | E27: =IF(D10>C10*(Assumptions!C51+C20)/C24,"preference","convert") -> preference | F27: =IF(D10>C10*(Assumptions!C52+C20)/C24,"preference","convert") -> convert | G27: =IF(D10>C10*(Assumptions!C53+C20)/C24,"preference","convert") -> convert | H27: =IF(D10>C10*(Assumptions!C54+C20)/C24,"preference","convert") -> convert | I27: =IF(D10>C10*(Assumptions!C55+C20)/C24,"preference","convert") -> convert
B28: Series B | E28: =IF(D11>C11*(Assumptions!C51+C20)/C24,"preference","convert") -> convert | F28: =IF(D11>C11*(Assumptions!C52+C20)/C24,"preference","convert") -> convert | G28: =IF(D11>C11*(Assumptions!C53+C20)/C24,"preference","convert") -> convert | H28: =IF(D11>C11*(Assumptions!C54+C20)/C24,"preference","convert") -> convert | I28: =IF(D11>C11*(Assumptions!C55+C20)/C24,"preference","convert") -> convert
B29: Series A | E29: =IF(D12>C12*(Assumptions!C51+C20)/C24,"preference","convert") -> convert | F29: =IF(D12>C12*(Assumptions!C52+C20)/C24,"preference","convert") -> convert | G29: =IF(D12>C12*(Assumptions!C53+C20)/C24,"preference","convert") -> convert | H29: =IF(D12>C12*(Assumptions!C54+C20)/C24,"preference","convert") -> convert | I29: =IF(D12>C12*(Assumptions!C55+C20)/C24,"preference","convert") -> convert
B30: Seed | E30: =IF(D13>C13*(Assumptions!C51+C20)/C24,"preference","convert") -> convert | F30: =IF(D13>C13*(Assumptions!C52+C20)/C24,"preference","convert") -> convert | G30: =IF(D13>C13*(Assumptions!C53+C20)/C24,"preference","convert") -> convert | H30: =IF(D13>C13*(Assumptions!C54+C20)/C24,"preference","convert") -> convert | I30: =IF(D13>C13*(Assumptions!C55+C20)/C24,"preference","convert") -> convert
B33: Iteration 2 (uses iter-1 profile of others)
B34: Per-exit aggregates from iter 1 | E34: Exit 1 | F34: Exit 2 | G34: Exit 3 | H34: Exit 4 | I34: Exit 5
B35: Total iter-1 prefs ($) | E35: =SUMPRODUCT((E24:E30="preference")*$D$7:$D$13) -> 4.8999682e+08 | F35: =SUMPRODUCT((F24:F30="preference")*$D$7:$D$13) -> 4.2999682e+08 | G35: =SUMPRODUCT((G24:G30="preference")*$D$7:$D$13) -> 100000020 | H35: =SUMPRODUCT((H24:H30="preference")*$D$7:$D$13) -> 0 | I35: =SUMPRODUCT((I24:I30="preference")*$D$7:$D$13) -> 0
B36: Total iter-1 convert shares | E36: =SUMPRODUCT((E24:E30="convert")*$C$7:$C$13) -> 13000000 | F36: =SUMPRODUCT((F24:F30="convert")*$C$7:$C$13) -> 15400000 | G36: =SUMPRODUCT((G24:G30="convert")*$C$7:$C$13) -> 22337457 | H36: =SUMPRODUCT((H24:H30="convert")*$C$7:$C$13) -> 24071381 | I36: =SUMPRODUCT((I24:I30="convert")*$C$7:$C$13) -> 24071381
B37: Iter 2 elections | E37: Exit 1 | F37: Exit 2 | G37: Exit 3 | H37: Exit 4 | I37: Exit 5
B38: Series F | E38: =IF(D7>(C7*(Assumptions!C51-(E$35-IF(E24="preference",D7,0))+$C$20)/($C$19+(E$36-IF(E24="convert",C7,0))+C7)),"preference","convert") -> preference | F38: =IF(D7>(C7*(Assumptions!C52-(F$35-IF(F24="preference",D7,0))+$C$20)/($C$19+(F$36-IF(F24="convert",C7,0))+C7)),"preference","convert") -> preference | G38: =IF(D7>(C7*(Assumptions!C53-(G$35-IF(G24="preference",D7,0))+$C$20)/($C$19+(G$36-IF(G24="convert",C7,0))+C7)),"preference","convert") -> convert | H38: =IF(D7>(C7*(Assumptions!C54-(H$35-IF(H24="preference",D7,0))+$C$20)/($C$19+(H$36-IF(H24="convert",C7,0))+C7)),"preference","convert") -> convert | I38: =IF(D7>(C7*(Assumptions!C55-(I$35-IF(I24="preference",D7,0))+$C$20)/($C$19+(I$36-IF(I24="convert",C7,0))+C7)),"preference","convert") -> convert
B39: Series E | E39: =IF(D8>(C8*(Assumptions!C51-(E$35-IF(E25="preference",D8,0))+$C$20)/($C$19+(E$36-IF(E25="convert",C8,0))+C8)),"preference","convert") -> preference | F39: =IF(D8>(C8*(Assumptions!C52-(F$35-IF(F25="preference",D8,0))+$C$20)/($C$19+(F$36-IF(F25="convert",C8,0))+C8)),"preference","convert") -> preference | G39: =IF(D8>(C8*(Assumptions!C53-(G$35-IF(G25="preference",D8,0))+$C$20)/($C$19+(G$36-IF(G25="convert",C8,0))+C8)),"preference","convert") -> convert | H39: =IF(D8>(C8*(Assumptions!C54-(H$35-IF(H25="preference",D8,0))+$C$20)/($C$19+(H$36-IF(H25="convert",C8,0))+C8)),"preference","convert") -> convert | I39: =IF(D8>(C8*(Assumptions!C55-(I$35-IF(I25="preference",D8,0))+$C$20)/($C$19+(I$36-IF(I25="convert",C8,0))+C8)),"preference","convert") -> convert
B40: Series D | E40: =IF(D9>(C9*(Assumptions!C51-(E$35-IF(E26="preference",D9,0))+$C$20)/($C$19+(E$36-IF(E26="convert",C9,0))+C9)),"preference","convert") -> preference | F40: =IF(D9>(C9*(Assumptions!C52-(F$35-IF(F26="preference",D9,0))+$C$20)/($C$19+(F$36-IF(F26="convert",C9,0))+C9)),"preference","convert") -> preference | G40: =IF(D9>(C9*(Assumptions!C53-(G$35-IF(G26="preference",D9,0))+$C$20)/($C$19+(G$36-IF(G26="convert",C9,0))+C9)),"preference","convert") -> preference | H40: =IF(D9>(C9*(Assumptions!C54-(H$35-IF(H26="preference",D9,0))+$C$20)/($C$19+(H$36-IF(H26="convert",C9,0))+C9)),"preference","convert") -> convert | I40: =IF(D9>(C9*(Assumptions!C55-(I$35-IF(I26="preference",D9,0))+$C$20)/($C$19+(I$36-IF(I26="convert",C9,0))+C9)),"preference","convert") -> convert
B41: Series C | E41: =IF(D10>(C10*(Assumptions!C51-(E$35-IF(E27="preference",D10,0))+$C$20)/($C$19+(E$36-IF(E27="convert",C10,0))+C10)),"preference","convert") -> preference | F41: =IF(D10>(C10*(Assumptions!C52-(F$35-IF(F27="preference",D10,0))+$C$20)/($C$19+(F$36-IF(F27="convert",C10,0))+C10)),"preference","convert") -> convert | G41: =IF(D10>(C10*(Assumptions!C53-(G$35-IF(G27="preference",D10,0))+$C$20)/($C$19+(G$36-IF(G27="convert",C10,0))+C10)),"preference","convert") -> convert | H41: =IF(D10>(C10*(Assumptions!C54-(H$35-IF(H27="preference",D10,0))+$C$20)/($C$19+(H$36-IF(H27="convert",C10,0))+C10)),"preference","convert") -> convert | I41: =IF(D10>(C10*(Assumptions!C55-(I$35-IF(I27="preference",D10,0))+$C$20)/($C$19+(I$36-IF(I27="convert",C10,0))+C10)),"preference","convert") -> convert
B42: Series B | E42: =IF(D11>(C11*(Assumptions!C51-(E$35-IF(E28="preference",D11,0))+$C$20)/($C$19+(E$36-IF(E28="convert",C11,0))+C11)),"preference","convert") -> preference | F42: =IF(D11>(C11*(Assumptions!C52-(F$35-IF(F28="preference",D11,0))+$C$20)/($C$19+(F$36-IF(F28="convert",C11,0))+C11)),"preference","convert") -> convert | G42: =IF(D11>(C11*(Assumptions!C53-(G$35-IF(G28="preference",D11,0))+$C$20)/($C$19+(G$36-IF(G28="convert",C11,0))+C11)),"preference","convert") -> convert | H42: =IF(D11>(C11*(Assumptions!C54-(H$35-IF(H28="preference",D11,0))+$C$20)/($C$19+(H$36-IF(H28="convert",C11,0))+C11)),"preference","convert") -> convert | I42: =IF(D11>(C11*(Assumptions!C55-(I$35-IF(I28="preference",D11,0))+$C$20)/($C$19+(I$36-IF(I28="convert",C11,0))+C11)),"preference","convert") -> convert
B43: Series A | E43: =IF(D12>(C12*(Assumptions!C51-(E$35-IF(E29="preference",D12,0))+$C$20)/($C$19+(E$36-IF(E29="convert",C12,0))+C12)),"preference","convert") -> convert | F43: =IF(D12>(C12*(Assumptions!C52-(F$35-IF(F29="preference",D12,0))+$C$20)/($C$19+(F$36-IF(F29="convert",C12,0))+C12)),"preference","convert") -> convert | G43: =IF(D12>(C12*(Assumptions!C53-(G$35-IF(G29="preference",D12,0))+$C$20)/($C$19+(G$36-IF(G29="convert",C12,0))+C12)),"preference","convert") -> convert | H43: =IF(D12>(C12*(Assumptions!C54-(H$35-IF(H29="preference",D12,0))+$C$20)/($C$19+(H$36-IF(H29="convert",C12,0))+C12)),"preference","convert") -> convert | I43: =IF(D12>(C12*(Assumptions!C55-(I$35-IF(I29="preference",D12,0))+$C$20)/($C$19+(I$36-IF(I29="convert",C12,0))+C12)),"preference","convert") -> convert
B44: Seed | E44: =IF(D13>(C13*(Assumptions!C51-(E$35-IF(E30="preference",D13,0))+$C$20)/($C$19+(E$36-IF(E30="convert",C13,0))+C13)),"preference","convert") -> convert | F44: =IF(D13>(C13*(Assumptions!C52-(F$35-IF(F30="preference",D13,0))+$C$20)/($C$19+(F$36-IF(F30="convert",C13,0))+C13)),"preference","convert") -> convert | G44: =IF(D13>(C13*(Assumptions!C53-(G$35-IF(G30="preference",D13,0))+$C$20)/($C$19+(G$36-IF(G30="convert",C13,0))+C13)),"preference","convert") -> convert | H44: =IF(D13>(C13*(Assumptions!C54-(H$35-IF(H30="preference",D13,0))+$C$20)/($C$19+(H$36-IF(H30="convert",C13,0))+C13)),"preference","convert") -> convert | I44: =IF(D13>(C13*(Assumptions!C55-(I$35-IF(I30="preference",D13,0))+$C$20)/($C$19+(I$36-IF(I30="convert",C13,0))+C13)),"preference","convert") -> convert
B47: Iteration 3 — FINAL (uses iter-2 profile of others)
B48: Per-exit aggregates from iter 2 | E48: Exit 1 | F48: Exit 2 | G48: Exit 3 | H48: Exit 4 | I48: Exit 5
B49: Total iter-2 prefs ($) | E49: =SUMPRODUCT((E38:E44="preference")*$D$7:$D$13) -> 5.1999682e+08 | F49: =SUMPRODUCT((F38:F44="preference")*$D$7:$D$13) -> 4.2999682e+08 | G49: =SUMPRODUCT((G38:G44="preference")*$D$7:$D$13) -> 100000020 | H49: =SUMPRODUCT((H38:H44="preference")*$D$7:$D$13) -> 0 | I49: =SUMPRODUCT((I38:I44="preference")*$D$7:$D$13) -> 0
B50: Total iter-2 convert shares | E50: =SUMPRODUCT((E38:E44="convert")*$C$7:$C$13) -> 10000000 | F50: =SUMPRODUCT((F38:F44="convert")*$C$7:$C$13) -> 15400000 | G50: =SUMPRODUCT((G38:G44="convert")*$C$7:$C$13) -> 22337457 | H50: =SUMPRODUCT((H38:H44="convert")*$C$7:$C$13) -> 24071381 | I50: =SUMPRODUCT((I38:I44="convert")*$C$7:$C$13) -> 24071381
B53: Proceeds Calculation
B54: Aggregate | E54: Exit 1 | F54: Exit 2 | G54: Exit 3 | H54: Exit 4 | I54: Exit 5
B55: Exit value | E55: =Assumptions!C51 -> 700000000 | F55: =Assumptions!C52 -> 1200000000 | G55: =Assumptions!C53 -> 2000000000 | H55: =Assumptions!C54 -> 4000000000 | I55: =Assumptions!C55 -> 8000000000
B56: Total preferences (preferring classes) | E56: =SUMPRODUCT((E$7:E$13="preference")*$D$7:$D$13) -> 5.1999682e+08 | F56: =SUMPRODUCT((F$7:F$13="preference")*$D$7:$D$13) -> 4.2999682e+08 | G56: =SUMPRODUCT((G$7:G$13="preference")*$D$7:$D$13) -> 100000020 | H56: =SUMPRODUCT((H$7:H$13="preference")*$D$7:$D$13) -> 0 | I56: =SUMPRODUCT((I$7:I$13="preference")*$D$7:$D$13) -> 0
B57: Total convert shares (converting classes) | E57: =SUMPRODUCT((E$7:E$13="convert")*$C$7:$C$13) -> 10000000 | F57: =SUMPRODUCT((F$7:F$13="convert")*$C$7:$C$13) -> 15400000 | G57: =SUMPRODUCT((G$7:G$13="convert")*$C$7:$C$13) -> 22337457 | H57: =SUMPRODUCT((H$7:H$13="convert")*$C$7:$C$13) -> 24071381 | I57: =SUMPRODUCT((I$7:I$13="convert")*$C$7:$C$13) -> 24071381
B58: Convert pool (non-class + converting classes) | E58: =$C$19+E57 -> 21780964 | F58: =$C$19+F57 -> 27180964 | G58: =$C$19+G57 -> 34118421 | H58: =$C$19+H57 -> 35852345 | I58: =$C$19+I57 -> 35852345
B59: Residual to convert pool | E59: =Assumptions!C51-E56+$C$20 -> 1.8250318e+08 | F59: =Assumptions!C52-F56+$C$20 -> 7.7250318e+08 | G59: =Assumptions!C53-G56+$C$20 -> 1902499980 | H59: =Assumptions!C54-H56+$C$20 -> 4002500000 | I59: =Assumptions!C55-I56+$C$20 -> 8002500000
B60: Per-share value (convert pool) | E60: =E59/E58 -> 8.379022 | F60: =F59/F58 -> 28.420742 | G60: =G59/G58 -> 55.761666 | H60: =H59/H58 -> 111.63844 | I60: =I59/I58 -> 223.20715
B62: Non-class proceeds detail | E62: Exit 1 | F62: Exit 2 | G62: Exit 3 | H62: Exit 4 | I62: Exit 5
B63: Common + RSA proceeds | E63: =$C$16*E60 -> 75411198 | F63: =$C$16*F60 -> 2.5578668e+08 | G63: =$C$16*G60 -> 5.0185499e+08 | H63: =$C$16*H60 -> 1.004746e+09 | I63: =$C$16*I60 -> 2.0088644e+09
B64: Notes (Note A + Note B) proceeds | E64: =$C$18*E60 -> 2354205.7 | F64: =$C$18*F60 -> 7985212.8 | G64: =$C$18*G60 -> 15667035 | H64: =$C$18*H60 -> 31366413 | I64: =$C$18*I60 -> 62713233
B65: Issued options proceeds (gross, less strike) | E65: =$C$17*E60-$C$20 -> 18447555 | F65: =$C$17*F60-$C$20 -> 68551855 | G65: =$C$17*G60-$C$20 -> 1.3690416e+08 | H65: =$C$17*H60-$C$20 -> 2.7659611e+08 | I65: =$C$17*I60-$C$20 -> 5.5551789e+08
B66: Sum non-class proceeds | E66: =E63+E64+E65 -> 96212958 | F66: =F63+F64+F65 -> 3.3232375e+08 | G66: =G63+G64+G65 -> 6.5442619e+08 | H66: =H63+H64+H65 -> 1.3127085e+09 | I66: =I63+I64+I65 -> 2.6270955e+09
B67: Sum class proceeds | E67: =SUM(J7:J13) -> 6.0378704e+08 | F67: =SUM(K7:K13) -> 8.6767625e+08 | G67: =SUM(L7:L13) -> 1.3455738e+09 | H67: =SUM(M7:M13) -> 2.6872915e+09 | I67: =SUM(N7:N13) -> 5.3729045e+09
B68: Total proceeds (class + non-class) | E68: =E66+E67 -> 700000000 | F68: =F66+F67 -> 1200000000 | G68: =G66+G67 -> 2e+09 | H68: =H66+H67 -> 4e+09 | I68: =I66+I67 -> 8e+09
B69: Reconcile: total - exit value | E69: =ROUND(E68-Assumptions!C51,0) -> 0 | F69: =ROUND(F68-Assumptions!C52,0) -> 0 | G69: =ROUND(G68-Assumptions!C53,0) -> 0 | H69: =ROUND(H68-Assumptions!C54,0) -> 0 | I69: =ROUND(I68-Assumptions!C55,0) -> 0
B70: Check | E70: =ROUND(E69,0) -> 0 | F70: =ROUND(F69,0) -> 0 | G70: =ROUND(G69,0) -> 0 | H70: =ROUND(H69,0) -> 0 | I70: =ROUND(I69,0) -> 0

Sheet Sensitivity
B2: Sensitivity: Our $10M Check at $2B Exit
B3: 3x3 grid: ESOP refresh % x Series F pre-money; each cell re-solves full fixed point
B5: Post-F Ownership % (Our $10M Check)
B6: ESOP \ Pre-Money | C6: =Assumptions!C61 -> 1200000000 | D6: =Assumptions!C62 -> 1400000000 | E6: =Assumptions!C63 -> 1800000000
B7: =Assumptions!C58 -> 0.11 | C7: =D104 -> 0.0081150469 | D7: =E104 -> 0.0069851711 | E7: =F104 -> 0.0054637141
B8: =Assumptions!C59 -> 0.13 | C8: =G104 -> 0.0081141505 | D8: =H104 -> 0.0069844697 | E8: =I104 -> 0.0054631986
B9: =Assumptions!C60 -> 0.15 | C9: =J104 -> 0.0081126595 | D9: =K104 -> 0.0069832552 | E9: =L104 -> 0.0054622664
B12: $ Proceeds at $2B Exit (Our $10M Check)
B13: ESOP \ Pre-Money | C13: =Assumptions!C61 -> 1200000000 | D13: =Assumptions!C62 -> 1400000000 | E13: =Assumptions!C63 -> 1800000000
B14: =Assumptions!C58 -> 0.11 | C14: =D103 -> 17075712 | D14: =E103 -> 14703203 | E14: =F103 -> 11505529
B15: =Assumptions!C59 -> 0.13 | C15: =G103 -> 17345736 | D15: =H103 -> 14927842 | E15: =I103 -> 11673414
B16: =Assumptions!C60 -> 0.15 | C16: =J103 -> 17750051 | D16: =K103 -> 15276172 | E16: =L103 -> 11946055
B19: Per-Cell Fixed-Point Solve & Waterfall (helper block)
B20: Cell parameter \ (esop, pre) | D20: 11% / $1.2B | E20: 11% / $1.4B | F20: 11% / $1.8B | G20: 13% / $1.2B | H20: 13% / $1.4B | I20: 13% / $1.8B | J20: 15% / $1.2B | K20: 15% / $1.4B | L20: 15% / $1.8B
B21: ESOP target | D21: =Assumptions!C58 -> 0.11 | E21: =Assumptions!C58 -> 0.11 | F21: =Assumptions!C58 -> 0.11 | G21: =Assumptions!C59 -> 0.13 | H21: =Assumptions!C59 -> 0.13 | I21: =Assumptions!C59 -> 0.13 | J21: =Assumptions!C60 -> 0.15 | K21: =Assumptions!C60 -> 0.15 | L21: =Assumptions!C60 -> 0.15
B22: Pre-money | D22: =Assumptions!C61 -> 1200000000 | E22: =Assumptions!C62 -> 1400000000 | F22: =Assumptions!C63 -> 1800000000 | G22: =Assumptions!C61 -> 1200000000 | H22: =Assumptions!C62 -> 1400000000 | I22: =Assumptions!C63 -> 1800000000 | J22: =Assumptions!C61 -> 1200000000 | K22: =Assumptions!C62 -> 1400000000 | L22: =Assumptions!C63 -> 1800000000
B23: Primary raise (constant) | D23: =Assumptions!C6 -> 30000000 | E23: =Assumptions!C6 -> 30000000 | F23: =Assumptions!C6 -> 30000000 | G23: =Assumptions!C6 -> 30000000 | H23: =Assumptions!C6 -> 30000000 | I23: =Assumptions!C6 -> 30000000 | J23: =Assumptions!C6 -> 30000000 | K23: =Assumptions!C6 -> 30000000 | L23: =Assumptions!C6 -> 30000000
B24: Iter 0: ESOP top-up (init=0) | D24: 0 | E24: 0 | F24: 0 | G24: 0 | H24: 0 | I24: 0 | J24: 0 | K24: 0 | L24: 0
B25: Iter 0: nA (init=0) | D25: 0 | E25: 0 | F25: 0 | G25: 0 | H25: 0 | I25: 0 | J25: 0 | K25: 0 | L25: 0
B26: Iter 0: nB (init=0) | D26: 0 | E26: 0 | F26: 0 | G26: 0 | H26: 0 | I26: 0 | J26: 0 | K26: 0 | L26: 0
B27: Iter 1: F PPS | D27: =D$22/(Assumptions!C21+D24+D25+D26) -> 32.770803 | E27: =E$22/(Assumptions!C21+E24+E25+E26) -> 38.232604 | F27: =F$22/(Assumptions!C21+F24+F25+F26) -> 49.156205 | G27: =G$22/(Assumptions!C21+G24+G25+G26) -> 32.770803 | H27: =H$22/(Assumptions!C21+H24+H25+H26) -> 38.232604 | I27: =I$22/(Assumptions!C21+I24+I25+I26) -> 49.156205 | J27: =J$22/(Assumptions!C21+J24+J25+J26) -> 32.770803 | K27: =K$22/(Assumptions!C21+K24+K25+K26) -> 38.232604 | L27: =L$22/(Assumptions!C21+L24+L25+L26) -> 49.156205
B28: Iter 1: ESOP top-up | D28: =MAX(0,D$21*(D$22+D$23)/D27-(Assumptions!C19+Assumptions!C20)) -> 0 | E28: =MAX(0,E$21*(E$22+E$23)/E27-(Assumptions!C19+Assumptions!C20)) -> 0 | F28: =MAX(0,F$21*(F$22+F$23)/F27-(Assumptions!C19+Assumptions!C20)) -> 0 | G28: =MAX(0,G$21*(G$22+G$23)/G27-(Assumptions!C19+Assumptions!C20)) -> 484676.3 | H28: =MAX(0,H$21*(H$22+H$23)/H27-(Assumptions!C19+Assumptions!C20)) -> 467675.11 | I28: =MAX(0,I$21*(I$22+I$23)/I27-(Assumptions!C19+Assumptions!C20)) -> 445006.85 | J28: =MAX(0,J$21*(J$22+J$23)/J27-(Assumptions!C19+Assumptions!C20)) -> 1235344.5 | K28: =MAX(0,K$21*(K$22+K$23)/K27-(Assumptions!C19+Assumptions!C20)) -> 1215727.7 | L28: =MAX(0,L$21*(L$22+L$23)/L27-(Assumptions!C19+Assumptions!C20)) -> 1189572.1
B29: Iter 1: nA = MAX(cap, disc) | D29: =MAX(Assumptions!C40*(Assumptions!C21+D28+D26)/Assumptions!C41,Assumptions!C40/((1-Assumptions!C42)*D27)) -> 190718.55 | E29: =MAX(Assumptions!C40*(Assumptions!C21+E28+E26)/Assumptions!C41,Assumptions!C40/((1-Assumptions!C42)*E27)) -> 183089.8 | F29: =MAX(Assumptions!C40*(Assumptions!C21+F28+F26)/Assumptions!C41,Assumptions!C40/((1-Assumptions!C42)*F27)) -> 183089.8 | G29: =MAX(Assumptions!C40*(Assumptions!C21+G28+G26)/Assumptions!C41,Assumptions!C40/((1-Assumptions!C42)*G27)) -> 190718.55 | H29: =MAX(Assumptions!C40*(Assumptions!C21+H28+H26)/Assumptions!C41,Assumptions!C40/((1-Assumptions!C42)*H27)) -> 185428.18 | I29: =MAX(Assumptions!C40*(Assumptions!C21+I28+I26)/Assumptions!C41,Assumptions!C40/((1-Assumptions!C42)*I27)) -> 185314.84 | J29: =MAX(Assumptions!C40*(Assumptions!C21+J28+J26)/Assumptions!C41,Assumptions!C40/((1-Assumptions!C42)*J27)) -> 190718.55 | K29: =MAX(Assumptions!C40*(Assumptions!C21+K28+K26)/Assumptions!C41,Assumptions!C40/((1-Assumptions!C42)*K27)) -> 189168.44 | L29: =MAX(Assumptions!C40*(Assumptions!C21+L28+L26)/Assumptions!C41,Assumptions!C40/((1-Assumptions!C42)*L27)) -> 189037.67
B30: Iter 1: nB = MAX(cap, disc) | D30: =MAX(Assumptions!C43*(Assumptions!C21+D28+D29)/Assumptions!C44,Assumptions!C43/((1-Assumptions!C45)*D27)) -> 107699.89 | E30: =MAX(Assumptions!C43*(Assumptions!C21+E28+E29)/Assumptions!C44,Assumptions!C43/((1-Assumptions!C45)*E27)) -> 92314.187 | F30: =MAX(Assumptions!C43*(Assumptions!C21+F28+F29)/Assumptions!C44,Assumptions!C43/((1-Assumptions!C45)*F27)) -> 71799.924 | G30: =MAX(Assumptions!C43*(Assumptions!C21+G28+G29)/Assumptions!C44,Assumptions!C43/((1-Assumptions!C45)*G27)) -> 107699.89 | H30: =MAX(Assumptions!C43*(Assumptions!C21+H28+H29)/Assumptions!C44,Assumptions!C43/((1-Assumptions!C45)*H27)) -> 92314.187 | I30: =MAX(Assumptions!C43*(Assumptions!C21+I28+I29)/Assumptions!C44,Assumptions!C43/((1-Assumptions!C45)*I27)) -> 71799.924 | J30: =MAX(Assumptions!C43*(Assumptions!C21+J28+J29)/Assumptions!C44,Assumptions!C43/((1-Assumptions!C45)*J27)) -> 107699.89 | K30: =MAX(Assumptions!C43*(Assumptions!C21+K28+K29)/Assumptions!C44,Assumptions!C43/((1-Assumptions!C45)*K27)) -> 92314.187 | L30: =MAX(Assumptions!C43*(Assumptions!C21+L28+L29)/Assumptions!C44,Assumptions!C43/((1-Assumptions!C45)*L27)) -> 71799.924
B31: Iter 2: F PPS | D31: =D$22/(Assumptions!C21+D28+D29+D30) -> 32.505896 | E31: =E$22/(Assumptions!C21+E28+E29+E30) -> 37.947203 | F31: =F$22/(Assumptions!C21+F28+F29+F30) -> 48.816405 | G31: =G$22/(Assumptions!C21+G28+G29+G30) -> 32.084656 | H31: =H$22/(Assumptions!C21+H28+H29+H30) -> 37.469845 | I31: =I$22/(Assumptions!C21+I28+I29+I30) -> 48.231404 | J31: =J$22/(Assumptions!C21+J28+J29+J30) -> 31.453362 | K31: =K$22/(Assumptions!C21+K28+K29+K30) -> 36.730781 | L31: =L$22/(Assumptions!C21+L28+L29+L30) -> 47.283348
B32: Iter 2: ESOP top-up | D32: =MAX(0,D$21*(D$22+D$23)/D31-(Assumptions!C19+Assumptions!C20)) -> 0 | E32: =MAX(0,E$21*(E$22+E$23)/E31-(Assumptions!C19+Assumptions!C20)) -> 0 | F32: =MAX(0,F$21*(F$22+F$23)/F31-(Assumptions!C19+Assumptions!C20)) -> 0 | G32: =MAX(0,G$21*(G$22+G$23)/G31-(Assumptions!C19+Assumptions!C20)) -> 589023.68 | H32: =MAX(0,H$21*(H$22+H$23)/H31-(Assumptions!C19+Assumptions!C20)) -> 566655.9 | I32: =MAX(0,I$21*(I$22+I$23)/I31-(Assumptions!C19+Assumptions!C20)) -> 537803.92 | J32: =MAX(0,J$21*(J$22+J$23)/J31-(Assumptions!C19+Assumptions!C20)) -> 1471160.6 | K32: =MAX(0,K$21*(K$22+K$23)/K31-(Assumptions!C19+Assumptions!C20)) -> 1445121.8 | L32: =MAX(0,L$21*(L$22+L$23)/L31-(Assumptions!C19+Assumptions!C20)) -> 1410759.5
B33: Iter 2: nA = MAX(cap, disc) | D33: =MAX(Assumptions!C40*(Assumptions!C21+D32+D30)/Assumptions!C41,Assumptions!C40/((1-Assumptions!C42)*D31)) -> 192272.81 | E33: =MAX(Assumptions!C40*(Assumptions!C21+E32+E30)/Assumptions!C41,Assumptions!C40/((1-Assumptions!C42)*E31)) -> 183551.38 | F33: =MAX(Assumptions!C40*(Assumptions!C21+F32+F30)/Assumptions!C41,Assumptions!C40/((1-Assumptions!C42)*F31)) -> 183448.8 | G33: =MAX(Assumptions!C40*(Assumptions!C21+G32+G30)/Assumptions!C41,Assumptions!C40/((1-Assumptions!C42)*G31)) -> 194797.17 | H33: =MAX(Assumptions!C40*(Assumptions!C21+H32+H30)/Assumptions!C41,Assumptions!C40/((1-Assumptions!C42)*H31)) -> 186384.66 | I33: =MAX(Assumptions!C40*(Assumptions!C21+I32+I30)/Assumptions!C41,Assumptions!C40/((1-Assumptions!C42)*I31)) -> 186137.82 | J33: =MAX(Assumptions!C40*(Assumptions!C21+J32+J30)/Assumptions!C41,Assumptions!C40/((1-Assumptions!C42)*J31)) -> 198706.9 | K33: =MAX(Assumptions!C40*(Assumptions!C21+K32+K30)/Assumptions!C41,Assumptions!C40/((1-Assumptions!C42)*K31)) -> 190776.98 | L33: =MAX(Assumptions!C40*(Assumptions!C21+L32+L30)/Assumptions!C41,Assumptions!C40/((1-Assumptions!C42)*L31)) -> 190502.6
B34: Iter 2: nB = MAX(cap, disc) | D34: =MAX(Assumptions!C43*(Assumptions!C21+D32+D33)/Assumptions!C44,Assumptions!C43/((1-Assumptions!C45)*D31)) -> 108577.59 | E34: =MAX(Assumptions!C43*(Assumptions!C21+E32+E33)/Assumptions!C44,Assumptions!C43/((1-Assumptions!C45)*E31)) -> 93008.483 | F34: =MAX(Assumptions!C43*(Assumptions!C21+F32+F33)/Assumptions!C44,Assumptions!C43/((1-Assumptions!C45)*F31)) -> 72299.707 | G34: =MAX(Assumptions!C43*(Assumptions!C21+G32+G33)/Assumptions!C44,Assumptions!C43/((1-Assumptions!C45)*G31)) -> 110003.11 | H34: =MAX(Assumptions!C43*(Assumptions!C21+H32+H33)/Assumptions!C44,Assumptions!C43/((1-Assumptions!C45)*H31)) -> 94193.391 | I34: =MAX(Assumptions!C43*(Assumptions!C21+I32+I33)/Assumptions!C44,Assumptions!C43/((1-Assumptions!C45)*I31)) -> 73176.633 | J34: =MAX(Assumptions!C43*(Assumptions!C21+J32+J33)/Assumptions!C44,Assumptions!C43/((1-Assumptions!C45)*J31)) -> 112210.95 | K34: =MAX(Assumptions!C43*(Assumptions!C21+K32+K33)/Assumptions!C44,Assumptions!C43/((1-Assumptions!C45)*K31)) -> 96088.667 | L34: =MAX(Assumptions!C43*(Assumptions!C21+L32+L33)/Assumptions!C44,Assumptions!C43/((1-Assumptions!C45)*L31)) -> 74643.864
B35: Iter 3: F PPS | D35: =D$22/(Assumptions!C21+D32+D33+D34) -> 32.503755 | E35: =E$22/(Assumptions!C21+E32+E33+E34) -> 37.946014 | F35: =F$22/(Assumptions!C21+F32+F33+F34) -> 48.815268 | G35: =G$22/(Assumptions!C21+G32+G33+G34) -> 31.989947 | H35: =H$22/(Assumptions!C21+H32+H33+H34) -> 37.368016 | I35: =I$22/(Assumptions!C21+I32+I33+I34) -> 48.108945 | J35: =J$22/(Assumptions!C21+J32+J33+J34) -> 31.249968 | K35: =K$22/(Assumptions!C21+K32+K33+K34) -> 36.505916 | L35: =L$22/(Assumptions!C21+L32+L33+L34) -> 47.004916
B36: Iter 3: ESOP top-up | D36: =MAX(0,D$21*(D$22+D$23)/D35-(Assumptions!C19+Assumptions!C20)) -> 0 | E36: =MAX(0,E$21*(E$22+E$23)/E35-(Assumptions!C19+Assumptions!C20)) -> 0 | F36: =MAX(0,F$21*(F$22+F$23)/F35-(Assumptions!C19+Assumptions!C20)) -> 0 | G36: =MAX(0,G$21*(G$22+G$23)/G35-(Assumptions!C19+Assumptions!C20)) -> 603778.34 | H36: =MAX(0,H$21*(H$22+H$23)/H35-(Assumptions!C19+Assumptions!C20)) -> 580175.67 | I36: =MAX(0,I$21*(I$22+I$23)/I35-(Assumptions!C19+Assumptions!C20)) -> 550359.32 | J36: =MAX(0,J$21*(J$22+J$23)/J35-(Assumptions!C19+Assumptions!C20)) -> 1509339.1 | K36: =MAX(0,K$21*(K$22+K$23)/K35-(Assumptions!C19+Assumptions!C20)) -> 1481093 | L36: =MAX(0,L$21*(L$22+L$23)/L35-(Assumptions!C19+Assumptions!C20)) -> 1445147.7
B37: Iter 3: nA = MAX(cap, disc) | D37: =MAX(Assumptions!C40*(Assumptions!C21+D36+D34)/Assumptions!C41,Assumptions!C40/((1-Assumptions!C42)*D35)) -> 192285.48 | E37: =MAX(Assumptions!C40*(Assumptions!C21+E36+E34)/Assumptions!C41,Assumptions!C40/((1-Assumptions!C42)*E35)) -> 183554.85 | F37: =MAX(Assumptions!C40*(Assumptions!C21+F36+F34)/Assumptions!C41,Assumptions!C40/((1-Assumptions!C42)*F35)) -> 183451.3 | G37: =MAX(Assumptions!C40*(Assumptions!C21+G36+G34)/Assumptions!C41,Assumptions!C40/((1-Assumptions!C42)*G35)) -> 195373.88 | H37: =MAX(Assumptions!C40*(Assumptions!C21+H36+H34)/Assumptions!C41,Assumptions!C40/((1-Assumptions!C42)*H35)) -> 186461.65 | I37: =MAX(Assumptions!C40*(Assumptions!C21+I36+I34)/Assumptions!C41,Assumptions!C40/((1-Assumptions!C42)*I35)) -> 186207.48 | J37: =MAX(Assumptions!C40*(Assumptions!C21+J36+J34)/Assumptions!C41,Assumptions!C40/((1-Assumptions!C42)*J35)) -> 200000.21 | K37: =MAX(Assumptions!C40*(Assumptions!C21+K36+K34)/Assumptions!C41,Assumptions!C40/((1-Assumptions!C42)*K35)) -> 190975.71 | L37: =MAX(Assumptions!C40*(Assumptions!C21+L36+L34)/Assumptions!C41,Assumptions!C40/((1-Assumptions!C42)*L35)) -> 190688.76
B38: Iter 3: nB = MAX(cap, disc) | D38: =MAX(Assumptions!C43*(Assumptions!C21+D36+D37)/Assumptions!C44,Assumptions!C43/((1-Assumptions!C45)*D35)) -> 108584.74 | E38: =MAX(Assumptions!C43*(Assumptions!C21+E36+E37)/Assumptions!C44,Assumptions!C43/((1-Assumptions!C45)*E35)) -> 93011.397 | F38: =MAX(Assumptions!C43*(Assumptions!C21+F36+F37)/Assumptions!C44,Assumptions!C43/((1-Assumptions!C45)*F35)) -> 72301.391 | G38: =MAX(Assumptions!C43*(Assumptions!C21+G36+G37)/Assumptions!C44,Assumptions!C43/((1-Assumptions!C45)*G35)) -> 110328.78 | H38: =MAX(Assumptions!C43*(Assumptions!C21+H36+H37)/Assumptions!C44,Assumptions!C43/((1-Assumptions!C45)*H35)) -> 94450.071 | I38: =MAX(Assumptions!C43*(Assumptions!C21+I36+I37)/Assumptions!C44,Assumptions!C43/((1-Assumptions!C45)*I35)) -> 73362.901 | J38: =MAX(Assumptions!C43*(Assumptions!C21+J36+J37)/Assumptions!C44,Assumptions!C43/((1-Assumptions!C45)*J35)) -> 112941.29 | K38: =MAX(Assumptions!C43*(Assumptions!C21+K36+K37)/Assumptions!C44,Assumptions!C43/((1-Assumptions!C45)*K35)) -> 96680.542 | L38: =MAX(Assumptions!C43*(Assumptions!C21+L36+L37)/Assumptions!C44,Assumptions!C43/((1-Assumptions!C45)*L35)) -> 75086.014
B39: Iter 4: F PPS | D39: =D$22/(Assumptions!C21+D36+D37+D38) -> 32.503738 | E39: =E$22/(Assumptions!C21+E36+E37+E38) -> 37.946007 | F39: =F$22/(Assumptions!C21+F36+F37+F38) -> 48.815262 | G39: =G$22/(Assumptions!C21+G36+G37+G38) -> 31.9766 | H39: =H$22/(Assumptions!C21+H36+H37+H38) -> 37.354203 | I39: =I$22/(Assumptions!C21+I36+I37+I38) -> 48.092478 | J39: =J$22/(Assumptions!C21+J36+J37+J38) -> 31.217286 | K39: =K$22/(Assumptions!C21+K36+K37+K38) -> 36.470956 | L39: =L$22/(Assumptions!C21+L36+L37+L38) -> 46.961973
B40: Iter 4: ESOP top-up | D40: =MAX(0,D$21*(D$22+D$23)/D39-(Assumptions!C19+Assumptions!C20)) -> 0 | E40: =MAX(0,E$21*(E$22+E$23)/E39-(Assumptions!C19+Assumptions!C20)) -> 0 | F40: =MAX(0,F$21*(F$22+F$23)/F39-(Assumptions!C19+Assumptions!C20)) -> 0 | G40: =MAX(0,G$21*(G$22+G$23)/G39-(Assumptions!C19+Assumptions!C20)) -> 605864.65 | H40: =MAX(0,H$21*(H$22+H$23)/H39-(Assumptions!C19+Assumptions!C20)) -> 582015.21 | I40: =MAX(0,I$21*(I$22+I$23)/I39-(Assumptions!C19+Assumptions!C20)) -> 552052.56 | J40: =MAX(0,J$21*(J$22+J$23)/J39-(Assumptions!C19+Assumptions!C20)) -> 1515520.1 | K40: =MAX(0,K$21*(K$22+K$23)/K39-(Assumptions!C19+Assumptions!C20)) -> 1486725.4 | L40: =MAX(0,L$21*(L$22+L$23)/L39-(Assumptions!C19+Assumptions!C20)) -> 1450487.7
B41: Iter 4: nA = MAX(cap, disc) | D41: =MAX(Assumptions!C40*(Assumptions!C21+D40+D38)/Assumptions!C41,Assumptions!C40/((1-Assumptions!C42)*D39)) -> 192285.58 | E41: =MAX(Assumptions!C40*(Assumptions!C21+E40+E38)/Assumptions!C41,Assumptions!C40/((1-Assumptions!C42)*E39)) -> 183554.86 | F41: =MAX(Assumptions!C40*(Assumptions!C21+F40+F38)/Assumptions!C41,Assumptions!C40/((1-Assumptions!C42)*F39)) -> 183451.31 | G41: =MAX(Assumptions!C40*(Assumptions!C21+G40+G38)/Assumptions!C41,Assumptions!C40/((1-Assumptions!C42)*G39)) -> 195455.43 | H41: =MAX(Assumptions!C40*(Assumptions!C21+H40+H38)/Assumptions!C41,Assumptions!C40/((1-Assumptions!C42)*H39)) -> 186472.13 | I41: =MAX(Assumptions!C40*(Assumptions!C21+I40+I38)/Assumptions!C41,Assumptions!C40/((1-Assumptions!C42)*I39)) -> 186216.88 | J41: =MAX(Assumptions!C40*(Assumptions!C21+J40+J38)/Assumptions!C41,Assumptions!C40/((1-Assumptions!C42)*J39)) -> 200209.59 | K41: =MAX(Assumptions!C40*(Assumptions!C21+K40+K38)/Assumptions!C41,Assumptions!C40/((1-Assumptions!C42)*K39)) -> 191006.83 | L41: =MAX(Assumptions!C40*(Assumptions!C21+L40+L38)/Assumptions!C41,Assumptions!C40/((1-Assumptions!C42)*L39)) -> 190717.67
B42: Iter 4: nB = MAX(cap, disc) | D42: =MAX(Assumptions!C43*(Assumptions!C21+D40+D41)/Assumptions!C44,Assumptions!C43/((1-Assumptions!C45)*D39)) -> 108584.8 | E42: =MAX(Assumptions!C43*(Assumptions!C21+E40+E41)/Assumptions!C44,Assumptions!C43/((1-Assumptions!C45)*E39)) -> 93011.413 | F42: =MAX(Assumptions!C43*(Assumptions!C21+F40+F41)/Assumptions!C44,Assumptions!C43/((1-Assumptions!C45)*F39)) -> 72301.399 | G42: =MAX(Assumptions!C43*(Assumptions!C21+G40+G41)/Assumptions!C44,Assumptions!C43/((1-Assumptions!C45)*G39)) -> 110374.83 | H42: =MAX(Assumptions!C43*(Assumptions!C21+H40+H41)/Assumptions!C44,Assumptions!C43/((1-Assumptions!C45)*H39)) -> 94484.996 | I42: =MAX(Assumptions!C43*(Assumptions!C21+I40+I41)/Assumptions!C44,Assumptions!C43/((1-Assumptions!C45)*I39)) -> 73388.021 | J42: =MAX(Assumptions!C43*(Assumptions!C21+J40+J41)/Assumptions!C44,Assumptions!C43/((1-Assumptions!C45)*J39)) -> 113059.53 | K42: =MAX(Assumptions!C43*(Assumptions!C21+K40+K41)/Assumptions!C44,Assumptions!C43/((1-Assumptions!C45)*K39)) -> 96773.219 | L42: =MAX(Assumptions!C43*(Assumptions!C21+L40+L41)/Assumptions!C44,Assumptions!C43/((1-Assumptions!C45)*L39)) -> 75154.674
B44: F PPS (final) | D44: =D39 -> 32.503738 | E44: =E39 -> 37.946007 | F44: =F39 -> 48.815262 | G44: =G39 -> 31.9766 | H44: =H39 -> 37.354203 | I44: =I39 -> 48.092478 | J44: =J39 -> 31.217286 | K44: =K39 -> 36.470956 | L44: =L39 -> 46.961973
B45: ESOP top-up (final) | D45: =D40 -> 0 | E45: =E40 -> 0 | F45: =F40 -> 0 | G45: =G40 -> 605864.65 | H45: =H40 -> 582015.21 | I45: =I40 -> 552052.56 | J45: =J40 -> 1515520.1 | K45: =K40 -> 1486725.4 | L45: =L40 -> 1450487.7
B46: nA (final) | D46: =D41 -> 192285.58 | E46: =E41 -> 183554.86 | F46: =F41 -> 183451.31 | G46: =G41 -> 195455.43 | H46: =H41 -> 186472.13 | I46: =I41 -> 186216.88 | J46: =J41 -> 200209.59 | K46: =K41 -> 191006.83 | L46: =L41 -> 190717.67
B47: nB (final) | D47: =D42 -> 108584.8 | E47: =E42 -> 93011.413 | F47: =F42 -> 72301.399 | G47: =G42 -> 110374.83 | H47: =H42 -> 94484.996 | I47: =I42 -> 73388.021 | J47: =J42 -> 113059.53 | K47: =K42 -> 96773.219 | L47: =L42 -> 75154.674
B48: F primary new shares | D48: =D$23/D44 -> 922970.78 | E48: =E$23/E44 -> 790597.01 | F48: =F$23/F44 -> 614561.89 | G48: =G$23/G44 -> 938186.05 | H48: =H$23/H44 -> 803122.47 | I48: =I$23/I44 -> 623798.18 | J48: =J$23/J44 -> 961006.04 | K48: =K$23/K44 -> 822572.36 | L48: =L$23/L44 -> 638814.72
B49: Our fund shares (= 1/3 of F primary) | D49: =Assumptions!C10/D44 -> 307656.93 | E49: =Assumptions!C10/E44 -> 263532.34 | F49: =Assumptions!C10/F44 -> 204853.96 | G49: =Assumptions!C10/G44 -> 312728.68 | H49: =Assumptions!C10/H44 -> 267707.49 | I49: =Assumptions!C10/I44 -> 207932.73 | J49: =Assumptions!C10/J44 -> 320335.35 | K49: =Assumptions!C10/K44 -> 274190.79 | L49: =Assumptions!C10/L44 -> 212938.24
B50: AD: NCP_D | D50: =IF(D44<Assumptions!C33,Assumptions!C33*(Assumptions!C48+D$23/Assumptions!C33)/(Assumptions!C48+D$23/D44),Assumptions!C33) -> 57.488593 | E50: =IF(E44<Assumptions!C33,Assumptions!C33*(Assumptions!C48+E$23/Assumptions!C33)/(Assumptions!C48+E$23/E44),Assumptions!C33) -> 57.692022 | F50: =IF(F44<Assumptions!C33,Assumptions!C33*(Assumptions!C48+F$23/Assumptions!C33)/(Assumptions!C48+F$23/F44),Assumptions!C33) -> 57.96479 | G50: =IF(G44<Assumptions!C33,Assumptions!C33*(Assumptions!C48+G$23/Assumptions!C33)/(Assumptions!C48+G$23/G44),Assumptions!C33) -> 57.465303 | H50: =IF(H44<Assumptions!C33,Assumptions!C33*(Assumptions!C48+H$23/Assumptions!C33)/(Assumptions!C48+H$23/H44),Assumptions!C33) -> 57.672712 | I50: =IF(I44<Assumptions!C33,Assumptions!C33*(Assumptions!C48+I$23/Assumptions!C33)/(Assumptions!C48+I$23/I44),Assumptions!C33) -> 57.950414 | J50: =IF(J44<Assumptions!C33,Assumptions!C33*(Assumptions!C48+J$23/Assumptions!C33)/(Assumptions!C48+J$23/J44),Assumptions!C33) -> 57.430407 | K50: =IF(K44<Assumptions!C33,Assumptions!C33*(Assumptions!C48+K$23/Assumptions!C33)/(Assumptions!C48+K$23/K44),Assumptions!C33) -> 57.642752 | L50: =IF(L44<Assumptions!C33,Assumptions!C33*(Assumptions!C48+L$23/Assumptions!C33)/(Assumptions!C48+L$23/L44),Assumptions!C33) -> 57.927057
B51: D as-converted shares | D51: =Assumptions!C35*Assumptions!C33/D50 -> 1739475.5 | E51: =Assumptions!C35*Assumptions!C33/E50 -> 1733341.9 | F51: =Assumptions!C35*Assumptions!C33/F50 -> 1725185.2 | G51: =Assumptions!C35*Assumptions!C33/G50 -> 1740180.5 | H51: =Assumptions!C35*Assumptions!C33/H50 -> 1733922.2 | I51: =Assumptions!C35*Assumptions!C33/I50 -> 1725613.2 | J51: =Assumptions!C35*Assumptions!C33/J50 -> 1741237.8 | K51: =Assumptions!C35*Assumptions!C33/K50 -> 1734823.4 | L51: =Assumptions!C35*Assumptions!C33/L50 -> 1726309
B52: AD: NCP_E | D52: =IF(D44<Assumptions!C37,Assumptions!C37*(Assumptions!C48+D$23/Assumptions!C37)/(Assumptions!C48+D$23/D44),Assumptions!C37) -> 48.748846 | E52: =IF(E44<Assumptions!C37,Assumptions!C37*(Assumptions!C48+E$23/Assumptions!C37)/(Assumptions!C48+E$23/E44),Assumptions!C37) -> 48.921349 | F52: =IF(F44<Assumptions!C37,Assumptions!C37*(Assumptions!C48+F$23/Assumptions!C37)/(Assumptions!C48+F$23/F44),Assumptions!C37) -> 49.152649 | G52: =IF(G44<Assumptions!C37,Assumptions!C37*(Assumptions!C48+G$23/Assumptions!C37)/(Assumptions!C48+G$23/G44),Assumptions!C37) -> 48.729097 | H52: =IF(H44<Assumptions!C37,Assumptions!C37*(Assumptions!C48+H$23/Assumptions!C37)/(Assumptions!C48+H$23/H44),Assumptions!C37) -> 48.904974 | I52: =IF(I44<Assumptions!C37,Assumptions!C37*(Assumptions!C48+I$23/Assumptions!C37)/(Assumptions!C48+I$23/I44),Assumptions!C37) -> 49.140458 | J52: =IF(J44<Assumptions!C37,Assumptions!C37*(Assumptions!C48+J$23/Assumptions!C37)/(Assumptions!C48+J$23/J44),Assumptions!C37) -> 48.699506 | K52: =IF(K44<Assumptions!C37,Assumptions!C37*(Assumptions!C48+K$23/Assumptions!C37)/(Assumptions!C48+K$23/K44),Assumptions!C37) -> 48.879568 | L52: =IF(L44<Assumptions!C37,Assumptions!C37*(Assumptions!C48+L$23/Assumptions!C37)/(Assumptions!C48+L$23/L44),Assumptions!C37) -> 49.120652
B53: E as-converted shares | D53: =Assumptions!C36*Assumptions!C37/D52 -> 6153926.2 | E53: =Assumptions!C36*Assumptions!C37/E52 -> 6132226.7 | F53: =Assumptions!C36*Assumptions!C37/F52 -> 6103370 | G53: =Assumptions!C36*Assumptions!C37/G52 -> 6156420.4 | H53: =Assumptions!C36*Assumptions!C37/H52 -> 6134280 | I53: =Assumptions!C36*Assumptions!C37/I52 -> 6104884.1 | J53: =Assumptions!C36*Assumptions!C37/J52 -> 6160161.2 | K53: =Assumptions!C36*Assumptions!C37/K52 -> 6137468.3 | L53: =Assumptions!C36*Assumptions!C37/L52 -> 6107345.7
B54: Total post-F FD (as-conv basis) | D54: =Assumptions!C21+D45+D46+D47+D48+(D51-Assumptions!C35)+(D53-Assumptions!C36) -> 37911910 | E54: =Assumptions!C21+E45+E46+E47+E48+(E51-Assumptions!C35)+(E53-Assumptions!C36) -> 37727399 | F54: =Assumptions!C21+F45+F46+F47+F48+(F51-Assumptions!C35)+(F53-Assumptions!C36) -> 37493537 | G54: =Assumptions!C21+G45+G46+G47+G48+(G51-Assumptions!C35)+(G53-Assumptions!C36) -> 38541149 | H54: =Assumptions!C21+H45+H46+H47+H48+(H51-Assumptions!C35)+(H53-Assumptions!C36) -> 38328964 | I54: =Assumptions!C21+I45+I46+I47+I48+(I51-Assumptions!C35)+(I53-Assumptions!C36) -> 38060620 | J54: =Assumptions!C21+J45+J46+J47+J48+(J51-Assumptions!C35)+(J53-Assumptions!C36) -> 39485861 | K54: =Assumptions!C21+K45+K46+K47+K48+(K51-Assumptions!C35)+(K53-Assumptions!C36) -> 39264037 | L54: =Assumptions!C21+L45+L46+L47+L48+(L51-Assumptions!C35)+(L53-Assumptions!C36) -> 38983496
B56: Waterfall at $2B Exit (per cell)
B57: F shares (= F primary new) | D57: =D48 -> 922970.78 | E57: =E48 -> 790597.01 | F57: =F48 -> 614561.89 | G57: =G48 -> 938186.05 | H57: =H48 -> 803122.47 | I57: =I48 -> 623798.18 | J57: =J48 -> 961006.04 | K57: =K48 -> 822572.36 | L57: =L48 -> 638814.72
B58: E shares (as-conv post-AD) | D58: =D53 -> 6153926.2 | E58: =E53 -> 6132226.7 | F58: =F53 -> 6103370 | G58: =G53 -> 6156420.4 | H58: =H53 -> 6134280 | I58: =I53 -> 6104884.1 | J58: =J53 -> 6160161.2 | K58: =K53 -> 6137468.3 | L58: =L53 -> 6107345.7
B59: D shares (as-conv post-AD) | D59: =D51 -> 1739475.5 | E59: =E51 -> 1733341.9 | F59: =F51 -> 1725185.2 | G59: =G51 -> 1740180.5 | H59: =H51 -> 1733922.2 | I59: =I51 -> 1725613.2 | J59: =J51 -> 1741237.8 | K59: =K51 -> 1734823.4 | L59: =L51 -> 1726309
B60: C shares | D60: =Assumptions!C30 -> 2400000 | E60: =Assumptions!C30 -> 2400000 | F60: =Assumptions!C30 -> 2400000 | G60: =Assumptions!C30 -> 2400000 | H60: =Assumptions!C30 -> 2400000 | I60: =Assumptions!C30 -> 2400000 | J60: =Assumptions!C30 -> 2400000 | K60: =Assumptions!C30 -> 2400000 | L60: =Assumptions!C30 -> 2400000
B61: B shares | D61: =Assumptions!C28 -> 3000000 | E61: =Assumptions!C28 -> 3000000 | F61: =Assumptions!C28 -> 3000000 | G61: =Assumptions!C28 -> 3000000 | H61: =Assumptions!C28 -> 3000000 | I61: =Assumptions!C28 -> 3000000 | J61: =Assumptions!C28 -> 3000000 | K61: =Assumptions!C28 -> 3000000 | L61: =Assumptions!C28 -> 3000000
B62: A shares | D62: =Assumptions!C26 -> 5000000 | E62: =Assumptions!C26 -> 5000000 | F62: =Assumptions!C26 -> 5000000 | G62: =Assumptions!C26 -> 5000000 | H62: =Assumptions!C26 -> 5000000 | I62: =Assumptions!C26 -> 5000000 | J62: =Assumptions!C26 -> 5000000 | K62: =Assumptions!C26 -> 5000000 | L62: =Assumptions!C26 -> 5000000
B63: Seed shares | D63: =Assumptions!C24 -> 5000000 | E63: =Assumptions!C24 -> 5000000 | F63: =Assumptions!C24 -> 5000000 | G63: =Assumptions!C24 -> 5000000 | H63: =Assumptions!C24 -> 5000000 | I63: =Assumptions!C24 -> 5000000 | J63: =Assumptions!C24 -> 5000000 | K63: =Assumptions!C24 -> 5000000 | L63: =Assumptions!C24 -> 5000000
B65: F pref ($) | D65: =Assumptions!C6 -> 30000000 | E65: =Assumptions!C6 -> 30000000 | F65: =Assumptions!C6 -> 30000000 | G65: =Assumptions!C6 -> 30000000 | H65: =Assumptions!C6 -> 30000000 | I65: =Assumptions!C6 -> 30000000 | J65: =Assumptions!C6 -> 30000000 | K65: =Assumptions!C6 -> 30000000 | L65: =Assumptions!C6 -> 30000000
B66: E pref ($) | D66: =Assumptions!C36*Assumptions!C37 -> 2.999968e+08 | E66: =Assumptions!C36*Assumptions!C37 -> 2.999968e+08 | F66: =Assumptions!C36*Assumptions!C37 -> 2.999968e+08 | G66: =Assumptions!C36*Assumptions!C37 -> 2.999968e+08 | H66: =Assumptions!C36*Assumptions!C37 -> 2.999968e+08 | I66: =Assumptions!C36*Assumptions!C37 -> 2.999968e+08 | J66: =Assumptions!C36*Assumptions!C37 -> 2.999968e+08 | K66: =Assumptions!C36*Assumptions!C37 -> 2.999968e+08 | L66: =Assumptions!C36*Assumptions!C37 -> 2.999968e+08
B67: D pref ($) | D67: =Assumptions!C32*Assumptions!C34 -> 100000020 | E67: =Assumptions!C32*Assumptions!C34 -> 100000020 | F67: =Assumptions!C32*Assumptions!C34 -> 100000020 | G67: =Assumptions!C32*Assumptions!C34 -> 100000020 | H67: =Assumptions!C32*Assumptions!C34 -> 100000020 | I67: =Assumptions!C32*Assumptions!C34 -> 100000020 | J67: =Assumptions!C32*Assumptions!C34 -> 100000020 | K67: =Assumptions!C32*Assumptions!C34 -> 100000020 | L67: =Assumptions!C32*Assumptions!C34 -> 100000020
B68: C pref ($) | D68: =Assumptions!C30*Assumptions!C31 -> 60000000 | E68: =Assumptions!C30*Assumptions!C31 -> 60000000 | F68: =Assumptions!C30*Assumptions!C31 -> 60000000 | G68: =Assumptions!C30*Assumptions!C31 -> 60000000 | H68: =Assumptions!C30*Assumptions!C31 -> 60000000 | I68: =Assumptions!C30*Assumptions!C31 -> 60000000 | J68: =Assumptions!C30*Assumptions!C31 -> 60000000 | K68: =Assumptions!C30*Assumptions!C31 -> 60000000 | L68: =Assumptions!C30*Assumptions!C31 -> 60000000
B69: B pref ($) | D69: =Assumptions!C28*Assumptions!C29 -> 30000000 | E69: =Assumptions!C28*Assumptions!C29 -> 30000000 | F69: =Assumptions!C28*Assumptions!C29 -> 30000000 | G69: =Assumptions!C28*Assumptions!C29 -> 30000000 | H69: =Assumptions!C28*Assumptions!C29 -> 30000000 | I69: =Assumptions!C28*Assumptions!C29 -> 30000000 | J69: =Assumptions!C28*Assumptions!C29 -> 30000000 | K69: =Assumptions!C28*Assumptions!C29 -> 30000000 | L69: =Assumptions!C28*Assumptions!C29 -> 30000000
B70: A pref ($) | D70: =Assumptions!C26*Assumptions!C27 -> 15000000 | E70: =Assumptions!C26*Assumptions!C27 -> 15000000 | F70: =Assumptions!C26*Assumptions!C27 -> 15000000 | G70: =Assumptions!C26*Assumptions!C27 -> 15000000 | H70: =Assumptions!C26*Assumptions!C27 -> 15000000 | I70: =Assumptions!C26*Assumptions!C27 -> 15000000 | J70: =Assumptions!C26*Assumptions!C27 -> 15000000 | K70: =Assumptions!C26*Assumptions!C27 -> 15000000 | L70: =Assumptions!C26*Assumptions!C27 -> 15000000
B71: Seed pref ($) | D71: =Assumptions!C24*Assumptions!C25 -> 5000000 | E71: =Assumptions!C24*Assumptions!C25 -> 5000000 | F71: =Assumptions!C24*Assumptions!C25 -> 5000000 | G71: =Assumptions!C24*Assumptions!C25 -> 5000000 | H71: =Assumptions!C24*Assumptions!C25 -> 5000000 | I71: =Assumptions!C24*Assumptions!C25 -> 5000000 | J71: =Assumptions!C24*Assumptions!C25 -> 5000000 | K71: =Assumptions!C24*Assumptions!C25 -> 5000000 | L71: =Assumptions!C24*Assumptions!C25 -> 5000000
B73: Non-class pool (common+RSA+notes+ITM opts) | D73: =(Assumptions!C15+Assumptions!C16+Assumptions!C17+Assumptions!C18)+D46+D47+Assumptions!C19 -> 11800870 | E73: =(Assumptions!C15+Assumptions!C16+Assumptions!C17+Assumptions!C18)+E46+E47+Assumptions!C19 -> 11776566 | F73: =(Assumptions!C15+Assumptions!C16+Assumptions!C17+Assumptions!C18)+F46+F47+Assumptions!C19 -> 11755753 | G73: =(Assumptions!C15+Assumptions!C16+Assumptions!C17+Assumptions!C18)+G46+G47+Assumptions!C19 -> 11805830 | H73: =(Assumptions!C15+Assumptions!C16+Assumptions!C17+Assumptions!C18)+H46+H47+Assumptions!C19 -> 11780957 | I73: =(Assumptions!C15+Assumptions!C16+Assumptions!C17+Assumptions!C18)+I46+I47+Assumptions!C19 -> 11759605 | J73: =(Assumptions!C15+Assumptions!C16+Assumptions!C17+Assumptions!C18)+J46+J47+Assumptions!C19 -> 11813269 | K73: =(Assumptions!C15+Assumptions!C16+Assumptions!C17+Assumptions!C18)+K46+K47+Assumptions!C19 -> 11787780 | L73: =(Assumptions!C15+Assumptions!C16+Assumptions!C17+Assumptions!C18)+L46+L47+Assumptions!C19 -> 11765872
B74: Exit value (= $2B) | D74: =Assumptions!C53 -> 2000000000 | E74: =Assumptions!C53 -> 2000000000 | F74: =Assumptions!C53 -> 2000000000 | G74: =Assumptions!C53 -> 2000000000 | H74: =Assumptions!C53 -> 2000000000 | I74: =Assumptions!C53 -> 2000000000 | J74: =Assumptions!C53 -> 2000000000 | K74: =Assumptions!C53 -> 2000000000 | L74: =Assumptions!C53 -> 2000000000
B75: Strike value (issued opts × $1) | D75: =Assumptions!C19*Assumptions!C12 -> 2500000 | E75: =Assumptions!C19*Assumptions!C12 -> 2500000 | F75: =Assumptions!C19*Assumptions!C12 -> 2500000 | G75: =Assumptions!C19*Assumptions!C12 -> 2500000 | H75: =Assumptions!C19*Assumptions!C12 -> 2500000 | I75: =Assumptions!C19*Assumptions!C12 -> 2500000 | J75: =Assumptions!C19*Assumptions!C12 -> 2500000 | K75: =Assumptions!C19*Assumptions!C12 -> 2500000 | L75: =Assumptions!C19*Assumptions!C12 -> 2500000
B76: Pool if all classes convert | D76: =D73+D57+D58+D59+D60+D61+D62+D63 -> 36017243 | E76: =E73+E57+E58+E59+E60+E61+E62+E63 -> 35832732 | F76: =F73+F57+F58+F59+F60+F61+F62+F63 -> 35598870 | G76: =G73+G57+G58+G59+G60+G61+G62+G63 -> 36040617 | H76: =H73+H57+H58+H59+H60+H61+H62+H63 -> 35852282 | I76: =I73+I57+I58+I59+I60+I61+I62+I63 -> 35613900 | J76: =J73+J57+J58+J59+J60+J61+J62+J63 -> 36075674 | K76: =K73+K57+K58+K59+K60+K61+K62+K63 -> 35882644 | L76: =L73+L57+L58+L59+L60+L61+L62+L63 -> 35638342
B77: Iter 1 elections (assume all-others-convert)
B78: F | D78: =IF(D65>D57*(D74+D75)/D76,"preference","convert") -> convert | E78: =IF(E65>E57*(E74+E75)/E76,"preference","convert") -> convert | F78: =IF(F65>F57*(F74+F75)/F76,"preference","convert") -> convert | G78: =IF(G65>G57*(G74+G75)/G76,"preference","convert") -> convert | H78: =IF(H65>H57*(H74+H75)/H76,"preference","convert") -> convert | I78: =IF(I65>I57*(I74+I75)/I76,"preference","convert") -> convert | J78: =IF(J65>J57*(J74+J75)/J76,"preference","convert") -> convert | K78: =IF(K65>K57*(K74+K75)/K76,"preference","convert") -> convert | L78: =IF(L65>L57*(L74+L75)/L76,"preference","convert") -> convert
B79: E | D79: =IF(D66>D58*(D74+D75)/D76,"preference","convert") -> convert | E79: =IF(E66>E58*(E74+E75)/E76,"preference","convert") -> convert | F79: =IF(F66>F58*(F74+F75)/F76,"preference","convert") -> convert | G79: =IF(G66>G58*(G74+G75)/G76,"preference","convert") -> convert | H79: =IF(H66>H58*(H74+H75)/H76,"preference","convert") -> convert | I79: =IF(I66>I58*(I74+I75)/I76,"preference","convert") -> convert | J79: =IF(J66>J58*(J74+J75)/J76,"preference","convert") -> convert | K79: =IF(K66>K58*(K74+K75)/K76,"preference","convert") -> convert | L79: =IF(L66>L58*(L74+L75)/L76,"preference","convert") -> convert
B80: D | D80: =IF(D67>D59*(D74+D75)/D76,"preference","convert") -> preference | E80: =IF(E67>E59*(E74+E75)/E76,"preference","convert") -> preference | F80: =IF(F67>F59*(F74+F75)/F76,"preference","convert") -> preference | G80: =IF(G67>G59*(G74+G75)/G76,"preference","convert") -> preference | H80: =IF(H67>H59*(H74+H75)/H76,"preference","convert") -> preference | I80: =IF(I67>I59*(I74+I75)/I76,"preference","convert") -> preference | J80: =IF(J67>J59*(J74+J75)/J76,"preference","convert") -> preference | K80: =IF(K67>K59*(K74+K75)/K76,"preference","convert") -> preference | L80: =IF(L67>L59*(L74+L75)/L76,"preference","convert") -> preference
B81: C | D81: =IF(D68>D60*(D74+D75)/D76,"preference","convert") -> convert | E81: =IF(E68>E60*(E74+E75)/E76,"preference","convert") -> convert | F81: =IF(F68>F60*(F74+F75)/F76,"preference","convert") -> convert | G81: =IF(G68>G60*(G74+G75)/G76,"preference","convert") -> convert | H81: =IF(H68>H60*(H74+H75)/H76,"preference","convert") -> convert | I81: =IF(I68>I60*(I74+I75)/I76,"preference","convert") -> convert | J81: =IF(J68>J60*(J74+J75)/J76,"preference","convert") -> convert | K81: =IF(K68>K60*(K74+K75)/K76,"preference","convert") -> convert | L81: =IF(L68>L60*(L74+L75)/L76,"preference","convert") -> convert
B82: B | D82: =IF(D69>D61*(D74+D75)/D76,"preference","convert") -> convert | E82: =IF(E69>E61*(E74+E75)/E76,"preference","convert") -> convert | F82: =IF(F69>F61*(F74+F75)/F76,"preference","convert") -> convert | G82: =IF(G69>G61*(G74+G75)/G76,"preference","convert") -> convert | H82: =IF(H69>H61*(H74+H75)/H76,"preference","convert") -> convert | I82: =IF(I69>I61*(I74+I75)/I76,"preference","convert") -> convert | J82: =IF(J69>J61*(J74+J75)/J76,"preference","convert") -> convert | K82: =IF(K69>K61*(K74+K75)/K76,"preference","convert") -> convert | L82: =IF(L69>L61*(L74+L75)/L76,"preference","convert") -> convert
B83: A | D83: =IF(D70>D62*(D74+D75)/D76,"preference","convert") -> convert | E83: =IF(E70>E62*(E74+E75)/E76,"preference","convert") -> convert | F83: =IF(F70>F62*(F74+F75)/F76,"preference","convert") -> convert | G83: =IF(G70>G62*(G74+G75)/G76,"preference","convert") -> convert | H83: =IF(H70>H62*(H74+H75)/H76,"preference","convert") -> convert | I83: =IF(I70>I62*(I74+I75)/I76,"preference","convert") -> convert | J83: =IF(J70>J62*(J74+J75)/J76,"preference","convert") -> convert | K83: =IF(K70>K62*(K74+K75)/K76,"preference","convert") -> convert | L83: =IF(L70>L62*(L74+L75)/L76,"preference","convert") -> convert
B84: Seed | D84: =IF(D71>D63*(D74+D75)/D76,"preference","convert") -> convert | E84: =IF(E71>E63*(E74+E75)/E76,"preference","convert") -> convert | F84: =IF(F71>F63*(F74+F75)/F76,"preference","convert") -> convert | G84: =IF(G71>G63*(G74+G75)/G76,"preference","convert") -> convert | H84: =IF(H71>H63*(H74+H75)/H76,"preference","convert") -> convert | I84: =IF(I71>I63*(I74+I75)/I76,"preference","convert") -> convert | J84: =IF(J71>J63*(J74+J75)/J76,"preference","convert") -> convert | K84: =IF(K71>K63*(K74+K75)/K76,"preference","convert") -> convert | L84: =IF(L71>L63*(L74+L75)/L76,"preference","convert") -> convert
B86: Iter 2 elections — FINAL (uses iter-1 profile)
B87: F | D87: =IF(D65>(D57*(D74-(D95-IF(D78="preference",D65,0))+D75)/(D73+(D96-IF(D78="convert",D57,0))+D57)),"preference","convert") -> convert | E87: =IF(E65>(E57*(E74-(E95-IF(E78="preference",E65,0))+E75)/(E73+(E96-IF(E78="convert",E57,0))+E57)),"preference","convert") -> convert | F87: =IF(F65>(F57*(F74-(F95-IF(F78="preference",F65,0))+F75)/(F73+(F96-IF(F78="convert",F57,0))+F57)),"preference","convert") -> convert | G87: =IF(G65>(G57*(G74-(G95-IF(G78="preference",G65,0))+G75)/(G73+(G96-IF(G78="convert",G57,0))+G57)),"preference","convert") -> convert | H87: =IF(H65>(H57*(H74-(H95-IF(H78="preference",H65,0))+H75)/(H73+(H96-IF(H78="convert",H57,0))+H57)),"preference","convert") -> convert | I87: =IF(I65>(I57*(I74-(I95-IF(I78="preference",I65,0))+I75)/(I73+(I96-IF(I78="convert",I57,0))+I57)),"preference","convert") -> convert | J87: =IF(J65>(J57*(J74-(J95-IF(J78="preference",J65,0))+J75)/(J73+(J96-IF(J78="convert",J57,0))+J57)),"preference","convert") -> convert | K87: =IF(K65>(K57*(K74-(K95-IF(K78="preference",K65,0))+K75)/(K73+(K96-IF(K78="convert",K57,0))+K57)),"preference","convert") -> convert | L87: =IF(L65>(L57*(L74-(L95-IF(L78="preference",L65,0))+L75)/(L73+(L96-IF(L78="convert",L57,0))+L57)),"preference","convert") -> convert
B88: E | D88: =IF(D66>(D58*(D74-(D95-IF(D79="preference",D66,0))+D75)/(D73+(D96-IF(D79="convert",D58,0))+D58)),"preference","convert") -> convert | E88: =IF(E66>(E58*(E74-(E95-IF(E79="preference",E66,0))+E75)/(E73+(E96-IF(E79="convert",E58,0))+E58)),"preference","convert") -> convert | F88: =IF(F66>(F58*(F74-(F95-IF(F79="preference",F66,0))+F75)/(F73+(F96-IF(F79="convert",F58,0))+F58)),"preference","convert") -> convert | G88: =IF(G66>(G58*(G74-(G95-IF(G79="preference",G66,0))+G75)/(G73+(G96-IF(G79="convert",G58,0))+G58)),"preference","convert") -> convert | H88: =IF(H66>(H58*(H74-(H95-IF(H79="preference",H66,0))+H75)/(H73+(H96-IF(H79="convert",H58,0))+H58)),"preference","convert") -> convert | I88: =IF(I66>(I58*(I74-(I95-IF(I79="preference",I66,0))+I75)/(I73+(I96-IF(I79="convert",I58,0))+I58)),"preference","convert") -> convert | J88: =IF(J66>(J58*(J74-(J95-IF(J79="preference",J66,0))+J75)/(J73+(J96-IF(J79="convert",J58,0))+J58)),"preference","convert") -> convert | K88: =IF(K66>(K58*(K74-(K95-IF(K79="preference",K66,0))+K75)/(K73+(K96-IF(K79="convert",K58,0))+K58)),"preference","convert") -> convert | L88: =IF(L66>(L58*(L74-(L95-IF(L79="preference",L66,0))+L75)/(L73+(L96-IF(L79="convert",L58,0))+L58)),"preference","convert") -> convert
B89: D | D89: =IF(D67>(D59*(D74-(D95-IF(D80="preference",D67,0))+D75)/(D73+(D96-IF(D80="convert",D59,0))+D59)),"preference","convert") -> preference | E89: =IF(E67>(E59*(E74-(E95-IF(E80="preference",E67,0))+E75)/(E73+(E96-IF(E80="convert",E59,0))+E59)),"preference","convert") -> preference | F89: =IF(F67>(F59*(F74-(F95-IF(F80="preference",F67,0))+F75)/(F73+(F96-IF(F80="convert",F59,0))+F59)),"preference","convert") -> preference | G89: =IF(G67>(G59*(G74-(G95-IF(G80="preference",G67,0))+G75)/(G73+(G96-IF(G80="convert",G59,0))+G59)),"preference","convert") -> preference | H89: =IF(H67>(H59*(H74-(H95-IF(H80="preference",H67,0))+H75)/(H73+(H96-IF(H80="convert",H59,0))+H59)),"preference","convert") -> preference | I89: =IF(I67>(I59*(I74-(I95-IF(I80="preference",I67,0))+I75)/(I73+(I96-IF(I80="convert",I59,0))+I59)),"preference","convert") -> preference | J89: =IF(J67>(J59*(J74-(J95-IF(J80="preference",J67,0))+J75)/(J73+(J96-IF(J80="convert",J59,0))+J59)),"preference","convert") -> preference | K89: =IF(K67>(K59*(K74-(K95-IF(K80="preference",K67,0))+K75)/(K73+(K96-IF(K80="convert",K59,0))+K59)),"preference","convert") -> preference | L89: =IF(L67>(L59*(L74-(L95-IF(L80="preference",L67,0))+L75)/(L73+(L96-IF(L80="convert",L59,0))+L59)),"preference","convert") -> preference
B90: C | D90: =IF(D68>(D60*(D74-(D95-IF(D81="preference",D68,0))+D75)/(D73+(D96-IF(D81="convert",D60,0))+D60)),"preference","convert") -> convert | E90: =IF(E68>(E60*(E74-(E95-IF(E81="preference",E68,0))+E75)/(E73+(E96-IF(E81="convert",E60,0))+E60)),"preference","convert") -> convert | F90: =IF(F68>(F60*(F74-(F95-IF(F81="preference",F68,0))+F75)/(F73+(F96-IF(F81="convert",F60,0))+F60)),"preference","convert") -> convert | G90: =IF(G68>(G60*(G74-(G95-IF(G81="preference",G68,0))+G75)/(G73+(G96-IF(G81="convert",G60,0))+G60)),"preference","convert") -> convert | H90: =IF(H68>(H60*(H74-(H95-IF(H81="preference",H68,0))+H75)/(H73+(H96-IF(H81="convert",H60,0))+H60)),"preference","convert") -> convert | I90: =IF(I68>(I60*(I74-(I95-IF(I81="preference",I68,0))+I75)/(I73+(I96-IF(I81="convert",I60,0))+I60)),"preference","convert") -> convert | J90: =IF(J68>(J60*(J74-(J95-IF(J81="preference",J68,0))+J75)/(J73+(J96-IF(J81="convert",J60,0))+J60)),"preference","convert") -> convert | K90: =IF(K68>(K60*(K74-(K95-IF(K81="preference",K68,0))+K75)/(K73+(K96-IF(K81="convert",K60,0))+K60)),"preference","convert") -> convert | L90: =IF(L68>(L60*(L74-(L95-IF(L81="preference",L68,0))+L75)/(L73+(L96-IF(L81="convert",L60,0))+L60)),"preference","convert") -> convert
B91: B | D91: =IF(D69>(D61*(D74-(D95-IF(D82="preference",D69,0))+D75)/(D73+(D96-IF(D82="convert",D61,0))+D61)),"preference","convert") -> convert | E91: =IF(E69>(E61*(E74-(E95-IF(E82="preference",E69,0))+E75)/(E73+(E96-IF(E82="convert",E61,0))+E61)),"preference","convert") -> convert | F91: =IF(F69>(F61*(F74-(F95-IF(F82="preference",F69,0))+F75)/(F73+(F96-IF(F82="convert",F61,0))+F61)),"preference","convert") -> convert | G91: =IF(G69>(G61*(G74-(G95-IF(G82="preference",G69,0))+G75)/(G73+(G96-IF(G82="convert",G61,0))+G61)),"preference","convert") -> convert | H91: =IF(H69>(H61*(H74-(H95-IF(H82="preference",H69,0))+H75)/(H73+(H96-IF(H82="convert",H61,0))+H61)),"preference","convert") -> convert | I91: =IF(I69>(I61*(I74-(I95-IF(I82="preference",I69,0))+I75)/(I73+(I96-IF(I82="convert",I61,0))+I61)),"preference","convert") -> convert | J91: =IF(J69>(J61*(J74-(J95-IF(J82="preference",J69,0))+J75)/(J73+(J96-IF(J82="convert",J61,0))+J61)),"preference","convert") -> convert | K91: =IF(K69>(K61*(K74-(K95-IF(K82="preference",K69,0))+K75)/(K73+(K96-IF(K82="convert",K61,0))+K61)),"preference","convert") -> convert | L91: =IF(L69>(L61*(L74-(L95-IF(L82="preference",L69,0))+L75)/(L73+(L96-IF(L82="convert",L61,0))+L61)),"preference","convert") -> convert
B92: A | D92: =IF(D70>(D62*(D74-(D95-IF(D83="preference",D70,0))+D75)/(D73+(D96-IF(D83="convert",D62,0))+D62)),"preference","convert") -> convert | E92: =IF(E70>(E62*(E74-(E95-IF(E83="preference",E70,0))+E75)/(E73+(E96-IF(E83="convert",E62,0))+E62)),"preference","convert") -> convert | F92: =IF(F70>(F62*(F74-(F95-IF(F83="preference",F70,0))+F75)/(F73+(F96-IF(F83="convert",F62,0))+F62)),"preference","convert") -> convert | G92: =IF(G70>(G62*(G74-(G95-IF(G83="preference",G70,0))+G75)/(G73+(G96-IF(G83="convert",G62,0))+G62)),"preference","convert") -> convert | H92: =IF(H70>(H62*(H74-(H95-IF(H83="preference",H70,0))+H75)/(H73+(H96-IF(H83="convert",H62,0))+H62)),"preference","convert") -> convert | I92: =IF(I70>(I62*(I74-(I95-IF(I83="preference",I70,0))+I75)/(I73+(I96-IF(I83="convert",I62,0))+I62)),"preference","convert") -> convert | J92: =IF(J70>(J62*(J74-(J95-IF(J83="preference",J70,0))+J75)/(J73+(J96-IF(J83="convert",J62,0))+J62)),"preference","convert") -> convert | K92: =IF(K70>(K62*(K74-(K95-IF(K83="preference",K70,0))+K75)/(K73+(K96-IF(K83="convert",K62,0))+K62)),"preference","convert") -> convert | L92: =IF(L70>(L62*(L74-(L95-IF(L83="preference",L70,0))+L75)/(L73+(L96-IF(L83="convert",L62,0))+L62)),"preference","convert") -> convert
B93: Seed | D93: =IF(D71>(D63*(D74-(D95-IF(D84="preference",D71,0))+D75)/(D73+(D96-IF(D84="convert",D63,0))+D63)),"preference","convert") -> convert | E93: =IF(E71>(E63*(E74-(E95-IF(E84="preference",E71,0))+E75)/(E73+(E96-IF(E84="convert",E63,0))+E63)),"preference","convert") -> convert | F93: =IF(F71>(F63*(F74-(F95-IF(F84="preference",F71,0))+F75)/(F73+(F96-IF(F84="convert",F63,0))+F63)),"preference","convert") -> convert | G93: =IF(G71>(G63*(G74-(G95-IF(G84="preference",G71,0))+G75)/(G73+(G96-IF(G84="convert",G63,0))+G63)),"preference","convert") -> convert | H93: =IF(H71>(H63*(H74-(H95-IF(H84="preference",H71,0))+H75)/(H73+(H96-IF(H84="convert",H63,0))+H63)),"preference","convert") -> convert | I93: =IF(I71>(I63*(I74-(I95-IF(I84="preference",I71,0))+I75)/(I73+(I96-IF(I84="convert",I63,0))+I63)),"preference","convert") -> convert | J93: =IF(J71>(J63*(J74-(J95-IF(J84="preference",J71,0))+J75)/(J73+(J96-IF(J84="convert",J63,0))+J63)),"preference","convert") -> convert | K93: =IF(K71>(K63*(K74-(K95-IF(K84="preference",K71,0))+K75)/(K73+(K96-IF(K84="convert",K63,0))+K63)),"preference","convert") -> convert | L93: =IF(L71>(L63*(L74-(L95-IF(L84="preference",L71,0))+L75)/(L73+(L96-IF(L84="convert",L63,0))+L63)),"preference","convert") -> convert
B95: Total iter-1 prefs ($) | D95: =SUMPRODUCT(--(D78:D84="preference")*D65:D71) -> 100000020 | E95: =SUMPRODUCT(--(E78:E84="preference")*E65:E71) -> 100000020 | F95: =SUMPRODUCT(--(F78:F84="preference")*F65:F71) -> 100000020 | G95: =SUMPRODUCT(--(G78:G84="preference")*G65:G71) -> 100000020 | H95: =SUMPRODUCT(--(H78:H84="preference")*H65:H71) -> 100000020 | I95: =SUMPRODUCT(--(I78:I84="preference")*I65:I71) -> 100000020 | J95: =SUMPRODUCT(--(J78:J84="preference")*J65:J71) -> 100000020 | K95: =SUMPRODUCT(--(K78:K84="preference")*K65:K71) -> 100000020 | L95: =SUMPRODUCT(--(L78:L84="preference")*L65:L71) -> 100000020
B96: Total iter-1 convert shares | D96: =SUMPRODUCT(--(D78:D84="convert")*D57:D63) -> 22476897 | E96: =SUMPRODUCT(--(E78:E84="convert")*E57:E63) -> 22322824 | F96: =SUMPRODUCT(--(F78:F84="convert")*F57:F63) -> 22117932 | G96: =SUMPRODUCT(--(G78:G84="convert")*G57:G63) -> 22494606 | H96: =SUMPRODUCT(--(H78:H84="convert")*H57:H63) -> 22337402 | I96: =SUMPRODUCT(--(I78:I84="convert")*I57:I63) -> 22128682 | J96: =SUMPRODUCT(--(J78:J84="convert")*J57:J63) -> 22521167 | K96: =SUMPRODUCT(--(K78:K84="convert")*K57:K63) -> 22360041 | L96: =SUMPRODUCT(--(L78:L84="convert")*L57:L63) -> 22146160
B98: Total iter-2 prefs ($) | D98: =SUMPRODUCT(--(D87:D93="preference")*D65:D71) -> 100000020 | E98: =SUMPRODUCT(--(E87:E93="preference")*E65:E71) -> 100000020 | F98: =SUMPRODUCT(--(F87:F93="preference")*F65:F71) -> 100000020 | G98: =SUMPRODUCT(--(G87:G93="preference")*G65:G71) -> 100000020 | H98: =SUMPRODUCT(--(H87:H93="preference")*H65:H71) -> 100000020 | I98: =SUMPRODUCT(--(I87:I93="preference")*I65:I71) -> 100000020 | J98: =SUMPRODUCT(--(J87:J93="preference")*J65:J71) -> 100000020 | K98: =SUMPRODUCT(--(K87:K93="preference")*K65:K71) -> 100000020 | L98: =SUMPRODUCT(--(L87:L93="preference")*L65:L71) -> 100000020
B99: Total iter-2 convert shares | D99: =SUMPRODUCT(--(D87:D93="convert")*D57:D63) -> 22476897 | E99: =SUMPRODUCT(--(E87:E93="convert")*E57:E63) -> 22322824 | F99: =SUMPRODUCT(--(F87:F93="convert")*F57:F63) -> 22117932 | G99: =SUMPRODUCT(--(G87:G93="convert")*G57:G63) -> 22494606 | H99: =SUMPRODUCT(--(H87:H93="convert")*H57:H63) -> 22337402 | I99: =SUMPRODUCT(--(I87:I93="convert")*I57:I63) -> 22128682 | J99: =SUMPRODUCT(--(J87:J93="convert")*J57:J63) -> 22521167 | K99: =SUMPRODUCT(--(K87:K93="convert")*K57:K63) -> 22360041 | L99: =SUMPRODUCT(--(L87:L93="convert")*L57:L63) -> 22146160
B100: Final convert pool | D100: =D73+D99 -> 34277767 | E100: =E73+E99 -> 34099390 | F100: =F73+F99 -> 33873685 | G100: =G73+G99 -> 34300437 | H100: =H73+H99 -> 34118360 | I100: =I73+I99 -> 33888287 | J100: =J73+J99 -> 34334436 | K100: =K73+K99 -> 34147821 | L100: =L73+L99 -> 33912033
B101: Final residual to convert pool | D101: =D74-D98+D75 -> 1902499980 | E101: =E74-E98+E75 -> 1902499980 | F101: =F74-F98+F75 -> 1902499980 | G101: =G74-G98+G75 -> 1902499980 | H101: =H74-H98+H75 -> 1902499980 | I101: =I74-I98+I75 -> 1902499980 | J101: =J74-J98+J75 -> 1902499980 | K101: =K74-K98+K75 -> 1902499980 | L101: =L74-L98+L75 -> 1902499980
B102: Per-share value | D102: =D101/D100 -> 55.502447 | E102: =E101/E100 -> 55.792786 | F102: =F101/F100 -> 56.164542 | G102: =G101/G100 -> 55.465766 | H102: =H101/H100 -> 55.761766 | I102: =I101/I100 -> 56.14034 | J102: =J101/J100 -> 55.410841 | K102: =K101/K100 -> 55.713657 | L102: =L101/L100 -> 56.10103
B103: Our $10M check $ proceeds | D103: =IF(D87="preference",Assumptions!C10,D49*D102) -> 17075712 | E103: =IF(E87="preference",Assumptions!C10,E49*E102) -> 14703203 | F103: =IF(F87="preference",Assumptions!C10,F49*F102) -> 11505529 | G103: =IF(G87="preference",Assumptions!C10,G49*G102) -> 17345736 | H103: =IF(H87="preference",Assumptions!C10,H49*H102) -> 14927842 | I103: =IF(I87="preference",Assumptions!C10,I49*I102) -> 11673414 | J103: =IF(J87="preference",Assumptions!C10,J49*J102) -> 17750051 | K103: =IF(K87="preference",Assumptions!C10,K49*K102) -> 15276172 | L103: =IF(L87="preference",Assumptions!C10,L49*L102) -> 11946055
B104: Our post-F ownership % | D104: =D49/D54 -> 0.0081150469 | E104: =E49/E54 -> 0.0069851711 | F104: =F49/F54 -> 0.0054637141 | G104: =G49/G54 -> 0.0081141505 | H104: =H49/H54 -> 0.0069844697 | I104: =I49/I54 -> 0.0054631986 | J104: =J49/J54 -> 0.0081126595 | K104: =K49/K54 -> 0.0069832552 | L104: =L49/L54 -> 0.0054622664
B106: Check: base case (13%, $1.4B) ownership matches Pro-Forma | C106: =ROUND((H104-'Pro-Forma'!C77)*1000000,0) -> 6984

Sheet Return-Solver
B2: Return Solver: Required Series F Ownership for 3x / 4x
B3: Solves the F-class ownership % our $10M check would need; uses base-case waterfall at each exit
B5: Per-Exit Inputs (referencing Waterfall and Pro-Forma)
B6: Item | C6: Exit 1 | D6: Exit 2 | E6: Exit 3 | F6: Exit 4 | G6: Exit 5
B7: Exit value | C7: =Assumptions!C51 -> 700000000 | D7: =Assumptions!C52 -> 1200000000 | E7: =Assumptions!C53 -> 2000000000 | F7: =Assumptions!C54 -> 4000000000 | G7: =Assumptions!C55 -> 8000000000
B8: F class election (from Waterfall) | C8: =Waterfall!E7 -> preference | D8: =Waterfall!F7 -> preference | E8: =Waterfall!G7 -> convert | F8: =Waterfall!H7 -> convert | G8: =Waterfall!I7 -> convert
B9: F class total proceeds (from Waterfall) | C9: =Waterfall!J7 -> 30000000 | D9: =Waterfall!K7 -> 30000000 | E9: =Waterfall!L7 -> 44786047 | F9: =Waterfall!M7 -> 89664548 | G9: =Waterfall!N7 -> 1.7927309e+08
B10: F class total preference (= primary $30M) | C10: =Assumptions!C6 -> 30000000 | D10: =Assumptions!C6 -> 30000000 | E10: =Assumptions!C6 -> 30000000 | F10: =Assumptions!C6 -> 30000000 | G10: =Assumptions!C6 -> 30000000
B11: F class shares (post-F primary) | C11: ='Pro-Forma'!C22 -> 803169.1 | D11: ='Pro-Forma'!C22 -> 803169.1 | E11: ='Pro-Forma'!C22 -> 803169.1 | F11: ='Pro-Forma'!C22 -> 803169.1 | G11: ='Pro-Forma'!C22 -> 803169.1
B12: Per-share value at exit (Waterfall row 60) | C12: =Waterfall!E60 -> 8.379022 | D12: =Waterfall!F60 -> 28.420742 | E12: =Waterfall!G60 -> 55.761666 | F12: =Waterfall!H60 -> 111.63844 | G12: =Waterfall!I60 -> 223.20715
B13: Total post-F FD (constant) | C13: ='Pro-Forma'!C25 -> 38329317 | D13: ='Pro-Forma'!C25 -> 38329317 | E13: ='Pro-Forma'!C25 -> 38329317 | F13: ='Pro-Forma'!C25 -> 38329317 | G13: ='Pro-Forma'!C25 -> 38329317
B15: 3x Return Solver ($30M target)
B16: Item | C16: Exit 1 | D16: Exit 2 | E16: Exit 3 | F16: Exit 4 | G16: Exit 5
B17: Target proceeds ($) | C17: =Assumptions!C10*Assumptions!C66 -> 30000000 | D17: =Assumptions!C10*Assumptions!C66 -> 30000000 | E17: =Assumptions!C10*Assumptions!C66 -> 30000000 | F17: =Assumptions!C10*Assumptions!C66 -> 30000000 | G17: =Assumptions!C10*Assumptions!C66 -> 30000000
B18: Required % of F class (= target / F class proceeds) | C18: =C17/C9 -> 1 | D18: =D17/D9 -> 1 | E18: =E17/E9 -> 0.66985149 | F18: =F17/F9 -> 0.3345804 | G18: =G17/G9 -> 0.16734246
B19: Required % of post-F FD (equivalent share count) | C19: =C18*C11/C13 -> 0.020954433 | D19: =D18*D11/D13 -> 0.020954433 | E19: =E18*E11/E13 -> 0.014036358 | F19: =F18*F11/F13 -> 0.0070109426 | G19: =G18*G11/G13 -> 0.0035065664
B20: Feasibility (TRUE = achievable) | C20: =IF(AND(C18>0,C18<=1),"feasible","infeasible") -> feasible | D20: =IF(AND(D18>0,D18<=1),"feasible","infeasible") -> feasible | E20: =IF(AND(E18>0,E18<=1),"feasible","infeasible") -> feasible | F20: =IF(AND(F18>0,F18<=1),"feasible","infeasible") -> feasible | G20: =IF(AND(G18>0,G18<=1),"feasible","infeasible") -> feasible
B22: 4x Return Solver ($40M target)
B23: Item | C23: Exit 1 | D23: Exit 2 | E23: Exit 3 | F23: Exit 4 | G23: Exit 5
B24: Target proceeds ($) | C24: =Assumptions!C10*Assumptions!C67 -> 40000000 | D24: =Assumptions!C10*Assumptions!C67 -> 40000000 | E24: =Assumptions!C10*Assumptions!C67 -> 40000000 | F24: =Assumptions!C10*Assumptions!C67 -> 40000000 | G24: =Assumptions!C10*Assumptions!C67 -> 40000000
B25: Required % of F class (= target / F class proceeds) | C25: =C24/C9 -> 1.3333333 | D25: =D24/D9 -> 1.3333333 | E25: =E24/E9 -> 0.89313531 | F25: =F24/F9 -> 0.4461072 | G25: =G24/G9 -> 0.22312328
B26: Required % of post-F FD (equivalent share count) | C26: =C25*C11/C13 -> 0.027939244 | D26: =D25*D11/D13 -> 0.027939244 | E26: =E25*E11/E13 -> 0.018715144 | F26: =F25*F11/F13 -> 0.0093479234 | G26: =G25*G11/G13 -> 0.0046754219
B27: Feasibility (TRUE = achievable) | C27: =IF(AND(C25>0,C25<=1),"feasible","infeasible") -> infeasible | D27: =IF(AND(D25>0,D25<=1),"feasible","infeasible") -> infeasible | E27: =IF(AND(E25>0,E25<=1),"feasible","infeasible") -> feasible | F27: =IF(AND(F25>0,F25<=1),"feasible","infeasible") -> feasible | G27: =IF(AND(G25>0,G25<=1),"feasible","infeasible") -> feasible
B29: Reference: Current ownership (our $10M = 1/3 of F primary)
B30: Current % of F class | C30: =Assumptions!C10/Assumptions!C6 -> 0.33333333
B31: Current % of post-F FD | C31: ='Pro-Forma'!C78 -> 0.006984811
B33: Note: F class proceeds reflect Nash-equilibrium election at each exit (Waterfall row 7, cols J-N).
B34: At low exits where F elects preference, F class total = $30M; required ownership of F approaches 100% (3x) or > 100% (4x, infeasible).
B35: At high exits where F converts, F class total scales with per-share value; required ownership decreases.
