Workbook

Sheet Assumptions
B2: Kelvin Dynamics — Series F Analysis
B3: $ in actuals; shares in actuals
B5: Round Terms
B6: Series F pre-money | C6: 1400000000 | D6: series_f_pre_money_usd
B7: Series F primary raise | C7: 30000000 | D7: series_f_primary_raise_usd
B8: Series F secondary raise | C8: 15000000 | D8: series_f_secondary_raise_usd
B9: Tender PPS multiplier | C9: 0.85 | D9: series_f_tender_pps_multiplier
B10: ESOP refresh target (% post-F FD) | C10: 0.13 | D10: esop_refresh_target_post_f
B11: Our fund check | C11: 10000000 | D11: our_fund_check_usd
B12: F_LEAD primary check | C12: 20000000 | D12: f_lead_primary_check_usd
B13: Option strike price | C13: 1 | D13: option_strike_usd
B15: Existing Equity (pre-F)
B16: Pre-F fully-diluted shares | C16: 36617961 | D16: pre_f_fd_total — also AD denominator A
B17: Pre-F options issued | C17: 2500000
B18: Pre-F options unissued | C18: 1894667
B19: Pre-F option pool total | C19: =C17+C18 -> 4394667
B21: Founders & RSAs
B22: F1 — Founder (CEO) common | C22: 4000000
B23: F2 — Founder (CTO) common | C23: 2500000
B24: F3 — Chief Scientist common | C24: 1500000
B25: Employee RSAs (E1–E10) | C25: 1000000
B26: Founder split: F1 share | C26: =C22/(C22+C23+C24) -> 0.5
B27: Founder split: F2 share | C27: =C23/(C22+C23+C24) -> 0.3125
B28: Founder split: F3 share | C28: =C24/(C22+C23+C24) -> 0.1875
B30: Prior-Round Pricing
B31: Class | C31: OCP for AD | D31: PPS issued | E31: Shares (current) | F31: Invested (USD)
B32: Seed | C32: 1 | D32: 1 | E32: 5000000 | F32: 5000000
B33: Series A | C33: 3 | D33: 3 | E33: 5000000 | F33: 15000000
B34: Series B | C34: 10 | D34: 10 | E34: 3000000 | F34: 30000000
B35: Series C | C35: 25 | D35: 25 | E35: 2400000 | F35: 60000000
B36: Series D | C36: 58.118347 | D36: 60 | E36: 1720627 | F36: 100000000
B37: Series E | C37: 49.158311 | D37: 49.158311 | E37: 6102667 | F37: 300000000
B39: Series D original issuance | C39: 1666667 | D39: orig D shares (ratio anchor)
B40: Series D original OCP | C40: 60 | D40: orig D OCP for compound ratio
B42: Convertible Notes
B43: Note | C43: Principal | D43: Cap | E43: Discount | F43: Interest
B44: Note A | C44: 5000000 | D44: 1000000000 | E44: 0.2 | F44: 0
B45: Note B | C45: 3000000 | D45: 1600000000 | E45: 0.15 | F45: 0
B47: Exit Scenarios
B48: Exit 1 | C48: 700000000
B49: Exit 2 | C49: 1200000000
B50: Exit 3 | C50: 2000000000
B51: Exit 4 | C51: 4000000000
B52: Exit 5 | C52: 8000000000
B54: Sensitivity Axes
B55: ESOP refresh — low | C55: 0.11
B56: ESOP refresh — base | C56: 0.13
B57: ESOP refresh — high | C57: 0.15
B58: Pre-money — low | C58: 1200000000
B59: Pre-money — base | C59: 1400000000
B60: Pre-money — high | C60: 1800000000
B62: Return Targets
B63: 3x our check | C63: =3*C11 -> 30000000
B64: 4x our check | C64: =4*C11 -> 40000000
B66: AD broad-based WA constants
B67: A — pre-F broad-based FD | C67: =C16 -> 36617961 | D67: denominator constant

Sheet Pro-Forma
B2: Pro-Forma Cap Table — Post Series F
B3: Round mechanics + AD + notes + tender + cap table
B5: Round Mechanics
B6: Pre-F FD (N) | C6: =Assumptions!C16 -> 36617961
B7: ESOP target (R) | C7: =Assumptions!C10 -> 0.13
B8: Existing pool (P_existing) | C8: =Assumptions!C19 -> 4394667
B9: α = primary / pre-money | C9: =Assumptions!C7/Assumptions!C6 -> 0.021428571
B10: R(1+α) | C10: =C7*(1+C9) -> 0.13278571
B11: ESOP top-up (closed-form) | C11: =MAX(0, (C10*C6 - C8) / (1 - C10)) -> 539284.37
B12: Pre-money FD (= N + ESOP top-up) | C12: =C6+C11 -> 37157245
B13: Series F PPS | C13: =Assumptions!C6/C12 -> 37.677712
B14: Series F new shares (primary) | C14: =Assumptions!C7/C13 -> 796226.69
B15: F_LEAD primary shares | C15: =Assumptions!C12/C13 -> 530817.79
B16: Our fund primary shares | C16: =Assumptions!C11/C13 -> 265408.9
B17: Tender PPS (= 0.85 × F PPS) | C17: =Assumptions!C9*C13 -> 32.026055
B18: Tender shares (= secondary / tender PPS) | C18: =Assumptions!C8/C17 -> 468368.64
B20: Anti-Dilution Block (Broad-Based WA)
B21: Class | C21: OCP for AD | D21: Triggered? (F_PPS < OCP) | E21: NCP | F21: New ratio (compound) | G21: As-converted shares | H21: Shares delta
B22: Seed | C22: =Assumptions!C32 -> 1 | D22: =IF(C13<C22,"Yes","No") -> No | E22: =IF(C13<C22, C22*(Assumptions!C16 + Assumptions!C7/C22)/(Assumptions!C16 + Assumptions!C7/C13), C22) -> 1 | F22: =C22/E22 -> 1 | G22: =Assumptions!E32*F22 -> 5000000 | H22: =G22 - Assumptions!E32 -> 0
B23: Series A | C23: =Assumptions!C33 -> 3 | D23: =IF(C13<C23,"Yes","No") -> No | E23: =IF(C13<C23, C23*(Assumptions!C16 + Assumptions!C7/C23)/(Assumptions!C16 + Assumptions!C7/C13), C23) -> 3 | F23: =C23/E23 -> 1 | G23: =Assumptions!E33*F23 -> 5000000 | H23: =G23 - Assumptions!E33 -> 0
B24: Series B | C24: =Assumptions!C34 -> 10 | D24: =IF(C13<C24,"Yes","No") -> No | E24: =IF(C13<C24, C24*(Assumptions!C16 + Assumptions!C7/C24)/(Assumptions!C16 + Assumptions!C7/C13), C24) -> 10 | F24: =C24/E24 -> 1 | G24: =Assumptions!E34*F24 -> 3000000 | H24: =G24 - Assumptions!E34 -> 0
B25: Series C | C25: =Assumptions!C35 -> 25 | D25: =IF(C13<C25,"Yes","No") -> No | E25: =IF(C13<C25, C25*(Assumptions!C16 + Assumptions!C7/C25)/(Assumptions!C16 + Assumptions!C7/C13), C25) -> 25 | F25: =C25/E25 -> 1 | G25: =Assumptions!E35*F25 -> 2400000 | H25: =G25 - Assumptions!E35 -> 0
B26: Series D | C26: =Assumptions!C36 -> 58.118347 | D26: =IF(C13<C26,"Yes","No") -> Yes | E26: =IF(C13<C26, C26*(Assumptions!C16 + Assumptions!C7/C26)/(Assumptions!C16 + Assumptions!C7/C13), C26) -> 57.683341 | F26: =Assumptions!C40/E26 -> 1.0401617 | G26: =Assumptions!C39*F26 -> 1733603.1 | H26: =G26 - Assumptions!E36 -> 12976.107
B27: Series E | C27: =Assumptions!C37 -> 49.158311 | D27: =IF(C13<C27,"Yes","No") -> Yes | E27: =IF(C13<C27, C27*(Assumptions!C16 + Assumptions!C7/C27)/(Assumptions!C16 + Assumptions!C7/C13), C27) -> 48.913988 | F27: =C27/E27 -> 1.004995 | G27: =Assumptions!E37*F27 -> 6133149.6 | H27: =G27 - Assumptions!E37 -> 30482.568
B28: Total AD top-up shares | H28: =SUM(H22:H27) -> 43458.675
B30: Convertible Notes Block
B31: Note | C31: Cap-implied PPS | D31: Discount-implied PPS | E31: Conversion PPS | F31: Branch | G31: Shares issued | K31: Helper | L31: Disc shares only
B32: Note A | C32: =Assumptions!D44/(C12 + H28 + L33) -> 26.813693 | D32: =(1-Assumptions!E44)*C13 -> 30.14217 | E32: =MIN(C32, D32) -> 26.813693 | F32: =IF(C32<D32,"cap","discount") -> cap | G32: =Assumptions!C44/E32 -> 186471.89 | K32: Note A | L32: =Assumptions!C44/((1-Assumptions!E44)*C13) -> 165880.56
B33: Note B | C33: =Assumptions!D45/(C12 + H28 + L32) -> 42.819006 | D33: =(1-Assumptions!E45)*C13 -> 32.026055 | E33: =MIN(C33, D33) -> 32.026055 | F33: =IF(C33<D33,"cap","discount") -> discount | G33: =Assumptions!C45/E33 -> 93673.728 | K33: Note B | L33: =Assumptions!C45/((1-Assumptions!E45)*C13) -> 93673.728
B34: Total notes shares | G34: =G32+G33 -> 280145.62
B36: Secondary Tender Block
B37: Tender PPS | C37: =C17 -> 32.026055
B38: Tender shares (transferred) | C38: =C18 -> 468368.64
B39: Founders pre-tender common (total) | C39: =Assumptions!C22+Assumptions!C23+Assumptions!C24 -> 8000000
B40: F1 tender outflow | C40: =C38*Assumptions!C26 -> 234184.32
B41: F2 tender outflow | C41: =C38*Assumptions!C27 -> 146365.2
B42: F3 tender outflow | C42: =C38*Assumptions!C28 -> 87819.12
B43: F_LEAD secondary common acquired | C43: =C38 -> 468368.64
B45: Post-F Fully-Diluted Total
B46: Pre-F FD | C46: =Assumptions!C16 -> 36617961
B47: ESOP top-up | C47: =C11 -> 539284.37
B48: AD top-up | C48: =H28 -> 43458.675
B49: Series F primary new shares | C49: =C14 -> 796226.69
B50: Note A converted shares | C50: =G32 -> 186471.89
B51: Note B converted shares | C51: =G33 -> 93673.728
B52: Post-F FD total (T_F) | C52: =SUM(C46:C51) -> 38277076
B54: Stakeholder Cap Table — Post-F
B55: Stakeholder | C55: Common | D55: Preferred (as-conv) | E55: Options | F55: Total FD | G55: Ownership %
B56: F1 — Founder (CEO) | C56: =Assumptions!C22 - C40 -> 3765815.7 | D56: =0 -> 0 | E56: =0 -> 0 | F56: =C56+D56+E56 -> 3765815.7 | G56: =F56/$C$52 -> 0.098383054
B57: F2 — Founder (CTO) | C57: =Assumptions!C23 - C41 -> 2353634.8 | D57: =0 -> 0 | E57: =0 -> 0 | F57: =C57+D57+E57 -> 2353634.8 | G57: =F57/$C$52 -> 0.061489409
B58: F3 — Chief Scientist | C58: =Assumptions!C24 - C42 -> 1412180.9 | D58: =0 -> 0 | E58: =0 -> 0 | F58: =C58+D58+E58 -> 1412180.9 | G58: =F58/$C$52 -> 0.036893645
B59: Employee RSAs (E1–E10) | C59: =Assumptions!C25 -> 1000000 | D59: =0 -> 0 | E59: =0 -> 0 | F59: =C59+D59+E59 -> 1000000 | G59: =F59/$C$52 -> 0.026125297
B60: Seed (SEED1) | C60: =0 -> 0 | D60: =G22 -> 5000000 | E60: =0 -> 0 | F60: =C60+D60+E60 -> 5000000 | G60: =F60/$C$52 -> 0.13062649
B61: Series A (A1) | C61: =0 -> 0 | D61: =G23 -> 5000000 | E61: =0 -> 0 | F61: =C61+D61+E61 -> 5000000 | G61: =F61/$C$52 -> 0.13062649
B62: Series B (B1) | C62: =0 -> 0 | D62: =G24 -> 3000000 | E62: =0 -> 0 | F62: =C62+D62+E62 -> 3000000 | G62: =F62/$C$52 -> 0.078375892
B63: Series C (C1) | C63: =0 -> 0 | D63: =G25 -> 2400000 | E63: =0 -> 0 | F63: =C63+D63+E63 -> 2400000 | G63: =F63/$C$52 -> 0.062700714
B64: Series D (D1) | C64: =0 -> 0 | D64: =G26 -> 1733603.1 | E64: =0 -> 0 | F64: =C64+D64+E64 -> 1733603.1 | G64: =F64/$C$52 -> 0.045290897
B65: Series E (E1_INV–E10_INV) | C65: =0 -> 0 | D65: =G27 -> 6133149.6 | E65: =0 -> 0 | F65: =C65+D65+E65 -> 6133149.6 | G65: =F65/$C$52 -> 0.16023036
B66: Note A holder (NA1) | C66: =0 -> 0 | D66: =G32 -> 186471.89 | E66: =0 -> 0 | F66: =C66+D66+E66 -> 186471.89 | G66: =F66/$C$52 -> 0.0048716335
B67: Note B holder (NB1) | C67: =0 -> 0 | D67: =G33 -> 93673.728 | E67: =0 -> 0 | F67: =C67+D67+E67 -> 93673.728 | G67: =F67/$C$52 -> 0.002447254
B68: F_LEAD — Series F lead | C68: =C38 -> 468368.64 | D68: =C15 -> 530817.79 | E68: =0 -> 0 | F68: =C68+D68+E68 -> 999186.43 | G68: =F68/$C$52 -> 0.026104043
B69: Our fund — Series F primary | C69: =0 -> 0 | D69: =C16 -> 265408.9 | E69: =0 -> 0 | F69: =C69+D69+E69 -> 265408.9 | G69: =F69/$C$52 -> 0.0069338863
B70: Issued options (employee pool) | C70: =0 -> 0 | D70: =0 -> 0 | E70: =Assumptions!C17 -> 2500000 | F70: =C70+D70+E70 -> 2500000 | G70: =F70/$C$52 -> 0.065313243
B71: Unissued options + ESOP top-up | C71: =0 -> 0 | D71: =0 -> 0 | E71: =Assumptions!C18 + C11 -> 2433951.4 | F71: =C71+D71+E71 -> 2433951.4 | G71: =F71/$C$52 -> 0.063587703
B72: Total post-F FD | C72: =SUM(C56:C71) -> 9000000 | D72: =SUM(D56:D71) -> 24343125 | E72: =SUM(E56:E71) -> 4933951.4 | F72: =SUM(F56:F71) -> 38277076 | G72: =SUM(G56:G71) -> 1
B75: T_F (sum) − T_F (calc) | F75: =ROUND(F72 - C52, 2) -> 0
B76: Ownership sum − 100% | F76: =ROUND(G72 - 1, 6) -> 0
B77: Check | F77: =ROUND((F72 - C52) + (G72 - 1)*1000000, 2) -> 0

Sheet Waterfall
B2: Liquidation Waterfall — Five Exit Scenarios
B3: Non-participating preferred with conversion election; sequential F→Seed; proceeds at final per-share
B5: Setup
B6: Post-F FD (T_F) | C6: ='Pro-Forma'!C52 -> 38277076
B7: Less: unissued + ESOP top-up (forfeit) | C7: =-Assumptions!C18 - 'Pro-Forma'!C11 -> -2433951.4
B8: Convert pool initial | C8: =C6+C7 -> 35843125
B9: Issued options strike | C9: =Assumptions!C13 -> 1
B11: Class / Metric | C11: Shares | D11: Preference | E11: Exit 1 ($700M) | F11: Exit 2 ($1.2B) | G11: Exit 3 ($2B) | H11: Exit 4 ($4B) | I11: Exit 5 ($8B)
B12: Exit value | E12: =Assumptions!C48 -> 700000000 | F12: =Assumptions!C49 -> 1200000000 | G12: =Assumptions!C50 -> 2000000000 | H12: =Assumptions!C51 -> 4000000000 | I12: =Assumptions!C52 -> 8000000000
B14: Series F
B15: Shares / Preference | C15: ='Pro-Forma'!C14 -> 796226.69 | D15: =Assumptions!C7 -> 30000000
B16: Residual in | E16: =$E$12 -> 700000000 | F16: =$F$12 -> 1200000000 | G16: =$G$12 -> 2000000000 | H16: =$H$12 -> 4000000000 | I16: =$I$12 -> 8000000000
B17: Pool in | E17: =$C$8 -> 35843125 | F17: =$C$8 -> 35843125 | G17: =$C$8 -> 35843125 | H17: =$C$8 -> 35843125 | I17: =$C$8 -> 35843125
B18: Convert proceeds (decision) | E18: =$C$15/E17*E16 -> 15549947 | F18: =$C$15/F17*F16 -> 26657051 | G18: =$C$15/G17*G16 -> 44428419 | H18: =$C$15/H17*H16 -> 88856838 | I18: =$C$15/I17*I16 -> 1.7771368e+08
B19: Election | E19: =IF(E18>$D$15,"convert","preference") -> preference | F19: =IF(F18>$D$15,"convert","preference") -> preference | G19: =IF(G18>$D$15,"convert","preference") -> convert | H19: =IF(H18>$D$15,"convert","preference") -> convert | I19: =IF(I18>$D$15,"convert","preference") -> convert
B20: Residual out | E20: =E16-IF(E19="preference",$D$15,0) -> 670000000 | F20: =F16-IF(F19="preference",$D$15,0) -> 1170000000 | G20: =G16-IF(G19="preference",$D$15,0) -> 2000000000 | H20: =H16-IF(H19="preference",$D$15,0) -> 4000000000 | I20: =I16-IF(I19="preference",$D$15,0) -> 8000000000
B21: Pool out | E21: =E17-IF(E19="preference",$C$15,0) -> 35046898 | F21: =F17-IF(F19="preference",$C$15,0) -> 35046898 | G21: =G17-IF(G19="preference",$C$15,0) -> 35843125 | H21: =H17-IF(H19="preference",$C$15,0) -> 35843125 | I21: =I17-IF(I19="preference",$C$15,0) -> 35843125
B23: Series E
B24: Shares / Preference | C24: ='Pro-Forma'!G27 -> 6133149.6 | D24: =Assumptions!F37 -> 300000000
B25: Residual in | E25: =$E$20 -> 670000000 | F25: =$F$20 -> 1170000000 | G25: =$G$20 -> 2000000000 | H25: =$H$20 -> 4000000000 | I25: =$I$20 -> 8000000000
B26: Pool in | E26: =$E$21 -> 35046898 | F26: =$F$21 -> 35046898 | G26: =$G$21 -> 35843125 | H26: =$H$21 -> 35843125 | I26: =$I$21 -> 35843125
B27: Convert proceeds (decision) | E27: =$C$24/E26*E25 -> 1.172489e+08 | F27: =$C$24/F26*F25 -> 2.0474808e+08 | G27: =$C$24/G26*G25 -> 3.4222181e+08 | H27: =$C$24/H26*H25 -> 6.8444362e+08 | I27: =$C$24/I26*I25 -> 1.3688872e+09
B28: Election | E28: =IF(E27>$D$24,"convert","preference") -> preference | F28: =IF(F27>$D$24,"convert","preference") -> preference | G28: =IF(G27>$D$24,"convert","preference") -> convert | H28: =IF(H27>$D$24,"convert","preference") -> convert | I28: =IF(I27>$D$24,"convert","preference") -> convert
B29: Residual out | E29: =E25-IF(E28="preference",$D$24,0) -> 370000000 | F29: =F25-IF(F28="preference",$D$24,0) -> 870000000 | G29: =G25-IF(G28="preference",$D$24,0) -> 2000000000 | H29: =H25-IF(H28="preference",$D$24,0) -> 4000000000 | I29: =I25-IF(I28="preference",$D$24,0) -> 8000000000
B30: Pool out | E30: =E26-IF(E28="preference",$C$24,0) -> 28913749 | F30: =F26-IF(F28="preference",$C$24,0) -> 28913749 | G30: =G26-IF(G28="preference",$C$24,0) -> 35843125 | H30: =H26-IF(H28="preference",$C$24,0) -> 35843125 | I30: =I26-IF(I28="preference",$C$24,0) -> 35843125
B32: Series D
B33: Shares / Preference | C33: ='Pro-Forma'!G26 -> 1733603.1 | D33: =Assumptions!F36 -> 100000000
B34: Residual in | E34: =$E$29 -> 370000000 | F34: =$F$29 -> 870000000 | G34: =$G$29 -> 2000000000 | H34: =$H$29 -> 4000000000 | I34: =$I$29 -> 8000000000
B35: Pool in | E35: =$E$30 -> 28913749 | F35: =$F$30 -> 28913749 | G35: =$G$30 -> 35843125 | H35: =$H$30 -> 35843125 | I35: =$I$30 -> 35843125
B36: Convert proceeds (decision) | E36: =$C$33/E35*E34 -> 22184365 | F36: =$C$33/F35*F34 -> 52163236 | G36: =$C$33/G35*G34 -> 96732810 | H36: =$C$33/H35*H34 -> 1.9346562e+08 | I36: =$C$33/I35*I34 -> 3.8693124e+08
B37: Election | E37: =IF(E36>$D$33,"convert","preference") -> preference | F37: =IF(F36>$D$33,"convert","preference") -> preference | G37: =IF(G36>$D$33,"convert","preference") -> preference | H37: =IF(H36>$D$33,"convert","preference") -> convert | I37: =IF(I36>$D$33,"convert","preference") -> convert
B38: Residual out | E38: =E34-IF(E37="preference",$D$33,0) -> 270000000 | F38: =F34-IF(F37="preference",$D$33,0) -> 770000000 | G38: =G34-IF(G37="preference",$D$33,0) -> 1900000000 | H38: =H34-IF(H37="preference",$D$33,0) -> 4000000000 | I38: =I34-IF(I37="preference",$D$33,0) -> 8000000000
B39: Pool out | E39: =E35-IF(E37="preference",$C$33,0) -> 27180146 | F39: =F35-IF(F37="preference",$C$33,0) -> 27180146 | G39: =G35-IF(G37="preference",$C$33,0) -> 34109522 | H39: =H35-IF(H37="preference",$C$33,0) -> 35843125 | I39: =I35-IF(I37="preference",$C$33,0) -> 35843125
B41: Series C
B42: Shares / Preference | C42: ='Pro-Forma'!G25 -> 2400000 | D42: =Assumptions!F35 -> 60000000
B43: Residual in | E43: =$E$38 -> 270000000 | F43: =$F$38 -> 770000000 | G43: =$G$38 -> 1900000000 | H43: =$H$38 -> 4000000000 | I43: =$I$38 -> 8000000000
B44: Pool in | E44: =$E$39 -> 27180146 | F44: =$F$39 -> 27180146 | G44: =$G$39 -> 34109522 | H44: =$H$39 -> 35843125 | I44: =$I$39 -> 35843125
B45: Convert proceeds (decision) | E45: =$C$42/E44*E43 -> 23840932 | F45: =$C$42/F44*F43 -> 67990806 | G45: =$C$42/G44*G43 -> 1.3368701e+08 | H45: =$C$42/H44*H43 -> 2.6783379e+08 | I45: =$C$42/I44*I43 -> 5.3566758e+08
B46: Election | E46: =IF(E45>$D$42,"convert","preference") -> preference | F46: =IF(F45>$D$42,"convert","preference") -> convert | G46: =IF(G45>$D$42,"convert","preference") -> convert | H46: =IF(H45>$D$42,"convert","preference") -> convert | I46: =IF(I45>$D$42,"convert","preference") -> convert
B47: Residual out | E47: =E43-IF(E46="preference",$D$42,0) -> 210000000 | F47: =F43-IF(F46="preference",$D$42,0) -> 770000000 | G47: =G43-IF(G46="preference",$D$42,0) -> 1900000000 | H47: =H43-IF(H46="preference",$D$42,0) -> 4000000000 | I47: =I43-IF(I46="preference",$D$42,0) -> 8000000000
B48: Pool out | E48: =E44-IF(E46="preference",$C$42,0) -> 24780146 | F48: =F44-IF(F46="preference",$C$42,0) -> 27180146 | G48: =G44-IF(G46="preference",$C$42,0) -> 34109522 | H48: =H44-IF(H46="preference",$C$42,0) -> 35843125 | I48: =I44-IF(I46="preference",$C$42,0) -> 35843125
B50: Series B
B51: Shares / Preference | C51: ='Pro-Forma'!G24 -> 3000000 | D51: =Assumptions!F34 -> 30000000
B52: Residual in | E52: =$E$47 -> 210000000 | F52: =$F$47 -> 770000000 | G52: =$G$47 -> 1900000000 | H52: =$H$47 -> 4000000000 | I52: =$I$47 -> 8000000000
B53: Pool in | E53: =$E$48 -> 24780146 | F53: =$F$48 -> 27180146 | G53: =$G$48 -> 34109522 | H53: =$H$48 -> 35843125 | I53: =$I$48 -> 35843125
B54: Convert proceeds (decision) | E54: =$C$51/E53*E52 -> 25423579 | F54: =$C$51/F53*F52 -> 84988507 | G54: =$C$51/G53*G52 -> 1.6710876e+08 | H54: =$C$51/H53*H52 -> 3.3479224e+08 | I54: =$C$51/I53*I52 -> 6.6958447e+08
B55: Election | E55: =IF(E54>$D$51,"convert","preference") -> preference | F55: =IF(F54>$D$51,"convert","preference") -> convert | G55: =IF(G54>$D$51,"convert","preference") -> convert | H55: =IF(H54>$D$51,"convert","preference") -> convert | I55: =IF(I54>$D$51,"convert","preference") -> convert
B56: Residual out | E56: =E52-IF(E55="preference",$D$51,0) -> 180000000 | F56: =F52-IF(F55="preference",$D$51,0) -> 770000000 | G56: =G52-IF(G55="preference",$D$51,0) -> 1900000000 | H56: =H52-IF(H55="preference",$D$51,0) -> 4000000000 | I56: =I52-IF(I55="preference",$D$51,0) -> 8000000000
B57: Pool out | E57: =E53-IF(E55="preference",$C$51,0) -> 21780146 | F57: =F53-IF(F55="preference",$C$51,0) -> 27180146 | G57: =G53-IF(G55="preference",$C$51,0) -> 34109522 | H57: =H53-IF(H55="preference",$C$51,0) -> 35843125 | I57: =I53-IF(I55="preference",$C$51,0) -> 35843125
B59: Series A
B60: Shares / Preference | C60: ='Pro-Forma'!G23 -> 5000000 | D60: =Assumptions!F33 -> 15000000
B61: Residual in | E61: =$E$56 -> 180000000 | F61: =$F$56 -> 770000000 | G61: =$G$56 -> 1900000000 | H61: =$H$56 -> 4000000000 | I61: =$I$56 -> 8000000000
B62: Pool in | E62: =$E$57 -> 21780146 | F62: =$F$57 -> 27180146 | G62: =$G$57 -> 34109522 | H62: =$H$57 -> 35843125 | I62: =$I$57 -> 35843125
B63: Convert proceeds (decision) | E63: =$C$60/E62*E61 -> 41322038 | F63: =$C$60/F62*F61 -> 1.4164751e+08 | G63: =$C$60/G62*G61 -> 2.785146e+08 | H63: =$C$60/H62*H61 -> 5.5798706e+08 | I63: =$C$60/I62*I61 -> 1.1159741e+09
B64: Election | E64: =IF(E63>$D$60,"convert","preference") -> convert | F64: =IF(F63>$D$60,"convert","preference") -> convert | G64: =IF(G63>$D$60,"convert","preference") -> convert | H64: =IF(H63>$D$60,"convert","preference") -> convert | I64: =IF(I63>$D$60,"convert","preference") -> convert
B65: Residual out | E65: =E61-IF(E64="preference",$D$60,0) -> 180000000 | F65: =F61-IF(F64="preference",$D$60,0) -> 770000000 | G65: =G61-IF(G64="preference",$D$60,0) -> 1900000000 | H65: =H61-IF(H64="preference",$D$60,0) -> 4000000000 | I65: =I61-IF(I64="preference",$D$60,0) -> 8000000000
B66: Pool out | E66: =E62-IF(E64="preference",$C$60,0) -> 21780146 | F66: =F62-IF(F64="preference",$C$60,0) -> 27180146 | G66: =G62-IF(G64="preference",$C$60,0) -> 34109522 | H66: =H62-IF(H64="preference",$C$60,0) -> 35843125 | I66: =I62-IF(I64="preference",$C$60,0) -> 35843125
B68: Seed
B69: Shares / Preference | C69: ='Pro-Forma'!G22 -> 5000000 | D69: =Assumptions!F32 -> 5000000
B70: Residual in | E70: =$E$65 -> 180000000 | F70: =$F$65 -> 770000000 | G70: =$G$65 -> 1900000000 | H70: =$H$65 -> 4000000000 | I70: =$I$65 -> 8000000000
B71: Pool in | E71: =$E$66 -> 21780146 | F71: =$F$66 -> 27180146 | G71: =$G$66 -> 34109522 | H71: =$H$66 -> 35843125 | I71: =$I$66 -> 35843125
B72: Convert proceeds (decision) | E72: =$C$69/E71*E70 -> 41322038 | F72: =$C$69/F71*F70 -> 1.4164751e+08 | G72: =$C$69/G71*G70 -> 2.785146e+08 | H72: =$C$69/H71*H70 -> 5.5798706e+08 | I72: =$C$69/I71*I70 -> 1.1159741e+09
B73: Election | E73: =IF(E72>$D$69,"convert","preference") -> convert | F73: =IF(F72>$D$69,"convert","preference") -> convert | G73: =IF(G72>$D$69,"convert","preference") -> convert | H73: =IF(H72>$D$69,"convert","preference") -> convert | I73: =IF(I72>$D$69,"convert","preference") -> convert
B74: Residual out | E74: =E70-IF(E73="preference",$D$69,0) -> 180000000 | F74: =F70-IF(F73="preference",$D$69,0) -> 770000000 | G74: =G70-IF(G73="preference",$D$69,0) -> 1900000000 | H74: =H70-IF(H73="preference",$D$69,0) -> 4000000000 | I74: =I70-IF(I73="preference",$D$69,0) -> 8000000000
B75: Pool out | E75: =E71-IF(E73="preference",$C$69,0) -> 21780146 | F75: =F71-IF(F73="preference",$C$69,0) -> 27180146 | G75: =G71-IF(G73="preference",$C$69,0) -> 34109522 | H75: =H71-IF(H73="preference",$C$69,0) -> 35843125 | I75: =I71-IF(I73="preference",$C$69,0) -> 35843125
B77: Final residual | E77: =E74 -> 180000000 | F77: =F74 -> 770000000 | G77: =G74 -> 1900000000 | H77: =H74 -> 4000000000 | I77: =I74 -> 8000000000
B78: Final pool | E78: =E75 -> 21780146 | F78: =F75 -> 27180146 | G78: =G75 -> 34109522 | H78: =H75 -> 35843125 | I78: =I75 -> 35843125
B79: Per-share value | E79: =E77/E78 -> 8.2644076 | F79: =F77/F78 -> 28.329502 | G79: =G77/G78 -> 55.702921 | H79: =H77/H78 -> 111.59741 | I79: =I77/I78 -> 223.19482
B81: Final Class Proceeds
B82: Series F proceeds | E82: =IF(E19="preference",$D$15,$C$15*E79) -> 30000000 | F82: =IF(F19="preference",$D$15,$C$15*F79) -> 30000000 | G82: =IF(G19="preference",$D$15,$C$15*G79) -> 44352152 | H82: =IF(H19="preference",$D$15,$C$15*H79) -> 88856838 | I82: =IF(I19="preference",$D$15,$C$15*I79) -> 1.7771368e+08
B83: Series E proceeds | E83: =IF(E28="preference",$D$24,$C$24*E79) -> 300000000 | F83: =IF(F28="preference",$D$24,$C$24*F79) -> 300000000 | G83: =IF(G28="preference",$D$24,$C$24*G79) -> 3.4163435e+08 | H83: =IF(H28="preference",$D$24,$C$24*H79) -> 6.8444362e+08 | I83: =IF(I28="preference",$D$24,$C$24*I79) -> 1.3688872e+09
B84: Series D proceeds | E84: =IF(E37="preference",$D$33,$C$33*E79) -> 100000000 | F84: =IF(F37="preference",$D$33,$C$33*F79) -> 100000000 | G84: =IF(G37="preference",$D$33,$C$33*G79) -> 100000000 | H84: =IF(H37="preference",$D$33,$C$33*H79) -> 1.9346562e+08 | I84: =IF(I37="preference",$D$33,$C$33*I79) -> 3.8693124e+08
B85: Series C proceeds | E85: =IF(E46="preference",$D$42,$C$42*E79) -> 60000000 | F85: =IF(F46="preference",$D$42,$C$42*F79) -> 67990806 | G85: =IF(G46="preference",$D$42,$C$42*G79) -> 1.3368701e+08 | H85: =IF(H46="preference",$D$42,$C$42*H79) -> 2.6783379e+08 | I85: =IF(I46="preference",$D$42,$C$42*I79) -> 5.3566758e+08
B86: Series B proceeds | E86: =IF(E55="preference",$D$51,$C$51*E79) -> 30000000 | F86: =IF(F55="preference",$D$51,$C$51*F79) -> 84988507 | G86: =IF(G55="preference",$D$51,$C$51*G79) -> 1.6710876e+08 | H86: =IF(H55="preference",$D$51,$C$51*H79) -> 3.3479224e+08 | I86: =IF(I55="preference",$D$51,$C$51*I79) -> 6.6958447e+08
B87: Series A proceeds | E87: =IF(E64="preference",$D$60,$C$60*E79) -> 41322038 | F87: =IF(F64="preference",$D$60,$C$60*F79) -> 1.4164751e+08 | G87: =IF(G64="preference",$D$60,$C$60*G79) -> 2.785146e+08 | H87: =IF(H64="preference",$D$60,$C$60*H79) -> 5.5798706e+08 | I87: =IF(I64="preference",$D$60,$C$60*I79) -> 1.1159741e+09
B88: Seed proceeds | E88: =IF(E73="preference",$D$69,$C$69*E79) -> 41322038 | F88: =IF(F73="preference",$D$69,$C$69*F79) -> 1.4164751e+08 | G88: =IF(G73="preference",$D$69,$C$69*G79) -> 2.785146e+08 | H88: =IF(H73="preference",$D$69,$C$69*H79) -> 5.5798706e+08 | I88: =IF(I73="preference",$D$69,$C$69*I79) -> 1.1159741e+09
B90: Common + RSAs | C90: =Assumptions!C22+Assumptions!C23+Assumptions!C24+Assumptions!C25 -> 9000000 | E90: =$C$90*E79 -> 74379668 | F90: =$C$90*F79 -> 2.5496552e+08 | G90: =$C$90*G79 -> 5.0132629e+08 | H90: =$C$90*H79 -> 1.0043767e+09 | I90: =$C$90*I79 -> 2.0087534e+09
B91: Issued options (net of strike if ITM) | C91: =Assumptions!C17 -> 2500000 | E91: =IF(E79>$C$9, $C$91*(E79-$C$9), 0) -> 18161019 | F91: =IF(F79>$C$9, $C$91*(F79-$C$9), 0) -> 68323756 | G91: =IF(G79>$C$9, $C$91*(G79-$C$9), 0) -> 1.367573e+08 | H91: =IF(H79>$C$9, $C$91*(H79-$C$9), 0) -> 2.7649353e+08 | I91: =IF(I79>$C$9, $C$91*(I79-$C$9), 0) -> 5.5548706e+08
B92: Note A holder | C92: ='Pro-Forma'!G32 -> 186471.89 | E92: =$C$92*E79 -> 1541079.7 | F92: =$C$92*F79 -> 5282655.8 | G92: =$C$92*G79 -> 10387029 | H92: =$C$92*H79 -> 20809780 | I92: =$C$92*I79 -> 41619561
B93: Note B holder | C93: ='Pro-Forma'!G33 -> 93673.728 | E93: =$C$93*E79 -> 774157.86 | F93: =$C$93*F79 -> 2653730.1 | G93: =$C$93*G79 -> 5217900.3 | H93: =$C$93*H79 -> 10453746 | I93: =$C$93*I79 -> 20907491
B95: Reconciliation
B96: Sum of class proceeds | E96: =SUM(E82:E88) -> 6.0264408e+08 | F96: =SUM(F82:F88) -> 8.6627434e+08 | G96: =SUM(G82:G88) -> 1.3438115e+09 | H96: =SUM(H82:H88) -> 2.6853662e+09 | I96: =SUM(I82:I88) -> 5.3707325e+09
B97: Common + RSA | E97: =E90 -> 74379668 | F97: =F90 -> 2.5496552e+08 | G97: =G90 -> 5.0132629e+08 | H97: =H90 -> 1.0043767e+09 | I97: =I90 -> 2.0087534e+09
B98: Options net | E98: =E91 -> 18161019 | F98: =F91 -> 68323756 | G98: =G91 -> 1.367573e+08 | H98: =H91 -> 2.7649353e+08 | I98: =I91 -> 5.5548706e+08
B99: Notes (A + B) | E99: =E92+E93 -> 2315237.6 | F99: =F92+F93 -> 7936385.9 | G99: =G92+G93 -> 15604929 | H99: =H92+H93 -> 31263526 | I99: =I92+I93 -> 62527052
B100: Strike paid (option exercise) | E100: =IF(E79>$C$9, $C$91*$C$9, 0) -> 2500000 | F100: =IF(F79>$C$9, $C$91*$C$9, 0) -> 2500000 | G100: =IF(G79>$C$9, $C$91*$C$9, 0) -> 2500000 | H100: =IF(H79>$C$9, $C$91*$C$9, 0) -> 2500000 | I100: =IF(I79>$C$9, $C$91*$C$9, 0) -> 2500000
B101: Total distributed | E101: =E96+E97+E98+E99+E100 -> 7e+08 | F101: =F96+F97+F98+F99+F100 -> 1.2e+09 | G101: =G96+G97+G98+G99+G100 -> 2e+09 | H101: =H96+H97+H98+H99+H100 -> 4e+09 | I101: =I96+I97+I98+I99+I100 -> 8e+09
B102: Exit value | E102: =E12 -> 700000000 | F102: =F12 -> 1200000000 | G102: =G12 -> 2000000000 | H102: =H12 -> 4000000000 | I102: =I12 -> 8000000000
B103: Check | E103: =ROUND(E101-E102,2) -> 0 | F103: =ROUND(F101-F102,2) -> 0 | G103: =ROUND(G101-G102,2) -> 0 | H103: =ROUND(H101-H102,2) -> 0 | I103: =ROUND(I101-I102,2) -> 0
B105: Election Summary — 35 cells
B106: Class | E106: Exit 1 ($700M) | F106: Exit 2 ($1.2B) | G106: Exit 3 ($2B) | H106: Exit 4 ($4B) | I106: Exit 5 ($8B)
B107: Series F | E107: =E19 -> preference | F107: =F19 -> preference | G107: =G19 -> convert | H107: =H19 -> convert | I107: =I19 -> convert
B108: Series E | E108: =E28 -> preference | F108: =F28 -> preference | G108: =G28 -> convert | H108: =H28 -> convert | I108: =I28 -> convert
B109: Series D | E109: =E37 -> preference | F109: =F37 -> preference | G109: =G37 -> preference | H109: =H37 -> convert | I109: =I37 -> convert
B110: Series C | E110: =E46 -> preference | F110: =F46 -> convert | G110: =G46 -> convert | H110: =H46 -> convert | I110: =I46 -> convert
B111: Series B | E111: =E55 -> preference | F111: =F55 -> convert | G111: =G55 -> convert | H111: =H55 -> convert | I111: =I55 -> convert
B112: Series A | E112: =E64 -> convert | F112: =F64 -> convert | G112: =G64 -> convert | H112: =H64 -> convert | I112: =I64 -> convert
B113: Seed | E113: =E73 -> convert | F113: =F73 -> convert | G113: =G73 -> convert | H113: =H73 -> convert | I113: =I73 -> convert

Sheet Sensitivity
B2: Sensitivity — Our Check at $2B Exit
B3: 3×3: ESOP refresh × Series F pre-money. Each cell re-solves the full round mechanics.
B5: Sensitivity Grid | K5: Per-cell Calculations (each column = one grid cell)
K6: Combo (ESOP / Pre) | L6: low/low | M6: low/base | N6: low/high | O6: base/low | P6: base/base | Q6: base/high | R6: high/low | S6: high/base | T6: high/high
B7: ESOP refresh \ Pre-money | C7: =Assumptions!C58 -> 1200000000 | D7: =Assumptions!C59 -> 1400000000 | E7: =Assumptions!C60 -> 1800000000
B8: =TEXT(Assumptions!C55,"0.0%") & " — Our %" -> 11.0% — Our % | C8: =L43 -> 0.0080513672 | D8: =M43 -> 0.0069342187 | E8: =N43 -> 0.0054266346 | K8: ESOP rate (R) | L8: =Assumptions!C55 -> 0.11 | M8: =Assumptions!C55 -> 0.11 | N8: =Assumptions!C55 -> 0.11 | O8: =Assumptions!C56 -> 0.13 | P8: =Assumptions!C56 -> 0.13 | Q8: =Assumptions!C56 -> 0.13 | R8: =Assumptions!C57 -> 0.15 | S8: =Assumptions!C57 -> 0.15 | T8: =Assumptions!C57 -> 0.15
B9: =TEXT(Assumptions!C55,"0.0%") & " — Our $" -> 11.0% — Our $ | C9: =L97 -> 16919830 | D9: =M97 -> 14576971 | E9: =N97 -> 11412548 | K9: Pre-money | L9: =Assumptions!C58 -> 1200000000 | M9: =Assumptions!C59 -> 1400000000 | N9: =Assumptions!C60 -> 1800000000 | O9: =Assumptions!C58 -> 1200000000 | P9: =Assumptions!C59 -> 1400000000 | Q9: =Assumptions!C60 -> 1800000000 | R9: =Assumptions!C58 -> 1200000000 | S9: =Assumptions!C59 -> 1400000000 | T9: =Assumptions!C60 -> 1800000000
B10: =TEXT(Assumptions!C56,"0.0%") & " — Our %" -> 13.0% — Our % | C10: =O43 -> 0.0080509711 | D10: =P43 -> 0.0069338863 | E10: =Q43 -> 0.0054263856 | K10: α = primary / pre | L10: =Assumptions!C7/L9 -> 0.025 | M10: =Assumptions!C7/M9 -> 0.021428571 | N10: =Assumptions!C7/N9 -> 0.016666667 | O10: =Assumptions!C7/O9 -> 0.025 | P10: =Assumptions!C7/P9 -> 0.021428571 | Q10: =Assumptions!C7/Q9 -> 0.016666667 | R10: =Assumptions!C7/R9 -> 0.025 | S10: =Assumptions!C7/S9 -> 0.021428571 | T10: =Assumptions!C7/T9 -> 0.016666667
B11: =TEXT(Assumptions!C56,"0.0%") & " — Our $" -> 13.0% — Our $ | C11: =O97 -> 17167775 | D11: =P97 -> 14784051 | E11: =Q97 -> 11567742 | K11: R(1+α) | L11: =L8*(1+L10) -> 0.11275 | M11: =M8*(1+M10) -> 0.11235714 | N11: =N8*(1+N10) -> 0.11183333 | O11: =O8*(1+O10) -> 0.13325 | P11: =P8*(1+P10) -> 0.13278571 | Q11: =Q8*(1+Q10) -> 0.13216667 | R11: =R8*(1+R10) -> 0.15375 | S11: =S8*(1+S10) -> 0.15321429 | T11: =T8*(1+T10) -> 0.1525
B12: =TEXT(Assumptions!C57,"0.0%") & " — Our %" -> 15.0% — Our % | C12: =R43 -> 0.0080503578 | D12: =S43 -> 0.0069333547 | E12: =T43 -> 0.005425969 | K12: ESOP top-up | L12: =MAX(0, (L11*Assumptions!C16 - Assumptions!C19)/(1 - L11)) -> 0 | M12: =MAX(0, (M11*Assumptions!C16 - Assumptions!C19)/(1 - M11)) -> 0 | N12: =MAX(0, (N11*Assumptions!C16 - Assumptions!C19)/(1 - N11)) -> 0 | O12: =MAX(0, (O11*Assumptions!C16 - Assumptions!C19)/(1 - O11)) -> 559188.12 | P12: =MAX(0, (P11*Assumptions!C16 - Assumptions!C19)/(1 - P11)) -> 539284.37 | Q12: =MAX(0, (Q11*Assumptions!C16 - Assumptions!C19)/(1 - Q11)) -> 512779.16 | R12: =MAX(0, (R11*Assumptions!C16 - Assumptions!C19)/(1 - R11)) -> 1459786.7 | S12: =MAX(0, (S11*Assumptions!C16 - Assumptions!C19)/(1 - S11)) -> 1435697 | T12: =MAX(0, (T11*Assumptions!C16 - Assumptions!C19)/(1 - T11)) -> 1403624.8
B13: =TEXT(Assumptions!C57,"0.0%") & " — Our $" -> 15.0% — Our $ | C13: =R97 -> 17566470 | D13: =S97 -> 15127794 | E13: =T97 -> 11837064 | K13: Pre-money FD | L13: =Assumptions!C16 + L12 -> 36617961 | M13: =Assumptions!C16 + M12 -> 36617961 | N13: =Assumptions!C16 + N12 -> 36617961 | O13: =Assumptions!C16 + O12 -> 37177149 | P13: =Assumptions!C16 + P12 -> 37157245 | Q13: =Assumptions!C16 + Q12 -> 37130740 | R13: =Assumptions!C16 + R12 -> 38077748 | S13: =Assumptions!C16 + S12 -> 38053658 | T13: =Assumptions!C16 + T12 -> 38021586
K14: F_PPS | L14: =L9 / L13 -> 32.770803 | M14: =M9 / M13 -> 38.232604 | N14: =N9 / N13 -> 49.156205 | O14: =O9 / O13 -> 32.277892 | P14: =P9 / P13 -> 37.677712 | Q14: =Q9 / Q13 -> 48.477353 | R14: =R9 / R13 -> 31.514469 | S14: =S9 / S13 -> 36.790156 | T14: =T9 / T13 -> 47.341529
K15: new_F shares | L15: =Assumptions!C7/L14 -> 915449.03 | M15: =Assumptions!C7/M14 -> 784670.59 | N15: =Assumptions!C7/N14 -> 610299.35 | O15: =Assumptions!C7/O14 -> 929428.73 | P15: =Assumptions!C7/P14 -> 796226.69 | Q15: =Assumptions!C7/Q14 -> 618845.67 | R15: =Assumptions!C7/R14 -> 951943.69 | S15: =Assumptions!C7/S14 -> 815435.53 | T15: =Assumptions!C7/T14 -> 633693.1
K17: — Anti-dilution —
K18: NCP_D | L18: =IF(L14<Assumptions!C36, Assumptions!C36*(Assumptions!C16+Assumptions!C7/Assumptions!C36)/(Assumptions!C16+L15), Assumptions!C36) -> 57.500114 | M18: =IF(M14<Assumptions!C36, Assumptions!C36*(Assumptions!C16+Assumptions!C7/Assumptions!C36)/(Assumptions!C16+M15), Assumptions!C36) -> 57.701164 | N18: =IF(N14<Assumptions!C36, Assumptions!C36*(Assumptions!C16+Assumptions!C7/Assumptions!C36)/(Assumptions!C16+N15), Assumptions!C36) -> 57.971427 | O18: =IF(O14<Assumptions!C36, Assumptions!C36*(Assumptions!C16+Assumptions!C7/Assumptions!C36)/(Assumptions!C16+O15), Assumptions!C36) -> 57.478706 | P18: =IF(P14<Assumptions!C36, Assumptions!C36*(Assumptions!C16+Assumptions!C7/Assumptions!C36)/(Assumptions!C16+P15), Assumptions!C36) -> 57.683341 | Q18: =IF(Q14<Assumptions!C36, Assumptions!C36*(Assumptions!C16+Assumptions!C7/Assumptions!C36)/(Assumptions!C16+Q15), Assumptions!C36) -> 57.958121 | R18: =IF(R14<Assumptions!C36, Assumptions!C36*(Assumptions!C16+Assumptions!C7/Assumptions!C36)/(Assumptions!C16+R15), Assumptions!C36) -> 57.44426 | S18: =IF(S14<Assumptions!C36, Assumptions!C36*(Assumptions!C16+Assumptions!C7/Assumptions!C36)/(Assumptions!C16+S15), Assumptions!C36) -> 57.653741 | T18: =IF(T14<Assumptions!C36, Assumptions!C36*(Assumptions!C16+Assumptions!C7/Assumptions!C36)/(Assumptions!C16+T15), Assumptions!C36) -> 57.935021
K19: D_postF shares | L19: =Assumptions!C39*Assumptions!C40/L18 -> 1739127.3 | M19: =Assumptions!C39*Assumptions!C40/M18 -> 1733067.7 | N19: =Assumptions!C39*Assumptions!C40/N18 -> 1724988.1 | O19: =Assumptions!C39*Assumptions!C40/O18 -> 1739775.1 | P19: =Assumptions!C39*Assumptions!C40/P18 -> 1733603.1 | Q19: =Assumptions!C39*Assumptions!C40/Q18 -> 1725384.1 | R19: =Assumptions!C39*Assumptions!C40/R18 -> 1740818.3 | S19: =Assumptions!C39*Assumptions!C40/S18 -> 1734493.2 | T19: =Assumptions!C39*Assumptions!C40/T18 -> 1726072
K20: AD_D delta | L20: =L19 - Assumptions!E36 -> 18500.328 | M20: =M19 - Assumptions!E36 -> 12440.651 | N20: =N19 - Assumptions!E36 -> 4361.0811 | O20: =O19 - Assumptions!E36 -> 19148.083 | P20: =P19 - Assumptions!E36 -> 12976.107 | Q20: =Q19 - Assumptions!E36 -> 4757.0786 | R20: =R19 - Assumptions!E36 -> 20191.324 | S20: =S19 - Assumptions!E36 -> 13866.158 | T20: =T19 - Assumptions!E36 -> 5445.0409
K21: NCP_E | L21: =IF(L14<Assumptions!C37, Assumptions!C37*(Assumptions!C16+Assumptions!C7/Assumptions!C37)/(Assumptions!C16+L15), Assumptions!C37) -> 48.758616 | M21: =IF(M14<Assumptions!C37, Assumptions!C37*(Assumptions!C16+Assumptions!C7/Assumptions!C37)/(Assumptions!C16+M15), Assumptions!C37) -> 48.9291 | N21: =IF(N14<Assumptions!C37, Assumptions!C37*(Assumptions!C16+Assumptions!C7/Assumptions!C37)/(Assumptions!C16+N15), Assumptions!C37) -> 49.158276 | O21: =IF(O14<Assumptions!C37, Assumptions!C37*(Assumptions!C16+Assumptions!C7/Assumptions!C37)/(Assumptions!C16+O15), Assumptions!C37) -> 48.740462 | P21: =IF(P14<Assumptions!C37, Assumptions!C37*(Assumptions!C16+Assumptions!C7/Assumptions!C37)/(Assumptions!C16+P15), Assumptions!C37) -> 48.913988 | Q21: =IF(Q14<Assumptions!C37, Assumptions!C37*(Assumptions!C16+Assumptions!C7/Assumptions!C37)/(Assumptions!C16+Q15), Assumptions!C37) -> 49.146994 | R21: =IF(R14<Assumptions!C37, Assumptions!C37*(Assumptions!C16+Assumptions!C7/Assumptions!C37)/(Assumptions!C16+R15), Assumptions!C37) -> 48.711253 | S21: =IF(S14<Assumptions!C37, Assumptions!C37*(Assumptions!C16+Assumptions!C7/Assumptions!C37)/(Assumptions!C16+S15), Assumptions!C37) -> 48.888888 | T21: =IF(T14<Assumptions!C37, Assumptions!C37*(Assumptions!C16+Assumptions!C7/Assumptions!C37)/(Assumptions!C16+T15), Assumptions!C37) -> 49.127405
K22: E_postF shares | L22: =Assumptions!E37*Assumptions!C37/L21 -> 6152693.2 | M22: =Assumptions!E37*Assumptions!C37/M21 -> 6131255.2 | N22: =Assumptions!E37*Assumptions!C37/N21 -> 6102671.3 | O22: =Assumptions!E37*Assumptions!C37/O21 -> 6154984.8 | P22: =Assumptions!E37*Assumptions!C37/P21 -> 6133149.6 | Q22: =Assumptions!E37*Assumptions!C37/Q21 -> 6104072.2 | R22: =Assumptions!E37*Assumptions!C37/R21 -> 6158675.6 | S22: =Assumptions!E37*Assumptions!C37/S21 -> 6136298.4 | T22: =Assumptions!E37*Assumptions!C37/T21 -> 6106506.1
K23: AD_E delta | L23: =L22 - Assumptions!E37 -> 50026.182 | M23: =M22 - Assumptions!E37 -> 28588.226 | N23: =N22 - Assumptions!E37 -> 4.2858605 | O23: =O22 - Assumptions!E37 -> 52317.815 | P23: =P22 - Assumptions!E37 -> 30482.568 | Q23: =Q22 - Assumptions!E37 -> 1405.2478 | R23: =R22 - Assumptions!E37 -> 56008.598 | S23: =S22 - Assumptions!E37 -> 33631.392 | T23: =T22 - Assumptions!E37 -> 3839.1239
K24: AD total | L24: =L20+L23 -> 68526.509 | M24: =M20+M23 -> 41028.877 | N24: =N20+N23 -> 4365.367 | O24: =O20+O23 -> 71465.899 | P24: =P20+P23 -> 43458.675 | Q24: =Q20+Q23 -> 6162.3265 | R24: =R20+R23 -> 76199.923 | S24: =S20+S23 -> 47497.55 | T24: =T20+T23 -> 9284.1648
K26: — Notes (mutual solve) —
K27: Note B disc-only shares (helper) | L27: =Assumptions!C45/((1-Assumptions!E45)*L14) -> 107699.89 | M27: =Assumptions!C45/((1-Assumptions!E45)*M14) -> 92314.187 | N27: =Assumptions!C45/((1-Assumptions!E45)*N14) -> 71799.924 | O27: =Assumptions!C45/((1-Assumptions!E45)*O14) -> 109344.56 | P27: =Assumptions!C45/((1-Assumptions!E45)*P14) -> 93673.728 | Q27: =Assumptions!C45/((1-Assumptions!E45)*Q14) -> 72805.373 | R27: =Assumptions!C45/((1-Assumptions!E45)*R14) -> 111993.38 | S27: =Assumptions!C45/((1-Assumptions!E45)*S14) -> 95933.592 | T27: =Assumptions!C45/((1-Assumptions!E45)*T14) -> 74552.129
K28: Note A cap-implied PPS | L28: =Assumptions!D44/(L13 + L24 + L27) -> 27.178206 | M28: =Assumptions!D44/(M13 + M24 + M27) -> 27.209919 | N28: =Assumptions!D44/(N13 + N24 + N27) -> 27.252318 | O28: =Assumptions!D44/(O13 + O24 + O27) -> 26.768057 | P28: =Assumptions!D44/(P13 + P24 + P27) -> 26.813693 | Q28: =Assumptions!D44/(Q13 + Q24 + Q27) -> 26.874707 | R28: =Assumptions!D44/(R13 + R24 + R27) -> 26.1329 | S28: =Assumptions!D44/(S13 + S24 + S27) -> 26.180005 | T28: =Assumptions!D44/(T13 + T24 + T27) -> 26.242984
K29: Note A disc-implied PPS | L29: =(1-Assumptions!E44)*L14 -> 26.216643 | M29: =(1-Assumptions!E44)*M14 -> 30.586083 | N29: =(1-Assumptions!E44)*N14 -> 39.324964 | O29: =(1-Assumptions!E44)*O14 -> 25.822314 | P29: =(1-Assumptions!E44)*P14 -> 30.14217 | Q29: =(1-Assumptions!E44)*Q14 -> 38.781882 | R29: =(1-Assumptions!E44)*R14 -> 25.211575 | S29: =(1-Assumptions!E44)*S14 -> 29.432124 | T29: =(1-Assumptions!E44)*T14 -> 37.873223
K30: Note A conv PPS | L30: =MIN(L28,L29) -> 26.216643 | M30: =MIN(M28,M29) -> 27.209919 | N30: =MIN(N28,N29) -> 27.252318 | O30: =MIN(O28,O29) -> 25.822314 | P30: =MIN(P28,P29) -> 26.813693 | Q30: =MIN(Q28,Q29) -> 26.874707 | R30: =MIN(R28,R29) -> 25.211575 | S30: =MIN(S28,S29) -> 26.180005 | T30: =MIN(T28,T29) -> 26.242984
K31: Note A branch | L31: =IF(L28<L29,"cap","discount") -> discount | M31: =IF(M28<M29,"cap","discount") -> cap | N31: =IF(N28<N29,"cap","discount") -> cap | O31: =IF(O28<O29,"cap","discount") -> discount | P31: =IF(P28<P29,"cap","discount") -> cap | Q31: =IF(Q28<Q29,"cap","discount") -> cap | R31: =IF(R28<R29,"cap","discount") -> discount | S31: =IF(S28<S29,"cap","discount") -> cap | T31: =IF(T28<T29,"cap","discount") -> cap
K32: Note A shares | L32: =Assumptions!C44/L30 -> 190718.55 | M32: =Assumptions!C44/M30 -> 183756.52 | N32: =Assumptions!C44/N30 -> 183470.63 | O32: =Assumptions!C44/O30 -> 193630.99 | P32: =Assumptions!C44/P30 -> 186471.89 | Q32: =Assumptions!C44/Q30 -> 186048.54 | R32: =Assumptions!C44/R30 -> 198321.6 | S32: =Assumptions!C44/S30 -> 190985.45 | T32: =Assumptions!C44/T30 -> 190527.11
K33: Note A disc-only shares (helper) | L33: =Assumptions!C44/((1-Assumptions!E44)*L14) -> 190718.55 | M33: =Assumptions!C44/((1-Assumptions!E44)*M14) -> 163473.04 | N33: =Assumptions!C44/((1-Assumptions!E44)*N14) -> 127145.7 | O33: =Assumptions!C44/((1-Assumptions!E44)*O14) -> 193630.99 | P33: =Assumptions!C44/((1-Assumptions!E44)*P14) -> 165880.56 | Q33: =Assumptions!C44/((1-Assumptions!E44)*Q14) -> 128926.18 | R33: =Assumptions!C44/((1-Assumptions!E44)*R14) -> 198321.6 | S33: =Assumptions!C44/((1-Assumptions!E44)*S14) -> 169882.4 | T33: =Assumptions!C44/((1-Assumptions!E44)*T14) -> 132019.4
K34: Note B cap-implied PPS | L34: =Assumptions!D45/(L13 + L24 + L33) -> 43.387235 | M34: =Assumptions!D45/(M13 + M24 + M33) -> 43.451738 | N34: =Assumptions!D45/(N13 + N24 + N33) -> 43.53804 | O34: =Assumptions!D45/(O13 + O24 + O33) -> 42.732479 | P34: =Assumptions!D45/(P13 + P24 + P33) -> 42.819006 | Q34: =Assumptions!D45/(Q13 + Q24 + Q33) -> 42.934776 | R34: =Assumptions!D45/(R13 + R24 + R33) -> 41.718522 | S34: =Assumptions!D45/(S13 + S24 + S33) -> 41.807071 | T34: =Assumptions!D45/(T13 + T24 + T33) -> 41.925547
K35: Note B disc-implied PPS | L35: =(1-Assumptions!E45)*L14 -> 27.855183 | M35: =(1-Assumptions!E45)*M14 -> 32.497713 | N35: =(1-Assumptions!E45)*N14 -> 41.782774 | O35: =(1-Assumptions!E45)*O14 -> 27.436208 | P35: =(1-Assumptions!E45)*P14 -> 32.026055 | Q35: =(1-Assumptions!E45)*Q14 -> 41.20575 | R35: =(1-Assumptions!E45)*R14 -> 26.787299 | S35: =(1-Assumptions!E45)*S14 -> 31.271632 | T35: =(1-Assumptions!E45)*T14 -> 40.240299
K36: Note B conv PPS | L36: =MIN(L34,L35) -> 27.855183 | M36: =MIN(M34,M35) -> 32.497713 | N36: =MIN(N34,N35) -> 41.782774 | O36: =MIN(O34,O35) -> 27.436208 | P36: =MIN(P34,P35) -> 32.026055 | Q36: =MIN(Q34,Q35) -> 41.20575 | R36: =MIN(R34,R35) -> 26.787299 | S36: =MIN(S34,S35) -> 31.271632 | T36: =MIN(T34,T35) -> 40.240299
K37: Note B branch | L37: =IF(L34<L35,"cap","discount") -> discount | M37: =IF(M34<M35,"cap","discount") -> discount | N37: =IF(N34<N35,"cap","discount") -> discount | O37: =IF(O34<O35,"cap","discount") -> discount | P37: =IF(P34<P35,"cap","discount") -> discount | Q37: =IF(Q34<Q35,"cap","discount") -> discount | R37: =IF(R34<R35,"cap","discount") -> discount | S37: =IF(S34<S35,"cap","discount") -> discount | T37: =IF(T34<T35,"cap","discount") -> discount
K38: Note B shares | L38: =Assumptions!C45/L36 -> 107699.89 | M38: =Assumptions!C45/M36 -> 92314.187 | N38: =Assumptions!C45/N36 -> 71799.924 | O38: =Assumptions!C45/O36 -> 109344.56 | P38: =Assumptions!C45/P36 -> 93673.728 | Q38: =Assumptions!C45/Q36 -> 72805.373 | R38: =Assumptions!C45/R36 -> 111993.38 | S38: =Assumptions!C45/S36 -> 95933.592 | T38: =Assumptions!C45/T36 -> 74552.129
K40: T_F (post-F FD) | L40: =Assumptions!C16+L12+L24+L15+L32+L38 -> 37900355 | M40: =Assumptions!C16+M12+M24+M15+M32+M38 -> 37719731 | N40: =Assumptions!C16+N12+N24+N15+N32+N38 -> 37487896 | O40: =Assumptions!C16+O12+O24+O15+O32+O38 -> 38481019 | P40: =Assumptions!C16+P12+P24+P15+P32+P38 -> 38277076 | Q40: =Assumptions!C16+Q12+Q24+Q15+Q32+Q38 -> 38014602 | R40: =Assumptions!C16+R12+R24+R15+R32+R38 -> 39416206 | S40: =Assumptions!C16+S12+S24+S15+S32+S38 -> 39203510 | T40: =Assumptions!C16+T12+T24+T15+T32+T38 -> 38929642
K41: Convert pool initial | L41: =L40 - Assumptions!C18 - L12 -> 36005688 | M41: =M40 - Assumptions!C18 - M12 -> 35825064 | N41: =N40 - Assumptions!C18 - N12 -> 35593229 | O41: =O40 - Assumptions!C18 - O12 -> 36027164 | P41: =P40 - Assumptions!C18 - P12 -> 35843125 | Q41: =Q40 - Assumptions!C18 - Q12 -> 35607156 | R41: =R40 - Assumptions!C18 - R12 -> 36061753 | S41: =S40 - Assumptions!C18 - S12 -> 35873146 | T41: =T40 - Assumptions!C18 - T12 -> 35631351
K42: Our F shares | L42: =Assumptions!C11/L14 -> 305149.68 | M42: =Assumptions!C11/M14 -> 261556.86 | N42: =Assumptions!C11/N14 -> 203433.12 | O42: =Assumptions!C11/O14 -> 309809.58 | P42: =Assumptions!C11/P14 -> 265408.9 | Q42: =Assumptions!C11/Q14 -> 206281.89 | R42: =Assumptions!C11/R14 -> 317314.56 | S42: =Assumptions!C11/S14 -> 271811.84 | T42: =Assumptions!C11/T14 -> 211231.03
K43: Our ownership % | L43: =L42/L40 -> 0.0080513672 | M43: =M42/M40 -> 0.0069342187 | N43: =N42/N40 -> 0.0054266346 | O43: =O42/O40 -> 0.0080509711 | P43: =P42/P40 -> 0.0069338863 | Q43: =Q42/Q40 -> 0.0054263856 | R43: =R42/R40 -> 0.0080503578 | S43: =S42/S40 -> 0.0069333547 | T43: =T42/T40 -> 0.005425969
K45: — Waterfall @ $2B exit (sequential F→Seed) —
K47: F: residual_in | L47: =Assumptions!C50 -> 2000000000 | M47: =Assumptions!C50 -> 2000000000 | N47: =Assumptions!C50 -> 2000000000 | O47: =Assumptions!C50 -> 2000000000 | P47: =Assumptions!C50 -> 2000000000 | Q47: =Assumptions!C50 -> 2000000000 | R47: =Assumptions!C50 -> 2000000000 | S47: =Assumptions!C50 -> 2000000000 | T47: =Assumptions!C50 -> 2000000000
K48: F: pool_in | L48: =L41 -> 36005688 | M48: =M41 -> 35825064 | N48: =N41 -> 35593229 | O48: =O41 -> 36027164 | P48: =P41 -> 35843125 | Q48: =Q41 -> 35607156 | R48: =R41 -> 36061753 | S48: =S41 -> 35873146 | T48: =T41 -> 35631351
K49: F: convert (decision) | L49: =L15/L48*L47 -> 50850245 | M49: =M15/M48*M47 -> 43805677 | N49: =N15/N48*N47 -> 34293002 | O49: =O15/O48*O47 -> 51595997 | P49: =P15/P48*P47 -> 44428419 | Q49: =Q15/Q48*Q47 -> 34759624 | R49: =R15/R48*R47 -> 52795198 | S49: =S15/S48*S47 -> 45462170 | T49: =T15/T48*T47 -> 35569412
K50: F: election | L50: =IF(L49>Assumptions!C7,"convert","preference") -> convert | M50: =IF(M49>Assumptions!C7,"convert","preference") -> convert | N50: =IF(N49>Assumptions!C7,"convert","preference") -> convert | O50: =IF(O49>Assumptions!C7,"convert","preference") -> convert | P50: =IF(P49>Assumptions!C7,"convert","preference") -> convert | Q50: =IF(Q49>Assumptions!C7,"convert","preference") -> convert | R50: =IF(R49>Assumptions!C7,"convert","preference") -> convert | S50: =IF(S49>Assumptions!C7,"convert","preference") -> convert | T50: =IF(T49>Assumptions!C7,"convert","preference") -> convert
K51: F: residual_out | L51: =L47-IF(L50="preference",Assumptions!C7,0) -> 2000000000 | M51: =M47-IF(M50="preference",Assumptions!C7,0) -> 2000000000 | N51: =N47-IF(N50="preference",Assumptions!C7,0) -> 2000000000 | O51: =O47-IF(O50="preference",Assumptions!C7,0) -> 2000000000 | P51: =P47-IF(P50="preference",Assumptions!C7,0) -> 2000000000 | Q51: =Q47-IF(Q50="preference",Assumptions!C7,0) -> 2000000000 | R51: =R47-IF(R50="preference",Assumptions!C7,0) -> 2000000000 | S51: =S47-IF(S50="preference",Assumptions!C7,0) -> 2000000000 | T51: =T47-IF(T50="preference",Assumptions!C7,0) -> 2000000000
K52: F: pool_out | L52: =L48-IF(L50="preference",L15,0) -> 36005688 | M52: =M48-IF(M50="preference",M15,0) -> 35825064 | N52: =N48-IF(N50="preference",N15,0) -> 35593229 | O52: =O48-IF(O50="preference",O15,0) -> 36027164 | P52: =P48-IF(P50="preference",P15,0) -> 35843125 | Q52: =Q48-IF(Q50="preference",Q15,0) -> 35607156 | R52: =R48-IF(R50="preference",R15,0) -> 36061753 | S52: =S48-IF(S50="preference",S15,0) -> 35873146 | T52: =T48-IF(T50="preference",T15,0) -> 35631351
K54: E: residual_in | L54: =L51 -> 2000000000 | M54: =M51 -> 2000000000 | N54: =N51 -> 2000000000 | O54: =O51 -> 2000000000 | P54: =P51 -> 2000000000 | Q54: =Q51 -> 2000000000 | R54: =R51 -> 2000000000 | S54: =S51 -> 2000000000 | T54: =T51 -> 2000000000
K55: E: pool_in | L55: =L52 -> 36005688 | M55: =M52 -> 35825064 | N55: =N52 -> 35593229 | O55: =O52 -> 36027164 | P55: =P52 -> 35843125 | Q55: =Q52 -> 35607156 | R55: =R52 -> 36061753 | S55: =S52 -> 35873146 | T55: =T52 -> 35631351
K56: E: convert (decision) | L56: =L22/L55*L54 -> 3.4176229e+08 | M56: =M22/M55*M54 -> 3.4228858e+08 | N56: =N22/N55*N54 -> 3.4291192e+08 | O56: =O22/O55*O54 -> 3.4168578e+08 | P56: =P22/P55*P54 -> 3.4222181e+08 | Q56: =Q22/Q55*Q54 -> 3.4285649e+08 | R56: =R22/R55*R54 -> 3.4156274e+08 | S56: =S22/S55*S54 -> 3.4211097e+08 | T56: =T22/T55*T54 -> 3.427603e+08
K57: E: election | L57: =IF(L56>Assumptions!F37,"convert","preference") -> convert | M57: =IF(M56>Assumptions!F37,"convert","preference") -> convert | N57: =IF(N56>Assumptions!F37,"convert","preference") -> convert | O57: =IF(O56>Assumptions!F37,"convert","preference") -> convert | P57: =IF(P56>Assumptions!F37,"convert","preference") -> convert | Q57: =IF(Q56>Assumptions!F37,"convert","preference") -> convert | R57: =IF(R56>Assumptions!F37,"convert","preference") -> convert | S57: =IF(S56>Assumptions!F37,"convert","preference") -> convert | T57: =IF(T56>Assumptions!F37,"convert","preference") -> convert
K58: E: residual_out | L58: =L54-IF(L57="preference",Assumptions!F37,0) -> 2000000000 | M58: =M54-IF(M57="preference",Assumptions!F37,0) -> 2000000000 | N58: =N54-IF(N57="preference",Assumptions!F37,0) -> 2000000000 | O58: =O54-IF(O57="preference",Assumptions!F37,0) -> 2000000000 | P58: =P54-IF(P57="preference",Assumptions!F37,0) -> 2000000000 | Q58: =Q54-IF(Q57="preference",Assumptions!F37,0) -> 2000000000 | R58: =R54-IF(R57="preference",Assumptions!F37,0) -> 2000000000 | S58: =S54-IF(S57="preference",Assumptions!F37,0) -> 2000000000 | T58: =T54-IF(T57="preference",Assumptions!F37,0) -> 2000000000
K59: E: pool_out | L59: =L55-IF(L57="preference",L22,0) -> 36005688 | M59: =M55-IF(M57="preference",M22,0) -> 35825064 | N59: =N55-IF(N57="preference",N22,0) -> 35593229 | O59: =O55-IF(O57="preference",O22,0) -> 36027164 | P59: =P55-IF(P57="preference",P22,0) -> 35843125 | Q59: =Q55-IF(Q57="preference",Q22,0) -> 35607156 | R59: =R55-IF(R57="preference",R22,0) -> 36061753 | S59: =S55-IF(S57="preference",S22,0) -> 35873146 | T59: =T55-IF(T57="preference",T22,0) -> 35631351
K61: D: residual_in | L61: =L58 -> 2000000000 | M61: =M58 -> 2000000000 | N61: =N58 -> 2000000000 | O61: =O58 -> 2000000000 | P61: =P58 -> 2000000000 | Q61: =Q58 -> 2000000000 | R61: =R58 -> 2000000000 | S61: =S58 -> 2000000000 | T61: =T58 -> 2000000000
K62: D: pool_in | L62: =L59 -> 36005688 | M62: =M59 -> 35825064 | N62: =N59 -> 35593229 | O62: =O59 -> 36027164 | P62: =P59 -> 35843125 | Q62: =Q59 -> 35607156 | R62: =R59 -> 36061753 | S62: =S59 -> 35873146 | T62: =T59 -> 35631351
K63: D: convert (decision) | L63: =L19/L62*L61 -> 96602922 | M63: =M19/M62*M61 -> 96751684 | N63: =N19/N62*N61 -> 96927877 | O63: =O19/O62*O61 -> 96581295 | P63: =P19/P62*P61 -> 96732810 | Q63: =Q19/Q62*Q61 -> 96912210 | R63: =R19/R62*R61 -> 96546518 | S63: =S19/S62*S61 -> 96701480 | T63: =T19/T62*T61 -> 96885019
K64: D: election | L64: =IF(L63>Assumptions!F36,"convert","preference") -> preference | M64: =IF(M63>Assumptions!F36,"convert","preference") -> preference | N64: =IF(N63>Assumptions!F36,"convert","preference") -> preference | O64: =IF(O63>Assumptions!F36,"convert","preference") -> preference | P64: =IF(P63>Assumptions!F36,"convert","preference") -> preference | Q64: =IF(Q63>Assumptions!F36,"convert","preference") -> preference | R64: =IF(R63>Assumptions!F36,"convert","preference") -> preference | S64: =IF(S63>Assumptions!F36,"convert","preference") -> preference | T64: =IF(T63>Assumptions!F36,"convert","preference") -> preference
K65: D: residual_out | L65: =L61-IF(L64="preference",Assumptions!F36,0) -> 1900000000 | M65: =M61-IF(M64="preference",Assumptions!F36,0) -> 1900000000 | N65: =N61-IF(N64="preference",Assumptions!F36,0) -> 1900000000 | O65: =O61-IF(O64="preference",Assumptions!F36,0) -> 1900000000 | P65: =P61-IF(P64="preference",Assumptions!F36,0) -> 1900000000 | Q65: =Q61-IF(Q64="preference",Assumptions!F36,0) -> 1900000000 | R65: =R61-IF(R64="preference",Assumptions!F36,0) -> 1900000000 | S65: =S61-IF(S64="preference",Assumptions!F36,0) -> 1900000000 | T65: =T61-IF(T64="preference",Assumptions!F36,0) -> 1900000000
K66: D: pool_out | L66: =L62-IF(L64="preference",L19,0) -> 34266561 | M66: =M62-IF(M64="preference",M19,0) -> 34091997 | N66: =N62-IF(N64="preference",N19,0) -> 33868241 | O66: =O62-IF(O64="preference",O19,0) -> 34287389 | P66: =P62-IF(P64="preference",P19,0) -> 34109522 | Q66: =Q62-IF(Q64="preference",Q19,0) -> 33881772 | R66: =R62-IF(R64="preference",R19,0) -> 34320934 | S66: =S62-IF(S64="preference",S19,0) -> 34138653 | T66: =T62-IF(T64="preference",T19,0) -> 33905278
K68: C: residual_in | L68: =L65 -> 1900000000 | M68: =M65 -> 1900000000 | N68: =N65 -> 1900000000 | O68: =O65 -> 1900000000 | P68: =P65 -> 1900000000 | Q68: =Q65 -> 1900000000 | R68: =R65 -> 1900000000 | S68: =S65 -> 1900000000 | T68: =T65 -> 1900000000
K69: C: pool_in | L69: =L66 -> 34266561 | M69: =M66 -> 34091997 | N69: =N66 -> 33868241 | O69: =O66 -> 34287389 | P69: =P66 -> 34109522 | Q69: =Q66 -> 33881772 | R69: =R66 -> 34320934 | S69: =S66 -> 34138653 | T69: =T66 -> 33905278
K70: C: convert (decision) | L70: =Assumptions!E35/L69*L68 -> 1.3307434e+08 | M70: =Assumptions!E35/M69*M68 -> 1.3375573e+08 | N70: =Assumptions!E35/N69*N68 -> 1.3463941e+08 | O70: =Assumptions!E35/O69*O68 -> 1.329935e+08 | P70: =Assumptions!E35/P69*P68 -> 1.3368701e+08 | Q70: =Assumptions!E35/Q69*Q68 -> 1.3458564e+08 | R70: =Assumptions!E35/R69*R68 -> 1.3286352e+08 | S70: =Assumptions!E35/S69*S68 -> 1.3357293e+08 | T70: =Assumptions!E35/T69*T68 -> 1.3449233e+08
K71: C: election | L71: =IF(L70>Assumptions!F35,"convert","preference") -> convert | M71: =IF(M70>Assumptions!F35,"convert","preference") -> convert | N71: =IF(N70>Assumptions!F35,"convert","preference") -> convert | O71: =IF(O70>Assumptions!F35,"convert","preference") -> convert | P71: =IF(P70>Assumptions!F35,"convert","preference") -> convert | Q71: =IF(Q70>Assumptions!F35,"convert","preference") -> convert | R71: =IF(R70>Assumptions!F35,"convert","preference") -> convert | S71: =IF(S70>Assumptions!F35,"convert","preference") -> convert | T71: =IF(T70>Assumptions!F35,"convert","preference") -> convert
K72: C: residual_out | L72: =L68-IF(L71="preference",Assumptions!F35,0) -> 1900000000 | M72: =M68-IF(M71="preference",Assumptions!F35,0) -> 1900000000 | N72: =N68-IF(N71="preference",Assumptions!F35,0) -> 1900000000 | O72: =O68-IF(O71="preference",Assumptions!F35,0) -> 1900000000 | P72: =P68-IF(P71="preference",Assumptions!F35,0) -> 1900000000 | Q72: =Q68-IF(Q71="preference",Assumptions!F35,0) -> 1900000000 | R72: =R68-IF(R71="preference",Assumptions!F35,0) -> 1900000000 | S72: =S68-IF(S71="preference",Assumptions!F35,0) -> 1900000000 | T72: =T68-IF(T71="preference",Assumptions!F35,0) -> 1900000000
K73: C: pool_out | L73: =L69-IF(L71="preference",Assumptions!E35,0) -> 34266561 | M73: =M69-IF(M71="preference",Assumptions!E35,0) -> 34091997 | N73: =N69-IF(N71="preference",Assumptions!E35,0) -> 33868241 | O73: =O69-IF(O71="preference",Assumptions!E35,0) -> 34287389 | P73: =P69-IF(P71="preference",Assumptions!E35,0) -> 34109522 | Q73: =Q69-IF(Q71="preference",Assumptions!E35,0) -> 33881772 | R73: =R69-IF(R71="preference",Assumptions!E35,0) -> 34320934 | S73: =S69-IF(S71="preference",Assumptions!E35,0) -> 34138653 | T73: =T69-IF(T71="preference",Assumptions!E35,0) -> 33905278
K75: B: residual_in | L75: =L72 -> 1900000000 | M75: =M72 -> 1900000000 | N75: =N72 -> 1900000000 | O75: =O72 -> 1900000000 | P75: =P72 -> 1900000000 | Q75: =Q72 -> 1900000000 | R75: =R72 -> 1900000000 | S75: =S72 -> 1900000000 | T75: =T72 -> 1900000000
K76: B: pool_in | L76: =L73 -> 34266561 | M76: =M73 -> 34091997 | N76: =N73 -> 33868241 | O76: =O73 -> 34287389 | P76: =P73 -> 34109522 | Q76: =Q73 -> 33881772 | R76: =R73 -> 34320934 | S76: =S73 -> 34138653 | T76: =T73 -> 33905278
K77: B: convert (decision) | L77: =Assumptions!E34/L76*L75 -> 1.6634293e+08 | M77: =Assumptions!E34/M76*M75 -> 1.6719467e+08 | N77: =Assumptions!E34/N76*N75 -> 1.6829926e+08 | O77: =Assumptions!E34/O76*O75 -> 1.6624188e+08 | P77: =Assumptions!E34/P76*P75 -> 1.6710876e+08 | Q77: =Assumptions!E34/Q76*Q75 -> 1.6823205e+08 | R77: =Assumptions!E34/R76*R75 -> 1.660794e+08 | S77: =Assumptions!E34/S76*S75 -> 1.6696617e+08 | T77: =Assumptions!E34/T76*T75 -> 1.6811542e+08
K78: B: election | L78: =IF(L77>Assumptions!F34,"convert","preference") -> convert | M78: =IF(M77>Assumptions!F34,"convert","preference") -> convert | N78: =IF(N77>Assumptions!F34,"convert","preference") -> convert | O78: =IF(O77>Assumptions!F34,"convert","preference") -> convert | P78: =IF(P77>Assumptions!F34,"convert","preference") -> convert | Q78: =IF(Q77>Assumptions!F34,"convert","preference") -> convert | R78: =IF(R77>Assumptions!F34,"convert","preference") -> convert | S78: =IF(S77>Assumptions!F34,"convert","preference") -> convert | T78: =IF(T77>Assumptions!F34,"convert","preference") -> convert
K79: B: residual_out | L79: =L75-IF(L78="preference",Assumptions!F34,0) -> 1900000000 | M79: =M75-IF(M78="preference",Assumptions!F34,0) -> 1900000000 | N79: =N75-IF(N78="preference",Assumptions!F34,0) -> 1900000000 | O79: =O75-IF(O78="preference",Assumptions!F34,0) -> 1900000000 | P79: =P75-IF(P78="preference",Assumptions!F34,0) -> 1900000000 | Q79: =Q75-IF(Q78="preference",Assumptions!F34,0) -> 1900000000 | R79: =R75-IF(R78="preference",Assumptions!F34,0) -> 1900000000 | S79: =S75-IF(S78="preference",Assumptions!F34,0) -> 1900000000 | T79: =T75-IF(T78="preference",Assumptions!F34,0) -> 1900000000
K80: B: pool_out | L80: =L76-IF(L78="preference",Assumptions!E34,0) -> 34266561 | M80: =M76-IF(M78="preference",Assumptions!E34,0) -> 34091997 | N80: =N76-IF(N78="preference",Assumptions!E34,0) -> 33868241 | O80: =O76-IF(O78="preference",Assumptions!E34,0) -> 34287389 | P80: =P76-IF(P78="preference",Assumptions!E34,0) -> 34109522 | Q80: =Q76-IF(Q78="preference",Assumptions!E34,0) -> 33881772 | R80: =R76-IF(R78="preference",Assumptions!E34,0) -> 34320934 | S80: =S76-IF(S78="preference",Assumptions!E34,0) -> 34138653 | T80: =T76-IF(T78="preference",Assumptions!E34,0) -> 33905278
K82: A: residual_in | L82: =L79 -> 1900000000 | M82: =M79 -> 1900000000 | N82: =N79 -> 1900000000 | O82: =O79 -> 1900000000 | P82: =P79 -> 1900000000 | Q82: =Q79 -> 1900000000 | R82: =R79 -> 1900000000 | S82: =S79 -> 1900000000 | T82: =T79 -> 1900000000
K83: A: pool_in | L83: =L80 -> 34266561 | M83: =M80 -> 34091997 | N83: =N80 -> 33868241 | O83: =O80 -> 34287389 | P83: =P80 -> 34109522 | Q83: =Q80 -> 33881772 | R83: =R80 -> 34320934 | S83: =S80 -> 34138653 | T83: =T80 -> 33905278
K84: A: convert (decision) | L84: =Assumptions!E33/L83*L82 -> 2.7723821e+08 | M84: =Assumptions!E33/M83*M82 -> 2.7865778e+08 | N84: =Assumptions!E33/N83*N82 -> 2.8049877e+08 | O84: =Assumptions!E33/O83*O82 -> 2.770698e+08 | P84: =Assumptions!E33/P83*P82 -> 2.785146e+08 | Q84: =Assumptions!E33/Q83*Q82 -> 2.8038675e+08 | R84: =Assumptions!E33/R83*R82 -> 2.7679899e+08 | S84: =Assumptions!E33/S83*S82 -> 2.7827694e+08 | T84: =Assumptions!E33/T83*T82 -> 2.8019236e+08
K85: A: election | L85: =IF(L84>Assumptions!F33,"convert","preference") -> convert | M85: =IF(M84>Assumptions!F33,"convert","preference") -> convert | N85: =IF(N84>Assumptions!F33,"convert","preference") -> convert | O85: =IF(O84>Assumptions!F33,"convert","preference") -> convert | P85: =IF(P84>Assumptions!F33,"convert","preference") -> convert | Q85: =IF(Q84>Assumptions!F33,"convert","preference") -> convert | R85: =IF(R84>Assumptions!F33,"convert","preference") -> convert | S85: =IF(S84>Assumptions!F33,"convert","preference") -> convert | T85: =IF(T84>Assumptions!F33,"convert","preference") -> convert
K86: A: residual_out | L86: =L82-IF(L85="preference",Assumptions!F33,0) -> 1900000000 | M86: =M82-IF(M85="preference",Assumptions!F33,0) -> 1900000000 | N86: =N82-IF(N85="preference",Assumptions!F33,0) -> 1900000000 | O86: =O82-IF(O85="preference",Assumptions!F33,0) -> 1900000000 | P86: =P82-IF(P85="preference",Assumptions!F33,0) -> 1900000000 | Q86: =Q82-IF(Q85="preference",Assumptions!F33,0) -> 1900000000 | R86: =R82-IF(R85="preference",Assumptions!F33,0) -> 1900000000 | S86: =S82-IF(S85="preference",Assumptions!F33,0) -> 1900000000 | T86: =T82-IF(T85="preference",Assumptions!F33,0) -> 1900000000
K87: A: pool_out | L87: =L83-IF(L85="preference",Assumptions!E33,0) -> 34266561 | M87: =M83-IF(M85="preference",Assumptions!E33,0) -> 34091997 | N87: =N83-IF(N85="preference",Assumptions!E33,0) -> 33868241 | O87: =O83-IF(O85="preference",Assumptions!E33,0) -> 34287389 | P87: =P83-IF(P85="preference",Assumptions!E33,0) -> 34109522 | Q87: =Q83-IF(Q85="preference",Assumptions!E33,0) -> 33881772 | R87: =R83-IF(R85="preference",Assumptions!E33,0) -> 34320934 | S87: =S83-IF(S85="preference",Assumptions!E33,0) -> 34138653 | T87: =T83-IF(T85="preference",Assumptions!E33,0) -> 33905278
K89: Seed: residual_in | L89: =L86 -> 1900000000 | M89: =M86 -> 1900000000 | N89: =N86 -> 1900000000 | O89: =O86 -> 1900000000 | P89: =P86 -> 1900000000 | Q89: =Q86 -> 1900000000 | R89: =R86 -> 1900000000 | S89: =S86 -> 1900000000 | T89: =T86 -> 1900000000
K90: Seed: pool_in | L90: =L87 -> 34266561 | M90: =M87 -> 34091997 | N90: =N87 -> 33868241 | O90: =O87 -> 34287389 | P90: =P87 -> 34109522 | Q90: =Q87 -> 33881772 | R90: =R87 -> 34320934 | S90: =S87 -> 34138653 | T90: =T87 -> 33905278
K91: Seed: convert (decision) | L91: =Assumptions!E32/L90*L89 -> 2.7723821e+08 | M91: =Assumptions!E32/M90*M89 -> 2.7865778e+08 | N91: =Assumptions!E32/N90*N89 -> 2.8049877e+08 | O91: =Assumptions!E32/O90*O89 -> 2.770698e+08 | P91: =Assumptions!E32/P90*P89 -> 2.785146e+08 | Q91: =Assumptions!E32/Q90*Q89 -> 2.8038675e+08 | R91: =Assumptions!E32/R90*R89 -> 2.7679899e+08 | S91: =Assumptions!E32/S90*S89 -> 2.7827694e+08 | T91: =Assumptions!E32/T90*T89 -> 2.8019236e+08
K92: Seed: election | L92: =IF(L91>Assumptions!F32,"convert","preference") -> convert | M92: =IF(M91>Assumptions!F32,"convert","preference") -> convert | N92: =IF(N91>Assumptions!F32,"convert","preference") -> convert | O92: =IF(O91>Assumptions!F32,"convert","preference") -> convert | P92: =IF(P91>Assumptions!F32,"convert","preference") -> convert | Q92: =IF(Q91>Assumptions!F32,"convert","preference") -> convert | R92: =IF(R91>Assumptions!F32,"convert","preference") -> convert | S92: =IF(S91>Assumptions!F32,"convert","preference") -> convert | T92: =IF(T91>Assumptions!F32,"convert","preference") -> convert
K93: Seed: residual_out (=final) | L93: =L89-IF(L92="preference",Assumptions!F32,0) -> 1900000000 | M93: =M89-IF(M92="preference",Assumptions!F32,0) -> 1900000000 | N93: =N89-IF(N92="preference",Assumptions!F32,0) -> 1900000000 | O93: =O89-IF(O92="preference",Assumptions!F32,0) -> 1900000000 | P93: =P89-IF(P92="preference",Assumptions!F32,0) -> 1900000000 | Q93: =Q89-IF(Q92="preference",Assumptions!F32,0) -> 1900000000 | R93: =R89-IF(R92="preference",Assumptions!F32,0) -> 1900000000 | S93: =S89-IF(S92="preference",Assumptions!F32,0) -> 1900000000 | T93: =T89-IF(T92="preference",Assumptions!F32,0) -> 1900000000
K94: Seed: pool_out (=final) | L94: =L90-IF(L92="preference",Assumptions!E32,0) -> 34266561 | M94: =M90-IF(M92="preference",Assumptions!E32,0) -> 34091997 | N94: =N90-IF(N92="preference",Assumptions!E32,0) -> 33868241 | O94: =O90-IF(O92="preference",Assumptions!E32,0) -> 34287389 | P94: =P90-IF(P92="preference",Assumptions!E32,0) -> 34109522 | Q94: =Q90-IF(Q92="preference",Assumptions!E32,0) -> 33881772 | R94: =R90-IF(R92="preference",Assumptions!E32,0) -> 34320934 | S94: =S90-IF(S92="preference",Assumptions!E32,0) -> 34138653 | T94: =T90-IF(T92="preference",Assumptions!E32,0) -> 33905278
K96: Final per-share | L96: =L93/L94 -> 55.447642 | M96: =M93/M94 -> 55.731556 | N96: =N93/N94 -> 56.099754 | O96: =O93/O94 -> 55.41396 | P96: =P93/P94 -> 55.702921 | Q96: =Q93/Q94 -> 56.077351 | R96: =R93/R94 -> 55.359798 | S96: =S93/S94 -> 55.655389 | T96: =T93/T94 -> 56.038472
K97: Our $ proceeds | L97: =IF(L50="preference",Assumptions!C11,L42*L96) -> 16919830 | M97: =IF(M50="preference",Assumptions!C11,M42*M96) -> 14576971 | N97: =IF(N50="preference",Assumptions!C11,N42*N96) -> 11412548 | O97: =IF(O50="preference",Assumptions!C11,O42*O96) -> 17167775 | P97: =IF(P50="preference",Assumptions!C11,P42*P96) -> 14784051 | Q97: =IF(Q50="preference",Assumptions!C11,Q42*Q96) -> 11567742 | R97: =IF(R50="preference",Assumptions!C11,R42*R96) -> 17566470 | S97: =IF(S50="preference",Assumptions!C11,S42*S96) -> 15127794 | T97: =IF(T50="preference",Assumptions!C11,T42*T96) -> 11837064

Sheet Return-Solver
B2: Return Solver — Required F Ownership %
B3: For each exit: solve for our post-F ownership % required to hit 3× ($30M) and 4× ($40M) on our $10M check
B5: Base Case Inputs
B6: Our check | C6: =Assumptions!C11 -> 10000000
B7: 3× target | C7: =Assumptions!C63 -> 30000000
B8: 4× target | C8: =Assumptions!C64 -> 40000000
B9: Post-F FD (T_F) | C9: ='Pro-Forma'!C52 -> 38277076
B10: F PPS | C10: ='Pro-Forma'!C13 -> 37.677712
B12: Exit Scenario | C12: Exit 1 ($700M) | D12: Exit 2 ($1.2B) | E12: Exit 3 ($2B) | F12: Exit 4 ($4B) | G12: Exit 5 ($8B)
B14: Exit value | C14: =Waterfall!E12 -> 700000000 | D14: =Waterfall!F12 -> 1200000000 | E14: =Waterfall!G12 -> 2000000000 | F14: =Waterfall!H12 -> 4000000000 | G14: =Waterfall!I12 -> 8000000000
B15: F election | C15: =Waterfall!E19 -> preference | D15: =Waterfall!F19 -> preference | E15: =Waterfall!G19 -> convert | F15: =Waterfall!H19 -> convert | G15: =Waterfall!I19 -> convert
B16: Final per-share value | C16: =Waterfall!E79 -> 8.2644076 | D16: =Waterfall!F79 -> 28.329502 | E16: =Waterfall!G79 -> 55.702921 | F16: =Waterfall!H79 -> 111.59741 | G16: =Waterfall!I79 -> 223.19482
B18: 3× Return Solve
B19: Required F shares (target / per-share) | C19: =IF(C15="convert", $C$7/C16, "n/a — F prefers") -> n/a — F prefers | D19: =IF(D15="convert", $C$7/D16, "n/a — F prefers") -> n/a — F prefers | E19: =IF(E15="convert", $C$7/E16, "n/a — F prefers") -> 538571.4 | F19: =IF(F15="convert", $C$7/F16, "n/a — F prefers") -> 268823.44 | G19: =IF(G15="convert", $C$7/G16, "n/a — F prefers") -> 134411.72
B20: Required ownership % | C20: =IF(C15="convert", $C$7/(C16*$C$9), "Infeasible — F prefers") -> Infeasible — F prefers | D20: =IF(D15="convert", $C$7/(D16*$C$9), "Infeasible — F prefers") -> Infeasible — F prefers | E20: =IF(E15="convert", $C$7/(E16*$C$9), "Infeasible — F prefers") -> 0.014070338 | F20: =IF(F15="convert", $C$7/(F16*$C$9), "Infeasible — F prefers") -> 0.0070230922 | G20: =IF(G15="convert", $C$7/(G16*$C$9), "Infeasible — F prefers") -> 0.0035115461
B21: Feasibility flag | C21: =IF(C15="preference","Infeasible (F prefers — caps at 1x)",IF(C20<=0,"Infeasible (≤ 0%)",IF(C20>1,"Infeasible (> 100%)","Feasible"))) -> Infeasible (F prefers — caps at 1x) | D21: =IF(D15="preference","Infeasible (F prefers — caps at 1x)",IF(D20<=0,"Infeasible (≤ 0%)",IF(D20>1,"Infeasible (> 100%)","Feasible"))) -> Infeasible (F prefers — caps at 1x) | E21: =IF(E15="preference","Infeasible (F prefers — caps at 1x)",IF(E20<=0,"Infeasible (≤ 0%)",IF(E20>1,"Infeasible (> 100%)","Feasible"))) -> Feasible | F21: =IF(F15="preference","Infeasible (F prefers — caps at 1x)",IF(F20<=0,"Infeasible (≤ 0%)",IF(F20>1,"Infeasible (> 100%)","Feasible"))) -> Feasible | G21: =IF(G15="preference","Infeasible (F prefers — caps at 1x)",IF(G20<=0,"Infeasible (≤ 0%)",IF(G20>1,"Infeasible (> 100%)","Feasible"))) -> Feasible
B23: 4× Return Solve
B24: Required F shares (target / per-share) | C24: =IF(C15="convert", $C$8/C16, "n/a — F prefers") -> n/a — F prefers | D24: =IF(D15="convert", $C$8/D16, "n/a — F prefers") -> n/a — F prefers | E24: =IF(E15="convert", $C$8/E16, "n/a — F prefers") -> 718095.2 | F24: =IF(F15="convert", $C$8/F16, "n/a — F prefers") -> 358431.25 | G24: =IF(G15="convert", $C$8/G16, "n/a — F prefers") -> 179215.62
B25: Required ownership % | C25: =IF(C15="convert", $C$8/(C16*$C$9), "Infeasible — F prefers") -> Infeasible — F prefers | D25: =IF(D15="convert", $C$8/(D16*$C$9), "Infeasible — F prefers") -> Infeasible — F prefers | E25: =IF(E15="convert", $C$8/(E16*$C$9), "Infeasible — F prefers") -> 0.018760451 | F25: =IF(F15="convert", $C$8/(F16*$C$9), "Infeasible — F prefers") -> 0.009364123 | G25: =IF(G15="convert", $C$8/(G16*$C$9), "Infeasible — F prefers") -> 0.0046820615
B26: Feasibility flag | C26: =IF(C15="preference","Infeasible (F prefers — caps at 1x)",IF(C25<=0,"Infeasible (≤ 0%)",IF(C25>1,"Infeasible (> 100%)","Feasible"))) -> Infeasible (F prefers — caps at 1x) | D26: =IF(D15="preference","Infeasible (F prefers — caps at 1x)",IF(D25<=0,"Infeasible (≤ 0%)",IF(D25>1,"Infeasible (> 100%)","Feasible"))) -> Infeasible (F prefers — caps at 1x) | E26: =IF(E15="preference","Infeasible (F prefers — caps at 1x)",IF(E25<=0,"Infeasible (≤ 0%)",IF(E25>1,"Infeasible (> 100%)","Feasible"))) -> Feasible | F26: =IF(F15="preference","Infeasible (F prefers — caps at 1x)",IF(F25<=0,"Infeasible (≤ 0%)",IF(F25>1,"Infeasible (> 100%)","Feasible"))) -> Feasible | G26: =IF(G15="preference","Infeasible (F prefers — caps at 1x)",IF(G25<=0,"Infeasible (≤ 0%)",IF(G25>1,"Infeasible (> 100%)","Feasible"))) -> Feasible
B28: Reference
B29: Base-case our ownership % | C29: =$C$6/$C$10/$C$9 -> 0.0069338863 | D29: =$C$6/$C$10/$C$9 -> 0.0069338863 | E29: =$C$6/$C$10/$C$9 -> 0.0069338863 | F29: =$C$6/$C$10/$C$9 -> 0.0069338863 | G29: =$C$6/$C$10/$C$9 -> 0.0069338863
B30: Base-case our $ proceeds | C30: =IF(C15="preference",$C$6,Waterfall!E82/Assumptions!C7*$C$6) -> 10000000 | D30: =IF(D15="preference",$C$6,Waterfall!F82/Assumptions!C7*$C$6) -> 10000000 | E30: =IF(E15="preference",$C$6,Waterfall!G82/Assumptions!C7*$C$6) -> 14784051 | F30: =IF(F15="preference",$C$6,Waterfall!H82/Assumptions!C7*$C$6) -> 29618946 | G30: =IF(G15="preference",$C$6,Waterfall!I82/Assumptions!C7*$C$6) -> 59237892
B31: Base-case multiple on $10M | C31: =C30/$C$6 -> 1 | D31: =D30/$C$6 -> 1 | E31: =E30/$C$6 -> 1.4784051 | F31: =F30/$C$6 -> 2.9618946 | G31: =G30/$C$6 -> 5.9237892
