Workbook

Sheet Assumptions
B2: Kelvin Dynamics — Series F Assumptions
B3: Sole source of inputs. All output tabs reference this sheet.
B5: Series F Round Terms
B6: Pre-money valuation ($) | C6: 1400000000
B7: Primary raise ($) | C7: 30000000
B8: Secondary tender ($) | C8: 15000000
B9: Tender PPS multiplier | C9: 0.85
B10: ESOP refresh target (% post-F FD) | C10: 0.13
B11: Our fund check ($) | C11: 10000000
B12: F_LEAD primary check ($) | C12: 20000000
B14: Exit Scenarios
B15: Exit 1 ($) | C15: 700000000
B16: Exit 2 ($) | C16: 1200000000
B17: Exit 3 ($, sensitivity ref) | C17: 2000000000
B18: Exit 4 ($) | C18: 4000000000
B19: Exit 5 ($) | C19: 8000000000
B21: Prior Round OCPs (for AD)
B22: Seed OCP ($/share) | C22: 1
B23: Series A OCP ($/share) | C23: 3
B24: Series B OCP ($/share) | C24: 10
B25: Series C OCP ($/share) | C25: 25
B26: Series D OCP (post-E NCP, $/share) | C26: 58.118347
B27: Series D original OCP ($/share) | C27: 60
B28: Series E OCP ($/share) | C28: 49.158311
B30: Pre-F Share Counts
B31: Founder F1 (CEO) common | C31: 4000000
B32: Founder F2 (CTO) common | C32: 2500000
B33: Founder F3 (CSci) common | C33: 1500000
B34: Employee RSAs (10 × 100k) | C34: 1000000
B35: Seed shares | C35: 5000000
B36: Series A shares | C36: 5000000
B37: Series B shares | C37: 3000000
B38: Series C shares | C38: 2400000
B39: Series D shares (post-E AD) | C39: 1720627
B40: Series D original shares (= $100M / $60) | C40: 1666667
B41: Series E shares | C41: 6102667
B42: Pre-F issued options | C42: 2500000
B43: Pre-F unissued option pool | C43: 1894667
B44: Pre-F FD total (sum) | C44: =SUM(C31:C43)-C40 -> 36617961
B46: Convertible Notes
B47: Note A principal ($) | C47: 5000000
B48: Note A valuation cap ($) | C48: 1000000000
B49: Note A discount | C49: 0.2
B50: Note B principal ($) | C50: 3000000
B51: Note B valuation cap ($) | C51: 1600000000
B52: Note B discount | C52: 0.15
B54: Options & Misc
B55: Option strike ($) | C55: 1
B56: Pre-F existing option pool (issued + unissued) | C56: 4394667
B58: Sensitivity Axes
B59: ESOP refresh — low | C59: 0.11
B60: ESOP refresh — base | C60: 0.13
B61: ESOP refresh — high | C61: 0.15
B62: Pre-money — low ($) | C62: 1200000000
B63: Pre-money — base ($) | C63: 1400000000
B64: Pre-money — high ($) | C64: 1800000000
B66: Return Solver Targets
B67: Target 3x ($) | C67: =C11*3 -> 30000000
B68: Target 4x ($) | C68: =C11*4 -> 40000000

Sheet Pro-Forma
B2: Kelvin Dynamics — Series F Pro-Forma
B3: Post-F cap table, AD adjustments, note conversions, tender. ($, shares)
B5: F PPS Solver — Iterative Fixed Point
B6: Iteration | C6: Iter 0 | D6: Iter 1 | E6: Iter 2 | F6: Iter 3 | G6: Iter 4 | H6: Iter 5 | I6: Iter 6 | J6: Iter 7 | K6: Iter 8 | L6: Iter 9
B7: F_PPS (input) | C7: 45 | D7: =C25 -> 37.375973 | E7: =D25 -> 37.300872 | F7: =E25 -> 37.299776 | G7: =F25 -> 37.29976 | H7: =G25 -> 37.29976 | I7: =H25 -> 37.29976 | J7: =I25 -> 37.29976 | K7: =J25 -> 37.29976 | L7: =K25 -> 37.29976
B8: NCP_D (post-F WA) | C8: =IF(C7<Assumptions!$C$26,Assumptions!$C$26*(Assumptions!$C$44+Assumptions!$C$7/Assumptions!$C$26)/(Assumptions!$C$44+Assumptions!$C$7/C7),Assumptions!$C$26) -> 57.883785 | D8: =IF(D7<Assumptions!$C$26,Assumptions!$C$26*(Assumptions!$C$44+Assumptions!$C$7/Assumptions!$C$26)/(Assumptions!$C$44+Assumptions!$C$7/D7),Assumptions!$C$26) -> 57.673433 | E8: =IF(E7<Assumptions!$C$26,Assumptions!$C$26*(Assumptions!$C$44+Assumptions!$C$7/Assumptions!$C$26)/(Assumptions!$C$44+Assumptions!$C$7/E7),Assumptions!$C$26) -> 57.670942 | F8: =IF(F7<Assumptions!$C$26,Assumptions!$C$26*(Assumptions!$C$44+Assumptions!$C$7/Assumptions!$C$26)/(Assumptions!$C$44+Assumptions!$C$7/F7),Assumptions!$C$26) -> 57.670906 | G8: =IF(G7<Assumptions!$C$26,Assumptions!$C$26*(Assumptions!$C$44+Assumptions!$C$7/Assumptions!$C$26)/(Assumptions!$C$44+Assumptions!$C$7/G7),Assumptions!$C$26) -> 57.670905 | H8: =IF(H7<Assumptions!$C$26,Assumptions!$C$26*(Assumptions!$C$44+Assumptions!$C$7/Assumptions!$C$26)/(Assumptions!$C$44+Assumptions!$C$7/H7),Assumptions!$C$26) -> 57.670905 | I8: =IF(I7<Assumptions!$C$26,Assumptions!$C$26*(Assumptions!$C$44+Assumptions!$C$7/Assumptions!$C$26)/(Assumptions!$C$44+Assumptions!$C$7/I7),Assumptions!$C$26) -> 57.670905 | J8: =IF(J7<Assumptions!$C$26,Assumptions!$C$26*(Assumptions!$C$44+Assumptions!$C$7/Assumptions!$C$26)/(Assumptions!$C$44+Assumptions!$C$7/J7),Assumptions!$C$26) -> 57.670905 | ... L8: =IF(L7<Assumptions!$C$26,Assumptions!$C$26*(Assumptions!$C$44+Assumptions!$C$7/Assumptions!$C$26)/(Assumptions!$C$44+Assumptions!$C$7/L7),Assumptions!$C$26) -> 57.670905
B9: Δ Series D shares | C9: =Assumptions!$C$40*Assumptions!$C$27/C8-Assumptions!$C$39 -> 6972.8859 | D9: =Assumptions!$C$40*Assumptions!$C$27/D8-Assumptions!$C$39 -> 13273.951 | E9: =Assumptions!$C$40*Assumptions!$C$27/E8-Assumptions!$C$39 -> 13348.833 | F9: =Assumptions!$C$40*Assumptions!$C$27/F8-Assumptions!$C$39 -> 13349.927 | G9: =Assumptions!$C$40*Assumptions!$C$27/G8-Assumptions!$C$39 -> 13349.943 | H9: =Assumptions!$C$40*Assumptions!$C$27/H8-Assumptions!$C$39 -> 13349.943 | I9: =Assumptions!$C$40*Assumptions!$C$27/I8-Assumptions!$C$39 -> 13349.943 | J9: =Assumptions!$C$40*Assumptions!$C$27/J8-Assumptions!$C$39 -> 13349.943 | ... L9: =Assumptions!$C$40*Assumptions!$C$27/L8-Assumptions!$C$39 -> 13349.943
B10: NCP_E (post-F WA) | C10: =IF(C7<Assumptions!$C$28,Assumptions!$C$28*(Assumptions!$C$44+Assumptions!$C$7/Assumptions!$C$28)/(Assumptions!$C$44+Assumptions!$C$7/C7),Assumptions!$C$28) -> 49.083958 | D10: =IF(D7<Assumptions!$C$28,Assumptions!$C$28*(Assumptions!$C$44+Assumptions!$C$7/Assumptions!$C$28)/(Assumptions!$C$44+Assumptions!$C$7/D7),Assumptions!$C$28) -> 48.905585 | E10: =IF(E7<Assumptions!$C$28,Assumptions!$C$28*(Assumptions!$C$44+Assumptions!$C$7/Assumptions!$C$28)/(Assumptions!$C$44+Assumptions!$C$7/E7),Assumptions!$C$28) -> 48.903473 | F10: =IF(F7<Assumptions!$C$28,Assumptions!$C$28*(Assumptions!$C$44+Assumptions!$C$7/Assumptions!$C$28)/(Assumptions!$C$44+Assumptions!$C$7/F7),Assumptions!$C$28) -> 48.903443 | G10: =IF(G7<Assumptions!$C$28,Assumptions!$C$28*(Assumptions!$C$44+Assumptions!$C$7/Assumptions!$C$28)/(Assumptions!$C$44+Assumptions!$C$7/G7),Assumptions!$C$28) -> 48.903442 | H10: =IF(H7<Assumptions!$C$28,Assumptions!$C$28*(Assumptions!$C$44+Assumptions!$C$7/Assumptions!$C$28)/(Assumptions!$C$44+Assumptions!$C$7/H7),Assumptions!$C$28) -> 48.903442 | I10: =IF(I7<Assumptions!$C$28,Assumptions!$C$28*(Assumptions!$C$44+Assumptions!$C$7/Assumptions!$C$28)/(Assumptions!$C$44+Assumptions!$C$7/I7),Assumptions!$C$28) -> 48.903442 | J10: =IF(J7<Assumptions!$C$28,Assumptions!$C$28*(Assumptions!$C$44+Assumptions!$C$7/Assumptions!$C$28)/(Assumptions!$C$44+Assumptions!$C$7/J7),Assumptions!$C$28) -> 48.903442 | ... L10: =IF(L7<Assumptions!$C$28,Assumptions!$C$28*(Assumptions!$C$44+Assumptions!$C$7/Assumptions!$C$28)/(Assumptions!$C$44+Assumptions!$C$7/L7),Assumptions!$C$28) -> 48.903442
B11: Δ Series E shares | C11: =Assumptions!$C$41*Assumptions!$C$28/C10-Assumptions!$C$41 -> 9244.3417 | D11: =Assumptions!$C$41*Assumptions!$C$28/D10-Assumptions!$C$41 -> 31536.282 | E11: =Assumptions!$C$41*Assumptions!$C$28/E10-Assumptions!$C$41 -> 31801.197 | F11: =Assumptions!$C$41*Assumptions!$C$28/F10-Assumptions!$C$41 -> 31805.07 | G11: =Assumptions!$C$41*Assumptions!$C$28/G10-Assumptions!$C$41 -> 31805.125 | H11: =Assumptions!$C$41*Assumptions!$C$28/H10-Assumptions!$C$41 -> 31805.125 | I11: =Assumptions!$C$41*Assumptions!$C$28/I10-Assumptions!$C$41 -> 31805.125 | J11: =Assumptions!$C$41*Assumptions!$C$28/J10-Assumptions!$C$41 -> 31805.125 | ... L11: =Assumptions!$C$41*Assumptions!$C$28/L10-Assumptions!$C$41 -> 31805.125
B12: Base FD (preF + ΔD + ΔE) | C12: =Assumptions!$C$44+C9+C11 -> 36634178 | D12: =Assumptions!$C$44+D9+D11 -> 36662771 | E12: =Assumptions!$C$44+E9+E11 -> 36663111 | F12: =Assumptions!$C$44+F9+F11 -> 36663116 | G12: =Assumptions!$C$44+G9+G11 -> 36663116 | H12: =Assumptions!$C$44+H9+H11 -> 36663116 | I12: =Assumptions!$C$44+I9+I11 -> 36663116 | J12: =Assumptions!$C$44+J9+J11 -> 36663116 | ... L12: =Assumptions!$C$44+L9+L11 -> 36663116
B13: F_S (new F primary shares) | C13: =Assumptions!$C$7/C7 -> 666666.67 | D13: =Assumptions!$C$7/D7 -> 802654.68 | E13: =Assumptions!$C$7/E7 -> 804270.75 | F13: =Assumptions!$C$7/F7 -> 804294.37 | G13: =Assumptions!$C$7/G7 -> 804294.71 | H13: =Assumptions!$C$7/H7 -> 804294.71 | I13: =Assumptions!$C$7/I7 -> 804294.71 | J13: =Assumptions!$C$7/J7 -> 804294.71 | ... L13: =Assumptions!$C$7/L7 -> 804294.71
B14: Note A — cap PPS | C14: =Assumptions!$C$48/(C12+0+0) -> 27.296914 | D14: =Assumptions!$C$48/(D12+C22+C21) -> 26.807754 | E14: =Assumptions!$C$48/(E12+D22+D21) -> 26.776298 | F14: =Assumptions!$C$48/(F12+E22+E21) -> 26.775905 | G14: =Assumptions!$C$48/(G12+F22+F21) -> 26.775899 | H14: =Assumptions!$C$48/(H12+G22+G21) -> 26.775899 | I14: =Assumptions!$C$48/(I12+H22+H21) -> 26.775899 | J14: =Assumptions!$C$48/(J12+I22+I21) -> 26.775899 | K14: =Assumptions!$C$48/(K12+J22+J21) -> 26.775899 | L14: =Assumptions!$C$48/(L12+K22+K21) -> 26.775899
B15: Note A — discount PPS | C15: =C7*(1-Assumptions!$C$49) -> 36 | D15: =D7*(1-Assumptions!$C$49) -> 29.900779 | E15: =E7*(1-Assumptions!$C$49) -> 29.840697 | F15: =F7*(1-Assumptions!$C$49) -> 29.839821 | G15: =G7*(1-Assumptions!$C$49) -> 29.839808 | H15: =H7*(1-Assumptions!$C$49) -> 29.839808 | I15: =I7*(1-Assumptions!$C$49) -> 29.839808 | J15: =J7*(1-Assumptions!$C$49) -> 29.839808 | ... L15: =L7*(1-Assumptions!$C$49) -> 29.839808
B16: Note A — conv PPS (min) | C16: =MIN(C14,C15) -> 27.296914 | D16: =MIN(D14,D15) -> 26.807754 | E16: =MIN(E14,E15) -> 26.776298 | F16: =MIN(F14,F15) -> 26.775905 | G16: =MIN(G14,G15) -> 26.775899 | H16: =MIN(H14,H15) -> 26.775899 | I16: =MIN(I14,I15) -> 26.775899 | J16: =MIN(J14,J15) -> 26.775899 | ... L16: =MIN(L14,L15) -> 26.775899
B17: Note A — shares issued | C17: =Assumptions!$C$47/C16 -> 183170.89 | D17: =Assumptions!$C$47/D16 -> 186513.2 | E17: =Assumptions!$C$47/E16 -> 186732.31 | F17: =Assumptions!$C$47/F16 -> 186735.05 | G17: =Assumptions!$C$47/G16 -> 186735.09 | H17: =Assumptions!$C$47/H16 -> 186735.09 | I17: =Assumptions!$C$47/I16 -> 186735.09 | J17: =Assumptions!$C$47/J16 -> 186735.09 | ... L17: =Assumptions!$C$47/L16 -> 186735.09
B18: Note B — cap PPS | C18: =Assumptions!$C$51/(C12+0+0) -> 43.675062 | D18: =Assumptions!$C$51/(D12+C22+C17) -> 42.772308 | E18: =Assumptions!$C$51/(E12+D22+D17) -> 42.736704 | F18: =Assumptions!$C$51/(F12+E22+E17) -> 42.736045 | G18: =Assumptions!$C$51/(G12+F22+F17) -> 42.736035 | H18: =Assumptions!$C$51/(H12+G22+G17) -> 42.736035 | I18: =Assumptions!$C$51/(I12+H22+H17) -> 42.736035 | J18: =Assumptions!$C$51/(J12+I22+I17) -> 42.736035 | K18: =Assumptions!$C$51/(K12+J22+J17) -> 42.736035 | L18: =Assumptions!$C$51/(L12+K22+K17) -> 42.736035
B19: Note B — discount PPS | C19: =C7*(1-Assumptions!$C$52) -> 38.25 | D19: =D7*(1-Assumptions!$C$52) -> 31.769577 | E19: =E7*(1-Assumptions!$C$52) -> 31.705741 | F19: =F7*(1-Assumptions!$C$52) -> 31.70481 | G19: =G7*(1-Assumptions!$C$52) -> 31.704796 | H19: =H7*(1-Assumptions!$C$52) -> 31.704796 | I19: =I7*(1-Assumptions!$C$52) -> 31.704796 | J19: =J7*(1-Assumptions!$C$52) -> 31.704796 | ... L19: =L7*(1-Assumptions!$C$52) -> 31.704796
B20: Note B — conv PPS (min) | C20: =MIN(C18,C19) -> 38.25 | D20: =MIN(D18,D19) -> 31.769577 | E20: =MIN(E18,E19) -> 31.705741 | F20: =MIN(F18,F19) -> 31.70481 | G20: =MIN(G18,G19) -> 31.704796 | H20: =MIN(H18,H19) -> 31.704796 | I20: =MIN(I18,I19) -> 31.704796 | J20: =MIN(J18,J19) -> 31.704796 | ... L20: =MIN(L18,L19) -> 31.704796
B21: Note B — shares issued | C21: =Assumptions!$C$50/C20 -> 78431.373 | D21: =Assumptions!$C$50/D20 -> 94429.963 | E21: =Assumptions!$C$50/E20 -> 94620.088 | F21: =Assumptions!$C$50/F20 -> 94622.868 | G21: =Assumptions!$C$50/G20 -> 94622.907 | H21: =Assumptions!$C$50/H20 -> 94622.907 | I21: =Assumptions!$C$50/I20 -> 94622.908 | J21: =Assumptions!$C$50/J20 -> 94622.908 | ... L21: =Assumptions!$C$50/L20 -> 94622.908
B22: ESOP top-up | C22: =MAX(0,(Assumptions!$C$10*(C12+C17+C21+C13)-Assumptions!$C$56)/(1-Assumptions!$C$10)) -> 561438.08 | D22: =MAX(0,(Assumptions!$C$10*(D12+D17+D21+D13)-Assumptions!$C$56)/(1-Assumptions!$C$10)) -> 588920.67 | E22: =MAX(0,(Assumptions!$C$10*(E12+E17+E21+E13)-Assumptions!$C$56)/(1-Assumptions!$C$10)) -> 589274.07 | F22: =MAX(0,(Assumptions!$C$10*(F12+F17+F21+F13)-Assumptions!$C$56)/(1-Assumptions!$C$10)) -> 589279.17 | G22: =MAX(0,(Assumptions!$C$10*(G12+G17+G21+G13)-Assumptions!$C$56)/(1-Assumptions!$C$10)) -> 589279.24 | H22: =MAX(0,(Assumptions!$C$10*(H12+H17+H21+H13)-Assumptions!$C$56)/(1-Assumptions!$C$10)) -> 589279.24 | I22: =MAX(0,(Assumptions!$C$10*(I12+I17+I21+I13)-Assumptions!$C$56)/(1-Assumptions!$C$10)) -> 589279.24 | J22: =MAX(0,(Assumptions!$C$10*(J12+J17+J21+J13)-Assumptions!$C$56)/(1-Assumptions!$C$10)) -> 589279.24 | ... L22: =MAX(0,(Assumptions!$C$10*(L12+L17+L21+L13)-Assumptions!$C$56)/(1-Assumptions!$C$10)) -> 589279.24
B23: T_F (post-F FD shares) | C23: =C12+C22+C17+C21+C13 -> 38123885 | D23: =D12+D22+D17+D21+D13 -> 38335290 | E23: =E12+E22+E17+E21+E13 -> 38338008 | F23: =F12+F22+F17+F21+F13 -> 38338047 | G23: =G12+G22+G17+G21+G13 -> 38338048 | H23: =H12+H22+H17+H21+H13 -> 38338048 | I23: =I12+I22+I17+I21+I13 -> 38338048 | J23: =J12+J22+J17+J21+J13 -> 38338048 | ... L23: =L12+L22+L17+L21+L13 -> 38338048
B24: Pre-money FD shares | C24: =C23-C13 -> 37457219 | D24: =D23-D13 -> 37532635 | E24: =E23-E13 -> 37533737 | F24: =F23-F13 -> 37533753 | G24: =G23-G13 -> 37533753 | H24: =H23-H13 -> 37533753 | I24: =I23-I13 -> 37533753 | J24: =J23-J13 -> 37533753 | ... L24: =L23-L13 -> 37533753
B25: F_PPS_new | C25: =Assumptions!$C$6/C24 -> 37.375973 | D25: =Assumptions!$C$6/D24 -> 37.300872 | E25: =Assumptions!$C$6/E24 -> 37.299776 | F25: =Assumptions!$C$6/F24 -> 37.29976 | G25: =Assumptions!$C$6/G24 -> 37.29976 | H25: =Assumptions!$C$6/H24 -> 37.29976 | I25: =Assumptions!$C$6/I24 -> 37.29976 | J25: =Assumptions!$C$6/J24 -> 37.29976 | ... L25: =Assumptions!$C$6/L24 -> 37.29976
B27: Converged Round Mechanics
B28: Series F PPS ($) | C28: =L25 -> 37.29976
B29: Series F new primary shares | C29: =L13 -> 804294.71
B30: Pre-money FD shares | C30: =L24 -> 37533753
B31: Post-F FD shares (T_F) | C31: =L23 -> 38338048
B32: ESOP top-up | C32: =L22 -> 589279.24
B33: Total post-F option pool | C33: =Assumptions!$C$56+L22 -> 4983946.2
B34: Implied post-money valuation ($) | C34: =C28*C31 -> 1430000000
B35: Tender PPS ($) | C35: =Assumptions!$C$9*C28 -> 31.704796
B36: Tender shares (founders → F_LEAD) | C36: =Assumptions!$C$8/C35 -> 473114.54
B38: Anti-Dilution Block (Broad-Based WA)
B39: Class | C39: Original OCP | D39: Trigger? | E39: New conv. price (NCP) | F39: New ratio (compound) | G39: As-converted shares | H39: Δ vs. pre-F
B40: Seed | C40: =Assumptions!$C$22 -> 1 | D40: =IF(C28<Assumptions!$C$22,"YES","no") -> no | E40: =IF(C28<Assumptions!$C$22,Assumptions!$C$22*(Assumptions!$C$44+Assumptions!$C$7/Assumptions!$C$22)/(Assumptions!$C$44+Assumptions!$C$7/C28),Assumptions!$C$22) -> 1 | F40: =Assumptions!$C$22/E40 -> 1 | G40: =Assumptions!$C$35*F40 -> 5000000 | H40: =G40-Assumptions!$C$35 -> 0
B41: Series A | C41: =Assumptions!$C$23 -> 3 | D41: =IF(C28<Assumptions!$C$23,"YES","no") -> no | E41: =IF(C28<Assumptions!$C$23,Assumptions!$C$23*(Assumptions!$C$44+Assumptions!$C$7/Assumptions!$C$23)/(Assumptions!$C$44+Assumptions!$C$7/C28),Assumptions!$C$23) -> 3 | F41: =Assumptions!$C$23/E41 -> 1 | G41: =Assumptions!$C$36*F41 -> 5000000 | H41: =G41-Assumptions!$C$36 -> 0
B42: Series B | C42: =Assumptions!$C$24 -> 10 | D42: =IF(C28<Assumptions!$C$24,"YES","no") -> no | E42: =IF(C28<Assumptions!$C$24,Assumptions!$C$24*(Assumptions!$C$44+Assumptions!$C$7/Assumptions!$C$24)/(Assumptions!$C$44+Assumptions!$C$7/C28),Assumptions!$C$24) -> 10 | F42: =Assumptions!$C$24/E42 -> 1 | G42: =Assumptions!$C$37*F42 -> 3000000 | H42: =G42-Assumptions!$C$37 -> 0
B43: Series C | C43: =Assumptions!$C$25 -> 25 | D43: =IF(C28<Assumptions!$C$25,"YES","no") -> no | E43: =IF(C28<Assumptions!$C$25,Assumptions!$C$25*(Assumptions!$C$44+Assumptions!$C$7/Assumptions!$C$25)/(Assumptions!$C$44+Assumptions!$C$7/C28),Assumptions!$C$25) -> 25 | F43: =Assumptions!$C$25/E43 -> 1 | G43: =Assumptions!$C$38*F43 -> 2400000 | H43: =G43-Assumptions!$C$38 -> 0
B44: Series D | C44: =Assumptions!$C$27 -> 60 | D44: =IF(C28<Assumptions!$C$26,"YES","no") -> YES | E44: =L8 -> 57.670905 | F44: =Assumptions!$C$27/E44 -> 1.040386 | G44: =Assumptions!$C$40*F44 -> 1733976.9 | H44: =G44-Assumptions!$C$39 -> 13349.943
B45: Series E | C45: =Assumptions!$C$28 -> 49.158311 | D45: =IF(C28<Assumptions!$C$28,"YES","no") -> YES | E45: =L10 -> 48.903442 | F45: =Assumptions!$C$28/E45 -> 1.0052117 | G45: =Assumptions!$C$41*F45 -> 6134472.1 | H45: =G45-Assumptions!$C$41 -> 31805.125
B47: Convertible Notes — Conversion at F Closing
B48: Note | C48: Cap-implied PPS | D48: Discount-implied PPS | E48: Conversion PPS (min) | F48: Branch | G48: Shares issued | H48: Principal ($)
B49: Note A | C49: =L14 -> 26.775899 | D49: =L15 -> 29.839808 | E49: =L16 -> 26.775899 | F49: =IF(L14<L15,"cap","discount") -> cap | G49: =L17 -> 186735.09 | H49: =Assumptions!$C$47 -> 5000000
B50: Note B | C50: =L18 -> 42.736035 | D50: =L19 -> 31.704796 | E50: =L20 -> 31.704796 | F50: =IF(L18<L19,"cap","discount") -> discount | G50: =L21 -> 94622.908 | H50: =Assumptions!$C$50 -> 3000000
B52: Secondary Tender ($15M @ 0.85·F_PPS, founders → F_LEAD)
B53: Tender PPS ($) | C53: =C35 -> 31.704796
B54: Tender shares (total) | C54: =C36 -> 473114.54
B55: F1 sells (50.00% pro rata) | C55: =C54*Assumptions!$C$31/(Assumptions!$C$31+Assumptions!$C$32+Assumptions!$C$33) -> 236557.27
B56: F2 sells (31.25% pro rata) | C56: =C54*Assumptions!$C$32/(Assumptions!$C$31+Assumptions!$C$32+Assumptions!$C$33) -> 147848.29
B57: F3 sells (18.75% pro rata) | C57: =C54*Assumptions!$C$33/(Assumptions!$C$31+Assumptions!$C$32+Assumptions!$C$33) -> 88708.976
B58: F_LEAD secondary common | C58: =C54 -> 473114.54
B60: Post-F Stakeholder Cap Table
B61: Stakeholder | C61: Role | D61: Common | E61: Class | F61: Preferred | G61: Total | H61: Ownership %
B62: F1 | C62: Founder (CEO) | D62: =Assumptions!$C$31-C55 -> 3763442.7 | E62: — | F62: 0 | G62: =D62+F62 -> 3763442.7 | H62: =G62/$C$31 -> 0.098164693
B63: F2 | C63: Founder (CTO) | D63: =Assumptions!$C$32-C56 -> 2352151.7 | E63: — | F63: 0 | G63: =D63+F63 -> 2352151.7 | H63: =G63/$C$31 -> 0.061352933
B64: F3 | C64: Founder (CSci) | D64: =Assumptions!$C$33-C57 -> 1411291 | E64: — | F64: 0 | G64: =D64+F64 -> 1411291 | H64: =G64/$C$31 -> 0.03681176
B65: Employees E1-E10 | C65: Employee RSAs | D65: =Assumptions!$C$34 -> 1000000 | E65: — | F65: 0 | G65: =D65+F65 -> 1000000 | H65: =G65/$C$31 -> 0.026083748
B66: SEED1 | C66: Seed LP | D66: 0 | E66: Seed | F66: =G40 -> 5000000 | G66: =D66+F66 -> 5000000 | H66: =G66/$C$31 -> 0.13041874
B67: A1 | C67: Series A LP | D67: 0 | E67: Series A | F67: =G41 -> 5000000 | G67: =D67+F67 -> 5000000 | H67: =G67/$C$31 -> 0.13041874
B68: B1 | C68: Series B LP | D68: 0 | E68: Series B | F68: =G42 -> 3000000 | G68: =D68+F68 -> 3000000 | H68: =G68/$C$31 -> 0.078251245
B69: C1 | C69: Series C LP | D69: 0 | E69: Series C | F69: =G43 -> 2400000 | G69: =D69+F69 -> 2400000 | H69: =G69/$C$31 -> 0.062600996
B70: D1 | C70: Series D LP | D70: 0 | E70: Series D | F70: =G44 -> 1733976.9 | G70: =D70+F70 -> 1733976.9 | H70: =G70/$C$31 -> 0.045228618
B71: E1-E10_INV | C71: Series E LPs | D71: 0 | E71: Series E | F71: =G45 -> 6134472.1 | G71: =D71+F71 -> 6134472.1 | H71: =G71/$C$31 -> 0.16001003
B72: NA1 | C72: Note A holder | D72: =G49 -> 186735.09 | E72: Common (note) | F72: 0 | G72: =D72+F72 -> 186735.09 | H72: =G72/$C$31 -> 0.0048707511
B73: NB1 | C73: Note B holder | D73: =G50 -> 94622.908 | E73: Common (note) | F73: 0 | G73: =D73+F73 -> 94622.908 | H73: =G73/$C$31 -> 0.0024681201
B74: F_LEAD | C74: Series F lead | D74: =C58 -> 473114.54 | E74: Series F | F74: =Assumptions!$C$12/C28 -> 536196.48 | G74: =D74+F74 -> 1009311 | H74: =G74/$C$31 -> 0.026326615
B75: F_FUND (our fund) | C75: Series F primary | D75: 0 | E75: Series F | F75: =Assumptions!$C$11/C28 -> 268098.24 | G75: =D75+F75 -> 268098.24 | H75: =G75/$C$31 -> 0.006993007
B76: Issued options | C76: Employee options | D76: =Assumptions!$C$42 -> 2500000 | E76: Options | F76: 0 | G76: =D76+F76 -> 2500000 | H76: =G76/$C$31 -> 0.065209371
B77: Unissued option pool | C77: ESOP unissued + top-up | D77: =Assumptions!$C$43+C32 -> 2483946.2 | E77: Options | F77: 0 | G77: =D77+F77 -> 2483946.2 | H77: =G77/$C$31 -> 0.064790629
B78: Total | D78: =SUM(D62:D77) -> 14265304 | F78: =SUM(F62:F77) -> 24072744 | G78: =SUM(G62:G77) -> 38338048 | H78: =SUM(H62:H77) -> 1
B79: Check | G79: =ROUND(G78-C31,2) -> 0

Sheet Waterfall
B2: Kelvin Dynamics — Waterfall
B3: 1× non-participating with conversion election. Notes ride convert. Game-theoretic Nash equilibrium per exit.
B5: Exit Scenarios ($M)
B6: Exit value ($) | C6: =Assumptions!$C$15 -> 700000000 | D6: =Assumptions!$C$16 -> 1200000000 | E6: =Assumptions!$C$17 -> 2000000000 | F6: =Assumptions!$C$18 -> 4000000000 | G6: =Assumptions!$C$19 -> 8000000000
B7: + Issued option strike cash | C7: ='Pro-Forma'!$D$76*Assumptions!$C$55 -> 2500000 | D7: ='Pro-Forma'!$D$76*Assumptions!$C$55 -> 2500000 | E7: ='Pro-Forma'!$D$76*Assumptions!$C$55 -> 2500000 | F7: ='Pro-Forma'!$D$76*Assumptions!$C$55 -> 2500000 | G7: ='Pro-Forma'!$D$76*Assumptions!$C$55 -> 2500000
B8: Distributable to equity ($) | C8: =C6+C7 -> 702500000 | D8: =D6+D7 -> 1202500000 | E8: =E6+E7 -> 2002500000 | F8: =F6+F7 -> 4002500000 | G8: =G6+G7 -> 8002500000
B10: Per-Class Election (Nash equilibrium)
B11: Series F | C11: =IF(H43,"preference","convert") -> preference | D11: =IF(H65,"preference","convert") -> preference | E11: =IF(H87,"preference","convert") -> convert | F11: =IF(H109,"preference","convert") -> convert | G11: =IF(H131,"preference","convert") -> convert
B12: Series E | C12: =IF(H44,"preference","convert") -> preference | D12: =IF(H66,"preference","convert") -> preference | E12: =IF(H88,"preference","convert") -> convert | F12: =IF(H110,"preference","convert") -> convert | G12: =IF(H132,"preference","convert") -> convert
B13: Series D | C13: =IF(H45,"preference","convert") -> preference | D13: =IF(H67,"preference","convert") -> preference | E13: =IF(H89,"preference","convert") -> preference | F13: =IF(H111,"preference","convert") -> convert | G13: =IF(H133,"preference","convert") -> convert
B14: Series C | C14: =IF(H46,"preference","convert") -> preference | D14: =IF(H68,"preference","convert") -> convert | E14: =IF(H90,"preference","convert") -> convert | F14: =IF(H112,"preference","convert") -> convert | G14: =IF(H134,"preference","convert") -> convert
B15: Series B | C15: =IF(H47,"preference","convert") -> preference | D15: =IF(H69,"preference","convert") -> convert | E15: =IF(H91,"preference","convert") -> convert | F15: =IF(H113,"preference","convert") -> convert | G15: =IF(H135,"preference","convert") -> convert
B16: Series A | C16: =IF(H48,"preference","convert") -> convert | D16: =IF(H70,"preference","convert") -> convert | E16: =IF(H92,"preference","convert") -> convert | F16: =IF(H114,"preference","convert") -> convert | G16: =IF(H136,"preference","convert") -> convert
B17: Seed | C17: =IF(H49,"preference","convert") -> convert | D17: =IF(H71,"preference","convert") -> convert | E17: =IF(H93,"preference","convert") -> convert | F17: =IF(H115,"preference","convert") -> convert | G17: =IF(H137,"preference","convert") -> convert
B19: Per-Class Proceeds ($)
B20: Series F | C20: =IF(H43,Assumptions!$C$7,'Pro-Forma'!$C$29*H53) -> 30000000 | D20: =IF(H65,Assumptions!$C$7,'Pro-Forma'!$C$29*H75) -> 30000000 | E20: =IF(H87,Assumptions!$C$7,'Pro-Forma'!$C$29*H97) -> 44846573 | F20: =IF(H109,Assumptions!$C$7,'Pro-Forma'!$C$29*H119) -> 89785811 | G20: =IF(H131,Assumptions!$C$7,'Pro-Forma'!$C$29*H141) -> 1.7951554e+08
B21: Series E | C21: =IF(H44,Assumptions!$C$41*Assumptions!$C$28,'Pro-Forma'!$G$45*H53) -> 2.999968e+08 | D21: =IF(H66,Assumptions!$C$41*Assumptions!$C$28,'Pro-Forma'!$G$45*H75) -> 2.999968e+08 | E21: =IF(H88,Assumptions!$C$41*Assumptions!$C$28,'Pro-Forma'!$G$45*H97) -> 3.420513e+08 | F21: =IF(H110,Assumptions!$C$41*Assumptions!$C$28,'Pro-Forma'!$G$45*H119) -> 6.8480937e+08 | G21: =IF(H132,Assumptions!$C$41*Assumptions!$C$28,'Pro-Forma'!$G$45*H141) -> 1.369191e+09
B22: Series D | C22: =IF(H45,Assumptions!$C$40*Assumptions!$C$27,'Pro-Forma'!$G$44*H53) -> 100000020 | D22: =IF(H67,Assumptions!$C$40*Assumptions!$C$27,'Pro-Forma'!$G$44*H75) -> 100000020 | E22: =IF(H89,Assumptions!$C$40*Assumptions!$C$27,'Pro-Forma'!$G$44*H97) -> 100000020 | F22: =IF(H111,Assumptions!$C$40*Assumptions!$C$27,'Pro-Forma'!$G$44*H119) -> 1.93569e+08 | G22: =IF(H133,Assumptions!$C$40*Assumptions!$C$27,'Pro-Forma'!$G$44*H141) -> 3.870171e+08
B23: Series C | C23: =IF(H46,Assumptions!$C$38*Assumptions!$C$25,'Pro-Forma'!$G$43*H53) -> 60000000 | D23: =IF(H68,Assumptions!$C$38*Assumptions!$C$25,'Pro-Forma'!$G$43*H75) -> 68208793 | E23: =IF(H90,Assumptions!$C$38*Assumptions!$C$25,'Pro-Forma'!$G$43*H97) -> 1.3382131e+08 | F23: =IF(H112,Assumptions!$C$38*Assumptions!$C$25,'Pro-Forma'!$G$43*H119) -> 2.6791914e+08 | G23: =IF(H134,Assumptions!$C$38*Assumptions!$C$25,'Pro-Forma'!$G$43*H141) -> 5.3567093e+08
B24: Series B | C24: =IF(H47,Assumptions!$C$37*Assumptions!$C$24,'Pro-Forma'!$G$42*H53) -> 30000000 | D24: =IF(H69,Assumptions!$C$37*Assumptions!$C$24,'Pro-Forma'!$G$42*H75) -> 85260991 | E24: =IF(H91,Assumptions!$C$37*Assumptions!$C$24,'Pro-Forma'!$G$42*H97) -> 1.6727664e+08 | F24: =IF(H113,Assumptions!$C$37*Assumptions!$C$24,'Pro-Forma'!$G$42*H119) -> 3.3489892e+08 | G24: =IF(H135,Assumptions!$C$37*Assumptions!$C$24,'Pro-Forma'!$G$42*H141) -> 6.6958866e+08
B25: Series A | C25: =IF(H48,Assumptions!$C$36*Assumptions!$C$23,'Pro-Forma'!$G$41*H53) -> 41894352 | D25: =IF(H70,Assumptions!$C$36*Assumptions!$C$23,'Pro-Forma'!$G$41*H75) -> 1.4210165e+08 | E25: =IF(H92,Assumptions!$C$36*Assumptions!$C$23,'Pro-Forma'!$G$41*H97) -> 2.787944e+08 | F25: =IF(H114,Assumptions!$C$36*Assumptions!$C$23,'Pro-Forma'!$G$41*H119) -> 5.5816487e+08 | G25: =IF(H136,Assumptions!$C$36*Assumptions!$C$23,'Pro-Forma'!$G$41*H141) -> 1.1159811e+09
B26: Seed | C26: =IF(H49,Assumptions!$C$35*Assumptions!$C$22,'Pro-Forma'!$G$40*H53) -> 41894352 | D26: =IF(H71,Assumptions!$C$35*Assumptions!$C$22,'Pro-Forma'!$G$40*H75) -> 1.4210165e+08 | E26: =IF(H93,Assumptions!$C$35*Assumptions!$C$22,'Pro-Forma'!$G$40*H97) -> 2.787944e+08 | F26: =IF(H115,Assumptions!$C$35*Assumptions!$C$22,'Pro-Forma'!$G$40*H119) -> 5.5816487e+08 | G26: =IF(H137,Assumptions!$C$35*Assumptions!$C$22,'Pro-Forma'!$G$40*H141) -> 1.1159811e+09
B27: Notes (combined A+B) | C27: =('Pro-Forma'!$G$49+'Pro-Forma'!$G$50)*H53 -> 2357462.2 | D27: =('Pro-Forma'!$G$49+'Pro-Forma'!$G$50)*H75 -> 7996287.3 | E27: =('Pro-Forma'!$G$49+'Pro-Forma'!$G$50)*H97 -> 15688207 | F27: =('Pro-Forma'!$G$49+'Pro-Forma'!$G$50)*H119 -> 31408830 | G27: =('Pro-Forma'!$G$49+'Pro-Forma'!$G$50)*H141 -> 62798042
B28: Common + RSAs (founders, employees, F_LEAD secondary) | C28: =('Pro-Forma'!$D$62+'Pro-Forma'!$D$63+'Pro-Forma'!$D$64+'Pro-Forma'!$D$65+'Pro-Forma'!$D$74)*H53 -> 75409834 | D28: =('Pro-Forma'!$D$62+'Pro-Forma'!$D$63+'Pro-Forma'!$D$64+'Pro-Forma'!$D$65+'Pro-Forma'!$D$74)*H75 -> 2.5578297e+08 | E28: =('Pro-Forma'!$D$62+'Pro-Forma'!$D$63+'Pro-Forma'!$D$64+'Pro-Forma'!$D$65+'Pro-Forma'!$D$74)*H97 -> 5.0182993e+08 | F28: =('Pro-Forma'!$D$62+'Pro-Forma'!$D$63+'Pro-Forma'!$D$64+'Pro-Forma'!$D$65+'Pro-Forma'!$D$74)*H119 -> 1.0046968e+09 | G28: =('Pro-Forma'!$D$62+'Pro-Forma'!$D$63+'Pro-Forma'!$D$64+'Pro-Forma'!$D$65+'Pro-Forma'!$D$74)*H141 -> 2.008766e+09
B29: Issued options (net of strike, ITM) | C29: =IF(H53>Assumptions!$C$55,'Pro-Forma'!$D$76*(H53-Assumptions!$C$55),0) -> 18447176 | D29: =IF(H75>Assumptions!$C$55,'Pro-Forma'!$D$76*(H75-Assumptions!$C$55),0) -> 68550826 | E29: =IF(H97>Assumptions!$C$55,'Pro-Forma'!$D$76*(H97-Assumptions!$C$55),0) -> 1.368972e+08 | F29: =IF(H119>Assumptions!$C$55,'Pro-Forma'!$D$76*(H119-Assumptions!$C$55),0) -> 2.7658243e+08 | G29: =IF(H141>Assumptions!$C$55,'Pro-Forma'!$D$76*(H141-Assumptions!$C$55),0) -> 5.5549055e+08
B30: Total to all stakeholders | C30: =SUM(C20:C29) -> 700000000 | D30: =SUM(D20:D29) -> 1200000000 | E30: =SUM(E20:E29) -> 2e+09 | F30: =SUM(F20:F29) -> 4000000000 | G30: =SUM(G20:G29) -> 8e+09
B31: Check (vs. exit value) | C31: =ROUND(C30-C6,0) -> 0 | D31: =ROUND(D30-D6,0) -> 0 | E31: =ROUND(E30-E6,0) -> 0 | F31: =ROUND(F30-F6,0) -> 0 | G31: =ROUND(G30-G6,0) -> 0
B40: Exit 1 Nash Solver — iterative best response
B41: Iteration | C41: Iter 0 | D41: Iter 1 | E41: Iter 2 | F41: Iter 3 | G41: Iter 4 | H41: Iter 5
B42: Distributable ($) | C42: =C$8 -> 702500000 | D42: =C$8 -> 702500000 | E42: =C$8 -> 702500000 | F42: =C$8 -> 702500000 | G42: =C$8 -> 702500000 | H42: =C$8 -> 702500000
B43: F_takes_pref | C43: FALSE | D43: =Assumptions!$C$7>C54 -> 1 | E43: =Assumptions!$C$7>D54 -> 1 | F43: =Assumptions!$C$7>E54 -> 1 | G43: =Assumptions!$C$7>F54 -> 1 | H43: =Assumptions!$C$7>G54 -> 1
B44: E_takes_pref | C44: FALSE | D44: =Assumptions!$C$41*Assumptions!$C$28>C55 -> 1 | E44: =Assumptions!$C$41*Assumptions!$C$28>D55 -> 1 | F44: =Assumptions!$C$41*Assumptions!$C$28>E55 -> 1 | G44: =Assumptions!$C$41*Assumptions!$C$28>F55 -> 1 | H44: =Assumptions!$C$41*Assumptions!$C$28>G55 -> 1
B45: D_takes_pref | C45: FALSE | D45: =Assumptions!$C$40*Assumptions!$C$27>C56 -> 1 | E45: =Assumptions!$C$40*Assumptions!$C$27>D56 -> 1 | F45: =Assumptions!$C$40*Assumptions!$C$27>E56 -> 1 | G45: =Assumptions!$C$40*Assumptions!$C$27>F56 -> 1 | H45: =Assumptions!$C$40*Assumptions!$C$27>G56 -> 1
B46: C_takes_pref | C46: FALSE | D46: =Assumptions!$C$38*Assumptions!$C$25>C57 -> 1 | E46: =Assumptions!$C$38*Assumptions!$C$25>D57 -> 1 | F46: =Assumptions!$C$38*Assumptions!$C$25>E57 -> 1 | G46: =Assumptions!$C$38*Assumptions!$C$25>F57 -> 1 | H46: =Assumptions!$C$38*Assumptions!$C$25>G57 -> 1
B47: B_takes_pref | C47: FALSE | D47: =Assumptions!$C$37*Assumptions!$C$24>C58 -> 0 | E47: =Assumptions!$C$37*Assumptions!$C$24>D58 -> 1 | F47: =Assumptions!$C$37*Assumptions!$C$24>E58 -> 1 | G47: =Assumptions!$C$37*Assumptions!$C$24>F58 -> 1 | H47: =Assumptions!$C$37*Assumptions!$C$24>G58 -> 1
B48: A_takes_pref | C48: FALSE | D48: =Assumptions!$C$36*Assumptions!$C$23>C59 -> 0 | E48: =Assumptions!$C$36*Assumptions!$C$23>D59 -> 0 | F48: =Assumptions!$C$36*Assumptions!$C$23>E59 -> 0 | G48: =Assumptions!$C$36*Assumptions!$C$23>F59 -> 0 | H48: =Assumptions!$C$36*Assumptions!$C$23>G59 -> 0
B49: Seed_takes_pref | C49: FALSE | D49: =Assumptions!$C$35*Assumptions!$C$22>C60 -> 0 | E49: =Assumptions!$C$35*Assumptions!$C$22>D60 -> 0 | F49: =Assumptions!$C$35*Assumptions!$C$22>E60 -> 0 | G49: =Assumptions!$C$35*Assumptions!$C$22>F60 -> 0 | H49: =Assumptions!$C$35*Assumptions!$C$22>G60 -> 0
B50: Sum prefs taken | C50: =IF(C43,Assumptions!$C$7,0)+IF(C44,Assumptions!$C$41*Assumptions!$C$28,0)+IF(C45,Assumptions!$C$40*Assumptions!$C$27,0)+IF(C46,Assumptions!$C$38*Assumptions!$C$25,0)+IF(C47,Assumptions!$C$37*Assumptions!$C$24,0)+IF(C48,Assumptions!$C$36*Assumptions!$C$23,0)+IF(C49,Assumptions!$C$35*Assumptions!$C$22,0) -> 0 | D50: =IF(D43,Assumptions!$C$7,0)+IF(D44,Assumptions!$C$41*Assumptions!$C$28,0)+IF(D45,Assumptions!$C$40*Assumptions!$C$27,0)+IF(D46,Assumptions!$C$38*Assumptions!$C$25,0)+IF(D47,Assumptions!$C$37*Assumptions!$C$24,0)+IF(D48,Assumptions!$C$36*Assumptions!$C$23,0)+IF(D49,Assumptions!$C$35*Assumptions!$C$22,0) -> 4.8999682e+08 | E50: =IF(E43,Assumptions!$C$7,0)+IF(E44,Assumptions!$C$41*Assumptions!$C$28,0)+IF(E45,Assumptions!$C$40*Assumptions!$C$27,0)+IF(E46,Assumptions!$C$38*Assumptions!$C$25,0)+IF(E47,Assumptions!$C$37*Assumptions!$C$24,0)+IF(E48,Assumptions!$C$36*Assumptions!$C$23,0)+IF(E49,Assumptions!$C$35*Assumptions!$C$22,0) -> 5.1999682e+08 | F50: =IF(F43,Assumptions!$C$7,0)+IF(F44,Assumptions!$C$41*Assumptions!$C$28,0)+IF(F45,Assumptions!$C$40*Assumptions!$C$27,0)+IF(F46,Assumptions!$C$38*Assumptions!$C$25,0)+IF(F47,Assumptions!$C$37*Assumptions!$C$24,0)+IF(F48,Assumptions!$C$36*Assumptions!$C$23,0)+IF(F49,Assumptions!$C$35*Assumptions!$C$22,0) -> 5.1999682e+08 | G50: =IF(G43,Assumptions!$C$7,0)+IF(G44,Assumptions!$C$41*Assumptions!$C$28,0)+IF(G45,Assumptions!$C$40*Assumptions!$C$27,0)+IF(G46,Assumptions!$C$38*Assumptions!$C$25,0)+IF(G47,Assumptions!$C$37*Assumptions!$C$24,0)+IF(G48,Assumptions!$C$36*Assumptions!$C$23,0)+IF(G49,Assumptions!$C$35*Assumptions!$C$22,0) -> 5.1999682e+08 | H50: =IF(H43,Assumptions!$C$7,0)+IF(H44,Assumptions!$C$41*Assumptions!$C$28,0)+IF(H45,Assumptions!$C$40*Assumptions!$C$27,0)+IF(H46,Assumptions!$C$38*Assumptions!$C$25,0)+IF(H47,Assumptions!$C$37*Assumptions!$C$24,0)+IF(H48,Assumptions!$C$36*Assumptions!$C$23,0)+IF(H49,Assumptions!$C$35*Assumptions!$C$22,0) -> 5.1999682e+08
B51: Convert pool (shares) | C51: =IF(C43,0,'Pro-Forma'!$C$29)+IF(C44,0,'Pro-Forma'!$G$45)+IF(C45,0,'Pro-Forma'!$G$44)+IF(C46,0,'Pro-Forma'!$G$43)+IF(C47,0,'Pro-Forma'!$G$42)+IF(C48,0,'Pro-Forma'!$G$41)+IF(C49,0,'Pro-Forma'!$G$40)+('Pro-Forma'!$D$62+'Pro-Forma'!$D$63+'Pro-Forma'!$D$64+'Pro-Forma'!$D$65+'Pro-Forma'!$D$74+'Pro-Forma'!$G$49+'Pro-Forma'!$G$50+'Pro-Forma'!$D$76) -> 35854102 | D51: =IF(D43,0,'Pro-Forma'!$C$29)+IF(D44,0,'Pro-Forma'!$G$45)+IF(D45,0,'Pro-Forma'!$G$44)+IF(D46,0,'Pro-Forma'!$G$43)+IF(D47,0,'Pro-Forma'!$G$42)+IF(D48,0,'Pro-Forma'!$G$41)+IF(D49,0,'Pro-Forma'!$G$40)+('Pro-Forma'!$D$62+'Pro-Forma'!$D$63+'Pro-Forma'!$D$64+'Pro-Forma'!$D$65+'Pro-Forma'!$D$74+'Pro-Forma'!$G$49+'Pro-Forma'!$G$50+'Pro-Forma'!$D$76) -> 24781358 | E51: =IF(E43,0,'Pro-Forma'!$C$29)+IF(E44,0,'Pro-Forma'!$G$45)+IF(E45,0,'Pro-Forma'!$G$44)+IF(E46,0,'Pro-Forma'!$G$43)+IF(E47,0,'Pro-Forma'!$G$42)+IF(E48,0,'Pro-Forma'!$G$41)+IF(E49,0,'Pro-Forma'!$G$40)+('Pro-Forma'!$D$62+'Pro-Forma'!$D$63+'Pro-Forma'!$D$64+'Pro-Forma'!$D$65+'Pro-Forma'!$D$74+'Pro-Forma'!$G$49+'Pro-Forma'!$G$50+'Pro-Forma'!$D$76) -> 21781358 | F51: =IF(F43,0,'Pro-Forma'!$C$29)+IF(F44,0,'Pro-Forma'!$G$45)+IF(F45,0,'Pro-Forma'!$G$44)+IF(F46,0,'Pro-Forma'!$G$43)+IF(F47,0,'Pro-Forma'!$G$42)+IF(F48,0,'Pro-Forma'!$G$41)+IF(F49,0,'Pro-Forma'!$G$40)+('Pro-Forma'!$D$62+'Pro-Forma'!$D$63+'Pro-Forma'!$D$64+'Pro-Forma'!$D$65+'Pro-Forma'!$D$74+'Pro-Forma'!$G$49+'Pro-Forma'!$G$50+'Pro-Forma'!$D$76) -> 21781358 | G51: =IF(G43,0,'Pro-Forma'!$C$29)+IF(G44,0,'Pro-Forma'!$G$45)+IF(G45,0,'Pro-Forma'!$G$44)+IF(G46,0,'Pro-Forma'!$G$43)+IF(G47,0,'Pro-Forma'!$G$42)+IF(G48,0,'Pro-Forma'!$G$41)+IF(G49,0,'Pro-Forma'!$G$40)+('Pro-Forma'!$D$62+'Pro-Forma'!$D$63+'Pro-Forma'!$D$64+'Pro-Forma'!$D$65+'Pro-Forma'!$D$74+'Pro-Forma'!$G$49+'Pro-Forma'!$G$50+'Pro-Forma'!$D$76) -> 21781358 | H51: =IF(H43,0,'Pro-Forma'!$C$29)+IF(H44,0,'Pro-Forma'!$G$45)+IF(H45,0,'Pro-Forma'!$G$44)+IF(H46,0,'Pro-Forma'!$G$43)+IF(H47,0,'Pro-Forma'!$G$42)+IF(H48,0,'Pro-Forma'!$G$41)+IF(H49,0,'Pro-Forma'!$G$40)+('Pro-Forma'!$D$62+'Pro-Forma'!$D$63+'Pro-Forma'!$D$64+'Pro-Forma'!$D$65+'Pro-Forma'!$D$74+'Pro-Forma'!$G$49+'Pro-Forma'!$G$50+'Pro-Forma'!$D$76) -> 21781358
B52: Residual ($) | C52: =C42-C50 -> 702500000 | D52: =D42-D50 -> 2.1250318e+08 | E52: =E42-E50 -> 1.8250318e+08 | F52: =F42-F50 -> 1.8250318e+08 | G52: =G42-G50 -> 1.8250318e+08 | H52: =H42-H50 -> 1.8250318e+08
B53: Common PPS at exit ($) | C53: =C52/C51 -> 19.593295 | D53: =D52/D51 -> 8.5751224 | E53: =E52/E51 -> 8.3788705 | F53: =F52/F51 -> 8.3788705 | G53: =G52/G51 -> 8.3788705 | H53: =H52/H51 -> 8.3788705
B54: F_convert_$ | C54: ='Pro-Forma'!$C$29*C53 -> 15758784 | D54: ='Pro-Forma'!$C$29*D53 -> 6896925.6 | E54: ='Pro-Forma'!$C$29*E53 -> 6739081.2 | F54: ='Pro-Forma'!$C$29*F53 -> 6739081.2 | G54: ='Pro-Forma'!$C$29*G53 -> 6739081.2 | H54: ='Pro-Forma'!$C$29*H53 -> 6739081.2
B55: E_convert_$ | C55: ='Pro-Forma'!$G$45*C53 -> 1.2019452e+08 | D55: ='Pro-Forma'!$G$45*D53 -> 52603849 | E55: ='Pro-Forma'!$G$45*E53 -> 51399947 | F55: ='Pro-Forma'!$G$45*F53 -> 51399947 | G55: ='Pro-Forma'!$G$45*G53 -> 51399947 | H55: ='Pro-Forma'!$G$45*H53 -> 51399947
B56: D_convert_$ | C56: ='Pro-Forma'!$G$44*C53 -> 33974322 | D56: ='Pro-Forma'!$G$44*D53 -> 14869064 | E56: ='Pro-Forma'!$G$44*E53 -> 14528768 | F56: ='Pro-Forma'!$G$44*F53 -> 14528768 | G56: ='Pro-Forma'!$G$44*G53 -> 14528768 | H56: ='Pro-Forma'!$G$44*H53 -> 14528768
B57: C_convert_$ | C57: ='Pro-Forma'!$G$43*C53 -> 47023908 | D57: ='Pro-Forma'!$G$43*D53 -> 20580294 | E57: ='Pro-Forma'!$G$43*E53 -> 20109289 | F57: ='Pro-Forma'!$G$43*F53 -> 20109289 | G57: ='Pro-Forma'!$G$43*G53 -> 20109289 | H57: ='Pro-Forma'!$G$43*H53 -> 20109289
B58: B_convert_$ | C58: ='Pro-Forma'!$G$42*C53 -> 58779886 | D58: ='Pro-Forma'!$G$42*D53 -> 25725367 | E58: ='Pro-Forma'!$G$42*E53 -> 25136611 | F58: ='Pro-Forma'!$G$42*F53 -> 25136611 | G58: ='Pro-Forma'!$G$42*G53 -> 25136611 | H58: ='Pro-Forma'!$G$42*H53 -> 25136611
B59: A_convert_$ | C59: ='Pro-Forma'!$G$41*C53 -> 97966476 | D59: ='Pro-Forma'!$G$41*D53 -> 42875612 | E59: ='Pro-Forma'!$G$41*E53 -> 41894352 | F59: ='Pro-Forma'!$G$41*F53 -> 41894352 | G59: ='Pro-Forma'!$G$41*G53 -> 41894352 | H59: ='Pro-Forma'!$G$41*H53 -> 41894352
B60: Seed_convert_$ | C60: ='Pro-Forma'!$G$40*C53 -> 97966476 | D60: ='Pro-Forma'!$G$40*D53 -> 42875612 | E60: ='Pro-Forma'!$G$40*E53 -> 41894352 | F60: ='Pro-Forma'!$G$40*F53 -> 41894352 | G60: ='Pro-Forma'!$G$40*G53 -> 41894352 | H60: ='Pro-Forma'!$G$40*H53 -> 41894352
B62: Exit 2 Nash Solver — iterative best response
B63: Iteration | C63: Iter 0 | D63: Iter 1 | E63: Iter 2 | F63: Iter 3 | G63: Iter 4 | H63: Iter 5
B64: Distributable ($) | C64: =D$8 -> 1202500000 | D64: =D$8 -> 1202500000 | E64: =D$8 -> 1202500000 | F64: =D$8 -> 1202500000 | G64: =D$8 -> 1202500000 | H64: =D$8 -> 1202500000
B65: F_takes_pref | C65: FALSE | D65: =Assumptions!$C$7>C76 -> 1 | E65: =Assumptions!$C$7>D76 -> 1 | F65: =Assumptions!$C$7>E76 -> 1 | G65: =Assumptions!$C$7>F76 -> 1 | H65: =Assumptions!$C$7>G76 -> 1
B66: E_takes_pref | C66: FALSE | D66: =Assumptions!$C$41*Assumptions!$C$28>C77 -> 1 | E66: =Assumptions!$C$41*Assumptions!$C$28>D77 -> 1 | F66: =Assumptions!$C$41*Assumptions!$C$28>E77 -> 1 | G66: =Assumptions!$C$41*Assumptions!$C$28>F77 -> 1 | H66: =Assumptions!$C$41*Assumptions!$C$28>G77 -> 1
B67: D_takes_pref | C67: FALSE | D67: =Assumptions!$C$40*Assumptions!$C$27>C78 -> 1 | E67: =Assumptions!$C$40*Assumptions!$C$27>D78 -> 1 | F67: =Assumptions!$C$40*Assumptions!$C$27>E78 -> 1 | G67: =Assumptions!$C$40*Assumptions!$C$27>F78 -> 1 | H67: =Assumptions!$C$40*Assumptions!$C$27>G78 -> 1
B68: C_takes_pref | C68: FALSE | D68: =Assumptions!$C$38*Assumptions!$C$25>C79 -> 0 | E68: =Assumptions!$C$38*Assumptions!$C$25>D79 -> 0 | F68: =Assumptions!$C$38*Assumptions!$C$25>E79 -> 0 | G68: =Assumptions!$C$38*Assumptions!$C$25>F79 -> 0 | H68: =Assumptions!$C$38*Assumptions!$C$25>G79 -> 0
B69: B_takes_pref | C69: FALSE | D69: =Assumptions!$C$37*Assumptions!$C$24>C80 -> 0 | E69: =Assumptions!$C$37*Assumptions!$C$24>D80 -> 0 | F69: =Assumptions!$C$37*Assumptions!$C$24>E80 -> 0 | G69: =Assumptions!$C$37*Assumptions!$C$24>F80 -> 0 | H69: =Assumptions!$C$37*Assumptions!$C$24>G80 -> 0
B70: A_takes_pref | C70: FALSE | D70: =Assumptions!$C$36*Assumptions!$C$23>C81 -> 0 | E70: =Assumptions!$C$36*Assumptions!$C$23>D81 -> 0 | F70: =Assumptions!$C$36*Assumptions!$C$23>E81 -> 0 | G70: =Assumptions!$C$36*Assumptions!$C$23>F81 -> 0 | H70: =Assumptions!$C$36*Assumptions!$C$23>G81 -> 0
B71: Seed_takes_pref | C71: FALSE | D71: =Assumptions!$C$35*Assumptions!$C$22>C82 -> 0 | E71: =Assumptions!$C$35*Assumptions!$C$22>D82 -> 0 | F71: =Assumptions!$C$35*Assumptions!$C$22>E82 -> 0 | G71: =Assumptions!$C$35*Assumptions!$C$22>F82 -> 0 | H71: =Assumptions!$C$35*Assumptions!$C$22>G82 -> 0
B72: Sum prefs taken | C72: =IF(C65,Assumptions!$C$7,0)+IF(C66,Assumptions!$C$41*Assumptions!$C$28,0)+IF(C67,Assumptions!$C$40*Assumptions!$C$27,0)+IF(C68,Assumptions!$C$38*Assumptions!$C$25,0)+IF(C69,Assumptions!$C$37*Assumptions!$C$24,0)+IF(C70,Assumptions!$C$36*Assumptions!$C$23,0)+IF(C71,Assumptions!$C$35*Assumptions!$C$22,0) -> 0 | D72: =IF(D65,Assumptions!$C$7,0)+IF(D66,Assumptions!$C$41*Assumptions!$C$28,0)+IF(D67,Assumptions!$C$40*Assumptions!$C$27,0)+IF(D68,Assumptions!$C$38*Assumptions!$C$25,0)+IF(D69,Assumptions!$C$37*Assumptions!$C$24,0)+IF(D70,Assumptions!$C$36*Assumptions!$C$23,0)+IF(D71,Assumptions!$C$35*Assumptions!$C$22,0) -> 4.2999682e+08 | E72: =IF(E65,Assumptions!$C$7,0)+IF(E66,Assumptions!$C$41*Assumptions!$C$28,0)+IF(E67,Assumptions!$C$40*Assumptions!$C$27,0)+IF(E68,Assumptions!$C$38*Assumptions!$C$25,0)+IF(E69,Assumptions!$C$37*Assumptions!$C$24,0)+IF(E70,Assumptions!$C$36*Assumptions!$C$23,0)+IF(E71,Assumptions!$C$35*Assumptions!$C$22,0) -> 4.2999682e+08 | F72: =IF(F65,Assumptions!$C$7,0)+IF(F66,Assumptions!$C$41*Assumptions!$C$28,0)+IF(F67,Assumptions!$C$40*Assumptions!$C$27,0)+IF(F68,Assumptions!$C$38*Assumptions!$C$25,0)+IF(F69,Assumptions!$C$37*Assumptions!$C$24,0)+IF(F70,Assumptions!$C$36*Assumptions!$C$23,0)+IF(F71,Assumptions!$C$35*Assumptions!$C$22,0) -> 4.2999682e+08 | G72: =IF(G65,Assumptions!$C$7,0)+IF(G66,Assumptions!$C$41*Assumptions!$C$28,0)+IF(G67,Assumptions!$C$40*Assumptions!$C$27,0)+IF(G68,Assumptions!$C$38*Assumptions!$C$25,0)+IF(G69,Assumptions!$C$37*Assumptions!$C$24,0)+IF(G70,Assumptions!$C$36*Assumptions!$C$23,0)+IF(G71,Assumptions!$C$35*Assumptions!$C$22,0) -> 4.2999682e+08 | H72: =IF(H65,Assumptions!$C$7,0)+IF(H66,Assumptions!$C$41*Assumptions!$C$28,0)+IF(H67,Assumptions!$C$40*Assumptions!$C$27,0)+IF(H68,Assumptions!$C$38*Assumptions!$C$25,0)+IF(H69,Assumptions!$C$37*Assumptions!$C$24,0)+IF(H70,Assumptions!$C$36*Assumptions!$C$23,0)+IF(H71,Assumptions!$C$35*Assumptions!$C$22,0) -> 4.2999682e+08
B73: Convert pool (shares) | C73: =IF(C65,0,'Pro-Forma'!$C$29)+IF(C66,0,'Pro-Forma'!$G$45)+IF(C67,0,'Pro-Forma'!$G$44)+IF(C68,0,'Pro-Forma'!$G$43)+IF(C69,0,'Pro-Forma'!$G$42)+IF(C70,0,'Pro-Forma'!$G$41)+IF(C71,0,'Pro-Forma'!$G$40)+('Pro-Forma'!$D$62+'Pro-Forma'!$D$63+'Pro-Forma'!$D$64+'Pro-Forma'!$D$65+'Pro-Forma'!$D$74+'Pro-Forma'!$G$49+'Pro-Forma'!$G$50+'Pro-Forma'!$D$76) -> 35854102 | D73: =IF(D65,0,'Pro-Forma'!$C$29)+IF(D66,0,'Pro-Forma'!$G$45)+IF(D67,0,'Pro-Forma'!$G$44)+IF(D68,0,'Pro-Forma'!$G$43)+IF(D69,0,'Pro-Forma'!$G$42)+IF(D70,0,'Pro-Forma'!$G$41)+IF(D71,0,'Pro-Forma'!$G$40)+('Pro-Forma'!$D$62+'Pro-Forma'!$D$63+'Pro-Forma'!$D$64+'Pro-Forma'!$D$65+'Pro-Forma'!$D$74+'Pro-Forma'!$G$49+'Pro-Forma'!$G$50+'Pro-Forma'!$D$76) -> 27181358 | E73: =IF(E65,0,'Pro-Forma'!$C$29)+IF(E66,0,'Pro-Forma'!$G$45)+IF(E67,0,'Pro-Forma'!$G$44)+IF(E68,0,'Pro-Forma'!$G$43)+IF(E69,0,'Pro-Forma'!$G$42)+IF(E70,0,'Pro-Forma'!$G$41)+IF(E71,0,'Pro-Forma'!$G$40)+('Pro-Forma'!$D$62+'Pro-Forma'!$D$63+'Pro-Forma'!$D$64+'Pro-Forma'!$D$65+'Pro-Forma'!$D$74+'Pro-Forma'!$G$49+'Pro-Forma'!$G$50+'Pro-Forma'!$D$76) -> 27181358 | F73: =IF(F65,0,'Pro-Forma'!$C$29)+IF(F66,0,'Pro-Forma'!$G$45)+IF(F67,0,'Pro-Forma'!$G$44)+IF(F68,0,'Pro-Forma'!$G$43)+IF(F69,0,'Pro-Forma'!$G$42)+IF(F70,0,'Pro-Forma'!$G$41)+IF(F71,0,'Pro-Forma'!$G$40)+('Pro-Forma'!$D$62+'Pro-Forma'!$D$63+'Pro-Forma'!$D$64+'Pro-Forma'!$D$65+'Pro-Forma'!$D$74+'Pro-Forma'!$G$49+'Pro-Forma'!$G$50+'Pro-Forma'!$D$76) -> 27181358 | G73: =IF(G65,0,'Pro-Forma'!$C$29)+IF(G66,0,'Pro-Forma'!$G$45)+IF(G67,0,'Pro-Forma'!$G$44)+IF(G68,0,'Pro-Forma'!$G$43)+IF(G69,0,'Pro-Forma'!$G$42)+IF(G70,0,'Pro-Forma'!$G$41)+IF(G71,0,'Pro-Forma'!$G$40)+('Pro-Forma'!$D$62+'Pro-Forma'!$D$63+'Pro-Forma'!$D$64+'Pro-Forma'!$D$65+'Pro-Forma'!$D$74+'Pro-Forma'!$G$49+'Pro-Forma'!$G$50+'Pro-Forma'!$D$76) -> 27181358 | H73: =IF(H65,0,'Pro-Forma'!$C$29)+IF(H66,0,'Pro-Forma'!$G$45)+IF(H67,0,'Pro-Forma'!$G$44)+IF(H68,0,'Pro-Forma'!$G$43)+IF(H69,0,'Pro-Forma'!$G$42)+IF(H70,0,'Pro-Forma'!$G$41)+IF(H71,0,'Pro-Forma'!$G$40)+('Pro-Forma'!$D$62+'Pro-Forma'!$D$63+'Pro-Forma'!$D$64+'Pro-Forma'!$D$65+'Pro-Forma'!$D$74+'Pro-Forma'!$G$49+'Pro-Forma'!$G$50+'Pro-Forma'!$D$76) -> 27181358
B74: Residual ($) | C74: =C64-C72 -> 1202500000 | D74: =D64-D72 -> 7.7250318e+08 | E74: =E64-E72 -> 7.7250318e+08 | F74: =F64-F72 -> 7.7250318e+08 | G74: =G64-G72 -> 7.7250318e+08 | H74: =H64-H72 -> 7.7250318e+08
B75: Common PPS at exit ($) | C75: =C74/C73 -> 33.538701 | D75: =D74/D73 -> 28.42033 | E75: =E74/E73 -> 28.42033 | F75: =F74/F73 -> 28.42033 | G75: =G74/G73 -> 28.42033 | H75: =H74/H73 -> 28.42033
B76: F_convert_$ | C76: ='Pro-Forma'!$C$29*C75 -> 26975000 | D76: ='Pro-Forma'!$C$29*D75 -> 22858322 | E76: ='Pro-Forma'!$C$29*E75 -> 22858322 | F76: ='Pro-Forma'!$C$29*F75 -> 22858322 | G76: ='Pro-Forma'!$C$29*G75 -> 22858322 | H76: ='Pro-Forma'!$C$29*H75 -> 22858322
B77: E_convert_$ | C77: ='Pro-Forma'!$G$45*C75 -> 2.0574223e+08 | D77: ='Pro-Forma'!$G$45*D75 -> 1.7434373e+08 | E77: ='Pro-Forma'!$G$45*E75 -> 1.7434373e+08 | F77: ='Pro-Forma'!$G$45*F75 -> 1.7434373e+08 | G77: ='Pro-Forma'!$G$45*G75 -> 1.7434373e+08 | H77: ='Pro-Forma'!$G$45*H75 -> 1.7434373e+08
B78: D_convert_$ | C78: ='Pro-Forma'!$G$44*C75 -> 58155334 | D78: ='Pro-Forma'!$G$44*D75 -> 49280198 | E78: ='Pro-Forma'!$G$44*E75 -> 49280198 | F78: ='Pro-Forma'!$G$44*F75 -> 49280198 | G78: ='Pro-Forma'!$G$44*G75 -> 49280198 | H78: ='Pro-Forma'!$G$44*H75 -> 49280198
B79: C_convert_$ | C79: ='Pro-Forma'!$G$43*C75 -> 80492882 | D79: ='Pro-Forma'!$G$43*D75 -> 68208793 | E79: ='Pro-Forma'!$G$43*E75 -> 68208793 | F79: ='Pro-Forma'!$G$43*F75 -> 68208793 | G79: ='Pro-Forma'!$G$43*G75 -> 68208793 | H79: ='Pro-Forma'!$G$43*H75 -> 68208793
B80: B_convert_$ | C80: ='Pro-Forma'!$G$42*C75 -> 1.006161e+08 | D80: ='Pro-Forma'!$G$42*D75 -> 85260991 | E80: ='Pro-Forma'!$G$42*E75 -> 85260991 | F80: ='Pro-Forma'!$G$42*F75 -> 85260991 | G80: ='Pro-Forma'!$G$42*G75 -> 85260991 | H80: ='Pro-Forma'!$G$42*H75 -> 85260991
B81: A_convert_$ | C81: ='Pro-Forma'!$G$41*C75 -> 1.6769351e+08 | D81: ='Pro-Forma'!$G$41*D75 -> 1.4210165e+08 | E81: ='Pro-Forma'!$G$41*E75 -> 1.4210165e+08 | F81: ='Pro-Forma'!$G$41*F75 -> 1.4210165e+08 | G81: ='Pro-Forma'!$G$41*G75 -> 1.4210165e+08 | H81: ='Pro-Forma'!$G$41*H75 -> 1.4210165e+08
B82: Seed_convert_$ | C82: ='Pro-Forma'!$G$40*C75 -> 1.6769351e+08 | D82: ='Pro-Forma'!$G$40*D75 -> 1.4210165e+08 | E82: ='Pro-Forma'!$G$40*E75 -> 1.4210165e+08 | F82: ='Pro-Forma'!$G$40*F75 -> 1.4210165e+08 | G82: ='Pro-Forma'!$G$40*G75 -> 1.4210165e+08 | H82: ='Pro-Forma'!$G$40*H75 -> 1.4210165e+08
B84: Exit 3 Nash Solver — iterative best response
B85: Iteration | C85: Iter 0 | D85: Iter 1 | E85: Iter 2 | F85: Iter 3 | G85: Iter 4 | H85: Iter 5
B86: Distributable ($) | C86: =E$8 -> 2002500000 | D86: =E$8 -> 2002500000 | E86: =E$8 -> 2002500000 | F86: =E$8 -> 2002500000 | G86: =E$8 -> 2002500000 | H86: =E$8 -> 2002500000
B87: F_takes_pref | C87: FALSE | D87: =Assumptions!$C$7>C98 -> 0 | E87: =Assumptions!$C$7>D98 -> 0 | F87: =Assumptions!$C$7>E98 -> 0 | G87: =Assumptions!$C$7>F98 -> 0 | H87: =Assumptions!$C$7>G98 -> 0
B88: E_takes_pref | C88: FALSE | D88: =Assumptions!$C$41*Assumptions!$C$28>C99 -> 0 | E88: =Assumptions!$C$41*Assumptions!$C$28>D99 -> 0 | F88: =Assumptions!$C$41*Assumptions!$C$28>E99 -> 0 | G88: =Assumptions!$C$41*Assumptions!$C$28>F99 -> 0 | H88: =Assumptions!$C$41*Assumptions!$C$28>G99 -> 0
B89: D_takes_pref | C89: FALSE | D89: =Assumptions!$C$40*Assumptions!$C$27>C100 -> 1 | E89: =Assumptions!$C$40*Assumptions!$C$27>D100 -> 1 | F89: =Assumptions!$C$40*Assumptions!$C$27>E100 -> 1 | G89: =Assumptions!$C$40*Assumptions!$C$27>F100 -> 1 | H89: =Assumptions!$C$40*Assumptions!$C$27>G100 -> 1
B90: C_takes_pref | C90: FALSE | D90: =Assumptions!$C$38*Assumptions!$C$25>C101 -> 0 | E90: =Assumptions!$C$38*Assumptions!$C$25>D101 -> 0 | F90: =Assumptions!$C$38*Assumptions!$C$25>E101 -> 0 | G90: =Assumptions!$C$38*Assumptions!$C$25>F101 -> 0 | H90: =Assumptions!$C$38*Assumptions!$C$25>G101 -> 0
B91: B_takes_pref | C91: FALSE | D91: =Assumptions!$C$37*Assumptions!$C$24>C102 -> 0 | E91: =Assumptions!$C$37*Assumptions!$C$24>D102 -> 0 | F91: =Assumptions!$C$37*Assumptions!$C$24>E102 -> 0 | G91: =Assumptions!$C$37*Assumptions!$C$24>F102 -> 0 | H91: =Assumptions!$C$37*Assumptions!$C$24>G102 -> 0
B92: A_takes_pref | C92: FALSE | D92: =Assumptions!$C$36*Assumptions!$C$23>C103 -> 0 | E92: =Assumptions!$C$36*Assumptions!$C$23>D103 -> 0 | F92: =Assumptions!$C$36*Assumptions!$C$23>E103 -> 0 | G92: =Assumptions!$C$36*Assumptions!$C$23>F103 -> 0 | H92: =Assumptions!$C$36*Assumptions!$C$23>G103 -> 0
B93: Seed_takes_pref | C93: FALSE | D93: =Assumptions!$C$35*Assumptions!$C$22>C104 -> 0 | E93: =Assumptions!$C$35*Assumptions!$C$22>D104 -> 0 | F93: =Assumptions!$C$35*Assumptions!$C$22>E104 -> 0 | G93: =Assumptions!$C$35*Assumptions!$C$22>F104 -> 0 | H93: =Assumptions!$C$35*Assumptions!$C$22>G104 -> 0
B94: Sum prefs taken | C94: =IF(C87,Assumptions!$C$7,0)+IF(C88,Assumptions!$C$41*Assumptions!$C$28,0)+IF(C89,Assumptions!$C$40*Assumptions!$C$27,0)+IF(C90,Assumptions!$C$38*Assumptions!$C$25,0)+IF(C91,Assumptions!$C$37*Assumptions!$C$24,0)+IF(C92,Assumptions!$C$36*Assumptions!$C$23,0)+IF(C93,Assumptions!$C$35*Assumptions!$C$22,0) -> 0 | D94: =IF(D87,Assumptions!$C$7,0)+IF(D88,Assumptions!$C$41*Assumptions!$C$28,0)+IF(D89,Assumptions!$C$40*Assumptions!$C$27,0)+IF(D90,Assumptions!$C$38*Assumptions!$C$25,0)+IF(D91,Assumptions!$C$37*Assumptions!$C$24,0)+IF(D92,Assumptions!$C$36*Assumptions!$C$23,0)+IF(D93,Assumptions!$C$35*Assumptions!$C$22,0) -> 100000020 | E94: =IF(E87,Assumptions!$C$7,0)+IF(E88,Assumptions!$C$41*Assumptions!$C$28,0)+IF(E89,Assumptions!$C$40*Assumptions!$C$27,0)+IF(E90,Assumptions!$C$38*Assumptions!$C$25,0)+IF(E91,Assumptions!$C$37*Assumptions!$C$24,0)+IF(E92,Assumptions!$C$36*Assumptions!$C$23,0)+IF(E93,Assumptions!$C$35*Assumptions!$C$22,0) -> 100000020 | F94: =IF(F87,Assumptions!$C$7,0)+IF(F88,Assumptions!$C$41*Assumptions!$C$28,0)+IF(F89,Assumptions!$C$40*Assumptions!$C$27,0)+IF(F90,Assumptions!$C$38*Assumptions!$C$25,0)+IF(F91,Assumptions!$C$37*Assumptions!$C$24,0)+IF(F92,Assumptions!$C$36*Assumptions!$C$23,0)+IF(F93,Assumptions!$C$35*Assumptions!$C$22,0) -> 100000020 | G94: =IF(G87,Assumptions!$C$7,0)+IF(G88,Assumptions!$C$41*Assumptions!$C$28,0)+IF(G89,Assumptions!$C$40*Assumptions!$C$27,0)+IF(G90,Assumptions!$C$38*Assumptions!$C$25,0)+IF(G91,Assumptions!$C$37*Assumptions!$C$24,0)+IF(G92,Assumptions!$C$36*Assumptions!$C$23,0)+IF(G93,Assumptions!$C$35*Assumptions!$C$22,0) -> 100000020 | H94: =IF(H87,Assumptions!$C$7,0)+IF(H88,Assumptions!$C$41*Assumptions!$C$28,0)+IF(H89,Assumptions!$C$40*Assumptions!$C$27,0)+IF(H90,Assumptions!$C$38*Assumptions!$C$25,0)+IF(H91,Assumptions!$C$37*Assumptions!$C$24,0)+IF(H92,Assumptions!$C$36*Assumptions!$C$23,0)+IF(H93,Assumptions!$C$35*Assumptions!$C$22,0) -> 100000020
B95: Convert pool (shares) | C95: =IF(C87,0,'Pro-Forma'!$C$29)+IF(C88,0,'Pro-Forma'!$G$45)+IF(C89,0,'Pro-Forma'!$G$44)+IF(C90,0,'Pro-Forma'!$G$43)+IF(C91,0,'Pro-Forma'!$G$42)+IF(C92,0,'Pro-Forma'!$G$41)+IF(C93,0,'Pro-Forma'!$G$40)+('Pro-Forma'!$D$62+'Pro-Forma'!$D$63+'Pro-Forma'!$D$64+'Pro-Forma'!$D$65+'Pro-Forma'!$D$74+'Pro-Forma'!$G$49+'Pro-Forma'!$G$50+'Pro-Forma'!$D$76) -> 35854102 | D95: =IF(D87,0,'Pro-Forma'!$C$29)+IF(D88,0,'Pro-Forma'!$G$45)+IF(D89,0,'Pro-Forma'!$G$44)+IF(D90,0,'Pro-Forma'!$G$43)+IF(D91,0,'Pro-Forma'!$G$42)+IF(D92,0,'Pro-Forma'!$G$41)+IF(D93,0,'Pro-Forma'!$G$40)+('Pro-Forma'!$D$62+'Pro-Forma'!$D$63+'Pro-Forma'!$D$64+'Pro-Forma'!$D$65+'Pro-Forma'!$D$74+'Pro-Forma'!$G$49+'Pro-Forma'!$G$50+'Pro-Forma'!$D$76) -> 34120125 | E95: =IF(E87,0,'Pro-Forma'!$C$29)+IF(E88,0,'Pro-Forma'!$G$45)+IF(E89,0,'Pro-Forma'!$G$44)+IF(E90,0,'Pro-Forma'!$G$43)+IF(E91,0,'Pro-Forma'!$G$42)+IF(E92,0,'Pro-Forma'!$G$41)+IF(E93,0,'Pro-Forma'!$G$40)+('Pro-Forma'!$D$62+'Pro-Forma'!$D$63+'Pro-Forma'!$D$64+'Pro-Forma'!$D$65+'Pro-Forma'!$D$74+'Pro-Forma'!$G$49+'Pro-Forma'!$G$50+'Pro-Forma'!$D$76) -> 34120125 | F95: =IF(F87,0,'Pro-Forma'!$C$29)+IF(F88,0,'Pro-Forma'!$G$45)+IF(F89,0,'Pro-Forma'!$G$44)+IF(F90,0,'Pro-Forma'!$G$43)+IF(F91,0,'Pro-Forma'!$G$42)+IF(F92,0,'Pro-Forma'!$G$41)+IF(F93,0,'Pro-Forma'!$G$40)+('Pro-Forma'!$D$62+'Pro-Forma'!$D$63+'Pro-Forma'!$D$64+'Pro-Forma'!$D$65+'Pro-Forma'!$D$74+'Pro-Forma'!$G$49+'Pro-Forma'!$G$50+'Pro-Forma'!$D$76) -> 34120125 | G95: =IF(G87,0,'Pro-Forma'!$C$29)+IF(G88,0,'Pro-Forma'!$G$45)+IF(G89,0,'Pro-Forma'!$G$44)+IF(G90,0,'Pro-Forma'!$G$43)+IF(G91,0,'Pro-Forma'!$G$42)+IF(G92,0,'Pro-Forma'!$G$41)+IF(G93,0,'Pro-Forma'!$G$40)+('Pro-Forma'!$D$62+'Pro-Forma'!$D$63+'Pro-Forma'!$D$64+'Pro-Forma'!$D$65+'Pro-Forma'!$D$74+'Pro-Forma'!$G$49+'Pro-Forma'!$G$50+'Pro-Forma'!$D$76) -> 34120125 | H95: =IF(H87,0,'Pro-Forma'!$C$29)+IF(H88,0,'Pro-Forma'!$G$45)+IF(H89,0,'Pro-Forma'!$G$44)+IF(H90,0,'Pro-Forma'!$G$43)+IF(H91,0,'Pro-Forma'!$G$42)+IF(H92,0,'Pro-Forma'!$G$41)+IF(H93,0,'Pro-Forma'!$G$40)+('Pro-Forma'!$D$62+'Pro-Forma'!$D$63+'Pro-Forma'!$D$64+'Pro-Forma'!$D$65+'Pro-Forma'!$D$74+'Pro-Forma'!$G$49+'Pro-Forma'!$G$50+'Pro-Forma'!$D$76) -> 34120125
B96: Residual ($) | C96: =C86-C94 -> 2002500000 | D96: =D86-D94 -> 1902499980 | E96: =E86-E94 -> 1902499980 | F96: =F86-F94 -> 1902499980 | G96: =G86-G94 -> 1902499980 | H96: =H86-H94 -> 1902499980
B97: Common PPS at exit ($) | C97: =C96/C95 -> 55.85135 | D97: =D96/D95 -> 55.758881 | E97: =E96/E95 -> 55.758881 | F97: =F96/F95 -> 55.758881 | G97: =G96/G95 -> 55.758881 | H97: =H96/H95 -> 55.758881
B98: F_convert_$ | C98: ='Pro-Forma'!$C$29*C97 -> 44920946 | D98: ='Pro-Forma'!$C$29*D97 -> 44846573 | E98: ='Pro-Forma'!$C$29*E97 -> 44846573 | F98: ='Pro-Forma'!$C$29*F97 -> 44846573 | G98: ='Pro-Forma'!$C$29*G97 -> 44846573 | H98: ='Pro-Forma'!$C$29*H97 -> 44846573
B99: E_convert_$ | C99: ='Pro-Forma'!$G$45*C97 -> 3.4261855e+08 | D99: ='Pro-Forma'!$G$45*D97 -> 3.420513e+08 | E99: ='Pro-Forma'!$G$45*E97 -> 3.420513e+08 | F99: ='Pro-Forma'!$G$45*F97 -> 3.420513e+08 | G99: ='Pro-Forma'!$G$45*G97 -> 3.420513e+08 | H99: ='Pro-Forma'!$G$45*H97 -> 3.420513e+08
B100: D_convert_$ | C100: ='Pro-Forma'!$G$44*C97 -> 96844954 | D100: ='Pro-Forma'!$G$44*D97 -> 96684614 | E100: ='Pro-Forma'!$G$44*E97 -> 96684614 | F100: ='Pro-Forma'!$G$44*F97 -> 96684614 | G100: ='Pro-Forma'!$G$44*G97 -> 96684614 | H100: ='Pro-Forma'!$G$44*H97 -> 96684614
B101: C_convert_$ | C101: ='Pro-Forma'!$G$43*C97 -> 1.3404324e+08 | D101: ='Pro-Forma'!$G$43*D97 -> 1.3382131e+08 | E101: ='Pro-Forma'!$G$43*E97 -> 1.3382131e+08 | F101: ='Pro-Forma'!$G$43*F97 -> 1.3382131e+08 | G101: ='Pro-Forma'!$G$43*G97 -> 1.3382131e+08 | H101: ='Pro-Forma'!$G$43*H97 -> 1.3382131e+08
B102: B_convert_$ | C102: ='Pro-Forma'!$G$42*C97 -> 1.6755405e+08 | D102: ='Pro-Forma'!$G$42*D97 -> 1.6727664e+08 | E102: ='Pro-Forma'!$G$42*E97 -> 1.6727664e+08 | F102: ='Pro-Forma'!$G$42*F97 -> 1.6727664e+08 | G102: ='Pro-Forma'!$G$42*G97 -> 1.6727664e+08 | H102: ='Pro-Forma'!$G$42*H97 -> 1.6727664e+08
B103: A_convert_$ | C103: ='Pro-Forma'!$G$41*C97 -> 2.7925675e+08 | D103: ='Pro-Forma'!$G$41*D97 -> 2.787944e+08 | E103: ='Pro-Forma'!$G$41*E97 -> 2.787944e+08 | F103: ='Pro-Forma'!$G$41*F97 -> 2.787944e+08 | G103: ='Pro-Forma'!$G$41*G97 -> 2.787944e+08 | H103: ='Pro-Forma'!$G$41*H97 -> 2.787944e+08
B104: Seed_convert_$ | C104: ='Pro-Forma'!$G$40*C97 -> 2.7925675e+08 | D104: ='Pro-Forma'!$G$40*D97 -> 2.787944e+08 | E104: ='Pro-Forma'!$G$40*E97 -> 2.787944e+08 | F104: ='Pro-Forma'!$G$40*F97 -> 2.787944e+08 | G104: ='Pro-Forma'!$G$40*G97 -> 2.787944e+08 | H104: ='Pro-Forma'!$G$40*H97 -> 2.787944e+08
B106: Exit 4 Nash Solver — iterative best response
B107: Iteration | C107: Iter 0 | D107: Iter 1 | E107: Iter 2 | F107: Iter 3 | G107: Iter 4 | H107: Iter 5
B108: Distributable ($) | C108: =F$8 -> 4002500000 | D108: =F$8 -> 4002500000 | E108: =F$8 -> 4002500000 | F108: =F$8 -> 4002500000 | G108: =F$8 -> 4002500000 | H108: =F$8 -> 4002500000
B109: F_takes_pref | C109: FALSE | D109: =Assumptions!$C$7>C120 -> 0 | E109: =Assumptions!$C$7>D120 -> 0 | F109: =Assumptions!$C$7>E120 -> 0 | G109: =Assumptions!$C$7>F120 -> 0 | H109: =Assumptions!$C$7>G120 -> 0
B110: E_takes_pref | C110: FALSE | D110: =Assumptions!$C$41*Assumptions!$C$28>C121 -> 0 | E110: =Assumptions!$C$41*Assumptions!$C$28>D121 -> 0 | F110: =Assumptions!$C$41*Assumptions!$C$28>E121 -> 0 | G110: =Assumptions!$C$41*Assumptions!$C$28>F121 -> 0 | H110: =Assumptions!$C$41*Assumptions!$C$28>G121 -> 0
B111: D_takes_pref | C111: FALSE | D111: =Assumptions!$C$40*Assumptions!$C$27>C122 -> 0 | E111: =Assumptions!$C$40*Assumptions!$C$27>D122 -> 0 | F111: =Assumptions!$C$40*Assumptions!$C$27>E122 -> 0 | G111: =Assumptions!$C$40*Assumptions!$C$27>F122 -> 0 | H111: =Assumptions!$C$40*Assumptions!$C$27>G122 -> 0
B112: C_takes_pref | C112: FALSE | D112: =Assumptions!$C$38*Assumptions!$C$25>C123 -> 0 | E112: =Assumptions!$C$38*Assumptions!$C$25>D123 -> 0 | F112: =Assumptions!$C$38*Assumptions!$C$25>E123 -> 0 | G112: =Assumptions!$C$38*Assumptions!$C$25>F123 -> 0 | H112: =Assumptions!$C$38*Assumptions!$C$25>G123 -> 0
B113: B_takes_pref | C113: FALSE | D113: =Assumptions!$C$37*Assumptions!$C$24>C124 -> 0 | E113: =Assumptions!$C$37*Assumptions!$C$24>D124 -> 0 | F113: =Assumptions!$C$37*Assumptions!$C$24>E124 -> 0 | G113: =Assumptions!$C$37*Assumptions!$C$24>F124 -> 0 | H113: =Assumptions!$C$37*Assumptions!$C$24>G124 -> 0
B114: A_takes_pref | C114: FALSE | D114: =Assumptions!$C$36*Assumptions!$C$23>C125 -> 0 | E114: =Assumptions!$C$36*Assumptions!$C$23>D125 -> 0 | F114: =Assumptions!$C$36*Assumptions!$C$23>E125 -> 0 | G114: =Assumptions!$C$36*Assumptions!$C$23>F125 -> 0 | H114: =Assumptions!$C$36*Assumptions!$C$23>G125 -> 0
B115: Seed_takes_pref | C115: FALSE | D115: =Assumptions!$C$35*Assumptions!$C$22>C126 -> 0 | E115: =Assumptions!$C$35*Assumptions!$C$22>D126 -> 0 | F115: =Assumptions!$C$35*Assumptions!$C$22>E126 -> 0 | G115: =Assumptions!$C$35*Assumptions!$C$22>F126 -> 0 | H115: =Assumptions!$C$35*Assumptions!$C$22>G126 -> 0
...

Sheet Sensitivity
B2: Kelvin Dynamics — Sensitivity
B3: Our $10M check — ownership % and $ proceeds at $2,000M exit. Each cell re-solves the full round.
B5: Sensitivity — Our $10M Check at $2,000M Exit
B7: Our Ownership % (post-F)
B8: Pre-Money ↓ / ESOP → | C8: ESOP 11% | D8: ESOP 13% | E8: ESOP 15%
B9: $1,200M | C9: =(Assumptions!$C$11/M57)/M55 -> 0.0081300813 | D9: =(Assumptions!$C$11/M102)/M100 -> 0.0081300813 | E9: =(Assumptions!$C$11/M147)/M145 -> 0.0081300813
B10: $1,400M (base) | C10: =(Assumptions!$C$11/M192)/M190 -> 0.006993007 | D10: =(Assumptions!$C$11/M237)/M235 -> 0.006993007 | E10: =(Assumptions!$C$11/M282)/M280 -> 0.006993007
B11: $1,800M | C11: =(Assumptions!$C$11/M327)/M325 -> 0.0054644809 | D11: =(Assumptions!$C$11/M372)/M370 -> 0.0054644809 | E11: =(Assumptions!$C$11/M417)/M415 -> 0.0054644809
B13: Our $ Proceeds at $2B Exit
B14: Pre-Money ↓ / ESOP → | C14: ESOP 11% | D14: ESOP 13% | E14: ESOP 15%
B15: $1,200M | C15: =(Assumptions!$C$11/Assumptions!$C$7)*IF(H60,Assumptions!$C$7,M45*H70) -> 17107259 | D15: =(Assumptions!$C$11/Assumptions!$C$7)*IF(H105,Assumptions!$C$7,M90*H115) -> 17384971 | E15: =(Assumptions!$C$11/Assumptions!$C$7)*IF(H150,Assumptions!$C$7,M135*H160) -> 17795002
B16: $1,400M (base) | C16: =(Assumptions!$C$11/Assumptions!$C$7)*IF(H195,Assumptions!$C$7,M180*H205) -> 14719656 | D16: =(Assumptions!$C$11/Assumptions!$C$7)*IF(H240,Assumptions!$C$7,M225*H250) -> 14948858 | E16: =(Assumptions!$C$11/Assumptions!$C$7)*IF(H285,Assumptions!$C$7,M270*H295) -> 15301320
B17: $1,800M | C17: =(Assumptions!$C$11/Assumptions!$C$7)*IF(H330,Assumptions!$C$7,M315*H340) -> 11507141 | D17: =(Assumptions!$C$11/Assumptions!$C$7)*IF(H375,Assumptions!$C$7,M360*H385) -> 11676568 | E17: =(Assumptions!$C$11/Assumptions!$C$7)*IF(H420,Assumptions!$C$7,M405*H430) -> 11951762
B35: Solver: ESOP=11%, Pre=$1,200M
B36: pre_money ($) | C36: =Assumptions!$C$62 -> 1200000000
B37: esop_target | C37: =Assumptions!$C$59 -> 0.11
B38: Iteration | D38: Iter 0 | E38: Iter 1 | F38: Iter 2 | G38: Iter 3 | H38: Iter 4 | I38: Iter 5 | J38: Iter 6 | K38: Iter 7 | L38: Iter 8 | M38: Iter 9
B39: F_PPS (input) | D39: 45 | E39: =D57 -> 32.524044 | F39: =E57 -> 32.442402 | G39: =F57 -> 32.44131 | H39: =G57 -> 32.441295 | I39: =H57 -> 32.441295 | J39: =I57 -> 32.441295 | K39: =J57 -> 32.441295 | L39: =K57 -> 32.441295 | M39: =L57 -> 32.441295
B40: NCP_D | D40: =IF(D39<Assumptions!$C$26,Assumptions!$C$26*(Assumptions!$C$44+Assumptions!$C$7/Assumptions!$C$26)/(Assumptions!$C$44+Assumptions!$C$7/D39),Assumptions!$C$26) -> 57.883785 | E40: =IF(E39<Assumptions!$C$26,Assumptions!$C$26*(Assumptions!$C$44+Assumptions!$C$7/Assumptions!$C$26)/(Assumptions!$C$44+Assumptions!$C$7/E39),Assumptions!$C$26) -> 57.489476 | F40: =IF(F39<Assumptions!$C$26,Assumptions!$C$26*(Assumptions!$C$44+Assumptions!$C$7/Assumptions!$C$26)/(Assumptions!$C$44+Assumptions!$C$7/F39),Assumptions!$C$26) -> 57.485921 | G40: =IF(G39<Assumptions!$C$26,Assumptions!$C$26*(Assumptions!$C$44+Assumptions!$C$7/Assumptions!$C$26)/(Assumptions!$C$44+Assumptions!$C$7/G39),Assumptions!$C$26) -> 57.485874 | H40: =IF(H39<Assumptions!$C$26,Assumptions!$C$26*(Assumptions!$C$44+Assumptions!$C$7/Assumptions!$C$26)/(Assumptions!$C$44+Assumptions!$C$7/H39),Assumptions!$C$26) -> 57.485873 | I40: =IF(I39<Assumptions!$C$26,Assumptions!$C$26*(Assumptions!$C$44+Assumptions!$C$7/Assumptions!$C$26)/(Assumptions!$C$44+Assumptions!$C$7/I39),Assumptions!$C$26) -> 57.485873 | J40: =IF(J39<Assumptions!$C$26,Assumptions!$C$26*(Assumptions!$C$44+Assumptions!$C$7/Assumptions!$C$26)/(Assumptions!$C$44+Assumptions!$C$7/J39),Assumptions!$C$26) -> 57.485873 | K40: =IF(K39<Assumptions!$C$26,Assumptions!$C$26*(Assumptions!$C$44+Assumptions!$C$7/Assumptions!$C$26)/(Assumptions!$C$44+Assumptions!$C$7/K39),Assumptions!$C$26) -> 57.485873 | ... M40: =IF(M39<Assumptions!$C$26,Assumptions!$C$26*(Assumptions!$C$44+Assumptions!$C$7/Assumptions!$C$26)/(Assumptions!$C$44+Assumptions!$C$7/M39),Assumptions!$C$26) -> 57.485873
B41: Δ D shares | D41: =Assumptions!$C$40*Assumptions!$C$27/D40-Assumptions!$C$39 -> 6972.8859 | E41: =Assumptions!$C$40*Assumptions!$C$27/E40-Assumptions!$C$39 -> 18822.15 | F41: =Assumptions!$C$40*Assumptions!$C$27/F40-Assumptions!$C$39 -> 18929.706 | G41: =Assumptions!$C$40*Assumptions!$C$27/G40-Assumptions!$C$39 -> 18931.148 | H41: =Assumptions!$C$40*Assumptions!$C$27/H40-Assumptions!$C$39 -> 18931.167 | I41: =Assumptions!$C$40*Assumptions!$C$27/I40-Assumptions!$C$39 -> 18931.167 | J41: =Assumptions!$C$40*Assumptions!$C$27/J40-Assumptions!$C$39 -> 18931.167 | K41: =Assumptions!$C$40*Assumptions!$C$27/K40-Assumptions!$C$39 -> 18931.167 | ... M41: =Assumptions!$C$40*Assumptions!$C$27/M40-Assumptions!$C$39 -> 18931.167
B42: NCP_E | D42: =IF(D39<Assumptions!$C$28,Assumptions!$C$28*(Assumptions!$C$44+Assumptions!$C$7/Assumptions!$C$28)/(Assumptions!$C$44+Assumptions!$C$7/D39),Assumptions!$C$28) -> 49.083958 | E42: =IF(E39<Assumptions!$C$28,Assumptions!$C$28*(Assumptions!$C$44+Assumptions!$C$7/Assumptions!$C$28)/(Assumptions!$C$44+Assumptions!$C$7/E39),Assumptions!$C$28) -> 48.749595 | F42: =IF(F39<Assumptions!$C$28,Assumptions!$C$28*(Assumptions!$C$44+Assumptions!$C$7/Assumptions!$C$28)/(Assumptions!$C$44+Assumptions!$C$7/F39),Assumptions!$C$28) -> 48.746581 | G42: =IF(G39<Assumptions!$C$28,Assumptions!$C$28*(Assumptions!$C$44+Assumptions!$C$7/Assumptions!$C$28)/(Assumptions!$C$44+Assumptions!$C$7/G39),Assumptions!$C$28) -> 48.74654 | H42: =IF(H39<Assumptions!$C$28,Assumptions!$C$28*(Assumptions!$C$44+Assumptions!$C$7/Assumptions!$C$28)/(Assumptions!$C$44+Assumptions!$C$7/H39),Assumptions!$C$28) -> 48.74654 | I42: =IF(I39<Assumptions!$C$28,Assumptions!$C$28*(Assumptions!$C$44+Assumptions!$C$7/Assumptions!$C$28)/(Assumptions!$C$44+Assumptions!$C$7/I39),Assumptions!$C$28) -> 48.74654 | J42: =IF(J39<Assumptions!$C$28,Assumptions!$C$28*(Assumptions!$C$44+Assumptions!$C$7/Assumptions!$C$28)/(Assumptions!$C$44+Assumptions!$C$7/J39),Assumptions!$C$28) -> 48.74654 | K42: =IF(K39<Assumptions!$C$28,Assumptions!$C$28*(Assumptions!$C$44+Assumptions!$C$7/Assumptions!$C$28)/(Assumptions!$C$44+Assumptions!$C$7/K39),Assumptions!$C$28) -> 48.74654 | ... M42: =IF(M39<Assumptions!$C$28,Assumptions!$C$28*(Assumptions!$C$44+Assumptions!$C$7/Assumptions!$C$28)/(Assumptions!$C$44+Assumptions!$C$7/M39),Assumptions!$C$28) -> 48.74654
B43: Δ E shares | D43: =Assumptions!$C$41*Assumptions!$C$28/D42-Assumptions!$C$41 -> 9244.3417 | E43: =Assumptions!$C$41*Assumptions!$C$28/E42-Assumptions!$C$41 -> 51164.726 | F43: =Assumptions!$C$41*Assumptions!$C$28/F42-Assumptions!$C$41 -> 51545.238 | G43: =Assumptions!$C$41*Assumptions!$C$28/G42-Assumptions!$C$41 -> 51550.339 | H43: =Assumptions!$C$41*Assumptions!$C$28/H42-Assumptions!$C$41 -> 51550.408 | I43: =Assumptions!$C$41*Assumptions!$C$28/I42-Assumptions!$C$41 -> 51550.409 | J43: =Assumptions!$C$41*Assumptions!$C$28/J42-Assumptions!$C$41 -> 51550.409 | K43: =Assumptions!$C$41*Assumptions!$C$28/K42-Assumptions!$C$41 -> 51550.409 | ... M43: =Assumptions!$C$41*Assumptions!$C$28/M42-Assumptions!$C$41 -> 51550.409
B44: Base FD | D44: =Assumptions!$C$44+D41+D43 -> 36634178 | E44: =Assumptions!$C$44+E41+E43 -> 36687948 | F44: =Assumptions!$C$44+F41+F43 -> 36688436 | G44: =Assumptions!$C$44+G41+G43 -> 36688442 | H44: =Assumptions!$C$44+H41+H43 -> 36688443 | I44: =Assumptions!$C$44+I41+I43 -> 36688443 | J44: =Assumptions!$C$44+J41+J43 -> 36688443 | K44: =Assumptions!$C$44+K41+K43 -> 36688443 | ... M44: =Assumptions!$C$44+M41+M43 -> 36688443
B45: F_S | D45: =Assumptions!$C$7/D39 -> 666666.67 | E45: =Assumptions!$C$7/E39 -> 922394.51 | F45: =Assumptions!$C$7/F39 -> 924715.76 | G45: =Assumptions!$C$7/G39 -> 924746.88 | H45: =Assumptions!$C$7/H39 -> 924747.3 | I45: =Assumptions!$C$7/I39 -> 924747.3 | J45: =Assumptions!$C$7/J39 -> 924747.3 | K45: =Assumptions!$C$7/K39 -> 924747.3 | ... M45: =Assumptions!$C$7/M39 -> 924747.3
B46: Note A cap PPS | D46: =Assumptions!$C$48/(D44+0+0) -> 27.296914 | E46: =Assumptions!$C$48/(E44+D54+D53) -> 27.198762 | F46: =Assumptions!$C$48/(F44+E54+E53) -> 27.176163 | G46: =Assumptions!$C$48/(G44+F54+F53) -> 27.175957 | H46: =Assumptions!$C$48/(H44+G54+G53) -> 27.175954 | I46: =Assumptions!$C$48/(I44+H54+H53) -> 27.175954 | J46: =Assumptions!$C$48/(J44+I54+I53) -> 27.175954 | K46: =Assumptions!$C$48/(K44+J54+J53) -> 27.175954 | L46: =Assumptions!$C$48/(L44+K54+K53) -> 27.175954 | M46: =Assumptions!$C$48/(M44+L54+L53) -> 27.175954
B47: Note A disc PPS | D47: =D39*(1-Assumptions!$C$49) -> 36 | E47: =E39*(1-Assumptions!$C$49) -> 26.019235 | F47: =F39*(1-Assumptions!$C$49) -> 25.953921 | G47: =G39*(1-Assumptions!$C$49) -> 25.953048 | H47: =H39*(1-Assumptions!$C$49) -> 25.953036 | I47: =I39*(1-Assumptions!$C$49) -> 25.953036 | J47: =J39*(1-Assumptions!$C$49) -> 25.953036 | K47: =K39*(1-Assumptions!$C$49) -> 25.953036 | ... M47: =M39*(1-Assumptions!$C$49) -> 25.953036
B48: Note A conv PPS | D48: =MIN(D46,D47) -> 27.296914 | E48: =MIN(E46,E47) -> 26.019235 | F48: =MIN(F46,F47) -> 25.953921 | G48: =MIN(G46,G47) -> 25.953048 | H48: =MIN(H46,H47) -> 25.953036 | I48: =MIN(I46,I47) -> 25.953036 | J48: =MIN(J46,J47) -> 25.953036 | K48: =MIN(K46,K47) -> 25.953036 | ... M48: =MIN(M46,M47) -> 25.953036
B49: Note A shares | D49: =Assumptions!$C$47/D48 -> 183170.89 | E49: =Assumptions!$C$47/E48 -> 192165.52 | F49: =Assumptions!$C$47/F48 -> 192649.12 | G49: =Assumptions!$C$47/G48 -> 192655.6 | H49: =Assumptions!$C$47/H48 -> 192655.69 | I49: =Assumptions!$C$47/I48 -> 192655.69 | J49: =Assumptions!$C$47/J48 -> 192655.69 | K49: =Assumptions!$C$47/K48 -> 192655.69 | ... M49: =Assumptions!$C$47/M48 -> 192655.69
B50: Note B cap PPS | D50: =Assumptions!$C$51/(D44+0+0) -> 43.675062 | E50: =Assumptions!$C$51/(E44+D54+D49) -> 43.394398 | F50: =Assumptions!$C$51/(F44+E54+E49) -> 43.38324 | G50: =Assumptions!$C$51/(G44+F54+F49) -> 43.382664 | H50: =Assumptions!$C$51/(H44+G54+G49) -> 43.382656 | I50: =Assumptions!$C$51/(I44+H54+H49) -> 43.382656 | J50: =Assumptions!$C$51/(J44+I54+I49) -> 43.382656 | K50: =Assumptions!$C$51/(K44+J54+J49) -> 43.382656 | L50: =Assumptions!$C$51/(L44+K54+K49) -> 43.382656 | M50: =Assumptions!$C$51/(M44+L54+L49) -> 43.382656
B51: Note B disc PPS | D51: =D39*(1-Assumptions!$C$52) -> 38.25 | E51: =E39*(1-Assumptions!$C$52) -> 27.645438 | F51: =F39*(1-Assumptions!$C$52) -> 27.576041 | G51: =G39*(1-Assumptions!$C$52) -> 27.575113 | H51: =H39*(1-Assumptions!$C$52) -> 27.575101 | I51: =I39*(1-Assumptions!$C$52) -> 27.575101 | J51: =J39*(1-Assumptions!$C$52) -> 27.575101 | K51: =K39*(1-Assumptions!$C$52) -> 27.575101 | ... M51: =M39*(1-Assumptions!$C$52) -> 27.575101
B52: Note B conv PPS | D52: =MIN(D50,D51) -> 38.25 | E52: =MIN(E50,E51) -> 27.645438 | F52: =MIN(F50,F51) -> 27.576041 | G52: =MIN(G50,G51) -> 27.575113 | H52: =MIN(H50,H51) -> 27.575101 | I52: =MIN(I50,I51) -> 27.575101 | J52: =MIN(J50,J51) -> 27.575101 | K52: =MIN(K50,K51) -> 27.575101 | ... M52: =MIN(M50,M51) -> 27.575101
B53: Note B shares | D53: =Assumptions!$C$50/D52 -> 78431.373 | E53: =Assumptions!$C$50/E52 -> 108517 | F53: =Assumptions!$C$50/F52 -> 108790.09 | G53: =Assumptions!$C$50/G52 -> 108793.75 | H53: =Assumptions!$C$50/H52 -> 108793.8 | I53: =Assumptions!$C$50/I52 -> 108793.8 | J53: =Assumptions!$C$50/J52 -> 108793.8 | K53: =Assumptions!$C$50/K52 -> 108793.8 | ... M53: =Assumptions!$C$50/M52 -> 108793.8
B54: ESOP top-up | D54: =MAX(0,(Assumptions!$C$59*(D44+D49+D53+D45)-Assumptions!$C$56)/(1-Assumptions!$C$59)) -> 0 | E54: =MAX(0,(Assumptions!$C$59*(E44+E49+E53+E45)-Assumptions!$C$56)/(1-Assumptions!$C$59)) -> 0 | F54: =MAX(0,(Assumptions!$C$59*(F44+F49+F53+F45)-Assumptions!$C$56)/(1-Assumptions!$C$59)) -> 0 | G54: =MAX(0,(Assumptions!$C$59*(G44+G49+G53+G45)-Assumptions!$C$56)/(1-Assumptions!$C$59)) -> 0 | H54: =MAX(0,(Assumptions!$C$59*(H44+H49+H53+H45)-Assumptions!$C$56)/(1-Assumptions!$C$59)) -> 0 | I54: =MAX(0,(Assumptions!$C$59*(I44+I49+I53+I45)-Assumptions!$C$56)/(1-Assumptions!$C$59)) -> 0 | J54: =MAX(0,(Assumptions!$C$59*(J44+J49+J53+J45)-Assumptions!$C$56)/(1-Assumptions!$C$59)) -> 0 | K54: =MAX(0,(Assumptions!$C$59*(K44+K49+K53+K45)-Assumptions!$C$56)/(1-Assumptions!$C$59)) -> 0 | ... M54: =MAX(0,(Assumptions!$C$59*(M44+M49+M53+M45)-Assumptions!$C$56)/(1-Assumptions!$C$59)) -> 0
B55: T_F | D55: =D44+D54+D49+D53+D45 -> 37562447 | E55: =E44+E54+E49+E53+E45 -> 37911025 | F55: =F44+F54+F49+F53+F45 -> 37914591 | G55: =G44+G54+G49+G53+G45 -> 37914639 | H55: =H44+H54+H49+H53+H45 -> 37914639 | I55: =I44+I54+I49+I53+I45 -> 37914639 | J55: =J44+J54+J49+J53+J45 -> 37914639 | K55: =K44+K54+K49+K53+K45 -> 37914639 | ... M55: =M44+M54+M49+M53+M45 -> 37914639
B56: Pre-money FD | D56: =D55-D45 -> 36895780 | E56: =E55-E45 -> 36988630 | F56: =F55-F45 -> 36989875 | G56: =G55-G45 -> 36989892 | H56: =H55-H45 -> 36989892 | I56: =I55-I45 -> 36989892 | J56: =J55-J45 -> 36989892 | K56: =K55-K45 -> 36989892 | ... M56: =M55-M45 -> 36989892
B57: F_PPS_new | D57: =Assumptions!$C$62/D56 -> 32.524044 | E57: =Assumptions!$C$62/E56 -> 32.442402 | F57: =Assumptions!$C$62/F56 -> 32.44131 | G57: =Assumptions!$C$62/G56 -> 32.441295 | H57: =Assumptions!$C$62/H56 -> 32.441295 | I57: =Assumptions!$C$62/I56 -> 32.441295 | J57: =Assumptions!$C$62/J56 -> 32.441295 | K57: =Assumptions!$C$62/K56 -> 32.441295 | ... M57: =Assumptions!$C$62/M56 -> 32.441295
B59: Distributable_$2B | D59: =Assumptions!$C$17+Assumptions!$C$42*Assumptions!$C$55 -> 2002500000 | E59: =Assumptions!$C$17+Assumptions!$C$42*Assumptions!$C$55 -> 2002500000 | F59: =Assumptions!$C$17+Assumptions!$C$42*Assumptions!$C$55 -> 2002500000 | G59: =Assumptions!$C$17+Assumptions!$C$42*Assumptions!$C$55 -> 2002500000 | H59: =Assumptions!$C$17+Assumptions!$C$42*Assumptions!$C$55 -> 2002500000
B60: F pref? | D60: FALSE | E60: =Assumptions!$C$7>D71 -> 0 | F60: =Assumptions!$C$7>E71 -> 0 | G60: =Assumptions!$C$7>F71 -> 0 | H60: =Assumptions!$C$7>G71 -> 0
B61: E pref? | D61: FALSE | E61: =Assumptions!$C$41*Assumptions!$C$28>D72 -> 0 | F61: =Assumptions!$C$41*Assumptions!$C$28>E72 -> 0 | G61: =Assumptions!$C$41*Assumptions!$C$28>F72 -> 0 | H61: =Assumptions!$C$41*Assumptions!$C$28>G72 -> 0
B62: D pref? | D62: FALSE | E62: =Assumptions!$C$40*Assumptions!$C$27>D73 -> 1 | F62: =Assumptions!$C$40*Assumptions!$C$27>E73 -> 1 | G62: =Assumptions!$C$40*Assumptions!$C$27>F73 -> 1 | H62: =Assumptions!$C$40*Assumptions!$C$27>G73 -> 1
B63: C pref? | D63: FALSE | E63: =Assumptions!$C$38*Assumptions!$C$25>D74 -> 0 | F63: =Assumptions!$C$38*Assumptions!$C$25>E74 -> 0 | G63: =Assumptions!$C$38*Assumptions!$C$25>F74 -> 0 | H63: =Assumptions!$C$38*Assumptions!$C$25>G74 -> 0
B64: B pref? | D64: FALSE | E64: =Assumptions!$C$37*Assumptions!$C$24>D75 -> 0 | F64: =Assumptions!$C$37*Assumptions!$C$24>E75 -> 0 | G64: =Assumptions!$C$37*Assumptions!$C$24>F75 -> 0 | H64: =Assumptions!$C$37*Assumptions!$C$24>G75 -> 0
B65: A pref? | D65: FALSE | E65: =Assumptions!$C$36*Assumptions!$C$23>D76 -> 0 | F65: =Assumptions!$C$36*Assumptions!$C$23>E76 -> 0 | G65: =Assumptions!$C$36*Assumptions!$C$23>F76 -> 0 | H65: =Assumptions!$C$36*Assumptions!$C$23>G76 -> 0
B66: Seed pref? | D66: FALSE | E66: =Assumptions!$C$35*Assumptions!$C$22>D77 -> 0 | F66: =Assumptions!$C$35*Assumptions!$C$22>E77 -> 0 | G66: =Assumptions!$C$35*Assumptions!$C$22>F77 -> 0 | H66: =Assumptions!$C$35*Assumptions!$C$22>G77 -> 0
B67: Sum prefs | D67: =IF(D60,Assumptions!$C$7,0)+IF(D61,Assumptions!$C$41*Assumptions!$C$28,0)+IF(D62,Assumptions!$C$40*Assumptions!$C$27,0)+IF(D63,Assumptions!$C$38*Assumptions!$C$25,0)+IF(D64,Assumptions!$C$37*Assumptions!$C$24,0)+IF(D65,Assumptions!$C$36*Assumptions!$C$23,0)+IF(D66,Assumptions!$C$35*Assumptions!$C$22,0) -> 0 | E67: =IF(E60,Assumptions!$C$7,0)+IF(E61,Assumptions!$C$41*Assumptions!$C$28,0)+IF(E62,Assumptions!$C$40*Assumptions!$C$27,0)+IF(E63,Assumptions!$C$38*Assumptions!$C$25,0)+IF(E64,Assumptions!$C$37*Assumptions!$C$24,0)+IF(E65,Assumptions!$C$36*Assumptions!$C$23,0)+IF(E66,Assumptions!$C$35*Assumptions!$C$22,0) -> 100000020 | F67: =IF(F60,Assumptions!$C$7,0)+IF(F61,Assumptions!$C$41*Assumptions!$C$28,0)+IF(F62,Assumptions!$C$40*Assumptions!$C$27,0)+IF(F63,Assumptions!$C$38*Assumptions!$C$25,0)+IF(F64,Assumptions!$C$37*Assumptions!$C$24,0)+IF(F65,Assumptions!$C$36*Assumptions!$C$23,0)+IF(F66,Assumptions!$C$35*Assumptions!$C$22,0) -> 100000020 | G67: =IF(G60,Assumptions!$C$7,0)+IF(G61,Assumptions!$C$41*Assumptions!$C$28,0)+IF(G62,Assumptions!$C$40*Assumptions!$C$27,0)+IF(G63,Assumptions!$C$38*Assumptions!$C$25,0)+IF(G64,Assumptions!$C$37*Assumptions!$C$24,0)+IF(G65,Assumptions!$C$36*Assumptions!$C$23,0)+IF(G66,Assumptions!$C$35*Assumptions!$C$22,0) -> 100000020 | H67: =IF(H60,Assumptions!$C$7,0)+IF(H61,Assumptions!$C$41*Assumptions!$C$28,0)+IF(H62,Assumptions!$C$40*Assumptions!$C$27,0)+IF(H63,Assumptions!$C$38*Assumptions!$C$25,0)+IF(H64,Assumptions!$C$37*Assumptions!$C$24,0)+IF(H65,Assumptions!$C$36*Assumptions!$C$23,0)+IF(H66,Assumptions!$C$35*Assumptions!$C$22,0) -> 100000020
B68: Convert pool | D68: =IF(D60,0,M45)+IF(D61,0,Assumptions!$C$41*Assumptions!$C$28/M42)+IF(D62,0,Assumptions!$C$40*Assumptions!$C$27/M40)+IF(D63,0,Assumptions!$C$38)+IF(D64,0,Assumptions!$C$37)+IF(D65,0,Assumptions!$C$36)+IF(D66,0,Assumptions!$C$35)+((Assumptions!$C$31+Assumptions!$C$32+Assumptions!$C$33+Assumptions!$C$34)+M49+M53+Assumptions!$C$42) -> 36019972 | E68: =IF(E60,0,M45)+IF(E61,0,Assumptions!$C$41*Assumptions!$C$28/M42)+IF(E62,0,Assumptions!$C$40*Assumptions!$C$27/M40)+IF(E63,0,Assumptions!$C$38)+IF(E64,0,Assumptions!$C$37)+IF(E65,0,Assumptions!$C$36)+IF(E66,0,Assumptions!$C$35)+((Assumptions!$C$31+Assumptions!$C$32+Assumptions!$C$33+Assumptions!$C$34)+M49+M53+Assumptions!$C$42) -> 34280414 | F68: =IF(F60,0,M45)+IF(F61,0,Assumptions!$C$41*Assumptions!$C$28/M42)+IF(F62,0,Assumptions!$C$40*Assumptions!$C$27/M40)+IF(F63,0,Assumptions!$C$38)+IF(F64,0,Assumptions!$C$37)+IF(F65,0,Assumptions!$C$36)+IF(F66,0,Assumptions!$C$35)+((Assumptions!$C$31+Assumptions!$C$32+Assumptions!$C$33+Assumptions!$C$34)+M49+M53+Assumptions!$C$42) -> 34280414 | G68: =IF(G60,0,M45)+IF(G61,0,Assumptions!$C$41*Assumptions!$C$28/M42)+IF(G62,0,Assumptions!$C$40*Assumptions!$C$27/M40)+IF(G63,0,Assumptions!$C$38)+IF(G64,0,Assumptions!$C$37)+IF(G65,0,Assumptions!$C$36)+IF(G66,0,Assumptions!$C$35)+((Assumptions!$C$31+Assumptions!$C$32+Assumptions!$C$33+Assumptions!$C$34)+M49+M53+Assumptions!$C$42) -> 34280414 | H68: =IF(H60,0,M45)+IF(H61,0,Assumptions!$C$41*Assumptions!$C$28/M42)+IF(H62,0,Assumptions!$C$40*Assumptions!$C$27/M40)+IF(H63,0,Assumptions!$C$38)+IF(H64,0,Assumptions!$C$37)+IF(H65,0,Assumptions!$C$36)+IF(H66,0,Assumptions!$C$35)+((Assumptions!$C$31+Assumptions!$C$32+Assumptions!$C$33+Assumptions!$C$34)+M49+M53+Assumptions!$C$42) -> 34280414
B69: Residual | D69: =D59-D67 -> 2002500000 | E69: =E59-E67 -> 1902499980 | F69: =F59-F67 -> 1902499980 | G69: =G59-G67 -> 1902499980 | H69: =H59-H67 -> 1902499980
B70: Common PPS @ exit | D70: =D69/D68 -> 55.594157 | E70: =E69/E68 -> 55.498162 | F70: =F69/F68 -> 55.498162 | G70: =G69/G68 -> 55.498162 | H70: =H69/H68 -> 55.498162
B71: F convert $ | D71: =M45*D70 -> 51410547 | E71: =M45*E70 -> 51321776 | F71: =M45*F70 -> 51321776 | G71: =M45*G70 -> 51321776 | H71: =M45*H70 -> 51321776
B72: E convert $ | D72: =Assumptions!$C$41*Assumptions!$C$28/M42*D70 -> 3.4213853e+08 | E72: =Assumptions!$C$41*Assumptions!$C$28/M42*E70 -> 3.4154775e+08 | F72: =Assumptions!$C$41*Assumptions!$C$28/M42*F70 -> 3.4154775e+08 | G72: =Assumptions!$C$41*Assumptions!$C$28/M42*G70 -> 3.4154775e+08 | H72: =Assumptions!$C$41*Assumptions!$C$28/M42*H70 -> 3.4154775e+08
B73: D convert $ | D73: =Assumptions!$C$40*Assumptions!$C$27/M40*D70 -> 96709270 | E73: =Assumptions!$C$40*Assumptions!$C$27/M40*E70 -> 96542281 | F73: =Assumptions!$C$40*Assumptions!$C$27/M40*F70 -> 96542281 | G73: =Assumptions!$C$40*Assumptions!$C$27/M40*G70 -> 96542281 | H73: =Assumptions!$C$40*Assumptions!$C$27/M40*H70 -> 96542281
B74: C convert $ | D74: =Assumptions!$C$38*D70 -> 1.3342598e+08 | E74: =Assumptions!$C$38*E70 -> 1.3319559e+08 | F74: =Assumptions!$C$38*F70 -> 1.3319559e+08 | G74: =Assumptions!$C$38*G70 -> 1.3319559e+08 | H74: =Assumptions!$C$38*H70 -> 1.3319559e+08
B75: B convert $ | D75: =Assumptions!$C$37*D70 -> 1.6678247e+08 | E75: =Assumptions!$C$37*E70 -> 1.6649449e+08 | F75: =Assumptions!$C$37*F70 -> 1.6649449e+08 | G75: =Assumptions!$C$37*G70 -> 1.6649449e+08 | H75: =Assumptions!$C$37*H70 -> 1.6649449e+08
B76: A convert $ | D76: =Assumptions!$C$36*D70 -> 2.7797079e+08 | E76: =Assumptions!$C$36*E70 -> 2.7749081e+08 | F76: =Assumptions!$C$36*F70 -> 2.7749081e+08 | G76: =Assumptions!$C$36*G70 -> 2.7749081e+08 | H76: =Assumptions!$C$36*H70 -> 2.7749081e+08
B77: Seed convert $ | D77: =Assumptions!$C$35*D70 -> 2.7797079e+08 | E77: =Assumptions!$C$35*E70 -> 2.7749081e+08 | F77: =Assumptions!$C$35*F70 -> 2.7749081e+08 | G77: =Assumptions!$C$35*G70 -> 2.7749081e+08 | H77: =Assumptions!$C$35*H70 -> 2.7749081e+08
B80: Solver: ESOP=13%, Pre=$1,200M
B81: pre_money ($) | C81: =Assumptions!$C$62 -> 1200000000
B82: esop_target | C82: =Assumptions!$C$60 -> 0.13
B83: Iteration | D83: Iter 0 | E83: Iter 1 | F83: Iter 2 | G83: Iter 3 | H83: Iter 4 | I83: Iter 5 | J83: Iter 6 | K83: Iter 7 | L83: Iter 8 | M83: Iter 9
B84: F_PPS (input) | D84: 45 | E84: =D102 -> 32.036549 | F84: =E102 -> 31.903945 | G84: =F102 -> 31.901417 | H84: =G102 -> 31.901369 | I84: =H102 -> 31.901368 | J84: =I102 -> 31.901368 | K84: =J102 -> 31.901368 | L84: =K102 -> 31.901368 | M84: =L102 -> 31.901368
B85: NCP_D | D85: =IF(D84<Assumptions!$C$26,Assumptions!$C$26*(Assumptions!$C$44+Assumptions!$C$7/Assumptions!$C$26)/(Assumptions!$C$44+Assumptions!$C$7/D84),Assumptions!$C$26) -> 57.883785 | E85: =IF(E84<Assumptions!$C$26,Assumptions!$C$26*(Assumptions!$C$44+Assumptions!$C$7/Assumptions!$C$26)/(Assumptions!$C$44+Assumptions!$C$7/E84),Assumptions!$C$26) -> 57.467989 | F85: =IF(F84<Assumptions!$C$26,Assumptions!$C$26*(Assumptions!$C$44+Assumptions!$C$7/Assumptions!$C$26)/(Assumptions!$C$44+Assumptions!$C$7/F84),Assumptions!$C$26) -> 57.462034 | G85: =IF(G84<Assumptions!$C$26,Assumptions!$C$26*(Assumptions!$C$44+Assumptions!$C$7/Assumptions!$C$26)/(Assumptions!$C$44+Assumptions!$C$7/G84),Assumptions!$C$26) -> 57.46192 | H85: =IF(H84<Assumptions!$C$26,Assumptions!$C$26*(Assumptions!$C$44+Assumptions!$C$7/Assumptions!$C$26)/(Assumptions!$C$44+Assumptions!$C$7/H84),Assumptions!$C$26) -> 57.461918 | I85: =IF(I84<Assumptions!$C$26,Assumptions!$C$26*(Assumptions!$C$44+Assumptions!$C$7/Assumptions!$C$26)/(Assumptions!$C$44+Assumptions!$C$7/I84),Assumptions!$C$26) -> 57.461918 | J85: =IF(J84<Assumptions!$C$26,Assumptions!$C$26*(Assumptions!$C$44+Assumptions!$C$7/Assumptions!$C$26)/(Assumptions!$C$44+Assumptions!$C$7/J84),Assumptions!$C$26) -> 57.461918 | K85: =IF(K84<Assumptions!$C$26,Assumptions!$C$26*(Assumptions!$C$44+Assumptions!$C$7/Assumptions!$C$26)/(Assumptions!$C$44+Assumptions!$C$7/K84),Assumptions!$C$26) -> 57.461918 | ... M85: =IF(M84<Assumptions!$C$26,Assumptions!$C$26*(Assumptions!$C$44+Assumptions!$C$7/Assumptions!$C$26)/(Assumptions!$C$44+Assumptions!$C$7/M84),Assumptions!$C$26) -> 57.461918
B86: Δ D shares | D86: =Assumptions!$C$40*Assumptions!$C$27/D85-Assumptions!$C$39 -> 6972.8859 | E86: =Assumptions!$C$40*Assumptions!$C$27/E85-Assumptions!$C$39 -> 19472.512 | F86: =Assumptions!$C$40*Assumptions!$C$27/F85-Assumptions!$C$39 -> 19652.855 | G86: =Assumptions!$C$40*Assumptions!$C$27/G85-Assumptions!$C$39 -> 19656.308 | H86: =Assumptions!$C$40*Assumptions!$C$27/H85-Assumptions!$C$39 -> 19656.374 | I86: =Assumptions!$C$40*Assumptions!$C$27/I85-Assumptions!$C$39 -> 19656.375 | J86: =Assumptions!$C$40*Assumptions!$C$27/J85-Assumptions!$C$39 -> 19656.375 | K86: =Assumptions!$C$40*Assumptions!$C$27/K85-Assumptions!$C$39 -> 19656.375 | ... M86: =Assumptions!$C$40*Assumptions!$C$27/M85-Assumptions!$C$39 -> 19656.375
B87: NCP_E | D87: =IF(D84<Assumptions!$C$28,Assumptions!$C$28*(Assumptions!$C$44+Assumptions!$C$7/Assumptions!$C$28)/(Assumptions!$C$44+Assumptions!$C$7/D84),Assumptions!$C$28) -> 49.083958 | E87: =IF(E84<Assumptions!$C$28,Assumptions!$C$28*(Assumptions!$C$44+Assumptions!$C$7/Assumptions!$C$28)/(Assumptions!$C$44+Assumptions!$C$7/E84),Assumptions!$C$28) -> 48.731375 | F87: =IF(F84<Assumptions!$C$28,Assumptions!$C$28*(Assumptions!$C$44+Assumptions!$C$7/Assumptions!$C$28)/(Assumptions!$C$44+Assumptions!$C$7/F84),Assumptions!$C$28) -> 48.726325 | G87: =IF(G84<Assumptions!$C$28,Assumptions!$C$28*(Assumptions!$C$44+Assumptions!$C$7/Assumptions!$C$28)/(Assumptions!$C$44+Assumptions!$C$7/G84),Assumptions!$C$28) -> 48.726228 | H87: =IF(H84<Assumptions!$C$28,Assumptions!$C$28*(Assumptions!$C$44+Assumptions!$C$7/Assumptions!$C$28)/(Assumptions!$C$44+Assumptions!$C$7/H84),Assumptions!$C$28) -> 48.726226 | I87: =IF(I84<Assumptions!$C$28,Assumptions!$C$28*(Assumptions!$C$44+Assumptions!$C$7/Assumptions!$C$28)/(Assumptions!$C$44+Assumptions!$C$7/I84),Assumptions!$C$28) -> 48.726226 | J87: =IF(J84<Assumptions!$C$28,Assumptions!$C$28*(Assumptions!$C$44+Assumptions!$C$7/Assumptions!$C$28)/(Assumptions!$C$44+Assumptions!$C$7/J84),Assumptions!$C$28) -> 48.726226 | K87: =IF(K84<Assumptions!$C$28,Assumptions!$C$28*(Assumptions!$C$44+Assumptions!$C$7/Assumptions!$C$28)/(Assumptions!$C$44+Assumptions!$C$7/K84),Assumptions!$C$28) -> 48.726226 | ... M87: =IF(M84<Assumptions!$C$28,Assumptions!$C$28*(Assumptions!$C$44+Assumptions!$C$7/Assumptions!$C$28)/(Assumptions!$C$44+Assumptions!$C$7/M84),Assumptions!$C$28) -> 48.726226
B88: Δ E shares | D88: =Assumptions!$C$41*Assumptions!$C$28/D87-Assumptions!$C$41 -> 9244.3417 | E88: =Assumptions!$C$41*Assumptions!$C$28/E87-Assumptions!$C$41 -> 53465.58 | F88: =Assumptions!$C$41*Assumptions!$C$28/F87-Assumptions!$C$41 -> 54103.599 | G88: =Assumptions!$C$41*Assumptions!$C$28/G87-Assumptions!$C$41 -> 54115.814 | H88: =Assumptions!$C$41*Assumptions!$C$28/H87-Assumptions!$C$41 -> 54116.048 | I88: =Assumptions!$C$41*Assumptions!$C$28/I87-Assumptions!$C$41 -> 54116.053 | J88: =Assumptions!$C$41*Assumptions!$C$28/J87-Assumptions!$C$41 -> 54116.053 | K88: =Assumptions!$C$41*Assumptions!$C$28/K87-Assumptions!$C$41 -> 54116.053 | ... M88: =Assumptions!$C$41*Assumptions!$C$28/M87-Assumptions!$C$41 -> 54116.053
B89: Base FD | D89: =Assumptions!$C$44+D86+D88 -> 36634178 | E89: =Assumptions!$C$44+E86+E88 -> 36690899 | F89: =Assumptions!$C$44+F86+F88 -> 36691717 | G89: =Assumptions!$C$44+G86+G88 -> 36691733 | H89: =Assumptions!$C$44+H86+H88 -> 36691733 | I89: =Assumptions!$C$44+I86+I88 -> 36691733 | J89: =Assumptions!$C$44+J86+J88 -> 36691733 | K89: =Assumptions!$C$44+K86+K88 -> 36691733 | ... M89: =Assumptions!$C$44+M86+M88 -> 36691733
B90: F_S | D90: =Assumptions!$C$7/D84 -> 666666.67 | E90: =Assumptions!$C$7/E84 -> 936430.46 | F90: =Assumptions!$C$7/F84 -> 940322.59 | G90: =Assumptions!$C$7/G84 -> 940397.1 | H90: =Assumptions!$C$7/H84 -> 940398.53 | I90: =Assumptions!$C$7/I84 -> 940398.55 | J90: =Assumptions!$C$7/J84 -> 940398.56 | K90: =Assumptions!$C$7/K84 -> 940398.56 | ... M90: =Assumptions!$C$7/M84 -> 940398.56
B91: Note A cap PPS | D91: =Assumptions!$C$48/(D89+0+0) -> 27.296914 | E91: =Assumptions!$C$48/(E89+D99+D98) -> 26.787555 | F91: =Assumptions!$C$48/(F89+E99+E98) -> 26.724654 | G91: =Assumptions!$C$48/(G89+F99+F98) -> 26.723678 | H91: =Assumptions!$C$48/(H89+G99+G98) -> 26.723659 | I91: =Assumptions!$C$48/(I89+H99+H98) -> 26.723659 | J91: =Assumptions!$C$48/(J89+I99+I98) -> 26.723659 | K91: =Assumptions!$C$48/(K89+J99+J98) -> 26.723659 | L91: =Assumptions!$C$48/(L89+K99+K98) -> 26.723659 | M91: =Assumptions!$C$48/(M89+L99+L98) -> 26.723659
B92: Note A disc PPS | D92: =D84*(1-Assumptions!$C$49) -> 36 | E92: =E84*(1-Assumptions!$C$49) -> 25.629239 | F92: =F84*(1-Assumptions!$C$49) -> 25.523156 | G92: =G84*(1-Assumptions!$C$49) -> 25.521134 | H92: =H84*(1-Assumptions!$C$49) -> 25.521095 | I92: =I84*(1-Assumptions!$C$49) -> 25.521094 | J92: =J84*(1-Assumptions!$C$49) -> 25.521094 | K92: =K84*(1-Assumptions!$C$49) -> 25.521094 | ... M92: =M84*(1-Assumptions!$C$49) -> 25.521094
B93: Note A conv PPS | D93: =MIN(D91,D92) -> 27.296914 | E93: =MIN(E91,E92) -> 25.629239 | F93: =MIN(F91,F92) -> 25.523156 | G93: =MIN(G91,G92) -> 25.521134 | H93: =MIN(H91,H92) -> 25.521095 | I93: =MIN(I91,I92) -> 25.521094 | J93: =MIN(J91,J92) -> 25.521094 | K93: =MIN(K91,K92) -> 25.521094 | ... M93: =MIN(M91,M92) -> 25.521094
B94: Note A shares | D94: =Assumptions!$C$47/D93 -> 183170.89 | E94: =Assumptions!$C$47/E93 -> 195089.68 | F94: =Assumptions!$C$47/F93 -> 195900.54 | G94: =Assumptions!$C$47/G93 -> 195916.06 | H94: =Assumptions!$C$47/H93 -> 195916.36 | I94: =Assumptions!$C$47/I93 -> 195916.37 | J94: =Assumptions!$C$47/J93 -> 195916.37 | K94: =Assumptions!$C$47/K93 -> 195916.37 | ... M94: =Assumptions!$C$47/M93 -> 195916.37
B95: Note B cap PPS | D95: =Assumptions!$C$51/(D89+0+0) -> 43.675062 | E95: =Assumptions!$C$51/(E89+D99+D94) -> 42.740171 | F95: =Assumptions!$C$51/(F89+E99+E94) -> 42.662624 | G95: =Assumptions!$C$51/(G89+F99+F94) -> 42.660667 | H95: =Assumptions!$C$51/(H89+G99+G94) -> 42.66063 | I95: =Assumptions!$C$51/(I89+H99+H94) -> 42.660629 | J95: =Assumptions!$C$51/(J89+I99+I94) -> 42.660629 | K95: =Assumptions!$C$51/(K89+J99+J94) -> 42.660629 | L95: =Assumptions!$C$51/(L89+K99+K94) -> 42.660629 | M95: =Assumptions!$C$51/(M89+L99+L94) -> 42.660629
B96: Note B disc PPS | D96: =D84*(1-Assumptions!$C$52) -> 38.25 | E96: =E84*(1-Assumptions!$C$52) -> 27.231066 | F96: =F84*(1-Assumptions!$C$52) -> 27.118353 | G96: =G84*(1-Assumptions!$C$52) -> 27.116204 | H96: =H84*(1-Assumptions!$C$52) -> 27.116163 | I96: =I84*(1-Assumptions!$C$52) -> 27.116162 | J96: =J84*(1-Assumptions!$C$52) -> 27.116162 | K96: =K84*(1-Assumptions!$C$52) -> 27.116162 | ... M96: =M84*(1-Assumptions!$C$52) -> 27.116162
B97: Note B conv PPS | D97: =MIN(D95,D96) -> 38.25 | E97: =MIN(E95,E96) -> 27.231066 | F97: =MIN(F95,F96) -> 27.118353 | G97: =MIN(G95,G96) -> 27.116204 | H97: =MIN(H95,H96) -> 27.116163 | I97: =MIN(I95,I96) -> 27.116162 | J97: =MIN(J95,J96) -> 27.116162 | K97: =MIN(K95,K96) -> 27.116162 | ... M97: =MIN(M95,M96) -> 27.116162
B98: Note B shares | D98: =Assumptions!$C$50/D97 -> 78431.373 | E98: =Assumptions!$C$50/E97 -> 110168.29 | F98: =Assumptions!$C$50/F97 -> 110626.19 | G98: =Assumptions!$C$50/G97 -> 110634.95 | H98: =Assumptions!$C$50/H97 -> 110635.12 | I98: =Assumptions!$C$50/I97 -> 110635.12 | J98: =Assumptions!$C$50/J97 -> 110635.12 | K98: =Assumptions!$C$50/K97 -> 110635.12 | ... M98: =Assumptions!$C$50/M97 -> 110635.12
B99: ESOP top-up | D99: =MAX(0,(Assumptions!$C$60*(D89+D94+D98+D90)-Assumptions!$C$56)/(1-Assumptions!$C$60)) -> 561438.08 | E99: =MAX(0,(Assumptions!$C$60*(E89+E94+E98+E90)-Assumptions!$C$56)/(1-Assumptions!$C$60)) -> 616746.41 | F99: =MAX(0,(Assumptions!$C$60*(F89+F94+F98+F90)-Assumptions!$C$56)/(1-Assumptions!$C$60)) -> 617639.86 | G99: =MAX(0,(Assumptions!$C$60*(G89+G94+G98+G90)-Assumptions!$C$56)/(1-Assumptions!$C$60)) -> 617656.97 | H99: =MAX(0,(Assumptions!$C$60*(H89+H94+H98+H90)-Assumptions!$C$56)/(1-Assumptions!$C$60)) -> 617657.29 | I99: =MAX(0,(Assumptions!$C$60*(I89+I94+I98+I90)-Assumptions!$C$56)/(1-Assumptions!$C$60)) -> 617657.3 | J99: =MAX(0,(Assumptions!$C$60*(J89+J94+J98+J90)-Assumptions!$C$56)/(1-Assumptions!$C$60)) -> 617657.3 | K99: =MAX(0,(Assumptions!$C$60*(K89+K94+K98+K90)-Assumptions!$C$56)/(1-Assumptions!$C$60)) -> 617657.3 | ... M99: =MAX(0,(Assumptions!$C$60*(M89+M94+M98+M90)-Assumptions!$C$56)/(1-Assumptions!$C$60)) -> 617657.3
B100: T_F | D100: =D89+D99+D94+D98+D90 -> 38123885 | E100: =E89+E99+E94+E98+E90 -> 38549334 | F100: =F89+F99+F94+F98+F90 -> 38556207 | G100: =G89+G99+G94+G98+G90 -> 38556338 | H100: =H89+H99+H94+H98+H90 -> 38556341 | I100: =I89+I99+I94+I98+I90 -> 38556341 | J100: =J89+J99+J94+J98+J90 -> 38556341 | K100: =K89+K99+K94+K98+K90 -> 38556341 | ... M100: =M89+M99+M94+M98+M90 -> 38556341
B101: Pre-money FD | D101: =D100-D90 -> 37457219 | E101: =E100-E90 -> 37612903 | F101: =F100-F90 -> 37615884 | G101: =G100-G90 -> 37615941 | H101: =H100-H90 -> 37615942 | I101: =I100-I90 -> 37615942 | J101: =J100-J90 -> 37615942 | K101: =K100-K90 -> 37615942 | ... M101: =M100-M90 -> 37615942
B102: F_PPS_new | D102: =Assumptions!$C$62/D101 -> 32.036549 | E102: =Assumptions!$C$62/E101 -> 31.903945 | F102: =Assumptions!$C$62/F101 -> 31.901417 | G102: =Assumptions!$C$62/G101 -> 31.901369 | H102: =Assumptions!$C$62/H101 -> 31.901368 | I102: =Assumptions!$C$62/I101 -> 31.901368 | J102: =Assumptions!$C$62/J101 -> 31.901368 | K102: =Assumptions!$C$62/K101 -> 31.901368 | ... M102: =Assumptions!$C$62/M101 -> 31.901368
B104: Distributable_$2B | D104: =Assumptions!$C$17+Assumptions!$C$42*Assumptions!$C$55 -> 2002500000 | E104: =Assumptions!$C$17+Assumptions!$C$42*Assumptions!$C$55 -> 2002500000 | F104: =Assumptions!$C$17+Assumptions!$C$42*Assumptions!$C$55 -> 2002500000 | G104: =Assumptions!$C$17+Assumptions!$C$42*Assumptions!$C$55 -> 2002500000 | H104: =Assumptions!$C$17+Assumptions!$C$42*Assumptions!$C$55 -> 2002500000
B105: F pref? | D105: FALSE | E105: =Assumptions!$C$7>D116 -> 0 | F105: =Assumptions!$C$7>E116 -> 0 | G105: =Assumptions!$C$7>F116 -> 0 | H105: =Assumptions!$C$7>G116 -> 0
B106: E pref? | D106: FALSE | E106: =Assumptions!$C$41*Assumptions!$C$28>D117 -> 0 | F106: =Assumptions!$C$41*Assumptions!$C$28>E117 -> 0 | G106: =Assumptions!$C$41*Assumptions!$C$28>F117 -> 0 | H106: =Assumptions!$C$41*Assumptions!$C$28>G117 -> 0
B107: D pref? | D107: FALSE | E107: =Assumptions!$C$40*Assumptions!$C$27>D118 -> 1 | F107: =Assumptions!$C$40*Assumptions!$C$27>E118 -> 1 | G107: =Assumptions!$C$40*Assumptions!$C$27>F118 -> 1 | H107: =Assumptions!$C$40*Assumptions!$C$27>G118 -> 1
B108: C pref? | D108: FALSE | E108: =Assumptions!$C$38*Assumptions!$C$25>D119 -> 0 | F108: =Assumptions!$C$38*Assumptions!$C$25>E119 -> 0 | G108: =Assumptions!$C$38*Assumptions!$C$25>F119 -> 0 | H108: =Assumptions!$C$38*Assumptions!$C$25>G119 -> 0
B109: B pref? | D109: FALSE | E109: =Assumptions!$C$37*Assumptions!$C$24>D120 -> 0 | F109: =Assumptions!$C$37*Assumptions!$C$24>E120 -> 0 | G109: =Assumptions!$C$37*Assumptions!$C$24>F120 -> 0 | H109: =Assumptions!$C$37*Assumptions!$C$24>G120 -> 0
B110: A pref? | D110: FALSE | E110: =Assumptions!$C$36*Assumptions!$C$23>D121 -> 0 | F110: =Assumptions!$C$36*Assumptions!$C$23>E121 -> 0 | G110: =Assumptions!$C$36*Assumptions!$C$23>F121 -> 0 | H110: =Assumptions!$C$36*Assumptions!$C$23>G121 -> 0
B111: Seed pref? | D111: FALSE | E111: =Assumptions!$C$35*Assumptions!$C$22>D122 -> 0 | F111: =Assumptions!$C$35*Assumptions!$C$22>E122 -> 0 | G111: =Assumptions!$C$35*Assumptions!$C$22>F122 -> 0 | H111: =Assumptions!$C$35*Assumptions!$C$22>G122 -> 0
B112: Sum prefs | D112: =IF(D105,Assumptions!$C$7,0)+IF(D106,Assumptions!$C$41*Assumptions!$C$28,0)+IF(D107,Assumptions!$C$40*Assumptions!$C$27,0)+IF(D108,Assumptions!$C$38*Assumptions!$C$25,0)+IF(D109,Assumptions!$C$37*Assumptions!$C$24,0)+IF(D110,Assumptions!$C$36*Assumptions!$C$23,0)+IF(D111,Assumptions!$C$35*Assumptions!$C$22,0) -> 0 | E112: =IF(E105,Assumptions!$C$7,0)+IF(E106,Assumptions!$C$41*Assumptions!$C$28,0)+IF(E107,Assumptions!$C$40*Assumptions!$C$27,0)+IF(E108,Assumptions!$C$38*Assumptions!$C$25,0)+IF(E109,Assumptions!$C$37*Assumptions!$C$24,0)+IF(E110,Assumptions!$C$36*Assumptions!$C$23,0)+IF(E111,Assumptions!$C$35*Assumptions!$C$22,0) -> 100000020 | F112: =IF(F105,Assumptions!$C$7,0)+IF(F106,Assumptions!$C$41*Assumptions!$C$28,0)+IF(F107,Assumptions!$C$40*Assumptions!$C$27,0)+IF(F108,Assumptions!$C$38*Assumptions!$C$25,0)+IF(F109,Assumptions!$C$37*Assumptions!$C$24,0)+IF(F110,Assumptions!$C$36*Assumptions!$C$23,0)+IF(F111,Assumptions!$C$35*Assumptions!$C$22,0) -> 100000020 | G112: =IF(G105,Assumptions!$C$7,0)+IF(G106,Assumptions!$C$41*Assumptions!$C$28,0)+IF(G107,Assumptions!$C$40*Assumptions!$C$27,0)+IF(G108,Assumptions!$C$38*Assumptions!$C$25,0)+IF(G109,Assumptions!$C$37*Assumptions!$C$24,0)+IF(G110,Assumptions!$C$36*Assumptions!$C$23,0)+IF(G111,Assumptions!$C$35*Assumptions!$C$22,0) -> 100000020 | H112: =IF(H105,Assumptions!$C$7,0)+IF(H106,Assumptions!$C$41*Assumptions!$C$28,0)+IF(H107,Assumptions!$C$40*Assumptions!$C$27,0)+IF(H108,Assumptions!$C$38*Assumptions!$C$25,0)+IF(H109,Assumptions!$C$37*Assumptions!$C$24,0)+IF(H110,Assumptions!$C$36*Assumptions!$C$23,0)+IF(H111,Assumptions!$C$35*Assumptions!$C$22,0) -> 100000020
B113: Convert pool | D113: =IF(D105,0,M90)+IF(D106,0,Assumptions!$C$41*Assumptions!$C$28/M87)+IF(D107,0,Assumptions!$C$40*Assumptions!$C$27/M85)+IF(D108,0,Assumptions!$C$38)+IF(D109,0,Assumptions!$C$37)+IF(D110,0,Assumptions!$C$36)+IF(D111,0,Assumptions!$C$35)+((Assumptions!$C$31+Assumptions!$C$32+Assumptions!$C$33+Assumptions!$C$34)+M94+M98+Assumptions!$C$42) -> 36044016 | E113: =IF(E105,0,M90)+IF(E106,0,Assumptions!$C$41*Assumptions!$C$28/M87)+IF(E107,0,Assumptions!$C$40*Assumptions!$C$27/M85)+IF(E108,0,Assumptions!$C$38)+IF(E109,0,Assumptions!$C$37)+IF(E110,0,Assumptions!$C$36)+IF(E111,0,Assumptions!$C$35)+((Assumptions!$C$31+Assumptions!$C$32+Assumptions!$C$33+Assumptions!$C$34)+M94+M98+Assumptions!$C$42) -> 34303733 | F113: =IF(F105,0,M90)+IF(F106,0,Assumptions!$C$41*Assumptions!$C$28/M87)+IF(F107,0,Assumptions!$C$40*Assumptions!$C$27/M85)+IF(F108,0,Assumptions!$C$38)+IF(F109,0,Assumptions!$C$37)+IF(F110,0,Assumptions!$C$36)+IF(F111,0,Assumptions!$C$35)+((Assumptions!$C$31+Assumptions!$C$32+Assumptions!$C$33+Assumptions!$C$34)+M94+M98+Assumptions!$C$42) -> 34303733 | G113: =IF(G105,0,M90)+IF(G106,0,Assumptions!$C$41*Assumptions!$C$28/M87)+IF(G107,0,Assumptions!$C$40*Assumptions!$C$27/M85)+IF(G108,0,Assumptions!$C$38)+IF(G109,0,Assumptions!$C$37)+IF(G110,0,Assumptions!$C$36)+IF(G111,0,Assumptions!$C$35)+((Assumptions!$C$31+Assumptions!$C$32+Assumptions!$C$33+Assumptions!$C$34)+M94+M98+Assumptions!$C$42) -> 34303733 | H113: =IF(H105,0,M90)+IF(H106,0,Assumptions!$C$41*Assumptions!$C$28/M87)+IF(H107,0,Assumptions!$C$40*Assumptions!$C$27/M85)+IF(H108,0,Assumptions!$C$38)+IF(H109,0,Assumptions!$C$37)+IF(H110,0,Assumptions!$C$36)+IF(H111,0,Assumptions!$C$35)+((Assumptions!$C$31+Assumptions!$C$32+Assumptions!$C$33+Assumptions!$C$34)+M94+M98+Assumptions!$C$42) -> 34303733
B114: Residual | D114: =D104-D112 -> 2002500000 | E114: =E104-E112 -> 1902499980 | F114: =F104-F112 -> 1902499980 | G114: =G104-G112 -> 1902499980 | H114: =H104-H112 -> 1902499980
B115: Common PPS @ exit | D115: =D114/D113 -> 55.557071 | E115: =E114/E113 -> 55.460436 | F115: =F114/F113 -> 55.460436 | G115: =G114/G113 -> 55.460436 | H115: =H114/H113 -> 55.460436
B116: F convert $ | D116: =M90*D115 -> 52245790 | E116: =M90*E115 -> 52154914 | F116: =M90*F115 -> 52154914 | G116: =M90*G115 -> 52154914 | H116: =M90*H115 -> 52154914
B117: E convert $ | D117: =Assumptions!$C$41*Assumptions!$C$28/M87*D115 -> 3.4205284e+08 | E117: =Assumptions!$C$41*Assumptions!$C$28/M87*E115 -> 3.4145787e+08 | F117: =Assumptions!$C$41*Assumptions!$C$28/M87*F115 -> 3.4145787e+08 | G117: =Assumptions!$C$41*Assumptions!$C$28/M87*G115 -> 3.4145787e+08 | H117: =Assumptions!$C$41*Assumptions!$C$28/M87*H115 -> 3.4145787e+08
B118: D convert $ | D118: =Assumptions!$C$40*Assumptions!$C$27/M85*D115 -> 96685048 | E118: =Assumptions!$C$40*Assumptions!$C$27/M85*E115 -> 96516874 | F118: =Assumptions!$C$40*Assumptions!$C$27/M85*F115 -> 96516874 | G118: =Assumptions!$C$40*Assumptions!$C$27/M85*G115 -> 96516874 | H118: =Assumptions!$C$40*Assumptions!$C$27/M85*H115 -> 96516874
B119: C convert $ | D119: =Assumptions!$C$38*D115 -> 1.3333697e+08 | E119: =Assumptions!$C$38*E115 -> 1.3310505e+08 | F119: =Assumptions!$C$38*F115 -> 1.3310505e+08 | G119: =Assumptions!$C$38*G115 -> 1.3310505e+08 | H119: =Assumptions!$C$38*H115 -> 1.3310505e+08
B120: B convert $ | D120: =Assumptions!$C$37*D115 -> 1.6667121e+08 | E120: =Assumptions!$C$37*E115 -> 1.6638131e+08 | F120: =Assumptions!$C$37*F115 -> 1.6638131e+08 | G120: =Assumptions!$C$37*G115 -> 1.6638131e+08 | H120: =Assumptions!$C$37*H115 -> 1.6638131e+08
B121: A convert $ | D121: =Assumptions!$C$36*D115 -> 2.7778536e+08 | E121: =Assumptions!$C$36*E115 -> 2.7730218e+08 | F121: =Assumptions!$C$36*F115 -> 2.7730218e+08 | G121: =Assumptions!$C$36*G115 -> 2.7730218e+08 | H121: =Assumptions!$C$36*H115 -> 2.7730218e+08
B122: Seed convert $ | D122: =Assumptions!$C$35*D115 -> 2.7778536e+08 | E122: =Assumptions!$C$35*E115 -> 2.7730218e+08 | F122: =Assumptions!$C$35*F115 -> 2.7730218e+08 | G122: =Assumptions!$C$35*G115 -> 2.7730218e+08 | H122: =Assumptions!$C$35*H115 -> 2.7730218e+08
B125: Solver: ESOP=15%, Pre=$1,200M
B126: pre_money ($) | C126: =Assumptions!$C$62 -> 1200000000
B127: esop_target | C127: =Assumptions!$C$61 -> 0.15
...

Sheet Return-Solver
B2: Kelvin Dynamics — Return Solver
B3: Required Series F ownership % to achieve 3x / 4x on our $10M check.
B5: Per-Exit Data (from Waterfall)
B6: Exit value ($) | C6: =Waterfall!C6 -> 700000000 | D6: =Waterfall!D6 -> 1200000000 | E6: =Waterfall!E6 -> 2000000000 | F6: =Waterfall!F6 -> 4000000000 | G6: =Waterfall!G6 -> 8000000000
B7: F class total proceeds ($) | C7: =Waterfall!C20 -> 30000000 | D7: =Waterfall!D20 -> 30000000 | E7: =Waterfall!E20 -> 44846573 | F7: =Waterfall!F20 -> 89785811 | G7: =Waterfall!G20 -> 1.7951554e+08
B8: F election | C8: =Waterfall!C11 -> preference | D8: =Waterfall!D11 -> preference | E8: =Waterfall!E11 -> convert | F8: =Waterfall!F11 -> convert | G8: =Waterfall!G11 -> convert
B9: $ per F share at exit | C9: =C7/'Pro-Forma'!$C$29 -> 37.29976 | D9: =D7/'Pro-Forma'!$C$29 -> 37.29976 | E9: =E7/'Pro-Forma'!$C$29 -> 55.758881 | F9: =F7/'Pro-Forma'!$C$29 -> 111.63297 | G9: =G7/'Pro-Forma'!$C$29 -> 223.19622
B10: $ per 1% of T_F (in F class) | C10: ='Pro-Forma'!$C$31*C9*0.01 -> 14300000 | D10: ='Pro-Forma'!$C$31*D9*0.01 -> 14300000 | E10: ='Pro-Forma'!$C$31*E9*0.01 -> 21376867 | F10: ='Pro-Forma'!$C$31*F9*0.01 -> 42797903 | G10: ='Pro-Forma'!$C$31*G9*0.01 -> 85569074
B12: Required Series F Ownership % (of post-F FD)
B13: Target 3x ($) | C13: =Assumptions!$C$67 -> 30000000 | D13: =Assumptions!$C$67 -> 30000000 | E13: =Assumptions!$C$67 -> 30000000 | F13: =Assumptions!$C$67 -> 30000000 | G13: =Assumptions!$C$67 -> 30000000
B14: Req. ownership % (3x) | C14: =Assumptions!$C$67*'Pro-Forma'!$C$29/('Pro-Forma'!$C$31*C7) -> 0.020979021 | D14: =Assumptions!$C$67*'Pro-Forma'!$C$29/('Pro-Forma'!$C$31*D7) -> 0.020979021 | E14: =Assumptions!$C$67*'Pro-Forma'!$C$29/('Pro-Forma'!$C$31*E7) -> 0.014033862 | F14: =Assumptions!$C$67*'Pro-Forma'!$C$29/('Pro-Forma'!$C$31*F7) -> 0.0070096892 | G14: =Assumptions!$C$67*'Pro-Forma'!$C$29/('Pro-Forma'!$C$31*G7) -> 0.0035059395
B15: Feasible? (3x) | C15: =IF(OR(C14<=0,C14>1),"INFEASIBLE","feasible") -> feasible | D15: =IF(OR(D14<=0,D14>1),"INFEASIBLE","feasible") -> feasible | E15: =IF(OR(E14<=0,E14>1),"INFEASIBLE","feasible") -> feasible | F15: =IF(OR(F14<=0,F14>1),"INFEASIBLE","feasible") -> feasible | G15: =IF(OR(G14<=0,G14>1),"INFEASIBLE","feasible") -> feasible
B16: Target 4x ($) | C16: =Assumptions!$C$68 -> 40000000 | D16: =Assumptions!$C$68 -> 40000000 | E16: =Assumptions!$C$68 -> 40000000 | F16: =Assumptions!$C$68 -> 40000000 | G16: =Assumptions!$C$68 -> 40000000
B17: Req. ownership % (4x) | C17: =Assumptions!$C$68*'Pro-Forma'!$C$29/('Pro-Forma'!$C$31*C7) -> 0.027972028 | D17: =Assumptions!$C$68*'Pro-Forma'!$C$29/('Pro-Forma'!$C$31*D7) -> 0.027972028 | E17: =Assumptions!$C$68*'Pro-Forma'!$C$29/('Pro-Forma'!$C$31*E7) -> 0.018711816 | F17: =Assumptions!$C$68*'Pro-Forma'!$C$29/('Pro-Forma'!$C$31*F7) -> 0.0093462523 | G17: =Assumptions!$C$68*'Pro-Forma'!$C$29/('Pro-Forma'!$C$31*G7) -> 0.004674586
B18: Feasible? (4x) | C18: =IF(OR(C17<=0,C17>1),"INFEASIBLE","feasible") -> feasible | D18: =IF(OR(D17<=0,D17>1),"INFEASIBLE","feasible") -> feasible | E18: =IF(OR(E17<=0,E17>1),"INFEASIBLE","feasible") -> feasible | F18: =IF(OR(F17<=0,F17>1),"INFEASIBLE","feasible") -> feasible | G18: =IF(OR(G17<=0,G17>1),"INFEASIBLE","feasible") -> feasible
B20: Reference
B21: T_F (post-F FD shares) | C21: ='Pro-Forma'!$C$31 -> 38338048
B22: F_S (Series F primary shares) | C22: ='Pro-Forma'!$C$29 -> 804294.71
B23: Our base ownership % of T_F | C23: =(Assumptions!$C$11/'Pro-Forma'!$C$28)/'Pro-Forma'!$C$31 -> 0.006993007
B24: Our base $ at $2B exit | C24: =C23*'Pro-Forma'!$C$31*E9 -> 14948858
