Workbook

Sheet Assumptions
A1: Kelvin Dynamics - Series F Analysis | H1: Label library | I1: Label text
H2: label_2 | I2: Iteration
A3: Assumption / source fact | B3: Value | C3: Units | D3: Source / note | E3: Key | H3: label_3 | I3: Top-up input
A4: Formula constant: zero | B4: 0 | D4: Workbook formula helper | E4: zero | H4: label_4 | I4: F PPS
A5: Formula constant: one | B5: 1 | D5: Workbook formula helper | E5: one | H5: label_5 | I5: F primary shares
A6: series f pre money usd | B6: 1400000000 | C6: USD | D6: Series F pre-money valuation | E6: series_f_pre_money_usd | H6: label_6 | I6: Prior as-converted
A7: series f primary raise usd | B7: 30000000 | C7: USD | D7: New Series F primary capital | E7: series_f_primary_raise_usd | H7: label_7 | I7: Note A cap PPS
A8: series f secondary raise usd | B8: 15000000 | C8: USD | D8: Secondary tender from founders | E8: series_f_secondary_raise_usd | H8: label_8 | I8: Note A discount PPS
A9: series f tender pps multiplier | B9: 0.85 | C9: fraction | D9: Tender PPS = multiplier x F_PPS | E9: series_f_tender_pps_multiplier | H9: label_9 | I9: Note A conversion PPS
A10: esop refresh target post f | B10: 0.13 | C10: fraction | D10: Post-F option pool as fraction of post-F FD | E10: esop_refresh_target_post_f | H10: label_10 | I10: Note A branch
A11: our fund check usd | B11: 10000000 | C11: USD | D11: Our fund's Series F primary check (= 1/3 of primary) | E11: our_fund_check_usd | H11: label_11 | I11: Note A shares
A12: f lead primary check usd | B12: 20000000 | C12: USD | D12: F_LEAD's Series F primary check (= 2/3 of primary) | E12: f_lead_primary_check_usd | H12: label_12 | I12: Note B cap PPS
A13: option strike usd | B13: 1 | C13: USD | D13: Option exercise price for issued options at exit | E13: option_strike_usd | H13: label_13 | I13: Note B discount PPS
A14: pre f options issued | B14: 2500000 | C14: shares | D14: Issued options outstanding pre-F (carryover from v3 post-E) | E14: pre_f_options_issued | H14: label_14 | I14: Note B conversion PPS
A15: pre f options unissued | B15: 1894667 | C15: shares | D15: Unissued option pool pre-F (carryover from v3 post-E refresh) | E15: pre_f_options_unissued | H15: label_15 | I15: Note B branch
A16: pre f fd total | B16: 36617961 | C16: shares | D16: Pre-F fully-diluted share count (post-E T from v3) | E16: pre_f_fd_total | H16: label_16 | I16: Note B shares
A17: pre-F option pool (issued + unissued) | B17: =Assumptions!$B$14+Assumptions!$B$15 -> 4394667 | C17: shares | D17: Derived from RoundTerms | E17: pre_f_option_pool | H17: label_17 | I17: ESOP top-up output
A18: pre-F founder common | B18: 8000000 | C18: shares | D18: Stakeholders | E18: pre_f_founder_common | H18: label_18 | I18: Post-F FD
A19: pre-F employee RSA common | B19: 1000000 | C19: shares | D19: Stakeholders | E19: pre_f_rsa_common | H19: label_19 | I19: Seed NCP
A20: pre-F common + RSAs | B20: 9000000 | C20: shares | D20: Stakeholders | E20: pre_f_common_rsa | H20: label_20 | I20: Seed ratio
A21: Broad-based WA A: pre-F FD | B21: 36617961 | C21: shares | D21: RoundTerms | E21: ad_pre_f_broad_based_fd | H21: label_21 | I21: Seed as-converted
A22: Broad-based WA new-money numerator | B22: 30000000 | C22: USD | D22: Notes excluded from B and C | E22: ad_new_money_usd | H22: label_22 | I22: Series A NCP
A23: Notes excluded from AD B and C | B23: TRUE | C23: boolean | D23: Instruction | E23: notes_excluded_from_ad_b_c | H23: label_23 | I23: Series A ratio
A24: Exit scenario 1 | B24: 700000000 | C24: USD | D24: exit_value_1_usd | E24: exit_value_1_usd | H24: label_24 | I24: Series A as-converted
A25: Exit scenario 2 | B25: 1200000000 | C25: USD | D25: exit_value_2_usd | E25: exit_value_2_usd | H25: label_25 | I25: Series B NCP
A26: Exit scenario 3 (sensitivity reference) | B26: 2000000000 | C26: USD | D26: exit_value_3_usd | E26: exit_value_3_usd | H26: label_26 | I26: Series B ratio
A27: Exit scenario 4 | B27: 4000000000 | C27: USD | D27: exit_value_4_usd | E27: exit_value_4_usd | H27: label_27 | I27: Series B as-converted
A28: Exit scenario 5 | B28: 8000000000 | C28: USD | D28: exit_value_5_usd | E28: exit_value_5_usd | H28: label_28 | I28: Series C NCP
A29: Sensitivity grid axis: low ESOP refresh | B29: 0.11 | C29: fraction | D29: sensitivity_esop_low | E29: sensitivity_esop_low | H29: label_29 | I29: Series C ratio
A30: Sensitivity grid axis: base ESOP refresh | B30: 0.13 | C30: fraction | D30: sensitivity_esop_base | E30: sensitivity_esop_base | H30: label_30 | I30: Series C as-converted
A31: Sensitivity grid axis: high ESOP refresh | B31: 0.15 | C31: fraction | D31: sensitivity_esop_high | E31: sensitivity_esop_high | H31: label_31 | I31: Series D NCP
A32: Sensitivity grid axis: low Series F pre-money | B32: 1200000000 | C32: USD | D32: sensitivity_pre_low_usd | E32: sensitivity_pre_low_usd | H32: label_32 | I32: Series D ratio
A33: Sensitivity grid axis: base Series F pre-money | B33: 1400000000 | C33: USD | D33: sensitivity_pre_base_usd | E33: sensitivity_pre_base_usd | H33: label_33 | I33: Series D as-converted
A34: Sensitivity grid axis: high Series F pre-money | B34: 1800000000 | C34: USD | D34: sensitivity_pre_high_usd | E34: sensitivity_pre_high_usd | H34: label_34 | I34: Series E NCP
A35: Return-solver target: 3x net | B35: 3 | C35: multiple | D35: return_multiple_3x | E35: return_multiple_3x | H35: label_35 | I35: Series E ratio
... A67: Series F aggregate 1x preference | B67: 30000000 | C67: USD | D67: RoundTerms | E67: series_f_invested_usd | H67: label_67 | I67: Discount-implied PPS
A68: Our fund share of Series F primary | B68: =Assumptions!$B$11/Assumptions!$B$7 -> 0.33333333 | C68: fraction | D68: Derived from RoundTerms | E68: our_primary_fraction | H68: label_68 | I68: Conversion PPS
A69: Note A principal | B69: 5000000 | C69: USD | D69: Notes | E69: note_a_principal_usd | H69: label_69 | I69: Branch
A70: Note A valuation cap | B70: 1000000000 | C70: USD | D70: Notes | E70: note_a_cap_usd | H70: label_70 | I70: Shares issued
A71: Note A discount | B71: 0.2 | C71: fraction | D71: Notes | E71: note_a_discount | H71: label_71 | I71: Note A
A72: Note A accrued interest | B72: 0 | C72: USD | D72: Notes | E72: note_a_interest_usd | H72: label_72 | I72: Note B
A73: Note B principal | B73: 3000000 | C73: USD | D73: Notes | E73: note_b_principal_usd | H73: label_73 | I73: Tender block
A74: Note B valuation cap | B74: 1600000000 | C74: USD | D74: Notes | E74: note_b_cap_usd | H74: label_74 | I74: Tender PPS
A75: Note B discount | B75: 0.15 | C75: fraction | D75: Notes | E75: note_b_discount | H75: label_75 | I75: Tender shares
A76: Note B accrued interest | B76: 0 | C76: USD | D76: Notes | E76: note_b_interest_usd | H76: label_76 | I76: F1 tendered shares
A77: series_f waterfall election weight | B77: 64 | C77: binary weight | D77: Workbook helper | E77: series_f_waterfall_weight | H77: label_77 | I77: F2 tendered shares
A78: series_e waterfall election weight | B78: 32 | C78: binary weight | D78: Workbook helper | E78: series_e_waterfall_weight | H78: label_78 | I78: F3 tendered shares
A79: series_d waterfall election weight | B79: 16 | C79: binary weight | D79: Workbook helper | E79: series_d_waterfall_weight | H79: label_79 | I79: F_LEAD secondary common
A80: series_c waterfall election weight | B80: 8 | C80: binary weight | D80: Workbook helper | E80: series_c_waterfall_weight | H80: label_80 | I80: Post-F cap table
... A83: seed waterfall election weight | B83: 1 | C83: binary weight | D83: Workbook helper | E83: seed_waterfall_weight | H83: label_83 | I83: Security class
H84: label_84 | I84: Common shares
A85: Stakeholders source table | H85: label_85 | I85: Preferred / note / option shares
A86: ID | B86: Role | C86: Common shares | D86: Preferred class | E86: Preferred shares | H86: label_86 | I86: FD shares
A87: F1 | B87: Founder (CEO) | C87: 4000000 | E87: 0 | H87: label_87 | I87: Ownership %
A88: F2 | B88: Founder (CTO) | C88: 2500000 | E88: 0 | H88: label_88 | I88: Common
A89: F3 | B89: Founder (Chief Scientist) | C89: 1500000 | E89: 0 | H89: label_89 | I89: RSA common
A90: E1 | B90: Employee RSA | C90: 100000 | E90: 0 | H90: label_90 | I90: Note A common-equivalent
A91: E2 | B91: Employee RSA | C91: 100000 | E91: 0 | H91: label_91 | I91: Note B common-equivalent
A92: E3 | B92: Employee RSA | C92: 100000 | E92: 0 | H92: label_92 | I92: Series F preferred
A93: E4 | B93: Employee RSA | C93: 100000 | E93: 0 | H93: label_93 | I93: Secondary common
A94: E5 | B94: Employee RSA | C94: 100000 | E94: 0 | H94: label_94 | I94: Option holders
A95: E6 | B95: Employee RSA | C95: 100000 | E95: 0 | H95: label_95 | I95: Issued option holders
A96: E7 | B96: Employee RSA | C96: 100000 | E96: 0 | H96: label_96 | I96: Issued options
A97: E8 | B97: Employee RSA | C97: 100000 | E97: 0 | H97: label_97 | I97: Unissued option pool
A98: E9 | B98: Employee RSA | C98: 100000 | E98: 0 | H98: label_98 | I98: Pre-money refresh pool
A99: E10 | B99: Employee RSA | C99: 100000 | E99: 0 | H99: label_99 | I99: Unissued options
A100: SEED1 | B100: Seed preferred LP | C100: 0 | D100: Seed | E100: 5000000 | H100: label_100 | I100: Ownership check
A101: A1 | B101: Series A preferred LP | C101: 0 | D101: Series A | E101: 5000000 | H101: label_101 | I101: Code
A102: B1 | B102: Series B preferred LP | C102: 0 | D102: Series B | E102: 3000000 | H102: label_102 | I102: F bit
A103: C1 | B103: Series C preferred LP | C103: 0 | D103: Series C | E103: 2400000 | H103: label_103 | I103: E bit
A104: D1 | B104: Series D preferred LP | C104: 0 | D104: Series D | E104: 1720627 | H104: label_104 | I104: D bit
A105: E1_INV | B105: Series E preferred LP | C105: 0 | D105: Series E | E105: 610267 | H105: label_105 | I105: C bit
A106: E2_INV | B106: Series E preferred LP | C106: 0 | D106: Series E | E106: 610267 | H106: label_106 | I106: B bit
A107: E3_INV | B107: Series E preferred LP | C107: 0 | D107: Series E | E107: 610267 | H107: label_107 | I107: A bit
A108: E4_INV | B108: Series E preferred LP | C108: 0 | D108: Series E | E108: 610267 | H108: label_108 | I108: Seed bit
A109: E5_INV | B109: Series E preferred LP | C109: 0 | D109: Series E | E109: 610267 | H109: label_109 | I109: F pref paid
A110: E6_INV | B110: Series E preferred LP | C110: 0 | D110: Series E | E110: 610267 | H110: label_110 | I110: E pref paid
A111: E7_INV | B111: Series E preferred LP | C111: 0 | D111: Series E | E111: 610267 | H111: label_111 | I111: D pref paid
... A114: E10_INV | B114: Series E preferred LP | C114: 0 | D114: Series E | E114: 610264 | H114: label_114 | I114: A pref paid
A115: NA1 | B115: Convertible Note A holder | C115: 0 | E115: 0 | H115: label_115 | I115: Seed pref paid
A116: NB1 | B116: Convertible Note B holder | C116: 0 | E116: 0 | H116: label_116 | I116: Total pref
A117: F_LEAD | B117: Series F lead investor | C117: 0 | E117: 0 | H117: label_117 | I117: Residual
A118: F_FUND | B118: Our fund (Series F primary) | C118: 0 | E118: 0 | H118: label_118 | I118: Non-option conv shares
H119: label_119 | I119: Options ITM
H120: label_120 | I120: Common PPS
H121: label_121 | I121: F proceeds
H122: label_122 | I122: E proceeds
H123: label_123 | I123: D proceeds
H124: label_124 | I124: C proceeds
H125: label_125 | I125: B proceeds
H126: label_126 | I126: A proceeds
H127: label_127 | I127: Seed proceeds
H128: label_128 | I128: Notes proceeds
H129: label_129 | I129: Common + RSAs proceeds
H130: label_130 | I130: Issued options net
... H176: label_176 | I176: Total

Sheet Pro-Forma
A1: =Assumptions!$I$37 -> Kelvin Dynamics - Series F Pro-Forma
A3: =Assumptions!$I$38 -> Series F PPS | B3: =$C$172 -> 37.628498
A4: =Assumptions!$I$39 -> Series F new shares | B4: =$D$172 -> 797268.07
A5: =Assumptions!$I$40 -> Our fund Series F shares | B5: =Assumptions!$B$11/$C$172 -> 265756.02
A6: =Assumptions!$I$41 -> F_LEAD primary Series F shares | B6: =Assumptions!$B$12/$C$172 -> 531512.05
A7: =Assumptions!$I$42 -> ESOP top-up shares | B7: =$P$172 -> 587882.23
A8: =Assumptions!$I$43 -> Post-F FD shares | B8: =$Q$172 -> 38327302
A9: =Assumptions!$I$44 -> Our post-F ownership | B9: =B5/$Q$172 -> 0.0069338568
A10: =Assumptions!$I$45 -> Series F post-F ownership | B10: =$D$172/$Q$172 -> 0.02080157
A12: =Assumptions!$I$46 -> Anti-dilution block
A13: =Assumptions!$I$47 -> Series | B13: =Assumptions!$I$48 -> F PPS < OCP | C13: =Assumptions!$I$49 -> OCP | D13: =Assumptions!$I$50 -> New conversion price | E13: =Assumptions!$I$51 -> New ratio | F13: =Assumptions!$I$52 -> As-converted shares | G13: =Assumptions!$I$53 -> AD B shares | H13: =Assumptions!$I$54 -> AD C shares
A14: =Assumptions!$I$55 -> Seed | B14: =$C$172<Assumptions!$B$37 -> 0 | C14: =Assumptions!$B$37 -> 1 | D14: =$R$172 -> 1 | E14: =$S$172 -> 1 | F14: =$T$172 -> 5000000 | G14: =Assumptions!$B$22/Assumptions!$B$37 -> 30000000 | H14: =Assumptions!$B$22/$C$172 -> 797268.07
A15: =Assumptions!$I$56 -> Series A | B15: =$C$172<Assumptions!$B$42 -> 0 | C15: =Assumptions!$B$42 -> 3 | D15: =$U$172 -> 3 | E15: =$V$172 -> 1 | F15: =$W$172 -> 5000000 | G15: =Assumptions!$B$22/Assumptions!$B$42 -> 10000000 | H15: =Assumptions!$B$22/$C$172 -> 797268.07
A16: =Assumptions!$I$57 -> Series B | B16: =$C$172<Assumptions!$B$47 -> 0 | C16: =Assumptions!$B$47 -> 10 | D16: =$X$172 -> 10 | E16: =$Y$172 -> 1 | F16: =$Z$172 -> 3000000 | G16: =Assumptions!$B$22/Assumptions!$B$47 -> 3000000 | H16: =Assumptions!$B$22/$C$172 -> 797268.07
A17: =Assumptions!$I$58 -> Series C | B17: =$C$172<Assumptions!$B$52 -> 0 | C17: =Assumptions!$B$52 -> 25 | D17: =$AA$172 -> 25 | E17: =$AB$172 -> 1 | F17: =$AC$172 -> 2400000 | G17: =Assumptions!$B$22/Assumptions!$B$52 -> 1200000 | H17: =Assumptions!$B$22/$C$172 -> 797268.07
A18: =Assumptions!$I$59 -> Series D | B18: =$C$172<Assumptions!$B$57 -> 1 | C18: =Assumptions!$B$57 -> 58.118347 | D18: =$AD$172 -> 57.681736 | E18: =$AE$172 -> 1.0401906 | F18: =$AF$172 -> 1733651.4 | G18: =Assumptions!$B$22/Assumptions!$B$57 -> 516188.12 | H18: =Assumptions!$B$22/$C$172 -> 797268.07
A19: =Assumptions!$I$60 -> Series E | B19: =$C$172<Assumptions!$B$62 -> 1 | C19: =Assumptions!$B$62 -> 49.158311 | D19: =$AG$172 -> 48.912626 | E19: =$AH$172 -> 1.0050229 | F19: =$AI$172 -> 6133320.3 | G19: =Assumptions!$B$22/Assumptions!$B$62 -> 610273.2 | H19: =Assumptions!$B$22/$C$172 -> 797268.07
A22: =Assumptions!$I$61 -> Notes block
A23: =Assumptions!$I$62 -> Note | B23: =Assumptions!$I$63 -> Principal | C23: =Assumptions!$I$64 -> Cap | D23: =Assumptions!$I$65 -> Discount | E23: =Assumptions!$I$66 -> Cap-implied PPS | F23: =Assumptions!$I$67 -> Discount-implied PPS | G23: =Assumptions!$I$68 -> Conversion PPS | H23: =Assumptions!$I$69 -> Branch | I23: =Assumptions!$I$70 -> Shares issued
A24: =Assumptions!$I$71 -> Note A | B24: =Assumptions!$B$69 -> 5000000 | C24: =Assumptions!$B$70 -> 1000000000 | D24: =Assumptions!$B$71 -> 0.2 | E24: =$F$172 -> 26.778553 | F24: =$G$172 -> 30.102798 | G24: =$H$172 -> 26.778553 | H24: =IF(E24<=F24,"cap","discount") -> cap | I24: =$J$172 -> 186716.59
A25: =Assumptions!$I$72 -> Note B | B25: =Assumptions!$B$73 -> 3000000 | C25: =Assumptions!$B$74 -> 1600000000 | D25: =Assumptions!$B$75 -> 0.15 | E25: =$K$172 -> 42.739338 | F25: =$L$172 -> 31.984223 | G25: =$M$172 -> 31.984223 | H25: =IF(E25<=F25,"cap","discount") -> discount | I25: =$O$172 -> 93796.243
A29: =Assumptions!$I$73 -> Tender block
A30: =Assumptions!$I$74 -> Tender PPS | B30: =Assumptions!$B$9*$C$172 -> 31.984223
A31: =Assumptions!$I$75 -> Tender shares | B31: =Assumptions!$B$8/B30 -> 468981.22
A32: =Assumptions!$I$76 -> F1 tendered shares | B32: =B31*Assumptions!$C$87/Assumptions!$B$18 -> 234490.61
A33: =Assumptions!$I$77 -> F2 tendered shares | B33: =B31*Assumptions!$C$88/Assumptions!$B$18 -> 146556.63
A34: =Assumptions!$I$78 -> F3 tendered shares | B34: =B31*Assumptions!$C$89/Assumptions!$B$18 -> 87933.978
A35: =Assumptions!$I$79 -> F_LEAD secondary common | B35: =B31 -> 468981.22
A38: =Assumptions!$I$80 -> Post-F cap table
A39: =Assumptions!$I$81 -> Stakeholder | B39: =Assumptions!$I$82 -> Role | C39: =Assumptions!$I$83 -> Security class | D39: =Assumptions!$I$84 -> Common shares | E39: =Assumptions!$I$85 -> Preferred / note / option shares | F39: =Assumptions!$I$86 -> FD shares | G39: =Assumptions!$I$87 -> Ownership %
A40: =Assumptions!$A$87 -> F1 | B40: =Assumptions!$B$87 -> Founder (CEO) | C40: =Assumptions!$I$88 -> Common | D40: =Assumptions!$C$87-B32 -> 3765509.4 | E40: =Assumptions!$B$4 -> 0 | F40: =D40 -> 3765509.4 | G40: =F40/$Q$172 -> 0.098246138
A41: =Assumptions!$A$88 -> F2 | B41: =Assumptions!$B$88 -> Founder (CTO) | C41: =Assumptions!$I$88 -> Common | D41: =Assumptions!$C$88-B33 -> 2353443.4 | E41: =Assumptions!$B$4 -> 0 | F41: =D41 -> 2353443.4 | G41: =F41/$Q$172 -> 0.061403836
A42: =Assumptions!$A$89 -> F3 | B42: =Assumptions!$B$89 -> Founder (Chief Scientist) | C42: =Assumptions!$I$88 -> Common | D42: =Assumptions!$C$89-B34 -> 1412066 | E42: =Assumptions!$B$4 -> 0 | F42: =D42 -> 1412066 | G42: =F42/$Q$172 -> 0.036842302
A43: =Assumptions!$A$90 -> E1 | B43: =Assumptions!$B$90 -> Employee RSA | C43: =Assumptions!$I$89 -> RSA common | D43: =Assumptions!$C$90 -> 100000 | E43: =Assumptions!$B$4 -> 0 | F43: =D43 -> 100000 | G43: =F43/$Q$172 -> 0.0026091062
A44: =Assumptions!$A$91 -> E2 | B44: =Assumptions!$B$91 -> Employee RSA | C44: =Assumptions!$I$89 -> RSA common | D44: =Assumptions!$C$91 -> 100000 | E44: =Assumptions!$B$4 -> 0 | F44: =D44 -> 100000 | G44: =F44/$Q$172 -> 0.0026091062
A45: =Assumptions!$A$92 -> E3 | B45: =Assumptions!$B$92 -> Employee RSA | C45: =Assumptions!$I$89 -> RSA common | D45: =Assumptions!$C$92 -> 100000 | E45: =Assumptions!$B$4 -> 0 | F45: =D45 -> 100000 | G45: =F45/$Q$172 -> 0.0026091062
A46: =Assumptions!$A$93 -> E4 | B46: =Assumptions!$B$93 -> Employee RSA | C46: =Assumptions!$I$89 -> RSA common | D46: =Assumptions!$C$93 -> 100000 | E46: =Assumptions!$B$4 -> 0 | F46: =D46 -> 100000 | G46: =F46/$Q$172 -> 0.0026091062
A47: =Assumptions!$A$94 -> E5 | B47: =Assumptions!$B$94 -> Employee RSA | C47: =Assumptions!$I$89 -> RSA common | D47: =Assumptions!$C$94 -> 100000 | E47: =Assumptions!$B$4 -> 0 | F47: =D47 -> 100000 | G47: =F47/$Q$172 -> 0.0026091062
A48: =Assumptions!$A$95 -> E6 | B48: =Assumptions!$B$95 -> Employee RSA | C48: =Assumptions!$I$89 -> RSA common | D48: =Assumptions!$C$95 -> 100000 | E48: =Assumptions!$B$4 -> 0 | F48: =D48 -> 100000 | G48: =F48/$Q$172 -> 0.0026091062
A49: =Assumptions!$A$96 -> E7 | B49: =Assumptions!$B$96 -> Employee RSA | C49: =Assumptions!$I$89 -> RSA common | D49: =Assumptions!$C$96 -> 100000 | E49: =Assumptions!$B$4 -> 0 | F49: =D49 -> 100000 | G49: =F49/$Q$172 -> 0.0026091062
A50: =Assumptions!$A$97 -> E8 | B50: =Assumptions!$B$97 -> Employee RSA | C50: =Assumptions!$I$89 -> RSA common | D50: =Assumptions!$C$97 -> 100000 | E50: =Assumptions!$B$4 -> 0 | F50: =D50 -> 100000 | G50: =F50/$Q$172 -> 0.0026091062
A51: =Assumptions!$A$98 -> E9 | B51: =Assumptions!$B$98 -> Employee RSA | C51: =Assumptions!$I$89 -> RSA common | D51: =Assumptions!$C$98 -> 100000 | E51: =Assumptions!$B$4 -> 0 | F51: =D51 -> 100000 | G51: =F51/$Q$172 -> 0.0026091062
A52: =Assumptions!$A$99 -> E10 | B52: =Assumptions!$B$99 -> Employee RSA | C52: =Assumptions!$I$89 -> RSA common | D52: =Assumptions!$C$99 -> 100000 | E52: =Assumptions!$B$4 -> 0 | F52: =D52 -> 100000 | G52: =F52/$Q$172 -> 0.0026091062
A53: =Assumptions!$A$100 -> SEED1 | B53: =Assumptions!$B$100 -> Seed preferred LP | C53: =Assumptions!$I$55 -> Seed | D53: =Assumptions!$B$4 -> 0 | E53: =Assumptions!$E$100*$S$172 -> 5000000 | F53: =E53 -> 5000000 | G53: =F53/$Q$172 -> 0.13045531
A54: =Assumptions!$A$101 -> A1 | B54: =Assumptions!$B$101 -> Series A preferred LP | C54: =Assumptions!$I$56 -> Series A | D54: =Assumptions!$B$4 -> 0 | E54: =Assumptions!$E$101*$V$172 -> 5000000 | F54: =E54 -> 5000000 | G54: =F54/$Q$172 -> 0.13045531
A55: =Assumptions!$A$102 -> B1 | B55: =Assumptions!$B$102 -> Series B preferred LP | C55: =Assumptions!$I$57 -> Series B | D55: =Assumptions!$B$4 -> 0 | E55: =Assumptions!$E$102*$Y$172 -> 3000000 | F55: =E55 -> 3000000 | G55: =F55/$Q$172 -> 0.078273185
A56: =Assumptions!$A$103 -> C1 | B56: =Assumptions!$B$103 -> Series C preferred LP | C56: =Assumptions!$I$58 -> Series C | D56: =Assumptions!$B$4 -> 0 | E56: =Assumptions!$E$103*$AB$172 -> 2400000 | F56: =E56 -> 2400000 | G56: =F56/$Q$172 -> 0.062618548
A57: =Assumptions!$A$104 -> D1 | B57: =Assumptions!$B$104 -> Series D preferred LP | C57: =Assumptions!$I$59 -> Series D | D57: =Assumptions!$B$4 -> 0 | E57: =$AF$172 -> 1733651.4 | F57: =$AF$172 -> 1733651.4 | G57: =F57/$Q$172 -> 0.045232805
A58: =Assumptions!$A$105 -> E1_INV | B58: =Assumptions!$B$105 -> Series E preferred LP | C58: =Assumptions!$I$60 -> Series E | D58: =Assumptions!$B$4 -> 0 | E58: =Assumptions!$E$105*$AH$172 -> 613332.33 | F58: =E58 -> 613332.33 | G58: =F58/$Q$172 -> 0.016002492
A59: =Assumptions!$A$106 -> E2_INV | B59: =Assumptions!$B$106 -> Series E preferred LP | C59: =Assumptions!$I$60 -> Series E | D59: =Assumptions!$B$4 -> 0 | E59: =Assumptions!$E$106*$AH$172 -> 613332.33 | F59: =E59 -> 613332.33 | G59: =F59/$Q$172 -> 0.016002492
A60: =Assumptions!$A$107 -> E3_INV | B60: =Assumptions!$B$107 -> Series E preferred LP | C60: =Assumptions!$I$60 -> Series E | D60: =Assumptions!$B$4 -> 0 | E60: =Assumptions!$E$107*$AH$172 -> 613332.33 | F60: =E60 -> 613332.33 | G60: =F60/$Q$172 -> 0.016002492
A61: =Assumptions!$A$108 -> E4_INV | B61: =Assumptions!$B$108 -> Series E preferred LP | C61: =Assumptions!$I$60 -> Series E | D61: =Assumptions!$B$4 -> 0 | E61: =Assumptions!$E$108*$AH$172 -> 613332.33 | F61: =E61 -> 613332.33 | G61: =F61/$Q$172 -> 0.016002492
A62: =Assumptions!$A$109 -> E5_INV | B62: =Assumptions!$B$109 -> Series E preferred LP | C62: =Assumptions!$I$60 -> Series E | D62: =Assumptions!$B$4 -> 0 | E62: =Assumptions!$E$109*$AH$172 -> 613332.33 | F62: =E62 -> 613332.33 | G62: =F62/$Q$172 -> 0.016002492
A63: =Assumptions!$A$110 -> E6_INV | B63: =Assumptions!$B$110 -> Series E preferred LP | C63: =Assumptions!$I$60 -> Series E | D63: =Assumptions!$B$4 -> 0 | E63: =Assumptions!$E$110*$AH$172 -> 613332.33 | F63: =E63 -> 613332.33 | G63: =F63/$Q$172 -> 0.016002492
A64: =Assumptions!$A$111 -> E7_INV | B64: =Assumptions!$B$111 -> Series E preferred LP | C64: =Assumptions!$I$60 -> Series E | D64: =Assumptions!$B$4 -> 0 | E64: =Assumptions!$E$111*$AH$172 -> 613332.33 | F64: =E64 -> 613332.33 | G64: =F64/$Q$172 -> 0.016002492
A65: =Assumptions!$A$112 -> E8_INV | B65: =Assumptions!$B$112 -> Series E preferred LP | C65: =Assumptions!$I$60 -> Series E | D65: =Assumptions!$B$4 -> 0 | E65: =Assumptions!$E$112*$AH$172 -> 613332.33 | F65: =E65 -> 613332.33 | G65: =F65/$Q$172 -> 0.016002492
A66: =Assumptions!$A$113 -> E9_INV | B66: =Assumptions!$B$113 -> Series E preferred LP | C66: =Assumptions!$I$60 -> Series E | D66: =Assumptions!$B$4 -> 0 | E66: =Assumptions!$E$113*$AH$172 -> 613332.33 | F66: =E66 -> 613332.33 | G66: =F66/$Q$172 -> 0.016002492
A67: =Assumptions!$A$114 -> E10_INV | B67: =Assumptions!$B$114 -> Series E preferred LP | C67: =Assumptions!$I$60 -> Series E | D67: =Assumptions!$B$4 -> 0 | E67: =Assumptions!$E$114*$AH$172 -> 613329.31 | F67: =E67 -> 613329.31 | G67: =F67/$Q$172 -> 0.016002413
A68: =Assumptions!$A$115 -> NA1 | B68: =Assumptions!$B$115 -> Convertible Note A holder | C68: =Assumptions!$I$90 -> Note A common-equivalent | D68: =Assumptions!$B$4 -> 0 | E68: =$J$172 -> 186716.59 | F68: =E68 -> 186716.59 | G68: =F68/$Q$172 -> 0.004871634
A69: =Assumptions!$A$116 -> NB1 | B69: =Assumptions!$B$116 -> Convertible Note B holder | C69: =Assumptions!$I$91 -> Note B common-equivalent | D69: =Assumptions!$B$4 -> 0 | E69: =$O$172 -> 93796.243 | F69: =E69 -> 93796.243 | G69: =F69/$Q$172 -> 0.0024472436
A70: =Assumptions!$A$117 -> F_LEAD | B70: =Assumptions!$B$117 -> Series F lead investor | C70: =Assumptions!$I$92 -> Series F preferred | D70: =Assumptions!$B$4 -> 0 | E70: =Assumptions!$B$12/$C$172 -> 531512.05 | F70: =E70 -> 531512.05 | G70: =F70/$Q$172 -> 0.013867714
A71: =Assumptions!$A$117 -> F_LEAD | B71: =Assumptions!$B$117 -> Series F lead investor | C71: =Assumptions!$I$93 -> Secondary common | D71: =B35 -> 468981.22 | E71: =Assumptions!$B$4 -> 0 | F71: =D71 -> 468981.22 | G71: =F71/$Q$172 -> 0.012236218
A72: =Assumptions!$A$118 -> F_FUND | B72: =Assumptions!$B$118 -> Our fund (Series F primary) | C72: =Assumptions!$I$92 -> Series F preferred | D72: =Assumptions!$B$4 -> 0 | E72: =Assumptions!$B$11/$C$172 -> 265756.02 | F72: =E72 -> 265756.02 | G72: =F72/$Q$172 -> 0.0069338568
A73: =Assumptions!$I$94 -> Option holders | B73: =Assumptions!$I$95 -> Issued option holders | C73: =Assumptions!$I$96 -> Issued options | D73: =Assumptions!$B$4 -> 0 | E73: =Assumptions!$B$14 -> 2500000 | F73: =E73 -> 2500000 | G73: =F73/$Q$172 -> 0.065227655
A74: =Assumptions!$I$97 -> Unissued option pool | B74: =Assumptions!$I$98 -> Pre-money refresh pool | C74: =Assumptions!$I$99 -> Unissued options | D74: =Assumptions!$B$4 -> 0 | E74: =Assumptions!$B$15+$P$172 -> 2482549.2 | F74: =E74 -> 2482549.2 | G74: =F74/$Q$172 -> 0.064772345
A75: =Assumptions!$I$100 -> Ownership check | F75: =SUM(F40:F74) -> 38327302 | G75: =SUM(G40:G74) -> 1
A92: =Assumptions!$I$2 -> Iteration | B92: =Assumptions!$I$3 -> Top-up input | C92: =Assumptions!$I$4 -> F PPS | D92: =Assumptions!$I$5 -> F primary shares | E92: =Assumptions!$I$6 -> Prior as-converted | F92: =Assumptions!$I$7 -> Note A cap PPS | G92: =Assumptions!$I$8 -> Note A discount PPS | H92: =Assumptions!$I$9 -> Note A conversion PPS | I92: =Assumptions!$I$10 -> Note A branch | J92: =Assumptions!$I$11 -> Note A shares | K92: =Assumptions!$I$12 -> Note B cap PPS | L92: =Assumptions!$I$13 -> Note B discount PPS | M92: =Assumptions!$I$14 -> Note B conversion PPS | N92: =Assumptions!$I$15 -> Note B branch | O92: =Assumptions!$I$16 -> Note B shares | P92: =Assumptions!$I$17 -> ESOP top-up output | Q92: =Assumptions!$I$18 -> Post-F FD | R92: =Assumptions!$I$19 -> Seed NCP | S92: =Assumptions!$I$20 -> Seed ratio | T92: =Assumptions!$I$21 -> Seed as-converted | U92: =Assumptions!$I$22 -> Series A NCP | V92: =Assumptions!$I$23 -> Series A ratio | W92: =Assumptions!$I$24 -> Series A as-converted | X92: =Assumptions!$I$25 -> Series B NCP | Y92: =Assumptions!$I$26 -> Series B ratio | Z92: =Assumptions!$I$27 -> Series B as-converted | AA92: =Assumptions!$I$28 -> Series C NCP | AB92: =Assumptions!$I$29 -> Series C ratio | AC92: =Assumptions!$I$30 -> Series C as-converted | AD92: =Assumptions!$I$31 -> Series D NCP | AE92: =Assumptions!$I$32 -> Series D ratio | AF92: =Assumptions!$I$33 -> Series D as-converted | AG92: =Assumptions!$I$34 -> Series E NCP | AH92: =Assumptions!$I$35 -> Series E ratio | AI92: =Assumptions!$I$36 -> Series E as-converted
A93: =ROW()-ROW($A$93)+Assumptions!$B$4 -> 0 | B93: =Assumptions!$B$4 -> 0 | C93: =Assumptions!$B$6/(Assumptions!$B$16+$B$93) -> 38.232604 | D93: =Assumptions!$B$7/$C$93 -> 784670.59 | E93: =$T$93+$W$93+$Z$93+$AC$93+$AF$93+$AI$93 -> 23264323 | F93: =Assumptions!$B$70/(Assumptions!$B$20+Assumptions!$B$17+$B$93+$E$93+Assumptions!$B$4) -> 27.278438 | G93: =$C$93*(1-Assumptions!$B$71) -> 30.586083 | H93: =MIN($F$93,$G$93) -> 27.278438 | I93: =IF($F$93<=$G$93,"cap","discount") -> cap | J93: =Assumptions!$B$69/$H$93 -> 183294.95 | K93: =Assumptions!$B$74/(Assumptions!$B$20+Assumptions!$B$17+$B$93+$E$93+$J$93) -> 43.42836 | L93: =$C$93*(1-Assumptions!$B$75) -> 32.497713 | M93: =MIN($K$93,$L$93) -> 32.497713 | N93: =IF($K$93<=$L$93,"cap","discount") -> discount | O93: =Assumptions!$B$73/$M$93 -> 92314.187 | P93: =MAX(Assumptions!$B$4,(Assumptions!$B$10*(Assumptions!$B$20+$E$93+Assumptions!$B$17+$J$93+$O$93+$D$93)-Assumptions!$B$17)/(1-Assumptions!$B$10)) -> 584871.32 | Q93: =Assumptions!$B$20+$E$93+Assumptions!$B$17+$P$93+$J$93+$O$93+$D$93 -> 38304141 | R93: =IF($C$93<Assumptions!$B$37,Assumptions!$B$37*(Assumptions!$B$21+Assumptions!$B$22/Assumptions!$B$37)/(Assumptions!$B$21+Assumptions!$B$22/$C$93),Assumptions!$B$37) -> 1 | S93: =Assumptions!$B$38/$R$93 -> 1 | T93: =Assumptions!$B$39*$S$93 -> 5000000 | U93: =IF($C$93<Assumptions!$B$42,Assumptions!$B$42*(Assumptions!$B$21+Assumptions!$B$22/Assumptions!$B$42)/(Assumptions!$B$21+Assumptions!$B$22/$C$93),Assumptions!$B$42) -> 3 | V93: =Assumptions!$B$43/$U$93 -> 1 | W93: =Assumptions!$B$44*$V$93 -> 5000000 | X93: =IF($C$93<Assumptions!$B$47,Assumptions!$B$47*(Assumptions!$B$21+Assumptions!$B$22/Assumptions!$B$47)/(Assumptions!$B$21+Assumptions!$B$22/$C$93),Assumptions!$B$47) -> 10 | Y93: =Assumptions!$B$48/$X$93 -> 1 | Z93: =Assumptions!$B$49*$Y$93 -> 3000000 | AA93: =IF($C$93<Assumptions!$B$52,Assumptions!$B$52*(Assumptions!$B$21+Assumptions!$B$22/Assumptions!$B$52)/(Assumptions!$B$21+Assumptions!$B$22/$C$93),Assumptions!$B$52) -> 25 | AB93: =Assumptions!$B$53/$AA$93 -> 1 | AC93: =Assumptions!$B$54*$AB$93 -> 2400000 | AD93: =IF($C$93<Assumptions!$B$57,Assumptions!$B$57*(Assumptions!$B$21+Assumptions!$B$22/Assumptions!$B$57)/(Assumptions!$B$21+Assumptions!$B$22/$C$93),Assumptions!$B$57) -> 57.701164 | AE93: =Assumptions!$B$58/$AD$93 -> 1.0398404 | AF93: =Assumptions!$B$59*$AE$93 -> 1733067.7 | AG93: =IF($C$93<Assumptions!$B$62,Assumptions!$B$62*(Assumptions!$B$21+Assumptions!$B$22/Assumptions!$B$62)/(Assumptions!$B$21+Assumptions!$B$22/$C$93),Assumptions!$B$62) -> 48.9291 | AH93: =Assumptions!$B$63/$AG$93 -> 1.0046845 | AI93: =Assumptions!$B$64*$AH$93 -> 6131255.2
A94: =ROW()-ROW($A$93)+Assumptions!$B$4 -> 1 | B94: =$P$93 -> 584871.32 | C94: =Assumptions!$B$6/(Assumptions!$B$16+$B$94) -> 37.631543 | D94: =Assumptions!$B$7/$C$94 -> 797203.55 | E94: =$T$94+$W$94+$Z$94+$AC$94+$AF$94+$AI$94 -> 23266958 | F94: =Assumptions!$B$70/(Assumptions!$B$20+Assumptions!$B$17+$B$94+$E$94+$O$93) -> 26.781785 | G94: =$C$94*(1-Assumptions!$B$71) -> 30.105235 | H94: =MIN($F$94,$G$94) -> 26.781785 | I94: =IF($F$94<=$G$94,"cap","discount") -> cap | J94: =Assumptions!$B$69/$H$94 -> 186694.05 | K94: =Assumptions!$B$74/(Assumptions!$B$20+Assumptions!$B$17+$B$94+$E$94+$J$94) -> 42.742817 | L94: =$C$94*(1-Assumptions!$B$75) -> 31.986812 | M94: =MIN($K$94,$L$94) -> 31.986812 | N94: =IF($K$94<=$L$94,"cap","discount") -> discount | O94: =Assumptions!$B$73/$M$94 -> 93788.653 | P94: =MAX(Assumptions!$B$4,(Assumptions!$B$10*(Assumptions!$B$20+$E$94+Assumptions!$B$17+$J$94+$O$94+$D$94)-Assumptions!$B$17)/(1-Assumptions!$B$10)) -> 587866.06 | Q94: =Assumptions!$B$20+$E$94+Assumptions!$B$17+$P$94+$J$94+$O$94+$D$94 -> 38327177 | R94: =IF($C$94<Assumptions!$B$37,Assumptions!$B$37*(Assumptions!$B$21+Assumptions!$B$22/Assumptions!$B$37)/(Assumptions!$B$21+Assumptions!$B$22/$C$94),Assumptions!$B$37) -> 1 | S94: =Assumptions!$B$38/$R$94 -> 1 | T94: =Assumptions!$B$39*$S$94 -> 5000000 | U94: =IF($C$94<Assumptions!$B$42,Assumptions!$B$42*(Assumptions!$B$21+Assumptions!$B$22/Assumptions!$B$42)/(Assumptions!$B$21+Assumptions!$B$22/$C$94),Assumptions!$B$42) -> 3 | V94: =Assumptions!$B$43/$U$94 -> 1 | W94: =Assumptions!$B$44*$V$94 -> 5000000 | X94: =IF($C$94<Assumptions!$B$47,Assumptions!$B$47*(Assumptions!$B$21+Assumptions!$B$22/Assumptions!$B$47)/(Assumptions!$B$21+Assumptions!$B$22/$C$94),Assumptions!$B$47) -> 10 | Y94: =Assumptions!$B$48/$X$94 -> 1 | Z94: =Assumptions!$B$49*$Y$94 -> 3000000 | AA94: =IF($C$94<Assumptions!$B$52,Assumptions!$B$52*(Assumptions!$B$21+Assumptions!$B$22/Assumptions!$B$52)/(Assumptions!$B$21+Assumptions!$B$22/$C$94),Assumptions!$B$52) -> 25 | AB94: =Assumptions!$B$53/$AA$94 -> 1 | AC94: =Assumptions!$B$54*$AB$94 -> 2400000 | AD94: =IF($C$94<Assumptions!$B$57,Assumptions!$B$57*(Assumptions!$B$21+Assumptions!$B$22/Assumptions!$B$57)/(Assumptions!$B$21+Assumptions!$B$22/$C$94),Assumptions!$B$57) -> 57.681835 | AE94: =Assumptions!$B$58/$AD$94 -> 1.0401888 | AF94: =Assumptions!$B$59*$AE$94 -> 1733648.4 | AG94: =IF($C$94<Assumptions!$B$62,Assumptions!$B$62*(Assumptions!$B$21+Assumptions!$B$22/Assumptions!$B$62)/(Assumptions!$B$21+Assumptions!$B$22/$C$94),Assumptions!$B$62) -> 48.912711 | AH94: =Assumptions!$B$63/$AG$94 -> 1.0050212 | AI94: =Assumptions!$B$64*$AH$94 -> 6133309.7
A95: =ROW()-ROW($A$93)+Assumptions!$B$4 -> 2 | B95: =$P$94 -> 587866.06 | C95: =Assumptions!$B$6/(Assumptions!$B$16+$B$95) -> 37.628514 | D95: =Assumptions!$B$7/$C$95 -> 797267.72 | E95: =$T$95+$W$95+$Z$95+$AC$95+$AF$95+$AI$95 -> 23266972 | F95: =Assumptions!$B$70/(Assumptions!$B$20+Assumptions!$B$17+$B$95+$E$95+$O$94) -> 26.77857 | G95: =$C$95*(1-Assumptions!$B$71) -> 30.102812 | H95: =MIN($F$95,$G$95) -> 26.77857 | I95: =IF($F$95<=$G$95,"cap","discount") -> cap | J95: =Assumptions!$B$69/$H$95 -> 186716.47 | K95: =Assumptions!$B$74/(Assumptions!$B$20+Assumptions!$B$17+$B$95+$E$95+$J$95) -> 42.739357 | L95: =$C$95*(1-Assumptions!$B$75) -> 31.984237 | M95: =MIN($K$95,$L$95) -> 31.984237 | N95: =IF($K$95<=$L$95,"cap","discount") -> discount | O95: =Assumptions!$B$73/$M$95 -> 93796.203 | P95: =MAX(Assumptions!$B$4,(Assumptions!$B$10*(Assumptions!$B$20+$E$95+Assumptions!$B$17+$J$95+$O$95+$D$95)-Assumptions!$B$17)/(1-Assumptions!$B$10)) -> 587882.14 | Q95: =Assumptions!$B$20+$E$95+Assumptions!$B$17+$P$95+$J$95+$O$95+$D$95 -> 38327301 | R95: =IF($C$95<Assumptions!$B$37,Assumptions!$B$37*(Assumptions!$B$21+Assumptions!$B$22/Assumptions!$B$37)/(Assumptions!$B$21+Assumptions!$B$22/$C$95),Assumptions!$B$37) -> 1 | S95: =Assumptions!$B$38/$R$95 -> 1 | T95: =Assumptions!$B$39*$S$95 -> 5000000 | U95: =IF($C$95<Assumptions!$B$42,Assumptions!$B$42*(Assumptions!$B$21+Assumptions!$B$22/Assumptions!$B$42)/(Assumptions!$B$21+Assumptions!$B$22/$C$95),Assumptions!$B$42) -> 3 | V95: =Assumptions!$B$43/$U$95 -> 1 | W95: =Assumptions!$B$44*$V$95 -> 5000000 | X95: =IF($C$95<Assumptions!$B$47,Assumptions!$B$47*(Assumptions!$B$21+Assumptions!$B$22/Assumptions!$B$47)/(Assumptions!$B$21+Assumptions!$B$22/$C$95),Assumptions!$B$47) -> 10 | Y95: =Assumptions!$B$48/$X$95 -> 1 | Z95: =Assumptions!$B$49*$Y$95 -> 3000000 | AA95: =IF($C$95<Assumptions!$B$52,Assumptions!$B$52*(Assumptions!$B$21+Assumptions!$B$22/Assumptions!$B$52)/(Assumptions!$B$21+Assumptions!$B$22/$C$95),Assumptions!$B$52) -> 25 | AB95: =Assumptions!$B$53/$AA$95 -> 1 | AC95: =Assumptions!$B$54*$AB$95 -> 2400000 | AD95: =IF($C$95<Assumptions!$B$57,Assumptions!$B$57*(Assumptions!$B$21+Assumptions!$B$22/Assumptions!$B$57)/(Assumptions!$B$21+Assumptions!$B$22/$C$95),Assumptions!$B$57) -> 57.681736 | AE95: =Assumptions!$B$58/$AD$95 -> 1.0401906 | AF95: =Assumptions!$B$59*$AE$95 -> 1733651.3 | AG95: =IF($C$95<Assumptions!$B$62,Assumptions!$B$62*(Assumptions!$B$21+Assumptions!$B$22/Assumptions!$B$62)/(Assumptions!$B$21+Assumptions!$B$22/$C$95),Assumptions!$B$62) -> 48.912627 | AH95: =Assumptions!$B$63/$AG$95 -> 1.0050229 | AI95: =Assumptions!$B$64*$AH$95 -> 6133320.2
A96: =ROW()-ROW($A$93)+Assumptions!$B$4 -> 3 | B96: =$P$95 -> 587882.14 | C96: =Assumptions!$B$6/(Assumptions!$B$16+$B$96) -> 37.628498 | D96: =Assumptions!$B$7/$C$96 -> 797268.07 | E96: =$T$96+$W$96+$Z$96+$AC$96+$AF$96+$AI$96 -> 23266972 | F96: =Assumptions!$B$70/(Assumptions!$B$20+Assumptions!$B$17+$B$96+$E$96+$O$95) -> 26.778553 | G96: =$C$96*(1-Assumptions!$B$71) -> 30.102799 | H96: =MIN($F$96,$G$96) -> 26.778553 | I96: =IF($F$96<=$G$96,"cap","discount") -> cap | J96: =Assumptions!$B$69/$H$96 -> 186716.58 | K96: =Assumptions!$B$74/(Assumptions!$B$20+Assumptions!$B$17+$B$96+$E$96+$J$96) -> 42.739338 | L96: =$C$96*(1-Assumptions!$B$75) -> 31.984223 | M96: =MIN($K$96,$L$96) -> 31.984223 | N96: =IF($K$96<=$L$96,"cap","discount") -> discount | O96: =Assumptions!$B$73/$M$96 -> 93796.243 | P96: =MAX(Assumptions!$B$4,(Assumptions!$B$10*(Assumptions!$B$20+$E$96+Assumptions!$B$17+$J$96+$O$96+$D$96)-Assumptions!$B$17)/(1-Assumptions!$B$10)) -> 587882.23 | Q96: =Assumptions!$B$20+$E$96+Assumptions!$B$17+$P$96+$J$96+$O$96+$D$96 -> 38327302 | R96: =IF($C$96<Assumptions!$B$37,Assumptions!$B$37*(Assumptions!$B$21+Assumptions!$B$22/Assumptions!$B$37)/(Assumptions!$B$21+Assumptions!$B$22/$C$96),Assumptions!$B$37) -> 1 | S96: =Assumptions!$B$38/$R$96 -> 1 | T96: =Assumptions!$B$39*$S$96 -> 5000000 | U96: =IF($C$96<Assumptions!$B$42,Assumptions!$B$42*(Assumptions!$B$21+Assumptions!$B$22/Assumptions!$B$42)/(Assumptions!$B$21+Assumptions!$B$22/$C$96),Assumptions!$B$42) -> 3 | V96: =Assumptions!$B$43/$U$96 -> 1 | W96: =Assumptions!$B$44*$V$96 -> 5000000 | X96: =IF($C$96<Assumptions!$B$47,Assumptions!$B$47*(Assumptions!$B$21+Assumptions!$B$22/Assumptions!$B$47)/(Assumptions!$B$21+Assumptions!$B$22/$C$96),Assumptions!$B$47) -> 10 | Y96: =Assumptions!$B$48/$X$96 -> 1 | Z96: =Assumptions!$B$49*$Y$96 -> 3000000 | AA96: =IF($C$96<Assumptions!$B$52,Assumptions!$B$52*(Assumptions!$B$21+Assumptions!$B$22/Assumptions!$B$52)/(Assumptions!$B$21+Assumptions!$B$22/$C$96),Assumptions!$B$52) -> 25 | AB96: =Assumptions!$B$53/$AA$96 -> 1 | AC96: =Assumptions!$B$54*$AB$96 -> 2400000 | AD96: =IF($C$96<Assumptions!$B$57,Assumptions!$B$57*(Assumptions!$B$21+Assumptions!$B$22/Assumptions!$B$57)/(Assumptions!$B$21+Assumptions!$B$22/$C$96),Assumptions!$B$57) -> 57.681736 | AE96: =Assumptions!$B$58/$AD$96 -> 1.0401906 | AF96: =Assumptions!$B$59*$AE$96 -> 1733651.4 | AG96: =IF($C$96<Assumptions!$B$62,Assumptions!$B$62*(Assumptions!$B$21+Assumptions!$B$22/Assumptions!$B$62)/(Assumptions!$B$21+Assumptions!$B$22/$C$96),Assumptions!$B$62) -> 48.912626 | AH96: =Assumptions!$B$63/$AG$96 -> 1.0050229 | AI96: =Assumptions!$B$64*$AH$96 -> 6133320.3
A97: =ROW()-ROW($A$93)+Assumptions!$B$4 -> 4 | B97: =$P$96 -> 587882.23 | C97: =Assumptions!$B$6/(Assumptions!$B$16+$B$97) -> 37.628498 | D97: =Assumptions!$B$7/$C$97 -> 797268.07 | E97: =$T$97+$W$97+$Z$97+$AC$97+$AF$97+$AI$97 -> 23266972 | F97: =Assumptions!$B$70/(Assumptions!$B$20+Assumptions!$B$17+$B$97+$E$97+$O$96) -> 26.778553 | G97: =$C$97*(1-Assumptions!$B$71) -> 30.102798 | H97: =MIN($F$97,$G$97) -> 26.778553 | I97: =IF($F$97<=$G$97,"cap","discount") -> cap | J97: =Assumptions!$B$69/$H$97 -> 186716.59 | K97: =Assumptions!$B$74/(Assumptions!$B$20+Assumptions!$B$17+$B$97+$E$97+$J$97) -> 42.739338 | L97: =$C$97*(1-Assumptions!$B$75) -> 31.984223 | M97: =MIN($K$97,$L$97) -> 31.984223 | N97: =IF($K$97<=$L$97,"cap","discount") -> discount | O97: =Assumptions!$B$73/$M$97 -> 93796.243 | P97: =MAX(Assumptions!$B$4,(Assumptions!$B$10*(Assumptions!$B$20+$E$97+Assumptions!$B$17+$J$97+$O$97+$D$97)-Assumptions!$B$17)/(1-Assumptions!$B$10)) -> 587882.23 | Q97: =Assumptions!$B$20+$E$97+Assumptions!$B$17+$P$97+$J$97+$O$97+$D$97 -> 38327302 | R97: =IF($C$97<Assumptions!$B$37,Assumptions!$B$37*(Assumptions!$B$21+Assumptions!$B$22/Assumptions!$B$37)/(Assumptions!$B$21+Assumptions!$B$22/$C$97),Assumptions!$B$37) -> 1 | S97: =Assumptions!$B$38/$R$97 -> 1 | T97: =Assumptions!$B$39*$S$97 -> 5000000 | U97: =IF($C$97<Assumptions!$B$42,Assumptions!$B$42*(Assumptions!$B$21+Assumptions!$B$22/Assumptions!$B$42)/(Assumptions!$B$21+Assumptions!$B$22/$C$97),Assumptions!$B$42) -> 3 | V97: =Assumptions!$B$43/$U$97 -> 1 | W97: =Assumptions!$B$44*$V$97 -> 5000000 | X97: =IF($C$97<Assumptions!$B$47,Assumptions!$B$47*(Assumptions!$B$21+Assumptions!$B$22/Assumptions!$B$47)/(Assumptions!$B$21+Assumptions!$B$22/$C$97),Assumptions!$B$47) -> 10 | Y97: =Assumptions!$B$48/$X$97 -> 1 | Z97: =Assumptions!$B$49*$Y$97 -> 3000000 | AA97: =IF($C$97<Assumptions!$B$52,Assumptions!$B$52*(Assumptions!$B$21+Assumptions!$B$22/Assumptions!$B$52)/(Assumptions!$B$21+Assumptions!$B$22/$C$97),Assumptions!$B$52) -> 25 | AB97: =Assumptions!$B$53/$AA$97 -> 1 | AC97: =Assumptions!$B$54*$AB$97 -> 2400000 | AD97: =IF($C$97<Assumptions!$B$57,Assumptions!$B$57*(Assumptions!$B$21+Assumptions!$B$22/Assumptions!$B$57)/(Assumptions!$B$21+Assumptions!$B$22/$C$97),Assumptions!$B$57) -> 57.681736 | AE97: =Assumptions!$B$58/$AD$97 -> 1.0401906 | AF97: =Assumptions!$B$59*$AE$97 -> 1733651.4 | AG97: =IF($C$97<Assumptions!$B$62,Assumptions!$B$62*(Assumptions!$B$21+Assumptions!$B$22/Assumptions!$B$62)/(Assumptions!$B$21+Assumptions!$B$22/$C$97),Assumptions!$B$62) -> 48.912626 | AH97: =Assumptions!$B$63/$AG$97 -> 1.0050229 | AI97: =Assumptions!$B$64*$AH$97 -> 6133320.3
A98: =ROW()-ROW($A$93)+Assumptions!$B$4 -> 5 | B98: =$P$97 -> 587882.23 | C98: =Assumptions!$B$6/(Assumptions!$B$16+$B$98) -> 37.628498 | D98: =Assumptions!$B$7/$C$98 -> 797268.07 | E98: =$T$98+$W$98+$Z$98+$AC$98+$AF$98+$AI$98 -> 23266972 | F98: =Assumptions!$B$70/(Assumptions!$B$20+Assumptions!$B$17+$B$98+$E$98+$O$97) -> 26.778553 | G98: =$C$98*(1-Assumptions!$B$71) -> 30.102798 | H98: =MIN($F$98,$G$98) -> 26.778553 | I98: =IF($F$98<=$G$98,"cap","discount") -> cap | J98: =Assumptions!$B$69/$H$98 -> 186716.59 | K98: =Assumptions!$B$74/(Assumptions!$B$20+Assumptions!$B$17+$B$98+$E$98+$J$98) -> 42.739338 | L98: =$C$98*(1-Assumptions!$B$75) -> 31.984223 | M98: =MIN($K$98,$L$98) -> 31.984223 | N98: =IF($K$98<=$L$98,"cap","discount") -> discount | O98: =Assumptions!$B$73/$M$98 -> 93796.243 | P98: =MAX(Assumptions!$B$4,(Assumptions!$B$10*(Assumptions!$B$20+$E$98+Assumptions!$B$17+$J$98+$O$98+$D$98)-Assumptions!$B$17)/(1-Assumptions!$B$10)) -> 587882.23 | Q98: =Assumptions!$B$20+$E$98+Assumptions!$B$17+$P$98+$J$98+$O$98+$D$98 -> 38327302 | R98: =IF($C$98<Assumptions!$B$37,Assumptions!$B$37*(Assumptions!$B$21+Assumptions!$B$22/Assumptions!$B$37)/(Assumptions!$B$21+Assumptions!$B$22/$C$98),Assumptions!$B$37) -> 1 | S98: =Assumptions!$B$38/$R$98 -> 1 | T98: =Assumptions!$B$39*$S$98 -> 5000000 | U98: =IF($C$98<Assumptions!$B$42,Assumptions!$B$42*(Assumptions!$B$21+Assumptions!$B$22/Assumptions!$B$42)/(Assumptions!$B$21+Assumptions!$B$22/$C$98),Assumptions!$B$42) -> 3 | V98: =Assumptions!$B$43/$U$98 -> 1 | W98: =Assumptions!$B$44*$V$98 -> 5000000 | X98: =IF($C$98<Assumptions!$B$47,Assumptions!$B$47*(Assumptions!$B$21+Assumptions!$B$22/Assumptions!$B$47)/(Assumptions!$B$21+Assumptions!$B$22/$C$98),Assumptions!$B$47) -> 10 | Y98: =Assumptions!$B$48/$X$98 -> 1 | Z98: =Assumptions!$B$49*$Y$98 -> 3000000 | AA98: =IF($C$98<Assumptions!$B$52,Assumptions!$B$52*(Assumptions!$B$21+Assumptions!$B$22/Assumptions!$B$52)/(Assumptions!$B$21+Assumptions!$B$22/$C$98),Assumptions!$B$52) -> 25 | AB98: =Assumptions!$B$53/$AA$98 -> 1 | AC98: =Assumptions!$B$54*$AB$98 -> 2400000 | AD98: =IF($C$98<Assumptions!$B$57,Assumptions!$B$57*(Assumptions!$B$21+Assumptions!$B$22/Assumptions!$B$57)/(Assumptions!$B$21+Assumptions!$B$22/$C$98),Assumptions!$B$57) -> 57.681736 | AE98: =Assumptions!$B$58/$AD$98 -> 1.0401906 | AF98: =Assumptions!$B$59*$AE$98 -> 1733651.4 | AG98: =IF($C$98<Assumptions!$B$62,Assumptions!$B$62*(Assumptions!$B$21+Assumptions!$B$22/Assumptions!$B$62)/(Assumptions!$B$21+Assumptions!$B$22/$C$98),Assumptions!$B$62) -> 48.912626 | AH98: =Assumptions!$B$63/$AG$98 -> 1.0050229 | AI98: =Assumptions!$B$64*$AH$98 -> 6133320.3
A99: =ROW()-ROW($A$93)+Assumptions!$B$4 -> 6 | B99: =$P$98 -> 587882.23 | C99: =Assumptions!$B$6/(Assumptions!$B$16+$B$99) -> 37.628498 | D99: =Assumptions!$B$7/$C$99 -> 797268.07 | E99: =$T$99+$W$99+$Z$99+$AC$99+$AF$99+$AI$99 -> 23266972 | F99: =Assumptions!$B$70/(Assumptions!$B$20+Assumptions!$B$17+$B$99+$E$99+$O$98) -> 26.778553 | G99: =$C$99*(1-Assumptions!$B$71) -> 30.102798 | H99: =MIN($F$99,$G$99) -> 26.778553 | I99: =IF($F$99<=$G$99,"cap","discount") -> cap | J99: =Assumptions!$B$69/$H$99 -> 186716.59 | K99: =Assumptions!$B$74/(Assumptions!$B$20+Assumptions!$B$17+$B$99+$E$99+$J$99) -> 42.739338 | L99: =$C$99*(1-Assumptions!$B$75) -> 31.984223 | M99: =MIN($K$99,$L$99) -> 31.984223 | N99: =IF($K$99<=$L$99,"cap","discount") -> discount | O99: =Assumptions!$B$73/$M$99 -> 93796.243 | P99: =MAX(Assumptions!$B$4,(Assumptions!$B$10*(Assumptions!$B$20+$E$99+Assumptions!$B$17+$J$99+$O$99+$D$99)-Assumptions!$B$17)/(1-Assumptions!$B$10)) -> 587882.23 | Q99: =Assumptions!$B$20+$E$99+Assumptions!$B$17+$P$99+$J$99+$O$99+$D$99 -> 38327302 | R99: =IF($C$99<Assumptions!$B$37,Assumptions!$B$37*(Assumptions!$B$21+Assumptions!$B$22/Assumptions!$B$37)/(Assumptions!$B$21+Assumptions!$B$22/$C$99),Assumptions!$B$37) -> 1 | S99: =Assumptions!$B$38/$R$99 -> 1 | T99: =Assumptions!$B$39*$S$99 -> 5000000 | U99: =IF($C$99<Assumptions!$B$42,Assumptions!$B$42*(Assumptions!$B$21+Assumptions!$B$22/Assumptions!$B$42)/(Assumptions!$B$21+Assumptions!$B$22/$C$99),Assumptions!$B$42) -> 3 | V99: =Assumptions!$B$43/$U$99 -> 1 | W99: =Assumptions!$B$44*$V$99 -> 5000000 | X99: =IF($C$99<Assumptions!$B$47,Assumptions!$B$47*(Assumptions!$B$21+Assumptions!$B$22/Assumptions!$B$47)/(Assumptions!$B$21+Assumptions!$B$22/$C$99),Assumptions!$B$47) -> 10 | Y99: =Assumptions!$B$48/$X$99 -> 1 | Z99: =Assumptions!$B$49*$Y$99 -> 3000000 | AA99: =IF($C$99<Assumptions!$B$52,Assumptions!$B$52*(Assumptions!$B$21+Assumptions!$B$22/Assumptions!$B$52)/(Assumptions!$B$21+Assumptions!$B$22/$C$99),Assumptions!$B$52) -> 25 | AB99: =Assumptions!$B$53/$AA$99 -> 1 | AC99: =Assumptions!$B$54*$AB$99 -> 2400000 | AD99: =IF($C$99<Assumptions!$B$57,Assumptions!$B$57*(Assumptions!$B$21+Assumptions!$B$22/Assumptions!$B$57)/(Assumptions!$B$21+Assumptions!$B$22/$C$99),Assumptions!$B$57) -> 57.681736 | AE99: =Assumptions!$B$58/$AD$99 -> 1.0401906 | AF99: =Assumptions!$B$59*$AE$99 -> 1733651.4 | AG99: =IF($C$99<Assumptions!$B$62,Assumptions!$B$62*(Assumptions!$B$21+Assumptions!$B$22/Assumptions!$B$62)/(Assumptions!$B$21+Assumptions!$B$22/$C$99),Assumptions!$B$62) -> 48.912626 | AH99: =Assumptions!$B$63/$AG$99 -> 1.0050229 | AI99: =Assumptions!$B$64*$AH$99 -> 6133320.3
A100: =ROW()-ROW($A$93)+Assumptions!$B$4 -> 7 | B100: =$P$99 -> 587882.23 | C100: =Assumptions!$B$6/(Assumptions!$B$16+$B$100) -> 37.628498 | D100: =Assumptions!$B$7/$C$100 -> 797268.07 | E100: =$T$100+$W$100+$Z$100+$AC$100+$AF$100+$AI$100 -> 23266972 | F100: =Assumptions!$B$70/(Assumptions!$B$20+Assumptions!$B$17+$B$100+$E$100+$O$99) -> 26.778553 | G100: =$C$100*(1-Assumptions!$B$71) -> 30.102798 | H100: =MIN($F$100,$G$100) -> 26.778553 | I100: =IF($F$100<=$G$100,"cap","discount") -> cap | J100: =Assumptions!$B$69/$H$100 -> 186716.59 | K100: =Assumptions!$B$74/(Assumptions!$B$20+Assumptions!$B$17+$B$100+$E$100+$J$100) -> 42.739338 | L100: =$C$100*(1-Assumptions!$B$75) -> 31.984223 | M100: =MIN($K$100,$L$100) -> 31.984223 | N100: =IF($K$100<=$L$100,"cap","discount") -> discount | O100: =Assumptions!$B$73/$M$100 -> 93796.243 | P100: =MAX(Assumptions!$B$4,(Assumptions!$B$10*(Assumptions!$B$20+$E$100+Assumptions!$B$17+$J$100+$O$100+$D$100)-Assumptions!$B$17)/(1-Assumptions!$B$10)) -> 587882.23 | Q100: =Assumptions!$B$20+$E$100+Assumptions!$B$17+$P$100+$J$100+$O$100+$D$100 -> 38327302 | R100: =IF($C$100<Assumptions!$B$37,Assumptions!$B$37*(Assumptions!$B$21+Assumptions!$B$22/Assumptions!$B$37)/(Assumptions!$B$21+Assumptions!$B$22/$C$100),Assumptions!$B$37) -> 1 | S100: =Assumptions!$B$38/$R$100 -> 1 | T100: =Assumptions!$B$39*$S$100 -> 5000000 | U100: =IF($C$100<Assumptions!$B$42,Assumptions!$B$42*(Assumptions!$B$21+Assumptions!$B$22/Assumptions!$B$42)/(Assumptions!$B$21+Assumptions!$B$22/$C$100),Assumptions!$B$42) -> 3 | V100: =Assumptions!$B$43/$U$100 -> 1 | W100: =Assumptions!$B$44*$V$100 -> 5000000 | X100: =IF($C$100<Assumptions!$B$47,Assumptions!$B$47*(Assumptions!$B$21+Assumptions!$B$22/Assumptions!$B$47)/(Assumptions!$B$21+Assumptions!$B$22/$C$100),Assumptions!$B$47) -> 10 | Y100: =Assumptions!$B$48/$X$100 -> 1 | Z100: =Assumptions!$B$49*$Y$100 -> 3000000 | AA100: =IF($C$100<Assumptions!$B$52,Assumptions!$B$52*(Assumptions!$B$21+Assumptions!$B$22/Assumptions!$B$52)/(Assumptions!$B$21+Assumptions!$B$22/$C$100),Assumptions!$B$52) -> 25 | AB100: =Assumptions!$B$53/$AA$100 -> 1 | AC100: =Assumptions!$B$54*$AB$100 -> 2400000 | AD100: =IF($C$100<Assumptions!$B$57,Assumptions!$B$57*(Assumptions!$B$21+Assumptions!$B$22/Assumptions!$B$57)/(Assumptions!$B$21+Assumptions!$B$22/$C$100),Assumptions!$B$57) -> 57.681736 | AE100: =Assumptions!$B$58/$AD$100 -> 1.0401906 | AF100: =Assumptions!$B$59*$AE$100 -> 1733651.4 | AG100: =IF($C$100<Assumptions!$B$62,Assumptions!$B$62*(Assumptions!$B$21+Assumptions!$B$22/Assumptions!$B$62)/(Assumptions!$B$21+Assumptions!$B$22/$C$100),Assumptions!$B$62) -> 48.912626 | AH100: =Assumptions!$B$63/$AG$100 -> 1.0050229 | AI100: =Assumptions!$B$64*$AH$100 -> 6133320.3
A101: =ROW()-ROW($A$93)+Assumptions!$B$4 -> 8 | B101: =$P$100 -> 587882.23 | C101: =Assumptions!$B$6/(Assumptions!$B$16+$B$101) -> 37.628498 | D101: =Assumptions!$B$7/$C$101 -> 797268.07 | E101: =$T$101+$W$101+$Z$101+$AC$101+$AF$101+$AI$101 -> 23266972 | F101: =Assumptions!$B$70/(Assumptions!$B$20+Assumptions!$B$17+$B$101+$E$101+$O$100) -> 26.778553 | G101: =$C$101*(1-Assumptions!$B$71) -> 30.102798 | H101: =MIN($F$101,$G$101) -> 26.778553 | I101: =IF($F$101<=$G$101,"cap","discount") -> cap | J101: =Assumptions!$B$69/$H$101 -> 186716.59 | K101: =Assumptions!$B$74/(Assumptions!$B$20+Assumptions!$B$17+$B$101+$E$101+$J$101) -> 42.739338 | L101: =$C$101*(1-Assumptions!$B$75) -> 31.984223 | M101: =MIN($K$101,$L$101) -> 31.984223 | N101: =IF($K$101<=$L$101,"cap","discount") -> discount | O101: =Assumptions!$B$73/$M$101 -> 93796.243 | P101: =MAX(Assumptions!$B$4,(Assumptions!$B$10*(Assumptions!$B$20+$E$101+Assumptions!$B$17+$J$101+$O$101+$D$101)-Assumptions!$B$17)/(1-Assumptions!$B$10)) -> 587882.23 | Q101: =Assumptions!$B$20+$E$101+Assumptions!$B$17+$P$101+$J$101+$O$101+$D$101 -> 38327302 | R101: =IF($C$101<Assumptions!$B$37,Assumptions!$B$37*(Assumptions!$B$21+Assumptions!$B$22/Assumptions!$B$37)/(Assumptions!$B$21+Assumptions!$B$22/$C$101),Assumptions!$B$37) -> 1 | S101: =Assumptions!$B$38/$R$101 -> 1 | T101: =Assumptions!$B$39*$S$101 -> 5000000 | U101: =IF($C$101<Assumptions!$B$42,Assumptions!$B$42*(Assumptions!$B$21+Assumptions!$B$22/Assumptions!$B$42)/(Assumptions!$B$21+Assumptions!$B$22/$C$101),Assumptions!$B$42) -> 3 | V101: =Assumptions!$B$43/$U$101 -> 1 | W101: =Assumptions!$B$44*$V$101 -> 5000000 | X101: =IF($C$101<Assumptions!$B$47,Assumptions!$B$47*(Assumptions!$B$21+Assumptions!$B$22/Assumptions!$B$47)/(Assumptions!$B$21+Assumptions!$B$22/$C$101),Assumptions!$B$47) -> 10 | Y101: =Assumptions!$B$48/$X$101 -> 1 | Z101: =Assumptions!$B$49*$Y$101 -> 3000000 | AA101: =IF($C$101<Assumptions!$B$52,Assumptions!$B$52*(Assumptions!$B$21+Assumptions!$B$22/Assumptions!$B$52)/(Assumptions!$B$21+Assumptions!$B$22/$C$101),Assumptions!$B$52) -> 25 | AB101: =Assumptions!$B$53/$AA$101 -> 1 | AC101: =Assumptions!$B$54*$AB$101 -> 2400000 | AD101: =IF($C$101<Assumptions!$B$57,Assumptions!$B$57*(Assumptions!$B$21+Assumptions!$B$22/Assumptions!$B$57)/(Assumptions!$B$21+Assumptions!$B$22/$C$101),Assumptions!$B$57) -> 57.681736 | AE101: =Assumptions!$B$58/$AD$101 -> 1.0401906 | AF101: =Assumptions!$B$59*$AE$101 -> 1733651.4 | AG101: =IF($C$101<Assumptions!$B$62,Assumptions!$B$62*(Assumptions!$B$21+Assumptions!$B$22/Assumptions!$B$62)/(Assumptions!$B$21+Assumptions!$B$22/$C$101),Assumptions!$B$62) -> 48.912626 | AH101: =Assumptions!$B$63/$AG$101 -> 1.0050229 | AI101: =Assumptions!$B$64*$AH$101 -> 6133320.3
A102: =ROW()-ROW($A$93)+Assumptions!$B$4 -> 9 | B102: =$P$101 -> 587882.23 | C102: =Assumptions!$B$6/(Assumptions!$B$16+$B$102) -> 37.628498 | D102: =Assumptions!$B$7/$C$102 -> 797268.07 | E102: =$T$102+$W$102+$Z$102+$AC$102+$AF$102+$AI$102 -> 23266972 | F102: =Assumptions!$B$70/(Assumptions!$B$20+Assumptions!$B$17+$B$102+$E$102+$O$101) -> 26.778553 | G102: =$C$102*(1-Assumptions!$B$71) -> 30.102798 | H102: =MIN($F$102,$G$102) -> 26.778553 | I102: =IF($F$102<=$G$102,"cap","discount") -> cap | J102: =Assumptions!$B$69/$H$102 -> 186716.59 | K102: =Assumptions!$B$74/(Assumptions!$B$20+Assumptions!$B$17+$B$102+$E$102+$J$102) -> 42.739338 | L102: =$C$102*(1-Assumptions!$B$75) -> 31.984223 | M102: =MIN($K$102,$L$102) -> 31.984223 | N102: =IF($K$102<=$L$102,"cap","discount") -> discount | O102: =Assumptions!$B$73/$M$102 -> 93796.243 | P102: =MAX(Assumptions!$B$4,(Assumptions!$B$10*(Assumptions!$B$20+$E$102+Assumptions!$B$17+$J$102+$O$102+$D$102)-Assumptions!$B$17)/(1-Assumptions!$B$10)) -> 587882.23 | Q102: =Assumptions!$B$20+$E$102+Assumptions!$B$17+$P$102+$J$102+$O$102+$D$102 -> 38327302 | R102: =IF($C$102<Assumptions!$B$37,Assumptions!$B$37*(Assumptions!$B$21+Assumptions!$B$22/Assumptions!$B$37)/(Assumptions!$B$21+Assumptions!$B$22/$C$102),Assumptions!$B$37) -> 1 | S102: =Assumptions!$B$38/$R$102 -> 1 | T102: =Assumptions!$B$39*$S$102 -> 5000000 | U102: =IF($C$102<Assumptions!$B$42,Assumptions!$B$42*(Assumptions!$B$21+Assumptions!$B$22/Assumptions!$B$42)/(Assumptions!$B$21+Assumptions!$B$22/$C$102),Assumptions!$B$42) -> 3 | V102: =Assumptions!$B$43/$U$102 -> 1 | W102: =Assumptions!$B$44*$V$102 -> 5000000 | X102: =IF($C$102<Assumptions!$B$47,Assumptions!$B$47*(Assumptions!$B$21+Assumptions!$B$22/Assumptions!$B$47)/(Assumptions!$B$21+Assumptions!$B$22/$C$102),Assumptions!$B$47) -> 10 | Y102: =Assumptions!$B$48/$X$102 -> 1 | Z102: =Assumptions!$B$49*$Y$102 -> 3000000 | AA102: =IF($C$102<Assumptions!$B$52,Assumptions!$B$52*(Assumptions!$B$21+Assumptions!$B$22/Assumptions!$B$52)/(Assumptions!$B$21+Assumptions!$B$22/$C$102),Assumptions!$B$52) -> 25 | AB102: =Assumptions!$B$53/$AA$102 -> 1 | AC102: =Assumptions!$B$54*$AB$102 -> 2400000 | AD102: =IF($C$102<Assumptions!$B$57,Assumptions!$B$57*(Assumptions!$B$21+Assumptions!$B$22/Assumptions!$B$57)/(Assumptions!$B$21+Assumptions!$B$22/$C$102),Assumptions!$B$57) -> 57.681736 | AE102: =Assumptions!$B$58/$AD$102 -> 1.0401906 | AF102: =Assumptions!$B$59*$AE$102 -> 1733651.4 | AG102: =IF($C$102<Assumptions!$B$62,Assumptions!$B$62*(Assumptions!$B$21+Assumptions!$B$22/Assumptions!$B$62)/(Assumptions!$B$21+Assumptions!$B$22/$C$102),Assumptions!$B$62) -> 48.912626 | AH102: =Assumptions!$B$63/$AG$102 -> 1.0050229 | AI102: =Assumptions!$B$64*$AH$102 -> 6133320.3
A103: =ROW()-ROW($A$93)+Assumptions!$B$4 -> 10 | B103: =$P$102 -> 587882.23 | C103: =Assumptions!$B$6/(Assumptions!$B$16+$B$103) -> 37.628498 | D103: =Assumptions!$B$7/$C$103 -> 797268.07 | E103: =$T$103+$W$103+$Z$103+$AC$103+$AF$103+$AI$103 -> 23266972 | F103: =Assumptions!$B$70/(Assumptions!$B$20+Assumptions!$B$17+$B$103+$E$103+$O$102) -> 26.778553 | G103: =$C$103*(1-Assumptions!$B$71) -> 30.102798 | H103: =MIN($F$103,$G$103) -> 26.778553 | I103: =IF($F$103<=$G$103,"cap","discount") -> cap | J103: =Assumptions!$B$69/$H$103 -> 186716.59 | K103: =Assumptions!$B$74/(Assumptions!$B$20+Assumptions!$B$17+$B$103+$E$103+$J$103) -> 42.739338 | L103: =$C$103*(1-Assumptions!$B$75) -> 31.984223 | M103: =MIN($K$103,$L$103) -> 31.984223 | N103: =IF($K$103<=$L$103,"cap","discount") -> discount | O103: =Assumptions!$B$73/$M$103 -> 93796.243 | P103: =MAX(Assumptions!$B$4,(Assumptions!$B$10*(Assumptions!$B$20+$E$103+Assumptions!$B$17+$J$103+$O$103+$D$103)-Assumptions!$B$17)/(1-Assumptions!$B$10)) -> 587882.23 | Q103: =Assumptions!$B$20+$E$103+Assumptions!$B$17+$P$103+$J$103+$O$103+$D$103 -> 38327302 | R103: =IF($C$103<Assumptions!$B$37,Assumptions!$B$37*(Assumptions!$B$21+Assumptions!$B$22/Assumptions!$B$37)/(Assumptions!$B$21+Assumptions!$B$22/$C$103),Assumptions!$B$37) -> 1 | S103: =Assumptions!$B$38/$R$103 -> 1 | T103: =Assumptions!$B$39*$S$103 -> 5000000 | U103: =IF($C$103<Assumptions!$B$42,Assumptions!$B$42*(Assumptions!$B$21+Assumptions!$B$22/Assumptions!$B$42)/(Assumptions!$B$21+Assumptions!$B$22/$C$103),Assumptions!$B$42) -> 3 | V103: =Assumptions!$B$43/$U$103 -> 1 | W103: =Assumptions!$B$44*$V$103 -> 5000000 | X103: =IF($C$103<Assumptions!$B$47,Assumptions!$B$47*(Assumptions!$B$21+Assumptions!$B$22/Assumptions!$B$47)/(Assumptions!$B$21+Assumptions!$B$22/$C$103),Assumptions!$B$47) -> 10 | Y103: =Assumptions!$B$48/$X$103 -> 1 | Z103: =Assumptions!$B$49*$Y$103 -> 3000000 | AA103: =IF($C$103<Assumptions!$B$52,Assumptions!$B$52*(Assumptions!$B$21+Assumptions!$B$22/Assumptions!$B$52)/(Assumptions!$B$21+Assumptions!$B$22/$C$103),Assumptions!$B$52) -> 25 | AB103: =Assumptions!$B$53/$AA$103 -> 1 | AC103: =Assumptions!$B$54*$AB$103 -> 2400000 | AD103: =IF($C$103<Assumptions!$B$57,Assumptions!$B$57*(Assumptions!$B$21+Assumptions!$B$22/Assumptions!$B$57)/(Assumptions!$B$21+Assumptions!$B$22/$C$103),Assumptions!$B$57) -> 57.681736 | AE103: =Assumptions!$B$58/$AD$103 -> 1.0401906 | AF103: =Assumptions!$B$59*$AE$103 -> 1733651.4 | AG103: =IF($C$103<Assumptions!$B$62,Assumptions!$B$62*(Assumptions!$B$21+Assumptions!$B$22/Assumptions!$B$62)/(Assumptions!$B$21+Assumptions!$B$22/$C$103),Assumptions!$B$62) -> 48.912626 | AH103: =Assumptions!$B$63/$AG$103 -> 1.0050229 | AI103: =Assumptions!$B$64*$AH$103 -> 6133320.3
A104: =ROW()-ROW($A$93)+Assumptions!$B$4 -> 11 | B104: =$P$103 -> 587882.23 | C104: =Assumptions!$B$6/(Assumptions!$B$16+$B$104) -> 37.628498 | D104: =Assumptions!$B$7/$C$104 -> 797268.07 | E104: =$T$104+$W$104+$Z$104+$AC$104+$AF$104+$AI$104 -> 23266972 | F104: =Assumptions!$B$70/(Assumptions!$B$20+Assumptions!$B$17+$B$104+$E$104+$O$103) -> 26.778553 | G104: =$C$104*(1-Assumptions!$B$71) -> 30.102798 | H104: =MIN($F$104,$G$104) -> 26.778553 | I104: =IF($F$104<=$G$104,"cap","discount") -> cap | J104: =Assumptions!$B$69/$H$104 -> 186716.59 | K104: =Assumptions!$B$74/(Assumptions!$B$20+Assumptions!$B$17+$B$104+$E$104+$J$104) -> 42.739338 | L104: =$C$104*(1-Assumptions!$B$75) -> 31.984223 | M104: =MIN($K$104,$L$104) -> 31.984223 | N104: =IF($K$104<=$L$104,"cap","discount") -> discount | O104: =Assumptions!$B$73/$M$104 -> 93796.243 | P104: =MAX(Assumptions!$B$4,(Assumptions!$B$10*(Assumptions!$B$20+$E$104+Assumptions!$B$17+$J$104+$O$104+$D$104)-Assumptions!$B$17)/(1-Assumptions!$B$10)) -> 587882.23 | Q104: =Assumptions!$B$20+$E$104+Assumptions!$B$17+$P$104+$J$104+$O$104+$D$104 -> 38327302 | R104: =IF($C$104<Assumptions!$B$37,Assumptions!$B$37*(Assumptions!$B$21+Assumptions!$B$22/Assumptions!$B$37)/(Assumptions!$B$21+Assumptions!$B$22/$C$104),Assumptions!$B$37) -> 1 | S104: =Assumptions!$B$38/$R$104 -> 1 | T104: =Assumptions!$B$39*$S$104 -> 5000000 | U104: =IF($C$104<Assumptions!$B$42,Assumptions!$B$42*(Assumptions!$B$21+Assumptions!$B$22/Assumptions!$B$42)/(Assumptions!$B$21+Assumptions!$B$22/$C$104),Assumptions!$B$42) -> 3 | V104: =Assumptions!$B$43/$U$104 -> 1 | W104: =Assumptions!$B$44*$V$104 -> 5000000 | X104: =IF($C$104<Assumptions!$B$47,Assumptions!$B$47*(Assumptions!$B$21+Assumptions!$B$22/Assumptions!$B$47)/(Assumptions!$B$21+Assumptions!$B$22/$C$104),Assumptions!$B$47) -> 10 | Y104: =Assumptions!$B$48/$X$104 -> 1 | Z104: =Assumptions!$B$49*$Y$104 -> 3000000 | AA104: =IF($C$104<Assumptions!$B$52,Assumptions!$B$52*(Assumptions!$B$21+Assumptions!$B$22/Assumptions!$B$52)/(Assumptions!$B$21+Assumptions!$B$22/$C$104),Assumptions!$B$52) -> 25 | AB104: =Assumptions!$B$53/$AA$104 -> 1 | AC104: =Assumptions!$B$54*$AB$104 -> 2400000 | AD104: =IF($C$104<Assumptions!$B$57,Assumptions!$B$57*(Assumptions!$B$21+Assumptions!$B$22/Assumptions!$B$57)/(Assumptions!$B$21+Assumptions!$B$22/$C$104),Assumptions!$B$57) -> 57.681736 | AE104: =Assumptions!$B$58/$AD$104 -> 1.0401906 | AF104: =Assumptions!$B$59*$AE$104 -> 1733651.4 | AG104: =IF($C$104<Assumptions!$B$62,Assumptions!$B$62*(Assumptions!$B$21+Assumptions!$B$22/Assumptions!$B$62)/(Assumptions!$B$21+Assumptions!$B$22/$C$104),Assumptions!$B$62) -> 48.912626 | AH104: =Assumptions!$B$63/$AG$104 -> 1.0050229 | AI104: =Assumptions!$B$64*$AH$104 -> 6133320.3
A105: =ROW()-ROW($A$93)+Assumptions!$B$4 -> 12 | B105: =$P$104 -> 587882.23 | C105: =Assumptions!$B$6/(Assumptions!$B$16+$B$105) -> 37.628498 | D105: =Assumptions!$B$7/$C$105 -> 797268.07 | E105: =$T$105+$W$105+$Z$105+$AC$105+$AF$105+$AI$105 -> 23266972 | F105: =Assumptions!$B$70/(Assumptions!$B$20+Assumptions!$B$17+$B$105+$E$105+$O$104) -> 26.778553 | G105: =$C$105*(1-Assumptions!$B$71) -> 30.102798 | H105: =MIN($F$105,$G$105) -> 26.778553 | I105: =IF($F$105<=$G$105,"cap","discount") -> cap | J105: =Assumptions!$B$69/$H$105 -> 186716.59 | K105: =Assumptions!$B$74/(Assumptions!$B$20+Assumptions!$B$17+$B$105+$E$105+$J$105) -> 42.739338 | L105: =$C$105*(1-Assumptions!$B$75) -> 31.984223 | M105: =MIN($K$105,$L$105) -> 31.984223 | N105: =IF($K$105<=$L$105,"cap","discount") -> discount | O105: =Assumptions!$B$73/$M$105 -> 93796.243 | P105: =MAX(Assumptions!$B$4,(Assumptions!$B$10*(Assumptions!$B$20+$E$105+Assumptions!$B$17+$J$105+$O$105+$D$105)-Assumptions!$B$17)/(1-Assumptions!$B$10)) -> 587882.23 | Q105: =Assumptions!$B$20+$E$105+Assumptions!$B$17+$P$105+$J$105+$O$105+$D$105 -> 38327302 | R105: =IF($C$105<Assumptions!$B$37,Assumptions!$B$37*(Assumptions!$B$21+Assumptions!$B$22/Assumptions!$B$37)/(Assumptions!$B$21+Assumptions!$B$22/$C$105),Assumptions!$B$37) -> 1 | S105: =Assumptions!$B$38/$R$105 -> 1 | T105: =Assumptions!$B$39*$S$105 -> 5000000 | U105: =IF($C$105<Assumptions!$B$42,Assumptions!$B$42*(Assumptions!$B$21+Assumptions!$B$22/Assumptions!$B$42)/(Assumptions!$B$21+Assumptions!$B$22/$C$105),Assumptions!$B$42) -> 3 | V105: =Assumptions!$B$43/$U$105 -> 1 | W105: =Assumptions!$B$44*$V$105 -> 5000000 | X105: =IF($C$105<Assumptions!$B$47,Assumptions!$B$47*(Assumptions!$B$21+Assumptions!$B$22/Assumptions!$B$47)/(Assumptions!$B$21+Assumptions!$B$22/$C$105),Assumptions!$B$47) -> 10 | Y105: =Assumptions!$B$48/$X$105 -> 1 | Z105: =Assumptions!$B$49*$Y$105 -> 3000000 | AA105: =IF($C$105<Assumptions!$B$52,Assumptions!$B$52*(Assumptions!$B$21+Assumptions!$B$22/Assumptions!$B$52)/(Assumptions!$B$21+Assumptions!$B$22/$C$105),Assumptions!$B$52) -> 25 | AB105: =Assumptions!$B$53/$AA$105 -> 1 | AC105: =Assumptions!$B$54*$AB$105 -> 2400000 | AD105: =IF($C$105<Assumptions!$B$57,Assumptions!$B$57*(Assumptions!$B$21+Assumptions!$B$22/Assumptions!$B$57)/(Assumptions!$B$21+Assumptions!$B$22/$C$105),Assumptions!$B$57) -> 57.681736 | AE105: =Assumptions!$B$58/$AD$105 -> 1.0401906 | AF105: =Assumptions!$B$59*$AE$105 -> 1733651.4 | AG105: =IF($C$105<Assumptions!$B$62,Assumptions!$B$62*(Assumptions!$B$21+Assumptions!$B$22/Assumptions!$B$62)/(Assumptions!$B$21+Assumptions!$B$22/$C$105),Assumptions!$B$62) -> 48.912626 | AH105: =Assumptions!$B$63/$AG$105 -> 1.0050229 | AI105: =Assumptions!$B$64*$AH$105 -> 6133320.3
A106: =ROW()-ROW($A$93)+Assumptions!$B$4 -> 13 | B106: =$P$105 -> 587882.23 | C106: =Assumptions!$B$6/(Assumptions!$B$16+$B$106) -> 37.628498 | D106: =Assumptions!$B$7/$C$106 -> 797268.07 | E106: =$T$106+$W$106+$Z$106+$AC$106+$AF$106+$AI$106 -> 23266972 | F106: =Assumptions!$B$70/(Assumptions!$B$20+Assumptions!$B$17+$B$106+$E$106+$O$105) -> 26.778553 | G106: =$C$106*(1-Assumptions!$B$71) -> 30.102798 | H106: =MIN($F$106,$G$106) -> 26.778553 | I106: =IF($F$106<=$G$106,"cap","discount") -> cap | J106: =Assumptions!$B$69/$H$106 -> 186716.59 | K106: =Assumptions!$B$74/(Assumptions!$B$20+Assumptions!$B$17+$B$106+$E$106+$J$106) -> 42.739338 | L106: =$C$106*(1-Assumptions!$B$75) -> 31.984223 | M106: =MIN($K$106,$L$106) -> 31.984223 | N106: =IF($K$106<=$L$106,"cap","discount") -> discount | O106: =Assumptions!$B$73/$M$106 -> 93796.243 | P106: =MAX(Assumptions!$B$4,(Assumptions!$B$10*(Assumptions!$B$20+$E$106+Assumptions!$B$17+$J$106+$O$106+$D$106)-Assumptions!$B$17)/(1-Assumptions!$B$10)) -> 587882.23 | Q106: =Assumptions!$B$20+$E$106+Assumptions!$B$17+$P$106+$J$106+$O$106+$D$106 -> 38327302 | R106: =IF($C$106<Assumptions!$B$37,Assumptions!$B$37*(Assumptions!$B$21+Assumptions!$B$22/Assumptions!$B$37)/(Assumptions!$B$21+Assumptions!$B$22/$C$106),Assumptions!$B$37) -> 1 | S106: =Assumptions!$B$38/$R$106 -> 1 | T106: =Assumptions!$B$39*$S$106 -> 5000000 | U106: =IF($C$106<Assumptions!$B$42,Assumptions!$B$42*(Assumptions!$B$21+Assumptions!$B$22/Assumptions!$B$42)/(Assumptions!$B$21+Assumptions!$B$22/$C$106),Assumptions!$B$42) -> 3 | V106: =Assumptions!$B$43/$U$106 -> 1 | W106: =Assumptions!$B$44*$V$106 -> 5000000 | X106: =IF($C$106<Assumptions!$B$47,Assumptions!$B$47*(Assumptions!$B$21+Assumptions!$B$22/Assumptions!$B$47)/(Assumptions!$B$21+Assumptions!$B$22/$C$106),Assumptions!$B$47) -> 10 | Y106: =Assumptions!$B$48/$X$106 -> 1 | Z106: =Assumptions!$B$49*$Y$106 -> 3000000 | AA106: =IF($C$106<Assumptions!$B$52,Assumptions!$B$52*(Assumptions!$B$21+Assumptions!$B$22/Assumptions!$B$52)/(Assumptions!$B$21+Assumptions!$B$22/$C$106),Assumptions!$B$52) -> 25 | AB106: =Assumptions!$B$53/$AA$106 -> 1 | AC106: =Assumptions!$B$54*$AB$106 -> 2400000 | AD106: =IF($C$106<Assumptions!$B$57,Assumptions!$B$57*(Assumptions!$B$21+Assumptions!$B$22/Assumptions!$B$57)/(Assumptions!$B$21+Assumptions!$B$22/$C$106),Assumptions!$B$57) -> 57.681736 | AE106: =Assumptions!$B$58/$AD$106 -> 1.0401906 | AF106: =Assumptions!$B$59*$AE$106 -> 1733651.4 | AG106: =IF($C$106<Assumptions!$B$62,Assumptions!$B$62*(Assumptions!$B$21+Assumptions!$B$22/Assumptions!$B$62)/(Assumptions!$B$21+Assumptions!$B$22/$C$106),Assumptions!$B$62) -> 48.912626 | AH106: =Assumptions!$B$63/$AG$106 -> 1.0050229 | AI106: =Assumptions!$B$64*$AH$106 -> 6133320.3
A107: =ROW()-ROW($A$93)+Assumptions!$B$4 -> 14 | B107: =$P$106 -> 587882.23 | C107: =Assumptions!$B$6/(Assumptions!$B$16+$B$107) -> 37.628498 | D107: =Assumptions!$B$7/$C$107 -> 797268.07 | E107: =$T$107+$W$107+$Z$107+$AC$107+$AF$107+$AI$107 -> 23266972 | F107: =Assumptions!$B$70/(Assumptions!$B$20+Assumptions!$B$17+$B$107+$E$107+$O$106) -> 26.778553 | G107: =$C$107*(1-Assumptions!$B$71) -> 30.102798 | H107: =MIN($F$107,$G$107) -> 26.778553 | I107: =IF($F$107<=$G$107,"cap","discount") -> cap | J107: =Assumptions!$B$69/$H$107 -> 186716.59 | K107: =Assumptions!$B$74/(Assumptions!$B$20+Assumptions!$B$17+$B$107+$E$107+$J$107) -> 42.739338 | L107: =$C$107*(1-Assumptions!$B$75) -> 31.984223 | M107: =MIN($K$107,$L$107) -> 31.984223 | N107: =IF($K$107<=$L$107,"cap","discount") -> discount | O107: =Assumptions!$B$73/$M$107 -> 93796.243 | P107: =MAX(Assumptions!$B$4,(Assumptions!$B$10*(Assumptions!$B$20+$E$107+Assumptions!$B$17+$J$107+$O$107+$D$107)-Assumptions!$B$17)/(1-Assumptions!$B$10)) -> 587882.23 | Q107: =Assumptions!$B$20+$E$107+Assumptions!$B$17+$P$107+$J$107+$O$107+$D$107 -> 38327302 | R107: =IF($C$107<Assumptions!$B$37,Assumptions!$B$37*(Assumptions!$B$21+Assumptions!$B$22/Assumptions!$B$37)/(Assumptions!$B$21+Assumptions!$B$22/$C$107),Assumptions!$B$37) -> 1 | S107: =Assumptions!$B$38/$R$107 -> 1 | T107: =Assumptions!$B$39*$S$107 -> 5000000 | U107: =IF($C$107<Assumptions!$B$42,Assumptions!$B$42*(Assumptions!$B$21+Assumptions!$B$22/Assumptions!$B$42)/(Assumptions!$B$21+Assumptions!$B$22/$C$107),Assumptions!$B$42) -> 3 | V107: =Assumptions!$B$43/$U$107 -> 1 | W107: =Assumptions!$B$44*$V$107 -> 5000000 | X107: =IF($C$107<Assumptions!$B$47,Assumptions!$B$47*(Assumptions!$B$21+Assumptions!$B$22/Assumptions!$B$47)/(Assumptions!$B$21+Assumptions!$B$22/$C$107),Assumptions!$B$47) -> 10 | Y107: =Assumptions!$B$48/$X$107 -> 1 | Z107: =Assumptions!$B$49*$Y$107 -> 3000000 | AA107: =IF($C$107<Assumptions!$B$52,Assumptions!$B$52*(Assumptions!$B$21+Assumptions!$B$22/Assumptions!$B$52)/(Assumptions!$B$21+Assumptions!$B$22/$C$107),Assumptions!$B$52) -> 25 | AB107: =Assumptions!$B$53/$AA$107 -> 1 | AC107: =Assumptions!$B$54*$AB$107 -> 2400000 | AD107: =IF($C$107<Assumptions!$B$57,Assumptions!$B$57*(Assumptions!$B$21+Assumptions!$B$22/Assumptions!$B$57)/(Assumptions!$B$21+Assumptions!$B$22/$C$107),Assumptions!$B$57) -> 57.681736 | AE107: =Assumptions!$B$58/$AD$107 -> 1.0401906 | AF107: =Assumptions!$B$59*$AE$107 -> 1733651.4 | AG107: =IF($C$107<Assumptions!$B$62,Assumptions!$B$62*(Assumptions!$B$21+Assumptions!$B$22/Assumptions!$B$62)/(Assumptions!$B$21+Assumptions!$B$22/$C$107),Assumptions!$B$62) -> 48.912626 | AH107: =Assumptions!$B$63/$AG$107 -> 1.0050229 | AI107: =Assumptions!$B$64*$AH$107 -> 6133320.3
A108: =ROW()-ROW($A$93)+Assumptions!$B$4 -> 15 | B108: =$P$107 -> 587882.23 | C108: =Assumptions!$B$6/(Assumptions!$B$16+$B$108) -> 37.628498 | D108: =Assumptions!$B$7/$C$108 -> 797268.07 | E108: =$T$108+$W$108+$Z$108+$AC$108+$AF$108+$AI$108 -> 23266972 | F108: =Assumptions!$B$70/(Assumptions!$B$20+Assumptions!$B$17+$B$108+$E$108+$O$107) -> 26.778553 | G108: =$C$108*(1-Assumptions!$B$71) -> 30.102798 | H108: =MIN($F$108,$G$108) -> 26.778553 | I108: =IF($F$108<=$G$108,"cap","discount") -> cap | J108: =Assumptions!$B$69/$H$108 -> 186716.59 | K108: =Assumptions!$B$74/(Assumptions!$B$20+Assumptions!$B$17+$B$108+$E$108+$J$108) -> 42.739338 | L108: =$C$108*(1-Assumptions!$B$75) -> 31.984223 | M108: =MIN($K$108,$L$108) -> 31.984223 | N108: =IF($K$108<=$L$108,"cap","discount") -> discount | O108: =Assumptions!$B$73/$M$108 -> 93796.243 | P108: =MAX(Assumptions!$B$4,(Assumptions!$B$10*(Assumptions!$B$20+$E$108+Assumptions!$B$17+$J$108+$O$108+$D$108)-Assumptions!$B$17)/(1-Assumptions!$B$10)) -> 587882.23 | Q108: =Assumptions!$B$20+$E$108+Assumptions!$B$17+$P$108+$J$108+$O$108+$D$108 -> 38327302 | R108: =IF($C$108<Assumptions!$B$37,Assumptions!$B$37*(Assumptions!$B$21+Assumptions!$B$22/Assumptions!$B$37)/(Assumptions!$B$21+Assumptions!$B$22/$C$108),Assumptions!$B$37) -> 1 | S108: =Assumptions!$B$38/$R$108 -> 1 | T108: =Assumptions!$B$39*$S$108 -> 5000000 | U108: =IF($C$108<Assumptions!$B$42,Assumptions!$B$42*(Assumptions!$B$21+Assumptions!$B$22/Assumptions!$B$42)/(Assumptions!$B$21+Assumptions!$B$22/$C$108),Assumptions!$B$42) -> 3 | V108: =Assumptions!$B$43/$U$108 -> 1 | W108: =Assumptions!$B$44*$V$108 -> 5000000 | X108: =IF($C$108<Assumptions!$B$47,Assumptions!$B$47*(Assumptions!$B$21+Assumptions!$B$22/Assumptions!$B$47)/(Assumptions!$B$21+Assumptions!$B$22/$C$108),Assumptions!$B$47) -> 10 | Y108: =Assumptions!$B$48/$X$108 -> 1 | Z108: =Assumptions!$B$49*$Y$108 -> 3000000 | AA108: =IF($C$108<Assumptions!$B$52,Assumptions!$B$52*(Assumptions!$B$21+Assumptions!$B$22/Assumptions!$B$52)/(Assumptions!$B$21+Assumptions!$B$22/$C$108),Assumptions!$B$52) -> 25 | AB108: =Assumptions!$B$53/$AA$108 -> 1 | AC108: =Assumptions!$B$54*$AB$108 -> 2400000 | AD108: =IF($C$108<Assumptions!$B$57,Assumptions!$B$57*(Assumptions!$B$21+Assumptions!$B$22/Assumptions!$B$57)/(Assumptions!$B$21+Assumptions!$B$22/$C$108),Assumptions!$B$57) -> 57.681736 | AE108: =Assumptions!$B$58/$AD$108 -> 1.0401906 | AF108: =Assumptions!$B$59*$AE$108 -> 1733651.4 | AG108: =IF($C$108<Assumptions!$B$62,Assumptions!$B$62*(Assumptions!$B$21+Assumptions!$B$22/Assumptions!$B$62)/(Assumptions!$B$21+Assumptions!$B$22/$C$108),Assumptions!$B$62) -> 48.912626 | AH108: =Assumptions!$B$63/$AG$108 -> 1.0050229 | AI108: =Assumptions!$B$64*$AH$108 -> 6133320.3
A109: =ROW()-ROW($A$93)+Assumptions!$B$4 -> 16 | B109: =$P$108 -> 587882.23 | C109: =Assumptions!$B$6/(Assumptions!$B$16+$B$109) -> 37.628498 | D109: =Assumptions!$B$7/$C$109 -> 797268.07 | E109: =$T$109+$W$109+$Z$109+$AC$109+$AF$109+$AI$109 -> 23266972 | F109: =Assumptions!$B$70/(Assumptions!$B$20+Assumptions!$B$17+$B$109+$E$109+$O$108) -> 26.778553 | G109: =$C$109*(1-Assumptions!$B$71) -> 30.102798 | H109: =MIN($F$109,$G$109) -> 26.778553 | I109: =IF($F$109<=$G$109,"cap","discount") -> cap | J109: =Assumptions!$B$69/$H$109 -> 186716.59 | K109: =Assumptions!$B$74/(Assumptions!$B$20+Assumptions!$B$17+$B$109+$E$109+$J$109) -> 42.739338 | L109: =$C$109*(1-Assumptions!$B$75) -> 31.984223 | M109: =MIN($K$109,$L$109) -> 31.984223 | N109: =IF($K$109<=$L$109,"cap","discount") -> discount | O109: =Assumptions!$B$73/$M$109 -> 93796.243 | P109: =MAX(Assumptions!$B$4,(Assumptions!$B$10*(Assumptions!$B$20+$E$109+Assumptions!$B$17+$J$109+$O$109+$D$109)-Assumptions!$B$17)/(1-Assumptions!$B$10)) -> 587882.23 | Q109: =Assumptions!$B$20+$E$109+Assumptions!$B$17+$P$109+$J$109+$O$109+$D$109 -> 38327302 | R109: =IF($C$109<Assumptions!$B$37,Assumptions!$B$37*(Assumptions!$B$21+Assumptions!$B$22/Assumptions!$B$37)/(Assumptions!$B$21+Assumptions!$B$22/$C$109),Assumptions!$B$37) -> 1 | S109: =Assumptions!$B$38/$R$109 -> 1 | T109: =Assumptions!$B$39*$S$109 -> 5000000 | U109: =IF($C$109<Assumptions!$B$42,Assumptions!$B$42*(Assumptions!$B$21+Assumptions!$B$22/Assumptions!$B$42)/(Assumptions!$B$21+Assumptions!$B$22/$C$109),Assumptions!$B$42) -> 3 | V109: =Assumptions!$B$43/$U$109 -> 1 | W109: =Assumptions!$B$44*$V$109 -> 5000000 | X109: =IF($C$109<Assumptions!$B$47,Assumptions!$B$47*(Assumptions!$B$21+Assumptions!$B$22/Assumptions!$B$47)/(Assumptions!$B$21+Assumptions!$B$22/$C$109),Assumptions!$B$47) -> 10 | Y109: =Assumptions!$B$48/$X$109 -> 1 | Z109: =Assumptions!$B$49*$Y$109 -> 3000000 | AA109: =IF($C$109<Assumptions!$B$52,Assumptions!$B$52*(Assumptions!$B$21+Assumptions!$B$22/Assumptions!$B$52)/(Assumptions!$B$21+Assumptions!$B$22/$C$109),Assumptions!$B$52) -> 25 | AB109: =Assumptions!$B$53/$AA$109 -> 1 | AC109: =Assumptions!$B$54*$AB$109 -> 2400000 | AD109: =IF($C$109<Assumptions!$B$57,Assumptions!$B$57*(Assumptions!$B$21+Assumptions!$B$22/Assumptions!$B$57)/(Assumptions!$B$21+Assumptions!$B$22/$C$109),Assumptions!$B$57) -> 57.681736 | AE109: =Assumptions!$B$58/$AD$109 -> 1.0401906 | AF109: =Assumptions!$B$59*$AE$109 -> 1733651.4 | AG109: =IF($C$109<Assumptions!$B$62,Assumptions!$B$62*(Assumptions!$B$21+Assumptions!$B$22/Assumptions!$B$62)/(Assumptions!$B$21+Assumptions!$B$22/$C$109),Assumptions!$B$62) -> 48.912626 | AH109: =Assumptions!$B$63/$AG$109 -> 1.0050229 | AI109: =Assumptions!$B$64*$AH$109 -> 6133320.3
A110: =ROW()-ROW($A$93)+Assumptions!$B$4 -> 17 | B110: =$P$109 -> 587882.23 | C110: =Assumptions!$B$6/(Assumptions!$B$16+$B$110) -> 37.628498 | D110: =Assumptions!$B$7/$C$110 -> 797268.07 | E110: =$T$110+$W$110+$Z$110+$AC$110+$AF$110+$AI$110 -> 23266972 | F110: =Assumptions!$B$70/(Assumptions!$B$20+Assumptions!$B$17+$B$110+$E$110+$O$109) -> 26.778553 | G110: =$C$110*(1-Assumptions!$B$71) -> 30.102798 | H110: =MIN($F$110,$G$110) -> 26.778553 | I110: =IF($F$110<=$G$110,"cap","discount") -> cap | J110: =Assumptions!$B$69/$H$110 -> 186716.59 | K110: =Assumptions!$B$74/(Assumptions!$B$20+Assumptions!$B$17+$B$110+$E$110+$J$110) -> 42.739338 | L110: =$C$110*(1-Assumptions!$B$75) -> 31.984223 | M110: =MIN($K$110,$L$110) -> 31.984223 | N110: =IF($K$110<=$L$110,"cap","discount") -> discount | O110: =Assumptions!$B$73/$M$110 -> 93796.243 | P110: =MAX(Assumptions!$B$4,(Assumptions!$B$10*(Assumptions!$B$20+$E$110+Assumptions!$B$17+$J$110+$O$110+$D$110)-Assumptions!$B$17)/(1-Assumptions!$B$10)) -> 587882.23 | Q110: =Assumptions!$B$20+$E$110+Assumptions!$B$17+$P$110+$J$110+$O$110+$D$110 -> 38327302 | R110: =IF($C$110<Assumptions!$B$37,Assumptions!$B$37*(Assumptions!$B$21+Assumptions!$B$22/Assumptions!$B$37)/(Assumptions!$B$21+Assumptions!$B$22/$C$110),Assumptions!$B$37) -> 1 | S110: =Assumptions!$B$38/$R$110 -> 1 | T110: =Assumptions!$B$39*$S$110 -> 5000000 | U110: =IF($C$110<Assumptions!$B$42,Assumptions!$B$42*(Assumptions!$B$21+Assumptions!$B$22/Assumptions!$B$42)/(Assumptions!$B$21+Assumptions!$B$22/$C$110),Assumptions!$B$42) -> 3 | V110: =Assumptions!$B$43/$U$110 -> 1 | W110: =Assumptions!$B$44*$V$110 -> 5000000 | X110: =IF($C$110<Assumptions!$B$47,Assumptions!$B$47*(Assumptions!$B$21+Assumptions!$B$22/Assumptions!$B$47)/(Assumptions!$B$21+Assumptions!$B$22/$C$110),Assumptions!$B$47) -> 10 | Y110: =Assumptions!$B$48/$X$110 -> 1 | Z110: =Assumptions!$B$49*$Y$110 -> 3000000 | AA110: =IF($C$110<Assumptions!$B$52,Assumptions!$B$52*(Assumptions!$B$21+Assumptions!$B$22/Assumptions!$B$52)/(Assumptions!$B$21+Assumptions!$B$22/$C$110),Assumptions!$B$52) -> 25 | AB110: =Assumptions!$B$53/$AA$110 -> 1 | AC110: =Assumptions!$B$54*$AB$110 -> 2400000 | AD110: =IF($C$110<Assumptions!$B$57,Assumptions!$B$57*(Assumptions!$B$21+Assumptions!$B$22/Assumptions!$B$57)/(Assumptions!$B$21+Assumptions!$B$22/$C$110),Assumptions!$B$57) -> 57.681736 | AE110: =Assumptions!$B$58/$AD$110 -> 1.0401906 | AF110: =Assumptions!$B$59*$AE$110 -> 1733651.4 | AG110: =IF($C$110<Assumptions!$B$62,Assumptions!$B$62*(Assumptions!$B$21+Assumptions!$B$22/Assumptions!$B$62)/(Assumptions!$B$21+Assumptions!$B$22/$C$110),Assumptions!$B$62) -> 48.912626 | AH110: =Assumptions!$B$63/$AG$110 -> 1.0050229 | AI110: =Assumptions!$B$64*$AH$110 -> 6133320.3
A111: =ROW()-ROW($A$93)+Assumptions!$B$4 -> 18 | B111: =$P$110 -> 587882.23 | C111: =Assumptions!$B$6/(Assumptions!$B$16+$B$111) -> 37.628498 | D111: =Assumptions!$B$7/$C$111 -> 797268.07 | E111: =$T$111+$W$111+$Z$111+$AC$111+$AF$111+$AI$111 -> 23266972 | F111: =Assumptions!$B$70/(Assumptions!$B$20+Assumptions!$B$17+$B$111+$E$111+$O$110) -> 26.778553 | G111: =$C$111*(1-Assumptions!$B$71) -> 30.102798 | H111: =MIN($F$111,$G$111) -> 26.778553 | I111: =IF($F$111<=$G$111,"cap","discount") -> cap | J111: =Assumptions!$B$69/$H$111 -> 186716.59 | K111: =Assumptions!$B$74/(Assumptions!$B$20+Assumptions!$B$17+$B$111+$E$111+$J$111) -> 42.739338 | L111: =$C$111*(1-Assumptions!$B$75) -> 31.984223 | M111: =MIN($K$111,$L$111) -> 31.984223 | N111: =IF($K$111<=$L$111,"cap","discount") -> discount | O111: =Assumptions!$B$73/$M$111 -> 93796.243 | P111: =MAX(Assumptions!$B$4,(Assumptions!$B$10*(Assumptions!$B$20+$E$111+Assumptions!$B$17+$J$111+$O$111+$D$111)-Assumptions!$B$17)/(1-Assumptions!$B$10)) -> 587882.23 | Q111: =Assumptions!$B$20+$E$111+Assumptions!$B$17+$P$111+$J$111+$O$111+$D$111 -> 38327302 | R111: =IF($C$111<Assumptions!$B$37,Assumptions!$B$37*(Assumptions!$B$21+Assumptions!$B$22/Assumptions!$B$37)/(Assumptions!$B$21+Assumptions!$B$22/$C$111),Assumptions!$B$37) -> 1 | S111: =Assumptions!$B$38/$R$111 -> 1 | T111: =Assumptions!$B$39*$S$111 -> 5000000 | U111: =IF($C$111<Assumptions!$B$42,Assumptions!$B$42*(Assumptions!$B$21+Assumptions!$B$22/Assumptions!$B$42)/(Assumptions!$B$21+Assumptions!$B$22/$C$111),Assumptions!$B$42) -> 3 | V111: =Assumptions!$B$43/$U$111 -> 1 | W111: =Assumptions!$B$44*$V$111 -> 5000000 | X111: =IF($C$111<Assumptions!$B$47,Assumptions!$B$47*(Assumptions!$B$21+Assumptions!$B$22/Assumptions!$B$47)/(Assumptions!$B$21+Assumptions!$B$22/$C$111),Assumptions!$B$47) -> 10 | Y111: =Assumptions!$B$48/$X$111 -> 1 | Z111: =Assumptions!$B$49*$Y$111 -> 3000000 | AA111: =IF($C$111<Assumptions!$B$52,Assumptions!$B$52*(Assumptions!$B$21+Assumptions!$B$22/Assumptions!$B$52)/(Assumptions!$B$21+Assumptions!$B$22/$C$111),Assumptions!$B$52) -> 25 | AB111: =Assumptions!$B$53/$AA$111 -> 1 | AC111: =Assumptions!$B$54*$AB$111 -> 2400000 | AD111: =IF($C$111<Assumptions!$B$57,Assumptions!$B$57*(Assumptions!$B$21+Assumptions!$B$22/Assumptions!$B$57)/(Assumptions!$B$21+Assumptions!$B$22/$C$111),Assumptions!$B$57) -> 57.681736 | AE111: =Assumptions!$B$58/$AD$111 -> 1.0401906 | AF111: =Assumptions!$B$59*$AE$111 -> 1733651.4 | AG111: =IF($C$111<Assumptions!$B$62,Assumptions!$B$62*(Assumptions!$B$21+Assumptions!$B$22/Assumptions!$B$62)/(Assumptions!$B$21+Assumptions!$B$22/$C$111),Assumptions!$B$62) -> 48.912626 | AH111: =Assumptions!$B$63/$AG$111 -> 1.0050229 | AI111: =Assumptions!$B$64*$AH$111 -> 6133320.3
A112: =ROW()-ROW($A$93)+Assumptions!$B$4 -> 19 | B112: =$P$111 -> 587882.23 | C112: =Assumptions!$B$6/(Assumptions!$B$16+$B$112) -> 37.628498 | D112: =Assumptions!$B$7/$C$112 -> 797268.07 | E112: =$T$112+$W$112+$Z$112+$AC$112+$AF$112+$AI$112 -> 23266972 | F112: =Assumptions!$B$70/(Assumptions!$B$20+Assumptions!$B$17+$B$112+$E$112+$O$111) -> 26.778553 | G112: =$C$112*(1-Assumptions!$B$71) -> 30.102798 | H112: =MIN($F$112,$G$112) -> 26.778553 | I112: =IF($F$112<=$G$112,"cap","discount") -> cap | J112: =Assumptions!$B$69/$H$112 -> 186716.59 | K112: =Assumptions!$B$74/(Assumptions!$B$20+Assumptions!$B$17+$B$112+$E$112+$J$112) -> 42.739338 | L112: =$C$112*(1-Assumptions!$B$75) -> 31.984223 | M112: =MIN($K$112,$L$112) -> 31.984223 | N112: =IF($K$112<=$L$112,"cap","discount") -> discount | O112: =Assumptions!$B$73/$M$112 -> 93796.243 | P112: =MAX(Assumptions!$B$4,(Assumptions!$B$10*(Assumptions!$B$20+$E$112+Assumptions!$B$17+$J$112+$O$112+$D$112)-Assumptions!$B$17)/(1-Assumptions!$B$10)) -> 587882.23 | Q112: =Assumptions!$B$20+$E$112+Assumptions!$B$17+$P$112+$J$112+$O$112+$D$112 -> 38327302 | R112: =IF($C$112<Assumptions!$B$37,Assumptions!$B$37*(Assumptions!$B$21+Assumptions!$B$22/Assumptions!$B$37)/(Assumptions!$B$21+Assumptions!$B$22/$C$112),Assumptions!$B$37) -> 1 | S112: =Assumptions!$B$38/$R$112 -> 1 | T112: =Assumptions!$B$39*$S$112 -> 5000000 | U112: =IF($C$112<Assumptions!$B$42,Assumptions!$B$42*(Assumptions!$B$21+Assumptions!$B$22/Assumptions!$B$42)/(Assumptions!$B$21+Assumptions!$B$22/$C$112),Assumptions!$B$42) -> 3 | V112: =Assumptions!$B$43/$U$112 -> 1 | W112: =Assumptions!$B$44*$V$112 -> 5000000 | X112: =IF($C$112<Assumptions!$B$47,Assumptions!$B$47*(Assumptions!$B$21+Assumptions!$B$22/Assumptions!$B$47)/(Assumptions!$B$21+Assumptions!$B$22/$C$112),Assumptions!$B$47) -> 10 | Y112: =Assumptions!$B$48/$X$112 -> 1 | Z112: =Assumptions!$B$49*$Y$112 -> 3000000 | AA112: =IF($C$112<Assumptions!$B$52,Assumptions!$B$52*(Assumptions!$B$21+Assumptions!$B$22/Assumptions!$B$52)/(Assumptions!$B$21+Assumptions!$B$22/$C$112),Assumptions!$B$52) -> 25 | AB112: =Assumptions!$B$53/$AA$112 -> 1 | AC112: =Assumptions!$B$54*$AB$112 -> 2400000 | AD112: =IF($C$112<Assumptions!$B$57,Assumptions!$B$57*(Assumptions!$B$21+Assumptions!$B$22/Assumptions!$B$57)/(Assumptions!$B$21+Assumptions!$B$22/$C$112),Assumptions!$B$57) -> 57.681736 | AE112: =Assumptions!$B$58/$AD$112 -> 1.0401906 | AF112: =Assumptions!$B$59*$AE$112 -> 1733651.4 | AG112: =IF($C$112<Assumptions!$B$62,Assumptions!$B$62*(Assumptions!$B$21+Assumptions!$B$22/Assumptions!$B$62)/(Assumptions!$B$21+Assumptions!$B$22/$C$112),Assumptions!$B$62) -> 48.912626 | AH112: =Assumptions!$B$63/$AG$112 -> 1.0050229 | AI112: =Assumptions!$B$64*$AH$112 -> 6133320.3
A113: =ROW()-ROW($A$93)+Assumptions!$B$4 -> 20 | B113: =$P$112 -> 587882.23 | C113: =Assumptions!$B$6/(Assumptions!$B$16+$B$113) -> 37.628498 | D113: =Assumptions!$B$7/$C$113 -> 797268.07 | E113: =$T$113+$W$113+$Z$113+$AC$113+$AF$113+$AI$113 -> 23266972 | F113: =Assumptions!$B$70/(Assumptions!$B$20+Assumptions!$B$17+$B$113+$E$113+$O$112) -> 26.778553 | G113: =$C$113*(1-Assumptions!$B$71) -> 30.102798 | H113: =MIN($F$113,$G$113) -> 26.778553 | I113: =IF($F$113<=$G$113,"cap","discount") -> cap | J113: =Assumptions!$B$69/$H$113 -> 186716.59 | K113: =Assumptions!$B$74/(Assumptions!$B$20+Assumptions!$B$17+$B$113+$E$113+$J$113) -> 42.739338 | L113: =$C$113*(1-Assumptions!$B$75) -> 31.984223 | M113: =MIN($K$113,$L$113) -> 31.984223 | N113: =IF($K$113<=$L$113,"cap","discount") -> discount | O113: =Assumptions!$B$73/$M$113 -> 93796.243 | P113: =MAX(Assumptions!$B$4,(Assumptions!$B$10*(Assumptions!$B$20+$E$113+Assumptions!$B$17+$J$113+$O$113+$D$113)-Assumptions!$B$17)/(1-Assumptions!$B$10)) -> 587882.23 | Q113: =Assumptions!$B$20+$E$113+Assumptions!$B$17+$P$113+$J$113+$O$113+$D$113 -> 38327302 | R113: =IF($C$113<Assumptions!$B$37,Assumptions!$B$37*(Assumptions!$B$21+Assumptions!$B$22/Assumptions!$B$37)/(Assumptions!$B$21+Assumptions!$B$22/$C$113),Assumptions!$B$37) -> 1 | S113: =Assumptions!$B$38/$R$113 -> 1 | T113: =Assumptions!$B$39*$S$113 -> 5000000 | U113: =IF($C$113<Assumptions!$B$42,Assumptions!$B$42*(Assumptions!$B$21+Assumptions!$B$22/Assumptions!$B$42)/(Assumptions!$B$21+Assumptions!$B$22/$C$113),Assumptions!$B$42) -> 3 | V113: =Assumptions!$B$43/$U$113 -> 1 | W113: =Assumptions!$B$44*$V$113 -> 5000000 | X113: =IF($C$113<Assumptions!$B$47,Assumptions!$B$47*(Assumptions!$B$21+Assumptions!$B$22/Assumptions!$B$47)/(Assumptions!$B$21+Assumptions!$B$22/$C$113),Assumptions!$B$47) -> 10 | Y113: =Assumptions!$B$48/$X$113 -> 1 | Z113: =Assumptions!$B$49*$Y$113 -> 3000000 | AA113: =IF($C$113<Assumptions!$B$52,Assumptions!$B$52*(Assumptions!$B$21+Assumptions!$B$22/Assumptions!$B$52)/(Assumptions!$B$21+Assumptions!$B$22/$C$113),Assumptions!$B$52) -> 25 | AB113: =Assumptions!$B$53/$AA$113 -> 1 | AC113: =Assumptions!$B$54*$AB$113 -> 2400000 | AD113: =IF($C$113<Assumptions!$B$57,Assumptions!$B$57*(Assumptions!$B$21+Assumptions!$B$22/Assumptions!$B$57)/(Assumptions!$B$21+Assumptions!$B$22/$C$113),Assumptions!$B$57) -> 57.681736 | AE113: =Assumptions!$B$58/$AD$113 -> 1.0401906 | AF113: =Assumptions!$B$59*$AE$113 -> 1733651.4 | AG113: =IF($C$113<Assumptions!$B$62,Assumptions!$B$62*(Assumptions!$B$21+Assumptions!$B$22/Assumptions!$B$62)/(Assumptions!$B$21+Assumptions!$B$22/$C$113),Assumptions!$B$62) -> 48.912626 | AH113: =Assumptions!$B$63/$AG$113 -> 1.0050229 | AI113: =Assumptions!$B$64*$AH$113 -> 6133320.3
A114: =ROW()-ROW($A$93)+Assumptions!$B$4 -> 21 | B114: =$P$113 -> 587882.23 | C114: =Assumptions!$B$6/(Assumptions!$B$16+$B$114) -> 37.628498 | D114: =Assumptions!$B$7/$C$114 -> 797268.07 | E114: =$T$114+$W$114+$Z$114+$AC$114+$AF$114+$AI$114 -> 23266972 | F114: =Assumptions!$B$70/(Assumptions!$B$20+Assumptions!$B$17+$B$114+$E$114+$O$113) -> 26.778553 | G114: =$C$114*(1-Assumptions!$B$71) -> 30.102798 | H114: =MIN($F$114,$G$114) -> 26.778553 | I114: =IF($F$114<=$G$114,"cap","discount") -> cap | J114: =Assumptions!$B$69/$H$114 -> 186716.59 | K114: =Assumptions!$B$74/(Assumptions!$B$20+Assumptions!$B$17+$B$114+$E$114+$J$114) -> 42.739338 | L114: =$C$114*(1-Assumptions!$B$75) -> 31.984223 | M114: =MIN($K$114,$L$114) -> 31.984223 | N114: =IF($K$114<=$L$114,"cap","discount") -> discount | O114: =Assumptions!$B$73/$M$114 -> 93796.243 | P114: =MAX(Assumptions!$B$4,(Assumptions!$B$10*(Assumptions!$B$20+$E$114+Assumptions!$B$17+$J$114+$O$114+$D$114)-Assumptions!$B$17)/(1-Assumptions!$B$10)) -> 587882.23 | Q114: =Assumptions!$B$20+$E$114+Assumptions!$B$17+$P$114+$J$114+$O$114+$D$114 -> 38327302 | R114: =IF($C$114<Assumptions!$B$37,Assumptions!$B$37*(Assumptions!$B$21+Assumptions!$B$22/Assumptions!$B$37)/(Assumptions!$B$21+Assumptions!$B$22/$C$114),Assumptions!$B$37) -> 1 | S114: =Assumptions!$B$38/$R$114 -> 1 | T114: =Assumptions!$B$39*$S$114 -> 5000000 | U114: =IF($C$114<Assumptions!$B$42,Assumptions!$B$42*(Assumptions!$B$21+Assumptions!$B$22/Assumptions!$B$42)/(Assumptions!$B$21+Assumptions!$B$22/$C$114),Assumptions!$B$42) -> 3 | V114: =Assumptions!$B$43/$U$114 -> 1 | W114: =Assumptions!$B$44*$V$114 -> 5000000 | X114: =IF($C$114<Assumptions!$B$47,Assumptions!$B$47*(Assumptions!$B$21+Assumptions!$B$22/Assumptions!$B$47)/(Assumptions!$B$21+Assumptions!$B$22/$C$114),Assumptions!$B$47) -> 10 | Y114: =Assumptions!$B$48/$X$114 -> 1 | Z114: =Assumptions!$B$49*$Y$114 -> 3000000 | AA114: =IF($C$114<Assumptions!$B$52,Assumptions!$B$52*(Assumptions!$B$21+Assumptions!$B$22/Assumptions!$B$52)/(Assumptions!$B$21+Assumptions!$B$22/$C$114),Assumptions!$B$52) -> 25 | AB114: =Assumptions!$B$53/$AA$114 -> 1 | AC114: =Assumptions!$B$54*$AB$114 -> 2400000 | AD114: =IF($C$114<Assumptions!$B$57,Assumptions!$B$57*(Assumptions!$B$21+Assumptions!$B$22/Assumptions!$B$57)/(Assumptions!$B$21+Assumptions!$B$22/$C$114),Assumptions!$B$57) -> 57.681736 | AE114: =Assumptions!$B$58/$AD$114 -> 1.0401906 | AF114: =Assumptions!$B$59*$AE$114 -> 1733651.4 | AG114: =IF($C$114<Assumptions!$B$62,Assumptions!$B$62*(Assumptions!$B$21+Assumptions!$B$22/Assumptions!$B$62)/(Assumptions!$B$21+Assumptions!$B$22/$C$114),Assumptions!$B$62) -> 48.912626 | AH114: =Assumptions!$B$63/$AG$114 -> 1.0050229 | AI114: =Assumptions!$B$64*$AH$114 -> 6133320.3
A115: =ROW()-ROW($A$93)+Assumptions!$B$4 -> 22 | B115: =$P$114 -> 587882.23 | C115: =Assumptions!$B$6/(Assumptions!$B$16+$B$115) -> 37.628498 | D115: =Assumptions!$B$7/$C$115 -> 797268.07 | E115: =$T$115+$W$115+$Z$115+$AC$115+$AF$115+$AI$115 -> 23266972 | F115: =Assumptions!$B$70/(Assumptions!$B$20+Assumptions!$B$17+$B$115+$E$115+$O$114) -> 26.778553 | G115: =$C$115*(1-Assumptions!$B$71) -> 30.102798 | H115: =MIN($F$115,$G$115) -> 26.778553 | I115: =IF($F$115<=$G$115,"cap","discount") -> cap | J115: =Assumptions!$B$69/$H$115 -> 186716.59 | K115: =Assumptions!$B$74/(Assumptions!$B$20+Assumptions!$B$17+$B$115+$E$115+$J$115) -> 42.739338 | L115: =$C$115*(1-Assumptions!$B$75) -> 31.984223 | M115: =MIN($K$115,$L$115) -> 31.984223 | N115: =IF($K$115<=$L$115,"cap","discount") -> discount | O115: =Assumptions!$B$73/$M$115 -> 93796.243 | P115: =MAX(Assumptions!$B$4,(Assumptions!$B$10*(Assumptions!$B$20+$E$115+Assumptions!$B$17+$J$115+$O$115+$D$115)-Assumptions!$B$17)/(1-Assumptions!$B$10)) -> 587882.23 | Q115: =Assumptions!$B$20+$E$115+Assumptions!$B$17+$P$115+$J$115+$O$115+$D$115 -> 38327302 | R115: =IF($C$115<Assumptions!$B$37,Assumptions!$B$37*(Assumptions!$B$21+Assumptions!$B$22/Assumptions!$B$37)/(Assumptions!$B$21+Assumptions!$B$22/$C$115),Assumptions!$B$37) -> 1 | S115: =Assumptions!$B$38/$R$115 -> 1 | T115: =Assumptions!$B$39*$S$115 -> 5000000 | U115: =IF($C$115<Assumptions!$B$42,Assumptions!$B$42*(Assumptions!$B$21+Assumptions!$B$22/Assumptions!$B$42)/(Assumptions!$B$21+Assumptions!$B$22/$C$115),Assumptions!$B$42) -> 3 | V115: =Assumptions!$B$43/$U$115 -> 1 | W115: =Assumptions!$B$44*$V$115 -> 5000000 | X115: =IF($C$115<Assumptions!$B$47,Assumptions!$B$47*(Assumptions!$B$21+Assumptions!$B$22/Assumptions!$B$47)/(Assumptions!$B$21+Assumptions!$B$22/$C$115),Assumptions!$B$47) -> 10 | Y115: =Assumptions!$B$48/$X$115 -> 1 | Z115: =Assumptions!$B$49*$Y$115 -> 3000000 | AA115: =IF($C$115<Assumptions!$B$52,Assumptions!$B$52*(Assumptions!$B$21+Assumptions!$B$22/Assumptions!$B$52)/(Assumptions!$B$21+Assumptions!$B$22/$C$115),Assumptions!$B$52) -> 25 | AB115: =Assumptions!$B$53/$AA$115 -> 1 | AC115: =Assumptions!$B$54*$AB$115 -> 2400000 | AD115: =IF($C$115<Assumptions!$B$57,Assumptions!$B$57*(Assumptions!$B$21+Assumptions!$B$22/Assumptions!$B$57)/(Assumptions!$B$21+Assumptions!$B$22/$C$115),Assumptions!$B$57) -> 57.681736 | AE115: =Assumptions!$B$58/$AD$115 -> 1.0401906 | AF115: =Assumptions!$B$59*$AE$115 -> 1733651.4 | AG115: =IF($C$115<Assumptions!$B$62,Assumptions!$B$62*(Assumptions!$B$21+Assumptions!$B$22/Assumptions!$B$62)/(Assumptions!$B$21+Assumptions!$B$22/$C$115),Assumptions!$B$62) -> 48.912626 | AH115: =Assumptions!$B$63/$AG$115 -> 1.0050229 | AI115: =Assumptions!$B$64*$AH$115 -> 6133320.3
A116: =ROW()-ROW($A$93)+Assumptions!$B$4 -> 23 | B116: =$P$115 -> 587882.23 | C116: =Assumptions!$B$6/(Assumptions!$B$16+$B$116) -> 37.628498 | D116: =Assumptions!$B$7/$C$116 -> 797268.07 | E116: =$T$116+$W$116+$Z$116+$AC$116+$AF$116+$AI$116 -> 23266972 | F116: =Assumptions!$B$70/(Assumptions!$B$20+Assumptions!$B$17+$B$116+$E$116+$O$115) -> 26.778553 | G116: =$C$116*(1-Assumptions!$B$71) -> 30.102798 | H116: =MIN($F$116,$G$116) -> 26.778553 | I116: =IF($F$116<=$G$116,"cap","discount") -> cap | J116: =Assumptions!$B$69/$H$116 -> 186716.59 | K116: =Assumptions!$B$74/(Assumptions!$B$20+Assumptions!$B$17+$B$116+$E$116+$J$116) -> 42.739338 | L116: =$C$116*(1-Assumptions!$B$75) -> 31.984223 | M116: =MIN($K$116,$L$116) -> 31.984223 | N116: =IF($K$116<=$L$116,"cap","discount") -> discount | O116: =Assumptions!$B$73/$M$116 -> 93796.243 | P116: =MAX(Assumptions!$B$4,(Assumptions!$B$10*(Assumptions!$B$20+$E$116+Assumptions!$B$17+$J$116+$O$116+$D$116)-Assumptions!$B$17)/(1-Assumptions!$B$10)) -> 587882.23 | Q116: =Assumptions!$B$20+$E$116+Assumptions!$B$17+$P$116+$J$116+$O$116+$D$116 -> 38327302 | R116: =IF($C$116<Assumptions!$B$37,Assumptions!$B$37*(Assumptions!$B$21+Assumptions!$B$22/Assumptions!$B$37)/(Assumptions!$B$21+Assumptions!$B$22/$C$116),Assumptions!$B$37) -> 1 | S116: =Assumptions!$B$38/$R$116 -> 1 | T116: =Assumptions!$B$39*$S$116 -> 5000000 | U116: =IF($C$116<Assumptions!$B$42,Assumptions!$B$42*(Assumptions!$B$21+Assumptions!$B$22/Assumptions!$B$42)/(Assumptions!$B$21+Assumptions!$B$22/$C$116),Assumptions!$B$42) -> 3 | V116: =Assumptions!$B$43/$U$116 -> 1 | W116: =Assumptions!$B$44*$V$116 -> 5000000 | X116: =IF($C$116<Assumptions!$B$47,Assumptions!$B$47*(Assumptions!$B$21+Assumptions!$B$22/Assumptions!$B$47)/(Assumptions!$B$21+Assumptions!$B$22/$C$116),Assumptions!$B$47) -> 10 | Y116: =Assumptions!$B$48/$X$116 -> 1 | Z116: =Assumptions!$B$49*$Y$116 -> 3000000 | AA116: =IF($C$116<Assumptions!$B$52,Assumptions!$B$52*(Assumptions!$B$21+Assumptions!$B$22/Assumptions!$B$52)/(Assumptions!$B$21+Assumptions!$B$22/$C$116),Assumptions!$B$52) -> 25 | AB116: =Assumptions!$B$53/$AA$116 -> 1 | AC116: =Assumptions!$B$54*$AB$116 -> 2400000 | AD116: =IF($C$116<Assumptions!$B$57,Assumptions!$B$57*(Assumptions!$B$21+Assumptions!$B$22/Assumptions!$B$57)/(Assumptions!$B$21+Assumptions!$B$22/$C$116),Assumptions!$B$57) -> 57.681736 | AE116: =Assumptions!$B$58/$AD$116 -> 1.0401906 | AF116: =Assumptions!$B$59*$AE$116 -> 1733651.4 | AG116: =IF($C$116<Assumptions!$B$62,Assumptions!$B$62*(Assumptions!$B$21+Assumptions!$B$22/Assumptions!$B$62)/(Assumptions!$B$21+Assumptions!$B$22/$C$116),Assumptions!$B$62) -> 48.912626 | AH116: =Assumptions!$B$63/$AG$116 -> 1.0050229 | AI116: =Assumptions!$B$64*$AH$116 -> 6133320.3
A117: =ROW()-ROW($A$93)+Assumptions!$B$4 -> 24 | B117: =$P$116 -> 587882.23 | C117: =Assumptions!$B$6/(Assumptions!$B$16+$B$117) -> 37.628498 | D117: =Assumptions!$B$7/$C$117 -> 797268.07 | E117: =$T$117+$W$117+$Z$117+$AC$117+$AF$117+$AI$117 -> 23266972 | F117: =Assumptions!$B$70/(Assumptions!$B$20+Assumptions!$B$17+$B$117+$E$117+$O$116) -> 26.778553 | G117: =$C$117*(1-Assumptions!$B$71) -> 30.102798 | H117: =MIN($F$117,$G$117) -> 26.778553 | I117: =IF($F$117<=$G$117,"cap","discount") -> cap | J117: =Assumptions!$B$69/$H$117 -> 186716.59 | K117: =Assumptions!$B$74/(Assumptions!$B$20+Assumptions!$B$17+$B$117+$E$117+$J$117) -> 42.739338 | L117: =$C$117*(1-Assumptions!$B$75) -> 31.984223 | M117: =MIN($K$117,$L$117) -> 31.984223 | N117: =IF($K$117<=$L$117,"cap","discount") -> discount | O117: =Assumptions!$B$73/$M$117 -> 93796.243 | P117: =MAX(Assumptions!$B$4,(Assumptions!$B$10*(Assumptions!$B$20+$E$117+Assumptions!$B$17+$J$117+$O$117+$D$117)-Assumptions!$B$17)/(1-Assumptions!$B$10)) -> 587882.23 | Q117: =Assumptions!$B$20+$E$117+Assumptions!$B$17+$P$117+$J$117+$O$117+$D$117 -> 38327302 | R117: =IF($C$117<Assumptions!$B$37,Assumptions!$B$37*(Assumptions!$B$21+Assumptions!$B$22/Assumptions!$B$37)/(Assumptions!$B$21+Assumptions!$B$22/$C$117),Assumptions!$B$37) -> 1 | S117: =Assumptions!$B$38/$R$117 -> 1 | T117: =Assumptions!$B$39*$S$117 -> 5000000 | U117: =IF($C$117<Assumptions!$B$42,Assumptions!$B$42*(Assumptions!$B$21+Assumptions!$B$22/Assumptions!$B$42)/(Assumptions!$B$21+Assumptions!$B$22/$C$117),Assumptions!$B$42) -> 3 | V117: =Assumptions!$B$43/$U$117 -> 1 | W117: =Assumptions!$B$44*$V$117 -> 5000000 | X117: =IF($C$117<Assumptions!$B$47,Assumptions!$B$47*(Assumptions!$B$21+Assumptions!$B$22/Assumptions!$B$47)/(Assumptions!$B$21+Assumptions!$B$22/$C$117),Assumptions!$B$47) -> 10 | Y117: =Assumptions!$B$48/$X$117 -> 1 | Z117: =Assumptions!$B$49*$Y$117 -> 3000000 | AA117: =IF($C$117<Assumptions!$B$52,Assumptions!$B$52*(Assumptions!$B$21+Assumptions!$B$22/Assumptions!$B$52)/(Assumptions!$B$21+Assumptions!$B$22/$C$117),Assumptions!$B$52) -> 25 | AB117: =Assumptions!$B$53/$AA$117 -> 1 | AC117: =Assumptions!$B$54*$AB$117 -> 2400000 | AD117: =IF($C$117<Assumptions!$B$57,Assumptions!$B$57*(Assumptions!$B$21+Assumptions!$B$22/Assumptions!$B$57)/(Assumptions!$B$21+Assumptions!$B$22/$C$117),Assumptions!$B$57) -> 57.681736 | AE117: =Assumptions!$B$58/$AD$117 -> 1.0401906 | AF117: =Assumptions!$B$59*$AE$117 -> 1733651.4 | AG117: =IF($C$117<Assumptions!$B$62,Assumptions!$B$62*(Assumptions!$B$21+Assumptions!$B$22/Assumptions!$B$62)/(Assumptions!$B$21+Assumptions!$B$22/$C$117),Assumptions!$B$62) -> 48.912626 | AH117: =Assumptions!$B$63/$AG$117 -> 1.0050229 | AI117: =Assumptions!$B$64*$AH$117 -> 6133320.3
A118: =ROW()-ROW($A$93)+Assumptions!$B$4 -> 25 | B118: =$P$117 -> 587882.23 | C118: =Assumptions!$B$6/(Assumptions!$B$16+$B$118) -> 37.628498 | D118: =Assumptions!$B$7/$C$118 -> 797268.07 | E118: =$T$118+$W$118+$Z$118+$AC$118+$AF$118+$AI$118 -> 23266972 | F118: =Assumptions!$B$70/(Assumptions!$B$20+Assumptions!$B$17+$B$118+$E$118+$O$117) -> 26.778553 | G118: =$C$118*(1-Assumptions!$B$71) -> 30.102798 | H118: =MIN($F$118,$G$118) -> 26.778553 | I118: =IF($F$118<=$G$118,"cap","discount") -> cap | J118: =Assumptions!$B$69/$H$118 -> 186716.59 | K118: =Assumptions!$B$74/(Assumptions!$B$20+Assumptions!$B$17+$B$118+$E$118+$J$118) -> 42.739338 | L118: =$C$118*(1-Assumptions!$B$75) -> 31.984223 | M118: =MIN($K$118,$L$118) -> 31.984223 | N118: =IF($K$118<=$L$118,"cap","discount") -> discount | O118: =Assumptions!$B$73/$M$118 -> 93796.243 | P118: =MAX(Assumptions!$B$4,(Assumptions!$B$10*(Assumptions!$B$20+$E$118+Assumptions!$B$17+$J$118+$O$118+$D$118)-Assumptions!$B$17)/(1-Assumptions!$B$10)) -> 587882.23 | Q118: =Assumptions!$B$20+$E$118+Assumptions!$B$17+$P$118+$J$118+$O$118+$D$118 -> 38327302 | R118: =IF($C$118<Assumptions!$B$37,Assumptions!$B$37*(Assumptions!$B$21+Assumptions!$B$22/Assumptions!$B$37)/(Assumptions!$B$21+Assumptions!$B$22/$C$118),Assumptions!$B$37) -> 1 | S118: =Assumptions!$B$38/$R$118 -> 1 | T118: =Assumptions!$B$39*$S$118 -> 5000000 | U118: =IF($C$118<Assumptions!$B$42,Assumptions!$B$42*(Assumptions!$B$21+Assumptions!$B$22/Assumptions!$B$42)/(Assumptions!$B$21+Assumptions!$B$22/$C$118),Assumptions!$B$42) -> 3 | V118: =Assumptions!$B$43/$U$118 -> 1 | W118: =Assumptions!$B$44*$V$118 -> 5000000 | X118: =IF($C$118<Assumptions!$B$47,Assumptions!$B$47*(Assumptions!$B$21+Assumptions!$B$22/Assumptions!$B$47)/(Assumptions!$B$21+Assumptions!$B$22/$C$118),Assumptions!$B$47) -> 10 | Y118: =Assumptions!$B$48/$X$118 -> 1 | Z118: =Assumptions!$B$49*$Y$118 -> 3000000 | AA118: =IF($C$118<Assumptions!$B$52,Assumptions!$B$52*(Assumptions!$B$21+Assumptions!$B$22/Assumptions!$B$52)/(Assumptions!$B$21+Assumptions!$B$22/$C$118),Assumptions!$B$52) -> 25 | AB118: =Assumptions!$B$53/$AA$118 -> 1 | AC118: =Assumptions!$B$54*$AB$118 -> 2400000 | AD118: =IF($C$118<Assumptions!$B$57,Assumptions!$B$57*(Assumptions!$B$21+Assumptions!$B$22/Assumptions!$B$57)/(Assumptions!$B$21+Assumptions!$B$22/$C$118),Assumptions!$B$57) -> 57.681736 | AE118: =Assumptions!$B$58/$AD$118 -> 1.0401906 | AF118: =Assumptions!$B$59*$AE$118 -> 1733651.4 | AG118: =IF($C$118<Assumptions!$B$62,Assumptions!$B$62*(Assumptions!$B$21+Assumptions!$B$22/Assumptions!$B$62)/(Assumptions!$B$21+Assumptions!$B$22/$C$118),Assumptions!$B$62) -> 48.912626 | AH118: =Assumptions!$B$63/$AG$118 -> 1.0050229 | AI118: =Assumptions!$B$64*$AH$118 -> 6133320.3
A119: =ROW()-ROW($A$93)+Assumptions!$B$4 -> 26 | B119: =$P$118 -> 587882.23 | C119: =Assumptions!$B$6/(Assumptions!$B$16+$B$119) -> 37.628498 | D119: =Assumptions!$B$7/$C$119 -> 797268.07 | E119: =$T$119+$W$119+$Z$119+$AC$119+$AF$119+$AI$119 -> 23266972 | F119: =Assumptions!$B$70/(Assumptions!$B$20+Assumptions!$B$17+$B$119+$E$119+$O$118) -> 26.778553 | G119: =$C$119*(1-Assumptions!$B$71) -> 30.102798 | H119: =MIN($F$119,$G$119) -> 26.778553 | I119: =IF($F$119<=$G$119,"cap","discount") -> cap | J119: =Assumptions!$B$69/$H$119 -> 186716.59 | K119: =Assumptions!$B$74/(Assumptions!$B$20+Assumptions!$B$17+$B$119+$E$119+$J$119) -> 42.739338 | L119: =$C$119*(1-Assumptions!$B$75) -> 31.984223 | M119: =MIN($K$119,$L$119) -> 31.984223 | N119: =IF($K$119<=$L$119,"cap","discount") -> discount | O119: =Assumptions!$B$73/$M$119 -> 93796.243 | P119: =MAX(Assumptions!$B$4,(Assumptions!$B$10*(Assumptions!$B$20+$E$119+Assumptions!$B$17+$J$119+$O$119+$D$119)-Assumptions!$B$17)/(1-Assumptions!$B$10)) -> 587882.23 | Q119: =Assumptions!$B$20+$E$119+Assumptions!$B$17+$P$119+$J$119+$O$119+$D$119 -> 38327302 | R119: =IF($C$119<Assumptions!$B$37,Assumptions!$B$37*(Assumptions!$B$21+Assumptions!$B$22/Assumptions!$B$37)/(Assumptions!$B$21+Assumptions!$B$22/$C$119),Assumptions!$B$37) -> 1 | S119: =Assumptions!$B$38/$R$119 -> 1 | T119: =Assumptions!$B$39*$S$119 -> 5000000 | U119: =IF($C$119<Assumptions!$B$42,Assumptions!$B$42*(Assumptions!$B$21+Assumptions!$B$22/Assumptions!$B$42)/(Assumptions!$B$21+Assumptions!$B$22/$C$119),Assumptions!$B$42) -> 3 | V119: =Assumptions!$B$43/$U$119 -> 1 | W119: =Assumptions!$B$44*$V$119 -> 5000000 | X119: =IF($C$119<Assumptions!$B$47,Assumptions!$B$47*(Assumptions!$B$21+Assumptions!$B$22/Assumptions!$B$47)/(Assumptions!$B$21+Assumptions!$B$22/$C$119),Assumptions!$B$47) -> 10 | Y119: =Assumptions!$B$48/$X$119 -> 1 | Z119: =Assumptions!$B$49*$Y$119 -> 3000000 | AA119: =IF($C$119<Assumptions!$B$52,Assumptions!$B$52*(Assumptions!$B$21+Assumptions!$B$22/Assumptions!$B$52)/(Assumptions!$B$21+Assumptions!$B$22/$C$119),Assumptions!$B$52) -> 25 | AB119: =Assumptions!$B$53/$AA$119 -> 1 | AC119: =Assumptions!$B$54*$AB$119 -> 2400000 | AD119: =IF($C$119<Assumptions!$B$57,Assumptions!$B$57*(Assumptions!$B$21+Assumptions!$B$22/Assumptions!$B$57)/(Assumptions!$B$21+Assumptions!$B$22/$C$119),Assumptions!$B$57) -> 57.681736 | AE119: =Assumptions!$B$58/$AD$119 -> 1.0401906 | AF119: =Assumptions!$B$59*$AE$119 -> 1733651.4 | AG119: =IF($C$119<Assumptions!$B$62,Assumptions!$B$62*(Assumptions!$B$21+Assumptions!$B$22/Assumptions!$B$62)/(Assumptions!$B$21+Assumptions!$B$22/$C$119),Assumptions!$B$62) -> 48.912626 | AH119: =Assumptions!$B$63/$AG$119 -> 1.0050229 | AI119: =Assumptions!$B$64*$AH$119 -> 6133320.3
A120: =ROW()-ROW($A$93)+Assumptions!$B$4 -> 27 | B120: =$P$119 -> 587882.23 | C120: =Assumptions!$B$6/(Assumptions!$B$16+$B$120) -> 37.628498 | D120: =Assumptions!$B$7/$C$120 -> 797268.07 | E120: =$T$120+$W$120+$Z$120+$AC$120+$AF$120+$AI$120 -> 23266972 | F120: =Assumptions!$B$70/(Assumptions!$B$20+Assumptions!$B$17+$B$120+$E$120+$O$119) -> 26.778553 | G120: =$C$120*(1-Assumptions!$B$71) -> 30.102798 | H120: =MIN($F$120,$G$120) -> 26.778553 | I120: =IF($F$120<=$G$120,"cap","discount") -> cap | J120: =Assumptions!$B$69/$H$120 -> 186716.59 | K120: =Assumptions!$B$74/(Assumptions!$B$20+Assumptions!$B$17+$B$120+$E$120+$J$120) -> 42.739338 | L120: =$C$120*(1-Assumptions!$B$75) -> 31.984223 | M120: =MIN($K$120,$L$120) -> 31.984223 | N120: =IF($K$120<=$L$120,"cap","discount") -> discount | O120: =Assumptions!$B$73/$M$120 -> 93796.243 | P120: =MAX(Assumptions!$B$4,(Assumptions!$B$10*(Assumptions!$B$20+$E$120+Assumptions!$B$17+$J$120+$O$120+$D$120)-Assumptions!$B$17)/(1-Assumptions!$B$10)) -> 587882.23 | Q120: =Assumptions!$B$20+$E$120+Assumptions!$B$17+$P$120+$J$120+$O$120+$D$120 -> 38327302 | R120: =IF($C$120<Assumptions!$B$37,Assumptions!$B$37*(Assumptions!$B$21+Assumptions!$B$22/Assumptions!$B$37)/(Assumptions!$B$21+Assumptions!$B$22/$C$120),Assumptions!$B$37) -> 1 | S120: =Assumptions!$B$38/$R$120 -> 1 | T120: =Assumptions!$B$39*$S$120 -> 5000000 | U120: =IF($C$120<Assumptions!$B$42,Assumptions!$B$42*(Assumptions!$B$21+Assumptions!$B$22/Assumptions!$B$42)/(Assumptions!$B$21+Assumptions!$B$22/$C$120),Assumptions!$B$42) -> 3 | V120: =Assumptions!$B$43/$U$120 -> 1 | W120: =Assumptions!$B$44*$V$120 -> 5000000 | X120: =IF($C$120<Assumptions!$B$47,Assumptions!$B$47*(Assumptions!$B$21+Assumptions!$B$22/Assumptions!$B$47)/(Assumptions!$B$21+Assumptions!$B$22/$C$120),Assumptions!$B$47) -> 10 | Y120: =Assumptions!$B$48/$X$120 -> 1 | Z120: =Assumptions!$B$49*$Y$120 -> 3000000 | AA120: =IF($C$120<Assumptions!$B$52,Assumptions!$B$52*(Assumptions!$B$21+Assumptions!$B$22/Assumptions!$B$52)/(Assumptions!$B$21+Assumptions!$B$22/$C$120),Assumptions!$B$52) -> 25 | AB120: =Assumptions!$B$53/$AA$120 -> 1 | AC120: =Assumptions!$B$54*$AB$120 -> 2400000 | AD120: =IF($C$120<Assumptions!$B$57,Assumptions!$B$57*(Assumptions!$B$21+Assumptions!$B$22/Assumptions!$B$57)/(Assumptions!$B$21+Assumptions!$B$22/$C$120),Assumptions!$B$57) -> 57.681736 | AE120: =Assumptions!$B$58/$AD$120 -> 1.0401906 | AF120: =Assumptions!$B$59*$AE$120 -> 1733651.4 | AG120: =IF($C$120<Assumptions!$B$62,Assumptions!$B$62*(Assumptions!$B$21+Assumptions!$B$22/Assumptions!$B$62)/(Assumptions!$B$21+Assumptions!$B$22/$C$120),Assumptions!$B$62) -> 48.912626 | AH120: =Assumptions!$B$63/$AG$120 -> 1.0050229 | AI120: =Assumptions!$B$64*$AH$120 -> 6133320.3
A121: =ROW()-ROW($A$93)+Assumptions!$B$4 -> 28 | B121: =$P$120 -> 587882.23 | C121: =Assumptions!$B$6/(Assumptions!$B$16+$B$121) -> 37.628498 | D121: =Assumptions!$B$7/$C$121 -> 797268.07 | E121: =$T$121+$W$121+$Z$121+$AC$121+$AF$121+$AI$121 -> 23266972 | F121: =Assumptions!$B$70/(Assumptions!$B$20+Assumptions!$B$17+$B$121+$E$121+$O$120) -> 26.778553 | G121: =$C$121*(1-Assumptions!$B$71) -> 30.102798 | H121: =MIN($F$121,$G$121) -> 26.778553 | I121: =IF($F$121<=$G$121,"cap","discount") -> cap | J121: =Assumptions!$B$69/$H$121 -> 186716.59 | K121: =Assumptions!$B$74/(Assumptions!$B$20+Assumptions!$B$17+$B$121+$E$121+$J$121) -> 42.739338 | L121: =$C$121*(1-Assumptions!$B$75) -> 31.984223 | M121: =MIN($K$121,$L$121) -> 31.984223 | N121: =IF($K$121<=$L$121,"cap","discount") -> discount | O121: =Assumptions!$B$73/$M$121 -> 93796.243 | P121: =MAX(Assumptions!$B$4,(Assumptions!$B$10*(Assumptions!$B$20+$E$121+Assumptions!$B$17+$J$121+$O$121+$D$121)-Assumptions!$B$17)/(1-Assumptions!$B$10)) -> 587882.23 | Q121: =Assumptions!$B$20+$E$121+Assumptions!$B$17+$P$121+$J$121+$O$121+$D$121 -> 38327302 | R121: =IF($C$121<Assumptions!$B$37,Assumptions!$B$37*(Assumptions!$B$21+Assumptions!$B$22/Assumptions!$B$37)/(Assumptions!$B$21+Assumptions!$B$22/$C$121),Assumptions!$B$37) -> 1 | S121: =Assumptions!$B$38/$R$121 -> 1 | T121: =Assumptions!$B$39*$S$121 -> 5000000 | U121: =IF($C$121<Assumptions!$B$42,Assumptions!$B$42*(Assumptions!$B$21+Assumptions!$B$22/Assumptions!$B$42)/(Assumptions!$B$21+Assumptions!$B$22/$C$121),Assumptions!$B$42) -> 3 | V121: =Assumptions!$B$43/$U$121 -> 1 | W121: =Assumptions!$B$44*$V$121 -> 5000000 | X121: =IF($C$121<Assumptions!$B$47,Assumptions!$B$47*(Assumptions!$B$21+Assumptions!$B$22/Assumptions!$B$47)/(Assumptions!$B$21+Assumptions!$B$22/$C$121),Assumptions!$B$47) -> 10 | Y121: =Assumptions!$B$48/$X$121 -> 1 | Z121: =Assumptions!$B$49*$Y$121 -> 3000000 | AA121: =IF($C$121<Assumptions!$B$52,Assumptions!$B$52*(Assumptions!$B$21+Assumptions!$B$22/Assumptions!$B$52)/(Assumptions!$B$21+Assumptions!$B$22/$C$121),Assumptions!$B$52) -> 25 | AB121: =Assumptions!$B$53/$AA$121 -> 1 | AC121: =Assumptions!$B$54*$AB$121 -> 2400000 | AD121: =IF($C$121<Assumptions!$B$57,Assumptions!$B$57*(Assumptions!$B$21+Assumptions!$B$22/Assumptions!$B$57)/(Assumptions!$B$21+Assumptions!$B$22/$C$121),Assumptions!$B$57) -> 57.681736 | AE121: =Assumptions!$B$58/$AD$121 -> 1.0401906 | AF121: =Assumptions!$B$59*$AE$121 -> 1733651.4 | AG121: =IF($C$121<Assumptions!$B$62,Assumptions!$B$62*(Assumptions!$B$21+Assumptions!$B$22/Assumptions!$B$62)/(Assumptions!$B$21+Assumptions!$B$22/$C$121),Assumptions!$B$62) -> 48.912626 | AH121: =Assumptions!$B$63/$AG$121 -> 1.0050229 | AI121: =Assumptions!$B$64*$AH$121 -> 6133320.3
A122: =ROW()-ROW($A$93)+Assumptions!$B$4 -> 29 | B122: =$P$121 -> 587882.23 | C122: =Assumptions!$B$6/(Assumptions!$B$16+$B$122) -> 37.628498 | D122: =Assumptions!$B$7/$C$122 -> 797268.07 | E122: =$T$122+$W$122+$Z$122+$AC$122+$AF$122+$AI$122 -> 23266972 | F122: =Assumptions!$B$70/(Assumptions!$B$20+Assumptions!$B$17+$B$122+$E$122+$O$121) -> 26.778553 | G122: =$C$122*(1-Assumptions!$B$71) -> 30.102798 | H122: =MIN($F$122,$G$122) -> 26.778553 | I122: =IF($F$122<=$G$122,"cap","discount") -> cap | J122: =Assumptions!$B$69/$H$122 -> 186716.59 | K122: =Assumptions!$B$74/(Assumptions!$B$20+Assumptions!$B$17+$B$122+$E$122+$J$122) -> 42.739338 | L122: =$C$122*(1-Assumptions!$B$75) -> 31.984223 | M122: =MIN($K$122,$L$122) -> 31.984223 | N122: =IF($K$122<=$L$122,"cap","discount") -> discount | O122: =Assumptions!$B$73/$M$122 -> 93796.243 | P122: =MAX(Assumptions!$B$4,(Assumptions!$B$10*(Assumptions!$B$20+$E$122+Assumptions!$B$17+$J$122+$O$122+$D$122)-Assumptions!$B$17)/(1-Assumptions!$B$10)) -> 587882.23 | Q122: =Assumptions!$B$20+$E$122+Assumptions!$B$17+$P$122+$J$122+$O$122+$D$122 -> 38327302 | R122: =IF($C$122<Assumptions!$B$37,Assumptions!$B$37*(Assumptions!$B$21+Assumptions!$B$22/Assumptions!$B$37)/(Assumptions!$B$21+Assumptions!$B$22/$C$122),Assumptions!$B$37) -> 1 | S122: =Assumptions!$B$38/$R$122 -> 1 | T122: =Assumptions!$B$39*$S$122 -> 5000000 | U122: =IF($C$122<Assumptions!$B$42,Assumptions!$B$42*(Assumptions!$B$21+Assumptions!$B$22/Assumptions!$B$42)/(Assumptions!$B$21+Assumptions!$B$22/$C$122),Assumptions!$B$42) -> 3 | V122: =Assumptions!$B$43/$U$122 -> 1 | W122: =Assumptions!$B$44*$V$122 -> 5000000 | X122: =IF($C$122<Assumptions!$B$47,Assumptions!$B$47*(Assumptions!$B$21+Assumptions!$B$22/Assumptions!$B$47)/(Assumptions!$B$21+Assumptions!$B$22/$C$122),Assumptions!$B$47) -> 10 | Y122: =Assumptions!$B$48/$X$122 -> 1 | Z122: =Assumptions!$B$49*$Y$122 -> 3000000 | AA122: =IF($C$122<Assumptions!$B$52,Assumptions!$B$52*(Assumptions!$B$21+Assumptions!$B$22/Assumptions!$B$52)/(Assumptions!$B$21+Assumptions!$B$22/$C$122),Assumptions!$B$52) -> 25 | AB122: =Assumptions!$B$53/$AA$122 -> 1 | AC122: =Assumptions!$B$54*$AB$122 -> 2400000 | AD122: =IF($C$122<Assumptions!$B$57,Assumptions!$B$57*(Assumptions!$B$21+Assumptions!$B$22/Assumptions!$B$57)/(Assumptions!$B$21+Assumptions!$B$22/$C$122),Assumptions!$B$57) -> 57.681736 | AE122: =Assumptions!$B$58/$AD$122 -> 1.0401906 | AF122: =Assumptions!$B$59*$AE$122 -> 1733651.4 | AG122: =IF($C$122<Assumptions!$B$62,Assumptions!$B$62*(Assumptions!$B$21+Assumptions!$B$22/Assumptions!$B$62)/(Assumptions!$B$21+Assumptions!$B$22/$C$122),Assumptions!$B$62) -> 48.912626 | AH122: =Assumptions!$B$63/$AG$122 -> 1.0050229 | AI122: =Assumptions!$B$64*$AH$122 -> 6133320.3
A123: =ROW()-ROW($A$93)+Assumptions!$B$4 -> 30 | B123: =$P$122 -> 587882.23 | C123: =Assumptions!$B$6/(Assumptions!$B$16+$B$123) -> 37.628498 | D123: =Assumptions!$B$7/$C$123 -> 797268.07 | E123: =$T$123+$W$123+$Z$123+$AC$123+$AF$123+$AI$123 -> 23266972 | F123: =Assumptions!$B$70/(Assumptions!$B$20+Assumptions!$B$17+$B$123+$E$123+$O$122) -> 26.778553 | G123: =$C$123*(1-Assumptions!$B$71) -> 30.102798 | H123: =MIN($F$123,$G$123) -> 26.778553 | I123: =IF($F$123<=$G$123,"cap","discount") -> cap | J123: =Assumptions!$B$69/$H$123 -> 186716.59 | K123: =Assumptions!$B$74/(Assumptions!$B$20+Assumptions!$B$17+$B$123+$E$123+$J$123) -> 42.739338 | L123: =$C$123*(1-Assumptions!$B$75) -> 31.984223 | M123: =MIN($K$123,$L$123) -> 31.984223 | N123: =IF($K$123<=$L$123,"cap","discount") -> discount | O123: =Assumptions!$B$73/$M$123 -> 93796.243 | P123: =MAX(Assumptions!$B$4,(Assumptions!$B$10*(Assumptions!$B$20+$E$123+Assumptions!$B$17+$J$123+$O$123+$D$123)-Assumptions!$B$17)/(1-Assumptions!$B$10)) -> 587882.23 | Q123: =Assumptions!$B$20+$E$123+Assumptions!$B$17+$P$123+$J$123+$O$123+$D$123 -> 38327302 | R123: =IF($C$123<Assumptions!$B$37,Assumptions!$B$37*(Assumptions!$B$21+Assumptions!$B$22/Assumptions!$B$37)/(Assumptions!$B$21+Assumptions!$B$22/$C$123),Assumptions!$B$37) -> 1 | S123: =Assumptions!$B$38/$R$123 -> 1 | T123: =Assumptions!$B$39*$S$123 -> 5000000 | U123: =IF($C$123<Assumptions!$B$42,Assumptions!$B$42*(Assumptions!$B$21+Assumptions!$B$22/Assumptions!$B$42)/(Assumptions!$B$21+Assumptions!$B$22/$C$123),Assumptions!$B$42) -> 3 | V123: =Assumptions!$B$43/$U$123 -> 1 | W123: =Assumptions!$B$44*$V$123 -> 5000000 | X123: =IF($C$123<Assumptions!$B$47,Assumptions!$B$47*(Assumptions!$B$21+Assumptions!$B$22/Assumptions!$B$47)/(Assumptions!$B$21+Assumptions!$B$22/$C$123),Assumptions!$B$47) -> 10 | Y123: =Assumptions!$B$48/$X$123 -> 1 | Z123: =Assumptions!$B$49*$Y$123 -> 3000000 | AA123: =IF($C$123<Assumptions!$B$52,Assumptions!$B$52*(Assumptions!$B$21+Assumptions!$B$22/Assumptions!$B$52)/(Assumptions!$B$21+Assumptions!$B$22/$C$123),Assumptions!$B$52) -> 25 | AB123: =Assumptions!$B$53/$AA$123 -> 1 | AC123: =Assumptions!$B$54*$AB$123 -> 2400000 | AD123: =IF($C$123<Assumptions!$B$57,Assumptions!$B$57*(Assumptions!$B$21+Assumptions!$B$22/Assumptions!$B$57)/(Assumptions!$B$21+Assumptions!$B$22/$C$123),Assumptions!$B$57) -> 57.681736 | AE123: =Assumptions!$B$58/$AD$123 -> 1.0401906 | AF123: =Assumptions!$B$59*$AE$123 -> 1733651.4 | AG123: =IF($C$123<Assumptions!$B$62,Assumptions!$B$62*(Assumptions!$B$21+Assumptions!$B$22/Assumptions!$B$62)/(Assumptions!$B$21+Assumptions!$B$22/$C$123),Assumptions!$B$62) -> 48.912626 | AH123: =Assumptions!$B$63/$AG$123 -> 1.0050229 | AI123: =Assumptions!$B$64*$AH$123 -> 6133320.3
A124: =ROW()-ROW($A$93)+Assumptions!$B$4 -> 31 | B124: =$P$123 -> 587882.23 | C124: =Assumptions!$B$6/(Assumptions!$B$16+$B$124) -> 37.628498 | D124: =Assumptions!$B$7/$C$124 -> 797268.07 | E124: =$T$124+$W$124+$Z$124+$AC$124+$AF$124+$AI$124 -> 23266972 | F124: =Assumptions!$B$70/(Assumptions!$B$20+Assumptions!$B$17+$B$124+$E$124+$O$123) -> 26.778553 | G124: =$C$124*(1-Assumptions!$B$71) -> 30.102798 | H124: =MIN($F$124,$G$124) -> 26.778553 | I124: =IF($F$124<=$G$124,"cap","discount") -> cap | J124: =Assumptions!$B$69/$H$124 -> 186716.59 | K124: =Assumptions!$B$74/(Assumptions!$B$20+Assumptions!$B$17+$B$124+$E$124+$J$124) -> 42.739338 | L124: =$C$124*(1-Assumptions!$B$75) -> 31.984223 | M124: =MIN($K$124,$L$124) -> 31.984223 | N124: =IF($K$124<=$L$124,"cap","discount") -> discount | O124: =Assumptions!$B$73/$M$124 -> 93796.243 | P124: =MAX(Assumptions!$B$4,(Assumptions!$B$10*(Assumptions!$B$20+$E$124+Assumptions!$B$17+$J$124+$O$124+$D$124)-Assumptions!$B$17)/(1-Assumptions!$B$10)) -> 587882.23 | Q124: =Assumptions!$B$20+$E$124+Assumptions!$B$17+$P$124+$J$124+$O$124+$D$124 -> 38327302 | R124: =IF($C$124<Assumptions!$B$37,Assumptions!$B$37*(Assumptions!$B$21+Assumptions!$B$22/Assumptions!$B$37)/(Assumptions!$B$21+Assumptions!$B$22/$C$124),Assumptions!$B$37) -> 1 | S124: =Assumptions!$B$38/$R$124 -> 1 | T124: =Assumptions!$B$39*$S$124 -> 5000000 | U124: =IF($C$124<Assumptions!$B$42,Assumptions!$B$42*(Assumptions!$B$21+Assumptions!$B$22/Assumptions!$B$42)/(Assumptions!$B$21+Assumptions!$B$22/$C$124),Assumptions!$B$42) -> 3 | V124: =Assumptions!$B$43/$U$124 -> 1 | W124: =Assumptions!$B$44*$V$124 -> 5000000 | X124: =IF($C$124<Assumptions!$B$47,Assumptions!$B$47*(Assumptions!$B$21+Assumptions!$B$22/Assumptions!$B$47)/(Assumptions!$B$21+Assumptions!$B$22/$C$124),Assumptions!$B$47) -> 10 | Y124: =Assumptions!$B$48/$X$124 -> 1 | Z124: =Assumptions!$B$49*$Y$124 -> 3000000 | AA124: =IF($C$124<Assumptions!$B$52,Assumptions!$B$52*(Assumptions!$B$21+Assumptions!$B$22/Assumptions!$B$52)/(Assumptions!$B$21+Assumptions!$B$22/$C$124),Assumptions!$B$52) -> 25 | AB124: =Assumptions!$B$53/$AA$124 -> 1 | AC124: =Assumptions!$B$54*$AB$124 -> 2400000 | AD124: =IF($C$124<Assumptions!$B$57,Assumptions!$B$57*(Assumptions!$B$21+Assumptions!$B$22/Assumptions!$B$57)/(Assumptions!$B$21+Assumptions!$B$22/$C$124),Assumptions!$B$57) -> 57.681736 | AE124: =Assumptions!$B$58/$AD$124 -> 1.0401906 | AF124: =Assumptions!$B$59*$AE$124 -> 1733651.4 | AG124: =IF($C$124<Assumptions!$B$62,Assumptions!$B$62*(Assumptions!$B$21+Assumptions!$B$22/Assumptions!$B$62)/(Assumptions!$B$21+Assumptions!$B$22/$C$124),Assumptions!$B$62) -> 48.912626 | AH124: =Assumptions!$B$63/$AG$124 -> 1.0050229 | AI124: =Assumptions!$B$64*$AH$124 -> 6133320.3
A125: =ROW()-ROW($A$93)+Assumptions!$B$4 -> 32 | B125: =$P$124 -> 587882.23 | C125: =Assumptions!$B$6/(Assumptions!$B$16+$B$125) -> 37.628498 | D125: =Assumptions!$B$7/$C$125 -> 797268.07 | E125: =$T$125+$W$125+$Z$125+$AC$125+$AF$125+$AI$125 -> 23266972 | F125: =Assumptions!$B$70/(Assumptions!$B$20+Assumptions!$B$17+$B$125+$E$125+$O$124) -> 26.778553 | G125: =$C$125*(1-Assumptions!$B$71) -> 30.102798 | H125: =MIN($F$125,$G$125) -> 26.778553 | I125: =IF($F$125<=$G$125,"cap","discount") -> cap | J125: =Assumptions!$B$69/$H$125 -> 186716.59 | K125: =Assumptions!$B$74/(Assumptions!$B$20+Assumptions!$B$17+$B$125+$E$125+$J$125) -> 42.739338 | L125: =$C$125*(1-Assumptions!$B$75) -> 31.984223 | M125: =MIN($K$125,$L$125) -> 31.984223 | N125: =IF($K$125<=$L$125,"cap","discount") -> discount | O125: =Assumptions!$B$73/$M$125 -> 93796.243 | P125: =MAX(Assumptions!$B$4,(Assumptions!$B$10*(Assumptions!$B$20+$E$125+Assumptions!$B$17+$J$125+$O$125+$D$125)-Assumptions!$B$17)/(1-Assumptions!$B$10)) -> 587882.23 | Q125: =Assumptions!$B$20+$E$125+Assumptions!$B$17+$P$125+$J$125+$O$125+$D$125 -> 38327302 | R125: =IF($C$125<Assumptions!$B$37,Assumptions!$B$37*(Assumptions!$B$21+Assumptions!$B$22/Assumptions!$B$37)/(Assumptions!$B$21+Assumptions!$B$22/$C$125),Assumptions!$B$37) -> 1 | S125: =Assumptions!$B$38/$R$125 -> 1 | T125: =Assumptions!$B$39*$S$125 -> 5000000 | U125: =IF($C$125<Assumptions!$B$42,Assumptions!$B$42*(Assumptions!$B$21+Assumptions!$B$22/Assumptions!$B$42)/(Assumptions!$B$21+Assumptions!$B$22/$C$125),Assumptions!$B$42) -> 3 | V125: =Assumptions!$B$43/$U$125 -> 1 | W125: =Assumptions!$B$44*$V$125 -> 5000000 | X125: =IF($C$125<Assumptions!$B$47,Assumptions!$B$47*(Assumptions!$B$21+Assumptions!$B$22/Assumptions!$B$47)/(Assumptions!$B$21+Assumptions!$B$22/$C$125),Assumptions!$B$47) -> 10 | Y125: =Assumptions!$B$48/$X$125 -> 1 | Z125: =Assumptions!$B$49*$Y$125 -> 3000000 | AA125: =IF($C$125<Assumptions!$B$52,Assumptions!$B$52*(Assumptions!$B$21+Assumptions!$B$22/Assumptions!$B$52)/(Assumptions!$B$21+Assumptions!$B$22/$C$125),Assumptions!$B$52) -> 25 | AB125: =Assumptions!$B$53/$AA$125 -> 1 | AC125: =Assumptions!$B$54*$AB$125 -> 2400000 | AD125: =IF($C$125<Assumptions!$B$57,Assumptions!$B$57*(Assumptions!$B$21+Assumptions!$B$22/Assumptions!$B$57)/(Assumptions!$B$21+Assumptions!$B$22/$C$125),Assumptions!$B$57) -> 57.681736 | AE125: =Assumptions!$B$58/$AD$125 -> 1.0401906 | AF125: =Assumptions!$B$59*$AE$125 -> 1733651.4 | AG125: =IF($C$125<Assumptions!$B$62,Assumptions!$B$62*(Assumptions!$B$21+Assumptions!$B$22/Assumptions!$B$62)/(Assumptions!$B$21+Assumptions!$B$22/$C$125),Assumptions!$B$62) -> 48.912626 | AH125: =Assumptions!$B$63/$AG$125 -> 1.0050229 | AI125: =Assumptions!$B$64*$AH$125 -> 6133320.3
...

Sheet Waterfall
A1: =Assumptions!$I$133 -> Waterfall
B2: =Assumptions!$B$24 -> 700000000 | C2: =Assumptions!$B$25 -> 1200000000 | D2: =Assumptions!$B$26 -> 2000000000 | E2: =Assumptions!$B$27 -> 4000000000 | F2: =Assumptions!$B$28 -> 8000000000
A3: =Assumptions!$I$134 -> F election | B3: =IF(INDEX($U$131:$U$258,1+$AH$130+IF(MOD(QUOTIENT($AH$130,Assumptions!$B$77),2)=1,0,Assumptions!$B$77))>=INDEX($U$131:$U$258,1+$AH$130-IF(MOD(QUOTIENT($AH$130,Assumptions!$B$77),2)=1,Assumptions!$B$77,0)),"preference","convert") -> preference | C3: =IF(INDEX($U$263:$U$390,1+$AH$262+IF(MOD(QUOTIENT($AH$262,Assumptions!$B$77),2)=1,0,Assumptions!$B$77))>=INDEX($U$263:$U$390,1+$AH$262-IF(MOD(QUOTIENT($AH$262,Assumptions!$B$77),2)=1,Assumptions!$B$77,0)),"preference","convert") -> preference | D3: =IF(INDEX($U$395:$U$522,1+$AH$394+IF(MOD(QUOTIENT($AH$394,Assumptions!$B$77),2)=1,0,Assumptions!$B$77))>=INDEX($U$395:$U$522,1+$AH$394-IF(MOD(QUOTIENT($AH$394,Assumptions!$B$77),2)=1,Assumptions!$B$77,0)),"preference","convert") -> convert | E3: =IF(INDEX($U$527:$U$654,1+$AH$526+IF(MOD(QUOTIENT($AH$526,Assumptions!$B$77),2)=1,0,Assumptions!$B$77))>=INDEX($U$527:$U$654,1+$AH$526-IF(MOD(QUOTIENT($AH$526,Assumptions!$B$77),2)=1,Assumptions!$B$77,0)),"preference","convert") -> convert | F3: =IF(INDEX($U$659:$U$786,1+$AH$658+IF(MOD(QUOTIENT($AH$658,Assumptions!$B$77),2)=1,0,Assumptions!$B$77))>=INDEX($U$659:$U$786,1+$AH$658-IF(MOD(QUOTIENT($AH$658,Assumptions!$B$77),2)=1,Assumptions!$B$77,0)),"preference","convert") -> convert
A4: =Assumptions!$I$135 -> E election | B4: =IF(INDEX($V$131:$V$258,1+$AH$130+IF(MOD(QUOTIENT($AH$130,Assumptions!$B$78),2)=1,0,Assumptions!$B$78))>=INDEX($V$131:$V$258,1+$AH$130-IF(MOD(QUOTIENT($AH$130,Assumptions!$B$78),2)=1,Assumptions!$B$78,0)),"preference","convert") -> preference | C4: =IF(INDEX($V$263:$V$390,1+$AH$262+IF(MOD(QUOTIENT($AH$262,Assumptions!$B$78),2)=1,0,Assumptions!$B$78))>=INDEX($V$263:$V$390,1+$AH$262-IF(MOD(QUOTIENT($AH$262,Assumptions!$B$78),2)=1,Assumptions!$B$78,0)),"preference","convert") -> preference | D4: =IF(INDEX($V$395:$V$522,1+$AH$394+IF(MOD(QUOTIENT($AH$394,Assumptions!$B$78),2)=1,0,Assumptions!$B$78))>=INDEX($V$395:$V$522,1+$AH$394-IF(MOD(QUOTIENT($AH$394,Assumptions!$B$78),2)=1,Assumptions!$B$78,0)),"preference","convert") -> convert | E4: =IF(INDEX($V$527:$V$654,1+$AH$526+IF(MOD(QUOTIENT($AH$526,Assumptions!$B$78),2)=1,0,Assumptions!$B$78))>=INDEX($V$527:$V$654,1+$AH$526-IF(MOD(QUOTIENT($AH$526,Assumptions!$B$78),2)=1,Assumptions!$B$78,0)),"preference","convert") -> convert | F4: =IF(INDEX($V$659:$V$786,1+$AH$658+IF(MOD(QUOTIENT($AH$658,Assumptions!$B$78),2)=1,0,Assumptions!$B$78))>=INDEX($V$659:$V$786,1+$AH$658-IF(MOD(QUOTIENT($AH$658,Assumptions!$B$78),2)=1,Assumptions!$B$78,0)),"preference","convert") -> convert
A5: =Assumptions!$I$136 -> D election | B5: =IF(INDEX($W$131:$W$258,1+$AH$130+IF(MOD(QUOTIENT($AH$130,Assumptions!$B$79),2)=1,0,Assumptions!$B$79))>=INDEX($W$131:$W$258,1+$AH$130-IF(MOD(QUOTIENT($AH$130,Assumptions!$B$79),2)=1,Assumptions!$B$79,0)),"preference","convert") -> preference | C5: =IF(INDEX($W$263:$W$390,1+$AH$262+IF(MOD(QUOTIENT($AH$262,Assumptions!$B$79),2)=1,0,Assumptions!$B$79))>=INDEX($W$263:$W$390,1+$AH$262-IF(MOD(QUOTIENT($AH$262,Assumptions!$B$79),2)=1,Assumptions!$B$79,0)),"preference","convert") -> preference | D5: =IF(INDEX($W$395:$W$522,1+$AH$394+IF(MOD(QUOTIENT($AH$394,Assumptions!$B$79),2)=1,0,Assumptions!$B$79))>=INDEX($W$395:$W$522,1+$AH$394-IF(MOD(QUOTIENT($AH$394,Assumptions!$B$79),2)=1,Assumptions!$B$79,0)),"preference","convert") -> preference | E5: =IF(INDEX($W$527:$W$654,1+$AH$526+IF(MOD(QUOTIENT($AH$526,Assumptions!$B$79),2)=1,0,Assumptions!$B$79))>=INDEX($W$527:$W$654,1+$AH$526-IF(MOD(QUOTIENT($AH$526,Assumptions!$B$79),2)=1,Assumptions!$B$79,0)),"preference","convert") -> convert | F5: =IF(INDEX($W$659:$W$786,1+$AH$658+IF(MOD(QUOTIENT($AH$658,Assumptions!$B$79),2)=1,0,Assumptions!$B$79))>=INDEX($W$659:$W$786,1+$AH$658-IF(MOD(QUOTIENT($AH$658,Assumptions!$B$79),2)=1,Assumptions!$B$79,0)),"preference","convert") -> convert
A6: =Assumptions!$I$137 -> C election | B6: =IF(INDEX($X$131:$X$258,1+$AH$130+IF(MOD(QUOTIENT($AH$130,Assumptions!$B$80),2)=1,0,Assumptions!$B$80))>=INDEX($X$131:$X$258,1+$AH$130-IF(MOD(QUOTIENT($AH$130,Assumptions!$B$80),2)=1,Assumptions!$B$80,0)),"preference","convert") -> preference | C6: =IF(INDEX($X$263:$X$390,1+$AH$262+IF(MOD(QUOTIENT($AH$262,Assumptions!$B$80),2)=1,0,Assumptions!$B$80))>=INDEX($X$263:$X$390,1+$AH$262-IF(MOD(QUOTIENT($AH$262,Assumptions!$B$80),2)=1,Assumptions!$B$80,0)),"preference","convert") -> convert | D6: =IF(INDEX($X$395:$X$522,1+$AH$394+IF(MOD(QUOTIENT($AH$394,Assumptions!$B$80),2)=1,0,Assumptions!$B$80))>=INDEX($X$395:$X$522,1+$AH$394-IF(MOD(QUOTIENT($AH$394,Assumptions!$B$80),2)=1,Assumptions!$B$80,0)),"preference","convert") -> convert | E6: =IF(INDEX($X$527:$X$654,1+$AH$526+IF(MOD(QUOTIENT($AH$526,Assumptions!$B$80),2)=1,0,Assumptions!$B$80))>=INDEX($X$527:$X$654,1+$AH$526-IF(MOD(QUOTIENT($AH$526,Assumptions!$B$80),2)=1,Assumptions!$B$80,0)),"preference","convert") -> convert | F6: =IF(INDEX($X$659:$X$786,1+$AH$658+IF(MOD(QUOTIENT($AH$658,Assumptions!$B$80),2)=1,0,Assumptions!$B$80))>=INDEX($X$659:$X$786,1+$AH$658-IF(MOD(QUOTIENT($AH$658,Assumptions!$B$80),2)=1,Assumptions!$B$80,0)),"preference","convert") -> convert
A7: =Assumptions!$I$138 -> B election | B7: =IF(INDEX($Y$131:$Y$258,1+$AH$130+IF(MOD(QUOTIENT($AH$130,Assumptions!$B$81),2)=1,0,Assumptions!$B$81))>=INDEX($Y$131:$Y$258,1+$AH$130-IF(MOD(QUOTIENT($AH$130,Assumptions!$B$81),2)=1,Assumptions!$B$81,0)),"preference","convert") -> preference | C7: =IF(INDEX($Y$263:$Y$390,1+$AH$262+IF(MOD(QUOTIENT($AH$262,Assumptions!$B$81),2)=1,0,Assumptions!$B$81))>=INDEX($Y$263:$Y$390,1+$AH$262-IF(MOD(QUOTIENT($AH$262,Assumptions!$B$81),2)=1,Assumptions!$B$81,0)),"preference","convert") -> convert | D7: =IF(INDEX($Y$395:$Y$522,1+$AH$394+IF(MOD(QUOTIENT($AH$394,Assumptions!$B$81),2)=1,0,Assumptions!$B$81))>=INDEX($Y$395:$Y$522,1+$AH$394-IF(MOD(QUOTIENT($AH$394,Assumptions!$B$81),2)=1,Assumptions!$B$81,0)),"preference","convert") -> convert | E7: =IF(INDEX($Y$527:$Y$654,1+$AH$526+IF(MOD(QUOTIENT($AH$526,Assumptions!$B$81),2)=1,0,Assumptions!$B$81))>=INDEX($Y$527:$Y$654,1+$AH$526-IF(MOD(QUOTIENT($AH$526,Assumptions!$B$81),2)=1,Assumptions!$B$81,0)),"preference","convert") -> convert | F7: =IF(INDEX($Y$659:$Y$786,1+$AH$658+IF(MOD(QUOTIENT($AH$658,Assumptions!$B$81),2)=1,0,Assumptions!$B$81))>=INDEX($Y$659:$Y$786,1+$AH$658-IF(MOD(QUOTIENT($AH$658,Assumptions!$B$81),2)=1,Assumptions!$B$81,0)),"preference","convert") -> convert
A8: =Assumptions!$I$139 -> A election | B8: =IF(INDEX($Z$131:$Z$258,1+$AH$130+IF(MOD(QUOTIENT($AH$130,Assumptions!$B$82),2)=1,0,Assumptions!$B$82))>=INDEX($Z$131:$Z$258,1+$AH$130-IF(MOD(QUOTIENT($AH$130,Assumptions!$B$82),2)=1,Assumptions!$B$82,0)),"preference","convert") -> convert | C8: =IF(INDEX($Z$263:$Z$390,1+$AH$262+IF(MOD(QUOTIENT($AH$262,Assumptions!$B$82),2)=1,0,Assumptions!$B$82))>=INDEX($Z$263:$Z$390,1+$AH$262-IF(MOD(QUOTIENT($AH$262,Assumptions!$B$82),2)=1,Assumptions!$B$82,0)),"preference","convert") -> convert | D8: =IF(INDEX($Z$395:$Z$522,1+$AH$394+IF(MOD(QUOTIENT($AH$394,Assumptions!$B$82),2)=1,0,Assumptions!$B$82))>=INDEX($Z$395:$Z$522,1+$AH$394-IF(MOD(QUOTIENT($AH$394,Assumptions!$B$82),2)=1,Assumptions!$B$82,0)),"preference","convert") -> convert | E8: =IF(INDEX($Z$527:$Z$654,1+$AH$526+IF(MOD(QUOTIENT($AH$526,Assumptions!$B$82),2)=1,0,Assumptions!$B$82))>=INDEX($Z$527:$Z$654,1+$AH$526-IF(MOD(QUOTIENT($AH$526,Assumptions!$B$82),2)=1,Assumptions!$B$82,0)),"preference","convert") -> convert | F8: =IF(INDEX($Z$659:$Z$786,1+$AH$658+IF(MOD(QUOTIENT($AH$658,Assumptions!$B$82),2)=1,0,Assumptions!$B$82))>=INDEX($Z$659:$Z$786,1+$AH$658-IF(MOD(QUOTIENT($AH$658,Assumptions!$B$82),2)=1,Assumptions!$B$82,0)),"preference","convert") -> convert
A9: =Assumptions!$I$140 -> Seed election | B9: =IF(INDEX($AA$131:$AA$258,1+$AH$130+IF(MOD(QUOTIENT($AH$130,Assumptions!$B$83),2)=1,0,Assumptions!$B$83))>=INDEX($AA$131:$AA$258,1+$AH$130-IF(MOD(QUOTIENT($AH$130,Assumptions!$B$83),2)=1,Assumptions!$B$83,0)),"preference","convert") -> convert | C9: =IF(INDEX($AA$263:$AA$390,1+$AH$262+IF(MOD(QUOTIENT($AH$262,Assumptions!$B$83),2)=1,0,Assumptions!$B$83))>=INDEX($AA$263:$AA$390,1+$AH$262-IF(MOD(QUOTIENT($AH$262,Assumptions!$B$83),2)=1,Assumptions!$B$83,0)),"preference","convert") -> convert | D9: =IF(INDEX($AA$395:$AA$522,1+$AH$394+IF(MOD(QUOTIENT($AH$394,Assumptions!$B$83),2)=1,0,Assumptions!$B$83))>=INDEX($AA$395:$AA$522,1+$AH$394-IF(MOD(QUOTIENT($AH$394,Assumptions!$B$83),2)=1,Assumptions!$B$83,0)),"preference","convert") -> convert | E9: =IF(INDEX($AA$527:$AA$654,1+$AH$526+IF(MOD(QUOTIENT($AH$526,Assumptions!$B$83),2)=1,0,Assumptions!$B$83))>=INDEX($AA$527:$AA$654,1+$AH$526-IF(MOD(QUOTIENT($AH$526,Assumptions!$B$83),2)=1,Assumptions!$B$83,0)),"preference","convert") -> convert | F9: =IF(INDEX($AA$659:$AA$786,1+$AH$658+IF(MOD(QUOTIENT($AH$658,Assumptions!$B$83),2)=1,0,Assumptions!$B$83))>=INDEX($AA$659:$AA$786,1+$AH$658-IF(MOD(QUOTIENT($AH$658,Assumptions!$B$83),2)=1,Assumptions!$B$83,0)),"preference","convert") -> convert
A12: =Assumptions!$I$141 -> F | B12: =INDEX($U$131:$U$258,1+$AH$130) -> 30000000 | C12: =INDEX($U$263:$U$390,1+$AH$262) -> 30000000 | D12: =INDEX($U$395:$U$522,1+$AH$394) -> 44466536 | E12: =INDEX($U$527:$U$654,1+$AH$526) -> 89024619 | F12: =INDEX($U$659:$U$786,1+$AH$658) -> 1.7799363e+08
A13: =Assumptions!$I$142 -> E | B13: =INDEX($V$131:$V$258,1+$AH$130) -> 300000000 | C13: =INDEX($V$263:$V$390,1+$AH$262) -> 300000000 | D13: =INDEX($V$395:$V$522,1+$AH$394) -> 3.4207755e+08 | E13: =INDEX($V$527:$V$654,1+$AH$526) -> 6.8485936e+08 | F13: =INDEX($V$659:$V$786,1+$AH$658) -> 1.369291e+09
A14: =Assumptions!$I$143 -> D | B14: =INDEX($W$131:$W$258,1+$AH$130) -> 100000000 | C14: =INDEX($W$263:$W$390,1+$AH$262) -> 100000000 | D14: =INDEX($W$395:$W$522,1+$AH$394) -> 100000000 | E14: =INDEX($W$527:$W$654,1+$AH$526) -> 1.9358314e+08 | F14: =INDEX($W$659:$W$786,1+$AH$658) -> 3.8704536e+08
A15: =Assumptions!$I$144 -> C | B15: =INDEX($X$131:$X$258,1+$AH$130) -> 60000000 | C15: =INDEX($X$263:$X$390,1+$AH$262) -> 68210634 | D15: =INDEX($X$395:$X$522,1+$AH$394) -> 1.3385672e+08 | E15: =INDEX($X$527:$X$654,1+$AH$526) -> 2.6798902e+08 | F15: =INDEX($X$659:$X$786,1+$AH$658) -> 5.3581065e+08
A16: =Assumptions!$I$145 -> B | B16: =INDEX($Y$131:$Y$258,1+$AH$130) -> 30000000 | C16: =INDEX($Y$263:$Y$390,1+$AH$262) -> 85263292 | D16: =INDEX($Y$395:$Y$522,1+$AH$394) -> 1.673209e+08 | E16: =INDEX($Y$527:$Y$654,1+$AH$526) -> 3.3498627e+08 | F16: =INDEX($Y$659:$Y$786,1+$AH$658) -> 6.6976331e+08
A17: =Assumptions!$I$146 -> A | B17: =INDEX($Z$131:$Z$258,1+$AH$130) -> 41895249 | C17: =INDEX($Z$263:$Z$390,1+$AH$262) -> 1.4210549e+08 | D17: =INDEX($Z$395:$Z$522,1+$AH$394) -> 2.7886816e+08 | E17: =INDEX($Z$527:$Z$654,1+$AH$526) -> 5.5831045e+08 | F17: =INDEX($Z$659:$Z$786,1+$AH$658) -> 1.1162722e+09
A18: =Assumptions!$I$55 -> Seed | B18: =INDEX($AA$131:$AA$258,1+$AH$130) -> 41895249 | C18: =INDEX($AA$263:$AA$390,1+$AH$262) -> 1.4210549e+08 | D18: =INDEX($AA$395:$AA$522,1+$AH$394) -> 2.7886816e+08 | E18: =INDEX($AA$527:$AA$654,1+$AH$526) -> 5.5831045e+08 | F18: =INDEX($AA$659:$AA$786,1+$AH$658) -> 1.1162722e+09
A19: =Assumptions!$I$147 -> Notes | B19: =INDEX($AB$131:$AB$258,1+$AH$130) -> 2350430.9 | C19: =INDEX($AB$263:$AB$390,1+$AH$262) -> 7972482.4 | D19: =INDEX($AB$395:$AB$522,1+$AH$394) -> 15645219 | E19: =INDEX($AB$527:$AB$654,1+$AH$526) -> 31322649 | F19: =INDEX($AB$659:$AB$786,1+$AH$658) -> 62625733
A20: =Assumptions!$I$148 -> Common + RSAs | B20: =INDEX($AC$131:$AC$258,1+$AH$130) -> 75411448 | C20: =INDEX($AC$263:$AC$390,1+$AH$262) -> 2.5578988e+08 | D20: =INDEX($AC$395:$AC$522,1+$AH$394) -> 5.0196269e+08 | E20: =INDEX($AC$527:$AC$654,1+$AH$526) -> 1.0049588e+09 | F20: =INDEX($AC$659:$AC$786,1+$AH$658) -> 2.0092899e+09
A21: =Assumptions!$I$96 -> Issued options | B21: =INDEX($AD$131:$AD$258,1+$AH$130) -> 18447624 | C21: =INDEX($AD$263:$AD$390,1+$AH$262) -> 68552743 | D21: =INDEX($AD$395:$AD$522,1+$AH$394) -> 1.3693408e+08 | E21: =INDEX($AD$527:$AD$654,1+$AH$526) -> 2.7665523e+08 | F21: =INDEX($AD$659:$AD$786,1+$AH$658) -> 5.5563609e+08
A23: =Assumptions!$I$131 -> Total distributed | B23: =SUM(B12:B21) -> 700000000 | C23: =SUM(C12:C21) -> 1200000000 | D23: =SUM(D12:D21) -> 2000000000 | E23: =SUM(E12:E21) -> 4000000000 | F23: =SUM(F12:F21) -> 8000000000
A24: =Assumptions!$I$149 -> Reconciliation to exit | B24: =B23-B2 -> 0 | C24: =C23-C2 -> 0 | D24: =D23-D2 -> 0 | E24: =E23-E2 -> 0 | F24: =F23-F2 -> 0
A40: =Assumptions!$I$2 -> Iteration | B40: =Assumptions!$I$3 -> Top-up input | C40: =Assumptions!$I$4 -> F PPS | D40: =Assumptions!$I$5 -> F primary shares | E40: =Assumptions!$I$6 -> Prior as-converted | F40: =Assumptions!$I$7 -> Note A cap PPS | G40: =Assumptions!$I$8 -> Note A discount PPS | H40: =Assumptions!$I$9 -> Note A conversion PPS | I40: =Assumptions!$I$10 -> Note A branch | J40: =Assumptions!$I$11 -> Note A shares | K40: =Assumptions!$I$12 -> Note B cap PPS | L40: =Assumptions!$I$13 -> Note B discount PPS | M40: =Assumptions!$I$14 -> Note B conversion PPS | N40: =Assumptions!$I$15 -> Note B branch | O40: =Assumptions!$I$16 -> Note B shares | P40: =Assumptions!$I$17 -> ESOP top-up output | Q40: =Assumptions!$I$18 -> Post-F FD | R40: =Assumptions!$I$19 -> Seed NCP | S40: =Assumptions!$I$20 -> Seed ratio | T40: =Assumptions!$I$21 -> Seed as-converted | U40: =Assumptions!$I$22 -> Series A NCP | V40: =Assumptions!$I$23 -> Series A ratio | W40: =Assumptions!$I$24 -> Series A as-converted | X40: =Assumptions!$I$25 -> Series B NCP | Y40: =Assumptions!$I$26 -> Series B ratio | Z40: =Assumptions!$I$27 -> Series B as-converted | AA40: =Assumptions!$I$28 -> Series C NCP | AB40: =Assumptions!$I$29 -> Series C ratio | AC40: =Assumptions!$I$30 -> Series C as-converted | AD40: =Assumptions!$I$31 -> Series D NCP | AE40: =Assumptions!$I$32 -> Series D ratio | AF40: =Assumptions!$I$33 -> Series D as-converted | AG40: =Assumptions!$I$34 -> Series E NCP | AH40: =Assumptions!$I$35 -> Series E ratio | AI40: =Assumptions!$I$36 -> Series E as-converted
A41: =ROW()-ROW($A$41)+Assumptions!$B$4 -> 0 | B41: =Assumptions!$B$4 -> 0 | C41: =Assumptions!$B$6/(Assumptions!$B$16+$B$41) -> 38.232604 | D41: =Assumptions!$B$7/$C$41 -> 784670.59 | E41: =$T$41+$W$41+$Z$41+$AC$41+$AF$41+$AI$41 -> 23264323 | F41: =Assumptions!$B$70/(Assumptions!$B$20+Assumptions!$B$17+$B$41+$E$41+Assumptions!$B$4) -> 27.278438 | G41: =$C$41*(1-Assumptions!$B$71) -> 30.586083 | H41: =MIN($F$41,$G$41) -> 27.278438 | I41: =IF($F$41<=$G$41,"cap","discount") -> cap | J41: =Assumptions!$B$69/$H$41 -> 183294.95 | K41: =Assumptions!$B$74/(Assumptions!$B$20+Assumptions!$B$17+$B$41+$E$41+$J$41) -> 43.42836 | L41: =$C$41*(1-Assumptions!$B$75) -> 32.497713 | M41: =MIN($K$41,$L$41) -> 32.497713 | N41: =IF($K$41<=$L$41,"cap","discount") -> discount | O41: =Assumptions!$B$73/$M$41 -> 92314.187 | P41: =MAX(Assumptions!$B$4,(Assumptions!$B$10*(Assumptions!$B$20+$E$41+Assumptions!$B$17+$J$41+$O$41+$D$41)-Assumptions!$B$17)/(1-Assumptions!$B$10)) -> 584871.32 | Q41: =Assumptions!$B$20+$E$41+Assumptions!$B$17+$P$41+$J$41+$O$41+$D$41 -> 38304141 | R41: =IF($C$41<Assumptions!$B$37,Assumptions!$B$37*(Assumptions!$B$21+Assumptions!$B$22/Assumptions!$B$37)/(Assumptions!$B$21+Assumptions!$B$22/$C$41),Assumptions!$B$37) -> 1 | S41: =Assumptions!$B$38/$R$41 -> 1 | T41: =Assumptions!$B$39*$S$41 -> 5000000 | U41: =IF($C$41<Assumptions!$B$42,Assumptions!$B$42*(Assumptions!$B$21+Assumptions!$B$22/Assumptions!$B$42)/(Assumptions!$B$21+Assumptions!$B$22/$C$41),Assumptions!$B$42) -> 3 | V41: =Assumptions!$B$43/$U$41 -> 1 | W41: =Assumptions!$B$44*$V$41 -> 5000000 | X41: =IF($C$41<Assumptions!$B$47,Assumptions!$B$47*(Assumptions!$B$21+Assumptions!$B$22/Assumptions!$B$47)/(Assumptions!$B$21+Assumptions!$B$22/$C$41),Assumptions!$B$47) -> 10 | Y41: =Assumptions!$B$48/$X$41 -> 1 | Z41: =Assumptions!$B$49*$Y$41 -> 3000000 | AA41: =IF($C$41<Assumptions!$B$52,Assumptions!$B$52*(Assumptions!$B$21+Assumptions!$B$22/Assumptions!$B$52)/(Assumptions!$B$21+Assumptions!$B$22/$C$41),Assumptions!$B$52) -> 25 | AB41: =Assumptions!$B$53/$AA$41 -> 1 | AC41: =Assumptions!$B$54*$AB$41 -> 2400000 | AD41: =IF($C$41<Assumptions!$B$57,Assumptions!$B$57*(Assumptions!$B$21+Assumptions!$B$22/Assumptions!$B$57)/(Assumptions!$B$21+Assumptions!$B$22/$C$41),Assumptions!$B$57) -> 57.701164 | AE41: =Assumptions!$B$58/$AD$41 -> 1.0398404 | AF41: =Assumptions!$B$59*$AE$41 -> 1733067.7 | AG41: =IF($C$41<Assumptions!$B$62,Assumptions!$B$62*(Assumptions!$B$21+Assumptions!$B$22/Assumptions!$B$62)/(Assumptions!$B$21+Assumptions!$B$22/$C$41),Assumptions!$B$62) -> 48.9291 | AH41: =Assumptions!$B$63/$AG$41 -> 1.0046845 | AI41: =Assumptions!$B$64*$AH$41 -> 6131255.2
A42: =ROW()-ROW($A$41)+Assumptions!$B$4 -> 1 | B42: =$P$41 -> 584871.32 | C42: =Assumptions!$B$6/(Assumptions!$B$16+$B$42) -> 37.631543 | D42: =Assumptions!$B$7/$C$42 -> 797203.55 | E42: =$T$42+$W$42+$Z$42+$AC$42+$AF$42+$AI$42 -> 23266958 | F42: =Assumptions!$B$70/(Assumptions!$B$20+Assumptions!$B$17+$B$42+$E$42+$O$41) -> 26.781785 | G42: =$C$42*(1-Assumptions!$B$71) -> 30.105235 | H42: =MIN($F$42,$G$42) -> 26.781785 | I42: =IF($F$42<=$G$42,"cap","discount") -> cap | J42: =Assumptions!$B$69/$H$42 -> 186694.05 | K42: =Assumptions!$B$74/(Assumptions!$B$20+Assumptions!$B$17+$B$42+$E$42+$J$42) -> 42.742817 | L42: =$C$42*(1-Assumptions!$B$75) -> 31.986812 | M42: =MIN($K$42,$L$42) -> 31.986812 | N42: =IF($K$42<=$L$42,"cap","discount") -> discount | O42: =Assumptions!$B$73/$M$42 -> 93788.653 | P42: =MAX(Assumptions!$B$4,(Assumptions!$B$10*(Assumptions!$B$20+$E$42+Assumptions!$B$17+$J$42+$O$42+$D$42)-Assumptions!$B$17)/(1-Assumptions!$B$10)) -> 587866.06 | Q42: =Assumptions!$B$20+$E$42+Assumptions!$B$17+$P$42+$J$42+$O$42+$D$42 -> 38327177 | R42: =IF($C$42<Assumptions!$B$37,Assumptions!$B$37*(Assumptions!$B$21+Assumptions!$B$22/Assumptions!$B$37)/(Assumptions!$B$21+Assumptions!$B$22/$C$42),Assumptions!$B$37) -> 1 | S42: =Assumptions!$B$38/$R$42 -> 1 | T42: =Assumptions!$B$39*$S$42 -> 5000000 | U42: =IF($C$42<Assumptions!$B$42,Assumptions!$B$42*(Assumptions!$B$21+Assumptions!$B$22/Assumptions!$B$42)/(Assumptions!$B$21+Assumptions!$B$22/$C$42),Assumptions!$B$42) -> 3 | V42: =Assumptions!$B$43/$U$42 -> 1 | W42: =Assumptions!$B$44*$V$42 -> 5000000 | X42: =IF($C$42<Assumptions!$B$47,Assumptions!$B$47*(Assumptions!$B$21+Assumptions!$B$22/Assumptions!$B$47)/(Assumptions!$B$21+Assumptions!$B$22/$C$42),Assumptions!$B$47) -> 10 | Y42: =Assumptions!$B$48/$X$42 -> 1 | Z42: =Assumptions!$B$49*$Y$42 -> 3000000 | AA42: =IF($C$42<Assumptions!$B$52,Assumptions!$B$52*(Assumptions!$B$21+Assumptions!$B$22/Assumptions!$B$52)/(Assumptions!$B$21+Assumptions!$B$22/$C$42),Assumptions!$B$52) -> 25 | AB42: =Assumptions!$B$53/$AA$42 -> 1 | AC42: =Assumptions!$B$54*$AB$42 -> 2400000 | AD42: =IF($C$42<Assumptions!$B$57,Assumptions!$B$57*(Assumptions!$B$21+Assumptions!$B$22/Assumptions!$B$57)/(Assumptions!$B$21+Assumptions!$B$22/$C$42),Assumptions!$B$57) -> 57.681835 | AE42: =Assumptions!$B$58/$AD$42 -> 1.0401888 | AF42: =Assumptions!$B$59*$AE$42 -> 1733648.4 | AG42: =IF($C$42<Assumptions!$B$62,Assumptions!$B$62*(Assumptions!$B$21+Assumptions!$B$22/Assumptions!$B$62)/(Assumptions!$B$21+Assumptions!$B$22/$C$42),Assumptions!$B$62) -> 48.912711 | AH42: =Assumptions!$B$63/$AG$42 -> 1.0050212 | AI42: =Assumptions!$B$64*$AH$42 -> 6133309.7
A43: =ROW()-ROW($A$41)+Assumptions!$B$4 -> 2 | B43: =$P$42 -> 587866.06 | C43: =Assumptions!$B$6/(Assumptions!$B$16+$B$43) -> 37.628514 | D43: =Assumptions!$B$7/$C$43 -> 797267.72 | E43: =$T$43+$W$43+$Z$43+$AC$43+$AF$43+$AI$43 -> 23266972 | F43: =Assumptions!$B$70/(Assumptions!$B$20+Assumptions!$B$17+$B$43+$E$43+$O$42) -> 26.77857 | G43: =$C$43*(1-Assumptions!$B$71) -> 30.102812 | H43: =MIN($F$43,$G$43) -> 26.77857 | I43: =IF($F$43<=$G$43,"cap","discount") -> cap | J43: =Assumptions!$B$69/$H$43 -> 186716.47 | K43: =Assumptions!$B$74/(Assumptions!$B$20+Assumptions!$B$17+$B$43+$E$43+$J$43) -> 42.739357 | L43: =$C$43*(1-Assumptions!$B$75) -> 31.984237 | M43: =MIN($K$43,$L$43) -> 31.984237 | N43: =IF($K$43<=$L$43,"cap","discount") -> discount | O43: =Assumptions!$B$73/$M$43 -> 93796.203 | P43: =MAX(Assumptions!$B$4,(Assumptions!$B$10*(Assumptions!$B$20+$E$43+Assumptions!$B$17+$J$43+$O$43+$D$43)-Assumptions!$B$17)/(1-Assumptions!$B$10)) -> 587882.14 | Q43: =Assumptions!$B$20+$E$43+Assumptions!$B$17+$P$43+$J$43+$O$43+$D$43 -> 38327301 | R43: =IF($C$43<Assumptions!$B$37,Assumptions!$B$37*(Assumptions!$B$21+Assumptions!$B$22/Assumptions!$B$37)/(Assumptions!$B$21+Assumptions!$B$22/$C$43),Assumptions!$B$37) -> 1 | S43: =Assumptions!$B$38/$R$43 -> 1 | T43: =Assumptions!$B$39*$S$43 -> 5000000 | U43: =IF($C$43<Assumptions!$B$42,Assumptions!$B$42*(Assumptions!$B$21+Assumptions!$B$22/Assumptions!$B$42)/(Assumptions!$B$21+Assumptions!$B$22/$C$43),Assumptions!$B$42) -> 3 | V43: =Assumptions!$B$43/$U$43 -> 1 | W43: =Assumptions!$B$44*$V$43 -> 5000000 | X43: =IF($C$43<Assumptions!$B$47,Assumptions!$B$47*(Assumptions!$B$21+Assumptions!$B$22/Assumptions!$B$47)/(Assumptions!$B$21+Assumptions!$B$22/$C$43),Assumptions!$B$47) -> 10 | Y43: =Assumptions!$B$48/$X$43 -> 1 | Z43: =Assumptions!$B$49*$Y$43 -> 3000000 | AA43: =IF($C$43<Assumptions!$B$52,Assumptions!$B$52*(Assumptions!$B$21+Assumptions!$B$22/Assumptions!$B$52)/(Assumptions!$B$21+Assumptions!$B$22/$C$43),Assumptions!$B$52) -> 25 | AB43: =Assumptions!$B$53/$AA$43 -> 1 | AC43: =Assumptions!$B$54*$AB$43 -> 2400000 | AD43: =IF($C$43<Assumptions!$B$57,Assumptions!$B$57*(Assumptions!$B$21+Assumptions!$B$22/Assumptions!$B$57)/(Assumptions!$B$21+Assumptions!$B$22/$C$43),Assumptions!$B$57) -> 57.681736 | AE43: =Assumptions!$B$58/$AD$43 -> 1.0401906 | AF43: =Assumptions!$B$59*$AE$43 -> 1733651.3 | AG43: =IF($C$43<Assumptions!$B$62,Assumptions!$B$62*(Assumptions!$B$21+Assumptions!$B$22/Assumptions!$B$62)/(Assumptions!$B$21+Assumptions!$B$22/$C$43),Assumptions!$B$62) -> 48.912627 | AH43: =Assumptions!$B$63/$AG$43 -> 1.0050229 | AI43: =Assumptions!$B$64*$AH$43 -> 6133320.2
A44: =ROW()-ROW($A$41)+Assumptions!$B$4 -> 3 | B44: =$P$43 -> 587882.14 | C44: =Assumptions!$B$6/(Assumptions!$B$16+$B$44) -> 37.628498 | D44: =Assumptions!$B$7/$C$44 -> 797268.07 | E44: =$T$44+$W$44+$Z$44+$AC$44+$AF$44+$AI$44 -> 23266972 | F44: =Assumptions!$B$70/(Assumptions!$B$20+Assumptions!$B$17+$B$44+$E$44+$O$43) -> 26.778553 | G44: =$C$44*(1-Assumptions!$B$71) -> 30.102799 | H44: =MIN($F$44,$G$44) -> 26.778553 | I44: =IF($F$44<=$G$44,"cap","discount") -> cap | J44: =Assumptions!$B$69/$H$44 -> 186716.58 | K44: =Assumptions!$B$74/(Assumptions!$B$20+Assumptions!$B$17+$B$44+$E$44+$J$44) -> 42.739338 | L44: =$C$44*(1-Assumptions!$B$75) -> 31.984223 | M44: =MIN($K$44,$L$44) -> 31.984223 | N44: =IF($K$44<=$L$44,"cap","discount") -> discount | O44: =Assumptions!$B$73/$M$44 -> 93796.243 | P44: =MAX(Assumptions!$B$4,(Assumptions!$B$10*(Assumptions!$B$20+$E$44+Assumptions!$B$17+$J$44+$O$44+$D$44)-Assumptions!$B$17)/(1-Assumptions!$B$10)) -> 587882.23 | Q44: =Assumptions!$B$20+$E$44+Assumptions!$B$17+$P$44+$J$44+$O$44+$D$44 -> 38327302 | R44: =IF($C$44<Assumptions!$B$37,Assumptions!$B$37*(Assumptions!$B$21+Assumptions!$B$22/Assumptions!$B$37)/(Assumptions!$B$21+Assumptions!$B$22/$C$44),Assumptions!$B$37) -> 1 | S44: =Assumptions!$B$38/$R$44 -> 1 | T44: =Assumptions!$B$39*$S$44 -> 5000000 | U44: =IF($C$44<Assumptions!$B$42,Assumptions!$B$42*(Assumptions!$B$21+Assumptions!$B$22/Assumptions!$B$42)/(Assumptions!$B$21+Assumptions!$B$22/$C$44),Assumptions!$B$42) -> 3 | V44: =Assumptions!$B$43/$U$44 -> 1 | W44: =Assumptions!$B$44*$V$44 -> 5000000 | X44: =IF($C$44<Assumptions!$B$47,Assumptions!$B$47*(Assumptions!$B$21+Assumptions!$B$22/Assumptions!$B$47)/(Assumptions!$B$21+Assumptions!$B$22/$C$44),Assumptions!$B$47) -> 10 | Y44: =Assumptions!$B$48/$X$44 -> 1 | Z44: =Assumptions!$B$49*$Y$44 -> 3000000 | AA44: =IF($C$44<Assumptions!$B$52,Assumptions!$B$52*(Assumptions!$B$21+Assumptions!$B$22/Assumptions!$B$52)/(Assumptions!$B$21+Assumptions!$B$22/$C$44),Assumptions!$B$52) -> 25 | AB44: =Assumptions!$B$53/$AA$44 -> 1 | AC44: =Assumptions!$B$54*$AB$44 -> 2400000 | AD44: =IF($C$44<Assumptions!$B$57,Assumptions!$B$57*(Assumptions!$B$21+Assumptions!$B$22/Assumptions!$B$57)/(Assumptions!$B$21+Assumptions!$B$22/$C$44),Assumptions!$B$57) -> 57.681736 | AE44: =Assumptions!$B$58/$AD$44 -> 1.0401906 | AF44: =Assumptions!$B$59*$AE$44 -> 1733651.4 | AG44: =IF($C$44<Assumptions!$B$62,Assumptions!$B$62*(Assumptions!$B$21+Assumptions!$B$22/Assumptions!$B$62)/(Assumptions!$B$21+Assumptions!$B$22/$C$44),Assumptions!$B$62) -> 48.912626 | AH44: =Assumptions!$B$63/$AG$44 -> 1.0050229 | AI44: =Assumptions!$B$64*$AH$44 -> 6133320.3
A45: =ROW()-ROW($A$41)+Assumptions!$B$4 -> 4 | B45: =$P$44 -> 587882.23 | C45: =Assumptions!$B$6/(Assumptions!$B$16+$B$45) -> 37.628498 | D45: =Assumptions!$B$7/$C$45 -> 797268.07 | E45: =$T$45+$W$45+$Z$45+$AC$45+$AF$45+$AI$45 -> 23266972 | F45: =Assumptions!$B$70/(Assumptions!$B$20+Assumptions!$B$17+$B$45+$E$45+$O$44) -> 26.778553 | G45: =$C$45*(1-Assumptions!$B$71) -> 30.102798 | H45: =MIN($F$45,$G$45) -> 26.778553 | I45: =IF($F$45<=$G$45,"cap","discount") -> cap | J45: =Assumptions!$B$69/$H$45 -> 186716.59 | K45: =Assumptions!$B$74/(Assumptions!$B$20+Assumptions!$B$17+$B$45+$E$45+$J$45) -> 42.739338 | L45: =$C$45*(1-Assumptions!$B$75) -> 31.984223 | M45: =MIN($K$45,$L$45) -> 31.984223 | N45: =IF($K$45<=$L$45,"cap","discount") -> discount | O45: =Assumptions!$B$73/$M$45 -> 93796.243 | P45: =MAX(Assumptions!$B$4,(Assumptions!$B$10*(Assumptions!$B$20+$E$45+Assumptions!$B$17+$J$45+$O$45+$D$45)-Assumptions!$B$17)/(1-Assumptions!$B$10)) -> 587882.23 | Q45: =Assumptions!$B$20+$E$45+Assumptions!$B$17+$P$45+$J$45+$O$45+$D$45 -> 38327302 | R45: =IF($C$45<Assumptions!$B$37,Assumptions!$B$37*(Assumptions!$B$21+Assumptions!$B$22/Assumptions!$B$37)/(Assumptions!$B$21+Assumptions!$B$22/$C$45),Assumptions!$B$37) -> 1 | S45: =Assumptions!$B$38/$R$45 -> 1 | T45: =Assumptions!$B$39*$S$45 -> 5000000 | U45: =IF($C$45<Assumptions!$B$42,Assumptions!$B$42*(Assumptions!$B$21+Assumptions!$B$22/Assumptions!$B$42)/(Assumptions!$B$21+Assumptions!$B$22/$C$45),Assumptions!$B$42) -> 3 | V45: =Assumptions!$B$43/$U$45 -> 1 | W45: =Assumptions!$B$44*$V$45 -> 5000000 | X45: =IF($C$45<Assumptions!$B$47,Assumptions!$B$47*(Assumptions!$B$21+Assumptions!$B$22/Assumptions!$B$47)/(Assumptions!$B$21+Assumptions!$B$22/$C$45),Assumptions!$B$47) -> 10 | Y45: =Assumptions!$B$48/$X$45 -> 1 | Z45: =Assumptions!$B$49*$Y$45 -> 3000000 | AA45: =IF($C$45<Assumptions!$B$52,Assumptions!$B$52*(Assumptions!$B$21+Assumptions!$B$22/Assumptions!$B$52)/(Assumptions!$B$21+Assumptions!$B$22/$C$45),Assumptions!$B$52) -> 25 | AB45: =Assumptions!$B$53/$AA$45 -> 1 | AC45: =Assumptions!$B$54*$AB$45 -> 2400000 | AD45: =IF($C$45<Assumptions!$B$57,Assumptions!$B$57*(Assumptions!$B$21+Assumptions!$B$22/Assumptions!$B$57)/(Assumptions!$B$21+Assumptions!$B$22/$C$45),Assumptions!$B$57) -> 57.681736 | AE45: =Assumptions!$B$58/$AD$45 -> 1.0401906 | AF45: =Assumptions!$B$59*$AE$45 -> 1733651.4 | AG45: =IF($C$45<Assumptions!$B$62,Assumptions!$B$62*(Assumptions!$B$21+Assumptions!$B$22/Assumptions!$B$62)/(Assumptions!$B$21+Assumptions!$B$22/$C$45),Assumptions!$B$62) -> 48.912626 | AH45: =Assumptions!$B$63/$AG$45 -> 1.0050229 | AI45: =Assumptions!$B$64*$AH$45 -> 6133320.3
A46: =ROW()-ROW($A$41)+Assumptions!$B$4 -> 5 | B46: =$P$45 -> 587882.23 | C46: =Assumptions!$B$6/(Assumptions!$B$16+$B$46) -> 37.628498 | D46: =Assumptions!$B$7/$C$46 -> 797268.07 | E46: =$T$46+$W$46+$Z$46+$AC$46+$AF$46+$AI$46 -> 23266972 | F46: =Assumptions!$B$70/(Assumptions!$B$20+Assumptions!$B$17+$B$46+$E$46+$O$45) -> 26.778553 | G46: =$C$46*(1-Assumptions!$B$71) -> 30.102798 | H46: =MIN($F$46,$G$46) -> 26.778553 | I46: =IF($F$46<=$G$46,"cap","discount") -> cap | J46: =Assumptions!$B$69/$H$46 -> 186716.59 | K46: =Assumptions!$B$74/(Assumptions!$B$20+Assumptions!$B$17+$B$46+$E$46+$J$46) -> 42.739338 | L46: =$C$46*(1-Assumptions!$B$75) -> 31.984223 | M46: =MIN($K$46,$L$46) -> 31.984223 | N46: =IF($K$46<=$L$46,"cap","discount") -> discount | O46: =Assumptions!$B$73/$M$46 -> 93796.243 | P46: =MAX(Assumptions!$B$4,(Assumptions!$B$10*(Assumptions!$B$20+$E$46+Assumptions!$B$17+$J$46+$O$46+$D$46)-Assumptions!$B$17)/(1-Assumptions!$B$10)) -> 587882.23 | Q46: =Assumptions!$B$20+$E$46+Assumptions!$B$17+$P$46+$J$46+$O$46+$D$46 -> 38327302 | R46: =IF($C$46<Assumptions!$B$37,Assumptions!$B$37*(Assumptions!$B$21+Assumptions!$B$22/Assumptions!$B$37)/(Assumptions!$B$21+Assumptions!$B$22/$C$46),Assumptions!$B$37) -> 1 | S46: =Assumptions!$B$38/$R$46 -> 1 | T46: =Assumptions!$B$39*$S$46 -> 5000000 | U46: =IF($C$46<Assumptions!$B$42,Assumptions!$B$42*(Assumptions!$B$21+Assumptions!$B$22/Assumptions!$B$42)/(Assumptions!$B$21+Assumptions!$B$22/$C$46),Assumptions!$B$42) -> 3 | V46: =Assumptions!$B$43/$U$46 -> 1 | W46: =Assumptions!$B$44*$V$46 -> 5000000 | X46: =IF($C$46<Assumptions!$B$47,Assumptions!$B$47*(Assumptions!$B$21+Assumptions!$B$22/Assumptions!$B$47)/(Assumptions!$B$21+Assumptions!$B$22/$C$46),Assumptions!$B$47) -> 10 | Y46: =Assumptions!$B$48/$X$46 -> 1 | Z46: =Assumptions!$B$49*$Y$46 -> 3000000 | AA46: =IF($C$46<Assumptions!$B$52,Assumptions!$B$52*(Assumptions!$B$21+Assumptions!$B$22/Assumptions!$B$52)/(Assumptions!$B$21+Assumptions!$B$22/$C$46),Assumptions!$B$52) -> 25 | AB46: =Assumptions!$B$53/$AA$46 -> 1 | AC46: =Assumptions!$B$54*$AB$46 -> 2400000 | AD46: =IF($C$46<Assumptions!$B$57,Assumptions!$B$57*(Assumptions!$B$21+Assumptions!$B$22/Assumptions!$B$57)/(Assumptions!$B$21+Assumptions!$B$22/$C$46),Assumptions!$B$57) -> 57.681736 | AE46: =Assumptions!$B$58/$AD$46 -> 1.0401906 | AF46: =Assumptions!$B$59*$AE$46 -> 1733651.4 | AG46: =IF($C$46<Assumptions!$B$62,Assumptions!$B$62*(Assumptions!$B$21+Assumptions!$B$22/Assumptions!$B$62)/(Assumptions!$B$21+Assumptions!$B$22/$C$46),Assumptions!$B$62) -> 48.912626 | AH46: =Assumptions!$B$63/$AG$46 -> 1.0050229 | AI46: =Assumptions!$B$64*$AH$46 -> 6133320.3
A47: =ROW()-ROW($A$41)+Assumptions!$B$4 -> 6 | B47: =$P$46 -> 587882.23 | C47: =Assumptions!$B$6/(Assumptions!$B$16+$B$47) -> 37.628498 | D47: =Assumptions!$B$7/$C$47 -> 797268.07 | E47: =$T$47+$W$47+$Z$47+$AC$47+$AF$47+$AI$47 -> 23266972 | F47: =Assumptions!$B$70/(Assumptions!$B$20+Assumptions!$B$17+$B$47+$E$47+$O$46) -> 26.778553 | G47: =$C$47*(1-Assumptions!$B$71) -> 30.102798 | H47: =MIN($F$47,$G$47) -> 26.778553 | I47: =IF($F$47<=$G$47,"cap","discount") -> cap | J47: =Assumptions!$B$69/$H$47 -> 186716.59 | K47: =Assumptions!$B$74/(Assumptions!$B$20+Assumptions!$B$17+$B$47+$E$47+$J$47) -> 42.739338 | L47: =$C$47*(1-Assumptions!$B$75) -> 31.984223 | M47: =MIN($K$47,$L$47) -> 31.984223 | N47: =IF($K$47<=$L$47,"cap","discount") -> discount | O47: =Assumptions!$B$73/$M$47 -> 93796.243 | P47: =MAX(Assumptions!$B$4,(Assumptions!$B$10*(Assumptions!$B$20+$E$47+Assumptions!$B$17+$J$47+$O$47+$D$47)-Assumptions!$B$17)/(1-Assumptions!$B$10)) -> 587882.23 | Q47: =Assumptions!$B$20+$E$47+Assumptions!$B$17+$P$47+$J$47+$O$47+$D$47 -> 38327302 | R47: =IF($C$47<Assumptions!$B$37,Assumptions!$B$37*(Assumptions!$B$21+Assumptions!$B$22/Assumptions!$B$37)/(Assumptions!$B$21+Assumptions!$B$22/$C$47),Assumptions!$B$37) -> 1 | S47: =Assumptions!$B$38/$R$47 -> 1 | T47: =Assumptions!$B$39*$S$47 -> 5000000 | U47: =IF($C$47<Assumptions!$B$42,Assumptions!$B$42*(Assumptions!$B$21+Assumptions!$B$22/Assumptions!$B$42)/(Assumptions!$B$21+Assumptions!$B$22/$C$47),Assumptions!$B$42) -> 3 | V47: =Assumptions!$B$43/$U$47 -> 1 | W47: =Assumptions!$B$44*$V$47 -> 5000000 | X47: =IF($C$47<Assumptions!$B$47,Assumptions!$B$47*(Assumptions!$B$21+Assumptions!$B$22/Assumptions!$B$47)/(Assumptions!$B$21+Assumptions!$B$22/$C$47),Assumptions!$B$47) -> 10 | Y47: =Assumptions!$B$48/$X$47 -> 1 | Z47: =Assumptions!$B$49*$Y$47 -> 3000000 | AA47: =IF($C$47<Assumptions!$B$52,Assumptions!$B$52*(Assumptions!$B$21+Assumptions!$B$22/Assumptions!$B$52)/(Assumptions!$B$21+Assumptions!$B$22/$C$47),Assumptions!$B$52) -> 25 | AB47: =Assumptions!$B$53/$AA$47 -> 1 | AC47: =Assumptions!$B$54*$AB$47 -> 2400000 | AD47: =IF($C$47<Assumptions!$B$57,Assumptions!$B$57*(Assumptions!$B$21+Assumptions!$B$22/Assumptions!$B$57)/(Assumptions!$B$21+Assumptions!$B$22/$C$47),Assumptions!$B$57) -> 57.681736 | AE47: =Assumptions!$B$58/$AD$47 -> 1.0401906 | AF47: =Assumptions!$B$59*$AE$47 -> 1733651.4 | AG47: =IF($C$47<Assumptions!$B$62,Assumptions!$B$62*(Assumptions!$B$21+Assumptions!$B$22/Assumptions!$B$62)/(Assumptions!$B$21+Assumptions!$B$22/$C$47),Assumptions!$B$62) -> 48.912626 | AH47: =Assumptions!$B$63/$AG$47 -> 1.0050229 | AI47: =Assumptions!$B$64*$AH$47 -> 6133320.3
A48: =ROW()-ROW($A$41)+Assumptions!$B$4 -> 7 | B48: =$P$47 -> 587882.23 | C48: =Assumptions!$B$6/(Assumptions!$B$16+$B$48) -> 37.628498 | D48: =Assumptions!$B$7/$C$48 -> 797268.07 | E48: =$T$48+$W$48+$Z$48+$AC$48+$AF$48+$AI$48 -> 23266972 | F48: =Assumptions!$B$70/(Assumptions!$B$20+Assumptions!$B$17+$B$48+$E$48+$O$47) -> 26.778553 | G48: =$C$48*(1-Assumptions!$B$71) -> 30.102798 | H48: =MIN($F$48,$G$48) -> 26.778553 | I48: =IF($F$48<=$G$48,"cap","discount") -> cap | J48: =Assumptions!$B$69/$H$48 -> 186716.59 | K48: =Assumptions!$B$74/(Assumptions!$B$20+Assumptions!$B$17+$B$48+$E$48+$J$48) -> 42.739338 | L48: =$C$48*(1-Assumptions!$B$75) -> 31.984223 | M48: =MIN($K$48,$L$48) -> 31.984223 | N48: =IF($K$48<=$L$48,"cap","discount") -> discount | O48: =Assumptions!$B$73/$M$48 -> 93796.243 | P48: =MAX(Assumptions!$B$4,(Assumptions!$B$10*(Assumptions!$B$20+$E$48+Assumptions!$B$17+$J$48+$O$48+$D$48)-Assumptions!$B$17)/(1-Assumptions!$B$10)) -> 587882.23 | Q48: =Assumptions!$B$20+$E$48+Assumptions!$B$17+$P$48+$J$48+$O$48+$D$48 -> 38327302 | R48: =IF($C$48<Assumptions!$B$37,Assumptions!$B$37*(Assumptions!$B$21+Assumptions!$B$22/Assumptions!$B$37)/(Assumptions!$B$21+Assumptions!$B$22/$C$48),Assumptions!$B$37) -> 1 | S48: =Assumptions!$B$38/$R$48 -> 1 | T48: =Assumptions!$B$39*$S$48 -> 5000000 | U48: =IF($C$48<Assumptions!$B$42,Assumptions!$B$42*(Assumptions!$B$21+Assumptions!$B$22/Assumptions!$B$42)/(Assumptions!$B$21+Assumptions!$B$22/$C$48),Assumptions!$B$42) -> 3 | V48: =Assumptions!$B$43/$U$48 -> 1 | W48: =Assumptions!$B$44*$V$48 -> 5000000 | X48: =IF($C$48<Assumptions!$B$47,Assumptions!$B$47*(Assumptions!$B$21+Assumptions!$B$22/Assumptions!$B$47)/(Assumptions!$B$21+Assumptions!$B$22/$C$48),Assumptions!$B$47) -> 10 | Y48: =Assumptions!$B$48/$X$48 -> 1 | Z48: =Assumptions!$B$49*$Y$48 -> 3000000 | AA48: =IF($C$48<Assumptions!$B$52,Assumptions!$B$52*(Assumptions!$B$21+Assumptions!$B$22/Assumptions!$B$52)/(Assumptions!$B$21+Assumptions!$B$22/$C$48),Assumptions!$B$52) -> 25 | AB48: =Assumptions!$B$53/$AA$48 -> 1 | AC48: =Assumptions!$B$54*$AB$48 -> 2400000 | AD48: =IF($C$48<Assumptions!$B$57,Assumptions!$B$57*(Assumptions!$B$21+Assumptions!$B$22/Assumptions!$B$57)/(Assumptions!$B$21+Assumptions!$B$22/$C$48),Assumptions!$B$57) -> 57.681736 | AE48: =Assumptions!$B$58/$AD$48 -> 1.0401906 | AF48: =Assumptions!$B$59*$AE$48 -> 1733651.4 | AG48: =IF($C$48<Assumptions!$B$62,Assumptions!$B$62*(Assumptions!$B$21+Assumptions!$B$22/Assumptions!$B$62)/(Assumptions!$B$21+Assumptions!$B$22/$C$48),Assumptions!$B$62) -> 48.912626 | AH48: =Assumptions!$B$63/$AG$48 -> 1.0050229 | AI48: =Assumptions!$B$64*$AH$48 -> 6133320.3
A49: =ROW()-ROW($A$41)+Assumptions!$B$4 -> 8 | B49: =$P$48 -> 587882.23 | C49: =Assumptions!$B$6/(Assumptions!$B$16+$B$49) -> 37.628498 | D49: =Assumptions!$B$7/$C$49 -> 797268.07 | E49: =$T$49+$W$49+$Z$49+$AC$49+$AF$49+$AI$49 -> 23266972 | F49: =Assumptions!$B$70/(Assumptions!$B$20+Assumptions!$B$17+$B$49+$E$49+$O$48) -> 26.778553 | G49: =$C$49*(1-Assumptions!$B$71) -> 30.102798 | H49: =MIN($F$49,$G$49) -> 26.778553 | I49: =IF($F$49<=$G$49,"cap","discount") -> cap | J49: =Assumptions!$B$69/$H$49 -> 186716.59 | K49: =Assumptions!$B$74/(Assumptions!$B$20+Assumptions!$B$17+$B$49+$E$49+$J$49) -> 42.739338 | L49: =$C$49*(1-Assumptions!$B$75) -> 31.984223 | M49: =MIN($K$49,$L$49) -> 31.984223 | N49: =IF($K$49<=$L$49,"cap","discount") -> discount | O49: =Assumptions!$B$73/$M$49 -> 93796.243 | P49: =MAX(Assumptions!$B$4,(Assumptions!$B$10*(Assumptions!$B$20+$E$49+Assumptions!$B$17+$J$49+$O$49+$D$49)-Assumptions!$B$17)/(1-Assumptions!$B$10)) -> 587882.23 | Q49: =Assumptions!$B$20+$E$49+Assumptions!$B$17+$P$49+$J$49+$O$49+$D$49 -> 38327302 | R49: =IF($C$49<Assumptions!$B$37,Assumptions!$B$37*(Assumptions!$B$21+Assumptions!$B$22/Assumptions!$B$37)/(Assumptions!$B$21+Assumptions!$B$22/$C$49),Assumptions!$B$37) -> 1 | S49: =Assumptions!$B$38/$R$49 -> 1 | T49: =Assumptions!$B$39*$S$49 -> 5000000 | U49: =IF($C$49<Assumptions!$B$42,Assumptions!$B$42*(Assumptions!$B$21+Assumptions!$B$22/Assumptions!$B$42)/(Assumptions!$B$21+Assumptions!$B$22/$C$49),Assumptions!$B$42) -> 3 | V49: =Assumptions!$B$43/$U$49 -> 1 | W49: =Assumptions!$B$44*$V$49 -> 5000000 | X49: =IF($C$49<Assumptions!$B$47,Assumptions!$B$47*(Assumptions!$B$21+Assumptions!$B$22/Assumptions!$B$47)/(Assumptions!$B$21+Assumptions!$B$22/$C$49),Assumptions!$B$47) -> 10 | Y49: =Assumptions!$B$48/$X$49 -> 1 | Z49: =Assumptions!$B$49*$Y$49 -> 3000000 | AA49: =IF($C$49<Assumptions!$B$52,Assumptions!$B$52*(Assumptions!$B$21+Assumptions!$B$22/Assumptions!$B$52)/(Assumptions!$B$21+Assumptions!$B$22/$C$49),Assumptions!$B$52) -> 25 | AB49: =Assumptions!$B$53/$AA$49 -> 1 | AC49: =Assumptions!$B$54*$AB$49 -> 2400000 | AD49: =IF($C$49<Assumptions!$B$57,Assumptions!$B$57*(Assumptions!$B$21+Assumptions!$B$22/Assumptions!$B$57)/(Assumptions!$B$21+Assumptions!$B$22/$C$49),Assumptions!$B$57) -> 57.681736 | AE49: =Assumptions!$B$58/$AD$49 -> 1.0401906 | AF49: =Assumptions!$B$59*$AE$49 -> 1733651.4 | AG49: =IF($C$49<Assumptions!$B$62,Assumptions!$B$62*(Assumptions!$B$21+Assumptions!$B$22/Assumptions!$B$62)/(Assumptions!$B$21+Assumptions!$B$22/$C$49),Assumptions!$B$62) -> 48.912626 | AH49: =Assumptions!$B$63/$AG$49 -> 1.0050229 | AI49: =Assumptions!$B$64*$AH$49 -> 6133320.3
A50: =ROW()-ROW($A$41)+Assumptions!$B$4 -> 9 | B50: =$P$49 -> 587882.23 | C50: =Assumptions!$B$6/(Assumptions!$B$16+$B$50) -> 37.628498 | D50: =Assumptions!$B$7/$C$50 -> 797268.07 | E50: =$T$50+$W$50+$Z$50+$AC$50+$AF$50+$AI$50 -> 23266972 | F50: =Assumptions!$B$70/(Assumptions!$B$20+Assumptions!$B$17+$B$50+$E$50+$O$49) -> 26.778553 | G50: =$C$50*(1-Assumptions!$B$71) -> 30.102798 | H50: =MIN($F$50,$G$50) -> 26.778553 | I50: =IF($F$50<=$G$50,"cap","discount") -> cap | J50: =Assumptions!$B$69/$H$50 -> 186716.59 | K50: =Assumptions!$B$74/(Assumptions!$B$20+Assumptions!$B$17+$B$50+$E$50+$J$50) -> 42.739338 | L50: =$C$50*(1-Assumptions!$B$75) -> 31.984223 | M50: =MIN($K$50,$L$50) -> 31.984223 | N50: =IF($K$50<=$L$50,"cap","discount") -> discount | O50: =Assumptions!$B$73/$M$50 -> 93796.243 | P50: =MAX(Assumptions!$B$4,(Assumptions!$B$10*(Assumptions!$B$20+$E$50+Assumptions!$B$17+$J$50+$O$50+$D$50)-Assumptions!$B$17)/(1-Assumptions!$B$10)) -> 587882.23 | Q50: =Assumptions!$B$20+$E$50+Assumptions!$B$17+$P$50+$J$50+$O$50+$D$50 -> 38327302 | R50: =IF($C$50<Assumptions!$B$37,Assumptions!$B$37*(Assumptions!$B$21+Assumptions!$B$22/Assumptions!$B$37)/(Assumptions!$B$21+Assumptions!$B$22/$C$50),Assumptions!$B$37) -> 1 | S50: =Assumptions!$B$38/$R$50 -> 1 | T50: =Assumptions!$B$39*$S$50 -> 5000000 | U50: =IF($C$50<Assumptions!$B$42,Assumptions!$B$42*(Assumptions!$B$21+Assumptions!$B$22/Assumptions!$B$42)/(Assumptions!$B$21+Assumptions!$B$22/$C$50),Assumptions!$B$42) -> 3 | V50: =Assumptions!$B$43/$U$50 -> 1 | W50: =Assumptions!$B$44*$V$50 -> 5000000 | X50: =IF($C$50<Assumptions!$B$47,Assumptions!$B$47*(Assumptions!$B$21+Assumptions!$B$22/Assumptions!$B$47)/(Assumptions!$B$21+Assumptions!$B$22/$C$50),Assumptions!$B$47) -> 10 | Y50: =Assumptions!$B$48/$X$50 -> 1 | Z50: =Assumptions!$B$49*$Y$50 -> 3000000 | AA50: =IF($C$50<Assumptions!$B$52,Assumptions!$B$52*(Assumptions!$B$21+Assumptions!$B$22/Assumptions!$B$52)/(Assumptions!$B$21+Assumptions!$B$22/$C$50),Assumptions!$B$52) -> 25 | AB50: =Assumptions!$B$53/$AA$50 -> 1 | AC50: =Assumptions!$B$54*$AB$50 -> 2400000 | AD50: =IF($C$50<Assumptions!$B$57,Assumptions!$B$57*(Assumptions!$B$21+Assumptions!$B$22/Assumptions!$B$57)/(Assumptions!$B$21+Assumptions!$B$22/$C$50),Assumptions!$B$57) -> 57.681736 | AE50: =Assumptions!$B$58/$AD$50 -> 1.0401906 | AF50: =Assumptions!$B$59*$AE$50 -> 1733651.4 | AG50: =IF($C$50<Assumptions!$B$62,Assumptions!$B$62*(Assumptions!$B$21+Assumptions!$B$22/Assumptions!$B$62)/(Assumptions!$B$21+Assumptions!$B$22/$C$50),Assumptions!$B$62) -> 48.912626 | AH50: =Assumptions!$B$63/$AG$50 -> 1.0050229 | AI50: =Assumptions!$B$64*$AH$50 -> 6133320.3
A51: =ROW()-ROW($A$41)+Assumptions!$B$4 -> 10 | B51: =$P$50 -> 587882.23 | C51: =Assumptions!$B$6/(Assumptions!$B$16+$B$51) -> 37.628498 | D51: =Assumptions!$B$7/$C$51 -> 797268.07 | E51: =$T$51+$W$51+$Z$51+$AC$51+$AF$51+$AI$51 -> 23266972 | F51: =Assumptions!$B$70/(Assumptions!$B$20+Assumptions!$B$17+$B$51+$E$51+$O$50) -> 26.778553 | G51: =$C$51*(1-Assumptions!$B$71) -> 30.102798 | H51: =MIN($F$51,$G$51) -> 26.778553 | I51: =IF($F$51<=$G$51,"cap","discount") -> cap | J51: =Assumptions!$B$69/$H$51 -> 186716.59 | K51: =Assumptions!$B$74/(Assumptions!$B$20+Assumptions!$B$17+$B$51+$E$51+$J$51) -> 42.739338 | L51: =$C$51*(1-Assumptions!$B$75) -> 31.984223 | M51: =MIN($K$51,$L$51) -> 31.984223 | N51: =IF($K$51<=$L$51,"cap","discount") -> discount | O51: =Assumptions!$B$73/$M$51 -> 93796.243 | P51: =MAX(Assumptions!$B$4,(Assumptions!$B$10*(Assumptions!$B$20+$E$51+Assumptions!$B$17+$J$51+$O$51+$D$51)-Assumptions!$B$17)/(1-Assumptions!$B$10)) -> 587882.23 | Q51: =Assumptions!$B$20+$E$51+Assumptions!$B$17+$P$51+$J$51+$O$51+$D$51 -> 38327302 | R51: =IF($C$51<Assumptions!$B$37,Assumptions!$B$37*(Assumptions!$B$21+Assumptions!$B$22/Assumptions!$B$37)/(Assumptions!$B$21+Assumptions!$B$22/$C$51),Assumptions!$B$37) -> 1 | S51: =Assumptions!$B$38/$R$51 -> 1 | T51: =Assumptions!$B$39*$S$51 -> 5000000 | U51: =IF($C$51<Assumptions!$B$42,Assumptions!$B$42*(Assumptions!$B$21+Assumptions!$B$22/Assumptions!$B$42)/(Assumptions!$B$21+Assumptions!$B$22/$C$51),Assumptions!$B$42) -> 3 | V51: =Assumptions!$B$43/$U$51 -> 1 | W51: =Assumptions!$B$44*$V$51 -> 5000000 | X51: =IF($C$51<Assumptions!$B$47,Assumptions!$B$47*(Assumptions!$B$21+Assumptions!$B$22/Assumptions!$B$47)/(Assumptions!$B$21+Assumptions!$B$22/$C$51),Assumptions!$B$47) -> 10 | Y51: =Assumptions!$B$48/$X$51 -> 1 | Z51: =Assumptions!$B$49*$Y$51 -> 3000000 | AA51: =IF($C$51<Assumptions!$B$52,Assumptions!$B$52*(Assumptions!$B$21+Assumptions!$B$22/Assumptions!$B$52)/(Assumptions!$B$21+Assumptions!$B$22/$C$51),Assumptions!$B$52) -> 25 | AB51: =Assumptions!$B$53/$AA$51 -> 1 | AC51: =Assumptions!$B$54*$AB$51 -> 2400000 | AD51: =IF($C$51<Assumptions!$B$57,Assumptions!$B$57*(Assumptions!$B$21+Assumptions!$B$22/Assumptions!$B$57)/(Assumptions!$B$21+Assumptions!$B$22/$C$51),Assumptions!$B$57) -> 57.681736 | AE51: =Assumptions!$B$58/$AD$51 -> 1.0401906 | AF51: =Assumptions!$B$59*$AE$51 -> 1733651.4 | AG51: =IF($C$51<Assumptions!$B$62,Assumptions!$B$62*(Assumptions!$B$21+Assumptions!$B$22/Assumptions!$B$62)/(Assumptions!$B$21+Assumptions!$B$22/$C$51),Assumptions!$B$62) -> 48.912626 | AH51: =Assumptions!$B$63/$AG$51 -> 1.0050229 | AI51: =Assumptions!$B$64*$AH$51 -> 6133320.3
A52: =ROW()-ROW($A$41)+Assumptions!$B$4 -> 11 | B52: =$P$51 -> 587882.23 | C52: =Assumptions!$B$6/(Assumptions!$B$16+$B$52) -> 37.628498 | D52: =Assumptions!$B$7/$C$52 -> 797268.07 | E52: =$T$52+$W$52+$Z$52+$AC$52+$AF$52+$AI$52 -> 23266972 | F52: =Assumptions!$B$70/(Assumptions!$B$20+Assumptions!$B$17+$B$52+$E$52+$O$51) -> 26.778553 | G52: =$C$52*(1-Assumptions!$B$71) -> 30.102798 | H52: =MIN($F$52,$G$52) -> 26.778553 | I52: =IF($F$52<=$G$52,"cap","discount") -> cap | J52: =Assumptions!$B$69/$H$52 -> 186716.59 | K52: =Assumptions!$B$74/(Assumptions!$B$20+Assumptions!$B$17+$B$52+$E$52+$J$52) -> 42.739338 | L52: =$C$52*(1-Assumptions!$B$75) -> 31.984223 | M52: =MIN($K$52,$L$52) -> 31.984223 | N52: =IF($K$52<=$L$52,"cap","discount") -> discount | O52: =Assumptions!$B$73/$M$52 -> 93796.243 | P52: =MAX(Assumptions!$B$4,(Assumptions!$B$10*(Assumptions!$B$20+$E$52+Assumptions!$B$17+$J$52+$O$52+$D$52)-Assumptions!$B$17)/(1-Assumptions!$B$10)) -> 587882.23 | Q52: =Assumptions!$B$20+$E$52+Assumptions!$B$17+$P$52+$J$52+$O$52+$D$52 -> 38327302 | R52: =IF($C$52<Assumptions!$B$37,Assumptions!$B$37*(Assumptions!$B$21+Assumptions!$B$22/Assumptions!$B$37)/(Assumptions!$B$21+Assumptions!$B$22/$C$52),Assumptions!$B$37) -> 1 | S52: =Assumptions!$B$38/$R$52 -> 1 | T52: =Assumptions!$B$39*$S$52 -> 5000000 | U52: =IF($C$52<Assumptions!$B$42,Assumptions!$B$42*(Assumptions!$B$21+Assumptions!$B$22/Assumptions!$B$42)/(Assumptions!$B$21+Assumptions!$B$22/$C$52),Assumptions!$B$42) -> 3 | V52: =Assumptions!$B$43/$U$52 -> 1 | W52: =Assumptions!$B$44*$V$52 -> 5000000 | X52: =IF($C$52<Assumptions!$B$47,Assumptions!$B$47*(Assumptions!$B$21+Assumptions!$B$22/Assumptions!$B$47)/(Assumptions!$B$21+Assumptions!$B$22/$C$52),Assumptions!$B$47) -> 10 | Y52: =Assumptions!$B$48/$X$52 -> 1 | Z52: =Assumptions!$B$49*$Y$52 -> 3000000 | AA52: =IF($C$52<Assumptions!$B$52,Assumptions!$B$52*(Assumptions!$B$21+Assumptions!$B$22/Assumptions!$B$52)/(Assumptions!$B$21+Assumptions!$B$22/$C$52),Assumptions!$B$52) -> 25 | AB52: =Assumptions!$B$53/$AA$52 -> 1 | AC52: =Assumptions!$B$54*$AB$52 -> 2400000 | AD52: =IF($C$52<Assumptions!$B$57,Assumptions!$B$57*(Assumptions!$B$21+Assumptions!$B$22/Assumptions!$B$57)/(Assumptions!$B$21+Assumptions!$B$22/$C$52),Assumptions!$B$57) -> 57.681736 | AE52: =Assumptions!$B$58/$AD$52 -> 1.0401906 | AF52: =Assumptions!$B$59*$AE$52 -> 1733651.4 | AG52: =IF($C$52<Assumptions!$B$62,Assumptions!$B$62*(Assumptions!$B$21+Assumptions!$B$22/Assumptions!$B$62)/(Assumptions!$B$21+Assumptions!$B$22/$C$52),Assumptions!$B$62) -> 48.912626 | AH52: =Assumptions!$B$63/$AG$52 -> 1.0050229 | AI52: =Assumptions!$B$64*$AH$52 -> 6133320.3
A53: =ROW()-ROW($A$41)+Assumptions!$B$4 -> 12 | B53: =$P$52 -> 587882.23 | C53: =Assumptions!$B$6/(Assumptions!$B$16+$B$53) -> 37.628498 | D53: =Assumptions!$B$7/$C$53 -> 797268.07 | E53: =$T$53+$W$53+$Z$53+$AC$53+$AF$53+$AI$53 -> 23266972 | F53: =Assumptions!$B$70/(Assumptions!$B$20+Assumptions!$B$17+$B$53+$E$53+$O$52) -> 26.778553 | G53: =$C$53*(1-Assumptions!$B$71) -> 30.102798 | H53: =MIN($F$53,$G$53) -> 26.778553 | I53: =IF($F$53<=$G$53,"cap","discount") -> cap | J53: =Assumptions!$B$69/$H$53 -> 186716.59 | K53: =Assumptions!$B$74/(Assumptions!$B$20+Assumptions!$B$17+$B$53+$E$53+$J$53) -> 42.739338 | L53: =$C$53*(1-Assumptions!$B$75) -> 31.984223 | M53: =MIN($K$53,$L$53) -> 31.984223 | N53: =IF($K$53<=$L$53,"cap","discount") -> discount | O53: =Assumptions!$B$73/$M$53 -> 93796.243 | P53: =MAX(Assumptions!$B$4,(Assumptions!$B$10*(Assumptions!$B$20+$E$53+Assumptions!$B$17+$J$53+$O$53+$D$53)-Assumptions!$B$17)/(1-Assumptions!$B$10)) -> 587882.23 | Q53: =Assumptions!$B$20+$E$53+Assumptions!$B$17+$P$53+$J$53+$O$53+$D$53 -> 38327302 | R53: =IF($C$53<Assumptions!$B$37,Assumptions!$B$37*(Assumptions!$B$21+Assumptions!$B$22/Assumptions!$B$37)/(Assumptions!$B$21+Assumptions!$B$22/$C$53),Assumptions!$B$37) -> 1 | S53: =Assumptions!$B$38/$R$53 -> 1 | T53: =Assumptions!$B$39*$S$53 -> 5000000 | U53: =IF($C$53<Assumptions!$B$42,Assumptions!$B$42*(Assumptions!$B$21+Assumptions!$B$22/Assumptions!$B$42)/(Assumptions!$B$21+Assumptions!$B$22/$C$53),Assumptions!$B$42) -> 3 | V53: =Assumptions!$B$43/$U$53 -> 1 | W53: =Assumptions!$B$44*$V$53 -> 5000000 | X53: =IF($C$53<Assumptions!$B$47,Assumptions!$B$47*(Assumptions!$B$21+Assumptions!$B$22/Assumptions!$B$47)/(Assumptions!$B$21+Assumptions!$B$22/$C$53),Assumptions!$B$47) -> 10 | Y53: =Assumptions!$B$48/$X$53 -> 1 | Z53: =Assumptions!$B$49*$Y$53 -> 3000000 | AA53: =IF($C$53<Assumptions!$B$52,Assumptions!$B$52*(Assumptions!$B$21+Assumptions!$B$22/Assumptions!$B$52)/(Assumptions!$B$21+Assumptions!$B$22/$C$53),Assumptions!$B$52) -> 25 | AB53: =Assumptions!$B$53/$AA$53 -> 1 | AC53: =Assumptions!$B$54*$AB$53 -> 2400000 | AD53: =IF($C$53<Assumptions!$B$57,Assumptions!$B$57*(Assumptions!$B$21+Assumptions!$B$22/Assumptions!$B$57)/(Assumptions!$B$21+Assumptions!$B$22/$C$53),Assumptions!$B$57) -> 57.681736 | AE53: =Assumptions!$B$58/$AD$53 -> 1.0401906 | AF53: =Assumptions!$B$59*$AE$53 -> 1733651.4 | AG53: =IF($C$53<Assumptions!$B$62,Assumptions!$B$62*(Assumptions!$B$21+Assumptions!$B$22/Assumptions!$B$62)/(Assumptions!$B$21+Assumptions!$B$22/$C$53),Assumptions!$B$62) -> 48.912626 | AH53: =Assumptions!$B$63/$AG$53 -> 1.0050229 | AI53: =Assumptions!$B$64*$AH$53 -> 6133320.3
A54: =ROW()-ROW($A$41)+Assumptions!$B$4 -> 13 | B54: =$P$53 -> 587882.23 | C54: =Assumptions!$B$6/(Assumptions!$B$16+$B$54) -> 37.628498 | D54: =Assumptions!$B$7/$C$54 -> 797268.07 | E54: =$T$54+$W$54+$Z$54+$AC$54+$AF$54+$AI$54 -> 23266972 | F54: =Assumptions!$B$70/(Assumptions!$B$20+Assumptions!$B$17+$B$54+$E$54+$O$53) -> 26.778553 | G54: =$C$54*(1-Assumptions!$B$71) -> 30.102798 | H54: =MIN($F$54,$G$54) -> 26.778553 | I54: =IF($F$54<=$G$54,"cap","discount") -> cap | J54: =Assumptions!$B$69/$H$54 -> 186716.59 | K54: =Assumptions!$B$74/(Assumptions!$B$20+Assumptions!$B$17+$B$54+$E$54+$J$54) -> 42.739338 | L54: =$C$54*(1-Assumptions!$B$75) -> 31.984223 | M54: =MIN($K$54,$L$54) -> 31.984223 | N54: =IF($K$54<=$L$54,"cap","discount") -> discount | O54: =Assumptions!$B$73/$M$54 -> 93796.243 | P54: =MAX(Assumptions!$B$4,(Assumptions!$B$10*(Assumptions!$B$20+$E$54+Assumptions!$B$17+$J$54+$O$54+$D$54)-Assumptions!$B$17)/(1-Assumptions!$B$10)) -> 587882.23 | Q54: =Assumptions!$B$20+$E$54+Assumptions!$B$17+$P$54+$J$54+$O$54+$D$54 -> 38327302 | R54: =IF($C$54<Assumptions!$B$37,Assumptions!$B$37*(Assumptions!$B$21+Assumptions!$B$22/Assumptions!$B$37)/(Assumptions!$B$21+Assumptions!$B$22/$C$54),Assumptions!$B$37) -> 1 | S54: =Assumptions!$B$38/$R$54 -> 1 | T54: =Assumptions!$B$39*$S$54 -> 5000000 | U54: =IF($C$54<Assumptions!$B$42,Assumptions!$B$42*(Assumptions!$B$21+Assumptions!$B$22/Assumptions!$B$42)/(Assumptions!$B$21+Assumptions!$B$22/$C$54),Assumptions!$B$42) -> 3 | V54: =Assumptions!$B$43/$U$54 -> 1 | W54: =Assumptions!$B$44*$V$54 -> 5000000 | X54: =IF($C$54<Assumptions!$B$47,Assumptions!$B$47*(Assumptions!$B$21+Assumptions!$B$22/Assumptions!$B$47)/(Assumptions!$B$21+Assumptions!$B$22/$C$54),Assumptions!$B$47) -> 10 | Y54: =Assumptions!$B$48/$X$54 -> 1 | Z54: =Assumptions!$B$49*$Y$54 -> 3000000 | AA54: =IF($C$54<Assumptions!$B$52,Assumptions!$B$52*(Assumptions!$B$21+Assumptions!$B$22/Assumptions!$B$52)/(Assumptions!$B$21+Assumptions!$B$22/$C$54),Assumptions!$B$52) -> 25 | AB54: =Assumptions!$B$53/$AA$54 -> 1 | AC54: =Assumptions!$B$54*$AB$54 -> 2400000 | AD54: =IF($C$54<Assumptions!$B$57,Assumptions!$B$57*(Assumptions!$B$21+Assumptions!$B$22/Assumptions!$B$57)/(Assumptions!$B$21+Assumptions!$B$22/$C$54),Assumptions!$B$57) -> 57.681736 | AE54: =Assumptions!$B$58/$AD$54 -> 1.0401906 | AF54: =Assumptions!$B$59*$AE$54 -> 1733651.4 | AG54: =IF($C$54<Assumptions!$B$62,Assumptions!$B$62*(Assumptions!$B$21+Assumptions!$B$22/Assumptions!$B$62)/(Assumptions!$B$21+Assumptions!$B$22/$C$54),Assumptions!$B$62) -> 48.912626 | AH54: =Assumptions!$B$63/$AG$54 -> 1.0050229 | AI54: =Assumptions!$B$64*$AH$54 -> 6133320.3
A55: =ROW()-ROW($A$41)+Assumptions!$B$4 -> 14 | B55: =$P$54 -> 587882.23 | C55: =Assumptions!$B$6/(Assumptions!$B$16+$B$55) -> 37.628498 | D55: =Assumptions!$B$7/$C$55 -> 797268.07 | E55: =$T$55+$W$55+$Z$55+$AC$55+$AF$55+$AI$55 -> 23266972 | F55: =Assumptions!$B$70/(Assumptions!$B$20+Assumptions!$B$17+$B$55+$E$55+$O$54) -> 26.778553 | G55: =$C$55*(1-Assumptions!$B$71) -> 30.102798 | H55: =MIN($F$55,$G$55) -> 26.778553 | I55: =IF($F$55<=$G$55,"cap","discount") -> cap | J55: =Assumptions!$B$69/$H$55 -> 186716.59 | K55: =Assumptions!$B$74/(Assumptions!$B$20+Assumptions!$B$17+$B$55+$E$55+$J$55) -> 42.739338 | L55: =$C$55*(1-Assumptions!$B$75) -> 31.984223 | M55: =MIN($K$55,$L$55) -> 31.984223 | N55: =IF($K$55<=$L$55,"cap","discount") -> discount | O55: =Assumptions!$B$73/$M$55 -> 93796.243 | P55: =MAX(Assumptions!$B$4,(Assumptions!$B$10*(Assumptions!$B$20+$E$55+Assumptions!$B$17+$J$55+$O$55+$D$55)-Assumptions!$B$17)/(1-Assumptions!$B$10)) -> 587882.23 | Q55: =Assumptions!$B$20+$E$55+Assumptions!$B$17+$P$55+$J$55+$O$55+$D$55 -> 38327302 | R55: =IF($C$55<Assumptions!$B$37,Assumptions!$B$37*(Assumptions!$B$21+Assumptions!$B$22/Assumptions!$B$37)/(Assumptions!$B$21+Assumptions!$B$22/$C$55),Assumptions!$B$37) -> 1 | S55: =Assumptions!$B$38/$R$55 -> 1 | T55: =Assumptions!$B$39*$S$55 -> 5000000 | U55: =IF($C$55<Assumptions!$B$42,Assumptions!$B$42*(Assumptions!$B$21+Assumptions!$B$22/Assumptions!$B$42)/(Assumptions!$B$21+Assumptions!$B$22/$C$55),Assumptions!$B$42) -> 3 | V55: =Assumptions!$B$43/$U$55 -> 1 | W55: =Assumptions!$B$44*$V$55 -> 5000000 | X55: =IF($C$55<Assumptions!$B$47,Assumptions!$B$47*(Assumptions!$B$21+Assumptions!$B$22/Assumptions!$B$47)/(Assumptions!$B$21+Assumptions!$B$22/$C$55),Assumptions!$B$47) -> 10 | Y55: =Assumptions!$B$48/$X$55 -> 1 | Z55: =Assumptions!$B$49*$Y$55 -> 3000000 | AA55: =IF($C$55<Assumptions!$B$52,Assumptions!$B$52*(Assumptions!$B$21+Assumptions!$B$22/Assumptions!$B$52)/(Assumptions!$B$21+Assumptions!$B$22/$C$55),Assumptions!$B$52) -> 25 | AB55: =Assumptions!$B$53/$AA$55 -> 1 | AC55: =Assumptions!$B$54*$AB$55 -> 2400000 | AD55: =IF($C$55<Assumptions!$B$57,Assumptions!$B$57*(Assumptions!$B$21+Assumptions!$B$22/Assumptions!$B$57)/(Assumptions!$B$21+Assumptions!$B$22/$C$55),Assumptions!$B$57) -> 57.681736 | AE55: =Assumptions!$B$58/$AD$55 -> 1.0401906 | AF55: =Assumptions!$B$59*$AE$55 -> 1733651.4 | AG55: =IF($C$55<Assumptions!$B$62,Assumptions!$B$62*(Assumptions!$B$21+Assumptions!$B$22/Assumptions!$B$62)/(Assumptions!$B$21+Assumptions!$B$22/$C$55),Assumptions!$B$62) -> 48.912626 | AH55: =Assumptions!$B$63/$AG$55 -> 1.0050229 | AI55: =Assumptions!$B$64*$AH$55 -> 6133320.3
A56: =ROW()-ROW($A$41)+Assumptions!$B$4 -> 15 | B56: =$P$55 -> 587882.23 | C56: =Assumptions!$B$6/(Assumptions!$B$16+$B$56) -> 37.628498 | D56: =Assumptions!$B$7/$C$56 -> 797268.07 | E56: =$T$56+$W$56+$Z$56+$AC$56+$AF$56+$AI$56 -> 23266972 | F56: =Assumptions!$B$70/(Assumptions!$B$20+Assumptions!$B$17+$B$56+$E$56+$O$55) -> 26.778553 | G56: =$C$56*(1-Assumptions!$B$71) -> 30.102798 | H56: =MIN($F$56,$G$56) -> 26.778553 | I56: =IF($F$56<=$G$56,"cap","discount") -> cap | J56: =Assumptions!$B$69/$H$56 -> 186716.59 | K56: =Assumptions!$B$74/(Assumptions!$B$20+Assumptions!$B$17+$B$56+$E$56+$J$56) -> 42.739338 | L56: =$C$56*(1-Assumptions!$B$75) -> 31.984223 | M56: =MIN($K$56,$L$56) -> 31.984223 | N56: =IF($K$56<=$L$56,"cap","discount") -> discount | O56: =Assumptions!$B$73/$M$56 -> 93796.243 | P56: =MAX(Assumptions!$B$4,(Assumptions!$B$10*(Assumptions!$B$20+$E$56+Assumptions!$B$17+$J$56+$O$56+$D$56)-Assumptions!$B$17)/(1-Assumptions!$B$10)) -> 587882.23 | Q56: =Assumptions!$B$20+$E$56+Assumptions!$B$17+$P$56+$J$56+$O$56+$D$56 -> 38327302 | R56: =IF($C$56<Assumptions!$B$37,Assumptions!$B$37*(Assumptions!$B$21+Assumptions!$B$22/Assumptions!$B$37)/(Assumptions!$B$21+Assumptions!$B$22/$C$56),Assumptions!$B$37) -> 1 | S56: =Assumptions!$B$38/$R$56 -> 1 | T56: =Assumptions!$B$39*$S$56 -> 5000000 | U56: =IF($C$56<Assumptions!$B$42,Assumptions!$B$42*(Assumptions!$B$21+Assumptions!$B$22/Assumptions!$B$42)/(Assumptions!$B$21+Assumptions!$B$22/$C$56),Assumptions!$B$42) -> 3 | V56: =Assumptions!$B$43/$U$56 -> 1 | W56: =Assumptions!$B$44*$V$56 -> 5000000 | X56: =IF($C$56<Assumptions!$B$47,Assumptions!$B$47*(Assumptions!$B$21+Assumptions!$B$22/Assumptions!$B$47)/(Assumptions!$B$21+Assumptions!$B$22/$C$56),Assumptions!$B$47) -> 10 | Y56: =Assumptions!$B$48/$X$56 -> 1 | Z56: =Assumptions!$B$49*$Y$56 -> 3000000 | AA56: =IF($C$56<Assumptions!$B$52,Assumptions!$B$52*(Assumptions!$B$21+Assumptions!$B$22/Assumptions!$B$52)/(Assumptions!$B$21+Assumptions!$B$22/$C$56),Assumptions!$B$52) -> 25 | AB56: =Assumptions!$B$53/$AA$56 -> 1 | AC56: =Assumptions!$B$54*$AB$56 -> 2400000 | AD56: =IF($C$56<Assumptions!$B$57,Assumptions!$B$57*(Assumptions!$B$21+Assumptions!$B$22/Assumptions!$B$57)/(Assumptions!$B$21+Assumptions!$B$22/$C$56),Assumptions!$B$57) -> 57.681736 | AE56: =Assumptions!$B$58/$AD$56 -> 1.0401906 | AF56: =Assumptions!$B$59*$AE$56 -> 1733651.4 | AG56: =IF($C$56<Assumptions!$B$62,Assumptions!$B$62*(Assumptions!$B$21+Assumptions!$B$22/Assumptions!$B$62)/(Assumptions!$B$21+Assumptions!$B$22/$C$56),Assumptions!$B$62) -> 48.912626 | AH56: =Assumptions!$B$63/$AG$56 -> 1.0050229 | AI56: =Assumptions!$B$64*$AH$56 -> 6133320.3
A57: =ROW()-ROW($A$41)+Assumptions!$B$4 -> 16 | B57: =$P$56 -> 587882.23 | C57: =Assumptions!$B$6/(Assumptions!$B$16+$B$57) -> 37.628498 | D57: =Assumptions!$B$7/$C$57 -> 797268.07 | E57: =$T$57+$W$57+$Z$57+$AC$57+$AF$57+$AI$57 -> 23266972 | F57: =Assumptions!$B$70/(Assumptions!$B$20+Assumptions!$B$17+$B$57+$E$57+$O$56) -> 26.778553 | G57: =$C$57*(1-Assumptions!$B$71) -> 30.102798 | H57: =MIN($F$57,$G$57) -> 26.778553 | I57: =IF($F$57<=$G$57,"cap","discount") -> cap | J57: =Assumptions!$B$69/$H$57 -> 186716.59 | K57: =Assumptions!$B$74/(Assumptions!$B$20+Assumptions!$B$17+$B$57+$E$57+$J$57) -> 42.739338 | L57: =$C$57*(1-Assumptions!$B$75) -> 31.984223 | M57: =MIN($K$57,$L$57) -> 31.984223 | N57: =IF($K$57<=$L$57,"cap","discount") -> discount | O57: =Assumptions!$B$73/$M$57 -> 93796.243 | P57: =MAX(Assumptions!$B$4,(Assumptions!$B$10*(Assumptions!$B$20+$E$57+Assumptions!$B$17+$J$57+$O$57+$D$57)-Assumptions!$B$17)/(1-Assumptions!$B$10)) -> 587882.23 | Q57: =Assumptions!$B$20+$E$57+Assumptions!$B$17+$P$57+$J$57+$O$57+$D$57 -> 38327302 | R57: =IF($C$57<Assumptions!$B$37,Assumptions!$B$37*(Assumptions!$B$21+Assumptions!$B$22/Assumptions!$B$37)/(Assumptions!$B$21+Assumptions!$B$22/$C$57),Assumptions!$B$37) -> 1 | S57: =Assumptions!$B$38/$R$57 -> 1 | T57: =Assumptions!$B$39*$S$57 -> 5000000 | U57: =IF($C$57<Assumptions!$B$42,Assumptions!$B$42*(Assumptions!$B$21+Assumptions!$B$22/Assumptions!$B$42)/(Assumptions!$B$21+Assumptions!$B$22/$C$57),Assumptions!$B$42) -> 3 | V57: =Assumptions!$B$43/$U$57 -> 1 | W57: =Assumptions!$B$44*$V$57 -> 5000000 | X57: =IF($C$57<Assumptions!$B$47,Assumptions!$B$47*(Assumptions!$B$21+Assumptions!$B$22/Assumptions!$B$47)/(Assumptions!$B$21+Assumptions!$B$22/$C$57),Assumptions!$B$47) -> 10 | Y57: =Assumptions!$B$48/$X$57 -> 1 | Z57: =Assumptions!$B$49*$Y$57 -> 3000000 | AA57: =IF($C$57<Assumptions!$B$52,Assumptions!$B$52*(Assumptions!$B$21+Assumptions!$B$22/Assumptions!$B$52)/(Assumptions!$B$21+Assumptions!$B$22/$C$57),Assumptions!$B$52) -> 25 | AB57: =Assumptions!$B$53/$AA$57 -> 1 | AC57: =Assumptions!$B$54*$AB$57 -> 2400000 | AD57: =IF($C$57<Assumptions!$B$57,Assumptions!$B$57*(Assumptions!$B$21+Assumptions!$B$22/Assumptions!$B$57)/(Assumptions!$B$21+Assumptions!$B$22/$C$57),Assumptions!$B$57) -> 57.681736 | AE57: =Assumptions!$B$58/$AD$57 -> 1.0401906 | AF57: =Assumptions!$B$59*$AE$57 -> 1733651.4 | AG57: =IF($C$57<Assumptions!$B$62,Assumptions!$B$62*(Assumptions!$B$21+Assumptions!$B$22/Assumptions!$B$62)/(Assumptions!$B$21+Assumptions!$B$22/$C$57),Assumptions!$B$62) -> 48.912626 | AH57: =Assumptions!$B$63/$AG$57 -> 1.0050229 | AI57: =Assumptions!$B$64*$AH$57 -> 6133320.3
A58: =ROW()-ROW($A$41)+Assumptions!$B$4 -> 17 | B58: =$P$57 -> 587882.23 | C58: =Assumptions!$B$6/(Assumptions!$B$16+$B$58) -> 37.628498 | D58: =Assumptions!$B$7/$C$58 -> 797268.07 | E58: =$T$58+$W$58+$Z$58+$AC$58+$AF$58+$AI$58 -> 23266972 | F58: =Assumptions!$B$70/(Assumptions!$B$20+Assumptions!$B$17+$B$58+$E$58+$O$57) -> 26.778553 | G58: =$C$58*(1-Assumptions!$B$71) -> 30.102798 | H58: =MIN($F$58,$G$58) -> 26.778553 | I58: =IF($F$58<=$G$58,"cap","discount") -> cap | J58: =Assumptions!$B$69/$H$58 -> 186716.59 | K58: =Assumptions!$B$74/(Assumptions!$B$20+Assumptions!$B$17+$B$58+$E$58+$J$58) -> 42.739338 | L58: =$C$58*(1-Assumptions!$B$75) -> 31.984223 | M58: =MIN($K$58,$L$58) -> 31.984223 | N58: =IF($K$58<=$L$58,"cap","discount") -> discount | O58: =Assumptions!$B$73/$M$58 -> 93796.243 | P58: =MAX(Assumptions!$B$4,(Assumptions!$B$10*(Assumptions!$B$20+$E$58+Assumptions!$B$17+$J$58+$O$58+$D$58)-Assumptions!$B$17)/(1-Assumptions!$B$10)) -> 587882.23 | Q58: =Assumptions!$B$20+$E$58+Assumptions!$B$17+$P$58+$J$58+$O$58+$D$58 -> 38327302 | R58: =IF($C$58<Assumptions!$B$37,Assumptions!$B$37*(Assumptions!$B$21+Assumptions!$B$22/Assumptions!$B$37)/(Assumptions!$B$21+Assumptions!$B$22/$C$58),Assumptions!$B$37) -> 1 | S58: =Assumptions!$B$38/$R$58 -> 1 | T58: =Assumptions!$B$39*$S$58 -> 5000000 | U58: =IF($C$58<Assumptions!$B$42,Assumptions!$B$42*(Assumptions!$B$21+Assumptions!$B$22/Assumptions!$B$42)/(Assumptions!$B$21+Assumptions!$B$22/$C$58),Assumptions!$B$42) -> 3 | V58: =Assumptions!$B$43/$U$58 -> 1 | W58: =Assumptions!$B$44*$V$58 -> 5000000 | X58: =IF($C$58<Assumptions!$B$47,Assumptions!$B$47*(Assumptions!$B$21+Assumptions!$B$22/Assumptions!$B$47)/(Assumptions!$B$21+Assumptions!$B$22/$C$58),Assumptions!$B$47) -> 10 | Y58: =Assumptions!$B$48/$X$58 -> 1 | Z58: =Assumptions!$B$49*$Y$58 -> 3000000 | AA58: =IF($C$58<Assumptions!$B$52,Assumptions!$B$52*(Assumptions!$B$21+Assumptions!$B$22/Assumptions!$B$52)/(Assumptions!$B$21+Assumptions!$B$22/$C$58),Assumptions!$B$52) -> 25 | AB58: =Assumptions!$B$53/$AA$58 -> 1 | AC58: =Assumptions!$B$54*$AB$58 -> 2400000 | AD58: =IF($C$58<Assumptions!$B$57,Assumptions!$B$57*(Assumptions!$B$21+Assumptions!$B$22/Assumptions!$B$57)/(Assumptions!$B$21+Assumptions!$B$22/$C$58),Assumptions!$B$57) -> 57.681736 | AE58: =Assumptions!$B$58/$AD$58 -> 1.0401906 | AF58: =Assumptions!$B$59*$AE$58 -> 1733651.4 | AG58: =IF($C$58<Assumptions!$B$62,Assumptions!$B$62*(Assumptions!$B$21+Assumptions!$B$22/Assumptions!$B$62)/(Assumptions!$B$21+Assumptions!$B$22/$C$58),Assumptions!$B$62) -> 48.912626 | AH58: =Assumptions!$B$63/$AG$58 -> 1.0050229 | AI58: =Assumptions!$B$64*$AH$58 -> 6133320.3
A59: =ROW()-ROW($A$41)+Assumptions!$B$4 -> 18 | B59: =$P$58 -> 587882.23 | C59: =Assumptions!$B$6/(Assumptions!$B$16+$B$59) -> 37.628498 | D59: =Assumptions!$B$7/$C$59 -> 797268.07 | E59: =$T$59+$W$59+$Z$59+$AC$59+$AF$59+$AI$59 -> 23266972 | F59: =Assumptions!$B$70/(Assumptions!$B$20+Assumptions!$B$17+$B$59+$E$59+$O$58) -> 26.778553 | G59: =$C$59*(1-Assumptions!$B$71) -> 30.102798 | H59: =MIN($F$59,$G$59) -> 26.778553 | I59: =IF($F$59<=$G$59,"cap","discount") -> cap | J59: =Assumptions!$B$69/$H$59 -> 186716.59 | K59: =Assumptions!$B$74/(Assumptions!$B$20+Assumptions!$B$17+$B$59+$E$59+$J$59) -> 42.739338 | L59: =$C$59*(1-Assumptions!$B$75) -> 31.984223 | M59: =MIN($K$59,$L$59) -> 31.984223 | N59: =IF($K$59<=$L$59,"cap","discount") -> discount | O59: =Assumptions!$B$73/$M$59 -> 93796.243 | P59: =MAX(Assumptions!$B$4,(Assumptions!$B$10*(Assumptions!$B$20+$E$59+Assumptions!$B$17+$J$59+$O$59+$D$59)-Assumptions!$B$17)/(1-Assumptions!$B$10)) -> 587882.23 | Q59: =Assumptions!$B$20+$E$59+Assumptions!$B$17+$P$59+$J$59+$O$59+$D$59 -> 38327302 | R59: =IF($C$59<Assumptions!$B$37,Assumptions!$B$37*(Assumptions!$B$21+Assumptions!$B$22/Assumptions!$B$37)/(Assumptions!$B$21+Assumptions!$B$22/$C$59),Assumptions!$B$37) -> 1 | S59: =Assumptions!$B$38/$R$59 -> 1 | T59: =Assumptions!$B$39*$S$59 -> 5000000 | U59: =IF($C$59<Assumptions!$B$42,Assumptions!$B$42*(Assumptions!$B$21+Assumptions!$B$22/Assumptions!$B$42)/(Assumptions!$B$21+Assumptions!$B$22/$C$59),Assumptions!$B$42) -> 3 | V59: =Assumptions!$B$43/$U$59 -> 1 | W59: =Assumptions!$B$44*$V$59 -> 5000000 | X59: =IF($C$59<Assumptions!$B$47,Assumptions!$B$47*(Assumptions!$B$21+Assumptions!$B$22/Assumptions!$B$47)/(Assumptions!$B$21+Assumptions!$B$22/$C$59),Assumptions!$B$47) -> 10 | Y59: =Assumptions!$B$48/$X$59 -> 1 | Z59: =Assumptions!$B$49*$Y$59 -> 3000000 | AA59: =IF($C$59<Assumptions!$B$52,Assumptions!$B$52*(Assumptions!$B$21+Assumptions!$B$22/Assumptions!$B$52)/(Assumptions!$B$21+Assumptions!$B$22/$C$59),Assumptions!$B$52) -> 25 | AB59: =Assumptions!$B$53/$AA$59 -> 1 | AC59: =Assumptions!$B$54*$AB$59 -> 2400000 | AD59: =IF($C$59<Assumptions!$B$57,Assumptions!$B$57*(Assumptions!$B$21+Assumptions!$B$22/Assumptions!$B$57)/(Assumptions!$B$21+Assumptions!$B$22/$C$59),Assumptions!$B$57) -> 57.681736 | AE59: =Assumptions!$B$58/$AD$59 -> 1.0401906 | AF59: =Assumptions!$B$59*$AE$59 -> 1733651.4 | AG59: =IF($C$59<Assumptions!$B$62,Assumptions!$B$62*(Assumptions!$B$21+Assumptions!$B$22/Assumptions!$B$62)/(Assumptions!$B$21+Assumptions!$B$22/$C$59),Assumptions!$B$62) -> 48.912626 | AH59: =Assumptions!$B$63/$AG$59 -> 1.0050229 | AI59: =Assumptions!$B$64*$AH$59 -> 6133320.3
A60: =ROW()-ROW($A$41)+Assumptions!$B$4 -> 19 | B60: =$P$59 -> 587882.23 | C60: =Assumptions!$B$6/(Assumptions!$B$16+$B$60) -> 37.628498 | D60: =Assumptions!$B$7/$C$60 -> 797268.07 | E60: =$T$60+$W$60+$Z$60+$AC$60+$AF$60+$AI$60 -> 23266972 | F60: =Assumptions!$B$70/(Assumptions!$B$20+Assumptions!$B$17+$B$60+$E$60+$O$59) -> 26.778553 | G60: =$C$60*(1-Assumptions!$B$71) -> 30.102798 | H60: =MIN($F$60,$G$60) -> 26.778553 | I60: =IF($F$60<=$G$60,"cap","discount") -> cap | J60: =Assumptions!$B$69/$H$60 -> 186716.59 | K60: =Assumptions!$B$74/(Assumptions!$B$20+Assumptions!$B$17+$B$60+$E$60+$J$60) -> 42.739338 | L60: =$C$60*(1-Assumptions!$B$75) -> 31.984223 | M60: =MIN($K$60,$L$60) -> 31.984223 | N60: =IF($K$60<=$L$60,"cap","discount") -> discount | O60: =Assumptions!$B$73/$M$60 -> 93796.243 | P60: =MAX(Assumptions!$B$4,(Assumptions!$B$10*(Assumptions!$B$20+$E$60+Assumptions!$B$17+$J$60+$O$60+$D$60)-Assumptions!$B$17)/(1-Assumptions!$B$10)) -> 587882.23 | Q60: =Assumptions!$B$20+$E$60+Assumptions!$B$17+$P$60+$J$60+$O$60+$D$60 -> 38327302 | R60: =IF($C$60<Assumptions!$B$37,Assumptions!$B$37*(Assumptions!$B$21+Assumptions!$B$22/Assumptions!$B$37)/(Assumptions!$B$21+Assumptions!$B$22/$C$60),Assumptions!$B$37) -> 1 | S60: =Assumptions!$B$38/$R$60 -> 1 | T60: =Assumptions!$B$39*$S$60 -> 5000000 | U60: =IF($C$60<Assumptions!$B$42,Assumptions!$B$42*(Assumptions!$B$21+Assumptions!$B$22/Assumptions!$B$42)/(Assumptions!$B$21+Assumptions!$B$22/$C$60),Assumptions!$B$42) -> 3 | V60: =Assumptions!$B$43/$U$60 -> 1 | W60: =Assumptions!$B$44*$V$60 -> 5000000 | X60: =IF($C$60<Assumptions!$B$47,Assumptions!$B$47*(Assumptions!$B$21+Assumptions!$B$22/Assumptions!$B$47)/(Assumptions!$B$21+Assumptions!$B$22/$C$60),Assumptions!$B$47) -> 10 | Y60: =Assumptions!$B$48/$X$60 -> 1 | Z60: =Assumptions!$B$49*$Y$60 -> 3000000 | AA60: =IF($C$60<Assumptions!$B$52,Assumptions!$B$52*(Assumptions!$B$21+Assumptions!$B$22/Assumptions!$B$52)/(Assumptions!$B$21+Assumptions!$B$22/$C$60),Assumptions!$B$52) -> 25 | AB60: =Assumptions!$B$53/$AA$60 -> 1 | AC60: =Assumptions!$B$54*$AB$60 -> 2400000 | AD60: =IF($C$60<Assumptions!$B$57,Assumptions!$B$57*(Assumptions!$B$21+Assumptions!$B$22/Assumptions!$B$57)/(Assumptions!$B$21+Assumptions!$B$22/$C$60),Assumptions!$B$57) -> 57.681736 | AE60: =Assumptions!$B$58/$AD$60 -> 1.0401906 | AF60: =Assumptions!$B$59*$AE$60 -> 1733651.4 | AG60: =IF($C$60<Assumptions!$B$62,Assumptions!$B$62*(Assumptions!$B$21+Assumptions!$B$22/Assumptions!$B$62)/(Assumptions!$B$21+Assumptions!$B$22/$C$60),Assumptions!$B$62) -> 48.912626 | AH60: =Assumptions!$B$63/$AG$60 -> 1.0050229 | AI60: =Assumptions!$B$64*$AH$60 -> 6133320.3
A61: =ROW()-ROW($A$41)+Assumptions!$B$4 -> 20 | B61: =$P$60 -> 587882.23 | C61: =Assumptions!$B$6/(Assumptions!$B$16+$B$61) -> 37.628498 | D61: =Assumptions!$B$7/$C$61 -> 797268.07 | E61: =$T$61+$W$61+$Z$61+$AC$61+$AF$61+$AI$61 -> 23266972 | F61: =Assumptions!$B$70/(Assumptions!$B$20+Assumptions!$B$17+$B$61+$E$61+$O$60) -> 26.778553 | G61: =$C$61*(1-Assumptions!$B$71) -> 30.102798 | H61: =MIN($F$61,$G$61) -> 26.778553 | I61: =IF($F$61<=$G$61,"cap","discount") -> cap | J61: =Assumptions!$B$69/$H$61 -> 186716.59 | K61: =Assumptions!$B$74/(Assumptions!$B$20+Assumptions!$B$17+$B$61+$E$61+$J$61) -> 42.739338 | L61: =$C$61*(1-Assumptions!$B$75) -> 31.984223 | M61: =MIN($K$61,$L$61) -> 31.984223 | N61: =IF($K$61<=$L$61,"cap","discount") -> discount | O61: =Assumptions!$B$73/$M$61 -> 93796.243 | P61: =MAX(Assumptions!$B$4,(Assumptions!$B$10*(Assumptions!$B$20+$E$61+Assumptions!$B$17+$J$61+$O$61+$D$61)-Assumptions!$B$17)/(1-Assumptions!$B$10)) -> 587882.23 | Q61: =Assumptions!$B$20+$E$61+Assumptions!$B$17+$P$61+$J$61+$O$61+$D$61 -> 38327302 | R61: =IF($C$61<Assumptions!$B$37,Assumptions!$B$37*(Assumptions!$B$21+Assumptions!$B$22/Assumptions!$B$37)/(Assumptions!$B$21+Assumptions!$B$22/$C$61),Assumptions!$B$37) -> 1 | S61: =Assumptions!$B$38/$R$61 -> 1 | T61: =Assumptions!$B$39*$S$61 -> 5000000 | U61: =IF($C$61<Assumptions!$B$42,Assumptions!$B$42*(Assumptions!$B$21+Assumptions!$B$22/Assumptions!$B$42)/(Assumptions!$B$21+Assumptions!$B$22/$C$61),Assumptions!$B$42) -> 3 | V61: =Assumptions!$B$43/$U$61 -> 1 | W61: =Assumptions!$B$44*$V$61 -> 5000000 | X61: =IF($C$61<Assumptions!$B$47,Assumptions!$B$47*(Assumptions!$B$21+Assumptions!$B$22/Assumptions!$B$47)/(Assumptions!$B$21+Assumptions!$B$22/$C$61),Assumptions!$B$47) -> 10 | Y61: =Assumptions!$B$48/$X$61 -> 1 | Z61: =Assumptions!$B$49*$Y$61 -> 3000000 | AA61: =IF($C$61<Assumptions!$B$52,Assumptions!$B$52*(Assumptions!$B$21+Assumptions!$B$22/Assumptions!$B$52)/(Assumptions!$B$21+Assumptions!$B$22/$C$61),Assumptions!$B$52) -> 25 | AB61: =Assumptions!$B$53/$AA$61 -> 1 | AC61: =Assumptions!$B$54*$AB$61 -> 2400000 | AD61: =IF($C$61<Assumptions!$B$57,Assumptions!$B$57*(Assumptions!$B$21+Assumptions!$B$22/Assumptions!$B$57)/(Assumptions!$B$21+Assumptions!$B$22/$C$61),Assumptions!$B$57) -> 57.681736 | AE61: =Assumptions!$B$58/$AD$61 -> 1.0401906 | AF61: =Assumptions!$B$59*$AE$61 -> 1733651.4 | AG61: =IF($C$61<Assumptions!$B$62,Assumptions!$B$62*(Assumptions!$B$21+Assumptions!$B$22/Assumptions!$B$62)/(Assumptions!$B$21+Assumptions!$B$22/$C$61),Assumptions!$B$62) -> 48.912626 | AH61: =Assumptions!$B$63/$AG$61 -> 1.0050229 | AI61: =Assumptions!$B$64*$AH$61 -> 6133320.3
A62: =ROW()-ROW($A$41)+Assumptions!$B$4 -> 21 | B62: =$P$61 -> 587882.23 | C62: =Assumptions!$B$6/(Assumptions!$B$16+$B$62) -> 37.628498 | D62: =Assumptions!$B$7/$C$62 -> 797268.07 | E62: =$T$62+$W$62+$Z$62+$AC$62+$AF$62+$AI$62 -> 23266972 | F62: =Assumptions!$B$70/(Assumptions!$B$20+Assumptions!$B$17+$B$62+$E$62+$O$61) -> 26.778553 | G62: =$C$62*(1-Assumptions!$B$71) -> 30.102798 | H62: =MIN($F$62,$G$62) -> 26.778553 | I62: =IF($F$62<=$G$62,"cap","discount") -> cap | J62: =Assumptions!$B$69/$H$62 -> 186716.59 | K62: =Assumptions!$B$74/(Assumptions!$B$20+Assumptions!$B$17+$B$62+$E$62+$J$62) -> 42.739338 | L62: =$C$62*(1-Assumptions!$B$75) -> 31.984223 | M62: =MIN($K$62,$L$62) -> 31.984223 | N62: =IF($K$62<=$L$62,"cap","discount") -> discount | O62: =Assumptions!$B$73/$M$62 -> 93796.243 | P62: =MAX(Assumptions!$B$4,(Assumptions!$B$10*(Assumptions!$B$20+$E$62+Assumptions!$B$17+$J$62+$O$62+$D$62)-Assumptions!$B$17)/(1-Assumptions!$B$10)) -> 587882.23 | Q62: =Assumptions!$B$20+$E$62+Assumptions!$B$17+$P$62+$J$62+$O$62+$D$62 -> 38327302 | R62: =IF($C$62<Assumptions!$B$37,Assumptions!$B$37*(Assumptions!$B$21+Assumptions!$B$22/Assumptions!$B$37)/(Assumptions!$B$21+Assumptions!$B$22/$C$62),Assumptions!$B$37) -> 1 | S62: =Assumptions!$B$38/$R$62 -> 1 | T62: =Assumptions!$B$39*$S$62 -> 5000000 | U62: =IF($C$62<Assumptions!$B$42,Assumptions!$B$42*(Assumptions!$B$21+Assumptions!$B$22/Assumptions!$B$42)/(Assumptions!$B$21+Assumptions!$B$22/$C$62),Assumptions!$B$42) -> 3 | V62: =Assumptions!$B$43/$U$62 -> 1 | W62: =Assumptions!$B$44*$V$62 -> 5000000 | X62: =IF($C$62<Assumptions!$B$47,Assumptions!$B$47*(Assumptions!$B$21+Assumptions!$B$22/Assumptions!$B$47)/(Assumptions!$B$21+Assumptions!$B$22/$C$62),Assumptions!$B$47) -> 10 | Y62: =Assumptions!$B$48/$X$62 -> 1 | Z62: =Assumptions!$B$49*$Y$62 -> 3000000 | AA62: =IF($C$62<Assumptions!$B$52,Assumptions!$B$52*(Assumptions!$B$21+Assumptions!$B$22/Assumptions!$B$52)/(Assumptions!$B$21+Assumptions!$B$22/$C$62),Assumptions!$B$52) -> 25 | AB62: =Assumptions!$B$53/$AA$62 -> 1 | AC62: =Assumptions!$B$54*$AB$62 -> 2400000 | AD62: =IF($C$62<Assumptions!$B$57,Assumptions!$B$57*(Assumptions!$B$21+Assumptions!$B$22/Assumptions!$B$57)/(Assumptions!$B$21+Assumptions!$B$22/$C$62),Assumptions!$B$57) -> 57.681736 | AE62: =Assumptions!$B$58/$AD$62 -> 1.0401906 | AF62: =Assumptions!$B$59*$AE$62 -> 1733651.4 | AG62: =IF($C$62<Assumptions!$B$62,Assumptions!$B$62*(Assumptions!$B$21+Assumptions!$B$22/Assumptions!$B$62)/(Assumptions!$B$21+Assumptions!$B$22/$C$62),Assumptions!$B$62) -> 48.912626 | AH62: =Assumptions!$B$63/$AG$62 -> 1.0050229 | AI62: =Assumptions!$B$64*$AH$62 -> 6133320.3
A63: =ROW()-ROW($A$41)+Assumptions!$B$4 -> 22 | B63: =$P$62 -> 587882.23 | C63: =Assumptions!$B$6/(Assumptions!$B$16+$B$63) -> 37.628498 | D63: =Assumptions!$B$7/$C$63 -> 797268.07 | E63: =$T$63+$W$63+$Z$63+$AC$63+$AF$63+$AI$63 -> 23266972 | F63: =Assumptions!$B$70/(Assumptions!$B$20+Assumptions!$B$17+$B$63+$E$63+$O$62) -> 26.778553 | G63: =$C$63*(1-Assumptions!$B$71) -> 30.102798 | H63: =MIN($F$63,$G$63) -> 26.778553 | I63: =IF($F$63<=$G$63,"cap","discount") -> cap | J63: =Assumptions!$B$69/$H$63 -> 186716.59 | K63: =Assumptions!$B$74/(Assumptions!$B$20+Assumptions!$B$17+$B$63+$E$63+$J$63) -> 42.739338 | L63: =$C$63*(1-Assumptions!$B$75) -> 31.984223 | M63: =MIN($K$63,$L$63) -> 31.984223 | N63: =IF($K$63<=$L$63,"cap","discount") -> discount | O63: =Assumptions!$B$73/$M$63 -> 93796.243 | P63: =MAX(Assumptions!$B$4,(Assumptions!$B$10*(Assumptions!$B$20+$E$63+Assumptions!$B$17+$J$63+$O$63+$D$63)-Assumptions!$B$17)/(1-Assumptions!$B$10)) -> 587882.23 | Q63: =Assumptions!$B$20+$E$63+Assumptions!$B$17+$P$63+$J$63+$O$63+$D$63 -> 38327302 | R63: =IF($C$63<Assumptions!$B$37,Assumptions!$B$37*(Assumptions!$B$21+Assumptions!$B$22/Assumptions!$B$37)/(Assumptions!$B$21+Assumptions!$B$22/$C$63),Assumptions!$B$37) -> 1 | S63: =Assumptions!$B$38/$R$63 -> 1 | T63: =Assumptions!$B$39*$S$63 -> 5000000 | U63: =IF($C$63<Assumptions!$B$42,Assumptions!$B$42*(Assumptions!$B$21+Assumptions!$B$22/Assumptions!$B$42)/(Assumptions!$B$21+Assumptions!$B$22/$C$63),Assumptions!$B$42) -> 3 | V63: =Assumptions!$B$43/$U$63 -> 1 | W63: =Assumptions!$B$44*$V$63 -> 5000000 | X63: =IF($C$63<Assumptions!$B$47,Assumptions!$B$47*(Assumptions!$B$21+Assumptions!$B$22/Assumptions!$B$47)/(Assumptions!$B$21+Assumptions!$B$22/$C$63),Assumptions!$B$47) -> 10 | Y63: =Assumptions!$B$48/$X$63 -> 1 | Z63: =Assumptions!$B$49*$Y$63 -> 3000000 | AA63: =IF($C$63<Assumptions!$B$52,Assumptions!$B$52*(Assumptions!$B$21+Assumptions!$B$22/Assumptions!$B$52)/(Assumptions!$B$21+Assumptions!$B$22/$C$63),Assumptions!$B$52) -> 25 | AB63: =Assumptions!$B$53/$AA$63 -> 1 | AC63: =Assumptions!$B$54*$AB$63 -> 2400000 | AD63: =IF($C$63<Assumptions!$B$57,Assumptions!$B$57*(Assumptions!$B$21+Assumptions!$B$22/Assumptions!$B$57)/(Assumptions!$B$21+Assumptions!$B$22/$C$63),Assumptions!$B$57) -> 57.681736 | AE63: =Assumptions!$B$58/$AD$63 -> 1.0401906 | AF63: =Assumptions!$B$59*$AE$63 -> 1733651.4 | AG63: =IF($C$63<Assumptions!$B$62,Assumptions!$B$62*(Assumptions!$B$21+Assumptions!$B$22/Assumptions!$B$62)/(Assumptions!$B$21+Assumptions!$B$22/$C$63),Assumptions!$B$62) -> 48.912626 | AH63: =Assumptions!$B$63/$AG$63 -> 1.0050229 | AI63: =Assumptions!$B$64*$AH$63 -> 6133320.3
A64: =ROW()-ROW($A$41)+Assumptions!$B$4 -> 23 | B64: =$P$63 -> 587882.23 | C64: =Assumptions!$B$6/(Assumptions!$B$16+$B$64) -> 37.628498 | D64: =Assumptions!$B$7/$C$64 -> 797268.07 | E64: =$T$64+$W$64+$Z$64+$AC$64+$AF$64+$AI$64 -> 23266972 | F64: =Assumptions!$B$70/(Assumptions!$B$20+Assumptions!$B$17+$B$64+$E$64+$O$63) -> 26.778553 | G64: =$C$64*(1-Assumptions!$B$71) -> 30.102798 | H64: =MIN($F$64,$G$64) -> 26.778553 | I64: =IF($F$64<=$G$64,"cap","discount") -> cap | J64: =Assumptions!$B$69/$H$64 -> 186716.59 | K64: =Assumptions!$B$74/(Assumptions!$B$20+Assumptions!$B$17+$B$64+$E$64+$J$64) -> 42.739338 | L64: =$C$64*(1-Assumptions!$B$75) -> 31.984223 | M64: =MIN($K$64,$L$64) -> 31.984223 | N64: =IF($K$64<=$L$64,"cap","discount") -> discount | O64: =Assumptions!$B$73/$M$64 -> 93796.243 | P64: =MAX(Assumptions!$B$4,(Assumptions!$B$10*(Assumptions!$B$20+$E$64+Assumptions!$B$17+$J$64+$O$64+$D$64)-Assumptions!$B$17)/(1-Assumptions!$B$10)) -> 587882.23 | Q64: =Assumptions!$B$20+$E$64+Assumptions!$B$17+$P$64+$J$64+$O$64+$D$64 -> 38327302 | R64: =IF($C$64<Assumptions!$B$37,Assumptions!$B$37*(Assumptions!$B$21+Assumptions!$B$22/Assumptions!$B$37)/(Assumptions!$B$21+Assumptions!$B$22/$C$64),Assumptions!$B$37) -> 1 | S64: =Assumptions!$B$38/$R$64 -> 1 | T64: =Assumptions!$B$39*$S$64 -> 5000000 | U64: =IF($C$64<Assumptions!$B$42,Assumptions!$B$42*(Assumptions!$B$21+Assumptions!$B$22/Assumptions!$B$42)/(Assumptions!$B$21+Assumptions!$B$22/$C$64),Assumptions!$B$42) -> 3 | V64: =Assumptions!$B$43/$U$64 -> 1 | W64: =Assumptions!$B$44*$V$64 -> 5000000 | X64: =IF($C$64<Assumptions!$B$47,Assumptions!$B$47*(Assumptions!$B$21+Assumptions!$B$22/Assumptions!$B$47)/(Assumptions!$B$21+Assumptions!$B$22/$C$64),Assumptions!$B$47) -> 10 | Y64: =Assumptions!$B$48/$X$64 -> 1 | Z64: =Assumptions!$B$49*$Y$64 -> 3000000 | AA64: =IF($C$64<Assumptions!$B$52,Assumptions!$B$52*(Assumptions!$B$21+Assumptions!$B$22/Assumptions!$B$52)/(Assumptions!$B$21+Assumptions!$B$22/$C$64),Assumptions!$B$52) -> 25 | AB64: =Assumptions!$B$53/$AA$64 -> 1 | AC64: =Assumptions!$B$54*$AB$64 -> 2400000 | AD64: =IF($C$64<Assumptions!$B$57,Assumptions!$B$57*(Assumptions!$B$21+Assumptions!$B$22/Assumptions!$B$57)/(Assumptions!$B$21+Assumptions!$B$22/$C$64),Assumptions!$B$57) -> 57.681736 | AE64: =Assumptions!$B$58/$AD$64 -> 1.0401906 | AF64: =Assumptions!$B$59*$AE$64 -> 1733651.4 | AG64: =IF($C$64<Assumptions!$B$62,Assumptions!$B$62*(Assumptions!$B$21+Assumptions!$B$22/Assumptions!$B$62)/(Assumptions!$B$21+Assumptions!$B$22/$C$64),Assumptions!$B$62) -> 48.912626 | AH64: =Assumptions!$B$63/$AG$64 -> 1.0050229 | AI64: =Assumptions!$B$64*$AH$64 -> 6133320.3
A65: =ROW()-ROW($A$41)+Assumptions!$B$4 -> 24 | B65: =$P$64 -> 587882.23 | C65: =Assumptions!$B$6/(Assumptions!$B$16+$B$65) -> 37.628498 | D65: =Assumptions!$B$7/$C$65 -> 797268.07 | E65: =$T$65+$W$65+$Z$65+$AC$65+$AF$65+$AI$65 -> 23266972 | F65: =Assumptions!$B$70/(Assumptions!$B$20+Assumptions!$B$17+$B$65+$E$65+$O$64) -> 26.778553 | G65: =$C$65*(1-Assumptions!$B$71) -> 30.102798 | H65: =MIN($F$65,$G$65) -> 26.778553 | I65: =IF($F$65<=$G$65,"cap","discount") -> cap | J65: =Assumptions!$B$69/$H$65 -> 186716.59 | K65: =Assumptions!$B$74/(Assumptions!$B$20+Assumptions!$B$17+$B$65+$E$65+$J$65) -> 42.739338 | L65: =$C$65*(1-Assumptions!$B$75) -> 31.984223 | M65: =MIN($K$65,$L$65) -> 31.984223 | N65: =IF($K$65<=$L$65,"cap","discount") -> discount | O65: =Assumptions!$B$73/$M$65 -> 93796.243 | P65: =MAX(Assumptions!$B$4,(Assumptions!$B$10*(Assumptions!$B$20+$E$65+Assumptions!$B$17+$J$65+$O$65+$D$65)-Assumptions!$B$17)/(1-Assumptions!$B$10)) -> 587882.23 | Q65: =Assumptions!$B$20+$E$65+Assumptions!$B$17+$P$65+$J$65+$O$65+$D$65 -> 38327302 | R65: =IF($C$65<Assumptions!$B$37,Assumptions!$B$37*(Assumptions!$B$21+Assumptions!$B$22/Assumptions!$B$37)/(Assumptions!$B$21+Assumptions!$B$22/$C$65),Assumptions!$B$37) -> 1 | S65: =Assumptions!$B$38/$R$65 -> 1 | T65: =Assumptions!$B$39*$S$65 -> 5000000 | U65: =IF($C$65<Assumptions!$B$42,Assumptions!$B$42*(Assumptions!$B$21+Assumptions!$B$22/Assumptions!$B$42)/(Assumptions!$B$21+Assumptions!$B$22/$C$65),Assumptions!$B$42) -> 3 | V65: =Assumptions!$B$43/$U$65 -> 1 | W65: =Assumptions!$B$44*$V$65 -> 5000000 | X65: =IF($C$65<Assumptions!$B$47,Assumptions!$B$47*(Assumptions!$B$21+Assumptions!$B$22/Assumptions!$B$47)/(Assumptions!$B$21+Assumptions!$B$22/$C$65),Assumptions!$B$47) -> 10 | Y65: =Assumptions!$B$48/$X$65 -> 1 | Z65: =Assumptions!$B$49*$Y$65 -> 3000000 | AA65: =IF($C$65<Assumptions!$B$52,Assumptions!$B$52*(Assumptions!$B$21+Assumptions!$B$22/Assumptions!$B$52)/(Assumptions!$B$21+Assumptions!$B$22/$C$65),Assumptions!$B$52) -> 25 | AB65: =Assumptions!$B$53/$AA$65 -> 1 | AC65: =Assumptions!$B$54*$AB$65 -> 2400000 | AD65: =IF($C$65<Assumptions!$B$57,Assumptions!$B$57*(Assumptions!$B$21+Assumptions!$B$22/Assumptions!$B$57)/(Assumptions!$B$21+Assumptions!$B$22/$C$65),Assumptions!$B$57) -> 57.681736 | AE65: =Assumptions!$B$58/$AD$65 -> 1.0401906 | AF65: =Assumptions!$B$59*$AE$65 -> 1733651.4 | AG65: =IF($C$65<Assumptions!$B$62,Assumptions!$B$62*(Assumptions!$B$21+Assumptions!$B$22/Assumptions!$B$62)/(Assumptions!$B$21+Assumptions!$B$22/$C$65),Assumptions!$B$62) -> 48.912626 | AH65: =Assumptions!$B$63/$AG$65 -> 1.0050229 | AI65: =Assumptions!$B$64*$AH$65 -> 6133320.3
A66: =ROW()-ROW($A$41)+Assumptions!$B$4 -> 25 | B66: =$P$65 -> 587882.23 | C66: =Assumptions!$B$6/(Assumptions!$B$16+$B$66) -> 37.628498 | D66: =Assumptions!$B$7/$C$66 -> 797268.07 | E66: =$T$66+$W$66+$Z$66+$AC$66+$AF$66+$AI$66 -> 23266972 | F66: =Assumptions!$B$70/(Assumptions!$B$20+Assumptions!$B$17+$B$66+$E$66+$O$65) -> 26.778553 | G66: =$C$66*(1-Assumptions!$B$71) -> 30.102798 | H66: =MIN($F$66,$G$66) -> 26.778553 | I66: =IF($F$66<=$G$66,"cap","discount") -> cap | J66: =Assumptions!$B$69/$H$66 -> 186716.59 | K66: =Assumptions!$B$74/(Assumptions!$B$20+Assumptions!$B$17+$B$66+$E$66+$J$66) -> 42.739338 | L66: =$C$66*(1-Assumptions!$B$75) -> 31.984223 | M66: =MIN($K$66,$L$66) -> 31.984223 | N66: =IF($K$66<=$L$66,"cap","discount") -> discount | O66: =Assumptions!$B$73/$M$66 -> 93796.243 | P66: =MAX(Assumptions!$B$4,(Assumptions!$B$10*(Assumptions!$B$20+$E$66+Assumptions!$B$17+$J$66+$O$66+$D$66)-Assumptions!$B$17)/(1-Assumptions!$B$10)) -> 587882.23 | Q66: =Assumptions!$B$20+$E$66+Assumptions!$B$17+$P$66+$J$66+$O$66+$D$66 -> 38327302 | R66: =IF($C$66<Assumptions!$B$37,Assumptions!$B$37*(Assumptions!$B$21+Assumptions!$B$22/Assumptions!$B$37)/(Assumptions!$B$21+Assumptions!$B$22/$C$66),Assumptions!$B$37) -> 1 | S66: =Assumptions!$B$38/$R$66 -> 1 | T66: =Assumptions!$B$39*$S$66 -> 5000000 | U66: =IF($C$66<Assumptions!$B$42,Assumptions!$B$42*(Assumptions!$B$21+Assumptions!$B$22/Assumptions!$B$42)/(Assumptions!$B$21+Assumptions!$B$22/$C$66),Assumptions!$B$42) -> 3 | V66: =Assumptions!$B$43/$U$66 -> 1 | W66: =Assumptions!$B$44*$V$66 -> 5000000 | X66: =IF($C$66<Assumptions!$B$47,Assumptions!$B$47*(Assumptions!$B$21+Assumptions!$B$22/Assumptions!$B$47)/(Assumptions!$B$21+Assumptions!$B$22/$C$66),Assumptions!$B$47) -> 10 | Y66: =Assumptions!$B$48/$X$66 -> 1 | Z66: =Assumptions!$B$49*$Y$66 -> 3000000 | AA66: =IF($C$66<Assumptions!$B$52,Assumptions!$B$52*(Assumptions!$B$21+Assumptions!$B$22/Assumptions!$B$52)/(Assumptions!$B$21+Assumptions!$B$22/$C$66),Assumptions!$B$52) -> 25 | AB66: =Assumptions!$B$53/$AA$66 -> 1 | AC66: =Assumptions!$B$54*$AB$66 -> 2400000 | AD66: =IF($C$66<Assumptions!$B$57,Assumptions!$B$57*(Assumptions!$B$21+Assumptions!$B$22/Assumptions!$B$57)/(Assumptions!$B$21+Assumptions!$B$22/$C$66),Assumptions!$B$57) -> 57.681736 | AE66: =Assumptions!$B$58/$AD$66 -> 1.0401906 | AF66: =Assumptions!$B$59*$AE$66 -> 1733651.4 | AG66: =IF($C$66<Assumptions!$B$62,Assumptions!$B$62*(Assumptions!$B$21+Assumptions!$B$22/Assumptions!$B$62)/(Assumptions!$B$21+Assumptions!$B$22/$C$66),Assumptions!$B$62) -> 48.912626 | AH66: =Assumptions!$B$63/$AG$66 -> 1.0050229 | AI66: =Assumptions!$B$64*$AH$66 -> 6133320.3
