Workbook

Sheet Assumptions
A1: Kelvin Dynamics — Series F Analysis
A3: Round / Ownership Knobs
A4: Label | B4: Value | C4: Units | D4: Source
A5: Series F pre-money | B5: 1400000000 | C5: USD | D5: RoundTerms.series_f_pre_money_usd
A6: Primary raise | B6: 30000000 | C6: USD | D6: RoundTerms.series_f_primary_raise_usd
A7: Secondary raise | B7: 15000000 | C7: USD | D7: RoundTerms.series_f_secondary_raise_usd
A8: Tender PPS multiplier | B8: 0.85 | C8: fraction | D8: RoundTerms.series_f_tender_pps_multiplier
A9: ESOP refresh target % post-F FD | B9: 0.13 | C9: fraction | D9: RoundTerms.esop_refresh_target_post_f
A10: Our check size | B10: 10000000 | C10: USD | D10: RoundTerms.our_fund_check_usd
A11: F_LEAD primary check | B11: 20000000 | C11: USD | D11: RoundTerms.f_lead_primary_check_usd
A12: Option strike | B12: 1 | C12: USD | D12: RoundTerms.option_strike_usd
A13: Pre-F issued options | B13: 2500000 | C13: shares | D13: RoundTerms.pre_f_options_issued
A14: Pre-F unissued options | B14: 1894667 | C14: shares | D14: RoundTerms.pre_f_options_unissued
A15: Pre-F broad-based FD / WA A | B15: 36617961 | C15: shares | D15: RoundTerms.pre_f_fd_total
A16: Pre-F option pool | B16: =$B$13+$B$14 -> 4394667 | C16: shares | D16: issued + unissued
A17: Founder F1 common | B17: 4000000 | C17: shares | D17: Stakeholders.F1
A18: Founder F2 common | B18: 2500000 | C18: shares | D18: Stakeholders.F2
A19: Founder F3 common | B19: 1500000 | C19: shares | D19: Stakeholders.F3
A20: Founder common total | B20: =SUM($B$17:$B$19) -> 8000000 | C20: shares | D20: F1 + F2 + F3
A21: Employee RSA common total | B21: 1000000 | C21: shares | D21: Stakeholders.Employee RSA
A22: Common + RSAs total | B22: =$B$20+$B$21 -> 9000000 | C22: shares | D22: founders + employee RSAs
A23: Zero | B23: 0 | C23: constant | D23: model helper
A24: One | B24: 1 | C24: constant | D24: model helper
A28: Exit Values
A29: Exit # | B29: Value | C29: Units | D29: Source
A30: Exit 1 | B30: 700000000 | C30: USD | D30: RoundTerms.exit_value_1_usd
A31: Exit 2 | B31: 1200000000 | C31: USD | D31: RoundTerms.exit_value_2_usd
A32: Exit 3 | B32: 2000000000 | C32: USD | D32: RoundTerms.exit_value_3_usd
A33: Exit 4 | B33: 4000000000 | C33: USD | D33: RoundTerms.exit_value_4_usd
A34: Exit 5 | B34: 8000000000 | C34: USD | D34: RoundTerms.exit_value_5_usd
A37: Sensitivity Axes
A38: Axis | B38: Low | C38: Base | D38: High
A39: ESOP refresh target | B39: 0.11 | C39: 0.13 | D39: 0.15
A40: Series F pre-money | B40: 1200000000 | C40: 1400000000 | D40: 1800000000
A43: Return Solver Targets
A44: Multiple | B44: Target proceeds | C44: Source
A45: 3 | B45: =$B$10*$A$45 -> 30000000 | C45: RoundTerms.return_multiple_3x
A46: 4 | B46: =$B$10*$A$46 -> 40000000 | C46: RoundTerms.return_multiple_4x
A50: Prior Priced Securities / OCPs
A51: Class | B51: OCP-for-AD | C51: Original PPS | D51: Pre-F as-converted shares | E51: Invested USD | F51: LP type | G51: AD type | H51: WA B at OCP | I51: WA C at base F PPS
A52: Seed | B52: 1 | C52: 1 | D52: 5000000 | E52: 5000000 | F52: 1x non-participating with conversion election | G52: broad-based weighted-average | H52: =$B$6/B52 -> 30000000 | I52: =$B$6/$B$94 -> #VALUE!
A53: A | B53: 3 | C53: 3 | D53: 5000000 | E53: 15000000 | F53: 1x non-participating with conversion election | G53: broad-based weighted-average | H53: =$B$6/B53 -> 10000000 | I53: =$B$6/$B$94 -> #VALUE!
A54: B | B54: 10 | C54: 10 | D54: 3000000 | E54: 30000000 | F54: 1x non-participating with conversion election | G54: broad-based weighted-average | H54: =$B$6/B54 -> 3000000 | I54: =$B$6/$B$94 -> #VALUE!
A55: C | B55: 25 | C55: 25 | D55: 2400000 | E55: 60000000 | F55: 1x non-participating with conversion election | G55: broad-based weighted-average | H55: =$B$6/B55 -> 1200000 | I55: =$B$6/$B$94 -> #VALUE!
A56: D | B56: 58.118347 | C56: 60 | D56: 1720627 | E56: 100000000 | F56: 1x non-participating with conversion election | G56: broad-based weighted-average | H56: =$B$6/B56 -> 516188.12 | I56: =$B$6/$B$94 -> #VALUE!
A57: E | B57: 49.158311 | C57: 49.158311 | D57: 6102667 | E57: 300000000 | F57: 1x non-participating with conversion election | G57: broad-based weighted-average | H57: =$B$6/B57 -> 610273.2 | I57: =$B$6/$B$94 -> #VALUE!
A61: Convertible Notes
A62: Note | B62: Holder | C62: Principal | D62: Cap | E62: Discount | F62: Interest | G62: Source
A63: Note A | B63: NA1 | C63: 5000000 | D63: 1000000000 | E63: 0.2 | F63: 0 | G63: Notes
A64: Note B | B64: NB1 | C64: 3000000 | D64: 1600000000 | E64: 0.15 | F64: 0 | G64: Notes
A68: Stakeholder Source
A69: ID | B69: Role | C69: Common shares | D69: Preferred class | E69: Preferred shares | F69: Security class
A70: F1 | B70: Founder (CEO) | C70: 4000000 | E70: 0 | F70: Common
A71: F2 | B71: Founder (CTO) | C71: 2500000 | E71: 0 | F71: Common
A72: F3 | B72: Founder (Chief Scientist) | C72: 1500000 | E72: 0 | F72: Common
A73: E1 | B73: Employee RSA | C73: 100000 | E73: 0 | F73: Common
A74: E2 | B74: Employee RSA | C74: 100000 | E74: 0 | F74: Common
A75: E3 | B75: Employee RSA | C75: 100000 | E75: 0 | F75: Common
A76: E4 | B76: Employee RSA | C76: 100000 | E76: 0 | F76: Common
A77: E5 | B77: Employee RSA | C77: 100000 | E77: 0 | F77: Common
A78: E6 | B78: Employee RSA | C78: 100000 | E78: 0 | F78: Common
A79: E7 | B79: Employee RSA | C79: 100000 | E79: 0 | F79: Common
A80: E8 | B80: Employee RSA | C80: 100000 | E80: 0 | F80: Common
A81: E9 | B81: Employee RSA | C81: 100000 | E81: 0 | F81: Common
A82: E10 | B82: Employee RSA | C82: 100000 | E82: 0 | F82: Common
A83: SEED1 | B83: Seed preferred LP | C83: 0 | D83: Seed | E83: 5000000 | F83: Seed
A84: A1 | B84: Series A preferred LP | C84: 0 | D84: Series A | E84: 5000000 | F84: Series A
A85: B1 | B85: Series B preferred LP | C85: 0 | D85: Series B | E85: 3000000 | F85: Series B
A86: C1 | B86: Series C preferred LP | C86: 0 | D86: Series C | E86: 2400000 | F86: Series C
A87: D1 | B87: Series D preferred LP | C87: 0 | D87: Series D | E87: 1720627 | F87: Series D
A88: E1_INV | B88: Series E preferred LP | C88: 0 | D88: Series E | E88: 610267 | F88: Series E
A89: E2_INV | B89: Series E preferred LP | C89: 0 | D89: Series E | E89: 610267 | F89: Series E
A90: E3_INV | B90: Series E preferred LP | C90: 0 | D90: Series E | E90: 610267 | F90: Series E
A91: E4_INV | B91: Series E preferred LP | C91: 0 | D91: Series E | E91: 610267 | F91: Series E
A92: E5_INV | B92: Series E preferred LP | C92: 0 | D92: Series E | E92: 610267 | F92: Series E
A93: E6_INV | B93: Series E preferred LP | C93: 0 | D93: Series E | E93: 610267 | F93: Series E
A94: E7_INV | B94: Series E preferred LP | C94: 0 | D94: Series E | E94: 610267 | F94: Series E
... A97: E10_INV | B97: Series E preferred LP | C97: 0 | D97: Series E | E97: 610264 | F97: Series E
A98: NA1 | B98: Convertible Note A holder | C98: 0 | E98: 0 | F98: Common
A99: NB1 | B99: Convertible Note B holder | C99: 0 | E99: 0 | F99: Common
A100: F_LEAD | B100: Series F lead investor | C100: 0 | E100: 0 | F100: Common
A101: F_FUND | B101: Our fund (Series F primary) | C101: 0 | E101: 0 | F101: Common
A112: Downstream Labels
A113: Pro-Forma Cap Table | B113: Pro-Forma Cap Table
A114: Stakeholder | B114: Stakeholder
A115: Security Class | B115: Security Class
A116: Common Shares | B116: Common Shares
A117: Preferred Shares | B117: Preferred Shares
A118: As-Converted Shares | B118: As-Converted Shares
A119: Ownership % | B119: Ownership %
A120: AD Block | B120: AD Block
A121: Class | B121: Class
A122: F PPS < OCP? | B122: F PPS < OCP?
A123: OCP | B123: OCP
A124: New Conversion Price | B124: New Conversion Price
... A178: Infeasible | B178: Infeasible
A180: Base Case Fixed Point
A181: Pre-money | B181: =$B$5 -> 1400000000
A182: ESOP target | B182: =$B$9 -> 0.13
A185: Case | B185: Topup active | C185: Note A assumed | D185: Note B assumed | E185: S const | F185: S slope | G185: y candidate | H185: S excl notes/F | I185: Topup raw | J185: Note A shares | K185: Note B shares | L185: A cap PPS | M185: A disc PPS | N185: A branch valid | O185: B cap PPS | P185: B disc PPS | Q185: B branch valid | R185: Topup valid | S185: Trigger valid | T185: Case valid
...

Sheet Pro-Forma
A1: =Assumptions!$B$113 -> Pro-Forma Cap Table
A3: =Assumptions!$B$114 -> Stakeholder | B3: =Assumptions!$B$115 -> Security Class | C3: =Assumptions!$B$116 -> Common Shares | D3: =Assumptions!$B$117 -> Preferred Shares | E3: =Assumptions!$B$118 -> As-Converted Shares | F3: =Assumptions!$B$119 -> Ownership %
A4: =Assumptions!$A$70 -> F1 | B4: =Assumptions!$B$168 -> Common + RSAs | C4: =Assumptions!$B$17-Assumptions!$B$214*Assumptions!$B$17/Assumptions!$B$20 -> 3763442.7 | D4: =Assumptions!$B$23 -> 0 | E4: =C4 -> 3763442.7 | F4: =E4/Assumptions!$B$199 -> 0.098164695
A5: =Assumptions!$A$71 -> F2 | B5: =Assumptions!$B$168 -> Common + RSAs | C5: =Assumptions!$B$18-Assumptions!$B$214*Assumptions!$B$18/Assumptions!$B$20 -> 2352151.7 | D5: =Assumptions!$B$23 -> 0 | E5: =C5 -> 2352151.7 | F5: =E5/Assumptions!$B$199 -> 0.061352934
A6: =Assumptions!$A$72 -> F3 | B6: =Assumptions!$B$168 -> Common + RSAs | C6: =Assumptions!$B$19-Assumptions!$B$214*Assumptions!$B$19/Assumptions!$B$20 -> 1411291 | D6: =Assumptions!$B$23 -> 0 | E6: =C6 -> 1411291 | F6: =E6/Assumptions!$B$199 -> 0.036811761
A7: =Assumptions!$A$73 -> E1 | B7: =Assumptions!$B$168 -> Common + RSAs | C7: =Assumptions!$C$73 -> 100000 | D7: =Assumptions!$B$23 -> 0 | E7: =C7 -> 100000 | F7: =E7/Assumptions!$B$199 -> 0.0026083749
A8: =Assumptions!$A$74 -> E2 | B8: =Assumptions!$B$168 -> Common + RSAs | C8: =Assumptions!$C$74 -> 100000 | D8: =Assumptions!$B$23 -> 0 | E8: =C8 -> 100000 | F8: =E8/Assumptions!$B$199 -> 0.0026083749
A9: =Assumptions!$A$75 -> E3 | B9: =Assumptions!$B$168 -> Common + RSAs | C9: =Assumptions!$C$75 -> 100000 | D9: =Assumptions!$B$23 -> 0 | E9: =C9 -> 100000 | F9: =E9/Assumptions!$B$199 -> 0.0026083749
A10: =Assumptions!$A$76 -> E4 | B10: =Assumptions!$B$168 -> Common + RSAs | C10: =Assumptions!$C$76 -> 100000 | D10: =Assumptions!$B$23 -> 0 | E10: =C10 -> 100000 | F10: =E10/Assumptions!$B$199 -> 0.0026083749
A11: =Assumptions!$A$77 -> E5 | B11: =Assumptions!$B$168 -> Common + RSAs | C11: =Assumptions!$C$77 -> 100000 | D11: =Assumptions!$B$23 -> 0 | E11: =C11 -> 100000 | F11: =E11/Assumptions!$B$199 -> 0.0026083749
A12: =Assumptions!$A$78 -> E6 | B12: =Assumptions!$B$168 -> Common + RSAs | C12: =Assumptions!$C$78 -> 100000 | D12: =Assumptions!$B$23 -> 0 | E12: =C12 -> 100000 | F12: =E12/Assumptions!$B$199 -> 0.0026083749
A13: =Assumptions!$A$79 -> E7 | B13: =Assumptions!$B$168 -> Common + RSAs | C13: =Assumptions!$C$79 -> 100000 | D13: =Assumptions!$B$23 -> 0 | E13: =C13 -> 100000 | F13: =E13/Assumptions!$B$199 -> 0.0026083749
A14: =Assumptions!$A$80 -> E8 | B14: =Assumptions!$B$168 -> Common + RSAs | C14: =Assumptions!$C$80 -> 100000 | D14: =Assumptions!$B$23 -> 0 | E14: =C14 -> 100000 | F14: =E14/Assumptions!$B$199 -> 0.0026083749
A15: =Assumptions!$A$81 -> E9 | B15: =Assumptions!$B$168 -> Common + RSAs | C15: =Assumptions!$C$81 -> 100000 | D15: =Assumptions!$B$23 -> 0 | E15: =C15 -> 100000 | F15: =E15/Assumptions!$B$199 -> 0.0026083749
A16: =Assumptions!$A$82 -> E10 | B16: =Assumptions!$B$168 -> Common + RSAs | C16: =Assumptions!$C$82 -> 100000 | D16: =Assumptions!$B$23 -> 0 | E16: =C16 -> 100000 | F16: =E16/Assumptions!$B$199 -> 0.0026083749
A17: =Assumptions!$A$83 -> SEED1 | B17: =Assumptions!$A$221 -> Seed | C17: =Assumptions!$B$23 -> 0 | D17: =Assumptions!$E$83 -> 5000000 | E17: =Assumptions!$E$83*Assumptions!$E$221/5000000 -> 5000000 | F17: =E17/Assumptions!$B$199 -> 0.13041874
A18: =Assumptions!$A$84 -> A1 | B18: =Assumptions!$A$222 -> A | C18: =Assumptions!$B$23 -> 0 | D18: =Assumptions!$E$84 -> 5000000 | E18: =Assumptions!$E$84*Assumptions!$E$222/5000000 -> 5000000 | F18: =E18/Assumptions!$B$199 -> 0.13041874
A19: =Assumptions!$A$85 -> B1 | B19: =Assumptions!$A$223 -> B | C19: =Assumptions!$B$23 -> 0 | D19: =Assumptions!$E$85 -> 3000000 | E19: =Assumptions!$E$85*Assumptions!$E$223/3000000 -> 3000000 | F19: =E19/Assumptions!$B$199 -> 0.078251246
A20: =Assumptions!$A$86 -> C1 | B20: =Assumptions!$A$224 -> C | C20: =Assumptions!$B$23 -> 0 | D20: =Assumptions!$E$86 -> 2400000 | E20: =Assumptions!$E$86*Assumptions!$E$224/2400000 -> 2400000 | F20: =E20/Assumptions!$B$199 -> 0.062600997
A21: =Assumptions!$A$87 -> D1 | B21: =Assumptions!$A$225 -> D | C21: =Assumptions!$B$23 -> 0 | D21: =Assumptions!$E$87 -> 1720627 | E21: =Assumptions!$E$87*Assumptions!$E$225/1720627 -> 1733976.5 | F21: =E21/Assumptions!$B$199 -> 0.045228609
A22: =Assumptions!$A$88 -> E1_INV | B22: =Assumptions!$A$226 -> E | C22: =Assumptions!$B$23 -> 0 | D22: =Assumptions!$E$88 -> 610267 | E22: =Assumptions!$E$88*Assumptions!$E$226/6102667 -> 613447.51 | F22: =E22/Assumptions!$B$199 -> 0.016001011
A23: =Assumptions!$A$89 -> E2_INV | B23: =Assumptions!$A$226 -> E | C23: =Assumptions!$B$23 -> 0 | D23: =Assumptions!$E$89 -> 610267 | E23: =Assumptions!$E$89*Assumptions!$E$226/6102667 -> 613447.51 | F23: =E23/Assumptions!$B$199 -> 0.016001011
A24: =Assumptions!$A$90 -> E3_INV | B24: =Assumptions!$A$226 -> E | C24: =Assumptions!$B$23 -> 0 | D24: =Assumptions!$E$90 -> 610267 | E24: =Assumptions!$E$90*Assumptions!$E$226/6102667 -> 613447.51 | F24: =E24/Assumptions!$B$199 -> 0.016001011
A25: =Assumptions!$A$91 -> E4_INV | B25: =Assumptions!$A$226 -> E | C25: =Assumptions!$B$23 -> 0 | D25: =Assumptions!$E$91 -> 610267 | E25: =Assumptions!$E$91*Assumptions!$E$226/6102667 -> 613447.51 | F25: =E25/Assumptions!$B$199 -> 0.016001011
A26: =Assumptions!$A$92 -> E5_INV | B26: =Assumptions!$A$226 -> E | C26: =Assumptions!$B$23 -> 0 | D26: =Assumptions!$E$92 -> 610267 | E26: =Assumptions!$E$92*Assumptions!$E$226/6102667 -> 613447.51 | F26: =E26/Assumptions!$B$199 -> 0.016001011
A27: =Assumptions!$A$93 -> E6_INV | B27: =Assumptions!$A$226 -> E | C27: =Assumptions!$B$23 -> 0 | D27: =Assumptions!$E$93 -> 610267 | E27: =Assumptions!$E$93*Assumptions!$E$226/6102667 -> 613447.51 | F27: =E27/Assumptions!$B$199 -> 0.016001011
A28: =Assumptions!$A$94 -> E7_INV | B28: =Assumptions!$A$226 -> E | C28: =Assumptions!$B$23 -> 0 | D28: =Assumptions!$E$94 -> 610267 | E28: =Assumptions!$E$94*Assumptions!$E$226/6102667 -> 613447.51 | F28: =E28/Assumptions!$B$199 -> 0.016001011
A29: =Assumptions!$A$95 -> E8_INV | B29: =Assumptions!$A$226 -> E | C29: =Assumptions!$B$23 -> 0 | D29: =Assumptions!$E$95 -> 610267 | E29: =Assumptions!$E$95*Assumptions!$E$226/6102667 -> 613447.51 | F29: =E29/Assumptions!$B$199 -> 0.016001011
A30: =Assumptions!$A$96 -> E9_INV | B30: =Assumptions!$A$226 -> E | C30: =Assumptions!$B$23 -> 0 | D30: =Assumptions!$E$96 -> 610267 | E30: =Assumptions!$E$96*Assumptions!$E$226/6102667 -> 613447.51 | F30: =E30/Assumptions!$B$199 -> 0.016001011
A31: =Assumptions!$A$97 -> E10_INV | B31: =Assumptions!$A$226 -> E | C31: =Assumptions!$B$23 -> 0 | D31: =Assumptions!$E$97 -> 610264 | E31: =Assumptions!$E$97*Assumptions!$E$226/6102667 -> 613444.5 | F31: =E31/Assumptions!$B$199 -> 0.016000932
A32: =Assumptions!$A$98 -> NA1 | B32: =Assumptions!$A$63&" conversion" -> Note A conversion | C32: =Assumptions!$B$23 -> 0 | D32: =Assumptions!$B$23 -> 0 | E32: =Assumptions!$B$203 -> 186735.09 | F32: =E32/Assumptions!$B$199 -> 0.0048707511
A33: =Assumptions!$A$99 -> NB1 | B33: =Assumptions!$A$64&" conversion" -> Note B conversion | C33: =Assumptions!$B$23 -> 0 | D33: =Assumptions!$B$23 -> 0 | E33: =Assumptions!$B$204 -> 94622.906 | F33: =E33/Assumptions!$B$199 -> 0.0024681201
A34: =Assumptions!$A$100 -> F_LEAD | B34: =Assumptions!$B$171 -> Series F Lead Primary | C34: =Assumptions!$B$23 -> 0 | D34: =Assumptions!$B$215 -> 536196.47 | E34: =D34 -> 536196.47 | F34: =E34/Assumptions!$B$199 -> 0.013986014
A35: =Assumptions!$A$100 -> F_LEAD | B35: =Assumptions!$B$173 -> Secondary Common | C35: =Assumptions!$B$214 -> 473114.53 | D35: =Assumptions!$B$23 -> 0 | E35: =C35 -> 473114.53 | F35: =E35/Assumptions!$B$199 -> 0.012340601
A36: =Assumptions!$A$101 -> F_FUND | B36: =Assumptions!$B$172 -> Our Fund Primary | C36: =Assumptions!$B$23 -> 0 | D36: =Assumptions!$B$216 -> 268098.23 | E36: =D36 -> 268098.23 | F36: =E36/Assumptions!$B$199 -> 0.006993007
A37: =Assumptions!$B$174 -> Issued Options | B37: =Assumptions!$B$174 -> Issued Options | C37: =Assumptions!$B$23 -> 0 | D37: =Assumptions!$B$23 -> 0 | E37: =Assumptions!$B$13 -> 2500000 | F37: =E37/Assumptions!$B$199 -> 0.065209372
A38: =Assumptions!$B$170 -> Unissued Option Pool | B38: =Assumptions!$B$170 -> Unissued Option Pool | C38: =Assumptions!$B$23 -> 0 | D38: =Assumptions!$B$23 -> 0 | E38: =Assumptions!$B$14+Assumptions!$B$201 -> 2483946.2 | F38: =E38/Assumptions!$B$199 -> 0.064790628
A39: =Assumptions!$B$176 -> Total | E39: =SUM(E4:E38) -> 38338048 | F39: =SUM(F4:F38) -> 1
A42: =Assumptions!$B$120 -> AD Block
A43: =Assumptions!$B$121 -> Class | B43: =Assumptions!$B$122 -> F PPS < OCP? | C43: =Assumptions!$B$123 -> OCP | D43: =Assumptions!$B$124 -> New Conversion Price | E43: =Assumptions!$B$125 -> New Ratio | F43: =Assumptions!$B$118 -> As-Converted Shares | G43: =Assumptions!$B$126 -> WA A | H43: =Assumptions!$B$127 -> WA B | I43: =Assumptions!$B$128 -> WA C
A44: =Assumptions!$A$221 -> Seed | B44: =Assumptions!$B$221 -> FALSE | C44: =Assumptions!$B$52 -> 1 | D44: =Assumptions!$C$221 -> 1 | E44: =Assumptions!$D$221 -> 1 | F44: =Assumptions!$E$221 -> 5000000 | G44: =Assumptions!$B$15 -> 36617961 | H44: =Assumptions!$B$6/C44 -> 30000000 | I44: =Assumptions!$B$6/Assumptions!$B$197 -> 804294.7
A45: =Assumptions!$A$222 -> A | B45: =Assumptions!$B$222 -> FALSE | C45: =Assumptions!$B$53 -> 3 | D45: =Assumptions!$C$222 -> 3 | E45: =Assumptions!$D$222 -> 1 | F45: =Assumptions!$E$222 -> 5000000 | G45: =Assumptions!$B$15 -> 36617961 | H45: =Assumptions!$B$6/C45 -> 10000000 | I45: =Assumptions!$B$6/Assumptions!$B$197 -> 804294.7
A46: =Assumptions!$A$223 -> B | B46: =Assumptions!$B$223 -> FALSE | C46: =Assumptions!$B$54 -> 10 | D46: =Assumptions!$C$223 -> 10 | E46: =Assumptions!$D$223 -> 1 | F46: =Assumptions!$E$223 -> 3000000 | G46: =Assumptions!$B$15 -> 36617961 | H46: =Assumptions!$B$6/C46 -> 3000000 | I46: =Assumptions!$B$6/Assumptions!$B$197 -> 804294.7
A47: =Assumptions!$A$224 -> C | B47: =Assumptions!$B$224 -> FALSE | C47: =Assumptions!$B$55 -> 25 | D47: =Assumptions!$C$224 -> 25 | E47: =Assumptions!$D$224 -> 1 | F47: =Assumptions!$E$224 -> 2400000 | G47: =Assumptions!$B$15 -> 36617961 | H47: =Assumptions!$B$6/C47 -> 1200000 | I47: =Assumptions!$B$6/Assumptions!$B$197 -> 804294.7
A48: =Assumptions!$A$225 -> D | B48: =Assumptions!$B$225 -> TRUE | C48: =Assumptions!$B$56 -> 58.118347 | D48: =Assumptions!$C$225 -> 57.670905 | E48: =Assumptions!$D$225 -> 1.040386 | F48: =Assumptions!$E$225 -> 1733976.5 | G48: =Assumptions!$B$15 -> 36617961 | H48: =Assumptions!$B$6/C48 -> 516188.12 | I48: =Assumptions!$B$6/Assumptions!$B$197 -> 804294.7
A49: =Assumptions!$A$226 -> E | B49: =Assumptions!$B$226 -> TRUE | C49: =Assumptions!$B$57 -> 49.158311 | D49: =Assumptions!$C$226 -> 48.903442 | E49: =Assumptions!$D$226 -> 1.0052117 | F49: =Assumptions!$E$226 -> 6134472.1 | G49: =Assumptions!$B$15 -> 36617961 | H49: =Assumptions!$B$6/C49 -> 610273.2 | I49: =Assumptions!$B$6/Assumptions!$B$197 -> 804294.7
A52: =Assumptions!$B$129 -> Notes Block
A53: =Assumptions!$B$130 -> Note | B53: =Assumptions!$B$131 -> Cap-Implied PPS | C53: =Assumptions!$B$132 -> Discount-Implied PPS | D53: =Assumptions!$B$133 -> Conversion PPS | E53: =Assumptions!$B$134 -> Branch | F53: =Assumptions!$B$135 -> Shares Issued
A54: =Assumptions!$A$63 -> Note A | B54: =Assumptions!$B$207 -> 26.7759 | C54: =Assumptions!$B$208 -> 29.839809 | D54: =MIN(B54,C54) -> 26.7759 | E54: =IF(B54<=C54,"cap","discount") -> cap | F54: =Assumptions!$B$203 -> 186735.09
A55: =Assumptions!$A$64 -> Note B | B55: =Assumptions!$B$210 -> 42.736036 | C55: =Assumptions!$B$211 -> 31.704797 | D55: =MIN(B55,C55) -> 31.704797 | E55: =IF(B55<=C55,"cap","discount") -> discount | F55: =Assumptions!$B$204 -> 94622.906
A58: =Assumptions!$B$136 -> Tender Block
A59: =Assumptions!$B$139 -> Founder | B59: =Assumptions!$B$140 -> Founder Share-Out | C59: =Assumptions!$B$137 -> Tender PPS | D59: =Assumptions!$B$138 -> Tender Shares | E59: =Assumptions!$B$141 -> F_LEAD Secondary Holding
A60: =Assumptions!$A$70 -> F1 | B60: =Assumptions!$B$214*Assumptions!$B$17/Assumptions!$B$20 -> 236557.27 | C60: =Assumptions!$B$213 -> 31.704797 | D60: =Assumptions!$B$214 -> 473114.53 | E60: =Assumptions!$B$214 -> 473114.53
A61: =Assumptions!$A$71 -> F2 | B61: =Assumptions!$B$214*Assumptions!$B$18/Assumptions!$B$20 -> 147848.29 | C61: =Assumptions!$B$213 -> 31.704797 | D61: =Assumptions!$B$214 -> 473114.53 | E61: =Assumptions!$B$214 -> 473114.53
A62: =Assumptions!$A$72 -> F3 | B62: =Assumptions!$B$214*Assumptions!$B$19/Assumptions!$B$20 -> 88708.975 | C62: =Assumptions!$B$213 -> 31.704797 | D62: =Assumptions!$B$214 -> 473114.53 | E62: =Assumptions!$B$214 -> 473114.53

Sheet Waterfall
A1: =Assumptions!$B$142 -> Waterfall
B2: =Assumptions!$B$900 -> 700000000 | C2: =Assumptions!$B$900 -> 700000000 | D2: =Assumptions!$B$1060 -> 1200000000 | E2: =Assumptions!$B$1060 -> 1200000000 | F2: =Assumptions!$B$1220 -> 2000000000 | G2: =Assumptions!$B$1220 -> 2000000000 | H2: =Assumptions!$B$1380 -> 4000000000 | I2: =Assumptions!$B$1380 -> 4000000000 | J2: =Assumptions!$B$1540 -> 8000000000 | K2: =Assumptions!$B$1540 -> 8000000000
A3: =Assumptions!$B$121 -> Class | B3: =Assumptions!$B$143 -> Election | C3: =Assumptions!$B$144 -> Proceeds | D3: =Assumptions!$B$143 -> Election | E3: =Assumptions!$B$144 -> Proceeds | F3: =Assumptions!$B$143 -> Election | G3: =Assumptions!$B$144 -> Proceeds | H3: =Assumptions!$B$143 -> Election | I3: =Assumptions!$B$144 -> Proceeds | J3: =Assumptions!$B$143 -> Election | K3: =Assumptions!$B$144 -> Proceeds
A4: =Assumptions!$B$160 -> F | B4: =IF(Assumptions!$C$1044>=Assumptions!$D$1044,"preference","convert") -> preference | C4: =Assumptions!$B$1033 -> 30000000 | D4: =IF(Assumptions!$C$1204>=Assumptions!$D$1204,"preference","convert") -> preference | E4: =Assumptions!$B$1193 -> 30000000 | F4: =IF(Assumptions!$C$1364>=Assumptions!$D$1364,"preference","convert") -> convert | G4: =Assumptions!$B$1353 -> 44846573 | H4: =IF(Assumptions!$C$1524>=Assumptions!$D$1524,"preference","convert") -> convert | I4: =Assumptions!$B$1513 -> 89785811 | J4: =IF(Assumptions!$C$1684>=Assumptions!$D$1684,"preference","convert") -> convert | K4: =Assumptions!$B$1673 -> 1.7951554e+08
A5: =Assumptions!$B$161 -> E | B5: =IF(Assumptions!$C$1045>=Assumptions!$D$1045,"preference","convert") -> preference | C5: =Assumptions!$B$1034 -> 300000000 | D5: =IF(Assumptions!$C$1205>=Assumptions!$D$1205,"preference","convert") -> preference | E5: =Assumptions!$B$1194 -> 300000000 | F5: =IF(Assumptions!$C$1365>=Assumptions!$D$1365,"preference","convert") -> convert | G5: =Assumptions!$B$1354 -> 3.420513e+08 | H5: =IF(Assumptions!$C$1525>=Assumptions!$D$1525,"preference","convert") -> convert | I5: =Assumptions!$B$1514 -> 6.8480937e+08 | J5: =IF(Assumptions!$C$1685>=Assumptions!$D$1685,"preference","convert") -> convert | K5: =Assumptions!$B$1674 -> 1.369191e+09
A6: =Assumptions!$B$162 -> D | B6: =IF(Assumptions!$C$1046>=Assumptions!$D$1046,"preference","convert") -> preference | C6: =Assumptions!$B$1035 -> 100000000 | D6: =IF(Assumptions!$C$1206>=Assumptions!$D$1206,"preference","convert") -> preference | E6: =Assumptions!$B$1195 -> 100000000 | F6: =IF(Assumptions!$C$1366>=Assumptions!$D$1366,"preference","convert") -> preference | G6: =Assumptions!$B$1355 -> 100000000 | H6: =IF(Assumptions!$C$1526>=Assumptions!$D$1526,"preference","convert") -> convert | I6: =Assumptions!$B$1515 -> 1.9356896e+08 | J6: =IF(Assumptions!$C$1686>=Assumptions!$D$1686,"preference","convert") -> convert | K6: =Assumptions!$B$1675 -> 3.8701702e+08
A7: =Assumptions!$B$163 -> C | B7: =IF(Assumptions!$C$1047>=Assumptions!$D$1047,"preference","convert") -> preference | C7: =Assumptions!$B$1036 -> 60000000 | D7: =IF(Assumptions!$C$1207>=Assumptions!$D$1207,"preference","convert") -> convert | E7: =Assumptions!$B$1196 -> 68208513 | F7: =IF(Assumptions!$C$1367>=Assumptions!$D$1367,"preference","convert") -> convert | G7: =Assumptions!$B$1356 -> 1.3382132e+08 | H7: =IF(Assumptions!$C$1527>=Assumptions!$D$1527,"preference","convert") -> convert | I7: =Assumptions!$B$1516 -> 2.6791914e+08 | J7: =IF(Assumptions!$C$1687>=Assumptions!$D$1687,"preference","convert") -> convert | K7: =Assumptions!$B$1676 -> 5.3567093e+08
A8: =Assumptions!$B$164 -> B | B8: =IF(Assumptions!$C$1048>=Assumptions!$D$1048,"preference","convert") -> preference | C8: =Assumptions!$B$1037 -> 30000000 | D8: =IF(Assumptions!$C$1208>=Assumptions!$D$1208,"preference","convert") -> convert | E8: =Assumptions!$B$1197 -> 85260641 | F8: =IF(Assumptions!$C$1368>=Assumptions!$D$1368,"preference","convert") -> convert | G8: =Assumptions!$B$1357 -> 1.6727664e+08 | H8: =IF(Assumptions!$C$1528>=Assumptions!$D$1528,"preference","convert") -> convert | I8: =Assumptions!$B$1517 -> 3.3489892e+08 | J8: =IF(Assumptions!$C$1688>=Assumptions!$D$1688,"preference","convert") -> convert | K8: =Assumptions!$B$1677 -> 6.6958867e+08
A9: =Assumptions!$B$165 -> A | B9: =IF(Assumptions!$C$1049>=Assumptions!$D$1049,"preference","convert") -> convert | C9: =Assumptions!$B$1038 -> 41893623 | D9: =IF(Assumptions!$C$1209>=Assumptions!$D$1209,"preference","convert") -> convert | E9: =Assumptions!$B$1198 -> 1.4210107e+08 | F9: =IF(Assumptions!$C$1369>=Assumptions!$D$1369,"preference","convert") -> convert | G9: =Assumptions!$B$1358 -> 2.7879441e+08 | H9: =IF(Assumptions!$C$1529>=Assumptions!$D$1529,"preference","convert") -> convert | I9: =Assumptions!$B$1518 -> 5.5816487e+08 | J9: =IF(Assumptions!$C$1689>=Assumptions!$D$1689,"preference","convert") -> convert | K9: =Assumptions!$B$1678 -> 1.1159811e+09
A10: =Assumptions!$B$166 -> Seed | B10: =IF(Assumptions!$C$1050>=Assumptions!$D$1050,"preference","convert") -> convert | C10: =Assumptions!$B$1039 -> 41893623 | D10: =IF(Assumptions!$C$1210>=Assumptions!$D$1210,"preference","convert") -> convert | E10: =Assumptions!$B$1199 -> 1.4210107e+08 | F10: =IF(Assumptions!$C$1370>=Assumptions!$D$1370,"preference","convert") -> convert | G10: =Assumptions!$B$1359 -> 2.7879441e+08 | H10: =IF(Assumptions!$C$1530>=Assumptions!$D$1530,"preference","convert") -> convert | I10: =Assumptions!$B$1519 -> 5.5816487e+08 | J10: =IF(Assumptions!$C$1690>=Assumptions!$D$1690,"preference","convert") -> convert | K10: =Assumptions!$B$1679 -> 1.1159811e+09
A11: =Assumptions!$B$167 -> Notes | C11: =Assumptions!$B$1040 -> 2357421.2 | E11: =Assumptions!$B$1200 -> 7996254.3 | G11: =Assumptions!$B$1360 -> 15688207 | I11: =Assumptions!$B$1520 -> 31408830 | K11: =Assumptions!$B$1680 -> 62798042
A12: =Assumptions!$B$168 -> Common + RSAs | C12: =Assumptions!$B$1041 -> 75408521 | E12: =Assumptions!$B$1201 -> 2.5578192e+08 | G12: =Assumptions!$B$1361 -> 5.0182993e+08 | I12: =Assumptions!$B$1521 -> 1.0046968e+09 | K12: =Assumptions!$B$1681 -> 2.008766e+09
A13: =Assumptions!$B$174 -> Issued Options | C13: =Assumptions!$B$1042 -> 18446811 | E13: =Assumptions!$B$1202 -> 68550534 | G13: =Assumptions!$B$1362 -> 1.368972e+08 | I13: =Assumptions!$B$1522 -> 2.7658244e+08 | K13: =Assumptions!$B$1682 -> 5.5549056e+08
A14: =Assumptions!$B$145 -> Reconciliation | C14: =Assumptions!$C$1052 -> 0 | E14: =Assumptions!$C$1212 -> 0 | G14: =Assumptions!$C$1372 -> 0 | I14: =Assumptions!$C$1532 -> 0 | K14: =Assumptions!$C$1692 -> 0

Sheet Sensitivity
A1: =Assumptions!$B$146 -> Sensitivity
A3: =Assumptions!$B$148 -> Our ownership / proceeds @ $2,000M exit
A4: =Assumptions!$B$147 -> ESOP \ Pre-money | B4: =Assumptions!$B$40 -> 1200000000 | C4: =Assumptions!$C$40 -> 1400000000 | D4: =Assumptions!$D$40 -> 1800000000
A5: =Assumptions!$B$39 -> 0.11 | B5: =TEXT(Assumptions!$B$287,"0.000000%")&" / $"&TEXT((Assumptions!$B$1833*Assumptions!$B$10/Assumptions!$B$6)/1000000,"0.000")&"M" -> 0.813008% / $17.107M | C5: =TEXT(Assumptions!$B$357,"0.000000%")&" / $"&TEXT((Assumptions!$B$1993*Assumptions!$B$10/Assumptions!$B$6)/1000000,"0.000")&"M" -> 0.699301% / $14.720M | D5: =TEXT(Assumptions!$B$427,"0.000000%")&" / $"&TEXT((Assumptions!$B$2153*Assumptions!$B$10/Assumptions!$B$6)/1000000,"0.000")&"M" -> 0.546448% / $11.507M
A6: =Assumptions!$C$39 -> 0.13 | B6: =TEXT(Assumptions!$B$497,"0.000000%")&" / $"&TEXT((Assumptions!$B$2313*Assumptions!$B$10/Assumptions!$B$6)/1000000,"0.000")&"M" -> 0.813008% / $17.385M | C6: =TEXT(Assumptions!$B$567,"0.000000%")&" / $"&TEXT((Assumptions!$B$2473*Assumptions!$B$10/Assumptions!$B$6)/1000000,"0.000")&"M" -> 0.699301% / $14.949M | D6: =TEXT(Assumptions!$B$637,"0.000000%")&" / $"&TEXT((Assumptions!$B$2633*Assumptions!$B$10/Assumptions!$B$6)/1000000,"0.000")&"M" -> 0.546448% / $11.677M
A7: =Assumptions!$D$39 -> 0.15 | B7: =TEXT(Assumptions!$B$707,"0.000000%")&" / $"&TEXT((Assumptions!$B$2793*Assumptions!$B$10/Assumptions!$B$6)/1000000,"0.000")&"M" -> 0.813008% / $17.795M | C7: =TEXT(Assumptions!$B$777,"0.000000%")&" / $"&TEXT((Assumptions!$B$2953*Assumptions!$B$10/Assumptions!$B$6)/1000000,"0.000")&"M" -> 0.699301% / $15.301M | D7: =TEXT(Assumptions!$B$847,"0.000000%")&" / $"&TEXT((Assumptions!$B$3113*Assumptions!$B$10/Assumptions!$B$6)/1000000,"0.000")&"M" -> 0.546448% / $11.952M
A10: =Assumptions!$B$158 -> Post-F ownership
A11: =Assumptions!$B$147 -> ESOP \ Pre-money | B11: =Assumptions!$B$40 -> 1200000000 | C11: =Assumptions!$C$40 -> 1400000000 | D11: =Assumptions!$D$40 -> 1800000000
A12: =Assumptions!$B$39 -> 0.11 | B12: =Assumptions!$B$287 -> 0.0081300813 | C12: =Assumptions!$B$357 -> 0.006993007 | D12: =Assumptions!$B$427 -> 0.0054644809
A13: =Assumptions!$C$39 -> 0.13 | B13: =Assumptions!$B$497 -> 0.0081300813 | C13: =Assumptions!$B$567 -> 0.006993007 | D13: =Assumptions!$B$637 -> 0.0054644809
A14: =Assumptions!$D$39 -> 0.15 | B14: =Assumptions!$B$707 -> 0.0081300813 | C14: =Assumptions!$B$777 -> 0.006993007 | D14: =Assumptions!$B$847 -> 0.0054644809
A17: =Assumptions!$B$159 -> Proceeds @ $2B
A18: =Assumptions!$B$147 -> ESOP \ Pre-money | B18: =Assumptions!$B$40 -> 1200000000 | C18: =Assumptions!$C$40 -> 1400000000 | D18: =Assumptions!$D$40 -> 1800000000
A19: =Assumptions!$B$39 -> 0.11 | B19: =Assumptions!$B$1833*Assumptions!$B$10/Assumptions!$B$6 -> 17107259 | C19: =Assumptions!$B$1993*Assumptions!$B$10/Assumptions!$B$6 -> 14719656 | D19: =Assumptions!$B$2153*Assumptions!$B$10/Assumptions!$B$6 -> 11507141
A20: =Assumptions!$C$39 -> 0.13 | B20: =Assumptions!$B$2313*Assumptions!$B$10/Assumptions!$B$6 -> 17384971 | C20: =Assumptions!$B$2473*Assumptions!$B$10/Assumptions!$B$6 -> 14948858 | D20: =Assumptions!$B$2633*Assumptions!$B$10/Assumptions!$B$6 -> 11676568
A21: =Assumptions!$D$39 -> 0.15 | B21: =Assumptions!$B$2793*Assumptions!$B$10/Assumptions!$B$6 -> 17795002 | C21: =Assumptions!$B$2953*Assumptions!$B$10/Assumptions!$B$6 -> 15301320 | D21: =Assumptions!$B$3113*Assumptions!$B$10/Assumptions!$B$6 -> 11951762

Sheet Return-Solver
A1: =Assumptions!$B$149 -> Return-Solver
A3: =Assumptions!$B$150 -> Exit Value | B3: =Assumptions!$B$151 -> 3x Required Ownership | C3: =Assumptions!$B$152 -> 3x F Election | D3: =Assumptions!$B$153 -> 3x Status | E3: =Assumptions!$B$154 -> 4x Required Ownership | F3: =Assumptions!$B$155 -> 4x F Election | G3: =Assumptions!$B$156 -> 4x Status
A4: =Assumptions!$B$900 -> 700000000 | B4: =IF(OR((Assumptions!$B$900-Assumptions!$B$1045*Assumptions!$F$226-Assumptions!$B$1046*Assumptions!$F$225-Assumptions!$B$1047*Assumptions!$F$224-Assumptions!$B$1048*Assumptions!$F$223-Assumptions!$B$1049*Assumptions!$F$222-Assumptions!$B$1050*Assumptions!$F$221)+Assumptions!$B$12*Assumptions!$B$13-Assumptions!$B$45<=0,((Assumptions!$B$45*((Assumptions!$B$203+Assumptions!$B$204+Assumptions!$B$22+Assumptions!$B$215+(1-Assumptions!$B$1045)*Assumptions!$E$226+(1-Assumptions!$B$1046)*Assumptions!$E$225+(1-Assumptions!$B$1047)*Assumptions!$E$224+(1-Assumptions!$B$1048)*Assumptions!$E$223+(1-Assumptions!$B$1049)*Assumptions!$E$222+(1-Assumptions!$B$1050)*Assumptions!$E$221)+Assumptions!$B$13)/((Assumptions!$B$900-Assumptions!$B$1045*Assumptions!$F$226-Assumptions!$B$1046*Assumptions!$F$225-Assumptions!$B$1047*Assumptions!$F$224-Assumptions!$B$1048*Assumptions!$F$223-Assumptions!$B$1049*Assumptions!$F$222-Assumptions!$B$1050*Assumptions!$F$221)+Assumptions!$B$12*Assumptions!$B$13-Assumptions!$B$45))/((Assumptions!$B$199-Assumptions!$B$216)+(Assumptions!$B$45*((Assumptions!$B$203+Assumptions!$B$204+Assumptions!$B$22+Assumptions!$B$215+(1-Assumptions!$B$1045)*Assumptions!$E$226+(1-Assumptions!$B$1046)*Assumptions!$E$225+(1-Assumptions!$B$1047)*Assumptions!$E$224+(1-Assumptions!$B$1048)*Assumptions!$E$223+(1-Assumptions!$B$1049)*Assumptions!$E$222+(1-Assumptions!$B$1050)*Assumptions!$E$221)+Assumptions!$B$13)/((Assumptions!$B$900-Assumptions!$B$1045*Assumptions!$F$226-Assumptions!$B$1046*Assumptions!$F$225-Assumptions!$B$1047*Assumptions!$F$224-Assumptions!$B$1048*Assumptions!$F$223-Assumptions!$B$1049*Assumptions!$F$222-Assumptions!$B$1050*Assumptions!$F$221)+Assumptions!$B$12*Assumptions!$B$13-Assumptions!$B$45))))<=0,((Assumptions!$B$45*((Assumptions!$B$203+Assumptions!$B$204+Assumptions!$B$22+Assumptions!$B$215+(1-Assumptions!$B$1045)*Assumptions!$E$226+(1-Assumptions!$B$1046)*Assumptions!$E$225+(1-Assumptions!$B$1047)*Assumptions!$E$224+(1-Assumptions!$B$1048)*Assumptions!$E$223+(1-Assumptions!$B$1049)*Assumptions!$E$222+(1-Assumptions!$B$1050)*Assumptions!$E$221)+Assumptions!$B$13)/((Assumptions!$B$900-Assumptions!$B$1045*Assumptions!$F$226-Assumptions!$B$1046*Assumptions!$F$225-Assumptions!$B$1047*Assumptions!$F$224-Assumptions!$B$1048*Assumptions!$F$223-Assumptions!$B$1049*Assumptions!$F$222-Assumptions!$B$1050*Assumptions!$F$221)+Assumptions!$B$12*Assumptions!$B$13-Assumptions!$B$45))/((Assumptions!$B$199-Assumptions!$B$216)+(Assumptions!$B$45*((Assumptions!$B$203+Assumptions!$B$204+Assumptions!$B$22+Assumptions!$B$215+(1-Assumptions!$B$1045)*Assumptions!$E$226+(1-Assumptions!$B$1046)*Assumptions!$E$225+(1-Assumptions!$B$1047)*Assumptions!$E$224+(1-Assumptions!$B$1048)*Assumptions!$E$223+(1-Assumptions!$B$1049)*Assumptions!$E$222+(1-Assumptions!$B$1050)*Assumptions!$E$221)+Assumptions!$B$13)/((Assumptions!$B$900-Assumptions!$B$1045*Assumptions!$F$226-Assumptions!$B$1046*Assumptions!$F$225-Assumptions!$B$1047*Assumptions!$F$224-Assumptions!$B$1048*Assumptions!$F$223-Assumptions!$B$1049*Assumptions!$F$222-Assumptions!$B$1050*Assumptions!$F$221)+Assumptions!$B$12*Assumptions!$B$13-Assumptions!$B$45))))>1),NA(),((Assumptions!$B$45*((Assumptions!$B$203+Assumptions!$B$204+Assumptions!$B$22+Assumptions!$B$215+(1-Assumptions!$B$1045)*Assumptions!$E$226+(1-Assumptions!$B$1046)*Assumptions!$E$225+(1-Assumptions!$B$1047)*Assumptions!$E$224+(1-Assumptions!$B$1048)*Assumptions!$E$223+(1-Assumptions!$B$1049)*Assumptions!$E$222+(1-Assumptions!$B$1050)*Assumptions!$E$221)+Assumptions!$B$13)/((Assumptions!$B$900-Assumptions!$B$1045*Assumptions!$F$226-Assumptions!$B$1046*Assumptions!$F$225-Assumptions!$B$1047*Assumptions!$F$224-Assumptions!$B$1048*Assumptions!$F$223-Assumptions!$B$1049*Assumptions!$F$222-Assumptions!$B$1050*Assumptions!$F$221)+Assumptions!$B$12*Assumptions!$B$13-Assumptions!$B$45))/((Assumptions!$B$199-Assumptions!$B$216)+(Assumptions!$B$45*((Assumptions!$B$203+Assumptions!$B$204+Assumptions!$B$22+Assumptions!$B$215+(1-Assumptions!$B$1045)*Assumptions!$E$226+(1-Assumptions!$B$1046)*Assumptions!$E$225+(1-Assumptions!$B$1047)*Assumptions!$E$224+(1-Assumptions!$B$1048)*Assumptions!$E$223+(1-Assumptions!$B$1049)*Assumptions!$E$222+(1-Assumptions!$B$1050)*Assumptions!$E$221)+Assumptions!$B$13)/((Assumptions!$B$900-Assumptions!$B$1045*Assumptions!$F$226-Assumptions!$B$1046*Assumptions!$F$225-Assumptions!$B$1047*Assumptions!$F$224-Assumptions!$B$1048*Assumptions!$F$223-Assumptions!$B$1049*Assumptions!$F$222-Assumptions!$B$1050*Assumptions!$F$221)+Assumptions!$B$12*Assumptions!$B$13-Assumptions!$B$45))))) -> 0.08789562 | C4: =IF(Assumptions!$B$6>=((Assumptions!$B$215+(Assumptions!$B$45*((Assumptions!$B$203+Assumptions!$B$204+Assumptions!$B$22+Assumptions!$B$215+(1-Assumptions!$B$1045)*Assumptions!$E$226+(1-Assumptions!$B$1046)*Assumptions!$E$225+(1-Assumptions!$B$1047)*Assumptions!$E$224+(1-Assumptions!$B$1048)*Assumptions!$E$223+(1-Assumptions!$B$1049)*Assumptions!$E$222+(1-Assumptions!$B$1050)*Assumptions!$E$221)+Assumptions!$B$13)/((Assumptions!$B$900-Assumptions!$B$1045*Assumptions!$F$226-Assumptions!$B$1046*Assumptions!$F$225-Assumptions!$B$1047*Assumptions!$F$224-Assumptions!$B$1048*Assumptions!$F$223-Assumptions!$B$1049*Assumptions!$F$222-Assumptions!$B$1050*Assumptions!$F$221)+Assumptions!$B$12*Assumptions!$B$13-Assumptions!$B$45)))*(((Assumptions!$B$900-Assumptions!$B$1045*Assumptions!$F$226-Assumptions!$B$1046*Assumptions!$F$225-Assumptions!$B$1047*Assumptions!$F$224-Assumptions!$B$1048*Assumptions!$F$223-Assumptions!$B$1049*Assumptions!$F$222-Assumptions!$B$1050*Assumptions!$F$221)+Assumptions!$B$12*Assumptions!$B$13)/((Assumptions!$B$203+Assumptions!$B$204+Assumptions!$B$22+Assumptions!$B$215+(1-Assumptions!$B$1045)*Assumptions!$E$226+(1-Assumptions!$B$1046)*Assumptions!$E$225+(1-Assumptions!$B$1047)*Assumptions!$E$224+(1-Assumptions!$B$1048)*Assumptions!$E$223+(1-Assumptions!$B$1049)*Assumptions!$E$222+(1-Assumptions!$B$1050)*Assumptions!$E$221)+(Assumptions!$B$45*((Assumptions!$B$203+Assumptions!$B$204+Assumptions!$B$22+Assumptions!$B$215+(1-Assumptions!$B$1045)*Assumptions!$E$226+(1-Assumptions!$B$1046)*Assumptions!$E$225+(1-Assumptions!$B$1047)*Assumptions!$E$224+(1-Assumptions!$B$1048)*Assumptions!$E$223+(1-Assumptions!$B$1049)*Assumptions!$E$222+(1-Assumptions!$B$1050)*Assumptions!$E$221)+Assumptions!$B$13)/((Assumptions!$B$900-Assumptions!$B$1045*Assumptions!$F$226-Assumptions!$B$1046*Assumptions!$F$225-Assumptions!$B$1047*Assumptions!$F$224-Assumptions!$B$1048*Assumptions!$F$223-Assumptions!$B$1049*Assumptions!$F$222-Assumptions!$B$1050*Assumptions!$F$221)+Assumptions!$B$12*Assumptions!$B$13-Assumptions!$B$45))+Assumptions!$B$13))),"preference","convert") -> convert | D4: =IF(OR(ISNA(B4),C4<>"convert"),"infeasible","feasible") -> feasible | E4: =IF(OR((Assumptions!$B$900-Assumptions!$B$1045*Assumptions!$F$226-Assumptions!$B$1046*Assumptions!$F$225-Assumptions!$B$1047*Assumptions!$F$224-Assumptions!$B$1048*Assumptions!$F$223-Assumptions!$B$1049*Assumptions!$F$222-Assumptions!$B$1050*Assumptions!$F$221)+Assumptions!$B$12*Assumptions!$B$13-Assumptions!$B$46<=0,((Assumptions!$B$46*((Assumptions!$B$203+Assumptions!$B$204+Assumptions!$B$22+Assumptions!$B$215+(1-Assumptions!$B$1045)*Assumptions!$E$226+(1-Assumptions!$B$1046)*Assumptions!$E$225+(1-Assumptions!$B$1047)*Assumptions!$E$224+(1-Assumptions!$B$1048)*Assumptions!$E$223+(1-Assumptions!$B$1049)*Assumptions!$E$222+(1-Assumptions!$B$1050)*Assumptions!$E$221)+Assumptions!$B$13)/((Assumptions!$B$900-Assumptions!$B$1045*Assumptions!$F$226-Assumptions!$B$1046*Assumptions!$F$225-Assumptions!$B$1047*Assumptions!$F$224-Assumptions!$B$1048*Assumptions!$F$223-Assumptions!$B$1049*Assumptions!$F$222-Assumptions!$B$1050*Assumptions!$F$221)+Assumptions!$B$12*Assumptions!$B$13-Assumptions!$B$46))/((Assumptions!$B$199-Assumptions!$B$216)+(Assumptions!$B$46*((Assumptions!$B$203+Assumptions!$B$204+Assumptions!$B$22+Assumptions!$B$215+(1-Assumptions!$B$1045)*Assumptions!$E$226+(1-Assumptions!$B$1046)*Assumptions!$E$225+(1-Assumptions!$B$1047)*Assumptions!$E$224+(1-Assumptions!$B$1048)*Assumptions!$E$223+(1-Assumptions!$B$1049)*Assumptions!$E$222+(1-Assumptions!$B$1050)*Assumptions!$E$221)+Assumptions!$B$13)/((Assumptions!$B$900-Assumptions!$B$1045*Assumptions!$F$226-Assumptions!$B$1046*Assumptions!$F$225-Assumptions!$B$1047*Assumptions!$F$224-Assumptions!$B$1048*Assumptions!$F$223-Assumptions!$B$1049*Assumptions!$F$222-Assumptions!$B$1050*Assumptions!$F$221)+Assumptions!$B$12*Assumptions!$B$13-Assumptions!$B$46))))<=0,((Assumptions!$B$46*((Assumptions!$B$203+Assumptions!$B$204+Assumptions!$B$22+Assumptions!$B$215+(1-Assumptions!$B$1045)*Assumptions!$E$226+(1-Assumptions!$B$1046)*Assumptions!$E$225+(1-Assumptions!$B$1047)*Assumptions!$E$224+(1-Assumptions!$B$1048)*Assumptions!$E$223+(1-Assumptions!$B$1049)*Assumptions!$E$222+(1-Assumptions!$B$1050)*Assumptions!$E$221)+Assumptions!$B$13)/((Assumptions!$B$900-Assumptions!$B$1045*Assumptions!$F$226-Assumptions!$B$1046*Assumptions!$F$225-Assumptions!$B$1047*Assumptions!$F$224-Assumptions!$B$1048*Assumptions!$F$223-Assumptions!$B$1049*Assumptions!$F$222-Assumptions!$B$1050*Assumptions!$F$221)+Assumptions!$B$12*Assumptions!$B$13-Assumptions!$B$46))/((Assumptions!$B$199-Assumptions!$B$216)+(Assumptions!$B$46*((Assumptions!$B$203+Assumptions!$B$204+Assumptions!$B$22+Assumptions!$B$215+(1-Assumptions!$B$1045)*Assumptions!$E$226+(1-Assumptions!$B$1046)*Assumptions!$E$225+(1-Assumptions!$B$1047)*Assumptions!$E$224+(1-Assumptions!$B$1048)*Assumptions!$E$223+(1-Assumptions!$B$1049)*Assumptions!$E$222+(1-Assumptions!$B$1050)*Assumptions!$E$221)+Assumptions!$B$13)/((Assumptions!$B$900-Assumptions!$B$1045*Assumptions!$F$226-Assumptions!$B$1046*Assumptions!$F$225-Assumptions!$B$1047*Assumptions!$F$224-Assumptions!$B$1048*Assumptions!$F$223-Assumptions!$B$1049*Assumptions!$F$222-Assumptions!$B$1050*Assumptions!$F$221)+Assumptions!$B$12*Assumptions!$B$13-Assumptions!$B$46))))>1),NA(),((Assumptions!$B$46*((Assumptions!$B$203+Assumptions!$B$204+Assumptions!$B$22+Assumptions!$B$215+(1-Assumptions!$B$1045)*Assumptions!$E$226+(1-Assumptions!$B$1046)*Assumptions!$E$225+(1-Assumptions!$B$1047)*Assumptions!$E$224+(1-Assumptions!$B$1048)*Assumptions!$E$223+(1-Assumptions!$B$1049)*Assumptions!$E$222+(1-Assumptions!$B$1050)*Assumptions!$E$221)+Assumptions!$B$13)/((Assumptions!$B$900-Assumptions!$B$1045*Assumptions!$F$226-Assumptions!$B$1046*Assumptions!$F$225-Assumptions!$B$1047*Assumptions!$F$224-Assumptions!$B$1048*Assumptions!$F$223-Assumptions!$B$1049*Assumptions!$F$222-Assumptions!$B$1050*Assumptions!$F$221)+Assumptions!$B$12*Assumptions!$B$13-Assumptions!$B$46))/((Assumptions!$B$199-Assumptions!$B$216)+(Assumptions!$B$46*((Assumptions!$B$203+Assumptions!$B$204+Assumptions!$B$22+Assumptions!$B$215+(1-Assumptions!$B$1045)*Assumptions!$E$226+(1-Assumptions!$B$1046)*Assumptions!$E$225+(1-Assumptions!$B$1047)*Assumptions!$E$224+(1-Assumptions!$B$1048)*Assumptions!$E$223+(1-Assumptions!$B$1049)*Assumptions!$E$222+(1-Assumptions!$B$1050)*Assumptions!$E$221)+Assumptions!$B$13)/((Assumptions!$B$900-Assumptions!$B$1045*Assumptions!$F$226-Assumptions!$B$1046*Assumptions!$F$225-Assumptions!$B$1047*Assumptions!$F$224-Assumptions!$B$1048*Assumptions!$F$223-Assumptions!$B$1049*Assumptions!$F$222-Assumptions!$B$1050*Assumptions!$F$221)+Assumptions!$B$12*Assumptions!$B$13-Assumptions!$B$46))))) -> 0.11966889 | F4: =IF(Assumptions!$B$6>=((Assumptions!$B$215+(Assumptions!$B$46*((Assumptions!$B$203+Assumptions!$B$204+Assumptions!$B$22+Assumptions!$B$215+(1-Assumptions!$B$1045)*Assumptions!$E$226+(1-Assumptions!$B$1046)*Assumptions!$E$225+(1-Assumptions!$B$1047)*Assumptions!$E$224+(1-Assumptions!$B$1048)*Assumptions!$E$223+(1-Assumptions!$B$1049)*Assumptions!$E$222+(1-Assumptions!$B$1050)*Assumptions!$E$221)+Assumptions!$B$13)/((Assumptions!$B$900-Assumptions!$B$1045*Assumptions!$F$226-Assumptions!$B$1046*Assumptions!$F$225-Assumptions!$B$1047*Assumptions!$F$224-Assumptions!$B$1048*Assumptions!$F$223-Assumptions!$B$1049*Assumptions!$F$222-Assumptions!$B$1050*Assumptions!$F$221)+Assumptions!$B$12*Assumptions!$B$13-Assumptions!$B$46)))*(((Assumptions!$B$900-Assumptions!$B$1045*Assumptions!$F$226-Assumptions!$B$1046*Assumptions!$F$225-Assumptions!$B$1047*Assumptions!$F$224-Assumptions!$B$1048*Assumptions!$F$223-Assumptions!$B$1049*Assumptions!$F$222-Assumptions!$B$1050*Assumptions!$F$221)+Assumptions!$B$12*Assumptions!$B$13)/((Assumptions!$B$203+Assumptions!$B$204+Assumptions!$B$22+Assumptions!$B$215+(1-Assumptions!$B$1045)*Assumptions!$E$226+(1-Assumptions!$B$1046)*Assumptions!$E$225+(1-Assumptions!$B$1047)*Assumptions!$E$224+(1-Assumptions!$B$1048)*Assumptions!$E$223+(1-Assumptions!$B$1049)*Assumptions!$E$222+(1-Assumptions!$B$1050)*Assumptions!$E$221)+(Assumptions!$B$46*((Assumptions!$B$203+Assumptions!$B$204+Assumptions!$B$22+Assumptions!$B$215+(1-Assumptions!$B$1045)*Assumptions!$E$226+(1-Assumptions!$B$1046)*Assumptions!$E$225+(1-Assumptions!$B$1047)*Assumptions!$E$224+(1-Assumptions!$B$1048)*Assumptions!$E$223+(1-Assumptions!$B$1049)*Assumptions!$E$222+(1-Assumptions!$B$1050)*Assumptions!$E$221)+Assumptions!$B$13)/((Assumptions!$B$900-Assumptions!$B$1045*Assumptions!$F$226-Assumptions!$B$1046*Assumptions!$F$225-Assumptions!$B$1047*Assumptions!$F$224-Assumptions!$B$1048*Assumptions!$F$223-Assumptions!$B$1049*Assumptions!$F$222-Assumptions!$B$1050*Assumptions!$F$221)+Assumptions!$B$12*Assumptions!$B$13-Assumptions!$B$46))+Assumptions!$B$13))),"preference","convert") -> convert | G4: =IF(OR(ISNA(E4),F4<>"convert"),"infeasible","feasible") -> feasible
A5: =Assumptions!$B$1060 -> 1200000000 | B5: =IF(OR((Assumptions!$B$1060-Assumptions!$B$1205*Assumptions!$F$226-Assumptions!$B$1206*Assumptions!$F$225-Assumptions!$B$1207*Assumptions!$F$224-Assumptions!$B$1208*Assumptions!$F$223-Assumptions!$B$1209*Assumptions!$F$222-Assumptions!$B$1210*Assumptions!$F$221)+Assumptions!$B$12*Assumptions!$B$13-Assumptions!$B$45<=0,((Assumptions!$B$45*((Assumptions!$B$203+Assumptions!$B$204+Assumptions!$B$22+Assumptions!$B$215+(1-Assumptions!$B$1205)*Assumptions!$E$226+(1-Assumptions!$B$1206)*Assumptions!$E$225+(1-Assumptions!$B$1207)*Assumptions!$E$224+(1-Assumptions!$B$1208)*Assumptions!$E$223+(1-Assumptions!$B$1209)*Assumptions!$E$222+(1-Assumptions!$B$1210)*Assumptions!$E$221)+Assumptions!$B$13)/((Assumptions!$B$1060-Assumptions!$B$1205*Assumptions!$F$226-Assumptions!$B$1206*Assumptions!$F$225-Assumptions!$B$1207*Assumptions!$F$224-Assumptions!$B$1208*Assumptions!$F$223-Assumptions!$B$1209*Assumptions!$F$222-Assumptions!$B$1210*Assumptions!$F$221)+Assumptions!$B$12*Assumptions!$B$13-Assumptions!$B$45))/((Assumptions!$B$199-Assumptions!$B$216)+(Assumptions!$B$45*((Assumptions!$B$203+Assumptions!$B$204+Assumptions!$B$22+Assumptions!$B$215+(1-Assumptions!$B$1205)*Assumptions!$E$226+(1-Assumptions!$B$1206)*Assumptions!$E$225+(1-Assumptions!$B$1207)*Assumptions!$E$224+(1-Assumptions!$B$1208)*Assumptions!$E$223+(1-Assumptions!$B$1209)*Assumptions!$E$222+(1-Assumptions!$B$1210)*Assumptions!$E$221)+Assumptions!$B$13)/((Assumptions!$B$1060-Assumptions!$B$1205*Assumptions!$F$226-Assumptions!$B$1206*Assumptions!$F$225-Assumptions!$B$1207*Assumptions!$F$224-Assumptions!$B$1208*Assumptions!$F$223-Assumptions!$B$1209*Assumptions!$F$222-Assumptions!$B$1210*Assumptions!$F$221)+Assumptions!$B$12*Assumptions!$B$13-Assumptions!$B$45))))<=0,((Assumptions!$B$45*((Assumptions!$B$203+Assumptions!$B$204+Assumptions!$B$22+Assumptions!$B$215+(1-Assumptions!$B$1205)*Assumptions!$E$226+(1-Assumptions!$B$1206)*Assumptions!$E$225+(1-Assumptions!$B$1207)*Assumptions!$E$224+(1-Assumptions!$B$1208)*Assumptions!$E$223+(1-Assumptions!$B$1209)*Assumptions!$E$222+(1-Assumptions!$B$1210)*Assumptions!$E$221)+Assumptions!$B$13)/((Assumptions!$B$1060-Assumptions!$B$1205*Assumptions!$F$226-Assumptions!$B$1206*Assumptions!$F$225-Assumptions!$B$1207*Assumptions!$F$224-Assumptions!$B$1208*Assumptions!$F$223-Assumptions!$B$1209*Assumptions!$F$222-Assumptions!$B$1210*Assumptions!$F$221)+Assumptions!$B$12*Assumptions!$B$13-Assumptions!$B$45))/((Assumptions!$B$199-Assumptions!$B$216)+(Assumptions!$B$45*((Assumptions!$B$203+Assumptions!$B$204+Assumptions!$B$22+Assumptions!$B$215+(1-Assumptions!$B$1205)*Assumptions!$E$226+(1-Assumptions!$B$1206)*Assumptions!$E$225+(1-Assumptions!$B$1207)*Assumptions!$E$224+(1-Assumptions!$B$1208)*Assumptions!$E$223+(1-Assumptions!$B$1209)*Assumptions!$E$222+(1-Assumptions!$B$1210)*Assumptions!$E$221)+Assumptions!$B$13)/((Assumptions!$B$1060-Assumptions!$B$1205*Assumptions!$F$226-Assumptions!$B$1206*Assumptions!$F$225-Assumptions!$B$1207*Assumptions!$F$224-Assumptions!$B$1208*Assumptions!$F$223-Assumptions!$B$1209*Assumptions!$F$222-Assumptions!$B$1210*Assumptions!$F$221)+Assumptions!$B$12*Assumptions!$B$13-Assumptions!$B$45))))>1),NA(),((Assumptions!$B$45*((Assumptions!$B$203+Assumptions!$B$204+Assumptions!$B$22+Assumptions!$B$215+(1-Assumptions!$B$1205)*Assumptions!$E$226+(1-Assumptions!$B$1206)*Assumptions!$E$225+(1-Assumptions!$B$1207)*Assumptions!$E$224+(1-Assumptions!$B$1208)*Assumptions!$E$223+(1-Assumptions!$B$1209)*Assumptions!$E$222+(1-Assumptions!$B$1210)*Assumptions!$E$221)+Assumptions!$B$13)/((Assumptions!$B$1060-Assumptions!$B$1205*Assumptions!$F$226-Assumptions!$B$1206*Assumptions!$F$225-Assumptions!$B$1207*Assumptions!$F$224-Assumptions!$B$1208*Assumptions!$F$223-Assumptions!$B$1209*Assumptions!$F$222-Assumptions!$B$1210*Assumptions!$F$221)+Assumptions!$B$12*Assumptions!$B$13-Assumptions!$B$45))/((Assumptions!$B$199-Assumptions!$B$216)+(Assumptions!$B$45*((Assumptions!$B$203+Assumptions!$B$204+Assumptions!$B$22+Assumptions!$B$215+(1-Assumptions!$B$1205)*Assumptions!$E$226+(1-Assumptions!$B$1206)*Assumptions!$E$225+(1-Assumptions!$B$1207)*Assumptions!$E$224+(1-Assumptions!$B$1208)*Assumptions!$E$223+(1-Assumptions!$B$1209)*Assumptions!$E$222+(1-Assumptions!$B$1210)*Assumptions!$E$221)+Assumptions!$B$13)/((Assumptions!$B$1060-Assumptions!$B$1205*Assumptions!$F$226-Assumptions!$B$1206*Assumptions!$F$225-Assumptions!$B$1207*Assumptions!$F$224-Assumptions!$B$1208*Assumptions!$F$223-Assumptions!$B$1209*Assumptions!$F$222-Assumptions!$B$1210*Assumptions!$F$221)+Assumptions!$B$12*Assumptions!$B$13-Assumptions!$B$45))))) -> 0.027497062 | C5: =IF(Assumptions!$B$6>=((Assumptions!$B$215+(Assumptions!$B$45*((Assumptions!$B$203+Assumptions!$B$204+Assumptions!$B$22+Assumptions!$B$215+(1-Assumptions!$B$1205)*Assumptions!$E$226+(1-Assumptions!$B$1206)*Assumptions!$E$225+(1-Assumptions!$B$1207)*Assumptions!$E$224+(1-Assumptions!$B$1208)*Assumptions!$E$223+(1-Assumptions!$B$1209)*Assumptions!$E$222+(1-Assumptions!$B$1210)*Assumptions!$E$221)+Assumptions!$B$13)/((Assumptions!$B$1060-Assumptions!$B$1205*Assumptions!$F$226-Assumptions!$B$1206*Assumptions!$F$225-Assumptions!$B$1207*Assumptions!$F$224-Assumptions!$B$1208*Assumptions!$F$223-Assumptions!$B$1209*Assumptions!$F$222-Assumptions!$B$1210*Assumptions!$F$221)+Assumptions!$B$12*Assumptions!$B$13-Assumptions!$B$45)))*(((Assumptions!$B$1060-Assumptions!$B$1205*Assumptions!$F$226-Assumptions!$B$1206*Assumptions!$F$225-Assumptions!$B$1207*Assumptions!$F$224-Assumptions!$B$1208*Assumptions!$F$223-Assumptions!$B$1209*Assumptions!$F$222-Assumptions!$B$1210*Assumptions!$F$221)+Assumptions!$B$12*Assumptions!$B$13)/((Assumptions!$B$203+Assumptions!$B$204+Assumptions!$B$22+Assumptions!$B$215+(1-Assumptions!$B$1205)*Assumptions!$E$226+(1-Assumptions!$B$1206)*Assumptions!$E$225+(1-Assumptions!$B$1207)*Assumptions!$E$224+(1-Assumptions!$B$1208)*Assumptions!$E$223+(1-Assumptions!$B$1209)*Assumptions!$E$222+(1-Assumptions!$B$1210)*Assumptions!$E$221)+(Assumptions!$B$45*((Assumptions!$B$203+Assumptions!$B$204+Assumptions!$B$22+Assumptions!$B$215+(1-Assumptions!$B$1205)*Assumptions!$E$226+(1-Assumptions!$B$1206)*Assumptions!$E$225+(1-Assumptions!$B$1207)*Assumptions!$E$224+(1-Assumptions!$B$1208)*Assumptions!$E$223+(1-Assumptions!$B$1209)*Assumptions!$E$222+(1-Assumptions!$B$1210)*Assumptions!$E$221)+Assumptions!$B$13)/((Assumptions!$B$1060-Assumptions!$B$1205*Assumptions!$F$226-Assumptions!$B$1206*Assumptions!$F$225-Assumptions!$B$1207*Assumptions!$F$224-Assumptions!$B$1208*Assumptions!$F$223-Assumptions!$B$1209*Assumptions!$F$222-Assumptions!$B$1210*Assumptions!$F$221)+Assumptions!$B$12*Assumptions!$B$13-Assumptions!$B$45))+Assumptions!$B$13))),"preference","convert") -> convert | D5: =IF(OR(ISNA(B5),C5<>"convert"),"infeasible","feasible") -> feasible | E5: =IF(OR((Assumptions!$B$1060-Assumptions!$B$1205*Assumptions!$F$226-Assumptions!$B$1206*Assumptions!$F$225-Assumptions!$B$1207*Assumptions!$F$224-Assumptions!$B$1208*Assumptions!$F$223-Assumptions!$B$1209*Assumptions!$F$222-Assumptions!$B$1210*Assumptions!$F$221)+Assumptions!$B$12*Assumptions!$B$13-Assumptions!$B$46<=0,((Assumptions!$B$46*((Assumptions!$B$203+Assumptions!$B$204+Assumptions!$B$22+Assumptions!$B$215+(1-Assumptions!$B$1205)*Assumptions!$E$226+(1-Assumptions!$B$1206)*Assumptions!$E$225+(1-Assumptions!$B$1207)*Assumptions!$E$224+(1-Assumptions!$B$1208)*Assumptions!$E$223+(1-Assumptions!$B$1209)*Assumptions!$E$222+(1-Assumptions!$B$1210)*Assumptions!$E$221)+Assumptions!$B$13)/((Assumptions!$B$1060-Assumptions!$B$1205*Assumptions!$F$226-Assumptions!$B$1206*Assumptions!$F$225-Assumptions!$B$1207*Assumptions!$F$224-Assumptions!$B$1208*Assumptions!$F$223-Assumptions!$B$1209*Assumptions!$F$222-Assumptions!$B$1210*Assumptions!$F$221)+Assumptions!$B$12*Assumptions!$B$13-Assumptions!$B$46))/((Assumptions!$B$199-Assumptions!$B$216)+(Assumptions!$B$46*((Assumptions!$B$203+Assumptions!$B$204+Assumptions!$B$22+Assumptions!$B$215+(1-Assumptions!$B$1205)*Assumptions!$E$226+(1-Assumptions!$B$1206)*Assumptions!$E$225+(1-Assumptions!$B$1207)*Assumptions!$E$224+(1-Assumptions!$B$1208)*Assumptions!$E$223+(1-Assumptions!$B$1209)*Assumptions!$E$222+(1-Assumptions!$B$1210)*Assumptions!$E$221)+Assumptions!$B$13)/((Assumptions!$B$1060-Assumptions!$B$1205*Assumptions!$F$226-Assumptions!$B$1206*Assumptions!$F$225-Assumptions!$B$1207*Assumptions!$F$224-Assumptions!$B$1208*Assumptions!$F$223-Assumptions!$B$1209*Assumptions!$F$222-Assumptions!$B$1210*Assumptions!$F$221)+Assumptions!$B$12*Assumptions!$B$13-Assumptions!$B$46))))<=0,((Assumptions!$B$46*((Assumptions!$B$203+Assumptions!$B$204+Assumptions!$B$22+Assumptions!$B$215+(1-Assumptions!$B$1205)*Assumptions!$E$226+(1-Assumptions!$B$1206)*Assumptions!$E$225+(1-Assumptions!$B$1207)*Assumptions!$E$224+(1-Assumptions!$B$1208)*Assumptions!$E$223+(1-Assumptions!$B$1209)*Assumptions!$E$222+(1-Assumptions!$B$1210)*Assumptions!$E$221)+Assumptions!$B$13)/((Assumptions!$B$1060-Assumptions!$B$1205*Assumptions!$F$226-Assumptions!$B$1206*Assumptions!$F$225-Assumptions!$B$1207*Assumptions!$F$224-Assumptions!$B$1208*Assumptions!$F$223-Assumptions!$B$1209*Assumptions!$F$222-Assumptions!$B$1210*Assumptions!$F$221)+Assumptions!$B$12*Assumptions!$B$13-Assumptions!$B$46))/((Assumptions!$B$199-Assumptions!$B$216)+(Assumptions!$B$46*((Assumptions!$B$203+Assumptions!$B$204+Assumptions!$B$22+Assumptions!$B$215+(1-Assumptions!$B$1205)*Assumptions!$E$226+(1-Assumptions!$B$1206)*Assumptions!$E$225+(1-Assumptions!$B$1207)*Assumptions!$E$224+(1-Assumptions!$B$1208)*Assumptions!$E$223+(1-Assumptions!$B$1209)*Assumptions!$E$222+(1-Assumptions!$B$1210)*Assumptions!$E$221)+Assumptions!$B$13)/((Assumptions!$B$1060-Assumptions!$B$1205*Assumptions!$F$226-Assumptions!$B$1206*Assumptions!$F$225-Assumptions!$B$1207*Assumptions!$F$224-Assumptions!$B$1208*Assumptions!$F$223-Assumptions!$B$1209*Assumptions!$F$222-Assumptions!$B$1210*Assumptions!$F$221)+Assumptions!$B$12*Assumptions!$B$13-Assumptions!$B$46))))>1),NA(),((Assumptions!$B$46*((Assumptions!$B$203+Assumptions!$B$204+Assumptions!$B$22+Assumptions!$B$215+(1-Assumptions!$B$1205)*Assumptions!$E$226+(1-Assumptions!$B$1206)*Assumptions!$E$225+(1-Assumptions!$B$1207)*Assumptions!$E$224+(1-Assumptions!$B$1208)*Assumptions!$E$223+(1-Assumptions!$B$1209)*Assumptions!$E$222+(1-Assumptions!$B$1210)*Assumptions!$E$221)+Assumptions!$B$13)/((Assumptions!$B$1060-Assumptions!$B$1205*Assumptions!$F$226-Assumptions!$B$1206*Assumptions!$F$225-Assumptions!$B$1207*Assumptions!$F$224-Assumptions!$B$1208*Assumptions!$F$223-Assumptions!$B$1209*Assumptions!$F$222-Assumptions!$B$1210*Assumptions!$F$221)+Assumptions!$B$12*Assumptions!$B$13-Assumptions!$B$46))/((Assumptions!$B$199-Assumptions!$B$216)+(Assumptions!$B$46*((Assumptions!$B$203+Assumptions!$B$204+Assumptions!$B$22+Assumptions!$B$215+(1-Assumptions!$B$1205)*Assumptions!$E$226+(1-Assumptions!$B$1206)*Assumptions!$E$225+(1-Assumptions!$B$1207)*Assumptions!$E$224+(1-Assumptions!$B$1208)*Assumptions!$E$223+(1-Assumptions!$B$1209)*Assumptions!$E$222+(1-Assumptions!$B$1210)*Assumptions!$E$221)+Assumptions!$B$13)/((Assumptions!$B$1060-Assumptions!$B$1205*Assumptions!$F$226-Assumptions!$B$1206*Assumptions!$F$225-Assumptions!$B$1207*Assumptions!$F$224-Assumptions!$B$1208*Assumptions!$F$223-Assumptions!$B$1209*Assumptions!$F$222-Assumptions!$B$1210*Assumptions!$F$221)+Assumptions!$B$12*Assumptions!$B$13-Assumptions!$B$46))))) -> 0.03678869 | F5: =IF(Assumptions!$B$6>=((Assumptions!$B$215+(Assumptions!$B$46*((Assumptions!$B$203+Assumptions!$B$204+Assumptions!$B$22+Assumptions!$B$215+(1-Assumptions!$B$1205)*Assumptions!$E$226+(1-Assumptions!$B$1206)*Assumptions!$E$225+(1-Assumptions!$B$1207)*Assumptions!$E$224+(1-Assumptions!$B$1208)*Assumptions!$E$223+(1-Assumptions!$B$1209)*Assumptions!$E$222+(1-Assumptions!$B$1210)*Assumptions!$E$221)+Assumptions!$B$13)/((Assumptions!$B$1060-Assumptions!$B$1205*Assumptions!$F$226-Assumptions!$B$1206*Assumptions!$F$225-Assumptions!$B$1207*Assumptions!$F$224-Assumptions!$B$1208*Assumptions!$F$223-Assumptions!$B$1209*Assumptions!$F$222-Assumptions!$B$1210*Assumptions!$F$221)+Assumptions!$B$12*Assumptions!$B$13-Assumptions!$B$46)))*(((Assumptions!$B$1060-Assumptions!$B$1205*Assumptions!$F$226-Assumptions!$B$1206*Assumptions!$F$225-Assumptions!$B$1207*Assumptions!$F$224-Assumptions!$B$1208*Assumptions!$F$223-Assumptions!$B$1209*Assumptions!$F$222-Assumptions!$B$1210*Assumptions!$F$221)+Assumptions!$B$12*Assumptions!$B$13)/((Assumptions!$B$203+Assumptions!$B$204+Assumptions!$B$22+Assumptions!$B$215+(1-Assumptions!$B$1205)*Assumptions!$E$226+(1-Assumptions!$B$1206)*Assumptions!$E$225+(1-Assumptions!$B$1207)*Assumptions!$E$224+(1-Assumptions!$B$1208)*Assumptions!$E$223+(1-Assumptions!$B$1209)*Assumptions!$E$222+(1-Assumptions!$B$1210)*Assumptions!$E$221)+(Assumptions!$B$46*((Assumptions!$B$203+Assumptions!$B$204+Assumptions!$B$22+Assumptions!$B$215+(1-Assumptions!$B$1205)*Assumptions!$E$226+(1-Assumptions!$B$1206)*Assumptions!$E$225+(1-Assumptions!$B$1207)*Assumptions!$E$224+(1-Assumptions!$B$1208)*Assumptions!$E$223+(1-Assumptions!$B$1209)*Assumptions!$E$222+(1-Assumptions!$B$1210)*Assumptions!$E$221)+Assumptions!$B$13)/((Assumptions!$B$1060-Assumptions!$B$1205*Assumptions!$F$226-Assumptions!$B$1206*Assumptions!$F$225-Assumptions!$B$1207*Assumptions!$F$224-Assumptions!$B$1208*Assumptions!$F$223-Assumptions!$B$1209*Assumptions!$F$222-Assumptions!$B$1210*Assumptions!$F$221)+Assumptions!$B$12*Assumptions!$B$13-Assumptions!$B$46))+Assumptions!$B$13))),"preference","convert") -> convert | G5: =IF(OR(ISNA(E5),F5<>"convert"),"infeasible","feasible") -> feasible
A6: =Assumptions!$B$1220 -> 2000000000 | B6: =IF(OR((Assumptions!$B$1220-Assumptions!$B$1365*Assumptions!$F$226-Assumptions!$B$1366*Assumptions!$F$225-Assumptions!$B$1367*Assumptions!$F$224-Assumptions!$B$1368*Assumptions!$F$223-Assumptions!$B$1369*Assumptions!$F$222-Assumptions!$B$1370*Assumptions!$F$221)+Assumptions!$B$12*Assumptions!$B$13-Assumptions!$B$45<=0,((Assumptions!$B$45*((Assumptions!$B$203+Assumptions!$B$204+Assumptions!$B$22+Assumptions!$B$215+(1-Assumptions!$B$1365)*Assumptions!$E$226+(1-Assumptions!$B$1366)*Assumptions!$E$225+(1-Assumptions!$B$1367)*Assumptions!$E$224+(1-Assumptions!$B$1368)*Assumptions!$E$223+(1-Assumptions!$B$1369)*Assumptions!$E$222+(1-Assumptions!$B$1370)*Assumptions!$E$221)+Assumptions!$B$13)/((Assumptions!$B$1220-Assumptions!$B$1365*Assumptions!$F$226-Assumptions!$B$1366*Assumptions!$F$225-Assumptions!$B$1367*Assumptions!$F$224-Assumptions!$B$1368*Assumptions!$F$223-Assumptions!$B$1369*Assumptions!$F$222-Assumptions!$B$1370*Assumptions!$F$221)+Assumptions!$B$12*Assumptions!$B$13-Assumptions!$B$45))/((Assumptions!$B$199-Assumptions!$B$216)+(Assumptions!$B$45*((Assumptions!$B$203+Assumptions!$B$204+Assumptions!$B$22+Assumptions!$B$215+(1-Assumptions!$B$1365)*Assumptions!$E$226+(1-Assumptions!$B$1366)*Assumptions!$E$225+(1-Assumptions!$B$1367)*Assumptions!$E$224+(1-Assumptions!$B$1368)*Assumptions!$E$223+(1-Assumptions!$B$1369)*Assumptions!$E$222+(1-Assumptions!$B$1370)*Assumptions!$E$221)+Assumptions!$B$13)/((Assumptions!$B$1220-Assumptions!$B$1365*Assumptions!$F$226-Assumptions!$B$1366*Assumptions!$F$225-Assumptions!$B$1367*Assumptions!$F$224-Assumptions!$B$1368*Assumptions!$F$223-Assumptions!$B$1369*Assumptions!$F$222-Assumptions!$B$1370*Assumptions!$F$221)+Assumptions!$B$12*Assumptions!$B$13-Assumptions!$B$45))))<=0,((Assumptions!$B$45*((Assumptions!$B$203+Assumptions!$B$204+Assumptions!$B$22+Assumptions!$B$215+(1-Assumptions!$B$1365)*Assumptions!$E$226+(1-Assumptions!$B$1366)*Assumptions!$E$225+(1-Assumptions!$B$1367)*Assumptions!$E$224+(1-Assumptions!$B$1368)*Assumptions!$E$223+(1-Assumptions!$B$1369)*Assumptions!$E$222+(1-Assumptions!$B$1370)*Assumptions!$E$221)+Assumptions!$B$13)/((Assumptions!$B$1220-Assumptions!$B$1365*Assumptions!$F$226-Assumptions!$B$1366*Assumptions!$F$225-Assumptions!$B$1367*Assumptions!$F$224-Assumptions!$B$1368*Assumptions!$F$223-Assumptions!$B$1369*Assumptions!$F$222-Assumptions!$B$1370*Assumptions!$F$221)+Assumptions!$B$12*Assumptions!$B$13-Assumptions!$B$45))/((Assumptions!$B$199-Assumptions!$B$216)+(Assumptions!$B$45*((Assumptions!$B$203+Assumptions!$B$204+Assumptions!$B$22+Assumptions!$B$215+(1-Assumptions!$B$1365)*Assumptions!$E$226+(1-Assumptions!$B$1366)*Assumptions!$E$225+(1-Assumptions!$B$1367)*Assumptions!$E$224+(1-Assumptions!$B$1368)*Assumptions!$E$223+(1-Assumptions!$B$1369)*Assumptions!$E$222+(1-Assumptions!$B$1370)*Assumptions!$E$221)+Assumptions!$B$13)/((Assumptions!$B$1220-Assumptions!$B$1365*Assumptions!$F$226-Assumptions!$B$1366*Assumptions!$F$225-Assumptions!$B$1367*Assumptions!$F$224-Assumptions!$B$1368*Assumptions!$F$223-Assumptions!$B$1369*Assumptions!$F$222-Assumptions!$B$1370*Assumptions!$F$221)+Assumptions!$B$12*Assumptions!$B$13-Assumptions!$B$45))))>1),NA(),((Assumptions!$B$45*((Assumptions!$B$203+Assumptions!$B$204+Assumptions!$B$22+Assumptions!$B$215+(1-Assumptions!$B$1365)*Assumptions!$E$226+(1-Assumptions!$B$1366)*Assumptions!$E$225+(1-Assumptions!$B$1367)*Assumptions!$E$224+(1-Assumptions!$B$1368)*Assumptions!$E$223+(1-Assumptions!$B$1369)*Assumptions!$E$222+(1-Assumptions!$B$1370)*Assumptions!$E$221)+Assumptions!$B$13)/((Assumptions!$B$1220-Assumptions!$B$1365*Assumptions!$F$226-Assumptions!$B$1366*Assumptions!$F$225-Assumptions!$B$1367*Assumptions!$F$224-Assumptions!$B$1368*Assumptions!$F$223-Assumptions!$B$1369*Assumptions!$F$222-Assumptions!$B$1370*Assumptions!$F$221)+Assumptions!$B$12*Assumptions!$B$13-Assumptions!$B$45))/((Assumptions!$B$199-Assumptions!$B$216)+(Assumptions!$B$45*((Assumptions!$B$203+Assumptions!$B$204+Assumptions!$B$22+Assumptions!$B$215+(1-Assumptions!$B$1365)*Assumptions!$E$226+(1-Assumptions!$B$1366)*Assumptions!$E$225+(1-Assumptions!$B$1367)*Assumptions!$E$224+(1-Assumptions!$B$1368)*Assumptions!$E$223+(1-Assumptions!$B$1369)*Assumptions!$E$222+(1-Assumptions!$B$1370)*Assumptions!$E$221)+Assumptions!$B$13)/((Assumptions!$B$1220-Assumptions!$B$1365*Assumptions!$F$226-Assumptions!$B$1366*Assumptions!$F$225-Assumptions!$B$1367*Assumptions!$F$224-Assumptions!$B$1368*Assumptions!$F$223-Assumptions!$B$1369*Assumptions!$F$222-Assumptions!$B$1370*Assumptions!$F$221)+Assumptions!$B$12*Assumptions!$B$13-Assumptions!$B$45))))) -> 0.014046185 | C6: =IF(Assumptions!$B$6>=((Assumptions!$B$215+(Assumptions!$B$45*((Assumptions!$B$203+Assumptions!$B$204+Assumptions!$B$22+Assumptions!$B$215+(1-Assumptions!$B$1365)*Assumptions!$E$226+(1-Assumptions!$B$1366)*Assumptions!$E$225+(1-Assumptions!$B$1367)*Assumptions!$E$224+(1-Assumptions!$B$1368)*Assumptions!$E$223+(1-Assumptions!$B$1369)*Assumptions!$E$222+(1-Assumptions!$B$1370)*Assumptions!$E$221)+Assumptions!$B$13)/((Assumptions!$B$1220-Assumptions!$B$1365*Assumptions!$F$226-Assumptions!$B$1366*Assumptions!$F$225-Assumptions!$B$1367*Assumptions!$F$224-Assumptions!$B$1368*Assumptions!$F$223-Assumptions!$B$1369*Assumptions!$F$222-Assumptions!$B$1370*Assumptions!$F$221)+Assumptions!$B$12*Assumptions!$B$13-Assumptions!$B$45)))*(((Assumptions!$B$1220-Assumptions!$B$1365*Assumptions!$F$226-Assumptions!$B$1366*Assumptions!$F$225-Assumptions!$B$1367*Assumptions!$F$224-Assumptions!$B$1368*Assumptions!$F$223-Assumptions!$B$1369*Assumptions!$F$222-Assumptions!$B$1370*Assumptions!$F$221)+Assumptions!$B$12*Assumptions!$B$13)/((Assumptions!$B$203+Assumptions!$B$204+Assumptions!$B$22+Assumptions!$B$215+(1-Assumptions!$B$1365)*Assumptions!$E$226+(1-Assumptions!$B$1366)*Assumptions!$E$225+(1-Assumptions!$B$1367)*Assumptions!$E$224+(1-Assumptions!$B$1368)*Assumptions!$E$223+(1-Assumptions!$B$1369)*Assumptions!$E$222+(1-Assumptions!$B$1370)*Assumptions!$E$221)+(Assumptions!$B$45*((Assumptions!$B$203+Assumptions!$B$204+Assumptions!$B$22+Assumptions!$B$215+(1-Assumptions!$B$1365)*Assumptions!$E$226+(1-Assumptions!$B$1366)*Assumptions!$E$225+(1-Assumptions!$B$1367)*Assumptions!$E$224+(1-Assumptions!$B$1368)*Assumptions!$E$223+(1-Assumptions!$B$1369)*Assumptions!$E$222+(1-Assumptions!$B$1370)*Assumptions!$E$221)+Assumptions!$B$13)/((Assumptions!$B$1220-Assumptions!$B$1365*Assumptions!$F$226-Assumptions!$B$1366*Assumptions!$F$225-Assumptions!$B$1367*Assumptions!$F$224-Assumptions!$B$1368*Assumptions!$F$223-Assumptions!$B$1369*Assumptions!$F$222-Assumptions!$B$1370*Assumptions!$F$221)+Assumptions!$B$12*Assumptions!$B$13-Assumptions!$B$45))+Assumptions!$B$13))),"preference","convert") -> convert | D6: =IF(OR(ISNA(B6),C6<>"convert"),"infeasible","feasible") -> feasible | E6: =IF(OR((Assumptions!$B$1220-Assumptions!$B$1365*Assumptions!$F$226-Assumptions!$B$1366*Assumptions!$F$225-Assumptions!$B$1367*Assumptions!$F$224-Assumptions!$B$1368*Assumptions!$F$223-Assumptions!$B$1369*Assumptions!$F$222-Assumptions!$B$1370*Assumptions!$F$221)+Assumptions!$B$12*Assumptions!$B$13-Assumptions!$B$46<=0,((Assumptions!$B$46*((Assumptions!$B$203+Assumptions!$B$204+Assumptions!$B$22+Assumptions!$B$215+(1-Assumptions!$B$1365)*Assumptions!$E$226+(1-Assumptions!$B$1366)*Assumptions!$E$225+(1-Assumptions!$B$1367)*Assumptions!$E$224+(1-Assumptions!$B$1368)*Assumptions!$E$223+(1-Assumptions!$B$1369)*Assumptions!$E$222+(1-Assumptions!$B$1370)*Assumptions!$E$221)+Assumptions!$B$13)/((Assumptions!$B$1220-Assumptions!$B$1365*Assumptions!$F$226-Assumptions!$B$1366*Assumptions!$F$225-Assumptions!$B$1367*Assumptions!$F$224-Assumptions!$B$1368*Assumptions!$F$223-Assumptions!$B$1369*Assumptions!$F$222-Assumptions!$B$1370*Assumptions!$F$221)+Assumptions!$B$12*Assumptions!$B$13-Assumptions!$B$46))/((Assumptions!$B$199-Assumptions!$B$216)+(Assumptions!$B$46*((Assumptions!$B$203+Assumptions!$B$204+Assumptions!$B$22+Assumptions!$B$215+(1-Assumptions!$B$1365)*Assumptions!$E$226+(1-Assumptions!$B$1366)*Assumptions!$E$225+(1-Assumptions!$B$1367)*Assumptions!$E$224+(1-Assumptions!$B$1368)*Assumptions!$E$223+(1-Assumptions!$B$1369)*Assumptions!$E$222+(1-Assumptions!$B$1370)*Assumptions!$E$221)+Assumptions!$B$13)/((Assumptions!$B$1220-Assumptions!$B$1365*Assumptions!$F$226-Assumptions!$B$1366*Assumptions!$F$225-Assumptions!$B$1367*Assumptions!$F$224-Assumptions!$B$1368*Assumptions!$F$223-Assumptions!$B$1369*Assumptions!$F$222-Assumptions!$B$1370*Assumptions!$F$221)+Assumptions!$B$12*Assumptions!$B$13-Assumptions!$B$46))))<=0,((Assumptions!$B$46*((Assumptions!$B$203+Assumptions!$B$204+Assumptions!$B$22+Assumptions!$B$215+(1-Assumptions!$B$1365)*Assumptions!$E$226+(1-Assumptions!$B$1366)*Assumptions!$E$225+(1-Assumptions!$B$1367)*Assumptions!$E$224+(1-Assumptions!$B$1368)*Assumptions!$E$223+(1-Assumptions!$B$1369)*Assumptions!$E$222+(1-Assumptions!$B$1370)*Assumptions!$E$221)+Assumptions!$B$13)/((Assumptions!$B$1220-Assumptions!$B$1365*Assumptions!$F$226-Assumptions!$B$1366*Assumptions!$F$225-Assumptions!$B$1367*Assumptions!$F$224-Assumptions!$B$1368*Assumptions!$F$223-Assumptions!$B$1369*Assumptions!$F$222-Assumptions!$B$1370*Assumptions!$F$221)+Assumptions!$B$12*Assumptions!$B$13-Assumptions!$B$46))/((Assumptions!$B$199-Assumptions!$B$216)+(Assumptions!$B$46*((Assumptions!$B$203+Assumptions!$B$204+Assumptions!$B$22+Assumptions!$B$215+(1-Assumptions!$B$1365)*Assumptions!$E$226+(1-Assumptions!$B$1366)*Assumptions!$E$225+(1-Assumptions!$B$1367)*Assumptions!$E$224+(1-Assumptions!$B$1368)*Assumptions!$E$223+(1-Assumptions!$B$1369)*Assumptions!$E$222+(1-Assumptions!$B$1370)*Assumptions!$E$221)+Assumptions!$B$13)/((Assumptions!$B$1220-Assumptions!$B$1365*Assumptions!$F$226-Assumptions!$B$1366*Assumptions!$F$225-Assumptions!$B$1367*Assumptions!$F$224-Assumptions!$B$1368*Assumptions!$F$223-Assumptions!$B$1369*Assumptions!$F$222-Assumptions!$B$1370*Assumptions!$F$221)+Assumptions!$B$12*Assumptions!$B$13-Assumptions!$B$46))))>1),NA(),((Assumptions!$B$46*((Assumptions!$B$203+Assumptions!$B$204+Assumptions!$B$22+Assumptions!$B$215+(1-Assumptions!$B$1365)*Assumptions!$E$226+(1-Assumptions!$B$1366)*Assumptions!$E$225+(1-Assumptions!$B$1367)*Assumptions!$E$224+(1-Assumptions!$B$1368)*Assumptions!$E$223+(1-Assumptions!$B$1369)*Assumptions!$E$222+(1-Assumptions!$B$1370)*Assumptions!$E$221)+Assumptions!$B$13)/((Assumptions!$B$1220-Assumptions!$B$1365*Assumptions!$F$226-Assumptions!$B$1366*Assumptions!$F$225-Assumptions!$B$1367*Assumptions!$F$224-Assumptions!$B$1368*Assumptions!$F$223-Assumptions!$B$1369*Assumptions!$F$222-Assumptions!$B$1370*Assumptions!$F$221)+Assumptions!$B$12*Assumptions!$B$13-Assumptions!$B$46))/((Assumptions!$B$199-Assumptions!$B$216)+(Assumptions!$B$46*((Assumptions!$B$203+Assumptions!$B$204+Assumptions!$B$22+Assumptions!$B$215+(1-Assumptions!$B$1365)*Assumptions!$E$226+(1-Assumptions!$B$1366)*Assumptions!$E$225+(1-Assumptions!$B$1367)*Assumptions!$E$224+(1-Assumptions!$B$1368)*Assumptions!$E$223+(1-Assumptions!$B$1369)*Assumptions!$E$222+(1-Assumptions!$B$1370)*Assumptions!$E$221)+Assumptions!$B$13)/((Assumptions!$B$1220-Assumptions!$B$1365*Assumptions!$F$226-Assumptions!$B$1366*Assumptions!$F$225-Assumptions!$B$1367*Assumptions!$F$224-Assumptions!$B$1368*Assumptions!$F$223-Assumptions!$B$1369*Assumptions!$F$222-Assumptions!$B$1370*Assumptions!$F$221)+Assumptions!$B$12*Assumptions!$B$13-Assumptions!$B$46))))) -> 0.018739178 | F6: =IF(Assumptions!$B$6>=((Assumptions!$B$215+(Assumptions!$B$46*((Assumptions!$B$203+Assumptions!$B$204+Assumptions!$B$22+Assumptions!$B$215+(1-Assumptions!$B$1365)*Assumptions!$E$226+(1-Assumptions!$B$1366)*Assumptions!$E$225+(1-Assumptions!$B$1367)*Assumptions!$E$224+(1-Assumptions!$B$1368)*Assumptions!$E$223+(1-Assumptions!$B$1369)*Assumptions!$E$222+(1-Assumptions!$B$1370)*Assumptions!$E$221)+Assumptions!$B$13)/((Assumptions!$B$1220-Assumptions!$B$1365*Assumptions!$F$226-Assumptions!$B$1366*Assumptions!$F$225-Assumptions!$B$1367*Assumptions!$F$224-Assumptions!$B$1368*Assumptions!$F$223-Assumptions!$B$1369*Assumptions!$F$222-Assumptions!$B$1370*Assumptions!$F$221)+Assumptions!$B$12*Assumptions!$B$13-Assumptions!$B$46)))*(((Assumptions!$B$1220-Assumptions!$B$1365*Assumptions!$F$226-Assumptions!$B$1366*Assumptions!$F$225-Assumptions!$B$1367*Assumptions!$F$224-Assumptions!$B$1368*Assumptions!$F$223-Assumptions!$B$1369*Assumptions!$F$222-Assumptions!$B$1370*Assumptions!$F$221)+Assumptions!$B$12*Assumptions!$B$13)/((Assumptions!$B$203+Assumptions!$B$204+Assumptions!$B$22+Assumptions!$B$215+(1-Assumptions!$B$1365)*Assumptions!$E$226+(1-Assumptions!$B$1366)*Assumptions!$E$225+(1-Assumptions!$B$1367)*Assumptions!$E$224+(1-Assumptions!$B$1368)*Assumptions!$E$223+(1-Assumptions!$B$1369)*Assumptions!$E$222+(1-Assumptions!$B$1370)*Assumptions!$E$221)+(Assumptions!$B$46*((Assumptions!$B$203+Assumptions!$B$204+Assumptions!$B$22+Assumptions!$B$215+(1-Assumptions!$B$1365)*Assumptions!$E$226+(1-Assumptions!$B$1366)*Assumptions!$E$225+(1-Assumptions!$B$1367)*Assumptions!$E$224+(1-Assumptions!$B$1368)*Assumptions!$E$223+(1-Assumptions!$B$1369)*Assumptions!$E$222+(1-Assumptions!$B$1370)*Assumptions!$E$221)+Assumptions!$B$13)/((Assumptions!$B$1220-Assumptions!$B$1365*Assumptions!$F$226-Assumptions!$B$1366*Assumptions!$F$225-Assumptions!$B$1367*Assumptions!$F$224-Assumptions!$B$1368*Assumptions!$F$223-Assumptions!$B$1369*Assumptions!$F$222-Assumptions!$B$1370*Assumptions!$F$221)+Assumptions!$B$12*Assumptions!$B$13-Assumptions!$B$46))+Assumptions!$B$13))),"preference","convert") -> convert | G6: =IF(OR(ISNA(E6),F6<>"convert"),"infeasible","feasible") -> feasible
A7: =Assumptions!$B$1380 -> 4000000000 | B7: =IF(OR((Assumptions!$B$1380-Assumptions!$B$1525*Assumptions!$F$226-Assumptions!$B$1526*Assumptions!$F$225-Assumptions!$B$1527*Assumptions!$F$224-Assumptions!$B$1528*Assumptions!$F$223-Assumptions!$B$1529*Assumptions!$F$222-Assumptions!$B$1530*Assumptions!$F$221)+Assumptions!$B$12*Assumptions!$B$13-Assumptions!$B$45<=0,((Assumptions!$B$45*((Assumptions!$B$203+Assumptions!$B$204+Assumptions!$B$22+Assumptions!$B$215+(1-Assumptions!$B$1525)*Assumptions!$E$226+(1-Assumptions!$B$1526)*Assumptions!$E$225+(1-Assumptions!$B$1527)*Assumptions!$E$224+(1-Assumptions!$B$1528)*Assumptions!$E$223+(1-Assumptions!$B$1529)*Assumptions!$E$222+(1-Assumptions!$B$1530)*Assumptions!$E$221)+Assumptions!$B$13)/((Assumptions!$B$1380-Assumptions!$B$1525*Assumptions!$F$226-Assumptions!$B$1526*Assumptions!$F$225-Assumptions!$B$1527*Assumptions!$F$224-Assumptions!$B$1528*Assumptions!$F$223-Assumptions!$B$1529*Assumptions!$F$222-Assumptions!$B$1530*Assumptions!$F$221)+Assumptions!$B$12*Assumptions!$B$13-Assumptions!$B$45))/((Assumptions!$B$199-Assumptions!$B$216)+(Assumptions!$B$45*((Assumptions!$B$203+Assumptions!$B$204+Assumptions!$B$22+Assumptions!$B$215+(1-Assumptions!$B$1525)*Assumptions!$E$226+(1-Assumptions!$B$1526)*Assumptions!$E$225+(1-Assumptions!$B$1527)*Assumptions!$E$224+(1-Assumptions!$B$1528)*Assumptions!$E$223+(1-Assumptions!$B$1529)*Assumptions!$E$222+(1-Assumptions!$B$1530)*Assumptions!$E$221)+Assumptions!$B$13)/((Assumptions!$B$1380-Assumptions!$B$1525*Assumptions!$F$226-Assumptions!$B$1526*Assumptions!$F$225-Assumptions!$B$1527*Assumptions!$F$224-Assumptions!$B$1528*Assumptions!$F$223-Assumptions!$B$1529*Assumptions!$F$222-Assumptions!$B$1530*Assumptions!$F$221)+Assumptions!$B$12*Assumptions!$B$13-Assumptions!$B$45))))<=0,((Assumptions!$B$45*((Assumptions!$B$203+Assumptions!$B$204+Assumptions!$B$22+Assumptions!$B$215+(1-Assumptions!$B$1525)*Assumptions!$E$226+(1-Assumptions!$B$1526)*Assumptions!$E$225+(1-Assumptions!$B$1527)*Assumptions!$E$224+(1-Assumptions!$B$1528)*Assumptions!$E$223+(1-Assumptions!$B$1529)*Assumptions!$E$222+(1-Assumptions!$B$1530)*Assumptions!$E$221)+Assumptions!$B$13)/((Assumptions!$B$1380-Assumptions!$B$1525*Assumptions!$F$226-Assumptions!$B$1526*Assumptions!$F$225-Assumptions!$B$1527*Assumptions!$F$224-Assumptions!$B$1528*Assumptions!$F$223-Assumptions!$B$1529*Assumptions!$F$222-Assumptions!$B$1530*Assumptions!$F$221)+Assumptions!$B$12*Assumptions!$B$13-Assumptions!$B$45))/((Assumptions!$B$199-Assumptions!$B$216)+(Assumptions!$B$45*((Assumptions!$B$203+Assumptions!$B$204+Assumptions!$B$22+Assumptions!$B$215+(1-Assumptions!$B$1525)*Assumptions!$E$226+(1-Assumptions!$B$1526)*Assumptions!$E$225+(1-Assumptions!$B$1527)*Assumptions!$E$224+(1-Assumptions!$B$1528)*Assumptions!$E$223+(1-Assumptions!$B$1529)*Assumptions!$E$222+(1-Assumptions!$B$1530)*Assumptions!$E$221)+Assumptions!$B$13)/((Assumptions!$B$1380-Assumptions!$B$1525*Assumptions!$F$226-Assumptions!$B$1526*Assumptions!$F$225-Assumptions!$B$1527*Assumptions!$F$224-Assumptions!$B$1528*Assumptions!$F$223-Assumptions!$B$1529*Assumptions!$F$222-Assumptions!$B$1530*Assumptions!$F$221)+Assumptions!$B$12*Assumptions!$B$13-Assumptions!$B$45))))>1),NA(),((Assumptions!$B$45*((Assumptions!$B$203+Assumptions!$B$204+Assumptions!$B$22+Assumptions!$B$215+(1-Assumptions!$B$1525)*Assumptions!$E$226+(1-Assumptions!$B$1526)*Assumptions!$E$225+(1-Assumptions!$B$1527)*Assumptions!$E$224+(1-Assumptions!$B$1528)*Assumptions!$E$223+(1-Assumptions!$B$1529)*Assumptions!$E$222+(1-Assumptions!$B$1530)*Assumptions!$E$221)+Assumptions!$B$13)/((Assumptions!$B$1380-Assumptions!$B$1525*Assumptions!$F$226-Assumptions!$B$1526*Assumptions!$F$225-Assumptions!$B$1527*Assumptions!$F$224-Assumptions!$B$1528*Assumptions!$F$223-Assumptions!$B$1529*Assumptions!$F$222-Assumptions!$B$1530*Assumptions!$F$221)+Assumptions!$B$12*Assumptions!$B$13-Assumptions!$B$45))/((Assumptions!$B$199-Assumptions!$B$216)+(Assumptions!$B$45*((Assumptions!$B$203+Assumptions!$B$204+Assumptions!$B$22+Assumptions!$B$215+(1-Assumptions!$B$1525)*Assumptions!$E$226+(1-Assumptions!$B$1526)*Assumptions!$E$225+(1-Assumptions!$B$1527)*Assumptions!$E$224+(1-Assumptions!$B$1528)*Assumptions!$E$223+(1-Assumptions!$B$1529)*Assumptions!$E$222+(1-Assumptions!$B$1530)*Assumptions!$E$221)+Assumptions!$B$13)/((Assumptions!$B$1380-Assumptions!$B$1525*Assumptions!$F$226-Assumptions!$B$1526*Assumptions!$F$225-Assumptions!$B$1527*Assumptions!$F$224-Assumptions!$B$1528*Assumptions!$F$223-Assumptions!$B$1529*Assumptions!$F$222-Assumptions!$B$1530*Assumptions!$F$221)+Assumptions!$B$12*Assumptions!$B$13-Assumptions!$B$45))))) -> 0.0070096974 | C7: =IF(Assumptions!$B$6>=((Assumptions!$B$215+(Assumptions!$B$45*((Assumptions!$B$203+Assumptions!$B$204+Assumptions!$B$22+Assumptions!$B$215+(1-Assumptions!$B$1525)*Assumptions!$E$226+(1-Assumptions!$B$1526)*Assumptions!$E$225+(1-Assumptions!$B$1527)*Assumptions!$E$224+(1-Assumptions!$B$1528)*Assumptions!$E$223+(1-Assumptions!$B$1529)*Assumptions!$E$222+(1-Assumptions!$B$1530)*Assumptions!$E$221)+Assumptions!$B$13)/((Assumptions!$B$1380-Assumptions!$B$1525*Assumptions!$F$226-Assumptions!$B$1526*Assumptions!$F$225-Assumptions!$B$1527*Assumptions!$F$224-Assumptions!$B$1528*Assumptions!$F$223-Assumptions!$B$1529*Assumptions!$F$222-Assumptions!$B$1530*Assumptions!$F$221)+Assumptions!$B$12*Assumptions!$B$13-Assumptions!$B$45)))*(((Assumptions!$B$1380-Assumptions!$B$1525*Assumptions!$F$226-Assumptions!$B$1526*Assumptions!$F$225-Assumptions!$B$1527*Assumptions!$F$224-Assumptions!$B$1528*Assumptions!$F$223-Assumptions!$B$1529*Assumptions!$F$222-Assumptions!$B$1530*Assumptions!$F$221)+Assumptions!$B$12*Assumptions!$B$13)/((Assumptions!$B$203+Assumptions!$B$204+Assumptions!$B$22+Assumptions!$B$215+(1-Assumptions!$B$1525)*Assumptions!$E$226+(1-Assumptions!$B$1526)*Assumptions!$E$225+(1-Assumptions!$B$1527)*Assumptions!$E$224+(1-Assumptions!$B$1528)*Assumptions!$E$223+(1-Assumptions!$B$1529)*Assumptions!$E$222+(1-Assumptions!$B$1530)*Assumptions!$E$221)+(Assumptions!$B$45*((Assumptions!$B$203+Assumptions!$B$204+Assumptions!$B$22+Assumptions!$B$215+(1-Assumptions!$B$1525)*Assumptions!$E$226+(1-Assumptions!$B$1526)*Assumptions!$E$225+(1-Assumptions!$B$1527)*Assumptions!$E$224+(1-Assumptions!$B$1528)*Assumptions!$E$223+(1-Assumptions!$B$1529)*Assumptions!$E$222+(1-Assumptions!$B$1530)*Assumptions!$E$221)+Assumptions!$B$13)/((Assumptions!$B$1380-Assumptions!$B$1525*Assumptions!$F$226-Assumptions!$B$1526*Assumptions!$F$225-Assumptions!$B$1527*Assumptions!$F$224-Assumptions!$B$1528*Assumptions!$F$223-Assumptions!$B$1529*Assumptions!$F$222-Assumptions!$B$1530*Assumptions!$F$221)+Assumptions!$B$12*Assumptions!$B$13-Assumptions!$B$45))+Assumptions!$B$13))),"preference","convert") -> convert | D7: =IF(OR(ISNA(B7),C7<>"convert"),"infeasible","feasible") -> feasible | E7: =IF(OR((Assumptions!$B$1380-Assumptions!$B$1525*Assumptions!$F$226-Assumptions!$B$1526*Assumptions!$F$225-Assumptions!$B$1527*Assumptions!$F$224-Assumptions!$B$1528*Assumptions!$F$223-Assumptions!$B$1529*Assumptions!$F$222-Assumptions!$B$1530*Assumptions!$F$221)+Assumptions!$B$12*Assumptions!$B$13-Assumptions!$B$46<=0,((Assumptions!$B$46*((Assumptions!$B$203+Assumptions!$B$204+Assumptions!$B$22+Assumptions!$B$215+(1-Assumptions!$B$1525)*Assumptions!$E$226+(1-Assumptions!$B$1526)*Assumptions!$E$225+(1-Assumptions!$B$1527)*Assumptions!$E$224+(1-Assumptions!$B$1528)*Assumptions!$E$223+(1-Assumptions!$B$1529)*Assumptions!$E$222+(1-Assumptions!$B$1530)*Assumptions!$E$221)+Assumptions!$B$13)/((Assumptions!$B$1380-Assumptions!$B$1525*Assumptions!$F$226-Assumptions!$B$1526*Assumptions!$F$225-Assumptions!$B$1527*Assumptions!$F$224-Assumptions!$B$1528*Assumptions!$F$223-Assumptions!$B$1529*Assumptions!$F$222-Assumptions!$B$1530*Assumptions!$F$221)+Assumptions!$B$12*Assumptions!$B$13-Assumptions!$B$46))/((Assumptions!$B$199-Assumptions!$B$216)+(Assumptions!$B$46*((Assumptions!$B$203+Assumptions!$B$204+Assumptions!$B$22+Assumptions!$B$215+(1-Assumptions!$B$1525)*Assumptions!$E$226+(1-Assumptions!$B$1526)*Assumptions!$E$225+(1-Assumptions!$B$1527)*Assumptions!$E$224+(1-Assumptions!$B$1528)*Assumptions!$E$223+(1-Assumptions!$B$1529)*Assumptions!$E$222+(1-Assumptions!$B$1530)*Assumptions!$E$221)+Assumptions!$B$13)/((Assumptions!$B$1380-Assumptions!$B$1525*Assumptions!$F$226-Assumptions!$B$1526*Assumptions!$F$225-Assumptions!$B$1527*Assumptions!$F$224-Assumptions!$B$1528*Assumptions!$F$223-Assumptions!$B$1529*Assumptions!$F$222-Assumptions!$B$1530*Assumptions!$F$221)+Assumptions!$B$12*Assumptions!$B$13-Assumptions!$B$46))))<=0,((Assumptions!$B$46*((Assumptions!$B$203+Assumptions!$B$204+Assumptions!$B$22+Assumptions!$B$215+(1-Assumptions!$B$1525)*Assumptions!$E$226+(1-Assumptions!$B$1526)*Assumptions!$E$225+(1-Assumptions!$B$1527)*Assumptions!$E$224+(1-Assumptions!$B$1528)*Assumptions!$E$223+(1-Assumptions!$B$1529)*Assumptions!$E$222+(1-Assumptions!$B$1530)*Assumptions!$E$221)+Assumptions!$B$13)/((Assumptions!$B$1380-Assumptions!$B$1525*Assumptions!$F$226-Assumptions!$B$1526*Assumptions!$F$225-Assumptions!$B$1527*Assumptions!$F$224-Assumptions!$B$1528*Assumptions!$F$223-Assumptions!$B$1529*Assumptions!$F$222-Assumptions!$B$1530*Assumptions!$F$221)+Assumptions!$B$12*Assumptions!$B$13-Assumptions!$B$46))/((Assumptions!$B$199-Assumptions!$B$216)+(Assumptions!$B$46*((Assumptions!$B$203+Assumptions!$B$204+Assumptions!$B$22+Assumptions!$B$215+(1-Assumptions!$B$1525)*Assumptions!$E$226+(1-Assumptions!$B$1526)*Assumptions!$E$225+(1-Assumptions!$B$1527)*Assumptions!$E$224+(1-Assumptions!$B$1528)*Assumptions!$E$223+(1-Assumptions!$B$1529)*Assumptions!$E$222+(1-Assumptions!$B$1530)*Assumptions!$E$221)+Assumptions!$B$13)/((Assumptions!$B$1380-Assumptions!$B$1525*Assumptions!$F$226-Assumptions!$B$1526*Assumptions!$F$225-Assumptions!$B$1527*Assumptions!$F$224-Assumptions!$B$1528*Assumptions!$F$223-Assumptions!$B$1529*Assumptions!$F$222-Assumptions!$B$1530*Assumptions!$F$221)+Assumptions!$B$12*Assumptions!$B$13-Assumptions!$B$46))))>1),NA(),((Assumptions!$B$46*((Assumptions!$B$203+Assumptions!$B$204+Assumptions!$B$22+Assumptions!$B$215+(1-Assumptions!$B$1525)*Assumptions!$E$226+(1-Assumptions!$B$1526)*Assumptions!$E$225+(1-Assumptions!$B$1527)*Assumptions!$E$224+(1-Assumptions!$B$1528)*Assumptions!$E$223+(1-Assumptions!$B$1529)*Assumptions!$E$222+(1-Assumptions!$B$1530)*Assumptions!$E$221)+Assumptions!$B$13)/((Assumptions!$B$1380-Assumptions!$B$1525*Assumptions!$F$226-Assumptions!$B$1526*Assumptions!$F$225-Assumptions!$B$1527*Assumptions!$F$224-Assumptions!$B$1528*Assumptions!$F$223-Assumptions!$B$1529*Assumptions!$F$222-Assumptions!$B$1530*Assumptions!$F$221)+Assumptions!$B$12*Assumptions!$B$13-Assumptions!$B$46))/((Assumptions!$B$199-Assumptions!$B$216)+(Assumptions!$B$46*((Assumptions!$B$203+Assumptions!$B$204+Assumptions!$B$22+Assumptions!$B$215+(1-Assumptions!$B$1525)*Assumptions!$E$226+(1-Assumptions!$B$1526)*Assumptions!$E$225+(1-Assumptions!$B$1527)*Assumptions!$E$224+(1-Assumptions!$B$1528)*Assumptions!$E$223+(1-Assumptions!$B$1529)*Assumptions!$E$222+(1-Assumptions!$B$1530)*Assumptions!$E$221)+Assumptions!$B$13)/((Assumptions!$B$1380-Assumptions!$B$1525*Assumptions!$F$226-Assumptions!$B$1526*Assumptions!$F$225-Assumptions!$B$1527*Assumptions!$F$224-Assumptions!$B$1528*Assumptions!$F$223-Assumptions!$B$1529*Assumptions!$F$222-Assumptions!$B$1530*Assumptions!$F$221)+Assumptions!$B$12*Assumptions!$B$13-Assumptions!$B$46))))) -> 0.0093477878 | F7: =IF(Assumptions!$B$6>=((Assumptions!$B$215+(Assumptions!$B$46*((Assumptions!$B$203+Assumptions!$B$204+Assumptions!$B$22+Assumptions!$B$215+(1-Assumptions!$B$1525)*Assumptions!$E$226+(1-Assumptions!$B$1526)*Assumptions!$E$225+(1-Assumptions!$B$1527)*Assumptions!$E$224+(1-Assumptions!$B$1528)*Assumptions!$E$223+(1-Assumptions!$B$1529)*Assumptions!$E$222+(1-Assumptions!$B$1530)*Assumptions!$E$221)+Assumptions!$B$13)/((Assumptions!$B$1380-Assumptions!$B$1525*Assumptions!$F$226-Assumptions!$B$1526*Assumptions!$F$225-Assumptions!$B$1527*Assumptions!$F$224-Assumptions!$B$1528*Assumptions!$F$223-Assumptions!$B$1529*Assumptions!$F$222-Assumptions!$B$1530*Assumptions!$F$221)+Assumptions!$B$12*Assumptions!$B$13-Assumptions!$B$46)))*(((Assumptions!$B$1380-Assumptions!$B$1525*Assumptions!$F$226-Assumptions!$B$1526*Assumptions!$F$225-Assumptions!$B$1527*Assumptions!$F$224-Assumptions!$B$1528*Assumptions!$F$223-Assumptions!$B$1529*Assumptions!$F$222-Assumptions!$B$1530*Assumptions!$F$221)+Assumptions!$B$12*Assumptions!$B$13)/((Assumptions!$B$203+Assumptions!$B$204+Assumptions!$B$22+Assumptions!$B$215+(1-Assumptions!$B$1525)*Assumptions!$E$226+(1-Assumptions!$B$1526)*Assumptions!$E$225+(1-Assumptions!$B$1527)*Assumptions!$E$224+(1-Assumptions!$B$1528)*Assumptions!$E$223+(1-Assumptions!$B$1529)*Assumptions!$E$222+(1-Assumptions!$B$1530)*Assumptions!$E$221)+(Assumptions!$B$46*((Assumptions!$B$203+Assumptions!$B$204+Assumptions!$B$22+Assumptions!$B$215+(1-Assumptions!$B$1525)*Assumptions!$E$226+(1-Assumptions!$B$1526)*Assumptions!$E$225+(1-Assumptions!$B$1527)*Assumptions!$E$224+(1-Assumptions!$B$1528)*Assumptions!$E$223+(1-Assumptions!$B$1529)*Assumptions!$E$222+(1-Assumptions!$B$1530)*Assumptions!$E$221)+Assumptions!$B$13)/((Assumptions!$B$1380-Assumptions!$B$1525*Assumptions!$F$226-Assumptions!$B$1526*Assumptions!$F$225-Assumptions!$B$1527*Assumptions!$F$224-Assumptions!$B$1528*Assumptions!$F$223-Assumptions!$B$1529*Assumptions!$F$222-Assumptions!$B$1530*Assumptions!$F$221)+Assumptions!$B$12*Assumptions!$B$13-Assumptions!$B$46))+Assumptions!$B$13))),"preference","convert") -> convert | G7: =IF(OR(ISNA(E7),F7<>"convert"),"infeasible","feasible") -> feasible
A8: =Assumptions!$B$1540 -> 8000000000 | B8: =IF(OR((Assumptions!$B$1540-Assumptions!$B$1685*Assumptions!$F$226-Assumptions!$B$1686*Assumptions!$F$225-Assumptions!$B$1687*Assumptions!$F$224-Assumptions!$B$1688*Assumptions!$F$223-Assumptions!$B$1689*Assumptions!$F$222-Assumptions!$B$1690*Assumptions!$F$221)+Assumptions!$B$12*Assumptions!$B$13-Assumptions!$B$45<=0,((Assumptions!$B$45*((Assumptions!$B$203+Assumptions!$B$204+Assumptions!$B$22+Assumptions!$B$215+(1-Assumptions!$B$1685)*Assumptions!$E$226+(1-Assumptions!$B$1686)*Assumptions!$E$225+(1-Assumptions!$B$1687)*Assumptions!$E$224+(1-Assumptions!$B$1688)*Assumptions!$E$223+(1-Assumptions!$B$1689)*Assumptions!$E$222+(1-Assumptions!$B$1690)*Assumptions!$E$221)+Assumptions!$B$13)/((Assumptions!$B$1540-Assumptions!$B$1685*Assumptions!$F$226-Assumptions!$B$1686*Assumptions!$F$225-Assumptions!$B$1687*Assumptions!$F$224-Assumptions!$B$1688*Assumptions!$F$223-Assumptions!$B$1689*Assumptions!$F$222-Assumptions!$B$1690*Assumptions!$F$221)+Assumptions!$B$12*Assumptions!$B$13-Assumptions!$B$45))/((Assumptions!$B$199-Assumptions!$B$216)+(Assumptions!$B$45*((Assumptions!$B$203+Assumptions!$B$204+Assumptions!$B$22+Assumptions!$B$215+(1-Assumptions!$B$1685)*Assumptions!$E$226+(1-Assumptions!$B$1686)*Assumptions!$E$225+(1-Assumptions!$B$1687)*Assumptions!$E$224+(1-Assumptions!$B$1688)*Assumptions!$E$223+(1-Assumptions!$B$1689)*Assumptions!$E$222+(1-Assumptions!$B$1690)*Assumptions!$E$221)+Assumptions!$B$13)/((Assumptions!$B$1540-Assumptions!$B$1685*Assumptions!$F$226-Assumptions!$B$1686*Assumptions!$F$225-Assumptions!$B$1687*Assumptions!$F$224-Assumptions!$B$1688*Assumptions!$F$223-Assumptions!$B$1689*Assumptions!$F$222-Assumptions!$B$1690*Assumptions!$F$221)+Assumptions!$B$12*Assumptions!$B$13-Assumptions!$B$45))))<=0,((Assumptions!$B$45*((Assumptions!$B$203+Assumptions!$B$204+Assumptions!$B$22+Assumptions!$B$215+(1-Assumptions!$B$1685)*Assumptions!$E$226+(1-Assumptions!$B$1686)*Assumptions!$E$225+(1-Assumptions!$B$1687)*Assumptions!$E$224+(1-Assumptions!$B$1688)*Assumptions!$E$223+(1-Assumptions!$B$1689)*Assumptions!$E$222+(1-Assumptions!$B$1690)*Assumptions!$E$221)+Assumptions!$B$13)/((Assumptions!$B$1540-Assumptions!$B$1685*Assumptions!$F$226-Assumptions!$B$1686*Assumptions!$F$225-Assumptions!$B$1687*Assumptions!$F$224-Assumptions!$B$1688*Assumptions!$F$223-Assumptions!$B$1689*Assumptions!$F$222-Assumptions!$B$1690*Assumptions!$F$221)+Assumptions!$B$12*Assumptions!$B$13-Assumptions!$B$45))/((Assumptions!$B$199-Assumptions!$B$216)+(Assumptions!$B$45*((Assumptions!$B$203+Assumptions!$B$204+Assumptions!$B$22+Assumptions!$B$215+(1-Assumptions!$B$1685)*Assumptions!$E$226+(1-Assumptions!$B$1686)*Assumptions!$E$225+(1-Assumptions!$B$1687)*Assumptions!$E$224+(1-Assumptions!$B$1688)*Assumptions!$E$223+(1-Assumptions!$B$1689)*Assumptions!$E$222+(1-Assumptions!$B$1690)*Assumptions!$E$221)+Assumptions!$B$13)/((Assumptions!$B$1540-Assumptions!$B$1685*Assumptions!$F$226-Assumptions!$B$1686*Assumptions!$F$225-Assumptions!$B$1687*Assumptions!$F$224-Assumptions!$B$1688*Assumptions!$F$223-Assumptions!$B$1689*Assumptions!$F$222-Assumptions!$B$1690*Assumptions!$F$221)+Assumptions!$B$12*Assumptions!$B$13-Assumptions!$B$45))))>1),NA(),((Assumptions!$B$45*((Assumptions!$B$203+Assumptions!$B$204+Assumptions!$B$22+Assumptions!$B$215+(1-Assumptions!$B$1685)*Assumptions!$E$226+(1-Assumptions!$B$1686)*Assumptions!$E$225+(1-Assumptions!$B$1687)*Assumptions!$E$224+(1-Assumptions!$B$1688)*Assumptions!$E$223+(1-Assumptions!$B$1689)*Assumptions!$E$222+(1-Assumptions!$B$1690)*Assumptions!$E$221)+Assumptions!$B$13)/((Assumptions!$B$1540-Assumptions!$B$1685*Assumptions!$F$226-Assumptions!$B$1686*Assumptions!$F$225-Assumptions!$B$1687*Assumptions!$F$224-Assumptions!$B$1688*Assumptions!$F$223-Assumptions!$B$1689*Assumptions!$F$222-Assumptions!$B$1690*Assumptions!$F$221)+Assumptions!$B$12*Assumptions!$B$13-Assumptions!$B$45))/((Assumptions!$B$199-Assumptions!$B$216)+(Assumptions!$B$45*((Assumptions!$B$203+Assumptions!$B$204+Assumptions!$B$22+Assumptions!$B$215+(1-Assumptions!$B$1685)*Assumptions!$E$226+(1-Assumptions!$B$1686)*Assumptions!$E$225+(1-Assumptions!$B$1687)*Assumptions!$E$224+(1-Assumptions!$B$1688)*Assumptions!$E$223+(1-Assumptions!$B$1689)*Assumptions!$E$222+(1-Assumptions!$B$1690)*Assumptions!$E$221)+Assumptions!$B$13)/((Assumptions!$B$1540-Assumptions!$B$1685*Assumptions!$F$226-Assumptions!$B$1686*Assumptions!$F$225-Assumptions!$B$1687*Assumptions!$F$224-Assumptions!$B$1688*Assumptions!$F$223-Assumptions!$B$1689*Assumptions!$F$222-Assumptions!$B$1690*Assumptions!$F$221)+Assumptions!$B$12*Assumptions!$B$13-Assumptions!$B$45))))) -> 0.0035050864 | C8: =IF(Assumptions!$B$6>=((Assumptions!$B$215+(Assumptions!$B$45*((Assumptions!$B$203+Assumptions!$B$204+Assumptions!$B$22+Assumptions!$B$215+(1-Assumptions!$B$1685)*Assumptions!$E$226+(1-Assumptions!$B$1686)*Assumptions!$E$225+(1-Assumptions!$B$1687)*Assumptions!$E$224+(1-Assumptions!$B$1688)*Assumptions!$E$223+(1-Assumptions!$B$1689)*Assumptions!$E$222+(1-Assumptions!$B$1690)*Assumptions!$E$221)+Assumptions!$B$13)/((Assumptions!$B$1540-Assumptions!$B$1685*Assumptions!$F$226-Assumptions!$B$1686*Assumptions!$F$225-Assumptions!$B$1687*Assumptions!$F$224-Assumptions!$B$1688*Assumptions!$F$223-Assumptions!$B$1689*Assumptions!$F$222-Assumptions!$B$1690*Assumptions!$F$221)+Assumptions!$B$12*Assumptions!$B$13-Assumptions!$B$45)))*(((Assumptions!$B$1540-Assumptions!$B$1685*Assumptions!$F$226-Assumptions!$B$1686*Assumptions!$F$225-Assumptions!$B$1687*Assumptions!$F$224-Assumptions!$B$1688*Assumptions!$F$223-Assumptions!$B$1689*Assumptions!$F$222-Assumptions!$B$1690*Assumptions!$F$221)+Assumptions!$B$12*Assumptions!$B$13)/((Assumptions!$B$203+Assumptions!$B$204+Assumptions!$B$22+Assumptions!$B$215+(1-Assumptions!$B$1685)*Assumptions!$E$226+(1-Assumptions!$B$1686)*Assumptions!$E$225+(1-Assumptions!$B$1687)*Assumptions!$E$224+(1-Assumptions!$B$1688)*Assumptions!$E$223+(1-Assumptions!$B$1689)*Assumptions!$E$222+(1-Assumptions!$B$1690)*Assumptions!$E$221)+(Assumptions!$B$45*((Assumptions!$B$203+Assumptions!$B$204+Assumptions!$B$22+Assumptions!$B$215+(1-Assumptions!$B$1685)*Assumptions!$E$226+(1-Assumptions!$B$1686)*Assumptions!$E$225+(1-Assumptions!$B$1687)*Assumptions!$E$224+(1-Assumptions!$B$1688)*Assumptions!$E$223+(1-Assumptions!$B$1689)*Assumptions!$E$222+(1-Assumptions!$B$1690)*Assumptions!$E$221)+Assumptions!$B$13)/((Assumptions!$B$1540-Assumptions!$B$1685*Assumptions!$F$226-Assumptions!$B$1686*Assumptions!$F$225-Assumptions!$B$1687*Assumptions!$F$224-Assumptions!$B$1688*Assumptions!$F$223-Assumptions!$B$1689*Assumptions!$F$222-Assumptions!$B$1690*Assumptions!$F$221)+Assumptions!$B$12*Assumptions!$B$13-Assumptions!$B$45))+Assumptions!$B$13))),"preference","convert") -> convert | D8: =IF(OR(ISNA(B8),C8<>"convert"),"infeasible","feasible") -> feasible | E8: =IF(OR((Assumptions!$B$1540-Assumptions!$B$1685*Assumptions!$F$226-Assumptions!$B$1686*Assumptions!$F$225-Assumptions!$B$1687*Assumptions!$F$224-Assumptions!$B$1688*Assumptions!$F$223-Assumptions!$B$1689*Assumptions!$F$222-Assumptions!$B$1690*Assumptions!$F$221)+Assumptions!$B$12*Assumptions!$B$13-Assumptions!$B$46<=0,((Assumptions!$B$46*((Assumptions!$B$203+Assumptions!$B$204+Assumptions!$B$22+Assumptions!$B$215+(1-Assumptions!$B$1685)*Assumptions!$E$226+(1-Assumptions!$B$1686)*Assumptions!$E$225+(1-Assumptions!$B$1687)*Assumptions!$E$224+(1-Assumptions!$B$1688)*Assumptions!$E$223+(1-Assumptions!$B$1689)*Assumptions!$E$222+(1-Assumptions!$B$1690)*Assumptions!$E$221)+Assumptions!$B$13)/((Assumptions!$B$1540-Assumptions!$B$1685*Assumptions!$F$226-Assumptions!$B$1686*Assumptions!$F$225-Assumptions!$B$1687*Assumptions!$F$224-Assumptions!$B$1688*Assumptions!$F$223-Assumptions!$B$1689*Assumptions!$F$222-Assumptions!$B$1690*Assumptions!$F$221)+Assumptions!$B$12*Assumptions!$B$13-Assumptions!$B$46))/((Assumptions!$B$199-Assumptions!$B$216)+(Assumptions!$B$46*((Assumptions!$B$203+Assumptions!$B$204+Assumptions!$B$22+Assumptions!$B$215+(1-Assumptions!$B$1685)*Assumptions!$E$226+(1-Assumptions!$B$1686)*Assumptions!$E$225+(1-Assumptions!$B$1687)*Assumptions!$E$224+(1-Assumptions!$B$1688)*Assumptions!$E$223+(1-Assumptions!$B$1689)*Assumptions!$E$222+(1-Assumptions!$B$1690)*Assumptions!$E$221)+Assumptions!$B$13)/((Assumptions!$B$1540-Assumptions!$B$1685*Assumptions!$F$226-Assumptions!$B$1686*Assumptions!$F$225-Assumptions!$B$1687*Assumptions!$F$224-Assumptions!$B$1688*Assumptions!$F$223-Assumptions!$B$1689*Assumptions!$F$222-Assumptions!$B$1690*Assumptions!$F$221)+Assumptions!$B$12*Assumptions!$B$13-Assumptions!$B$46))))<=0,((Assumptions!$B$46*((Assumptions!$B$203+Assumptions!$B$204+Assumptions!$B$22+Assumptions!$B$215+(1-Assumptions!$B$1685)*Assumptions!$E$226+(1-Assumptions!$B$1686)*Assumptions!$E$225+(1-Assumptions!$B$1687)*Assumptions!$E$224+(1-Assumptions!$B$1688)*Assumptions!$E$223+(1-Assumptions!$B$1689)*Assumptions!$E$222+(1-Assumptions!$B$1690)*Assumptions!$E$221)+Assumptions!$B$13)/((Assumptions!$B$1540-Assumptions!$B$1685*Assumptions!$F$226-Assumptions!$B$1686*Assumptions!$F$225-Assumptions!$B$1687*Assumptions!$F$224-Assumptions!$B$1688*Assumptions!$F$223-Assumptions!$B$1689*Assumptions!$F$222-Assumptions!$B$1690*Assumptions!$F$221)+Assumptions!$B$12*Assumptions!$B$13-Assumptions!$B$46))/((Assumptions!$B$199-Assumptions!$B$216)+(Assumptions!$B$46*((Assumptions!$B$203+Assumptions!$B$204+Assumptions!$B$22+Assumptions!$B$215+(1-Assumptions!$B$1685)*Assumptions!$E$226+(1-Assumptions!$B$1686)*Assumptions!$E$225+(1-Assumptions!$B$1687)*Assumptions!$E$224+(1-Assumptions!$B$1688)*Assumptions!$E$223+(1-Assumptions!$B$1689)*Assumptions!$E$222+(1-Assumptions!$B$1690)*Assumptions!$E$221)+Assumptions!$B$13)/((Assumptions!$B$1540-Assumptions!$B$1685*Assumptions!$F$226-Assumptions!$B$1686*Assumptions!$F$225-Assumptions!$B$1687*Assumptions!$F$224-Assumptions!$B$1688*Assumptions!$F$223-Assumptions!$B$1689*Assumptions!$F$222-Assumptions!$B$1690*Assumptions!$F$221)+Assumptions!$B$12*Assumptions!$B$13-Assumptions!$B$46))))>1),NA(),((Assumptions!$B$46*((Assumptions!$B$203+Assumptions!$B$204+Assumptions!$B$22+Assumptions!$B$215+(1-Assumptions!$B$1685)*Assumptions!$E$226+(1-Assumptions!$B$1686)*Assumptions!$E$225+(1-Assumptions!$B$1687)*Assumptions!$E$224+(1-Assumptions!$B$1688)*Assumptions!$E$223+(1-Assumptions!$B$1689)*Assumptions!$E$222+(1-Assumptions!$B$1690)*Assumptions!$E$221)+Assumptions!$B$13)/((Assumptions!$B$1540-Assumptions!$B$1685*Assumptions!$F$226-Assumptions!$B$1686*Assumptions!$F$225-Assumptions!$B$1687*Assumptions!$F$224-Assumptions!$B$1688*Assumptions!$F$223-Assumptions!$B$1689*Assumptions!$F$222-Assumptions!$B$1690*Assumptions!$F$221)+Assumptions!$B$12*Assumptions!$B$13-Assumptions!$B$46))/((Assumptions!$B$199-Assumptions!$B$216)+(Assumptions!$B$46*((Assumptions!$B$203+Assumptions!$B$204+Assumptions!$B$22+Assumptions!$B$215+(1-Assumptions!$B$1685)*Assumptions!$E$226+(1-Assumptions!$B$1686)*Assumptions!$E$225+(1-Assumptions!$B$1687)*Assumptions!$E$224+(1-Assumptions!$B$1688)*Assumptions!$E$223+(1-Assumptions!$B$1689)*Assumptions!$E$222+(1-Assumptions!$B$1690)*Assumptions!$E$221)+Assumptions!$B$13)/((Assumptions!$B$1540-Assumptions!$B$1685*Assumptions!$F$226-Assumptions!$B$1686*Assumptions!$F$225-Assumptions!$B$1687*Assumptions!$F$224-Assumptions!$B$1688*Assumptions!$F$223-Assumptions!$B$1689*Assumptions!$F$222-Assumptions!$B$1690*Assumptions!$F$221)+Assumptions!$B$12*Assumptions!$B$13-Assumptions!$B$46))))) -> 0.0046738297 | F8: =IF(Assumptions!$B$6>=((Assumptions!$B$215+(Assumptions!$B$46*((Assumptions!$B$203+Assumptions!$B$204+Assumptions!$B$22+Assumptions!$B$215+(1-Assumptions!$B$1685)*Assumptions!$E$226+(1-Assumptions!$B$1686)*Assumptions!$E$225+(1-Assumptions!$B$1687)*Assumptions!$E$224+(1-Assumptions!$B$1688)*Assumptions!$E$223+(1-Assumptions!$B$1689)*Assumptions!$E$222+(1-Assumptions!$B$1690)*Assumptions!$E$221)+Assumptions!$B$13)/((Assumptions!$B$1540-Assumptions!$B$1685*Assumptions!$F$226-Assumptions!$B$1686*Assumptions!$F$225-Assumptions!$B$1687*Assumptions!$F$224-Assumptions!$B$1688*Assumptions!$F$223-Assumptions!$B$1689*Assumptions!$F$222-Assumptions!$B$1690*Assumptions!$F$221)+Assumptions!$B$12*Assumptions!$B$13-Assumptions!$B$46)))*(((Assumptions!$B$1540-Assumptions!$B$1685*Assumptions!$F$226-Assumptions!$B$1686*Assumptions!$F$225-Assumptions!$B$1687*Assumptions!$F$224-Assumptions!$B$1688*Assumptions!$F$223-Assumptions!$B$1689*Assumptions!$F$222-Assumptions!$B$1690*Assumptions!$F$221)+Assumptions!$B$12*Assumptions!$B$13)/((Assumptions!$B$203+Assumptions!$B$204+Assumptions!$B$22+Assumptions!$B$215+(1-Assumptions!$B$1685)*Assumptions!$E$226+(1-Assumptions!$B$1686)*Assumptions!$E$225+(1-Assumptions!$B$1687)*Assumptions!$E$224+(1-Assumptions!$B$1688)*Assumptions!$E$223+(1-Assumptions!$B$1689)*Assumptions!$E$222+(1-Assumptions!$B$1690)*Assumptions!$E$221)+(Assumptions!$B$46*((Assumptions!$B$203+Assumptions!$B$204+Assumptions!$B$22+Assumptions!$B$215+(1-Assumptions!$B$1685)*Assumptions!$E$226+(1-Assumptions!$B$1686)*Assumptions!$E$225+(1-Assumptions!$B$1687)*Assumptions!$E$224+(1-Assumptions!$B$1688)*Assumptions!$E$223+(1-Assumptions!$B$1689)*Assumptions!$E$222+(1-Assumptions!$B$1690)*Assumptions!$E$221)+Assumptions!$B$13)/((Assumptions!$B$1540-Assumptions!$B$1685*Assumptions!$F$226-Assumptions!$B$1686*Assumptions!$F$225-Assumptions!$B$1687*Assumptions!$F$224-Assumptions!$B$1688*Assumptions!$F$223-Assumptions!$B$1689*Assumptions!$F$222-Assumptions!$B$1690*Assumptions!$F$221)+Assumptions!$B$12*Assumptions!$B$13-Assumptions!$B$46))+Assumptions!$B$13))),"preference","convert") -> convert | G8: =IF(OR(ISNA(E8),F8<>"convert"),"infeasible","feasible") -> feasible
