Workbook

Sheet Assumptions
A1: Kelvin Dynamics - Series F Analysis
A3: Model knobs
A4: Key | B4: Label | C4: Value | D4: Units | E4: Source / Notes
A5: series_f_pre_money_usd | B5: Series F pre-money | C5: 1400000000 | D5: USD | E5: Series F pre-money valuation
A6: series_f_primary_raise_usd | B6: Series F primary raise | C6: 30000000 | D6: USD | E6: New Series F primary capital
A7: series_f_secondary_raise_usd | B7: Series F secondary tender raise | C7: 15000000 | D7: USD | E7: Secondary tender from founders
A8: series_f_tender_pps_multiplier | B8: Tender PPS multiplier | C8: 0.85 | D8: fraction | E8: Tender PPS = multiplier x F_PPS
A9: esop_refresh_target_post_f | B9: ESOP refresh target % of post-F FD | C9: 0.13 | D9: fraction | E9: Post-F option pool as fraction of post-F FD
A10: our_fund_check_usd | B10: Our fund check size | C10: 10000000 | D10: USD | E10: Our fund's Series F primary check (= 1/3 of primary)
A11: f_lead_primary_check_usd | B11: F_LEAD primary check size | C11: 20000000 | D11: USD | E11: F_LEAD's Series F primary check (= 2/3 of primary)
A12: option_strike_usd | B12: Issued option strike | C12: 1 | D12: USD | E12: Option exercise price for issued options at exit
A13: pre_f_options_issued | B13: Pre-F issued options | C13: 2500000 | D13: shares | E13: Issued options outstanding pre-F (carryover from v3 post-E)
A14: pre_f_options_unissued | B14: Pre-F unissued option pool | C14: 1894667 | D14: shares | E14: Unissued option pool pre-F (carryover from v3 post-E refresh)
A15: pre_f_fd_total | B15: Pre-F broad-based FD total | C15: 36617961 | D15: shares | E15: Pre-F fully-diluted share count (post-E T from v3)
A16: pre_f_option_pool_total | B16: Pre-F total option pool | C16: =Assumptions!$C$13+Assumptions!$C$14 -> 4394667 | D16: shares | E16: Issued + unissued pre-F option pool
A17: const_one | B17: Formula constant: one | C17: 1 | D17: number | E17: Used by downstream formulas
A18: const_zero | B18: Formula constant: zero | C18: 0 | D18: number | E18: Used by downstream formulas
A19: usd_in_millions | B19: USD display divisor | C19: 1000000 | D19: USD | E19: Used by downstream display formulas
A20: exit_value_1_usd | B20: Exit value 1 | C20: 700000000 | D20: USD | E20: Exit scenario 1
A21: exit_value_2_usd | B21: Exit value 2 | C21: 1200000000 | D21: USD | E21: Exit scenario 2
A22: exit_value_3_usd | B22: Exit value 3 | C22: 2000000000 | D22: USD | E22: Exit scenario 3 (sensitivity reference)
A23: exit_value_4_usd | B23: Exit value 4 | C23: 4000000000 | D23: USD | E23: Exit scenario 4
A24: exit_value_5_usd | B24: Exit value 5 | C24: 8000000000 | D24: USD | E24: Exit scenario 5
A25: sensitivity_esop_low | B25: Sensitivity ESOP low | C25: 0.11 | D25: fraction | E25: Sensitivity grid axis: low ESOP refresh
A26: sensitivity_esop_base | B26: Sensitivity ESOP base | C26: 0.13 | D26: fraction | E26: Sensitivity grid axis: base ESOP refresh
A27: sensitivity_esop_high | B27: Sensitivity ESOP high | C27: 0.15 | D27: fraction | E27: Sensitivity grid axis: high ESOP refresh
A28: sensitivity_pre_low_usd | B28: Sensitivity pre-money low | C28: 1200000000 | D28: USD | E28: Sensitivity grid axis: low Series F pre-money
... A46: note_b_interest_usd | B46: Note B accrued interest | C46: 0 | D46: USD | E46: Notes!Interest
A47: ad_pre_f_broad_based_fd | B47: Broad-based WA A: pre-F FD | C47: =pre_f_fd_total -> 36617961 | D47: shares | E47: RoundTerms!pre_f_fd_total
A48: ad_primary_raise_usd | B48: Broad-based WA new-money numerator | C48: =series_f_primary_raise_usd -> 30000000 | D48: USD | E48: Notes excluded from B and C
A49: sensitivity_exit_usd | B49: Sensitivity waterfall exit | C49: =exit_value_3_usd -> 2000000000 | D49: USD | E49: Exit value used in Sensitivity
A52: Raw Stakeholders
A53: ID | B53: Role | C53: Common shares | D53: Preferred class | E53: Preferred shares
A54: F1 | B54: Founder (CEO) | C54: 4000000 | E54: 0
A55: F2 | B55: Founder (CTO) | C55: 2500000 | E55: 0
A56: F3 | B56: Founder (Chief Scientist) | C56: 1500000 | E56: 0
A57: E1 | B57: Employee RSA | C57: 100000 | E57: 0
A58: E2 | B58: Employee RSA | C58: 100000 | E58: 0
A59: E3 | B59: Employee RSA | C59: 100000 | E59: 0
A60: E4 | B60: Employee RSA | C60: 100000 | E60: 0
A61: E5 | B61: Employee RSA | C61: 100000 | E61: 0
A62: E6 | B62: Employee RSA | C62: 100000 | E62: 0
A63: E7 | B63: Employee RSA | C63: 100000 | E63: 0
A64: E8 | B64: Employee RSA | C64: 100000 | E64: 0
A65: E9 | B65: Employee RSA | C65: 100000 | E65: 0
A66: E10 | B66: Employee RSA | C66: 100000 | E66: 0
A67: SEED1 | B67: Seed preferred LP | C67: 0 | D67: Seed | E67: 5000000
A68: A1 | B68: Series A preferred LP | C68: 0 | D68: Series A | E68: 5000000
A69: B1 | B69: Series B preferred LP | C69: 0 | D69: Series B | E69: 3000000
A70: C1 | B70: Series C preferred LP | C70: 0 | D70: Series C | E70: 2400000
A71: D1 | B71: Series D preferred LP | C71: 0 | D71: Series D | E71: 1720627
A72: E1_INV | B72: Series E preferred LP | C72: 0 | D72: Series E | E72: 610267
A73: E2_INV | B73: Series E preferred LP | C73: 0 | D73: Series E | E73: 610267
A74: E3_INV | B74: Series E preferred LP | C74: 0 | D74: Series E | E74: 610267
A75: E4_INV | B75: Series E preferred LP | C75: 0 | D75: Series E | E75: 610267
A76: E5_INV | B76: Series E preferred LP | C76: 0 | D76: Series E | E76: 610267
A77: E6_INV | B77: Series E preferred LP | C77: 0 | D77: Series E | E77: 610267
A78: E7_INV | B78: Series E preferred LP | C78: 0 | D78: Series E | E78: 610267
... A81: E10_INV | B81: Series E preferred LP | C81: 0 | D81: Series E | E81: 610264
A82: NA1 | B82: Convertible Note A holder | C82: 0 | E82: 0
A83: NB1 | B83: Convertible Note B holder | C83: 0 | E83: 0
A84: F_LEAD | B84: Series F lead investor | C84: 0 | E84: 0
A85: F_FUND | B85: Our fund (Series F primary) | C85: 0 | E85: 0
A88: Raw Securities
A89: Series | B89: Date | C89: OCP-for-AD | D89: PPS-issued-at | E89: Shares | F89: Invested USD | G89: LP-type | H89: AD-type
A90: Seed | B90: 2020-Q2 | C90: 1 | D90: 1 | E90: 5000000 | F90: 5000000 | G90: 1x non-participating with conversion election | H90: broad-based weighted-average
A91: Series A | B91: 2021-Q1 | C91: 3 | D91: 3 | E91: 5000000 | F91: 15000000 | G91: 1x non-participating with conversion election | H91: broad-based weighted-average
A92: Series B | B92: 2022-Q2 | C92: 10 | D92: 10 | E92: 3000000 | F92: 30000000 | G92: 1x non-participating with conversion election | H92: broad-based weighted-average
A93: Series C | B93: 2023-Q4 | C93: 25 | D93: 25 | E93: 2400000 | F93: 60000000 | G93: 1x non-participating with conversion election | H93: broad-based weighted-average
A94: Series D | B94: 2025-Q2 | C94: 58.118347 | D94: 60 | E94: 1666667 | F94: 100000000 | G94: 1x non-participating with conversion election | H94: broad-based weighted-average
A95: Series E | B95: 2026-Q1 | C95: 49.158311 | D95: 49.158311 | E95: 6102667 | F95: 300000000 | G95: 1x non-participating with conversion election | H95: broad-based weighted-average
A98: Raw Notes
A99: Note ID | B99: Holder ID | C99: Principal USD | D99: Cap USD | E99: Discount | F99: Interest
A100: Note A | B100: NA1 | C100: 5000000 | D100: 1000000000 | E100: 0.2 | F100: 0
A101: Note B | B101: NB1 | C101: 3000000 | D101: 1600000000 | E101: 0.15 | F101: 0
A104: Derived Cap-Table Inputs
A105: Key | B105: Label | C105: Value | D105: Units | E105: Notes
A106: founder_common_total | B106: Founder common total | C106: =Assumptions!$C$54+Assumptions!$C$55+Assumptions!$C$56 -> 8000000 | D106: shares | E106: F1 + F2 + F3
A107: rsa_common_total | B107: Employee RSA common total | C107: =SUMIF($B$54:$B$85,"Employee RSA",$C$54:$C$85) -> 1000000 | D107: shares | E107: Employee RSA rows
A108: common_rsa_total | B108: Common + RSA total | C108: =founder_common_total+rsa_common_total -> 9000000 | D108: shares | E108: Tender transfers do not change this total
A111: Class Inputs
A112: Class key | B112: Class label | C112: OCP | D112: Original issue PPS | E112: Original preferred shares | F112: Current as-converted shares | G112: Invested USD | H112: Source series
A113: seed | B113: Seed | C113: =ocp_seed -> 1 | D113: =Assumptions!$D$90 -> 1 | E113: =Assumptions!$E$90 -> 5000000 | F113: =SUMIF($D$54:$D$85,Assumptions!$B$113,$E$54:$E$85) -> 5000000 | G113: =Assumptions!$F$90 -> 5000000 | H113: Seed
A114: series_a | B114: Series A | C114: =ocp_series_a -> 3 | D114: =Assumptions!$D$91 -> 3 | E114: =Assumptions!$E$91 -> 5000000 | F114: =SUMIF($D$54:$D$85,Assumptions!$B$114,$E$54:$E$85) -> 5000000 | G114: =Assumptions!$F$91 -> 15000000 | H114: Series A
A115: series_b | B115: Series B | C115: =ocp_series_b -> 10 | D115: =Assumptions!$D$92 -> 10 | E115: =Assumptions!$E$92 -> 3000000 | F115: =SUMIF($D$54:$D$85,Assumptions!$B$115,$E$54:$E$85) -> 3000000 | G115: =Assumptions!$F$92 -> 30000000 | H115: Series B
A116: series_c | B116: Series C | C116: =ocp_series_c -> 25 | D116: =Assumptions!$D$93 -> 25 | E116: =Assumptions!$E$93 -> 2400000 | F116: =SUMIF($D$54:$D$85,Assumptions!$B$116,$E$54:$E$85) -> 2400000 | G116: =Assumptions!$F$93 -> 60000000 | H116: Series C
A117: series_d | B117: Series D | C117: =ocp_series_d_post_e_ncp -> 58.118347 | D117: =Assumptions!$D$94 -> 60 | E117: =Assumptions!$E$94 -> 1666667 | F117: =SUMIF($D$54:$D$85,Assumptions!$B$117,$E$54:$E$85) -> 1720627 | G117: =Assumptions!$F$94 -> 100000000 | H117: Series D
A118: series_e | B118: Series E | C118: =ocp_series_e -> 49.158311 | D118: =Assumptions!$D$95 -> 49.158311 | E118: =Assumptions!$E$95 -> 6102667 | F118: =SUMIF($D$54:$D$85,Assumptions!$B$118,$E$54:$E$85) -> 6102667 | G118: =Assumptions!$F$95 -> 300000000 | H118: Series E
A119: series_f | B119: Series F | G119: =series_f_primary_raise_usd -> 30000000 | H119: RoundTerms
A122: Formula Labels
A123: Label key | B123: Text
A124: lbl_title | B124: Kelvin Dynamics - Series F Analysis
A125: lbl_assumptions | B125: Assumptions
A126: lbl_pro_forma | B126: Pro-Forma
A127: lbl_waterfall | B127: Waterfall
A128: lbl_sensitivity | B128: Sensitivity
A129: lbl_return_solver | B129: Return-Solver
A130: lbl_metric | B130: Metric
A131: lbl_value | B131: Value
A132: lbl_units | B132: Units
...

Sheet Pro-Forma
A1: =lbl_pro_forma -> Pro-Forma
A3: =lbl_fixed_point -> Fixed Point
A4: =lbl_f_pps -> Series F PPS | B4: ='Pro-Forma'!$V$63 -> 37.628498 | R4: =const_zero -> 0 | S4: =const_zero -> 0 | T4: =const_zero -> 0 | U4: =const_zero -> 0 | V4: =series_f_pre_money_usd/(pre_f_fd_total+'Pro-Forma'!S4) -> 38.232604 | W4: =series_f_primary_raise_usd/'Pro-Forma'!V4 -> 784670.59 | X4: =IF('Pro-Forma'!V4<class_seed_ocp,class_seed_ocp*(ad_pre_f_broad_based_fd+series_f_primary_raise_usd/class_seed_ocp)/(ad_pre_f_broad_based_fd+series_f_primary_raise_usd/'Pro-Forma'!V4),class_seed_ocp) -> 1 | Y4: =class_seed_original_shares*class_seed_issue_pps/'Pro-Forma'!X4 -> 5000000 | Z4: =IF('Pro-Forma'!V4<class_series_a_ocp,class_series_a_ocp*(ad_pre_f_broad_based_fd+series_f_primary_raise_usd/class_series_a_ocp)/(ad_pre_f_broad_based_fd+series_f_primary_raise_usd/'Pro-Forma'!V4),class_series_a_ocp) -> 3 | AA4: =class_series_a_original_shares*class_series_a_issue_pps/'Pro-Forma'!Z4 -> 5000000 | AB4: =IF('Pro-Forma'!V4<class_series_b_ocp,class_series_b_ocp*(ad_pre_f_broad_based_fd+series_f_primary_raise_usd/class_series_b_ocp)/(ad_pre_f_broad_based_fd+series_f_primary_raise_usd/'Pro-Forma'!V4),class_series_b_ocp) -> 10 | AC4: =class_series_b_original_shares*class_series_b_issue_pps/'Pro-Forma'!AB4 -> 3000000 | AD4: =IF('Pro-Forma'!V4<class_series_c_ocp,class_series_c_ocp*(ad_pre_f_broad_based_fd+series_f_primary_raise_usd/class_series_c_ocp)/(ad_pre_f_broad_based_fd+series_f_primary_raise_usd/'Pro-Forma'!V4),class_series_c_ocp) -> 25 | AE4: =class_series_c_original_shares*class_series_c_issue_pps/'Pro-Forma'!AD4 -> 2400000 | AF4: =IF('Pro-Forma'!V4<class_series_d_ocp,class_series_d_ocp*(ad_pre_f_broad_based_fd+series_f_primary_raise_usd/class_series_d_ocp)/(ad_pre_f_broad_based_fd+series_f_primary_raise_usd/'Pro-Forma'!V4),class_series_d_ocp) -> 57.701164 | AG4: =class_series_d_original_shares*class_series_d_issue_pps/'Pro-Forma'!AF4 -> 1733067.7 | AH4: =IF('Pro-Forma'!V4<class_series_e_ocp,class_series_e_ocp*(ad_pre_f_broad_based_fd+series_f_primary_raise_usd/class_series_e_ocp)/(ad_pre_f_broad_based_fd+series_f_primary_raise_usd/'Pro-Forma'!V4),class_series_e_ocp) -> 48.9291 | AI4: =class_series_e_original_shares*class_series_e_issue_pps/'Pro-Forma'!AH4 -> 6131255.2 | AJ4: ='Pro-Forma'!Y4-class_seed_current_shares+'Pro-Forma'!AA4-class_series_a_current_shares+'Pro-Forma'!AC4-class_series_b_current_shares+'Pro-Forma'!AE4-class_series_c_current_shares+'Pro-Forma'!AG4-class_series_d_current_shares+'Pro-Forma'!AI4-class_series_e_current_shares -> 41028.877 | AK4: =note_a_cap_usd/(pre_f_fd_total+'Pro-Forma'!S4+'Pro-Forma'!AJ4+'Pro-Forma'!U4) -> 27.278438 | AL4: ='Pro-Forma'!V4*(const_one-note_a_discount) -> 30.586083 | AM4: =MIN('Pro-Forma'!AK4,'Pro-Forma'!AL4) -> 27.278438 | AN4: =note_a_principal_usd/'Pro-Forma'!AM4 -> 183294.95 | AO4: =note_b_cap_usd/(pre_f_fd_total+'Pro-Forma'!S4+'Pro-Forma'!AJ4+'Pro-Forma'!T4) -> 43.645502 | AP4: ='Pro-Forma'!V4*(const_one-note_b_discount) -> 32.497713 | AQ4: =MIN('Pro-Forma'!AO4,'Pro-Forma'!AP4) -> 32.497713 | AR4: =note_b_principal_usd/'Pro-Forma'!AQ4 -> 92314.187 | AS4: =pre_f_fd_total+'Pro-Forma'!S4+'Pro-Forma'!W4+'Pro-Forma'!AN4+'Pro-Forma'!AR4+'Pro-Forma'!AJ4 -> 37719270 | AT4: =MAX(const_zero,esop_refresh_target_post_f*'Pro-Forma'!AS4-pre_f_option_pool_total) -> 508838.05
A5: =lbl_primary_shares -> Series F primary shares | B5: =series_f_primary_raise_usd/B4 -> 797268.07 | R5: ='Pro-Forma'!R4+const_one -> 1 | S5: ='Pro-Forma'!AT4 -> 508838.05 | T5: ='Pro-Forma'!AN4 -> 183294.95 | U5: ='Pro-Forma'!AR4 -> 92314.187 | V5: =series_f_pre_money_usd/(pre_f_fd_total+'Pro-Forma'!S5) -> 37.70861 | W5: =series_f_primary_raise_usd/'Pro-Forma'!V5 -> 795574.27 | X5: =IF('Pro-Forma'!V5<class_seed_ocp,class_seed_ocp*(ad_pre_f_broad_based_fd+series_f_primary_raise_usd/class_seed_ocp)/(ad_pre_f_broad_based_fd+series_f_primary_raise_usd/'Pro-Forma'!V5),class_seed_ocp) -> 1 | Y5: =class_seed_original_shares*class_seed_issue_pps/'Pro-Forma'!X5 -> 5000000 | Z5: =IF('Pro-Forma'!V5<class_series_a_ocp,class_series_a_ocp*(ad_pre_f_broad_based_fd+series_f_primary_raise_usd/class_series_a_ocp)/(ad_pre_f_broad_based_fd+series_f_primary_raise_usd/'Pro-Forma'!V5),class_series_a_ocp) -> 3 | AA5: =class_series_a_original_shares*class_series_a_issue_pps/'Pro-Forma'!Z5 -> 5000000 | AB5: =IF('Pro-Forma'!V5<class_series_b_ocp,class_series_b_ocp*(ad_pre_f_broad_based_fd+series_f_primary_raise_usd/class_series_b_ocp)/(ad_pre_f_broad_based_fd+series_f_primary_raise_usd/'Pro-Forma'!V5),class_series_b_ocp) -> 10 | AC5: =class_series_b_original_shares*class_series_b_issue_pps/'Pro-Forma'!AB5 -> 3000000 | AD5: =IF('Pro-Forma'!V5<class_series_c_ocp,class_series_c_ocp*(ad_pre_f_broad_based_fd+series_f_primary_raise_usd/class_series_c_ocp)/(ad_pre_f_broad_based_fd+series_f_primary_raise_usd/'Pro-Forma'!V5),class_series_c_ocp) -> 25 | AE5: =class_series_c_original_shares*class_series_c_issue_pps/'Pro-Forma'!AD5 -> 2400000 | AF5: =IF('Pro-Forma'!V5<class_series_d_ocp,class_series_d_ocp*(ad_pre_f_broad_based_fd+series_f_primary_raise_usd/class_series_d_ocp)/(ad_pre_f_broad_based_fd+series_f_primary_raise_usd/'Pro-Forma'!V5),class_series_d_ocp) -> 57.684347 | AG5: =class_series_d_original_shares*class_series_d_issue_pps/'Pro-Forma'!AF5 -> 1733572.9 | AH5: =IF('Pro-Forma'!V5<class_series_e_ocp,class_series_e_ocp*(ad_pre_f_broad_based_fd+series_f_primary_raise_usd/class_series_e_ocp)/(ad_pre_f_broad_based_fd+series_f_primary_raise_usd/'Pro-Forma'!V5),class_series_e_ocp) -> 48.914841 | AI5: =class_series_e_original_shares*class_series_e_issue_pps/'Pro-Forma'!AH5 -> 6133042.6 | AJ5: ='Pro-Forma'!Y5-class_seed_current_shares+'Pro-Forma'!AA5-class_series_a_current_shares+'Pro-Forma'!AC5-class_series_b_current_shares+'Pro-Forma'!AE5-class_series_c_current_shares+'Pro-Forma'!AG5-class_series_d_current_shares+'Pro-Forma'!AI5-class_series_e_current_shares -> 43321.496 | AK5: =note_a_cap_usd/(pre_f_fd_total+'Pro-Forma'!S5+'Pro-Forma'!AJ5+'Pro-Forma'!U5) -> 26.836679 | AL5: ='Pro-Forma'!V5*(const_one-note_a_discount) -> 30.166888 | AM5: =MIN('Pro-Forma'!AK5,'Pro-Forma'!AL5) -> 26.836679 | AN5: =note_a_principal_usd/'Pro-Forma'!AM5 -> 186312.17 | AO5: =note_b_cap_usd/(pre_f_fd_total+'Pro-Forma'!S5+'Pro-Forma'!AJ5+'Pro-Forma'!T5) -> 42.834102 | AP5: ='Pro-Forma'!V5*(const_one-note_b_discount) -> 32.052319 | AQ5: =MIN('Pro-Forma'!AO5,'Pro-Forma'!AP5) -> 32.052319 | AR5: =note_b_principal_usd/'Pro-Forma'!AQ5 -> 93596.972 | AS5: =pre_f_fd_total+'Pro-Forma'!S5+'Pro-Forma'!W5+'Pro-Forma'!AN5+'Pro-Forma'!AR5+'Pro-Forma'!AJ5 -> 38245604 | AT5: =MAX(const_zero,esop_refresh_target_post_f*'Pro-Forma'!AS5-pre_f_option_pool_total) -> 577261.51
A6: =lbl_our_primary_shares -> Our Series F primary shares | B6: =our_fund_check_usd/B4 -> 265756.02 | R6: ='Pro-Forma'!R5+const_one -> 2 | S6: ='Pro-Forma'!AT5 -> 577261.51 | T6: ='Pro-Forma'!AN5 -> 186312.17 | U6: ='Pro-Forma'!AR5 -> 93596.972 | V6: =series_f_pre_money_usd/(pre_f_fd_total+'Pro-Forma'!S6) -> 37.639242 | W6: =series_f_primary_raise_usd/'Pro-Forma'!V6 -> 797040.48 | X6: =IF('Pro-Forma'!V6<class_seed_ocp,class_seed_ocp*(ad_pre_f_broad_based_fd+series_f_primary_raise_usd/class_seed_ocp)/(ad_pre_f_broad_based_fd+series_f_primary_raise_usd/'Pro-Forma'!V6),class_seed_ocp) -> 1 | Y6: =class_seed_original_shares*class_seed_issue_pps/'Pro-Forma'!X6 -> 5000000 | Z6: =IF('Pro-Forma'!V6<class_series_a_ocp,class_series_a_ocp*(ad_pre_f_broad_based_fd+series_f_primary_raise_usd/class_series_a_ocp)/(ad_pre_f_broad_based_fd+series_f_primary_raise_usd/'Pro-Forma'!V6),class_series_a_ocp) -> 3 | AA6: =class_series_a_original_shares*class_series_a_issue_pps/'Pro-Forma'!Z6 -> 5000000 | AB6: =IF('Pro-Forma'!V6<class_series_b_ocp,class_series_b_ocp*(ad_pre_f_broad_based_fd+series_f_primary_raise_usd/class_series_b_ocp)/(ad_pre_f_broad_based_fd+series_f_primary_raise_usd/'Pro-Forma'!V6),class_series_b_ocp) -> 10 | AC6: =class_series_b_original_shares*class_series_b_issue_pps/'Pro-Forma'!AB6 -> 3000000 | AD6: =IF('Pro-Forma'!V6<class_series_c_ocp,class_series_c_ocp*(ad_pre_f_broad_based_fd+series_f_primary_raise_usd/class_series_c_ocp)/(ad_pre_f_broad_based_fd+series_f_primary_raise_usd/'Pro-Forma'!V6),class_series_c_ocp) -> 25 | AE6: =class_series_c_original_shares*class_series_c_issue_pps/'Pro-Forma'!AD6 -> 2400000 | AF6: =IF('Pro-Forma'!V6<class_series_d_ocp,class_series_d_ocp*(ad_pre_f_broad_based_fd+series_f_primary_raise_usd/class_series_d_ocp)/(ad_pre_f_broad_based_fd+series_f_primary_raise_usd/'Pro-Forma'!V6),class_series_d_ocp) -> 57.682087 | AG6: =class_series_d_original_shares*class_series_d_issue_pps/'Pro-Forma'!AF6 -> 1733640.8 | AH6: =IF('Pro-Forma'!V6<class_series_e_ocp,class_series_e_ocp*(ad_pre_f_broad_based_fd+series_f_primary_raise_usd/class_series_e_ocp)/(ad_pre_f_broad_based_fd+series_f_primary_raise_usd/'Pro-Forma'!V6),class_series_e_ocp) -> 48.912924 | AI6: =class_series_e_original_shares*class_series_e_issue_pps/'Pro-Forma'!AH6 -> 6133283 | AJ6: ='Pro-Forma'!Y6-class_seed_current_shares+'Pro-Forma'!AA6-class_series_a_current_shares+'Pro-Forma'!AC6-class_series_b_current_shares+'Pro-Forma'!AE6-class_series_c_current_shares+'Pro-Forma'!AG6-class_series_d_current_shares+'Pro-Forma'!AI6-class_series_e_current_shares -> 43629.785 | AK6: =note_a_cap_usd/(pre_f_fd_total+'Pro-Forma'!S6+'Pro-Forma'!AJ6+'Pro-Forma'!U6) -> 26.786349 | AL6: ='Pro-Forma'!V6*(const_one-note_a_discount) -> 30.111394 | AM6: =MIN('Pro-Forma'!AK6,'Pro-Forma'!AL6) -> 26.786349 | AN6: =note_a_principal_usd/'Pro-Forma'!AM6 -> 186662.25 | AO6: =note_b_cap_usd/(pre_f_fd_total+'Pro-Forma'!S6+'Pro-Forma'!AJ6+'Pro-Forma'!T6) -> 42.751983 | AP6: ='Pro-Forma'!V6*(const_one-note_b_discount) -> 31.993356 | AQ6: =MIN('Pro-Forma'!AO6,'Pro-Forma'!AP6) -> 31.993356 | AR6: =note_b_principal_usd/'Pro-Forma'!AQ6 -> 93769.469 | AS6: =pre_f_fd_total+'Pro-Forma'!S6+'Pro-Forma'!W6+'Pro-Forma'!AN6+'Pro-Forma'!AR6+'Pro-Forma'!AJ6 -> 38316324 | AT6: =MAX(const_zero,esop_refresh_target_post_f*'Pro-Forma'!AS6-pre_f_option_pool_total) -> 586455.18
A7: =lbl_f_lead_primary_shares -> F_LEAD Series F primary shares | B7: =f_lead_primary_check_usd/B4 -> 531512.05 | R7: ='Pro-Forma'!R6+const_one -> 3 | S7: ='Pro-Forma'!AT6 -> 586455.18 | T7: ='Pro-Forma'!AN6 -> 186662.25 | U7: ='Pro-Forma'!AR6 -> 93769.469 | V7: =series_f_pre_money_usd/(pre_f_fd_total+'Pro-Forma'!S7) -> 37.629941 | W7: =series_f_primary_raise_usd/'Pro-Forma'!V7 -> 797237.49 | X7: =IF('Pro-Forma'!V7<class_seed_ocp,class_seed_ocp*(ad_pre_f_broad_based_fd+series_f_primary_raise_usd/class_seed_ocp)/(ad_pre_f_broad_based_fd+series_f_primary_raise_usd/'Pro-Forma'!V7),class_seed_ocp) -> 1 | Y7: =class_seed_original_shares*class_seed_issue_pps/'Pro-Forma'!X7 -> 5000000 | Z7: =IF('Pro-Forma'!V7<class_series_a_ocp,class_series_a_ocp*(ad_pre_f_broad_based_fd+series_f_primary_raise_usd/class_series_a_ocp)/(ad_pre_f_broad_based_fd+series_f_primary_raise_usd/'Pro-Forma'!V7),class_series_a_ocp) -> 3 | AA7: =class_series_a_original_shares*class_series_a_issue_pps/'Pro-Forma'!Z7 -> 5000000 | AB7: =IF('Pro-Forma'!V7<class_series_b_ocp,class_series_b_ocp*(ad_pre_f_broad_based_fd+series_f_primary_raise_usd/class_series_b_ocp)/(ad_pre_f_broad_based_fd+series_f_primary_raise_usd/'Pro-Forma'!V7),class_series_b_ocp) -> 10 | AC7: =class_series_b_original_shares*class_series_b_issue_pps/'Pro-Forma'!AB7 -> 3000000 | AD7: =IF('Pro-Forma'!V7<class_series_c_ocp,class_series_c_ocp*(ad_pre_f_broad_based_fd+series_f_primary_raise_usd/class_series_c_ocp)/(ad_pre_f_broad_based_fd+series_f_primary_raise_usd/'Pro-Forma'!V7),class_series_c_ocp) -> 25 | AE7: =class_series_c_original_shares*class_series_c_issue_pps/'Pro-Forma'!AD7 -> 2400000 | AF7: =IF('Pro-Forma'!V7<class_series_d_ocp,class_series_d_ocp*(ad_pre_f_broad_based_fd+series_f_primary_raise_usd/class_series_d_ocp)/(ad_pre_f_broad_based_fd+series_f_primary_raise_usd/'Pro-Forma'!V7),class_series_d_ocp) -> 57.681783 | AG7: =class_series_d_original_shares*class_series_d_issue_pps/'Pro-Forma'!AF7 -> 1733649.9 | AH7: =IF('Pro-Forma'!V7<class_series_e_ocp,class_series_e_ocp*(ad_pre_f_broad_based_fd+series_f_primary_raise_usd/class_series_e_ocp)/(ad_pre_f_broad_based_fd+series_f_primary_raise_usd/'Pro-Forma'!V7),class_series_e_ocp) -> 48.912666 | AI7: =class_series_e_original_shares*class_series_e_issue_pps/'Pro-Forma'!AH7 -> 6133315.3 | AJ7: ='Pro-Forma'!Y7-class_seed_current_shares+'Pro-Forma'!AA7-class_series_a_current_shares+'Pro-Forma'!AC7-class_series_b_current_shares+'Pro-Forma'!AE7-class_series_c_current_shares+'Pro-Forma'!AG7-class_series_d_current_shares+'Pro-Forma'!AI7-class_series_e_current_shares -> 43671.208 | AK7: =note_a_cap_usd/(pre_f_fd_total+'Pro-Forma'!S7+'Pro-Forma'!AJ7+'Pro-Forma'!U7) -> 26.7796 | AL7: ='Pro-Forma'!V7*(const_one-note_a_discount) -> 30.103953 | AM7: =MIN('Pro-Forma'!AK7,'Pro-Forma'!AL7) -> 26.7796 | AN7: =note_a_principal_usd/'Pro-Forma'!AM7 -> 186709.28 | AO7: =note_b_cap_usd/(pre_f_fd_total+'Pro-Forma'!S7+'Pro-Forma'!AJ7+'Pro-Forma'!T7) -> 42.741036 | AP7: ='Pro-Forma'!V7*(const_one-note_b_discount) -> 31.98545 | AQ7: =MIN('Pro-Forma'!AO7,'Pro-Forma'!AP7) -> 31.98545 | AR7: =note_b_principal_usd/'Pro-Forma'!AQ7 -> 93792.646 | AS7: =pre_f_fd_total+'Pro-Forma'!S7+'Pro-Forma'!W7+'Pro-Forma'!AN7+'Pro-Forma'!AR7+'Pro-Forma'!AJ7 -> 38325827 | AT7: =MAX(const_zero,esop_refresh_target_post_f*'Pro-Forma'!AS7-pre_f_option_pool_total) -> 587690.49
A8: =lbl_esop_topup -> ESOP top-up | B8: ='Pro-Forma'!$AT$63 -> 587882.23 | R8: ='Pro-Forma'!R7+const_one -> 4 | S8: ='Pro-Forma'!AT7 -> 587690.49 | T8: ='Pro-Forma'!AN7 -> 186709.28 | U8: ='Pro-Forma'!AR7 -> 93792.646 | V8: =series_f_pre_money_usd/(pre_f_fd_total+'Pro-Forma'!S8) -> 37.628692 | W8: =series_f_primary_raise_usd/'Pro-Forma'!V8 -> 797263.96 | X8: =IF('Pro-Forma'!V8<class_seed_ocp,class_seed_ocp*(ad_pre_f_broad_based_fd+series_f_primary_raise_usd/class_seed_ocp)/(ad_pre_f_broad_based_fd+series_f_primary_raise_usd/'Pro-Forma'!V8),class_seed_ocp) -> 1 | Y8: =class_seed_original_shares*class_seed_issue_pps/'Pro-Forma'!X8 -> 5000000 | Z8: =IF('Pro-Forma'!V8<class_series_a_ocp,class_series_a_ocp*(ad_pre_f_broad_based_fd+series_f_primary_raise_usd/class_series_a_ocp)/(ad_pre_f_broad_based_fd+series_f_primary_raise_usd/'Pro-Forma'!V8),class_series_a_ocp) -> 3 | AA8: =class_series_a_original_shares*class_series_a_issue_pps/'Pro-Forma'!Z8 -> 5000000 | AB8: =IF('Pro-Forma'!V8<class_series_b_ocp,class_series_b_ocp*(ad_pre_f_broad_based_fd+series_f_primary_raise_usd/class_series_b_ocp)/(ad_pre_f_broad_based_fd+series_f_primary_raise_usd/'Pro-Forma'!V8),class_series_b_ocp) -> 10 | AC8: =class_series_b_original_shares*class_series_b_issue_pps/'Pro-Forma'!AB8 -> 3000000 | AD8: =IF('Pro-Forma'!V8<class_series_c_ocp,class_series_c_ocp*(ad_pre_f_broad_based_fd+series_f_primary_raise_usd/class_series_c_ocp)/(ad_pre_f_broad_based_fd+series_f_primary_raise_usd/'Pro-Forma'!V8),class_series_c_ocp) -> 25 | AE8: =class_series_c_original_shares*class_series_c_issue_pps/'Pro-Forma'!AD8 -> 2400000 | AF8: =IF('Pro-Forma'!V8<class_series_d_ocp,class_series_d_ocp*(ad_pre_f_broad_based_fd+series_f_primary_raise_usd/class_series_d_ocp)/(ad_pre_f_broad_based_fd+series_f_primary_raise_usd/'Pro-Forma'!V8),class_series_d_ocp) -> 57.681742 | AG8: =class_series_d_original_shares*class_series_d_issue_pps/'Pro-Forma'!AF8 -> 1733651.2 | AH8: =IF('Pro-Forma'!V8<class_series_e_ocp,class_series_e_ocp*(ad_pre_f_broad_based_fd+series_f_primary_raise_usd/class_series_e_ocp)/(ad_pre_f_broad_based_fd+series_f_primary_raise_usd/'Pro-Forma'!V8),class_series_e_ocp) -> 48.912632 | AI8: =class_series_e_original_shares*class_series_e_issue_pps/'Pro-Forma'!AH8 -> 6133319.6 | AJ8: ='Pro-Forma'!Y8-class_seed_current_shares+'Pro-Forma'!AA8-class_series_a_current_shares+'Pro-Forma'!AC8-class_series_b_current_shares+'Pro-Forma'!AE8-class_series_c_current_shares+'Pro-Forma'!AG8-class_series_d_current_shares+'Pro-Forma'!AI8-class_series_e_current_shares -> 43676.774 | AK8: =note_a_cap_usd/(pre_f_fd_total+'Pro-Forma'!S8+'Pro-Forma'!AJ8+'Pro-Forma'!U8) -> 26.778694 | AL8: ='Pro-Forma'!V8*(const_one-note_a_discount) -> 30.102954 | AM8: =MIN('Pro-Forma'!AK8,'Pro-Forma'!AL8) -> 26.778694 | AN8: =note_a_principal_usd/'Pro-Forma'!AM8 -> 186715.6 | AO8: =note_b_cap_usd/(pre_f_fd_total+'Pro-Forma'!S8+'Pro-Forma'!AJ8+'Pro-Forma'!T8) -> 42.739566 | AP8: ='Pro-Forma'!V8*(const_one-note_b_discount) -> 31.984388 | AQ8: =MIN('Pro-Forma'!AO8,'Pro-Forma'!AP8) -> 31.984388 | AR8: =note_b_principal_usd/'Pro-Forma'!AQ8 -> 93795.76 | AS8: =pre_f_fd_total+'Pro-Forma'!S8+'Pro-Forma'!W8+'Pro-Forma'!AN8+'Pro-Forma'!AR8+'Pro-Forma'!AJ8 -> 38327104 | AT8: =MAX(const_zero,esop_refresh_target_post_f*'Pro-Forma'!AS8-pre_f_option_pool_total) -> 587856.47
A9: =lbl_ad_increment -> AD incremental shares | B9: =SUM(G22:G27) -> 43677.638 | R9: ='Pro-Forma'!R8+const_one -> 5 | S9: ='Pro-Forma'!AT8 -> 587856.47 | T9: ='Pro-Forma'!AN8 -> 186715.6 | U9: ='Pro-Forma'!AR8 -> 93795.76 | V9: =series_f_pre_money_usd/(pre_f_fd_total+'Pro-Forma'!S9) -> 37.628524 | W9: =series_f_primary_raise_usd/'Pro-Forma'!V9 -> 797267.52 | X9: =IF('Pro-Forma'!V9<class_seed_ocp,class_seed_ocp*(ad_pre_f_broad_based_fd+series_f_primary_raise_usd/class_seed_ocp)/(ad_pre_f_broad_based_fd+series_f_primary_raise_usd/'Pro-Forma'!V9),class_seed_ocp) -> 1 | Y9: =class_seed_original_shares*class_seed_issue_pps/'Pro-Forma'!X9 -> 5000000 | Z9: =IF('Pro-Forma'!V9<class_series_a_ocp,class_series_a_ocp*(ad_pre_f_broad_based_fd+series_f_primary_raise_usd/class_series_a_ocp)/(ad_pre_f_broad_based_fd+series_f_primary_raise_usd/'Pro-Forma'!V9),class_series_a_ocp) -> 3 | AA9: =class_series_a_original_shares*class_series_a_issue_pps/'Pro-Forma'!Z9 -> 5000000 | AB9: =IF('Pro-Forma'!V9<class_series_b_ocp,class_series_b_ocp*(ad_pre_f_broad_based_fd+series_f_primary_raise_usd/class_series_b_ocp)/(ad_pre_f_broad_based_fd+series_f_primary_raise_usd/'Pro-Forma'!V9),class_series_b_ocp) -> 10 | AC9: =class_series_b_original_shares*class_series_b_issue_pps/'Pro-Forma'!AB9 -> 3000000 | AD9: =IF('Pro-Forma'!V9<class_series_c_ocp,class_series_c_ocp*(ad_pre_f_broad_based_fd+series_f_primary_raise_usd/class_series_c_ocp)/(ad_pre_f_broad_based_fd+series_f_primary_raise_usd/'Pro-Forma'!V9),class_series_c_ocp) -> 25 | AE9: =class_series_c_original_shares*class_series_c_issue_pps/'Pro-Forma'!AD9 -> 2400000 | AF9: =IF('Pro-Forma'!V9<class_series_d_ocp,class_series_d_ocp*(ad_pre_f_broad_based_fd+series_f_primary_raise_usd/class_series_d_ocp)/(ad_pre_f_broad_based_fd+series_f_primary_raise_usd/'Pro-Forma'!V9),class_series_d_ocp) -> 57.681737 | AG9: =class_series_d_original_shares*class_series_d_issue_pps/'Pro-Forma'!AF9 -> 1733651.3 | AH9: =IF('Pro-Forma'!V9<class_series_e_ocp,class_series_e_ocp*(ad_pre_f_broad_based_fd+series_f_primary_raise_usd/class_series_e_ocp)/(ad_pre_f_broad_based_fd+series_f_primary_raise_usd/'Pro-Forma'!V9),class_series_e_ocp) -> 48.912627 | AI9: =class_series_e_original_shares*class_series_e_issue_pps/'Pro-Forma'!AH9 -> 6133320.2 | AJ9: ='Pro-Forma'!Y9-class_seed_current_shares+'Pro-Forma'!AA9-class_series_a_current_shares+'Pro-Forma'!AC9-class_series_b_current_shares+'Pro-Forma'!AE9-class_series_c_current_shares+'Pro-Forma'!AG9-class_series_d_current_shares+'Pro-Forma'!AI9-class_series_e_current_shares -> 43677.522 | AK9: =note_a_cap_usd/(pre_f_fd_total+'Pro-Forma'!S9+'Pro-Forma'!AJ9+'Pro-Forma'!U9) -> 26.778572 | AL9: ='Pro-Forma'!V9*(const_one-note_a_discount) -> 30.102819 | AM9: =MIN('Pro-Forma'!AK9,'Pro-Forma'!AL9) -> 26.778572 | AN9: =note_a_principal_usd/'Pro-Forma'!AM9 -> 186716.45 | AO9: =note_b_cap_usd/(pre_f_fd_total+'Pro-Forma'!S9+'Pro-Forma'!AJ9+'Pro-Forma'!T9) -> 42.739369 | AP9: ='Pro-Forma'!V9*(const_one-note_b_discount) -> 31.984246 | AQ9: =MIN('Pro-Forma'!AO9,'Pro-Forma'!AP9) -> 31.984246 | AR9: =note_b_principal_usd/'Pro-Forma'!AQ9 -> 93796.178 | AS9: =pre_f_fd_total+'Pro-Forma'!S9+'Pro-Forma'!W9+'Pro-Forma'!AN9+'Pro-Forma'!AR9+'Pro-Forma'!AJ9 -> 38327275 | AT9: =MAX(const_zero,esop_refresh_target_post_f*'Pro-Forma'!AS9-pre_f_option_pool_total) -> 587878.77
A10: =lbl_note_a_shares -> Note A shares | B10: =I31 -> 186716.59 | R10: ='Pro-Forma'!R9+const_one -> 6 | S10: ='Pro-Forma'!AT9 -> 587878.77 | T10: ='Pro-Forma'!AN9 -> 186716.45 | U10: ='Pro-Forma'!AR9 -> 93796.178 | V10: =series_f_pre_money_usd/(pre_f_fd_total+'Pro-Forma'!S10) -> 37.628502 | W10: =series_f_primary_raise_usd/'Pro-Forma'!V10 -> 797268 | X10: =IF('Pro-Forma'!V10<class_seed_ocp,class_seed_ocp*(ad_pre_f_broad_based_fd+series_f_primary_raise_usd/class_seed_ocp)/(ad_pre_f_broad_based_fd+series_f_primary_raise_usd/'Pro-Forma'!V10),class_seed_ocp) -> 1 | Y10: =class_seed_original_shares*class_seed_issue_pps/'Pro-Forma'!X10 -> 5000000 | Z10: =IF('Pro-Forma'!V10<class_series_a_ocp,class_series_a_ocp*(ad_pre_f_broad_based_fd+series_f_primary_raise_usd/class_series_a_ocp)/(ad_pre_f_broad_based_fd+series_f_primary_raise_usd/'Pro-Forma'!V10),class_series_a_ocp) -> 3 | AA10: =class_series_a_original_shares*class_series_a_issue_pps/'Pro-Forma'!Z10 -> 5000000 | AB10: =IF('Pro-Forma'!V10<class_series_b_ocp,class_series_b_ocp*(ad_pre_f_broad_based_fd+series_f_primary_raise_usd/class_series_b_ocp)/(ad_pre_f_broad_based_fd+series_f_primary_raise_usd/'Pro-Forma'!V10),class_series_b_ocp) -> 10 | AC10: =class_series_b_original_shares*class_series_b_issue_pps/'Pro-Forma'!AB10 -> 3000000 | AD10: =IF('Pro-Forma'!V10<class_series_c_ocp,class_series_c_ocp*(ad_pre_f_broad_based_fd+series_f_primary_raise_usd/class_series_c_ocp)/(ad_pre_f_broad_based_fd+series_f_primary_raise_usd/'Pro-Forma'!V10),class_series_c_ocp) -> 25 | AE10: =class_series_c_original_shares*class_series_c_issue_pps/'Pro-Forma'!AD10 -> 2400000 | AF10: =IF('Pro-Forma'!V10<class_series_d_ocp,class_series_d_ocp*(ad_pre_f_broad_based_fd+series_f_primary_raise_usd/class_series_d_ocp)/(ad_pre_f_broad_based_fd+series_f_primary_raise_usd/'Pro-Forma'!V10),class_series_d_ocp) -> 57.681736 | AG10: =class_series_d_original_shares*class_series_d_issue_pps/'Pro-Forma'!AF10 -> 1733651.4 | AH10: =IF('Pro-Forma'!V10<class_series_e_ocp,class_series_e_ocp*(ad_pre_f_broad_based_fd+series_f_primary_raise_usd/class_series_e_ocp)/(ad_pre_f_broad_based_fd+series_f_primary_raise_usd/'Pro-Forma'!V10),class_series_e_ocp) -> 48.912626 | AI10: =class_series_e_original_shares*class_series_e_issue_pps/'Pro-Forma'!AH10 -> 6133320.3 | AJ10: ='Pro-Forma'!Y10-class_seed_current_shares+'Pro-Forma'!AA10-class_series_a_current_shares+'Pro-Forma'!AC10-class_series_b_current_shares+'Pro-Forma'!AE10-class_series_c_current_shares+'Pro-Forma'!AG10-class_series_d_current_shares+'Pro-Forma'!AI10-class_series_e_current_shares -> 43677.622 | AK10: =note_a_cap_usd/(pre_f_fd_total+'Pro-Forma'!S10+'Pro-Forma'!AJ10+'Pro-Forma'!U10) -> 26.778556 | AL10: ='Pro-Forma'!V10*(const_one-note_a_discount) -> 30.102801 | AM10: =MIN('Pro-Forma'!AK10,'Pro-Forma'!AL10) -> 26.778556 | AN10: =note_a_principal_usd/'Pro-Forma'!AM10 -> 186716.57 | AO10: =note_b_cap_usd/(pre_f_fd_total+'Pro-Forma'!S10+'Pro-Forma'!AJ10+'Pro-Forma'!T10) -> 42.739342 | AP10: ='Pro-Forma'!V10*(const_one-note_b_discount) -> 31.984226 | AQ10: =MIN('Pro-Forma'!AO10,'Pro-Forma'!AP10) -> 31.984226 | AR10: =note_b_principal_usd/'Pro-Forma'!AQ10 -> 93796.235 | AS10: =pre_f_fd_total+'Pro-Forma'!S10+'Pro-Forma'!W10+'Pro-Forma'!AN10+'Pro-Forma'!AR10+'Pro-Forma'!AJ10 -> 38327298 | AT10: =MAX(const_zero,esop_refresh_target_post_f*'Pro-Forma'!AS10-pre_f_option_pool_total) -> 587881.76
A11: =lbl_note_b_shares -> Note B shares | B11: =I32 -> 93796.243 | R11: ='Pro-Forma'!R10+const_one -> 7 | S11: ='Pro-Forma'!AT10 -> 587881.76 | T11: ='Pro-Forma'!AN10 -> 186716.57 | U11: ='Pro-Forma'!AR10 -> 93796.235 | V11: =series_f_pre_money_usd/(pre_f_fd_total+'Pro-Forma'!S11) -> 37.628499 | W11: =series_f_primary_raise_usd/'Pro-Forma'!V11 -> 797268.06 | X11: =IF('Pro-Forma'!V11<class_seed_ocp,class_seed_ocp*(ad_pre_f_broad_based_fd+series_f_primary_raise_usd/class_seed_ocp)/(ad_pre_f_broad_based_fd+series_f_primary_raise_usd/'Pro-Forma'!V11),class_seed_ocp) -> 1 | Y11: =class_seed_original_shares*class_seed_issue_pps/'Pro-Forma'!X11 -> 5000000 | Z11: =IF('Pro-Forma'!V11<class_series_a_ocp,class_series_a_ocp*(ad_pre_f_broad_based_fd+series_f_primary_raise_usd/class_series_a_ocp)/(ad_pre_f_broad_based_fd+series_f_primary_raise_usd/'Pro-Forma'!V11),class_series_a_ocp) -> 3 | AA11: =class_series_a_original_shares*class_series_a_issue_pps/'Pro-Forma'!Z11 -> 5000000 | AB11: =IF('Pro-Forma'!V11<class_series_b_ocp,class_series_b_ocp*(ad_pre_f_broad_based_fd+series_f_primary_raise_usd/class_series_b_ocp)/(ad_pre_f_broad_based_fd+series_f_primary_raise_usd/'Pro-Forma'!V11),class_series_b_ocp) -> 10 | AC11: =class_series_b_original_shares*class_series_b_issue_pps/'Pro-Forma'!AB11 -> 3000000 | AD11: =IF('Pro-Forma'!V11<class_series_c_ocp,class_series_c_ocp*(ad_pre_f_broad_based_fd+series_f_primary_raise_usd/class_series_c_ocp)/(ad_pre_f_broad_based_fd+series_f_primary_raise_usd/'Pro-Forma'!V11),class_series_c_ocp) -> 25 | AE11: =class_series_c_original_shares*class_series_c_issue_pps/'Pro-Forma'!AD11 -> 2400000 | AF11: =IF('Pro-Forma'!V11<class_series_d_ocp,class_series_d_ocp*(ad_pre_f_broad_based_fd+series_f_primary_raise_usd/class_series_d_ocp)/(ad_pre_f_broad_based_fd+series_f_primary_raise_usd/'Pro-Forma'!V11),class_series_d_ocp) -> 57.681736 | AG11: =class_series_d_original_shares*class_series_d_issue_pps/'Pro-Forma'!AF11 -> 1733651.4 | AH11: =IF('Pro-Forma'!V11<class_series_e_ocp,class_series_e_ocp*(ad_pre_f_broad_based_fd+series_f_primary_raise_usd/class_series_e_ocp)/(ad_pre_f_broad_based_fd+series_f_primary_raise_usd/'Pro-Forma'!V11),class_series_e_ocp) -> 48.912626 | AI11: =class_series_e_original_shares*class_series_e_issue_pps/'Pro-Forma'!AH11 -> 6133320.3 | AJ11: ='Pro-Forma'!Y11-class_seed_current_shares+'Pro-Forma'!AA11-class_series_a_current_shares+'Pro-Forma'!AC11-class_series_b_current_shares+'Pro-Forma'!AE11-class_series_c_current_shares+'Pro-Forma'!AG11-class_series_d_current_shares+'Pro-Forma'!AI11-class_series_e_current_shares -> 43677.636 | AK11: =note_a_cap_usd/(pre_f_fd_total+'Pro-Forma'!S11+'Pro-Forma'!AJ11+'Pro-Forma'!U11) -> 26.778553 | AL11: ='Pro-Forma'!V11*(const_one-note_a_discount) -> 30.102799 | AM11: =MIN('Pro-Forma'!AK11,'Pro-Forma'!AL11) -> 26.778553 | AN11: =note_a_principal_usd/'Pro-Forma'!AM11 -> 186716.58 | AO11: =note_b_cap_usd/(pre_f_fd_total+'Pro-Forma'!S11+'Pro-Forma'!AJ11+'Pro-Forma'!T11) -> 42.739338 | AP11: ='Pro-Forma'!V11*(const_one-note_b_discount) -> 31.984224 | AQ11: =MIN('Pro-Forma'!AO11,'Pro-Forma'!AP11) -> 31.984224 | AR11: =note_b_principal_usd/'Pro-Forma'!AQ11 -> 93796.242 | AS11: =pre_f_fd_total+'Pro-Forma'!S11+'Pro-Forma'!W11+'Pro-Forma'!AN11+'Pro-Forma'!AR11+'Pro-Forma'!AJ11 -> 38327301 | AT11: =MAX(const_zero,esop_refresh_target_post_f*'Pro-Forma'!AS11-pre_f_option_pool_total) -> 587882.17
A12: =lbl_f_lead_secondary -> F_LEAD secondary common | B12: =B39 -> 468981.22 | R12: ='Pro-Forma'!R11+const_one -> 8 | S12: ='Pro-Forma'!AT11 -> 587882.17 | T12: ='Pro-Forma'!AN11 -> 186716.58 | U12: ='Pro-Forma'!AR11 -> 93796.242 | V12: =series_f_pre_money_usd/(pre_f_fd_total+'Pro-Forma'!S12) -> 37.628498 | W12: =series_f_primary_raise_usd/'Pro-Forma'!V12 -> 797268.07 | X12: =IF('Pro-Forma'!V12<class_seed_ocp,class_seed_ocp*(ad_pre_f_broad_based_fd+series_f_primary_raise_usd/class_seed_ocp)/(ad_pre_f_broad_based_fd+series_f_primary_raise_usd/'Pro-Forma'!V12),class_seed_ocp) -> 1 | Y12: =class_seed_original_shares*class_seed_issue_pps/'Pro-Forma'!X12 -> 5000000 | Z12: =IF('Pro-Forma'!V12<class_series_a_ocp,class_series_a_ocp*(ad_pre_f_broad_based_fd+series_f_primary_raise_usd/class_series_a_ocp)/(ad_pre_f_broad_based_fd+series_f_primary_raise_usd/'Pro-Forma'!V12),class_series_a_ocp) -> 3 | AA12: =class_series_a_original_shares*class_series_a_issue_pps/'Pro-Forma'!Z12 -> 5000000 | AB12: =IF('Pro-Forma'!V12<class_series_b_ocp,class_series_b_ocp*(ad_pre_f_broad_based_fd+series_f_primary_raise_usd/class_series_b_ocp)/(ad_pre_f_broad_based_fd+series_f_primary_raise_usd/'Pro-Forma'!V12),class_series_b_ocp) -> 10 | AC12: =class_series_b_original_shares*class_series_b_issue_pps/'Pro-Forma'!AB12 -> 3000000 | AD12: =IF('Pro-Forma'!V12<class_series_c_ocp,class_series_c_ocp*(ad_pre_f_broad_based_fd+series_f_primary_raise_usd/class_series_c_ocp)/(ad_pre_f_broad_based_fd+series_f_primary_raise_usd/'Pro-Forma'!V12),class_series_c_ocp) -> 25 | AE12: =class_series_c_original_shares*class_series_c_issue_pps/'Pro-Forma'!AD12 -> 2400000 | AF12: =IF('Pro-Forma'!V12<class_series_d_ocp,class_series_d_ocp*(ad_pre_f_broad_based_fd+series_f_primary_raise_usd/class_series_d_ocp)/(ad_pre_f_broad_based_fd+series_f_primary_raise_usd/'Pro-Forma'!V12),class_series_d_ocp) -> 57.681736 | AG12: =class_series_d_original_shares*class_series_d_issue_pps/'Pro-Forma'!AF12 -> 1733651.4 | AH12: =IF('Pro-Forma'!V12<class_series_e_ocp,class_series_e_ocp*(ad_pre_f_broad_based_fd+series_f_primary_raise_usd/class_series_e_ocp)/(ad_pre_f_broad_based_fd+series_f_primary_raise_usd/'Pro-Forma'!V12),class_series_e_ocp) -> 48.912626 | AI12: =class_series_e_original_shares*class_series_e_issue_pps/'Pro-Forma'!AH12 -> 6133320.3 | AJ12: ='Pro-Forma'!Y12-class_seed_current_shares+'Pro-Forma'!AA12-class_series_a_current_shares+'Pro-Forma'!AC12-class_series_b_current_shares+'Pro-Forma'!AE12-class_series_c_current_shares+'Pro-Forma'!AG12-class_series_d_current_shares+'Pro-Forma'!AI12-class_series_e_current_shares -> 43677.637 | AK12: =note_a_cap_usd/(pre_f_fd_total+'Pro-Forma'!S12+'Pro-Forma'!AJ12+'Pro-Forma'!U12) -> 26.778553 | AL12: ='Pro-Forma'!V12*(const_one-note_a_discount) -> 30.102799 | AM12: =MIN('Pro-Forma'!AK12,'Pro-Forma'!AL12) -> 26.778553 | AN12: =note_a_principal_usd/'Pro-Forma'!AM12 -> 186716.59 | AO12: =note_b_cap_usd/(pre_f_fd_total+'Pro-Forma'!S12+'Pro-Forma'!AJ12+'Pro-Forma'!T12) -> 42.739338 | AP12: ='Pro-Forma'!V12*(const_one-note_b_discount) -> 31.984223 | AQ12: =MIN('Pro-Forma'!AO12,'Pro-Forma'!AP12) -> 31.984223 | AR12: =note_b_principal_usd/'Pro-Forma'!AQ12 -> 93796.243 | AS12: =pre_f_fd_total+'Pro-Forma'!S12+'Pro-Forma'!W12+'Pro-Forma'!AN12+'Pro-Forma'!AR12+'Pro-Forma'!AJ12 -> 38327302 | AT12: =MAX(const_zero,esop_refresh_target_post_f*'Pro-Forma'!AS12-pre_f_option_pool_total) -> 587882.22
A13: =lbl_common_gross_pps -> Gross common PPS | B13: =B4 -> 37.628498 | R13: ='Pro-Forma'!R12+const_one -> 9 | S13: ='Pro-Forma'!AT12 -> 587882.22 | T13: ='Pro-Forma'!AN12 -> 186716.59 | U13: ='Pro-Forma'!AR12 -> 93796.243 | V13: =series_f_pre_money_usd/(pre_f_fd_total+'Pro-Forma'!S13) -> 37.628498 | W13: =series_f_primary_raise_usd/'Pro-Forma'!V13 -> 797268.07 | X13: =IF('Pro-Forma'!V13<class_seed_ocp,class_seed_ocp*(ad_pre_f_broad_based_fd+series_f_primary_raise_usd/class_seed_ocp)/(ad_pre_f_broad_based_fd+series_f_primary_raise_usd/'Pro-Forma'!V13),class_seed_ocp) -> 1 | Y13: =class_seed_original_shares*class_seed_issue_pps/'Pro-Forma'!X13 -> 5000000 | Z13: =IF('Pro-Forma'!V13<class_series_a_ocp,class_series_a_ocp*(ad_pre_f_broad_based_fd+series_f_primary_raise_usd/class_series_a_ocp)/(ad_pre_f_broad_based_fd+series_f_primary_raise_usd/'Pro-Forma'!V13),class_series_a_ocp) -> 3 | AA13: =class_series_a_original_shares*class_series_a_issue_pps/'Pro-Forma'!Z13 -> 5000000 | AB13: =IF('Pro-Forma'!V13<class_series_b_ocp,class_series_b_ocp*(ad_pre_f_broad_based_fd+series_f_primary_raise_usd/class_series_b_ocp)/(ad_pre_f_broad_based_fd+series_f_primary_raise_usd/'Pro-Forma'!V13),class_series_b_ocp) -> 10 | AC13: =class_series_b_original_shares*class_series_b_issue_pps/'Pro-Forma'!AB13 -> 3000000 | AD13: =IF('Pro-Forma'!V13<class_series_c_ocp,class_series_c_ocp*(ad_pre_f_broad_based_fd+series_f_primary_raise_usd/class_series_c_ocp)/(ad_pre_f_broad_based_fd+series_f_primary_raise_usd/'Pro-Forma'!V13),class_series_c_ocp) -> 25 | AE13: =class_series_c_original_shares*class_series_c_issue_pps/'Pro-Forma'!AD13 -> 2400000 | AF13: =IF('Pro-Forma'!V13<class_series_d_ocp,class_series_d_ocp*(ad_pre_f_broad_based_fd+series_f_primary_raise_usd/class_series_d_ocp)/(ad_pre_f_broad_based_fd+series_f_primary_raise_usd/'Pro-Forma'!V13),class_series_d_ocp) -> 57.681736 | AG13: =class_series_d_original_shares*class_series_d_issue_pps/'Pro-Forma'!AF13 -> 1733651.4 | AH13: =IF('Pro-Forma'!V13<class_series_e_ocp,class_series_e_ocp*(ad_pre_f_broad_based_fd+series_f_primary_raise_usd/class_series_e_ocp)/(ad_pre_f_broad_based_fd+series_f_primary_raise_usd/'Pro-Forma'!V13),class_series_e_ocp) -> 48.912626 | AI13: =class_series_e_original_shares*class_series_e_issue_pps/'Pro-Forma'!AH13 -> 6133320.3 | AJ13: ='Pro-Forma'!Y13-class_seed_current_shares+'Pro-Forma'!AA13-class_series_a_current_shares+'Pro-Forma'!AC13-class_series_b_current_shares+'Pro-Forma'!AE13-class_series_c_current_shares+'Pro-Forma'!AG13-class_series_d_current_shares+'Pro-Forma'!AI13-class_series_e_current_shares -> 43677.638 | AK13: =note_a_cap_usd/(pre_f_fd_total+'Pro-Forma'!S13+'Pro-Forma'!AJ13+'Pro-Forma'!U13) -> 26.778553 | AL13: ='Pro-Forma'!V13*(const_one-note_a_discount) -> 30.102798 | AM13: =MIN('Pro-Forma'!AK13,'Pro-Forma'!AL13) -> 26.778553 | AN13: =note_a_principal_usd/'Pro-Forma'!AM13 -> 186716.59 | AO13: =note_b_cap_usd/(pre_f_fd_total+'Pro-Forma'!S13+'Pro-Forma'!AJ13+'Pro-Forma'!T13) -> 42.739338 | AP13: ='Pro-Forma'!V13*(const_one-note_b_discount) -> 31.984223 | AQ13: =MIN('Pro-Forma'!AO13,'Pro-Forma'!AP13) -> 31.984223 | AR13: =note_b_principal_usd/'Pro-Forma'!AQ13 -> 93796.243 | AS13: =pre_f_fd_total+'Pro-Forma'!S13+'Pro-Forma'!W13+'Pro-Forma'!AN13+'Pro-Forma'!AR13+'Pro-Forma'!AJ13 -> 38327302 | AT13: =MAX(const_zero,esop_refresh_target_post_f*'Pro-Forma'!AS13-pre_f_option_pool_total) -> 587882.23
A14: =lbl_post_f_fd -> Post-F FD shares | B14: =pre_f_fd_total+B8+B5+B10+B11+B9 -> 38327302 | R14: ='Pro-Forma'!R13+const_one -> 10 | S14: ='Pro-Forma'!AT13 -> 587882.23 | T14: ='Pro-Forma'!AN13 -> 186716.59 | U14: ='Pro-Forma'!AR13 -> 93796.243 | V14: =series_f_pre_money_usd/(pre_f_fd_total+'Pro-Forma'!S14) -> 37.628498 | W14: =series_f_primary_raise_usd/'Pro-Forma'!V14 -> 797268.07 | X14: =IF('Pro-Forma'!V14<class_seed_ocp,class_seed_ocp*(ad_pre_f_broad_based_fd+series_f_primary_raise_usd/class_seed_ocp)/(ad_pre_f_broad_based_fd+series_f_primary_raise_usd/'Pro-Forma'!V14),class_seed_ocp) -> 1 | Y14: =class_seed_original_shares*class_seed_issue_pps/'Pro-Forma'!X14 -> 5000000 | Z14: =IF('Pro-Forma'!V14<class_series_a_ocp,class_series_a_ocp*(ad_pre_f_broad_based_fd+series_f_primary_raise_usd/class_series_a_ocp)/(ad_pre_f_broad_based_fd+series_f_primary_raise_usd/'Pro-Forma'!V14),class_series_a_ocp) -> 3 | AA14: =class_series_a_original_shares*class_series_a_issue_pps/'Pro-Forma'!Z14 -> 5000000 | AB14: =IF('Pro-Forma'!V14<class_series_b_ocp,class_series_b_ocp*(ad_pre_f_broad_based_fd+series_f_primary_raise_usd/class_series_b_ocp)/(ad_pre_f_broad_based_fd+series_f_primary_raise_usd/'Pro-Forma'!V14),class_series_b_ocp) -> 10 | AC14: =class_series_b_original_shares*class_series_b_issue_pps/'Pro-Forma'!AB14 -> 3000000 | AD14: =IF('Pro-Forma'!V14<class_series_c_ocp,class_series_c_ocp*(ad_pre_f_broad_based_fd+series_f_primary_raise_usd/class_series_c_ocp)/(ad_pre_f_broad_based_fd+series_f_primary_raise_usd/'Pro-Forma'!V14),class_series_c_ocp) -> 25 | AE14: =class_series_c_original_shares*class_series_c_issue_pps/'Pro-Forma'!AD14 -> 2400000 | AF14: =IF('Pro-Forma'!V14<class_series_d_ocp,class_series_d_ocp*(ad_pre_f_broad_based_fd+series_f_primary_raise_usd/class_series_d_ocp)/(ad_pre_f_broad_based_fd+series_f_primary_raise_usd/'Pro-Forma'!V14),class_series_d_ocp) -> 57.681736 | AG14: =class_series_d_original_shares*class_series_d_issue_pps/'Pro-Forma'!AF14 -> 1733651.4 | AH14: =IF('Pro-Forma'!V14<class_series_e_ocp,class_series_e_ocp*(ad_pre_f_broad_based_fd+series_f_primary_raise_usd/class_series_e_ocp)/(ad_pre_f_broad_based_fd+series_f_primary_raise_usd/'Pro-Forma'!V14),class_series_e_ocp) -> 48.912626 | AI14: =class_series_e_original_shares*class_series_e_issue_pps/'Pro-Forma'!AH14 -> 6133320.3 | AJ14: ='Pro-Forma'!Y14-class_seed_current_shares+'Pro-Forma'!AA14-class_series_a_current_shares+'Pro-Forma'!AC14-class_series_b_current_shares+'Pro-Forma'!AE14-class_series_c_current_shares+'Pro-Forma'!AG14-class_series_d_current_shares+'Pro-Forma'!AI14-class_series_e_current_shares -> 43677.638 | AK14: =note_a_cap_usd/(pre_f_fd_total+'Pro-Forma'!S14+'Pro-Forma'!AJ14+'Pro-Forma'!U14) -> 26.778553 | AL14: ='Pro-Forma'!V14*(const_one-note_a_discount) -> 30.102798 | AM14: =MIN('Pro-Forma'!AK14,'Pro-Forma'!AL14) -> 26.778553 | AN14: =note_a_principal_usd/'Pro-Forma'!AM14 -> 186716.59 | AO14: =note_b_cap_usd/(pre_f_fd_total+'Pro-Forma'!S14+'Pro-Forma'!AJ14+'Pro-Forma'!T14) -> 42.739338 | AP14: ='Pro-Forma'!V14*(const_one-note_b_discount) -> 31.984223 | AQ14: =MIN('Pro-Forma'!AO14,'Pro-Forma'!AP14) -> 31.984223 | AR14: =note_b_principal_usd/'Pro-Forma'!AQ14 -> 93796.243 | AS14: =pre_f_fd_total+'Pro-Forma'!S14+'Pro-Forma'!W14+'Pro-Forma'!AN14+'Pro-Forma'!AR14+'Pro-Forma'!AJ14 -> 38327302 | AT14: =MAX(const_zero,esop_refresh_target_post_f*'Pro-Forma'!AS14-pre_f_option_pool_total) -> 587882.23
R15: ='Pro-Forma'!R14+const_one -> 11 | S15: ='Pro-Forma'!AT14 -> 587882.23 | T15: ='Pro-Forma'!AN14 -> 186716.59 | U15: ='Pro-Forma'!AR14 -> 93796.243 | V15: =series_f_pre_money_usd/(pre_f_fd_total+'Pro-Forma'!S15) -> 37.628498 | W15: =series_f_primary_raise_usd/'Pro-Forma'!V15 -> 797268.07 | X15: =IF('Pro-Forma'!V15<class_seed_ocp,class_seed_ocp*(ad_pre_f_broad_based_fd+series_f_primary_raise_usd/class_seed_ocp)/(ad_pre_f_broad_based_fd+series_f_primary_raise_usd/'Pro-Forma'!V15),class_seed_ocp) -> 1 | Y15: =class_seed_original_shares*class_seed_issue_pps/'Pro-Forma'!X15 -> 5000000 | Z15: =IF('Pro-Forma'!V15<class_series_a_ocp,class_series_a_ocp*(ad_pre_f_broad_based_fd+series_f_primary_raise_usd/class_series_a_ocp)/(ad_pre_f_broad_based_fd+series_f_primary_raise_usd/'Pro-Forma'!V15),class_series_a_ocp) -> 3 | AA15: =class_series_a_original_shares*class_series_a_issue_pps/'Pro-Forma'!Z15 -> 5000000 | AB15: =IF('Pro-Forma'!V15<class_series_b_ocp,class_series_b_ocp*(ad_pre_f_broad_based_fd+series_f_primary_raise_usd/class_series_b_ocp)/(ad_pre_f_broad_based_fd+series_f_primary_raise_usd/'Pro-Forma'!V15),class_series_b_ocp) -> 10 | AC15: =class_series_b_original_shares*class_series_b_issue_pps/'Pro-Forma'!AB15 -> 3000000 | AD15: =IF('Pro-Forma'!V15<class_series_c_ocp,class_series_c_ocp*(ad_pre_f_broad_based_fd+series_f_primary_raise_usd/class_series_c_ocp)/(ad_pre_f_broad_based_fd+series_f_primary_raise_usd/'Pro-Forma'!V15),class_series_c_ocp) -> 25 | AE15: =class_series_c_original_shares*class_series_c_issue_pps/'Pro-Forma'!AD15 -> 2400000 | AF15: =IF('Pro-Forma'!V15<class_series_d_ocp,class_series_d_ocp*(ad_pre_f_broad_based_fd+series_f_primary_raise_usd/class_series_d_ocp)/(ad_pre_f_broad_based_fd+series_f_primary_raise_usd/'Pro-Forma'!V15),class_series_d_ocp) -> 57.681736 | AG15: =class_series_d_original_shares*class_series_d_issue_pps/'Pro-Forma'!AF15 -> 1733651.4 | AH15: =IF('Pro-Forma'!V15<class_series_e_ocp,class_series_e_ocp*(ad_pre_f_broad_based_fd+series_f_primary_raise_usd/class_series_e_ocp)/(ad_pre_f_broad_based_fd+series_f_primary_raise_usd/'Pro-Forma'!V15),class_series_e_ocp) -> 48.912626 | AI15: =class_series_e_original_shares*class_series_e_issue_pps/'Pro-Forma'!AH15 -> 6133320.3 | AJ15: ='Pro-Forma'!Y15-class_seed_current_shares+'Pro-Forma'!AA15-class_series_a_current_shares+'Pro-Forma'!AC15-class_series_b_current_shares+'Pro-Forma'!AE15-class_series_c_current_shares+'Pro-Forma'!AG15-class_series_d_current_shares+'Pro-Forma'!AI15-class_series_e_current_shares -> 43677.638 | AK15: =note_a_cap_usd/(pre_f_fd_total+'Pro-Forma'!S15+'Pro-Forma'!AJ15+'Pro-Forma'!U15) -> 26.778553 | AL15: ='Pro-Forma'!V15*(const_one-note_a_discount) -> 30.102798 | AM15: =MIN('Pro-Forma'!AK15,'Pro-Forma'!AL15) -> 26.778553 | AN15: =note_a_principal_usd/'Pro-Forma'!AM15 -> 186716.59 | AO15: =note_b_cap_usd/(pre_f_fd_total+'Pro-Forma'!S15+'Pro-Forma'!AJ15+'Pro-Forma'!T15) -> 42.739338 | AP15: ='Pro-Forma'!V15*(const_one-note_b_discount) -> 31.984223 | AQ15: =MIN('Pro-Forma'!AO15,'Pro-Forma'!AP15) -> 31.984223 | AR15: =note_b_principal_usd/'Pro-Forma'!AQ15 -> 93796.243 | AS15: =pre_f_fd_total+'Pro-Forma'!S15+'Pro-Forma'!W15+'Pro-Forma'!AN15+'Pro-Forma'!AR15+'Pro-Forma'!AJ15 -> 38327302 | AT15: =MAX(const_zero,esop_refresh_target_post_f*'Pro-Forma'!AS15-pre_f_option_pool_total) -> 587882.23
R16: ='Pro-Forma'!R15+const_one -> 12 | S16: ='Pro-Forma'!AT15 -> 587882.23 | T16: ='Pro-Forma'!AN15 -> 186716.59 | U16: ='Pro-Forma'!AR15 -> 93796.243 | V16: =series_f_pre_money_usd/(pre_f_fd_total+'Pro-Forma'!S16) -> 37.628498 | W16: =series_f_primary_raise_usd/'Pro-Forma'!V16 -> 797268.07 | X16: =IF('Pro-Forma'!V16<class_seed_ocp,class_seed_ocp*(ad_pre_f_broad_based_fd+series_f_primary_raise_usd/class_seed_ocp)/(ad_pre_f_broad_based_fd+series_f_primary_raise_usd/'Pro-Forma'!V16),class_seed_ocp) -> 1 | Y16: =class_seed_original_shares*class_seed_issue_pps/'Pro-Forma'!X16 -> 5000000 | Z16: =IF('Pro-Forma'!V16<class_series_a_ocp,class_series_a_ocp*(ad_pre_f_broad_based_fd+series_f_primary_raise_usd/class_series_a_ocp)/(ad_pre_f_broad_based_fd+series_f_primary_raise_usd/'Pro-Forma'!V16),class_series_a_ocp) -> 3 | AA16: =class_series_a_original_shares*class_series_a_issue_pps/'Pro-Forma'!Z16 -> 5000000 | AB16: =IF('Pro-Forma'!V16<class_series_b_ocp,class_series_b_ocp*(ad_pre_f_broad_based_fd+series_f_primary_raise_usd/class_series_b_ocp)/(ad_pre_f_broad_based_fd+series_f_primary_raise_usd/'Pro-Forma'!V16),class_series_b_ocp) -> 10 | AC16: =class_series_b_original_shares*class_series_b_issue_pps/'Pro-Forma'!AB16 -> 3000000 | AD16: =IF('Pro-Forma'!V16<class_series_c_ocp,class_series_c_ocp*(ad_pre_f_broad_based_fd+series_f_primary_raise_usd/class_series_c_ocp)/(ad_pre_f_broad_based_fd+series_f_primary_raise_usd/'Pro-Forma'!V16),class_series_c_ocp) -> 25 | AE16: =class_series_c_original_shares*class_series_c_issue_pps/'Pro-Forma'!AD16 -> 2400000 | AF16: =IF('Pro-Forma'!V16<class_series_d_ocp,class_series_d_ocp*(ad_pre_f_broad_based_fd+series_f_primary_raise_usd/class_series_d_ocp)/(ad_pre_f_broad_based_fd+series_f_primary_raise_usd/'Pro-Forma'!V16),class_series_d_ocp) -> 57.681736 | AG16: =class_series_d_original_shares*class_series_d_issue_pps/'Pro-Forma'!AF16 -> 1733651.4 | AH16: =IF('Pro-Forma'!V16<class_series_e_ocp,class_series_e_ocp*(ad_pre_f_broad_based_fd+series_f_primary_raise_usd/class_series_e_ocp)/(ad_pre_f_broad_based_fd+series_f_primary_raise_usd/'Pro-Forma'!V16),class_series_e_ocp) -> 48.912626 | AI16: =class_series_e_original_shares*class_series_e_issue_pps/'Pro-Forma'!AH16 -> 6133320.3 | AJ16: ='Pro-Forma'!Y16-class_seed_current_shares+'Pro-Forma'!AA16-class_series_a_current_shares+'Pro-Forma'!AC16-class_series_b_current_shares+'Pro-Forma'!AE16-class_series_c_current_shares+'Pro-Forma'!AG16-class_series_d_current_shares+'Pro-Forma'!AI16-class_series_e_current_shares -> 43677.638 | AK16: =note_a_cap_usd/(pre_f_fd_total+'Pro-Forma'!S16+'Pro-Forma'!AJ16+'Pro-Forma'!U16) -> 26.778553 | AL16: ='Pro-Forma'!V16*(const_one-note_a_discount) -> 30.102798 | AM16: =MIN('Pro-Forma'!AK16,'Pro-Forma'!AL16) -> 26.778553 | AN16: =note_a_principal_usd/'Pro-Forma'!AM16 -> 186716.59 | AO16: =note_b_cap_usd/(pre_f_fd_total+'Pro-Forma'!S16+'Pro-Forma'!AJ16+'Pro-Forma'!T16) -> 42.739338 | AP16: ='Pro-Forma'!V16*(const_one-note_b_discount) -> 31.984223 | AQ16: =MIN('Pro-Forma'!AO16,'Pro-Forma'!AP16) -> 31.984223 | AR16: =note_b_principal_usd/'Pro-Forma'!AQ16 -> 93796.243 | AS16: =pre_f_fd_total+'Pro-Forma'!S16+'Pro-Forma'!W16+'Pro-Forma'!AN16+'Pro-Forma'!AR16+'Pro-Forma'!AJ16 -> 38327302 | AT16: =MAX(const_zero,esop_refresh_target_post_f*'Pro-Forma'!AS16-pre_f_option_pool_total) -> 587882.23
R17: ='Pro-Forma'!R16+const_one -> 13 | S17: ='Pro-Forma'!AT16 -> 587882.23 | T17: ='Pro-Forma'!AN16 -> 186716.59 | U17: ='Pro-Forma'!AR16 -> 93796.243 | V17: =series_f_pre_money_usd/(pre_f_fd_total+'Pro-Forma'!S17) -> 37.628498 | W17: =series_f_primary_raise_usd/'Pro-Forma'!V17 -> 797268.07 | X17: =IF('Pro-Forma'!V17<class_seed_ocp,class_seed_ocp*(ad_pre_f_broad_based_fd+series_f_primary_raise_usd/class_seed_ocp)/(ad_pre_f_broad_based_fd+series_f_primary_raise_usd/'Pro-Forma'!V17),class_seed_ocp) -> 1 | Y17: =class_seed_original_shares*class_seed_issue_pps/'Pro-Forma'!X17 -> 5000000 | Z17: =IF('Pro-Forma'!V17<class_series_a_ocp,class_series_a_ocp*(ad_pre_f_broad_based_fd+series_f_primary_raise_usd/class_series_a_ocp)/(ad_pre_f_broad_based_fd+series_f_primary_raise_usd/'Pro-Forma'!V17),class_series_a_ocp) -> 3 | AA17: =class_series_a_original_shares*class_series_a_issue_pps/'Pro-Forma'!Z17 -> 5000000 | AB17: =IF('Pro-Forma'!V17<class_series_b_ocp,class_series_b_ocp*(ad_pre_f_broad_based_fd+series_f_primary_raise_usd/class_series_b_ocp)/(ad_pre_f_broad_based_fd+series_f_primary_raise_usd/'Pro-Forma'!V17),class_series_b_ocp) -> 10 | AC17: =class_series_b_original_shares*class_series_b_issue_pps/'Pro-Forma'!AB17 -> 3000000 | AD17: =IF('Pro-Forma'!V17<class_series_c_ocp,class_series_c_ocp*(ad_pre_f_broad_based_fd+series_f_primary_raise_usd/class_series_c_ocp)/(ad_pre_f_broad_based_fd+series_f_primary_raise_usd/'Pro-Forma'!V17),class_series_c_ocp) -> 25 | AE17: =class_series_c_original_shares*class_series_c_issue_pps/'Pro-Forma'!AD17 -> 2400000 | AF17: =IF('Pro-Forma'!V17<class_series_d_ocp,class_series_d_ocp*(ad_pre_f_broad_based_fd+series_f_primary_raise_usd/class_series_d_ocp)/(ad_pre_f_broad_based_fd+series_f_primary_raise_usd/'Pro-Forma'!V17),class_series_d_ocp) -> 57.681736 | AG17: =class_series_d_original_shares*class_series_d_issue_pps/'Pro-Forma'!AF17 -> 1733651.4 | AH17: =IF('Pro-Forma'!V17<class_series_e_ocp,class_series_e_ocp*(ad_pre_f_broad_based_fd+series_f_primary_raise_usd/class_series_e_ocp)/(ad_pre_f_broad_based_fd+series_f_primary_raise_usd/'Pro-Forma'!V17),class_series_e_ocp) -> 48.912626 | AI17: =class_series_e_original_shares*class_series_e_issue_pps/'Pro-Forma'!AH17 -> 6133320.3 | AJ17: ='Pro-Forma'!Y17-class_seed_current_shares+'Pro-Forma'!AA17-class_series_a_current_shares+'Pro-Forma'!AC17-class_series_b_current_shares+'Pro-Forma'!AE17-class_series_c_current_shares+'Pro-Forma'!AG17-class_series_d_current_shares+'Pro-Forma'!AI17-class_series_e_current_shares -> 43677.638 | AK17: =note_a_cap_usd/(pre_f_fd_total+'Pro-Forma'!S17+'Pro-Forma'!AJ17+'Pro-Forma'!U17) -> 26.778553 | AL17: ='Pro-Forma'!V17*(const_one-note_a_discount) -> 30.102798 | AM17: =MIN('Pro-Forma'!AK17,'Pro-Forma'!AL17) -> 26.778553 | AN17: =note_a_principal_usd/'Pro-Forma'!AM17 -> 186716.59 | AO17: =note_b_cap_usd/(pre_f_fd_total+'Pro-Forma'!S17+'Pro-Forma'!AJ17+'Pro-Forma'!T17) -> 42.739338 | AP17: ='Pro-Forma'!V17*(const_one-note_b_discount) -> 31.984223 | AQ17: =MIN('Pro-Forma'!AO17,'Pro-Forma'!AP17) -> 31.984223 | AR17: =note_b_principal_usd/'Pro-Forma'!AQ17 -> 93796.243 | AS17: =pre_f_fd_total+'Pro-Forma'!S17+'Pro-Forma'!W17+'Pro-Forma'!AN17+'Pro-Forma'!AR17+'Pro-Forma'!AJ17 -> 38327302 | AT17: =MAX(const_zero,esop_refresh_target_post_f*'Pro-Forma'!AS17-pre_f_option_pool_total) -> 587882.23
A18: =lbl_ad_block -> Anti-Dilution Block | R18: ='Pro-Forma'!R17+const_one -> 14 | S18: ='Pro-Forma'!AT17 -> 587882.23 | T18: ='Pro-Forma'!AN17 -> 186716.59 | U18: ='Pro-Forma'!AR17 -> 93796.243 | V18: =series_f_pre_money_usd/(pre_f_fd_total+'Pro-Forma'!S18) -> 37.628498 | W18: =series_f_primary_raise_usd/'Pro-Forma'!V18 -> 797268.07 | X18: =IF('Pro-Forma'!V18<class_seed_ocp,class_seed_ocp*(ad_pre_f_broad_based_fd+series_f_primary_raise_usd/class_seed_ocp)/(ad_pre_f_broad_based_fd+series_f_primary_raise_usd/'Pro-Forma'!V18),class_seed_ocp) -> 1 | Y18: =class_seed_original_shares*class_seed_issue_pps/'Pro-Forma'!X18 -> 5000000 | Z18: =IF('Pro-Forma'!V18<class_series_a_ocp,class_series_a_ocp*(ad_pre_f_broad_based_fd+series_f_primary_raise_usd/class_series_a_ocp)/(ad_pre_f_broad_based_fd+series_f_primary_raise_usd/'Pro-Forma'!V18),class_series_a_ocp) -> 3 | AA18: =class_series_a_original_shares*class_series_a_issue_pps/'Pro-Forma'!Z18 -> 5000000 | AB18: =IF('Pro-Forma'!V18<class_series_b_ocp,class_series_b_ocp*(ad_pre_f_broad_based_fd+series_f_primary_raise_usd/class_series_b_ocp)/(ad_pre_f_broad_based_fd+series_f_primary_raise_usd/'Pro-Forma'!V18),class_series_b_ocp) -> 10 | AC18: =class_series_b_original_shares*class_series_b_issue_pps/'Pro-Forma'!AB18 -> 3000000 | AD18: =IF('Pro-Forma'!V18<class_series_c_ocp,class_series_c_ocp*(ad_pre_f_broad_based_fd+series_f_primary_raise_usd/class_series_c_ocp)/(ad_pre_f_broad_based_fd+series_f_primary_raise_usd/'Pro-Forma'!V18),class_series_c_ocp) -> 25 | AE18: =class_series_c_original_shares*class_series_c_issue_pps/'Pro-Forma'!AD18 -> 2400000 | AF18: =IF('Pro-Forma'!V18<class_series_d_ocp,class_series_d_ocp*(ad_pre_f_broad_based_fd+series_f_primary_raise_usd/class_series_d_ocp)/(ad_pre_f_broad_based_fd+series_f_primary_raise_usd/'Pro-Forma'!V18),class_series_d_ocp) -> 57.681736 | AG18: =class_series_d_original_shares*class_series_d_issue_pps/'Pro-Forma'!AF18 -> 1733651.4 | AH18: =IF('Pro-Forma'!V18<class_series_e_ocp,class_series_e_ocp*(ad_pre_f_broad_based_fd+series_f_primary_raise_usd/class_series_e_ocp)/(ad_pre_f_broad_based_fd+series_f_primary_raise_usd/'Pro-Forma'!V18),class_series_e_ocp) -> 48.912626 | AI18: =class_series_e_original_shares*class_series_e_issue_pps/'Pro-Forma'!AH18 -> 6133320.3 | AJ18: ='Pro-Forma'!Y18-class_seed_current_shares+'Pro-Forma'!AA18-class_series_a_current_shares+'Pro-Forma'!AC18-class_series_b_current_shares+'Pro-Forma'!AE18-class_series_c_current_shares+'Pro-Forma'!AG18-class_series_d_current_shares+'Pro-Forma'!AI18-class_series_e_current_shares -> 43677.638 | AK18: =note_a_cap_usd/(pre_f_fd_total+'Pro-Forma'!S18+'Pro-Forma'!AJ18+'Pro-Forma'!U18) -> 26.778553 | AL18: ='Pro-Forma'!V18*(const_one-note_a_discount) -> 30.102798 | AM18: =MIN('Pro-Forma'!AK18,'Pro-Forma'!AL18) -> 26.778553 | AN18: =note_a_principal_usd/'Pro-Forma'!AM18 -> 186716.59 | AO18: =note_b_cap_usd/(pre_f_fd_total+'Pro-Forma'!S18+'Pro-Forma'!AJ18+'Pro-Forma'!T18) -> 42.739338 | AP18: ='Pro-Forma'!V18*(const_one-note_b_discount) -> 31.984223 | AQ18: =MIN('Pro-Forma'!AO18,'Pro-Forma'!AP18) -> 31.984223 | AR18: =note_b_principal_usd/'Pro-Forma'!AQ18 -> 93796.243 | AS18: =pre_f_fd_total+'Pro-Forma'!S18+'Pro-Forma'!W18+'Pro-Forma'!AN18+'Pro-Forma'!AR18+'Pro-Forma'!AJ18 -> 38327302 | AT18: =MAX(const_zero,esop_refresh_target_post_f*'Pro-Forma'!AS18-pre_f_option_pool_total) -> 587882.23
R19: ='Pro-Forma'!R18+const_one -> 15 | S19: ='Pro-Forma'!AT18 -> 587882.23 | T19: ='Pro-Forma'!AN18 -> 186716.59 | U19: ='Pro-Forma'!AR18 -> 93796.243 | V19: =series_f_pre_money_usd/(pre_f_fd_total+'Pro-Forma'!S19) -> 37.628498 | W19: =series_f_primary_raise_usd/'Pro-Forma'!V19 -> 797268.07 | X19: =IF('Pro-Forma'!V19<class_seed_ocp,class_seed_ocp*(ad_pre_f_broad_based_fd+series_f_primary_raise_usd/class_seed_ocp)/(ad_pre_f_broad_based_fd+series_f_primary_raise_usd/'Pro-Forma'!V19),class_seed_ocp) -> 1 | Y19: =class_seed_original_shares*class_seed_issue_pps/'Pro-Forma'!X19 -> 5000000 | Z19: =IF('Pro-Forma'!V19<class_series_a_ocp,class_series_a_ocp*(ad_pre_f_broad_based_fd+series_f_primary_raise_usd/class_series_a_ocp)/(ad_pre_f_broad_based_fd+series_f_primary_raise_usd/'Pro-Forma'!V19),class_series_a_ocp) -> 3 | AA19: =class_series_a_original_shares*class_series_a_issue_pps/'Pro-Forma'!Z19 -> 5000000 | AB19: =IF('Pro-Forma'!V19<class_series_b_ocp,class_series_b_ocp*(ad_pre_f_broad_based_fd+series_f_primary_raise_usd/class_series_b_ocp)/(ad_pre_f_broad_based_fd+series_f_primary_raise_usd/'Pro-Forma'!V19),class_series_b_ocp) -> 10 | AC19: =class_series_b_original_shares*class_series_b_issue_pps/'Pro-Forma'!AB19 -> 3000000 | AD19: =IF('Pro-Forma'!V19<class_series_c_ocp,class_series_c_ocp*(ad_pre_f_broad_based_fd+series_f_primary_raise_usd/class_series_c_ocp)/(ad_pre_f_broad_based_fd+series_f_primary_raise_usd/'Pro-Forma'!V19),class_series_c_ocp) -> 25 | AE19: =class_series_c_original_shares*class_series_c_issue_pps/'Pro-Forma'!AD19 -> 2400000 | AF19: =IF('Pro-Forma'!V19<class_series_d_ocp,class_series_d_ocp*(ad_pre_f_broad_based_fd+series_f_primary_raise_usd/class_series_d_ocp)/(ad_pre_f_broad_based_fd+series_f_primary_raise_usd/'Pro-Forma'!V19),class_series_d_ocp) -> 57.681736 | AG19: =class_series_d_original_shares*class_series_d_issue_pps/'Pro-Forma'!AF19 -> 1733651.4 | AH19: =IF('Pro-Forma'!V19<class_series_e_ocp,class_series_e_ocp*(ad_pre_f_broad_based_fd+series_f_primary_raise_usd/class_series_e_ocp)/(ad_pre_f_broad_based_fd+series_f_primary_raise_usd/'Pro-Forma'!V19),class_series_e_ocp) -> 48.912626 | AI19: =class_series_e_original_shares*class_series_e_issue_pps/'Pro-Forma'!AH19 -> 6133320.3 | AJ19: ='Pro-Forma'!Y19-class_seed_current_shares+'Pro-Forma'!AA19-class_series_a_current_shares+'Pro-Forma'!AC19-class_series_b_current_shares+'Pro-Forma'!AE19-class_series_c_current_shares+'Pro-Forma'!AG19-class_series_d_current_shares+'Pro-Forma'!AI19-class_series_e_current_shares -> 43677.638 | AK19: =note_a_cap_usd/(pre_f_fd_total+'Pro-Forma'!S19+'Pro-Forma'!AJ19+'Pro-Forma'!U19) -> 26.778553 | AL19: ='Pro-Forma'!V19*(const_one-note_a_discount) -> 30.102798 | AM19: =MIN('Pro-Forma'!AK19,'Pro-Forma'!AL19) -> 26.778553 | AN19: =note_a_principal_usd/'Pro-Forma'!AM19 -> 186716.59 | AO19: =note_b_cap_usd/(pre_f_fd_total+'Pro-Forma'!S19+'Pro-Forma'!AJ19+'Pro-Forma'!T19) -> 42.739338 | AP19: ='Pro-Forma'!V19*(const_one-note_b_discount) -> 31.984223 | AQ19: =MIN('Pro-Forma'!AO19,'Pro-Forma'!AP19) -> 31.984223 | AR19: =note_b_principal_usd/'Pro-Forma'!AQ19 -> 93796.243 | AS19: =pre_f_fd_total+'Pro-Forma'!S19+'Pro-Forma'!W19+'Pro-Forma'!AN19+'Pro-Forma'!AR19+'Pro-Forma'!AJ19 -> 38327302 | AT19: =MAX(const_zero,esop_refresh_target_post_f*'Pro-Forma'!AS19-pre_f_option_pool_total) -> 587882.23
A20: =lbl_class -> Class | B20: =lbl_ocp -> OCP | C20: =lbl_trigger_test -> Trigger test | D20: =lbl_new_conversion_price -> New conversion price | E20: =lbl_new_ratio -> New ratio | F20: =lbl_as_converted -> As-converted shares | G20: =lbl_ad_shares -> AD shares | R20: ='Pro-Forma'!R19+const_one -> 16 | S20: ='Pro-Forma'!AT19 -> 587882.23 | T20: ='Pro-Forma'!AN19 -> 186716.59 | U20: ='Pro-Forma'!AR19 -> 93796.243 | V20: =series_f_pre_money_usd/(pre_f_fd_total+'Pro-Forma'!S20) -> 37.628498 | W20: =series_f_primary_raise_usd/'Pro-Forma'!V20 -> 797268.07 | X20: =IF('Pro-Forma'!V20<class_seed_ocp,class_seed_ocp*(ad_pre_f_broad_based_fd+series_f_primary_raise_usd/class_seed_ocp)/(ad_pre_f_broad_based_fd+series_f_primary_raise_usd/'Pro-Forma'!V20),class_seed_ocp) -> 1 | Y20: =class_seed_original_shares*class_seed_issue_pps/'Pro-Forma'!X20 -> 5000000 | Z20: =IF('Pro-Forma'!V20<class_series_a_ocp,class_series_a_ocp*(ad_pre_f_broad_based_fd+series_f_primary_raise_usd/class_series_a_ocp)/(ad_pre_f_broad_based_fd+series_f_primary_raise_usd/'Pro-Forma'!V20),class_series_a_ocp) -> 3 | AA20: =class_series_a_original_shares*class_series_a_issue_pps/'Pro-Forma'!Z20 -> 5000000 | AB20: =IF('Pro-Forma'!V20<class_series_b_ocp,class_series_b_ocp*(ad_pre_f_broad_based_fd+series_f_primary_raise_usd/class_series_b_ocp)/(ad_pre_f_broad_based_fd+series_f_primary_raise_usd/'Pro-Forma'!V20),class_series_b_ocp) -> 10 | AC20: =class_series_b_original_shares*class_series_b_issue_pps/'Pro-Forma'!AB20 -> 3000000 | AD20: =IF('Pro-Forma'!V20<class_series_c_ocp,class_series_c_ocp*(ad_pre_f_broad_based_fd+series_f_primary_raise_usd/class_series_c_ocp)/(ad_pre_f_broad_based_fd+series_f_primary_raise_usd/'Pro-Forma'!V20),class_series_c_ocp) -> 25 | AE20: =class_series_c_original_shares*class_series_c_issue_pps/'Pro-Forma'!AD20 -> 2400000 | AF20: =IF('Pro-Forma'!V20<class_series_d_ocp,class_series_d_ocp*(ad_pre_f_broad_based_fd+series_f_primary_raise_usd/class_series_d_ocp)/(ad_pre_f_broad_based_fd+series_f_primary_raise_usd/'Pro-Forma'!V20),class_series_d_ocp) -> 57.681736 | AG20: =class_series_d_original_shares*class_series_d_issue_pps/'Pro-Forma'!AF20 -> 1733651.4 | AH20: =IF('Pro-Forma'!V20<class_series_e_ocp,class_series_e_ocp*(ad_pre_f_broad_based_fd+series_f_primary_raise_usd/class_series_e_ocp)/(ad_pre_f_broad_based_fd+series_f_primary_raise_usd/'Pro-Forma'!V20),class_series_e_ocp) -> 48.912626 | AI20: =class_series_e_original_shares*class_series_e_issue_pps/'Pro-Forma'!AH20 -> 6133320.3 | AJ20: ='Pro-Forma'!Y20-class_seed_current_shares+'Pro-Forma'!AA20-class_series_a_current_shares+'Pro-Forma'!AC20-class_series_b_current_shares+'Pro-Forma'!AE20-class_series_c_current_shares+'Pro-Forma'!AG20-class_series_d_current_shares+'Pro-Forma'!AI20-class_series_e_current_shares -> 43677.638 | AK20: =note_a_cap_usd/(pre_f_fd_total+'Pro-Forma'!S20+'Pro-Forma'!AJ20+'Pro-Forma'!U20) -> 26.778553 | AL20: ='Pro-Forma'!V20*(const_one-note_a_discount) -> 30.102798 | AM20: =MIN('Pro-Forma'!AK20,'Pro-Forma'!AL20) -> 26.778553 | AN20: =note_a_principal_usd/'Pro-Forma'!AM20 -> 186716.59 | AO20: =note_b_cap_usd/(pre_f_fd_total+'Pro-Forma'!S20+'Pro-Forma'!AJ20+'Pro-Forma'!T20) -> 42.739338 | AP20: ='Pro-Forma'!V20*(const_one-note_b_discount) -> 31.984223 | AQ20: =MIN('Pro-Forma'!AO20,'Pro-Forma'!AP20) -> 31.984223 | AR20: =note_b_principal_usd/'Pro-Forma'!AQ20 -> 93796.243 | AS20: =pre_f_fd_total+'Pro-Forma'!S20+'Pro-Forma'!W20+'Pro-Forma'!AN20+'Pro-Forma'!AR20+'Pro-Forma'!AJ20 -> 38327302 | AT20: =MAX(const_zero,esop_refresh_target_post_f*'Pro-Forma'!AS20-pre_f_option_pool_total) -> 587882.23
R21: ='Pro-Forma'!R20+const_one -> 17 | S21: ='Pro-Forma'!AT20 -> 587882.23 | T21: ='Pro-Forma'!AN20 -> 186716.59 | U21: ='Pro-Forma'!AR20 -> 93796.243 | V21: =series_f_pre_money_usd/(pre_f_fd_total+'Pro-Forma'!S21) -> 37.628498 | W21: =series_f_primary_raise_usd/'Pro-Forma'!V21 -> 797268.07 | X21: =IF('Pro-Forma'!V21<class_seed_ocp,class_seed_ocp*(ad_pre_f_broad_based_fd+series_f_primary_raise_usd/class_seed_ocp)/(ad_pre_f_broad_based_fd+series_f_primary_raise_usd/'Pro-Forma'!V21),class_seed_ocp) -> 1 | Y21: =class_seed_original_shares*class_seed_issue_pps/'Pro-Forma'!X21 -> 5000000 | Z21: =IF('Pro-Forma'!V21<class_series_a_ocp,class_series_a_ocp*(ad_pre_f_broad_based_fd+series_f_primary_raise_usd/class_series_a_ocp)/(ad_pre_f_broad_based_fd+series_f_primary_raise_usd/'Pro-Forma'!V21),class_series_a_ocp) -> 3 | AA21: =class_series_a_original_shares*class_series_a_issue_pps/'Pro-Forma'!Z21 -> 5000000 | AB21: =IF('Pro-Forma'!V21<class_series_b_ocp,class_series_b_ocp*(ad_pre_f_broad_based_fd+series_f_primary_raise_usd/class_series_b_ocp)/(ad_pre_f_broad_based_fd+series_f_primary_raise_usd/'Pro-Forma'!V21),class_series_b_ocp) -> 10 | AC21: =class_series_b_original_shares*class_series_b_issue_pps/'Pro-Forma'!AB21 -> 3000000 | AD21: =IF('Pro-Forma'!V21<class_series_c_ocp,class_series_c_ocp*(ad_pre_f_broad_based_fd+series_f_primary_raise_usd/class_series_c_ocp)/(ad_pre_f_broad_based_fd+series_f_primary_raise_usd/'Pro-Forma'!V21),class_series_c_ocp) -> 25 | AE21: =class_series_c_original_shares*class_series_c_issue_pps/'Pro-Forma'!AD21 -> 2400000 | AF21: =IF('Pro-Forma'!V21<class_series_d_ocp,class_series_d_ocp*(ad_pre_f_broad_based_fd+series_f_primary_raise_usd/class_series_d_ocp)/(ad_pre_f_broad_based_fd+series_f_primary_raise_usd/'Pro-Forma'!V21),class_series_d_ocp) -> 57.681736 | AG21: =class_series_d_original_shares*class_series_d_issue_pps/'Pro-Forma'!AF21 -> 1733651.4 | AH21: =IF('Pro-Forma'!V21<class_series_e_ocp,class_series_e_ocp*(ad_pre_f_broad_based_fd+series_f_primary_raise_usd/class_series_e_ocp)/(ad_pre_f_broad_based_fd+series_f_primary_raise_usd/'Pro-Forma'!V21),class_series_e_ocp) -> 48.912626 | AI21: =class_series_e_original_shares*class_series_e_issue_pps/'Pro-Forma'!AH21 -> 6133320.3 | AJ21: ='Pro-Forma'!Y21-class_seed_current_shares+'Pro-Forma'!AA21-class_series_a_current_shares+'Pro-Forma'!AC21-class_series_b_current_shares+'Pro-Forma'!AE21-class_series_c_current_shares+'Pro-Forma'!AG21-class_series_d_current_shares+'Pro-Forma'!AI21-class_series_e_current_shares -> 43677.638 | AK21: =note_a_cap_usd/(pre_f_fd_total+'Pro-Forma'!S21+'Pro-Forma'!AJ21+'Pro-Forma'!U21) -> 26.778553 | AL21: ='Pro-Forma'!V21*(const_one-note_a_discount) -> 30.102798 | AM21: =MIN('Pro-Forma'!AK21,'Pro-Forma'!AL21) -> 26.778553 | AN21: =note_a_principal_usd/'Pro-Forma'!AM21 -> 186716.59 | AO21: =note_b_cap_usd/(pre_f_fd_total+'Pro-Forma'!S21+'Pro-Forma'!AJ21+'Pro-Forma'!T21) -> 42.739338 | AP21: ='Pro-Forma'!V21*(const_one-note_b_discount) -> 31.984223 | AQ21: =MIN('Pro-Forma'!AO21,'Pro-Forma'!AP21) -> 31.984223 | AR21: =note_b_principal_usd/'Pro-Forma'!AQ21 -> 93796.243 | AS21: =pre_f_fd_total+'Pro-Forma'!S21+'Pro-Forma'!W21+'Pro-Forma'!AN21+'Pro-Forma'!AR21+'Pro-Forma'!AJ21 -> 38327302 | AT21: =MAX(const_zero,esop_refresh_target_post_f*'Pro-Forma'!AS21-pre_f_option_pool_total) -> 587882.23
A22: =lbl_seed -> Seed | B22: =class_seed_ocp -> 1 | C22: =IF($B$4<B22,lbl_trigger,lbl_no_trigger) -> no trigger | D22: =IF($B$4<B22,B22*(ad_pre_f_broad_based_fd+series_f_primary_raise_usd/B22)/(ad_pre_f_broad_based_fd+series_f_primary_raise_usd/$B$4),B22) -> 1 | E22: =class_seed_issue_pps/D22 -> 1 | F22: =class_seed_original_shares*E22 -> 5000000 | G22: =F22-class_seed_current_shares -> 0 | R22: ='Pro-Forma'!R21+const_one -> 18 | S22: ='Pro-Forma'!AT21 -> 587882.23 | T22: ='Pro-Forma'!AN21 -> 186716.59 | U22: ='Pro-Forma'!AR21 -> 93796.243 | V22: =series_f_pre_money_usd/(pre_f_fd_total+'Pro-Forma'!S22) -> 37.628498 | W22: =series_f_primary_raise_usd/'Pro-Forma'!V22 -> 797268.07 | X22: =IF('Pro-Forma'!V22<class_seed_ocp,class_seed_ocp*(ad_pre_f_broad_based_fd+series_f_primary_raise_usd/class_seed_ocp)/(ad_pre_f_broad_based_fd+series_f_primary_raise_usd/'Pro-Forma'!V22),class_seed_ocp) -> 1 | Y22: =class_seed_original_shares*class_seed_issue_pps/'Pro-Forma'!X22 -> 5000000 | Z22: =IF('Pro-Forma'!V22<class_series_a_ocp,class_series_a_ocp*(ad_pre_f_broad_based_fd+series_f_primary_raise_usd/class_series_a_ocp)/(ad_pre_f_broad_based_fd+series_f_primary_raise_usd/'Pro-Forma'!V22),class_series_a_ocp) -> 3 | AA22: =class_series_a_original_shares*class_series_a_issue_pps/'Pro-Forma'!Z22 -> 5000000 | AB22: =IF('Pro-Forma'!V22<class_series_b_ocp,class_series_b_ocp*(ad_pre_f_broad_based_fd+series_f_primary_raise_usd/class_series_b_ocp)/(ad_pre_f_broad_based_fd+series_f_primary_raise_usd/'Pro-Forma'!V22),class_series_b_ocp) -> 10 | AC22: =class_series_b_original_shares*class_series_b_issue_pps/'Pro-Forma'!AB22 -> 3000000 | AD22: =IF('Pro-Forma'!V22<class_series_c_ocp,class_series_c_ocp*(ad_pre_f_broad_based_fd+series_f_primary_raise_usd/class_series_c_ocp)/(ad_pre_f_broad_based_fd+series_f_primary_raise_usd/'Pro-Forma'!V22),class_series_c_ocp) -> 25 | AE22: =class_series_c_original_shares*class_series_c_issue_pps/'Pro-Forma'!AD22 -> 2400000 | AF22: =IF('Pro-Forma'!V22<class_series_d_ocp,class_series_d_ocp*(ad_pre_f_broad_based_fd+series_f_primary_raise_usd/class_series_d_ocp)/(ad_pre_f_broad_based_fd+series_f_primary_raise_usd/'Pro-Forma'!V22),class_series_d_ocp) -> 57.681736 | AG22: =class_series_d_original_shares*class_series_d_issue_pps/'Pro-Forma'!AF22 -> 1733651.4 | AH22: =IF('Pro-Forma'!V22<class_series_e_ocp,class_series_e_ocp*(ad_pre_f_broad_based_fd+series_f_primary_raise_usd/class_series_e_ocp)/(ad_pre_f_broad_based_fd+series_f_primary_raise_usd/'Pro-Forma'!V22),class_series_e_ocp) -> 48.912626 | AI22: =class_series_e_original_shares*class_series_e_issue_pps/'Pro-Forma'!AH22 -> 6133320.3 | AJ22: ='Pro-Forma'!Y22-class_seed_current_shares+'Pro-Forma'!AA22-class_series_a_current_shares+'Pro-Forma'!AC22-class_series_b_current_shares+'Pro-Forma'!AE22-class_series_c_current_shares+'Pro-Forma'!AG22-class_series_d_current_shares+'Pro-Forma'!AI22-class_series_e_current_shares -> 43677.638 | AK22: =note_a_cap_usd/(pre_f_fd_total+'Pro-Forma'!S22+'Pro-Forma'!AJ22+'Pro-Forma'!U22) -> 26.778553 | AL22: ='Pro-Forma'!V22*(const_one-note_a_discount) -> 30.102798 | AM22: =MIN('Pro-Forma'!AK22,'Pro-Forma'!AL22) -> 26.778553 | AN22: =note_a_principal_usd/'Pro-Forma'!AM22 -> 186716.59 | AO22: =note_b_cap_usd/(pre_f_fd_total+'Pro-Forma'!S22+'Pro-Forma'!AJ22+'Pro-Forma'!T22) -> 42.739338 | AP22: ='Pro-Forma'!V22*(const_one-note_b_discount) -> 31.984223 | AQ22: =MIN('Pro-Forma'!AO22,'Pro-Forma'!AP22) -> 31.984223 | AR22: =note_b_principal_usd/'Pro-Forma'!AQ22 -> 93796.243 | AS22: =pre_f_fd_total+'Pro-Forma'!S22+'Pro-Forma'!W22+'Pro-Forma'!AN22+'Pro-Forma'!AR22+'Pro-Forma'!AJ22 -> 38327302 | AT22: =MAX(const_zero,esop_refresh_target_post_f*'Pro-Forma'!AS22-pre_f_option_pool_total) -> 587882.23
A23: =lbl_series_a -> Series A | B23: =class_series_a_ocp -> 3 | C23: =IF($B$4<B23,lbl_trigger,lbl_no_trigger) -> no trigger | D23: =IF($B$4<B23,B23*(ad_pre_f_broad_based_fd+series_f_primary_raise_usd/B23)/(ad_pre_f_broad_based_fd+series_f_primary_raise_usd/$B$4),B23) -> 3 | E23: =class_series_a_issue_pps/D23 -> 1 | F23: =class_series_a_original_shares*E23 -> 5000000 | G23: =F23-class_series_a_current_shares -> 0 | R23: ='Pro-Forma'!R22+const_one -> 19 | S23: ='Pro-Forma'!AT22 -> 587882.23 | T23: ='Pro-Forma'!AN22 -> 186716.59 | U23: ='Pro-Forma'!AR22 -> 93796.243 | V23: =series_f_pre_money_usd/(pre_f_fd_total+'Pro-Forma'!S23) -> 37.628498 | W23: =series_f_primary_raise_usd/'Pro-Forma'!V23 -> 797268.07 | X23: =IF('Pro-Forma'!V23<class_seed_ocp,class_seed_ocp*(ad_pre_f_broad_based_fd+series_f_primary_raise_usd/class_seed_ocp)/(ad_pre_f_broad_based_fd+series_f_primary_raise_usd/'Pro-Forma'!V23),class_seed_ocp) -> 1 | Y23: =class_seed_original_shares*class_seed_issue_pps/'Pro-Forma'!X23 -> 5000000 | Z23: =IF('Pro-Forma'!V23<class_series_a_ocp,class_series_a_ocp*(ad_pre_f_broad_based_fd+series_f_primary_raise_usd/class_series_a_ocp)/(ad_pre_f_broad_based_fd+series_f_primary_raise_usd/'Pro-Forma'!V23),class_series_a_ocp) -> 3 | AA23: =class_series_a_original_shares*class_series_a_issue_pps/'Pro-Forma'!Z23 -> 5000000 | AB23: =IF('Pro-Forma'!V23<class_series_b_ocp,class_series_b_ocp*(ad_pre_f_broad_based_fd+series_f_primary_raise_usd/class_series_b_ocp)/(ad_pre_f_broad_based_fd+series_f_primary_raise_usd/'Pro-Forma'!V23),class_series_b_ocp) -> 10 | AC23: =class_series_b_original_shares*class_series_b_issue_pps/'Pro-Forma'!AB23 -> 3000000 | AD23: =IF('Pro-Forma'!V23<class_series_c_ocp,class_series_c_ocp*(ad_pre_f_broad_based_fd+series_f_primary_raise_usd/class_series_c_ocp)/(ad_pre_f_broad_based_fd+series_f_primary_raise_usd/'Pro-Forma'!V23),class_series_c_ocp) -> 25 | AE23: =class_series_c_original_shares*class_series_c_issue_pps/'Pro-Forma'!AD23 -> 2400000 | AF23: =IF('Pro-Forma'!V23<class_series_d_ocp,class_series_d_ocp*(ad_pre_f_broad_based_fd+series_f_primary_raise_usd/class_series_d_ocp)/(ad_pre_f_broad_based_fd+series_f_primary_raise_usd/'Pro-Forma'!V23),class_series_d_ocp) -> 57.681736 | AG23: =class_series_d_original_shares*class_series_d_issue_pps/'Pro-Forma'!AF23 -> 1733651.4 | AH23: =IF('Pro-Forma'!V23<class_series_e_ocp,class_series_e_ocp*(ad_pre_f_broad_based_fd+series_f_primary_raise_usd/class_series_e_ocp)/(ad_pre_f_broad_based_fd+series_f_primary_raise_usd/'Pro-Forma'!V23),class_series_e_ocp) -> 48.912626 | AI23: =class_series_e_original_shares*class_series_e_issue_pps/'Pro-Forma'!AH23 -> 6133320.3 | AJ23: ='Pro-Forma'!Y23-class_seed_current_shares+'Pro-Forma'!AA23-class_series_a_current_shares+'Pro-Forma'!AC23-class_series_b_current_shares+'Pro-Forma'!AE23-class_series_c_current_shares+'Pro-Forma'!AG23-class_series_d_current_shares+'Pro-Forma'!AI23-class_series_e_current_shares -> 43677.638 | AK23: =note_a_cap_usd/(pre_f_fd_total+'Pro-Forma'!S23+'Pro-Forma'!AJ23+'Pro-Forma'!U23) -> 26.778553 | AL23: ='Pro-Forma'!V23*(const_one-note_a_discount) -> 30.102798 | AM23: =MIN('Pro-Forma'!AK23,'Pro-Forma'!AL23) -> 26.778553 | AN23: =note_a_principal_usd/'Pro-Forma'!AM23 -> 186716.59 | AO23: =note_b_cap_usd/(pre_f_fd_total+'Pro-Forma'!S23+'Pro-Forma'!AJ23+'Pro-Forma'!T23) -> 42.739338 | AP23: ='Pro-Forma'!V23*(const_one-note_b_discount) -> 31.984223 | AQ23: =MIN('Pro-Forma'!AO23,'Pro-Forma'!AP23) -> 31.984223 | AR23: =note_b_principal_usd/'Pro-Forma'!AQ23 -> 93796.243 | AS23: =pre_f_fd_total+'Pro-Forma'!S23+'Pro-Forma'!W23+'Pro-Forma'!AN23+'Pro-Forma'!AR23+'Pro-Forma'!AJ23 -> 38327302 | AT23: =MAX(const_zero,esop_refresh_target_post_f*'Pro-Forma'!AS23-pre_f_option_pool_total) -> 587882.23
A24: =lbl_series_b -> Series B | B24: =class_series_b_ocp -> 10 | C24: =IF($B$4<B24,lbl_trigger,lbl_no_trigger) -> no trigger | D24: =IF($B$4<B24,B24*(ad_pre_f_broad_based_fd+series_f_primary_raise_usd/B24)/(ad_pre_f_broad_based_fd+series_f_primary_raise_usd/$B$4),B24) -> 10 | E24: =class_series_b_issue_pps/D24 -> 1 | F24: =class_series_b_original_shares*E24 -> 3000000 | G24: =F24-class_series_b_current_shares -> 0 | R24: ='Pro-Forma'!R23+const_one -> 20 | S24: ='Pro-Forma'!AT23 -> 587882.23 | T24: ='Pro-Forma'!AN23 -> 186716.59 | U24: ='Pro-Forma'!AR23 -> 93796.243 | V24: =series_f_pre_money_usd/(pre_f_fd_total+'Pro-Forma'!S24) -> 37.628498 | W24: =series_f_primary_raise_usd/'Pro-Forma'!V24 -> 797268.07 | X24: =IF('Pro-Forma'!V24<class_seed_ocp,class_seed_ocp*(ad_pre_f_broad_based_fd+series_f_primary_raise_usd/class_seed_ocp)/(ad_pre_f_broad_based_fd+series_f_primary_raise_usd/'Pro-Forma'!V24),class_seed_ocp) -> 1 | Y24: =class_seed_original_shares*class_seed_issue_pps/'Pro-Forma'!X24 -> 5000000 | Z24: =IF('Pro-Forma'!V24<class_series_a_ocp,class_series_a_ocp*(ad_pre_f_broad_based_fd+series_f_primary_raise_usd/class_series_a_ocp)/(ad_pre_f_broad_based_fd+series_f_primary_raise_usd/'Pro-Forma'!V24),class_series_a_ocp) -> 3 | AA24: =class_series_a_original_shares*class_series_a_issue_pps/'Pro-Forma'!Z24 -> 5000000 | AB24: =IF('Pro-Forma'!V24<class_series_b_ocp,class_series_b_ocp*(ad_pre_f_broad_based_fd+series_f_primary_raise_usd/class_series_b_ocp)/(ad_pre_f_broad_based_fd+series_f_primary_raise_usd/'Pro-Forma'!V24),class_series_b_ocp) -> 10 | AC24: =class_series_b_original_shares*class_series_b_issue_pps/'Pro-Forma'!AB24 -> 3000000 | AD24: =IF('Pro-Forma'!V24<class_series_c_ocp,class_series_c_ocp*(ad_pre_f_broad_based_fd+series_f_primary_raise_usd/class_series_c_ocp)/(ad_pre_f_broad_based_fd+series_f_primary_raise_usd/'Pro-Forma'!V24),class_series_c_ocp) -> 25 | AE24: =class_series_c_original_shares*class_series_c_issue_pps/'Pro-Forma'!AD24 -> 2400000 | AF24: =IF('Pro-Forma'!V24<class_series_d_ocp,class_series_d_ocp*(ad_pre_f_broad_based_fd+series_f_primary_raise_usd/class_series_d_ocp)/(ad_pre_f_broad_based_fd+series_f_primary_raise_usd/'Pro-Forma'!V24),class_series_d_ocp) -> 57.681736 | AG24: =class_series_d_original_shares*class_series_d_issue_pps/'Pro-Forma'!AF24 -> 1733651.4 | AH24: =IF('Pro-Forma'!V24<class_series_e_ocp,class_series_e_ocp*(ad_pre_f_broad_based_fd+series_f_primary_raise_usd/class_series_e_ocp)/(ad_pre_f_broad_based_fd+series_f_primary_raise_usd/'Pro-Forma'!V24),class_series_e_ocp) -> 48.912626 | AI24: =class_series_e_original_shares*class_series_e_issue_pps/'Pro-Forma'!AH24 -> 6133320.3 | AJ24: ='Pro-Forma'!Y24-class_seed_current_shares+'Pro-Forma'!AA24-class_series_a_current_shares+'Pro-Forma'!AC24-class_series_b_current_shares+'Pro-Forma'!AE24-class_series_c_current_shares+'Pro-Forma'!AG24-class_series_d_current_shares+'Pro-Forma'!AI24-class_series_e_current_shares -> 43677.638 | AK24: =note_a_cap_usd/(pre_f_fd_total+'Pro-Forma'!S24+'Pro-Forma'!AJ24+'Pro-Forma'!U24) -> 26.778553 | AL24: ='Pro-Forma'!V24*(const_one-note_a_discount) -> 30.102798 | AM24: =MIN('Pro-Forma'!AK24,'Pro-Forma'!AL24) -> 26.778553 | AN24: =note_a_principal_usd/'Pro-Forma'!AM24 -> 186716.59 | AO24: =note_b_cap_usd/(pre_f_fd_total+'Pro-Forma'!S24+'Pro-Forma'!AJ24+'Pro-Forma'!T24) -> 42.739338 | AP24: ='Pro-Forma'!V24*(const_one-note_b_discount) -> 31.984223 | AQ24: =MIN('Pro-Forma'!AO24,'Pro-Forma'!AP24) -> 31.984223 | AR24: =note_b_principal_usd/'Pro-Forma'!AQ24 -> 93796.243 | AS24: =pre_f_fd_total+'Pro-Forma'!S24+'Pro-Forma'!W24+'Pro-Forma'!AN24+'Pro-Forma'!AR24+'Pro-Forma'!AJ24 -> 38327302 | AT24: =MAX(const_zero,esop_refresh_target_post_f*'Pro-Forma'!AS24-pre_f_option_pool_total) -> 587882.23
A25: =lbl_series_c -> Series C | B25: =class_series_c_ocp -> 25 | C25: =IF($B$4<B25,lbl_trigger,lbl_no_trigger) -> no trigger | D25: =IF($B$4<B25,B25*(ad_pre_f_broad_based_fd+series_f_primary_raise_usd/B25)/(ad_pre_f_broad_based_fd+series_f_primary_raise_usd/$B$4),B25) -> 25 | E25: =class_series_c_issue_pps/D25 -> 1 | F25: =class_series_c_original_shares*E25 -> 2400000 | G25: =F25-class_series_c_current_shares -> 0 | R25: ='Pro-Forma'!R24+const_one -> 21 | S25: ='Pro-Forma'!AT24 -> 587882.23 | T25: ='Pro-Forma'!AN24 -> 186716.59 | U25: ='Pro-Forma'!AR24 -> 93796.243 | V25: =series_f_pre_money_usd/(pre_f_fd_total+'Pro-Forma'!S25) -> 37.628498 | W25: =series_f_primary_raise_usd/'Pro-Forma'!V25 -> 797268.07 | X25: =IF('Pro-Forma'!V25<class_seed_ocp,class_seed_ocp*(ad_pre_f_broad_based_fd+series_f_primary_raise_usd/class_seed_ocp)/(ad_pre_f_broad_based_fd+series_f_primary_raise_usd/'Pro-Forma'!V25),class_seed_ocp) -> 1 | Y25: =class_seed_original_shares*class_seed_issue_pps/'Pro-Forma'!X25 -> 5000000 | Z25: =IF('Pro-Forma'!V25<class_series_a_ocp,class_series_a_ocp*(ad_pre_f_broad_based_fd+series_f_primary_raise_usd/class_series_a_ocp)/(ad_pre_f_broad_based_fd+series_f_primary_raise_usd/'Pro-Forma'!V25),class_series_a_ocp) -> 3 | AA25: =class_series_a_original_shares*class_series_a_issue_pps/'Pro-Forma'!Z25 -> 5000000 | AB25: =IF('Pro-Forma'!V25<class_series_b_ocp,class_series_b_ocp*(ad_pre_f_broad_based_fd+series_f_primary_raise_usd/class_series_b_ocp)/(ad_pre_f_broad_based_fd+series_f_primary_raise_usd/'Pro-Forma'!V25),class_series_b_ocp) -> 10 | AC25: =class_series_b_original_shares*class_series_b_issue_pps/'Pro-Forma'!AB25 -> 3000000 | AD25: =IF('Pro-Forma'!V25<class_series_c_ocp,class_series_c_ocp*(ad_pre_f_broad_based_fd+series_f_primary_raise_usd/class_series_c_ocp)/(ad_pre_f_broad_based_fd+series_f_primary_raise_usd/'Pro-Forma'!V25),class_series_c_ocp) -> 25 | AE25: =class_series_c_original_shares*class_series_c_issue_pps/'Pro-Forma'!AD25 -> 2400000 | AF25: =IF('Pro-Forma'!V25<class_series_d_ocp,class_series_d_ocp*(ad_pre_f_broad_based_fd+series_f_primary_raise_usd/class_series_d_ocp)/(ad_pre_f_broad_based_fd+series_f_primary_raise_usd/'Pro-Forma'!V25),class_series_d_ocp) -> 57.681736 | AG25: =class_series_d_original_shares*class_series_d_issue_pps/'Pro-Forma'!AF25 -> 1733651.4 | AH25: =IF('Pro-Forma'!V25<class_series_e_ocp,class_series_e_ocp*(ad_pre_f_broad_based_fd+series_f_primary_raise_usd/class_series_e_ocp)/(ad_pre_f_broad_based_fd+series_f_primary_raise_usd/'Pro-Forma'!V25),class_series_e_ocp) -> 48.912626 | AI25: =class_series_e_original_shares*class_series_e_issue_pps/'Pro-Forma'!AH25 -> 6133320.3 | AJ25: ='Pro-Forma'!Y25-class_seed_current_shares+'Pro-Forma'!AA25-class_series_a_current_shares+'Pro-Forma'!AC25-class_series_b_current_shares+'Pro-Forma'!AE25-class_series_c_current_shares+'Pro-Forma'!AG25-class_series_d_current_shares+'Pro-Forma'!AI25-class_series_e_current_shares -> 43677.638 | AK25: =note_a_cap_usd/(pre_f_fd_total+'Pro-Forma'!S25+'Pro-Forma'!AJ25+'Pro-Forma'!U25) -> 26.778553 | AL25: ='Pro-Forma'!V25*(const_one-note_a_discount) -> 30.102798 | AM25: =MIN('Pro-Forma'!AK25,'Pro-Forma'!AL25) -> 26.778553 | AN25: =note_a_principal_usd/'Pro-Forma'!AM25 -> 186716.59 | AO25: =note_b_cap_usd/(pre_f_fd_total+'Pro-Forma'!S25+'Pro-Forma'!AJ25+'Pro-Forma'!T25) -> 42.739338 | AP25: ='Pro-Forma'!V25*(const_one-note_b_discount) -> 31.984223 | AQ25: =MIN('Pro-Forma'!AO25,'Pro-Forma'!AP25) -> 31.984223 | AR25: =note_b_principal_usd/'Pro-Forma'!AQ25 -> 93796.243 | AS25: =pre_f_fd_total+'Pro-Forma'!S25+'Pro-Forma'!W25+'Pro-Forma'!AN25+'Pro-Forma'!AR25+'Pro-Forma'!AJ25 -> 38327302 | AT25: =MAX(const_zero,esop_refresh_target_post_f*'Pro-Forma'!AS25-pre_f_option_pool_total) -> 587882.23
A26: =lbl_series_d -> Series D | B26: =class_series_d_ocp -> 58.118347 | C26: =IF($B$4<B26,lbl_trigger,lbl_no_trigger) -> trigger | D26: =IF($B$4<B26,B26*(ad_pre_f_broad_based_fd+series_f_primary_raise_usd/B26)/(ad_pre_f_broad_based_fd+series_f_primary_raise_usd/$B$4),B26) -> 57.681736 | E26: =class_series_d_issue_pps/D26 -> 1.0401906 | F26: =class_series_d_original_shares*E26 -> 1733651.4 | G26: =F26-class_series_d_current_shares -> 13024.36 | R26: ='Pro-Forma'!R25+const_one -> 22 | S26: ='Pro-Forma'!AT25 -> 587882.23 | T26: ='Pro-Forma'!AN25 -> 186716.59 | U26: ='Pro-Forma'!AR25 -> 93796.243 | V26: =series_f_pre_money_usd/(pre_f_fd_total+'Pro-Forma'!S26) -> 37.628498 | W26: =series_f_primary_raise_usd/'Pro-Forma'!V26 -> 797268.07 | X26: =IF('Pro-Forma'!V26<class_seed_ocp,class_seed_ocp*(ad_pre_f_broad_based_fd+series_f_primary_raise_usd/class_seed_ocp)/(ad_pre_f_broad_based_fd+series_f_primary_raise_usd/'Pro-Forma'!V26),class_seed_ocp) -> 1 | Y26: =class_seed_original_shares*class_seed_issue_pps/'Pro-Forma'!X26 -> 5000000 | Z26: =IF('Pro-Forma'!V26<class_series_a_ocp,class_series_a_ocp*(ad_pre_f_broad_based_fd+series_f_primary_raise_usd/class_series_a_ocp)/(ad_pre_f_broad_based_fd+series_f_primary_raise_usd/'Pro-Forma'!V26),class_series_a_ocp) -> 3 | AA26: =class_series_a_original_shares*class_series_a_issue_pps/'Pro-Forma'!Z26 -> 5000000 | AB26: =IF('Pro-Forma'!V26<class_series_b_ocp,class_series_b_ocp*(ad_pre_f_broad_based_fd+series_f_primary_raise_usd/class_series_b_ocp)/(ad_pre_f_broad_based_fd+series_f_primary_raise_usd/'Pro-Forma'!V26),class_series_b_ocp) -> 10 | AC26: =class_series_b_original_shares*class_series_b_issue_pps/'Pro-Forma'!AB26 -> 3000000 | AD26: =IF('Pro-Forma'!V26<class_series_c_ocp,class_series_c_ocp*(ad_pre_f_broad_based_fd+series_f_primary_raise_usd/class_series_c_ocp)/(ad_pre_f_broad_based_fd+series_f_primary_raise_usd/'Pro-Forma'!V26),class_series_c_ocp) -> 25 | AE26: =class_series_c_original_shares*class_series_c_issue_pps/'Pro-Forma'!AD26 -> 2400000 | AF26: =IF('Pro-Forma'!V26<class_series_d_ocp,class_series_d_ocp*(ad_pre_f_broad_based_fd+series_f_primary_raise_usd/class_series_d_ocp)/(ad_pre_f_broad_based_fd+series_f_primary_raise_usd/'Pro-Forma'!V26),class_series_d_ocp) -> 57.681736 | AG26: =class_series_d_original_shares*class_series_d_issue_pps/'Pro-Forma'!AF26 -> 1733651.4 | AH26: =IF('Pro-Forma'!V26<class_series_e_ocp,class_series_e_ocp*(ad_pre_f_broad_based_fd+series_f_primary_raise_usd/class_series_e_ocp)/(ad_pre_f_broad_based_fd+series_f_primary_raise_usd/'Pro-Forma'!V26),class_series_e_ocp) -> 48.912626 | AI26: =class_series_e_original_shares*class_series_e_issue_pps/'Pro-Forma'!AH26 -> 6133320.3 | AJ26: ='Pro-Forma'!Y26-class_seed_current_shares+'Pro-Forma'!AA26-class_series_a_current_shares+'Pro-Forma'!AC26-class_series_b_current_shares+'Pro-Forma'!AE26-class_series_c_current_shares+'Pro-Forma'!AG26-class_series_d_current_shares+'Pro-Forma'!AI26-class_series_e_current_shares -> 43677.638 | AK26: =note_a_cap_usd/(pre_f_fd_total+'Pro-Forma'!S26+'Pro-Forma'!AJ26+'Pro-Forma'!U26) -> 26.778553 | AL26: ='Pro-Forma'!V26*(const_one-note_a_discount) -> 30.102798 | AM26: =MIN('Pro-Forma'!AK26,'Pro-Forma'!AL26) -> 26.778553 | AN26: =note_a_principal_usd/'Pro-Forma'!AM26 -> 186716.59 | AO26: =note_b_cap_usd/(pre_f_fd_total+'Pro-Forma'!S26+'Pro-Forma'!AJ26+'Pro-Forma'!T26) -> 42.739338 | AP26: ='Pro-Forma'!V26*(const_one-note_b_discount) -> 31.984223 | AQ26: =MIN('Pro-Forma'!AO26,'Pro-Forma'!AP26) -> 31.984223 | AR26: =note_b_principal_usd/'Pro-Forma'!AQ26 -> 93796.243 | AS26: =pre_f_fd_total+'Pro-Forma'!S26+'Pro-Forma'!W26+'Pro-Forma'!AN26+'Pro-Forma'!AR26+'Pro-Forma'!AJ26 -> 38327302 | AT26: =MAX(const_zero,esop_refresh_target_post_f*'Pro-Forma'!AS26-pre_f_option_pool_total) -> 587882.23
A27: =lbl_series_e -> Series E | B27: =class_series_e_ocp -> 49.158311 | C27: =IF($B$4<B27,lbl_trigger,lbl_no_trigger) -> trigger | D27: =IF($B$4<B27,B27*(ad_pre_f_broad_based_fd+series_f_primary_raise_usd/B27)/(ad_pre_f_broad_based_fd+series_f_primary_raise_usd/$B$4),B27) -> 48.912626 | E27: =class_series_e_issue_pps/D27 -> 1.0050229 | F27: =class_series_e_original_shares*E27 -> 6133320.3 | G27: =F27-class_series_e_current_shares -> 30653.277 | R27: ='Pro-Forma'!R26+const_one -> 23 | S27: ='Pro-Forma'!AT26 -> 587882.23 | T27: ='Pro-Forma'!AN26 -> 186716.59 | U27: ='Pro-Forma'!AR26 -> 93796.243 | V27: =series_f_pre_money_usd/(pre_f_fd_total+'Pro-Forma'!S27) -> 37.628498 | W27: =series_f_primary_raise_usd/'Pro-Forma'!V27 -> 797268.07 | X27: =IF('Pro-Forma'!V27<class_seed_ocp,class_seed_ocp*(ad_pre_f_broad_based_fd+series_f_primary_raise_usd/class_seed_ocp)/(ad_pre_f_broad_based_fd+series_f_primary_raise_usd/'Pro-Forma'!V27),class_seed_ocp) -> 1 | Y27: =class_seed_original_shares*class_seed_issue_pps/'Pro-Forma'!X27 -> 5000000 | Z27: =IF('Pro-Forma'!V27<class_series_a_ocp,class_series_a_ocp*(ad_pre_f_broad_based_fd+series_f_primary_raise_usd/class_series_a_ocp)/(ad_pre_f_broad_based_fd+series_f_primary_raise_usd/'Pro-Forma'!V27),class_series_a_ocp) -> 3 | AA27: =class_series_a_original_shares*class_series_a_issue_pps/'Pro-Forma'!Z27 -> 5000000 | AB27: =IF('Pro-Forma'!V27<class_series_b_ocp,class_series_b_ocp*(ad_pre_f_broad_based_fd+series_f_primary_raise_usd/class_series_b_ocp)/(ad_pre_f_broad_based_fd+series_f_primary_raise_usd/'Pro-Forma'!V27),class_series_b_ocp) -> 10 | AC27: =class_series_b_original_shares*class_series_b_issue_pps/'Pro-Forma'!AB27 -> 3000000 | AD27: =IF('Pro-Forma'!V27<class_series_c_ocp,class_series_c_ocp*(ad_pre_f_broad_based_fd+series_f_primary_raise_usd/class_series_c_ocp)/(ad_pre_f_broad_based_fd+series_f_primary_raise_usd/'Pro-Forma'!V27),class_series_c_ocp) -> 25 | AE27: =class_series_c_original_shares*class_series_c_issue_pps/'Pro-Forma'!AD27 -> 2400000 | AF27: =IF('Pro-Forma'!V27<class_series_d_ocp,class_series_d_ocp*(ad_pre_f_broad_based_fd+series_f_primary_raise_usd/class_series_d_ocp)/(ad_pre_f_broad_based_fd+series_f_primary_raise_usd/'Pro-Forma'!V27),class_series_d_ocp) -> 57.681736 | AG27: =class_series_d_original_shares*class_series_d_issue_pps/'Pro-Forma'!AF27 -> 1733651.4 | AH27: =IF('Pro-Forma'!V27<class_series_e_ocp,class_series_e_ocp*(ad_pre_f_broad_based_fd+series_f_primary_raise_usd/class_series_e_ocp)/(ad_pre_f_broad_based_fd+series_f_primary_raise_usd/'Pro-Forma'!V27),class_series_e_ocp) -> 48.912626 | AI27: =class_series_e_original_shares*class_series_e_issue_pps/'Pro-Forma'!AH27 -> 6133320.3 | AJ27: ='Pro-Forma'!Y27-class_seed_current_shares+'Pro-Forma'!AA27-class_series_a_current_shares+'Pro-Forma'!AC27-class_series_b_current_shares+'Pro-Forma'!AE27-class_series_c_current_shares+'Pro-Forma'!AG27-class_series_d_current_shares+'Pro-Forma'!AI27-class_series_e_current_shares -> 43677.638 | AK27: =note_a_cap_usd/(pre_f_fd_total+'Pro-Forma'!S27+'Pro-Forma'!AJ27+'Pro-Forma'!U27) -> 26.778553 | AL27: ='Pro-Forma'!V27*(const_one-note_a_discount) -> 30.102798 | AM27: =MIN('Pro-Forma'!AK27,'Pro-Forma'!AL27) -> 26.778553 | AN27: =note_a_principal_usd/'Pro-Forma'!AM27 -> 186716.59 | AO27: =note_b_cap_usd/(pre_f_fd_total+'Pro-Forma'!S27+'Pro-Forma'!AJ27+'Pro-Forma'!T27) -> 42.739338 | AP27: ='Pro-Forma'!V27*(const_one-note_b_discount) -> 31.984223 | AQ27: =MIN('Pro-Forma'!AO27,'Pro-Forma'!AP27) -> 31.984223 | AR27: =note_b_principal_usd/'Pro-Forma'!AQ27 -> 93796.243 | AS27: =pre_f_fd_total+'Pro-Forma'!S27+'Pro-Forma'!W27+'Pro-Forma'!AN27+'Pro-Forma'!AR27+'Pro-Forma'!AJ27 -> 38327302 | AT27: =MAX(const_zero,esop_refresh_target_post_f*'Pro-Forma'!AS27-pre_f_option_pool_total) -> 587882.23
R28: ='Pro-Forma'!R27+const_one -> 24 | S28: ='Pro-Forma'!AT27 -> 587882.23 | T28: ='Pro-Forma'!AN27 -> 186716.59 | U28: ='Pro-Forma'!AR27 -> 93796.243 | V28: =series_f_pre_money_usd/(pre_f_fd_total+'Pro-Forma'!S28) -> 37.628498 | W28: =series_f_primary_raise_usd/'Pro-Forma'!V28 -> 797268.07 | X28: =IF('Pro-Forma'!V28<class_seed_ocp,class_seed_ocp*(ad_pre_f_broad_based_fd+series_f_primary_raise_usd/class_seed_ocp)/(ad_pre_f_broad_based_fd+series_f_primary_raise_usd/'Pro-Forma'!V28),class_seed_ocp) -> 1 | Y28: =class_seed_original_shares*class_seed_issue_pps/'Pro-Forma'!X28 -> 5000000 | Z28: =IF('Pro-Forma'!V28<class_series_a_ocp,class_series_a_ocp*(ad_pre_f_broad_based_fd+series_f_primary_raise_usd/class_series_a_ocp)/(ad_pre_f_broad_based_fd+series_f_primary_raise_usd/'Pro-Forma'!V28),class_series_a_ocp) -> 3 | AA28: =class_series_a_original_shares*class_series_a_issue_pps/'Pro-Forma'!Z28 -> 5000000 | AB28: =IF('Pro-Forma'!V28<class_series_b_ocp,class_series_b_ocp*(ad_pre_f_broad_based_fd+series_f_primary_raise_usd/class_series_b_ocp)/(ad_pre_f_broad_based_fd+series_f_primary_raise_usd/'Pro-Forma'!V28),class_series_b_ocp) -> 10 | AC28: =class_series_b_original_shares*class_series_b_issue_pps/'Pro-Forma'!AB28 -> 3000000 | AD28: =IF('Pro-Forma'!V28<class_series_c_ocp,class_series_c_ocp*(ad_pre_f_broad_based_fd+series_f_primary_raise_usd/class_series_c_ocp)/(ad_pre_f_broad_based_fd+series_f_primary_raise_usd/'Pro-Forma'!V28),class_series_c_ocp) -> 25 | AE28: =class_series_c_original_shares*class_series_c_issue_pps/'Pro-Forma'!AD28 -> 2400000 | AF28: =IF('Pro-Forma'!V28<class_series_d_ocp,class_series_d_ocp*(ad_pre_f_broad_based_fd+series_f_primary_raise_usd/class_series_d_ocp)/(ad_pre_f_broad_based_fd+series_f_primary_raise_usd/'Pro-Forma'!V28),class_series_d_ocp) -> 57.681736 | AG28: =class_series_d_original_shares*class_series_d_issue_pps/'Pro-Forma'!AF28 -> 1733651.4 | AH28: =IF('Pro-Forma'!V28<class_series_e_ocp,class_series_e_ocp*(ad_pre_f_broad_based_fd+series_f_primary_raise_usd/class_series_e_ocp)/(ad_pre_f_broad_based_fd+series_f_primary_raise_usd/'Pro-Forma'!V28),class_series_e_ocp) -> 48.912626 | AI28: =class_series_e_original_shares*class_series_e_issue_pps/'Pro-Forma'!AH28 -> 6133320.3 | AJ28: ='Pro-Forma'!Y28-class_seed_current_shares+'Pro-Forma'!AA28-class_series_a_current_shares+'Pro-Forma'!AC28-class_series_b_current_shares+'Pro-Forma'!AE28-class_series_c_current_shares+'Pro-Forma'!AG28-class_series_d_current_shares+'Pro-Forma'!AI28-class_series_e_current_shares -> 43677.638 | AK28: =note_a_cap_usd/(pre_f_fd_total+'Pro-Forma'!S28+'Pro-Forma'!AJ28+'Pro-Forma'!U28) -> 26.778553 | AL28: ='Pro-Forma'!V28*(const_one-note_a_discount) -> 30.102798 | AM28: =MIN('Pro-Forma'!AK28,'Pro-Forma'!AL28) -> 26.778553 | AN28: =note_a_principal_usd/'Pro-Forma'!AM28 -> 186716.59 | AO28: =note_b_cap_usd/(pre_f_fd_total+'Pro-Forma'!S28+'Pro-Forma'!AJ28+'Pro-Forma'!T28) -> 42.739338 | AP28: ='Pro-Forma'!V28*(const_one-note_b_discount) -> 31.984223 | AQ28: =MIN('Pro-Forma'!AO28,'Pro-Forma'!AP28) -> 31.984223 | AR28: =note_b_principal_usd/'Pro-Forma'!AQ28 -> 93796.243 | AS28: =pre_f_fd_total+'Pro-Forma'!S28+'Pro-Forma'!W28+'Pro-Forma'!AN28+'Pro-Forma'!AR28+'Pro-Forma'!AJ28 -> 38327302 | AT28: =MAX(const_zero,esop_refresh_target_post_f*'Pro-Forma'!AS28-pre_f_option_pool_total) -> 587882.23
A29: =lbl_notes_block -> Notes Block | R29: ='Pro-Forma'!R28+const_one -> 25 | S29: ='Pro-Forma'!AT28 -> 587882.23 | T29: ='Pro-Forma'!AN28 -> 186716.59 | U29: ='Pro-Forma'!AR28 -> 93796.243 | V29: =series_f_pre_money_usd/(pre_f_fd_total+'Pro-Forma'!S29) -> 37.628498 | W29: =series_f_primary_raise_usd/'Pro-Forma'!V29 -> 797268.07 | X29: =IF('Pro-Forma'!V29<class_seed_ocp,class_seed_ocp*(ad_pre_f_broad_based_fd+series_f_primary_raise_usd/class_seed_ocp)/(ad_pre_f_broad_based_fd+series_f_primary_raise_usd/'Pro-Forma'!V29),class_seed_ocp) -> 1 | Y29: =class_seed_original_shares*class_seed_issue_pps/'Pro-Forma'!X29 -> 5000000 | Z29: =IF('Pro-Forma'!V29<class_series_a_ocp,class_series_a_ocp*(ad_pre_f_broad_based_fd+series_f_primary_raise_usd/class_series_a_ocp)/(ad_pre_f_broad_based_fd+series_f_primary_raise_usd/'Pro-Forma'!V29),class_series_a_ocp) -> 3 | AA29: =class_series_a_original_shares*class_series_a_issue_pps/'Pro-Forma'!Z29 -> 5000000 | AB29: =IF('Pro-Forma'!V29<class_series_b_ocp,class_series_b_ocp*(ad_pre_f_broad_based_fd+series_f_primary_raise_usd/class_series_b_ocp)/(ad_pre_f_broad_based_fd+series_f_primary_raise_usd/'Pro-Forma'!V29),class_series_b_ocp) -> 10 | AC29: =class_series_b_original_shares*class_series_b_issue_pps/'Pro-Forma'!AB29 -> 3000000 | AD29: =IF('Pro-Forma'!V29<class_series_c_ocp,class_series_c_ocp*(ad_pre_f_broad_based_fd+series_f_primary_raise_usd/class_series_c_ocp)/(ad_pre_f_broad_based_fd+series_f_primary_raise_usd/'Pro-Forma'!V29),class_series_c_ocp) -> 25 | AE29: =class_series_c_original_shares*class_series_c_issue_pps/'Pro-Forma'!AD29 -> 2400000 | AF29: =IF('Pro-Forma'!V29<class_series_d_ocp,class_series_d_ocp*(ad_pre_f_broad_based_fd+series_f_primary_raise_usd/class_series_d_ocp)/(ad_pre_f_broad_based_fd+series_f_primary_raise_usd/'Pro-Forma'!V29),class_series_d_ocp) -> 57.681736 | AG29: =class_series_d_original_shares*class_series_d_issue_pps/'Pro-Forma'!AF29 -> 1733651.4 | AH29: =IF('Pro-Forma'!V29<class_series_e_ocp,class_series_e_ocp*(ad_pre_f_broad_based_fd+series_f_primary_raise_usd/class_series_e_ocp)/(ad_pre_f_broad_based_fd+series_f_primary_raise_usd/'Pro-Forma'!V29),class_series_e_ocp) -> 48.912626 | AI29: =class_series_e_original_shares*class_series_e_issue_pps/'Pro-Forma'!AH29 -> 6133320.3 | AJ29: ='Pro-Forma'!Y29-class_seed_current_shares+'Pro-Forma'!AA29-class_series_a_current_shares+'Pro-Forma'!AC29-class_series_b_current_shares+'Pro-Forma'!AE29-class_series_c_current_shares+'Pro-Forma'!AG29-class_series_d_current_shares+'Pro-Forma'!AI29-class_series_e_current_shares -> 43677.638 | AK29: =note_a_cap_usd/(pre_f_fd_total+'Pro-Forma'!S29+'Pro-Forma'!AJ29+'Pro-Forma'!U29) -> 26.778553 | AL29: ='Pro-Forma'!V29*(const_one-note_a_discount) -> 30.102798 | AM29: =MIN('Pro-Forma'!AK29,'Pro-Forma'!AL29) -> 26.778553 | AN29: =note_a_principal_usd/'Pro-Forma'!AM29 -> 186716.59 | AO29: =note_b_cap_usd/(pre_f_fd_total+'Pro-Forma'!S29+'Pro-Forma'!AJ29+'Pro-Forma'!T29) -> 42.739338 | AP29: ='Pro-Forma'!V29*(const_one-note_b_discount) -> 31.984223 | AQ29: =MIN('Pro-Forma'!AO29,'Pro-Forma'!AP29) -> 31.984223 | AR29: =note_b_principal_usd/'Pro-Forma'!AQ29 -> 93796.243 | AS29: =pre_f_fd_total+'Pro-Forma'!S29+'Pro-Forma'!W29+'Pro-Forma'!AN29+'Pro-Forma'!AR29+'Pro-Forma'!AJ29 -> 38327302 | AT29: =MAX(const_zero,esop_refresh_target_post_f*'Pro-Forma'!AS29-pre_f_option_pool_total) -> 587882.23
A30: =lbl_note -> Note | B30: =lbl_principal -> Principal | C30: =lbl_cap_value -> Cap | D30: =lbl_discount_rate -> Discount | E30: =lbl_cap_implied_pps -> Cap-implied PPS | F30: =lbl_discount_implied_pps -> Discount-implied PPS | G30: =lbl_conversion_pps -> Conversion PPS | H30: =lbl_conversion_branch -> Conversion branch | I30: =lbl_shares_issued -> Shares issued | R30: ='Pro-Forma'!R29+const_one -> 26 | S30: ='Pro-Forma'!AT29 -> 587882.23 | T30: ='Pro-Forma'!AN29 -> 186716.59 | U30: ='Pro-Forma'!AR29 -> 93796.243 | V30: =series_f_pre_money_usd/(pre_f_fd_total+'Pro-Forma'!S30) -> 37.628498 | W30: =series_f_primary_raise_usd/'Pro-Forma'!V30 -> 797268.07 | X30: =IF('Pro-Forma'!V30<class_seed_ocp,class_seed_ocp*(ad_pre_f_broad_based_fd+series_f_primary_raise_usd/class_seed_ocp)/(ad_pre_f_broad_based_fd+series_f_primary_raise_usd/'Pro-Forma'!V30),class_seed_ocp) -> 1 | Y30: =class_seed_original_shares*class_seed_issue_pps/'Pro-Forma'!X30 -> 5000000 | Z30: =IF('Pro-Forma'!V30<class_series_a_ocp,class_series_a_ocp*(ad_pre_f_broad_based_fd+series_f_primary_raise_usd/class_series_a_ocp)/(ad_pre_f_broad_based_fd+series_f_primary_raise_usd/'Pro-Forma'!V30),class_series_a_ocp) -> 3 | AA30: =class_series_a_original_shares*class_series_a_issue_pps/'Pro-Forma'!Z30 -> 5000000 | AB30: =IF('Pro-Forma'!V30<class_series_b_ocp,class_series_b_ocp*(ad_pre_f_broad_based_fd+series_f_primary_raise_usd/class_series_b_ocp)/(ad_pre_f_broad_based_fd+series_f_primary_raise_usd/'Pro-Forma'!V30),class_series_b_ocp) -> 10 | AC30: =class_series_b_original_shares*class_series_b_issue_pps/'Pro-Forma'!AB30 -> 3000000 | AD30: =IF('Pro-Forma'!V30<class_series_c_ocp,class_series_c_ocp*(ad_pre_f_broad_based_fd+series_f_primary_raise_usd/class_series_c_ocp)/(ad_pre_f_broad_based_fd+series_f_primary_raise_usd/'Pro-Forma'!V30),class_series_c_ocp) -> 25 | AE30: =class_series_c_original_shares*class_series_c_issue_pps/'Pro-Forma'!AD30 -> 2400000 | AF30: =IF('Pro-Forma'!V30<class_series_d_ocp,class_series_d_ocp*(ad_pre_f_broad_based_fd+series_f_primary_raise_usd/class_series_d_ocp)/(ad_pre_f_broad_based_fd+series_f_primary_raise_usd/'Pro-Forma'!V30),class_series_d_ocp) -> 57.681736 | AG30: =class_series_d_original_shares*class_series_d_issue_pps/'Pro-Forma'!AF30 -> 1733651.4 | AH30: =IF('Pro-Forma'!V30<class_series_e_ocp,class_series_e_ocp*(ad_pre_f_broad_based_fd+series_f_primary_raise_usd/class_series_e_ocp)/(ad_pre_f_broad_based_fd+series_f_primary_raise_usd/'Pro-Forma'!V30),class_series_e_ocp) -> 48.912626 | AI30: =class_series_e_original_shares*class_series_e_issue_pps/'Pro-Forma'!AH30 -> 6133320.3 | AJ30: ='Pro-Forma'!Y30-class_seed_current_shares+'Pro-Forma'!AA30-class_series_a_current_shares+'Pro-Forma'!AC30-class_series_b_current_shares+'Pro-Forma'!AE30-class_series_c_current_shares+'Pro-Forma'!AG30-class_series_d_current_shares+'Pro-Forma'!AI30-class_series_e_current_shares -> 43677.638 | AK30: =note_a_cap_usd/(pre_f_fd_total+'Pro-Forma'!S30+'Pro-Forma'!AJ30+'Pro-Forma'!U30) -> 26.778553 | AL30: ='Pro-Forma'!V30*(const_one-note_a_discount) -> 30.102798 | AM30: =MIN('Pro-Forma'!AK30,'Pro-Forma'!AL30) -> 26.778553 | AN30: =note_a_principal_usd/'Pro-Forma'!AM30 -> 186716.59 | AO30: =note_b_cap_usd/(pre_f_fd_total+'Pro-Forma'!S30+'Pro-Forma'!AJ30+'Pro-Forma'!T30) -> 42.739338 | AP30: ='Pro-Forma'!V30*(const_one-note_b_discount) -> 31.984223 | AQ30: =MIN('Pro-Forma'!AO30,'Pro-Forma'!AP30) -> 31.984223 | AR30: =note_b_principal_usd/'Pro-Forma'!AQ30 -> 93796.243 | AS30: =pre_f_fd_total+'Pro-Forma'!S30+'Pro-Forma'!W30+'Pro-Forma'!AN30+'Pro-Forma'!AR30+'Pro-Forma'!AJ30 -> 38327302 | AT30: =MAX(const_zero,esop_refresh_target_post_f*'Pro-Forma'!AS30-pre_f_option_pool_total) -> 587882.23
A31: =lbl_note_a -> Note A | B31: =note_a_principal_usd -> 5000000 | C31: =note_a_cap_usd -> 1000000000 | D31: =note_a_discount -> 0.2 | E31: ='Pro-Forma'!$AK$63 -> 26.778553 | F31: ='Pro-Forma'!$AL$63 -> 30.102798 | G31: =MIN(E31,F31) -> 26.778553 | H31: =IF(E31<=F31,lbl_cap,lbl_discount) -> cap | I31: =note_a_principal_usd/G31 -> 186716.59 | R31: ='Pro-Forma'!R30+const_one -> 27 | S31: ='Pro-Forma'!AT30 -> 587882.23 | T31: ='Pro-Forma'!AN30 -> 186716.59 | U31: ='Pro-Forma'!AR30 -> 93796.243 | V31: =series_f_pre_money_usd/(pre_f_fd_total+'Pro-Forma'!S31) -> 37.628498 | W31: =series_f_primary_raise_usd/'Pro-Forma'!V31 -> 797268.07 | X31: =IF('Pro-Forma'!V31<class_seed_ocp,class_seed_ocp*(ad_pre_f_broad_based_fd+series_f_primary_raise_usd/class_seed_ocp)/(ad_pre_f_broad_based_fd+series_f_primary_raise_usd/'Pro-Forma'!V31),class_seed_ocp) -> 1 | Y31: =class_seed_original_shares*class_seed_issue_pps/'Pro-Forma'!X31 -> 5000000 | Z31: =IF('Pro-Forma'!V31<class_series_a_ocp,class_series_a_ocp*(ad_pre_f_broad_based_fd+series_f_primary_raise_usd/class_series_a_ocp)/(ad_pre_f_broad_based_fd+series_f_primary_raise_usd/'Pro-Forma'!V31),class_series_a_ocp) -> 3 | AA31: =class_series_a_original_shares*class_series_a_issue_pps/'Pro-Forma'!Z31 -> 5000000 | AB31: =IF('Pro-Forma'!V31<class_series_b_ocp,class_series_b_ocp*(ad_pre_f_broad_based_fd+series_f_primary_raise_usd/class_series_b_ocp)/(ad_pre_f_broad_based_fd+series_f_primary_raise_usd/'Pro-Forma'!V31),class_series_b_ocp) -> 10 | AC31: =class_series_b_original_shares*class_series_b_issue_pps/'Pro-Forma'!AB31 -> 3000000 | AD31: =IF('Pro-Forma'!V31<class_series_c_ocp,class_series_c_ocp*(ad_pre_f_broad_based_fd+series_f_primary_raise_usd/class_series_c_ocp)/(ad_pre_f_broad_based_fd+series_f_primary_raise_usd/'Pro-Forma'!V31),class_series_c_ocp) -> 25 | AE31: =class_series_c_original_shares*class_series_c_issue_pps/'Pro-Forma'!AD31 -> 2400000 | AF31: =IF('Pro-Forma'!V31<class_series_d_ocp,class_series_d_ocp*(ad_pre_f_broad_based_fd+series_f_primary_raise_usd/class_series_d_ocp)/(ad_pre_f_broad_based_fd+series_f_primary_raise_usd/'Pro-Forma'!V31),class_series_d_ocp) -> 57.681736 | AG31: =class_series_d_original_shares*class_series_d_issue_pps/'Pro-Forma'!AF31 -> 1733651.4 | AH31: =IF('Pro-Forma'!V31<class_series_e_ocp,class_series_e_ocp*(ad_pre_f_broad_based_fd+series_f_primary_raise_usd/class_series_e_ocp)/(ad_pre_f_broad_based_fd+series_f_primary_raise_usd/'Pro-Forma'!V31),class_series_e_ocp) -> 48.912626 | AI31: =class_series_e_original_shares*class_series_e_issue_pps/'Pro-Forma'!AH31 -> 6133320.3 | AJ31: ='Pro-Forma'!Y31-class_seed_current_shares+'Pro-Forma'!AA31-class_series_a_current_shares+'Pro-Forma'!AC31-class_series_b_current_shares+'Pro-Forma'!AE31-class_series_c_current_shares+'Pro-Forma'!AG31-class_series_d_current_shares+'Pro-Forma'!AI31-class_series_e_current_shares -> 43677.638 | AK31: =note_a_cap_usd/(pre_f_fd_total+'Pro-Forma'!S31+'Pro-Forma'!AJ31+'Pro-Forma'!U31) -> 26.778553 | AL31: ='Pro-Forma'!V31*(const_one-note_a_discount) -> 30.102798 | AM31: =MIN('Pro-Forma'!AK31,'Pro-Forma'!AL31) -> 26.778553 | AN31: =note_a_principal_usd/'Pro-Forma'!AM31 -> 186716.59 | AO31: =note_b_cap_usd/(pre_f_fd_total+'Pro-Forma'!S31+'Pro-Forma'!AJ31+'Pro-Forma'!T31) -> 42.739338 | AP31: ='Pro-Forma'!V31*(const_one-note_b_discount) -> 31.984223 | AQ31: =MIN('Pro-Forma'!AO31,'Pro-Forma'!AP31) -> 31.984223 | AR31: =note_b_principal_usd/'Pro-Forma'!AQ31 -> 93796.243 | AS31: =pre_f_fd_total+'Pro-Forma'!S31+'Pro-Forma'!W31+'Pro-Forma'!AN31+'Pro-Forma'!AR31+'Pro-Forma'!AJ31 -> 38327302 | AT31: =MAX(const_zero,esop_refresh_target_post_f*'Pro-Forma'!AS31-pre_f_option_pool_total) -> 587882.23
A32: =lbl_note_b -> Note B | B32: =note_b_principal_usd -> 3000000 | C32: =note_b_cap_usd -> 1600000000 | D32: =note_b_discount -> 0.15 | E32: ='Pro-Forma'!$AO$63 -> 42.739338 | F32: ='Pro-Forma'!$AP$63 -> 31.984223 | G32: =MIN(E32,F32) -> 31.984223 | H32: =IF(E32<=F32,lbl_cap,lbl_discount) -> discount | I32: =note_b_principal_usd/G32 -> 93796.243 | R32: ='Pro-Forma'!R31+const_one -> 28 | S32: ='Pro-Forma'!AT31 -> 587882.23 | T32: ='Pro-Forma'!AN31 -> 186716.59 | U32: ='Pro-Forma'!AR31 -> 93796.243 | V32: =series_f_pre_money_usd/(pre_f_fd_total+'Pro-Forma'!S32) -> 37.628498 | W32: =series_f_primary_raise_usd/'Pro-Forma'!V32 -> 797268.07 | X32: =IF('Pro-Forma'!V32<class_seed_ocp,class_seed_ocp*(ad_pre_f_broad_based_fd+series_f_primary_raise_usd/class_seed_ocp)/(ad_pre_f_broad_based_fd+series_f_primary_raise_usd/'Pro-Forma'!V32),class_seed_ocp) -> 1 | Y32: =class_seed_original_shares*class_seed_issue_pps/'Pro-Forma'!X32 -> 5000000 | Z32: =IF('Pro-Forma'!V32<class_series_a_ocp,class_series_a_ocp*(ad_pre_f_broad_based_fd+series_f_primary_raise_usd/class_series_a_ocp)/(ad_pre_f_broad_based_fd+series_f_primary_raise_usd/'Pro-Forma'!V32),class_series_a_ocp) -> 3 | AA32: =class_series_a_original_shares*class_series_a_issue_pps/'Pro-Forma'!Z32 -> 5000000 | AB32: =IF('Pro-Forma'!V32<class_series_b_ocp,class_series_b_ocp*(ad_pre_f_broad_based_fd+series_f_primary_raise_usd/class_series_b_ocp)/(ad_pre_f_broad_based_fd+series_f_primary_raise_usd/'Pro-Forma'!V32),class_series_b_ocp) -> 10 | AC32: =class_series_b_original_shares*class_series_b_issue_pps/'Pro-Forma'!AB32 -> 3000000 | AD32: =IF('Pro-Forma'!V32<class_series_c_ocp,class_series_c_ocp*(ad_pre_f_broad_based_fd+series_f_primary_raise_usd/class_series_c_ocp)/(ad_pre_f_broad_based_fd+series_f_primary_raise_usd/'Pro-Forma'!V32),class_series_c_ocp) -> 25 | AE32: =class_series_c_original_shares*class_series_c_issue_pps/'Pro-Forma'!AD32 -> 2400000 | AF32: =IF('Pro-Forma'!V32<class_series_d_ocp,class_series_d_ocp*(ad_pre_f_broad_based_fd+series_f_primary_raise_usd/class_series_d_ocp)/(ad_pre_f_broad_based_fd+series_f_primary_raise_usd/'Pro-Forma'!V32),class_series_d_ocp) -> 57.681736 | AG32: =class_series_d_original_shares*class_series_d_issue_pps/'Pro-Forma'!AF32 -> 1733651.4 | AH32: =IF('Pro-Forma'!V32<class_series_e_ocp,class_series_e_ocp*(ad_pre_f_broad_based_fd+series_f_primary_raise_usd/class_series_e_ocp)/(ad_pre_f_broad_based_fd+series_f_primary_raise_usd/'Pro-Forma'!V32),class_series_e_ocp) -> 48.912626 | AI32: =class_series_e_original_shares*class_series_e_issue_pps/'Pro-Forma'!AH32 -> 6133320.3 | AJ32: ='Pro-Forma'!Y32-class_seed_current_shares+'Pro-Forma'!AA32-class_series_a_current_shares+'Pro-Forma'!AC32-class_series_b_current_shares+'Pro-Forma'!AE32-class_series_c_current_shares+'Pro-Forma'!AG32-class_series_d_current_shares+'Pro-Forma'!AI32-class_series_e_current_shares -> 43677.638 | AK32: =note_a_cap_usd/(pre_f_fd_total+'Pro-Forma'!S32+'Pro-Forma'!AJ32+'Pro-Forma'!U32) -> 26.778553 | AL32: ='Pro-Forma'!V32*(const_one-note_a_discount) -> 30.102798 | AM32: =MIN('Pro-Forma'!AK32,'Pro-Forma'!AL32) -> 26.778553 | AN32: =note_a_principal_usd/'Pro-Forma'!AM32 -> 186716.59 | AO32: =note_b_cap_usd/(pre_f_fd_total+'Pro-Forma'!S32+'Pro-Forma'!AJ32+'Pro-Forma'!T32) -> 42.739338 | AP32: ='Pro-Forma'!V32*(const_one-note_b_discount) -> 31.984223 | AQ32: =MIN('Pro-Forma'!AO32,'Pro-Forma'!AP32) -> 31.984223 | AR32: =note_b_principal_usd/'Pro-Forma'!AQ32 -> 93796.243 | AS32: =pre_f_fd_total+'Pro-Forma'!S32+'Pro-Forma'!W32+'Pro-Forma'!AN32+'Pro-Forma'!AR32+'Pro-Forma'!AJ32 -> 38327302 | AT32: =MAX(const_zero,esop_refresh_target_post_f*'Pro-Forma'!AS32-pre_f_option_pool_total) -> 587882.23
R33: ='Pro-Forma'!R32+const_one -> 29 | S33: ='Pro-Forma'!AT32 -> 587882.23 | T33: ='Pro-Forma'!AN32 -> 186716.59 | U33: ='Pro-Forma'!AR32 -> 93796.243 | V33: =series_f_pre_money_usd/(pre_f_fd_total+'Pro-Forma'!S33) -> 37.628498 | W33: =series_f_primary_raise_usd/'Pro-Forma'!V33 -> 797268.07 | X33: =IF('Pro-Forma'!V33<class_seed_ocp,class_seed_ocp*(ad_pre_f_broad_based_fd+series_f_primary_raise_usd/class_seed_ocp)/(ad_pre_f_broad_based_fd+series_f_primary_raise_usd/'Pro-Forma'!V33),class_seed_ocp) -> 1 | Y33: =class_seed_original_shares*class_seed_issue_pps/'Pro-Forma'!X33 -> 5000000 | Z33: =IF('Pro-Forma'!V33<class_series_a_ocp,class_series_a_ocp*(ad_pre_f_broad_based_fd+series_f_primary_raise_usd/class_series_a_ocp)/(ad_pre_f_broad_based_fd+series_f_primary_raise_usd/'Pro-Forma'!V33),class_series_a_ocp) -> 3 | AA33: =class_series_a_original_shares*class_series_a_issue_pps/'Pro-Forma'!Z33 -> 5000000 | AB33: =IF('Pro-Forma'!V33<class_series_b_ocp,class_series_b_ocp*(ad_pre_f_broad_based_fd+series_f_primary_raise_usd/class_series_b_ocp)/(ad_pre_f_broad_based_fd+series_f_primary_raise_usd/'Pro-Forma'!V33),class_series_b_ocp) -> 10 | AC33: =class_series_b_original_shares*class_series_b_issue_pps/'Pro-Forma'!AB33 -> 3000000 | AD33: =IF('Pro-Forma'!V33<class_series_c_ocp,class_series_c_ocp*(ad_pre_f_broad_based_fd+series_f_primary_raise_usd/class_series_c_ocp)/(ad_pre_f_broad_based_fd+series_f_primary_raise_usd/'Pro-Forma'!V33),class_series_c_ocp) -> 25 | AE33: =class_series_c_original_shares*class_series_c_issue_pps/'Pro-Forma'!AD33 -> 2400000 | AF33: =IF('Pro-Forma'!V33<class_series_d_ocp,class_series_d_ocp*(ad_pre_f_broad_based_fd+series_f_primary_raise_usd/class_series_d_ocp)/(ad_pre_f_broad_based_fd+series_f_primary_raise_usd/'Pro-Forma'!V33),class_series_d_ocp) -> 57.681736 | AG33: =class_series_d_original_shares*class_series_d_issue_pps/'Pro-Forma'!AF33 -> 1733651.4 | AH33: =IF('Pro-Forma'!V33<class_series_e_ocp,class_series_e_ocp*(ad_pre_f_broad_based_fd+series_f_primary_raise_usd/class_series_e_ocp)/(ad_pre_f_broad_based_fd+series_f_primary_raise_usd/'Pro-Forma'!V33),class_series_e_ocp) -> 48.912626 | AI33: =class_series_e_original_shares*class_series_e_issue_pps/'Pro-Forma'!AH33 -> 6133320.3 | AJ33: ='Pro-Forma'!Y33-class_seed_current_shares+'Pro-Forma'!AA33-class_series_a_current_shares+'Pro-Forma'!AC33-class_series_b_current_shares+'Pro-Forma'!AE33-class_series_c_current_shares+'Pro-Forma'!AG33-class_series_d_current_shares+'Pro-Forma'!AI33-class_series_e_current_shares -> 43677.638 | AK33: =note_a_cap_usd/(pre_f_fd_total+'Pro-Forma'!S33+'Pro-Forma'!AJ33+'Pro-Forma'!U33) -> 26.778553 | AL33: ='Pro-Forma'!V33*(const_one-note_a_discount) -> 30.102798 | AM33: =MIN('Pro-Forma'!AK33,'Pro-Forma'!AL33) -> 26.778553 | AN33: =note_a_principal_usd/'Pro-Forma'!AM33 -> 186716.59 | AO33: =note_b_cap_usd/(pre_f_fd_total+'Pro-Forma'!S33+'Pro-Forma'!AJ33+'Pro-Forma'!T33) -> 42.739338 | AP33: ='Pro-Forma'!V33*(const_one-note_b_discount) -> 31.984223 | AQ33: =MIN('Pro-Forma'!AO33,'Pro-Forma'!AP33) -> 31.984223 | AR33: =note_b_principal_usd/'Pro-Forma'!AQ33 -> 93796.243 | AS33: =pre_f_fd_total+'Pro-Forma'!S33+'Pro-Forma'!W33+'Pro-Forma'!AN33+'Pro-Forma'!AR33+'Pro-Forma'!AJ33 -> 38327302 | AT33: =MAX(const_zero,esop_refresh_target_post_f*'Pro-Forma'!AS33-pre_f_option_pool_total) -> 587882.23
R34: ='Pro-Forma'!R33+const_one -> 30 | S34: ='Pro-Forma'!AT33 -> 587882.23 | T34: ='Pro-Forma'!AN33 -> 186716.59 | U34: ='Pro-Forma'!AR33 -> 93796.243 | V34: =series_f_pre_money_usd/(pre_f_fd_total+'Pro-Forma'!S34) -> 37.628498 | W34: =series_f_primary_raise_usd/'Pro-Forma'!V34 -> 797268.07 | X34: =IF('Pro-Forma'!V34<class_seed_ocp,class_seed_ocp*(ad_pre_f_broad_based_fd+series_f_primary_raise_usd/class_seed_ocp)/(ad_pre_f_broad_based_fd+series_f_primary_raise_usd/'Pro-Forma'!V34),class_seed_ocp) -> 1 | Y34: =class_seed_original_shares*class_seed_issue_pps/'Pro-Forma'!X34 -> 5000000 | Z34: =IF('Pro-Forma'!V34<class_series_a_ocp,class_series_a_ocp*(ad_pre_f_broad_based_fd+series_f_primary_raise_usd/class_series_a_ocp)/(ad_pre_f_broad_based_fd+series_f_primary_raise_usd/'Pro-Forma'!V34),class_series_a_ocp) -> 3 | AA34: =class_series_a_original_shares*class_series_a_issue_pps/'Pro-Forma'!Z34 -> 5000000 | AB34: =IF('Pro-Forma'!V34<class_series_b_ocp,class_series_b_ocp*(ad_pre_f_broad_based_fd+series_f_primary_raise_usd/class_series_b_ocp)/(ad_pre_f_broad_based_fd+series_f_primary_raise_usd/'Pro-Forma'!V34),class_series_b_ocp) -> 10 | AC34: =class_series_b_original_shares*class_series_b_issue_pps/'Pro-Forma'!AB34 -> 3000000 | AD34: =IF('Pro-Forma'!V34<class_series_c_ocp,class_series_c_ocp*(ad_pre_f_broad_based_fd+series_f_primary_raise_usd/class_series_c_ocp)/(ad_pre_f_broad_based_fd+series_f_primary_raise_usd/'Pro-Forma'!V34),class_series_c_ocp) -> 25 | AE34: =class_series_c_original_shares*class_series_c_issue_pps/'Pro-Forma'!AD34 -> 2400000 | AF34: =IF('Pro-Forma'!V34<class_series_d_ocp,class_series_d_ocp*(ad_pre_f_broad_based_fd+series_f_primary_raise_usd/class_series_d_ocp)/(ad_pre_f_broad_based_fd+series_f_primary_raise_usd/'Pro-Forma'!V34),class_series_d_ocp) -> 57.681736 | AG34: =class_series_d_original_shares*class_series_d_issue_pps/'Pro-Forma'!AF34 -> 1733651.4 | AH34: =IF('Pro-Forma'!V34<class_series_e_ocp,class_series_e_ocp*(ad_pre_f_broad_based_fd+series_f_primary_raise_usd/class_series_e_ocp)/(ad_pre_f_broad_based_fd+series_f_primary_raise_usd/'Pro-Forma'!V34),class_series_e_ocp) -> 48.912626 | AI34: =class_series_e_original_shares*class_series_e_issue_pps/'Pro-Forma'!AH34 -> 6133320.3 | AJ34: ='Pro-Forma'!Y34-class_seed_current_shares+'Pro-Forma'!AA34-class_series_a_current_shares+'Pro-Forma'!AC34-class_series_b_current_shares+'Pro-Forma'!AE34-class_series_c_current_shares+'Pro-Forma'!AG34-class_series_d_current_shares+'Pro-Forma'!AI34-class_series_e_current_shares -> 43677.638 | AK34: =note_a_cap_usd/(pre_f_fd_total+'Pro-Forma'!S34+'Pro-Forma'!AJ34+'Pro-Forma'!U34) -> 26.778553 | AL34: ='Pro-Forma'!V34*(const_one-note_a_discount) -> 30.102798 | AM34: =MIN('Pro-Forma'!AK34,'Pro-Forma'!AL34) -> 26.778553 | AN34: =note_a_principal_usd/'Pro-Forma'!AM34 -> 186716.59 | AO34: =note_b_cap_usd/(pre_f_fd_total+'Pro-Forma'!S34+'Pro-Forma'!AJ34+'Pro-Forma'!T34) -> 42.739338 | AP34: ='Pro-Forma'!V34*(const_one-note_b_discount) -> 31.984223 | AQ34: =MIN('Pro-Forma'!AO34,'Pro-Forma'!AP34) -> 31.984223 | AR34: =note_b_principal_usd/'Pro-Forma'!AQ34 -> 93796.243 | AS34: =pre_f_fd_total+'Pro-Forma'!S34+'Pro-Forma'!W34+'Pro-Forma'!AN34+'Pro-Forma'!AR34+'Pro-Forma'!AJ34 -> 38327302 | AT34: =MAX(const_zero,esop_refresh_target_post_f*'Pro-Forma'!AS34-pre_f_option_pool_total) -> 587882.23
R35: ='Pro-Forma'!R34+const_one -> 31 | S35: ='Pro-Forma'!AT34 -> 587882.23 | T35: ='Pro-Forma'!AN34 -> 186716.59 | U35: ='Pro-Forma'!AR34 -> 93796.243 | V35: =series_f_pre_money_usd/(pre_f_fd_total+'Pro-Forma'!S35) -> 37.628498 | W35: =series_f_primary_raise_usd/'Pro-Forma'!V35 -> 797268.07 | X35: =IF('Pro-Forma'!V35<class_seed_ocp,class_seed_ocp*(ad_pre_f_broad_based_fd+series_f_primary_raise_usd/class_seed_ocp)/(ad_pre_f_broad_based_fd+series_f_primary_raise_usd/'Pro-Forma'!V35),class_seed_ocp) -> 1 | Y35: =class_seed_original_shares*class_seed_issue_pps/'Pro-Forma'!X35 -> 5000000 | Z35: =IF('Pro-Forma'!V35<class_series_a_ocp,class_series_a_ocp*(ad_pre_f_broad_based_fd+series_f_primary_raise_usd/class_series_a_ocp)/(ad_pre_f_broad_based_fd+series_f_primary_raise_usd/'Pro-Forma'!V35),class_series_a_ocp) -> 3 | AA35: =class_series_a_original_shares*class_series_a_issue_pps/'Pro-Forma'!Z35 -> 5000000 | AB35: =IF('Pro-Forma'!V35<class_series_b_ocp,class_series_b_ocp*(ad_pre_f_broad_based_fd+series_f_primary_raise_usd/class_series_b_ocp)/(ad_pre_f_broad_based_fd+series_f_primary_raise_usd/'Pro-Forma'!V35),class_series_b_ocp) -> 10 | AC35: =class_series_b_original_shares*class_series_b_issue_pps/'Pro-Forma'!AB35 -> 3000000 | AD35: =IF('Pro-Forma'!V35<class_series_c_ocp,class_series_c_ocp*(ad_pre_f_broad_based_fd+series_f_primary_raise_usd/class_series_c_ocp)/(ad_pre_f_broad_based_fd+series_f_primary_raise_usd/'Pro-Forma'!V35),class_series_c_ocp) -> 25 | AE35: =class_series_c_original_shares*class_series_c_issue_pps/'Pro-Forma'!AD35 -> 2400000 | AF35: =IF('Pro-Forma'!V35<class_series_d_ocp,class_series_d_ocp*(ad_pre_f_broad_based_fd+series_f_primary_raise_usd/class_series_d_ocp)/(ad_pre_f_broad_based_fd+series_f_primary_raise_usd/'Pro-Forma'!V35),class_series_d_ocp) -> 57.681736 | AG35: =class_series_d_original_shares*class_series_d_issue_pps/'Pro-Forma'!AF35 -> 1733651.4 | AH35: =IF('Pro-Forma'!V35<class_series_e_ocp,class_series_e_ocp*(ad_pre_f_broad_based_fd+series_f_primary_raise_usd/class_series_e_ocp)/(ad_pre_f_broad_based_fd+series_f_primary_raise_usd/'Pro-Forma'!V35),class_series_e_ocp) -> 48.912626 | AI35: =class_series_e_original_shares*class_series_e_issue_pps/'Pro-Forma'!AH35 -> 6133320.3 | AJ35: ='Pro-Forma'!Y35-class_seed_current_shares+'Pro-Forma'!AA35-class_series_a_current_shares+'Pro-Forma'!AC35-class_series_b_current_shares+'Pro-Forma'!AE35-class_series_c_current_shares+'Pro-Forma'!AG35-class_series_d_current_shares+'Pro-Forma'!AI35-class_series_e_current_shares -> 43677.638 | AK35: =note_a_cap_usd/(pre_f_fd_total+'Pro-Forma'!S35+'Pro-Forma'!AJ35+'Pro-Forma'!U35) -> 26.778553 | AL35: ='Pro-Forma'!V35*(const_one-note_a_discount) -> 30.102798 | AM35: =MIN('Pro-Forma'!AK35,'Pro-Forma'!AL35) -> 26.778553 | AN35: =note_a_principal_usd/'Pro-Forma'!AM35 -> 186716.59 | AO35: =note_b_cap_usd/(pre_f_fd_total+'Pro-Forma'!S35+'Pro-Forma'!AJ35+'Pro-Forma'!T35) -> 42.739338 | AP35: ='Pro-Forma'!V35*(const_one-note_b_discount) -> 31.984223 | AQ35: =MIN('Pro-Forma'!AO35,'Pro-Forma'!AP35) -> 31.984223 | AR35: =note_b_principal_usd/'Pro-Forma'!AQ35 -> 93796.243 | AS35: =pre_f_fd_total+'Pro-Forma'!S35+'Pro-Forma'!W35+'Pro-Forma'!AN35+'Pro-Forma'!AR35+'Pro-Forma'!AJ35 -> 38327302 | AT35: =MAX(const_zero,esop_refresh_target_post_f*'Pro-Forma'!AS35-pre_f_option_pool_total) -> 587882.23
A36: =lbl_tender_block -> Tender Block | R36: ='Pro-Forma'!R35+const_one -> 32 | S36: ='Pro-Forma'!AT35 -> 587882.23 | T36: ='Pro-Forma'!AN35 -> 186716.59 | U36: ='Pro-Forma'!AR35 -> 93796.243 | V36: =series_f_pre_money_usd/(pre_f_fd_total+'Pro-Forma'!S36) -> 37.628498 | W36: =series_f_primary_raise_usd/'Pro-Forma'!V36 -> 797268.07 | X36: =IF('Pro-Forma'!V36<class_seed_ocp,class_seed_ocp*(ad_pre_f_broad_based_fd+series_f_primary_raise_usd/class_seed_ocp)/(ad_pre_f_broad_based_fd+series_f_primary_raise_usd/'Pro-Forma'!V36),class_seed_ocp) -> 1 | Y36: =class_seed_original_shares*class_seed_issue_pps/'Pro-Forma'!X36 -> 5000000 | Z36: =IF('Pro-Forma'!V36<class_series_a_ocp,class_series_a_ocp*(ad_pre_f_broad_based_fd+series_f_primary_raise_usd/class_series_a_ocp)/(ad_pre_f_broad_based_fd+series_f_primary_raise_usd/'Pro-Forma'!V36),class_series_a_ocp) -> 3 | AA36: =class_series_a_original_shares*class_series_a_issue_pps/'Pro-Forma'!Z36 -> 5000000 | AB36: =IF('Pro-Forma'!V36<class_series_b_ocp,class_series_b_ocp*(ad_pre_f_broad_based_fd+series_f_primary_raise_usd/class_series_b_ocp)/(ad_pre_f_broad_based_fd+series_f_primary_raise_usd/'Pro-Forma'!V36),class_series_b_ocp) -> 10 | AC36: =class_series_b_original_shares*class_series_b_issue_pps/'Pro-Forma'!AB36 -> 3000000 | AD36: =IF('Pro-Forma'!V36<class_series_c_ocp,class_series_c_ocp*(ad_pre_f_broad_based_fd+series_f_primary_raise_usd/class_series_c_ocp)/(ad_pre_f_broad_based_fd+series_f_primary_raise_usd/'Pro-Forma'!V36),class_series_c_ocp) -> 25 | AE36: =class_series_c_original_shares*class_series_c_issue_pps/'Pro-Forma'!AD36 -> 2400000 | AF36: =IF('Pro-Forma'!V36<class_series_d_ocp,class_series_d_ocp*(ad_pre_f_broad_based_fd+series_f_primary_raise_usd/class_series_d_ocp)/(ad_pre_f_broad_based_fd+series_f_primary_raise_usd/'Pro-Forma'!V36),class_series_d_ocp) -> 57.681736 | AG36: =class_series_d_original_shares*class_series_d_issue_pps/'Pro-Forma'!AF36 -> 1733651.4 | AH36: =IF('Pro-Forma'!V36<class_series_e_ocp,class_series_e_ocp*(ad_pre_f_broad_based_fd+series_f_primary_raise_usd/class_series_e_ocp)/(ad_pre_f_broad_based_fd+series_f_primary_raise_usd/'Pro-Forma'!V36),class_series_e_ocp) -> 48.912626 | AI36: =class_series_e_original_shares*class_series_e_issue_pps/'Pro-Forma'!AH36 -> 6133320.3 | AJ36: ='Pro-Forma'!Y36-class_seed_current_shares+'Pro-Forma'!AA36-class_series_a_current_shares+'Pro-Forma'!AC36-class_series_b_current_shares+'Pro-Forma'!AE36-class_series_c_current_shares+'Pro-Forma'!AG36-class_series_d_current_shares+'Pro-Forma'!AI36-class_series_e_current_shares -> 43677.638 | AK36: =note_a_cap_usd/(pre_f_fd_total+'Pro-Forma'!S36+'Pro-Forma'!AJ36+'Pro-Forma'!U36) -> 26.778553 | AL36: ='Pro-Forma'!V36*(const_one-note_a_discount) -> 30.102798 | AM36: =MIN('Pro-Forma'!AK36,'Pro-Forma'!AL36) -> 26.778553 | AN36: =note_a_principal_usd/'Pro-Forma'!AM36 -> 186716.59 | AO36: =note_b_cap_usd/(pre_f_fd_total+'Pro-Forma'!S36+'Pro-Forma'!AJ36+'Pro-Forma'!T36) -> 42.739338 | AP36: ='Pro-Forma'!V36*(const_one-note_b_discount) -> 31.984223 | AQ36: =MIN('Pro-Forma'!AO36,'Pro-Forma'!AP36) -> 31.984223 | AR36: =note_b_principal_usd/'Pro-Forma'!AQ36 -> 93796.243 | AS36: =pre_f_fd_total+'Pro-Forma'!S36+'Pro-Forma'!W36+'Pro-Forma'!AN36+'Pro-Forma'!AR36+'Pro-Forma'!AJ36 -> 38327302 | AT36: =MAX(const_zero,esop_refresh_target_post_f*'Pro-Forma'!AS36-pre_f_option_pool_total) -> 587882.23
A37: =lbl_tender_pps -> Tender PPS | B37: =series_f_tender_pps_multiplier*$B$4 -> 31.984223 | R37: ='Pro-Forma'!R36+const_one -> 33 | S37: ='Pro-Forma'!AT36 -> 587882.23 | T37: ='Pro-Forma'!AN36 -> 186716.59 | U37: ='Pro-Forma'!AR36 -> 93796.243 | V37: =series_f_pre_money_usd/(pre_f_fd_total+'Pro-Forma'!S37) -> 37.628498 | W37: =series_f_primary_raise_usd/'Pro-Forma'!V37 -> 797268.07 | X37: =IF('Pro-Forma'!V37<class_seed_ocp,class_seed_ocp*(ad_pre_f_broad_based_fd+series_f_primary_raise_usd/class_seed_ocp)/(ad_pre_f_broad_based_fd+series_f_primary_raise_usd/'Pro-Forma'!V37),class_seed_ocp) -> 1 | Y37: =class_seed_original_shares*class_seed_issue_pps/'Pro-Forma'!X37 -> 5000000 | Z37: =IF('Pro-Forma'!V37<class_series_a_ocp,class_series_a_ocp*(ad_pre_f_broad_based_fd+series_f_primary_raise_usd/class_series_a_ocp)/(ad_pre_f_broad_based_fd+series_f_primary_raise_usd/'Pro-Forma'!V37),class_series_a_ocp) -> 3 | AA37: =class_series_a_original_shares*class_series_a_issue_pps/'Pro-Forma'!Z37 -> 5000000 | AB37: =IF('Pro-Forma'!V37<class_series_b_ocp,class_series_b_ocp*(ad_pre_f_broad_based_fd+series_f_primary_raise_usd/class_series_b_ocp)/(ad_pre_f_broad_based_fd+series_f_primary_raise_usd/'Pro-Forma'!V37),class_series_b_ocp) -> 10 | AC37: =class_series_b_original_shares*class_series_b_issue_pps/'Pro-Forma'!AB37 -> 3000000 | AD37: =IF('Pro-Forma'!V37<class_series_c_ocp,class_series_c_ocp*(ad_pre_f_broad_based_fd+series_f_primary_raise_usd/class_series_c_ocp)/(ad_pre_f_broad_based_fd+series_f_primary_raise_usd/'Pro-Forma'!V37),class_series_c_ocp) -> 25 | AE37: =class_series_c_original_shares*class_series_c_issue_pps/'Pro-Forma'!AD37 -> 2400000 | AF37: =IF('Pro-Forma'!V37<class_series_d_ocp,class_series_d_ocp*(ad_pre_f_broad_based_fd+series_f_primary_raise_usd/class_series_d_ocp)/(ad_pre_f_broad_based_fd+series_f_primary_raise_usd/'Pro-Forma'!V37),class_series_d_ocp) -> 57.681736 | AG37: =class_series_d_original_shares*class_series_d_issue_pps/'Pro-Forma'!AF37 -> 1733651.4 | AH37: =IF('Pro-Forma'!V37<class_series_e_ocp,class_series_e_ocp*(ad_pre_f_broad_based_fd+series_f_primary_raise_usd/class_series_e_ocp)/(ad_pre_f_broad_based_fd+series_f_primary_raise_usd/'Pro-Forma'!V37),class_series_e_ocp) -> 48.912626 | AI37: =class_series_e_original_shares*class_series_e_issue_pps/'Pro-Forma'!AH37 -> 6133320.3 | AJ37: ='Pro-Forma'!Y37-class_seed_current_shares+'Pro-Forma'!AA37-class_series_a_current_shares+'Pro-Forma'!AC37-class_series_b_current_shares+'Pro-Forma'!AE37-class_series_c_current_shares+'Pro-Forma'!AG37-class_series_d_current_shares+'Pro-Forma'!AI37-class_series_e_current_shares -> 43677.638 | AK37: =note_a_cap_usd/(pre_f_fd_total+'Pro-Forma'!S37+'Pro-Forma'!AJ37+'Pro-Forma'!U37) -> 26.778553 | AL37: ='Pro-Forma'!V37*(const_one-note_a_discount) -> 30.102798 | AM37: =MIN('Pro-Forma'!AK37,'Pro-Forma'!AL37) -> 26.778553 | AN37: =note_a_principal_usd/'Pro-Forma'!AM37 -> 186716.59 | AO37: =note_b_cap_usd/(pre_f_fd_total+'Pro-Forma'!S37+'Pro-Forma'!AJ37+'Pro-Forma'!T37) -> 42.739338 | AP37: ='Pro-Forma'!V37*(const_one-note_b_discount) -> 31.984223 | AQ37: =MIN('Pro-Forma'!AO37,'Pro-Forma'!AP37) -> 31.984223 | AR37: =note_b_principal_usd/'Pro-Forma'!AQ37 -> 93796.243 | AS37: =pre_f_fd_total+'Pro-Forma'!S37+'Pro-Forma'!W37+'Pro-Forma'!AN37+'Pro-Forma'!AR37+'Pro-Forma'!AJ37 -> 38327302 | AT37: =MAX(const_zero,esop_refresh_target_post_f*'Pro-Forma'!AS37-pre_f_option_pool_total) -> 587882.23
A38: =lbl_tender_shares -> Tender shares | B38: =series_f_secondary_raise_usd/B37 -> 468981.22 | R38: ='Pro-Forma'!R37+const_one -> 34 | S38: ='Pro-Forma'!AT37 -> 587882.23 | T38: ='Pro-Forma'!AN37 -> 186716.59 | U38: ='Pro-Forma'!AR37 -> 93796.243 | V38: =series_f_pre_money_usd/(pre_f_fd_total+'Pro-Forma'!S38) -> 37.628498 | W38: =series_f_primary_raise_usd/'Pro-Forma'!V38 -> 797268.07 | X38: =IF('Pro-Forma'!V38<class_seed_ocp,class_seed_ocp*(ad_pre_f_broad_based_fd+series_f_primary_raise_usd/class_seed_ocp)/(ad_pre_f_broad_based_fd+series_f_primary_raise_usd/'Pro-Forma'!V38),class_seed_ocp) -> 1 | Y38: =class_seed_original_shares*class_seed_issue_pps/'Pro-Forma'!X38 -> 5000000 | Z38: =IF('Pro-Forma'!V38<class_series_a_ocp,class_series_a_ocp*(ad_pre_f_broad_based_fd+series_f_primary_raise_usd/class_series_a_ocp)/(ad_pre_f_broad_based_fd+series_f_primary_raise_usd/'Pro-Forma'!V38),class_series_a_ocp) -> 3 | AA38: =class_series_a_original_shares*class_series_a_issue_pps/'Pro-Forma'!Z38 -> 5000000 | AB38: =IF('Pro-Forma'!V38<class_series_b_ocp,class_series_b_ocp*(ad_pre_f_broad_based_fd+series_f_primary_raise_usd/class_series_b_ocp)/(ad_pre_f_broad_based_fd+series_f_primary_raise_usd/'Pro-Forma'!V38),class_series_b_ocp) -> 10 | AC38: =class_series_b_original_shares*class_series_b_issue_pps/'Pro-Forma'!AB38 -> 3000000 | AD38: =IF('Pro-Forma'!V38<class_series_c_ocp,class_series_c_ocp*(ad_pre_f_broad_based_fd+series_f_primary_raise_usd/class_series_c_ocp)/(ad_pre_f_broad_based_fd+series_f_primary_raise_usd/'Pro-Forma'!V38),class_series_c_ocp) -> 25 | AE38: =class_series_c_original_shares*class_series_c_issue_pps/'Pro-Forma'!AD38 -> 2400000 | AF38: =IF('Pro-Forma'!V38<class_series_d_ocp,class_series_d_ocp*(ad_pre_f_broad_based_fd+series_f_primary_raise_usd/class_series_d_ocp)/(ad_pre_f_broad_based_fd+series_f_primary_raise_usd/'Pro-Forma'!V38),class_series_d_ocp) -> 57.681736 | AG38: =class_series_d_original_shares*class_series_d_issue_pps/'Pro-Forma'!AF38 -> 1733651.4 | AH38: =IF('Pro-Forma'!V38<class_series_e_ocp,class_series_e_ocp*(ad_pre_f_broad_based_fd+series_f_primary_raise_usd/class_series_e_ocp)/(ad_pre_f_broad_based_fd+series_f_primary_raise_usd/'Pro-Forma'!V38),class_series_e_ocp) -> 48.912626 | AI38: =class_series_e_original_shares*class_series_e_issue_pps/'Pro-Forma'!AH38 -> 6133320.3 | AJ38: ='Pro-Forma'!Y38-class_seed_current_shares+'Pro-Forma'!AA38-class_series_a_current_shares+'Pro-Forma'!AC38-class_series_b_current_shares+'Pro-Forma'!AE38-class_series_c_current_shares+'Pro-Forma'!AG38-class_series_d_current_shares+'Pro-Forma'!AI38-class_series_e_current_shares -> 43677.638 | AK38: =note_a_cap_usd/(pre_f_fd_total+'Pro-Forma'!S38+'Pro-Forma'!AJ38+'Pro-Forma'!U38) -> 26.778553 | AL38: ='Pro-Forma'!V38*(const_one-note_a_discount) -> 30.102798 | AM38: =MIN('Pro-Forma'!AK38,'Pro-Forma'!AL38) -> 26.778553 | AN38: =note_a_principal_usd/'Pro-Forma'!AM38 -> 186716.59 | AO38: =note_b_cap_usd/(pre_f_fd_total+'Pro-Forma'!S38+'Pro-Forma'!AJ38+'Pro-Forma'!T38) -> 42.739338 | AP38: ='Pro-Forma'!V38*(const_one-note_b_discount) -> 31.984223 | AQ38: =MIN('Pro-Forma'!AO38,'Pro-Forma'!AP38) -> 31.984223 | AR38: =note_b_principal_usd/'Pro-Forma'!AQ38 -> 93796.243 | AS38: =pre_f_fd_total+'Pro-Forma'!S38+'Pro-Forma'!W38+'Pro-Forma'!AN38+'Pro-Forma'!AR38+'Pro-Forma'!AJ38 -> 38327302 | AT38: =MAX(const_zero,esop_refresh_target_post_f*'Pro-Forma'!AS38-pre_f_option_pool_total) -> 587882.23
A39: =lbl_f_lead_secondary -> F_LEAD secondary common | B39: =B38 -> 468981.22 | R39: ='Pro-Forma'!R38+const_one -> 35 | S39: ='Pro-Forma'!AT38 -> 587882.23 | T39: ='Pro-Forma'!AN38 -> 186716.59 | U39: ='Pro-Forma'!AR38 -> 93796.243 | V39: =series_f_pre_money_usd/(pre_f_fd_total+'Pro-Forma'!S39) -> 37.628498 | W39: =series_f_primary_raise_usd/'Pro-Forma'!V39 -> 797268.07 | X39: =IF('Pro-Forma'!V39<class_seed_ocp,class_seed_ocp*(ad_pre_f_broad_based_fd+series_f_primary_raise_usd/class_seed_ocp)/(ad_pre_f_broad_based_fd+series_f_primary_raise_usd/'Pro-Forma'!V39),class_seed_ocp) -> 1 | Y39: =class_seed_original_shares*class_seed_issue_pps/'Pro-Forma'!X39 -> 5000000 | Z39: =IF('Pro-Forma'!V39<class_series_a_ocp,class_series_a_ocp*(ad_pre_f_broad_based_fd+series_f_primary_raise_usd/class_series_a_ocp)/(ad_pre_f_broad_based_fd+series_f_primary_raise_usd/'Pro-Forma'!V39),class_series_a_ocp) -> 3 | AA39: =class_series_a_original_shares*class_series_a_issue_pps/'Pro-Forma'!Z39 -> 5000000 | AB39: =IF('Pro-Forma'!V39<class_series_b_ocp,class_series_b_ocp*(ad_pre_f_broad_based_fd+series_f_primary_raise_usd/class_series_b_ocp)/(ad_pre_f_broad_based_fd+series_f_primary_raise_usd/'Pro-Forma'!V39),class_series_b_ocp) -> 10 | AC39: =class_series_b_original_shares*class_series_b_issue_pps/'Pro-Forma'!AB39 -> 3000000 | AD39: =IF('Pro-Forma'!V39<class_series_c_ocp,class_series_c_ocp*(ad_pre_f_broad_based_fd+series_f_primary_raise_usd/class_series_c_ocp)/(ad_pre_f_broad_based_fd+series_f_primary_raise_usd/'Pro-Forma'!V39),class_series_c_ocp) -> 25 | AE39: =class_series_c_original_shares*class_series_c_issue_pps/'Pro-Forma'!AD39 -> 2400000 | AF39: =IF('Pro-Forma'!V39<class_series_d_ocp,class_series_d_ocp*(ad_pre_f_broad_based_fd+series_f_primary_raise_usd/class_series_d_ocp)/(ad_pre_f_broad_based_fd+series_f_primary_raise_usd/'Pro-Forma'!V39),class_series_d_ocp) -> 57.681736 | AG39: =class_series_d_original_shares*class_series_d_issue_pps/'Pro-Forma'!AF39 -> 1733651.4 | AH39: =IF('Pro-Forma'!V39<class_series_e_ocp,class_series_e_ocp*(ad_pre_f_broad_based_fd+series_f_primary_raise_usd/class_series_e_ocp)/(ad_pre_f_broad_based_fd+series_f_primary_raise_usd/'Pro-Forma'!V39),class_series_e_ocp) -> 48.912626 | AI39: =class_series_e_original_shares*class_series_e_issue_pps/'Pro-Forma'!AH39 -> 6133320.3 | AJ39: ='Pro-Forma'!Y39-class_seed_current_shares+'Pro-Forma'!AA39-class_series_a_current_shares+'Pro-Forma'!AC39-class_series_b_current_shares+'Pro-Forma'!AE39-class_series_c_current_shares+'Pro-Forma'!AG39-class_series_d_current_shares+'Pro-Forma'!AI39-class_series_e_current_shares -> 43677.638 | AK39: =note_a_cap_usd/(pre_f_fd_total+'Pro-Forma'!S39+'Pro-Forma'!AJ39+'Pro-Forma'!U39) -> 26.778553 | AL39: ='Pro-Forma'!V39*(const_one-note_a_discount) -> 30.102798 | AM39: =MIN('Pro-Forma'!AK39,'Pro-Forma'!AL39) -> 26.778553 | AN39: =note_a_principal_usd/'Pro-Forma'!AM39 -> 186716.59 | AO39: =note_b_cap_usd/(pre_f_fd_total+'Pro-Forma'!S39+'Pro-Forma'!AJ39+'Pro-Forma'!T39) -> 42.739338 | AP39: ='Pro-Forma'!V39*(const_one-note_b_discount) -> 31.984223 | AQ39: =MIN('Pro-Forma'!AO39,'Pro-Forma'!AP39) -> 31.984223 | AR39: =note_b_principal_usd/'Pro-Forma'!AQ39 -> 93796.243 | AS39: =pre_f_fd_total+'Pro-Forma'!S39+'Pro-Forma'!W39+'Pro-Forma'!AN39+'Pro-Forma'!AR39+'Pro-Forma'!AJ39 -> 38327302 | AT39: =MAX(const_zero,esop_refresh_target_post_f*'Pro-Forma'!AS39-pre_f_option_pool_total) -> 587882.23
R40: ='Pro-Forma'!R39+const_one -> 36 | S40: ='Pro-Forma'!AT39 -> 587882.23 | T40: ='Pro-Forma'!AN39 -> 186716.59 | U40: ='Pro-Forma'!AR39 -> 93796.243 | V40: =series_f_pre_money_usd/(pre_f_fd_total+'Pro-Forma'!S40) -> 37.628498 | W40: =series_f_primary_raise_usd/'Pro-Forma'!V40 -> 797268.07 | X40: =IF('Pro-Forma'!V40<class_seed_ocp,class_seed_ocp*(ad_pre_f_broad_based_fd+series_f_primary_raise_usd/class_seed_ocp)/(ad_pre_f_broad_based_fd+series_f_primary_raise_usd/'Pro-Forma'!V40),class_seed_ocp) -> 1 | Y40: =class_seed_original_shares*class_seed_issue_pps/'Pro-Forma'!X40 -> 5000000 | Z40: =IF('Pro-Forma'!V40<class_series_a_ocp,class_series_a_ocp*(ad_pre_f_broad_based_fd+series_f_primary_raise_usd/class_series_a_ocp)/(ad_pre_f_broad_based_fd+series_f_primary_raise_usd/'Pro-Forma'!V40),class_series_a_ocp) -> 3 | AA40: =class_series_a_original_shares*class_series_a_issue_pps/'Pro-Forma'!Z40 -> 5000000 | AB40: =IF('Pro-Forma'!V40<class_series_b_ocp,class_series_b_ocp*(ad_pre_f_broad_based_fd+series_f_primary_raise_usd/class_series_b_ocp)/(ad_pre_f_broad_based_fd+series_f_primary_raise_usd/'Pro-Forma'!V40),class_series_b_ocp) -> 10 | AC40: =class_series_b_original_shares*class_series_b_issue_pps/'Pro-Forma'!AB40 -> 3000000 | AD40: =IF('Pro-Forma'!V40<class_series_c_ocp,class_series_c_ocp*(ad_pre_f_broad_based_fd+series_f_primary_raise_usd/class_series_c_ocp)/(ad_pre_f_broad_based_fd+series_f_primary_raise_usd/'Pro-Forma'!V40),class_series_c_ocp) -> 25 | AE40: =class_series_c_original_shares*class_series_c_issue_pps/'Pro-Forma'!AD40 -> 2400000 | AF40: =IF('Pro-Forma'!V40<class_series_d_ocp,class_series_d_ocp*(ad_pre_f_broad_based_fd+series_f_primary_raise_usd/class_series_d_ocp)/(ad_pre_f_broad_based_fd+series_f_primary_raise_usd/'Pro-Forma'!V40),class_series_d_ocp) -> 57.681736 | AG40: =class_series_d_original_shares*class_series_d_issue_pps/'Pro-Forma'!AF40 -> 1733651.4 | AH40: =IF('Pro-Forma'!V40<class_series_e_ocp,class_series_e_ocp*(ad_pre_f_broad_based_fd+series_f_primary_raise_usd/class_series_e_ocp)/(ad_pre_f_broad_based_fd+series_f_primary_raise_usd/'Pro-Forma'!V40),class_series_e_ocp) -> 48.912626 | AI40: =class_series_e_original_shares*class_series_e_issue_pps/'Pro-Forma'!AH40 -> 6133320.3 | AJ40: ='Pro-Forma'!Y40-class_seed_current_shares+'Pro-Forma'!AA40-class_series_a_current_shares+'Pro-Forma'!AC40-class_series_b_current_shares+'Pro-Forma'!AE40-class_series_c_current_shares+'Pro-Forma'!AG40-class_series_d_current_shares+'Pro-Forma'!AI40-class_series_e_current_shares -> 43677.638 | AK40: =note_a_cap_usd/(pre_f_fd_total+'Pro-Forma'!S40+'Pro-Forma'!AJ40+'Pro-Forma'!U40) -> 26.778553 | AL40: ='Pro-Forma'!V40*(const_one-note_a_discount) -> 30.102798 | AM40: =MIN('Pro-Forma'!AK40,'Pro-Forma'!AL40) -> 26.778553 | AN40: =note_a_principal_usd/'Pro-Forma'!AM40 -> 186716.59 | AO40: =note_b_cap_usd/(pre_f_fd_total+'Pro-Forma'!S40+'Pro-Forma'!AJ40+'Pro-Forma'!T40) -> 42.739338 | AP40: ='Pro-Forma'!V40*(const_one-note_b_discount) -> 31.984223 | AQ40: =MIN('Pro-Forma'!AO40,'Pro-Forma'!AP40) -> 31.984223 | AR40: =note_b_principal_usd/'Pro-Forma'!AQ40 -> 93796.243 | AS40: =pre_f_fd_total+'Pro-Forma'!S40+'Pro-Forma'!W40+'Pro-Forma'!AN40+'Pro-Forma'!AR40+'Pro-Forma'!AJ40 -> 38327302 | AT40: =MAX(const_zero,esop_refresh_target_post_f*'Pro-Forma'!AS40-pre_f_option_pool_total) -> 587882.23
A41: =lbl_founder -> Founder | B41: =lbl_initial_common -> Initial common | C41: =lbl_prorata -> Pro-rata % | D41: =lbl_share_out -> Tender share-out | E41: =lbl_post_common -> Post-tender common | R41: ='Pro-Forma'!R40+const_one -> 37 | S41: ='Pro-Forma'!AT40 -> 587882.23 | T41: ='Pro-Forma'!AN40 -> 186716.59 | U41: ='Pro-Forma'!AR40 -> 93796.243 | V41: =series_f_pre_money_usd/(pre_f_fd_total+'Pro-Forma'!S41) -> 37.628498 | W41: =series_f_primary_raise_usd/'Pro-Forma'!V41 -> 797268.07 | X41: =IF('Pro-Forma'!V41<class_seed_ocp,class_seed_ocp*(ad_pre_f_broad_based_fd+series_f_primary_raise_usd/class_seed_ocp)/(ad_pre_f_broad_based_fd+series_f_primary_raise_usd/'Pro-Forma'!V41),class_seed_ocp) -> 1 | Y41: =class_seed_original_shares*class_seed_issue_pps/'Pro-Forma'!X41 -> 5000000 | Z41: =IF('Pro-Forma'!V41<class_series_a_ocp,class_series_a_ocp*(ad_pre_f_broad_based_fd+series_f_primary_raise_usd/class_series_a_ocp)/(ad_pre_f_broad_based_fd+series_f_primary_raise_usd/'Pro-Forma'!V41),class_series_a_ocp) -> 3 | AA41: =class_series_a_original_shares*class_series_a_issue_pps/'Pro-Forma'!Z41 -> 5000000 | AB41: =IF('Pro-Forma'!V41<class_series_b_ocp,class_series_b_ocp*(ad_pre_f_broad_based_fd+series_f_primary_raise_usd/class_series_b_ocp)/(ad_pre_f_broad_based_fd+series_f_primary_raise_usd/'Pro-Forma'!V41),class_series_b_ocp) -> 10 | AC41: =class_series_b_original_shares*class_series_b_issue_pps/'Pro-Forma'!AB41 -> 3000000 | AD41: =IF('Pro-Forma'!V41<class_series_c_ocp,class_series_c_ocp*(ad_pre_f_broad_based_fd+series_f_primary_raise_usd/class_series_c_ocp)/(ad_pre_f_broad_based_fd+series_f_primary_raise_usd/'Pro-Forma'!V41),class_series_c_ocp) -> 25 | AE41: =class_series_c_original_shares*class_series_c_issue_pps/'Pro-Forma'!AD41 -> 2400000 | AF41: =IF('Pro-Forma'!V41<class_series_d_ocp,class_series_d_ocp*(ad_pre_f_broad_based_fd+series_f_primary_raise_usd/class_series_d_ocp)/(ad_pre_f_broad_based_fd+series_f_primary_raise_usd/'Pro-Forma'!V41),class_series_d_ocp) -> 57.681736 | AG41: =class_series_d_original_shares*class_series_d_issue_pps/'Pro-Forma'!AF41 -> 1733651.4 | AH41: =IF('Pro-Forma'!V41<class_series_e_ocp,class_series_e_ocp*(ad_pre_f_broad_based_fd+series_f_primary_raise_usd/class_series_e_ocp)/(ad_pre_f_broad_based_fd+series_f_primary_raise_usd/'Pro-Forma'!V41),class_series_e_ocp) -> 48.912626 | AI41: =class_series_e_original_shares*class_series_e_issue_pps/'Pro-Forma'!AH41 -> 6133320.3 | AJ41: ='Pro-Forma'!Y41-class_seed_current_shares+'Pro-Forma'!AA41-class_series_a_current_shares+'Pro-Forma'!AC41-class_series_b_current_shares+'Pro-Forma'!AE41-class_series_c_current_shares+'Pro-Forma'!AG41-class_series_d_current_shares+'Pro-Forma'!AI41-class_series_e_current_shares -> 43677.638 | AK41: =note_a_cap_usd/(pre_f_fd_total+'Pro-Forma'!S41+'Pro-Forma'!AJ41+'Pro-Forma'!U41) -> 26.778553 | AL41: ='Pro-Forma'!V41*(const_one-note_a_discount) -> 30.102798 | AM41: =MIN('Pro-Forma'!AK41,'Pro-Forma'!AL41) -> 26.778553 | AN41: =note_a_principal_usd/'Pro-Forma'!AM41 -> 186716.59 | AO41: =note_b_cap_usd/(pre_f_fd_total+'Pro-Forma'!S41+'Pro-Forma'!AJ41+'Pro-Forma'!T41) -> 42.739338 | AP41: ='Pro-Forma'!V41*(const_one-note_b_discount) -> 31.984223 | AQ41: =MIN('Pro-Forma'!AO41,'Pro-Forma'!AP41) -> 31.984223 | AR41: =note_b_principal_usd/'Pro-Forma'!AQ41 -> 93796.243 | AS41: =pre_f_fd_total+'Pro-Forma'!S41+'Pro-Forma'!W41+'Pro-Forma'!AN41+'Pro-Forma'!AR41+'Pro-Forma'!AJ41 -> 38327302 | AT41: =MAX(const_zero,esop_refresh_target_post_f*'Pro-Forma'!AS41-pre_f_option_pool_total) -> 587882.23
A42: =Assumptions!$A$54 -> F1 | B42: =Assumptions!$C$54 -> 4000000 | C42: =B42/founder_common_total -> 0.5 | D42: =$B$38*C42 -> 234490.61 | E42: =B42-D42 -> 3765509.4 | R42: ='Pro-Forma'!R41+const_one -> 38 | S42: ='Pro-Forma'!AT41 -> 587882.23 | T42: ='Pro-Forma'!AN41 -> 186716.59 | U42: ='Pro-Forma'!AR41 -> 93796.243 | V42: =series_f_pre_money_usd/(pre_f_fd_total+'Pro-Forma'!S42) -> 37.628498 | W42: =series_f_primary_raise_usd/'Pro-Forma'!V42 -> 797268.07 | X42: =IF('Pro-Forma'!V42<class_seed_ocp,class_seed_ocp*(ad_pre_f_broad_based_fd+series_f_primary_raise_usd/class_seed_ocp)/(ad_pre_f_broad_based_fd+series_f_primary_raise_usd/'Pro-Forma'!V42),class_seed_ocp) -> 1 | Y42: =class_seed_original_shares*class_seed_issue_pps/'Pro-Forma'!X42 -> 5000000 | Z42: =IF('Pro-Forma'!V42<class_series_a_ocp,class_series_a_ocp*(ad_pre_f_broad_based_fd+series_f_primary_raise_usd/class_series_a_ocp)/(ad_pre_f_broad_based_fd+series_f_primary_raise_usd/'Pro-Forma'!V42),class_series_a_ocp) -> 3 | AA42: =class_series_a_original_shares*class_series_a_issue_pps/'Pro-Forma'!Z42 -> 5000000 | AB42: =IF('Pro-Forma'!V42<class_series_b_ocp,class_series_b_ocp*(ad_pre_f_broad_based_fd+series_f_primary_raise_usd/class_series_b_ocp)/(ad_pre_f_broad_based_fd+series_f_primary_raise_usd/'Pro-Forma'!V42),class_series_b_ocp) -> 10 | AC42: =class_series_b_original_shares*class_series_b_issue_pps/'Pro-Forma'!AB42 -> 3000000 | AD42: =IF('Pro-Forma'!V42<class_series_c_ocp,class_series_c_ocp*(ad_pre_f_broad_based_fd+series_f_primary_raise_usd/class_series_c_ocp)/(ad_pre_f_broad_based_fd+series_f_primary_raise_usd/'Pro-Forma'!V42),class_series_c_ocp) -> 25 | AE42: =class_series_c_original_shares*class_series_c_issue_pps/'Pro-Forma'!AD42 -> 2400000 | AF42: =IF('Pro-Forma'!V42<class_series_d_ocp,class_series_d_ocp*(ad_pre_f_broad_based_fd+series_f_primary_raise_usd/class_series_d_ocp)/(ad_pre_f_broad_based_fd+series_f_primary_raise_usd/'Pro-Forma'!V42),class_series_d_ocp) -> 57.681736 | AG42: =class_series_d_original_shares*class_series_d_issue_pps/'Pro-Forma'!AF42 -> 1733651.4 | AH42: =IF('Pro-Forma'!V42<class_series_e_ocp,class_series_e_ocp*(ad_pre_f_broad_based_fd+series_f_primary_raise_usd/class_series_e_ocp)/(ad_pre_f_broad_based_fd+series_f_primary_raise_usd/'Pro-Forma'!V42),class_series_e_ocp) -> 48.912626 | AI42: =class_series_e_original_shares*class_series_e_issue_pps/'Pro-Forma'!AH42 -> 6133320.3 | AJ42: ='Pro-Forma'!Y42-class_seed_current_shares+'Pro-Forma'!AA42-class_series_a_current_shares+'Pro-Forma'!AC42-class_series_b_current_shares+'Pro-Forma'!AE42-class_series_c_current_shares+'Pro-Forma'!AG42-class_series_d_current_shares+'Pro-Forma'!AI42-class_series_e_current_shares -> 43677.638 | AK42: =note_a_cap_usd/(pre_f_fd_total+'Pro-Forma'!S42+'Pro-Forma'!AJ42+'Pro-Forma'!U42) -> 26.778553 | AL42: ='Pro-Forma'!V42*(const_one-note_a_discount) -> 30.102798 | AM42: =MIN('Pro-Forma'!AK42,'Pro-Forma'!AL42) -> 26.778553 | AN42: =note_a_principal_usd/'Pro-Forma'!AM42 -> 186716.59 | AO42: =note_b_cap_usd/(pre_f_fd_total+'Pro-Forma'!S42+'Pro-Forma'!AJ42+'Pro-Forma'!T42) -> 42.739338 | AP42: ='Pro-Forma'!V42*(const_one-note_b_discount) -> 31.984223 | AQ42: =MIN('Pro-Forma'!AO42,'Pro-Forma'!AP42) -> 31.984223 | AR42: =note_b_principal_usd/'Pro-Forma'!AQ42 -> 93796.243 | AS42: =pre_f_fd_total+'Pro-Forma'!S42+'Pro-Forma'!W42+'Pro-Forma'!AN42+'Pro-Forma'!AR42+'Pro-Forma'!AJ42 -> 38327302 | AT42: =MAX(const_zero,esop_refresh_target_post_f*'Pro-Forma'!AS42-pre_f_option_pool_total) -> 587882.23
A43: =Assumptions!$A$55 -> F2 | B43: =Assumptions!$C$55 -> 2500000 | C43: =B43/founder_common_total -> 0.3125 | D43: =$B$38*C43 -> 146556.63 | E43: =B43-D43 -> 2353443.4 | R43: ='Pro-Forma'!R42+const_one -> 39 | S43: ='Pro-Forma'!AT42 -> 587882.23 | T43: ='Pro-Forma'!AN42 -> 186716.59 | U43: ='Pro-Forma'!AR42 -> 93796.243 | V43: =series_f_pre_money_usd/(pre_f_fd_total+'Pro-Forma'!S43) -> 37.628498 | W43: =series_f_primary_raise_usd/'Pro-Forma'!V43 -> 797268.07 | X43: =IF('Pro-Forma'!V43<class_seed_ocp,class_seed_ocp*(ad_pre_f_broad_based_fd+series_f_primary_raise_usd/class_seed_ocp)/(ad_pre_f_broad_based_fd+series_f_primary_raise_usd/'Pro-Forma'!V43),class_seed_ocp) -> 1 | Y43: =class_seed_original_shares*class_seed_issue_pps/'Pro-Forma'!X43 -> 5000000 | Z43: =IF('Pro-Forma'!V43<class_series_a_ocp,class_series_a_ocp*(ad_pre_f_broad_based_fd+series_f_primary_raise_usd/class_series_a_ocp)/(ad_pre_f_broad_based_fd+series_f_primary_raise_usd/'Pro-Forma'!V43),class_series_a_ocp) -> 3 | AA43: =class_series_a_original_shares*class_series_a_issue_pps/'Pro-Forma'!Z43 -> 5000000 | AB43: =IF('Pro-Forma'!V43<class_series_b_ocp,class_series_b_ocp*(ad_pre_f_broad_based_fd+series_f_primary_raise_usd/class_series_b_ocp)/(ad_pre_f_broad_based_fd+series_f_primary_raise_usd/'Pro-Forma'!V43),class_series_b_ocp) -> 10 | AC43: =class_series_b_original_shares*class_series_b_issue_pps/'Pro-Forma'!AB43 -> 3000000 | AD43: =IF('Pro-Forma'!V43<class_series_c_ocp,class_series_c_ocp*(ad_pre_f_broad_based_fd+series_f_primary_raise_usd/class_series_c_ocp)/(ad_pre_f_broad_based_fd+series_f_primary_raise_usd/'Pro-Forma'!V43),class_series_c_ocp) -> 25 | AE43: =class_series_c_original_shares*class_series_c_issue_pps/'Pro-Forma'!AD43 -> 2400000 | AF43: =IF('Pro-Forma'!V43<class_series_d_ocp,class_series_d_ocp*(ad_pre_f_broad_based_fd+series_f_primary_raise_usd/class_series_d_ocp)/(ad_pre_f_broad_based_fd+series_f_primary_raise_usd/'Pro-Forma'!V43),class_series_d_ocp) -> 57.681736 | AG43: =class_series_d_original_shares*class_series_d_issue_pps/'Pro-Forma'!AF43 -> 1733651.4 | AH43: =IF('Pro-Forma'!V43<class_series_e_ocp,class_series_e_ocp*(ad_pre_f_broad_based_fd+series_f_primary_raise_usd/class_series_e_ocp)/(ad_pre_f_broad_based_fd+series_f_primary_raise_usd/'Pro-Forma'!V43),class_series_e_ocp) -> 48.912626 | AI43: =class_series_e_original_shares*class_series_e_issue_pps/'Pro-Forma'!AH43 -> 6133320.3 | AJ43: ='Pro-Forma'!Y43-class_seed_current_shares+'Pro-Forma'!AA43-class_series_a_current_shares+'Pro-Forma'!AC43-class_series_b_current_shares+'Pro-Forma'!AE43-class_series_c_current_shares+'Pro-Forma'!AG43-class_series_d_current_shares+'Pro-Forma'!AI43-class_series_e_current_shares -> 43677.638 | AK43: =note_a_cap_usd/(pre_f_fd_total+'Pro-Forma'!S43+'Pro-Forma'!AJ43+'Pro-Forma'!U43) -> 26.778553 | AL43: ='Pro-Forma'!V43*(const_one-note_a_discount) -> 30.102798 | AM43: =MIN('Pro-Forma'!AK43,'Pro-Forma'!AL43) -> 26.778553 | AN43: =note_a_principal_usd/'Pro-Forma'!AM43 -> 186716.59 | AO43: =note_b_cap_usd/(pre_f_fd_total+'Pro-Forma'!S43+'Pro-Forma'!AJ43+'Pro-Forma'!T43) -> 42.739338 | AP43: ='Pro-Forma'!V43*(const_one-note_b_discount) -> 31.984223 | AQ43: =MIN('Pro-Forma'!AO43,'Pro-Forma'!AP43) -> 31.984223 | AR43: =note_b_principal_usd/'Pro-Forma'!AQ43 -> 93796.243 | AS43: =pre_f_fd_total+'Pro-Forma'!S43+'Pro-Forma'!W43+'Pro-Forma'!AN43+'Pro-Forma'!AR43+'Pro-Forma'!AJ43 -> 38327302 | AT43: =MAX(const_zero,esop_refresh_target_post_f*'Pro-Forma'!AS43-pre_f_option_pool_total) -> 587882.23
A44: =Assumptions!$A$56 -> F3 | B44: =Assumptions!$C$56 -> 1500000 | C44: =B44/founder_common_total -> 0.1875 | D44: =$B$38*C44 -> 87933.978 | E44: =B44-D44 -> 1412066 | R44: ='Pro-Forma'!R43+const_one -> 40 | S44: ='Pro-Forma'!AT43 -> 587882.23 | T44: ='Pro-Forma'!AN43 -> 186716.59 | U44: ='Pro-Forma'!AR43 -> 93796.243 | V44: =series_f_pre_money_usd/(pre_f_fd_total+'Pro-Forma'!S44) -> 37.628498 | W44: =series_f_primary_raise_usd/'Pro-Forma'!V44 -> 797268.07 | X44: =IF('Pro-Forma'!V44<class_seed_ocp,class_seed_ocp*(ad_pre_f_broad_based_fd+series_f_primary_raise_usd/class_seed_ocp)/(ad_pre_f_broad_based_fd+series_f_primary_raise_usd/'Pro-Forma'!V44),class_seed_ocp) -> 1 | Y44: =class_seed_original_shares*class_seed_issue_pps/'Pro-Forma'!X44 -> 5000000 | Z44: =IF('Pro-Forma'!V44<class_series_a_ocp,class_series_a_ocp*(ad_pre_f_broad_based_fd+series_f_primary_raise_usd/class_series_a_ocp)/(ad_pre_f_broad_based_fd+series_f_primary_raise_usd/'Pro-Forma'!V44),class_series_a_ocp) -> 3 | AA44: =class_series_a_original_shares*class_series_a_issue_pps/'Pro-Forma'!Z44 -> 5000000 | AB44: =IF('Pro-Forma'!V44<class_series_b_ocp,class_series_b_ocp*(ad_pre_f_broad_based_fd+series_f_primary_raise_usd/class_series_b_ocp)/(ad_pre_f_broad_based_fd+series_f_primary_raise_usd/'Pro-Forma'!V44),class_series_b_ocp) -> 10 | AC44: =class_series_b_original_shares*class_series_b_issue_pps/'Pro-Forma'!AB44 -> 3000000 | AD44: =IF('Pro-Forma'!V44<class_series_c_ocp,class_series_c_ocp*(ad_pre_f_broad_based_fd+series_f_primary_raise_usd/class_series_c_ocp)/(ad_pre_f_broad_based_fd+series_f_primary_raise_usd/'Pro-Forma'!V44),class_series_c_ocp) -> 25 | AE44: =class_series_c_original_shares*class_series_c_issue_pps/'Pro-Forma'!AD44 -> 2400000 | AF44: =IF('Pro-Forma'!V44<class_series_d_ocp,class_series_d_ocp*(ad_pre_f_broad_based_fd+series_f_primary_raise_usd/class_series_d_ocp)/(ad_pre_f_broad_based_fd+series_f_primary_raise_usd/'Pro-Forma'!V44),class_series_d_ocp) -> 57.681736 | AG44: =class_series_d_original_shares*class_series_d_issue_pps/'Pro-Forma'!AF44 -> 1733651.4 | AH44: =IF('Pro-Forma'!V44<class_series_e_ocp,class_series_e_ocp*(ad_pre_f_broad_based_fd+series_f_primary_raise_usd/class_series_e_ocp)/(ad_pre_f_broad_based_fd+series_f_primary_raise_usd/'Pro-Forma'!V44),class_series_e_ocp) -> 48.912626 | AI44: =class_series_e_original_shares*class_series_e_issue_pps/'Pro-Forma'!AH44 -> 6133320.3 | AJ44: ='Pro-Forma'!Y44-class_seed_current_shares+'Pro-Forma'!AA44-class_series_a_current_shares+'Pro-Forma'!AC44-class_series_b_current_shares+'Pro-Forma'!AE44-class_series_c_current_shares+'Pro-Forma'!AG44-class_series_d_current_shares+'Pro-Forma'!AI44-class_series_e_current_shares -> 43677.638 | AK44: =note_a_cap_usd/(pre_f_fd_total+'Pro-Forma'!S44+'Pro-Forma'!AJ44+'Pro-Forma'!U44) -> 26.778553 | AL44: ='Pro-Forma'!V44*(const_one-note_a_discount) -> 30.102798 | AM44: =MIN('Pro-Forma'!AK44,'Pro-Forma'!AL44) -> 26.778553 | AN44: =note_a_principal_usd/'Pro-Forma'!AM44 -> 186716.59 | AO44: =note_b_cap_usd/(pre_f_fd_total+'Pro-Forma'!S44+'Pro-Forma'!AJ44+'Pro-Forma'!T44) -> 42.739338 | AP44: ='Pro-Forma'!V44*(const_one-note_b_discount) -> 31.984223 | AQ44: =MIN('Pro-Forma'!AO44,'Pro-Forma'!AP44) -> 31.984223 | AR44: =note_b_principal_usd/'Pro-Forma'!AQ44 -> 93796.243 | AS44: =pre_f_fd_total+'Pro-Forma'!S44+'Pro-Forma'!W44+'Pro-Forma'!AN44+'Pro-Forma'!AR44+'Pro-Forma'!AJ44 -> 38327302 | AT44: =MAX(const_zero,esop_refresh_target_post_f*'Pro-Forma'!AS44-pre_f_option_pool_total) -> 587882.23
R45: ='Pro-Forma'!R44+const_one -> 41 | S45: ='Pro-Forma'!AT44 -> 587882.23 | T45: ='Pro-Forma'!AN44 -> 186716.59 | U45: ='Pro-Forma'!AR44 -> 93796.243 | V45: =series_f_pre_money_usd/(pre_f_fd_total+'Pro-Forma'!S45) -> 37.628498 | W45: =series_f_primary_raise_usd/'Pro-Forma'!V45 -> 797268.07 | X45: =IF('Pro-Forma'!V45<class_seed_ocp,class_seed_ocp*(ad_pre_f_broad_based_fd+series_f_primary_raise_usd/class_seed_ocp)/(ad_pre_f_broad_based_fd+series_f_primary_raise_usd/'Pro-Forma'!V45),class_seed_ocp) -> 1 | Y45: =class_seed_original_shares*class_seed_issue_pps/'Pro-Forma'!X45 -> 5000000 | Z45: =IF('Pro-Forma'!V45<class_series_a_ocp,class_series_a_ocp*(ad_pre_f_broad_based_fd+series_f_primary_raise_usd/class_series_a_ocp)/(ad_pre_f_broad_based_fd+series_f_primary_raise_usd/'Pro-Forma'!V45),class_series_a_ocp) -> 3 | AA45: =class_series_a_original_shares*class_series_a_issue_pps/'Pro-Forma'!Z45 -> 5000000 | AB45: =IF('Pro-Forma'!V45<class_series_b_ocp,class_series_b_ocp*(ad_pre_f_broad_based_fd+series_f_primary_raise_usd/class_series_b_ocp)/(ad_pre_f_broad_based_fd+series_f_primary_raise_usd/'Pro-Forma'!V45),class_series_b_ocp) -> 10 | AC45: =class_series_b_original_shares*class_series_b_issue_pps/'Pro-Forma'!AB45 -> 3000000 | AD45: =IF('Pro-Forma'!V45<class_series_c_ocp,class_series_c_ocp*(ad_pre_f_broad_based_fd+series_f_primary_raise_usd/class_series_c_ocp)/(ad_pre_f_broad_based_fd+series_f_primary_raise_usd/'Pro-Forma'!V45),class_series_c_ocp) -> 25 | AE45: =class_series_c_original_shares*class_series_c_issue_pps/'Pro-Forma'!AD45 -> 2400000 | AF45: =IF('Pro-Forma'!V45<class_series_d_ocp,class_series_d_ocp*(ad_pre_f_broad_based_fd+series_f_primary_raise_usd/class_series_d_ocp)/(ad_pre_f_broad_based_fd+series_f_primary_raise_usd/'Pro-Forma'!V45),class_series_d_ocp) -> 57.681736 | AG45: =class_series_d_original_shares*class_series_d_issue_pps/'Pro-Forma'!AF45 -> 1733651.4 | AH45: =IF('Pro-Forma'!V45<class_series_e_ocp,class_series_e_ocp*(ad_pre_f_broad_based_fd+series_f_primary_raise_usd/class_series_e_ocp)/(ad_pre_f_broad_based_fd+series_f_primary_raise_usd/'Pro-Forma'!V45),class_series_e_ocp) -> 48.912626 | AI45: =class_series_e_original_shares*class_series_e_issue_pps/'Pro-Forma'!AH45 -> 6133320.3 | AJ45: ='Pro-Forma'!Y45-class_seed_current_shares+'Pro-Forma'!AA45-class_series_a_current_shares+'Pro-Forma'!AC45-class_series_b_current_shares+'Pro-Forma'!AE45-class_series_c_current_shares+'Pro-Forma'!AG45-class_series_d_current_shares+'Pro-Forma'!AI45-class_series_e_current_shares -> 43677.638 | AK45: =note_a_cap_usd/(pre_f_fd_total+'Pro-Forma'!S45+'Pro-Forma'!AJ45+'Pro-Forma'!U45) -> 26.778553 | AL45: ='Pro-Forma'!V45*(const_one-note_a_discount) -> 30.102798 | AM45: =MIN('Pro-Forma'!AK45,'Pro-Forma'!AL45) -> 26.778553 | AN45: =note_a_principal_usd/'Pro-Forma'!AM45 -> 186716.59 | AO45: =note_b_cap_usd/(pre_f_fd_total+'Pro-Forma'!S45+'Pro-Forma'!AJ45+'Pro-Forma'!T45) -> 42.739338 | AP45: ='Pro-Forma'!V45*(const_one-note_b_discount) -> 31.984223 | AQ45: =MIN('Pro-Forma'!AO45,'Pro-Forma'!AP45) -> 31.984223 | AR45: =note_b_principal_usd/'Pro-Forma'!AQ45 -> 93796.243 | AS45: =pre_f_fd_total+'Pro-Forma'!S45+'Pro-Forma'!W45+'Pro-Forma'!AN45+'Pro-Forma'!AR45+'Pro-Forma'!AJ45 -> 38327302 | AT45: =MAX(const_zero,esop_refresh_target_post_f*'Pro-Forma'!AS45-pre_f_option_pool_total) -> 587882.23
R46: ='Pro-Forma'!R45+const_one -> 42 | S46: ='Pro-Forma'!AT45 -> 587882.23 | T46: ='Pro-Forma'!AN45 -> 186716.59 | U46: ='Pro-Forma'!AR45 -> 93796.243 | V46: =series_f_pre_money_usd/(pre_f_fd_total+'Pro-Forma'!S46) -> 37.628498 | W46: =series_f_primary_raise_usd/'Pro-Forma'!V46 -> 797268.07 | X46: =IF('Pro-Forma'!V46<class_seed_ocp,class_seed_ocp*(ad_pre_f_broad_based_fd+series_f_primary_raise_usd/class_seed_ocp)/(ad_pre_f_broad_based_fd+series_f_primary_raise_usd/'Pro-Forma'!V46),class_seed_ocp) -> 1 | Y46: =class_seed_original_shares*class_seed_issue_pps/'Pro-Forma'!X46 -> 5000000 | Z46: =IF('Pro-Forma'!V46<class_series_a_ocp,class_series_a_ocp*(ad_pre_f_broad_based_fd+series_f_primary_raise_usd/class_series_a_ocp)/(ad_pre_f_broad_based_fd+series_f_primary_raise_usd/'Pro-Forma'!V46),class_series_a_ocp) -> 3 | AA46: =class_series_a_original_shares*class_series_a_issue_pps/'Pro-Forma'!Z46 -> 5000000 | AB46: =IF('Pro-Forma'!V46<class_series_b_ocp,class_series_b_ocp*(ad_pre_f_broad_based_fd+series_f_primary_raise_usd/class_series_b_ocp)/(ad_pre_f_broad_based_fd+series_f_primary_raise_usd/'Pro-Forma'!V46),class_series_b_ocp) -> 10 | AC46: =class_series_b_original_shares*class_series_b_issue_pps/'Pro-Forma'!AB46 -> 3000000 | AD46: =IF('Pro-Forma'!V46<class_series_c_ocp,class_series_c_ocp*(ad_pre_f_broad_based_fd+series_f_primary_raise_usd/class_series_c_ocp)/(ad_pre_f_broad_based_fd+series_f_primary_raise_usd/'Pro-Forma'!V46),class_series_c_ocp) -> 25 | AE46: =class_series_c_original_shares*class_series_c_issue_pps/'Pro-Forma'!AD46 -> 2400000 | AF46: =IF('Pro-Forma'!V46<class_series_d_ocp,class_series_d_ocp*(ad_pre_f_broad_based_fd+series_f_primary_raise_usd/class_series_d_ocp)/(ad_pre_f_broad_based_fd+series_f_primary_raise_usd/'Pro-Forma'!V46),class_series_d_ocp) -> 57.681736 | AG46: =class_series_d_original_shares*class_series_d_issue_pps/'Pro-Forma'!AF46 -> 1733651.4 | AH46: =IF('Pro-Forma'!V46<class_series_e_ocp,class_series_e_ocp*(ad_pre_f_broad_based_fd+series_f_primary_raise_usd/class_series_e_ocp)/(ad_pre_f_broad_based_fd+series_f_primary_raise_usd/'Pro-Forma'!V46),class_series_e_ocp) -> 48.912626 | AI46: =class_series_e_original_shares*class_series_e_issue_pps/'Pro-Forma'!AH46 -> 6133320.3 | AJ46: ='Pro-Forma'!Y46-class_seed_current_shares+'Pro-Forma'!AA46-class_series_a_current_shares+'Pro-Forma'!AC46-class_series_b_current_shares+'Pro-Forma'!AE46-class_series_c_current_shares+'Pro-Forma'!AG46-class_series_d_current_shares+'Pro-Forma'!AI46-class_series_e_current_shares -> 43677.638 | AK46: =note_a_cap_usd/(pre_f_fd_total+'Pro-Forma'!S46+'Pro-Forma'!AJ46+'Pro-Forma'!U46) -> 26.778553 | AL46: ='Pro-Forma'!V46*(const_one-note_a_discount) -> 30.102798 | AM46: =MIN('Pro-Forma'!AK46,'Pro-Forma'!AL46) -> 26.778553 | AN46: =note_a_principal_usd/'Pro-Forma'!AM46 -> 186716.59 | AO46: =note_b_cap_usd/(pre_f_fd_total+'Pro-Forma'!S46+'Pro-Forma'!AJ46+'Pro-Forma'!T46) -> 42.739338 | AP46: ='Pro-Forma'!V46*(const_one-note_b_discount) -> 31.984223 | AQ46: =MIN('Pro-Forma'!AO46,'Pro-Forma'!AP46) -> 31.984223 | AR46: =note_b_principal_usd/'Pro-Forma'!AQ46 -> 93796.243 | AS46: =pre_f_fd_total+'Pro-Forma'!S46+'Pro-Forma'!W46+'Pro-Forma'!AN46+'Pro-Forma'!AR46+'Pro-Forma'!AJ46 -> 38327302 | AT46: =MAX(const_zero,esop_refresh_target_post_f*'Pro-Forma'!AS46-pre_f_option_pool_total) -> 587882.23
R47: ='Pro-Forma'!R46+const_one -> 43 | S47: ='Pro-Forma'!AT46 -> 587882.23 | T47: ='Pro-Forma'!AN46 -> 186716.59 | U47: ='Pro-Forma'!AR46 -> 93796.243 | V47: =series_f_pre_money_usd/(pre_f_fd_total+'Pro-Forma'!S47) -> 37.628498 | W47: =series_f_primary_raise_usd/'Pro-Forma'!V47 -> 797268.07 | X47: =IF('Pro-Forma'!V47<class_seed_ocp,class_seed_ocp*(ad_pre_f_broad_based_fd+series_f_primary_raise_usd/class_seed_ocp)/(ad_pre_f_broad_based_fd+series_f_primary_raise_usd/'Pro-Forma'!V47),class_seed_ocp) -> 1 | Y47: =class_seed_original_shares*class_seed_issue_pps/'Pro-Forma'!X47 -> 5000000 | Z47: =IF('Pro-Forma'!V47<class_series_a_ocp,class_series_a_ocp*(ad_pre_f_broad_based_fd+series_f_primary_raise_usd/class_series_a_ocp)/(ad_pre_f_broad_based_fd+series_f_primary_raise_usd/'Pro-Forma'!V47),class_series_a_ocp) -> 3 | AA47: =class_series_a_original_shares*class_series_a_issue_pps/'Pro-Forma'!Z47 -> 5000000 | AB47: =IF('Pro-Forma'!V47<class_series_b_ocp,class_series_b_ocp*(ad_pre_f_broad_based_fd+series_f_primary_raise_usd/class_series_b_ocp)/(ad_pre_f_broad_based_fd+series_f_primary_raise_usd/'Pro-Forma'!V47),class_series_b_ocp) -> 10 | AC47: =class_series_b_original_shares*class_series_b_issue_pps/'Pro-Forma'!AB47 -> 3000000 | AD47: =IF('Pro-Forma'!V47<class_series_c_ocp,class_series_c_ocp*(ad_pre_f_broad_based_fd+series_f_primary_raise_usd/class_series_c_ocp)/(ad_pre_f_broad_based_fd+series_f_primary_raise_usd/'Pro-Forma'!V47),class_series_c_ocp) -> 25 | AE47: =class_series_c_original_shares*class_series_c_issue_pps/'Pro-Forma'!AD47 -> 2400000 | AF47: =IF('Pro-Forma'!V47<class_series_d_ocp,class_series_d_ocp*(ad_pre_f_broad_based_fd+series_f_primary_raise_usd/class_series_d_ocp)/(ad_pre_f_broad_based_fd+series_f_primary_raise_usd/'Pro-Forma'!V47),class_series_d_ocp) -> 57.681736 | AG47: =class_series_d_original_shares*class_series_d_issue_pps/'Pro-Forma'!AF47 -> 1733651.4 | AH47: =IF('Pro-Forma'!V47<class_series_e_ocp,class_series_e_ocp*(ad_pre_f_broad_based_fd+series_f_primary_raise_usd/class_series_e_ocp)/(ad_pre_f_broad_based_fd+series_f_primary_raise_usd/'Pro-Forma'!V47),class_series_e_ocp) -> 48.912626 | AI47: =class_series_e_original_shares*class_series_e_issue_pps/'Pro-Forma'!AH47 -> 6133320.3 | AJ47: ='Pro-Forma'!Y47-class_seed_current_shares+'Pro-Forma'!AA47-class_series_a_current_shares+'Pro-Forma'!AC47-class_series_b_current_shares+'Pro-Forma'!AE47-class_series_c_current_shares+'Pro-Forma'!AG47-class_series_d_current_shares+'Pro-Forma'!AI47-class_series_e_current_shares -> 43677.638 | AK47: =note_a_cap_usd/(pre_f_fd_total+'Pro-Forma'!S47+'Pro-Forma'!AJ47+'Pro-Forma'!U47) -> 26.778553 | AL47: ='Pro-Forma'!V47*(const_one-note_a_discount) -> 30.102798 | AM47: =MIN('Pro-Forma'!AK47,'Pro-Forma'!AL47) -> 26.778553 | AN47: =note_a_principal_usd/'Pro-Forma'!AM47 -> 186716.59 | AO47: =note_b_cap_usd/(pre_f_fd_total+'Pro-Forma'!S47+'Pro-Forma'!AJ47+'Pro-Forma'!T47) -> 42.739338 | AP47: ='Pro-Forma'!V47*(const_one-note_b_discount) -> 31.984223 | AQ47: =MIN('Pro-Forma'!AO47,'Pro-Forma'!AP47) -> 31.984223 | AR47: =note_b_principal_usd/'Pro-Forma'!AQ47 -> 93796.243 | AS47: =pre_f_fd_total+'Pro-Forma'!S47+'Pro-Forma'!W47+'Pro-Forma'!AN47+'Pro-Forma'!AR47+'Pro-Forma'!AJ47 -> 38327302 | AT47: =MAX(const_zero,esop_refresh_target_post_f*'Pro-Forma'!AS47-pre_f_option_pool_total) -> 587882.23
A48: =lbl_cap_table -> Post-F Cap Table | R48: ='Pro-Forma'!R47+const_one -> 44 | S48: ='Pro-Forma'!AT47 -> 587882.23 | T48: ='Pro-Forma'!AN47 -> 186716.59 | U48: ='Pro-Forma'!AR47 -> 93796.243 | V48: =series_f_pre_money_usd/(pre_f_fd_total+'Pro-Forma'!S48) -> 37.628498 | W48: =series_f_primary_raise_usd/'Pro-Forma'!V48 -> 797268.07 | X48: =IF('Pro-Forma'!V48<class_seed_ocp,class_seed_ocp*(ad_pre_f_broad_based_fd+series_f_primary_raise_usd/class_seed_ocp)/(ad_pre_f_broad_based_fd+series_f_primary_raise_usd/'Pro-Forma'!V48),class_seed_ocp) -> 1 | Y48: =class_seed_original_shares*class_seed_issue_pps/'Pro-Forma'!X48 -> 5000000 | Z48: =IF('Pro-Forma'!V48<class_series_a_ocp,class_series_a_ocp*(ad_pre_f_broad_based_fd+series_f_primary_raise_usd/class_series_a_ocp)/(ad_pre_f_broad_based_fd+series_f_primary_raise_usd/'Pro-Forma'!V48),class_series_a_ocp) -> 3 | AA48: =class_series_a_original_shares*class_series_a_issue_pps/'Pro-Forma'!Z48 -> 5000000 | AB48: =IF('Pro-Forma'!V48<class_series_b_ocp,class_series_b_ocp*(ad_pre_f_broad_based_fd+series_f_primary_raise_usd/class_series_b_ocp)/(ad_pre_f_broad_based_fd+series_f_primary_raise_usd/'Pro-Forma'!V48),class_series_b_ocp) -> 10 | AC48: =class_series_b_original_shares*class_series_b_issue_pps/'Pro-Forma'!AB48 -> 3000000 | AD48: =IF('Pro-Forma'!V48<class_series_c_ocp,class_series_c_ocp*(ad_pre_f_broad_based_fd+series_f_primary_raise_usd/class_series_c_ocp)/(ad_pre_f_broad_based_fd+series_f_primary_raise_usd/'Pro-Forma'!V48),class_series_c_ocp) -> 25 | AE48: =class_series_c_original_shares*class_series_c_issue_pps/'Pro-Forma'!AD48 -> 2400000 | AF48: =IF('Pro-Forma'!V48<class_series_d_ocp,class_series_d_ocp*(ad_pre_f_broad_based_fd+series_f_primary_raise_usd/class_series_d_ocp)/(ad_pre_f_broad_based_fd+series_f_primary_raise_usd/'Pro-Forma'!V48),class_series_d_ocp) -> 57.681736 | AG48: =class_series_d_original_shares*class_series_d_issue_pps/'Pro-Forma'!AF48 -> 1733651.4 | AH48: =IF('Pro-Forma'!V48<class_series_e_ocp,class_series_e_ocp*(ad_pre_f_broad_based_fd+series_f_primary_raise_usd/class_series_e_ocp)/(ad_pre_f_broad_based_fd+series_f_primary_raise_usd/'Pro-Forma'!V48),class_series_e_ocp) -> 48.912626 | AI48: =class_series_e_original_shares*class_series_e_issue_pps/'Pro-Forma'!AH48 -> 6133320.3 | AJ48: ='Pro-Forma'!Y48-class_seed_current_shares+'Pro-Forma'!AA48-class_series_a_current_shares+'Pro-Forma'!AC48-class_series_b_current_shares+'Pro-Forma'!AE48-class_series_c_current_shares+'Pro-Forma'!AG48-class_series_d_current_shares+'Pro-Forma'!AI48-class_series_e_current_shares -> 43677.638 | AK48: =note_a_cap_usd/(pre_f_fd_total+'Pro-Forma'!S48+'Pro-Forma'!AJ48+'Pro-Forma'!U48) -> 26.778553 | AL48: ='Pro-Forma'!V48*(const_one-note_a_discount) -> 30.102798 | AM48: =MIN('Pro-Forma'!AK48,'Pro-Forma'!AL48) -> 26.778553 | AN48: =note_a_principal_usd/'Pro-Forma'!AM48 -> 186716.59 | AO48: =note_b_cap_usd/(pre_f_fd_total+'Pro-Forma'!S48+'Pro-Forma'!AJ48+'Pro-Forma'!T48) -> 42.739338 | AP48: ='Pro-Forma'!V48*(const_one-note_b_discount) -> 31.984223 | AQ48: =MIN('Pro-Forma'!AO48,'Pro-Forma'!AP48) -> 31.984223 | AR48: =note_b_principal_usd/'Pro-Forma'!AQ48 -> 93796.243 | AS48: =pre_f_fd_total+'Pro-Forma'!S48+'Pro-Forma'!W48+'Pro-Forma'!AN48+'Pro-Forma'!AR48+'Pro-Forma'!AJ48 -> 38327302 | AT48: =MAX(const_zero,esop_refresh_target_post_f*'Pro-Forma'!AS48-pre_f_option_pool_total) -> 587882.23
R49: ='Pro-Forma'!R48+const_one -> 45 | S49: ='Pro-Forma'!AT48 -> 587882.23 | T49: ='Pro-Forma'!AN48 -> 186716.59 | U49: ='Pro-Forma'!AR48 -> 93796.243 | V49: =series_f_pre_money_usd/(pre_f_fd_total+'Pro-Forma'!S49) -> 37.628498 | W49: =series_f_primary_raise_usd/'Pro-Forma'!V49 -> 797268.07 | X49: =IF('Pro-Forma'!V49<class_seed_ocp,class_seed_ocp*(ad_pre_f_broad_based_fd+series_f_primary_raise_usd/class_seed_ocp)/(ad_pre_f_broad_based_fd+series_f_primary_raise_usd/'Pro-Forma'!V49),class_seed_ocp) -> 1 | Y49: =class_seed_original_shares*class_seed_issue_pps/'Pro-Forma'!X49 -> 5000000 | Z49: =IF('Pro-Forma'!V49<class_series_a_ocp,class_series_a_ocp*(ad_pre_f_broad_based_fd+series_f_primary_raise_usd/class_series_a_ocp)/(ad_pre_f_broad_based_fd+series_f_primary_raise_usd/'Pro-Forma'!V49),class_series_a_ocp) -> 3 | AA49: =class_series_a_original_shares*class_series_a_issue_pps/'Pro-Forma'!Z49 -> 5000000 | AB49: =IF('Pro-Forma'!V49<class_series_b_ocp,class_series_b_ocp*(ad_pre_f_broad_based_fd+series_f_primary_raise_usd/class_series_b_ocp)/(ad_pre_f_broad_based_fd+series_f_primary_raise_usd/'Pro-Forma'!V49),class_series_b_ocp) -> 10 | AC49: =class_series_b_original_shares*class_series_b_issue_pps/'Pro-Forma'!AB49 -> 3000000 | AD49: =IF('Pro-Forma'!V49<class_series_c_ocp,class_series_c_ocp*(ad_pre_f_broad_based_fd+series_f_primary_raise_usd/class_series_c_ocp)/(ad_pre_f_broad_based_fd+series_f_primary_raise_usd/'Pro-Forma'!V49),class_series_c_ocp) -> 25 | AE49: =class_series_c_original_shares*class_series_c_issue_pps/'Pro-Forma'!AD49 -> 2400000 | AF49: =IF('Pro-Forma'!V49<class_series_d_ocp,class_series_d_ocp*(ad_pre_f_broad_based_fd+series_f_primary_raise_usd/class_series_d_ocp)/(ad_pre_f_broad_based_fd+series_f_primary_raise_usd/'Pro-Forma'!V49),class_series_d_ocp) -> 57.681736 | AG49: =class_series_d_original_shares*class_series_d_issue_pps/'Pro-Forma'!AF49 -> 1733651.4 | AH49: =IF('Pro-Forma'!V49<class_series_e_ocp,class_series_e_ocp*(ad_pre_f_broad_based_fd+series_f_primary_raise_usd/class_series_e_ocp)/(ad_pre_f_broad_based_fd+series_f_primary_raise_usd/'Pro-Forma'!V49),class_series_e_ocp) -> 48.912626 | AI49: =class_series_e_original_shares*class_series_e_issue_pps/'Pro-Forma'!AH49 -> 6133320.3 | AJ49: ='Pro-Forma'!Y49-class_seed_current_shares+'Pro-Forma'!AA49-class_series_a_current_shares+'Pro-Forma'!AC49-class_series_b_current_shares+'Pro-Forma'!AE49-class_series_c_current_shares+'Pro-Forma'!AG49-class_series_d_current_shares+'Pro-Forma'!AI49-class_series_e_current_shares -> 43677.638 | AK49: =note_a_cap_usd/(pre_f_fd_total+'Pro-Forma'!S49+'Pro-Forma'!AJ49+'Pro-Forma'!U49) -> 26.778553 | AL49: ='Pro-Forma'!V49*(const_one-note_a_discount) -> 30.102798 | AM49: =MIN('Pro-Forma'!AK49,'Pro-Forma'!AL49) -> 26.778553 | AN49: =note_a_principal_usd/'Pro-Forma'!AM49 -> 186716.59 | AO49: =note_b_cap_usd/(pre_f_fd_total+'Pro-Forma'!S49+'Pro-Forma'!AJ49+'Pro-Forma'!T49) -> 42.739338 | AP49: ='Pro-Forma'!V49*(const_one-note_b_discount) -> 31.984223 | AQ49: =MIN('Pro-Forma'!AO49,'Pro-Forma'!AP49) -> 31.984223 | AR49: =note_b_principal_usd/'Pro-Forma'!AQ49 -> 93796.243 | AS49: =pre_f_fd_total+'Pro-Forma'!S49+'Pro-Forma'!W49+'Pro-Forma'!AN49+'Pro-Forma'!AR49+'Pro-Forma'!AJ49 -> 38327302 | AT49: =MAX(const_zero,esop_refresh_target_post_f*'Pro-Forma'!AS49-pre_f_option_pool_total) -> 587882.23
A50: =lbl_stakeholder_id -> Stakeholder ID | B50: =lbl_role -> Role | C50: =lbl_common_rsas -> Common + RSAs | D50: =lbl_seed -> Seed | E50: =lbl_series_a -> Series A | F50: =lbl_series_b -> Series B | G50: =lbl_series_c -> Series C | H50: =lbl_series_d -> Series D | I50: =lbl_series_e -> Series E | J50: =lbl_note_a -> Note A | K50: =lbl_note_b -> Note B | L50: =lbl_series_f -> Series F | M50: =lbl_issued_options -> Issued options | N50: =lbl_unissued_options -> Unissued options | O50: =lbl_total_fd -> Total FD shares | P50: =lbl_ownership_pct -> Ownership % | R50: ='Pro-Forma'!R49+const_one -> 46 | S50: ='Pro-Forma'!AT49 -> 587882.23 | T50: ='Pro-Forma'!AN49 -> 186716.59 | U50: ='Pro-Forma'!AR49 -> 93796.243 | V50: =series_f_pre_money_usd/(pre_f_fd_total+'Pro-Forma'!S50) -> 37.628498 | W50: =series_f_primary_raise_usd/'Pro-Forma'!V50 -> 797268.07 | X50: =IF('Pro-Forma'!V50<class_seed_ocp,class_seed_ocp*(ad_pre_f_broad_based_fd+series_f_primary_raise_usd/class_seed_ocp)/(ad_pre_f_broad_based_fd+series_f_primary_raise_usd/'Pro-Forma'!V50),class_seed_ocp) -> 1 | Y50: =class_seed_original_shares*class_seed_issue_pps/'Pro-Forma'!X50 -> 5000000 | Z50: =IF('Pro-Forma'!V50<class_series_a_ocp,class_series_a_ocp*(ad_pre_f_broad_based_fd+series_f_primary_raise_usd/class_series_a_ocp)/(ad_pre_f_broad_based_fd+series_f_primary_raise_usd/'Pro-Forma'!V50),class_series_a_ocp) -> 3 | AA50: =class_series_a_original_shares*class_series_a_issue_pps/'Pro-Forma'!Z50 -> 5000000 | AB50: =IF('Pro-Forma'!V50<class_series_b_ocp,class_series_b_ocp*(ad_pre_f_broad_based_fd+series_f_primary_raise_usd/class_series_b_ocp)/(ad_pre_f_broad_based_fd+series_f_primary_raise_usd/'Pro-Forma'!V50),class_series_b_ocp) -> 10 | AC50: =class_series_b_original_shares*class_series_b_issue_pps/'Pro-Forma'!AB50 -> 3000000 | AD50: =IF('Pro-Forma'!V50<class_series_c_ocp,class_series_c_ocp*(ad_pre_f_broad_based_fd+series_f_primary_raise_usd/class_series_c_ocp)/(ad_pre_f_broad_based_fd+series_f_primary_raise_usd/'Pro-Forma'!V50),class_series_c_ocp) -> 25 | AE50: =class_series_c_original_shares*class_series_c_issue_pps/'Pro-Forma'!AD50 -> 2400000 | AF50: =IF('Pro-Forma'!V50<class_series_d_ocp,class_series_d_ocp*(ad_pre_f_broad_based_fd+series_f_primary_raise_usd/class_series_d_ocp)/(ad_pre_f_broad_based_fd+series_f_primary_raise_usd/'Pro-Forma'!V50),class_series_d_ocp) -> 57.681736 | AG50: =class_series_d_original_shares*class_series_d_issue_pps/'Pro-Forma'!AF50 -> 1733651.4 | AH50: =IF('Pro-Forma'!V50<class_series_e_ocp,class_series_e_ocp*(ad_pre_f_broad_based_fd+series_f_primary_raise_usd/class_series_e_ocp)/(ad_pre_f_broad_based_fd+series_f_primary_raise_usd/'Pro-Forma'!V50),class_series_e_ocp) -> 48.912626 | AI50: =class_series_e_original_shares*class_series_e_issue_pps/'Pro-Forma'!AH50 -> 6133320.3 | AJ50: ='Pro-Forma'!Y50-class_seed_current_shares+'Pro-Forma'!AA50-class_series_a_current_shares+'Pro-Forma'!AC50-class_series_b_current_shares+'Pro-Forma'!AE50-class_series_c_current_shares+'Pro-Forma'!AG50-class_series_d_current_shares+'Pro-Forma'!AI50-class_series_e_current_shares -> 43677.638 | AK50: =note_a_cap_usd/(pre_f_fd_total+'Pro-Forma'!S50+'Pro-Forma'!AJ50+'Pro-Forma'!U50) -> 26.778553 | AL50: ='Pro-Forma'!V50*(const_one-note_a_discount) -> 30.102798 | AM50: =MIN('Pro-Forma'!AK50,'Pro-Forma'!AL50) -> 26.778553 | AN50: =note_a_principal_usd/'Pro-Forma'!AM50 -> 186716.59 | AO50: =note_b_cap_usd/(pre_f_fd_total+'Pro-Forma'!S50+'Pro-Forma'!AJ50+'Pro-Forma'!T50) -> 42.739338 | AP50: ='Pro-Forma'!V50*(const_one-note_b_discount) -> 31.984223 | AQ50: =MIN('Pro-Forma'!AO50,'Pro-Forma'!AP50) -> 31.984223 | AR50: =note_b_principal_usd/'Pro-Forma'!AQ50 -> 93796.243 | AS50: =pre_f_fd_total+'Pro-Forma'!S50+'Pro-Forma'!W50+'Pro-Forma'!AN50+'Pro-Forma'!AR50+'Pro-Forma'!AJ50 -> 38327302 | AT50: =MAX(const_zero,esop_refresh_target_post_f*'Pro-Forma'!AS50-pre_f_option_pool_total) -> 587882.23
A51: =Assumptions!$A$54 -> F1 | B51: =Assumptions!$B$54 -> Founder (CEO) | C51: =E42 -> 3765509.4 | D51: =IF(Assumptions!$D$54=lbl_seed,Assumptions!$E$54/class_seed_current_shares*$F$22,const_zero) -> 0 | E51: =IF(Assumptions!$D$54=lbl_series_a,Assumptions!$E$54/class_series_a_current_shares*$F$23,const_zero) -> 0 | F51: =IF(Assumptions!$D$54=lbl_series_b,Assumptions!$E$54/class_series_b_current_shares*$F$24,const_zero) -> 0 | G51: =IF(Assumptions!$D$54=lbl_series_c,Assumptions!$E$54/class_series_c_current_shares*$F$25,const_zero) -> 0 | H51: =IF(Assumptions!$D$54=lbl_series_d,Assumptions!$E$54/class_series_d_current_shares*$F$26,const_zero) -> 0 | I51: =IF(Assumptions!$D$54=lbl_series_e,Assumptions!$E$54/class_series_e_current_shares*$F$27,const_zero) -> 0 | J51: =IF(Assumptions!$A$54="NA1",$B$10,const_zero) -> 0 | K51: =IF(Assumptions!$A$54="NB1",$B$11,const_zero) -> 0 | L51: =IF(Assumptions!$A$54="F_LEAD",$B$7,IF(Assumptions!$A$54="F_FUND",$B$6,const_zero)) -> 0 | M51: =const_zero -> 0 | N51: =const_zero -> 0 | O51: =SUM(C51:N51) -> 3765509.4 | P51: =O51/$B$14 -> 0.098246138 | R51: ='Pro-Forma'!R50+const_one -> 47 | S51: ='Pro-Forma'!AT50 -> 587882.23 | T51: ='Pro-Forma'!AN50 -> 186716.59 | U51: ='Pro-Forma'!AR50 -> 93796.243 | V51: =series_f_pre_money_usd/(pre_f_fd_total+'Pro-Forma'!S51) -> 37.628498 | W51: =series_f_primary_raise_usd/'Pro-Forma'!V51 -> 797268.07 | X51: =IF('Pro-Forma'!V51<class_seed_ocp,class_seed_ocp*(ad_pre_f_broad_based_fd+series_f_primary_raise_usd/class_seed_ocp)/(ad_pre_f_broad_based_fd+series_f_primary_raise_usd/'Pro-Forma'!V51),class_seed_ocp) -> 1 | Y51: =class_seed_original_shares*class_seed_issue_pps/'Pro-Forma'!X51 -> 5000000 | Z51: =IF('Pro-Forma'!V51<class_series_a_ocp,class_series_a_ocp*(ad_pre_f_broad_based_fd+series_f_primary_raise_usd/class_series_a_ocp)/(ad_pre_f_broad_based_fd+series_f_primary_raise_usd/'Pro-Forma'!V51),class_series_a_ocp) -> 3 | AA51: =class_series_a_original_shares*class_series_a_issue_pps/'Pro-Forma'!Z51 -> 5000000 | AB51: =IF('Pro-Forma'!V51<class_series_b_ocp,class_series_b_ocp*(ad_pre_f_broad_based_fd+series_f_primary_raise_usd/class_series_b_ocp)/(ad_pre_f_broad_based_fd+series_f_primary_raise_usd/'Pro-Forma'!V51),class_series_b_ocp) -> 10 | AC51: =class_series_b_original_shares*class_series_b_issue_pps/'Pro-Forma'!AB51 -> 3000000 | AD51: =IF('Pro-Forma'!V51<class_series_c_ocp,class_series_c_ocp*(ad_pre_f_broad_based_fd+series_f_primary_raise_usd/class_series_c_ocp)/(ad_pre_f_broad_based_fd+series_f_primary_raise_usd/'Pro-Forma'!V51),class_series_c_ocp) -> 25 | AE51: =class_series_c_original_shares*class_series_c_issue_pps/'Pro-Forma'!AD51 -> 2400000 | AF51: =IF('Pro-Forma'!V51<class_series_d_ocp,class_series_d_ocp*(ad_pre_f_broad_based_fd+series_f_primary_raise_usd/class_series_d_ocp)/(ad_pre_f_broad_based_fd+series_f_primary_raise_usd/'Pro-Forma'!V51),class_series_d_ocp) -> 57.681736 | AG51: =class_series_d_original_shares*class_series_d_issue_pps/'Pro-Forma'!AF51 -> 1733651.4 | AH51: =IF('Pro-Forma'!V51<class_series_e_ocp,class_series_e_ocp*(ad_pre_f_broad_based_fd+series_f_primary_raise_usd/class_series_e_ocp)/(ad_pre_f_broad_based_fd+series_f_primary_raise_usd/'Pro-Forma'!V51),class_series_e_ocp) -> 48.912626 | AI51: =class_series_e_original_shares*class_series_e_issue_pps/'Pro-Forma'!AH51 -> 6133320.3 | AJ51: ='Pro-Forma'!Y51-class_seed_current_shares+'Pro-Forma'!AA51-class_series_a_current_shares+'Pro-Forma'!AC51-class_series_b_current_shares+'Pro-Forma'!AE51-class_series_c_current_shares+'Pro-Forma'!AG51-class_series_d_current_shares+'Pro-Forma'!AI51-class_series_e_current_shares -> 43677.638 | AK51: =note_a_cap_usd/(pre_f_fd_total+'Pro-Forma'!S51+'Pro-Forma'!AJ51+'Pro-Forma'!U51) -> 26.778553 | AL51: ='Pro-Forma'!V51*(const_one-note_a_discount) -> 30.102798 | AM51: =MIN('Pro-Forma'!AK51,'Pro-Forma'!AL51) -> 26.778553 | AN51: =note_a_principal_usd/'Pro-Forma'!AM51 -> 186716.59 | AO51: =note_b_cap_usd/(pre_f_fd_total+'Pro-Forma'!S51+'Pro-Forma'!AJ51+'Pro-Forma'!T51) -> 42.739338 | AP51: ='Pro-Forma'!V51*(const_one-note_b_discount) -> 31.984223 | AQ51: =MIN('Pro-Forma'!AO51,'Pro-Forma'!AP51) -> 31.984223 | AR51: =note_b_principal_usd/'Pro-Forma'!AQ51 -> 93796.243 | AS51: =pre_f_fd_total+'Pro-Forma'!S51+'Pro-Forma'!W51+'Pro-Forma'!AN51+'Pro-Forma'!AR51+'Pro-Forma'!AJ51 -> 38327302 | AT51: =MAX(const_zero,esop_refresh_target_post_f*'Pro-Forma'!AS51-pre_f_option_pool_total) -> 587882.23
A52: =Assumptions!$A$55 -> F2 | B52: =Assumptions!$B$55 -> Founder (CTO) | C52: =E43 -> 2353443.4 | D52: =IF(Assumptions!$D$55=lbl_seed,Assumptions!$E$55/class_seed_current_shares*$F$22,const_zero) -> 0 | E52: =IF(Assumptions!$D$55=lbl_series_a,Assumptions!$E$55/class_series_a_current_shares*$F$23,const_zero) -> 0 | F52: =IF(Assumptions!$D$55=lbl_series_b,Assumptions!$E$55/class_series_b_current_shares*$F$24,const_zero) -> 0 | G52: =IF(Assumptions!$D$55=lbl_series_c,Assumptions!$E$55/class_series_c_current_shares*$F$25,const_zero) -> 0 | H52: =IF(Assumptions!$D$55=lbl_series_d,Assumptions!$E$55/class_series_d_current_shares*$F$26,const_zero) -> 0 | I52: =IF(Assumptions!$D$55=lbl_series_e,Assumptions!$E$55/class_series_e_current_shares*$F$27,const_zero) -> 0 | J52: =IF(Assumptions!$A$55="NA1",$B$10,const_zero) -> 0 | K52: =IF(Assumptions!$A$55="NB1",$B$11,const_zero) -> 0 | L52: =IF(Assumptions!$A$55="F_LEAD",$B$7,IF(Assumptions!$A$55="F_FUND",$B$6,const_zero)) -> 0 | M52: =const_zero -> 0 | N52: =const_zero -> 0 | O52: =SUM(C52:N52) -> 2353443.4 | P52: =O52/$B$14 -> 0.061403836 | R52: ='Pro-Forma'!R51+const_one -> 48 | S52: ='Pro-Forma'!AT51 -> 587882.23 | T52: ='Pro-Forma'!AN51 -> 186716.59 | U52: ='Pro-Forma'!AR51 -> 93796.243 | V52: =series_f_pre_money_usd/(pre_f_fd_total+'Pro-Forma'!S52) -> 37.628498 | W52: =series_f_primary_raise_usd/'Pro-Forma'!V52 -> 797268.07 | X52: =IF('Pro-Forma'!V52<class_seed_ocp,class_seed_ocp*(ad_pre_f_broad_based_fd+series_f_primary_raise_usd/class_seed_ocp)/(ad_pre_f_broad_based_fd+series_f_primary_raise_usd/'Pro-Forma'!V52),class_seed_ocp) -> 1 | Y52: =class_seed_original_shares*class_seed_issue_pps/'Pro-Forma'!X52 -> 5000000 | Z52: =IF('Pro-Forma'!V52<class_series_a_ocp,class_series_a_ocp*(ad_pre_f_broad_based_fd+series_f_primary_raise_usd/class_series_a_ocp)/(ad_pre_f_broad_based_fd+series_f_primary_raise_usd/'Pro-Forma'!V52),class_series_a_ocp) -> 3 | AA52: =class_series_a_original_shares*class_series_a_issue_pps/'Pro-Forma'!Z52 -> 5000000 | AB52: =IF('Pro-Forma'!V52<class_series_b_ocp,class_series_b_ocp*(ad_pre_f_broad_based_fd+series_f_primary_raise_usd/class_series_b_ocp)/(ad_pre_f_broad_based_fd+series_f_primary_raise_usd/'Pro-Forma'!V52),class_series_b_ocp) -> 10 | AC52: =class_series_b_original_shares*class_series_b_issue_pps/'Pro-Forma'!AB52 -> 3000000 | AD52: =IF('Pro-Forma'!V52<class_series_c_ocp,class_series_c_ocp*(ad_pre_f_broad_based_fd+series_f_primary_raise_usd/class_series_c_ocp)/(ad_pre_f_broad_based_fd+series_f_primary_raise_usd/'Pro-Forma'!V52),class_series_c_ocp) -> 25 | AE52: =class_series_c_original_shares*class_series_c_issue_pps/'Pro-Forma'!AD52 -> 2400000 | AF52: =IF('Pro-Forma'!V52<class_series_d_ocp,class_series_d_ocp*(ad_pre_f_broad_based_fd+series_f_primary_raise_usd/class_series_d_ocp)/(ad_pre_f_broad_based_fd+series_f_primary_raise_usd/'Pro-Forma'!V52),class_series_d_ocp) -> 57.681736 | AG52: =class_series_d_original_shares*class_series_d_issue_pps/'Pro-Forma'!AF52 -> 1733651.4 | AH52: =IF('Pro-Forma'!V52<class_series_e_ocp,class_series_e_ocp*(ad_pre_f_broad_based_fd+series_f_primary_raise_usd/class_series_e_ocp)/(ad_pre_f_broad_based_fd+series_f_primary_raise_usd/'Pro-Forma'!V52),class_series_e_ocp) -> 48.912626 | AI52: =class_series_e_original_shares*class_series_e_issue_pps/'Pro-Forma'!AH52 -> 6133320.3 | AJ52: ='Pro-Forma'!Y52-class_seed_current_shares+'Pro-Forma'!AA52-class_series_a_current_shares+'Pro-Forma'!AC52-class_series_b_current_shares+'Pro-Forma'!AE52-class_series_c_current_shares+'Pro-Forma'!AG52-class_series_d_current_shares+'Pro-Forma'!AI52-class_series_e_current_shares -> 43677.638 | AK52: =note_a_cap_usd/(pre_f_fd_total+'Pro-Forma'!S52+'Pro-Forma'!AJ52+'Pro-Forma'!U52) -> 26.778553 | AL52: ='Pro-Forma'!V52*(const_one-note_a_discount) -> 30.102798 | AM52: =MIN('Pro-Forma'!AK52,'Pro-Forma'!AL52) -> 26.778553 | AN52: =note_a_principal_usd/'Pro-Forma'!AM52 -> 186716.59 | AO52: =note_b_cap_usd/(pre_f_fd_total+'Pro-Forma'!S52+'Pro-Forma'!AJ52+'Pro-Forma'!T52) -> 42.739338 | AP52: ='Pro-Forma'!V52*(const_one-note_b_discount) -> 31.984223 | AQ52: =MIN('Pro-Forma'!AO52,'Pro-Forma'!AP52) -> 31.984223 | AR52: =note_b_principal_usd/'Pro-Forma'!AQ52 -> 93796.243 | AS52: =pre_f_fd_total+'Pro-Forma'!S52+'Pro-Forma'!W52+'Pro-Forma'!AN52+'Pro-Forma'!AR52+'Pro-Forma'!AJ52 -> 38327302 | AT52: =MAX(const_zero,esop_refresh_target_post_f*'Pro-Forma'!AS52-pre_f_option_pool_total) -> 587882.23
A53: =Assumptions!$A$56 -> F3 | B53: =Assumptions!$B$56 -> Founder (Chief Scientist) | C53: =E44 -> 1412066 | D53: =IF(Assumptions!$D$56=lbl_seed,Assumptions!$E$56/class_seed_current_shares*$F$22,const_zero) -> 0 | E53: =IF(Assumptions!$D$56=lbl_series_a,Assumptions!$E$56/class_series_a_current_shares*$F$23,const_zero) -> 0 | F53: =IF(Assumptions!$D$56=lbl_series_b,Assumptions!$E$56/class_series_b_current_shares*$F$24,const_zero) -> 0 | G53: =IF(Assumptions!$D$56=lbl_series_c,Assumptions!$E$56/class_series_c_current_shares*$F$25,const_zero) -> 0 | H53: =IF(Assumptions!$D$56=lbl_series_d,Assumptions!$E$56/class_series_d_current_shares*$F$26,const_zero) -> 0 | I53: =IF(Assumptions!$D$56=lbl_series_e,Assumptions!$E$56/class_series_e_current_shares*$F$27,const_zero) -> 0 | J53: =IF(Assumptions!$A$56="NA1",$B$10,const_zero) -> 0 | K53: =IF(Assumptions!$A$56="NB1",$B$11,const_zero) -> 0 | L53: =IF(Assumptions!$A$56="F_LEAD",$B$7,IF(Assumptions!$A$56="F_FUND",$B$6,const_zero)) -> 0 | M53: =const_zero -> 0 | N53: =const_zero -> 0 | O53: =SUM(C53:N53) -> 1412066 | P53: =O53/$B$14 -> 0.036842302 | R53: ='Pro-Forma'!R52+const_one -> 49 | S53: ='Pro-Forma'!AT52 -> 587882.23 | T53: ='Pro-Forma'!AN52 -> 186716.59 | U53: ='Pro-Forma'!AR52 -> 93796.243 | V53: =series_f_pre_money_usd/(pre_f_fd_total+'Pro-Forma'!S53) -> 37.628498 | W53: =series_f_primary_raise_usd/'Pro-Forma'!V53 -> 797268.07 | X53: =IF('Pro-Forma'!V53<class_seed_ocp,class_seed_ocp*(ad_pre_f_broad_based_fd+series_f_primary_raise_usd/class_seed_ocp)/(ad_pre_f_broad_based_fd+series_f_primary_raise_usd/'Pro-Forma'!V53),class_seed_ocp) -> 1 | Y53: =class_seed_original_shares*class_seed_issue_pps/'Pro-Forma'!X53 -> 5000000 | Z53: =IF('Pro-Forma'!V53<class_series_a_ocp,class_series_a_ocp*(ad_pre_f_broad_based_fd+series_f_primary_raise_usd/class_series_a_ocp)/(ad_pre_f_broad_based_fd+series_f_primary_raise_usd/'Pro-Forma'!V53),class_series_a_ocp) -> 3 | AA53: =class_series_a_original_shares*class_series_a_issue_pps/'Pro-Forma'!Z53 -> 5000000 | AB53: =IF('Pro-Forma'!V53<class_series_b_ocp,class_series_b_ocp*(ad_pre_f_broad_based_fd+series_f_primary_raise_usd/class_series_b_ocp)/(ad_pre_f_broad_based_fd+series_f_primary_raise_usd/'Pro-Forma'!V53),class_series_b_ocp) -> 10 | AC53: =class_series_b_original_shares*class_series_b_issue_pps/'Pro-Forma'!AB53 -> 3000000 | AD53: =IF('Pro-Forma'!V53<class_series_c_ocp,class_series_c_ocp*(ad_pre_f_broad_based_fd+series_f_primary_raise_usd/class_series_c_ocp)/(ad_pre_f_broad_based_fd+series_f_primary_raise_usd/'Pro-Forma'!V53),class_series_c_ocp) -> 25 | AE53: =class_series_c_original_shares*class_series_c_issue_pps/'Pro-Forma'!AD53 -> 2400000 | AF53: =IF('Pro-Forma'!V53<class_series_d_ocp,class_series_d_ocp*(ad_pre_f_broad_based_fd+series_f_primary_raise_usd/class_series_d_ocp)/(ad_pre_f_broad_based_fd+series_f_primary_raise_usd/'Pro-Forma'!V53),class_series_d_ocp) -> 57.681736 | AG53: =class_series_d_original_shares*class_series_d_issue_pps/'Pro-Forma'!AF53 -> 1733651.4 | AH53: =IF('Pro-Forma'!V53<class_series_e_ocp,class_series_e_ocp*(ad_pre_f_broad_based_fd+series_f_primary_raise_usd/class_series_e_ocp)/(ad_pre_f_broad_based_fd+series_f_primary_raise_usd/'Pro-Forma'!V53),class_series_e_ocp) -> 48.912626 | AI53: =class_series_e_original_shares*class_series_e_issue_pps/'Pro-Forma'!AH53 -> 6133320.3 | AJ53: ='Pro-Forma'!Y53-class_seed_current_shares+'Pro-Forma'!AA53-class_series_a_current_shares+'Pro-Forma'!AC53-class_series_b_current_shares+'Pro-Forma'!AE53-class_series_c_current_shares+'Pro-Forma'!AG53-class_series_d_current_shares+'Pro-Forma'!AI53-class_series_e_current_shares -> 43677.638 | AK53: =note_a_cap_usd/(pre_f_fd_total+'Pro-Forma'!S53+'Pro-Forma'!AJ53+'Pro-Forma'!U53) -> 26.778553 | AL53: ='Pro-Forma'!V53*(const_one-note_a_discount) -> 30.102798 | AM53: =MIN('Pro-Forma'!AK53,'Pro-Forma'!AL53) -> 26.778553 | AN53: =note_a_principal_usd/'Pro-Forma'!AM53 -> 186716.59 | AO53: =note_b_cap_usd/(pre_f_fd_total+'Pro-Forma'!S53+'Pro-Forma'!AJ53+'Pro-Forma'!T53) -> 42.739338 | AP53: ='Pro-Forma'!V53*(const_one-note_b_discount) -> 31.984223 | AQ53: =MIN('Pro-Forma'!AO53,'Pro-Forma'!AP53) -> 31.984223 | AR53: =note_b_principal_usd/'Pro-Forma'!AQ53 -> 93796.243 | AS53: =pre_f_fd_total+'Pro-Forma'!S53+'Pro-Forma'!W53+'Pro-Forma'!AN53+'Pro-Forma'!AR53+'Pro-Forma'!AJ53 -> 38327302 | AT53: =MAX(const_zero,esop_refresh_target_post_f*'Pro-Forma'!AS53-pre_f_option_pool_total) -> 587882.23
A54: =Assumptions!$A$57 -> E1 | B54: =Assumptions!$B$57 -> Employee RSA | C54: =Assumptions!$C$57 -> 100000 | D54: =IF(Assumptions!$D$57=lbl_seed,Assumptions!$E$57/class_seed_current_shares*$F$22,const_zero) -> 0 | E54: =IF(Assumptions!$D$57=lbl_series_a,Assumptions!$E$57/class_series_a_current_shares*$F$23,const_zero) -> 0 | F54: =IF(Assumptions!$D$57=lbl_series_b,Assumptions!$E$57/class_series_b_current_shares*$F$24,const_zero) -> 0 | G54: =IF(Assumptions!$D$57=lbl_series_c,Assumptions!$E$57/class_series_c_current_shares*$F$25,const_zero) -> 0 | H54: =IF(Assumptions!$D$57=lbl_series_d,Assumptions!$E$57/class_series_d_current_shares*$F$26,const_zero) -> 0 | I54: =IF(Assumptions!$D$57=lbl_series_e,Assumptions!$E$57/class_series_e_current_shares*$F$27,const_zero) -> 0 | J54: =IF(Assumptions!$A$57="NA1",$B$10,const_zero) -> 0 | K54: =IF(Assumptions!$A$57="NB1",$B$11,const_zero) -> 0 | L54: =IF(Assumptions!$A$57="F_LEAD",$B$7,IF(Assumptions!$A$57="F_FUND",$B$6,const_zero)) -> 0 | M54: =const_zero -> 0 | N54: =const_zero -> 0 | O54: =SUM(C54:N54) -> 100000 | P54: =O54/$B$14 -> 0.0026091062 | R54: ='Pro-Forma'!R53+const_one -> 50 | S54: ='Pro-Forma'!AT53 -> 587882.23 | T54: ='Pro-Forma'!AN53 -> 186716.59 | U54: ='Pro-Forma'!AR53 -> 93796.243 | V54: =series_f_pre_money_usd/(pre_f_fd_total+'Pro-Forma'!S54) -> 37.628498 | W54: =series_f_primary_raise_usd/'Pro-Forma'!V54 -> 797268.07 | X54: =IF('Pro-Forma'!V54<class_seed_ocp,class_seed_ocp*(ad_pre_f_broad_based_fd+series_f_primary_raise_usd/class_seed_ocp)/(ad_pre_f_broad_based_fd+series_f_primary_raise_usd/'Pro-Forma'!V54),class_seed_ocp) -> 1 | Y54: =class_seed_original_shares*class_seed_issue_pps/'Pro-Forma'!X54 -> 5000000 | Z54: =IF('Pro-Forma'!V54<class_series_a_ocp,class_series_a_ocp*(ad_pre_f_broad_based_fd+series_f_primary_raise_usd/class_series_a_ocp)/(ad_pre_f_broad_based_fd+series_f_primary_raise_usd/'Pro-Forma'!V54),class_series_a_ocp) -> 3 | AA54: =class_series_a_original_shares*class_series_a_issue_pps/'Pro-Forma'!Z54 -> 5000000 | AB54: =IF('Pro-Forma'!V54<class_series_b_ocp,class_series_b_ocp*(ad_pre_f_broad_based_fd+series_f_primary_raise_usd/class_series_b_ocp)/(ad_pre_f_broad_based_fd+series_f_primary_raise_usd/'Pro-Forma'!V54),class_series_b_ocp) -> 10 | AC54: =class_series_b_original_shares*class_series_b_issue_pps/'Pro-Forma'!AB54 -> 3000000 | AD54: =IF('Pro-Forma'!V54<class_series_c_ocp,class_series_c_ocp*(ad_pre_f_broad_based_fd+series_f_primary_raise_usd/class_series_c_ocp)/(ad_pre_f_broad_based_fd+series_f_primary_raise_usd/'Pro-Forma'!V54),class_series_c_ocp) -> 25 | AE54: =class_series_c_original_shares*class_series_c_issue_pps/'Pro-Forma'!AD54 -> 2400000 | AF54: =IF('Pro-Forma'!V54<class_series_d_ocp,class_series_d_ocp*(ad_pre_f_broad_based_fd+series_f_primary_raise_usd/class_series_d_ocp)/(ad_pre_f_broad_based_fd+series_f_primary_raise_usd/'Pro-Forma'!V54),class_series_d_ocp) -> 57.681736 | AG54: =class_series_d_original_shares*class_series_d_issue_pps/'Pro-Forma'!AF54 -> 1733651.4 | AH54: =IF('Pro-Forma'!V54<class_series_e_ocp,class_series_e_ocp*(ad_pre_f_broad_based_fd+series_f_primary_raise_usd/class_series_e_ocp)/(ad_pre_f_broad_based_fd+series_f_primary_raise_usd/'Pro-Forma'!V54),class_series_e_ocp) -> 48.912626 | AI54: =class_series_e_original_shares*class_series_e_issue_pps/'Pro-Forma'!AH54 -> 6133320.3 | AJ54: ='Pro-Forma'!Y54-class_seed_current_shares+'Pro-Forma'!AA54-class_series_a_current_shares+'Pro-Forma'!AC54-class_series_b_current_shares+'Pro-Forma'!AE54-class_series_c_current_shares+'Pro-Forma'!AG54-class_series_d_current_shares+'Pro-Forma'!AI54-class_series_e_current_shares -> 43677.638 | AK54: =note_a_cap_usd/(pre_f_fd_total+'Pro-Forma'!S54+'Pro-Forma'!AJ54+'Pro-Forma'!U54) -> 26.778553 | AL54: ='Pro-Forma'!V54*(const_one-note_a_discount) -> 30.102798 | AM54: =MIN('Pro-Forma'!AK54,'Pro-Forma'!AL54) -> 26.778553 | AN54: =note_a_principal_usd/'Pro-Forma'!AM54 -> 186716.59 | AO54: =note_b_cap_usd/(pre_f_fd_total+'Pro-Forma'!S54+'Pro-Forma'!AJ54+'Pro-Forma'!T54) -> 42.739338 | AP54: ='Pro-Forma'!V54*(const_one-note_b_discount) -> 31.984223 | AQ54: =MIN('Pro-Forma'!AO54,'Pro-Forma'!AP54) -> 31.984223 | AR54: =note_b_principal_usd/'Pro-Forma'!AQ54 -> 93796.243 | AS54: =pre_f_fd_total+'Pro-Forma'!S54+'Pro-Forma'!W54+'Pro-Forma'!AN54+'Pro-Forma'!AR54+'Pro-Forma'!AJ54 -> 38327302 | AT54: =MAX(const_zero,esop_refresh_target_post_f*'Pro-Forma'!AS54-pre_f_option_pool_total) -> 587882.23
A55: =Assumptions!$A$58 -> E2 | B55: =Assumptions!$B$58 -> Employee RSA | C55: =Assumptions!$C$58 -> 100000 | D55: =IF(Assumptions!$D$58=lbl_seed,Assumptions!$E$58/class_seed_current_shares*$F$22,const_zero) -> 0 | E55: =IF(Assumptions!$D$58=lbl_series_a,Assumptions!$E$58/class_series_a_current_shares*$F$23,const_zero) -> 0 | F55: =IF(Assumptions!$D$58=lbl_series_b,Assumptions!$E$58/class_series_b_current_shares*$F$24,const_zero) -> 0 | G55: =IF(Assumptions!$D$58=lbl_series_c,Assumptions!$E$58/class_series_c_current_shares*$F$25,const_zero) -> 0 | H55: =IF(Assumptions!$D$58=lbl_series_d,Assumptions!$E$58/class_series_d_current_shares*$F$26,const_zero) -> 0 | I55: =IF(Assumptions!$D$58=lbl_series_e,Assumptions!$E$58/class_series_e_current_shares*$F$27,const_zero) -> 0 | J55: =IF(Assumptions!$A$58="NA1",$B$10,const_zero) -> 0 | K55: =IF(Assumptions!$A$58="NB1",$B$11,const_zero) -> 0 | L55: =IF(Assumptions!$A$58="F_LEAD",$B$7,IF(Assumptions!$A$58="F_FUND",$B$6,const_zero)) -> 0 | M55: =const_zero -> 0 | N55: =const_zero -> 0 | O55: =SUM(C55:N55) -> 100000 | P55: =O55/$B$14 -> 0.0026091062 | R55: ='Pro-Forma'!R54+const_one -> 51 | S55: ='Pro-Forma'!AT54 -> 587882.23 | T55: ='Pro-Forma'!AN54 -> 186716.59 | U55: ='Pro-Forma'!AR54 -> 93796.243 | V55: =series_f_pre_money_usd/(pre_f_fd_total+'Pro-Forma'!S55) -> 37.628498 | W55: =series_f_primary_raise_usd/'Pro-Forma'!V55 -> 797268.07 | X55: =IF('Pro-Forma'!V55<class_seed_ocp,class_seed_ocp*(ad_pre_f_broad_based_fd+series_f_primary_raise_usd/class_seed_ocp)/(ad_pre_f_broad_based_fd+series_f_primary_raise_usd/'Pro-Forma'!V55),class_seed_ocp) -> 1 | Y55: =class_seed_original_shares*class_seed_issue_pps/'Pro-Forma'!X55 -> 5000000 | Z55: =IF('Pro-Forma'!V55<class_series_a_ocp,class_series_a_ocp*(ad_pre_f_broad_based_fd+series_f_primary_raise_usd/class_series_a_ocp)/(ad_pre_f_broad_based_fd+series_f_primary_raise_usd/'Pro-Forma'!V55),class_series_a_ocp) -> 3 | AA55: =class_series_a_original_shares*class_series_a_issue_pps/'Pro-Forma'!Z55 -> 5000000 | AB55: =IF('Pro-Forma'!V55<class_series_b_ocp,class_series_b_ocp*(ad_pre_f_broad_based_fd+series_f_primary_raise_usd/class_series_b_ocp)/(ad_pre_f_broad_based_fd+series_f_primary_raise_usd/'Pro-Forma'!V55),class_series_b_ocp) -> 10 | AC55: =class_series_b_original_shares*class_series_b_issue_pps/'Pro-Forma'!AB55 -> 3000000 | AD55: =IF('Pro-Forma'!V55<class_series_c_ocp,class_series_c_ocp*(ad_pre_f_broad_based_fd+series_f_primary_raise_usd/class_series_c_ocp)/(ad_pre_f_broad_based_fd+series_f_primary_raise_usd/'Pro-Forma'!V55),class_series_c_ocp) -> 25 | AE55: =class_series_c_original_shares*class_series_c_issue_pps/'Pro-Forma'!AD55 -> 2400000 | AF55: =IF('Pro-Forma'!V55<class_series_d_ocp,class_series_d_ocp*(ad_pre_f_broad_based_fd+series_f_primary_raise_usd/class_series_d_ocp)/(ad_pre_f_broad_based_fd+series_f_primary_raise_usd/'Pro-Forma'!V55),class_series_d_ocp) -> 57.681736 | AG55: =class_series_d_original_shares*class_series_d_issue_pps/'Pro-Forma'!AF55 -> 1733651.4 | AH55: =IF('Pro-Forma'!V55<class_series_e_ocp,class_series_e_ocp*(ad_pre_f_broad_based_fd+series_f_primary_raise_usd/class_series_e_ocp)/(ad_pre_f_broad_based_fd+series_f_primary_raise_usd/'Pro-Forma'!V55),class_series_e_ocp) -> 48.912626 | AI55: =class_series_e_original_shares*class_series_e_issue_pps/'Pro-Forma'!AH55 -> 6133320.3 | AJ55: ='Pro-Forma'!Y55-class_seed_current_shares+'Pro-Forma'!AA55-class_series_a_current_shares+'Pro-Forma'!AC55-class_series_b_current_shares+'Pro-Forma'!AE55-class_series_c_current_shares+'Pro-Forma'!AG55-class_series_d_current_shares+'Pro-Forma'!AI55-class_series_e_current_shares -> 43677.638 | AK55: =note_a_cap_usd/(pre_f_fd_total+'Pro-Forma'!S55+'Pro-Forma'!AJ55+'Pro-Forma'!U55) -> 26.778553 | AL55: ='Pro-Forma'!V55*(const_one-note_a_discount) -> 30.102798 | AM55: =MIN('Pro-Forma'!AK55,'Pro-Forma'!AL55) -> 26.778553 | AN55: =note_a_principal_usd/'Pro-Forma'!AM55 -> 186716.59 | AO55: =note_b_cap_usd/(pre_f_fd_total+'Pro-Forma'!S55+'Pro-Forma'!AJ55+'Pro-Forma'!T55) -> 42.739338 | AP55: ='Pro-Forma'!V55*(const_one-note_b_discount) -> 31.984223 | AQ55: =MIN('Pro-Forma'!AO55,'Pro-Forma'!AP55) -> 31.984223 | AR55: =note_b_principal_usd/'Pro-Forma'!AQ55 -> 93796.243 | AS55: =pre_f_fd_total+'Pro-Forma'!S55+'Pro-Forma'!W55+'Pro-Forma'!AN55+'Pro-Forma'!AR55+'Pro-Forma'!AJ55 -> 38327302 | AT55: =MAX(const_zero,esop_refresh_target_post_f*'Pro-Forma'!AS55-pre_f_option_pool_total) -> 587882.23
A56: =Assumptions!$A$59 -> E3 | B56: =Assumptions!$B$59 -> Employee RSA | C56: =Assumptions!$C$59 -> 100000 | D56: =IF(Assumptions!$D$59=lbl_seed,Assumptions!$E$59/class_seed_current_shares*$F$22,const_zero) -> 0 | E56: =IF(Assumptions!$D$59=lbl_series_a,Assumptions!$E$59/class_series_a_current_shares*$F$23,const_zero) -> 0 | F56: =IF(Assumptions!$D$59=lbl_series_b,Assumptions!$E$59/class_series_b_current_shares*$F$24,const_zero) -> 0 | G56: =IF(Assumptions!$D$59=lbl_series_c,Assumptions!$E$59/class_series_c_current_shares*$F$25,const_zero) -> 0 | H56: =IF(Assumptions!$D$59=lbl_series_d,Assumptions!$E$59/class_series_d_current_shares*$F$26,const_zero) -> 0 | I56: =IF(Assumptions!$D$59=lbl_series_e,Assumptions!$E$59/class_series_e_current_shares*$F$27,const_zero) -> 0 | J56: =IF(Assumptions!$A$59="NA1",$B$10,const_zero) -> 0 | K56: =IF(Assumptions!$A$59="NB1",$B$11,const_zero) -> 0 | L56: =IF(Assumptions!$A$59="F_LEAD",$B$7,IF(Assumptions!$A$59="F_FUND",$B$6,const_zero)) -> 0 | M56: =const_zero -> 0 | N56: =const_zero -> 0 | O56: =SUM(C56:N56) -> 100000 | P56: =O56/$B$14 -> 0.0026091062 | R56: ='Pro-Forma'!R55+const_one -> 52 | S56: ='Pro-Forma'!AT55 -> 587882.23 | T56: ='Pro-Forma'!AN55 -> 186716.59 | U56: ='Pro-Forma'!AR55 -> 93796.243 | V56: =series_f_pre_money_usd/(pre_f_fd_total+'Pro-Forma'!S56) -> 37.628498 | W56: =series_f_primary_raise_usd/'Pro-Forma'!V56 -> 797268.07 | X56: =IF('Pro-Forma'!V56<class_seed_ocp,class_seed_ocp*(ad_pre_f_broad_based_fd+series_f_primary_raise_usd/class_seed_ocp)/(ad_pre_f_broad_based_fd+series_f_primary_raise_usd/'Pro-Forma'!V56),class_seed_ocp) -> 1 | Y56: =class_seed_original_shares*class_seed_issue_pps/'Pro-Forma'!X56 -> 5000000 | Z56: =IF('Pro-Forma'!V56<class_series_a_ocp,class_series_a_ocp*(ad_pre_f_broad_based_fd+series_f_primary_raise_usd/class_series_a_ocp)/(ad_pre_f_broad_based_fd+series_f_primary_raise_usd/'Pro-Forma'!V56),class_series_a_ocp) -> 3 | AA56: =class_series_a_original_shares*class_series_a_issue_pps/'Pro-Forma'!Z56 -> 5000000 | AB56: =IF('Pro-Forma'!V56<class_series_b_ocp,class_series_b_ocp*(ad_pre_f_broad_based_fd+series_f_primary_raise_usd/class_series_b_ocp)/(ad_pre_f_broad_based_fd+series_f_primary_raise_usd/'Pro-Forma'!V56),class_series_b_ocp) -> 10 | AC56: =class_series_b_original_shares*class_series_b_issue_pps/'Pro-Forma'!AB56 -> 3000000 | AD56: =IF('Pro-Forma'!V56<class_series_c_ocp,class_series_c_ocp*(ad_pre_f_broad_based_fd+series_f_primary_raise_usd/class_series_c_ocp)/(ad_pre_f_broad_based_fd+series_f_primary_raise_usd/'Pro-Forma'!V56),class_series_c_ocp) -> 25 | AE56: =class_series_c_original_shares*class_series_c_issue_pps/'Pro-Forma'!AD56 -> 2400000 | AF56: =IF('Pro-Forma'!V56<class_series_d_ocp,class_series_d_ocp*(ad_pre_f_broad_based_fd+series_f_primary_raise_usd/class_series_d_ocp)/(ad_pre_f_broad_based_fd+series_f_primary_raise_usd/'Pro-Forma'!V56),class_series_d_ocp) -> 57.681736 | AG56: =class_series_d_original_shares*class_series_d_issue_pps/'Pro-Forma'!AF56 -> 1733651.4 | AH56: =IF('Pro-Forma'!V56<class_series_e_ocp,class_series_e_ocp*(ad_pre_f_broad_based_fd+series_f_primary_raise_usd/class_series_e_ocp)/(ad_pre_f_broad_based_fd+series_f_primary_raise_usd/'Pro-Forma'!V56),class_series_e_ocp) -> 48.912626 | AI56: =class_series_e_original_shares*class_series_e_issue_pps/'Pro-Forma'!AH56 -> 6133320.3 | AJ56: ='Pro-Forma'!Y56-class_seed_current_shares+'Pro-Forma'!AA56-class_series_a_current_shares+'Pro-Forma'!AC56-class_series_b_current_shares+'Pro-Forma'!AE56-class_series_c_current_shares+'Pro-Forma'!AG56-class_series_d_current_shares+'Pro-Forma'!AI56-class_series_e_current_shares -> 43677.638 | AK56: =note_a_cap_usd/(pre_f_fd_total+'Pro-Forma'!S56+'Pro-Forma'!AJ56+'Pro-Forma'!U56) -> 26.778553 | AL56: ='Pro-Forma'!V56*(const_one-note_a_discount) -> 30.102798 | AM56: =MIN('Pro-Forma'!AK56,'Pro-Forma'!AL56) -> 26.778553 | AN56: =note_a_principal_usd/'Pro-Forma'!AM56 -> 186716.59 | AO56: =note_b_cap_usd/(pre_f_fd_total+'Pro-Forma'!S56+'Pro-Forma'!AJ56+'Pro-Forma'!T56) -> 42.739338 | AP56: ='Pro-Forma'!V56*(const_one-note_b_discount) -> 31.984223 | AQ56: =MIN('Pro-Forma'!AO56,'Pro-Forma'!AP56) -> 31.984223 | AR56: =note_b_principal_usd/'Pro-Forma'!AQ56 -> 93796.243 | AS56: =pre_f_fd_total+'Pro-Forma'!S56+'Pro-Forma'!W56+'Pro-Forma'!AN56+'Pro-Forma'!AR56+'Pro-Forma'!AJ56 -> 38327302 | AT56: =MAX(const_zero,esop_refresh_target_post_f*'Pro-Forma'!AS56-pre_f_option_pool_total) -> 587882.23
